Workbook
Name Btu_to_J: Conversions!$M$3
Name deflate_1983: Conversions!$H$3
Name deflate_1984: Conversions!$H$4
Name deflate_1985: Conversions!$H$5
Name deflate_1986: Conversions!$H$6
Name deflate_1987: Conversions!$H$7
Name deflate_1988: Conversions!$H$8
Name deflate_1989: Conversions!$H$9
Name deflate_1990: Conversions!$H$10
Name deflate_1991: Conversions!$H$11
Name deflate_1992: Conversions!$H$12
Name deflate_1993: Conversions!$H$13
Name deflate_1994: Conversions!$H$14
Name deflate_1995: Conversions!$H$15
Name deflate_1996: Conversions!$H$16
Name deflate_1997: Conversions!$H$17
Name deflate_1998: Conversions!$H$18
Name deflate_1999: Conversions!$H$19
Name deflate_2000: Conversions!$H$20
Name deflate_2001: Conversions!$H$21
Name deflate_2002: Conversions!$H$22
Name deflate_2003: Conversions!$H$23
Name deflate_2004: Conversions!$H$24
Name deflate_2005: Conversions!$H$25
Name deflate_2006: Conversions!$H$26
Name deflate_2007: Conversions!$H$27
Name deflate_2008: Conversions!$H$28
Name deflate_2009: Conversions!$H$29
Name deflate_2010: Conversions!$H$30
Name deflate_2011: Conversions!$H$31
Name deflate_2012: Conversions!$H$32
Name deflate_2012: Conversions!$H$32
Name deflate_2013: Conversions!$H$33
Name GW_to_Pja: Conversions!$L$9
Name GW_to_Pja: Conversions!$M$9
Name I_D: WindTimeSlices!$X$8
Name I_N: WindTimeSlices!$Y$8
Name INF: #REF!
Name IQ_CH: 110000
Name IQ_CQ: 5000
Name IQ_CY: 10000
Name IQ_DAILY: 500000
Name IQ_FH: 100000
Name IQ_FQ: 500
Name IQ_FY: 1000
Name IQ_LTM: 2000
Name IQ_MONTH: 15000
Name IQ_NTM: 6000
Name IQ_WEEK: 50000
Name IQ_YTD: 3000
Name kWh_to_btu_hr: Conversions!$M$11
Name kWh_to_MJ: Conversions!$M$4
Name lookup_deflator_2013: TechData_NewCap!$AB$5
Name lookup_deflator_2023: TechData_NewCap!$P$29
Name mills_kWh_to__Million_PJ: Conversions!$M$10
Name MMBtu_to_J: Conversions!$M$7
Name MWh_to_PJ: Conversions!$M$5
Name PJ_to_J: Conversions!$M$6
Name S_D: WindTimeSlices!$Z$8
Name S_N: WindTimeSlices!$AA$8

Sheet Documentation
A1: worksheet | B1: table | C1: data_use | D1: dependency_1 | E1: dependency_2 | F1: dependency_3 | G1: dependency_4 | H1: update_freq | I1: formula | J1: source | K1: description | L1: notes
A2: Commodities | B2: =Commodities!$C$6 -> ELC_subres_commodities | C2: output | H2: NA | I2: - | J2: - | K2: Definitions of commodities and technologies; no need to update
A3: Technologies | B3: =Technologies!$C$6 -> ELC_subres_technologies | C3: output | H3: NA | I3: - | J3: - | K3: Definitions of commodities and technologies; no need to update
A4: TechData_NewCap | B4: =TechData_NewCap!$B$5 -> new_capacity_conventional_technologies | C4: output | D4: =B5 -> AEO_raw_cost_data | E4: =B6 -> lifetime_assumptions | F4: =B9 -> 2023_new_cap_cost_data | H4: Updated | J4: - | K4: Technical specs (Best Buy) for new natural gas and nuclear technology.
A5: 2013 Cap Raw Data | B5: ='2013 Cap Raw Data'!$A$3 -> AEO_raw_cost_data | C5: input | H5: Historical Reference Data | J5: Assumptions to the Annual Energy Outlook 2014, Early Release (http://www.eia.gov/forecasts/aeo/assumptions/pdf/table8_2_2014er.pdf) | K5: 2014 release of AEO costs of new tech installation
A6: LifetimeAssumptions | B6: =LifetimeAssumptions!$B$1 -> lifetime_assumptions | C6: input
A7: TechData_NewCap | B7: =TechData_NewCap!$B$29 -> new_battery_storage | C7: output | D7: =B8 -> regional_base_cost | E7: =B9 -> 2023_new_cap_cost_data | F7: =B5 -> AEO_raw_cost_data | H7: Updated | K7: Technical specs (Best Buy) for new battery energy storage.
A8: 2023_Regional_Cost_Factor | B8: ='2023_Regional_Cost_Factor'!$A$3 -> regional_base_cost | C8: input | H8: Updated | J8: https://www.eia.gov/outlooks/aeo/assumptions/pdf/elec_cost_perf.pdf | K8: Regional cost shifters for base cost of new capital
A9: 2023 Cap Raw Data | B9: ='2023 Cap Raw Data'!$A$4 -> 2023_new_cap_cost_data | C9: input | H9: Updated | J9: https://www.eia.gov/outlooks/aeo/assumptions/pdf/elec_cost_perf.pdf | K9: Cost and performance of new technologies
A10: TechData_NewCap | B10: =TechData_NewCap!$B$44 -> new_cap_CHP | C10: output | H10: Update Needed | J10: Hard Coded | K10: Cost and performance of CHP technologies
A11: TechData_SolarWind | B11: =TechData_SolarWind!$B$5 -> solarPV_technologies | C11: output | D11: =B12 -> #REF! | H11: Need to find source | J11: Mostly hard coded | K11: Cost inputs for solar technologies
A12: SOL | B12: =#REF! -> #REF! | C12: input | H12: Update Needed | J12: SEIA, NY State solar targets | K12: Capacity for rest of state solar installation
A13: TechData_SolarWind | B13: =TechData_SolarWind!$B$8 -> wind_technologies | C13: output | D13: ATB | E13: =B6 -> lifetime_assumptions | F13: Nrel_ReEDS | I13: AEO Cost Assumptions, multiplied by NREL ReEDS scaling factors to get cost at different technology steps, multiplied by ATB for how cost, FOM scale over time | K13: Costs, capacity, and activity factors for wind
A14: TechData_Hydro | B14: =TechData_Hydro!$B$5 -> conventional_hydro | C14: output | H14: Need to find source | K14: Cost and activity factor for existing conventional hydro
A15: TechData_Hydro | B15: =TechData_Hydro!$B$11 -> reversible_hydro | C15: output | H15: Need to find source | K15: Cost and activity factor for existing reversible hydro
A16: TechData_CoalResid | B16: =#REF! -> #REF! | C16: output | H16: NA | K16: No residual coal after 2020. No need to update.
A17: ATB_Capex | B17: =ATB_CAPEX!$C$1 -> ATB_capex | C17: input | H17: Updated | J17: https://atb.nrel.gov/electricity/2024/data | K17: NREL Annual Technology Baseline.
A18: ATB_CF | B18: =ATB_CF!$C$1 -> ATB_CF | C18: input | H18: Updated | J18: https://atb.nrel.gov/electricity/2024/data | K18: NREL Annual Technology Baseline.
A19: ATB_FOM | B19: =ATB_FOM!$F$1 -> ATB_FOM | C19: input | H19: Updated | J19: https://atb.nrel.gov/electricity/2024/data | K19: NREL Annual Technology Baseline.
A20: ATB_VOM | B20: =ATB_VOM!$G$1 -> ATB_VOM | C20: input | H20: Updated | J20: https://atb.nrel.gov/electricity/2024/data | K20: NREL Annual Technology Baseline.

Sheet Commodities
B1: Commodities | C1: _GLOBAL,R0,R1,R2,R3,R4,R5,R6
B6: ~FI_Comm | C6: ELC_subres_commodities
B7: Region | C7: CommName | D7: CommDesc | E7: Unit | F7: Csets | G7: LimType | H7: CTSLvl | I7: PeakTS | J7: Ctype | O7: Comment
B8: R1,R2,R3,R4,R5,R6 | C8: ELC | D8: Electricity | E8: PJ | F8: NRG
B9: R1 | C9: RDMDELC | D9: Dummy ELC demand | E9: PJ | F9: DEM
B10: R0,R1 | C10: ELCNB | D10: Electricity from R0 | E10: PJ | F10: NRG
B11: R2, R3, R4, R5, R6 | C11: ELCR1 | D11: Electricity from R1 (NE) | E11: PJ
B12: R1,R3,R4,R5,R6 | C12: ELCR2 | D12: Electricity from R2 (BK) | E12: PJ
B13: R1,R2,R3,R4,R5,R6 | C13: ELCR3 | D13: Electricity from R3 (BX) | E13: PJ
B14: R1,R2,R3,R4,R5,R6 | C14: ELCR4 | D14: Electricity from R4 (MH) | E14: PJ
B15: R1,R2,R3,R4,R5,R6 | C15: ELCR5 | D15: Electricity from R5 (SI) | E15: PJ
B16: R1,R2,R3,R4,R5,R6 | C16: ELCR6 | D16: Electricity from R6 (QN) | E16: PJ
B17: *Material Carriers to Nuclear Techs
B18: R0 | C18: NURN | D18: Natural Uranium | E18: t | F18: MAT
B19: R0 | C19: URD | D19: Depleted uranium generated during enrichment | E19: t
B20: R0,R1,R2,R3,R4,R5,R6 | C20: URNA | D20: Enriched Uranium (4.5%) for LWRs | E20: t
B21: R0,R1,R2,R3,R4,R5,R6 | C21: URNB | D21: Enriched Uranium (9%) for PBMRs | E21: t
B22: R0,R1,R2,R3,R4,R5,R6 | C22: URNC | D22: Enriched Uranium (19%) for GT-MHRs | E22: t
B23: R1,R2,R3,R4,R5,R6 | C23: USPTA | D23: Spent U from LWRs | E23: t
B24: R1,R2,R3,R4,R5,R6 | C24: USPTB | D24: Spent U from PBMRs | E24: t
B25: R1,R2,R3,R4,R5,R6 | C25: USPTC | D25: Spent U from GT-MHRs | E25: t
B26: *Coal Energy Carriers
B27: R1 | C27: CSTMBH | D27: High Sulfur Bituminous to SOx Control | E27: PJ | F27: NRG
B28: R1 | C28: CSTMBM | D28: Medium Sulfur Bituminous to SOx Control | E28: PJ
B29: R1 | C29: CSTMBL | D29: Low Sulfur Bituminous to SOx Control | E29: PJ
B30: R1 | C30: CSTMSM | D30: Medium Sulfur Sub-Bituminous to SOx Control | E30: PJ
B31: R1 | C31: CSTMSL | D31: Low Sulfur Sub-Bituminous to SOx Control | E31: PJ
B32: R1 | C32: CSTMLH | D32: High Sulfur Lignite to SOx Control | E32: PJ
B33: R1 | C33: CSTMLM | D33: Medium Sulfur Lignite to SOx Control | E33: PJ
B34: R1 | C34: CSTMBIT1O | D34: Bituminous to NOX Control Over 100MW | E34: PJ
B35: R1 | C35: CSTMSUB1O | D35: Sub-Bituminous to NOX Control Over 100MW | E35: PJ
B36: R1 | C36: CSTMLIG1O | D36: Lignite to NOX Control Over 100MW | E36: PJ
B37: R1 | C37: CSTMBIT1U | D37: Bituminous to NOX Control Under 100MW | E37: PJ
B38: R1 | C38: CSTMSUB1U | D38: Sub-Bituminous to NOX Control Under 100MW | E38: PJ
B39: R1 | C39: CSTMLIG1U | D39: Lignite to NOX Control Under 100MW | E39: PJ
... B66: R1 | C66: COALIGCC | D66: Coal to IGCC | E66: PJ
B67: *Non-Coal Energy Carriers to Conversion Techs
B68: R1,R2,R3,R4,R5,R6 | C68: ELCDSLEA | D68: Diesel | E68: PJ | F68: NRG
B69: R1,R2,R3,R4,R5,R6 | C69: ELCDSL | D69: Diesel to the electric system | E69: PJ
B70: R1,R2,R3,R4,R5,R6 | C70: ELCDSLPN | D70: Diesel to the electric system PN | E70: PJ
B71: R1,R2,R3,R4,R5,R6 | C71: ELCRFLEA | D71: Residual Fuel Oil LS | E71: PJ
B72: R1,R2,R3,R4,R5,R6 | C72: ELCRFHEA | D72: Residual Fuel Oil HS | E72: PJ
B73: R1,R2,R3,R4,R5,R6 | C73: ELCRFH | D73: Residual fuel oil, high sulfur, to electric system | E73: PJ
B74: R1,R2,R3,R4,R5,R6 | C74: ELCRFL | D74: Residual fuel oil, low sulfur, to electric system | E74: PJ
B75: R1,R2,R3,R4,R5,R6 | C75: ELCRFHPS | D75: Residual fuel oil, high sulfur, to electric system PS | E75: PJ
B76: R1,R2,R3,R4,R5,R6 | C76: ELCRFLPS | D76: Residual fuel oil, low sulfur, to electric system PS | E76: PJ
B77: R1,R2,R3,R4,R5,R6 | C77: ELCRFHPN | D77: Residual fuel oil, high sulfur, to electric system PN | E77: PJ
B78: R1,R2,R3,R4,R5,R6 | C78: ELCRFLPN | D78: Residual fuel oil, low sulfur, to electric system PN | E78: PJ
B79: R1,R2,R3,R4,R5,R6 | C79: ELCNGAEA | D79: Natural Gas to Combustion Turbines | E79: PJ
B80: R1,R2,R3,R4,R5,R6 | C80: ELCNGCEA | D80: Natural Gas to Combined-Cycle | E80: PJ
... B86: R1 | C86: ELCSOL | D86: Solar | E86: PJ
B87: *Biomass energy carriers
B88: *R1,R2,R3,R4,R5,R6 | C88: AGR | D88: Delivered ag residues - other (in Mt) | E88: Mt | F88: MAT
B89: *R1,R2,R3,R4,R5,R6 | C89: ECG | D89: Delivered energy crop - grasses (in Mt) | E89: Mt
B90: *R1,R2,R3,R4,R5,R6 | C90: ECW | D90: Delivered energy crop - woody (in Mt) | E90: Mt
B91: *R1,R2,R3,R4,R5,R6 | C91: FSR | D91: Delivered forest residues (in Mt) | E91: Mt
B92: *R1,R2,R3,R4,R5,R6 | C92: PMR | D92: Delivered primary mill residues (in Mt) | E92: Mt
B93: *R1,R2,R3,R4,R5,R6 | C93: UWW | D93: Delivered urban wood waste (in Mt) | E93: Mt
B94: *R1,R2,R3,R4,R5,R6 | C94: STV | D94: Delivered corn stover (in Mt) | E94: Mt
B95: *R1,R2,R3,R4,R5,R6 | C95: AGR_PJ | D95: Delivered ag residues - other (in PJ) | E95: PJ | F95: NRG
B96: *R1,R2,R3,R4,R5,R6 | C96: ECG_PJ | D96: Delivered energy crop - grasses (in PJ) | E96: PJ
B97: *R1,R2,R3,R4,R5,R6 | C97: ECW_PJ | D97: Delivered energy crop - woody (in PJ) | E97: PJ
B98: *R1,R2,R3,R4,R5,R6 | C98: FSR_PJ | D98: Delivered forest residues (in PJ) | E98: PJ
B99: *R1,R2,R3,R4,R5,R6 | C99: PMR_PJ | D99: Delivered primary mill residues (in PJ) | E99: PJ
B100: *R1,R2,R3,R4,R5,R6 | C100: UWW_PJ | D100: Delivered urban wood waste (in PJ) | E100: PJ
B101: *R1,R2,R3,R4,R5,R6 | C101: STV_PJ | D101: Delivered corn stover (in PJ) | E101: PJ
B102: *R1,R2,R3,R4,R5,R6 | C102: ELCBIO | D102: Biomass all kinds | E102: PJ
B103: *R1,R2,R3,R4,R5,R6 | C103: ELCBIGCCEA | D103: Electric sector biomass (all kinds) to EBIOIGCC after emissions accounting | E103: PJ
B104: *R1,R2,R3,R4,R5,R6 | C104: ELCMSWEA | D104: Municipal Solid Waste | E104: PJ
B105: *R1,R2,R3,R4,R5,R6 | C105: ELCMSW | D105: MSW to the electric system | E105: PJ
B106: *R1,R2,R3,R4,R5,R6 | C106: ELCBSTMEA | D106: Electric sector biomass (all kinds) to steam combustion after CO2 and SO2 emissions accounting | E106: PJ
B107: *R1,R2,R3,R4,R5,R6 | C107: ELCBIOSTM | D107: Electric sector biomass to dedicated steam combustion | E107: PJ
... B112: *R1,R2,R3,R4,R5,R6 | C112: LFG | D112: Landfill gas | E112: PJ
B113: *Emissions Commodities
B114: R1,R2,R3,R4,R5,R6 | C114: CARBON | D114: Carbon Emissions | E114: Mt | F114: ENV
B115: R1,R2,R3,R4,R5,R6 | C115: CO2BE | D115: Carbon dioxide- Electricity from biomass | E115: kt | F115: ENV
B116: R1,R2,R3,R4,R5,R6 | C116: CO2E | D116: Electric Sector Carbon Emissions | E116: kt | F116: ENV
B117: R1,R2,R3,R4,R5,R6 | C117: CO2EN | D117: Electric Sector CO2 from new coal | E117: kt | F117: ENV
B118: R1,R2,R3,R4,R5,R6 | C118: CO2EO | D118: Electric Sector CO2 from old coal | E118: kt | F118: ENV
B119: R1,R2,R3,R4,R5,R6 | C119: SO2E | D119: Electric Sector Sulfur Emissions | E119: kt | F119: ENV
B120: R1,R2,R3,R4,R5,R6 | C120: SO2BE | D120: Sulfur dioxide - Electricity from biomass | E120: kt | F120: ENV
B121: R1,R2,R3,R4,R5,R6 | C121: NOXE | D121: Electric Sector NOX Emissions | E121: kt | F121: ENV
B122: R1,R2,R3,R4,R5,R6 | C122: NOXBE | D122: NOX Emissions - Electricity from biomass | E122: kt | F122: ENV
B123: R1,R2,R3,R4,R5,R6 | C123: PM10E | D123: Electric Sector PM10 Emissions | E123: kt | F123: ENV
B124: R1,R2,R3,R4,R5,R6 | C124: NH3 | D124: Electric Sector NH3 Emissions | E124: kt | F124: ENV
B125: R1,R2,R3,R4,R5,R6 | C125: CO2EF | D125: Electric Sector Fossil CO2 | E125: kt | F125: ENV
... B128: R1,R2,R3,R4,R5,R6 | C128: CO2CPP | D128: Electric Sector CO2 on CPP techs | E128: kt | F128: ENV
B129: *Emissions Commodities
B130: R1 | C130: ELCCOABH | D130: Coal to Electric Sector | E130: PJ | F130: NRG
B131: R1 | C131: ELCCOABL | D131: Coal to Electric Sector | E131: PJ
B132: R1 | C132: ELCCOABM | D132: Coal to Electric Sector | E132: PJ
B133: R1 | C133: ELCCOALH | D133: Coal to Electric Sector | E133: PJ
B134: R1 | C134: ELCCOALM | D134: Coal to Electric Sector | E134: PJ
B135: R1 | C135: ELCCOASL | D135: Coal to Electric Sector | E135: PJ
B136: R1 | C136: ELCCOASM | D136: Coal to Electric Sector | E136: PJ
B137: *CCS: Coal Energy Carriers
B138: R1 | C138: CSTMBHCCO | D138: High Sulfur Bituminous Coal Between SO2 and CO2 Controls or Pass Through Over 100MW | E138: PJ | F138: NRG
B139: R1 | C139: CSTMBLCCO | D139: Low Sulfur Bituminous Coal Between SO2 and CO2 Controls or Pass Through Over 100MW | E139: PJ
B140: R1 | C140: CSTMBMCCO | D140: Medium Sulfur Bituminous Coal Between SO2 and CO2 Controls or Pass Through Over 100MW | E140: PJ
B141: R1 | C141: CSTMLHCCO | D141: High Sulfur lignite Coal Between SO2 and CO2 Controls or Pass Through Over 100MW | E141: PJ
...

Sheet Technologies
B1: _GLOBAL,R0,R1,R2,R3,R4,R5,R6 | M1: Technologies
B6: ~FI_Process | C6: ELC_subres_technologies
B7: TechName | C7: TechDesc | D7: Tact | E7: Tcap | F7: Sets | G7: Tslvl | H7: PrimaryCG | I7: Vintage | M7: Region | P7: Comment
B8: *Electricity production New capacity
B9: ENGACC11 | C9: Natural Gas - Combined-Cycle (Turbine) | D9: PJ | E9: GW | F9: ELE | G9: DAYNITE
B10: ENGACC15 | C10: Natural Gas - Combined-Cycle (Turbine) | D10: PJ | E10: GW | F10: ELE | G10: DAYNITE
B11: ENGACC20 | C11: Natural Gas - Combined-Cycle (Turbine) | D11: PJ | E11: GW | F11: ELE | G11: DAYNITE
B12: ENGAACC20 | C12: Natural Gas - Advanced Combined-Cycle (Turbine) | D12: PJ | E12: GW | F12: ELE | G12: DAYNITE
B13: ENGACC25 | C13: Natural Gas - Advanced Combined-Cycle (Turbine) | D13: PJ | E13: GW | F13: ELE | G13: DAYNITE
B14: ENGACT11 | C14: Natural Gas - Combustion Turbine | D14: PJ | E14: GW | F14: ELE | G14: DAYNITE
B15: ENGACT15 | C15: Natural Gas - Combustion Turbine | D15: PJ | E15: GW | F15: ELE | G15: DAYNITE
B16: ENGACT20 | C16: Natural Gas - Combustion Turbine | D16: PJ | E16: GW | F16: ELE | G16: DAYNITE
B17: ENGAACT20 | C17: Natural Gas - Advanced Combustion Turbine | D17: PJ | E17: GW | F17: ELE | G17: DAYNITE
B18: EURNALWR28 | C18: Nuclear LWRs in 2028 | D18: PJ | E18: GW | F18: ELE | G18: SEASON | H18: NRGO
B19: EURNASMR | C19: Advanced nuclear technology: Small Modular Reactors | D19: PJ | E19: GW | F19: ELE | G19: SEASON | H19: NRGO
B20: *CHP production New capacity
B21: ECHPBIO11 | C21: Electric sector BIO CHP | D21: PJ | E21: GW | F21: HPL | G21: SEASON
B22: ECHPCOAL11 | C22: Electric sector Coal CHP | D22: PJ | E22: GW | F22: HPL | G22: DAYNITE
B23: ECHPNGA11 | C23: Electric sector NGA CHP | D23: PJ | E23: GW | F23: HPL | G23: DAYNITE
B24: ECHPOIL11 | C24: Electric sector Oil CHP | D24: PJ | E24: GW | F24: HPL | G24: DAYNITE
B25: *Hydro production New capacity
B26: EHYDCONR11 | C26: Hydroelectric, Conventional | D26: PJ | E26: GW | F26: ELE | G26: DAYNITE
B27: SHYDREVRIN11 | C27: Hydroelectric, Reversible | D27: PJ | E27: GW | F27: STG | G27: DAYNITE
B28: EHYDREVROUT11 | C28: Hydroelectric, Reversible | D28: PJ | E28: GW | F28: ELE | G28: DAYNITE
B29: *Utility-Scale Battery
B30: SSTOBATUTI-IN | C30: Electricity Battery Storage 4-hour Utility Scale | D30: PJ | E30: GW | F30: STG | G30: DAYNITE
B31: ESTOBATUTI-OUT | C31: Electricity Battery Storage 4-hour Utility Scale | D31: PJ | E31: GW | F31: ELE | G31: DAYNITE
B32: =TechData_NewCap!A34 -> SSTOBAT10HRUTI-IN | C32: =TechData_NewCap!B34 -> Electricity Battery Storage 10-hour Utility Scale | D32: PJ | E32: GW | F32: STG | G32: DAYNITE
B33: =TechData_NewCap!A35 -> ESTOBAT10HRUTI-OUT | C33: =TechData_NewCap!B35 -> Electricity Battery Storage 10-hour Utility Scale | D33: PJ | E33: GW | F33: ELE | G33: DAYNITE
B34: *Solar wind electricity production New capacity
B35: * Solar PV Technologies | G35: DAYNITE
B36: =TechData_SolarWind!A6 -> ESOLPVCLOWCOST | C36: =TechData_SolarWind!B6 -> Solar PV Centralized Generation, Low Cost | D36: PJ | E36: GW | F36: ELE | G36: DAYNITE
B37: =TechData_SolarWind!A7 -> ESOLPVCHIGHCOST | C37: =TechData_SolarWind!B7 -> Solar PV Centralized Generation, High Cost | D37: PJ | E37: GW | F37: ELE | G37: DAYNITE
B38: * Wind Technologies | C38: 0 | D38: PJ | E38: GW | F38: ELE | G38: DAYNITE
B39: =TechData_SolarWind!A9 -> EWNDONLOWCOST | C39: =TechData_SolarWind!B9 -> Onshore Wind, Low Cost | D39: PJ | E39: GW | F39: ELE | G39: DAYNITE
B40: =TechData_SolarWind!A10 -> EWNDONHIGHCOST | C40: =TechData_SolarWind!B10 -> Onshore Wind, High Cost | D40: PJ | E40: GW | F40: ELE | G40: DAYNITE
B41: =TechData_SolarWind!A11 -> EWNDOFFIX | C41: =TechData_SolarWind!B11 -> Offshore Wind Fixed Bottom | D41: PJ | E41: GW | F41: ELE | G41: DAYNITE
B42: =TechData_SolarWind!A12 -> EWNDOFFIX | C42: =TechData_SolarWind!B12 -> Offshore Wind Fixed Bottom | D42: PJ | E42: GW | F42: ELE | G42: DAYNITE
B43: =TechData_SolarWind!A13 -> EWNDOFFLT | C43: =TechData_SolarWind!B13 -> Offshore Wind Floating | D43: PJ | E43: GW | F43: ELE | G43: DAYNITE

Sheet TechData_NewCap
A1: _GLOBAL,R0,R1,R2,R3,R4,R5,R6
E3: ~FI_T
A4: TechName | B4: *TechDesc | C4: *Units | D4: Region | E4: CommIN | F4: CommOUT | G4: NCAP_START | H4: PRC_CAPACT | I4: EFF~2010 | J4: EFF~2015 | K4: EFF~2020 | L4: EFF~2025 | M4: EFF~2055 | N4: Output | O4: *lookup | P4: NCAP_TLIFE | Q4: Peak | R4: NCAP_DRATE | S4: NCAP_AFA | T4: NCAP_BND~UP~2015 | U4: NCAP_BND~UP~2020 | V4: NCAP_BND~UP~2025 | W4: NCAP_BND~UP~2030 | X4: NCAP_BND~UP~2035 | Y4: NCAP_BND~UP~2055 | Z4: *lookup | AA4: *Regional Cost Lookup | AB4: NCAP_FOM~2010 | AC4: ACT_COST~2010 | AD4: NCAP_FOM~2020 | AE4: ACT_COST~2020 | AF4: NCAP_COST~2010 | AG4: NCAP_COST~2015 | AH4: NCAP_COST~2020 | AI4: *LOOKUP: ATB Tech | AJ4: *LOOKUP: ATB TechDetail | AK4: *ATB CAPEX Base | AL4: NCAP_COST~2025 | AM4: NCAP_COST~2030 | AN4: NCAP_COST~2035 | AO4: NCAP_COST~2040 | AP4: NCAP_COST~2045 | AQ4: NCAP_COST~2050 | AR4: *ATB FOM Base | AS4: NCAP_FOM~2025 | AT4: NCAP_FOM~2030 | AU4: NCAP_FOM~2035 | AV4: NCAP_FOM~2040 | AW4: NCAP_FOM~2045 | AX4: NCAP_FOM~2050 | AY4: *ATB VOM Base | AZ4: ACT_COST~2025 | BA4: ACT_COST~2030 | BB4: ACT_COST~2035 | BC4: ACT_COST~2040 | BD4: ACT_COST~2045 | BE4: ACT_COST~2050 | BF4: Input~2010 | BG4: Input~2015 | BH4: Input~2020 | BI4: Input~2055 | BJ4: Region | BK4: ENV_ACT~CO2CPP~2010 | BL4: ENV_ACT~CO2CPP~2015 | BM4: ENV_ACT~CO2CPP~2020 | BN4: ENV_ACT~CO2CPP~2025 | BO4: ENV_ACT~CO2CPP~2055
A5: * | B5: new_capacity_conventional_technologies | I5: Burnup (MWD/kgHM): | J5: 50 | O5: Lookup from LifetimeAssumptions | Z5: Lookup from New Cap Raw Data | AB5: 2012 | AC5: 2022 | AL5: 2025 | AM5: 2030 | AN5: 2035 | AO5: 2040 | AP5: 2045 | AQ5: 2050 | AS5: 2025 | AT5: 2030 | AU5: 2035 | AV5: 2040 | AW5: 2045 | AX5: 2050 | AZ5: 2025 | BA5: 2030 | BB5: 2035 | BC5: 2040 | BD5: 2045 | BE5: 2050 | BK5: 57.838547
A6: ENGACC11 | B6: Natural Gas - Combined-Cycle (Turbine) | C6: PJ, GW | D6: R1,R2,R3,R4,R5,R6 | E6: ELCNGCEA | F6: ELC | G6: 2011 | H6: =GW_to_Pja -> 31.536 | I6: =1/BF6 -> 0.53774626 | J6: =1/BG6 -> 0.55751634 | K6: =1/BH6 -> 0.55751634 | L6: =1/BI6 -> 0.55751634 | M6: =L6 -> 0.55751634 | O6: =LifetimeAssumptions!$B$7 -> Existing Gas & oil turbines | P6: =_xlfn.XLOOKUP($O6, LifetimeAssumptions[technology],LifetimeAssumptions[Lifetime]) -> 50 | Q6: =_xlfn.XLOOKUP($O6, LifetimeAssumptions[technology],LifetimeAssumptions[Peak (con)]) -> 0.95 | R6: =_xlfn.XLOOKUP($O6, LifetimeAssumptions[technology],LifetimeAssumptions[Discrate]) -> 0.15 | S6: =_xlfn.XLOOKUP($O6, LifetimeAssumptions[technology],LifetimeAssumptions[AF]) -> 0.9 | T6: 0 | U6: 0 | V6: 0 | W6: 0 | X6: 0 | Y6: 0 | Z6: ='2013 Cap Raw Data'!$A$8 -> Conv Gas/Oil Comb Cycle | AB6: =_xlfn.XLOOKUP($Z6, NewCapCosts2013[Technology],NewCapCosts2013[Fixed O&M ($2012/kW)])*_xlfn.XLOOKUP($AB$5,GDP_deflator[Year],GDP_deflator[Multiply By (for $2005)]) -> 11.526453 | AC6: =_xlfn.XLOOKUP($Z6, NewCapCosts2013[Technology],NewCapCosts2013[Variable O&M ($2012 mills/kWh)])*_xlfn.XLOOKUP($AB$5,GDP_deflator[Year],GDP_deflator[Multiply By (for $2005)])*mills_kWh_to__Million_PJ -> 0.87520524 | AD6: =_xlfn.XLOOKUP($Z6, NewCapCosts2013[Technology],NewCapCosts2013[Fixed O&M ($2012/kW)])*_xlfn.XLOOKUP($AB$5,GDP_deflator[Year],GDP_deflator[Multiply By (for $2005)]) -> 11.526453 | AE6: =_xlfn.XLOOKUP($Z6, NewCapCosts2013[Technology],NewCapCosts2013[Variable O&M ($2012 mills/kWh)])*_xlfn.XLOOKUP($AB$5,GDP_deflator[Year],GDP_deflator[Multiply By (for $2005)])*mills_kWh_to__Million_PJ -> 0.87520524 | AF6: =_xlfn.XLOOKUP($Z6, NewCapCosts2013[Technology],NewCapCosts2013[Base Overnight Costs in 2012 ($2012/kW)])*_xlfn.XLOOKUP($AB$5,GDP_deflator[Year],GDP_deflator[Multiply By (for $2005)]) -> 762.30376 | AG6: =AF6 -> 762.30376 | AH6: =AG6 -> 762.30376 | AI6: =ATB_CAPEX!$E$490 -> NaturalGas_FE | AJ6: =ATB_CAPEX!$F$485 -> CTAvgCF | AK6: =SUMIFS(ATB_CAPEX[2022],ATB_CAPEX[CostCase],"Conservative",ATB_CAPEX[Technology],$AI6, ATB_CAPEX[TechDetail],$AJ6) -> 1348.8151 | AL6: =$AH6 * SUMIFS(INDIRECT("ATB_CAPEX["&AL$5&"]"),ATB_CAPEX[CostCase],"Conservative",ATB_CAPEX[Technology],$AI6, ATB_CAPEX[TechDetail],$AJ6)/$AK6 -> 745.67718 | AM6: =$AH6 * SUMIFS(INDIRECT("ATB_CAPEX["&AM$5&"]"),ATB_CAPEX[CostCase],"Conservative",ATB_CAPEX[Technology],$AI6, ATB_CAPEX[TechDetail],$AJ6)/$AK6 -> 718.02918 | AN6: =$AH6 * SUMIFS(INDIRECT("ATB_CAPEX["&AN$5&"]"),ATB_CAPEX[CostCase],"Conservative",ATB_CAPEX[Technology],$AI6, ATB_CAPEX[TechDetail],$AJ6)/$AK6 -> 690.3182 | AO6: =$AH6 * SUMIFS(INDIRECT("ATB_CAPEX["&AO$5&"]"),ATB_CAPEX[CostCase],"Conservative",ATB_CAPEX[Technology],$AI6, ATB_CAPEX[TechDetail],$AJ6)/$AK6 -> 662.67021 | AP6: =$AH6 * SUMIFS(INDIRECT("ATB_CAPEX["&AP$5&"]"),ATB_CAPEX[CostCase],"Conservative",ATB_CAPEX[Technology],$AI6, ATB_CAPEX[TechDetail],$AJ6)/$AK6 -> 635.02221 | AQ6: =$AH6 * SUMIFS(INDIRECT("ATB_CAPEX["&AQ$5&"]"),ATB_CAPEX[CostCase],"Conservative",ATB_CAPEX[Technology],$AI6, ATB_CAPEX[TechDetail],$AJ6)/$AK6 -> 607.31123 | AR6: =SUMIFS(ATB_FOM[2022],ATB_FOM[CostCase],"Conservative",ATB_FOM[Technology],$AI6, ATB_FOM[TechDetail],$AJ6) -> 26.1 | AS6: =$AB6 * SUMIFS(INDIRECT("ATB_FOM["&AS$5&"]"),ATB_FOM[CostCase],"Conservative",ATB_FOM[Technology],$AI6, ATB_FOM[TechDetail],$AJ6)/$AR6 -> 11.349802 | AT6: =$AB6 * SUMIFS(INDIRECT("ATB_FOM["&AT$5&"]"),ATB_FOM[CostCase],"Conservative",ATB_FOM[Technology],$AI6, ATB_FOM[TechDetail],$AJ6)/$AR6 -> 11.040664 | AU6: =$AB6 * SUMIFS(INDIRECT("ATB_FOM["&AU$5&"]"),ATB_FOM[CostCase],"Conservative",ATB_FOM[Technology],$AI6, ATB_FOM[TechDetail],$AJ6)/$AR6 -> 10.687363 | AV6: =$AB6 * SUMIFS(INDIRECT("ATB_FOM["&AV$5&"]"),ATB_FOM[CostCase],"Conservative",ATB_FOM[Technology],$AI6, ATB_FOM[TechDetail],$AJ6)/$AR6 -> 10.378224 | AW6: =$AB6 * SUMIFS(INDIRECT("ATB_FOM["&AW$5&"]"),ATB_FOM[CostCase],"Conservative",ATB_FOM[Technology],$AI6, ATB_FOM[TechDetail],$AJ6)/$AR6 -> 10.069085 | AX6: =$AB6 * SUMIFS(INDIRECT("ATB_FOM["&AX$5&"]"),ATB_FOM[CostCase],"Conservative",ATB_FOM[Technology],$AI6, ATB_FOM[TechDetail],$AJ6)/$AR6 -> 9.7157841 | AY6: =SUMIFS(ATB_VOM[2022],ATB_VOM[CostCase],"Conservative",ATB_VOM[Technology],$AI6, ATB_VOM[TechDetail],$AJ6) -> 6.94 | AZ6: =$AC6 * SUMIFS(INDIRECT("ATB_VOM["&AZ$5&"]"),ATB_VOM[CostCase],"Conservative",ATB_VOM[Technology],$AI6, ATB_VOM[TechDetail],$AJ6)/$AY6 -> 0.87520524 | BA6: =$AC6 * SUMIFS(INDIRECT("ATB_VOM["&BA$5&"]"),ATB_VOM[CostCase],"Conservative",ATB_VOM[Technology],$AI6, ATB_VOM[TechDetail],$AJ6)/$AY6 -> 0.87520524 | BB6: =$AC6 * SUMIFS(INDIRECT("ATB_VOM["&BB$5&"]"),ATB_VOM[CostCase],"Conservative",ATB_VOM[Technology],$AI6, ATB_VOM[TechDetail],$AJ6)/$AY6 -> 0.87520524 | BC6: =$AC6 * SUMIFS(INDIRECT("ATB_VOM["&BC$5&"]"),ATB_VOM[CostCase],"Conservative",ATB_VOM[Technology],$AI6, ATB_VOM[TechDetail],$AJ6)/$AY6 -> 0.87520524 | BD6: =$AC6 * SUMIFS(INDIRECT("ATB_VOM["&BD$5&"]"),ATB_VOM[CostCase],"Conservative",ATB_VOM[Technology],$AI6, ATB_VOM[TechDetail],$AJ6)/$AY6 -> 0.87520524 | BE6: =$AC6 * SUMIFS(INDIRECT("ATB_VOM["&BE$5&"]"),ATB_VOM[CostCase],"Conservative",ATB_VOM[Technology],$AI6, ATB_VOM[TechDetail],$AJ6)/$AY6 -> 0.87520524 | BF6: =_xlfn.XLOOKUP($Z6, NewCapCosts2013[Technology],NewCapCosts2013[Heatrate in 2013 (Btu/kWhr)])*0.9/kWh_to_btu_hr -> 1.8596131 | BG6: =_xlfn.XLOOKUP($Z6, NewCapCosts2013[Technology],NewCapCosts2013[Heatrate nth-of-a-kind (Btu/kWr)])*0.9/kWh_to_btu_hr -> 1.7936694 | BH6: =_xlfn.XLOOKUP($Z6, NewCapCosts2013[Technology],NewCapCosts2013[Heatrate nth-of-a-kind (Btu/kWr)])*0.9/kWh_to_btu_hr -> 1.7936694 | BI6: =_xlfn.XLOOKUP($Z6, NewCapCosts2013[Technology],NewCapCosts2013[Heatrate nth-of-a-kind (Btu/kWr)])*0.9/kWh_to_btu_hr -> 1.7936694 | BJ6: R2,R3,R4,R5,R6 | BK6: =$BK$5*BF6 -> 107.55732 | BM6: =$BK$5*BH6 -> 103.74323 | BN6: =$BK$5*BI6 -> 103.74323
A7: ENGACC15 | B7: Natural Gas - Combined-Cycle (Turbine) | C7: PJ, GW | D7: R1 | E7: ELCNGCEA | F7: ELC | G7: 2015 | H7: =GW_to_Pja -> 31.536 | I7: =1/BF7 -> 0.53774626 | J7: =1/BG7 -> 0.55751634 | K7: =1/BH7 -> 0.55751634 | L7: =1/BI7 -> 0.55751634 | M7: =L7 -> 0.55751634 | O7: =LifetimeAssumptions!$B$7 -> Existing Gas & oil turbines | P7: =_xlfn.XLOOKUP($O7, LifetimeAssumptions[technology],LifetimeAssumptions[Lifetime]) -> 50 | Q7: =_xlfn.XLOOKUP($O7, LifetimeAssumptions[technology],LifetimeAssumptions[Peak (con)]) -> 0.95 | R7: =_xlfn.XLOOKUP($O7, LifetimeAssumptions[technology],LifetimeAssumptions[Discrate]) -> 0.15 | S7: =_xlfn.XLOOKUP($O7, LifetimeAssumptions[technology],LifetimeAssumptions[AF]) -> 0.9 | U7: 0 | V7: 0 | W7: 0 | X7: 0 | Y7: 0 | Z7: ='2013 Cap Raw Data'!$A$8 -> Conv Gas/Oil Comb Cycle | AB7: =_xlfn.XLOOKUP($Z7, NewCapCosts2013[Technology],NewCapCosts2013[Fixed O&M ($2012/kW)])*_xlfn.XLOOKUP($AB$5,GDP_deflator[Year],GDP_deflator[Multiply By (for $2005)]) -> 11.526453 | AC7: =_xlfn.XLOOKUP($Z7, NewCapCosts2013[Technology],NewCapCosts2013[Variable O&M ($2012 mills/kWh)])*_xlfn.XLOOKUP($AB$5,GDP_deflator[Year],GDP_deflator[Multiply By (for $2005)])*mills_kWh_to__Million_PJ -> 0.87520524 | AD7: =_xlfn.XLOOKUP($Z7, NewCapCosts2013[Technology],NewCapCosts2013[Fixed O&M ($2012/kW)])*_xlfn.XLOOKUP($AB$5,GDP_deflator[Year],GDP_deflator[Multiply By (for $2005)]) -> 11.526453 | AE7: =_xlfn.XLOOKUP($Z7, NewCapCosts2013[Technology],NewCapCosts2013[Variable O&M ($2012 mills/kWh)])*_xlfn.XLOOKUP($AB$5,GDP_deflator[Year],GDP_deflator[Multiply By (for $2005)])*mills_kWh_to__Million_PJ -> 0.87520524 | AF7: =_xlfn.XLOOKUP($Z7, NewCapCosts2013[Technology],NewCapCosts2013[Base Overnight Costs in 2012 ($2012/kW)])*_xlfn.XLOOKUP($AB$5,GDP_deflator[Year],GDP_deflator[Multiply By (for $2005)]) -> 762.30376 | AG7: =AF7 -> 762.30376 | AH7: =AG7 -> 762.30376 | AI7: =ATB_CAPEX!$E$490 -> NaturalGas_FE | AJ7: =ATB_CAPEX!$F$485 -> CTAvgCF | AK7: =SUMIFS(ATB_CAPEX[2022],ATB_CAPEX[CostCase],"Conservative",ATB_CAPEX[Technology],$AI7, ATB_CAPEX[TechDetail],$AJ7) -> 1348.8151 | AL7: =$AH7 * SUMIFS(INDIRECT("ATB_CAPEX["&AL$5&"]"),ATB_CAPEX[CostCase],"Conservative",ATB_CAPEX[Technology],$AI7, ATB_CAPEX[TechDetail],$AJ7)/$AK7 -> 745.67718 | AM7: =$AH7 * SUMIFS(INDIRECT("ATB_CAPEX["&AM$5&"]"),ATB_CAPEX[CostCase],"Conservative",ATB_CAPEX[Technology],$AI7, ATB_CAPEX[TechDetail],$AJ7)/$AK7 -> 718.02918 | AN7: =$AH7 * SUMIFS(INDIRECT("ATB_CAPEX["&AN$5&"]"),ATB_CAPEX[CostCase],"Conservative",ATB_CAPEX[Technology],$AI7, ATB_CAPEX[TechDetail],$AJ7)/$AK7 -> 690.3182 | AO7: =$AH7 * SUMIFS(INDIRECT("ATB_CAPEX["&AO$5&"]"),ATB_CAPEX[CostCase],"Conservative",ATB_CAPEX[Technology],$AI7, ATB_CAPEX[TechDetail],$AJ7)/$AK7 -> 662.67021 | AP7: =$AH7 * SUMIFS(INDIRECT("ATB_CAPEX["&AP$5&"]"),ATB_CAPEX[CostCase],"Conservative",ATB_CAPEX[Technology],$AI7, ATB_CAPEX[TechDetail],$AJ7)/$AK7 -> 635.02221 | AQ7: =$AH7 * SUMIFS(INDIRECT("ATB_CAPEX["&AQ$5&"]"),ATB_CAPEX[CostCase],"Conservative",ATB_CAPEX[Technology],$AI7, ATB_CAPEX[TechDetail],$AJ7)/$AK7 -> 607.31123 | AR7: =SUMIFS(ATB_FOM[2022],ATB_FOM[CostCase],"Conservative",ATB_FOM[Technology],$AI7, ATB_FOM[TechDetail],$AJ7) -> 26.1 | AS7: =$AB7 * SUMIFS(INDIRECT("ATB_FOM["&AS$5&"]"),ATB_FOM[CostCase],"Conservative",ATB_FOM[Technology],$AI7, ATB_FOM[TechDetail],$AJ7)/$AR7 -> 11.349802 | AT7: =$AB7 * SUMIFS(INDIRECT("ATB_FOM["&AT$5&"]"),ATB_FOM[CostCase],"Conservative",ATB_FOM[Technology],$AI7, ATB_FOM[TechDetail],$AJ7)/$AR7 -> 11.040664 | AU7: =$AB7 * SUMIFS(INDIRECT("ATB_FOM["&AU$5&"]"),ATB_FOM[CostCase],"Conservative",ATB_FOM[Technology],$AI7, ATB_FOM[TechDetail],$AJ7)/$AR7 -> 10.687363 | AV7: =$AB7 * SUMIFS(INDIRECT("ATB_FOM["&AV$5&"]"),ATB_FOM[CostCase],"Conservative",ATB_FOM[Technology],$AI7, ATB_FOM[TechDetail],$AJ7)/$AR7 -> 10.378224 | AW7: =$AB7 * SUMIFS(INDIRECT("ATB_FOM["&AW$5&"]"),ATB_FOM[CostCase],"Conservative",ATB_FOM[Technology],$AI7, ATB_FOM[TechDetail],$AJ7)/$AR7 -> 10.069085 | AX7: =$AB7 * SUMIFS(INDIRECT("ATB_FOM["&AX$5&"]"),ATB_FOM[CostCase],"Conservative",ATB_FOM[Technology],$AI7, ATB_FOM[TechDetail],$AJ7)/$AR7 -> 9.7157841 | AY7: =SUMIFS(ATB_VOM[2022],ATB_VOM[CostCase],"Conservative",ATB_VOM[Technology],$AI7, ATB_VOM[TechDetail],$AJ7) -> 6.94 | AZ7: =$AC7 * SUMIFS(INDIRECT("ATB_VOM["&AZ$5&"]"),ATB_VOM[CostCase],"Conservative",ATB_VOM[Technology],$AI7, ATB_VOM[TechDetail],$AJ7)/$AY7 -> 0.87520524 | BA7: =$AC7 * SUMIFS(INDIRECT("ATB_VOM["&BA$5&"]"),ATB_VOM[CostCase],"Conservative",ATB_VOM[Technology],$AI7, ATB_VOM[TechDetail],$AJ7)/$AY7 -> 0.87520524 | BB7: =$AC7 * SUMIFS(INDIRECT("ATB_VOM["&BB$5&"]"),ATB_VOM[CostCase],"Conservative",ATB_VOM[Technology],$AI7, ATB_VOM[TechDetail],$AJ7)/$AY7 -> 0.87520524 | BC7: =$AC7 * SUMIFS(INDIRECT("ATB_VOM["&BC$5&"]"),ATB_VOM[CostCase],"Conservative",ATB_VOM[Technology],$AI7, ATB_VOM[TechDetail],$AJ7)/$AY7 -> 0.87520524 | BD7: =$AC7 * SUMIFS(INDIRECT("ATB_VOM["&BD$5&"]"),ATB_VOM[CostCase],"Conservative",ATB_VOM[Technology],$AI7, ATB_VOM[TechDetail],$AJ7)/$AY7 -> 0.87520524 | BE7: =$AC7 * SUMIFS(INDIRECT("ATB_VOM["&BE$5&"]"),ATB_VOM[CostCase],"Conservative",ATB_VOM[Technology],$AI7, ATB_VOM[TechDetail],$AJ7)/$AY7 -> 0.87520524 | BF7: =_xlfn.XLOOKUP($Z7, NewCapCosts2013[Technology],NewCapCosts2013[Heatrate in 2013 (Btu/kWhr)])*0.9/kWh_to_btu_hr -> 1.8596131 | BG7: =_xlfn.XLOOKUP($Z7, NewCapCosts2013[Technology],NewCapCosts2013[Heatrate nth-of-a-kind (Btu/kWr)])*0.9/kWh_to_btu_hr -> 1.7936694 | BH7: =_xlfn.XLOOKUP($Z7, NewCapCosts2013[Technology],NewCapCosts2013[Heatrate nth-of-a-kind (Btu/kWr)])*0.9/kWh_to_btu_hr -> 1.7936694 | BI7: =_xlfn.XLOOKUP($Z7, NewCapCosts2013[Technology],NewCapCosts2013[Heatrate nth-of-a-kind (Btu/kWr)])*0.9/kWh_to_btu_hr -> 1.7936694 | BJ7: R2,R3,R4,R5,R6 | BK7: =$BK$5*BF7 -> 107.55732 | BM7: =$BK$5*BH7 -> 103.74323 | BN7: =$BK$5*BI7 -> 103.74323
A8: ENGACC20 | B8: Natural Gas - Combined-Cycle (Turbine) | C8: PJ, GW | D8: R1 | E8: ELCNGCEA | F8: ELC | G8: 2020 | H8: =GW_to_Pja -> 31.536 | I8: =1/BF8 -> 0.53774626 | J8: =1/BG8 -> 0.55751634 | K8: =1/BH8 -> 0.55751634 | L8: =1/BI8 -> 0.55751634 | M8: =L8 -> 0.55751634 | O8: =LifetimeAssumptions!$B$8 -> New Gas & oil turbines | P8: =_xlfn.XLOOKUP($O8, LifetimeAssumptions[technology],LifetimeAssumptions[Lifetime]) -> 30 | Q8: =_xlfn.XLOOKUP($O8, LifetimeAssumptions[technology],LifetimeAssumptions[Peak (con)]) -> 0.95 | R8: =_xlfn.XLOOKUP($O8, LifetimeAssumptions[technology],LifetimeAssumptions[Discrate]) -> 0.15 | S8: =_xlfn.XLOOKUP($O8, LifetimeAssumptions[technology],LifetimeAssumptions[AF]) -> 0.9 | V8: 0 | W8: 0 | X8: 0 | Y8: 0 | Z8: ='2013 Cap Raw Data'!$A$8 -> Conv Gas/Oil Comb Cycle | AB8: =_xlfn.XLOOKUP($Z8, NewCapCosts2013[Technology],NewCapCosts2013[Fixed O&M ($2012/kW)])*_xlfn.XLOOKUP($AB$5,GDP_deflator[Year],GDP_deflator[Multiply By (for $2005)]) -> 11.526453 | AC8: =_xlfn.XLOOKUP($Z8, NewCapCosts2013[Technology],NewCapCosts2013[Variable O&M ($2012 mills/kWh)])*_xlfn.XLOOKUP($AB$5,GDP_deflator[Year],GDP_deflator[Multiply By (for $2005)])*mills_kWh_to__Million_PJ -> 0.87520524 | AD8: =_xlfn.XLOOKUP($Z8, NewCapCosts2013[Technology],NewCapCosts2013[Fixed O&M ($2012/kW)])*_xlfn.XLOOKUP($AB$5,GDP_deflator[Year],GDP_deflator[Multiply By (for $2005)]) -> 11.526453 | AE8: =_xlfn.XLOOKUP($Z8, NewCapCosts2013[Technology],NewCapCosts2013[Variable O&M ($2012 mills/kWh)])*_xlfn.XLOOKUP($AB$5,GDP_deflator[Year],GDP_deflator[Multiply By (for $2005)])*mills_kWh_to__Million_PJ -> 0.87520524 | AF8: =_xlfn.XLOOKUP($Z8, NewCapCosts2013[Technology],NewCapCosts2013[Base Overnight Costs in 2012 ($2012/kW)])*_xlfn.XLOOKUP($AB$5,GDP_deflator[Year],GDP_deflator[Multiply By (for $2005)]) -> 762.30376 | AG8: =AF8 -> 762.30376 | AH8: =AG8 -> 762.30376 | AI8: =ATB_CAPEX!$E$490 -> NaturalGas_FE | AJ8: =ATB_CAPEX!$F$485 -> CTAvgCF | AK8: =SUMIFS(ATB_CAPEX[2022],ATB_CAPEX[CostCase],"Conservative",ATB_CAPEX[Technology],$AI8, ATB_CAPEX[TechDetail],$AJ8) -> 1348.8151 | AL8: =$AH8 * SUMIFS(INDIRECT("ATB_CAPEX["&AL$5&"]"),ATB_CAPEX[CostCase],"Conservative",ATB_CAPEX[Technology],$AI8, ATB_CAPEX[TechDetail],$AJ8)/$AK8 -> 745.67718 | AM8: =$AH8 * SUMIFS(INDIRECT("ATB_CAPEX["&AM$5&"]"),ATB_CAPEX[CostCase],"Conservative",ATB_CAPEX[Technology],$AI8, ATB_CAPEX[TechDetail],$AJ8)/$AK8 -> 718.02918 | AN8: =$AH8 * SUMIFS(INDIRECT("ATB_CAPEX["&AN$5&"]"),ATB_CAPEX[CostCase],"Conservative",ATB_CAPEX[Technology],$AI8, ATB_CAPEX[TechDetail],$AJ8)/$AK8 -> 690.3182 | AO8: =$AH8 * SUMIFS(INDIRECT("ATB_CAPEX["&AO$5&"]"),ATB_CAPEX[CostCase],"Conservative",ATB_CAPEX[Technology],$AI8, ATB_CAPEX[TechDetail],$AJ8)/$AK8 -> 662.67021 | AP8: =$AH8 * SUMIFS(INDIRECT("ATB_CAPEX["&AP$5&"]"),ATB_CAPEX[CostCase],"Conservative",ATB_CAPEX[Technology],$AI8, ATB_CAPEX[TechDetail],$AJ8)/$AK8 -> 635.02221 | AQ8: =$AH8 * SUMIFS(INDIRECT("ATB_CAPEX["&AQ$5&"]"),ATB_CAPEX[CostCase],"Conservative",ATB_CAPEX[Technology],$AI8, ATB_CAPEX[TechDetail],$AJ8)/$AK8 -> 607.31123 | AR8: =SUMIFS(ATB_FOM[2022],ATB_FOM[CostCase],"Conservative",ATB_FOM[Technology],$AI8, ATB_FOM[TechDetail],$AJ8) -> 26.1 | AS8: =$AB8 * SUMIFS(INDIRECT("ATB_FOM["&AS$5&"]"),ATB_FOM[CostCase],"Conservative",ATB_FOM[Technology],$AI8, ATB_FOM[TechDetail],$AJ8)/$AR8 -> 11.349802 | AT8: =$AB8 * SUMIFS(INDIRECT("ATB_FOM["&AT$5&"]"),ATB_FOM[CostCase],"Conservative",ATB_FOM[Technology],$AI8, ATB_FOM[TechDetail],$AJ8)/$AR8 -> 11.040664 | AU8: =$AB8 * SUMIFS(INDIRECT("ATB_FOM["&AU$5&"]"),ATB_FOM[CostCase],"Conservative",ATB_FOM[Technology],$AI8, ATB_FOM[TechDetail],$AJ8)/$AR8 -> 10.687363 | AV8: =$AB8 * SUMIFS(INDIRECT("ATB_FOM["&AV$5&"]"),ATB_FOM[CostCase],"Conservative",ATB_FOM[Technology],$AI8, ATB_FOM[TechDetail],$AJ8)/$AR8 -> 10.378224 | AW8: =$AB8 * SUMIFS(INDIRECT("ATB_FOM["&AW$5&"]"),ATB_FOM[CostCase],"Conservative",ATB_FOM[Technology],$AI8, ATB_FOM[TechDetail],$AJ8)/$AR8 -> 10.069085 | AX8: =$AB8 * SUMIFS(INDIRECT("ATB_FOM["&AX$5&"]"),ATB_FOM[CostCase],"Conservative",ATB_FOM[Technology],$AI8, ATB_FOM[TechDetail],$AJ8)/$AR8 -> 9.7157841 | AY8: =SUMIFS(ATB_VOM[2022],ATB_VOM[CostCase],"Conservative",ATB_VOM[Technology],$AI8, ATB_VOM[TechDetail],$AJ8) -> 6.94 | AZ8: =$AC8 * SUMIFS(INDIRECT("ATB_VOM["&AZ$5&"]"),ATB_VOM[CostCase],"Conservative",ATB_VOM[Technology],$AI8, ATB_VOM[TechDetail],$AJ8)/$AY8 -> 0.87520524 | BA8: =$AC8 * SUMIFS(INDIRECT("ATB_VOM["&BA$5&"]"),ATB_VOM[CostCase],"Conservative",ATB_VOM[Technology],$AI8, ATB_VOM[TechDetail],$AJ8)/$AY8 -> 0.87520524 | BB8: =$AC8 * SUMIFS(INDIRECT("ATB_VOM["&BB$5&"]"),ATB_VOM[CostCase],"Conservative",ATB_VOM[Technology],$AI8, ATB_VOM[TechDetail],$AJ8)/$AY8 -> 0.87520524 | BC8: =$AC8 * SUMIFS(INDIRECT("ATB_VOM["&BC$5&"]"),ATB_VOM[CostCase],"Conservative",ATB_VOM[Technology],$AI8, ATB_VOM[TechDetail],$AJ8)/$AY8 -> 0.87520524 | BD8: =$AC8 * SUMIFS(INDIRECT("ATB_VOM["&BD$5&"]"),ATB_VOM[CostCase],"Conservative",ATB_VOM[Technology],$AI8, ATB_VOM[TechDetail],$AJ8)/$AY8 -> 0.87520524 | BE8: =$AC8 * SUMIFS(INDIRECT("ATB_VOM["&BE$5&"]"),ATB_VOM[CostCase],"Conservative",ATB_VOM[Technology],$AI8, ATB_VOM[TechDetail],$AJ8)/$AY8 -> 0.87520524 | BF8: =_xlfn.XLOOKUP($Z8, NewCapCosts2013[Technology],NewCapCosts2013[Heatrate in 2013 (Btu/kWhr)])*0.9/kWh_to_btu_hr -> 1.8596131 | BG8: =_xlfn.XLOOKUP($Z8, NewCapCosts2013[Technology],NewCapCosts2013[Heatrate nth-of-a-kind (Btu/kWr)])*0.9/kWh_to_btu_hr -> 1.7936694 | BH8: =_xlfn.XLOOKUP($Z8, NewCapCosts2013[Technology],NewCapCosts2013[Heatrate nth-of-a-kind (Btu/kWr)])*0.9/kWh_to_btu_hr -> 1.7936694 | BI8: =_xlfn.XLOOKUP($Z8, NewCapCosts2013[Technology],NewCapCosts2013[Heatrate nth-of-a-kind (Btu/kWr)])*0.9/kWh_to_btu_hr -> 1.7936694 | BJ8: R2,R3,R4,R5,R6
A9: ENGAACC20 | B9: Natural Gas - Advanced Combined-Cycle (Turbine) | C9: PJ, GW | D9: R1 | E9: ELCNGCEA | F9: ELC | G9: 2020 | H9: =GW_to_Pja -> 31.536 | I9: =1/BF9 -> 0.58959737 | J9: =1/BG9 -> 0.598628 | K9: =1/BH9 -> 0.598628 | L9: =1/BI9 -> 0.598628 | M9: =L9 -> 0.598628 | O9: =LifetimeAssumptions!$B$8 -> New Gas & oil turbines | P9: =_xlfn.XLOOKUP($O9, LifetimeAssumptions[technology],LifetimeAssumptions[Lifetime]) -> 30 | Q9: =_xlfn.XLOOKUP($O9, LifetimeAssumptions[technology],LifetimeAssumptions[Peak (con)]) -> 0.95 | R9: =_xlfn.XLOOKUP($O9, LifetimeAssumptions[technology],LifetimeAssumptions[Discrate]) -> 0.15 | S9: =_xlfn.XLOOKUP($O9, LifetimeAssumptions[technology],LifetimeAssumptions[AF]) -> 0.9 | V9: 0 | W9: 0 | X9: 0 | Y9: 0 | Z9: ='2013 Cap Raw Data'!$A$9 -> Adv Gas/Oil Comb Cycle (CC) | AB9: =_xlfn.XLOOKUP($Z9, NewCapCosts2013[Technology],NewCapCosts2013[Fixed O&M ($2012/kW)])*_xlfn.XLOOKUP($AB$5,GDP_deflator[Year],GDP_deflator[Multiply By (for $2005)]) -> 13.451904 | AC9: =_xlfn.XLOOKUP($Z9, NewCapCosts2013[Technology],NewCapCosts2013[Variable O&M ($2012 mills/kWh)])*_xlfn.XLOOKUP($AB$5,GDP_deflator[Year],GDP_deflator[Multiply By (for $2005)])*mills_kWh_to__Million_PJ -> 0.79497809 | AD9: =_xlfn.XLOOKUP($Z9, NewCapCosts2013[Technology],NewCapCosts2013[Fixed O&M ($2012/kW)])*_xlfn.XLOOKUP($AB$5,GDP_deflator[Year],GDP_deflator[Multiply By (for $2005)]) -> 13.451904 | AE9: =_xlfn.XLOOKUP($Z9, NewCapCosts2013[Technology],NewCapCosts2013[Variable O&M ($2012 mills/kWh)])*_xlfn.XLOOKUP($AB$5,GDP_deflator[Year],GDP_deflator[Multiply By (for $2005)])*mills_kWh_to__Million_PJ -> 0.79497809 | AF9: =_xlfn.XLOOKUP($Z9, NewCapCosts2013[Technology],NewCapCosts2013[Base Overnight Costs in 2012 ($2012/kW)])*_xlfn.XLOOKUP($AB$5,GDP_deflator[Year],GDP_deflator[Multiply By (for $2005)]) -> 827.06895 | AG9: =AF9 -> 827.06895 | AH9: =AG9 -> 827.06895 | AI9: =ATB_CAPEX!$E$490 -> NaturalGas_FE | AJ9: =ATB_CAPEX!$F$485 -> CTAvgCF | AK9: =SUMIFS(ATB_CAPEX[2022],ATB_CAPEX[CostCase],"Conservative",ATB_CAPEX[Technology],$AI9, ATB_CAPEX[TechDetail],$AJ9) -> 1348.8151 | AL9: =$AH9 * SUMIFS(INDIRECT("ATB_CAPEX["&AL$5&"]"),ATB_CAPEX[CostCase],"Conservative",ATB_CAPEX[Technology],$AI9, ATB_CAPEX[TechDetail],$AJ9)/$AK9 -> 809.02977 | AM9: =$AH9 * SUMIFS(INDIRECT("ATB_CAPEX["&AM$5&"]"),ATB_CAPEX[CostCase],"Conservative",ATB_CAPEX[Technology],$AI9, ATB_CAPEX[TechDetail],$AJ9)/$AK9 -> 779.03281 | AN9: =$AH9 * SUMIFS(INDIRECT("ATB_CAPEX["&AN$5&"]"),ATB_CAPEX[CostCase],"Conservative",ATB_CAPEX[Technology],$AI9, ATB_CAPEX[TechDetail],$AJ9)/$AK9 -> 748.96751 | AO9: =$AH9 * SUMIFS(INDIRECT("ATB_CAPEX["&AO$5&"]"),ATB_CAPEX[CostCase],"Conservative",ATB_CAPEX[Technology],$AI9, ATB_CAPEX[TechDetail],$AJ9)/$AK9 -> 718.97055 | AP9: =$AH9 * SUMIFS(INDIRECT("ATB_CAPEX["&AP$5&"]"),ATB_CAPEX[CostCase],"Conservative",ATB_CAPEX[Technology],$AI9, ATB_CAPEX[TechDetail],$AJ9)/$AK9 -> 688.97358 | AQ9: =$AH9 * SUMIFS(INDIRECT("ATB_CAPEX["&AQ$5&"]"),ATB_CAPEX[CostCase],"Conservative",ATB_CAPEX[Technology],$AI9, ATB_CAPEX[TechDetail],$AJ9)/$AK9 -> 658.90828 | AR9: =SUMIFS(ATB_FOM[2022],ATB_FOM[CostCase],"Conservative",ATB_FOM[Technology],$AI9, ATB_FOM[TechDetail],$AJ9) -> 26.1 | AS9: =$AB9 * SUMIFS(INDIRECT("ATB_FOM["&AS$5&"]"),ATB_FOM[CostCase],"Conservative",ATB_FOM[Technology],$AI9, ATB_FOM[TechDetail],$AJ9)/$AR9 -> 13.245745 | AT9: =$AB9 * SUMIFS(INDIRECT("ATB_FOM["&AT$5&"]"),ATB_FOM[CostCase],"Conservative",ATB_FOM[Technology],$AI9, ATB_FOM[TechDetail],$AJ9)/$AR9 -> 12.884966 | AU9: =$AB9 * SUMIFS(INDIRECT("ATB_FOM["&AU$5&"]"),ATB_FOM[CostCase],"Conservative",ATB_FOM[Technology],$AI9, ATB_FOM[TechDetail],$AJ9)/$AR9 -> 12.472647 | AV9: =$AB9 * SUMIFS(INDIRECT("ATB_FOM["&AV$5&"]"),ATB_FOM[CostCase],"Conservative",ATB_FOM[Technology],$AI9, ATB_FOM[TechDetail],$AJ9)/$AR9 -> 12.111868 | AW9: =$AB9 * SUMIFS(INDIRECT("ATB_FOM["&AW$5&"]"),ATB_FOM[CostCase],"Conservative",ATB_FOM[Technology],$AI9, ATB_FOM[TechDetail],$AJ9)/$AR9 -> 11.751089 | AX9: =$AB9 * SUMIFS(INDIRECT("ATB_FOM["&AX$5&"]"),ATB_FOM[CostCase],"Conservative",ATB_FOM[Technology],$AI9, ATB_FOM[TechDetail],$AJ9)/$AR9 -> 11.33877 | AY9: =SUMIFS(ATB_VOM[2022],ATB_VOM[CostCase],"Conservative",ATB_VOM[Technology],$AI9, ATB_VOM[TechDetail],$AJ9) -> 6.94 | AZ9: =$AC9 * SUMIFS(INDIRECT("ATB_VOM["&AZ$5&"]"),ATB_VOM[CostCase],"Conservative",ATB_VOM[Technology],$AI9, ATB_VOM[TechDetail],$AJ9)/$AY9 -> 0.79497809 | BA9: =$AC9 * SUMIFS(INDIRECT("ATB_VOM["&BA$5&"]"),ATB_VOM[CostCase],"Conservative",ATB_VOM[Technology],$AI9, ATB_VOM[TechDetail],$AJ9)/$AY9 -> 0.79497809 | BB9: =$AC9 * SUMIFS(INDIRECT("ATB_VOM["&BB$5&"]"),ATB_VOM[CostCase],"Conservative",ATB_VOM[Technology],$AI9, ATB_VOM[TechDetail],$AJ9)/$AY9 -> 0.79497809 | BC9: =$AC9 * SUMIFS(INDIRECT("ATB_VOM["&BC$5&"]"),ATB_VOM[CostCase],"Conservative",ATB_VOM[Technology],$AI9, ATB_VOM[TechDetail],$AJ9)/$AY9 -> 0.79497809 | BD9: =$AC9 * SUMIFS(INDIRECT("ATB_VOM["&BD$5&"]"),ATB_VOM[CostCase],"Conservative",ATB_VOM[Technology],$AI9, ATB_VOM[TechDetail],$AJ9)/$AY9 -> 0.79497809 | BE9: =$AC9 * SUMIFS(INDIRECT("ATB_VOM["&BE$5&"]"),ATB_VOM[CostCase],"Conservative",ATB_VOM[Technology],$AI9, ATB_VOM[TechDetail],$AJ9)/$AY9 -> 0.79497809 | BF9: =_xlfn.XLOOKUP($Z9, NewCapCosts2013[Technology],NewCapCosts2013[Heatrate in 2013 (Btu/kWhr)])*0.9/kWh_to_btu_hr -> 1.6960727 | BG9: =_xlfn.XLOOKUP($Z9, NewCapCosts2013[Technology],NewCapCosts2013[Heatrate nth-of-a-kind (Btu/kWr)])*0.9/kWh_to_btu_hr -> 1.6704865 | BH9: =_xlfn.XLOOKUP($Z9, NewCapCosts2013[Technology],NewCapCosts2013[Heatrate nth-of-a-kind (Btu/kWr)])*0.9/kWh_to_btu_hr -> 1.6704865 | BI9: =_xlfn.XLOOKUP($Z9, NewCapCosts2013[Technology],NewCapCosts2013[Heatrate nth-of-a-kind (Btu/kWr)])*0.9/kWh_to_btu_hr -> 1.6704865 | BJ9: R2,R3,R4,R5,R6
A10: ENGACC25 | B10: Natural Gas - Combined-Cycle (Turbine) | C10: PJ, GW | D10: R1 | E10: ELCNGCEA | F10: ELC | G10: 2025 | H10: =GW_to_Pja -> 31.536 | I10: =1/BF10 -> 0.59515088 | J10: =1/BG10 -> 0.59515088 | K10: =1/BH10 -> 0.59515088 | L10: =1/BI10 -> 0.59515088 | M10: =L10 -> 0.59515088 | O10: =LifetimeAssumptions!$B$8 -> New Gas & oil turbines | P10: =_xlfn.XLOOKUP($O10, LifetimeAssumptions[technology],LifetimeAssumptions[Lifetime]) -> 30 | Q10: =_xlfn.XLOOKUP($O10, LifetimeAssumptions[technology],LifetimeAssumptions[Peak (con)]) -> 0.95 | R10: =_xlfn.XLOOKUP($O10, LifetimeAssumptions[technology],LifetimeAssumptions[Discrate]) -> 0.15 | S10: =_xlfn.XLOOKUP($O10, LifetimeAssumptions[technology],LifetimeAssumptions[AF]) -> 0.9 | Z10: ='2023 Cap Raw Data'!$A$10 -> Combined-cycle—multi-shaft | AA10: ='2023_Regional_Cost_Factor'!$A$9 -> CC – multi shaft | AB10: =_xlfn.XLOOKUP($Z10, NewCapCosts2023[Technology],NewCapCosts2023[Fixed O&M (2022$/Kw-y)])*_xlfn.XLOOKUP($AC$5,GDP_deflator[Year],GDP_deflator[Multiply By (for $2005)]) -> 9.4882051 | AC10: =_xlfn.XLOOKUP($Z10, NewCapCosts2023[Technology],NewCapCosts2023[Variable O&Mf (2022 $/MWh)])*_xlfn.XLOOKUP($AC$5,GDP_deflator[Year],GDP_deflator[Multiply By (for $2005)])*mills_kWh_to__Million_PJ -> 0.40398315 | AD10: =_xlfn.XLOOKUP($Z10, NewCapCosts2023[Technology],NewCapCosts2023[Fixed O&M (2022$/Kw-y)])*_xlfn.XLOOKUP($AC$5,GDP_deflator[Year],GDP_deflator[Multiply By (for $2005)]) -> 9.4882051 | AE10: =_xlfn.XLOOKUP($Z10, NewCapCosts2023[Technology],NewCapCosts2023[Variable O&Mf (2022 $/MWh)])*_xlfn.XLOOKUP($AC$5,GDP_deflator[Year],GDP_deflator[Multiply By (for $2005)])*mills_kWh_to__Million_PJ -> 0.40398315 | AF10: =_xlfn.XLOOKUP($AA10,NewCapRegionalCosts[Technology], NewCapRegionalCosts[9 (NYUP)])*_xlfn.XLOOKUP($AC$5,GDP_deflator[Year],GDP_deflator[Multiply By (for $2005)]) -> 946.79625 | AG10: =AF10 -> 946.79625 | AH10: =AG10 -> 946.79625 | AI10: =ATB_CAPEX!$E$490 -> NaturalGas_FE | AJ10: =ATB_CAPEX!$F$485 -> CTAvgCF | AK10: =SUMIFS(ATB_CAPEX[2022],ATB_CAPEX[CostCase],"Conservative",ATB_CAPEX[Technology],$AI10, ATB_CAPEX[TechDetail],$AJ10) -> 1348.8151 | AL10: =$AH10 * SUMIFS(INDIRECT("ATB_CAPEX["&AL$5&"]"),ATB_CAPEX[CostCase],"Conservative",ATB_CAPEX[Technology],$AI10, ATB_CAPEX[TechDetail],$AJ10)/$AK10 -> 926.1457 | AM10: =$AH10 * SUMIFS(INDIRECT("ATB_CAPEX["&AM$5&"]"),ATB_CAPEX[CostCase],"Conservative",ATB_CAPEX[Technology],$AI10, ATB_CAPEX[TechDetail],$AJ10)/$AK10 -> 891.80634 | AN10: =$AH10 * SUMIFS(INDIRECT("ATB_CAPEX["&AN$5&"]"),ATB_CAPEX[CostCase],"Conservative",ATB_CAPEX[Technology],$AI10, ATB_CAPEX[TechDetail],$AJ10)/$AK10 -> 857.38877 | AO10: =$AH10 * SUMIFS(INDIRECT("ATB_CAPEX["&AO$5&"]"),ATB_CAPEX[CostCase],"Conservative",ATB_CAPEX[Technology],$AI10, ATB_CAPEX[TechDetail],$AJ10)/$AK10 -> 823.04941 | AP10: =$AH10 * SUMIFS(INDIRECT("ATB_CAPEX["&AP$5&"]"),ATB_CAPEX[CostCase],"Conservative",ATB_CAPEX[Technology],$AI10, ATB_CAPEX[TechDetail],$AJ10)/$AK10 -> 788.71006 | AQ10: =$AH10 * SUMIFS(INDIRECT("ATB_CAPEX["&AQ$5&"]"),ATB_CAPEX[CostCase],"Conservative",ATB_CAPEX[Technology],$AI10, ATB_CAPEX[TechDetail],$AJ10)/$AK10 -> 754.29248 | AR10: =SUMIFS(ATB_FOM[2022],ATB_FOM[CostCase],"Conservative",ATB_FOM[Technology],$AI10, ATB_FOM[TechDetail],$AJ10) -> 26.1 | AS10: =$AB10 * SUMIFS(INDIRECT("ATB_FOM["&AS$5&"]"),ATB_FOM[CostCase],"Conservative",ATB_FOM[Technology],$AI10, ATB_FOM[TechDetail],$AJ10)/$AR10 -> 9.342792 | AT10: =$AB10 * SUMIFS(INDIRECT("ATB_FOM["&AT$5&"]"),ATB_FOM[CostCase],"Conservative",ATB_FOM[Technology],$AI10, ATB_FOM[TechDetail],$AJ10)/$AR10 -> 9.0883191 | AU10: =$AB10 * SUMIFS(INDIRECT("ATB_FOM["&AU$5&"]"),ATB_FOM[CostCase],"Conservative",ATB_FOM[Technology],$AI10, ATB_FOM[TechDetail],$AJ10)/$AR10 -> 8.7974929 | AV10: =$AB10 * SUMIFS(INDIRECT("ATB_FOM["&AV$5&"]"),ATB_FOM[CostCase],"Conservative",ATB_FOM[Technology],$AI10, ATB_FOM[TechDetail],$AJ10)/$AR10 -> 8.5430199 | AW10: =$AB10 * SUMIFS(INDIRECT("ATB_FOM["&AW$5&"]"),ATB_FOM[CostCase],"Conservative",ATB_FOM[Technology],$AI10, ATB_FOM[TechDetail],$AJ10)/$AR10 -> 8.288547 | AX10: =$AB10 * SUMIFS(INDIRECT("ATB_FOM["&AX$5&"]"),ATB_FOM[CostCase],"Conservative",ATB_FOM[Technology],$AI10, ATB_FOM[TechDetail],$AJ10)/$AR10 -> 7.9977208 | AY10: =SUMIFS(ATB_VOM[2022],ATB_VOM[CostCase],"Conservative",ATB_VOM[Technology],$AI10, ATB_VOM[TechDetail],$AJ10) -> 6.94 | AZ10: =$AC10 * SUMIFS(INDIRECT("ATB_VOM["&AZ$5&"]"),ATB_VOM[CostCase],"Conservative",ATB_VOM[Technology],$AI10, ATB_VOM[TechDetail],$AJ10)/$AY10 -> 0.40398315 | BA10: =$AC10 * SUMIFS(INDIRECT("ATB_VOM["&BA$5&"]"),ATB_VOM[CostCase],"Conservative",ATB_VOM[Technology],$AI10, ATB_VOM[TechDetail],$AJ10)/$AY10 -> 0.40398315 | BB10: =$AC10 * SUMIFS(INDIRECT("ATB_VOM["&BB$5&"]"),ATB_VOM[CostCase],"Conservative",ATB_VOM[Technology],$AI10, ATB_VOM[TechDetail],$AJ10)/$AY10 -> 0.40398315 | BC10: =$AC10 * SUMIFS(INDIRECT("ATB_VOM["&BC$5&"]"),ATB_VOM[CostCase],"Conservative",ATB_VOM[Technology],$AI10, ATB_VOM[TechDetail],$AJ10)/$AY10 -> 0.40398315 | BD10: =$AC10 * SUMIFS(INDIRECT("ATB_VOM["&BD$5&"]"),ATB_VOM[CostCase],"Conservative",ATB_VOM[Technology],$AI10, ATB_VOM[TechDetail],$AJ10)/$AY10 -> 0.40398315 | BE10: =$AC10 * SUMIFS(INDIRECT("ATB_VOM["&BE$5&"]"),ATB_VOM[CostCase],"Conservative",ATB_VOM[Technology],$AI10, ATB_VOM[TechDetail],$AJ10)/$AY10 -> 0.40398315 | BF10: =_xlfn.XLOOKUP($Z10, NewCapCosts2023[Technology],NewCapCosts2023[Heat rateg (Btu/kWh)])*0.9/kWh_to_btu_hr -> 1.6802462 | BG10: =_xlfn.XLOOKUP($Z10, NewCapCosts2023[Technology],NewCapCosts2023[Heat rateg (Btu/kWh)])*0.9/kWh_to_btu_hr -> 1.6802462 | BH10: =_xlfn.XLOOKUP($Z10, NewCapCosts2023[Technology],NewCapCosts2023[Heat rateg (Btu/kWh)])*0.9/kWh_to_btu_hr -> 1.6802462 | BI10: =_xlfn.XLOOKUP($Z10, NewCapCosts2023[Technology],NewCapCosts2023[Heat rateg (Btu/kWh)])*0.9/kWh_to_btu_hr -> 1.6802462 | BJ10: R2,R3,R4,R5,R6
A11: *ENGACC25 | B11: Natural Gas - Combined-Cycle (Turbine) | C11: PJ, GW | D11: R2,R3,R4,R5,R6 | E11: ELCNGCEA | F11: ELC | G11: 2025 | H11: =GW_to_Pja -> 31.536 | I11: =1/BF11 -> 0.59515088 | J11: =1/BG11 -> 0.59515088 | K11: =1/BH11 -> 0.59515088 | L11: =1/BI11 -> 0.59515088 | M11: =L11 -> 0.59515088 | O11: =LifetimeAssumptions!$B$8 -> New Gas & oil turbines | P11: =_xlfn.XLOOKUP($O11, LifetimeAssumptions[technology],LifetimeAssumptions[Lifetime]) -> 30 | Q11: =_xlfn.XLOOKUP($O11, LifetimeAssumptions[technology],LifetimeAssumptions[Peak (con)]) -> 0.95 | R11: =_xlfn.XLOOKUP($O11, LifetimeAssumptions[technology],LifetimeAssumptions[Discrate]) -> 0.15 | S11: =_xlfn.XLOOKUP($O11, LifetimeAssumptions[technology],LifetimeAssumptions[AF]) -> 0.9 | Z11: ='2023 Cap Raw Data'!$A$10 -> Combined-cycle—multi-shaft | AA11: ='2023_Regional_Cost_Factor'!$A$9 -> CC – multi shaft | AB11: =_xlfn.XLOOKUP($Z11, NewCapCosts2023[Technology],NewCapCosts2023[Fixed O&M (2022$/Kw-y)])*_xlfn.XLOOKUP($AC$5,GDP_deflator[Year],GDP_deflator[Multiply By (for $2005)]) -> 9.4882051 | AC11: =_xlfn.XLOOKUP($Z11, NewCapCosts2023[Technology],NewCapCosts2023[Variable O&Mf (2022 $/MWh)])*_xlfn.XLOOKUP($AC$5,GDP_deflator[Year],GDP_deflator[Multiply By (for $2005)])*mills_kWh_to__Million_PJ -> 0.40398315 | AD11: =_xlfn.XLOOKUP($Z11, NewCapCosts2023[Technology],NewCapCosts2023[Fixed O&M (2022$/Kw-y)])*_xlfn.XLOOKUP($AC$5,GDP_deflator[Year],GDP_deflator[Multiply By (for $2005)]) -> 9.4882051 | AE11: =_xlfn.XLOOKUP($Z11, NewCapCosts2023[Technology],NewCapCosts2023[Variable O&Mf (2022 $/MWh)])*_xlfn.XLOOKUP($AC$5,GDP_deflator[Year],GDP_deflator[Multiply By (for $2005)])*mills_kWh_to__Million_PJ -> 0.40398315 | AF11: =_xlfn.XLOOKUP($AA11,NewCapRegionalCosts[Technology], NewCapRegionalCosts[8 (NYCW)])*_xlfn.XLOOKUP($AC$5,GDP_deflator[Year],GDP_deflator[Multiply By (for $2005)]) -> 1318.8732 | AG11: =AF11 -> 1318.8732 | AH11: =AG11 -> 1318.8732 | AI11: =ATB_CAPEX!$E$490 -> NaturalGas_FE | AJ11: =ATB_CAPEX!$F$485 -> CTAvgCF | AK11: =SUMIFS(ATB_CAPEX[2022],ATB_CAPEX[CostCase],"Conservative",ATB_CAPEX[Technology],$AI11, ATB_CAPEX[TechDetail],$AJ11) -> 1348.8151 | AL11: =$AH11 * SUMIFS(INDIRECT("ATB_CAPEX["&AL$5&"]"),ATB_CAPEX[CostCase],"Conservative",ATB_CAPEX[Technology],$AI11, ATB_CAPEX[TechDetail],$AJ11)/$AK11 -> 1290.1073 | AM11: =$AH11 * SUMIFS(INDIRECT("ATB_CAPEX["&AM$5&"]"),ATB_CAPEX[CostCase],"Conservative",ATB_CAPEX[Technology],$AI11, ATB_CAPEX[TechDetail],$AJ11)/$AK11 -> 1242.273 | AN11: =$AH11 * SUMIFS(INDIRECT("ATB_CAPEX["&AN$5&"]"),ATB_CAPEX[CostCase],"Conservative",ATB_CAPEX[Technology],$AI11, ATB_CAPEX[TechDetail],$AJ11)/$AK11 -> 1194.3299 | AO11: =$AH11 * SUMIFS(INDIRECT("ATB_CAPEX["&AO$5&"]"),ATB_CAPEX[CostCase],"Conservative",ATB_CAPEX[Technology],$AI11, ATB_CAPEX[TechDetail],$AJ11)/$AK11 -> 1146.4957 | AP11: =$AH11 * SUMIFS(INDIRECT("ATB_CAPEX["&AP$5&"]"),ATB_CAPEX[CostCase],"Conservative",ATB_CAPEX[Technology],$AI11, ATB_CAPEX[TechDetail],$AJ11)/$AK11 -> 1098.6614 | AQ11: =$AH11 * SUMIFS(INDIRECT("ATB_CAPEX["&AQ$5&"]"),ATB_CAPEX[CostCase],"Conservative",ATB_CAPEX[Technology],$AI11, ATB_CAPEX[TechDetail],$AJ11)/$AK11 -> 1050.7183 | AR11: =SUMIFS(ATB_FOM[2022],ATB_FOM[CostCase],"Conservative",ATB_FOM[Technology],$AI11, ATB_FOM[TechDetail],$AJ11) -> 26.1 | AS11: =$AB11 * SUMIFS(INDIRECT("ATB_FOM["&AS$5&"]"),ATB_FOM[CostCase],"Conservative",ATB_FOM[Technology],$AI11, ATB_FOM[TechDetail],$AJ11)/$AR11 -> 9.342792 | AT11: =$AB11 * SUMIFS(INDIRECT("ATB_FOM["&AT$5&"]"),ATB_FOM[CostCase],"Conservative",ATB_FOM[Technology],$AI11, ATB_FOM[TechDetail],$AJ11)/$AR11 -> 9.0883191 | AU11: =$AB11 * SUMIFS(INDIRECT("ATB_FOM["&AU$5&"]"),ATB_FOM[CostCase],"Conservative",ATB_FOM[Technology],$AI11, ATB_FOM[TechDetail],$AJ11)/$AR11 -> 8.7974929 | AV11: =$AB11 * SUMIFS(INDIRECT("ATB_FOM["&AV$5&"]"),ATB_FOM[CostCase],"Conservative",ATB_FOM[Technology],$AI11, ATB_FOM[TechDetail],$AJ11)/$AR11 -> 8.5430199 | AW11: =$AB11 * SUMIFS(INDIRECT("ATB_FOM["&AW$5&"]"),ATB_FOM[CostCase],"Conservative",ATB_FOM[Technology],$AI11, ATB_FOM[TechDetail],$AJ11)/$AR11 -> 8.288547 | AX11: =$AB11 * SUMIFS(INDIRECT("ATB_FOM["&AX$5&"]"),ATB_FOM[CostCase],"Conservative",ATB_FOM[Technology],$AI11, ATB_FOM[TechDetail],$AJ11)/$AR11 -> 7.9977208 | AY11: =SUMIFS(ATB_VOM[2022],ATB_VOM[CostCase],"Conservative",ATB_VOM[Technology],$AI11, ATB_VOM[TechDetail],$AJ11) -> 6.94 | AZ11: =$AC11 * SUMIFS(INDIRECT("ATB_VOM["&AZ$5&"]"),ATB_VOM[CostCase],"Conservative",ATB_VOM[Technology],$AI11, ATB_VOM[TechDetail],$AJ11)/$AY11 -> 0.40398315 | BA11: =$AC11 * SUMIFS(INDIRECT("ATB_VOM["&BA$5&"]"),ATB_VOM[CostCase],"Conservative",ATB_VOM[Technology],$AI11, ATB_VOM[TechDetail],$AJ11)/$AY11 -> 0.40398315 | BB11: =$AC11 * SUMIFS(INDIRECT("ATB_VOM["&BB$5&"]"),ATB_VOM[CostCase],"Conservative",ATB_VOM[Technology],$AI11, ATB_VOM[TechDetail],$AJ11)/$AY11 -> 0.40398315 | BC11: =$AC11 * SUMIFS(INDIRECT("ATB_VOM["&BC$5&"]"),ATB_VOM[CostCase],"Conservative",ATB_VOM[Technology],$AI11, ATB_VOM[TechDetail],$AJ11)/$AY11 -> 0.40398315 | BD11: =$AC11 * SUMIFS(INDIRECT("ATB_VOM["&BD$5&"]"),ATB_VOM[CostCase],"Conservative",ATB_VOM[Technology],$AI11, ATB_VOM[TechDetail],$AJ11)/$AY11 -> 0.40398315 | BE11: =$AC11 * SUMIFS(INDIRECT("ATB_VOM["&BE$5&"]"),ATB_VOM[CostCase],"Conservative",ATB_VOM[Technology],$AI11, ATB_VOM[TechDetail],$AJ11)/$AY11 -> 0.40398315 | BF11: =_xlfn.XLOOKUP($Z11, NewCapCosts2023[Technology],NewCapCosts2023[Heat rateg (Btu/kWh)])*0.9/kWh_to_btu_hr -> 1.6802462 | BG11: =_xlfn.XLOOKUP($Z11, NewCapCosts2023[Technology],NewCapCosts2023[Heat rateg (Btu/kWh)])*0.9/kWh_to_btu_hr -> 1.6802462 | BH11: =_xlfn.XLOOKUP($Z11, NewCapCosts2023[Technology],NewCapCosts2023[Heat rateg (Btu/kWh)])*0.9/kWh_to_btu_hr -> 1.6802462 | BI11: =_xlfn.XLOOKUP($Z11, NewCapCosts2023[Technology],NewCapCosts2023[Heat rateg (Btu/kWh)])*0.9/kWh_to_btu_hr -> 1.6802462 | BJ11: R2,R3,R4,R5,R6
A12: ENGACT11 | B12: Natural Gas - Combustion Turbine | C12: PJ, GW | D12: R1,R2,R3,R4,R5,R6 | E12: ELCNGAEA | F12: ELC | G12: 2011 | H12: =GW_to_Pja -> 31.536 | I12: =1/BF12 -> 0.34726675 | J12: =1/BG12 -> 0.36278575 | K12: =1/BH12 -> 0.36278575 | L12: =1/BI12 -> 0.36278575 | M12: =L12 -> 0.36278575 | O12: =LifetimeAssumptions!$B$7 -> Existing Gas & oil turbines | P12: =_xlfn.XLOOKUP($O12, LifetimeAssumptions[technology],LifetimeAssumptions[Lifetime]) -> 50 | Q12: =_xlfn.XLOOKUP($O12, LifetimeAssumptions[technology],LifetimeAssumptions[Peak (con)]) -> 0.95 | R12: =_xlfn.XLOOKUP($O12, LifetimeAssumptions[technology],LifetimeAssumptions[Discrate]) -> 0.15 | S12: =_xlfn.XLOOKUP($O12, LifetimeAssumptions[technology],LifetimeAssumptions[AF]) -> 0.9 | T12: 0 | U12: 0 | V12: 0 | W12: 0 | X12: 0 | Y12: 0 | Z12: ='2013 Cap Raw Data'!$A$11 -> Conv Combustion Turbine | AB12: =_xlfn.XLOOKUP($Z12, NewCapCosts2013[Technology],NewCapCosts2013[Fixed O&M ($2012/kW)])*_xlfn.XLOOKUP($AB$5,GDP_deflator[Year],GDP_deflator[Multiply By (for $2005)]) -> 6.4240064 | AC12: =_xlfn.XLOOKUP($Z12, NewCapCosts2013[Technology],NewCapCosts2013[Variable O&M ($2012 mills/kWh)])*_xlfn.XLOOKUP($AB$5,GDP_deflator[Year],GDP_deflator[Multiply By (for $2005)])*mills_kWh_to__Million_PJ -> 3.7560891 | AD12: =_xlfn.XLOOKUP($Z12, NewCapCosts2013[Technology],NewCapCosts2013[Fixed O&M ($2012/kW)])*_xlfn.XLOOKUP($AB$5,GDP_deflator[Year],GDP_deflator[Multiply By (for $2005)]) -> 6.4240064 | AE12: =_xlfn.XLOOKUP($Z12, NewCapCosts2013[Technology],NewCapCosts2013[Variable O&M ($2012 mills/kWh)])*_xlfn.XLOOKUP($AB$5,GDP_deflator[Year],GDP_deflator[Multiply By (for $2005)])*mills_kWh_to__Million_PJ -> 3.7560891 | AF12: =_xlfn.XLOOKUP($Z12, NewCapCosts2013[Technology],NewCapCosts2013[Base Overnight Costs in 2012 ($2012/kW)])*_xlfn.XLOOKUP($AB$5,GDP_deflator[Year],GDP_deflator[Multiply By (for $2005)]) -> 808.68964 | AG12: =AF12 -> 808.68964 | AH12: =AG12 -> 808.68964 | AI12: =ATB_CAPEX!$E$490 -> NaturalGas_FE | AJ12: =ATB_CAPEX!$F$488 -> CCAvgCF | AK12: =SUMIFS(ATB_CAPEX[2022],ATB_CAPEX[CostCase],"Conservative",ATB_CAPEX[Technology],$AI12, ATB_CAPEX[TechDetail],$AJ12) -> 1499.253 | AL12: =$AH12 * SUMIFS(INDIRECT("ATB_CAPEX["&AL$5&"]"),ATB_CAPEX[CostCase],"Conservative",ATB_CAPEX[Technology],$AI12, ATB_CAPEX[TechDetail],$AJ12)/$AK12 -> 793.78292 | AM12: =$AH12 * SUMIFS(INDIRECT("ATB_CAPEX["&AM$5&"]"),ATB_CAPEX[CostCase],"Conservative",ATB_CAPEX[Technology],$AI12, ATB_CAPEX[TechDetail],$AJ12)/$AK12 -> 768.89831 | AN12: =$AH12 * SUMIFS(INDIRECT("ATB_CAPEX["&AN$5&"]"),ATB_CAPEX[CostCase],"Conservative",ATB_CAPEX[Technology],$AI12, ATB_CAPEX[TechDetail],$AJ12)/$AK12 -> 744.0137 | AO12: =$AH12 * SUMIFS(INDIRECT("ATB_CAPEX["&AO$5&"]"),ATB_CAPEX[CostCase],"Conservative",ATB_CAPEX[Technology],$AI12, ATB_CAPEX[TechDetail],$AJ12)/$AK12 -> 719.12909 | AP12: =$AH12 * SUMIFS(INDIRECT("ATB_CAPEX["&AP$5&"]"),ATB_CAPEX[CostCase],"Conservative",ATB_CAPEX[Technology],$AI12, ATB_CAPEX[TechDetail],$AJ12)/$AK12 -> 694.24449 | AQ12: =$AH12 * SUMIFS(INDIRECT("ATB_CAPEX["&AQ$5&"]"),ATB_CAPEX[CostCase],"Conservative",ATB_CAPEX[Technology],$AI12, ATB_CAPEX[TechDetail],$AJ12)/$AK12 -> 669.41999 | AR12: =SUMIFS(ATB_FOM[2022],ATB_FOM[CostCase],"Conservative",ATB_FOM[Technology],$AI12, ATB_FOM[TechDetail],$AJ12) -> 34.5 | AS12: =$AB12 * SUMIFS(INDIRECT("ATB_FOM["&AS$5&"]"),ATB_FOM[CostCase],"Conservative",ATB_FOM[Technology],$AI12, ATB_FOM[TechDetail],$AJ12)/$AR12 -> 6.3122846 | AT12: =$AB12 * SUMIFS(INDIRECT("ATB_FOM["&AT$5&"]"),ATB_FOM[CostCase],"Conservative",ATB_FOM[Technology],$AI12, ATB_FOM[TechDetail],$AJ12)/$AR12 -> 6.1074612 | AU12: =$AB12 * SUMIFS(INDIRECT("ATB_FOM["&AU$5&"]"),ATB_FOM[CostCase],"Conservative",ATB_FOM[Technology],$AI12, ATB_FOM[TechDetail],$AJ12)/$AR12 -> 5.9212581 | AV12: =$AB12 * SUMIFS(INDIRECT("ATB_FOM["&AV$5&"]"),ATB_FOM[CostCase],"Conservative",ATB_FOM[Technology],$AI12, ATB_FOM[TechDetail],$AJ12)/$AR12 -> 5.735055 | AW12: =$AB12 * SUMIFS(INDIRECT("ATB_FOM["&AW$5&"]"),ATB_FOM[CostCase],"Conservative",ATB_FOM[Technology],$AI12, ATB_FOM[TechDetail],$AJ12)/$AR12 -> 5.5488519 | AX12: =$AB12 * SUMIFS(INDIRECT("ATB_FOM["&AX$5&"]"),ATB_FOM[CostCase],"Conservative",ATB_FOM[Technology],$AI12, ATB_FOM[TechDetail],$AJ12)/$AR12 -> 5.3626489 | AY12: =SUMIFS(ATB_VOM[2022],ATB_VOM[CostCase],"Conservative",ATB_VOM[Technology],$AI12, ATB_VOM[TechDetail],$AJ12) -> 2.17 | AZ12: =$AC12 * SUMIFS(INDIRECT("ATB_VOM["&AZ$5&"]"),ATB_VOM[CostCase],"Conservative",ATB_VOM[Technology],$AI12, ATB_VOM[TechDetail],$AJ12)/$AY12 -> 3.7041616 | BA12: =$AC12 * SUMIFS(INDIRECT("ATB_VOM["&BA$5&"]"),ATB_VOM[CostCase],"Conservative",ATB_VOM[Technology],$AI12, ATB_VOM[TechDetail],$AJ12)/$AY12 -> 3.6003066 | BB12: =$AC12 * SUMIFS(INDIRECT("ATB_VOM["&BB$5&"]"),ATB_VOM[CostCase],"Conservative",ATB_VOM[Technology],$AI12, ATB_VOM[TechDetail],$AJ12)/$AY12 -> 3.5137608 | BC12: =$AC12 * SUMIFS(INDIRECT("ATB_VOM["&BC$5&"]"),ATB_VOM[CostCase],"Conservative",ATB_VOM[Technology],$AI12, ATB_VOM[TechDetail],$AJ12)/$AY12 -> 3.427215 | BD12: =$AC12 * SUMIFS(INDIRECT("ATB_VOM["&BD$5&"]"),ATB_VOM[CostCase],"Conservative",ATB_VOM[Technology],$AI12, ATB_VOM[TechDetail],$AJ12)/$AY12 -> 3.3406691 | BE12: =$AC12 * SUMIFS(INDIRECT("ATB_VOM["&BE$5&"]"),ATB_VOM[CostCase],"Conservative",ATB_VOM[Technology],$AI12, ATB_VOM[TechDetail],$AJ12)/$AY12 -> 3.2368141 | BF12: =_xlfn.XLOOKUP($Z12, NewCapCosts2013[Technology],NewCapCosts2013[Heatrate in 2013 (Btu/kWhr)])*0.9/kWh_to_btu_hr -> 2.8796307 | BG12: =_xlfn.XLOOKUP($Z12, NewCapCosts2013[Technology],NewCapCosts2013[Heatrate nth-of-a-kind (Btu/kWr)])*0.9/kWh_to_btu_hr -> 2.7564478 | BH12: =_xlfn.XLOOKUP($Z12, NewCapCosts2013[Technology],NewCapCosts2013[Heatrate nth-of-a-kind (Btu/kWr)])*0.9/kWh_to_btu_hr -> 2.7564478 | BI12: =_xlfn.XLOOKUP($Z12, NewCapCosts2013[Technology],NewCapCosts2013[Heatrate nth-of-a-kind (Btu/kWr)])*0.9/kWh_to_btu_hr -> 2.7564478 | BJ12: R2,R3,R4,R5,R6
A13: ENGACT15 | B13: Natural Gas - Combustion Turbine | C13: PJ, GW | D13: R1 | E13: ELCNGAEA | F13: ELC | G13: 2015 | H13: =GW_to_Pja -> 31.536 | I13: =1/BF13 -> 0.34726675 | J13: =1/BG13 -> 0.36278575 | K13: =1/BH13 -> 0.36278575 | L13: =1/BI13 -> 0.36278575 | M13: =L13 -> 0.36278575 | O13: =LifetimeAssumptions!$B$7 -> Existing Gas & oil turbines | P13: =_xlfn.XLOOKUP($O13, LifetimeAssumptions[technology],LifetimeAssumptions[Lifetime]) -> 50 | Q13: =_xlfn.XLOOKUP($O13, LifetimeAssumptions[technology],LifetimeAssumptions[Peak (con)]) -> 0.95 | R13: =_xlfn.XLOOKUP($O13, LifetimeAssumptions[technology],LifetimeAssumptions[Discrate]) -> 0.15 | S13: =_xlfn.XLOOKUP($O13, LifetimeAssumptions[technology],LifetimeAssumptions[AF]) -> 0.9 | U13: 0 | V13: 0 | W13: 0 | X13: 0 | Y13: 0 | Z13: ='2013 Cap Raw Data'!$A$11 -> Conv Combustion Turbine | AB13: =_xlfn.XLOOKUP($Z13, NewCapCosts2013[Technology],NewCapCosts2013[Fixed O&M ($2012/kW)])*_xlfn.XLOOKUP($AB$5,GDP_deflator[Year],GDP_deflator[Multiply By (for $2005)]) -> 6.4240064 | AC13: =_xlfn.XLOOKUP($Z13, NewCapCosts2013[Technology],NewCapCosts2013[Variable O&M ($2012 mills/kWh)])*_xlfn.XLOOKUP($AB$5,GDP_deflator[Year],GDP_deflator[Multiply By (for $2005)])*mills_kWh_to__Million_PJ -> 3.7560891 | AD13: =_xlfn.XLOOKUP($Z13, NewCapCosts2013[Technology],NewCapCosts2013[Fixed O&M ($2012/kW)])*_xlfn.XLOOKUP($AB$5,GDP_deflator[Year],GDP_deflator[Multiply By (for $2005)]) -> 6.4240064 | AE13: =_xlfn.XLOOKUP($Z13, NewCapCosts2013[Technology],NewCapCosts2013[Variable O&M ($2012 mills/kWh)])*_xlfn.XLOOKUP($AB$5,GDP_deflator[Year],GDP_deflator[Multiply By (for $2005)])*mills_kWh_to__Million_PJ -> 3.7560891 | AF13: =_xlfn.XLOOKUP($Z13, NewCapCosts2013[Technology],NewCapCosts2013[Base Overnight Costs in 2012 ($2012/kW)])*_xlfn.XLOOKUP($AB$5,GDP_deflator[Year],GDP_deflator[Multiply By (for $2005)]) -> 808.68964 | AG13: =AF13 -> 808.68964 | AH13: =AG13 -> 808.68964 | AI13: =ATB_CAPEX!$E$490 -> NaturalGas_FE | AJ13: =ATB_CAPEX!$F$488 -> CCAvgCF | AK13: =SUMIFS(ATB_CAPEX[2022],ATB_CAPEX[CostCase],"Conservative",ATB_CAPEX[Technology],$AI13, ATB_CAPEX[TechDetail],$AJ13) -> 1499.253 | AL13: =$AH13 * SUMIFS(INDIRECT("ATB_CAPEX["&AL$5&"]"),ATB_CAPEX[CostCase],"Conservative",ATB_CAPEX[Technology],$AI13, ATB_CAPEX[TechDetail],$AJ13)/$AK13 -> 793.78292 | AM13: =$AH13 * SUMIFS(INDIRECT("ATB_CAPEX["&AM$5&"]"),ATB_CAPEX[CostCase],"Conservative",ATB_CAPEX[Technology],$AI13, ATB_CAPEX[TechDetail],$AJ13)/$AK13 -> 768.89831 | AN13: =$AH13 * SUMIFS(INDIRECT("ATB_CAPEX["&AN$5&"]"),ATB_CAPEX[CostCase],"Conservative",ATB_CAPEX[Technology],$AI13, ATB_CAPEX[TechDetail],$AJ13)/$AK13 -> 744.0137 | AO13: =$AH13 * SUMIFS(INDIRECT("ATB_CAPEX["&AO$5&"]"),ATB_CAPEX[CostCase],"Conservative",ATB_CAPEX[Technology],$AI13, ATB_CAPEX[TechDetail],$AJ13)/$AK13 -> 719.12909 | AP13: =$AH13 * SUMIFS(INDIRECT("ATB_CAPEX["&AP$5&"]"),ATB_CAPEX[CostCase],"Conservative",ATB_CAPEX[Technology],$AI13, ATB_CAPEX[TechDetail],$AJ13)/$AK13 -> 694.24449 | AQ13: =$AH13 * SUMIFS(INDIRECT("ATB_CAPEX["&AQ$5&"]"),ATB_CAPEX[CostCase],"Conservative",ATB_CAPEX[Technology],$AI13, ATB_CAPEX[TechDetail],$AJ13)/$AK13 -> 669.41999 | AR13: =SUMIFS(ATB_FOM[2022],ATB_FOM[CostCase],"Conservative",ATB_FOM[Technology],$AI13, ATB_FOM[TechDetail],$AJ13) -> 34.5 | AS13: =$AB13 * SUMIFS(INDIRECT("ATB_FOM["&AS$5&"]"),ATB_FOM[CostCase],"Conservative",ATB_FOM[Technology],$AI13, ATB_FOM[TechDetail],$AJ13)/$AR13 -> 6.3122846 | AT13: =$AB13 * SUMIFS(INDIRECT("ATB_FOM["&AT$5&"]"),ATB_FOM[CostCase],"Conservative",ATB_FOM[Technology],$AI13, ATB_FOM[TechDetail],$AJ13)/$AR13 -> 6.1074612 | AU13: =$AB13 * SUMIFS(INDIRECT("ATB_FOM["&AU$5&"]"),ATB_FOM[CostCase],"Conservative",ATB_FOM[Technology],$AI13, ATB_FOM[TechDetail],$AJ13)/$AR13 -> 5.9212581 | AV13: =$AB13 * SUMIFS(INDIRECT("ATB_FOM["&AV$5&"]"),ATB_FOM[CostCase],"Conservative",ATB_FOM[Technology],$AI13, ATB_FOM[TechDetail],$AJ13)/$AR13 -> 5.735055 | AW13: =$AB13 * SUMIFS(INDIRECT("ATB_FOM["&AW$5&"]"),ATB_FOM[CostCase],"Conservative",ATB_FOM[Technology],$AI13, ATB_FOM[TechDetail],$AJ13)/$AR13 -> 5.5488519 | AX13: =$AB13 * SUMIFS(INDIRECT("ATB_FOM["&AX$5&"]"),ATB_FOM[CostCase],"Conservative",ATB_FOM[Technology],$AI13, ATB_FOM[TechDetail],$AJ13)/$AR13 -> 5.3626489 | AY13: =SUMIFS(ATB_VOM[2022],ATB_VOM[CostCase],"Conservative",ATB_VOM[Technology],$AI13, ATB_VOM[TechDetail],$AJ13) -> 2.17 | AZ13: =$AC13 * SUMIFS(INDIRECT("ATB_VOM["&AZ$5&"]"),ATB_VOM[CostCase],"Conservative",ATB_VOM[Technology],$AI13, ATB_VOM[TechDetail],$AJ13)/$AY13 -> 3.7041616 | BA13: =$AC13 * SUMIFS(INDIRECT("ATB_VOM["&BA$5&"]"),ATB_VOM[CostCase],"Conservative",ATB_VOM[Technology],$AI13, ATB_VOM[TechDetail],$AJ13)/$AY13 -> 3.6003066 | BB13: =$AC13 * SUMIFS(INDIRECT("ATB_VOM["&BB$5&"]"),ATB_VOM[CostCase],"Conservative",ATB_VOM[Technology],$AI13, ATB_VOM[TechDetail],$AJ13)/$AY13 -> 3.5137608 | BC13: =$AC13 * SUMIFS(INDIRECT("ATB_VOM["&BC$5&"]"),ATB_VOM[CostCase],"Conservative",ATB_VOM[Technology],$AI13, ATB_VOM[TechDetail],$AJ13)/$AY13 -> 3.427215 | BD13: =$AC13 * SUMIFS(INDIRECT("ATB_VOM["&BD$5&"]"),ATB_VOM[CostCase],"Conservative",ATB_VOM[Technology],$AI13, ATB_VOM[TechDetail],$AJ13)/$AY13 -> 3.3406691 | BE13: =$AC13 * SUMIFS(INDIRECT("ATB_VOM["&BE$5&"]"),ATB_VOM[CostCase],"Conservative",ATB_VOM[Technology],$AI13, ATB_VOM[TechDetail],$AJ13)/$AY13 -> 3.2368141 | BF13: =_xlfn.XLOOKUP($Z13, NewCapCosts2013[Technology],NewCapCosts2013[Heatrate in 2013 (Btu/kWhr)])*0.9/kWh_to_btu_hr -> 2.8796307 | BG13: =_xlfn.XLOOKUP($Z13, NewCapCosts2013[Technology],NewCapCosts2013[Heatrate nth-of-a-kind (Btu/kWr)])*0.9/kWh_to_btu_hr -> 2.7564478 | BH13: =_xlfn.XLOOKUP($Z13, NewCapCosts2013[Technology],NewCapCosts2013[Heatrate nth-of-a-kind (Btu/kWr)])*0.9/kWh_to_btu_hr -> 2.7564478 | BI13: =_xlfn.XLOOKUP($Z13, NewCapCosts2013[Technology],NewCapCosts2013[Heatrate nth-of-a-kind (Btu/kWr)])*0.9/kWh_to_btu_hr -> 2.7564478 | BJ13: R2,R3,R4,R5,R6
A14: ENGACT20 | B14: Natural Gas - Combustion Turbine | C14: PJ, GW | D14: R1 | E14: ELCNGAEA | F14: ELC | G14: 2020 | H14: =GW_to_Pja -> 31.536 | I14: =1/BF14 -> 0.34726675 | J14: =1/BG14 -> 0.36278575 | K14: =1/BH14 -> 0.36278575 | L14: =1/BI14 -> 0.36278575 | M14: =L14 -> 0.36278575 | O14: =LifetimeAssumptions!$B$8 -> New Gas & oil turbines | P14: =_xlfn.XLOOKUP($O14, LifetimeAssumptions[technology],LifetimeAssumptions[Lifetime]) -> 30 | Q14: =_xlfn.XLOOKUP($O14, LifetimeAssumptions[technology],LifetimeAssumptions[Peak (con)]) -> 0.95 | R14: =_xlfn.XLOOKUP($O14, LifetimeAssumptions[technology],LifetimeAssumptions[Discrate]) -> 0.15 | S14: =_xlfn.XLOOKUP($O14, LifetimeAssumptions[technology],LifetimeAssumptions[AF]) -> 0.9 | V14: 0 | W14: 0 | X14: 0 | Y14: 0 | Z14: ='2013 Cap Raw Data'!$A$11 -> Conv Combustion Turbine | AB14: =_xlfn.XLOOKUP($Z14, NewCapCosts2013[Technology],NewCapCosts2013[Fixed O&M ($2012/kW)])*_xlfn.XLOOKUP($AB$5,GDP_deflator[Year],GDP_deflator[Multiply By (for $2005)]) -> 6.4240064 | AC14: =_xlfn.XLOOKUP($Z14, NewCapCosts2013[Technology],NewCapCosts2013[Variable O&M ($2012 mills/kWh)])*_xlfn.XLOOKUP($AB$5,GDP_deflator[Year],GDP_deflator[Multiply By (for $2005)])*mills_kWh_to__Million_PJ -> 3.7560891 | AD14: =_xlfn.XLOOKUP($Z14, NewCapCosts2013[Technology],NewCapCosts2013[Fixed O&M ($2012/kW)])*_xlfn.XLOOKUP($AB$5,GDP_deflator[Year],GDP_deflator[Multiply By (for $2005)]) -> 6.4240064 | AE14: =_xlfn.XLOOKUP($Z14, NewCapCosts2013[Technology],NewCapCosts2013[Variable O&M ($2012 mills/kWh)])*_xlfn.XLOOKUP($AB$5,GDP_deflator[Year],GDP_deflator[Multiply By (for $2005)])*mills_kWh_to__Million_PJ -> 3.7560891 | AF14: =_xlfn.XLOOKUP($Z14, NewCapCosts2013[Technology],NewCapCosts2013[Base Overnight Costs in 2012 ($2012/kW)])*_xlfn.XLOOKUP($AB$5,GDP_deflator[Year],GDP_deflator[Multiply By (for $2005)]) -> 808.68964 | AG14: =AF14 -> 808.68964 | AH14: =AG14 -> 808.68964 | AI14: =ATB_CAPEX!$E$490 -> NaturalGas_FE | AJ14: =ATB_CAPEX!$F$488 -> CCAvgCF | AK14: =SUMIFS(ATB_CAPEX[2022],ATB_CAPEX[CostCase],"Conservative",ATB_CAPEX[Technology],$AI14, ATB_CAPEX[TechDetail],$AJ14) -> 1499.253 | AL14: =$AH14 * SUMIFS(INDIRECT("ATB_CAPEX["&AL$5&"]"),ATB_CAPEX[CostCase],"Conservative",ATB_CAPEX[Technology],$AI14, ATB_CAPEX[TechDetail],$AJ14)/$AK14 -> 793.78292 | AM14: =$AH14 * SUMIFS(INDIRECT("ATB_CAPEX["&AM$5&"]"),ATB_CAPEX[CostCase],"Conservative",ATB_CAPEX[Technology],$AI14, ATB_CAPEX[TechDetail],$AJ14)/$AK14 -> 768.89831 | AN14: =$AH14 * SUMIFS(INDIRECT("ATB_CAPEX["&AN$5&"]"),ATB_CAPEX[CostCase],"Conservative",ATB_CAPEX[Technology],$AI14, ATB_CAPEX[TechDetail],$AJ14)/$AK14 -> 744.0137 | AO14: =$AH14 * SUMIFS(INDIRECT("ATB_CAPEX["&AO$5&"]"),ATB_CAPEX[CostCase],"Conservative",ATB_CAPEX[Technology],$AI14, ATB_CAPEX[TechDetail],$AJ14)/$AK14 -> 719.12909 | AP14: =$AH14 * SUMIFS(INDIRECT("ATB_CAPEX["&AP$5&"]"),ATB_CAPEX[CostCase],"Conservative",ATB_CAPEX[Technology],$AI14, ATB_CAPEX[TechDetail],$AJ14)/$AK14 -> 694.24449 | AQ14: =$AH14 * SUMIFS(INDIRECT("ATB_CAPEX["&AQ$5&"]"),ATB_CAPEX[CostCase],"Conservative",ATB_CAPEX[Technology],$AI14, ATB_CAPEX[TechDetail],$AJ14)/$AK14 -> 669.41999 | AR14: =SUMIFS(ATB_FOM[2022],ATB_FOM[CostCase],"Conservative",ATB_FOM[Technology],$AI14, ATB_FOM[TechDetail],$AJ14) -> 34.5 | AS14: =$AB14 * SUMIFS(INDIRECT("ATB_FOM["&AS$5&"]"),ATB_FOM[CostCase],"Conservative",ATB_FOM[Technology],$AI14, ATB_FOM[TechDetail],$AJ14)/$AR14 -> 6.3122846 | AT14: =$AB14 * SUMIFS(INDIRECT("ATB_FOM["&AT$5&"]"),ATB_FOM[CostCase],"Conservative",ATB_FOM[Technology],$AI14, ATB_FOM[TechDetail],$AJ14)/$AR14 -> 6.1074612 | AU14: =$AB14 * SUMIFS(INDIRECT("ATB_FOM["&AU$5&"]"),ATB_FOM[CostCase],"Conservative",ATB_FOM[Technology],$AI14, ATB_FOM[TechDetail],$AJ14)/$AR14 -> 5.9212581 | AV14: =$AB14 * SUMIFS(INDIRECT("ATB_FOM["&AV$5&"]"),ATB_FOM[CostCase],"Conservative",ATB_FOM[Technology],$AI14, ATB_FOM[TechDetail],$AJ14)/$AR14 -> 5.735055 | AW14: =$AB14 * SUMIFS(INDIRECT("ATB_FOM["&AW$5&"]"),ATB_FOM[CostCase],"Conservative",ATB_FOM[Technology],$AI14, ATB_FOM[TechDetail],$AJ14)/$AR14 -> 5.5488519 | AX14: =$AB14 * SUMIFS(INDIRECT("ATB_FOM["&AX$5&"]"),ATB_FOM[CostCase],"Conservative",ATB_FOM[Technology],$AI14, ATB_FOM[TechDetail],$AJ14)/$AR14 -> 5.3626489 | AY14: =SUMIFS(ATB_VOM[2022],ATB_VOM[CostCase],"Conservative",ATB_VOM[Technology],$AI14, ATB_VOM[TechDetail],$AJ14) -> 2.17 | AZ14: =$AC14 * SUMIFS(INDIRECT("ATB_VOM["&AZ$5&"]"),ATB_VOM[CostCase],"Conservative",ATB_VOM[Technology],$AI14, ATB_VOM[TechDetail],$AJ14)/$AY14 -> 3.7041616 | BA14: =$AC14 * SUMIFS(INDIRECT("ATB_VOM["&BA$5&"]"),ATB_VOM[CostCase],"Conservative",ATB_VOM[Technology],$AI14, ATB_VOM[TechDetail],$AJ14)/$AY14 -> 3.6003066 | BB14: =$AC14 * SUMIFS(INDIRECT("ATB_VOM["&BB$5&"]"),ATB_VOM[CostCase],"Conservative",ATB_VOM[Technology],$AI14, ATB_VOM[TechDetail],$AJ14)/$AY14 -> 3.5137608 | BC14: =$AC14 * SUMIFS(INDIRECT("ATB_VOM["&BC$5&"]"),ATB_VOM[CostCase],"Conservative",ATB_VOM[Technology],$AI14, ATB_VOM[TechDetail],$AJ14)/$AY14 -> 3.427215 | BD14: =$AC14 * SUMIFS(INDIRECT("ATB_VOM["&BD$5&"]"),ATB_VOM[CostCase],"Conservative",ATB_VOM[Technology],$AI14, ATB_VOM[TechDetail],$AJ14)/$AY14 -> 3.3406691 | BE14: =$AC14 * SUMIFS(INDIRECT("ATB_VOM["&BE$5&"]"),ATB_VOM[CostCase],"Conservative",ATB_VOM[Technology],$AI14, ATB_VOM[TechDetail],$AJ14)/$AY14 -> 3.2368141 | BF14: =_xlfn.XLOOKUP($Z14, NewCapCosts2013[Technology],NewCapCosts2013[Heatrate in 2013 (Btu/kWhr)])*0.9/kWh_to_btu_hr -> 2.8796307 | BG14: =_xlfn.XLOOKUP($Z14, NewCapCosts2013[Technology],NewCapCosts2013[Heatrate nth-of-a-kind (Btu/kWr)])*0.9/kWh_to_btu_hr -> 2.7564478 | BH14: =_xlfn.XLOOKUP($Z14, NewCapCosts2013[Technology],NewCapCosts2013[Heatrate nth-of-a-kind (Btu/kWr)])*0.9/kWh_to_btu_hr -> 2.7564478 | BI14: =_xlfn.XLOOKUP($Z14, NewCapCosts2013[Technology],NewCapCosts2013[Heatrate nth-of-a-kind (Btu/kWr)])*0.9/kWh_to_btu_hr -> 2.7564478 | BJ14: R2,R3,R4,R5,R6
A15: ENGAACT20 | B15: Natural Gas - Advanced Combustion Turbine | C15: PJ, GW | D15: R1 | E15: ELCNGAEA | F15: ELC | G15: 2020 | H15: =GW_to_Pja -> 31.536 | I15: =1/BF15 -> 0.38883191 | J15: =1/BG15 -> 0.38883191 | K15: =1/BH15 -> 0.38883191 | L15: =1/BI15 -> 0.38883191 | M15: =L15 -> 0.38883191 | O15: =LifetimeAssumptions!$B$8 -> New Gas & oil turbines | P15: =_xlfn.XLOOKUP($O15, LifetimeAssumptions[technology],LifetimeAssumptions[Lifetime]) -> 30 | Q15: =_xlfn.XLOOKUP($O15, LifetimeAssumptions[technology],LifetimeAssumptions[Peak (con)]) -> 0.95 | R15: =_xlfn.XLOOKUP($O15, LifetimeAssumptions[technology],LifetimeAssumptions[Discrate]) -> 0.15 | S15: =_xlfn.XLOOKUP($O15, LifetimeAssumptions[technology],LifetimeAssumptions[AF]) -> 0.9 | V15: 0 | W15: 0 | X15: 0 | Y15: 0 | Z15: ='2013 Cap Raw Data'!$A$12 -> Adv Combustion Turbine | AB15: =_xlfn.XLOOKUP($Z15, NewCapCosts2013[Technology],NewCapCosts2013[Fixed O&M ($2012/kW)])*_xlfn.XLOOKUP($AB$5,GDP_deflator[Year],GDP_deflator[Multiply By (for $2005)]) -> 6.1614449 | AC15: =_xlfn.XLOOKUP($Z15, NewCapCosts2013[Technology],NewCapCosts2013[Variable O&M ($2012 mills/kWh)])*_xlfn.XLOOKUP($AB$5,GDP_deflator[Year],GDP_deflator[Multiply By (for $2005)])*mills_kWh_to__Million_PJ -> 2.5210773 | AD15: =_xlfn.XLOOKUP($Z15, NewCapCosts2013[Technology],NewCapCosts2013[Fixed O&M ($2012/kW)])*_xlfn.XLOOKUP($AB$5,GDP_deflator[Year],GDP_deflator[Multiply By (for $2005)]) -> 6.1614449 | AE15: =_xlfn.XLOOKUP($Z15, NewCapCosts2013[Technology],NewCapCosts2013[Variable O&M ($2012 mills/kWh)])*_xlfn.XLOOKUP($AB$5,GDP_deflator[Year],GDP_deflator[Multiply By (for $2005)])*mills_kWh_to__Million_PJ -> 2.5210773 | AF15: =_xlfn.XLOOKUP($Z15, NewCapCosts2013[Technology],NewCapCosts2013[Base Overnight Costs in 2012 ($2012/kW)])*_xlfn.XLOOKUP($AB$5,GDP_deflator[Year],GDP_deflator[Multiply By (for $2005)]) -> 561.00656 | AG15: =AF15 -> 561.00656 | AH15: =AG15 -> 561.00656 | AI15: =ATB_CAPEX!$E$490 -> NaturalGas_FE | AJ15: =ATB_CAPEX!$F$488 -> CCAvgCF | AK15: =SUMIFS(ATB_CAPEX[2022],ATB_CAPEX[CostCase],"Conservative",ATB_CAPEX[Technology],$AI15, ATB_CAPEX[TechDetail],$AJ15) -> 1499.253 | AL15: =$AH15 * SUMIFS(INDIRECT("ATB_CAPEX["&AL$5&"]"),ATB_CAPEX[CostCase],"Conservative",ATB_CAPEX[Technology],$AI15, ATB_CAPEX[TechDetail],$AJ15)/$AK15 -> 550.66542 | AM15: =$AH15 * SUMIFS(INDIRECT("ATB_CAPEX["&AM$5&"]"),ATB_CAPEX[CostCase],"Conservative",ATB_CAPEX[Technology],$AI15, ATB_CAPEX[TechDetail],$AJ15)/$AK15 -> 533.4024 | AN15: =$AH15 * SUMIFS(INDIRECT("ATB_CAPEX["&AN$5&"]"),ATB_CAPEX[CostCase],"Conservative",ATB_CAPEX[Technology],$AI15, ATB_CAPEX[TechDetail],$AJ15)/$AK15 -> 516.13938 | AO15: =$AH15 * SUMIFS(INDIRECT("ATB_CAPEX["&AO$5&"]"),ATB_CAPEX[CostCase],"Conservative",ATB_CAPEX[Technology],$AI15, ATB_CAPEX[TechDetail],$AJ15)/$AK15 -> 498.87635 | AP15: =$AH15 * SUMIFS(INDIRECT("ATB_CAPEX["&AP$5&"]"),ATB_CAPEX[CostCase],"Conservative",ATB_CAPEX[Technology],$AI15, ATB_CAPEX[TechDetail],$AJ15)/$AK15 -> 481.61333 | AQ15: =$AH15 * SUMIFS(INDIRECT("ATB_CAPEX["&AQ$5&"]"),ATB_CAPEX[CostCase],"Conservative",ATB_CAPEX[Technology],$AI15, ATB_CAPEX[TechDetail],$AJ15)/$AK15 -> 464.392 | AR15: =SUMIFS(ATB_FOM[2022],ATB_FOM[CostCase],"Conservative",ATB_FOM[Technology],$AI15, ATB_FOM[TechDetail],$AJ15) -> 34.5 | AS15: =$AB15 * SUMIFS(INDIRECT("ATB_FOM["&AS$5&"]"),ATB_FOM[CostCase],"Conservative",ATB_FOM[Technology],$AI15, ATB_FOM[TechDetail],$AJ15)/$AR15 -> 6.0542893 | AT15: =$AB15 * SUMIFS(INDIRECT("ATB_FOM["&AT$5&"]"),ATB_FOM[CostCase],"Conservative",ATB_FOM[Technology],$AI15, ATB_FOM[TechDetail],$AJ15)/$AR15 -> 5.8578374 | AU15: =$AB15 * SUMIFS(INDIRECT("ATB_FOM["&AU$5&"]"),ATB_FOM[CostCase],"Conservative",ATB_FOM[Technology],$AI15, ATB_FOM[TechDetail],$AJ15)/$AR15 -> 5.6792448 | AV15: =$AB15 * SUMIFS(INDIRECT("ATB_FOM["&AV$5&"]"),ATB_FOM[CostCase],"Conservative",ATB_FOM[Technology],$AI15, ATB_FOM[TechDetail],$AJ15)/$AR15 -> 5.5006522 | AW15: =$AB15 * SUMIFS(INDIRECT("ATB_FOM["&AW$5&"]"),ATB_FOM[CostCase],"Conservative",ATB_FOM[Technology],$AI15, ATB_FOM[TechDetail],$AJ15)/$AR15 -> 5.3220596 | AX15: =$AB15 * SUMIFS(INDIRECT("ATB_FOM["&AX$5&"]"),ATB_FOM[CostCase],"Conservative",ATB_FOM[Technology],$AI15, ATB_FOM[TechDetail],$AJ15)/$AR15 -> 5.143467 | AY15: =SUMIFS(ATB_VOM[2022],ATB_VOM[CostCase],"Conservative",ATB_VOM[Technology],$AI15, ATB_VOM[TechDetail],$AJ15) -> 2.17 | AZ15: =$AC15 * SUMIFS(INDIRECT("ATB_VOM["&AZ$5&"]"),ATB_VOM[CostCase],"Conservative",ATB_VOM[Technology],$AI15, ATB_VOM[TechDetail],$AJ15)/$AY15 -> 2.4862237 | BA15: =$AC15 * SUMIFS(INDIRECT("ATB_VOM["&BA$5&"]"),ATB_VOM[CostCase],"Conservative",ATB_VOM[Technology],$AI15, ATB_VOM[TechDetail],$AJ15)/$AY15 -> 2.4165165 | BB15: =$AC15 * SUMIFS(INDIRECT("ATB_VOM["&BB$5&"]"),ATB_VOM[CostCase],"Conservative",ATB_VOM[Technology],$AI15, ATB_VOM[TechDetail],$AJ15)/$AY15 -> 2.3584272 | BC15: =$AC15 * SUMIFS(INDIRECT("ATB_VOM["&BC$5&"]"),ATB_VOM[CostCase],"Conservative",ATB_VOM[Technology],$AI15, ATB_VOM[TechDetail],$AJ15)/$AY15 -> 2.3003378 | BD15: =$AC15 * SUMIFS(INDIRECT("ATB_VOM["&BD$5&"]"),ATB_VOM[CostCase],"Conservative",ATB_VOM[Technology],$AI15, ATB_VOM[TechDetail],$AJ15)/$AY15 -> 2.2422485 | BE15: =$AC15 * SUMIFS(INDIRECT("ATB_VOM["&BE$5&"]"),ATB_VOM[CostCase],"Conservative",ATB_VOM[Technology],$AI15, ATB_VOM[TechDetail],$AJ15)/$AY15 -> 2.1725413 | BF15: =_xlfn.XLOOKUP($Z15, NewCapCosts2013[Technology],NewCapCosts2013[Heatrate in 2013 (Btu/kWhr)])*0.9/kWh_to_btu_hr -> 2.5718054 | BG15: =BF15 -> 2.5718054 | BH15: =BG15 -> 2.5718054 | BI15: =BH15 -> 2.5718054 | BJ15: R2,R3,R4,R5,R6
A16: ENGACT25 | B16: Natural Gas - Combustion Turbine | C16: PJ, GW | D16: R1 | E16: ELCNGCEA | F16: ELC | G16: 2025 | H16: =GW_to_Pja -> 31.536 | I16: =1/BF16 -> 0.41550977 | J16: =1/BG16 -> 0.41550977 | K16: =1/BH16 -> 0.41550977 | L16: =1/BI16 -> 0.41550977 | M16: =L16 -> 0.41550977 | O16: =LifetimeAssumptions!$B$8 -> New Gas & oil turbines | P16: =_xlfn.XLOOKUP($O16, LifetimeAssumptions[technology],LifetimeAssumptions[Lifetime]) -> 30 | Q16: =_xlfn.XLOOKUP($O16, LifetimeAssumptions[technology],LifetimeAssumptions[Peak (con)]) -> 0.95 | R16: =_xlfn.XLOOKUP($O16, LifetimeAssumptions[technology],LifetimeAssumptions[Discrate]) -> 0.15 | S16: =_xlfn.XLOOKUP($O16, LifetimeAssumptions[technology],LifetimeAssumptions[AF]) -> 0.9 | Z16: ='2023 Cap Raw Data'!$A$13 -> Combustion turbine—aeroderivativeh | AA16: ='2023_Regional_Cost_Factor'!$A$12 -> CT – aeroderivative | AB16: =_xlfn.XLOOKUP($Z16, NewCapCosts2023[Technology],NewCapCosts2023[Fixed O&M (2022$/Kw-y)])*_xlfn.XLOOKUP($AC$5,GDP_deflator[Year],GDP_deflator[Multiply By (for $2005)]) -> 12.676864 | AC16: =_xlfn.XLOOKUP($Z16, NewCapCosts2023[Technology],NewCapCosts2023[Variable O&Mf (2022 $/MWh)])*_xlfn.XLOOKUP($AC$5,GDP_deflator[Year],GDP_deflator[Multiply By (for $2005)])*mills_kWh_to__Million_PJ -> 1.0153589 | AD16: =_xlfn.XLOOKUP($Z16, NewCapCosts2023[Technology],NewCapCosts2023[Fixed O&M (2022$/Kw-y)])*_xlfn.XLOOKUP($AC$5,GDP_deflator[Year],GDP_deflator[Multiply By (for $2005)]) -> 12.676864 | AE16: =_xlfn.XLOOKUP($Z16, NewCapCosts2023[Technology],NewCapCosts2023[Variable O&Mf (2022 $/MWh)])*_xlfn.XLOOKUP($AC$5,GDP_deflator[Year],GDP_deflator[Multiply By (for $2005)])*mills_kWh_to__Million_PJ -> 1.0153589 | AF16: =_xlfn.XLOOKUP($AA16,NewCapRegionalCosts[Technology], NewCapRegionalCosts[9 (NYUP)])*_xlfn.XLOOKUP($AC$5,GDP_deflator[Year],GDP_deflator[Multiply By (for $2005)]) -> 1071.4031 | AG16: =AF16 -> 1071.4031 | AH16: =AG16 -> 1071.4031 | AI16: =ATB_CAPEX!$E$490 -> NaturalGas_FE | AJ16: =ATB_CAPEX!$F$488 -> CCAvgCF | AK16: =SUMIFS(ATB_CAPEX[2022],ATB_CAPEX[CostCase],"Conservative",ATB_CAPEX[Technology],$AI16, ATB_CAPEX[TechDetail],$AJ16) -> 1499.253 | AL16: =$AH16 * SUMIFS(INDIRECT("ATB_CAPEX["&AL$5&"]"),ATB_CAPEX[CostCase],"Conservative",ATB_CAPEX[Technology],$AI16, ATB_CAPEX[TechDetail],$AJ16)/$AK16 -> 1051.6538 | AM16: =$AH16 * SUMIFS(INDIRECT("ATB_CAPEX["&AM$5&"]"),ATB_CAPEX[CostCase],"Conservative",ATB_CAPEX[Technology],$AI16, ATB_CAPEX[TechDetail],$AJ16)/$AK16 -> 1018.6851 | AN16: =$AH16 * SUMIFS(INDIRECT("ATB_CAPEX["&AN$5&"]"),ATB_CAPEX[CostCase],"Conservative",ATB_CAPEX[Technology],$AI16, ATB_CAPEX[TechDetail],$AJ16)/$AK16 -> 985.71635 | AO16: =$AH16 * SUMIFS(INDIRECT("ATB_CAPEX["&AO$5&"]"),ATB_CAPEX[CostCase],"Conservative",ATB_CAPEX[Technology],$AI16, ATB_CAPEX[TechDetail],$AJ16)/$AK16 -> 952.74765 | AP16: =$AH16 * SUMIFS(INDIRECT("ATB_CAPEX["&AP$5&"]"),ATB_CAPEX[CostCase],"Conservative",ATB_CAPEX[Technology],$AI16, ATB_CAPEX[TechDetail],$AJ16)/$AK16 -> 919.77895 | AQ16: =$AH16 * SUMIFS(INDIRECT("ATB_CAPEX["&AQ$5&"]"),ATB_CAPEX[CostCase],"Conservative",ATB_CAPEX[Technology],$AI16, ATB_CAPEX[TechDetail],$AJ16)/$AK16 -> 886.88988 | AR16: =SUMIFS(ATB_FOM[2022],ATB_FOM[CostCase],"Conservative",ATB_FOM[Technology],$AI16, ATB_FOM[TechDetail],$AJ16) -> 34.5 | AS16: =$AB16 * SUMIFS(INDIRECT("ATB_FOM["&AS$5&"]"),ATB_FOM[CostCase],"Conservative",ATB_FOM[Technology],$AI16, ATB_FOM[TechDetail],$AJ16)/$AR16 -> 12.456397 | AT16: =$AB16 * SUMIFS(INDIRECT("ATB_FOM["&AT$5&"]"),ATB_FOM[CostCase],"Conservative",ATB_FOM[Technology],$AI16, ATB_FOM[TechDetail],$AJ16)/$AR16 -> 12.052207 | AU16: =$AB16 * SUMIFS(INDIRECT("ATB_FOM["&AU$5&"]"),ATB_FOM[CostCase],"Conservative",ATB_FOM[Technology],$AI16, ATB_FOM[TechDetail],$AJ16)/$AR16 -> 11.684762 | AV16: =$AB16 * SUMIFS(INDIRECT("ATB_FOM["&AV$5&"]"),ATB_FOM[CostCase],"Conservative",ATB_FOM[Technology],$AI16, ATB_FOM[TechDetail],$AJ16)/$AR16 -> 11.317316 | AW16: =$AB16 * SUMIFS(INDIRECT("ATB_FOM["&AW$5&"]"),ATB_FOM[CostCase],"Conservative",ATB_FOM[Technology],$AI16, ATB_FOM[TechDetail],$AJ16)/$AR16 -> 10.949871 | AX16: =$AB16 * SUMIFS(INDIRECT("ATB_FOM["&AX$5&"]"),ATB_FOM[CostCase],"Conservative",ATB_FOM[Technology],$AI16, ATB_FOM[TechDetail],$AJ16)/$AR16 -> 10.582426 | AY16: =SUMIFS(ATB_VOM[2022],ATB_VOM[CostCase],"Conservative",ATB_VOM[Technology],$AI16, ATB_VOM[TechDetail],$AJ16) -> 2.17 | AZ16: =$AC16 * SUMIFS(INDIRECT("ATB_VOM["&AZ$5&"]"),ATB_VOM[CostCase],"Conservative",ATB_VOM[Technology],$AI16, ATB_VOM[TechDetail],$AJ16)/$AY16 -> 1.0013217 | BA16: =$AC16 * SUMIFS(INDIRECT("ATB_VOM["&BA$5&"]"),ATB_VOM[CostCase],"Conservative",ATB_VOM[Technology],$AI16, ATB_VOM[TechDetail],$AJ16)/$AY16 -> 0.97324724 | BB16: =$AC16 * SUMIFS(INDIRECT("ATB_VOM["&BB$5&"]"),ATB_VOM[CostCase],"Conservative",ATB_VOM[Technology],$AI16, ATB_VOM[TechDetail],$AJ16)/$AY16 -> 0.94985187 | BC16: =$AC16 * SUMIFS(INDIRECT("ATB_VOM["&BC$5&"]"),ATB_VOM[CostCase],"Conservative",ATB_VOM[Technology],$AI16, ATB_VOM[TechDetail],$AJ16)/$AY16 -> 0.9264565 | BD16: =$AC16 * SUMIFS(INDIRECT("ATB_VOM["&BD$5&"]"),ATB_VOM[CostCase],"Conservative",ATB_VOM[Technology],$AI16, ATB_VOM[TechDetail],$AJ16)/$AY16 -> 0.90306114 | BE16: =$AC16 * SUMIFS(INDIRECT("ATB_VOM["&BE$5&"]"),ATB_VOM[CostCase],"Conservative",ATB_VOM[Technology],$AI16, ATB_VOM[TechDetail],$AJ16)/$AY16 -> 0.8749867 | BF16: =_xlfn.XLOOKUP($Z16, NewCapCosts2023[Technology],NewCapCosts2023[Heat rateg (Btu/kWh)])*0.9/kWh_to_btu_hr -> 2.4066823 | BG16: =_xlfn.XLOOKUP($Z16, NewCapCosts2023[Technology],NewCapCosts2023[Heat rateg (Btu/kWh)])*0.9/kWh_to_btu_hr -> 2.4066823 | BH16: =_xlfn.XLOOKUP($Z16, NewCapCosts2023[Technology],NewCapCosts2023[Heat rateg (Btu/kWh)])*0.9/kWh_to_btu_hr -> 2.4066823 | BI16: =_xlfn.XLOOKUP($Z16, NewCapCosts2023[Technology],NewCapCosts2023[Heat rateg (Btu/kWh)])*0.9/kWh_to_btu_hr -> 2.4066823 | BJ16: R2,R3,R4,R5,R6
A17: *ENGACT25 | B17: Natural Gas - Combustion Turbine | C17: PJ, GW | D17: R2,R3,R4,R5,R6 | E17: ELCNGCEA | F17: ELC | G17: 2025 | H17: =GW_to_Pja -> 31.536 | I17: =1/BF17 -> 0.41550977 | J17: =1/BG17 -> 0.41550977 | K17: =1/BH17 -> 0.41550977 | L17: =1/BI17 -> 0.41550977 | M17: =L17 -> 0.41550977 | O17: =LifetimeAssumptions!$B$8 -> New Gas & oil turbines | P17: =_xlfn.XLOOKUP($O17, LifetimeAssumptions[technology],LifetimeAssumptions[Lifetime]) -> 30 | Q17: =_xlfn.XLOOKUP($O17, LifetimeAssumptions[technology],LifetimeAssumptions[Peak (con)]) -> 0.95 | R17: =_xlfn.XLOOKUP($O17, LifetimeAssumptions[technology],LifetimeAssumptions[Discrate]) -> 0.15 | S17: =_xlfn.XLOOKUP($O17, LifetimeAssumptions[technology],LifetimeAssumptions[AF]) -> 0.9 | Z17: ='2023 Cap Raw Data'!$A$13 -> Combustion turbine—aeroderivativeh | AA17: ='2023_Regional_Cost_Factor'!$A$12 -> CT – aeroderivative | AB17: =_xlfn.XLOOKUP($Z17, NewCapCosts2023[Technology],NewCapCosts2023[Fixed O&M (2022$/Kw-y)])*_xlfn.XLOOKUP($AC$5,GDP_deflator[Year],GDP_deflator[Multiply By (for $2005)]) -> 12.676864 | AC17: =_xlfn.XLOOKUP($Z17, NewCapCosts2023[Technology],NewCapCosts2023[Variable O&Mf (2022 $/MWh)])*_xlfn.XLOOKUP($AC$5,GDP_deflator[Year],GDP_deflator[Multiply By (for $2005)])*mills_kWh_to__Million_PJ -> 1.0153589 | AD17: =_xlfn.XLOOKUP($Z17, NewCapCosts2023[Technology],NewCapCosts2023[Fixed O&M (2022$/Kw-y)])*_xlfn.XLOOKUP($AC$5,GDP_deflator[Year],GDP_deflator[Multiply By (for $2005)]) -> 12.676864 | AE17: =_xlfn.XLOOKUP($Z17, NewCapCosts2023[Technology],NewCapCosts2023[Variable O&Mf (2022 $/MWh)])*_xlfn.XLOOKUP($AC$5,GDP_deflator[Year],GDP_deflator[Multiply By (for $2005)])*mills_kWh_to__Million_PJ -> 1.0153589 | AF17: =_xlfn.XLOOKUP($AA17,NewCapRegionalCosts[Technology], NewCapRegionalCosts[8 (NYCW)])*_xlfn.XLOOKUP($AC$5,GDP_deflator[Year],GDP_deflator[Multiply By (for $2005)]) -> 1421.2493 | AG17: =AF17 -> 1421.2493 | AH17: =AG17 -> 1421.2493 | AI17: =ATB_CAPEX!$E$490 -> NaturalGas_FE | AJ17: =ATB_CAPEX!$F$488 -> CCAvgCF | AK17: =SUMIFS(ATB_CAPEX[2022],ATB_CAPEX[CostCase],"Conservative",ATB_CAPEX[Technology],$AI17, ATB_CAPEX[TechDetail],$AJ17) -> 1499.253 | AL17: =$AH17 * SUMIFS(INDIRECT("ATB_CAPEX["&AL$5&"]"),ATB_CAPEX[CostCase],"Conservative",ATB_CAPEX[Technology],$AI17, ATB_CAPEX[TechDetail],$AJ17)/$AK17 -> 1395.0511 | AM17: =$AH17 * SUMIFS(INDIRECT("ATB_CAPEX["&AM$5&"]"),ATB_CAPEX[CostCase],"Conservative",ATB_CAPEX[Technology],$AI17, ATB_CAPEX[TechDetail],$AJ17)/$AK17 -> 1351.3171 | AN17: =$AH17 * SUMIFS(INDIRECT("ATB_CAPEX["&AN$5&"]"),ATB_CAPEX[CostCase],"Conservative",ATB_CAPEX[Technology],$AI17, ATB_CAPEX[TechDetail],$AJ17)/$AK17 -> 1307.5831 | AO17: =$AH17 * SUMIFS(INDIRECT("ATB_CAPEX["&AO$5&"]"),ATB_CAPEX[CostCase],"Conservative",ATB_CAPEX[Technology],$AI17, ATB_CAPEX[TechDetail],$AJ17)/$AK17 -> 1263.8491 | AP17: =$AH17 * SUMIFS(INDIRECT("ATB_CAPEX["&AP$5&"]"),ATB_CAPEX[CostCase],"Conservative",ATB_CAPEX[Technology],$AI17, ATB_CAPEX[TechDetail],$AJ17)/$AK17 -> 1220.1151 | AQ17: =$AH17 * SUMIFS(INDIRECT("ATB_CAPEX["&AQ$5&"]"),ATB_CAPEX[CostCase],"Conservative",ATB_CAPEX[Technology],$AI17, ATB_CAPEX[TechDetail],$AJ17)/$AK17 -> 1176.4868 | AR17: =SUMIFS(ATB_FOM[2022],ATB_FOM[CostCase],"Conservative",ATB_FOM[Technology],$AI17, ATB_FOM[TechDetail],$AJ17) -> 34.5 | AS17: =$AB17 * SUMIFS(INDIRECT("ATB_FOM["&AS$5&"]"),ATB_FOM[CostCase],"Conservative",ATB_FOM[Technology],$AI17, ATB_FOM[TechDetail],$AJ17)/$AR17 -> 12.456397 | AT17: =$AB17 * SUMIFS(INDIRECT("ATB_FOM["&AT$5&"]"),ATB_FOM[CostCase],"Conservative",ATB_FOM[Technology],$AI17, ATB_FOM[TechDetail],$AJ17)/$AR17 -> 12.052207 | AU17: =$AB17 * SUMIFS(INDIRECT("ATB_FOM["&AU$5&"]"),ATB_FOM[CostCase],"Conservative",ATB_FOM[Technology],$AI17, ATB_FOM[TechDetail],$AJ17)/$AR17 -> 11.684762 | AV17: =$AB17 * SUMIFS(INDIRECT("ATB_FOM["&AV$5&"]"),ATB_FOM[CostCase],"Conservative",ATB_FOM[Technology],$AI17, ATB_FOM[TechDetail],$AJ17)/$AR17 -> 11.317316 | AW17: =$AB17 * SUMIFS(INDIRECT("ATB_FOM["&AW$5&"]"),ATB_FOM[CostCase],"Conservative",ATB_FOM[Technology],$AI17, ATB_FOM[TechDetail],$AJ17)/$AR17 -> 10.949871 | AX17: =$AB17 * SUMIFS(INDIRECT("ATB_FOM["&AX$5&"]"),ATB_FOM[CostCase],"Conservative",ATB_FOM[Technology],$AI17, ATB_FOM[TechDetail],$AJ17)/$AR17 -> 10.582426 | AY17: =SUMIFS(ATB_VOM[2022],ATB_VOM[CostCase],"Conservative",ATB_VOM[Technology],$AI17, ATB_VOM[TechDetail],$AJ17) -> 2.17 | AZ17: =$AC17 * SUMIFS(INDIRECT("ATB_VOM["&AZ$5&"]"),ATB_VOM[CostCase],"Conservative",ATB_VOM[Technology],$AI17, ATB_VOM[TechDetail],$AJ17)/$AY17 -> 1.0013217 | BA17: =$AC17 * SUMIFS(INDIRECT("ATB_VOM["&BA$5&"]"),ATB_VOM[CostCase],"Conservative",ATB_VOM[Technology],$AI17, ATB_VOM[TechDetail],$AJ17)/$AY17 -> 0.97324724 | BB17: =$AC17 * SUMIFS(INDIRECT("ATB_VOM["&BB$5&"]"),ATB_VOM[CostCase],"Conservative",ATB_VOM[Technology],$AI17, ATB_VOM[TechDetail],$AJ17)/$AY17 -> 0.94985187 | BC17: =$AC17 * SUMIFS(INDIRECT("ATB_VOM["&BC$5&"]"),ATB_VOM[CostCase],"Conservative",ATB_VOM[Technology],$AI17, ATB_VOM[TechDetail],$AJ17)/$AY17 -> 0.9264565 | BD17: =$AC17 * SUMIFS(INDIRECT("ATB_VOM["&BD$5&"]"),ATB_VOM[CostCase],"Conservative",ATB_VOM[Technology],$AI17, ATB_VOM[TechDetail],$AJ17)/$AY17 -> 0.90306114 | BE17: =$AC17 * SUMIFS(INDIRECT("ATB_VOM["&BE$5&"]"),ATB_VOM[CostCase],"Conservative",ATB_VOM[Technology],$AI17, ATB_VOM[TechDetail],$AJ17)/$AY17 -> 0.8749867 | BF17: =_xlfn.XLOOKUP($Z17, NewCapCosts2023[Technology],NewCapCosts2023[Heat rateg (Btu/kWh)])*0.9/kWh_to_btu_hr -> 2.4066823 | BG17: =_xlfn.XLOOKUP($Z17, NewCapCosts2023[Technology],NewCapCosts2023[Heat rateg (Btu/kWh)])*0.9/kWh_to_btu_hr -> 2.4066823 | BH17: =_xlfn.XLOOKUP($Z17, NewCapCosts2023[Technology],NewCapCosts2023[Heat rateg (Btu/kWh)])*0.9/kWh_to_btu_hr -> 2.4066823 | BI17: =_xlfn.XLOOKUP($Z17, NewCapCosts2023[Technology],NewCapCosts2023[Heat rateg (Btu/kWh)])*0.9/kWh_to_btu_hr -> 2.4066823 | BJ17: R2,R3,R4,R5,R6
A18: EURNALWR28 | B18: Nuclear LWRs online in 2028. Assuming 6-year delay | C18: PJ, GW | D18: R1 | E18: URNA | G18: 2035 | H18: =GW_to_Pja -> 31.536 | I18: =1/N20 -> 1.5335877 | M18: =I18 -> 1.5335877 | O18: =LifetimeAssumptions!$B$13 -> Nuclear | P18: =_xlfn.XLOOKUP($O18, LifetimeAssumptions[technology],LifetimeAssumptions[Lifetime]) -> 30 | Q18: =_xlfn.XLOOKUP($O18, LifetimeAssumptions[technology],LifetimeAssumptions[Peak (con)]) -> 0.95 | R18: =_xlfn.XLOOKUP($O18, LifetimeAssumptions[technology],LifetimeAssumptions[Discrate]) -> 0.25 | S18: =_xlfn.XLOOKUP($O18, LifetimeAssumptions[technology],LifetimeAssumptions[AF]) -> 0.9 | Z18: ='2023 Cap Raw Data'!$A$16 -> Nuclear—light water reactor | AA18: ='2023_Regional_Cost_Factor'!$A$15 -> Nuclear– light water reactor | AB18: =_xlfn.XLOOKUP($Z18, NewCapCosts2023[Technology],NewCapCosts2023[Fixed O&M (2022$/Kw-y)])*_xlfn.XLOOKUP($AC$5,GDP_deflator[Year],GDP_deflator[Multiply By (for $2005)]) -> 94.602068 | AC18: =_xlfn.XLOOKUP($Z18, NewCapCosts2023[Technology],NewCapCosts2023[Variable O&Mf (2022 $/MWh)])*_xlfn.XLOOKUP($AC$5,GDP_deflator[Year],GDP_deflator[Multiply By (for $2005)])*mills_kWh_to__Million_PJ -> 0.51200012 | AD18: =_xlfn.XLOOKUP($Z18, NewCapCosts2023[Technology],NewCapCosts2023[Fixed O&M (2022$/Kw-y)])*_xlfn.XLOOKUP($AC$5,GDP_deflator[Year],GDP_deflator[Multiply By (for $2005)]) -> 94.602068 | AE18: =_xlfn.XLOOKUP($Z18, NewCapCosts2023[Technology],NewCapCosts2023[Variable O&Mf (2022 $/MWh)])*_xlfn.XLOOKUP($AC$5,GDP_deflator[Year],GDP_deflator[Multiply By (for $2005)])*mills_kWh_to__Million_PJ -> 0.51200012 | AF18: =_xlfn.XLOOKUP($AA18,NewCapRegionalCosts[Technology], NewCapRegionalCosts[9 (NYUP)])*_xlfn.XLOOKUP($AC$5,GDP_deflator[Year],GDP_deflator[Multiply By (for $2005)]) -> 5679.3293 | AG18: =AF18 -> 5679.3293 | AH18: =AG18 -> 5679.3293 | AI18: =ATB_FOM!$E$314 -> Nuclear | AJ18: =ATB_FOM!$F$314 -> Nuclear | AK18: =SUMIFS(ATB_CAPEX[2030],ATB_CAPEX[CostCase],"Conservative",ATB_CAPEX[Technology],$AI18, ATB_CAPEX[TechDetail],$AJ18) -> 11836.118 | AN18: =$AH18 * SUMIFS(INDIRECT("ATB_CAPEX["&AN$5&"]"),ATB_CAPEX[CostCase],"Conservative",ATB_CAPEX[Technology],$AI18, ATB_CAPEX[TechDetail],$AJ18)/$AK18 -> 5679.3293 | AO18: =$AH18 * SUMIFS(INDIRECT("ATB_CAPEX["&AO$5&"]"),ATB_CAPEX[CostCase],"Conservative",ATB_CAPEX[Technology],$AI18, ATB_CAPEX[TechDetail],$AJ18)/$AK18 -> 5498.459 | AP18: =$AH18 * SUMIFS(INDIRECT("ATB_CAPEX["&AP$5&"]"),ATB_CAPEX[CostCase],"Conservative",ATB_CAPEX[Technology],$AI18, ATB_CAPEX[TechDetail],$AJ18)/$AK18 -> 4955.8479 | AQ18: =$AH18 * SUMIFS(INDIRECT("ATB_CAPEX["&AQ$5&"]"),ATB_CAPEX[CostCase],"Conservative",ATB_CAPEX[Technology],$AI18, ATB_CAPEX[TechDetail],$AJ18)/$AK18 -> 4413.2368 | AR18: =SUMIFS(ATB_FOM[2030],ATB_FOM[CostCase],"Conservative",ATB_FOM[Technology],$AI18, ATB_FOM[TechDetail],$AJ18) -> 204 | AU18: =$AB18 * SUMIFS(INDIRECT("ATB_FOM["&AU$5&"]"),ATB_FOM[CostCase],"Conservative",ATB_FOM[Technology],$AI18, ATB_FOM[TechDetail],$AJ18)/$AR18 -> 94.602068 | AV18: =$AB18 * SUMIFS(INDIRECT("ATB_FOM["&AV$5&"]"),ATB_FOM[CostCase],"Conservative",ATB_FOM[Technology],$AI18, ATB_FOM[TechDetail],$AJ18)/$AR18 -> 94.602068 | AW18: =$AB18 * SUMIFS(INDIRECT("ATB_FOM["&AW$5&"]"),ATB_FOM[CostCase],"Conservative",ATB_FOM[Technology],$AI18, ATB_FOM[TechDetail],$AJ18)/$AR18 -> 94.602068 | AX18: =$AB18 * SUMIFS(INDIRECT("ATB_FOM["&AX$5&"]"),ATB_FOM[CostCase],"Conservative",ATB_FOM[Technology],$AI18, ATB_FOM[TechDetail],$AJ18)/$AR18 -> 94.602068 | AY18: =SUMIFS(ATB_VOM[2030],ATB_VOM[CostCase],"Conservative",ATB_VOM[Technology],$AI18, ATB_VOM[TechDetail],$AJ18) -> 3.4 | AZ18: =$AC18 * SUMIFS(INDIRECT("ATB_VOM["&AZ$5&"]"),ATB_VOM[CostCase],"Conservative",ATB_VOM[Technology],$AI18, ATB_VOM[TechDetail],$AJ18)/$AY18 -> 0 | BA18: =$AC18 * SUMIFS(INDIRECT("ATB_VOM["&BA$5&"]"),ATB_VOM[CostCase],"Conservative",ATB_VOM[Technology],$AI18, ATB_VOM[TechDetail],$AJ18)/$AY18 -> 0.51200012 | BB18: =$AC18 * SUMIFS(INDIRECT("ATB_VOM["&BB$5&"]"),ATB_VOM[CostCase],"Conservative",ATB_VOM[Technology],$AI18, ATB_VOM[TechDetail],$AJ18)/$AY18 -> 0.51200012 | BC18: =$AC18 * SUMIFS(INDIRECT("ATB_VOM["&BC$5&"]"),ATB_VOM[CostCase],"Conservative",ATB_VOM[Technology],$AI18, ATB_VOM[TechDetail],$AJ18)/$AY18 -> 0.51200012 | BD18: =$AC18 * SUMIFS(INDIRECT("ATB_VOM["&BD$5&"]"),ATB_VOM[CostCase],"Conservative",ATB_VOM[Technology],$AI18, ATB_VOM[TechDetail],$AJ18)/$AY18 -> 0.51200012 | BE18: =$AC18 * SUMIFS(INDIRECT("ATB_VOM["&BE$5&"]"),ATB_VOM[CostCase],"Conservative",ATB_VOM[Technology],$AI18, ATB_VOM[TechDetail],$AJ18)/$AY18 -> 0.51200012 | BJ18: R1
F19: ELC
F20: USPTA | N20: =(1/(($J$5*24)/(277.78)))/0.355 -> 0.65206573
A21: EURNASMR | B21: Advanced nuclear technology: Small Modular Reactors | C21: PJ, GW | D21: R1 | E21: URNA | G21: 2035 | H21: =GW_to_Pja -> 31.536 | I21: =1/N23 -> 1.5335877 | M21: =I21 -> 1.5335877 | O21: =LifetimeAssumptions!$B$13 -> Nuclear | P21: =_xlfn.XLOOKUP($O21, LifetimeAssumptions[technology],LifetimeAssumptions[Lifetime]) -> 30 | Q21: =_xlfn.XLOOKUP($O21, LifetimeAssumptions[technology],LifetimeAssumptions[Peak (con)]) -> 0.95 | R21: =_xlfn.XLOOKUP($O21, LifetimeAssumptions[technology],LifetimeAssumptions[Discrate]) -> 0.25 | S21: =_xlfn.XLOOKUP($O21, LifetimeAssumptions[technology],LifetimeAssumptions[AF]) -> 0.9 | Z21: ='2023 Cap Raw Data'!$A$17 -> Nuclear—small modular reactor | AA21: ='2023_Regional_Cost_Factor'!$A$16 -> Nuclear– small modular reactor | AB21: =_xlfn.XLOOKUP($Z21, NewCapCosts2023[Technology],NewCapCosts2023[Fixed O&M (2022$/Kw-y)])*_xlfn.XLOOKUP($AC$5,GDP_deflator[Year],GDP_deflator[Multiply By (for $2005)]) -> 73.883568 | AC21: =_xlfn.XLOOKUP($Z21, NewCapCosts2023[Technology],NewCapCosts2023[Variable O&Mf (2022 $/MWh)])*_xlfn.XLOOKUP($AC$5,GDP_deflator[Year],GDP_deflator[Multiply By (for $2005)])*mills_kWh_to__Million_PJ -> 0.64810145 | AD21: =_xlfn.XLOOKUP($Z21, NewCapCosts2023[Technology],NewCapCosts2023[Fixed O&M (2022$/Kw-y)])*_xlfn.XLOOKUP($AC$5,GDP_deflator[Year],GDP_deflator[Multiply By (for $2005)]) -> 73.883568 | AE21: =_xlfn.XLOOKUP($Z21, NewCapCosts2023[Technology],NewCapCosts2023[Variable O&Mf (2022 $/MWh)])*_xlfn.XLOOKUP($AC$5,GDP_deflator[Year],GDP_deflator[Multiply By (for $2005)])*mills_kWh_to__Million_PJ -> 0.64810145 | AF21: =_xlfn.XLOOKUP($AA21,NewCapRegionalCosts[Technology], NewCapRegionalCosts[9 (NYUP)])*_xlfn.XLOOKUP($AC$5,GDP_deflator[Year],GDP_deflator[Multiply By (for $2005)]) -> 6145.5798 | AG21: =AF21 -> 6145.5798 | AH21: =AG21 -> 6145.5798 | AI21: =ATB_FOM!$E$315 -> Nuclear | AJ21: =ATB_FOM!$F$315 -> NuclearSMR | AK21: =SUMIFS(ATB_CAPEX[2030],ATB_CAPEX[CostCase],"Conservative",ATB_CAPEX[Technology],$AI21, ATB_CAPEX[TechDetail],$AJ21) -> 12681.127 | AN21: =$AH21 * SUMIFS(INDIRECT("ATB_CAPEX["&AN$5&"]"),ATB_CAPEX[CostCase],"Conservative",ATB_CAPEX[Technology],$AI21, ATB_CAPEX[TechDetail],$AJ21)/$AK21 -> 5841.3431 | AO21: =$AH21 * SUMIFS(INDIRECT("ATB_CAPEX["&AO$5&"]"),ATB_CAPEX[CostCase],"Conservative",ATB_CAPEX[Technology],$AI21, ATB_CAPEX[TechDetail],$AJ21)/$AK21 -> 4928.6333 | AP21: =$AH21 * SUMIFS(INDIRECT("ATB_CAPEX["&AP$5&"]"),ATB_CAPEX[CostCase],"Conservative",ATB_CAPEX[Technology],$AI21, ATB_CAPEX[TechDetail],$AJ21)/$AK21 -> 4320.16 | AQ21: =$AH21 * SUMIFS(INDIRECT("ATB_CAPEX["&AQ$5&"]"),ATB_CAPEX[CostCase],"Conservative",ATB_CAPEX[Technology],$AI21, ATB_CAPEX[TechDetail],$AJ21)/$AK21 -> 3863.8051 | AR21: =SUMIFS(ATB_FOM[2030],ATB_FOM[CostCase],"Conservative",ATB_FOM[Technology],$AI21, ATB_FOM[TechDetail],$AJ21) -> 216 | AU21: =$AB21 * SUMIFS(INDIRECT("ATB_FOM["&AU$5&"]"),ATB_FOM[CostCase],"Conservative",ATB_FOM[Technology],$AI21, ATB_FOM[TechDetail],$AJ21)/$AR21 -> 73.883568 | AV21: =$AB21 * SUMIFS(INDIRECT("ATB_FOM["&AV$5&"]"),ATB_FOM[CostCase],"Conservative",ATB_FOM[Technology],$AI21, ATB_FOM[TechDetail],$AJ21)/$AR21 -> 73.883568 | AW21: =$AB21 * SUMIFS(INDIRECT("ATB_FOM["&AW$5&"]"),ATB_FOM[CostCase],"Conservative",ATB_FOM[Technology],$AI21, ATB_FOM[TechDetail],$AJ21)/$AR21 -> 73.883568 | AX21: =$AB21 * SUMIFS(INDIRECT("ATB_FOM["&AX$5&"]"),ATB_FOM[CostCase],"Conservative",ATB_FOM[Technology],$AI21, ATB_FOM[TechDetail],$AJ21)/$AR21 -> 73.883568 | AY21: =SUMIFS(ATB_VOM[2030],ATB_VOM[CostCase],"Conservative",ATB_VOM[Technology],$AI21, ATB_VOM[TechDetail],$AJ21) -> 2.8 | AZ21: =$AC21 * SUMIFS(INDIRECT("ATB_VOM["&AZ$5&"]"),ATB_VOM[CostCase],"Conservative",ATB_VOM[Technology],$AI21, ATB_VOM[TechDetail],$AJ21)/$AY21 -> 0 | BA21: =$AC21 * SUMIFS(INDIRECT("ATB_VOM["&BA$5&"]"),ATB_VOM[CostCase],"Conservative",ATB_VOM[Technology],$AI21, ATB_VOM[TechDetail],$AJ21)/$AY21 -> 0.64810145 | BB21: =$AC21 * SUMIFS(INDIRECT("ATB_VOM["&BB$5&"]"),ATB_VOM[CostCase],"Conservative",ATB_VOM[Technology],$AI21, ATB_VOM[TechDetail],$AJ21)/$AY21 -> 0.64810145 | BC21: =$AC21 * SUMIFS(INDIRECT("ATB_VOM["&BC$5&"]"),ATB_VOM[CostCase],"Conservative",ATB_VOM[Technology],$AI21, ATB_VOM[TechDetail],$AJ21)/$AY21 -> 0.64810145 | BD21: =$AC21 * SUMIFS(INDIRECT("ATB_VOM["&BD$5&"]"),ATB_VOM[CostCase],"Conservative",ATB_VOM[Technology],$AI21, ATB_VOM[TechDetail],$AJ21)/$AY21 -> 0.64810145 | BE21: =$AC21 * SUMIFS(INDIRECT("ATB_VOM["&BE$5&"]"),ATB_VOM[CostCase],"Conservative",ATB_VOM[Technology],$AI21, ATB_VOM[TechDetail],$AJ21)/$AY21 -> 0.64810145 | BJ21: R1
F22: ELC
F23: USPTA | N23: =(1/(($J$5*24)/(277.78)))/0.355 -> 0.65206573
E27: ~FI_T
A28: TechName | B28: *TechDesc | C28: *Units | D28: Region | E28: CommIN | F28: CommOUT | G28: NCAP_START | H28: PRC_CAPACT | I28: EFF | J28: STG_EFF | K28: Peak | L28: *lookup | M28: NCAP_TLIFE | N28: NCAP_DRATE | O28: *lookup | P28: NCAP_FOM~2010 | Q28: NCAP_FOM~2020 | R28: ACT_COST | S28: NCAP_COST~2010 | T28: NCAP_COST~2020 | U28: *LOOKUP: ATB Tech | V28: *LOOKUP: ATB TechDetail | W28: *ATB CAPEX Base | X28: NCAP_COST~2025 | Y28: NCAP_COST~2030 | Z28: NCAP_COST~2035 | AA28: NCAP_COST~2040 | AB28: NCAP_COST~2045 | AC28: NCAP_COST~2050 | AD28: *ATB FOM Base | AE28: NCAP_FOM~2025 | AF28: NCAP_FOM~2030 | AG28: NCAP_FOM~2035 | AH28: NCAP_FOM~2040 | AI28: NCAP_FOM~2045 | AJ28: NCAP_FOM~2050 | AK28: NCAP_AF | AL28: NCAP_AFC | AM28: NCAP_AF~WP | AN28: NCAP_AF~SP | AO28: NCAP_AF~IP | AP28: NCAP_AF~WN | AQ28: NCAP_AF~SN | AR28: NCAP_AF~IN | AS28: Output_ELC | AT28: Input~2010 | AU28: Input~2015 | AV28: Input~2020 | AW28: Input~2055
A29: * | B29: new_battery_storage | L29: Lookup from LifetimeAssumptions | O29: Lookup from 2023 Cap Raw Data | P29: 2022 | Q29: 2022 | X29: 2025 | Y29: 2030 | Z29: 2035 | AA29: 2040 | AB29: 2045 | AC29: 2050 | AE29: 2025 | AF29: 2030 | AG29: 2035 | AH29: 2040 | AI29: 2045 | AJ29: 2050
A30: SSTOBATUTI-IN | B30: Electricity Battery Storage 4-hour Utility Scale | C30: PJ,GW | D30: R2,R3,R4,R5,R6 | E30: ELC | F30: BATELC | G30: 2023 | H30: =GW_to_Pja -> 31.536 | J30: 1 | L30: =LifetimeAssumptions!$B$12 -> Battery Storage | M30: =_xlfn.XLOOKUP($L30, LifetimeAssumptions[technology],LifetimeAssumptions[Lifetime]) -> 15 | N30: =_xlfn.XLOOKUP($L30, LifetimeAssumptions[technology],LifetimeAssumptions[Discrate]) -> 0.1 | O30: ='2023 Cap Raw Data'!$A$20 -> Battery storage | U30: =ATB_CAPEX!$E$326 -> Utility-Scale Battery Storage | V30: =ATB_CAPEX!$F$326 -> 4Hr Battery Storage | W30: =SUMIFS(ATB_CAPEX[2022],ATB_CAPEX[CostCase],"Conservative",ATB_CAPEX[Technology],$U30, ATB_CAPEX[TechDetail],$V30) -> 2100.7782 | AD30: =SUMIFS(ATB_FOM[2022],ATB_FOM[CostCase],"Conservative",ATB_FOM[Technology],$U30, ATB_FOM[TechDetail],$V30) -> 48.168 | AL30: =4/24 -> 0.16666667 | AS30: 1 | AT30: 1.1 | AV30: 1.1 | AW30: 1.1
A31: ESTOBATUTI-OUT | B31: Electricity Battery Storage 4-hour Utility Scale | C31: PJ,GW | D31: R2,R3,R4,R5,R6 | E31: BATELC | F31: ELC | G31: 2023 | H31: =GW_to_Pja -> 31.536 | I31: 0.85 | K31: 0.5 | L31: =LifetimeAssumptions!$B$12 -> Battery Storage | M31: =_xlfn.XLOOKUP($L31, LifetimeAssumptions[technology],LifetimeAssumptions[Lifetime]) -> 15 | N31: =_xlfn.XLOOKUP($L31, LifetimeAssumptions[technology],LifetimeAssumptions[Discrate]) -> 0.1 | O31: ='2023 Cap Raw Data'!$A$20 -> Battery storage | P31: =_xlfn.XLOOKUP($O31,NewCapCosts2023[Technology],NewCapCosts2023[Fixed O&M (2022$/Kw-y)])*_xlfn.XLOOKUP(lookup_deflator_2023,GDP_deflator[Year],GDP_deflator[Multiply By (for $2005)]) -> 31.622415 | Q31: =_xlfn.XLOOKUP($O31,NewCapCosts2023[Technology],NewCapCosts2023[Fixed O&M (2022$/Kw-y)])*_xlfn.XLOOKUP(lookup_deflator_2023,GDP_deflator[Year],GDP_deflator[Multiply By (for $2005)]) -> 31.622415 | S31: =_xlfn.XLOOKUP($O31,NewCapRegionalCosts[Technology],NewCapRegionalCosts[8 (NYCW)])*_xlfn.XLOOKUP(lookup_deflator_2023,GDP_deflator[Year],GDP_deflator[Multiply By (for $2005)]) -> 901.07894 | T31: =S31 -> 901.07894 | X31: =$T31*SUMIFS(INDIRECT("ATB_CAPEX["&X$29&"]"),ATB_CAPEX[CostCase],"Conservative",ATB_CAPEX[Technology],$U30, ATB_CAPEX[TechDetail],$V30)/$W30 -> 926.45615 | Y31: =$T31*SUMIFS(INDIRECT("ATB_CAPEX["&Y$29&"]"),ATB_CAPEX[CostCase],"Conservative",ATB_CAPEX[Technology],$U30, ATB_CAPEX[TechDetail],$V30)/$W30 -> 761.30756 | Z31: =$T31*SUMIFS(INDIRECT("ATB_CAPEX["&Z$29&"]"),ATB_CAPEX[CostCase],"Conservative",ATB_CAPEX[Technology],$U30, ATB_CAPEX[TechDetail],$V30)/$W30 -> 736.76707 | AA31: =$T31*SUMIFS(INDIRECT("ATB_CAPEX["&AA$29&"]"),ATB_CAPEX[CostCase],"Conservative",ATB_CAPEX[Technology],$U30, ATB_CAPEX[TechDetail],$V30)/$W30 -> 712.22657 | AB31: =$T31*SUMIFS(INDIRECT("ATB_CAPEX["&AB$29&"]"),ATB_CAPEX[CostCase],"Conservative",ATB_CAPEX[Technology],$U30, ATB_CAPEX[TechDetail],$V30)/$W30 -> 687.68607 | AC31: =$T31*SUMIFS(INDIRECT("ATB_CAPEX["&AC$29&"]"),ATB_CAPEX[CostCase],"Conservative",ATB_CAPEX[Technology],$U30, ATB_CAPEX[TechDetail],$V30)/$W30 -> 663.14557 | AE31: =$P31*SUMIFS(INDIRECT("ATB_FOM["&AE$29&"]"),ATB_FOM[CostCase],"Conservative",ATB_FOM[Technology],$U30, ATB_FOM[TechDetail],$V30)/$AD30 -> 32.559225 | AF31: =$P31*SUMIFS(INDIRECT("ATB_FOM["&AF$29&"]"),ATB_FOM[CostCase],"Conservative",ATB_FOM[Technology],$U30, ATB_FOM[TechDetail],$V30)/$AD30 -> 26.462702 | AG31: =$P31*SUMIFS(INDIRECT("ATB_FOM["&AG$29&"]"),ATB_FOM[CostCase],"Conservative",ATB_FOM[Technology],$U30, ATB_FOM[TechDetail],$V30)/$AD30 -> 25.55678 | AH31: =$P31*SUMIFS(INDIRECT("ATB_FOM["&AH$29&"]"),ATB_FOM[CostCase],"Conservative",ATB_FOM[Technology],$U30, ATB_FOM[TechDetail],$V30)/$AD30 -> 24.650858 | AI31: =$P31*SUMIFS(INDIRECT("ATB_FOM["&AI$29&"]"),ATB_FOM[CostCase],"Conservative",ATB_FOM[Technology],$U30, ATB_FOM[TechDetail],$V30)/$AD30 -> 23.744936 | AJ31: =$P31*SUMIFS(INDIRECT("ATB_FOM["&AJ$29&"]"),ATB_FOM[CostCase],"Conservative",ATB_FOM[Technology],$U30, ATB_FOM[TechDetail],$V30)/$AD30 -> 22.839015 | AK31: =AL30 -> 0.16666667 | AM31: =1/2*1/(1+20%) -> 0.41666667 | AN31: =1/2*1/(1+20%) -> 0.41666667 | AO31: =1/2*1/(1+20%) -> 0.41666667 | AS31: 1 | AT31: 1.1 | AV31: 1.1 | AW31: 1.1
A32: SSTOBATUTI-IN | B32: Electricity Battery Storage 4-hour Utility Scale | C32: PJ,GW | D32: R1 | E32: ELC | F32: BATELC | G32: 2023 | H32: =GW_to_Pja -> 31.536 | J32: 1 | L32: =LifetimeAssumptions!$B$12 -> Battery Storage | M32: =_xlfn.XLOOKUP($L32, LifetimeAssumptions[technology],LifetimeAssumptions[Lifetime]) -> 15 | N32: =_xlfn.XLOOKUP($L32, LifetimeAssumptions[technology],LifetimeAssumptions[Discrate]) -> 0.1 | O32: ='2023 Cap Raw Data'!$A$20 -> Battery storage | U32: =ATB_CAPEX!$E$326 -> Utility-Scale Battery Storage | V32: =ATB_CAPEX!$F$326 -> 4Hr Battery Storage | W32: =SUMIFS(ATB_CAPEX[2022],ATB_CAPEX[CostCase],"Conservative",ATB_CAPEX[Technology],$U32, ATB_CAPEX[TechDetail],$V32) -> 2100.7782 | AD32: =SUMIFS(ATB_FOM[2022],ATB_FOM[CostCase],"Conservative",ATB_FOM[Technology],$U32, ATB_FOM[TechDetail],$V32) -> 48.168 | AL32: =4/24 -> 0.16666667 | AS32: 1 | AT32: 1.1 | AV32: 1.1 | AW32: 1.1
A33: ESTOBATUTI-OUT | B33: Electricity Battery Storage 4-hour Utility Scale | C33: PJ,GW | D33: R1 | E33: BATELC | F33: ELC | G33: 2023 | H33: =GW_to_Pja -> 31.536 | I33: 0.85 | K33: 0.5 | L33: =LifetimeAssumptions!$B$12 -> Battery Storage | M33: =_xlfn.XLOOKUP($L33, LifetimeAssumptions[technology],LifetimeAssumptions[Lifetime]) -> 15 | N33: =_xlfn.XLOOKUP($L33, LifetimeAssumptions[technology],LifetimeAssumptions[Discrate]) -> 0.1 | O33: ='2023 Cap Raw Data'!$A$20 -> Battery storage | P33: =_xlfn.XLOOKUP($O33,NewCapCosts2023[Technology],NewCapCosts2023[Fixed O&M (2022$/Kw-y)])*_xlfn.XLOOKUP(lookup_deflator_2023,GDP_deflator[Year],GDP_deflator[Multiply By (for $2005)]) -> 31.622415 | Q33: =_xlfn.XLOOKUP($O33,NewCapCosts2023[Technology],NewCapCosts2023[Fixed O&M (2022$/Kw-y)])*_xlfn.XLOOKUP(lookup_deflator_2023,GDP_deflator[Year],GDP_deflator[Multiply By (for $2005)]) -> 31.622415 | S33: =_xlfn.XLOOKUP($O33,NewCapRegionalCosts[Technology],NewCapRegionalCosts[9 (NYUP)])*_xlfn.XLOOKUP(lookup_deflator_2023,GDP_deflator[Year],GDP_deflator[Multiply By (for $2005)]) -> 880.89107 | T33: =S33 -> 880.89107 | X33: =$T33*SUMIFS(INDIRECT("ATB_CAPEX["&X29&"]"),ATB_CAPEX[CostCase],"Conservative",ATB_CAPEX[Technology],$U32, ATB_CAPEX[TechDetail],$V32)/$W$30 -> 905.69972 | Y33: =$T33*SUMIFS(INDIRECT("ATB_CAPEX["&Y29&"]"),ATB_CAPEX[CostCase],"Conservative",ATB_CAPEX[Technology],$U32, ATB_CAPEX[TechDetail],$V32)/$W$30 -> 744.25114 | Z33: =$T33*SUMIFS(INDIRECT("ATB_CAPEX["&Z29&"]"),ATB_CAPEX[CostCase],"Conservative",ATB_CAPEX[Technology],$U32, ATB_CAPEX[TechDetail],$V32)/$W$30 -> 720.26045 | AA33: =$T33*SUMIFS(INDIRECT("ATB_CAPEX["&AA29&"]"),ATB_CAPEX[CostCase],"Conservative",ATB_CAPEX[Technology],$U32, ATB_CAPEX[TechDetail],$V32)/$W$30 -> 696.26976 | AB33: =$T33*SUMIFS(INDIRECT("ATB_CAPEX["&AB29&"]"),ATB_CAPEX[CostCase],"Conservative",ATB_CAPEX[Technology],$U32, ATB_CAPEX[TechDetail],$V32)/$W$30 -> 672.27907 | AC33: =$T33*SUMIFS(INDIRECT("ATB_CAPEX["&AC29&"]"),ATB_CAPEX[CostCase],"Conservative",ATB_CAPEX[Technology],$U32, ATB_CAPEX[TechDetail],$V32)/$W$30 -> 648.28838 | AE33: =$P33*SUMIFS(INDIRECT("ATB_FOM["&AE$29&"]"),ATB_FOM[CostCase],"Conservative",ATB_FOM[Technology],$U32, ATB_FOM[TechDetail],$V32)/$AD32 -> 32.559225 | AF33: =$P33*SUMIFS(INDIRECT("ATB_FOM["&AF$29&"]"),ATB_FOM[CostCase],"Conservative",ATB_FOM[Technology],$U32, ATB_FOM[TechDetail],$V32)/$AD32 -> 26.462702 | AG33: =$P33*SUMIFS(INDIRECT("ATB_FOM["&AG$29&"]"),ATB_FOM[CostCase],"Conservative",ATB_FOM[Technology],$U32, ATB_FOM[TechDetail],$V32)/$AD32 -> 25.55678 | AH33: =$P33*SUMIFS(INDIRECT("ATB_FOM["&AH$29&"]"),ATB_FOM[CostCase],"Conservative",ATB_FOM[Technology],$U32, ATB_FOM[TechDetail],$V32)/$AD32 -> 24.650858 | AI33: =$P33*SUMIFS(INDIRECT("ATB_FOM["&AI$29&"]"),ATB_FOM[CostCase],"Conservative",ATB_FOM[Technology],$U32, ATB_FOM[TechDetail],$V32)/$AD32 -> 23.744936 | AJ33: =$P33*SUMIFS(INDIRECT("ATB_FOM["&AJ$29&"]"),ATB_FOM[CostCase],"Conservative",ATB_FOM[Technology],$U32, ATB_FOM[TechDetail],$V32)/$AD32 -> 22.839015 | AK33: =AL32 -> 0.16666667 | AM33: =1/2*1/(1+20%) -> 0.41666667 | AN33: =1/2*1/(1+20%) -> 0.41666667 | AO33: =1/2*1/(1+20%) -> 0.41666667 | AS33: 1 | AT33: 1.1 | AV33: 1.1 | AW33: 1.1
A34: SSTOBAT10HRUTI-IN | B34: Electricity Battery Storage 10-hour Utility Scale | C34: PJ,GW | D34: R2,R3,R4,R5,R6 | E34: ELC | F34: BATELC | G34: 2030 | H34: =GW_to_Pja -> 31.536 | J34: 1 | L34: =LifetimeAssumptions!$B$12 -> Battery Storage | M34: =_xlfn.XLOOKUP($L34, LifetimeAssumptions[technology],LifetimeAssumptions[Lifetime]) -> 15 | N34: =_xlfn.XLOOKUP($L34, LifetimeAssumptions[technology],LifetimeAssumptions[Discrate]) -> 0.1 | O34: ='2023 Cap Raw Data'!$A$20 -> Battery storage | U34: =ATB_CAPEX!$E$326 -> Utility-Scale Battery Storage | V34: =ATB_CAPEX!$F$333 -> 10Hr Battery Storage | W34: =SUMIFS(ATB_CAPEX[2022],ATB_CAPEX[CostCase],"Conservative",ATB_CAPEX[Technology],$U34, ATB_CAPEX[TechDetail],$V34) -> 4532.0592 | AD34: =SUMIFS(ATB_FOM[2022],ATB_FOM[CostCase],"Conservative",ATB_FOM[Technology],$U34, ATB_FOM[TechDetail],$V34) -> 106.80729 | AL34: =8/24 -> 0.33333333 | AS34: 1 | AT34: 1.1 | AV34: 1.1 | AW34: 1.1
A35: ESTOBAT10HRUTI-OUT | B35: Electricity Battery Storage 10-hour Utility Scale | C35: PJ,GW | D35: R2,R3,R4,R5,R6 | E35: BATELC | F35: ELC | G35: 2030 | H35: =GW_to_Pja -> 31.536 | I35: 0.85 | K35: 0.5 | L35: =LifetimeAssumptions!$B$12 -> Battery Storage | M35: =_xlfn.XLOOKUP($L35, LifetimeAssumptions[technology],LifetimeAssumptions[Lifetime]) -> 15 | N35: =_xlfn.XLOOKUP($L35, LifetimeAssumptions[technology],LifetimeAssumptions[Discrate]) -> 0.1 | O35: ='2023 Cap Raw Data'!$A$20 -> Battery storage | P35: =_xlfn.XLOOKUP($O35,NewCapCosts2023[Technology],NewCapCosts2023[Fixed O&M (2022$/Kw-y)])*_xlfn.XLOOKUP(lookup_deflator_2023,GDP_deflator[Year],GDP_deflator[Multiply By (for $2005)]) -> 31.622415 | Q35: =_xlfn.XLOOKUP($O35,NewCapCosts2023[Technology],NewCapCosts2023[Fixed O&M (2022$/Kw-y)])*_xlfn.XLOOKUP(lookup_deflator_2023,GDP_deflator[Year],GDP_deflator[Multiply By (for $2005)]) -> 31.622415 | S35: =_xlfn.XLOOKUP($O35,NewCapRegionalCosts[Technology],NewCapRegionalCosts[8 (NYCW)])*_xlfn.XLOOKUP(lookup_deflator_2023,GDP_deflator[Year],GDP_deflator[Multiply By (for $2005)]) -> 901.07894 | T35: =S35 -> 901.07894 | X35: =$T35*SUMIFS(INDIRECT("ATB_CAPEX["&X$29&"]"),ATB_CAPEX[CostCase],"Conservative",ATB_CAPEX[Technology],$U34, ATB_CAPEX[TechDetail],$V34)/$W30 -> 1999.6539 | Y35: =$T35*SUMIFS(INDIRECT("ATB_CAPEX["&Y$29&"]"),ATB_CAPEX[CostCase],"Conservative",ATB_CAPEX[Technology],$U34, ATB_CAPEX[TechDetail],$V34)/$W30 -> 1611.163 | Z35: =$T35*SUMIFS(INDIRECT("ATB_CAPEX["&Z$29&"]"),ATB_CAPEX[CostCase],"Conservative",ATB_CAPEX[Technology],$U34, ATB_CAPEX[TechDetail],$V34)/$W30 -> 1557.5286 | AA35: =$T35*SUMIFS(INDIRECT("ATB_CAPEX["&AA$29&"]"),ATB_CAPEX[CostCase],"Conservative",ATB_CAPEX[Technology],$U34, ATB_CAPEX[TechDetail],$V34)/$W30 -> 1503.8943 | AB35: =$T35*SUMIFS(INDIRECT("ATB_CAPEX["&AB$29&"]"),ATB_CAPEX[CostCase],"Conservative",ATB_CAPEX[Technology],$U34, ATB_CAPEX[TechDetail],$V34)/$W30 -> 1450.2599 | AC35: =$T35*SUMIFS(INDIRECT("ATB_CAPEX["&AC$29&"]"),ATB_CAPEX[CostCase],"Conservative",ATB_CAPEX[Technology],$U34, ATB_CAPEX[TechDetail],$V34)/$W30 -> 1396.6255 | AE35: =$P35*SUMIFS(INDIRECT("ATB_FOM["&AE$29&"]"),ATB_FOM[CostCase],"Conservative",ATB_FOM[Technology],$U34, ATB_FOM[TechDetail],$V34)/$AD34 -> 32.550293 | AF35: =$P35*SUMIFS(INDIRECT("ATB_FOM["&AF$29&"]"),ATB_FOM[CostCase],"Conservative",ATB_FOM[Technology],$U34, ATB_FOM[TechDetail],$V34)/$AD34 -> 26.082652 | AG35: =$P35*SUMIFS(INDIRECT("ATB_FOM["&AG$29&"]"),ATB_FOM[CostCase],"Conservative",ATB_FOM[Technology],$U34, ATB_FOM[TechDetail],$V34)/$AD34 -> 25.189741 | AH35: =$P35*SUMIFS(INDIRECT("ATB_FOM["&AH$29&"]"),ATB_FOM[CostCase],"Conservative",ATB_FOM[Technology],$U34, ATB_FOM[TechDetail],$V34)/$AD34 -> 24.29683 | AI35: =$P35*SUMIFS(INDIRECT("ATB_FOM["&AI$29&"]"),ATB_FOM[CostCase],"Conservative",ATB_FOM[Technology],$U34, ATB_FOM[TechDetail],$V34)/$AD34 -> 23.403919 | AJ35: =$P35*SUMIFS(INDIRECT("ATB_FOM["&AJ$29&"]"),ATB_FOM[CostCase],"Conservative",ATB_FOM[Technology],$U34, ATB_FOM[TechDetail],$V34)/$AD34 -> 22.511007 | AK35: =AL34 -> 0.33333333 | AM35: =1/2*1/(1+20%) -> 0.41666667 | AN35: =1/2*1/(1+20%) -> 0.41666667 | AO35: =1/2*1/(1+20%) -> 0.41666667 | AP35: =1/2*1/(1+20%) -> 0.41666667 | AQ35: =1/2*1/(1+20%) -> 0.41666667 | AR35: =1/2*1/(1+20%) -> 0.41666667 | AS35: 1 | AT35: 1.1 | AV35: 1.1 | AW35: 1.1
A36: SSTOBAT10HRUTI-IN | B36: Electricity Battery Storage 10-hour Utility Scale | C36: PJ,GW | D36: R1 | E36: ELC | F36: BATELC | G36: 2030 | H36: =GW_to_Pja -> 31.536 | J36: 1 | L36: =LifetimeAssumptions!$B$12 -> Battery Storage | M36: =_xlfn.XLOOKUP($L36, LifetimeAssumptions[technology],LifetimeAssumptions[Lifetime]) -> 15 | N36: =_xlfn.XLOOKUP($L36, LifetimeAssumptions[technology],LifetimeAssumptions[Discrate]) -> 0.1 | O36: ='2023 Cap Raw Data'!$A$20 -> Battery storage | U36: =ATB_CAPEX!$E$326 -> Utility-Scale Battery Storage | V36: =ATB_CAPEX!$F$333 -> 10Hr Battery Storage | W36: =SUMIFS(ATB_CAPEX[2022],ATB_CAPEX[CostCase],"Conservative",ATB_CAPEX[Technology],$U36, ATB_CAPEX[TechDetail],$V36) -> 4532.0592 | AD36: =SUMIFS(ATB_FOM[2022],ATB_FOM[CostCase],"Conservative",ATB_FOM[Technology],$U36, ATB_FOM[TechDetail],$V36) -> 106.80729 | AL36: =8/24 -> 0.33333333 | AS36: 1 | AT36: 1.1 | AV36: 1.1 | AW36: 1.1
A37: ESTOBAT10HRUTI-OUT | B37: Electricity Battery Storage 10-hour Utility Scale | C37: PJ,GW | D37: R1 | E37: BATELC | F37: ELC | G37: 2030 | H37: =GW_to_Pja -> 31.536 | I37: 0.85 | K37: 0.5 | L37: =LifetimeAssumptions!$B$12 -> Battery Storage | M37: =_xlfn.XLOOKUP($L37, LifetimeAssumptions[technology],LifetimeAssumptions[Lifetime]) -> 15 | N37: =_xlfn.XLOOKUP($L37, LifetimeAssumptions[technology],LifetimeAssumptions[Discrate]) -> 0.1 | O37: ='2023 Cap Raw Data'!$A$20 -> Battery storage | P37: =_xlfn.XLOOKUP($O37,NewCapCosts2023[Technology],NewCapCosts2023[Fixed O&M (2022$/Kw-y)])*_xlfn.XLOOKUP(lookup_deflator_2023,GDP_deflator[Year],GDP_deflator[Multiply By (for $2005)]) -> 31.622415 | Q37: =_xlfn.XLOOKUP($O37,NewCapCosts2023[Technology],NewCapCosts2023[Fixed O&M (2022$/Kw-y)])*_xlfn.XLOOKUP(lookup_deflator_2023,GDP_deflator[Year],GDP_deflator[Multiply By (for $2005)]) -> 31.622415 | S37: =_xlfn.XLOOKUP($O37,NewCapRegionalCosts[Technology],NewCapRegionalCosts[9 (NYUP)])*_xlfn.XLOOKUP(lookup_deflator_2023,GDP_deflator[Year],GDP_deflator[Multiply By (for $2005)]) -> 880.89107 | T37: =S37 -> 880.89107 | X37: =$T37*SUMIFS(INDIRECT("ATB_CAPEX["&X$29&"]"),ATB_CAPEX[CostCase],"Conservative",ATB_CAPEX[Technology],$U36, ATB_CAPEX[TechDetail],$V36)/$W32 -> 1954.8534 | Y37: =$T37*SUMIFS(INDIRECT("ATB_CAPEX["&Y$29&"]"),ATB_CAPEX[CostCase],"Conservative",ATB_CAPEX[Technology],$U36, ATB_CAPEX[TechDetail],$V36)/$W32 -> 1575.0663 | Z37: =$T37*SUMIFS(INDIRECT("ATB_CAPEX["&Z$29&"]"),ATB_CAPEX[CostCase],"Conservative",ATB_CAPEX[Technology],$U36, ATB_CAPEX[TechDetail],$V36)/$W32 -> 1522.6336 | AA37: =$T37*SUMIFS(INDIRECT("ATB_CAPEX["&AA$29&"]"),ATB_CAPEX[CostCase],"Conservative",ATB_CAPEX[Technology],$U36, ATB_CAPEX[TechDetail],$V36)/$W32 -> 1470.2008 | AB37: =$T37*SUMIFS(INDIRECT("ATB_CAPEX["&AB$29&"]"),ATB_CAPEX[CostCase],"Conservative",ATB_CAPEX[Technology],$U36, ATB_CAPEX[TechDetail],$V36)/$W32 -> 1417.7681 | AC37: =$T37*SUMIFS(INDIRECT("ATB_CAPEX["&AC$29&"]"),ATB_CAPEX[CostCase],"Conservative",ATB_CAPEX[Technology],$U36, ATB_CAPEX[TechDetail],$V36)/$W32 -> 1365.3353 | AE37: =$P37*SUMIFS(INDIRECT("ATB_FOM["&AE$29&"]"),ATB_FOM[CostCase],"Conservative",ATB_FOM[Technology],$U36, ATB_FOM[TechDetail],$V36)/$AD36 -> 32.550293 | AF37: =$P37*SUMIFS(INDIRECT("ATB_FOM["&AF$29&"]"),ATB_FOM[CostCase],"Conservative",ATB_FOM[Technology],$U36, ATB_FOM[TechDetail],$V36)/$AD36 -> 26.082652 | AG37: =$P37*SUMIFS(INDIRECT("ATB_FOM["&AG$29&"]"),ATB_FOM[CostCase],"Conservative",ATB_FOM[Technology],$U36, ATB_FOM[TechDetail],$V36)/$AD36 -> 25.189741 | AH37: =$P37*SUMIFS(INDIRECT("ATB_FOM["&AH$29&"]"),ATB_FOM[CostCase],"Conservative",ATB_FOM[Technology],$U36, ATB_FOM[TechDetail],$V36)/$AD36 -> 24.29683 | AI37: =$P37*SUMIFS(INDIRECT("ATB_FOM["&AI$29&"]"),ATB_FOM[CostCase],"Conservative",ATB_FOM[Technology],$U36, ATB_FOM[TechDetail],$V36)/$AD36 -> 23.403919 | AJ37: =$P37*SUMIFS(INDIRECT("ATB_FOM["&AJ$29&"]"),ATB_FOM[CostCase],"Conservative",ATB_FOM[Technology],$U36, ATB_FOM[TechDetail],$V36)/$AD36 -> 22.511007 | AK37: =AL36 -> 0.33333333 | AM37: =1/2*1/(1+20%) -> 0.41666667 | AN37: =1/2*1/(1+20%) -> 0.41666667 | AO37: =1/2*1/(1+20%) -> 0.41666667 | AP37: =1/2*1/(1+20%) -> 0.41666667 | AQ37: =1/2*1/(1+20%) -> 0.41666667 | AR37: =1/2*1/(1+20%) -> 0.41666667 | AS37: 1 | AT37: 1.1 | AV37: 1.1 | AW37: 1.1
E42: ~FI_T
A43: TechName | B43: *TechDesc | C43: *Units | D43: CommIN | E43: CommOUT | F43: Share~LO | G43: Share~UP | H43: ACT_EFF | I43: NCAP_START | J43: NCAP_TLIFE | K43: PRC_CAPACT | L43: Peak | M43: NCAP_COST | N43: NCAP_FOM | O43: ACT_COST | P43: NCAP_AF | Q43: NCAP_DRATE
A44: *CHP Technologies | B44: new_cap_CHP
A45: ECHPBIO11 | B45: Electric sector BIO CHP | C45: PJ, GW | D45: ELCBIOSTM | H45: 0.8 | I45: 2011 | J45: 45 | K45: 31.536 | L45: 0.95 | M45: =M49 -> 2874.2698 | N45: =N49 -> 32.779711 | O45: =O49 -> 1.3053712 | P45: 0.9 | Q45: 0.15
E46: ELC | F46: 0.35 | G46: 0.35
E47: COMSTBUC | F47: =G47*0.75 -> 0.39 | G47: =(1-G46)*80% -> 0.52
E48: RESSTBUC | F48: =G48*0.75 -> 0.0975 | G48: =(1-G46)*(1-80%) -> 0.13
A49: ECHPCOAL11 | B49: Electric sector Coal CHP | C49: PJ, GW | D49: COALBST | H49: 0.8 | I49: 2011 | J49: 45 | K49: 31.536 | L49: 0.95 | M49: 2874.2698 | N49: 32.779711 | O49: 1.3053712 | P49: 1 | Q49: 0.15
E50: ELC | F50: 0.35 | G50: 0.35
E51: COMSTBUC | F51: =G51*0.75 -> 0.39 | G51: =(1-G50)*80% -> 0.52
E52: RESSTBUC | F52: =G52*0.75 -> 0.0975 | G52: =(1-G50)*(1-80%) -> 0.13
A53: ECHPNGA11 | B53: Electric sector NGA CHP | C53: PJ, GW | D53: ELCNGAEA | H53: 0.8 | I53: 2011 | J53: 45 | K53: 31.536 | L53: 0.95 | M53: 971.40646 | N53: 7.7165838 | O53: 4.5118536 | P53: 1 | Q53: 0.15
E54: ELC | F54: 0.35 | G54: 0.35
E55: COMSTNUC | F55: =G55*0.75 -> 0.39 | G55: =(1-G54)*80% -> 0.52
E56: RESSTNUC | F56: =G56*0.75 -> 0.0975 | G56: =(1-G54)*(1-80%) -> 0.13
A57: ECHPOIL11 | B57: Electric sector Oil CHP | C57: PJ, GW | D57: ELCDSLEA | H57: 0.8 | I57: 2011 | J57: 45 | K57: 31.536 | L57: 0.95 | M57: 971.40646 | N57: 7.7165838 | O57: 4.5118536 | P57: 1 | Q57: 0.15
E58: ELC | F58: 0.35 | G58: 0.35
E59: COMSTNUC | F59: =G59*0.75 -> 0.39 | G59: =(1-G58)*80% -> 0.52
E60: RESSTNUC | F60: =G60*0.75 -> 0.0975 | G60: =(1-G58)*(1-80%) -> 0.13

Sheet TechData_SolarWind
A1: _GLOBAL,R0,R1,R2,R3,R4,R5,R6
F3: ~FI_T
A4: TechName | B4: *TechDesc | C4: Region | D4: *Units | E4: CommIN | F4: CommOUT | G4: NCAP_START | H4: *lookup | I4: NCAP_DRATE | J4: NCAP_TLIFE | K4: EFF | L4: PRC_CAPACT | M4: Peak | N4: *LOOKUP | O4: *Base Cost 2012 - not class adjusted | P4: *2023 Cost LOOKUP | Q4: *Base Cost 2023 - not class adjusted | R4: *Supply Curve Label | S4: *Supply Curve Reference Price | T4: *Supply Curve Class Cost Adjustor | U4: NCAP_COST~2010 | V4: NCAP_COST~2022 | W4: NCAP_COST~2025 | X4: NCAP_COST~2030 | Y4: NCAP_COST~2035 | Z4: NCAP_COST~2040 | AA4: NCAP_COST~2055 | AB4: NCAP_FOM~2005 | AC4: NCAP_FOM~2010 | AD4: NCAP_FOM~2015 | AE4: NCAP_FOM~2020 | AF4: NCAP_FOM~2025 | AG4: NCAP_FOM~2030 | AH4: NCAP_FOM~2035 | AI4: NCAP_FOM~2040 | AJ4: NCAP_FOM~2045 | AK4: NCAP_FOM~2050 | AL4: *ATB_CapacityFactor | AM4: NCAP_AF~IDAM | AN4: NCAP_AF~IDPM | AO4: *NCAP_AF~IP_Calculation | AP4: NCAP_AF~IP | AQ4: NCAP_AF~IN | AR4: NCAP_AF~SDAM | AS4: NCAP_AF~SDPM | AT4: *NCAP_AF~SP_Calc | AU4: NCAP_AF~SP | AV4: NCAP_AF~SN | AW4: NCAP_AF~WDAM | AX4: NCAP_AF~WDPM | AY4: *NCAP_AF~WP_Calculation | AZ4: NCAP_AF~WP | BA4: NCAP_AF~WN | BB4: CAP_BND~UP
A5: * Solar PV Technologies | B5: solarPV_technologies | H5: *lifetime_lookup | W5: 2025 | X5: 2030 | Y5: 2035 | Z5: 2040 | AF5: 2025 | AG5: 2030 | AH5: 2035 | AI5: 2040 | AJ5: 2045 | AK5: 2050
A6: ESOLPVCLOWCOST | B6: Solar PV Centralized Generation, Low Cost | C6: R1 | D6: PJ, GW | E6: ELCSOL | F6: ELC | G6: 2011 | H6: =LifetimeAssumptions!$B$15 -> Solar PV | I6: =_xlfn.XLOOKUP($H6, LifetimeAssumptions[technology],LifetimeAssumptions[Discrate]) -> 0.1 | J6: =_xlfn.XLOOKUP($H6, LifetimeAssumptions[technology],LifetimeAssumptions[Lifetime]) -> 30 | K6: =1/2.8 -> 0.35714286 | L6: 31.536 | M6: 0.1 | N6: ='2013 Cap Raw Data'!$A$25 -> Photovoltaic | O6: =_xlfn.XLOOKUP($N6,NewCapCosts2013[Technology],NewCapCosts2013[Total Overnight Cost in 2012 (2012 $/kW)])*_xlfn.XLOOKUP(2012, GDP_deflator[Year],GDP_deflator[Multiply By (for $2005)]) -> 3119.2315 | P6: ='2023_Regional_Cost_Factor'!$A$26 -> Solar PV with tracking | Q6: =_xlfn.XLOOKUP($P6,NewCapRegionalCosts[Technology],NewCapRegionalCosts[9 (NYUP)])*_xlfn.XLOOKUP(2022, GDP_deflator[Year],GDP_deflator[Multiply By (for $2005)]) -> 1022.9702 | R6: =SupplyCurveProcessed!$E$21 -> Utility-scale Solar_Rest of State_Low Cost | S6: =SupplyCurveProcessed!$E$24 -> Utility-scale Solar_Rest of State_All | T6: =SUMIFS(NYSERDA_SupplyProcessed[Average Capex ($2024 / kW)],NYSERDA_SupplyProcessed[Label],$R6)/ SUMIFS(NYSERDA_SupplyProcessed[Average Capex ($2024 / kW)],NYSERDA_SupplyProcessed[Label],$S6) -> 0.95799329 | U6: =$T6*$O6 -> 2988.2028 | V6: =$T6*$Q6 -> 979.99856 | W6: =SUMIFS(INDIRECT("NYSERDA_SupplyProcessed[CapEx Escalator_"&W$5&"]"), NYSERDA_SupplyProcessed[Label],$R6) *$V6 -> 962.41305 | X6: =SUMIFS(INDIRECT("NYSERDA_SupplyProcessed[CapEx Escalator_"&X$5&"]"), NYSERDA_SupplyProcessed[Label],$R6) *$V6 -> 953.21919 | Y6: =SUMIFS(INDIRECT("NYSERDA_SupplyProcessed[CapEx Escalator_"&Y$5&"]"), NYSERDA_SupplyProcessed[Label],$R6) *$V6 -> 996.5911 | Z6: =SUMIFS(INDIRECT("NYSERDA_SupplyProcessed[CapEx Escalator_"&Z$5&"]"), NYSERDA_SupplyProcessed[Label],$R6) *$V6 -> 1054.1697 | AA6: =Z6 -> 1054.1697 | AB6: =_xlfn.XLOOKUP($N6,NewCapCosts2013[Technology],NewCapCosts2013[Fixed O&M ($2012/kW)])*_xlfn.XLOOKUP(2012, GDP_deflator[Year],GDP_deflator[Multiply By (for $2005)]) -> 21.608817 | AC6: =_xlfn.XLOOKUP($N6,NewCapCosts2013[Technology],NewCapCosts2013[Fixed O&M ($2012/kW)])*_xlfn.XLOOKUP(2012, GDP_deflator[Year],GDP_deflator[Multiply By (for $2005)]) -> 21.608817 | AD6: =_xlfn.XLOOKUP($N6,NewCapCosts2013[Technology],NewCapCosts2013[Fixed O&M ($2012/kW)])*_xlfn.XLOOKUP(2012, GDP_deflator[Year],GDP_deflator[Multiply By (for $2005)]) -> 21.608817 | AE6: =_xlfn.XLOOKUP($N6,NewCapCosts2013[Technology],NewCapCosts2013[Fixed O&M ($2012/kW)])*_xlfn.XLOOKUP(2012, GDP_deflator[Year],GDP_deflator[Multiply By (for $2005)]) -> 21.608817 | AF6: =SUMIFS(NYSERDA_SupplyProcessed[OpEx (thousand $ 2024 / kW - year)], NYSERDA_SupplyProcessed[Label],$R6) *_xlfn.XLOOKUP(2023, GDP_deflator[Year],GDP_deflator[Multiply By (for $2005)]) -> 18.265358 | AG6: =SUMIFS(NYSERDA_SupplyProcessed[OpEx (thousand $ 2024 / kW - year)], NYSERDA_SupplyProcessed[Label],$R6) *_xlfn.XLOOKUP(2023, GDP_deflator[Year],GDP_deflator[Multiply By (for $2005)]) -> 18.265358 | AH6: =SUMIFS(NYSERDA_SupplyProcessed[OpEx (thousand $ 2024 / kW - year)], NYSERDA_SupplyProcessed[Label],$R6) *_xlfn.XLOOKUP(2023, GDP_deflator[Year],GDP_deflator[Multiply By (for $2005)]) -> 18.265358 | AI6: =SUMIFS(NYSERDA_SupplyProcessed[OpEx (thousand $ 2024 / kW - year)], NYSERDA_SupplyProcessed[Label],$R6) *_xlfn.XLOOKUP(2023, GDP_deflator[Year],GDP_deflator[Multiply By (for $2005)]) -> 18.265358 | AJ6: =SUMIFS(NYSERDA_SupplyProcessed[OpEx (thousand $ 2024 / kW - year)], NYSERDA_SupplyProcessed[Label],$R6) *_xlfn.XLOOKUP(2023, GDP_deflator[Year],GDP_deflator[Multiply By (for $2005)]) -> 18.265358 | AK6: =SUMIFS(NYSERDA_SupplyProcessed[OpEx (thousand $ 2024 / kW - year)], NYSERDA_SupplyProcessed[Label],$R6) *_xlfn.XLOOKUP(2023, GDP_deflator[Year],GDP_deflator[Multiply By (for $2005)]) -> 18.265358 | AM6: 0.33964956 | AN6: 0.33964956 | AO6: 0.33964956 | AP6: =AO6*0.2 -> 0.067929912 | AQ6: 0 | AR6: 0.35623894 | AS6: 0.35623894 | AT6: 0.35623894 | AU6: =AT6*0.2 -> 0.071247788 | AV6: 0 | AW6: 0.32014566 | AX6: 0.32014566 | AY6: 0.32014566 | AZ6: =AY6*0.2 -> 0.064029133 | BA6: 0 | BB6: =SUMIFS(NYSERDA_SupplyProcessed[Total Capacity (MW)], NYSERDA_SupplyProcessed[Label],$R6)/1000 -> 50.438526
A7: ESOLPVCHIGHCOST | B7: Solar PV Centralized Generation, High Cost | C7: R1 | D7: PJ, GW | E7: ELCSOL | F7: ELC | G7: 2011 | H7: =LifetimeAssumptions!$B$15 -> Solar PV | I7: =_xlfn.XLOOKUP($H7, LifetimeAssumptions[technology],LifetimeAssumptions[Discrate]) -> 0.1 | J7: =_xlfn.XLOOKUP($H7, LifetimeAssumptions[technology],LifetimeAssumptions[Lifetime]) -> 30 | K7: =1/2.8 -> 0.35714286 | L7: 31.536 | M7: 0.1 | N7: ='2013 Cap Raw Data'!$A$25 -> Photovoltaic | O7: =_xlfn.XLOOKUP($N7,NewCapCosts2013[Technology],NewCapCosts2013[Total Overnight Cost in 2012 (2012 $/kW)])*_xlfn.XLOOKUP(2012, GDP_deflator[Year],GDP_deflator[Multiply By (for $2005)]) -> 3119.2315 | P7: ='2023_Regional_Cost_Factor'!$A$26 -> Solar PV with tracking | Q7: =_xlfn.XLOOKUP($P7,NewCapRegionalCosts[Technology],NewCapRegionalCosts[9 (NYUP)])*_xlfn.XLOOKUP(2022, GDP_deflator[Year],GDP_deflator[Multiply By (for $2005)]) -> 1022.9702 | R7: =SupplyCurveProcessed!$E$23 -> Utility-scale Solar_Rest of State_High Cost | S7: =SupplyCurveProcessed!$E$24 -> Utility-scale Solar_Rest of State_All | T7: =SUMIFS(NYSERDA_SupplyProcessed[Average Capex ($2024 / kW)],NYSERDA_SupplyProcessed[Label],$R7)/ SUMIFS(NYSERDA_SupplyProcessed[Average Capex ($2024 / kW)],NYSERDA_SupplyProcessed[Label],$S7) -> 1.0977576 | U7: =$T7*$O7 -> 3424.1599 | V7: =$T7*$Q7 -> 1122.9732 | W7: =SUMIFS(INDIRECT("NYSERDA_SupplyProcessed[CapEx Escalator_"&W$5&"]"), NYSERDA_SupplyProcessed[Label],$R7) *$V7 -> 1102.8221 | X7: =SUMIFS(INDIRECT("NYSERDA_SupplyProcessed[CapEx Escalator_"&X$5&"]"), NYSERDA_SupplyProcessed[Label],$R7) *$V7 -> 1092.2869 | Y7: =SUMIFS(INDIRECT("NYSERDA_SupplyProcessed[CapEx Escalator_"&Y$5&"]"), NYSERDA_SupplyProcessed[Label],$R7) *$V7 -> 1141.9865 | Z7: =SUMIFS(INDIRECT("NYSERDA_SupplyProcessed[CapEx Escalator_"&Z$5&"]"), NYSERDA_SupplyProcessed[Label],$R7) *$V7 -> 1207.9654 | AA7: =Z7 -> 1207.9654 | AB7: =_xlfn.XLOOKUP($N7,NewCapCosts2013[Technology],NewCapCosts2013[Fixed O&M ($2012/kW)])*_xlfn.XLOOKUP(2012, GDP_deflator[Year],GDP_deflator[Multiply By (for $2005)]) -> 21.608817 | AC7: =_xlfn.XLOOKUP($N7,NewCapCosts2013[Technology],NewCapCosts2013[Fixed O&M ($2012/kW)])*_xlfn.XLOOKUP(2012, GDP_deflator[Year],GDP_deflator[Multiply By (for $2005)]) -> 21.608817 | AD7: =_xlfn.XLOOKUP($N7,NewCapCosts2013[Technology],NewCapCosts2013[Fixed O&M ($2012/kW)])*_xlfn.XLOOKUP(2012, GDP_deflator[Year],GDP_deflator[Multiply By (for $2005)]) -> 21.608817 | AE7: =_xlfn.XLOOKUP($N7,NewCapCosts2013[Technology],NewCapCosts2013[Fixed O&M ($2012/kW)])*_xlfn.XLOOKUP(2012, GDP_deflator[Year],GDP_deflator[Multiply By (for $2005)]) -> 21.608817 | AF7: =SUMIFS(NYSERDA_SupplyProcessed[OpEx (thousand $ 2024 / kW - year)], NYSERDA_SupplyProcessed[Label],$R7) *_xlfn.XLOOKUP(2023, GDP_deflator[Year],GDP_deflator[Multiply By (for $2005)]) -> 18.299442 | AG7: =SUMIFS(NYSERDA_SupplyProcessed[OpEx (thousand $ 2024 / kW - year)], NYSERDA_SupplyProcessed[Label],$R7) *_xlfn.XLOOKUP(2023, GDP_deflator[Year],GDP_deflator[Multiply By (for $2005)]) -> 18.299442 | AH7: =SUMIFS(NYSERDA_SupplyProcessed[OpEx (thousand $ 2024 / kW - year)], NYSERDA_SupplyProcessed[Label],$R7) *_xlfn.XLOOKUP(2023, GDP_deflator[Year],GDP_deflator[Multiply By (for $2005)]) -> 18.299442 | AI7: =SUMIFS(NYSERDA_SupplyProcessed[OpEx (thousand $ 2024 / kW - year)], NYSERDA_SupplyProcessed[Label],$R7) *_xlfn.XLOOKUP(2023, GDP_deflator[Year],GDP_deflator[Multiply By (for $2005)]) -> 18.299442 | AJ7: =SUMIFS(NYSERDA_SupplyProcessed[OpEx (thousand $ 2024 / kW - year)], NYSERDA_SupplyProcessed[Label],$R7) *_xlfn.XLOOKUP(2023, GDP_deflator[Year],GDP_deflator[Multiply By (for $2005)]) -> 18.299442 | AK7: =SUMIFS(NYSERDA_SupplyProcessed[OpEx (thousand $ 2024 / kW - year)], NYSERDA_SupplyProcessed[Label],$R7) *_xlfn.XLOOKUP(2023, GDP_deflator[Year],GDP_deflator[Multiply By (for $2005)]) -> 18.299442 | AM7: 0.33964956 | AN7: 0.33964956 | AO7: 0.33964956 | AP7: =AO7*0.2 -> 0.067929912 | AQ7: 0 | AR7: 0.35623894 | AS7: 0.35623894 | AT7: 0.35623894 | AU7: =AT7*0.2 -> 0.071247788 | AV7: 0 | AW7: 0.32014566 | AX7: 0.32014566 | AY7: 0.32014566 | AZ7: =AY7*0.2 -> 0.064029133 | BA7: 0 | BB7: =SUMIFS(NYSERDA_SupplyProcessed[Total Capacity (MW)], NYSERDA_SupplyProcessed[Label],$R7)/1000 -> 21.673583
A8: * Wind Technologies | B8: wind_technologies | AL8: timeslice_lookup | AM8: =I_D -> 1.1925 | AN8: =I_D -> 1.1925 | AO8: =I_D -> 1.1925 | AQ8: =I_N -> 0.9555 | AR8: =S_D -> 0.71861538 | AS8: =S_D -> 0.71861538 | AT8: =S_D -> 0.71861538 | AV8: =S_N -> 0.52527273 | AW8: =W_D -> 1.3876364 | AX8: =W_D -> 1.3876364 | AY8: =W_D -> 1.3876364 | BA8: =W_N -> 1.2295385
A9: EWNDONLOWCOST | B9: Onshore Wind, Low Cost | C9: R1 | E9: ELCWND | F9: ELC | G9: 2011 | H9: =LifetimeAssumptions!$B$17 -> Wind | I9: =_xlfn.XLOOKUP($H9, LifetimeAssumptions[technology],LifetimeAssumptions[Discrate]) -> 0.1 | J9: =_xlfn.XLOOKUP($H9, LifetimeAssumptions[technology],LifetimeAssumptions[Lifetime]) -> 30 | K9: =1/2.8 -> 0.35714286 | L9: 31.536 | M9: 0.1 | N9: Wind | O9: =_xlfn.XLOOKUP($N9,NewCapCosts2013[Technology],NewCapCosts2013[Total Overnight Cost in 2012 (2012 $/kW)])*_xlfn.XLOOKUP(2012, GDP_deflator[Year],GDP_deflator[Multiply By (for $2005)]) -> 1929.8275 | P9: Wind | Q9: =_xlfn.XLOOKUP($P9,NewCapRegionalCosts[Technology],NewCapRegionalCosts[9 (NYUP)])*_xlfn.XLOOKUP(2022, GDP_deflator[Year],GDP_deflator[Multiply By (for $2005)]) -> 1749.1851 | R9: =SupplyCurveProcessed!$E$16 -> Land-based Wind_Rest of State_Low Cost | S9: =SupplyCurveProcessed!$E$17 -> Land-based Wind_Rest of State_All | T9: =SUMIFS(NYSERDA_SupplyProcessed[Average Capex ($2024 / kW)],NYSERDA_SupplyProcessed[Label],$R9)/ SUMIFS(NYSERDA_SupplyProcessed[Average Capex ($2024 / kW)],NYSERDA_SupplyProcessed[Label],$S9) -> 0.98733995 | U9: =$T9*$O9 -> 1905.3958 | V9: =$T9*$Q9 -> 1727.0403 | W9: =SUMIFS(INDIRECT("NYSERDA_SupplyProcessed[CapEx Escalator_"&W$5&"]"), NYSERDA_SupplyProcessed[Label],$R9) *$V9 -> 1766.7622 | X9: =SUMIFS(INDIRECT("NYSERDA_SupplyProcessed[CapEx Escalator_"&X$5&"]"), NYSERDA_SupplyProcessed[Label],$R9) *$V9 -> 1905.4481 | Y9: =SUMIFS(INDIRECT("NYSERDA_SupplyProcessed[CapEx Escalator_"&Y$5&"]"), NYSERDA_SupplyProcessed[Label],$R9) *$V9 -> 2050.7494 | Z9: =SUMIFS(INDIRECT("NYSERDA_SupplyProcessed[CapEx Escalator_"&Z$5&"]"), NYSERDA_SupplyProcessed[Label],$R9) *$V9 -> 2220.4401 | AA9: =Z9 -> 2220.4401 | AB9: =_xlfn.XLOOKUP($N9,NewCapCosts2013[Technology],NewCapCosts2013[Fixed O&M ($2012/kW)])*_xlfn.XLOOKUP(2012, GDP_deflator[Year],GDP_deflator[Multiply By (for $2005)]) -> 34.614367 | AC9: =_xlfn.XLOOKUP($N9,NewCapCosts2013[Technology],NewCapCosts2013[Fixed O&M ($2012/kW)])*_xlfn.XLOOKUP(2012, GDP_deflator[Year],GDP_deflator[Multiply By (for $2005)]) -> 34.614367 | AD9: =_xlfn.XLOOKUP($N9,NewCapCosts2013[Technology],NewCapCosts2013[Fixed O&M ($2012/kW)])*_xlfn.XLOOKUP(2012, GDP_deflator[Year],GDP_deflator[Multiply By (for $2005)]) -> 34.614367 | AE9: =_xlfn.XLOOKUP($N9,NewCapCosts2013[Technology],NewCapCosts2013[Fixed O&M ($2012/kW)])*_xlfn.XLOOKUP(2012, GDP_deflator[Year],GDP_deflator[Multiply By (for $2005)]) -> 34.614367 | AF9: =SUMIFS(NYSERDA_SupplyProcessed[OpEx (thousand $ 2024 / kW - year)], NYSERDA_SupplyProcessed[Label],$R9) *_xlfn.XLOOKUP(2023, GDP_deflator[Year],GDP_deflator[Multiply By (for $2005)]) -> 37.939372 | AG9: =SUMIFS(NYSERDA_SupplyProcessed[OpEx (thousand $ 2024 / kW - year)], NYSERDA_SupplyProcessed[Label],$R9) *_xlfn.XLOOKUP(2023, GDP_deflator[Year],GDP_deflator[Multiply By (for $2005)]) -> 37.939372 | AH9: =SUMIFS(NYSERDA_SupplyProcessed[OpEx (thousand $ 2024 / kW - year)], NYSERDA_SupplyProcessed[Label],$R9) *_xlfn.XLOOKUP(2023, GDP_deflator[Year],GDP_deflator[Multiply By (for $2005)]) -> 37.939372 | AI9: =SUMIFS(NYSERDA_SupplyProcessed[OpEx (thousand $ 2024 / kW - year)], NYSERDA_SupplyProcessed[Label],$R9) *_xlfn.XLOOKUP(2023, GDP_deflator[Year],GDP_deflator[Multiply By (for $2005)]) -> 37.939372 | AJ9: =SUMIFS(NYSERDA_SupplyProcessed[OpEx (thousand $ 2024 / kW - year)], NYSERDA_SupplyProcessed[Label],$R9) *_xlfn.XLOOKUP(2023, GDP_deflator[Year],GDP_deflator[Multiply By (for $2005)]) -> 37.939372 | AK9: =SUMIFS(NYSERDA_SupplyProcessed[OpEx (thousand $ 2024 / kW - year)], NYSERDA_SupplyProcessed[Label],$R9) *_xlfn.XLOOKUP(2023, GDP_deflator[Year],GDP_deflator[Multiply By (for $2005)]) -> 37.939372 | AL9: =SUMIFS(NYSERDA_SupplyProcessed[Average Capacity Factor], NYSERDA_SupplyProcessed[Label],$R9) -> 0.35832433 | AM9: =AM$8*$AL9 -> 0.42730177 | AN9: =AN$8*$AL9 -> 0.42730177 | AO9: =AO$8*$AL9 -> 0.42730177 | AP9: =AO9*0.2 -> 0.085460353 | AQ9: =AQ$8*$AL9 -> 0.3423789 | AR9: =AR$8*$AL9 -> 0.25749738 | AS9: =AS$8*$AL9 -> 0.25749738 | AT9: =AT$8*$AL9 -> 0.25749738 | AU9: =AT9*0.2 -> 0.051499476 | AV9: =AV$8*$AL9 -> 0.188218 | AW9: =AW$8*$AL9 -> 0.49722387 | AX9: =AX$8*$AL9 -> 0.49722387 | AY9: =AY$8*$AL9 -> 0.49722387 | AZ9: =AY9*0.2 -> 0.099444775 | BA9: =BA$8*$AL9 -> 0.44057355 | BB9: =SUMIFS(NYSERDA_SupplyProcessed[Total Capacity (MW)], NYSERDA_SupplyProcessed[Label],$R9)/1000 -> 11.060268
A10: EWNDONHIGHCOST | B10: Onshore Wind, High Cost | C10: R1 | E10: ELCWND | F10: ELC | G10: 2011 | H10: =LifetimeAssumptions!$B$17 -> Wind | I10: =_xlfn.XLOOKUP($H10, LifetimeAssumptions[technology],LifetimeAssumptions[Discrate]) -> 0.1 | J10: =_xlfn.XLOOKUP($H10, LifetimeAssumptions[technology],LifetimeAssumptions[Lifetime]) -> 30 | K10: =1/2.8 -> 0.35714286 | L10: 31.536 | M10: 0.1 | N10: Wind | O10: =_xlfn.XLOOKUP($N10,NewCapCosts2013[Technology],NewCapCosts2013[Total Overnight Cost in 2012 (2012 $/kW)])*_xlfn.XLOOKUP(2012, GDP_deflator[Year],GDP_deflator[Multiply By (for $2005)]) -> 1929.8275 | P10: Wind | Q10: =_xlfn.XLOOKUP($P10,NewCapRegionalCosts[Technology],NewCapRegionalCosts[9 (NYUP)])*_xlfn.XLOOKUP(2022, GDP_deflator[Year],GDP_deflator[Multiply By (for $2005)]) -> 1749.1851 | R10: =SupplyCurveProcessed!$E$19 -> Land-based Wind_Rest of State_High Cost | S10: =SupplyCurveProcessed!$E$17 -> Land-based Wind_Rest of State_All | T10: =SUMIFS(NYSERDA_SupplyProcessed[Average Capex ($2024 / kW)],NYSERDA_SupplyProcessed[Label],$R10)/ SUMIFS(NYSERDA_SupplyProcessed[Average Capex ($2024 / kW)],NYSERDA_SupplyProcessed[Label],$S10) -> 1.1592578 | U10: =$T10*$O10 -> 2237.1676 | V10: =$T10*$Q10 -> 2027.7564 | W10: =SUMIFS(INDIRECT("NYSERDA_SupplyProcessed[CapEx Escalator_"&W$5&"]"), NYSERDA_SupplyProcessed[Label],$R10) *$V10 -> 2074.3948 | X10: =SUMIFS(INDIRECT("NYSERDA_SupplyProcessed[CapEx Escalator_"&X$5&"]"), NYSERDA_SupplyProcessed[Label],$R10) *$V10 -> 2237.2289 | Y10: =SUMIFS(INDIRECT("NYSERDA_SupplyProcessed[CapEx Escalator_"&Y$5&"]"), NYSERDA_SupplyProcessed[Label],$R10) *$V10 -> 2407.8304 | Z10: =SUMIFS(INDIRECT("NYSERDA_SupplyProcessed[CapEx Escalator_"&Z$5&"]"), NYSERDA_SupplyProcessed[Label],$R10) *$V10 -> 2607.068 | AA10: =Z10 -> 2607.068 | AB10: =_xlfn.XLOOKUP($N10,NewCapCosts2013[Technology],NewCapCosts2013[Fixed O&M ($2012/kW)])*_xlfn.XLOOKUP(2012, GDP_deflator[Year],GDP_deflator[Multiply By (for $2005)]) -> 34.614367 | AC10: =_xlfn.XLOOKUP($N10,NewCapCosts2013[Technology],NewCapCosts2013[Fixed O&M ($2012/kW)])*_xlfn.XLOOKUP(2012, GDP_deflator[Year],GDP_deflator[Multiply By (for $2005)]) -> 34.614367 | AD10: =_xlfn.XLOOKUP($N10,NewCapCosts2013[Technology],NewCapCosts2013[Fixed O&M ($2012/kW)])*_xlfn.XLOOKUP(2012, GDP_deflator[Year],GDP_deflator[Multiply By (for $2005)]) -> 34.614367 | AE10: =_xlfn.XLOOKUP($N10,NewCapCosts2013[Technology],NewCapCosts2013[Fixed O&M ($2012/kW)])*_xlfn.XLOOKUP(2012, GDP_deflator[Year],GDP_deflator[Multiply By (for $2005)]) -> 34.614367 | AF10: =SUMIFS(NYSERDA_SupplyProcessed[OpEx (thousand $ 2024 / kW - year)], NYSERDA_SupplyProcessed[Label],$R10) *_xlfn.XLOOKUP(2023, GDP_deflator[Year],GDP_deflator[Multiply By (for $2005)]) -> 38.119502 | AG10: =SUMIFS(NYSERDA_SupplyProcessed[OpEx (thousand $ 2024 / kW - year)], NYSERDA_SupplyProcessed[Label],$R10) *_xlfn.XLOOKUP(2023, GDP_deflator[Year],GDP_deflator[Multiply By (for $2005)]) -> 38.119502 | AH10: =SUMIFS(NYSERDA_SupplyProcessed[OpEx (thousand $ 2024 / kW - year)], NYSERDA_SupplyProcessed[Label],$R10) *_xlfn.XLOOKUP(2023, GDP_deflator[Year],GDP_deflator[Multiply By (for $2005)]) -> 38.119502 | AI10: =SUMIFS(NYSERDA_SupplyProcessed[OpEx (thousand $ 2024 / kW - year)], NYSERDA_SupplyProcessed[Label],$R10) *_xlfn.XLOOKUP(2023, GDP_deflator[Year],GDP_deflator[Multiply By (for $2005)]) -> 38.119502 | AJ10: =SUMIFS(NYSERDA_SupplyProcessed[OpEx (thousand $ 2024 / kW - year)], NYSERDA_SupplyProcessed[Label],$R10) *_xlfn.XLOOKUP(2023, GDP_deflator[Year],GDP_deflator[Multiply By (for $2005)]) -> 38.119502 | AK10: =SUMIFS(NYSERDA_SupplyProcessed[OpEx (thousand $ 2024 / kW - year)], NYSERDA_SupplyProcessed[Label],$R10) *_xlfn.XLOOKUP(2023, GDP_deflator[Year],GDP_deflator[Multiply By (for $2005)]) -> 38.119502 | AL10: =SUMIFS(NYSERDA_SupplyProcessed[Average Capacity Factor], NYSERDA_SupplyProcessed[Label],$R10) -> 0.37295162 | AM10: =AM$8*$AL10 -> 0.44474481 | AN10: =AN$8*$AL10 -> 0.44474481 | AO10: =AO$8*$AL10 -> 0.44474481 | AP10: =AO10*0.2 -> 0.088948962 | AQ10: =AQ$8*$AL10 -> 0.35635528 | AR10: =AR$8*$AL10 -> 0.26800877 | AS10: =AS$8*$AL10 -> 0.26800877 | AT10: =AT$8*$AL10 -> 0.26800877 | AU10: =AT10*0.2 -> 0.053601755 | AV10: =AV$8*$AL10 -> 0.19590132 | AW10: =AW$8*$AL10 -> 0.51752123 | AX10: =AX$8*$AL10 -> 0.51752123 | AY10: =AY$8*$AL10 -> 0.51752123 | AZ10: =AY10*0.2 -> 0.10350425 | BA10: =BA$8*$AL10 -> 0.45855836 | BB10: =SUMIFS(NYSERDA_SupplyProcessed[Total Capacity (MW)], NYSERDA_SupplyProcessed[Label],$R10)/1000 -> 0.8792259
A11: EWNDOFFIX | B11: Offshore Wind Fixed Bottom | C11: R1 | E11: ELCWND | F11: ELC | G11: 2035 | H11: =LifetimeAssumptions!$B$17 -> Wind | I11: =_xlfn.XLOOKUP($H11, LifetimeAssumptions[technology],LifetimeAssumptions[Discrate]) -> 0.1 | J11: =_xlfn.XLOOKUP($H11, LifetimeAssumptions[technology],LifetimeAssumptions[Lifetime]) -> 30 | K11: =1/2.8 -> 0.35714286 | L11: 31.536 | M11: 0.1 | P11: ='2023_Regional_Cost_Factor'!$A$24 -> Wind offshore | Q11: =_xlfn.XLOOKUP($P11,NewCapRegionalCosts[Technology],NewCapRegionalCosts[8 (NYCW)])*_xlfn.XLOOKUP(2022, GDP_deflator[Year],GDP_deflator[Multiply By (for $2005)]) -> 4639.0432 | R11: =SupplyCurveProcessed!$E$26 -> Offshore Wind - Fixed Bottom_Rest of State_Fixed Bottom | S11: =SupplyCurveProcessed!$E$29 -> Offshore Wind*_All_All | T11: =SUMIFS(NYSERDA_SupplyProcessed[Average Capex ($2024 / kW)],NYSERDA_SupplyProcessed[Label],$R11)/ SUMIFS(NYSERDA_SupplyProcessed[Average Capex ($2024 / kW)],NYSERDA_SupplyProcessed[Label],$S11) -> 0.8515787 | Y11: =SUMIFS(INDIRECT("NYSERDA_SupplyProcessed[CapEx Escalator_"&Y$5&"]"), NYSERDA_SupplyProcessed[Label],$R10)*$Q11*$T11 -> 4690.9773 | Z11: =SUMIFS(INDIRECT("NYSERDA_SupplyProcessed[CapEx Escalator_"&Z$5&"]"), NYSERDA_SupplyProcessed[Label],$R10)*$Q11*$T11 -> 5079.1353 | AA11: =Z11 -> 5079.1353 | AH11: =SUMIFS(NYSERDA_SupplyProcessed[OpEx (thousand $ 2024 / kW - year)], NYSERDA_SupplyProcessed[Label],$R11) *_xlfn.XLOOKUP(2023, GDP_deflator[Year],GDP_deflator[Multiply By (for $2005)]) -> 57.515215 | AI11: =SUMIFS(NYSERDA_SupplyProcessed[OpEx (thousand $ 2024 / kW - year)], NYSERDA_SupplyProcessed[Label],$R11) *_xlfn.XLOOKUP(2023, GDP_deflator[Year],GDP_deflator[Multiply By (for $2005)]) -> 57.515215 | AJ11: =SUMIFS(NYSERDA_SupplyProcessed[OpEx (thousand $ 2024 / kW - year)], NYSERDA_SupplyProcessed[Label],$R11) *_xlfn.XLOOKUP(2023, GDP_deflator[Year],GDP_deflator[Multiply By (for $2005)]) -> 57.515215 | AK11: =SUMIFS(NYSERDA_SupplyProcessed[OpEx (thousand $ 2024 / kW - year)], NYSERDA_SupplyProcessed[Label],$R11) *_xlfn.XLOOKUP(2023, GDP_deflator[Year],GDP_deflator[Multiply By (for $2005)]) -> 57.515215 | AL11: =SUMIFS(NYSERDA_SupplyProcessed[Average Capacity Factor], NYSERDA_SupplyProcessed[Label],$R11) -> 0.55383249 | AM11: =AM$8*$AL11 -> 0.66044525 | AN11: =AN$8*$AL11 -> 0.66044525 | AO11: =AO$8*$AL11 -> 0.66044525 | AP11: =AO11*0.2 -> 0.13208905 | AQ11: =AQ$8*$AL11 -> 0.52918695 | AR11: =AR$8*$AL11 -> 0.39799255 | AS11: =AS$8*$AL11 -> 0.39799255 | AT11: =AT$8*$AL11 -> 0.39799255 | AU11: =AT11*0.2 -> 0.07959851 | AV11: =AV$8*$AL11 -> 0.2909131 | AW11: =AW$8*$AL11 -> 0.7685181 | AX11: =AX$8*$AL11 -> 0.7685181 | AY11: =AY$8*$AL11 -> 0.7685181 | AZ11: =AY11*0.2 -> 0.15370362 | BA11: =BA$8*$AL11 -> 0.68095835 | BB11: =SUMIFS(NYSERDA_SupplyProcessed[Total Capacity (MW)], NYSERDA_SupplyProcessed[Label],$R11)/1000 -> 10.890375
A12: EWNDOFFIX | B12: Offshore Wind Fixed Bottom | C12: R2 | E12: ELCWND | F12: ELC | G12: 2035 | H12: =LifetimeAssumptions!$B$17 -> Wind | I12: =_xlfn.XLOOKUP($H12, LifetimeAssumptions[technology],LifetimeAssumptions[Discrate]) -> 0.1 | J12: =_xlfn.XLOOKUP($H12, LifetimeAssumptions[technology],LifetimeAssumptions[Lifetime]) -> 30 | K12: =1/2.8 -> 0.35714286 | L12: 31.536 | M12: 0.1 | P12: ='2023_Regional_Cost_Factor'!$A$24 -> Wind offshore | Q12: =_xlfn.XLOOKUP($P12,NewCapRegionalCosts[Technology],NewCapRegionalCosts[8 (NYCW)])*_xlfn.XLOOKUP(2022, GDP_deflator[Year],GDP_deflator[Multiply By (for $2005)]) -> 4639.0432 | R12: =SupplyCurveProcessed!$E$25 -> Offshore Wind - Fixed Bottom_NYC_Fixed Bottom | S12: =SupplyCurveProcessed!$E$29 -> Offshore Wind*_All_All | T12: =SUMIFS(NYSERDA_SupplyProcessed[Average Capex ($2024 / kW)],NYSERDA_SupplyProcessed[Label],$R12)/ SUMIFS(NYSERDA_SupplyProcessed[Average Capex ($2024 / kW)],NYSERDA_SupplyProcessed[Label],$S12) -> 0.887805 | Y12: =SUMIFS(INDIRECT("NYSERDA_SupplyProcessed[CapEx Escalator_"&Y$5&"]"), NYSERDA_SupplyProcessed[Label],$R11)*$Q12*$T12 -> 4047.0302 | Z12: =SUMIFS(INDIRECT("NYSERDA_SupplyProcessed[CapEx Escalator_"&Z$5&"]"), NYSERDA_SupplyProcessed[Label],$R11)*$Q12*$T12 -> 4118.5657 | AA12: =Z12 -> 4118.5657 | AH12: =SUMIFS(NYSERDA_SupplyProcessed[OpEx (thousand $ 2024 / kW - year)], NYSERDA_SupplyProcessed[Label],$R12) *_xlfn.XLOOKUP(2023, GDP_deflator[Year],GDP_deflator[Multiply By (for $2005)]) -> 58.377012 | AI12: =SUMIFS(NYSERDA_SupplyProcessed[OpEx (thousand $ 2024 / kW - year)], NYSERDA_SupplyProcessed[Label],$R12) *_xlfn.XLOOKUP(2023, GDP_deflator[Year],GDP_deflator[Multiply By (for $2005)]) -> 58.377012 | AJ12: =SUMIFS(NYSERDA_SupplyProcessed[OpEx (thousand $ 2024 / kW - year)], NYSERDA_SupplyProcessed[Label],$R12) *_xlfn.XLOOKUP(2023, GDP_deflator[Year],GDP_deflator[Multiply By (for $2005)]) -> 58.377012 | AK12: =SUMIFS(NYSERDA_SupplyProcessed[OpEx (thousand $ 2024 / kW - year)], NYSERDA_SupplyProcessed[Label],$R12) *_xlfn.XLOOKUP(2023, GDP_deflator[Year],GDP_deflator[Multiply By (for $2005)]) -> 58.377012 | AL12: =SUMIFS(NYSERDA_SupplyProcessed[Average Capacity Factor], NYSERDA_SupplyProcessed[Label],$R12) -> 0.54464272 | AM12: =AM$8*$AL12 -> 0.64948645 | AN12: =AN$8*$AL12 -> 0.64948645 | AO12: =AO$8*$AL12 -> 0.64948645 | AP12: =AO12*0.2 -> 0.12989729 | AQ12: =AQ$8*$AL12 -> 0.52040612 | AR12: =AR$8*$AL12 -> 0.39138864 | AS12: =AS$8*$AL12 -> 0.39138864 | AT12: =AT$8*$AL12 -> 0.39138864 | AU12: =AT12*0.2 -> 0.078277728 | AV12: =AV$8*$AL12 -> 0.28608597 | AW12: =AW$8*$AL12 -> 0.75576605 | AX12: =AX$8*$AL12 -> 0.75576605 | AY12: =AY$8*$AL12 -> 0.75576605 | AZ12: =AY12*0.2 -> 0.15115321 | BA12: =BA$8*$AL12 -> 0.66965918 | BB12: =SUMIFS(NYSERDA_SupplyProcessed[Total Capacity (MW)], NYSERDA_SupplyProcessed[Label],$R12)/1000 -> 4.137525
A13: EWNDOFFLT | B13: Offshore Wind Floating | C13: R2 | E13: ELCWND | F13: ELC | G13: 2040 | H13: =LifetimeAssumptions!$B$17 -> Wind | I13: =_xlfn.XLOOKUP($H13, LifetimeAssumptions[technology],LifetimeAssumptions[Discrate]) -> 0.1 | J13: =_xlfn.XLOOKUP($H13, LifetimeAssumptions[technology],LifetimeAssumptions[Lifetime]) -> 30 | K13: =1/2.8 -> 0.35714286 | L13: 31.536 | M13: 0.1 | P13: ='2023_Regional_Cost_Factor'!$A$24 -> Wind offshore | Q13: =_xlfn.XLOOKUP($P13,NewCapRegionalCosts[Technology],NewCapRegionalCosts[8 (NYCW)])*_xlfn.XLOOKUP(2022, GDP_deflator[Year],GDP_deflator[Multiply By (for $2005)]) -> 4639.0432 | R13: =SupplyCurveProcessed!$E$28 -> Offshore Wind - Floating_All_Floating | S13: =SupplyCurveProcessed!$E$29 -> Offshore Wind*_All_All | T13: =SUMIFS(NYSERDA_SupplyProcessed[Average Capex ($2024 / kW)],NYSERDA_SupplyProcessed[Label],$R13)/ SUMIFS(NYSERDA_SupplyProcessed[Average Capex ($2024 / kW)],NYSERDA_SupplyProcessed[Label],$S13) -> 1.2056606 | Z13: =SUMIFS(INDIRECT("NYSERDA_SupplyProcessed[CapEx Escalator_"&Z$5&"]"), NYSERDA_SupplyProcessed[Label],$R12)*$Q13*$T13 -> 5593.1114 | AA13: =Z13 -> 5593.1114 | AH13: =SUMIFS(NYSERDA_SupplyProcessed[OpEx (thousand $ 2024 / kW - year)], NYSERDA_SupplyProcessed[Label],$R13) *_xlfn.XLOOKUP(2023, GDP_deflator[Year],GDP_deflator[Multiply By (for $2005)]) -> 98.177309 | AI13: =SUMIFS(NYSERDA_SupplyProcessed[OpEx (thousand $ 2024 / kW - year)], NYSERDA_SupplyProcessed[Label],$R13) *_xlfn.XLOOKUP(2023, GDP_deflator[Year],GDP_deflator[Multiply By (for $2005)]) -> 98.177309 | AJ13: =SUMIFS(NYSERDA_SupplyProcessed[OpEx (thousand $ 2024 / kW - year)], NYSERDA_SupplyProcessed[Label],$R13) *_xlfn.XLOOKUP(2023, GDP_deflator[Year],GDP_deflator[Multiply By (for $2005)]) -> 98.177309 | AK13: =SUMIFS(NYSERDA_SupplyProcessed[OpEx (thousand $ 2024 / kW - year)], NYSERDA_SupplyProcessed[Label],$R13) *_xlfn.XLOOKUP(2023, GDP_deflator[Year],GDP_deflator[Multiply By (for $2005)]) -> 98.177309 | AL13: =SUMIFS(NYSERDA_SupplyProcessed[Average Capacity Factor], NYSERDA_SupplyProcessed[Label],$R13) -> 0.54586965 | AM13: =AM$8*$AL13 -> 0.65094956 | AN13: =AN$8*$AL13 -> 0.65094956 | AO13: =AO$8*$AL13 -> 0.65094956 | AP13: =AO13*0.2 -> 0.13018991 | AQ13: =AQ$8*$AL13 -> 0.52157845 | AR13: =AR$8*$AL13 -> 0.39227033 | AS13: =AS$8*$AL13 -> 0.39227033 | AT13: =AT$8*$AL13 -> 0.39227033 | AU13: =AT13*0.2 -> 0.078454066 | AV13: =AV$8*$AL13 -> 0.28673044 | AW13: =AW$8*$AL13 -> 0.75746858 | AX13: =AX$8*$AL13 -> 0.75746858 | AY13: =AY$8*$AL13 -> 0.75746858 | AZ13: =AY13*0.2 -> 0.15149372 | BA13: =BA$8*$AL13 -> 0.67116773 | BB13: =SUMIFS(NYSERDA_SupplyProcessed[Total Capacity (MW)], NYSERDA_SupplyProcessed[Label],$R13)/1000 -> 10.11654

Sheet TechData_Hydro
A1: _GLOBAL,R0,R1,R2,R3,R4,R5,R6 | D1: Placeholder
E3: ~FI_T
A4: TechName | B4: *TechDesc | C4: *Units | D4: CommIN | E4: CommOUT | F4: NCAP_START | G4: NCAP_TLIFE | H4: EFF | I4: PRC_CAPACT | J4: NCAP_FOM | K4: ACT_COST | L4: NCAP_COST | M4: Peak | N4: NCAP_AF | O4: NCAP_DRATE | P4: NCAP_BND~UP | Q4: NCAP_AFC | S4: Region | T4: ACT_BND~UP~2010 | U4: ACT_BND~UP~2015 | V4: ACT_BND~UP~2020 | W4: ACT_BND~UP~2025 | X4: ACT_BND~UP~2030 | Y4: ACT_BND~UP~2035 | Z4: ACT_BND~UP~2040 | AA4: ACT_BND~UP~2045 | AB4: ACT_BND~UP~2050 | AC4: ACT_BND~UP~2055 | AE4: Input | AF4: Output_elc
A5: *R1 Conversion Tech RESIDS | B5: conventional_hydro | S5: *R1 Conversion Tech RESIDS
A6: EHYDCONR11 | B6: Hydroelectric, Conventional | C6: PJ, GW | D6: ELCHYD | E6: ELC | F6: 2011 | G6: 120 | H6: =AF6/AE6 -> 0.35714286 | I6: 31.536 | J6: 32.235796 | K6: 0 | L6: 6518.0571 | M6: 0.95 | N6: 0.9 | O6: 0.11 | S6: R1 | V6: 254 | X6: 230 | AE6: 2.8 | AF6: 1
E9: ~FI_T
A10: TechName | B10: *TechDesc | C10: *Units | D10: CommIN | E10: CommOUT | F10: NCAP_START | G10: NCAP_TLIFE | H10: STG_EFF | I10: EFF | J10: PRC_CAPACT | K10: NCAP_FOM | L10: ACT_COST | M10: NCAP_COST | N10: Peak | O10: NCAP_DRATE | P10: NCAP_BND~UP | Q10: NCAP_AF | R10: NCAP_AFC | S10: Region | T10: ACT_BND~UP~2010 | U10: ACT_BND~UP~2015 | V10: ACT_BND~UP~2020 | W10: ACT_BND~UP~2025 | X10: ACT_BND~UP~2030 | Y10: ACT_BND~UP~2035 | Z10: ACT_BND~UP~2040 | AA10: ACT_BND~UP~2045 | AB10: ACT_BND~UP~2050 | AC10: ACT_BND~UP~2055 | AE10: Input | AF10: Output_elc
A11: * | B11: reversible_hydro
A12: SHYDREVRIN11 | B12: Hydroelectric, Reversible | C12: PJ, GW | D12: ELC | E12: HYDELC | F12: 2011 | G12: 45 | H12: 1 | J12: 31.536 | O12: 0.11 | R12: =12/24 -> 0.5 | S12: R1 | V12: =4.01*0.9 -> 3.609 | X12: =20.05*0.9 -> 18.045 | AE12: 1 | AF12: 0.8
A13: EHYDREVROUT11 | B13: Hydroelectric, Reversible | C13: PJ, GW | D13: HYDELC | E13: ELC | F13: 2011 | G13: 45 | I13: =AF13/AE13 -> 0.8 | J13: 31.536 | K13: 32.235796 | L13: 0 | M13: =L6 -> 6518.0571 | N13: 0.9 | O13: 0.11 | Q13: =R12 -> 0.5 | S13: R1 | V13: =4.01*0.9 -> 3.609 | X13: =20.05*0.9 -> 18.045 | AE13: 1 | AF13: 0.8

Sheet LifetimeAssumptions
B1: lifetime_assumptions | Q1: Hurdle rate modifiers
B2: For resids and new | F2: New | G2: Existing | H2: CO2 capture | I2: Start year | K2: Application of hurdle rate increments?
B3: technology | C3: AF | D3: Peak (con) | E3: Discrate | F3: Lifetime | G3: Lifetime2 | H3: Rate | K3: High CO2? | L3: New/unproven? | M3: Combo new/unproven? | N3: Infrastructure? | O3: Public/private hesitency? | Q3: Base value | T3: 0.1
B4: Coal boilers | C4: 0.85 | D4: 0.95 | E4: =$T$3+K4*$T$7+L4*$T$8+M4*$T$9+N4*$T$10+O4*$T$11 -> 0.2 | F4: 40 | G4: 50 | K4: 1
B5: Coal life extension | E5: =$T$3+K5*$T$7+L5*$T$8+M5*$T$9+N5*$T$10+O5*$T$11 -> 0.1 | F5: 50 | I5: 50 yr lifetime selected via calibration | T5: Incremental
B6: Gas boilers | C6: 0.9 | D6: 0.95 | E6: =$T$3+K6*$T$7+L6*$T$8+M6*$T$9+N6*$T$10+O6*$T$11 -> 0.15 | F6: 40 | G6: 50 | K6: 0.5 | Q6: Factors impacting hurdle rate | T6: Penalty
B7: Existing Gas & oil turbines | C7: 0.9 | D7: 0.95 | E7: =$T$3+K7*$T$7+L7*$T$8+M7*$T$9+N7*$T$10+O7*$T$11 -> 0.15 | F7: 50 | G7: 50 | K7: 0.5 | Q7: High CO2 emissions | T7: 0.1
B8: New Gas & oil turbines | C8: 0.9 | D8: 0.95 | E8: =$T$3+K8*$T$7+L8*$T$8+M8*$T$9+N8*$T$10+O8*$T$11 -> 0.15 | F8: 30 | G8: 50 | K8: 0.5 | Q8: New or unproven technology | T8: 0.1
B9: Geothermal | C9: 0.9 | D9: 0.9 | E9: =$T$3+K9*$T$7+L9*$T$8+M9*$T$9+N9*$T$10+O9*$T$11 -> 0.1 | F9: 30 | G9: 40 | Q9: Combo of new/unproven techs | T9: 0.1
B10: Hydro | D10: 0.95 | E10: =$T$3+K10*$T$7+L10*$T$8+M10*$T$9+N10*$T$10+O10*$T$11 -> 0.1 | F10: 50 | G10: 120 | Q10: Additional infrastructure needed | T10: 0.025
B11: Reversible hydro | E11: =$T$3+K11*$T$7+L11*$T$8+M11*$T$9+N11*$T$10+O11*$T$11 -> 0.1 | F11: 40 | G11: 40 | Q11: Public/private hesitency associated with risk | T11: 0.15
B12: Battery Storage | D12: 0.5 | E12: =$T$3+K12*$T$7+L12*$T$8+M12*$T$9+N12*$T$10+O12*$T$11 -> 0.1 | F12: 15
B13: Nuclear | C13: 0.9 | D13: 0.95 | E13: =$T$3+K13*$T$7+L13*$T$8+M13*$T$9+N13*$T$10+O13*$T$11 -> 0.25 | F13: 30 | G13: 50 | O13: 1
B14: 40-yr Nuclear life extension | C14: 0.9 | D14: 0.95 | E14: =$T$3+K14*$T$7+L14*$T$8+M14*$T$9+N14*$T$10+O14*$T$11 -> 0.1 | F14: 40 | G14: 40
B15: Solar PV | D15: 0.5 | E15: =$T$3+K15*$T$7+L15*$T$8+M15*$T$9+N15*$T$10+O15*$T$11 -> 0.1 | F15: 30 | G15: 30
B16: Solar Thermal | C16: 0.5 | D16: 0.75 | E16: =$T$3+K16*$T$7+L16*$T$8+M16*$T$9+N16*$T$10+O16*$T$11 -> 0.1 | F16: 30 | G16: 30
B17: Wind | D17: 0.55 | E17: =$T$3+K17*$T$7+L17*$T$8+M17*$T$9+N17*$T$10+O17*$T$11 -> 0.1 | F17: 30 | G17: 30
B18: MSW & LFG | C18: 0.9 | D18: 0.25 | E18: =$T$3+K18*$T$7+L18*$T$8+M18*$T$9+N18*$T$10+O18*$T$11 -> 0.1 | F18: 30 | G18: 30
B19: CHP | C19: 0.9 | D19: 0.95 | E19: =$T$3+K19*$T$7+L19*$T$8+M19*$T$9+N19*$T$10+O19*$T$11 -> 0.125 | F19: 30 | G19: 40 | N19: 1
B20: Coal CCS retrofit | E20: =$T$3+K20*$T$7+L20*$T$8+M20*$T$9+N20*$T$10+O20*$T$11 -> 0.2 | F20: 30 | H20: 0.9 | I20: 2020 | L20: 1
B21: Gas CCS retrofit | E21: =$T$3+K21*$T$7+L21*$T$8+M21*$T$9+N21*$T$10+O21*$T$11 -> 0.2 | F21: 30 | H21: 0.85 | I21: 2025 | L21: 1
B22: IGCC-CCS | C22: 0.9 | D22: 0.9 | E22: =$T$3+K22*$T$7+L22*$T$8+M22*$T$9+N22*$T$10+O22*$T$11 -> 0.3 | F22: 30 | H22: 0.9 | I22: 2025 | L22: 1 | M22: 1
B23: NGA-CCS | C23: 0.9 | D23: 0.9 | E23: =$T$3+K23*$T$7+L23*$T$8+M23*$T$9+N23*$T$10+O23*$T$11 -> 0.2 | F23: 30 | H23: 0.85 | I23: 2025 | L23: 1
B24: IGCC | E24: =$T$3+K24*$T$7+L24*$T$8+M24*$T$9+N24*$T$10+O24*$T$11 -> 0.2 | F24: 30 | I24: 2020 | L24: 1
B25: BioIGCC | E25: =$T$3+K25*$T$7+L25*$T$8+M25*$T$9+N25*$T$10+O25*$T$11 -> 0.2 | F25: 30 | I25: 2025 | L25: 1
B26: BioIGCC-CCS | C26: 0.85 | D26: 0.85 | E26: =$T$3+K26*$T$7+L26*$T$8+M26*$T$9+N26*$T$10+O26*$T$11 -> 0.3 | F26: 30 | H26: 0.85 | I26: 2030 | L26: 1 | M26: 1
B27: Other coal egu retrofits | E27: =$T$3+K27*$T$7+L27*$T$8+M27*$T$9+N27*$T$10+O27*$T$11 -> 0.1 | F27: 30
D29: Fraction | E29: Orig value
B30: Cost multiplier for retrofit CCS | D30: 1.25 | E30: 1.1

Sheet SupplyCurveProcessed
C14: Region | D14: CapEx_Lookup | E14: Label | F14: Technology_Lookup | G14: Zone | H14: CapEx Bin | I14: Total Capacity (MW) | J14: Average Capex ($2024 / kW) | K14: OpEx (thousand $ 2024 / kW - year) | L14: Average Capacity Factor | M14: CapEx Escalator_2024 | N14: CapEx Escalator_2025 | O14: CapEx Escalator_2026 | P14: CapEx Escalator_2027 | Q14: CapEx Escalator_2028 | R14: CapEx Escalator_2029 | S14: CapEx Escalator_2030 | T14: CapEx Escalator_2031 | U14: CapEx Escalator_2032 | V14: CapEx Escalator_2033 | W14: CapEx Escalator_2034 | X14: CapEx Escalator_2035 | Y14: CapEx Escalator_2036 | Z14: CapEx Escalator_2037 | AA14: CapEx Escalator_2038 | AB14: CapEx Escalator_2039 | AC14: CapEx Escalator_2040
C15: NYC | D15: Low Cost | E15: =NYSERDA_SupplyProcessed[[#This Row],[Technology_Lookup]]&"_"&NYSERDA_SupplyProcessed[[#This Row],[Region]]&"_"&NYSERDA_SupplyProcessed[[#This Row],[CapEx_Lookup]] -> Land-based Wind_NYC_Low Cost | F15: Land-based Wind | G15: J | H15: {=_xlfn.IFS(NYSERDA_SupplyProcessed[[#This Row],[CapEx_Lookup]]="Low Cost","Low Cost",NYSERDA_SupplyProcessed[[#This Row],[CapEx_Lookup]]="High Cost","High Cost",TRUE, "*")} -> Low Cost | I15: =SUMIFS(NYSERDA_SupplyCurve_Raw[Available Capacity (MWac)],NYSERDA_SupplyCurve_Raw[Interconnection Zone],$G15,NYSERDA_SupplyCurve_Raw[CapEx Bin],$H15,NYSERDA_SupplyCurve_Raw[Technology Type],$F15) -> 0 | J15: =IF($I15>0,SUMIFS(NYSERDA_SupplyCurve_Raw[Total Capex Cost (thousand $)],NYSERDA_SupplyCurve_Raw[Interconnection Zone],$G15,NYSERDA_SupplyCurve_Raw[CapEx Bin],$H15,NYSERDA_SupplyCurve_Raw[Technology Type],$F15)/$I15,"") | K15: =IF($I15>0,SUMIFS(NYSERDA_SupplyCurve_Raw[Total OpEx Cost (thousand $ / kW- year)],NYSERDA_SupplyCurve_Raw[Interconnection Zone],$G15,NYSERDA_SupplyCurve_Raw[CapEx Bin],$H15,NYSERDA_SupplyCurve_Raw[Technology Type],$F15)/$I15,"") | L15: =IF($I15>0,SUMIFS(NYSERDA_SupplyCurve_Raw[Avg OpEx x Total Generation],NYSERDA_SupplyCurve_Raw[Interconnection Zone],$G15,NYSERDA_SupplyCurve_Raw[CapEx Bin],$H15,NYSERDA_SupplyCurve_Raw[Technology Type],$F15)/$I15,"") | M15: =IFERROR(AVERAGEIFS(INDIRECT("NYSERDA_SupplyCurve_Raw[Resource "&M$14&"]"), NYSERDA_SupplyCurve_Raw[Interconnection Zone],$G15,NYSERDA_SupplyCurve_Raw[CapEx Bin],$H15,NYSERDA_SupplyCurve_Raw[Technology Type],$F15),"") | N15: =IFERROR(AVERAGEIFS(INDIRECT("NYSERDA_SupplyCurve_Raw[Resource "&N$14&"]"), NYSERDA_SupplyCurve_Raw[Interconnection Zone],$G15,NYSERDA_SupplyCurve_Raw[CapEx Bin],$H15,NYSERDA_SupplyCurve_Raw[Technology Type],$F15),"") | O15: =IFERROR(AVERAGEIFS(INDIRECT("NYSERDA_SupplyCurve_Raw[Resource "&O$14&"]"), NYSERDA_SupplyCurve_Raw[Interconnection Zone],$G15,NYSERDA_SupplyCurve_Raw[CapEx Bin],$H15,NYSERDA_SupplyCurve_Raw[Technology Type],$F15),"") | P15: =IFERROR(AVERAGEIFS(INDIRECT("NYSERDA_SupplyCurve_Raw[Resource "&P$14&"]"), NYSERDA_SupplyCurve_Raw[Interconnection Zone],$G15,NYSERDA_SupplyCurve_Raw[CapEx Bin],$H15,NYSERDA_SupplyCurve_Raw[Technology Type],$F15),"") | Q15: =IFERROR(AVERAGEIFS(INDIRECT("NYSERDA_SupplyCurve_Raw[Resource "&Q$14&"]"), NYSERDA_SupplyCurve_Raw[Interconnection Zone],$G15,NYSERDA_SupplyCurve_Raw[CapEx Bin],$H15,NYSERDA_SupplyCurve_Raw[Technology Type],$F15),"") | R15: =IFERROR(AVERAGEIFS(INDIRECT("NYSERDA_SupplyCurve_Raw[Resource "&R$14&"]"), NYSERDA_SupplyCurve_Raw[Interconnection Zone],$G15,NYSERDA_SupplyCurve_Raw[CapEx Bin],$H15,NYSERDA_SupplyCurve_Raw[Technology Type],$F15),"") | S15: =IFERROR(AVERAGEIFS(INDIRECT("NYSERDA_SupplyCurve_Raw[Resource "&S$14&"]"), NYSERDA_SupplyCurve_Raw[Interconnection Zone],$G15,NYSERDA_SupplyCurve_Raw[CapEx Bin],$H15,NYSERDA_SupplyCurve_Raw[Technology Type],$F15),"") | T15: =IFERROR(AVERAGEIFS(INDIRECT("NYSERDA_SupplyCurve_Raw[Resource "&T$14&"]"), NYSERDA_SupplyCurve_Raw[Interconnection Zone],$G15,NYSERDA_SupplyCurve_Raw[CapEx Bin],$H15,NYSERDA_SupplyCurve_Raw[Technology Type],$F15),"") | ... AC15: =IFERROR(AVERAGEIFS(INDIRECT("NYSERDA_SupplyCurve_Raw[Resource "&AC$14&"]"), NYSERDA_SupplyCurve_Raw[Interconnection Zone],$G15,NYSERDA_SupplyCurve_Raw[CapEx Bin],$H15,NYSERDA_SupplyCurve_Raw[Technology Type],$F15),"")
C16: Rest of State | D16: Low Cost | E16: =NYSERDA_SupplyProcessed[[#This Row],[Technology_Lookup]]&"_"&NYSERDA_SupplyProcessed[[#This Row],[Region]]&"_"&NYSERDA_SupplyProcessed[[#This Row],[CapEx_Lookup]] -> Land-based Wind_Rest of State_Low Cost | F16: Land-based Wind | G16: <>J | H16: Low Cost | I16: =SUMIFS(NYSERDA_SupplyCurve_Raw[Available Capacity (MWac)],NYSERDA_SupplyCurve_Raw[Interconnection Zone],$G16,NYSERDA_SupplyCurve_Raw[CapEx Bin],$H16,NYSERDA_SupplyCurve_Raw[Technology Type],$F16) -> 11060.268 | J16: =IF($I16>0,SUMIFS(NYSERDA_SupplyCurve_Raw[Total Capex Cost (thousand $)],NYSERDA_SupplyCurve_Raw[Interconnection Zone],$G16,NYSERDA_SupplyCurve_Raw[CapEx Bin],$H16,NYSERDA_SupplyCurve_Raw[Technology Type],$F16)/$I16,"") -> 2554.0769 | K16: =IF($I16>0,SUMIFS(NYSERDA_SupplyCurve_Raw[Total OpEx Cost (thousand $ / kW- year)],NYSERDA_SupplyCurve_Raw[Interconnection Zone],$G16,NYSERDA_SupplyCurve_Raw[CapEx Bin],$H16,NYSERDA_SupplyCurve_Raw[Technology Type],$F16)/$I16,"") -> 56.880682 | L16: =IF($I16>0,SUMIFS(NYSERDA_SupplyCurve_Raw[Avg OpEx x Total Generation],NYSERDA_SupplyCurve_Raw[Interconnection Zone],$G16,NYSERDA_SupplyCurve_Raw[CapEx Bin],$H16,NYSERDA_SupplyCurve_Raw[Technology Type],$F16)/$I16,"") -> 0.35832433 | M16: =IFERROR(AVERAGEIFS(INDIRECT("NYSERDA_SupplyCurve_Raw[Resource "&M$14&"]"), NYSERDA_SupplyCurve_Raw[Interconnection Zone],$G16,NYSERDA_SupplyCurve_Raw[CapEx Bin],$H16,NYSERDA_SupplyCurve_Raw[Technology Type],$F16),"") -> 1 | N16: =IFERROR(AVERAGEIFS(INDIRECT("NYSERDA_SupplyCurve_Raw[Resource "&N$14&"]"), NYSERDA_SupplyCurve_Raw[Interconnection Zone],$G16,NYSERDA_SupplyCurve_Raw[CapEx Bin],$H16,NYSERDA_SupplyCurve_Raw[Technology Type],$F16),"") -> 1.023 | O16: =IFERROR(AVERAGEIFS(INDIRECT("NYSERDA_SupplyCurve_Raw[Resource "&O$14&"]"), NYSERDA_SupplyCurve_Raw[Interconnection Zone],$G16,NYSERDA_SupplyCurve_Raw[CapEx Bin],$H16,NYSERDA_SupplyCurve_Raw[Technology Type],$F16),"") -> 1.046529 | P16: =IFERROR(AVERAGEIFS(INDIRECT("NYSERDA_SupplyCurve_Raw[Resource "&P$14&"]"), NYSERDA_SupplyCurve_Raw[Interconnection Zone],$G16,NYSERDA_SupplyCurve_Raw[CapEx Bin],$H16,NYSERDA_SupplyCurve_Raw[Technology Type],$F16),"") -> 1.0598021 | Q16: =IFERROR(AVERAGEIFS(INDIRECT("NYSERDA_SupplyCurve_Raw[Resource "&Q$14&"]"), NYSERDA_SupplyCurve_Raw[Interconnection Zone],$G16,NYSERDA_SupplyCurve_Raw[CapEx Bin],$H16,NYSERDA_SupplyCurve_Raw[Technology Type],$F16),"") -> 1.0736988 | R16: =IFERROR(AVERAGEIFS(INDIRECT("NYSERDA_SupplyCurve_Raw[Resource "&R$14&"]"), NYSERDA_SupplyCurve_Raw[Interconnection Zone],$G16,NYSERDA_SupplyCurve_Raw[CapEx Bin],$H16,NYSERDA_SupplyCurve_Raw[Technology Type],$F16),"") -> 1.0882033 | S16: =IFERROR(AVERAGEIFS(INDIRECT("NYSERDA_SupplyCurve_Raw[Resource "&S$14&"]"), NYSERDA_SupplyCurve_Raw[Interconnection Zone],$G16,NYSERDA_SupplyCurve_Raw[CapEx Bin],$H16,NYSERDA_SupplyCurve_Raw[Technology Type],$F16),"") -> 1.1033026 | T16: =IFERROR(AVERAGEIFS(INDIRECT("NYSERDA_SupplyCurve_Raw[Resource "&T$14&"]"), NYSERDA_SupplyCurve_Raw[Interconnection Zone],$G16,NYSERDA_SupplyCurve_Raw[CapEx Bin],$H16,NYSERDA_SupplyCurve_Raw[Technology Type],$F16),"") -> 1.1189864 | ... AC16: =IFERROR(AVERAGEIFS(INDIRECT("NYSERDA_SupplyCurve_Raw[Resource "&AC$14&"]"), NYSERDA_SupplyCurve_Raw[Interconnection Zone],$G16,NYSERDA_SupplyCurve_Raw[CapEx Bin],$H16,NYSERDA_SupplyCurve_Raw[Technology Type],$F16),"") -> 1.2856909
C17: Rest of State | D17: All | E17: =NYSERDA_SupplyProcessed[[#This Row],[Technology_Lookup]]&"_"&NYSERDA_SupplyProcessed[[#This Row],[Region]]&"_"&NYSERDA_SupplyProcessed[[#This Row],[CapEx_Lookup]] -> Land-based Wind_Rest of State_All | F17: Land-based Wind | G17: <>J | H17: * | I17: =SUMIFS(NYSERDA_SupplyCurve_Raw[Available Capacity (MWac)],NYSERDA_SupplyCurve_Raw[Interconnection Zone],$G17,NYSERDA_SupplyCurve_Raw[CapEx Bin],$H17,NYSERDA_SupplyCurve_Raw[Technology Type],$F17) -> 11939.494 | J17: =IF($I17>0,SUMIFS(NYSERDA_SupplyCurve_Raw[Total Capex Cost (thousand $)],NYSERDA_SupplyCurve_Raw[Interconnection Zone],$G17,NYSERDA_SupplyCurve_Raw[CapEx Bin],$H17,NYSERDA_SupplyCurve_Raw[Technology Type],$F17)/$I17,"") -> 2586.8263 | K17: =IF($I17>0,SUMIFS(NYSERDA_SupplyCurve_Raw[Total OpEx Cost (thousand $ / kW- year)],NYSERDA_SupplyCurve_Raw[Interconnection Zone],$G17,NYSERDA_SupplyCurve_Raw[CapEx Bin],$H17,NYSERDA_SupplyCurve_Raw[Technology Type],$F17)/$I17,"") -> 56.900569 | L17: =IF($I17>0,SUMIFS(NYSERDA_SupplyCurve_Raw[Avg OpEx x Total Generation],NYSERDA_SupplyCurve_Raw[Interconnection Zone],$G17,NYSERDA_SupplyCurve_Raw[CapEx Bin],$H17,NYSERDA_SupplyCurve_Raw[Technology Type],$F17)/$I17,"") -> 0.35940149 | M17: =IFERROR(AVERAGEIFS(INDIRECT("NYSERDA_SupplyCurve_Raw[Resource "&M$14&"]"), NYSERDA_SupplyCurve_Raw[Interconnection Zone],$G17,NYSERDA_SupplyCurve_Raw[CapEx Bin],$H17,NYSERDA_SupplyCurve_Raw[Technology Type],$F17),"") -> 1 | N17: =IFERROR(AVERAGEIFS(INDIRECT("NYSERDA_SupplyCurve_Raw[Resource "&N$14&"]"), NYSERDA_SupplyCurve_Raw[Interconnection Zone],$G17,NYSERDA_SupplyCurve_Raw[CapEx Bin],$H17,NYSERDA_SupplyCurve_Raw[Technology Type],$F17),"") -> 1.023 | O17: =IFERROR(AVERAGEIFS(INDIRECT("NYSERDA_SupplyCurve_Raw[Resource "&O$14&"]"), NYSERDA_SupplyCurve_Raw[Interconnection Zone],$G17,NYSERDA_SupplyCurve_Raw[CapEx Bin],$H17,NYSERDA_SupplyCurve_Raw[Technology Type],$F17),"") -> 1.046529 | P17: =IFERROR(AVERAGEIFS(INDIRECT("NYSERDA_SupplyCurve_Raw[Resource "&P$14&"]"), NYSERDA_SupplyCurve_Raw[Interconnection Zone],$G17,NYSERDA_SupplyCurve_Raw[CapEx Bin],$H17,NYSERDA_SupplyCurve_Raw[Technology Type],$F17),"") -> 1.0598021 | Q17: =IFERROR(AVERAGEIFS(INDIRECT("NYSERDA_SupplyCurve_Raw[Resource "&Q$14&"]"), NYSERDA_SupplyCurve_Raw[Interconnection Zone],$G17,NYSERDA_SupplyCurve_Raw[CapEx Bin],$H17,NYSERDA_SupplyCurve_Raw[Technology Type],$F17),"") -> 1.0736988 | R17: =IFERROR(AVERAGEIFS(INDIRECT("NYSERDA_SupplyCurve_Raw[Resource "&R$14&"]"), NYSERDA_SupplyCurve_Raw[Interconnection Zone],$G17,NYSERDA_SupplyCurve_Raw[CapEx Bin],$H17,NYSERDA_SupplyCurve_Raw[Technology Type],$F17),"") -> 1.0882033 | S17: =IFERROR(AVERAGEIFS(INDIRECT("NYSERDA_SupplyCurve_Raw[Resource "&S$14&"]"), NYSERDA_SupplyCurve_Raw[Interconnection Zone],$G17,NYSERDA_SupplyCurve_Raw[CapEx Bin],$H17,NYSERDA_SupplyCurve_Raw[Technology Type],$F17),"") -> 1.1033026 | T17: =IFERROR(AVERAGEIFS(INDIRECT("NYSERDA_SupplyCurve_Raw[Resource "&T$14&"]"), NYSERDA_SupplyCurve_Raw[Interconnection Zone],$G17,NYSERDA_SupplyCurve_Raw[CapEx Bin],$H17,NYSERDA_SupplyCurve_Raw[Technology Type],$F17),"") -> 1.1189864 | ... AC17: =IFERROR(AVERAGEIFS(INDIRECT("NYSERDA_SupplyCurve_Raw[Resource "&AC$14&"]"), NYSERDA_SupplyCurve_Raw[Interconnection Zone],$G17,NYSERDA_SupplyCurve_Raw[CapEx Bin],$H17,NYSERDA_SupplyCurve_Raw[Technology Type],$F17),"") -> 1.2856909
C18: NYC | D18: High Cost | E18: =NYSERDA_SupplyProcessed[[#This Row],[Technology_Lookup]]&"_"&NYSERDA_SupplyProcessed[[#This Row],[Region]]&"_"&NYSERDA_SupplyProcessed[[#This Row],[CapEx_Lookup]] -> Land-based Wind_NYC_High Cost | F18: Land-based Wind | G18: J | H18: High Cost | I18: =SUMIFS(NYSERDA_SupplyCurve_Raw[Available Capacity (MWac)],NYSERDA_SupplyCurve_Raw[Interconnection Zone],$G18,NYSERDA_SupplyCurve_Raw[CapEx Bin],$H18,NYSERDA_SupplyCurve_Raw[Technology Type],$F18) -> 0 | J18: =IF($I18>0,SUMIFS(NYSERDA_SupplyCurve_Raw[Total Capex Cost (thousand $)],NYSERDA_SupplyCurve_Raw[Interconnection Zone],$G18,NYSERDA_SupplyCurve_Raw[CapEx Bin],$H18,NYSERDA_SupplyCurve_Raw[Technology Type],$F18)/$I18,"") | K18: =IF($I18>0,SUMIFS(NYSERDA_SupplyCurve_Raw[Total OpEx Cost (thousand $ / kW- year)],NYSERDA_SupplyCurve_Raw[Interconnection Zone],$G18,NYSERDA_SupplyCurve_Raw[CapEx Bin],$H18,NYSERDA_SupplyCurve_Raw[Technology Type],$F18)/$I18,"") | L18: =IF($I18>0,SUMIFS(NYSERDA_SupplyCurve_Raw[Avg OpEx x Total Generation],NYSERDA_SupplyCurve_Raw[Interconnection Zone],$G18,NYSERDA_SupplyCurve_Raw[CapEx Bin],$H18,NYSERDA_SupplyCurve_Raw[Technology Type],$F18)/$I18,"") | M18: =IFERROR(AVERAGEIFS(INDIRECT("NYSERDA_SupplyCurve_Raw[Resource "&M$14&"]"), NYSERDA_SupplyCurve_Raw[Interconnection Zone],$G18,NYSERDA_SupplyCurve_Raw[CapEx Bin],$H18,NYSERDA_SupplyCurve_Raw[Technology Type],$F18),"") | N18: =IFERROR(AVERAGEIFS(INDIRECT("NYSERDA_SupplyCurve_Raw[Resource "&N$14&"]"), NYSERDA_SupplyCurve_Raw[Interconnection Zone],$G18,NYSERDA_SupplyCurve_Raw[CapEx Bin],$H18,NYSERDA_SupplyCurve_Raw[Technology Type],$F18),"") | O18: =IFERROR(AVERAGEIFS(INDIRECT("NYSERDA_SupplyCurve_Raw[Resource "&O$14&"]"), NYSERDA_SupplyCurve_Raw[Interconnection Zone],$G18,NYSERDA_SupplyCurve_Raw[CapEx Bin],$H18,NYSERDA_SupplyCurve_Raw[Technology Type],$F18),"") | P18: =IFERROR(AVERAGEIFS(INDIRECT("NYSERDA_SupplyCurve_Raw[Resource "&P$14&"]"), NYSERDA_SupplyCurve_Raw[Interconnection Zone],$G18,NYSERDA_SupplyCurve_Raw[CapEx Bin],$H18,NYSERDA_SupplyCurve_Raw[Technology Type],$F18),"") | Q18: =IFERROR(AVERAGEIFS(INDIRECT("NYSERDA_SupplyCurve_Raw[Resource "&Q$14&"]"), NYSERDA_SupplyCurve_Raw[Interconnection Zone],$G18,NYSERDA_SupplyCurve_Raw[CapEx Bin],$H18,NYSERDA_SupplyCurve_Raw[Technology Type],$F18),"") | R18: =IFERROR(AVERAGEIFS(INDIRECT("NYSERDA_SupplyCurve_Raw[Resource "&R$14&"]"), NYSERDA_SupplyCurve_Raw[Interconnection Zone],$G18,NYSERDA_SupplyCurve_Raw[CapEx Bin],$H18,NYSERDA_SupplyCurve_Raw[Technology Type],$F18),"") | S18: =IFERROR(AVERAGEIFS(INDIRECT("NYSERDA_SupplyCurve_Raw[Resource "&S$14&"]"), NYSERDA_SupplyCurve_Raw[Interconnection Zone],$G18,NYSERDA_SupplyCurve_Raw[CapEx Bin],$H18,NYSERDA_SupplyCurve_Raw[Technology Type],$F18),"") | T18: =IFERROR(AVERAGEIFS(INDIRECT("NYSERDA_SupplyCurve_Raw[Resource "&T$14&"]"), NYSERDA_SupplyCurve_Raw[Interconnection Zone],$G18,NYSERDA_SupplyCurve_Raw[CapEx Bin],$H18,NYSERDA_SupplyCurve_Raw[Technology Type],$F18),"") | ... AC18: =IFERROR(AVERAGEIFS(INDIRECT("NYSERDA_SupplyCurve_Raw[Resource "&AC$14&"]"), NYSERDA_SupplyCurve_Raw[Interconnection Zone],$G18,NYSERDA_SupplyCurve_Raw[CapEx Bin],$H18,NYSERDA_SupplyCurve_Raw[Technology Type],$F18),"")
C19: Rest of State | D19: High Cost | E19: =NYSERDA_SupplyProcessed[[#This Row],[Technology_Lookup]]&"_"&NYSERDA_SupplyProcessed[[#This Row],[Region]]&"_"&NYSERDA_SupplyProcessed[[#This Row],[CapEx_Lookup]] -> Land-based Wind_Rest of State_High Cost | F19: Land-based Wind | G19: <>J | H19: High Cost | I19: =SUMIFS(NYSERDA_SupplyCurve_Raw[Available Capacity (MWac)],NYSERDA_SupplyCurve_Raw[Interconnection Zone],$G19,NYSERDA_SupplyCurve_Raw[CapEx Bin],$H19,NYSERDA_SupplyCurve_Raw[Technology Type],$F19) -> 879.2259 | J19: =IF($I19>0,SUMIFS(NYSERDA_SupplyCurve_Raw[Total Capex Cost (thousand $)],NYSERDA_SupplyCurve_Raw[Interconnection Zone],$G19,NYSERDA_SupplyCurve_Raw[CapEx Bin],$H19,NYSERDA_SupplyCurve_Raw[Technology Type],$F19)/$I19,"") -> 2998.7985 | K19: =IF($I19>0,SUMIFS(NYSERDA_SupplyCurve_Raw[Total OpEx Cost (thousand $ / kW- year)],NYSERDA_SupplyCurve_Raw[Interconnection Zone],$G19,NYSERDA_SupplyCurve_Raw[CapEx Bin],$H19,NYSERDA_SupplyCurve_Raw[Technology Type],$F19)/$I19,"") -> 57.150742 | L19: =IF($I19>0,SUMIFS(NYSERDA_SupplyCurve_Raw[Avg OpEx x Total Generation],NYSERDA_SupplyCurve_Raw[Interconnection Zone],$G19,NYSERDA_SupplyCurve_Raw[CapEx Bin],$H19,NYSERDA_SupplyCurve_Raw[Technology Type],$F19)/$I19,"") -> 0.37295162 | M19: =IFERROR(AVERAGEIFS(INDIRECT("NYSERDA_SupplyCurve_Raw[Resource "&M$14&"]"), NYSERDA_SupplyCurve_Raw[Interconnection Zone],$G19,NYSERDA_SupplyCurve_Raw[CapEx Bin],$H19,NYSERDA_SupplyCurve_Raw[Technology Type],$F19),"") -> 1 | N19: =IFERROR(AVERAGEIFS(INDIRECT("NYSERDA_SupplyCurve_Raw[Resource "&N$14&"]"), NYSERDA_SupplyCurve_Raw[Interconnection Zone],$G19,NYSERDA_SupplyCurve_Raw[CapEx Bin],$H19,NYSERDA_SupplyCurve_Raw[Technology Type],$F19),"") -> 1.023 | O19: =IFERROR(AVERAGEIFS(INDIRECT("NYSERDA_SupplyCurve_Raw[Resource "&O$14&"]"), NYSERDA_SupplyCurve_Raw[Interconnection Zone],$G19,NYSERDA_SupplyCurve_Raw[CapEx Bin],$H19,NYSERDA_SupplyCurve_Raw[Technology Type],$F19),"") -> 1.046529 | P19: =IFERROR(AVERAGEIFS(INDIRECT("NYSERDA_SupplyCurve_Raw[Resource "&P$14&"]"), NYSERDA_SupplyCurve_Raw[Interconnection Zone],$G19,NYSERDA_SupplyCurve_Raw[CapEx Bin],$H19,NYSERDA_SupplyCurve_Raw[Technology Type],$F19),"") -> 1.0598021 | Q19: =IFERROR(AVERAGEIFS(INDIRECT("NYSERDA_SupplyCurve_Raw[Resource "&Q$14&"]"), NYSERDA_SupplyCurve_Raw[Interconnection Zone],$G19,NYSERDA_SupplyCurve_Raw[CapEx Bin],$H19,NYSERDA_SupplyCurve_Raw[Technology Type],$F19),"") -> 1.0736988 | R19: =IFERROR(AVERAGEIFS(INDIRECT("NYSERDA_SupplyCurve_Raw[Resource "&R$14&"]"), NYSERDA_SupplyCurve_Raw[Interconnection Zone],$G19,NYSERDA_SupplyCurve_Raw[CapEx Bin],$H19,NYSERDA_SupplyCurve_Raw[Technology Type],$F19),"") -> 1.0882033 | S19: =IFERROR(AVERAGEIFS(INDIRECT("NYSERDA_SupplyCurve_Raw[Resource "&S$14&"]"), NYSERDA_SupplyCurve_Raw[Interconnection Zone],$G19,NYSERDA_SupplyCurve_Raw[CapEx Bin],$H19,NYSERDA_SupplyCurve_Raw[Technology Type],$F19),"") -> 1.1033026 | T19: =IFERROR(AVERAGEIFS(INDIRECT("NYSERDA_SupplyCurve_Raw[Resource "&T$14&"]"), NYSERDA_SupplyCurve_Raw[Interconnection Zone],$G19,NYSERDA_SupplyCurve_Raw[CapEx Bin],$H19,NYSERDA_SupplyCurve_Raw[Technology Type],$F19),"") -> 1.1189864 | ... AC19: =IFERROR(AVERAGEIFS(INDIRECT("NYSERDA_SupplyCurve_Raw[Resource "&AC$14&"]"), NYSERDA_SupplyCurve_Raw[Interconnection Zone],$G19,NYSERDA_SupplyCurve_Raw[CapEx Bin],$H19,NYSERDA_SupplyCurve_Raw[Technology Type],$F19),"") -> 1.2856909
C20: NYC | D20: Low Cost | E20: =NYSERDA_SupplyProcessed[[#This Row],[Technology_Lookup]]&"_"&NYSERDA_SupplyProcessed[[#This Row],[Region]]&"_"&NYSERDA_SupplyProcessed[[#This Row],[CapEx_Lookup]] -> Utility-scale Solar_NYC_Low Cost | F20: Utility-scale Solar | G20: J | H20: Low Cost | I20: =SUMIFS(NYSERDA_SupplyCurve_Raw[Available Capacity (MWac)],NYSERDA_SupplyCurve_Raw[Interconnection Zone],$G20,NYSERDA_SupplyCurve_Raw[CapEx Bin],$H20,NYSERDA_SupplyCurve_Raw[Technology Type],$F20) -> 0 | J20: =IF($I20>0,SUMIFS(NYSERDA_SupplyCurve_Raw[Total Capex Cost (thousand $)],NYSERDA_SupplyCurve_Raw[Interconnection Zone],$G20,NYSERDA_SupplyCurve_Raw[CapEx Bin],$H20,NYSERDA_SupplyCurve_Raw[Technology Type],$F20)/$I20,"") | K20: =IF($I20>0,SUMIFS(NYSERDA_SupplyCurve_Raw[Total OpEx Cost (thousand $ / kW- year)],NYSERDA_SupplyCurve_Raw[Interconnection Zone],$G20,NYSERDA_SupplyCurve_Raw[CapEx Bin],$H20,NYSERDA_SupplyCurve_Raw[Technology Type],$F20)/$I20,"") | L20: =IF($I20>0,SUMIFS(NYSERDA_SupplyCurve_Raw[Avg OpEx x Total Generation],NYSERDA_SupplyCurve_Raw[Interconnection Zone],$G20,NYSERDA_SupplyCurve_Raw[CapEx Bin],$H20,NYSERDA_SupplyCurve_Raw[Technology Type],$F20)/$I20,"") | M20: =IFERROR(AVERAGEIFS(INDIRECT("NYSERDA_SupplyCurve_Raw[Resource "&M$14&"]"), NYSERDA_SupplyCurve_Raw[Interconnection Zone],$G20,NYSERDA_SupplyCurve_Raw[CapEx Bin],$H20,NYSERDA_SupplyCurve_Raw[Technology Type],$F20),"") | N20: =IFERROR(AVERAGEIFS(INDIRECT("NYSERDA_SupplyCurve_Raw[Resource "&N$14&"]"), NYSERDA_SupplyCurve_Raw[Interconnection Zone],$G20,NYSERDA_SupplyCurve_Raw[CapEx Bin],$H20,NYSERDA_SupplyCurve_Raw[Technology Type],$F20),"") | O20: =IFERROR(AVERAGEIFS(INDIRECT("NYSERDA_SupplyCurve_Raw[Resource "&O$14&"]"), NYSERDA_SupplyCurve_Raw[Interconnection Zone],$G20,NYSERDA_SupplyCurve_Raw[CapEx Bin],$H20,NYSERDA_SupplyCurve_Raw[Technology Type],$F20),"") | P20: =IFERROR(AVERAGEIFS(INDIRECT("NYSERDA_SupplyCurve_Raw[Resource "&P$14&"]"), NYSERDA_SupplyCurve_Raw[Interconnection Zone],$G20,NYSERDA_SupplyCurve_Raw[CapEx Bin],$H20,NYSERDA_SupplyCurve_Raw[Technology Type],$F20),"") | Q20: =IFERROR(AVERAGEIFS(INDIRECT("NYSERDA_SupplyCurve_Raw[Resource "&Q$14&"]"), NYSERDA_SupplyCurve_Raw[Interconnection Zone],$G20,NYSERDA_SupplyCurve_Raw[CapEx Bin],$H20,NYSERDA_SupplyCurve_Raw[Technology Type],$F20),"") | R20: =IFERROR(AVERAGEIFS(INDIRECT("NYSERDA_SupplyCurve_Raw[Resource "&R$14&"]"), NYSERDA_SupplyCurve_Raw[Interconnection Zone],$G20,NYSERDA_SupplyCurve_Raw[CapEx Bin],$H20,NYSERDA_SupplyCurve_Raw[Technology Type],$F20),"") | S20: =IFERROR(AVERAGEIFS(INDIRECT("NYSERDA_SupplyCurve_Raw[Resource "&S$14&"]"), NYSERDA_SupplyCurve_Raw[Interconnection Zone],$G20,NYSERDA_SupplyCurve_Raw[CapEx Bin],$H20,NYSERDA_SupplyCurve_Raw[Technology Type],$F20),"") | T20: =IFERROR(AVERAGEIFS(INDIRECT("NYSERDA_SupplyCurve_Raw[Resource "&T$14&"]"), NYSERDA_SupplyCurve_Raw[Interconnection Zone],$G20,NYSERDA_SupplyCurve_Raw[CapEx Bin],$H20,NYSERDA_SupplyCurve_Raw[Technology Type],$F20),"") | ... AC20: =IFERROR(AVERAGEIFS(INDIRECT("NYSERDA_SupplyCurve_Raw[Resource "&AC$14&"]"), NYSERDA_SupplyCurve_Raw[Interconnection Zone],$G20,NYSERDA_SupplyCurve_Raw[CapEx Bin],$H20,NYSERDA_SupplyCurve_Raw[Technology Type],$F20),"")
C21: Rest of State | D21: Low Cost | E21: =NYSERDA_SupplyProcessed[[#This Row],[Technology_Lookup]]&"_"&NYSERDA_SupplyProcessed[[#This Row],[Region]]&"_"&NYSERDA_SupplyProcessed[[#This Row],[CapEx_Lookup]] -> Utility-scale Solar_Rest of State_Low Cost | F21: Utility-scale Solar | G21: <>J | H21: Low Cost | I21: =SUMIFS(NYSERDA_SupplyCurve_Raw[Available Capacity (MWac)],NYSERDA_SupplyCurve_Raw[Interconnection Zone],$G21,NYSERDA_SupplyCurve_Raw[CapEx Bin],$H21,NYSERDA_SupplyCurve_Raw[Technology Type],$F21) -> 50438.526 | J21: =IF($I21>0,SUMIFS(NYSERDA_SupplyCurve_Raw[Total Capex Cost (thousand $)],NYSERDA_SupplyCurve_Raw[Interconnection Zone],$G21,NYSERDA_SupplyCurve_Raw[CapEx Bin],$H21,NYSERDA_SupplyCurve_Raw[Technology Type],$F21)/$I21,"") -> 1814.938 | K21: =IF($I21>0,SUMIFS(NYSERDA_SupplyCurve_Raw[Total OpEx Cost (thousand $ / kW- year)],NYSERDA_SupplyCurve_Raw[Interconnection Zone],$G21,NYSERDA_SupplyCurve_Raw[CapEx Bin],$H21,NYSERDA_SupplyCurve_Raw[Technology Type],$F21)/$I21,"") -> 27.384375 | L21: =IF($I21>0,SUMIFS(NYSERDA_SupplyCurve_Raw[Avg OpEx x Total Generation],NYSERDA_SupplyCurve_Raw[Interconnection Zone],$G21,NYSERDA_SupplyCurve_Raw[CapEx Bin],$H21,NYSERDA_SupplyCurve_Raw[Technology Type],$F21)/$I21,"") -> 0.20347115 | M21: =IFERROR(AVERAGEIFS(INDIRECT("NYSERDA_SupplyCurve_Raw[Resource "&M$14&"]"), NYSERDA_SupplyCurve_Raw[Interconnection Zone],$G21,NYSERDA_SupplyCurve_Raw[CapEx Bin],$H21,NYSERDA_SupplyCurve_Raw[Technology Type],$F21),"") -> 1 | N21: =IFERROR(AVERAGEIFS(INDIRECT("NYSERDA_SupplyCurve_Raw[Resource "&N$14&"]"), NYSERDA_SupplyCurve_Raw[Interconnection Zone],$G21,NYSERDA_SupplyCurve_Raw[CapEx Bin],$H21,NYSERDA_SupplyCurve_Raw[Technology Type],$F21),"") -> 0.98205558 | O21: =IFERROR(AVERAGEIFS(INDIRECT("NYSERDA_SupplyCurve_Raw[Resource "&O$14&"]"), NYSERDA_SupplyCurve_Raw[Interconnection Zone],$G21,NYSERDA_SupplyCurve_Raw[CapEx Bin],$H21,NYSERDA_SupplyCurve_Raw[Technology Type],$F21),"") -> 0.97508644 | P21: =IFERROR(AVERAGEIFS(INDIRECT("NYSERDA_SupplyCurve_Raw[Resource "&P$14&"]"), NYSERDA_SupplyCurve_Raw[Interconnection Zone],$G21,NYSERDA_SupplyCurve_Raw[CapEx Bin],$H21,NYSERDA_SupplyCurve_Raw[Technology Type],$F21),"") -> 0.9710687 | Q21: =IFERROR(AVERAGEIFS(INDIRECT("NYSERDA_SupplyCurve_Raw[Resource "&Q$14&"]"), NYSERDA_SupplyCurve_Raw[Interconnection Zone],$G21,NYSERDA_SupplyCurve_Raw[CapEx Bin],$H21,NYSERDA_SupplyCurve_Raw[Technology Type],$F21),"") -> 0.96272884 | R21: =IFERROR(AVERAGEIFS(INDIRECT("NYSERDA_SupplyCurve_Raw[Resource "&R$14&"]"), NYSERDA_SupplyCurve_Raw[Interconnection Zone],$G21,NYSERDA_SupplyCurve_Raw[CapEx Bin],$H21,NYSERDA_SupplyCurve_Raw[Technology Type],$F21),"") -> 0.96698975 | S21: =IFERROR(AVERAGEIFS(INDIRECT("NYSERDA_SupplyCurve_Raw[Resource "&S$14&"]"), NYSERDA_SupplyCurve_Raw[Interconnection Zone],$G21,NYSERDA_SupplyCurve_Raw[CapEx Bin],$H21,NYSERDA_SupplyCurve_Raw[Technology Type],$F21),"") -> 0.97267407 | T21: =IFERROR(AVERAGEIFS(INDIRECT("NYSERDA_SupplyCurve_Raw[Resource "&T$14&"]"), NYSERDA_SupplyCurve_Raw[Interconnection Zone],$G21,NYSERDA_SupplyCurve_Raw[CapEx Bin],$H21,NYSERDA_SupplyCurve_Raw[Technology Type],$F21),"") -> 0.97869558 | ... AC21: =IFERROR(AVERAGEIFS(INDIRECT("NYSERDA_SupplyCurve_Raw[Resource "&AC$14&"]"), NYSERDA_SupplyCurve_Raw[Interconnection Zone],$G21,NYSERDA_SupplyCurve_Raw[CapEx Bin],$H21,NYSERDA_SupplyCurve_Raw[Technology Type],$F21),"") -> 1.0756849
C22: NYC | D22: High Cost | E22: =NYSERDA_SupplyProcessed[[#This Row],[Technology_Lookup]]&"_"&NYSERDA_SupplyProcessed[[#This Row],[Region]]&"_"&NYSERDA_SupplyProcessed[[#This Row],[CapEx_Lookup]] -> Utility-scale Solar_NYC_High Cost | F22: Utility-scale Solar | G22: J | H22: High Cost | I22: =SUMIFS(NYSERDA_SupplyCurve_Raw[Available Capacity (MWac)],NYSERDA_SupplyCurve_Raw[Interconnection Zone],$G22,NYSERDA_SupplyCurve_Raw[CapEx Bin],$H22,NYSERDA_SupplyCurve_Raw[Technology Type],$F22) -> 0 | J22: =IF($I22>0,SUMIFS(NYSERDA_SupplyCurve_Raw[Total Capex Cost (thousand $)],NYSERDA_SupplyCurve_Raw[Interconnection Zone],$G22,NYSERDA_SupplyCurve_Raw[CapEx Bin],$H22,NYSERDA_SupplyCurve_Raw[Technology Type],$F22)/$I22,"") | K22: =IF($I22>0,SUMIFS(NYSERDA_SupplyCurve_Raw[Total OpEx Cost (thousand $ / kW- year)],NYSERDA_SupplyCurve_Raw[Interconnection Zone],$G22,NYSERDA_SupplyCurve_Raw[CapEx Bin],$H22,NYSERDA_SupplyCurve_Raw[Technology Type],$F22)/$I22,"") | L22: =IF($I22>0,SUMIFS(NYSERDA_SupplyCurve_Raw[Avg OpEx x Total Generation],NYSERDA_SupplyCurve_Raw[Interconnection Zone],$G22,NYSERDA_SupplyCurve_Raw[CapEx Bin],$H22,NYSERDA_SupplyCurve_Raw[Technology Type],$F22)/$I22,"") | M22: =IFERROR(AVERAGEIFS(INDIRECT("NYSERDA_SupplyCurve_Raw[Resource "&M$14&"]"), NYSERDA_SupplyCurve_Raw[Interconnection Zone],$G22,NYSERDA_SupplyCurve_Raw[CapEx Bin],$H22,NYSERDA_SupplyCurve_Raw[Technology Type],$F22),"") | N22: =IFERROR(AVERAGEIFS(INDIRECT("NYSERDA_SupplyCurve_Raw[Resource "&N$14&"]"), NYSERDA_SupplyCurve_Raw[Interconnection Zone],$G22,NYSERDA_SupplyCurve_Raw[CapEx Bin],$H22,NYSERDA_SupplyCurve_Raw[Technology Type],$F22),"") | O22: =IFERROR(AVERAGEIFS(INDIRECT("NYSERDA_SupplyCurve_Raw[Resource "&O$14&"]"), NYSERDA_SupplyCurve_Raw[Interconnection Zone],$G22,NYSERDA_SupplyCurve_Raw[CapEx Bin],$H22,NYSERDA_SupplyCurve_Raw[Technology Type],$F22),"") | P22: =IFERROR(AVERAGEIFS(INDIRECT("NYSERDA_SupplyCurve_Raw[Resource "&P$14&"]"), NYSERDA_SupplyCurve_Raw[Interconnection Zone],$G22,NYSERDA_SupplyCurve_Raw[CapEx Bin],$H22,NYSERDA_SupplyCurve_Raw[Technology Type],$F22),"") | Q22: =IFERROR(AVERAGEIFS(INDIRECT("NYSERDA_SupplyCurve_Raw[Resource "&Q$14&"]"), NYSERDA_SupplyCurve_Raw[Interconnection Zone],$G22,NYSERDA_SupplyCurve_Raw[CapEx Bin],$H22,NYSERDA_SupplyCurve_Raw[Technology Type],$F22),"") | R22: =IFERROR(AVERAGEIFS(INDIRECT("NYSERDA_SupplyCurve_Raw[Resource "&R$14&"]"), NYSERDA_SupplyCurve_Raw[Interconnection Zone],$G22,NYSERDA_SupplyCurve_Raw[CapEx Bin],$H22,NYSERDA_SupplyCurve_Raw[Technology Type],$F22),"") | S22: =IFERROR(AVERAGEIFS(INDIRECT("NYSERDA_SupplyCurve_Raw[Resource "&S$14&"]"), NYSERDA_SupplyCurve_Raw[Interconnection Zone],$G22,NYSERDA_SupplyCurve_Raw[CapEx Bin],$H22,NYSERDA_SupplyCurve_Raw[Technology Type],$F22),"") | T22: =IFERROR(AVERAGEIFS(INDIRECT("NYSERDA_SupplyCurve_Raw[Resource "&T$14&"]"), NYSERDA_SupplyCurve_Raw[Interconnection Zone],$G22,NYSERDA_SupplyCurve_Raw[CapEx Bin],$H22,NYSERDA_SupplyCurve_Raw[Technology Type],$F22),"") | ... AC22: =IFERROR(AVERAGEIFS(INDIRECT("NYSERDA_SupplyCurve_Raw[Resource "&AC$14&"]"), NYSERDA_SupplyCurve_Raw[Interconnection Zone],$G22,NYSERDA_SupplyCurve_Raw[CapEx Bin],$H22,NYSERDA_SupplyCurve_Raw[Technology Type],$F22),"")
C23: Rest of State | D23: High Cost | E23: =NYSERDA_SupplyProcessed[[#This Row],[Technology_Lookup]]&"_"&NYSERDA_SupplyProcessed[[#This Row],[Region]]&"_"&NYSERDA_SupplyProcessed[[#This Row],[CapEx_Lookup]] -> Utility-scale Solar_Rest of State_High Cost | F23: Utility-scale Solar | G23: <>J | H23: High Cost | I23: =SUMIFS(NYSERDA_SupplyCurve_Raw[Available Capacity (MWac)],NYSERDA_SupplyCurve_Raw[Interconnection Zone],$G23,NYSERDA_SupplyCurve_Raw[CapEx Bin],$H23,NYSERDA_SupplyCurve_Raw[Technology Type],$F23) -> 21673.583 | J23: =IF($I23>0,SUMIFS(NYSERDA_SupplyCurve_Raw[Total Capex Cost (thousand $)],NYSERDA_SupplyCurve_Raw[Interconnection Zone],$G23,NYSERDA_SupplyCurve_Raw[CapEx Bin],$H23,NYSERDA_SupplyCurve_Raw[Technology Type],$F23)/$I23,"") -> 2079.7243 | K23: =IF($I23>0,SUMIFS(NYSERDA_SupplyCurve_Raw[Total OpEx Cost (thousand $ / kW- year)],NYSERDA_SupplyCurve_Raw[Interconnection Zone],$G23,NYSERDA_SupplyCurve_Raw[CapEx Bin],$H23,NYSERDA_SupplyCurve_Raw[Technology Type],$F23)/$I23,"") -> 27.435476 | L23: =IF($I23>0,SUMIFS(NYSERDA_SupplyCurve_Raw[Avg OpEx x Total Generation],NYSERDA_SupplyCurve_Raw[Interconnection Zone],$G23,NYSERDA_SupplyCurve_Raw[CapEx Bin],$H23,NYSERDA_SupplyCurve_Raw[Technology Type],$F23)/$I23,"") -> 0.20321292 | M23: =IFERROR(AVERAGEIFS(INDIRECT("NYSERDA_SupplyCurve_Raw[Resource "&M$14&"]"), NYSERDA_SupplyCurve_Raw[Interconnection Zone],$G23,NYSERDA_SupplyCurve_Raw[CapEx Bin],$H23,NYSERDA_SupplyCurve_Raw[Technology Type],$F23),"") -> 1 | N23: =IFERROR(AVERAGEIFS(INDIRECT("NYSERDA_SupplyCurve_Raw[Resource "&N$14&"]"), NYSERDA_SupplyCurve_Raw[Interconnection Zone],$G23,NYSERDA_SupplyCurve_Raw[CapEx Bin],$H23,NYSERDA_SupplyCurve_Raw[Technology Type],$F23),"") -> 0.98205558 | O23: =IFERROR(AVERAGEIFS(INDIRECT("NYSERDA_SupplyCurve_Raw[Resource "&O$14&"]"), NYSERDA_SupplyCurve_Raw[Interconnection Zone],$G23,NYSERDA_SupplyCurve_Raw[CapEx Bin],$H23,NYSERDA_SupplyCurve_Raw[Technology Type],$F23),"") -> 0.97508644 | P23: =IFERROR(AVERAGEIFS(INDIRECT("NYSERDA_SupplyCurve_Raw[Resource "&P$14&"]"), NYSERDA_SupplyCurve_Raw[Interconnection Zone],$G23,NYSERDA_SupplyCurve_Raw[CapEx Bin],$H23,NYSERDA_SupplyCurve_Raw[Technology Type],$F23),"") -> 0.9710687 | Q23: =IFERROR(AVERAGEIFS(INDIRECT("NYSERDA_SupplyCurve_Raw[Resource "&Q$14&"]"), NYSERDA_SupplyCurve_Raw[Interconnection Zone],$G23,NYSERDA_SupplyCurve_Raw[CapEx Bin],$H23,NYSERDA_SupplyCurve_Raw[Technology Type],$F23),"") -> 0.96272884 | R23: =IFERROR(AVERAGEIFS(INDIRECT("NYSERDA_SupplyCurve_Raw[Resource "&R$14&"]"), NYSERDA_SupplyCurve_Raw[Interconnection Zone],$G23,NYSERDA_SupplyCurve_Raw[CapEx Bin],$H23,NYSERDA_SupplyCurve_Raw[Technology Type],$F23),"") -> 0.96698975 | S23: =IFERROR(AVERAGEIFS(INDIRECT("NYSERDA_SupplyCurve_Raw[Resource "&S$14&"]"), NYSERDA_SupplyCurve_Raw[Interconnection Zone],$G23,NYSERDA_SupplyCurve_Raw[CapEx Bin],$H23,NYSERDA_SupplyCurve_Raw[Technology Type],$F23),"") -> 0.97267407 | T23: =IFERROR(AVERAGEIFS(INDIRECT("NYSERDA_SupplyCurve_Raw[Resource "&T$14&"]"), NYSERDA_SupplyCurve_Raw[Interconnection Zone],$G23,NYSERDA_SupplyCurve_Raw[CapEx Bin],$H23,NYSERDA_SupplyCurve_Raw[Technology Type],$F23),"") -> 0.97869558 | ... AC23: =IFERROR(AVERAGEIFS(INDIRECT("NYSERDA_SupplyCurve_Raw[Resource "&AC$14&"]"), NYSERDA_SupplyCurve_Raw[Interconnection Zone],$G23,NYSERDA_SupplyCurve_Raw[CapEx Bin],$H23,NYSERDA_SupplyCurve_Raw[Technology Type],$F23),"") -> 1.0756849
C24: Rest of State | D24: All | E24: =NYSERDA_SupplyProcessed[[#This Row],[Technology_Lookup]]&"_"&NYSERDA_SupplyProcessed[[#This Row],[Region]]&"_"&NYSERDA_SupplyProcessed[[#This Row],[CapEx_Lookup]] -> Utility-scale Solar_Rest of State_All | F24: Utility-scale Solar | G24: <>J | H24: * | I24: =SUMIFS(NYSERDA_SupplyCurve_Raw[Available Capacity (MWac)],NYSERDA_SupplyCurve_Raw[Interconnection Zone],$G24,NYSERDA_SupplyCurve_Raw[CapEx Bin],$H24,NYSERDA_SupplyCurve_Raw[Technology Type],$F24) -> 72112.109 | J24: =IF($I24>0,SUMIFS(NYSERDA_SupplyCurve_Raw[Total Capex Cost (thousand $)],NYSERDA_SupplyCurve_Raw[Interconnection Zone],$G24,NYSERDA_SupplyCurve_Raw[CapEx Bin],$H24,NYSERDA_SupplyCurve_Raw[Technology Type],$F24)/$I24,"") -> 1894.5206 | K24: =IF($I24>0,SUMIFS(NYSERDA_SupplyCurve_Raw[Total OpEx Cost (thousand $ / kW- year)],NYSERDA_SupplyCurve_Raw[Interconnection Zone],$G24,NYSERDA_SupplyCurve_Raw[CapEx Bin],$H24,NYSERDA_SupplyCurve_Raw[Technology Type],$F24)/$I24,"") -> 27.399734 | L24: =IF($I24>0,SUMIFS(NYSERDA_SupplyCurve_Raw[Avg OpEx x Total Generation],NYSERDA_SupplyCurve_Raw[Interconnection Zone],$G24,NYSERDA_SupplyCurve_Raw[CapEx Bin],$H24,NYSERDA_SupplyCurve_Raw[Technology Type],$F24)/$I24,"") -> 0.20339354 | M24: =IFERROR(AVERAGEIFS(INDIRECT("NYSERDA_SupplyCurve_Raw[Resource "&M$14&"]"), NYSERDA_SupplyCurve_Raw[Interconnection Zone],$G24,NYSERDA_SupplyCurve_Raw[CapEx Bin],$H24,NYSERDA_SupplyCurve_Raw[Technology Type],$F24),"") -> 1 | N24: =IFERROR(AVERAGEIFS(INDIRECT("NYSERDA_SupplyCurve_Raw[Resource "&N$14&"]"), NYSERDA_SupplyCurve_Raw[Interconnection Zone],$G24,NYSERDA_SupplyCurve_Raw[CapEx Bin],$H24,NYSERDA_SupplyCurve_Raw[Technology Type],$F24),"") -> 0.98205558 | O24: =IFERROR(AVERAGEIFS(INDIRECT("NYSERDA_SupplyCurve_Raw[Resource "&O$14&"]"), NYSERDA_SupplyCurve_Raw[Interconnection Zone],$G24,NYSERDA_SupplyCurve_Raw[CapEx Bin],$H24,NYSERDA_SupplyCurve_Raw[Technology Type],$F24),"") -> 0.97508644 | P24: =IFERROR(AVERAGEIFS(INDIRECT("NYSERDA_SupplyCurve_Raw[Resource "&P$14&"]"), NYSERDA_SupplyCurve_Raw[Interconnection Zone],$G24,NYSERDA_SupplyCurve_Raw[CapEx Bin],$H24,NYSERDA_SupplyCurve_Raw[Technology Type],$F24),"") -> 0.9710687 | Q24: =IFERROR(AVERAGEIFS(INDIRECT("NYSERDA_SupplyCurve_Raw[Resource "&Q$14&"]"), NYSERDA_SupplyCurve_Raw[Interconnection Zone],$G24,NYSERDA_SupplyCurve_Raw[CapEx Bin],$H24,NYSERDA_SupplyCurve_Raw[Technology Type],$F24),"") -> 0.96272884 | R24: =IFERROR(AVERAGEIFS(INDIRECT("NYSERDA_SupplyCurve_Raw[Resource "&R$14&"]"), NYSERDA_SupplyCurve_Raw[Interconnection Zone],$G24,NYSERDA_SupplyCurve_Raw[CapEx Bin],$H24,NYSERDA_SupplyCurve_Raw[Technology Type],$F24),"") -> 0.96698975 | S24: =IFERROR(AVERAGEIFS(INDIRECT("NYSERDA_SupplyCurve_Raw[Resource "&S$14&"]"), NYSERDA_SupplyCurve_Raw[Interconnection Zone],$G24,NYSERDA_SupplyCurve_Raw[CapEx Bin],$H24,NYSERDA_SupplyCurve_Raw[Technology Type],$F24),"") -> 0.97267407 | T24: =IFERROR(AVERAGEIFS(INDIRECT("NYSERDA_SupplyCurve_Raw[Resource "&T$14&"]"), NYSERDA_SupplyCurve_Raw[Interconnection Zone],$G24,NYSERDA_SupplyCurve_Raw[CapEx Bin],$H24,NYSERDA_SupplyCurve_Raw[Technology Type],$F24),"") -> 0.97869558 | ... AC24: =IFERROR(AVERAGEIFS(INDIRECT("NYSERDA_SupplyCurve_Raw[Resource "&AC$14&"]"), NYSERDA_SupplyCurve_Raw[Interconnection Zone],$G24,NYSERDA_SupplyCurve_Raw[CapEx Bin],$H24,NYSERDA_SupplyCurve_Raw[Technology Type],$F24),"") -> 1.0756849
C25: NYC | D25: Fixed Bottom | E25: =NYSERDA_SupplyProcessed[[#This Row],[Technology_Lookup]]&"_"&NYSERDA_SupplyProcessed[[#This Row],[Region]]&"_"&NYSERDA_SupplyProcessed[[#This Row],[CapEx_Lookup]] -> Offshore Wind - Fixed Bottom_NYC_Fixed Bottom | F25: Offshore Wind - Fixed Bottom | G25: J | H25: * | I25: =SUMIFS(NYSERDA_SupplyCurve_Raw[Available Capacity (MWac)],NYSERDA_SupplyCurve_Raw[Interconnection Zone],$G25,NYSERDA_SupplyCurve_Raw[CapEx Bin],$H25,NYSERDA_SupplyCurve_Raw[Technology Type],$F25) -> 4137.525 | J25: =IF($I25>0,SUMIFS(NYSERDA_SupplyCurve_Raw[Total Capex Cost (thousand $)],NYSERDA_SupplyCurve_Raw[Interconnection Zone],$G25,NYSERDA_SupplyCurve_Raw[CapEx Bin],$H25,NYSERDA_SupplyCurve_Raw[Technology Type],$F25)/$I25,"") -> 5419.3639 | K25: =IF($I25>0,SUMIFS(NYSERDA_SupplyCurve_Raw[Total OpEx Cost (thousand $ / kW- year)],NYSERDA_SupplyCurve_Raw[Interconnection Zone],$G25,NYSERDA_SupplyCurve_Raw[CapEx Bin],$H25,NYSERDA_SupplyCurve_Raw[Technology Type],$F25)/$I25,"") -> 87.521855 | L25: =IF($I25>0,SUMIFS(NYSERDA_SupplyCurve_Raw[Avg OpEx x Total Generation],NYSERDA_SupplyCurve_Raw[Interconnection Zone],$G25,NYSERDA_SupplyCurve_Raw[CapEx Bin],$H25,NYSERDA_SupplyCurve_Raw[Technology Type],$F25)/$I25,"") -> 0.54464272 | M25: =IFERROR(AVERAGEIFS(INDIRECT("NYSERDA_SupplyCurve_Raw[Resource "&M$14&"]"), NYSERDA_SupplyCurve_Raw[Interconnection Zone],$G25,NYSERDA_SupplyCurve_Raw[CapEx Bin],$H25,NYSERDA_SupplyCurve_Raw[Technology Type],$F25),"") -> 0.92827577 | N25: =IFERROR(AVERAGEIFS(INDIRECT("NYSERDA_SupplyCurve_Raw[Resource "&N$14&"]"), NYSERDA_SupplyCurve_Raw[Interconnection Zone],$G25,NYSERDA_SupplyCurve_Raw[CapEx Bin],$H25,NYSERDA_SupplyCurve_Raw[Technology Type],$F25),"") -> 1.0089777 | O25: =IFERROR(AVERAGEIFS(INDIRECT("NYSERDA_SupplyCurve_Raw[Resource "&O$14&"]"), NYSERDA_SupplyCurve_Raw[Interconnection Zone],$G25,NYSERDA_SupplyCurve_Raw[CapEx Bin],$H25,NYSERDA_SupplyCurve_Raw[Technology Type],$F25),"") -> 1.092901 | P25: =IFERROR(AVERAGEIFS(INDIRECT("NYSERDA_SupplyCurve_Raw[Resource "&P$14&"]"), NYSERDA_SupplyCurve_Raw[Interconnection Zone],$G25,NYSERDA_SupplyCurve_Raw[CapEx Bin],$H25,NYSERDA_SupplyCurve_Raw[Technology Type],$F25),"") -> 1.0714528 | Q25: =IFERROR(AVERAGEIFS(INDIRECT("NYSERDA_SupplyCurve_Raw[Resource "&Q$14&"]"), NYSERDA_SupplyCurve_Raw[Interconnection Zone],$G25,NYSERDA_SupplyCurve_Raw[CapEx Bin],$H25,NYSERDA_SupplyCurve_Raw[Technology Type],$F25),"") -> 1.0484398 | R25: =IFERROR(AVERAGEIFS(INDIRECT("NYSERDA_SupplyCurve_Raw[Resource "&R$14&"]"), NYSERDA_SupplyCurve_Raw[Interconnection Zone],$G25,NYSERDA_SupplyCurve_Raw[CapEx Bin],$H25,NYSERDA_SupplyCurve_Raw[Technology Type],$F25),"") -> 1.0238015 | S25: =IFERROR(AVERAGEIFS(INDIRECT("NYSERDA_SupplyCurve_Raw[Resource "&S$14&"]"), NYSERDA_SupplyCurve_Raw[Interconnection Zone],$G25,NYSERDA_SupplyCurve_Raw[CapEx Bin],$H25,NYSERDA_SupplyCurve_Raw[Technology Type],$F25),"") -> 0.99747517 | T25: =IFERROR(AVERAGEIFS(INDIRECT("NYSERDA_SupplyCurve_Raw[Resource "&T$14&"]"), NYSERDA_SupplyCurve_Raw[Interconnection Zone],$G25,NYSERDA_SupplyCurve_Raw[CapEx Bin],$H25,NYSERDA_SupplyCurve_Raw[Technology Type],$F25),"") -> 0.99475266 | ... AC25: =IFERROR(AVERAGEIFS(INDIRECT("NYSERDA_SupplyCurve_Raw[Resource "&AC$14&"]"), NYSERDA_SupplyCurve_Raw[Interconnection Zone],$G25,NYSERDA_SupplyCurve_Raw[CapEx Bin],$H25,NYSERDA_SupplyCurve_Raw[Technology Type],$F25),"") -> 1
C26: Rest of State | D26: Fixed Bottom | E26: =NYSERDA_SupplyProcessed[[#This Row],[Technology_Lookup]]&"_"&NYSERDA_SupplyProcessed[[#This Row],[Region]]&"_"&NYSERDA_SupplyProcessed[[#This Row],[CapEx_Lookup]] -> Offshore Wind - Fixed Bottom_Rest of State_Fixed Bottom | F26: Offshore Wind - Fixed Bottom | G26: <>J | H26: * | I26: =SUMIFS(NYSERDA_SupplyCurve_Raw[Available Capacity (MWac)],NYSERDA_SupplyCurve_Raw[Interconnection Zone],$G26,NYSERDA_SupplyCurve_Raw[CapEx Bin],$H26,NYSERDA_SupplyCurve_Raw[Technology Type],$F26) -> 10890.375 | J26: =IF($I26>0,SUMIFS(NYSERDA_SupplyCurve_Raw[Total Capex Cost (thousand $)],NYSERDA_SupplyCurve_Raw[Interconnection Zone],$G26,NYSERDA_SupplyCurve_Raw[CapEx Bin],$H26,NYSERDA_SupplyCurve_Raw[Technology Type],$F26)/$I26,"") -> 5198.2303 | K26: =IF($I26>0,SUMIFS(NYSERDA_SupplyCurve_Raw[Total OpEx Cost (thousand $ / kW- year)],NYSERDA_SupplyCurve_Raw[Interconnection Zone],$G26,NYSERDA_SupplyCurve_Raw[CapEx Bin],$H26,NYSERDA_SupplyCurve_Raw[Technology Type],$F26)/$I26,"") -> 86.229804 | L26: =IF($I26>0,SUMIFS(NYSERDA_SupplyCurve_Raw[Avg OpEx x Total Generation],NYSERDA_SupplyCurve_Raw[Interconnection Zone],$G26,NYSERDA_SupplyCurve_Raw[CapEx Bin],$H26,NYSERDA_SupplyCurve_Raw[Technology Type],$F26)/$I26,"") -> 0.55383249 | M26: =IFERROR(AVERAGEIFS(INDIRECT("NYSERDA_SupplyCurve_Raw[Resource "&M$14&"]"), NYSERDA_SupplyCurve_Raw[Interconnection Zone],$G26,NYSERDA_SupplyCurve_Raw[CapEx Bin],$H26,NYSERDA_SupplyCurve_Raw[Technology Type],$F26),"") -> 0.92827577 | N26: =IFERROR(AVERAGEIFS(INDIRECT("NYSERDA_SupplyCurve_Raw[Resource "&N$14&"]"), NYSERDA_SupplyCurve_Raw[Interconnection Zone],$G26,NYSERDA_SupplyCurve_Raw[CapEx Bin],$H26,NYSERDA_SupplyCurve_Raw[Technology Type],$F26),"") -> 1.0089777 | O26: =IFERROR(AVERAGEIFS(INDIRECT("NYSERDA_SupplyCurve_Raw[Resource "&O$14&"]"), NYSERDA_SupplyCurve_Raw[Interconnection Zone],$G26,NYSERDA_SupplyCurve_Raw[CapEx Bin],$H26,NYSERDA_SupplyCurve_Raw[Technology Type],$F26),"") -> 1.092901 | P26: =IFERROR(AVERAGEIFS(INDIRECT("NYSERDA_SupplyCurve_Raw[Resource "&P$14&"]"), NYSERDA_SupplyCurve_Raw[Interconnection Zone],$G26,NYSERDA_SupplyCurve_Raw[CapEx Bin],$H26,NYSERDA_SupplyCurve_Raw[Technology Type],$F26),"") -> 1.0714528 | Q26: =IFERROR(AVERAGEIFS(INDIRECT("NYSERDA_SupplyCurve_Raw[Resource "&Q$14&"]"), NYSERDA_SupplyCurve_Raw[Interconnection Zone],$G26,NYSERDA_SupplyCurve_Raw[CapEx Bin],$H26,NYSERDA_SupplyCurve_Raw[Technology Type],$F26),"") -> 1.0484398 | R26: =IFERROR(AVERAGEIFS(INDIRECT("NYSERDA_SupplyCurve_Raw[Resource "&R$14&"]"), NYSERDA_SupplyCurve_Raw[Interconnection Zone],$G26,NYSERDA_SupplyCurve_Raw[CapEx Bin],$H26,NYSERDA_SupplyCurve_Raw[Technology Type],$F26),"") -> 1.0238015 | S26: =IFERROR(AVERAGEIFS(INDIRECT("NYSERDA_SupplyCurve_Raw[Resource "&S$14&"]"), NYSERDA_SupplyCurve_Raw[Interconnection Zone],$G26,NYSERDA_SupplyCurve_Raw[CapEx Bin],$H26,NYSERDA_SupplyCurve_Raw[Technology Type],$F26),"") -> 0.99747517 | T26: =IFERROR(AVERAGEIFS(INDIRECT("NYSERDA_SupplyCurve_Raw[Resource "&T$14&"]"), NYSERDA_SupplyCurve_Raw[Interconnection Zone],$G26,NYSERDA_SupplyCurve_Raw[CapEx Bin],$H26,NYSERDA_SupplyCurve_Raw[Technology Type],$F26),"") -> 0.99475266 | ... AC26: =IFERROR(AVERAGEIFS(INDIRECT("NYSERDA_SupplyCurve_Raw[Resource "&AC$14&"]"), NYSERDA_SupplyCurve_Raw[Interconnection Zone],$G26,NYSERDA_SupplyCurve_Raw[CapEx Bin],$H26,NYSERDA_SupplyCurve_Raw[Technology Type],$F26),"") -> 1
C27: All | D27: Fixed Bottom | E27: =NYSERDA_SupplyProcessed[[#This Row],[Technology_Lookup]]&"_"&NYSERDA_SupplyProcessed[[#This Row],[Region]]&"_"&NYSERDA_SupplyProcessed[[#This Row],[CapEx_Lookup]] -> Offshore Wind - Fixed Bottom_All_Fixed Bottom | F27: Offshore Wind - Fixed Bottom | G27: * | H27: * | I27: =SUMIFS(NYSERDA_SupplyCurve_Raw[Available Capacity (MWac)],NYSERDA_SupplyCurve_Raw[Interconnection Zone],$G27,NYSERDA_SupplyCurve_Raw[CapEx Bin],$H27,NYSERDA_SupplyCurve_Raw[Technology Type],$F27) -> 15027.9 | J27: =IF($I27>0,SUMIFS(NYSERDA_SupplyCurve_Raw[Total Capex Cost (thousand $)],NYSERDA_SupplyCurve_Raw[Interconnection Zone],$G27,NYSERDA_SupplyCurve_Raw[CapEx Bin],$H27,NYSERDA_SupplyCurve_Raw[Technology Type],$F27)/$I27,"") -> 5259.1134 | K27: =IF($I27>0,SUMIFS(NYSERDA_SupplyCurve_Raw[Total OpEx Cost (thousand $ / kW- year)],NYSERDA_SupplyCurve_Raw[Interconnection Zone],$G27,NYSERDA_SupplyCurve_Raw[CapEx Bin],$H27,NYSERDA_SupplyCurve_Raw[Technology Type],$F27)/$I27,"") -> 86.585535 | L27: =IF($I27>0,SUMIFS(NYSERDA_SupplyCurve_Raw[Avg OpEx x Total Generation],NYSERDA_SupplyCurve_Raw[Interconnection Zone],$G27,NYSERDA_SupplyCurve_Raw[CapEx Bin],$H27,NYSERDA_SupplyCurve_Raw[Technology Type],$F27)/$I27,"") -> 0.55130234 | M27: =IFERROR(AVERAGEIFS(INDIRECT("NYSERDA_SupplyCurve_Raw[Resource "&M$14&"]"), NYSERDA_SupplyCurve_Raw[Interconnection Zone],$G27,NYSERDA_SupplyCurve_Raw[CapEx Bin],$H27,NYSERDA_SupplyCurve_Raw[Technology Type],$F27),"") -> 0.92827577 | N27: =IFERROR(AVERAGEIFS(INDIRECT("NYSERDA_SupplyCurve_Raw[Resource "&N$14&"]"), NYSERDA_SupplyCurve_Raw[Interconnection Zone],$G27,NYSERDA_SupplyCurve_Raw[CapEx Bin],$H27,NYSERDA_SupplyCurve_Raw[Technology Type],$F27),"") -> 1.0089777 | O27: =IFERROR(AVERAGEIFS(INDIRECT("NYSERDA_SupplyCurve_Raw[Resource "&O$14&"]"), NYSERDA_SupplyCurve_Raw[Interconnection Zone],$G27,NYSERDA_SupplyCurve_Raw[CapEx Bin],$H27,NYSERDA_SupplyCurve_Raw[Technology Type],$F27),"") -> 1.092901 | P27: =IFERROR(AVERAGEIFS(INDIRECT("NYSERDA_SupplyCurve_Raw[Resource "&P$14&"]"), NYSERDA_SupplyCurve_Raw[Interconnection Zone],$G27,NYSERDA_SupplyCurve_Raw[CapEx Bin],$H27,NYSERDA_SupplyCurve_Raw[Technology Type],$F27),"") -> 1.0714528 | Q27: =IFERROR(AVERAGEIFS(INDIRECT("NYSERDA_SupplyCurve_Raw[Resource "&Q$14&"]"), NYSERDA_SupplyCurve_Raw[Interconnection Zone],$G27,NYSERDA_SupplyCurve_Raw[CapEx Bin],$H27,NYSERDA_SupplyCurve_Raw[Technology Type],$F27),"") -> 1.0484398 | R27: =IFERROR(AVERAGEIFS(INDIRECT("NYSERDA_SupplyCurve_Raw[Resource "&R$14&"]"), NYSERDA_SupplyCurve_Raw[Interconnection Zone],$G27,NYSERDA_SupplyCurve_Raw[CapEx Bin],$H27,NYSERDA_SupplyCurve_Raw[Technology Type],$F27),"") -> 1.0238015 | S27: =IFERROR(AVERAGEIFS(INDIRECT("NYSERDA_SupplyCurve_Raw[Resource "&S$14&"]"), NYSERDA_SupplyCurve_Raw[Interconnection Zone],$G27,NYSERDA_SupplyCurve_Raw[CapEx Bin],$H27,NYSERDA_SupplyCurve_Raw[Technology Type],$F27),"") -> 0.99747517 | T27: =IFERROR(AVERAGEIFS(INDIRECT("NYSERDA_SupplyCurve_Raw[Resource "&T$14&"]"), NYSERDA_SupplyCurve_Raw[Interconnection Zone],$G27,NYSERDA_SupplyCurve_Raw[CapEx Bin],$H27,NYSERDA_SupplyCurve_Raw[Technology Type],$F27),"") -> 0.99475266 | ... AC27: =IFERROR(AVERAGEIFS(INDIRECT("NYSERDA_SupplyCurve_Raw[Resource "&AC$14&"]"), NYSERDA_SupplyCurve_Raw[Interconnection Zone],$G27,NYSERDA_SupplyCurve_Raw[CapEx Bin],$H27,NYSERDA_SupplyCurve_Raw[Technology Type],$F27),"") -> 1
