Workbook
Name __HDV50: #REF!
Name __HDV50: #REF!
Name __HDV50: #REF!
Name __LDV50: #REF!
Name __LDV50: #REF!
Name __LDV50: #REF!
Name _1995_Implicit_GDP_Deflator: #REF!
Name _1995_Implicit_GDP_Deflator: #REF!
Name _1995_Implicit_GDP_Deflator: #REF!
Name _2001_Implicit_GDP_Deflator: #REF!
Name _2001_Implicit_GDP_Deflator: #REF!
Name _2001_Implicit_GDP_Deflator: #REF!
Name Age_of_car: #REF!
Name Age_of_car: #REF!
Name Age_of_car: #REF!
Name AnswerData: #REF!
Name avg_water_heater_PJ: '[1]AEO HW'!$B$33
Name bprint: #REF!
Name btu_per_watthr: #REF!
Name btu_per_watthr: #REF!
Name btu_per_watthr: #REF!
Name CAPCST: '[2]AEO16 Com Tech'!$H$103:$H$4268
Name CMM_SUPPLY_CRV_TABLE: [3]cum2025curves!#REF!
Name conv: #REF!
Name conv: #REF!
Name conv: #REF!
Name cprint: #REF!
Name CRI: '[2]AEO16 Com Tech'!$AF$103:$AF$4268
Name days_per_year: #REF!
Name days_per_year: #REF!
Name days_per_year: #REF!
Name Diesel_Car_CO: #REF!
Name Diesel_Car_CO: #REF!
Name Diesel_Car_CO: #REF!
Name Diesel_Car_Nox: #REF!
Name Diesel_Car_Nox: #REF!
Name Diesel_Car_Nox: #REF!
Name Diesel_Car_PM: #REF!
Name Diesel_Car_PM: #REF!
Name Diesel_Car_PM: #REF!
Name Diesel_Car_VOCs: #REF!
Name Diesel_Car_VOCs: #REF!
Name Diesel_Car_VOCs: #REF!
Name Diesel_HDT_CO: #REF!
Name Diesel_HDT_CO: #REF!
Name Diesel_HDT_CO: #REF!
Name Diesel_HDT_NOx: #REF!
Name Diesel_HDT_NOx: #REF!
Name Diesel_HDT_NOx: #REF!
Name Diesel_HDT_PM: #REF!
Name Diesel_HDT_PM: #REF!
Name Diesel_HDT_PM: #REF!
Name Diesel_HDT_SO2: #REF!
Name Diesel_HDT_SO2: #REF!
Name Diesel_HDT_SO2: #REF!
Name Diesel_HDT_VOCs: #REF!
Name Diesel_HDT_VOCs: #REF!
Name Diesel_HDT_VOCs: #REF!
Name Diesel_LDT_CO: #REF!
Name Diesel_LDT_CO: #REF!

Sheet ANSv6.0-Commodities
A1: ANSWER-Commodities
B7: CommName | C7: CommDesc | D7: CommUnit | E7: Set Memberships | F7: Comment

Sheet ANSv6.1-Commodities
A1: ANSWER-Commodities
B7: CommName | C7: CommDesc | D7: CommUnit | E7: Set Memberships | F7: Comment

Sheet Commodities
B6: ~FI_Comm
B7: Region | C7: Csets | D7: CommName | E7: CommDesc | F7: Unit | G7: LimType | H7: CTSLvl | I7: PeakTS | J7: Ctype | O7: Comment
B24: *Demands
B25: R2,R3,R4,R5,R6 | C25: DEM | D25: TL | E25: Transportation Light Duty | F25: bn-vmt
B26: *Energy Carriers
B27: R2,R3,R4,R5,R6 | C27: NRG | D27: TRNDSL | E27: DSL to TRN | F27: PJ
B28: R2,R3,R4,R5,R6 | C28: NRG | D28: TLGSL | E28: GSL to TRN | F28: PJ
B29: *R2,R3,R4,R5,R6 | C29: NRG | D29: TLE85X | E29: E85X to TL | F29: PJ
B30: *R2,R3,R4,R5,R6 | C30: NRG | D30: TRNCNG | E30: CNG to TRN | F30: PJ
B31: *R2,R3,R4,R5,R6 | C31: NRG | D31: TRNLPGX | E31: LPGX to TRN | F31: PJ
B32: R2,R3,R4,R5,R6 | C32: NRG | D32: TRNELC | E32: ELC to TRN | F32: PJ
B33: *Energy Carriers
B34: R2,R3,R4,R5,R6 | C34: NRG | D34: ELC | E34: Electricity | F34: PJ
B35: *R2,R3,R4,R5,R6 | C35: NRG | D35: TRNNGA | E35: Natural Gas to Transportation Sector | F35: PJ
B36: *R2,R3,R4,R5,R6 | C36: NRG | D36: TRNCNGH | E36: CNG to TRN - Heavy Duty Vehicles | F36: PJ
B37: R2,R3,R4,R5,R6 | C37: NRG | D37: TRNCNGL | E37: CNG to TRN - Light Duty Vehicles | F37: PJ
B38: *R2,R3,R4,R5,R6 | C38: NRG | D38: TRNCNGX | E38: CNGX to TRN | F38: PJ
B39: *R2,R3,R4,R5,R6 | C39: NRG | D39: TRDSLL | E39: DSLL to Blend | F39: PJ
B40: *R2,R3,R4,R5,R6 | C40: NRG | D40: TRDSLU | E40: DSLU to Blend | F40: PJ
B41: *R2,R3,R4,R5,R6 | C41: NRG | D41: TRNDSLB | E41: DSL combo of DSLL and DSLU | F41: PJ
B42: *R2,R3,R4,R5,R6 | C42: NRG | D42: TRNE10 | E42: E10 Blend | F42: PJ
B43: *R2,R3,R4,R5,R6 | C43: NRG | D43: TRNE85 | E43: E85 Blend | F43: PJ
B44: *R2,R3,R4,R5,R6 | C44: NRG | D44: TRNETH | E44: Ethanol to Transportation Sector | F44: PJ
B45: *R2,R3,R4,R5,R6 | C45: NRG | D45: TRGSLC1 | E45: CONV GSL to TRN after Collection | F45: PJ
... B63: R2,R3,R4,R5,R6 | C63: NRG | D63: ZZDMY | E63: Dummy commodity | F63: PJ
B64: *Emissions Commodities
B65: *R2,R3,R4,R5,R6 | C65: ENV | D65: CO2 | E65: Carbon dioxide emissions | F65: Mt
B66: R2,R3,R4,R5,R6 | C66: ENV | D66: NOX | E66: NOx emissions | F66: kt
B67: R2,R3,R4,R5,R6 | C67: ENV | D67: SO2 | E67: SO2 emissions | F67: kt
B68: R2,R3,R4,R5,R6 | C68: ENV | D68: PM10 | E68: PM10 emissions | F68: kt
B69: *R2,R3,R4,R5,R6 | C69: ENV | D69: PM25 | E69: PM2.5 emissions | F69: kt
B70: *R2,R3,R4,R5,R6 | C70: ENV | D70: CO | E70: Carbon monoxide | F70: kt
B71: *R2,R3,R4,R5,R6 | C71: ENV | D71: N2O | E71: Nitrous oxide | F71: kt
B72: *R2,R3,R4,R5,R6 | C72: ENV | D72: CH4 | E72: Methane | F72: kt
B73: *R2,R3,R4,R5,R6 | C73: ENV | D73: VOC | E73: VOCs | F73: kt
B74: *R2,R3,R4,R5,R6 | C74: ENV | D74: NH3 | E74: Ammonia | F74: kt
B75: *R2,R3,R4,R5,R6 | C75: ENV | D75: BC | E75: Black carbon | F75: kt
B76: *R2,R3,R4,R5,R6 | C76: ENV | D76: OC | E76: Organic carbon | F76: kt
... B81: *R2,R3,R4,R5,R6 | C81: ENV | D81: PM25T | E81: Transportation sector PM25 | F81: kt

Sheet ANSv6.0-Technologies
A1: ANSWER-Technologies
B7: TechName | C7: TechDesc | D7: TACTUnit | E7: TCAPUnit | F7: Set Memberships | G7: Comment

Sheet ANSv6.1-Technologies
A1: ANSWER-Technologies
B7: TechName | C7: TechDesc | D7: TACTUnit | E7: TCAPUnit | F7: Set Memberships | G7: Comment

Sheet Technologies
B6: ~FI_Process
B7: Sets | C7: TechName | D7: TechDesc | E7: Tact | F7: Tcap | G7: PrimaryCG | H7: Vintage | M7: Region
B8: * Light Duty Vehicle Demand Technologies
B9: DMD | C9: =TechData_All!A9 -> TLMCGSLC11 | D9: =TechData_All!C9 -> TL.GSL.MC.CONV.2011 | E9: bn-vmt | F9: bn-vmt/a | M9: R2,R3,R4,R5,R6
B10: DMD | C10: =TechData_All!A10 -> TLMCELC100 | D10: =TechData_All!C10 -> TL.ELC.MC.ELC100 | E10: bn-vmt | F10: bn-vmt/a | M10: R2,R3,R4,R5,R6
B11: DMD | C11: =TechData_All!A11 -> TLMCELC200 | D11: =TechData_All!C11 -> TL.ELC.MC.ELC200 | E11: bn-vmt | F11: bn-vmt/a | M11: R2,R3,R4,R5,R6
B12: DMD | C12: =TechData_All!A12 -> TLCGSLC11 | D12: =TechData_All!C12 -> TL.GSL.C.CONV.2011 | E12: bn-vmt | F12: bn-vmt/a | M12: R2,R3,R4,R5,R6
B13: DMD | C13: =TechData_All!A13 -> TLCELC100 | D13: =TechData_All!C13 -> TL.ELC.C.ELC100 | E13: bn-vmt | F13: bn-vmt/a | M13: R2,R3,R4,R5,R6
B14: DMD | C14: =TechData_All!A14 -> TLCELC200 | D14: =TechData_All!C14 -> TL.ELC.C.ELC200 | E14: bn-vmt | F14: bn-vmt/a | M14: R2,R3,R4,R5,R6
B15: DMD | C15: =TechData_All!A15 -> TLCDSL11 | D15: =TechData_All!C15 -> TL.DSL.C.DSL.2011 | E15: bn-vmt | F15: bn-vmt/a | M15: R2,R3,R4,R5,R6
B16: DMD | C16: =TechData_All!A16 -> TLCCNG11 | D16: =TechData_All!C16 -> TL.CNG.C.CNG.2011 | E16: bn-vmt | F16: bn-vmt/a | M16: R2,R3,R4,R5,R6
B17: DMD | C17: =TechData_All!A17 -> TLCCNGX11 | D17: =TechData_All!C17 -> TL.CNGX.C.CNGX.2011 | E17: bn-vmt | F17: bn-vmt/a | M17: R2,R3,R4,R5,R6
B18: DMD | C18: =TechData_All!A18 -> *TLCDHEV15 | D18: =TechData_All!C18 -> TL.DSL.C.DHEV.2015 | E18: bn-vmt | F18: bn-vmt/a | M18: *R2,R3,R4,R5,R6
B19: DMD | C19: =TechData_All!A19 -> TLCETHX11 | D19: =TechData_All!C19 -> TL.E85X.C.ETHX.2011 | E19: bn-vmt | F19: bn-vmt/a | M19: R2,R3,R4,R5,R6
B20: DMD | C20: =TechData_All!A20 -> TLCFCH11 | D20: =TechData_All!C20 -> TL.H2.C.FCH.2011 | E20: bn-vmt | F20: bn-vmt/a | M20: *R2,R3,R4,R5,R6
... B23: DMD | C23: =TechData_All!A23 -> TLCGPHEV10 | D23: =TechData_All!C23 -> TL.GSL.C.PHEV.2011 | E23: bn-vmt | F23: bn-vmt/a | M23: R2,R3,R4,R5,R6
B24: DMD | C24: =TechData_All!A26 -> TLFGSLC11 | D24: =TechData_All!C26 -> TL.GSL.F.CONV.2011 | E24: bn-vmt | F24: bn-vmt/a | M24: R2,R3,R4,R5,R6
B25: DMD | C25: =TechData_All!A27 -> TLFELC100 | D25: =TechData_All!C27 -> Electric fullsize car w/100 mi range | E25: bn-vmt | F25: bn-vmt/a | M25: R2,R3,R4,R5,R6
B26: DMD | C26: =TechData_All!A28 -> TLFELC200 | D26: =TechData_All!C28 -> Electric fullsize car w/200 mi range | E26: bn-vmt | F26: bn-vmt/a | M26: R2,R3,R4,R5,R6
B27: DMD | C27: =TechData_All!A29 -> TLFCNG11 | D27: =TechData_All!C29 -> TL.CNG.F.CNG.2011 | E27: bn-vmt | F27: bn-vmt/a | M27: R2,R3,R4,R5,R6
B28: DMD | C28: =TechData_All!A30 -> TLFCNGX11 | D28: =TechData_All!C30 -> TL.CNGX.F.CNGX.2011 | E28: bn-vmt | F28: bn-vmt/a | M28: R2,R3,R4,R5,R6
B29: DMD | C29: =TechData_All!A31 -> *TLFDHEV20 | D29: =TechData_All!C31 -> TL.DSL.F.DHEV.2020 | E29: bn-vmt | F29: bn-vmt/a | M29: *R2,R3,R4,R5,R6
B30: DMD | C30: =TechData_All!A32 -> TLFDSL11 | D30: =TechData_All!C32 -> TL.DSL.F.DSL.2011 | E30: bn-vmt | F30: bn-vmt/a | M30: R2,R3,R4,R5,R6
B31: DMD | C31: =TechData_All!A33 -> TLFETHX11 | D31: =TechData_All!C33 -> TL.E85X.F.ETHX.2011 | E31: bn-vmt | F31: bn-vmt/a | M31: R2,R3,R4,R5,R6
B32: DMD | C32: =TechData_All!A34 -> TLFFCH15 | D32: =TechData_All!C34 -> TL.H2.F.FCH.2015 | E32: bn-vmt | F32: bn-vmt/a | M32: *R2,R3,R4,R5,R6
B33: DMD | C33: =TechData_All!A35 -> TLFGHEV11 | D33: =TechData_All!C35 -> TL.GSL.F.HEV.2011 | E33: bn-vmt | F33: bn-vmt/a | M33: R2,R3,R4,R5,R6
B34: DMD | C34: =TechData_All!A36 -> TLFLPGX11 | D34: =TechData_All!C36 -> TL.LPGX.F.LPGX.2011 | E34: bn-vmt | F34: bn-vmt/a | M34: R2,R3,R4,R5,R6
B35: DMD | C35: =TechData_All!A37 -> TLFGPHEV10 | D35: =TechData_All!C37 -> TL.GSL.F.PHEV.2011 | E35: bn-vmt | F35: bn-vmt/a | M35: R2,R3,R4,R5,R6
B36: DMD | C36: =TechData_All!A40 -> TLMGSLC11 | D36: =TechData_All!C40 -> TL.GSL.M.CONV.2011 | E36: bn-vmt | F36: bn-vmt/a | M36: R2,R3,R4,R5,R6
B37: DMD | C37: =TechData_All!A41 -> *TLMELC100 | D37: =TechData_All!C41 -> Electric minivan w/100 mi range | E37: bn-vmt | F37: bn-vmt/a | M37: *R2,R3,R4,R5,R6
B38: DMD | C38: =TechData_All!A42 -> TLMELC200 | D38: =TechData_All!C42 -> Electric minivan w/200 mi range | E38: bn-vmt | F38: bn-vmt/a | M38: R2,R3,R4,R5,R6
B39: DMD | C39: =TechData_All!A43 -> TLMCNG11 | D39: =TechData_All!C43 -> TL.CNG.M.CNG.2011 | E39: bn-vmt | F39: bn-vmt/a | M39: R2,R3,R4,R5,R6
B40: DMD | C40: =TechData_All!A44 -> TLMCNGX11 | D40: =TechData_All!C44 -> TL.CNGX.M.CNGX.2011 | E40: bn-vmt | F40: bn-vmt/a | M40: R2,R3,R4,R5,R6
B41: DMD | C41: =TechData_All!A45 -> *TLMDHEV15 | D41: =TechData_All!C45 -> TL.DSL.M.DHEV.2015 | E41: bn-vmt | F41: bn-vmt/a | M41: *R2,R3,R4,R5,R6
B42: DMD | C42: =TechData_All!A46 -> TLMDSL11 | D42: =TechData_All!C46 -> TL.DSL.M.DSL.2011 | E42: bn-vmt | F42: bn-vmt/a | M42: R2,R3,R4,R5,R6
B43: DMD | C43: =TechData_All!A47 -> TLMETHX11 | D43: =TechData_All!C47 -> TL.E85X.M.ETHX.2011 | E43: bn-vmt | F43: bn-vmt/a | M43: R2,R3,R4,R5,R6
B44: DMD | C44: =TechData_All!A48 -> TLMFCH15 | D44: =TechData_All!C48 -> TL.H2.M.FCH.2015 | E44: bn-vmt | F44: bn-vmt/a | M44: *R2,R3,R4,R5,R6
B45: DMD | C45: =TechData_All!A49 -> TLMGHEV11 | D45: =TechData_All!C49 -> TL.GSL.M.HEV.2011 | E45: bn-vmt | F45: bn-vmt/a | M45: R2,R3,R4,R5,R6
B46: DMD | C46: =TechData_All!A50 -> TLMLPG11 | D46: =TechData_All!C50 -> TL.LPG1.M.LPG.2011 | E46: bn-vmt | F46: bn-vmt/a | M46: R2,R3,R4,R5,R6
B47: DMD | C47: =TechData_All!A51 -> TLMLPGX11 | D47: =TechData_All!C51 -> TL.LPGX.M.LPGX.2011 | E47: bn-vmt | F47: bn-vmt/a | M47: R2,R3,R4,R5,R6
B48: DMD | C48: =TechData_All!A52 -> TLVGPHEV10 | D48: =TechData_All!C52 -> TL.GSL.M.PHEV.2011 | E48: bn-vmt | F48: bn-vmt/a | M48: R2,R3,R4,R5,R6
B49: DMD | C49: =TechData_All!A55 -> TLPGSLC11 | D49: =TechData_All!C55 -> TL.GSL.P.CONV.2011 | E49: bn-vmt | F49: bn-vmt/a | M49: R2,R3,R4,R5,R6
B50: DMD | C50: =TechData_All!A56 -> *TLPELC100 | D50: =TechData_All!C56 -> Electric pickup truck w/100 mi range | E50: bn-vmt | F50: bn-vmt/a | M50: *R2,R3,R4,R5,R6
B51: DMD | C51: =TechData_All!A57 -> TLPELC200 | D51: =TechData_All!C57 -> Electric pickup truck w/200 mi range | E51: bn-vmt | F51: bn-vmt/a | M51: R2,R3,R4,R5,R6
B52: DMD | C52: =TechData_All!A58 -> TLPCNG11 | D52: =TechData_All!C58 -> TL.CNG.P.CNG.2011 | E52: bn-vmt | F52: bn-vmt/a | M52: R2,R3,R4,R5,R6
B53: DMD | C53: =TechData_All!A59 -> TLPCNGX11 | D53: =TechData_All!C59 -> TL.CNGX.P.CNGX.2011 | E53: bn-vmt | F53: bn-vmt/a | M53: R2,R3,R4,R5,R6
B54: DMD | C54: =TechData_All!A60 -> TLPDSL11 | D54: =TechData_All!C60 -> TL.DSL.P.DSL.2011 | E54: bn-vmt | F54: bn-vmt/a | M54: R2,R3,R4,R5,R6
B55: DMD | C55: =TechData_All!A61 -> TLPETHX11 | D55: =TechData_All!C61 -> TL.E85X.P.ETHX.2011 | E55: bn-vmt | F55: bn-vmt/a | M55: R2,R3,R4,R5,R6
B56: DMD | C56: =TechData_All!A62 -> TLGPHEV15 | D56: =TechData_All!C62 -> TL.GSL.P.HEV.2015 | E56: bn-vmt | F56: bn-vmt/a | M56: R2,R3,R4,R5,R6
B57: DMD | C57: =TechData_All!A63 -> TLPLPG11 | D57: =TechData_All!C63 -> TL.LPG1.P.LPG.2011 | E57: bn-vmt | F57: bn-vmt/a | M57: R2,R3,R4,R5,R6
B58: DMD | C58: =TechData_All!A64 -> TLPLPGX11 | D58: =TechData_All!C64 -> TL.LPGX.P.LPGX.2011 | E58: bn-vmt | F58: bn-vmt/a | M58: R2,R3,R4,R5,R6
B59: DMD | C59: =TechData_All!A65 -> TLPGPHEV10 | D59: =TechData_All!C65 -> TL.GSL.P.PHEV.2015 | E59: bn-vmt | F59: bn-vmt/a | M59: *R2,R3,R4,R5,R6
B60: DMD | C60: =TechData_All!A68 -> TLSSGSLC11 | D60: =TechData_All!C68 -> TL.GSL.SS.CONV.2011 | E60: bn-vmt | F60: bn-vmt/a | M60: R2,R3,R4,R5,R6
B61: DMD | C61: =TechData_All!A69 -> *TLSSELC100 | D61: =TechData_All!C69 -> Electric small SUV w/100 mi range | E61: bn-vmt | F61: bn-vmt/a | M61: *R2,R3,R4,R5,R6
B62: DMD | C62: =TechData_All!A70 -> TLSSELC200 | D62: =TechData_All!C70 -> Electric small SUV w/200 mi range | E62: bn-vmt | F62: bn-vmt/a | M62: R2,R3,R4,R5,R6
B63: DMD | C63: =TechData_All!A71 -> *TLSSDHEV20 | D63: =TechData_All!C71 -> TL.DSL.SS.DHEV.2020 | E63: bn-vmt | F63: bn-vmt/a | M63: *R2,R3,R4,R5,R6
B64: DMD | C64: =TechData_All!A72 -> TLSSDSL11 | D64: =TechData_All!C72 -> TL.DSL.SS.DSL.2011 | E64: bn-vmt | F64: bn-vmt/a | M64: R2,R3,R4,R5,R6
B65: DMD | C65: =TechData_All!A73 -> TLSSETHX11 | D65: =TechData_All!C73 -> TL.E85X.SS.ETHX.2011 | E65: bn-vmt | F65: bn-vmt/a | M65: R2,R3,R4,R5,R6
B66: DMD | C66: =TechData_All!A74 -> TLSSFCH25 | D66: =TechData_All!C74 -> TL.H2.SS.FCH | E66: bn-vmt | F66: bn-vmt/a | M66: *R2,R3,R4,R5,R6
B67: DMD | C67: =TechData_All!A75 -> TLSSGHEV11 | D67: =TechData_All!C75 -> TL.GSL.SS.HEV.2011 | E67: bn-vmt | F67: bn-vmt/a | M67: R2,R3,R4,R5,R6
B68: DMD | C68: =TechData_All!A76 -> TLSSGPHEV11 | D68: =TechData_All!C76 -> TL.GSL.SS.PHEV.2011 | E68: bn-vmt | F68: bn-vmt/a | M68: R2,R3,R4,R5,R6
B69: DMD | C69: =TechData_All!A79 -> TLLSGSLC11 | D69: =TechData_All!C79 -> TL.GSL.LS.CONV.2011 | E69: bn-vmt | F69: bn-vmt/a | M69: R2,R3,R4,R5,R6
B70: DMD | C70: =TechData_All!A80 -> *TLLSELC100 | D70: =TechData_All!C80 -> Electric large SUV w/100 mi range | E70: bn-vmt | F70: bn-vmt/a | M70: *R2,R3,R4,R5,R6
B71: DMD | C71: =TechData_All!A81 -> TLLSELC200 | D71: =TechData_All!C81 -> Electric large SUV w/200 mi range | E71: bn-vmt | F71: bn-vmt/a | M71: R2,R3,R4,R5,R6
B72: DMD | C72: =TechData_All!A82 -> *TLLSDHEV20 | D72: =TechData_All!C82 -> TL.DSL.LS.DHEV.2020 | E72: bn-vmt | F72: bn-vmt/a | M72: *R2,R3,R4,R5,R6
B73: DMD | C73: =TechData_All!A83 -> TLLSDSL11 | D73: =TechData_All!C83 -> TL.DSL.LS.DSL.2011 | E73: bn-vmt | F73: bn-vmt/a | M73: R2,R3,R4,R5,R6
B74: DMD | C74: =TechData_All!A84 -> TLLSETHX11 | D74: =TechData_All!C84 -> TL.E85X.LS.ETHX.2011 | E74: bn-vmt | F74: bn-vmt/a | M74: R2,R3,R4,R5,R6
B75: DMD | C75: =TechData_All!A85 -> TLLSFCH25 | D75: =TechData_All!C85 -> TL.H2.LS.FCH.2025 | E75: bn-vmt | F75: bn-vmt/a | M75: *R2,R3,R4,R5,R6
B76: DMD | C76: =TechData_All!A86 -> TLLSGHEV11 | D76: =TechData_All!C86 -> TL.GSL.LS.HEV.2011 | E76: bn-vmt | F76: bn-vmt/a | M76: R2,R3,R4,R5,R6
B77: DMD | C77: =TechData_All!A87 -> TLLSPHVG11 | D77: =TechData_All!C87 -> TL.GSL.LS.PHEV.2011 | E77: bn-vmt | F77: bn-vmt/a | M77: *R2,R3,R4,R5,R6
B78: DMD | C78: =TechData_All!A90 -> TLCHE8511 | D78: =TechData_All!C90 -> TL.E85X.C.HE85.2011 | E78: bn-vmt | F78: bn-vmt/a | M78: R2,R3,R4,R5,R6
B79: DMD | C79: =TechData_All!A91 -> TLFHE8511 | D79: =TechData_All!C91 -> TL.E85X.F.HE85.2011 | E79: bn-vmt | F79: bn-vmt/a | M79: R2,R3,R4,R5,R6
B80: DMD | C80: =TechData_All!A92 -> TLPHE8515 | D80: =TechData_All!C92 -> TL.E85X.P.HE85.2015 | E80: bn-vmt | F80: bn-vmt/a | M80: R2,R3,R4,R5,R6
B81: DMD | C81: =TechData_All!A93 -> TLMHE8511 | D81: =TechData_All!C93 -> TL.E85X.M.HE85.2011 | E81: bn-vmt | F81: bn-vmt/a | M81: R2,R3,R4,R5,R6
B82: DMD | C82: =TechData_All!A94 -> TLLSHE8511 | D82: =TechData_All!C94 -> TL.E85X.LS.HE85.2011 | E82: bn-vmt | F82: bn-vmt/a | M82: R2,R3,R4,R5,R6
B83: DMD | C83: =TechData_All!A95 -> TLSSHE8511 | D83: =TechData_All!C95 -> TL.E85X.SS.HE85.2011 | E83: bn-vmt | F83: bn-vmt/a | M83: R2,R3,R4,R5,R6
B84: DMD | C84: =TechData_All!A96 -> TLCGPHEV40 | D84: =TechData_All!C96 -> TL.GSL.C.PHEV.2011 | E84: bn-vmt | F84: bn-vmt/a | M84: R2,R3,R4,R5,R6
B85: DMD | C85: =TechData_All!A99 -> TLFGPHEV40 | D85: =TechData_All!C99 -> TL.GSL.F.PHEV.2015 | E85: bn-vmt | F85: bn-vmt/a | M85: R2,R3,R4,R5,R6
B86: DMD | C86: =TechData_All!A102 -> TLPGPHEV40 | D86: =TechData_All!C102 -> TL.GSL.P.PHEV.2020 | E86: bn-vmt | F86: bn-vmt/a | M86: R2,R3,R4,R5,R6
B87: DMD | C87: =TechData_All!A105 -> TLVGPHEV40 | D87: =TechData_All!C105 -> TL.GSL.M.PHEV.2020 | E87: bn-vmt | F87: bn-vmt/a | M87: R2,R3,R4,R5,R6
B88: DMD | C88: =TechData_All!A108 -> *TLLSGPHEV40 | D88: =TechData_All!C108 -> TL.GSL.LS.PHEV.2020 | E88: bn-vmt | F88: bn-vmt/a | M88: *R2,R3,R4,R5,R6
B89: DMD | C89: =TechData_All!A111 -> TLSSGPHEV40 | D89: =TechData_All!C111 -> TL.GSL.SS.PHEV.2020 | E89: bn-vmt | F89: bn-vmt/a | M89: R2,R3,R4,R5,R6
B90: DMD | C90: =TechData_All!A114 -> TLMCELC300 | D90: =TechData_All!C114 -> TL.ELC.MC.300 | E90: bn-vmt | F90: bn-vmt/a | M90: R2,R3,R4,R5,R6
B91: DMD | C91: =TechData_All!A115 -> TLCELC300 | D91: =TechData_All!C115 -> TL.ELC.C.300 | E91: bn-vmt | F91: bn-vmt/a | M91: R2,R3,R4,R5,R6
B92: DMD | C92: =TechData_All!A116 -> TLFELC300 | D92: =TechData_All!C116 -> TL.ELC.F.300 | E92: bn-vmt | F92: bn-vmt/a | M92: R2,R3,R4,R5,R6
B93: DMD | C93: =TechData_All!A117 -> TLSSELC300 | D93: =TechData_All!C117 -> TL.ELC.SS.300 | E93: bn-vmt | F93: bn-vmt/a | M93: R2,R3,R4,R5,R6
B94: DMD | C94: =TechData_All!A118 -> TLLSELC300 | D94: =TechData_All!C118 -> TL.ELC.LS.300 | E94: bn-vmt | F94: bn-vmt/a | M94: R2,R3,R4,R5,R6
B95: =TechData_All!A119 -> * EV with Subsidies | E95: bn-vmt | F95: bn-vmt/a | M95: R2,R3,R4,R5,R6
B96: DMD | C96: =TechData_All!A120 -> TLMCELC100SUB | D96: =TechData_All!C120 -> TL.ELC.MC.ELC100SUB | E96: bn-vmt | F96: bn-vmt/a | M96: R2,R3,R4,R5,R6
B97: DMD | C97: =TechData_All!A121 -> TLMCELC200SUB | D97: =TechData_All!C121 -> TL.ELC.MC.ELC200SUB | E97: bn-vmt | F97: bn-vmt/a | M97: R2,R3,R4,R5,R6
B98: DMD | C98: =TechData_All!A122 -> TLCELC100SUB | D98: =TechData_All!C122 -> TL.ELC.C.ELC100SUB | E98: bn-vmt | F98: bn-vmt/a | M98: R2,R3,R4,R5,R6
B99: DMD | C99: =TechData_All!A123 -> TLCELC200SUB | D99: =TechData_All!C123 -> TL.ELC.C.ELC200SUB | E99: bn-vmt | F99: bn-vmt/a | M99: R2,R3,R4,R5,R6
B100: DMD | C100: =TechData_All!A124 -> TLFELC100SUB | D100: =TechData_All!C124 -> Electric fullsize car w/100 mi rangeSUB | E100: bn-vmt | F100: bn-vmt/a | M100: R2,R3,R4,R5,R6
B101: DMD | C101: =TechData_All!A125 -> TLFELC200SUB | D101: =TechData_All!C125 -> Electric fullsize car w/200 mi rangeSUB | E101: bn-vmt | F101: bn-vmt/a | M101: R2,R3,R4,R5,R6
B102: DMD | C102: =TechData_All!A126 -> *TLMELC100SUB | D102: =TechData_All!C126 -> Electric minivan w/100 mi rangeSUB | E102: bn-vmt | F102: bn-vmt/a | M102: R2,R3,R4,R5,R6
B103: DMD | C103: =TechData_All!A127 -> TLMELC200SUB | D103: =TechData_All!C127 -> Electric minivan w/200 mi rangeSUB | E103: bn-vmt | F103: bn-vmt/a | M103: R2,R3,R4,R5,R6
B104: DMD | C104: =TechData_All!A128 -> *TLPELC100SUB | D104: =TechData_All!C128 -> Electric pickup truck w/100 mi rangeSUB | E104: bn-vmt | F104: bn-vmt/a | M104: R2,R3,R4,R5,R6
B105: DMD | C105: =TechData_All!A129 -> TLPELC200SUB | D105: =TechData_All!C129 -> Electric pickup truck w/200 mi rangeSUB | E105: bn-vmt | F105: bn-vmt/a | M105: R2,R3,R4,R5,R6
B106: DMD | C106: =TechData_All!A130 -> *TLSSELC100SUB | D106: =TechData_All!C130 -> Electric small SUV w/100 mi rangeSUB | E106: bn-vmt | F106: bn-vmt/a | M106: R2,R3,R4,R5,R6
B107: DMD | C107: =TechData_All!A131 -> TLSSELC200SUB | D107: =TechData_All!C131 -> Electric small SUV w/200 mi rangeSUB | E107: bn-vmt | F107: bn-vmt/a | M107: R2,R3,R4,R5,R6
...

Sheet TechData_All
G1: 2010 | L1: 2010 | M1: 2015 | N1: 2020 | O1: 2025 | P1: 2030 | Q1: 2035 | R1: 2040 | S1: 2045 | T1: 2050 | U1: 2055 | AJ1: TechData
F6: ~FI_T
A7: TechName | B7: *Old_TechName | C7: *TechDesc | D7: *Units | E7: CommIN | F7: CommOUT | G7: NCAP_BND~2010 | H7: Share~UP | I7: NCAP_START | J7: *NCAP_START | K7: NCAP_TLIFE | L7: NCAP_COST~2010 | M7: NCAP_COST~2015 | N7: NCAP_COST~2020 | O7: NCAP_COST~2025 | P7: NCAP_COST~2030 | Q7: NCAP_COST~2035 | R7: NCAP_COST~2040 | S7: NCAP_COST~2045 | T7: NCAP_COST~2050 | U7: NCAP_COST~2055 | V7: EFF~2010 | W7: EFF~2015 | X7: EFF~2020 | Y7: EFF~2025 | Z7: EFF~2030 | AA7: EFF~2035 | AB7: EFF~2040 | AC7: EFF~2045 | AD7: EFF~2050 | AE7: EFF~2055 | AF7: NCAP_FOM | AG7: NCAP_DRATE | AH7: *NCAP_BND~UP~2010 | AJ7: Region
A8: * | B8: * | AJ8: * Light Duty Vehicle Demand Technologies
A9: TLMCGSLC11 | B9: TLMCCONV10 | C9: TL.GSL.MC.CONV.2011 | D9: bn-vmt, bn-vmt/a | E9: TLGSL | F9: TL | H9: 1 | I9: 2011 | J9: =INDEX(ConsolidatedVehData!$D$22:$D$858,MATCH(B9,ConsolidatedVehData!$A$22:$A$858,0)) -> 2010 | K9: 20 | L9: 3712.5791 | M9: 4299.2343 | N9: 4021.9395 | O9: 3744.6447 | P9: 3793.1888 | Q9: 3817.8798 | R9: 3843.5635 | S9: 3855.1902 | T9: 3866.0737 | U9: =T9 -> 3866.0737 | V9: 0.19166001 | W9: 0.2064227 | X9: 0.20015938 | Y9: 0.21589175 | Z9: 0.23045573 | AA9: 0.23605123 | AB9: 0.24107086 | AC9: 0.241691 | AD9: 0.24218659 | AE9: =AD9 -> 0.24218659 | AF9: =INDEX(ConsolidatedVehData!$AB$22:$AB$858,MATCH(B9,ConsolidatedVehData!$A$22:$A$858,0)) -> #REF! | AG9: 0.18 | AH9: 0 | AJ9: =Technologies!M9 -> R2,R3,R4,R5,R6
A10: TLMCELC100 | B10: TLMCELC | C10: TL.ELC.MC.ELC100 | D10: bn-vmt, bn-vmt/a | E10: TRNELC | F10: TL | G10: =IF($J10<G$1,0,"") | H10: 1 | I10: 2015 | J10: 2015 | K10: 20 | L10: 0 | M10: 5477.8845 | N10: 8085.3899 | O10: 2374.9122 | P10: 2217.2659 | Q10: 2175.3377 | R10: 2152.692 | S10: 2142.3738 | T10: 2136.6045 | U10: =T10 -> 2136.6045 | V10: 0 | W10: 0.85944227 | X10: 0.97494472 | Y10: 0.81749126 | Z10: 0.83015957 | AA10: 0.82928761 | AB10: 0.82870929 | AC10: 0.82855578 | AD10: 0.82863039 | AE10: =AD10 -> 0.82863039 | AF10: =0.5*AF9 -> #REF! | AG10: 0.28 | AH10: 0 | AJ10: =Technologies!M10 -> R2,R3,R4,R5,R6
A11: TLMCELC200 | B11: TLMCELCB | C11: TL.ELC.MC.ELC200 | D11: bn-vmt, bn-vmt/a | E11: TRNELC | F11: TL | G11: =IF($J11<G$1,0,"") | H11: 1 | I11: 2020 | J11: 2020 | K11: 20 | L11: 10354.508 | M11: 7408.9244 | N11: 9315.0119 | O11: 2649.8886 | P11: 2414.1394 | Q11: 2353.3601 | R11: 2319.8834 | S11: 2302.6679 | T11: 2291.7672 | U11: =T11 -> 2291.7672 | V11: 0.59552355 | W11: 0.92912184 | X11: 1.0846238 | Y11: 0.44861171 | Z11: 0.45396177 | AA11: 0.45414417 | AB11: 0.45459692 | AC11: 0.45304073 | AD11: 0.45213833 | AE11: =AD11 -> 0.45213833 | AF11: =0.5*AF9 -> #REF! | AG11: 0.28 | AH11: 0 | AJ11: =Technologies!M11 -> R2,R3,R4,R5,R6
A12: TLCGSLC11 | B12: TLCCONV10 | C12: TL.GSL.C.CONV.2011 | D12: bn-vmt, bn-vmt/a | E12: TLGSL | F12: TL | H12: 1 | I12: 2011 | J12: =INDEX(ConsolidatedVehData!$D$22:$D$858,MATCH(B12,ConsolidatedVehData!$A$22:$A$858,0)) -> 2010 | K12: 20 | L12: 1748.8504 | M12: 1901.0124 | N12: 2466.093 | O12: 2150.7212 | P12: 2202.3614 | Q12: 2227.2998 | R12: 2253.8266 | S12: 2273.1456 | T12: 2291.2155 | U12: =T12 -> 2291.2155 | V12: 0.22757469 | W12: 0.24750373 | X12: 0.25858033 | Y12: 0.29690918 | Z12: 0.31083696 | AA12: 0.31103711 | AB12: 0.31387333 | AC12: 0.31319474 | AD12: 0.31277284 | AE12: =AD12 -> 0.31277284 | AF12: =INDEX(ConsolidatedVehData!$AB$22:$AB$858,MATCH(B12,ConsolidatedVehData!$A$22:$A$858,0)) -> #REF! | AG12: 0.18 | AH12: 0 | AJ12: =Technologies!M12 -> R2,R3,R4,R5,R6
A13: TLCELC100 | B13: TLCELC | C13: TL.ELC.C.ELC100 | D13: bn-vmt, bn-vmt/a | E13: TRNELC | F13: TL | G13: =IF($J13<G$1,0,"") | H13: 1 | I13: 2015 | J13: 2015 | K13: 20 | L13: 3231.3899 | M13: 2911.6157 | N13: 3298.8823 | O13: 864.98095 | P13: 807.11825 | Q13: 794.63399 | R13: 785.75554 | S13: 781.90594 | T13: 780.76753 | U13: =T13 -> 780.76753 | V13: 0.85638231 | W13: 0.85638231 | X13: 0.93986126 | Y13: 0.80791486 | Z13: 0.82064163 | AA13: 0.82094258 | AB13: 0.82145798 | AC13: 0.82158957 | AD13: 0.82145676 | AE13: =AD13 -> 0.82145676 | AF13: =0.5*AF12 -> #REF! | AG13: 0.28 | AH13: 0 | AJ13: =Technologies!M13 -> R2,R3,R4,R5,R6
A14: TLCELC200 | B14: TLCELCB | C14: TL.ELC.C.ELC200 | D14: bn-vmt, bn-vmt/a | E14: TRNELC | F14: TL | G14: =IF($J14<G$1,0,"") | H14: 1 | I14: 2020 | J14: 2020 | K14: 20 | L14: 0 | M14: 0 | N14: 3827.0933 | O14: 2457.8977 | P14: 2231.8283 | Q14: 2172.4737 | R14: 2138.6708 | S14: 2122.9681 | T14: 2112.5633 | U14: =T14 -> 2112.5633 | V14: 0 | W14: 0 | X14: 1.0623621 | Y14: 0.87517546 | Z14: 0.89148181 | AA14: 0.89484281 | AB14: 0.89972484 | AC14: 0.90136399 | AD14: 0.9023557 | AE14: =AD14 -> 0.9023557 | AF14: =0.5*AF12 -> #REF! | AG14: 0.28 | AH14: 0 | AJ14: =Technologies!M14 -> R2,R3,R4,R5,R6
A15: TLCDSL11 | B15: TLCDSL10 | C15: TL.DSL.C.DSL.2011 | D15: bn-vmt, bn-vmt/a | E15: TRNDSL | F15: TL | H15: 1 | I15: 2011 | J15: =INDEX(ConsolidatedVehData!$D$22:$D$858,MATCH(B15,ConsolidatedVehData!$A$22:$A$858,0)) -> 2010 | K15: 20 | L15: 1966.6678 | M15: 2215.9891 | N15: 2784.0095 | O15: 2407.211 | P15: 2444.0793 | Q15: 2467.188 | R15: 2487.8222 | S15: 2504.3427 | T15: 2519.2067 | U15: =T15 -> 2519.2067 | V15: 0.28561862 | W15: 0.31185469 | X15: 0.32167604 | Y15: 0.3371585 | Z15: 0.34630264 | AA15: 0.3466543 | AB15: 0.34829945 | AC15: 0.3465202 | AD15: 0.34503343 | AE15: =AD15 -> 0.34503343 | AF15: =INDEX(ConsolidatedVehData!$AB$22:$AB$858,MATCH(B15,ConsolidatedVehData!$A$22:$A$858,0)) -> #REF! | AG15: 0.24 | AH15: 0 | AJ15: =Technologies!M15 -> R2,R3,R4,R5,R6
A16: TLCCNG11 | B16: TLCCNG10 | C16: TL.CNG.C.CNG.2011 | D16: bn-vmt, bn-vmt/a | E16: TRNCNGL | F16: TL | H16: 1 | I16: 2011 | J16: =INDEX(ConsolidatedVehData!$D$22:$D$858,MATCH(B16,ConsolidatedVehData!$A$22:$A$858,0)) -> 2010 | K16: 20 | L16: 2358.8235 | M16: 2469.0886 | N16: 2911.51 | O16: 1452.4185 | P16: 1455.3022 | Q16: 1455.3466 | R16: 1471.4272 | S16: 1474.6165 | T16: 1476.0495 | U16: =T16 -> 1476.0495 | V16: 0.24668554 | W16: 0.27278546 | X16: 0.28755158 | Y16: 0.21060449 | Z16: 0.22011832 | AA16: 0.21760381 | AB16: 0.21777031 | AC16: 0.21706947 | AD16: 0.21649927 | AE16: =AD16 -> 0.21649927 | AF16: =INDEX(ConsolidatedVehData!$AB$22:$AB$858,MATCH(B16,ConsolidatedVehData!$A$22:$A$858,0)) -> #REF! | AG16: 0.24 | AH16: 0 | AJ16: =Technologies!M16 -> R2,R3,R4,R5,R6
A17: TLCCNGX11 | B17: TLCCNGX10 | C17: TL.CNGX.C.CNGX.2011 | D17: bn-vmt, bn-vmt/a | E17: TRNCNGX | F17: TL | G17: 0 | H17: 1 | I17: 2011 | J17: =INDEX(ConsolidatedVehData!$D$22:$D$858,MATCH(B17,ConsolidatedVehData!$A$22:$A$858,0)) -> 2010 | K17: 20 | L17: 2239.4732 | M17: 2351.055 | N17: 2795.2967 | O17: 1392.1924 | P17: 1395.1176 | Q17: 1395.3633 | R17: 1411.7446 | S17: 1414.856 | T17: 1416.332 | U17: =T17 -> 1416.332 | V17: 0.22859409 | W17: 0.25257915 | X17: 0.26734603 | Y17: 0.19610634 | Z17: 0.2048795 | AA17: 0.20272311 | AB17: 0.20355799 | AC17: 0.20296736 | AD17: 0.20252472 | AE17: =AD17 -> 0.20252472 | AF17: =INDEX(ConsolidatedVehData!$AB$22:$AB$858,MATCH(B17,ConsolidatedVehData!$A$22:$A$858,0)) -> #REF! | AG17: 0.24 | AH17: 0 | AJ17: =Technologies!M17 -> R2,R3,R4,R5,R6
A18: *TLCDHEV15 | B18: TLCDHEV15 | C18: TL.DSL.C.DHEV.2015 | D18: bn-vmt, bn-vmt/a | E18: TRNDSL | F18: TL | H18: 1 | I18: 2020 | J18: 2020 | K18: 20 | L18: 0 | M18: 0 | N18: 0 | O18: 0 | P18: 0 | Q18: 0 | R18: 0 | S18: 0 | T18: 0 | U18: =T18 -> 0 | V18: 0 | W18: 0 | X18: 0 | Y18: 0 | Z18: 0 | AA18: 0 | AB18: 0 | AC18: 0 | AD18: 0 | AE18: =AD18 -> 0 | AJ18: =Technologies!M18 -> *R2,R3,R4,R5,R6
A19: TLCETHX11 | B19: TLCETHX10 | C19: TL.E85X.C.ETHX.2011 | D19: bn-vmt, bn-vmt/a | E19: TLE85X | F19: TL | H19: 1 | I19: 2011 | J19: =INDEX(ConsolidatedVehData!$D$22:$D$858,MATCH(B19,ConsolidatedVehData!$A$22:$A$858,0)) -> 2010 | K19: 20 | L19: 1757.5977 | M19: 1909.6327 | N19: 2474.4068 | O19: 2158.0922 | P19: 2209.7187 | Q19: 2234.5437 | R19: 2260.9156 | S19: 2280.1852 | T19: 2298.2913 | U19: =T19 -> 2298.2913 | V19: 0.22981262 | W19: 0.24997875 | X19: 0.26097025 | Y19: 0.29964882 | Z19: 0.3137066 | AA19: 0.31382515 | AB19: 0.31658023 | AC19: 0.31587693 | AD19: 0.31548409 | AE19: =AD19 -> 0.31548409 | AF19: =INDEX(ConsolidatedVehData!$AB$22:$AB$858,MATCH(B19,ConsolidatedVehData!$A$22:$A$858,0)) -> #REF! | AG19: 0.18 | AH19: 0 | AJ19: =Technologies!M19 -> R2,R3,R4,R5,R6
A20: TLCFCH11 | B20: TLCFCH10 | C20: TL.H2.C.FCH.2011 | D20: bn-vmt, bn-vmt/a | E20: TRNH2 | F20: TL | H20: 1 | I20: 2011 | J20: =INDEX(ConsolidatedVehData!$D$22:$D$858,MATCH(B20,ConsolidatedVehData!$A$22:$A$858,0)) -> 2010 | K20: 20 | L20: =M20 -> 6353.3245 | M20: 6353.3245 | N20: 5699.9065 | O20: 4601.7849 | P20: 4195.0068 | Q20: 3880.7048 | R20: 3630.7102 | S20: 3435.624 | T20: 3280.9057 | U20: =T20 -> 3280.9057 | V20: =W20 -> 0.35093368 | W20: 0.35093368 | X20: 0.36515866 | Y20: 0.35101908 | Z20: 0.35524503 | AA20: 0.35650584 | AB20: 0.35825788 | AC20: 0.3588399 | AD20: 0.35917241 | AE20: =AD20 -> 0.35917241 | AF20: =INDEX(ConsolidatedVehData!$AB$22:$AB$858,MATCH(B20,ConsolidatedVehData!$A$22:$A$858,0)) -> #REF! | AG20: 0.28 | AH20: 0 | AJ20: =Technologies!M20 -> *R2,R3,R4,R5,R6
A21: TLCGHEV11 | B21: TLCHEV10 | C21: TL.GSL.C.HEV.2011 | D21: bn-vmt, bn-vmt/a | E21: TLGSL | F21: TL | H21: 1 | I21: 2011 | J21: =INDEX(ConsolidatedVehData!$D$22:$D$858,MATCH(B21,ConsolidatedVehData!$A$22:$A$858,0)) -> 2010 | K21: 20 | L21: 2045.0717 | M21: 2310.5405 | N21: 2798.8912 | O21: 2241.7542 | P21: 2260.4491 | Q21: 2270.3986 | R21: 2285.5443 | S21: 2297.8918 | T21: 2308.9777 | U21: =T21 -> 2308.9777 | V21: 0.32799402 | W21: 0.35888038 | X21: 0.36700087 | Y21: 0.41269668 | Z21: 0.4283797 | AA21: 0.42446001 | AB21: 0.42498343 | AC21: 0.42304113 | AD21: 0.42188661 | AE21: =AD21 -> 0.42188661 | AF21: =INDEX(ConsolidatedVehData!$AB$22:$AB$858,MATCH(B21,ConsolidatedVehData!$A$22:$A$858,0)) -> #REF! | AG21: 0.24 | AH21: 0 | AJ21: =Technologies!M21 -> R2,R3,R4,R5,R6
A22: TLCLPGX11 | B22: TLCLPGX10 | C22: TL.LPGX.C.LPGX.2011 | D22: bn-vmt, bn-vmt/a | E22: TRNLPGX | F22: TL | G22: 0 | H22: 1 | I22: 2011 | J22: =INDEX(ConsolidatedVehData!$D$22:$D$858,MATCH(B22,ConsolidatedVehData!$A$22:$A$858,0)) -> 2010 | K22: 20 | L22: 2185.701 | M22: 2298.0063 | N22: 2742.8219 | O22: 1363.9481 | P22: 1366.8996 | Q22: 1367.3921 | R22: 1383.2663 | S22: 1386.3685 | T22: 1387.8669 | U22: =T22 -> 1387.8669 | V22: 0.22859558 | W22: 0.25257915 | X22: 0.26791547 | Y22: 0.19666915 | Z22: 0.20534171 | AA22: 0.20347386 | AB22: 0.20408735 | AC22: 0.20350064 | AD22: 0.20301152 | AE22: =AD22 -> 0.20301152 | AF22: =INDEX(ConsolidatedVehData!$AB$22:$AB$858,MATCH(B22,ConsolidatedVehData!$A$22:$A$858,0)) -> #REF! | AG22: 0.24 | AH22: 0 | AJ22: =Technologies!M22 -> R2,R3,R4,R5,R6
A23: TLCGPHEV10 | B23: TLCPHVG10 | C23: TL.GSL.C.PHEV.2011 | D23: bn-vmt, bn-vmt/a | E23: TLGSL | H23: =1-H24 -> #REF! | I23: 2011 | J23: =INDEX(ConsolidatedVehData!$D$22:$D$858,MATCH(B23,ConsolidatedVehData!$A$22:$A$858,0)) -> 2010 | K23: 20 | L23: =M23 -> 2523.1024 | M23: 2523.1024 | N23: 2866.7614 | O23: 2599.4581 | P23: 2562.0364 | Q23: 2530.4634 | R23: 2522.7612 | S23: 2525.1092 | T23: 2530.9021 | U23: =T23 -> 2530.9021 | V23: 0 | W23: 0.38308764 | X23: 0.40544253 | Y23: 0.3695289 | Z23: 0.38301035 | AA23: 0.38358568 | AB23: 0.38653686 | AC23: 0.38620726 | AD23: 0.38601724 | AE23: =AD23 -> 0.38601724 | AF23: =INDEX(ConsolidatedVehData!$AB$22:$AB$858,MATCH(B23,ConsolidatedVehData!$A$22:$A$858,0)) -> #REF! | AG23: 0.28 | AH23: 0 | AJ23: =Technologies!M23 -> R2,R3,R4,R5,R6
E24: TRNELC | H24: =INDEX(ConsolidatedVehData!$AG$22:$AG$858,MATCH(B23,ConsolidatedVehData!$A$22:$A$858,0)) -> #REF!
F25: TL
A26: TLFGSLC11 | B26: TLFCONV10 | C26: TL.GSL.F.CONV.2011 | D26: bn-vmt, bn-vmt/a | E26: TLGSL | F26: TL | H26: 1 | I26: 2011 | J26: =INDEX(ConsolidatedVehData!$D$22:$D$858,MATCH(B26,ConsolidatedVehData!$A$22:$A$858,0)) -> 2010 | K26: 20 | L26: 2179.1253 | M26: 2184.927 | N26: 2278.4535 | O26: 2051.7269 | P26: 2101.5781 | Q26: 2123.2134 | R26: 2148.88 | S26: 2168.9391 | T26: 2187.4473 | U26: =T26 -> 2187.4473 | V26: 0.22579871 | W26: 0.23205197 | X26: 0.28321835 | Y26: 0.31323662 | Z26: 0.32667799 | AA26: 0.3234353 | AB26: 0.32541914 | AC26: 0.32429831 | AD26: 0.3240026 | AE26: =AD26 -> 0.3240026 | AF26: =INDEX(ConsolidatedVehData!$AB$22:$AB$858,MATCH(B26,ConsolidatedVehData!$A$22:$A$858,0)) -> #REF! | AG26: 0.18 | AH26: 0 | AJ26: =Technologies!M24 -> R2,R3,R4,R5,R6
A27: TLFELC100 | B27: TLFELC | C27: Electric fullsize car w/100 mi range | D27: bn-vmt, bn-vmt/a | E27: TRNELC | F27: TL | G27: =IF($J27<G$1,0,"") | H27: 1 | I27: 2015 | J27: 2015 | K27: 20 | L27: 0 | M27: 3177.0824 | N27: 3098.4757 | O27: 3307.3787 | P27: 3165.3446 | Q27: 3123.8024 | R27: 3107.4457 | S27: 3095.8173 | T27: 3089.6312 | U27: =T27 -> 3089.6312 | V27: 0 | W27: 0.78511683 | X27: 0.9259943 | Y27: 0.43737237 | Z27: 0.44310991 | AA27: 0.44192602 | AB27: 0.44265342 | AC27: 0.44104703 | AD27: 0.44006058 | AE27: =AD27 -> 0.44006058 | AF27: =0.5*AF26 -> #REF! | AG27: 0.28 | AH27: 0 | AJ27: =Technologies!M25 -> R2,R3,R4,R5,R6
A28: TLFELC200 | B28: TLFELCB | C28: Electric fullsize car w/200 mi range | D28: bn-vmt, bn-vmt/a | E28: TRNELC | F28: TL | G28: =IF($J28<G$1,0,"") | H28: 1 | I28: 2015 | J28: 2020 | K28: 20 | L28: 0 | M28: 5564.2245 | N28: 3851.1125 | O28: 3556.7185 | P28: 3344.6153 | Q28: 3285.9921 | R28: 3259.6683 | S28: 3241.6917 | T28: 3230.6826 | U28: =T28 -> 3230.6826 | V28: 0 | W28: 0.74385125 | X28: 1.0203922 | Y28: 0.83899436 | Z28: 0.85207635 | AA28: 0.85551207 | AB28: 0.86053925 | AC28: 0.86214255 | AD28: 0.86362892 | AE28: =AD28 -> 0.86362892 | AF28: =0.5*AF26 -> #REF! | AG28: 0.28 | AH28: 0 | AJ28: =Technologies!M26 -> R2,R3,R4,R5,R6
A29: TLFCNG11 | B29: TLFCNG10 | C29: TL.CNG.F.CNG.2011 | D29: bn-vmt, bn-vmt/a | E29: TRNCNGL | F29: TL | H29: 1 | I29: 2011 | J29: =INDEX(ConsolidatedVehData!$D$22:$D$858,MATCH(B29,ConsolidatedVehData!$A$22:$A$858,0)) -> 2010 | K29: 20 | L29: 3234.3071 | M29: 3766.3624 | N29: 3294.0991 | O29: 1256.4477 | P29: 1263.0512 | Q29: 1269.7657 | R29: 1277.3889 | S29: 1284.3992 | T29: 1289.0091 | U29: =T29 -> 1289.0091 | V29: 0.21524556 | W29: 0.20358325 | X29: 0.27604705 | Y29: 0.14465131 | Z29: 0.15258005 | AA29: 0.15149485 | AB29: 0.15165203 | AC29: 0.15184142 | AD29: 0.15221818 | AE29: =AD29 -> 0.15221818 | AF29: =INDEX(ConsolidatedVehData!$AB$22:$AB$858,MATCH(B29,ConsolidatedVehData!$A$22:$A$858,0)) -> #REF! | AG29: 0.24 | AH29: 0 | AJ29: =Technologies!M27 -> R2,R3,R4,R5,R6
A30: TLFCNGX11 | B30: TLFCNGX10 | C30: TL.CNGX.F.CNGX.2011 | D30: bn-vmt, bn-vmt/a | E30: TRNCNGX | F30: TL | G30: 0 | H30: 1 | I30: 2011 | J30: =INDEX(ConsolidatedVehData!$D$22:$D$858,MATCH(B30,ConsolidatedVehData!$A$22:$A$858,0)) -> 2010 | K30: 20 | L30: 3115.1547 | M30: 3648.3286 | N30: 3178.4352 | O30: 1208.2291 | P30: 1214.7574 | Q30: 1221.2051 | R30: 1229.3399 | S30: 1236.1255 | T30: 1240.6188 | U30: =T30 -> 1240.6188 | V30: 0.19950468 | W30: 0.188503 | X30: 0.25684155 | Y30: 0.13455921 | Z30: 0.14172782 | AA30: 0.1411638 | AB30: 0.14192617 | AC30: 0.14212214 | AD30: 0.1424639 | AE30: =AD30 -> 0.1424639 | AF30: =INDEX(ConsolidatedVehData!$AB$22:$AB$858,MATCH(B30,ConsolidatedVehData!$A$22:$A$858,0)) -> #REF! | AG30: 0.24 | AH30: 0 | AJ30: =Technologies!M28 -> R2,R3,R4,R5,R6
A31: *TLFDHEV20 | B31: TLFDHEV20 | C31: TL.DSL.F.DHEV.2020 | D31: bn-vmt, bn-vmt/a | E31: TRNDSL | F31: TL | H31: 1 | I31: 2020 | J31: 2020 | K31: 20 | L31: 0 | M31: 0 | N31: 0 | O31: 0 | P31: 0 | Q31: 0 | R31: 0 | S31: 0 | T31: 0 | U31: =T31 -> 0 | V31: 0 | W31: 0 | X31: 0 | Y31: 0 | Z31: 0 | AA31: 0 | AB31: 0 | AC31: 0 | AD31: 0 | AE31: =AD31 -> 0 | AF31: =INDEX(ConsolidatedVehData!$AB$22:$AB$858,MATCH(B31,ConsolidatedVehData!$A$22:$A$858,0)) -> #REF! | AG31: 0.24 | AH31: 0 | AJ31: =Technologies!M29 -> *R2,R3,R4,R5,R6
A32: TLFDSL11 | B32: TLFDSL10 | C32: TL.DSL.F.DSL.2011 | D32: bn-vmt, bn-vmt/a | E32: TRNDSL | F32: TL | H32: 1 | I32: 2011 | J32: =INDEX(ConsolidatedVehData!$D$22:$D$858,MATCH(B32,ConsolidatedVehData!$A$22:$A$858,0)) -> 2010 | K32: 20 | L32: 2363.327 | M32: 2499.9035 | N32: 2579.3047 | O32: 2308.1866 | P32: 2346.1751 | Q32: 2366.7932 | R32: 2385.387 | S32: 2402.2835 | T32: 2417.3441 | U32: =T32 -> 2417.3441 | V32: 0.28280164 | W32: 0.29238549 | X32: 0.34441447 | Y32: 0.35329348 | Z32: 0.36168984 | AA32: 0.35997545 | AB32: 0.36001047 | AC32: 0.35778709 | AD32: 0.3562221 | AE32: =AD32 -> 0.3562221 | AF32: =INDEX(ConsolidatedVehData!$AB$22:$AB$858,MATCH(B32,ConsolidatedVehData!$A$22:$A$858,0)) -> #REF! | AG32: 0.24 | AH32: 0 | AJ32: =Technologies!M30 -> R2,R3,R4,R5,R6
A33: TLFETHX11 | B33: TLFETHX10 | C33: TL.E85X.F.ETHX.2011 | D33: bn-vmt, bn-vmt/a | E33: TLE85X | F33: TL | H33: 1 | I33: 2011 | J33: =INDEX(ConsolidatedVehData!$D$22:$D$858,MATCH(B33,ConsolidatedVehData!$A$22:$A$858,0)) -> 2010 | K33: 20 | L33: 2187.8082 | M33: 2193.5473 | N33: 2286.83 | O33: 2059.1174 | P33: 2108.942 | Q33: 2130.4823 | R33: 2155.919 | S33: 2175.9227 | T33: 2194.3704 | U33: =T33 -> 2194.3704 | V33: 0.22803315 | W33: 0.23437248 | X33: 0.28588027 | Y33: 0.31611825 | Z33: 0.32972952 | AA33: 0.32634247 | AB33: 0.32819896 | AC33: 0.32705964 | AD33: 0.32676928 | AE33: =AD33 -> 0.32676928 | AF33: =INDEX(ConsolidatedVehData!$AB$22:$AB$858,MATCH(B33,ConsolidatedVehData!$A$22:$A$858,0)) -> #REF! | AG33: 0.18 | AH33: 0 | AJ33: =Technologies!M31 -> R2,R3,R4,R5,R6
A34: TLFFCH15 | B34: TLFFCH15 | C34: TL.H2.F.FCH.2015 | D34: bn-vmt, bn-vmt/a | E34: TRNH2 | F34: TL | H34: 1 | I34: 2015 | J34: =INDEX(ConsolidatedVehData!$D$22:$D$858,MATCH(B34,ConsolidatedVehData!$A$22:$A$858,0)) -> 2015 | K34: 20 | L34: 0 | M34: 6562.3822 | N34: 5616.4373 | O34: =N34 -> 5616.4373 | P34: =O34 -> 5616.4373 | Q34: =P34 -> 5616.4373 | R34: =Q34 -> 5616.4373 | S34: =R34 -> 5616.4373 | T34: =S34 -> 5616.4373 | U34: =T34 -> 5616.4373 | V34: 0 | W34: 0.32451983 | X34: 0.35073268 | Y34: 0.33713548 | Z34: 0.3403773 | AA34: 0.34172423 | AB34: 0.34364203 | AC34: 0.34424208 | AD34: 0.34479546 | AE34: =AD34 -> 0.34479546 | AF34: =INDEX(ConsolidatedVehData!$AB$22:$AB$858,MATCH(B34,ConsolidatedVehData!$A$22:$A$858,0)) -> #REF! | AG34: 0.28 | AH34: 0 | AJ34: =Technologies!M32 -> *R2,R3,R4,R5,R6
A35: TLFGHEV11 | B35: TLFHEV10 | C35: TL.GSL.F.HEV.2011 | D35: bn-vmt, bn-vmt/a | E35: TLGSL | F35: TL | H35: 1 | I35: 2011 | J35: =INDEX(ConsolidatedVehData!$D$22:$D$858,MATCH(B35,ConsolidatedVehData!$A$22:$A$858,0)) -> 2010 | K35: 20 | L35: 2486.9194 | M35: 2655.1751 | N35: 2653.098 | O35: 3425.4638 | P35: 3441.2605 | Q35: 3446.8041 | R35: 3462.0924 | S35: 3466.3832 | T35: 3471.5982 | U35: =T35 -> 3471.5982 | V35: 0.32530032 | W35: 0.33647538 | X35: 0.40311534 | Y35: 0.43755224 | Z35: 0.45167565 | AA35: 0.44469431 | AB35: 0.44385239 | AC35: 0.44100435 | AD35: 0.43943756 | AE35: =AD35 -> 0.43943756 | AF35: =INDEX(ConsolidatedVehData!$AB$22:$AB$858,MATCH(B35,ConsolidatedVehData!$A$22:$A$858,0)) -> #REF! | AG35: 0.24 | AH35: 0 | AJ35: =Technologies!M33 -> R2,R3,R4,R5,R6
A36: TLFLPGX11 | B36: TLFLPGX10 | C36: TL.LPGX.F.LPGX.2011 | D36: bn-vmt, bn-vmt/a | E36: TRNLPGX | F36: TL | G36: 0 | H36: 1 | I36: 2011 | J36: =INDEX(ConsolidatedVehData!$D$22:$D$858,MATCH(B36,ConsolidatedVehData!$A$22:$A$858,0)) -> 2010 | K36: 20 | L36: 2656.2576 | M36: 2655.7344 | N36: 2748.0052 | O36: 2477.9709 | P36: 2483.9551 | Q36: 2491.7264 | R36: 2518.7688 | S36: 2523.8147 | T36: 2528.3317 | U36: =T36 -> 2528.3317 | V36: 0.22579725 | W36: 0.23205197 | X36: 0.28290242 | Y36: 0.31267899 | Z36: 0.32600022 | AA36: 0.32277826 | AB36: 0.32477509 | AC36: 0.32364406 | AD36: 0.32332167 | AE36: =AD36 -> 0.32332167 | AF36: =INDEX(ConsolidatedVehData!$AB$22:$AB$858,MATCH(B36,ConsolidatedVehData!$A$22:$A$858,0)) -> #REF! | AG36: 0.24 | AH36: 0 | AJ36: =Technologies!M34 -> R2,R3,R4,R5,R6
A37: TLFGPHEV10 | B37: TLFPHVG10 | C37: TL.GSL.F.PHEV.2011 | D37: bn-vmt, bn-vmt/a | E37: TLGSL | H37: =1-H38 -> #REF! | I37: 2011 | J37: =INDEX(ConsolidatedVehData!$D$22:$D$858,MATCH(B37,ConsolidatedVehData!$A$22:$A$858,0)) -> 2010 | K37: 20 | L37: =M37 -> 3073.2874 | M37: 3073.2874 | N37: 3036.1525 | O37: 2543.3387 | P37: 2500.6987 | Q37: 2464.1416 | R37: 2451.7027 | S37: 2453.0904 | T37: 2458.582 | U37: =T37 -> 2458.582 | V37: 0 | W37: 0.3445613 | X37: 0.41990311 | Y37: 0.38127558 | Z37: 0.39388941 | AA37: 0.39160311 | AB37: 0.39367271 | AC37: 0.3930067 | AD37: 0.39297739 | AE37: =AD37 -> 0.39297739 | AF37: =INDEX(ConsolidatedVehData!$AB$22:$AB$858,MATCH(B37,ConsolidatedVehData!$A$22:$A$858,0)) -> #REF! | AG37: 0.28 | AJ37: =Technologies!M35 -> R2,R3,R4,R5,R6
E38: TRNELC | H38: =INDEX(ConsolidatedVehData!$AG$22:$AG$858,MATCH(B37,ConsolidatedVehData!$A$22:$A$858,0)) -> #REF!
F39: TL
A40: TLMGSLC11 | B40: TLMCONV10 | C40: TL.GSL.M.CONV.2011 | D40: bn-vmt, bn-vmt/a | E40: TLGSL | F40: TL | H40: 1 | I40: 2011 | J40: =INDEX(ConsolidatedVehData!$D$22:$D$858,MATCH(B40,ConsolidatedVehData!$A$22:$A$858,0)) -> 2010 | K40: 20 | L40: 2351.4662 | M40: 2290.0448 | N40: 2474.0619 | O40: 2156.3581 | P40: 2230.9836 | Q40: 2251.4764 | R40: 2264.918 | S40: 2270.7773 | T40: 2276.9184 | U40: =T40 -> 2276.9184 | V40: 0.1717302 | W40: 0.17812069 | X40: 0.19408797 | Y40: 0.2577156 | Z40: 0.28219751 | AA40: 0.28619193 | AB40: 0.29021088 | AC40: 0.29062154 | AD40: 0.290962 | AE40: =AD40 -> 0.290962 | AF40: =INDEX(ConsolidatedVehData!$AB$22:$AB$858,MATCH(B40,ConsolidatedVehData!$A$22:$A$858,0)) -> #REF! | AG40: 0.18 | AH40: 0 | AJ40: =Technologies!M36 -> R2,R3,R4,R5,R6
A41: *TLMELC100 | B41: TLMELC | C41: Electric minivan w/100 mi range | D41: bn-vmt, bn-vmt/a | E41: TRNELC | F41: TL | G41: =IF($J41<G$1,0,"") | H41: 1 | I41: 2020 | J41: 2020 | K41: 20 | AF41: =0.5*AF40 -> #REF! | AG41: 0.28 | AH41: 0 | AJ41: =Technologies!M37 -> *R2,R3,R4,R5,R6
A42: TLMELC200 | B42: TLMELCB | C42: Electric minivan w/200 mi range | D42: bn-vmt, bn-vmt/a | E42: TRNELC | F42: TL | G42: =IF($J42<G$1,0,"") | H42: 1 | I42: 2025 | J42: 2020 | K42: 20 | L42: 0 | M42: 0 | N42: 0 | O42: 4308.6384 | P42: 3966.185 | Q42: 3865.5484 | R42: 3808.5568 | S42: 3773.2593 | T42: 3751.9724 | U42: =T42 -> 3751.9724 | V42: 0 | W42: 0 | X42: 0 | Y42: 0.40134315 | Z42: 0.41106552 | AA42: 0.41594254 | AB42: 0.41744451 | AC42: 0.41874 | AD42: 0.41841515 | AE42: =AD42 -> 0.41841515 | AF42: =0.5*AF40 -> #REF! | AG42: 0.28 | AH42: 0 | AJ42: =Technologies!M38 -> R2,R3,R4,R5,R6
A43: TLMCNG11 | B43: TLMCNG10 | C43: TL.CNG.M.CNG.2011 | D43: bn-vmt, bn-vmt/a | E43: TRNCNGL | F43: TL | H43: 1 | I43: 2011 | J43: =INDEX(ConsolidatedVehData!$D$22:$D$858,MATCH(B43,ConsolidatedVehData!$A$22:$A$858,0)) -> 2010 | K43: 20 | L43: 3112.5723 | M43: 3108.9537 | N43: 3135.9421 | O43: 1381.0306 | P43: 1394.1899 | Q43: 1382.2454 | R43: 1389.6202 | S43: 1386.7896 | T43: 1390.2892 | U43: =T43 -> 1390.2892 | V43: 0.18511771 | W43: 0.18640126 | X43: 0.20024204 | Y43: 0.11349073 | Z43: 0.1226857 | AA43: 0.12382378 | AB43: 0.12597156 | AC43: 0.12595119 | AD43: 0.12645011 | AE43: =AD43 -> 0.12645011 | AF43: =INDEX(ConsolidatedVehData!$AB$22:$AB$858,MATCH(B43,ConsolidatedVehData!$A$22:$A$858,0)) -> #REF! | AG43: 0.24 | AH43: 0 | AJ43: =Technologies!M39 -> R2,R3,R4,R5,R6
A44: TLMCNGX11 | B44: TLMCNGX10 | C44: TL.CNGX.M.CNGX.2011 | D44: bn-vmt, bn-vmt/a | E44: TRNCNGX | F44: TL | G44: 0 | H44: 1 | I44: 2011 | J44: =INDEX(ConsolidatedVehData!$D$22:$D$858,MATCH(B44,ConsolidatedVehData!$A$22:$A$858,0)) -> 2010 | K44: 20 | L44: 3030.8887 | M44: 3027.859 | N44: 3058.7997 | O44: 1349.61 | P44: 1362.1957 | Q44: 1350.8203 | R44: 1358.5732 | S44: 1355.8073 | T44: 1359.157 | U44: =T44 -> 1359.157 | V44: 0.17158124 | W44: 0.17259373 | X44: 0.18659671 | Y44: 0.10545418 | Z44: 0.11400587 | AA44: 0.11534939 | AB44: 0.1174622 | AC44: 0.11736505 | AD44: 0.11782057 | AE44: =AD44 -> 0.11782057 | AF44: =INDEX(ConsolidatedVehData!$AB$22:$AB$858,MATCH(B44,ConsolidatedVehData!$A$22:$A$858,0)) -> #REF! | AG44: 0.24 | AH44: 0 | AJ44: =Technologies!M40 -> R2,R3,R4,R5,R6
A45: *TLMDHEV15 | B45: TLMDHEV15 | C45: TL.DSL.M.DHEV.2015 | D45: bn-vmt, bn-vmt/a | E45: TRNDSL | F45: TL | H45: 1 | I45: 2015 | J45: =INDEX(ConsolidatedVehData!$D$22:$D$858,MATCH(B45,ConsolidatedVehData!$A$22:$A$858,0)) -> 2015 | K45: 20 | L45: 0 | M45: 0 | N45: 0 | O45: 0 | P45: 0 | Q45: 0 | R45: 0 | S45: 0 | T45: 0 | U45: =T45 -> 0 | V45: 0 | W45: 0 | X45: 0 | Y45: 0 | Z45: 0 | AA45: 0 | AB45: 0 | AC45: 0 | AD45: 0 | AE45: =AD45 -> 0 | AF45: =INDEX(ConsolidatedVehData!$AB$22:$AB$858,MATCH(B45,ConsolidatedVehData!$A$22:$A$858,0)) -> #REF! | AG45: 0.24 | AH45: 0 | AJ45: =Technologies!M41 -> *R2,R3,R4,R5,R6
A46: TLMDSL11 | B46: TLMDSL10 | C46: TL.DSL.M.DSL.2011 | D46: bn-vmt, bn-vmt/a | E46: TRNDSL | F46: TL | H46: 1 | I46: 2011 | J46: =INDEX(ConsolidatedVehData!$D$22:$D$858,MATCH(B46,ConsolidatedVehData!$A$22:$A$858,0)) -> 2010 | K46: 20 | L46: 2839.5063 | M46: 2774.5857 | N46: 2933.9786 | O46: 2551.2077 | P46: 2613.556 | Q46: 2636.8372 | R46: 2645.5687 | S46: 2650.131 | T46: 2654.7292 | U46: =T46 -> 2654.7292 | V46: 0.2148098 | W46: 0.2244321 | X46: 0.23374457 | Y46: 0.28160295 | Z46: 0.29846453 | AA46: 0.30300723 | AB46: 0.30628892 | AC46: 0.30666412 | AD46: 0.30663478 | AE46: =AD46 -> 0.30663478 | AF46: =INDEX(ConsolidatedVehData!$AB$22:$AB$858,MATCH(B46,ConsolidatedVehData!$A$22:$A$858,0)) -> #REF! | AG46: 0.24 | AH46: 0 | AJ46: =Technologies!M42 -> R2,R3,R4,R5,R6
A47: TLMETHX11 | B47: TLMETHX10 | C47: TL.E85X.M.ETHX.2011 | D47: bn-vmt, bn-vmt/a | E47: TLE85X | F47: TL | H47: 1 | I47: 2011 | J47: =INDEX(ConsolidatedVehData!$D$22:$D$858,MATCH(B47,ConsolidatedVehData!$A$22:$A$858,0)) -> 2010 | K47: 20 | L47: 2360.2898 | M47: 2298.8298 | N47: 2482.3568 | O47: 2163.9027 | P47: 2238.6127 | Q47: 2258.9947 | R47: 2272.4353 | S47: 2278.3816 | T47: 2284.482 | U47: =T47 -> 2284.482 | V47: 0.17342708 | W47: 0.1799019 | X47: 0.19588105 | Y47: 0.26022017 | Z47: 0.2849274 | AA47: 0.2888569 | AB47: 0.29284527 | AC47: 0.29326553 | AD47: 0.29358945 | AE47: =AD47 -> 0.29358945 | AF47: =INDEX(ConsolidatedVehData!$AB$22:$AB$858,MATCH(B47,ConsolidatedVehData!$A$22:$A$858,0)) -> #REF! | AG47: 0.18 | AH47: 0 | AJ47: =Technologies!M43 -> R2,R3,R4,R5,R6
A48: TLMFCH15 | B48: TLMFCH15 | C48: TL.H2.M.FCH.2015 | D48: bn-vmt, bn-vmt/a | E48: TRNH2 | F48: TL | H48: 1 | I48: 2015 | J48: =INDEX(ConsolidatedVehData!$D$22:$D$858,MATCH(B48,ConsolidatedVehData!$A$22:$A$858,0)) -> 2015 | K48: 20 | L48: 0 | M48: 6244.9204 | N48: 6730.3081 | O48: =N48 -> 6730.3081 | P48: =O48 -> 6730.3081 | Q48: =P48 -> 6730.3081 | R48: =Q48 -> 6730.3081 | S48: =R48 -> 6730.3081 | T48: =S48 -> 6730.3081 | U48: =T48 -> 6730.3081 | V48: 0 | W48: 0.32031455 | X48: 0.27228368 | Y48: 0.17673503 | Z48: 0.18011291 | AA48: 0.18223933 | AB48: 0.18287989 | AC48: 0.18344698 | AD48: 0.18330617 | AE48: =AD48 -> 0.18330617 | AF48: =INDEX(ConsolidatedVehData!$AB$22:$AB$858,MATCH(B48,ConsolidatedVehData!$A$22:$A$858,0)) -> #REF! | AG48: 0.28 | AH48: 0 | AJ48: =Technologies!M44 -> *R2,R3,R4,R5,R6
A49: TLMGHEV11 | B49: TLMHEV10 | C49: TL.GSL.M.HEV.2011 | D49: bn-vmt, bn-vmt/a | E49: TLGSL | F49: TL | H49: 1 | I49: 2011 | J49: =INDEX(ConsolidatedVehData!$D$22:$D$858,MATCH(B49,ConsolidatedVehData!$A$22:$A$858,0)) -> 2010 | K49: 20 | L49: 2484.3821 | M49: 2689.0441 | N49: 2895.0768 | O49: 3594.1599 | P49: 3649.6389 | Q49: 3654.8225 | R49: 3663.0964 | S49: 3664.0939 | T49: 3668.5964 | U49: =T49 -> 3668.5964 | V49: 0.24846007 | W49: 0.2613443 | X49: 0.27422852 | Y49: 0.36495117 | Z49: 0.39346387 | AA49: 0.39712553 | AB49: 0.3986356 | AC49: 0.39875348 | AD49: 0.39903629 | AE49: =AD49 -> 0.39903629 | AF49: =INDEX(ConsolidatedVehData!$AB$22:$AB$858,MATCH(B49,ConsolidatedVehData!$A$22:$A$858,0)) -> #REF! | AG49: 0.24 | AH49: 0 | AJ49: =Technologies!M45 -> R2,R3,R4,R5,R6
A50: TLMLPG11 | B50: TLMLPG10 | C50: TL.LPG1.M.LPG.2011 | D50: bn-vmt, bn-vmt/a | E50: TRNLPGEA | F50: TL | H50: 1 | I50: 2011 | J50: =INDEX(ConsolidatedVehData!$D$22:$D$858,MATCH(B50,ConsolidatedVehData!$A$22:$A$858,0)) -> 2010 | K50: 20 | L50: 3125.1438 | M50: 3121.118 | N50: 3150.1494 | O50: 1386.3185 | P50: 1399.2169 | Q50: 1387.3171 | R50: 1394.7919 | S50: 1391.9995 | T50: 1395.4114 | U50: =T50 -> 1395.4114 | V50: 0.17838301 | W50: 0.17949748 | X50: 0.19379129 | Y50: 0.10955068 | Z50: 0.11849186 | AA50: 0.11973125 | AB50: 0.12182433 | AC50: 0.12173708 | AD50: 0.12219998 | AE50: =AD50 -> 0.12219998 | AF50: =INDEX(ConsolidatedVehData!$AB$22:$AB$858,MATCH(B50,ConsolidatedVehData!$A$22:$A$858,0)) -> #REF! | AG50: 0.24 | AH50: 0 | AJ50: =Technologies!M46 -> R2,R3,R4,R5,R6
A51: TLMLPGX11 | B51: TLMLPGX10 | C51: TL.LPGX.M.LPGX.2011 | D51: bn-vmt, bn-vmt/a | E51: TRNLPGX | F51: TL | G51: 0 | H51: 1 | I51: 2011 | J51: =INDEX(ConsolidatedVehData!$D$22:$D$858,MATCH(B51,ConsolidatedVehData!$A$22:$A$858,0)) -> 2010 | K51: 20 | L51: 2908.9928 | M51: 2907.5686 | N51: 2939.3812 | O51: 1300.9615 | P51: 1313.4391 | Q51: 1302.6112 | R51: 1310.3294 | S51: 1307.7713 | T51: 1311.0824 | U51: =T51 -> 1311.0824 | V51: 0.17161145 | W51: 0.17259373 | X51: 0.18701742 | Y51: 0.10553315 | Z51: 0.11417098 | AA51: 0.11548273 | AB51: 0.11758301 | AC51: 0.1174861 | AD51: 0.1179434 | AE51: =AD51 -> 0.1179434 | AF51: =INDEX(ConsolidatedVehData!$AB$22:$AB$858,MATCH(B51,ConsolidatedVehData!$A$22:$A$858,0)) -> #REF! | AG51: 0.24 | AH51: 0 | AJ51: =Technologies!M47 -> R2,R3,R4,R5,R6
A52: TLVGPHEV10 | B52: TLMPHVG10 | C52: TL.GSL.M.PHEV.2011 | D52: bn-vmt, bn-vmt/a | E52: TLGSL | H52: =1-H53 -> #REF! | I52: 2011 | J52: =INDEX(ConsolidatedVehData!$D$22:$D$858,MATCH(B52,ConsolidatedVehData!$A$22:$A$858,0)) -> 2010 | K52: 20 | L52: =N52 -> 3273.91 | M52: =N52 -> 3273.91 | N52: 3273.91 | O52: 1364.2708 | P52: 1352.4197 | Q52: 1342.8522 | R52: 1328.2547 | S52: 1325.1324 | T52: 1320.4402 | U52: =T52 -> 1320.4402 | V52: 0 | W52: 0 | X52: 0.30961301 | Y52: 0.19226322 | Z52: 0.20594888 | AA52: 0.20885338 | AB52: 0.2105739 | AC52: 0.21121496 | AD52: 0.21107427 | AE52: =AD52 -> 0.21107427 | AF52: =INDEX(ConsolidatedVehData!$AB$22:$AB$858,MATCH(B52,ConsolidatedVehData!$A$22:$A$858,0)) -> #REF! | AG52: 0.28 | AH52: 0 | AJ52: =Technologies!M48 -> R2,R3,R4,R5,R6
E53: TRNELC | H53: =INDEX(ConsolidatedVehData!$AG$22:$AG$858,MATCH(B52,ConsolidatedVehData!$A$22:$A$858,0)) -> #REF!
F54: TL
A55: TLPGSLC11 | B55: TLPCONV10 | C55: TL.GSL.P.CONV.2011 | D55: bn-vmt, bn-vmt/a | E55: TLGSL | F55: TL | H55: 1 | I55: 2011 | J55: =INDEX(ConsolidatedVehData!$D$22:$D$858,MATCH(B55,ConsolidatedVehData!$A$22:$A$858,0)) -> 2010 | K55: 20 | L55: 2583.144 | M55: 2841.516 | N55: 2884.0964 | O55: 2630.9524 | P55: 2695.5099 | Q55: 2725.9624 | R55: 2745.0239 | S55: 2754.5292 | T55: 2761.5174 | U55: =T55 -> 2761.5174 | V55: 0.17038822 | W55: 0.15253469 | X55: 0.17963541 | Y55: 0.20760947 | Z55: 0.22240077 | AA55: 0.22650523 | AB55: 0.23160069 | AC55: 0.23249983 | AD55: 0.23285322 | AE55: =AD55 -> 0.23285322 | AF55: =INDEX(ConsolidatedVehData!$AB$22:$AB$858,MATCH(B55,ConsolidatedVehData!$A$22:$A$858,0)) -> #REF! | AG55: 0.18 | AH55: 0 | AJ55: =Technologies!M49 -> R2,R3,R4,R5,R6
A56: *TLPELC100 | B56: TLPELC | C56: Electric pickup truck w/100 mi range | D56: bn-vmt, bn-vmt/a | E56: TRNELC | F56: TL | G56: =IF($J56<G$1,0,"") | H56: 1 | I56: 2025 | J56: 2025 | K56: 20 | AF56: =0.5*AF55 -> #REF! | AG56: 0.28 | AH56: 0 | AJ56: =Technologies!M50 -> *R2,R3,R4,R5,R6
A57: TLPELC200 | B57: TLPELCB | C57: Electric pickup truck w/200 mi range | D57: bn-vmt, bn-vmt/a | E57: TRNELC | F57: TL | G57: =IF($J57<G$1,0,"") | H57: 1 | I57: 2020 | J57: 2025 | K57: 20 | N57: 4209.9506 | O57: 1323.1084 | P57: 1207.8024 | Q57: 1181.3349 | R57: 1167.0642 | S57: 1154.9832 | T57: 1148.2968 | U57: =T57 -> 1148.2968 | V57: 0 | W57: 0 | X57: 0.83603285 | Y57: 0.60257823 | Z57: 0.61286077 | AA57: 0.61437924 | AB57: 0.61540213 | AC57: 0.61572999 | AD57: 0.61608039 | AE57: =AD57 -> 0.61608039 | AF57: =0.5*AF55 -> #REF! | AG57: 0.28 | AH57: 0 | AJ57: =Technologies!M51 -> R2,R3,R4,R5,R6
A58: TLPCNG11 | B58: TLPCNG10 | C58: TL.CNG.P.CNG.2011 | D58: bn-vmt, bn-vmt/a | E58: TRNCNGL | F58: TL | H58: 1 | I58: 2011 | J58: =INDEX(ConsolidatedVehData!$D$22:$D$858,MATCH(B58,ConsolidatedVehData!$A$22:$A$858,0)) -> 2010 | K58: 20 | L58: 3433.6635 | M58: 3726.0043 | N58: 3659.4653 | O58: 1589.418 | P58: 1600.395 | Q58: 1601.9803 | R58: 1600.9121 | S58: 1606.0723 | T58: 1606.9576 | U58: =T58 -> 1606.9576 | V58: 0.18605869 | W58: 0.16251003 | X58: 0.19018737 | Y58: 0.087559466 | Z58: 0.092869935 | AA58: 0.094248122 | AB58: 0.094969835 | AC58: 0.09518109 | AD58: 0.095098743 | AE58: =AD58 -> 0.095098743 | AF58: =INDEX(ConsolidatedVehData!$AB$22:$AB$858,MATCH(B58,ConsolidatedVehData!$A$22:$A$858,0)) -> #REF! | AG58: 0.24 | AH58: 0 | AJ58: =Technologies!M52 -> R2,R3,R4,R5,R6
A59: TLPCNGX11 | B59: TLPCNGX10 | C59: TL.CNGX.P.CNGX.2011 | D59: bn-vmt, bn-vmt/a | E59: TRNCNGX | F59: TL | G59: 0 | H59: 1 | I59: 2011 | J59: =INDEX(ConsolidatedVehData!$D$22:$D$858,MATCH(B59,ConsolidatedVehData!$A$22:$A$858,0)) -> 2010 | K59: 20 | L59: 3351.9435 | M59: 3644.9095 | N59: 3581.1785 | O59: 1558.692 | P59: 1568.8789 | Q59: 1570.6145 | R59: 1570.5296 | S59: 1575.685 | T59: 1576.6065 | U59: =T59 -> 1576.6065 | V59: 0.17241658 | W59: 0.15047227 | X59: 0.17674197 | Y59: 0.081260369 | Z59: 0.086214014 | AA59: 0.087632438 | AB59: 0.088281116 | AC59: 0.088493291 | AD59: 0.088395005 | AE59: =AD59 -> 0.088395005 | AF59: =INDEX(ConsolidatedVehData!$AB$22:$AB$858,MATCH(B59,ConsolidatedVehData!$A$22:$A$858,0)) -> #REF! | AG59: 0.24 | AH59: 0 | AJ59: =Technologies!M53 -> R2,R3,R4,R5,R6
A60: TLPDSL11 | B60: TLPDSL10 | C60: TL.DSL.P.DSL.2011 | D60: bn-vmt, bn-vmt/a | E60: TRNDSL | F60: TL | H60: 1 | I60: 2011 | J60: =INDEX(ConsolidatedVehData!$D$22:$D$858,MATCH(B60,ConsolidatedVehData!$A$22:$A$858,0)) -> 2010 | K60: 20 | L60: 3070.5409 | M60: 3326.0569 | N60: 3333.5858 | O60: 3012.8036 | P60: 3071.038 | Q60: 3099.2146 | R60: 3109.8715 | S60: 3116.7634 | T60: 3122.2386 | U60: =T60 -> 3122.2386 | V60: 0.21300289 | W60: 0.1921937 | X60: 0.21289053 | Y60: 0.22496716 | Z60: 0.236439 | AA60: 0.24016258 | AB60: 0.2434428 | AC60: 0.24381969 | AD60: 0.24402247 | AE60: =AD60 -> 0.24402247 | AF60: =INDEX(ConsolidatedVehData!$AB$22:$AB$858,MATCH(B60,ConsolidatedVehData!$A$22:$A$858,0)) -> #REF! | AG60: 0.24 | AH60: 0 | AJ60: =Technologies!M54 -> R2,R3,R4,R5,R6
A61: TLPETHX11 | B61: TLPETHX10 | C61: TL.E85X.P.ETHX.2011 | D61: bn-vmt, bn-vmt/a | E61: TLE85X | F61: TL | H61: 1 | I61: 2011 | J61: =INDEX(ConsolidatedVehData!$D$22:$D$858,MATCH(B61,ConsolidatedVehData!$A$22:$A$858,0)) -> 2010 | K61: 20 | L61: 2591.9757 | M61: 2850.3011 | N61: 2892.5371 | O61: 2638.3317 | P61: 2702.9071 | Q61: 2733.1468 | R61: 2752.1874 | S61: 2761.7579 | T61: 2768.7377 | U61: =T61 -> 2768.7377 | V61: 0.17207386 | W61: 0.15406004 | X61: 0.18132363 | Y61: 0.20959552 | Z61: 0.22450678 | AA61: 0.22857802 | AB61: 0.23368579 | AC61: 0.23461703 | AD61: 0.23498272 | AE61: =AD61 -> 0.23498272 | AF61: =INDEX(ConsolidatedVehData!$AB$22:$AB$858,MATCH(B61,ConsolidatedVehData!$A$22:$A$858,0)) -> #REF! | AG61: 0.18 | AH61: 0 | AJ61: =Technologies!M55 -> R2,R3,R4,R5,R6
A62: TLGPHEV15 | B62: TLPHEV15 | C62: TL.GSL.P.HEV.2015 | D62: bn-vmt, bn-vmt/a | E62: TLGSL | F62: TL | H62: 1 | I62: 2015 | J62: =INDEX(ConsolidatedVehData!$D$22:$D$858,MATCH(B62,ConsolidatedVehData!$A$22:$A$858,0)) -> 2015 | K62: 20 | L62: 0 | M62: 3609.6844 | N62: 3336.1199 | O62: 2373.0207 | P62: 2413.8685 | Q62: 2422.3731 | R62: 2420.5034 | S62: 2420.0959 | T62: 2419.5849 | U62: =T62 -> 2419.5849 | V62: 0 | W62: 0.21818478 | X62: 0.25393999 | Y62: 0.29063801 | Z62: 0.30748866 | AA62: 0.30941421 | AB62: 0.31317922 | AC62: 0.313907 | AD62: 0.31448962 | AE62: =AD62 -> 0.31448962 | AF62: =INDEX(ConsolidatedVehData!$AB$22:$AB$858,MATCH(B62,ConsolidatedVehData!$A$22:$A$858,0)) -> #REF! | AG62: 0.24 | AH62: 0 | AJ62: =Technologies!M56 -> R2,R3,R4,R5,R6
A63: TLPLPG11 | B63: TLPLPG10 | C63: TL.LPG1.P.LPG.2011 | D63: bn-vmt, bn-vmt/a | E63: TRNLPGEA | F63: TL | H63: 1 | I63: 2011 | J63: =INDEX(ConsolidatedVehData!$D$22:$D$858,MATCH(B63,ConsolidatedVehData!$A$22:$A$858,0)) -> 2010 | K63: 20 | L63: 3446.23 | M63: 3738.1678 | N63: 3672.6745 | O63: 1594.7423 | P63: 1605.2677 | Q63: 1606.885 | R63: 1606.2525 | S63: 1611.4593 | T63: 1612.3617 | U63: =T63 -> 1612.3617 | V63: 0.17926694 | W63: 0.15649113 | X63: 0.18367569 | Y63: 0.084473796 | Z63: 0.08961047 | AA63: 0.090983859 | AB63: 0.091673432 | AC63: 0.09188618 | AD63: 0.09180349 | AE63: =AD63 -> 0.09180349 | AF63: =INDEX(ConsolidatedVehData!$AB$22:$AB$858,MATCH(B63,ConsolidatedVehData!$A$22:$A$858,0)) -> #REF! | AG63: 0.24 | AH63: 0 | AJ63: =Technologies!M57 -> R2,R3,R4,R5,R6
A64: TLPLPGX11 | B64: TLPLPGX10 | C64: TL.LPGX.P.LPGX.2011 | D64: bn-vmt, bn-vmt/a | E64: TRNLPGX | F64: TL | G64: 0 | H64: 1 | I64: 2011 | J64: =INDEX(ConsolidatedVehData!$D$22:$D$858,MATCH(B64,ConsolidatedVehData!$A$22:$A$858,0)) -> 2010 | K64: 20 | L64: 3230.0636 | M64: 3524.6188 | N64: 3461.2371 | O64: 1511.0836 | P64: 1521.1899 | Q64: 1523.0238 | R64: 1523.3422 | S64: 1528.4811 | T64: 1529.4658 | U64: =T64 -> 1529.4658 | V64: 0.17244659 | W64: 0.15047227 | X64: 0.17698144 | Y64: 0.081335271 | Z64: 0.086298852 | AA64: 0.087704107 | AB64: 0.088374066 | AC64: 0.088589451 | AD64: 0.088494837 | AE64: =AD64 -> 0.088494837 | AF64: =INDEX(ConsolidatedVehData!$AB$22:$AB$858,MATCH(B64,ConsolidatedVehData!$A$22:$A$858,0)) -> #REF! | AG64: 0.24 | AH64: 0 | AJ64: =Technologies!M58 -> R2,R3,R4,R5,R6
A65: TLPGPHEV10 | B65: TLPPHVG15 | C65: TL.GSL.P.PHEV.2015 | D65: bn-vmt, bn-vmt/a | E65: TLGSL | H65: =1-H66 -> #REF! | I65: 2020 | J65: =INDEX(ConsolidatedVehData!$D$22:$D$858,MATCH(B65,ConsolidatedVehData!$A$22:$A$858,0)) -> 2015 | K65: 20 | L65: 3238.766 | M65: 3534.1149 | N65: 3470.5624 | O65: 1515.1548 | P65: 1525.2883 | Q65: 1527.1272 | R65: 1527.4464 | S65: 1532.5992 | T65: 1533.5865 | U65: 1533.5865 | V65: 0.41954904 | W65: 0.41266303 | X65: 0.40577702 | Y65: 0.48611498 | Z65: 0.49164831 | AA65: 0.49548042 | AB65: 0.49705153 | AC65: 0.49705153 | AD65: 0.49705153 | AE65: 0.49705153 | AF65: =INDEX(ConsolidatedVehData!$AB$22:$AB$858,MATCH(B65,ConsolidatedVehData!$A$22:$A$858,0)) -> #REF! | AG65: 0.28 | AH65: 0 | AJ65: =Technologies!M59 -> *R2,R3,R4,R5,R6
E66: TRNELC | H66: =INDEX(ConsolidatedVehData!$AG$22:$AG$858,MATCH(B65,ConsolidatedVehData!$A$22:$A$858,0)) -> #REF!
F67: TL
A68: TLSSGSLC11 | B68: TLSSCONV10 | C68: TL.GSL.SS.CONV.2011 | D68: bn-vmt, bn-vmt/a | E68: TLGSL | F68: TL | H68: 1 | I68: 2011 | J68: =INDEX(ConsolidatedVehData!$D$22:$D$858,MATCH(B68,ConsolidatedVehData!$A$22:$A$858,0)) -> 2010 | K68: 20 | L68: 2235.152 | M68: 2190.0932 | N68: 2787.3317 | O68: 2667.264 | P68: 2738.3287 | Q68: 2771.7896 | R68: 2791.5565 | S68: 2799.23 | T68: 2805.2669 | U68: =T68 -> 2805.2669 | V68: 0.18960687 | W68: 0.21408528 | X68: 0.17994959 | Y68: 0.22042484 | Z68: 0.23569356 | AA68: 0.24226718 | AB68: 0.2470769 | AC68: 0.2477306 | AD68: 0.24804907 | AE68: =AD68 -> 0.24804907 | AF68: =INDEX(ConsolidatedVehData!$AB$22:$AB$858,MATCH(B68,ConsolidatedVehData!$A$22:$A$858,0)) -> #REF! | AG68: 0.18 | AH68: 0 | AJ68: =Technologies!M60 -> R2,R3,R4,R5,R6
A69: *TLSSELC100 | B69: TLSSELC | C69: Electric small SUV w/100 mi range | D69: bn-vmt, bn-vmt/a | E69: TRNELC | F69: TL | G69: =IF($J69<G$1,0,"") | H69: 1 | I69: 2020 | J69: 2020 | K69: 20 | AH69: 0 | AJ69: =Technologies!M61 -> *R2,R3,R4,R5,R6
A70: TLSSELC200 | B70: TLSSELCB | C70: Electric small SUV w/200 mi range | D70: bn-vmt, bn-vmt/a | E70: TRNELC | F70: TL | G70: =IF($J70<G$1,0,"") | H70: 1 | I70: 2020 | J70: 2020 | K70: 20 | L70: 0 | M70: 0 | N70: 4499.9491 | O70: 2531.36 | P70: 2321.0882 | Q70: 2266.3322 | R70: 2226.9894 | S70: 2206.2504 | T70: 2193.1836 | U70: =T70 -> 2193.1836 | V70: 0 | W70: 0 | X70: 0.81035603 | Y70: 0.61931843 | Z70: 0.63186757 | AA70: 0.63426561 | AB70: 0.63528438 | AC70: 0.63575734 | AD70: 0.6360426 | AE70: =AD70 -> 0.6360426 | AF70: =0.5*AF68 -> #REF! | AG70: 0.28 | AH70: 0 | AJ70: =Technologies!M62 -> R2,R3,R4,R5,R6
A71: *TLSSDHEV20 | B71: TLSSDHEV20 | C71: TL.DSL.SS.DHEV.2020 | D71: bn-vmt, bn-vmt/a | E71: TRNDSL | F71: TL | H71: 1 | I71: 2020 | J71: =INDEX(ConsolidatedVehData!$D$22:$D$858,MATCH(B71,ConsolidatedVehData!$A$22:$A$858,0)) -> 2020 | K71: 20 | L71: 0 | M71: 0 | N71: 0 | O71: 0 | P71: 0 | Q71: 0 | R71: 0 | S71: 0 | T71: 0 | U71: =T71 -> 0 | V71: 0 | W71: 0 | X71: 0 | Y71: 0 | Z71: 0 | AA71: 0 | AB71: 0 | AC71: 0 | AD71: 0 | AE71: =AD71 -> 0 | AF71: =INDEX(ConsolidatedVehData!$AB$22:$AB$858,MATCH(B71,ConsolidatedVehData!$A$22:$A$858,0)) -> #REF! | AG71: 0.24 | AH71: 0 | AJ71: =Technologies!M63 -> *R2,R3,R4,R5,R6
A72: TLSSDSL11 | B72: TLSSDSL10 | C72: TL.DSL.SS.DSL.2011 | D72: bn-vmt, bn-vmt/a | E72: TRNDSL | F72: TL | H72: 1 | I72: 2011 | J72: =INDEX(ConsolidatedVehData!$D$22:$D$858,MATCH(B72,ConsolidatedVehData!$A$22:$A$858,0)) -> 2010 | K72: 20 | L72: 2636.3684 | M72: 2674.6347 | N72: 3240.7212 | O72: 3051.8786 | P72: 3115.0225 | Q72: 3144.8587 | R72: 3156.5086 | S72: 3162.7325 | T72: 3168.08 | U72: =T72 -> 3168.08 | V72: 0.23698173 | W72: 0.26974748 | X72: 0.21312383 | Y72: 0.24067248 | Z72: 0.25507158 | AA72: 0.25974989 | AB72: 0.26320569 | AC72: 0.26371362 | AD72: 0.26400362 | AE72: =AD72 -> 0.26400362 | AF72: =INDEX(ConsolidatedVehData!$AB$22:$AB$858,MATCH(B72,ConsolidatedVehData!$A$22:$A$858,0)) -> #REF! | AG72: 0.24 | AH72: 0 | AJ72: =Technologies!M64 -> R2,R3,R4,R5,R6
A73: TLSSETHX11 | B73: TLSSETHX10 | C73: TL.E85X.SS.ETHX.2011 | D73: bn-vmt, bn-vmt/a | E73: TLE85X | F73: TL | H73: 1 | I73: 2011 | J73: =INDEX(ConsolidatedVehData!$D$22:$D$858,MATCH(B73,ConsolidatedVehData!$A$22:$A$858,0)) -> 2010 | K73: 20 | L73: 2243.9537 | M73: 2198.8786 | N73: 2795.6987 | O73: 2674.5107 | P73: 2745.6828 | Q73: 2778.9251 | R73: 2798.8685 | S73: 2806.5115 | T73: 2812.505 | U73: =T73 -> 2812.505 | V73: 0.19146707 | W73: 0.21622614 | X73: 0.18159853 | Y73: 0.2224848 | Z73: 0.23792432 | AA73: 0.24450952 | AB73: 0.24939733 | AC73: 0.25004299 | AD73: 0.25037245 | AE73: =AD73 -> 0.25037245 | AF73: =INDEX(ConsolidatedVehData!$AB$22:$AB$858,MATCH(B73,ConsolidatedVehData!$A$22:$A$858,0)) -> #REF! | AG73: 0.18 | AH73: 0 | AJ73: =Technologies!M65 -> R2,R3,R4,R5,R6
A74: TLSSFCH25 | B74: TLSSFCH10 | C74: TL.H2.SS.FCH | D74: bn-vmt, bn-vmt/a | E74: TRNH2 | F74: TL | H74: 1 | I74: 2025 | J74: 2015 | K74: 20 | O74: 6730.3081 | P74: 6730.3081 | Q74: 6730.3081 | R74: 6730.3081 | S74: 6730.3081 | T74: 6730.3081 | U74: 6730.3081 | V74: =V70*0.6 -> 0 | W74: =W70*0.6 -> 0 | X74: =X70*0.6 -> 0.48621362 | Y74: =Y70*0.6 -> 0.37159106 | Z74: =Z70*0.6 -> 0.37912054 | AA74: =AA70*0.6 -> 0.38055937 | AB74: =AB70*0.6 -> 0.38117063 | AC74: =AC70*0.6 -> 0.38145441 | ... AE74: =AE70*0.6 -> 0.38162556 | AF74: =INDEX(ConsolidatedVehData!$AB$22:$AB$858,MATCH(B74,ConsolidatedVehData!$A$22:$A$858,0)) -> #REF! | AG74: 0.18 | AH74: 0 | AJ74: =Technologies!M66 -> *R2,R3,R4,R5,R6
A75: TLSSGHEV11 | B75: TLSSHEV10 | C75: TL.GSL.SS.HEV.2011 | D75: bn-vmt, bn-vmt/a | E75: TLGSL | F75: TL | H75: 1 | I75: 2011 | J75: =INDEX(ConsolidatedVehData!$D$22:$D$858,MATCH(B75,ConsolidatedVehData!$A$22:$A$858,0)) -> 2010 | K75: 20 | L75: 2566.6779 | M75: 2662.8705 | N75: 3176.077 | O75: 2307.6439 | P75: 2348.0129 | Q75: 2363.2736 | R75: 2368.5082 | S75: 2371.7936 | T75: 2374.9462 | U75: =T75 -> 2374.9462 | V75: 0.27246193 | W75: 0.31042367 | X75: 0.25145203 | Y75: 0.30722177 | Z75: 0.32803487 | AA75: 0.33128206 | AB75: 0.33625754 | AC75: 0.33728941 | AD75: 0.33833071 | AE75: =AD75 -> 0.33833071 | AF75: =INDEX(ConsolidatedVehData!$AB$22:$AB$858,MATCH(B75,ConsolidatedVehData!$A$22:$A$858,0)) -> #REF! | AG75: 0.24 | AH75: 0 | AJ75: =Technologies!M67 -> R2,R3,R4,R5,R6
A76: TLSSGPHEV11 | B76: TLSSPHVG10 | C76: TL.GSL.SS.PHEV.2011 | D76: bn-vmt, bn-vmt/a | E76: TLGSL | H76: =1-H77 -> #REF! | I76: 2011 | J76: =INDEX(ConsolidatedVehData!$D$22:$D$858,MATCH(B76,ConsolidatedVehData!$A$22:$A$858,0)) -> 2010 | K76: 20 | L76: =M76 -> 3514.1012 | M76: =N76 -> 3514.1012 | N76: 3514.1012 | O76: 3134.1462 | P76: 3108.6351 | Q76: 3075.2569 | R76: 3060.6996 | S76: 3051.8122 | T76: 3047.8675 | U76: =T76 -> 3047.8675 | V76: =W76 -> 0.2728349 | W76: =X76 -> 0.2728349 | X76: 0.2728349 | Y76: 0.28945351 | Z76: 0.30406277 | AA76: 0.31007032 | AB76: 0.31434944 | AC76: 0.31497671 | AD76: 0.31529835 | AE76: =AD76 -> 0.31529835 | AF76: =INDEX(ConsolidatedVehData!$AB$22:$AB$858,MATCH(B76,ConsolidatedVehData!$A$22:$A$858,0)) -> #REF! | AG76: 0.28 | AH76: 0 | AJ76: =Technologies!M68 -> R2,R3,R4,R5,R6
E77: TRNELC | H77: =INDEX(ConsolidatedVehData!$AG$22:$AG$858,MATCH(B76,ConsolidatedVehData!$A$22:$A$858,0)) -> #REF! | AJ77: =IF(LEFT(AJ76,1)="*","*","")
F78: TL
A79: TLLSGSLC11 | B79: TLLSCONV10 | C79: TL.GSL.LS.CONV.2011 | D79: bn-vmt, bn-vmt/a | E79: TLGSL | F79: TL | H79: 1 | I79: 2011 | J79: =INDEX(ConsolidatedVehData!$D$22:$D$858,MATCH(B79,ConsolidatedVehData!$A$22:$A$858,0)) -> 2010 | K79: 20 | L79: 3204.7023 | M79: 3311.762 | N79: 4803.7599 | O79: 4377.6249 | P79: 4461.5348 | Q79: 4497.3324 | R79: 4518.3293 | S79: 4528.2229 | T79: 4536.5916 | U79: =T79 -> 4536.5916 | V79: 0.16004206 | W79: 0.16363001 | X79: 0.1658803 | Y79: 0.17740769 | Z79: 0.190863 | AA79: 0.1965945 | AB79: 0.1995963 | AC79: 0.19996847 | AD79: 0.20027769 | AE79: =AD79 -> 0.20027769 | AF79: =INDEX(ConsolidatedVehData!$AB$22:$AB$858,MATCH(B79,ConsolidatedVehData!$A$22:$A$858,0)) -> #REF! | AG79: 0.18 | AH79: 0 | AJ79: =Technologies!M69 -> R2,R3,R4,R5,R6
A80: *TLLSELC100 | B80: TLLSELC | C80: Electric large SUV w/100 mi range | D80: bn-vmt, bn-vmt/a | E80: TRNELC | F80: TL | G80: =IF($J80<G$1,0,"") | H80: 1 | I80: 2025 | J80: 2025 | K80: 20 | AF80: =0.5*AF79 -> #REF! | AG80: 0.28 | AH80: 0 | AJ80: =Technologies!M70 -> *R2,R3,R4,R5,R6
A81: TLLSELC200 | B81: TLLSELCB | C81: Electric large SUV w/200 mi range | D81: bn-vmt, bn-vmt/a | E81: TRNELC | F81: TL | G81: =IF($J81<G$1,0,"") | H81: 1 | I81: 2020 | J81: 2025 | K81: 20 | L81: 0 | M81: 0 | N81: 7001.5146 | O81: 3715.3531 | P81: 3426.2834 | Q81: 3355.1751 | R81: 3307.9444 | S81: 3280.3795 | T81: 3261.2278 | U81: =T81 -> 3261.2278 | V81: 0 | W81: 0 | X81: 0.63072378 | Y81: 0.46031482 | Z81: 0.47150912 | AA81: 0.47496565 | AB81: 0.4768426 | AC81: 0.47738254 | AD81: 0.47774317 | AE81: =AD81 -> 0.47774317 | AF81: =0.5*AF79 -> #REF! | AG81: 0.28 | AH81: 0 | AJ81: =Technologies!M71 -> R2,R3,R4,R5,R6
A82: *TLLSDHEV20 | B82: TLLSDHEV20 | C82: TL.DSL.LS.DHEV.2020 | D82: bn-vmt, bn-vmt/a | E82: TRNDSL | F82: TL | H82: 1 | I82: 2020 | J82: =INDEX(ConsolidatedVehData!$D$22:$D$858,MATCH(B82,ConsolidatedVehData!$A$22:$A$858,0)) -> 2020 | K82: 20 | L82: 0 | M82: 0 | N82: 0 | O82: 0 | P82: 0 | Q82: 0 | R82: 0 | S82: 0 | T82: 0 | U82: =T82 -> 0 | V82: 0 | W82: 0 | X82: 0 | Y82: 0 | Z82: 0 | AA82: 0 | AB82: 0 | AC82: 0 | AD82: 0 | AE82: =AD82 -> 0 | AF82: =INDEX(ConsolidatedVehData!$AB$22:$AB$858,MATCH(B82,ConsolidatedVehData!$A$22:$A$858,0)) -> #REF! | AG82: 0.24 | AH82: 0 | AJ82: =Technologies!M72 -> *R2,R3,R4,R5,R6
A83: TLLSDSL11 | B83: TLLSDSL10 | C83: TL.DSL.LS.DSL.2011 | D83: bn-vmt, bn-vmt/a | E83: TRNDSL | F83: TL | H83: 1 | I83: 2011 | J83: =INDEX(ConsolidatedVehData!$D$22:$D$858,MATCH(B83,ConsolidatedVehData!$A$22:$A$858,0)) -> 2010 | K83: 20 | L83: 3638.7818 | M83: 3796.3029 | N83: 5268.5569 | O83: 4786.4628 | P83: 4850.1751 | Q83: 4879.9371 | R83: 4893.9375 | S83: 4901.2114 | T83: 4907.1742 | U83: =T83 -> 4907.1742 | V83: 0.19969295 | W83: 0.2061738 | X83: 0.20156144 | Y83: 0.20061382 | Z83: 0.21149632 | AA83: 0.21500287 | AB83: 0.2181435 | AC83: 0.21867368 | AD83: 0.21894902 | AE83: =AD83 -> 0.21894902 | AF83: =INDEX(ConsolidatedVehData!$AB$22:$AB$858,MATCH(B83,ConsolidatedVehData!$A$22:$A$858,0)) -> #REF! | AG83: 0.24 | AH83: 0 | AJ83: =Technologies!M73 -> R2,R3,R4,R5,R6
A84: TLLSETHX11 | B84: TLLSETHX10 | C84: TL.E85X.LS.ETHX.2011 | D84: bn-vmt, bn-vmt/a | E84: TLE85X | F84: TL | H84: 1 | I84: 2011 | J84: =INDEX(ConsolidatedVehData!$D$22:$D$858,MATCH(B84,ConsolidatedVehData!$A$22:$A$858,0)) -> 2010 | K84: 20 | L84: 3213.4979 | M84: 3320.5474 | N84: 4812.2907 | O84: 4385.0504 | P84: 4469.0253 | Q84: 4504.7029 | R84: 4525.8747 | S84: 4535.8875 | T84: 4544.3714 | U84: =T84 -> 4544.3714 | V84: 0.16161128 | W84: 0.1652663 | X84: 0.16745487 | Y84: 0.1791149 | Z84: 0.19263669 | AA84: 0.1982953 | AB84: 0.20131523 | AC84: 0.20164324 | AD84: 0.20193847 | AE84: =AD84 -> 0.20193847 | AF84: =INDEX(ConsolidatedVehData!$AB$22:$AB$858,MATCH(B84,ConsolidatedVehData!$A$22:$A$858,0)) -> #REF! | AG84: 0.18 | AH84: 0 | AJ84: =Technologies!M74 -> R2,R3,R4,R5,R6
A85: TLLSFCH25 | B85: TLLSFCH25 | C85: TL.H2.LS.FCH.2025 | D85: bn-vmt, bn-vmt/a | E85: TRNH2 | F85: TL | H85: 1 | I85: 2025 | J85: =INDEX(ConsolidatedVehData!$D$22:$D$858,MATCH(B85,ConsolidatedVehData!$A$22:$A$858,0)) -> 2025 | K85: 20 | O85: 6730.3081 | P85: 6730.3081 | Q85: 6730.3081 | R85: 6730.3081 | S85: 6730.3081 | T85: 6730.3081 | U85: 6730.3081 | AF85: =INDEX(ConsolidatedVehData!$AB$22:$AB$858,MATCH(B85,ConsolidatedVehData!$A$22:$A$858,0)) -> #REF! | AG85: 0.28 | AH85: 0 | AJ85: =Technologies!M75 -> *R2,R3,R4,R5,R6
A86: TLLSGHEV11 | B86: TLLSHEV10 | C86: TL.GSL.LS.HEV.2011 | D86: bn-vmt, bn-vmt/a | E86: TLGSL | F86: TL | H86: 1 | I86: 2011 | J86: =INDEX(ConsolidatedVehData!$D$22:$D$858,MATCH(B86,ConsolidatedVehData!$A$22:$A$858,0)) -> 2010 | K86: 20 | L86: 3570.2581 | M86: 3884.4663 | N86: 5279.7581 | O86: 3249.8178 | P86: 3286.4395 | Q86: 3303.1539 | R86: 3312.3421 | S86: 3316.6392 | T86: 3320.4491 | U86: =T86 -> 3320.4491 | V86: 0.23006339 | W86: 0.23726352 | X86: 0.23444337 | Y86: 0.24797523 | Z86: 0.26356527 | AA86: 0.26599462 | AB86: 0.27017825 | AC86: 0.27089801 | AD86: 0.27169786 | AE86: =AD86 -> 0.27169786 | AF86: =INDEX(ConsolidatedVehData!$AB$22:$AB$858,MATCH(B86,ConsolidatedVehData!$A$22:$A$858,0)) -> #REF! | AG86: 0.24 | AH86: 0 | AJ86: =Technologies!M76 -> R2,R3,R4,R5,R6
A87: TLLSPHVG11 | B87: TLLSPHVG10 | C87: TL.GSL.LS.PHEV.2011 | D87: bn-vmt, bn-vmt/a | E87: TLGSL | H87: =1-H88 -> #REF! | I87: 2011 | J87: =INDEX(ConsolidatedVehData!$D$22:$D$858,MATCH(B87,ConsolidatedVehData!$A$22:$A$858,0)) -> 2010 | K87: 20 | L87: 3245 | M87: 3285 | N87: 3366 | O87: 3454 | P87: 3461 | Q87: 3463 | R87: 3464 | S87: 3464 | T87: 3464 | U87: 3464 | V87: 0.375 | W87: 0.351 | X87: 0.407 | Y87: 0.497 | Z87: 0.507 | AA87: 0.51 | AB87: 0.511 | AC87: 0.511 | AD87: 0.511 | AE87: 0.511 | AF87: =INDEX(ConsolidatedVehData!$AB$22:$AB$858,MATCH(B87,ConsolidatedVehData!$A$22:$A$858,0)) -> #REF! | AG87: 0.28 | AH87: 0 | AJ87: =Technologies!M77 -> *R2,R3,R4,R5,R6
E88: TRNELC | H88: =INDEX(ConsolidatedVehData!$AG$22:$AG$858,MATCH(B87,ConsolidatedVehData!$A$22:$A$858,0)) -> #REF!
F89: TL
A90: TLCHE8511 | B90: TLCHE8510 | C90: TL.E85X.C.HE85.2011 | D90: bn-vmt, bn-vmt/a | E90: TLE85X | F90: TL | H90: 1 | I90: 2011 | J90: =INDEX(ConsolidatedVehData!$D$22:$D$858,MATCH(B90,ConsolidatedVehData!$A$22:$A$858,0)) -> 2010 | K90: 20 | L90: 1757.5977 | M90: 1909.6327 | N90: 2474.4068 | O90: 2158.0922 | P90: 2209.7187 | Q90: 2234.5437 | R90: 2260.9156 | S90: 2280.1852 | T90: 2298.2913 | U90: =T90 -> 2298.2913 | V90: 0.22981262 | W90: 0.24997875 | X90: 0.26097025 | Y90: 0.29964882 | Z90: 0.3137066 | AA90: 0.31382515 | AB90: 0.31658023 | AC90: 0.31587693 | AD90: 0.31548409 | AE90: =AD90 -> 0.31548409 | AF90: =INDEX(ConsolidatedVehData!$AB$22:$AB$858,MATCH(B90,ConsolidatedVehData!$A$22:$A$858,0)) -> #REF! | AG90: 0.24 | AH90: 0 | AJ90: =Technologies!M78 -> R2,R3,R4,R5,R6
A91: TLFHE8511 | B91: TLFHE8510 | C91: TL.E85X.F.HE85.2011 | D91: bn-vmt, bn-vmt/a | E91: TLE85X | F91: TL | H91: 1 | I91: 2011 | J91: =INDEX(ConsolidatedVehData!$D$22:$D$858,MATCH(B91,ConsolidatedVehData!$A$22:$A$858,0)) -> 2010 | K91: 20 | L91: 2187.8082 | M91: 2193.5473 | N91: 2286.83 | O91: 2059.1174 | P91: 2108.942 | Q91: 2130.4823 | R91: 2155.919 | S91: 2175.9227 | T91: 2194.3704 | U91: =T91 -> 2194.3704 | V91: 0.22803315 | W91: 0.23437248 | X91: 0.28588027 | Y91: 0.31611825 | Z91: 0.32972952 | AA91: 0.32634247 | AB91: 0.32819896 | AC91: 0.32705964 | AD91: 0.32676928 | AE91: =AD91 -> 0.32676928 | AF91: =INDEX(ConsolidatedVehData!$AB$22:$AB$858,MATCH(B91,ConsolidatedVehData!$A$22:$A$858,0)) -> #REF! | AG91: 0.24 | AH91: 0 | AJ91: =Technologies!M79 -> R2,R3,R4,R5,R6
A92: TLPHE8515 | B92: TLPHE8515 | C92: TL.E85X.P.HE85.2015 | D92: bn-vmt, bn-vmt/a | E92: TLE85X | F92: TL | H92: 1 | I92: 2011 | J92: =INDEX(ConsolidatedVehData!$D$22:$D$858,MATCH(B92,ConsolidatedVehData!$A$22:$A$858,0)) -> 2015 | K92: 20 | L92: 2591.9757 | M92: 2850.3011 | N92: 2892.5371 | O92: 2638.3317 | P92: 2702.9071 | Q92: 2733.1468 | R92: 2752.1874 | S92: 2761.7579 | T92: 2768.7377 | U92: =T92 -> 2768.7377 | V92: 0.17207386 | W92: 0.15406004 | X92: 0.18132363 | Y92: 0.20959552 | Z92: 0.22450678 | AA92: 0.22857802 | AB92: 0.23368579 | AC92: 0.23461703 | AD92: 0.23498272 | AE92: =AD92 -> 0.23498272 | AF92: =INDEX(ConsolidatedVehData!$AB$22:$AB$858,MATCH(B92,ConsolidatedVehData!$A$22:$A$858,0)) -> #REF! | AG92: 0.24 | AH92: 0 | AJ92: =Technologies!M80 -> R2,R3,R4,R5,R6
A93: TLMHE8511 | B93: TLMHE8510 | C93: TL.E85X.M.HE85.2011 | D93: bn-vmt, bn-vmt/a | E93: TLE85X | F93: TL | H93: 1 | I93: 2011 | J93: =INDEX(ConsolidatedVehData!$D$22:$D$858,MATCH(B93,ConsolidatedVehData!$A$22:$A$858,0)) -> 2010 | K93: 20 | L93: 2360.2898 | M93: 2298.8298 | N93: 2482.3568 | O93: 2163.9027 | P93: 2238.6127 | Q93: 2258.9947 | R93: 2272.4353 | S93: 2278.3816 | T93: 2284.482 | U93: =T93 -> 2284.482 | V93: 0.17342708 | W93: 0.1799019 | X93: 0.19588105 | Y93: 0.26022017 | Z93: 0.2849274 | AA93: 0.2888569 | AB93: 0.29284527 | AC93: 0.29326553 | AD93: 0.29358945 | AE93: =AD93 -> 0.29358945 | AF93: =INDEX(ConsolidatedVehData!$AB$22:$AB$858,MATCH(B93,ConsolidatedVehData!$A$22:$A$858,0)) -> #REF! | AG93: 0.24 | AH93: 0 | AJ93: =Technologies!M81 -> R2,R3,R4,R5,R6
A94: TLLSHE8511 | B94: TLLSHE8510 | C94: TL.E85X.LS.HE85.2011 | D94: bn-vmt, bn-vmt/a | E94: TLE85X | F94: TL | H94: 1 | I94: 2011 | J94: =INDEX(ConsolidatedVehData!$D$22:$D$858,MATCH(B94,ConsolidatedVehData!$A$22:$A$858,0)) -> 2010 | K94: 20 | L94: 3213.4979 | M94: 3320.5474 | N94: 4812.2907 | O94: 4385.0504 | P94: 4469.0253 | Q94: 4504.7029 | R94: 4525.8747 | S94: 4535.8875 | T94: 4544.3714 | U94: =T94 -> 4544.3714 | V94: 0.16161128 | W94: 0.1652663 | X94: 0.16745487 | Y94: 0.1791149 | Z94: 0.19263669 | AA94: 0.1982953 | AB94: 0.20131523 | AC94: 0.20164324 | AD94: 0.20193847 | AE94: =AD94 -> 0.20193847 | AF94: =INDEX(ConsolidatedVehData!$AB$22:$AB$858,MATCH(B94,ConsolidatedVehData!$A$22:$A$858,0)) -> #REF! | AG94: 0.24 | AH94: 0 | AJ94: =Technologies!M82 -> R2,R3,R4,R5,R6
A95: TLSSHE8511 | B95: TLSSHE8510 | C95: TL.E85X.SS.HE85.2011 | D95: bn-vmt, bn-vmt/a | E95: TLE85X | F95: TL | H95: 1 | I95: 2011 | J95: =INDEX(ConsolidatedVehData!$D$22:$D$858,MATCH(B95,ConsolidatedVehData!$A$22:$A$858,0)) -> 2010 | K95: 20 | L95: 2243.9537 | M95: 2198.8786 | N95: 2795.6987 | O95: 2674.5107 | P95: 2745.6828 | Q95: 2778.9251 | R95: 2798.8685 | S95: 2806.5115 | T95: 2812.505 | U95: =T95 -> 2812.505 | V95: 0.19146707 | W95: 0.21622614 | X95: 0.18159853 | Y95: 0.2224848 | Z95: 0.23792432 | AA95: 0.24450952 | AB95: 0.24939733 | AC95: 0.25004299 | AD95: 0.25037245 | AE95: =AD95 -> 0.25037245 | AF95: =INDEX(ConsolidatedVehData!$AB$22:$AB$858,MATCH(B95,ConsolidatedVehData!$A$22:$A$858,0)) -> #REF! | AG95: 0.24 | AH95: 0 | AJ95: =Technologies!M83 -> R2,R3,R4,R5,R6
A96: TLCGPHEV40 | B96: TLCP20G10 | C96: TL.GSL.C.PHEV.2011 | D96: bn-vmt, bn-vmt/a | E96: TLGSL | H96: =#REF! -> #REF! | I96: 2015 | J96: =INDEX(ConsolidatedVehData!$D$22:$D$858,MATCH(B96,ConsolidatedVehData!$A$22:$A$858,0)) -> 2010 | K96: 20 | L96: 2391.1031 | M96: 2428.004 | N96: 3359.6919 | O96: 2709.9695 | P96: 2640.3005 | Q96: 2598.0416 | R96: 2579.1983 | S96: 2576.8477 | T96: 2579.9666 | U96: =T96 -> 2579.9666 | V96: 0.32025471 | W96: 0.38543726 | X96: 0.48884977 | Y96: 0.51470433 | Z96: 0.5293978 | AA96: 0.53033647 | AB96: 0.53372823 | AC96: 0.53358144 | AD96: 0.53352164 | AE96: =AD96 -> 0.53352164 | AF96: =INDEX(ConsolidatedVehData!$AB$22:$AB$858,MATCH(B96,ConsolidatedVehData!$A$22:$A$858,0)) -> #REF! | AG96: 0.28 | AH96: 0 | AJ96: =Technologies!M84 -> R2,R3,R4,R5,R6
E97: TRNELC | H97: =1-H96 -> #REF!
F98: TL
A99: TLFGPHEV40 | C99: TL.GSL.F.PHEV.2015 | D99: bn-vmt, bn-vmt/a | E99: TLGSL | H99: 0.42103321 | I99: 2015 | K99: 20 | M99: 3510.9277 | N99: 3347.0293 | O99: 2677.3834 | P99: 2593.4153 | Q99: 2544.9732 | R99: 2523.2193 | S99: 2520.0057 | T99: 2521.4222 | U99: =T99 -> 2521.4222 | V99: 0 | W99: 0.41135992 | X99: 0.50553109 | Y99: 0.52519968 | Z99: 0.53832672 | AA99: 0.53640799 | AB99: 0.53878543 | AC99: 0.53829087 | AD99: 0.53839631 | AE99: =AD99 -> 0.53839631 | AF99: =AF37 -> #REF! | AG99: 0.28 | AH99: 0 | AJ99: =Technologies!M85 -> R2,R3,R4,R5,R6
E100: TRNELC | H100: 0.57896679
F101: TL
A102: TLPGPHEV40 | C102: TL.GSL.P.PHEV.2020 | D102: bn-vmt, bn-vmt/a | E102: TLGSL | H102: 0.42103321 | I102: 2020 | K102: 20 | N102: 3662.2488 | O102: 1733.8311 | P102: 1683.1103 | Q102: 1653.664 | R102: 1641.4378 | S102: 1629.6822 | T102: 1625.1651 | U102: =T102 -> 1625.1651 | V102: 0 | W102: 0 | X102: 0.38033612 | Y102: 0.2428058 | Z102: 0.25295542 | AA102: 0.25580253 | AB102: 0.26056091 | AC102: 0.26110655 | AD102: 0.26164951 | AE102: =AD102 -> 0.26164951 | AF102: =AF65 -> #REF! | AG102: 0.28 | AH102: 0 | AJ102: =Technologies!M86 -> R2,R3,R4,R5,R6
E103: TRNELC | H103: 0.57896679
F104: TL | V104: 0 | W104: 0 | X104: 0 | Y104: 0 | Z104: 0 | AA104: 0 | AB104: 0 | AC104: 0 | AD104: 0
...

Sheet TechData-Emis
G1: * | H1: * | I1: * | J1: * | K1: * | L1: * | M1: * | N1: * | O1: * | P1: * | Q1: * | R1: * | S1: * | T1: * | AY1: * | AZ1: * | BA1: * | BB1: * | BC1: * | BD1: * | BE1: * | BF1: * | BG1: * | BH1: * | BI1: * | BJ1: * | BK1: * | BL1: * | BM1: * | BN1: * | BO1: * | BP1: * | BQ1: * | BR1: * | BS1: * | BT1: * | BU1: * | BV1: * | BW1: * | BX1: * | BY1: * | BZ1: * | CA1: * | CB1: * | CC1: * | CD1: * | CE1: * | CF1: * | CG1: * | CH1: * | CI1: * | CJ1: * | CK1: * | CL1: * | CM1: * | CN1: * | CO1: * | CP1: * | CQ1: * | CR1: * | CS1: * | CT1: * | CU1: * | CV1: * | CW1: * | CX1: * | CY1: * | CZ1: * | DA1: * | DB1: * | DC1: * | DD1: * | DE1: * | DF1: * | DG1: * | DH1: * | DI1: * | DJ1: * | DK1: * | DL1: * | DM1: * | DN1: * | DO1: * | DP1: * | DQ1: * | DR1: * | DS1: * | DT1: * | DU1: * | DV1: * | DW1: * | DX1: * | DY1: * | DZ1: * | EA1: * | EB1: * | EC1: * | ED1: * | EE1: * | EF1: * | EG1: * | EH1: * | EI1: * | EJ1: * | EK1: * | EL1: * | EM1: * | EN1: * | EO1: * | EP1: * | EQ1: * | ER1: * | ES1: * | ET1: * | EU1: * | EV1: * | EW1: * | EX1: * | EY1: * | EZ1: * | FA1: * | FB1: * | FC1: * | FD1: * | FE1: * | FF1: * | FG1: * | FH1: * | FI1: * | FJ1: * | FK1: * | FL1: * | FM1: * | FN1: * | FO1: * | FP1: * | FQ1: * | FR1: * | FS1: * | FT1: * | FU1: * | FV1: * | FW1: * | FX1: *
K2: CO2 | L2: CO2 | M2: CO2 | N2: CO2 | O2: CO2 | P2: CO2 | Q2: CO2 | R2: CO2 | S2: CO2 | T2: CO2 | U2: NOX | V2: NOX | W2: NOX | X2: NOX | Y2: NOX | Z2: NOX | AA2: NOX | AB2: NOX | AC2: NOX | AD2: NOX | AE2: SO2 | AF2: SO2 | AG2: SO2 | AH2: SO2 | AI2: SO2 | AJ2: SO2 | AK2: SO2 | AL2: SO2 | AM2: SO2 | AN2: SO2 | AO2: PM10 | AP2: PM10 | AQ2: PM10 | AR2: PM10 | AS2: PM10 | AT2: PM10 | AU2: PM10 | AV2: PM10 | AW2: PM10 | AX2: PM10 | AY2: PM25 | AZ2: PM25 | BA2: PM25 | BB2: PM25 | BC2: PM25 | BD2: PM25 | BE2: PM25 | BF2: PM25 | BG2: PM25 | BH2: PM25 | BI2: CO | BJ2: CO | BK2: CO | BL2: CO | BM2: CO | BN2: CO | BO2: CO | BP2: CO | BQ2: CO | BR2: CO | BS2: VOC | BT2: VOC | BU2: VOC | BV2: VOC | BW2: VOC | BX2: VOC | BY2: VOC | BZ2: VOC | CA2: VOC | CB2: VOC | CC2: NH3 | CD2: NH3 | CE2: NH3 | CF2: NH3 | CG2: NH3 | CH2: NH3 | CI2: NH3 | CJ2: NH3 | CK2: NH3 | CL2: NH3 | CM2: N2O | CN2: N2O | CO2: N2O | CP2: N2O | CQ2: N2O | CR2: N2O | CS2: N2O | CT2: N2O | CU2: N2O | CV2: N2O | CW2: BC | CX2: BC | CY2: BC | CZ2: BC | DA2: BC | DB2: BC | DC2: BC | DD2: BC | DE2: BC | DF2: BC | DG2: OC | DH2: OC | DI2: OC | DJ2: OC | DK2: OC | DL2: OC | DM2: OC | DN2: OC | DO2: OC | DP2: OC | DQ2: CH4 | DR2: CH4 | DS2: CH4 | DT2: CH4 | DU2: CH4 | DV2: CH4 | DW2: CH4 | DX2: CH4 | DY2: CH4 | DZ2: CH4 | EA2: =CONCATENATE(K2,"T") -> CO2T | EB2: =CONCATENATE(L2,"T") -> CO2T | EC2: =CONCATENATE(M2,"T") -> CO2T | ED2: =CONCATENATE(N2,"T") -> CO2T | EE2: =CONCATENATE(O2,"T") -> CO2T | EF2: =CONCATENATE(P2,"T") -> CO2T | EG2: =CONCATENATE(Q2,"T") -> CO2T | EH2: =CONCATENATE(R2,"T") -> CO2T | ... FX2: =CONCATENATE(BH2,"T") -> PM25T
F7: ~FI_T
A8: Region | B8: TechName | C8: *TechDesc | D8: *Units | E8: *CommIN | F8: *CommOUT | G8: *Type | H8: *Fuel | I8: *Adjustment | J8: *Categories for tracking emissions | K8: *ENV_ACT~CO2~2010 | L8: *ENV_ACT~CO2~2015 | M8: *ENV_ACT~CO2~2020 | N8: *ENV_ACT~CO2~2025 | O8: *ENV_ACT~CO2~2030 | P8: *ENV_ACT~CO2~2035 | Q8: *ENV_ACT~CO2~2040 | R8: *ENV_ACT~CO2~2045 | S8: *ENV_ACT~CO2~2050 | T8: *ENV_ACT~CO2~2055 | U8: ENV_ACT~NOX~2010 | V8: ENV_ACT~NOX~2015 | W8: ENV_ACT~NOX~2020 | X8: ENV_ACT~NOX~2025 | Y8: ENV_ACT~NOX~2030 | Z8: ENV_ACT~NOX~2035 | AA8: ENV_ACT~NOX~2040 | AB8: ENV_ACT~NOX~2045 | AC8: ENV_ACT~NOX~2050 | AD8: ENV_ACT~NOX~2055 | AE8: ENV_ACT~SO2~2010 | AF8: ENV_ACT~SO2~2015 | AG8: ENV_ACT~SO2~2020 | AH8: ENV_ACT~SO2~2025 | AI8: ENV_ACT~SO2~2030 | AJ8: ENV_ACT~SO2~2035 | AK8: ENV_ACT~SO2~2040 | AL8: ENV_ACT~SO2~2045 | AM8: ENV_ACT~SO2~2050 | AN8: ENV_ACT~SO2~2055 | AO8: ENV_ACT~PM10~2010 | AP8: ENV_ACT~PM10~2015 | AQ8: ENV_ACT~PM10~2020 | AR8: ENV_ACT~PM10~2025 | AS8: ENV_ACT~PM10~2030 | AT8: ENV_ACT~PM10~2035 | AU8: ENV_ACT~PM10~2040 | AV8: ENV_ACT~PM10~2045 | AW8: ENV_ACT~PM10~2050 | AX8: ENV_ACT~PM10~2055 | AY8: ENV_ACT~PM25~2010 | AZ8: ENV_ACT~PM25~2015 | BA8: ENV_ACT~PM25~2020 | BB8: ENV_ACT~PM25~2025 | BC8: ENV_ACT~PM25~2030 | BD8: ENV_ACT~PM25~2035 | BE8: ENV_ACT~PM25~2040 | BF8: ENV_ACT~PM25~2045 | BG8: ENV_ACT~PM25~2050 | BH8: ENV_ACT~PM25~2055 | BI8: ENV_ACT~CO~2010 | BJ8: ENV_ACT~CO~2015 | BK8: ENV_ACT~CO~2020 | BL8: ENV_ACT~CO~2025 | BM8: ENV_ACT~CO~2030 | BN8: ENV_ACT~CO~2035 | BO8: ENV_ACT~CO~2040 | BP8: ENV_ACT~CO~2045 | BQ8: ENV_ACT~CO~2050 | BR8: ENV_ACT~CO~2055 | BS8: ENV_ACT~VOC~2010 | BT8: ENV_ACT~VOC~2015 | BU8: ENV_ACT~VOC~2020 | BV8: ENV_ACT~VOC~2025 | BW8: ENV_ACT~VOC~2030 | BX8: ENV_ACT~VOC~2035 | BY8: ENV_ACT~VOC~2040 | BZ8: ENV_ACT~VOC~2045 | CA8: ENV_ACT~VOC~2050 | CB8: ENV_ACT~VOC~2055 | CC8: ENV_ACT~NH3~2010 | CD8: ENV_ACT~NH3~2015 | CE8: ENV_ACT~NH3~2020 | CF8: ENV_ACT~NH3~2025 | CG8: ENV_ACT~NH3~2030 | CH8: ENV_ACT~NH3~2035 | CI8: ENV_ACT~NH3~2040 | CJ8: ENV_ACT~NH3~2045 | CK8: ENV_ACT~NH3~2050 | CL8: ENV_ACT~NH3~2055 | CM8: ENV_ACT~N2O~2010 | CN8: ENV_ACT~N2O~2015 | CO8: ENV_ACT~N2O~2020 | CP8: ENV_ACT~N2O~2025 | CQ8: ENV_ACT~N2O~2030 | CR8: ENV_ACT~N2O~2035 | CS8: ENV_ACT~N2O~2040 | CT8: ENV_ACT~N2O~2045 | CU8: ENV_ACT~N2O~2050 | CV8: ENV_ACT~N2O~2055 | CW8: ENV_ACT~BC~2010 | CX8: ENV_ACT~BC~2015 | CY8: ENV_ACT~BC~2020 | CZ8: ENV_ACT~BC~2025 | DA8: ENV_ACT~BC~2030 | DB8: ENV_ACT~BC~2035 | DC8: ENV_ACT~BC~2040 | DD8: ENV_ACT~BC~2045 | DE8: ENV_ACT~BC~2050 | DF8: ENV_ACT~BC~2055 | DG8: *ENV_ACT~OC~2010 | DH8: *ENV_ACT~OC~2015 | DI8: *ENV_ACT~OC~2020 | DJ8: *ENV_ACT~OC~2025 | DK8: *ENV_ACT~OC~2030 | DL8: *ENV_ACT~OC~2035 | DM8: *ENV_ACT~OC~2040 | DN8: *ENV_ACT~OC~2045 | DO8: *ENV_ACT~OC~2050 | DP8: *ENV_ACT~OC~2055 | DQ8: *ENV_ACT~CH4~2010 | DR8: *ENV_ACT~CH4~2015 | DS8: *ENV_ACT~CH4~2020 | DT8: *ENV_ACT~CH4~2025 | DU8: *ENV_ACT~CH4~2030 | DV8: *ENV_ACT~CH4~2035 | DW8: *ENV_ACT~CH4~2040 | DX8: *ENV_ACT~CH4~2045 | DY8: *ENV_ACT~CH4~2050 | DZ8: *ENV_ACT~CH4~2055 | EA8: *ENV_ACT~CO2T~2010 | EB8: *ENV_ACT~CO2T~2015 | EC8: *ENV_ACT~CO2T~2020 | ED8: *ENV_ACT~CO2T~2025 | EE8: *ENV_ACT~CO2T~2030 | EF8: *ENV_ACT~CO2T~2035 | EG8: *ENV_ACT~CO2T~2040 | EH8: *ENV_ACT~CO2T~2045 | EI8: *ENV_ACT~CO2T~2050 | EJ8: *ENV_ACT~CO2T~2055 | EK8: *ENV_ACT~NOXT~2010 | EL8: *ENV_ACT~NOXT~2015 | EM8: *ENV_ACT~NOXT~2020 | EN8: *ENV_ACT~NOXT~2025 | EO8: *ENV_ACT~NOXT~2030 | EP8: *ENV_ACT~NOXT~2035 | EQ8: *ENV_ACT~NOXT~2040 | ER8: *ENV_ACT~NOXT~2045 | ES8: *ENV_ACT~NOXT~2050 | ET8: *ENV_ACT~NOXT~2055 | EU8: *ENV_ACT~SO2T~2010 | EV8: *ENV_ACT~SO2T~2015 | EW8: *ENV_ACT~SO2T~2020 | EX8: *ENV_ACT~SO2T~2025 | EY8: *ENV_ACT~SO2T~2030 | EZ8: *ENV_ACT~SO2T~2035 | FA8: *ENV_ACT~SO2T~2040 | FB8: *ENV_ACT~SO2T~2045 | FC8: *ENV_ACT~SO2T~2050 | FD8: *ENV_ACT~SO2T~2055 | FE8: *ENV_ACT~PM10T~2010 | FF8: *ENV_ACT~PM10T~2015 | FG8: *ENV_ACT~PM10T~2020 | FH8: *ENV_ACT~PM10T~2025 | FI8: *ENV_ACT~PM10T~2030 | FJ8: *ENV_ACT~PM10T~2035 | FK8: *ENV_ACT~PM10T~2040 | FL8: *ENV_ACT~PM10T~2045 | FM8: *ENV_ACT~PM10T~2050 | FN8: *ENV_ACT~PM10T~2055 | FO8: *ENV_ACT~PM25T~2010 | FP8: *ENV_ACT~PM25T~2015 | FQ8: *ENV_ACT~PM25T~2020 | FR8: *ENV_ACT~PM25T~2025 | FS8: *ENV_ACT~PM25T~2030 | FT8: *ENV_ACT~PM25T~2035 | FU8: *ENV_ACT~PM25T~2040 | FV8: *ENV_ACT~PM25T~2045 | FW8: *ENV_ACT~PM25T~2050 | FX8: *ENV_ACT~PM25T~2055
A9: * New Vehicles | EA9: =K9 -> 0 | EB9: =L9 -> 0 | EC9: =M9 -> 0 | ED9: =N9 -> 0 | EE9: =O9 -> 0 | EF9: =P9 -> 0 | EG9: =Q9 -> 0 | EH9: =R9 -> 0 | ... FX9: =BH9 -> 0
A10: =IF(LEFT(TRIM(TechData_All!AJ9),1)="*", _xlfn.CONCAT("*","R2"), "R2") -> R2 | B10: =TechData_All!A9 -> TLMCGSLC11 | C10: =TechData_All!C9 -> TL.GSL.MC.CONV.2011 | D10: =TechData_All!D9 -> bn-vmt, bn-vmt/a | E10: =TechData_All!E9 -> TLGSL | F10: =TechData_All!F9 -> TL | G10: Mini car | H10: GSL | I10: 1 | J10: =CONCATENATE(G10,"-",H10) -> Mini car-GSL | K10: =$I10*IF($G10="Pickup", SUMIFS(NewEmisData!E:E, NewEmisData!$A:$A, "Pickup", NewEmisData!$B:$B, $A10, NewEmisData!$C:$C, $H10, NewEmisData!$D:$D, K$2), SUMIFS(NewEmisData!E:E, NewEmisData!$A:$A, "LDV", NewEmisData!$B:$B, $A10, NewEmisData!$C:$C, $H10, NewEmisData!$D:$D, K$2)) -> 477.08587 | L10: =$I10*IF($G10="Pickup", SUMIFS(NewEmisData!F:F, NewEmisData!$A:$A, "Pickup", NewEmisData!$B:$B, $A10, NewEmisData!$C:$C, $H10, NewEmisData!$D:$D, L$2), SUMIFS(NewEmisData!F:F, NewEmisData!$A:$A, "LDV", NewEmisData!$B:$B, $A10, NewEmisData!$C:$C, $H10, NewEmisData!$D:$D, L$2)) -> 459.34104 | M10: =$I10*IF($G10="Pickup", SUMIFS(NewEmisData!G:G, NewEmisData!$A:$A, "Pickup", NewEmisData!$B:$B, $A10, NewEmisData!$C:$C, $H10, NewEmisData!$D:$D, M$2), SUMIFS(NewEmisData!G:G, NewEmisData!$A:$A, "LDV", NewEmisData!$B:$B, $A10, NewEmisData!$C:$C, $H10, NewEmisData!$D:$D, M$2)) -> 447.45897 | N10: =$I10*IF($G10="Pickup", SUMIFS(NewEmisData!H:H, NewEmisData!$A:$A, "Pickup", NewEmisData!$B:$B, $A10, NewEmisData!$C:$C, $H10, NewEmisData!$D:$D, N$2), SUMIFS(NewEmisData!H:H, NewEmisData!$A:$A, "LDV", NewEmisData!$B:$B, $A10, NewEmisData!$C:$C, $H10, NewEmisData!$D:$D, N$2)) -> 380.72393 | O10: =$I10*IF($G10="Pickup", SUMIFS(NewEmisData!I:I, NewEmisData!$A:$A, "Pickup", NewEmisData!$B:$B, $A10, NewEmisData!$C:$C, $H10, NewEmisData!$D:$D, O$2), SUMIFS(NewEmisData!I:I, NewEmisData!$A:$A, "LDV", NewEmisData!$B:$B, $A10, NewEmisData!$C:$C, $H10, NewEmisData!$D:$D, O$2)) -> 329.54737 | P10: =$I10*IF($G10="Pickup", SUMIFS(NewEmisData!J:J, NewEmisData!$A:$A, "Pickup", NewEmisData!$B:$B, $A10, NewEmisData!$C:$C, $H10, NewEmisData!$D:$D, P$2), SUMIFS(NewEmisData!J:J, NewEmisData!$A:$A, "LDV", NewEmisData!$B:$B, $A10, NewEmisData!$C:$C, $H10, NewEmisData!$D:$D, P$2)) -> 300.6983 | Q10: =$I10*IF($G10="Pickup", SUMIFS(NewEmisData!K:K, NewEmisData!$A:$A, "Pickup", NewEmisData!$B:$B, $A10, NewEmisData!$C:$C, $H10, NewEmisData!$D:$D, Q$2), SUMIFS(NewEmisData!K:K, NewEmisData!$A:$A, "LDV", NewEmisData!$B:$B, $A10, NewEmisData!$C:$C, $H10, NewEmisData!$D:$D, Q$2)) -> 287.838 | R10: =$I10*IF($G10="Pickup", SUMIFS(NewEmisData!L:L, NewEmisData!$A:$A, "Pickup", NewEmisData!$B:$B, $A10, NewEmisData!$C:$C, $H10, NewEmisData!$D:$D, R$2), SUMIFS(NewEmisData!L:L, NewEmisData!$A:$A, "LDV", NewEmisData!$B:$B, $A10, NewEmisData!$C:$C, $H10, NewEmisData!$D:$D, R$2)) -> 283.26611 | S10: =$I10*IF($G10="Pickup", SUMIFS(NewEmisData!M:M, NewEmisData!$A:$A, "Pickup", NewEmisData!$B:$B, $A10, NewEmisData!$C:$C, $H10, NewEmisData!$D:$D, S$2), SUMIFS(NewEmisData!M:M, NewEmisData!$A:$A, "LDV", NewEmisData!$B:$B, $A10, NewEmisData!$C:$C, $H10, NewEmisData!$D:$D, S$2)) -> 281.57834 | T10: 0.20692409 | U10: =$I10*IF($G10="Pickup", SUMIFS(NewEmisData!E:E, NewEmisData!$A:$A, "Pickup", NewEmisData!$B:$B, $A10, NewEmisData!$C:$C, $H10, NewEmisData!$D:$D, U$2), SUMIFS(NewEmisData!E:E, NewEmisData!$A:$A, "LDV", NewEmisData!$B:$B, $A10, NewEmisData!$C:$C, $H10, NewEmisData!$D:$D, U$2)) -> 0.82339104 | V10: =$I10*IF($G10="Pickup", SUMIFS(NewEmisData!F:F, NewEmisData!$A:$A, "Pickup", NewEmisData!$B:$B, $A10, NewEmisData!$C:$C, $H10, NewEmisData!$D:$D, V$2), SUMIFS(NewEmisData!F:F, NewEmisData!$A:$A, "LDV", NewEmisData!$B:$B, $A10, NewEmisData!$C:$C, $H10, NewEmisData!$D:$D, V$2)) -> 0.36087273 | W10: =$I10*IF($G10="Pickup", SUMIFS(NewEmisData!G:G, NewEmisData!$A:$A, "Pickup", NewEmisData!$B:$B, $A10, NewEmisData!$C:$C, $H10, NewEmisData!$D:$D, W$2), SUMIFS(NewEmisData!G:G, NewEmisData!$A:$A, "LDV", NewEmisData!$B:$B, $A10, NewEmisData!$C:$C, $H10, NewEmisData!$D:$D, W$2)) -> 0.21658171 | X10: =$I10*IF($G10="Pickup", SUMIFS(NewEmisData!H:H, NewEmisData!$A:$A, "Pickup", NewEmisData!$B:$B, $A10, NewEmisData!$C:$C, $H10, NewEmisData!$D:$D, X$2), SUMIFS(NewEmisData!H:H, NewEmisData!$A:$A, "LDV", NewEmisData!$B:$B, $A10, NewEmisData!$C:$C, $H10, NewEmisData!$D:$D, X$2)) -> 0.14200533 | Y10: =$I10*IF($G10="Pickup", SUMIFS(NewEmisData!I:I, NewEmisData!$A:$A, "Pickup", NewEmisData!$B:$B, $A10, NewEmisData!$C:$C, $H10, NewEmisData!$D:$D, Y$2), SUMIFS(NewEmisData!I:I, NewEmisData!$A:$A, "LDV", NewEmisData!$B:$B, $A10, NewEmisData!$C:$C, $H10, NewEmisData!$D:$D, Y$2)) -> 0.088016805 | Z10: =$I10*IF($G10="Pickup", SUMIFS(NewEmisData!J:J, NewEmisData!$A:$A, "Pickup", NewEmisData!$B:$B, $A10, NewEmisData!$C:$C, $H10, NewEmisData!$D:$D, Z$2), SUMIFS(NewEmisData!J:J, NewEmisData!$A:$A, "LDV", NewEmisData!$B:$B, $A10, NewEmisData!$C:$C, $H10, NewEmisData!$D:$D, Z$2)) -> 0.06573638 | AA10: =$I10*IF($G10="Pickup", SUMIFS(NewEmisData!K:K, NewEmisData!$A:$A, "Pickup", NewEmisData!$B:$B, $A10, NewEmisData!$C:$C, $H10, NewEmisData!$D:$D, AA$2), SUMIFS(NewEmisData!K:K, NewEmisData!$A:$A, "LDV", NewEmisData!$B:$B, $A10, NewEmisData!$C:$C, $H10, NewEmisData!$D:$D, AA$2)) -> 0.056635638 | AB10: =$I10*IF($G10="Pickup", SUMIFS(NewEmisData!L:L, NewEmisData!$A:$A, "Pickup", NewEmisData!$B:$B, $A10, NewEmisData!$C:$C, $H10, NewEmisData!$D:$D, AB$2), SUMIFS(NewEmisData!L:L, NewEmisData!$A:$A, "LDV", NewEmisData!$B:$B, $A10, NewEmisData!$C:$C, $H10, NewEmisData!$D:$D, AB$2)) -> 0.054115247 | AC10: =$I10*IF($G10="Pickup", SUMIFS(NewEmisData!M:M, NewEmisData!$A:$A, "Pickup", NewEmisData!$B:$B, $A10, NewEmisData!$C:$C, $H10, NewEmisData!$D:$D, AC$2), SUMIFS(NewEmisData!M:M, NewEmisData!$A:$A, "LDV", NewEmisData!$B:$B, $A10, NewEmisData!$C:$C, $H10, NewEmisData!$D:$D, AC$2)) -> 0.052826207 | AD10: 0.055587066 | AE10: =$I10*IF($G10="Pickup", SUMIFS(NewEmisData!E:E, NewEmisData!$A:$A, "Pickup", NewEmisData!$B:$B, $A10, NewEmisData!$C:$C, $H10, NewEmisData!$D:$D, AE$2), SUMIFS(NewEmisData!E:E, NewEmisData!$A:$A, "LDV", NewEmisData!$B:$B, $A10, NewEmisData!$C:$C, $H10, NewEmisData!$D:$D, AE$2)) -> 0.0082552586 | AF10: =$I10*IF($G10="Pickup", SUMIFS(NewEmisData!F:F, NewEmisData!$A:$A, "Pickup", NewEmisData!$B:$B, $A10, NewEmisData!$C:$C, $H10, NewEmisData!$D:$D, AF$2), SUMIFS(NewEmisData!F:F, NewEmisData!$A:$A, "LDV", NewEmisData!$B:$B, $A10, NewEmisData!$C:$C, $H10, NewEmisData!$D:$D, AF$2)) -> 0.0079482132 | AG10: =$I10*IF($G10="Pickup", SUMIFS(NewEmisData!G:G, NewEmisData!$A:$A, "Pickup", NewEmisData!$B:$B, $A10, NewEmisData!$C:$C, $H10, NewEmisData!$D:$D, AG$2), SUMIFS(NewEmisData!G:G, NewEmisData!$A:$A, "LDV", NewEmisData!$B:$B, $A10, NewEmisData!$C:$C, $H10, NewEmisData!$D:$D, AG$2)) -> 0.0064190306 | AH10: =$I10*IF($G10="Pickup", SUMIFS(NewEmisData!H:H, NewEmisData!$A:$A, "Pickup", NewEmisData!$B:$B, $A10, NewEmisData!$C:$C, $H10, NewEmisData!$D:$D, AH$2), SUMIFS(NewEmisData!H:H, NewEmisData!$A:$A, "LDV", NewEmisData!$B:$B, $A10, NewEmisData!$C:$C, $H10, NewEmisData!$D:$D, AH$2)) -> 0.0054616828 | AI10: =$I10*IF($G10="Pickup", SUMIFS(NewEmisData!I:I, NewEmisData!$A:$A, "Pickup", NewEmisData!$B:$B, $A10, NewEmisData!$C:$C, $H10, NewEmisData!$D:$D, AI$2), SUMIFS(NewEmisData!I:I, NewEmisData!$A:$A, "LDV", NewEmisData!$B:$B, $A10, NewEmisData!$C:$C, $H10, NewEmisData!$D:$D, AI$2)) -> 0.0047275286 | AJ10: =$I10*IF($G10="Pickup", SUMIFS(NewEmisData!J:J, NewEmisData!$A:$A, "Pickup", NewEmisData!$B:$B, $A10, NewEmisData!$C:$C, $H10, NewEmisData!$D:$D, AJ$2), SUMIFS(NewEmisData!J:J, NewEmisData!$A:$A, "LDV", NewEmisData!$B:$B, $A10, NewEmisData!$C:$C, $H10, NewEmisData!$D:$D, AJ$2)) -> 0.0043136735 | AK10: =$I10*IF($G10="Pickup", SUMIFS(NewEmisData!K:K, NewEmisData!$A:$A, "Pickup", NewEmisData!$B:$B, $A10, NewEmisData!$C:$C, $H10, NewEmisData!$D:$D, AK$2), SUMIFS(NewEmisData!K:K, NewEmisData!$A:$A, "LDV", NewEmisData!$B:$B, $A10, NewEmisData!$C:$C, $H10, NewEmisData!$D:$D, AK$2)) -> 0.0041291858 | AL10: =$I10*IF($G10="Pickup", SUMIFS(NewEmisData!L:L, NewEmisData!$A:$A, "Pickup", NewEmisData!$B:$B, $A10, NewEmisData!$C:$C, $H10, NewEmisData!$D:$D, AL$2), SUMIFS(NewEmisData!L:L, NewEmisData!$A:$A, "LDV", NewEmisData!$B:$B, $A10, NewEmisData!$C:$C, $H10, NewEmisData!$D:$D, AL$2)) -> 0.0040635984 | AM10: =$I10*IF($G10="Pickup", SUMIFS(NewEmisData!M:M, NewEmisData!$A:$A, "Pickup", NewEmisData!$B:$B, $A10, NewEmisData!$C:$C, $H10, NewEmisData!$D:$D, AM$2), SUMIFS(NewEmisData!M:M, NewEmisData!$A:$A, "LDV", NewEmisData!$B:$B, $A10, NewEmisData!$C:$C, $H10, NewEmisData!$D:$D, AM$2)) -> 0.0040393864 | AN10: 0.0013041984 | AO10: =$I10*IF($G10="Pickup", SUMIFS(NewEmisData!E:E, NewEmisData!$A:$A, "Pickup", NewEmisData!$B:$B, $A10, NewEmisData!$C:$C, $H10, NewEmisData!$D:$D, AO$2), SUMIFS(NewEmisData!E:E, NewEmisData!$A:$A, "LDV", NewEmisData!$B:$B, $A10, NewEmisData!$C:$C, $H10, NewEmisData!$D:$D, AO$2)) -> 0.081828644 | AP10: =$I10*IF($G10="Pickup", SUMIFS(NewEmisData!F:F, NewEmisData!$A:$A, "Pickup", NewEmisData!$B:$B, $A10, NewEmisData!$C:$C, $H10, NewEmisData!$D:$D, AP$2), SUMIFS(NewEmisData!F:F, NewEmisData!$A:$A, "LDV", NewEmisData!$B:$B, $A10, NewEmisData!$C:$C, $H10, NewEmisData!$D:$D, AP$2)) -> 0.076175839 | AQ10: =$I10*IF($G10="Pickup", SUMIFS(NewEmisData!G:G, NewEmisData!$A:$A, "Pickup", NewEmisData!$B:$B, $A10, NewEmisData!$C:$C, $H10, NewEmisData!$D:$D, AQ$2), SUMIFS(NewEmisData!G:G, NewEmisData!$A:$A, "LDV", NewEmisData!$B:$B, $A10, NewEmisData!$C:$C, $H10, NewEmisData!$D:$D, AQ$2)) -> 0.081302809 | AR10: =$I10*IF($G10="Pickup", SUMIFS(NewEmisData!H:H, NewEmisData!$A:$A, "Pickup", NewEmisData!$B:$B, $A10, NewEmisData!$C:$C, $H10, NewEmisData!$D:$D, AR$2), SUMIFS(NewEmisData!H:H, NewEmisData!$A:$A, "LDV", NewEmisData!$B:$B, $A10, NewEmisData!$C:$C, $H10, NewEmisData!$D:$D, AR$2)) -> 0.079561689 | AS10: =$I10*IF($G10="Pickup", SUMIFS(NewEmisData!I:I, NewEmisData!$A:$A, "Pickup", NewEmisData!$B:$B, $A10, NewEmisData!$C:$C, $H10, NewEmisData!$D:$D, AS$2), SUMIFS(NewEmisData!I:I, NewEmisData!$A:$A, "LDV", NewEmisData!$B:$B, $A10, NewEmisData!$C:$C, $H10, NewEmisData!$D:$D, AS$2)) -> 0.07791053 | AT10: =$I10*IF($G10="Pickup", SUMIFS(NewEmisData!J:J, NewEmisData!$A:$A, "Pickup", NewEmisData!$B:$B, $A10, NewEmisData!$C:$C, $H10, NewEmisData!$D:$D, AT$2), SUMIFS(NewEmisData!J:J, NewEmisData!$A:$A, "LDV", NewEmisData!$B:$B, $A10, NewEmisData!$C:$C, $H10, NewEmisData!$D:$D, AT$2)) -> 0.076590334 | AU10: =$I10*IF($G10="Pickup", SUMIFS(NewEmisData!K:K, NewEmisData!$A:$A, "Pickup", NewEmisData!$B:$B, $A10, NewEmisData!$C:$C, $H10, NewEmisData!$D:$D, AU$2), SUMIFS(NewEmisData!K:K, NewEmisData!$A:$A, "LDV", NewEmisData!$B:$B, $A10, NewEmisData!$C:$C, $H10, NewEmisData!$D:$D, AU$2)) -> 0.075767939 | AV10: =$I10*IF($G10="Pickup", SUMIFS(NewEmisData!L:L, NewEmisData!$A:$A, "Pickup", NewEmisData!$B:$B, $A10, NewEmisData!$C:$C, $H10, NewEmisData!$D:$D, AV$2), SUMIFS(NewEmisData!L:L, NewEmisData!$A:$A, "LDV", NewEmisData!$B:$B, $A10, NewEmisData!$C:$C, $H10, NewEmisData!$D:$D, AV$2)) -> 0.07535371 | AW10: =$I10*IF($G10="Pickup", SUMIFS(NewEmisData!M:M, NewEmisData!$A:$A, "Pickup", NewEmisData!$B:$B, $A10, NewEmisData!$C:$C, $H10, NewEmisData!$D:$D, AW$2), SUMIFS(NewEmisData!M:M, NewEmisData!$A:$A, "LDV", NewEmisData!$B:$B, $A10, NewEmisData!$C:$C, $H10, NewEmisData!$D:$D, AW$2)) -> 0.075117977 | AX10: 0.032948539 | AY10: =$I10*IF($G10="Pickup", SUMIFS(NewEmisData!E:E, NewEmisData!$A:$A, "Pickup", NewEmisData!$B:$B, $A10, NewEmisData!$C:$C, $H10, NewEmisData!$D:$D, AY$2), SUMIFS(NewEmisData!E:E, NewEmisData!$A:$A, "LDV", NewEmisData!$B:$B, $A10, NewEmisData!$C:$C, $H10, NewEmisData!$D:$D, AY$2)) -> 0.021998194 | AZ10: =$I10*IF($G10="Pickup", SUMIFS(NewEmisData!F:F, NewEmisData!$A:$A, "Pickup", NewEmisData!$B:$B, $A10, NewEmisData!$C:$C, $H10, NewEmisData!$D:$D, AZ$2), SUMIFS(NewEmisData!F:F, NewEmisData!$A:$A, "LDV", NewEmisData!$B:$B, $A10, NewEmisData!$C:$C, $H10, NewEmisData!$D:$D, AZ$2)) -> 0.016997575 | BA10: =$I10*IF($G10="Pickup", SUMIFS(NewEmisData!G:G, NewEmisData!$A:$A, "Pickup", NewEmisData!$B:$B, $A10, NewEmisData!$C:$C, $H10, NewEmisData!$D:$D, BA$2), SUMIFS(NewEmisData!G:G, NewEmisData!$A:$A, "LDV", NewEmisData!$B:$B, $A10, NewEmisData!$C:$C, $H10, NewEmisData!$D:$D, BA$2)) -> 0.016580879 | BB10: =$I10*IF($G10="Pickup", SUMIFS(NewEmisData!H:H, NewEmisData!$A:$A, "Pickup", NewEmisData!$B:$B, $A10, NewEmisData!$C:$C, $H10, NewEmisData!$D:$D, BB$2), SUMIFS(NewEmisData!H:H, NewEmisData!$A:$A, "LDV", NewEmisData!$B:$B, $A10, NewEmisData!$C:$C, $H10, NewEmisData!$D:$D, BB$2)) -> 0.015040645 | BC10: =$I10*IF($G10="Pickup", SUMIFS(NewEmisData!I:I, NewEmisData!$A:$A, "Pickup", NewEmisData!$B:$B, $A10, NewEmisData!$C:$C, $H10, NewEmisData!$D:$D, BC$2), SUMIFS(NewEmisData!I:I, NewEmisData!$A:$A, "LDV", NewEmisData!$B:$B, $A10, NewEmisData!$C:$C, $H10, NewEmisData!$D:$D, BC$2)) -> 0.013579961 | BD10: =$I10*IF($G10="Pickup", SUMIFS(NewEmisData!J:J, NewEmisData!$A:$A, "Pickup", NewEmisData!$B:$B, $A10, NewEmisData!$C:$C, $H10, NewEmisData!$D:$D, BD$2), SUMIFS(NewEmisData!J:J, NewEmisData!$A:$A, "LDV", NewEmisData!$B:$B, $A10, NewEmisData!$C:$C, $H10, NewEmisData!$D:$D, BD$2)) -> 0.012412067 | BE10: =$I10*IF($G10="Pickup", SUMIFS(NewEmisData!K:K, NewEmisData!$A:$A, "Pickup", NewEmisData!$B:$B, $A10, NewEmisData!$C:$C, $H10, NewEmisData!$D:$D, BE$2), SUMIFS(NewEmisData!K:K, NewEmisData!$A:$A, "LDV", NewEmisData!$B:$B, $A10, NewEmisData!$C:$C, $H10, NewEmisData!$D:$D, BE$2)) -> 0.011684507 | BF10: =$I10*IF($G10="Pickup", SUMIFS(NewEmisData!L:L, NewEmisData!$A:$A, "Pickup", NewEmisData!$B:$B, $A10, NewEmisData!$C:$C, $H10, NewEmisData!$D:$D, BF$2), SUMIFS(NewEmisData!L:L, NewEmisData!$A:$A, "LDV", NewEmisData!$B:$B, $A10, NewEmisData!$C:$C, $H10, NewEmisData!$D:$D, BF$2)) -> 0.011318096 | BG10: =$I10*IF($G10="Pickup", SUMIFS(NewEmisData!M:M, NewEmisData!$A:$A, "Pickup", NewEmisData!$B:$B, $A10, NewEmisData!$C:$C, $H10, NewEmisData!$D:$D, BG$2), SUMIFS(NewEmisData!M:M, NewEmisData!$A:$A, "LDV", NewEmisData!$B:$B, $A10, NewEmisData!$C:$C, $H10, NewEmisData!$D:$D, BG$2)) -> 0.011109457 | BH10: 0.0066026126 | BI10: =$I10*IF($G10="Pickup", SUMIFS(NewEmisData!E:E, NewEmisData!$A:$A, "Pickup", NewEmisData!$B:$B, $A10, NewEmisData!$C:$C, $H10, NewEmisData!$D:$D, BI$2), SUMIFS(NewEmisData!E:E, NewEmisData!$A:$A, "LDV", NewEmisData!$B:$B, $A10, NewEmisData!$C:$C, $H10, NewEmisData!$D:$D, BI$2)) -> 6.633983 | BJ10: =$I10*IF($G10="Pickup", SUMIFS(NewEmisData!F:F, NewEmisData!$A:$A, "Pickup", NewEmisData!$B:$B, $A10, NewEmisData!$C:$C, $H10, NewEmisData!$D:$D, BJ$2), SUMIFS(NewEmisData!F:F, NewEmisData!$A:$A, "LDV", NewEmisData!$B:$B, $A10, NewEmisData!$C:$C, $H10, NewEmisData!$D:$D, BJ$2)) -> 3.9206206 | BK10: =$I10*IF($G10="Pickup", SUMIFS(NewEmisData!G:G, NewEmisData!$A:$A, "Pickup", NewEmisData!$B:$B, $A10, NewEmisData!$C:$C, $H10, NewEmisData!$D:$D, BK$2), SUMIFS(NewEmisData!G:G, NewEmisData!$A:$A, "LDV", NewEmisData!$B:$B, $A10, NewEmisData!$C:$C, $H10, NewEmisData!$D:$D, BK$2)) -> 3.0174466 | BL10: =$I10*IF($G10="Pickup", SUMIFS(NewEmisData!H:H, NewEmisData!$A:$A, "Pickup", NewEmisData!$B:$B, $A10, NewEmisData!$C:$C, $H10, NewEmisData!$D:$D, BL$2), SUMIFS(NewEmisData!H:H, NewEmisData!$A:$A, "LDV", NewEmisData!$B:$B, $A10, NewEmisData!$C:$C, $H10, NewEmisData!$D:$D, BL$2)) -> 2.3529222 | BM10: =$I10*IF($G10="Pickup", SUMIFS(NewEmisData!I:I, NewEmisData!$A:$A, "Pickup", NewEmisData!$B:$B, $A10, NewEmisData!$C:$C, $H10, NewEmisData!$D:$D, BM$2), SUMIFS(NewEmisData!I:I, NewEmisData!$A:$A, "LDV", NewEmisData!$B:$B, $A10, NewEmisData!$C:$C, $H10, NewEmisData!$D:$D, BM$2)) -> 1.7038406 | BN10: =$I10*IF($G10="Pickup", SUMIFS(NewEmisData!J:J, NewEmisData!$A:$A, "Pickup", NewEmisData!$B:$B, $A10, NewEmisData!$C:$C, $H10, NewEmisData!$D:$D, BN$2), SUMIFS(NewEmisData!J:J, NewEmisData!$A:$A, "LDV", NewEmisData!$B:$B, $A10, NewEmisData!$C:$C, $H10, NewEmisData!$D:$D, BN$2)) -> 1.3463731 | BO10: =$I10*IF($G10="Pickup", SUMIFS(NewEmisData!K:K, NewEmisData!$A:$A, "Pickup", NewEmisData!$B:$B, $A10, NewEmisData!$C:$C, $H10, NewEmisData!$D:$D, BO$2), SUMIFS(NewEmisData!K:K, NewEmisData!$A:$A, "LDV", NewEmisData!$B:$B, $A10, NewEmisData!$C:$C, $H10, NewEmisData!$D:$D, BO$2)) -> 1.1858347 | BP10: =$I10*IF($G10="Pickup", SUMIFS(NewEmisData!L:L, NewEmisData!$A:$A, "Pickup", NewEmisData!$B:$B, $A10, NewEmisData!$C:$C, $H10, NewEmisData!$D:$D, BP$2), SUMIFS(NewEmisData!L:L, NewEmisData!$A:$A, "LDV", NewEmisData!$B:$B, $A10, NewEmisData!$C:$C, $H10, NewEmisData!$D:$D, BP$2)) -> 1.1335062 | BQ10: =$I10*IF($G10="Pickup", SUMIFS(NewEmisData!M:M, NewEmisData!$A:$A, "Pickup", NewEmisData!$B:$B, $A10, NewEmisData!$C:$C, $H10, NewEmisData!$D:$D, BQ$2), SUMIFS(NewEmisData!M:M, NewEmisData!$A:$A, "LDV", NewEmisData!$B:$B, $A10, NewEmisData!$C:$C, $H10, NewEmisData!$D:$D, BQ$2)) -> 1.1009029 | BR10: 1.5622002 | BS10: =$I10*IF($G10="Pickup", SUMIFS(NewEmisData!E:E, NewEmisData!$A:$A, "Pickup", NewEmisData!$B:$B, $A10, NewEmisData!$C:$C, $H10, NewEmisData!$D:$D, BS$2), SUMIFS(NewEmisData!E:E, NewEmisData!$A:$A, "LDV", NewEmisData!$B:$B, $A10, NewEmisData!$C:$C, $H10, NewEmisData!$D:$D, BS$2)) -> 0.77473151 | BT10: =$I10*IF($G10="Pickup", SUMIFS(NewEmisData!F:F, NewEmisData!$A:$A, "Pickup", NewEmisData!$B:$B, $A10, NewEmisData!$C:$C, $H10, NewEmisData!$D:$D, BT$2), SUMIFS(NewEmisData!F:F, NewEmisData!$A:$A, "LDV", NewEmisData!$B:$B, $A10, NewEmisData!$C:$C, $H10, NewEmisData!$D:$D, BT$2)) -> 0.41904908 | BU10: =$I10*IF($G10="Pickup", SUMIFS(NewEmisData!G:G, NewEmisData!$A:$A, "Pickup", NewEmisData!$B:$B, $A10, NewEmisData!$C:$C, $H10, NewEmisData!$D:$D, BU$2), SUMIFS(NewEmisData!G:G, NewEmisData!$A:$A, "LDV", NewEmisData!$B:$B, $A10, NewEmisData!$C:$C, $H10, NewEmisData!$D:$D, BU$2)) -> 0.309829 | BV10: =$I10*IF($G10="Pickup", SUMIFS(NewEmisData!H:H, NewEmisData!$A:$A, "Pickup", NewEmisData!$B:$B, $A10, NewEmisData!$C:$C, $H10, NewEmisData!$D:$D, BV$2), SUMIFS(NewEmisData!H:H, NewEmisData!$A:$A, "LDV", NewEmisData!$B:$B, $A10, NewEmisData!$C:$C, $H10, NewEmisData!$D:$D, BV$2)) -> 0.25046259 | BW10: =$I10*IF($G10="Pickup", SUMIFS(NewEmisData!I:I, NewEmisData!$A:$A, "Pickup", NewEmisData!$B:$B, $A10, NewEmisData!$C:$C, $H10, NewEmisData!$D:$D, BW$2), SUMIFS(NewEmisData!I:I, NewEmisData!$A:$A, "LDV", NewEmisData!$B:$B, $A10, NewEmisData!$C:$C, $H10, NewEmisData!$D:$D, BW$2)) -> 0.18616224 | BX10: =$I10*IF($G10="Pickup", SUMIFS(NewEmisData!J:J, NewEmisData!$A:$A, "Pickup", NewEmisData!$B:$B, $A10, NewEmisData!$C:$C, $H10, NewEmisData!$D:$D, BX$2), SUMIFS(NewEmisData!J:J, NewEmisData!$A:$A, "LDV", NewEmisData!$B:$B, $A10, NewEmisData!$C:$C, $H10, NewEmisData!$D:$D, BX$2)) -> 0.15683047 | BY10: =$I10*IF($G10="Pickup", SUMIFS(NewEmisData!K:K, NewEmisData!$A:$A, "Pickup", NewEmisData!$B:$B, $A10, NewEmisData!$C:$C, $H10, NewEmisData!$D:$D, BY$2), SUMIFS(NewEmisData!K:K, NewEmisData!$A:$A, "LDV", NewEmisData!$B:$B, $A10, NewEmisData!$C:$C, $H10, NewEmisData!$D:$D, BY$2)) -> 0.14094 | BZ10: =$I10*IF($G10="Pickup", SUMIFS(NewEmisData!L:L, NewEmisData!$A:$A, "Pickup", NewEmisData!$B:$B, $A10, NewEmisData!$C:$C, $H10, NewEmisData!$D:$D, BZ$2), SUMIFS(NewEmisData!L:L, NewEmisData!$A:$A, "LDV", NewEmisData!$B:$B, $A10, NewEmisData!$C:$C, $H10, NewEmisData!$D:$D, BZ$2)) -> 0.13477407 | CA10: =$I10*IF($G10="Pickup", SUMIFS(NewEmisData!M:M, NewEmisData!$A:$A, "Pickup", NewEmisData!$B:$B, $A10, NewEmisData!$C:$C, $H10, NewEmisData!$D:$D, CA$2), SUMIFS(NewEmisData!M:M, NewEmisData!$A:$A, "LDV", NewEmisData!$B:$B, $A10, NewEmisData!$C:$C, $H10, NewEmisData!$D:$D, CA$2)) -> 0.12984033 | CB10: 0.11295847 | CC10: =$I10*IF($G10="Pickup", SUMIFS(NewEmisData!E:E, NewEmisData!$A:$A, "Pickup", NewEmisData!$B:$B, $A10, NewEmisData!$C:$C, $H10, NewEmisData!$D:$D, CC$2), SUMIFS(NewEmisData!E:E, NewEmisData!$A:$A, "LDV", NewEmisData!$B:$B, $A10, NewEmisData!$C:$C, $H10, NewEmisData!$D:$D, CC$2)) -> 0.045278925 | CD10: =$I10*IF($G10="Pickup", SUMIFS(NewEmisData!F:F, NewEmisData!$A:$A, "Pickup", NewEmisData!$B:$B, $A10, NewEmisData!$C:$C, $H10, NewEmisData!$D:$D, CD$2), SUMIFS(NewEmisData!F:F, NewEmisData!$A:$A, "LDV", NewEmisData!$B:$B, $A10, NewEmisData!$C:$C, $H10, NewEmisData!$D:$D, CD$2)) -> 0.030659932 | CE10: =$I10*IF($G10="Pickup", SUMIFS(NewEmisData!G:G, NewEmisData!$A:$A, "Pickup", NewEmisData!$B:$B, $A10, NewEmisData!$C:$C, $H10, NewEmisData!$D:$D, CE$2), SUMIFS(NewEmisData!G:G, NewEmisData!$A:$A, "LDV", NewEmisData!$B:$B, $A10, NewEmisData!$C:$C, $H10, NewEmisData!$D:$D, CE$2)) -> 0.028386595 | CF10: =$I10*IF($G10="Pickup", SUMIFS(NewEmisData!H:H, NewEmisData!$A:$A, "Pickup", NewEmisData!$B:$B, $A10, NewEmisData!$C:$C, $H10, NewEmisData!$D:$D, CF$2), SUMIFS(NewEmisData!H:H, NewEmisData!$A:$A, "LDV", NewEmisData!$B:$B, $A10, NewEmisData!$C:$C, $H10, NewEmisData!$D:$D, CF$2)) -> 0.027093413 | CG10: =$I10*IF($G10="Pickup", SUMIFS(NewEmisData!I:I, NewEmisData!$A:$A, "Pickup", NewEmisData!$B:$B, $A10, NewEmisData!$C:$C, $H10, NewEmisData!$D:$D, CG$2), SUMIFS(NewEmisData!I:I, NewEmisData!$A:$A, "LDV", NewEmisData!$B:$B, $A10, NewEmisData!$C:$C, $H10, NewEmisData!$D:$D, CG$2)) -> 0.026239575 | CH10: =$I10*IF($G10="Pickup", SUMIFS(NewEmisData!J:J, NewEmisData!$A:$A, "Pickup", NewEmisData!$B:$B, $A10, NewEmisData!$C:$C, $H10, NewEmisData!$D:$D, CH$2), SUMIFS(NewEmisData!J:J, NewEmisData!$A:$A, "LDV", NewEmisData!$B:$B, $A10, NewEmisData!$C:$C, $H10, NewEmisData!$D:$D, CH$2)) -> 0.025564245 | CI10: =$I10*IF($G10="Pickup", SUMIFS(NewEmisData!K:K, NewEmisData!$A:$A, "Pickup", NewEmisData!$B:$B, $A10, NewEmisData!$C:$C, $H10, NewEmisData!$D:$D, CI$2), SUMIFS(NewEmisData!K:K, NewEmisData!$A:$A, "LDV", NewEmisData!$B:$B, $A10, NewEmisData!$C:$C, $H10, NewEmisData!$D:$D, CI$2)) -> 0.025562136 | CJ10: =$I10*IF($G10="Pickup", SUMIFS(NewEmisData!L:L, NewEmisData!$A:$A, "Pickup", NewEmisData!$B:$B, $A10, NewEmisData!$C:$C, $H10, NewEmisData!$D:$D, CJ$2), SUMIFS(NewEmisData!L:L, NewEmisData!$A:$A, "LDV", NewEmisData!$B:$B, $A10, NewEmisData!$C:$C, $H10, NewEmisData!$D:$D, CJ$2)) -> 0.02556154 | CK10: =$I10*IF($G10="Pickup", SUMIFS(NewEmisData!M:M, NewEmisData!$A:$A, "Pickup", NewEmisData!$B:$B, $A10, NewEmisData!$C:$C, $H10, NewEmisData!$D:$D, CK$2), SUMIFS(NewEmisData!M:M, NewEmisData!$A:$A, "LDV", NewEmisData!$B:$B, $A10, NewEmisData!$C:$C, $H10, NewEmisData!$D:$D, CK$2)) -> 0.025560994 | CL10: 0.020846549 | CM10: =$I10*IF($G10="Pickup", SUMIFS(NewEmisData!E:E, NewEmisData!$A:$A, "Pickup", NewEmisData!$B:$B, $A10, NewEmisData!$C:$C, $H10, NewEmisData!$D:$D, CM$2), SUMIFS(NewEmisData!E:E, NewEmisData!$A:$A, "LDV", NewEmisData!$B:$B, $A10, NewEmisData!$C:$C, $H10, NewEmisData!$D:$D, CM$2)) -> 0.022616228 | CN10: =$I10*IF($G10="Pickup", SUMIFS(NewEmisData!F:F, NewEmisData!$A:$A, "Pickup", NewEmisData!$B:$B, $A10, NewEmisData!$C:$C, $H10, NewEmisData!$D:$D, CN$2), SUMIFS(NewEmisData!F:F, NewEmisData!$A:$A, "LDV", NewEmisData!$B:$B, $A10, NewEmisData!$C:$C, $H10, NewEmisData!$D:$D, CN$2)) -> 0.013703994 | CO10: =$I10*IF($G10="Pickup", SUMIFS(NewEmisData!G:G, NewEmisData!$A:$A, "Pickup", NewEmisData!$B:$B, $A10, NewEmisData!$C:$C, $H10, NewEmisData!$D:$D, CO$2), SUMIFS(NewEmisData!G:G, NewEmisData!$A:$A, "LDV", NewEmisData!$B:$B, $A10, NewEmisData!$C:$C, $H10, NewEmisData!$D:$D, CO$2)) -> 0.011127954 | CP10: =$I10*IF($G10="Pickup", SUMIFS(NewEmisData!H:H, NewEmisData!$A:$A, "Pickup", NewEmisData!$B:$B, $A10, NewEmisData!$C:$C, $H10, NewEmisData!$D:$D, CP$2), SUMIFS(NewEmisData!H:H, NewEmisData!$A:$A, "LDV", NewEmisData!$B:$B, $A10, NewEmisData!$C:$C, $H10, NewEmisData!$D:$D, CP$2)) -> 0.0091642249 | CQ10: =$I10*IF($G10="Pickup", SUMIFS(NewEmisData!I:I, NewEmisData!$A:$A, "Pickup", NewEmisData!$B:$B, $A10, NewEmisData!$C:$C, $H10, NewEmisData!$D:$D, CQ$2), SUMIFS(NewEmisData!I:I, NewEmisData!$A:$A, "LDV", NewEmisData!$B:$B, $A10, NewEmisData!$C:$C, $H10, NewEmisData!$D:$D, CQ$2)) -> 0.0082157407 | CR10: =$I10*IF($G10="Pickup", SUMIFS(NewEmisData!J:J, NewEmisData!$A:$A, "Pickup", NewEmisData!$B:$B, $A10, NewEmisData!$C:$C, $H10, NewEmisData!$D:$D, CR$2), SUMIFS(NewEmisData!J:J, NewEmisData!$A:$A, "LDV", NewEmisData!$B:$B, $A10, NewEmisData!$C:$C, $H10, NewEmisData!$D:$D, CR$2)) -> 0.0078051703 | CS10: =$I10*IF($G10="Pickup", SUMIFS(NewEmisData!K:K, NewEmisData!$A:$A, "Pickup", NewEmisData!$B:$B, $A10, NewEmisData!$C:$C, $H10, NewEmisData!$D:$D, CS$2), SUMIFS(NewEmisData!K:K, NewEmisData!$A:$A, "LDV", NewEmisData!$B:$B, $A10, NewEmisData!$C:$C, $H10, NewEmisData!$D:$D, CS$2)) -> 0.0077607553 | CT10: =$I10*IF($G10="Pickup", SUMIFS(NewEmisData!L:L, NewEmisData!$A:$A, "Pickup", NewEmisData!$B:$B, $A10, NewEmisData!$C:$C, $H10, NewEmisData!$D:$D, CT$2), SUMIFS(NewEmisData!L:L, NewEmisData!$A:$A, "LDV", NewEmisData!$B:$B, $A10, NewEmisData!$C:$C, $H10, NewEmisData!$D:$D, CT$2)) -> 0.0076883349 | CU10: =$I10*IF($G10="Pickup", SUMIFS(NewEmisData!M:M, NewEmisData!$A:$A, "Pickup", NewEmisData!$B:$B, $A10, NewEmisData!$C:$C, $H10, NewEmisData!$D:$D, CU$2), SUMIFS(NewEmisData!M:M, NewEmisData!$A:$A, "LDV", NewEmisData!$B:$B, $A10, NewEmisData!$C:$C, $H10, NewEmisData!$D:$D, CU$2)) -> 0.0076878848 | CV10: 0.0052030688 | CW10: 0.0030448047 | CX10: 0.0018865909 | CY10: 0.0015570268 | CZ10: 0.0012432183 | DA10: 0.00092522519 | DB10: 0.00072309457 | DC10: 0.00068940707 | DD10: 0.00068441484 | DE10: 0.00068634617 | DF10: 0.00068634617 | DG10: =$I10*IF($G10="Pickup", SUMIFS(NewEmisData!E:E, NewEmisData!$A:$A, "Pickup", NewEmisData!$B:$B, $A10, NewEmisData!$C:$C, $H10, NewEmisData!$D:$D, DG$2), SUMIFS(NewEmisData!E:E, NewEmisData!$A:$A, "LDV", NewEmisData!$B:$B, $A10, NewEmisData!$C:$C, $H10, NewEmisData!$D:$D, DG$2)) -> 0 | DH10: =$I10*IF($G10="Pickup", SUMIFS(NewEmisData!F:F, NewEmisData!$A:$A, "Pickup", NewEmisData!$B:$B, $A10, NewEmisData!$C:$C, $H10, NewEmisData!$D:$D, DH$2), SUMIFS(NewEmisData!F:F, NewEmisData!$A:$A, "LDV", NewEmisData!$B:$B, $A10, NewEmisData!$C:$C, $H10, NewEmisData!$D:$D, DH$2)) -> 0 | DI10: =$I10*IF($G10="Pickup", SUMIFS(NewEmisData!G:G, NewEmisData!$A:$A, "Pickup", NewEmisData!$B:$B, $A10, NewEmisData!$C:$C, $H10, NewEmisData!$D:$D, DI$2), SUMIFS(NewEmisData!G:G, NewEmisData!$A:$A, "LDV", NewEmisData!$B:$B, $A10, NewEmisData!$C:$C, $H10, NewEmisData!$D:$D, DI$2)) -> 0 | DJ10: =$I10*IF($G10="Pickup", SUMIFS(NewEmisData!H:H, NewEmisData!$A:$A, "Pickup", NewEmisData!$B:$B, $A10, NewEmisData!$C:$C, $H10, NewEmisData!$D:$D, DJ$2), SUMIFS(NewEmisData!H:H, NewEmisData!$A:$A, "LDV", NewEmisData!$B:$B, $A10, NewEmisData!$C:$C, $H10, NewEmisData!$D:$D, DJ$2)) -> 0 | DK10: =$I10*IF($G10="Pickup", SUMIFS(NewEmisData!I:I, NewEmisData!$A:$A, "Pickup", NewEmisData!$B:$B, $A10, NewEmisData!$C:$C, $H10, NewEmisData!$D:$D, DK$2), SUMIFS(NewEmisData!I:I, NewEmisData!$A:$A, "LDV", NewEmisData!$B:$B, $A10, NewEmisData!$C:$C, $H10, NewEmisData!$D:$D, DK$2)) -> 0 | DL10: =$I10*IF($G10="Pickup", SUMIFS(NewEmisData!J:J, NewEmisData!$A:$A, "Pickup", NewEmisData!$B:$B, $A10, NewEmisData!$C:$C, $H10, NewEmisData!$D:$D, DL$2), SUMIFS(NewEmisData!J:J, NewEmisData!$A:$A, "LDV", NewEmisData!$B:$B, $A10, NewEmisData!$C:$C, $H10, NewEmisData!$D:$D, DL$2)) -> 0 | DM10: =$I10*IF($G10="Pickup", SUMIFS(NewEmisData!K:K, NewEmisData!$A:$A, "Pickup", NewEmisData!$B:$B, $A10, NewEmisData!$C:$C, $H10, NewEmisData!$D:$D, DM$2), SUMIFS(NewEmisData!K:K, NewEmisData!$A:$A, "LDV", NewEmisData!$B:$B, $A10, NewEmisData!$C:$C, $H10, NewEmisData!$D:$D, DM$2)) -> 0 | DN10: =$I10*IF($G10="Pickup", SUMIFS(NewEmisData!L:L, NewEmisData!$A:$A, "Pickup", NewEmisData!$B:$B, $A10, NewEmisData!$C:$C, $H10, NewEmisData!$D:$D, DN$2), SUMIFS(NewEmisData!L:L, NewEmisData!$A:$A, "LDV", NewEmisData!$B:$B, $A10, NewEmisData!$C:$C, $H10, NewEmisData!$D:$D, DN$2)) -> 0 | DO10: =$I10*IF($G10="Pickup", SUMIFS(NewEmisData!M:M, NewEmisData!$A:$A, "Pickup", NewEmisData!$B:$B, $A10, NewEmisData!$C:$C, $H10, NewEmisData!$D:$D, DO$2), SUMIFS(NewEmisData!M:M, NewEmisData!$A:$A, "LDV", NewEmisData!$B:$B, $A10, NewEmisData!$C:$C, $H10, NewEmisData!$D:$D, DO$2)) -> 0 | DP10: 0.0013868758 | DQ10: =$I10*IF($G10="Pickup", SUMIFS(NewEmisData!E:E, NewEmisData!$A:$A, "Pickup", NewEmisData!$B:$B, $A10, NewEmisData!$C:$C, $H10, NewEmisData!$D:$D, DQ$2), SUMIFS(NewEmisData!E:E, NewEmisData!$A:$A, "LDV", NewEmisData!$B:$B, $A10, NewEmisData!$C:$C, $H10, NewEmisData!$D:$D, DQ$2)) -> 0.01533373 | DR10: =$I10*IF($G10="Pickup", SUMIFS(NewEmisData!F:F, NewEmisData!$A:$A, "Pickup", NewEmisData!$B:$B, $A10, NewEmisData!$C:$C, $H10, NewEmisData!$D:$D, DR$2), SUMIFS(NewEmisData!F:F, NewEmisData!$A:$A, "LDV", NewEmisData!$B:$B, $A10, NewEmisData!$C:$C, $H10, NewEmisData!$D:$D, DR$2)) -> 0.00857914 | DS10: =$I10*IF($G10="Pickup", SUMIFS(NewEmisData!G:G, NewEmisData!$A:$A, "Pickup", NewEmisData!$B:$B, $A10, NewEmisData!$C:$C, $H10, NewEmisData!$D:$D, DS$2), SUMIFS(NewEmisData!G:G, NewEmisData!$A:$A, "LDV", NewEmisData!$B:$B, $A10, NewEmisData!$C:$C, $H10, NewEmisData!$D:$D, DS$2)) -> 0.0068261405 | DT10: =$I10*IF($G10="Pickup", SUMIFS(NewEmisData!H:H, NewEmisData!$A:$A, "Pickup", NewEmisData!$B:$B, $A10, NewEmisData!$C:$C, $H10, NewEmisData!$D:$D, DT$2), SUMIFS(NewEmisData!H:H, NewEmisData!$A:$A, "LDV", NewEmisData!$B:$B, $A10, NewEmisData!$C:$C, $H10, NewEmisData!$D:$D, DT$2)) -> 0.005230609 | DU10: =$I10*IF($G10="Pickup", SUMIFS(NewEmisData!I:I, NewEmisData!$A:$A, "Pickup", NewEmisData!$B:$B, $A10, NewEmisData!$C:$C, $H10, NewEmisData!$D:$D, DU$2), SUMIFS(NewEmisData!I:I, NewEmisData!$A:$A, "LDV", NewEmisData!$B:$B, $A10, NewEmisData!$C:$C, $H10, NewEmisData!$D:$D, DU$2)) -> 0.0040991034 | DV10: =$I10*IF($G10="Pickup", SUMIFS(NewEmisData!J:J, NewEmisData!$A:$A, "Pickup", NewEmisData!$B:$B, $A10, NewEmisData!$C:$C, $H10, NewEmisData!$D:$D, DV$2), SUMIFS(NewEmisData!J:J, NewEmisData!$A:$A, "LDV", NewEmisData!$B:$B, $A10, NewEmisData!$C:$C, $H10, NewEmisData!$D:$D, DV$2)) -> 0.0035909984 | DW10: =$I10*IF($G10="Pickup", SUMIFS(NewEmisData!K:K, NewEmisData!$A:$A, "Pickup", NewEmisData!$B:$B, $A10, NewEmisData!$C:$C, $H10, NewEmisData!$D:$D, DW$2), SUMIFS(NewEmisData!K:K, NewEmisData!$A:$A, "LDV", NewEmisData!$B:$B, $A10, NewEmisData!$C:$C, $H10, NewEmisData!$D:$D, DW$2)) -> 0.0033016557 | DX10: =$I10*IF($G10="Pickup", SUMIFS(NewEmisData!L:L, NewEmisData!$A:$A, "Pickup", NewEmisData!$B:$B, $A10, NewEmisData!$C:$C, $H10, NewEmisData!$D:$D, DX$2), SUMIFS(NewEmisData!L:L, NewEmisData!$A:$A, "LDV", NewEmisData!$B:$B, $A10, NewEmisData!$C:$C, $H10, NewEmisData!$D:$D, DX$2)) -> 0.0032097041 | DY10: =$I10*IF($G10="Pickup", SUMIFS(NewEmisData!M:M, NewEmisData!$A:$A, "Pickup", NewEmisData!$B:$B, $A10, NewEmisData!$C:$C, $H10, NewEmisData!$D:$D, DY$2), SUMIFS(NewEmisData!M:M, NewEmisData!$A:$A, "LDV", NewEmisData!$B:$B, $A10, NewEmisData!$C:$C, $H10, NewEmisData!$D:$D, DY$2)) -> 0.0031631495 | DZ10: 0.0043350573 | EA10: =K10 -> 477.08587 | EB10: =L10 -> 459.34104 | EC10: =M10 -> 447.45897 | ED10: =N10 -> 380.72393 | EE10: =O10 -> 329.54737 | EF10: =P10 -> 300.6983 | EG10: =Q10 -> 287.838 | EH10: =R10 -> 283.26611 | ... FX10: =BH10 -> 0.0066026126
A11: =_xlfn.CONCAT(IF(LEFT(TRIM(A10),1)="*", "*R", "R"), 1+RIGHT(TRIM(A10),1)) -> R3 | B11: =B10 -> TLMCGSLC11 | C11: =C10 -> TL.GSL.MC.CONV.2011 | D11: =D10 -> bn-vmt, bn-vmt/a | E11: =E10 -> TLGSL | F11: =F10 -> TL | G11: Mini car | H11: GSL | I11: 1 | J11: =CONCATENATE(G11,"-",H11) -> Mini car-GSL | K11: =$I11*IF($G11="Pickup", SUMIFS(NewEmisData!E:E, NewEmisData!$A:$A, "Pickup", NewEmisData!$B:$B, $A11, NewEmisData!$C:$C, $H11, NewEmisData!$D:$D, K$2), SUMIFS(NewEmisData!E:E, NewEmisData!$A:$A, "LDV", NewEmisData!$B:$B, $A11, NewEmisData!$C:$C, $H11, NewEmisData!$D:$D, K$2)) -> 437.85747 | L11: =$I11*IF($G11="Pickup", SUMIFS(NewEmisData!F:F, NewEmisData!$A:$A, "Pickup", NewEmisData!$B:$B, $A11, NewEmisData!$C:$C, $H11, NewEmisData!$D:$D, L$2), SUMIFS(NewEmisData!F:F, NewEmisData!$A:$A, "LDV", NewEmisData!$B:$B, $A11, NewEmisData!$C:$C, $H11, NewEmisData!$D:$D, L$2)) -> 424.60988 | M11: =$I11*IF($G11="Pickup", SUMIFS(NewEmisData!G:G, NewEmisData!$A:$A, "Pickup", NewEmisData!$B:$B, $A11, NewEmisData!$C:$C, $H11, NewEmisData!$D:$D, M$2), SUMIFS(NewEmisData!G:G, NewEmisData!$A:$A, "LDV", NewEmisData!$B:$B, $A11, NewEmisData!$C:$C, $H11, NewEmisData!$D:$D, M$2)) -> 389.26792 | N11: =$I11*IF($G11="Pickup", SUMIFS(NewEmisData!H:H, NewEmisData!$A:$A, "Pickup", NewEmisData!$B:$B, $A11, NewEmisData!$C:$C, $H11, NewEmisData!$D:$D, N$2), SUMIFS(NewEmisData!H:H, NewEmisData!$A:$A, "LDV", NewEmisData!$B:$B, $A11, NewEmisData!$C:$C, $H11, NewEmisData!$D:$D, N$2)) -> 331.09003 | O11: =$I11*IF($G11="Pickup", SUMIFS(NewEmisData!I:I, NewEmisData!$A:$A, "Pickup", NewEmisData!$B:$B, $A11, NewEmisData!$C:$C, $H11, NewEmisData!$D:$D, O$2), SUMIFS(NewEmisData!I:I, NewEmisData!$A:$A, "LDV", NewEmisData!$B:$B, $A11, NewEmisData!$C:$C, $H11, NewEmisData!$D:$D, O$2)) -> 286.4693 | P11: =$I11*IF($G11="Pickup", SUMIFS(NewEmisData!J:J, NewEmisData!$A:$A, "Pickup", NewEmisData!$B:$B, $A11, NewEmisData!$C:$C, $H11, NewEmisData!$D:$D, P$2), SUMIFS(NewEmisData!J:J, NewEmisData!$A:$A, "LDV", NewEmisData!$B:$B, $A11, NewEmisData!$C:$C, $H11, NewEmisData!$D:$D, P$2)) -> 261.3308 | Q11: =$I11*IF($G11="Pickup", SUMIFS(NewEmisData!K:K, NewEmisData!$A:$A, "Pickup", NewEmisData!$B:$B, $A11, NewEmisData!$C:$C, $H11, NewEmisData!$D:$D, Q$2), SUMIFS(NewEmisData!K:K, NewEmisData!$A:$A, "LDV", NewEmisData!$B:$B, $A11, NewEmisData!$C:$C, $H11, NewEmisData!$D:$D, Q$2)) -> 250.12665 | R11: =$I11*IF($G11="Pickup", SUMIFS(NewEmisData!L:L, NewEmisData!$A:$A, "Pickup", NewEmisData!$B:$B, $A11, NewEmisData!$C:$C, $H11, NewEmisData!$D:$D, R$2), SUMIFS(NewEmisData!L:L, NewEmisData!$A:$A, "LDV", NewEmisData!$B:$B, $A11, NewEmisData!$C:$C, $H11, NewEmisData!$D:$D, R$2)) -> 246.14649 | S11: =$I11*IF($G11="Pickup", SUMIFS(NewEmisData!M:M, NewEmisData!$A:$A, "Pickup", NewEmisData!$B:$B, $A11, NewEmisData!$C:$C, $H11, NewEmisData!$D:$D, S$2), SUMIFS(NewEmisData!M:M, NewEmisData!$A:$A, "LDV", NewEmisData!$B:$B, $A11, NewEmisData!$C:$C, $H11, NewEmisData!$D:$D, S$2)) -> 244.67782 | T11: 0.20692409 | U11: =$I11*IF($G11="Pickup", SUMIFS(NewEmisData!E:E, NewEmisData!$A:$A, "Pickup", NewEmisData!$B:$B, $A11, NewEmisData!$C:$C, $H11, NewEmisData!$D:$D, U$2), SUMIFS(NewEmisData!E:E, NewEmisData!$A:$A, "LDV", NewEmisData!$B:$B, $A11, NewEmisData!$C:$C, $H11, NewEmisData!$D:$D, U$2)) -> 0.78000131 | V11: =$I11*IF($G11="Pickup", SUMIFS(NewEmisData!F:F, NewEmisData!$A:$A, "Pickup", NewEmisData!$B:$B, $A11, NewEmisData!$C:$C, $H11, NewEmisData!$D:$D, V$2), SUMIFS(NewEmisData!F:F, NewEmisData!$A:$A, "LDV", NewEmisData!$B:$B, $A11, NewEmisData!$C:$C, $H11, NewEmisData!$D:$D, V$2)) -> 0.32360528 | W11: =$I11*IF($G11="Pickup", SUMIFS(NewEmisData!G:G, NewEmisData!$A:$A, "Pickup", NewEmisData!$B:$B, $A11, NewEmisData!$C:$C, $H11, NewEmisData!$D:$D, W$2), SUMIFS(NewEmisData!G:G, NewEmisData!$A:$A, "LDV", NewEmisData!$B:$B, $A11, NewEmisData!$C:$C, $H11, NewEmisData!$D:$D, W$2)) -> 0.19152447 | X11: =$I11*IF($G11="Pickup", SUMIFS(NewEmisData!H:H, NewEmisData!$A:$A, "Pickup", NewEmisData!$B:$B, $A11, NewEmisData!$C:$C, $H11, NewEmisData!$D:$D, X$2), SUMIFS(NewEmisData!H:H, NewEmisData!$A:$A, "LDV", NewEmisData!$B:$B, $A11, NewEmisData!$C:$C, $H11, NewEmisData!$D:$D, X$2)) -> 0.12537128 | Y11: =$I11*IF($G11="Pickup", SUMIFS(NewEmisData!I:I, NewEmisData!$A:$A, "Pickup", NewEmisData!$B:$B, $A11, NewEmisData!$C:$C, $H11, NewEmisData!$D:$D, Y$2), SUMIFS(NewEmisData!I:I, NewEmisData!$A:$A, "LDV", NewEmisData!$B:$B, $A11, NewEmisData!$C:$C, $H11, NewEmisData!$D:$D, Y$2)) -> 0.076671767 | Z11: =$I11*IF($G11="Pickup", SUMIFS(NewEmisData!J:J, NewEmisData!$A:$A, "Pickup", NewEmisData!$B:$B, $A11, NewEmisData!$C:$C, $H11, NewEmisData!$D:$D, Z$2), SUMIFS(NewEmisData!J:J, NewEmisData!$A:$A, "LDV", NewEmisData!$B:$B, $A11, NewEmisData!$C:$C, $H11, NewEmisData!$D:$D, Z$2)) -> 0.057019027 | AA11: =$I11*IF($G11="Pickup", SUMIFS(NewEmisData!K:K, NewEmisData!$A:$A, "Pickup", NewEmisData!$B:$B, $A11, NewEmisData!$C:$C, $H11, NewEmisData!$D:$D, AA$2), SUMIFS(NewEmisData!K:K, NewEmisData!$A:$A, "LDV", NewEmisData!$B:$B, $A11, NewEmisData!$C:$C, $H11, NewEmisData!$D:$D, AA$2)) -> 0.048823282 | AB11: =$I11*IF($G11="Pickup", SUMIFS(NewEmisData!L:L, NewEmisData!$A:$A, "Pickup", NewEmisData!$B:$B, $A11, NewEmisData!$C:$C, $H11, NewEmisData!$D:$D, AB$2), SUMIFS(NewEmisData!L:L, NewEmisData!$A:$A, "LDV", NewEmisData!$B:$B, $A11, NewEmisData!$C:$C, $H11, NewEmisData!$D:$D, AB$2)) -> 0.046542407 | AC11: =$I11*IF($G11="Pickup", SUMIFS(NewEmisData!M:M, NewEmisData!$A:$A, "Pickup", NewEmisData!$B:$B, $A11, NewEmisData!$C:$C, $H11, NewEmisData!$D:$D, AC$2), SUMIFS(NewEmisData!M:M, NewEmisData!$A:$A, "LDV", NewEmisData!$B:$B, $A11, NewEmisData!$C:$C, $H11, NewEmisData!$D:$D, AC$2)) -> 0.045415311 | AD11: 0.055587066 | AE11: =$I11*IF($G11="Pickup", SUMIFS(NewEmisData!E:E, NewEmisData!$A:$A, "Pickup", NewEmisData!$B:$B, $A11, NewEmisData!$C:$C, $H11, NewEmisData!$D:$D, AE$2), SUMIFS(NewEmisData!E:E, NewEmisData!$A:$A, "LDV", NewEmisData!$B:$B, $A11, NewEmisData!$C:$C, $H11, NewEmisData!$D:$D, AE$2)) -> 0.0075764719 | AF11: =$I11*IF($G11="Pickup", SUMIFS(NewEmisData!F:F, NewEmisData!$A:$A, "Pickup", NewEmisData!$B:$B, $A11, NewEmisData!$C:$C, $H11, NewEmisData!$D:$D, AF$2), SUMIFS(NewEmisData!F:F, NewEmisData!$A:$A, "LDV", NewEmisData!$B:$B, $A11, NewEmisData!$C:$C, $H11, NewEmisData!$D:$D, AF$2)) -> 0.00734724 | AG11: =$I11*IF($G11="Pickup", SUMIFS(NewEmisData!G:G, NewEmisData!$A:$A, "Pickup", NewEmisData!$B:$B, $A11, NewEmisData!$C:$C, $H11, NewEmisData!$D:$D, AG$2), SUMIFS(NewEmisData!G:G, NewEmisData!$A:$A, "LDV", NewEmisData!$B:$B, $A11, NewEmisData!$C:$C, $H11, NewEmisData!$D:$D, AG$2)) -> 0.0055842494 | AH11: =$I11*IF($G11="Pickup", SUMIFS(NewEmisData!H:H, NewEmisData!$A:$A, "Pickup", NewEmisData!$B:$B, $A11, NewEmisData!$C:$C, $H11, NewEmisData!$D:$D, AH$2), SUMIFS(NewEmisData!H:H, NewEmisData!$A:$A, "LDV", NewEmisData!$B:$B, $A11, NewEmisData!$C:$C, $H11, NewEmisData!$D:$D, AH$2)) -> 0.0047496587 | AI11: =$I11*IF($G11="Pickup", SUMIFS(NewEmisData!I:I, NewEmisData!$A:$A, "Pickup", NewEmisData!$B:$B, $A11, NewEmisData!$C:$C, $H11, NewEmisData!$D:$D, AI$2), SUMIFS(NewEmisData!I:I, NewEmisData!$A:$A, "LDV", NewEmisData!$B:$B, $A11, NewEmisData!$C:$C, $H11, NewEmisData!$D:$D, AI$2)) -> 0.0041095519 | AJ11: =$I11*IF($G11="Pickup", SUMIFS(NewEmisData!J:J, NewEmisData!$A:$A, "Pickup", NewEmisData!$B:$B, $A11, NewEmisData!$C:$C, $H11, NewEmisData!$D:$D, AJ$2), SUMIFS(NewEmisData!J:J, NewEmisData!$A:$A, "LDV", NewEmisData!$B:$B, $A11, NewEmisData!$C:$C, $H11, NewEmisData!$D:$D, AJ$2)) -> 0.0037489265 | AK11: =$I11*IF($G11="Pickup", SUMIFS(NewEmisData!K:K, NewEmisData!$A:$A, "Pickup", NewEmisData!$B:$B, $A11, NewEmisData!$C:$C, $H11, NewEmisData!$D:$D, AK$2), SUMIFS(NewEmisData!K:K, NewEmisData!$A:$A, "LDV", NewEmisData!$B:$B, $A11, NewEmisData!$C:$C, $H11, NewEmisData!$D:$D, AK$2)) -> 0.003588196 | AL11: =$I11*IF($G11="Pickup", SUMIFS(NewEmisData!L:L, NewEmisData!$A:$A, "Pickup", NewEmisData!$B:$B, $A11, NewEmisData!$C:$C, $H11, NewEmisData!$D:$D, AL$2), SUMIFS(NewEmisData!L:L, NewEmisData!$A:$A, "LDV", NewEmisData!$B:$B, $A11, NewEmisData!$C:$C, $H11, NewEmisData!$D:$D, AL$2)) -> 0.0035311006 | AM11: =$I11*IF($G11="Pickup", SUMIFS(NewEmisData!M:M, NewEmisData!$A:$A, "Pickup", NewEmisData!$B:$B, $A11, NewEmisData!$C:$C, $H11, NewEmisData!$D:$D, AM$2), SUMIFS(NewEmisData!M:M, NewEmisData!$A:$A, "LDV", NewEmisData!$B:$B, $A11, NewEmisData!$C:$C, $H11, NewEmisData!$D:$D, AM$2)) -> 0.003510031 | AN11: 0.0013041984 | AO11: =$I11*IF($G11="Pickup", SUMIFS(NewEmisData!E:E, NewEmisData!$A:$A, "Pickup", NewEmisData!$B:$B, $A11, NewEmisData!$C:$C, $H11, NewEmisData!$D:$D, AO$2), SUMIFS(NewEmisData!E:E, NewEmisData!$A:$A, "LDV", NewEmisData!$B:$B, $A11, NewEmisData!$C:$C, $H11, NewEmisData!$D:$D, AO$2)) -> 0.067831755 | AP11: =$I11*IF($G11="Pickup", SUMIFS(NewEmisData!F:F, NewEmisData!$A:$A, "Pickup", NewEmisData!$B:$B, $A11, NewEmisData!$C:$C, $H11, NewEmisData!$D:$D, AP$2), SUMIFS(NewEmisData!F:F, NewEmisData!$A:$A, "LDV", NewEmisData!$B:$B, $A11, NewEmisData!$C:$C, $H11, NewEmisData!$D:$D, AP$2)) -> 0.063250667 | AQ11: =$I11*IF($G11="Pickup", SUMIFS(NewEmisData!G:G, NewEmisData!$A:$A, "Pickup", NewEmisData!$B:$B, $A11, NewEmisData!$C:$C, $H11, NewEmisData!$D:$D, AQ$2), SUMIFS(NewEmisData!G:G, NewEmisData!$A:$A, "LDV", NewEmisData!$B:$B, $A11, NewEmisData!$C:$C, $H11, NewEmisData!$D:$D, AQ$2)) -> 0.062628417 | AR11: =$I11*IF($G11="Pickup", SUMIFS(NewEmisData!H:H, NewEmisData!$A:$A, "Pickup", NewEmisData!$B:$B, $A11, NewEmisData!$C:$C, $H11, NewEmisData!$D:$D, AR$2), SUMIFS(NewEmisData!H:H, NewEmisData!$A:$A, "LDV", NewEmisData!$B:$B, $A11, NewEmisData!$C:$C, $H11, NewEmisData!$D:$D, AR$2)) -> 0.061216981 | AS11: =$I11*IF($G11="Pickup", SUMIFS(NewEmisData!I:I, NewEmisData!$A:$A, "Pickup", NewEmisData!$B:$B, $A11, NewEmisData!$C:$C, $H11, NewEmisData!$D:$D, AS$2), SUMIFS(NewEmisData!I:I, NewEmisData!$A:$A, "LDV", NewEmisData!$B:$B, $A11, NewEmisData!$C:$C, $H11, NewEmisData!$D:$D, AS$2)) -> 0.059842025 | AT11: =$I11*IF($G11="Pickup", SUMIFS(NewEmisData!J:J, NewEmisData!$A:$A, "Pickup", NewEmisData!$B:$B, $A11, NewEmisData!$C:$C, $H11, NewEmisData!$D:$D, AT$2), SUMIFS(NewEmisData!J:J, NewEmisData!$A:$A, "LDV", NewEmisData!$B:$B, $A11, NewEmisData!$C:$C, $H11, NewEmisData!$D:$D, AT$2)) -> 0.058761886 | AU11: =$I11*IF($G11="Pickup", SUMIFS(NewEmisData!K:K, NewEmisData!$A:$A, "Pickup", NewEmisData!$B:$B, $A11, NewEmisData!$C:$C, $H11, NewEmisData!$D:$D, AU$2), SUMIFS(NewEmisData!K:K, NewEmisData!$A:$A, "LDV", NewEmisData!$B:$B, $A11, NewEmisData!$C:$C, $H11, NewEmisData!$D:$D, AU$2)) -> 0.058072078 | AV11: =$I11*IF($G11="Pickup", SUMIFS(NewEmisData!L:L, NewEmisData!$A:$A, "Pickup", NewEmisData!$B:$B, $A11, NewEmisData!$C:$C, $H11, NewEmisData!$D:$D, AV$2), SUMIFS(NewEmisData!L:L, NewEmisData!$A:$A, "LDV", NewEmisData!$B:$B, $A11, NewEmisData!$C:$C, $H11, NewEmisData!$D:$D, AV$2)) -> 0.057726484 | AW11: =$I11*IF($G11="Pickup", SUMIFS(NewEmisData!M:M, NewEmisData!$A:$A, "Pickup", NewEmisData!$B:$B, $A11, NewEmisData!$C:$C, $H11, NewEmisData!$D:$D, AW$2), SUMIFS(NewEmisData!M:M, NewEmisData!$A:$A, "LDV", NewEmisData!$B:$B, $A11, NewEmisData!$C:$C, $H11, NewEmisData!$D:$D, AW$2)) -> 0.057530227 | AX11: 0.032948539 | AY11: =$I11*IF($G11="Pickup", SUMIFS(NewEmisData!E:E, NewEmisData!$A:$A, "Pickup", NewEmisData!$B:$B, $A11, NewEmisData!$C:$C, $H11, NewEmisData!$D:$D, AY$2), SUMIFS(NewEmisData!E:E, NewEmisData!$A:$A, "LDV", NewEmisData!$B:$B, $A11, NewEmisData!$C:$C, $H11, NewEmisData!$D:$D, AY$2)) -> 0.018324823 | AZ11: =$I11*IF($G11="Pickup", SUMIFS(NewEmisData!F:F, NewEmisData!$A:$A, "Pickup", NewEmisData!$B:$B, $A11, NewEmisData!$C:$C, $H11, NewEmisData!$D:$D, AZ$2), SUMIFS(NewEmisData!F:F, NewEmisData!$A:$A, "LDV", NewEmisData!$B:$B, $A11, NewEmisData!$C:$C, $H11, NewEmisData!$D:$D, AZ$2)) -> 0.014272294 | BA11: =$I11*IF($G11="Pickup", SUMIFS(NewEmisData!G:G, NewEmisData!$A:$A, "Pickup", NewEmisData!$B:$B, $A11, NewEmisData!$C:$C, $H11, NewEmisData!$D:$D, BA$2), SUMIFS(NewEmisData!G:G, NewEmisData!$A:$A, "LDV", NewEmisData!$B:$B, $A11, NewEmisData!$C:$C, $H11, NewEmisData!$D:$D, BA$2)) -> 0.013165752 | BB11: =$I11*IF($G11="Pickup", SUMIFS(NewEmisData!H:H, NewEmisData!$A:$A, "Pickup", NewEmisData!$B:$B, $A11, NewEmisData!$C:$C, $H11, NewEmisData!$D:$D, BB$2), SUMIFS(NewEmisData!H:H, NewEmisData!$A:$A, "LDV", NewEmisData!$B:$B, $A11, NewEmisData!$C:$C, $H11, NewEmisData!$D:$D, BB$2)) -> 0.011917195 | BC11: =$I11*IF($G11="Pickup", SUMIFS(NewEmisData!I:I, NewEmisData!$A:$A, "Pickup", NewEmisData!$B:$B, $A11, NewEmisData!$C:$C, $H11, NewEmisData!$D:$D, BC$2), SUMIFS(NewEmisData!I:I, NewEmisData!$A:$A, "LDV", NewEmisData!$B:$B, $A11, NewEmisData!$C:$C, $H11, NewEmisData!$D:$D, BC$2)) -> 0.010700862 | BD11: =$I11*IF($G11="Pickup", SUMIFS(NewEmisData!J:J, NewEmisData!$A:$A, "Pickup", NewEmisData!$B:$B, $A11, NewEmisData!$C:$C, $H11, NewEmisData!$D:$D, BD$2), SUMIFS(NewEmisData!J:J, NewEmisData!$A:$A, "LDV", NewEmisData!$B:$B, $A11, NewEmisData!$C:$C, $H11, NewEmisData!$D:$D, BD$2)) -> 0.0097453522 | BE11: =$I11*IF($G11="Pickup", SUMIFS(NewEmisData!K:K, NewEmisData!$A:$A, "Pickup", NewEmisData!$B:$B, $A11, NewEmisData!$C:$C, $H11, NewEmisData!$D:$D, BE$2), SUMIFS(NewEmisData!K:K, NewEmisData!$A:$A, "LDV", NewEmisData!$B:$B, $A11, NewEmisData!$C:$C, $H11, NewEmisData!$D:$D, BE$2)) -> 0.0091351471 | BF11: =$I11*IF($G11="Pickup", SUMIFS(NewEmisData!L:L, NewEmisData!$A:$A, "Pickup", NewEmisData!$B:$B, $A11, NewEmisData!$C:$C, $H11, NewEmisData!$D:$D, BF$2), SUMIFS(NewEmisData!L:L, NewEmisData!$A:$A, "LDV", NewEmisData!$B:$B, $A11, NewEmisData!$C:$C, $H11, NewEmisData!$D:$D, BF$2)) -> 0.0088293874 | BG11: =$I11*IF($G11="Pickup", SUMIFS(NewEmisData!M:M, NewEmisData!$A:$A, "Pickup", NewEmisData!$B:$B, $A11, NewEmisData!$C:$C, $H11, NewEmisData!$D:$D, BG$2), SUMIFS(NewEmisData!M:M, NewEmisData!$A:$A, "LDV", NewEmisData!$B:$B, $A11, NewEmisData!$C:$C, $H11, NewEmisData!$D:$D, BG$2)) -> 0.0086558174 | BH11: 0.0066026126 | BI11: =$I11*IF($G11="Pickup", SUMIFS(NewEmisData!E:E, NewEmisData!$A:$A, "Pickup", NewEmisData!$B:$B, $A11, NewEmisData!$C:$C, $H11, NewEmisData!$D:$D, BI$2), SUMIFS(NewEmisData!E:E, NewEmisData!$A:$A, "LDV", NewEmisData!$B:$B, $A11, NewEmisData!$C:$C, $H11, NewEmisData!$D:$D, BI$2)) -> 5.6341972 | BJ11: =$I11*IF($G11="Pickup", SUMIFS(NewEmisData!F:F, NewEmisData!$A:$A, "Pickup", NewEmisData!$B:$B, $A11, NewEmisData!$C:$C, $H11, NewEmisData!$D:$D, BJ$2), SUMIFS(NewEmisData!F:F, NewEmisData!$A:$A, "LDV", NewEmisData!$B:$B, $A11, NewEmisData!$C:$C, $H11, NewEmisData!$D:$D, BJ$2)) -> 3.2912081 | BK11: =$I11*IF($G11="Pickup", SUMIFS(NewEmisData!G:G, NewEmisData!$A:$A, "Pickup", NewEmisData!$B:$B, $A11, NewEmisData!$C:$C, $H11, NewEmisData!$D:$D, BK$2), SUMIFS(NewEmisData!G:G, NewEmisData!$A:$A, "LDV", NewEmisData!$B:$B, $A11, NewEmisData!$C:$C, $H11, NewEmisData!$D:$D, BK$2)) -> 2.5038449 | BL11: =$I11*IF($G11="Pickup", SUMIFS(NewEmisData!H:H, NewEmisData!$A:$A, "Pickup", NewEmisData!$B:$B, $A11, NewEmisData!$C:$C, $H11, NewEmisData!$D:$D, BL$2), SUMIFS(NewEmisData!H:H, NewEmisData!$A:$A, "LDV", NewEmisData!$B:$B, $A11, NewEmisData!$C:$C, $H11, NewEmisData!$D:$D, BL$2)) -> 1.9586302 | BM11: =$I11*IF($G11="Pickup", SUMIFS(NewEmisData!I:I, NewEmisData!$A:$A, "Pickup", NewEmisData!$B:$B, $A11, NewEmisData!$C:$C, $H11, NewEmisData!$D:$D, BM$2), SUMIFS(NewEmisData!I:I, NewEmisData!$A:$A, "LDV", NewEmisData!$B:$B, $A11, NewEmisData!$C:$C, $H11, NewEmisData!$D:$D, BM$2)) -> 1.4188081 | BN11: =$I11*IF($G11="Pickup", SUMIFS(NewEmisData!J:J, NewEmisData!$A:$A, "Pickup", NewEmisData!$B:$B, $A11, NewEmisData!$C:$C, $H11, NewEmisData!$D:$D, BN$2), SUMIFS(NewEmisData!J:J, NewEmisData!$A:$A, "LDV", NewEmisData!$B:$B, $A11, NewEmisData!$C:$C, $H11, NewEmisData!$D:$D, BN$2)) -> 1.1229583 | BO11: =$I11*IF($G11="Pickup", SUMIFS(NewEmisData!K:K, NewEmisData!$A:$A, "Pickup", NewEmisData!$B:$B, $A11, NewEmisData!$C:$C, $H11, NewEmisData!$D:$D, BO$2), SUMIFS(NewEmisData!K:K, NewEmisData!$A:$A, "LDV", NewEmisData!$B:$B, $A11, NewEmisData!$C:$C, $H11, NewEmisData!$D:$D, BO$2)) -> 0.98917471 | BP11: =$I11*IF($G11="Pickup", SUMIFS(NewEmisData!L:L, NewEmisData!$A:$A, "Pickup", NewEmisData!$B:$B, $A11, NewEmisData!$C:$C, $H11, NewEmisData!$D:$D, BP$2), SUMIFS(NewEmisData!L:L, NewEmisData!$A:$A, "LDV", NewEmisData!$B:$B, $A11, NewEmisData!$C:$C, $H11, NewEmisData!$D:$D, BP$2)) -> 0.94587291 | BQ11: =$I11*IF($G11="Pickup", SUMIFS(NewEmisData!M:M, NewEmisData!$A:$A, "Pickup", NewEmisData!$B:$B, $A11, NewEmisData!$C:$C, $H11, NewEmisData!$D:$D, BQ$2), SUMIFS(NewEmisData!M:M, NewEmisData!$A:$A, "LDV", NewEmisData!$B:$B, $A11, NewEmisData!$C:$C, $H11, NewEmisData!$D:$D, BQ$2)) -> 0.91886505 | BR11: 1.5622002 | BS11: =$I11*IF($G11="Pickup", SUMIFS(NewEmisData!E:E, NewEmisData!$A:$A, "Pickup", NewEmisData!$B:$B, $A11, NewEmisData!$C:$C, $H11, NewEmisData!$D:$D, BS$2), SUMIFS(NewEmisData!E:E, NewEmisData!$A:$A, "LDV", NewEmisData!$B:$B, $A11, NewEmisData!$C:$C, $H11, NewEmisData!$D:$D, BS$2)) -> 0.64604041 | BT11: =$I11*IF($G11="Pickup", SUMIFS(NewEmisData!F:F, NewEmisData!$A:$A, "Pickup", NewEmisData!$B:$B, $A11, NewEmisData!$C:$C, $H11, NewEmisData!$D:$D, BT$2), SUMIFS(NewEmisData!F:F, NewEmisData!$A:$A, "LDV", NewEmisData!$B:$B, $A11, NewEmisData!$C:$C, $H11, NewEmisData!$D:$D, BT$2)) -> 0.33711602 | BU11: =$I11*IF($G11="Pickup", SUMIFS(NewEmisData!G:G, NewEmisData!$A:$A, "Pickup", NewEmisData!$B:$B, $A11, NewEmisData!$C:$C, $H11, NewEmisData!$D:$D, BU$2), SUMIFS(NewEmisData!G:G, NewEmisData!$A:$A, "LDV", NewEmisData!$B:$B, $A11, NewEmisData!$C:$C, $H11, NewEmisData!$D:$D, BU$2)) -> 0.24835485 | BV11: =$I11*IF($G11="Pickup", SUMIFS(NewEmisData!H:H, NewEmisData!$A:$A, "Pickup", NewEmisData!$B:$B, $A11, NewEmisData!$C:$C, $H11, NewEmisData!$D:$D, BV$2), SUMIFS(NewEmisData!H:H, NewEmisData!$A:$A, "LDV", NewEmisData!$B:$B, $A11, NewEmisData!$C:$C, $H11, NewEmisData!$D:$D, BV$2)) -> 0.20063726 | BW11: =$I11*IF($G11="Pickup", SUMIFS(NewEmisData!I:I, NewEmisData!$A:$A, "Pickup", NewEmisData!$B:$B, $A11, NewEmisData!$C:$C, $H11, NewEmisData!$D:$D, BW$2), SUMIFS(NewEmisData!I:I, NewEmisData!$A:$A, "LDV", NewEmisData!$B:$B, $A11, NewEmisData!$C:$C, $H11, NewEmisData!$D:$D, BW$2)) -> 0.14838807 | BX11: =$I11*IF($G11="Pickup", SUMIFS(NewEmisData!J:J, NewEmisData!$A:$A, "Pickup", NewEmisData!$B:$B, $A11, NewEmisData!$C:$C, $H11, NewEmisData!$D:$D, BX$2), SUMIFS(NewEmisData!J:J, NewEmisData!$A:$A, "LDV", NewEmisData!$B:$B, $A11, NewEmisData!$C:$C, $H11, NewEmisData!$D:$D, BX$2)) -> 0.12460658 | BY11: =$I11*IF($G11="Pickup", SUMIFS(NewEmisData!K:K, NewEmisData!$A:$A, "Pickup", NewEmisData!$B:$B, $A11, NewEmisData!$C:$C, $H11, NewEmisData!$D:$D, BY$2), SUMIFS(NewEmisData!K:K, NewEmisData!$A:$A, "LDV", NewEmisData!$B:$B, $A11, NewEmisData!$C:$C, $H11, NewEmisData!$D:$D, BY$2)) -> 0.1117761 | BZ11: =$I11*IF($G11="Pickup", SUMIFS(NewEmisData!L:L, NewEmisData!$A:$A, "Pickup", NewEmisData!$B:$B, $A11, NewEmisData!$C:$C, $H11, NewEmisData!$D:$D, BZ$2), SUMIFS(NewEmisData!L:L, NewEmisData!$A:$A, "LDV", NewEmisData!$B:$B, $A11, NewEmisData!$C:$C, $H11, NewEmisData!$D:$D, BZ$2)) -> 0.10678198 | CA11: =$I11*IF($G11="Pickup", SUMIFS(NewEmisData!M:M, NewEmisData!$A:$A, "Pickup", NewEmisData!$B:$B, $A11, NewEmisData!$C:$C, $H11, NewEmisData!$D:$D, CA$2), SUMIFS(NewEmisData!M:M, NewEmisData!$A:$A, "LDV", NewEmisData!$B:$B, $A11, NewEmisData!$C:$C, $H11, NewEmisData!$D:$D, CA$2)) -> 0.10278869 | CB11: 0.11295847 | CC11: =$I11*IF($G11="Pickup", SUMIFS(NewEmisData!E:E, NewEmisData!$A:$A, "Pickup", NewEmisData!$B:$B, $A11, NewEmisData!$C:$C, $H11, NewEmisData!$D:$D, CC$2), SUMIFS(NewEmisData!E:E, NewEmisData!$A:$A, "LDV", NewEmisData!$B:$B, $A11, NewEmisData!$C:$C, $H11, NewEmisData!$D:$D, CC$2)) -> 0.045186599 | CD11: =$I11*IF($G11="Pickup", SUMIFS(NewEmisData!F:F, NewEmisData!$A:$A, "Pickup", NewEmisData!$B:$B, $A11, NewEmisData!$C:$C, $H11, NewEmisData!$D:$D, CD$2), SUMIFS(NewEmisData!F:F, NewEmisData!$A:$A, "LDV", NewEmisData!$B:$B, $A11, NewEmisData!$C:$C, $H11, NewEmisData!$D:$D, CD$2)) -> 0.030321043 | CE11: =$I11*IF($G11="Pickup", SUMIFS(NewEmisData!G:G, NewEmisData!$A:$A, "Pickup", NewEmisData!$B:$B, $A11, NewEmisData!$C:$C, $H11, NewEmisData!$D:$D, CE$2), SUMIFS(NewEmisData!G:G, NewEmisData!$A:$A, "LDV", NewEmisData!$B:$B, $A11, NewEmisData!$C:$C, $H11, NewEmisData!$D:$D, CE$2)) -> 0.025916716 | CF11: =$I11*IF($G11="Pickup", SUMIFS(NewEmisData!H:H, NewEmisData!$A:$A, "Pickup", NewEmisData!$B:$B, $A11, NewEmisData!$C:$C, $H11, NewEmisData!$D:$D, CF$2), SUMIFS(NewEmisData!H:H, NewEmisData!$A:$A, "LDV", NewEmisData!$B:$B, $A11, NewEmisData!$C:$C, $H11, NewEmisData!$D:$D, CF$2)) -> 0.024735956 | CG11: =$I11*IF($G11="Pickup", SUMIFS(NewEmisData!I:I, NewEmisData!$A:$A, "Pickup", NewEmisData!$B:$B, $A11, NewEmisData!$C:$C, $H11, NewEmisData!$D:$D, CG$2), SUMIFS(NewEmisData!I:I, NewEmisData!$A:$A, "LDV", NewEmisData!$B:$B, $A11, NewEmisData!$C:$C, $H11, NewEmisData!$D:$D, CG$2)) -> 0.023950742 | CH11: =$I11*IF($G11="Pickup", SUMIFS(NewEmisData!J:J, NewEmisData!$A:$A, "Pickup", NewEmisData!$B:$B, $A11, NewEmisData!$C:$C, $H11, NewEmisData!$D:$D, CH$2), SUMIFS(NewEmisData!J:J, NewEmisData!$A:$A, "LDV", NewEmisData!$B:$B, $A11, NewEmisData!$C:$C, $H11, NewEmisData!$D:$D, CH$2)) -> 0.02333433 | CI11: =$I11*IF($G11="Pickup", SUMIFS(NewEmisData!K:K, NewEmisData!$A:$A, "Pickup", NewEmisData!$B:$B, $A11, NewEmisData!$C:$C, $H11, NewEmisData!$D:$D, CI$2), SUMIFS(NewEmisData!K:K, NewEmisData!$A:$A, "LDV", NewEmisData!$B:$B, $A11, NewEmisData!$C:$C, $H11, NewEmisData!$D:$D, CI$2)) -> 0.023332378 | CJ11: =$I11*IF($G11="Pickup", SUMIFS(NewEmisData!L:L, NewEmisData!$A:$A, "Pickup", NewEmisData!$B:$B, $A11, NewEmisData!$C:$C, $H11, NewEmisData!$D:$D, CJ$2), SUMIFS(NewEmisData!L:L, NewEmisData!$A:$A, "LDV", NewEmisData!$B:$B, $A11, NewEmisData!$C:$C, $H11, NewEmisData!$D:$D, CJ$2)) -> 0.023331869 | CK11: =$I11*IF($G11="Pickup", SUMIFS(NewEmisData!M:M, NewEmisData!$A:$A, "Pickup", NewEmisData!$B:$B, $A11, NewEmisData!$C:$C, $H11, NewEmisData!$D:$D, CK$2), SUMIFS(NewEmisData!M:M, NewEmisData!$A:$A, "LDV", NewEmisData!$B:$B, $A11, NewEmisData!$C:$C, $H11, NewEmisData!$D:$D, CK$2)) -> 0.023331334 | CL11: 0.020846549 | CM11: =$I11*IF($G11="Pickup", SUMIFS(NewEmisData!E:E, NewEmisData!$A:$A, "Pickup", NewEmisData!$B:$B, $A11, NewEmisData!$C:$C, $H11, NewEmisData!$D:$D, CM$2), SUMIFS(NewEmisData!E:E, NewEmisData!$A:$A, "LDV", NewEmisData!$B:$B, $A11, NewEmisData!$C:$C, $H11, NewEmisData!$D:$D, CM$2)) -> 0.018999641 | CN11: =$I11*IF($G11="Pickup", SUMIFS(NewEmisData!F:F, NewEmisData!$A:$A, "Pickup", NewEmisData!$B:$B, $A11, NewEmisData!$C:$C, $H11, NewEmisData!$D:$D, CN$2), SUMIFS(NewEmisData!F:F, NewEmisData!$A:$A, "LDV", NewEmisData!$B:$B, $A11, NewEmisData!$C:$C, $H11, NewEmisData!$D:$D, CN$2)) -> 0.011293404 | CO11: =$I11*IF($G11="Pickup", SUMIFS(NewEmisData!G:G, NewEmisData!$A:$A, "Pickup", NewEmisData!$B:$B, $A11, NewEmisData!$C:$C, $H11, NewEmisData!$D:$D, CO$2), SUMIFS(NewEmisData!G:G, NewEmisData!$A:$A, "LDV", NewEmisData!$B:$B, $A11, NewEmisData!$C:$C, $H11, NewEmisData!$D:$D, CO$2)) -> 0.0089155865 | CP11: =$I11*IF($G11="Pickup", SUMIFS(NewEmisData!H:H, NewEmisData!$A:$A, "Pickup", NewEmisData!$B:$B, $A11, NewEmisData!$C:$C, $H11, NewEmisData!$D:$D, CP$2), SUMIFS(NewEmisData!H:H, NewEmisData!$A:$A, "LDV", NewEmisData!$B:$B, $A11, NewEmisData!$C:$C, $H11, NewEmisData!$D:$D, CP$2)) -> 0.0073372922 | CQ11: =$I11*IF($G11="Pickup", SUMIFS(NewEmisData!I:I, NewEmisData!$A:$A, "Pickup", NewEmisData!$B:$B, $A11, NewEmisData!$C:$C, $H11, NewEmisData!$D:$D, CQ$2), SUMIFS(NewEmisData!I:I, NewEmisData!$A:$A, "LDV", NewEmisData!$B:$B, $A11, NewEmisData!$C:$C, $H11, NewEmisData!$D:$D, CQ$2)) -> 0.0065724995 | CR11: =$I11*IF($G11="Pickup", SUMIFS(NewEmisData!J:J, NewEmisData!$A:$A, "Pickup", NewEmisData!$B:$B, $A11, NewEmisData!$C:$C, $H11, NewEmisData!$D:$D, CR$2), SUMIFS(NewEmisData!J:J, NewEmisData!$A:$A, "LDV", NewEmisData!$B:$B, $A11, NewEmisData!$C:$C, $H11, NewEmisData!$D:$D, CR$2)) -> 0.0062407198 | CS11: =$I11*IF($G11="Pickup", SUMIFS(NewEmisData!K:K, NewEmisData!$A:$A, "Pickup", NewEmisData!$B:$B, $A11, NewEmisData!$C:$C, $H11, NewEmisData!$D:$D, CS$2), SUMIFS(NewEmisData!K:K, NewEmisData!$A:$A, "LDV", NewEmisData!$B:$B, $A11, NewEmisData!$C:$C, $H11, NewEmisData!$D:$D, CS$2)) -> 0.0062045762 | CT11: =$I11*IF($G11="Pickup", SUMIFS(NewEmisData!L:L, NewEmisData!$A:$A, "Pickup", NewEmisData!$B:$B, $A11, NewEmisData!$C:$C, $H11, NewEmisData!$D:$D, CT$2), SUMIFS(NewEmisData!L:L, NewEmisData!$A:$A, "LDV", NewEmisData!$B:$B, $A11, NewEmisData!$C:$C, $H11, NewEmisData!$D:$D, CT$2)) -> 0.0061456645 | CU11: =$I11*IF($G11="Pickup", SUMIFS(NewEmisData!M:M, NewEmisData!$A:$A, "Pickup", NewEmisData!$B:$B, $A11, NewEmisData!$C:$C, $H11, NewEmisData!$D:$D, CU$2), SUMIFS(NewEmisData!M:M, NewEmisData!$A:$A, "LDV", NewEmisData!$B:$B, $A11, NewEmisData!$C:$C, $H11, NewEmisData!$D:$D, CU$2)) -> 0.0061452936 | CV11: 0.0052030688 | CW11: 0.0030448047 | CX11: 0.0018865909 | CY11: 0.0015570268 | CZ11: 0.0012432183 | DA11: 0.00092522519 | DB11: 0.00072309457 | DC11: 0.00068940707 | DD11: 0.00068441484 | DE11: 0.00068634617 | DF11: 0.00068634617 | DG11: =$I11*IF($G11="Pickup", SUMIFS(NewEmisData!E:E, NewEmisData!$A:$A, "Pickup", NewEmisData!$B:$B, $A11, NewEmisData!$C:$C, $H11, NewEmisData!$D:$D, DG$2), SUMIFS(NewEmisData!E:E, NewEmisData!$A:$A, "LDV", NewEmisData!$B:$B, $A11, NewEmisData!$C:$C, $H11, NewEmisData!$D:$D, DG$2)) -> 0 | DH11: =$I11*IF($G11="Pickup", SUMIFS(NewEmisData!F:F, NewEmisData!$A:$A, "Pickup", NewEmisData!$B:$B, $A11, NewEmisData!$C:$C, $H11, NewEmisData!$D:$D, DH$2), SUMIFS(NewEmisData!F:F, NewEmisData!$A:$A, "LDV", NewEmisData!$B:$B, $A11, NewEmisData!$C:$C, $H11, NewEmisData!$D:$D, DH$2)) -> 0 | DI11: =$I11*IF($G11="Pickup", SUMIFS(NewEmisData!G:G, NewEmisData!$A:$A, "Pickup", NewEmisData!$B:$B, $A11, NewEmisData!$C:$C, $H11, NewEmisData!$D:$D, DI$2), SUMIFS(NewEmisData!G:G, NewEmisData!$A:$A, "LDV", NewEmisData!$B:$B, $A11, NewEmisData!$C:$C, $H11, NewEmisData!$D:$D, DI$2)) -> 0 | DJ11: =$I11*IF($G11="Pickup", SUMIFS(NewEmisData!H:H, NewEmisData!$A:$A, "Pickup", NewEmisData!$B:$B, $A11, NewEmisData!$C:$C, $H11, NewEmisData!$D:$D, DJ$2), SUMIFS(NewEmisData!H:H, NewEmisData!$A:$A, "LDV", NewEmisData!$B:$B, $A11, NewEmisData!$C:$C, $H11, NewEmisData!$D:$D, DJ$2)) -> 0 | DK11: =$I11*IF($G11="Pickup", SUMIFS(NewEmisData!I:I, NewEmisData!$A:$A, "Pickup", NewEmisData!$B:$B, $A11, NewEmisData!$C:$C, $H11, NewEmisData!$D:$D, DK$2), SUMIFS(NewEmisData!I:I, NewEmisData!$A:$A, "LDV", NewEmisData!$B:$B, $A11, NewEmisData!$C:$C, $H11, NewEmisData!$D:$D, DK$2)) -> 0 | DL11: =$I11*IF($G11="Pickup", SUMIFS(NewEmisData!J:J, NewEmisData!$A:$A, "Pickup", NewEmisData!$B:$B, $A11, NewEmisData!$C:$C, $H11, NewEmisData!$D:$D, DL$2), SUMIFS(NewEmisData!J:J, NewEmisData!$A:$A, "LDV", NewEmisData!$B:$B, $A11, NewEmisData!$C:$C, $H11, NewEmisData!$D:$D, DL$2)) -> 0 | DM11: =$I11*IF($G11="Pickup", SUMIFS(NewEmisData!K:K, NewEmisData!$A:$A, "Pickup", NewEmisData!$B:$B, $A11, NewEmisData!$C:$C, $H11, NewEmisData!$D:$D, DM$2), SUMIFS(NewEmisData!K:K, NewEmisData!$A:$A, "LDV", NewEmisData!$B:$B, $A11, NewEmisData!$C:$C, $H11, NewEmisData!$D:$D, DM$2)) -> 0 | DN11: =$I11*IF($G11="Pickup", SUMIFS(NewEmisData!L:L, NewEmisData!$A:$A, "Pickup", NewEmisData!$B:$B, $A11, NewEmisData!$C:$C, $H11, NewEmisData!$D:$D, DN$2), SUMIFS(NewEmisData!L:L, NewEmisData!$A:$A, "LDV", NewEmisData!$B:$B, $A11, NewEmisData!$C:$C, $H11, NewEmisData!$D:$D, DN$2)) -> 0 | DO11: =$I11*IF($G11="Pickup", SUMIFS(NewEmisData!M:M, NewEmisData!$A:$A, "Pickup", NewEmisData!$B:$B, $A11, NewEmisData!$C:$C, $H11, NewEmisData!$D:$D, DO$2), SUMIFS(NewEmisData!M:M, NewEmisData!$A:$A, "LDV", NewEmisData!$B:$B, $A11, NewEmisData!$C:$C, $H11, NewEmisData!$D:$D, DO$2)) -> 0 | DP11: 0.0013868758 | DQ11: =$I11*IF($G11="Pickup", SUMIFS(NewEmisData!E:E, NewEmisData!$A:$A, "Pickup", NewEmisData!$B:$B, $A11, NewEmisData!$C:$C, $H11, NewEmisData!$D:$D, DQ$2), SUMIFS(NewEmisData!E:E, NewEmisData!$A:$A, "LDV", NewEmisData!$B:$B, $A11, NewEmisData!$C:$C, $H11, NewEmisData!$D:$D, DQ$2)) -> 0.012810027 | DR11: =$I11*IF($G11="Pickup", SUMIFS(NewEmisData!F:F, NewEmisData!$A:$A, "Pickup", NewEmisData!$B:$B, $A11, NewEmisData!$C:$C, $H11, NewEmisData!$D:$D, DR$2), SUMIFS(NewEmisData!F:F, NewEmisData!$A:$A, "LDV", NewEmisData!$B:$B, $A11, NewEmisData!$C:$C, $H11, NewEmisData!$D:$D, DR$2)) -> 0.0069424261 | DS11: =$I11*IF($G11="Pickup", SUMIFS(NewEmisData!G:G, NewEmisData!$A:$A, "Pickup", NewEmisData!$B:$B, $A11, NewEmisData!$C:$C, $H11, NewEmisData!$D:$D, DS$2), SUMIFS(NewEmisData!G:G, NewEmisData!$A:$A, "LDV", NewEmisData!$B:$B, $A11, NewEmisData!$C:$C, $H11, NewEmisData!$D:$D, DS$2)) -> 0.0055718063 | DT11: =$I11*IF($G11="Pickup", SUMIFS(NewEmisData!H:H, NewEmisData!$A:$A, "Pickup", NewEmisData!$B:$B, $A11, NewEmisData!$C:$C, $H11, NewEmisData!$D:$D, DT$2), SUMIFS(NewEmisData!H:H, NewEmisData!$A:$A, "LDV", NewEmisData!$B:$B, $A11, NewEmisData!$C:$C, $H11, NewEmisData!$D:$D, DT$2)) -> 0.0042603418 | DU11: =$I11*IF($G11="Pickup", SUMIFS(NewEmisData!I:I, NewEmisData!$A:$A, "Pickup", NewEmisData!$B:$B, $A11, NewEmisData!$C:$C, $H11, NewEmisData!$D:$D, DU$2), SUMIFS(NewEmisData!I:I, NewEmisData!$A:$A, "LDV", NewEmisData!$B:$B, $A11, NewEmisData!$C:$C, $H11, NewEmisData!$D:$D, DU$2)) -> 0.003319595 | DV11: =$I11*IF($G11="Pickup", SUMIFS(NewEmisData!J:J, NewEmisData!$A:$A, "Pickup", NewEmisData!$B:$B, $A11, NewEmisData!$C:$C, $H11, NewEmisData!$D:$D, DV$2), SUMIFS(NewEmisData!J:J, NewEmisData!$A:$A, "LDV", NewEmisData!$B:$B, $A11, NewEmisData!$C:$C, $H11, NewEmisData!$D:$D, DV$2)) -> 0.0028901417 | DW11: =$I11*IF($G11="Pickup", SUMIFS(NewEmisData!K:K, NewEmisData!$A:$A, "Pickup", NewEmisData!$B:$B, $A11, NewEmisData!$C:$C, $H11, NewEmisData!$D:$D, DW$2), SUMIFS(NewEmisData!K:K, NewEmisData!$A:$A, "LDV", NewEmisData!$B:$B, $A11, NewEmisData!$C:$C, $H11, NewEmisData!$D:$D, DW$2)) -> 0.0026480526 | DX11: =$I11*IF($G11="Pickup", SUMIFS(NewEmisData!L:L, NewEmisData!$A:$A, "Pickup", NewEmisData!$B:$B, $A11, NewEmisData!$C:$C, $H11, NewEmisData!$D:$D, DX$2), SUMIFS(NewEmisData!L:L, NewEmisData!$A:$A, "LDV", NewEmisData!$B:$B, $A11, NewEmisData!$C:$C, $H11, NewEmisData!$D:$D, DX$2)) -> 0.0025707167 | DY11: =$I11*IF($G11="Pickup", SUMIFS(NewEmisData!M:M, NewEmisData!$A:$A, "Pickup", NewEmisData!$B:$B, $A11, NewEmisData!$C:$C, $H11, NewEmisData!$D:$D, DY$2), SUMIFS(NewEmisData!M:M, NewEmisData!$A:$A, "LDV", NewEmisData!$B:$B, $A11, NewEmisData!$C:$C, $H11, NewEmisData!$D:$D, DY$2)) -> 0.0025319063 | DZ11: 0.0043350573 | EA11: =K11 -> 437.85747 | EB11: =L11 -> 424.60988 | EC11: =M11 -> 389.26792 | ED11: =N11 -> 331.09003 | EE11: =O11 -> 286.4693 | EF11: =P11 -> 261.3308 | EG11: =Q11 -> 250.12665 | EH11: =R11 -> 246.14649 | ... FX11: =BH11 -> 0.0066026126
A12: =_xlfn.CONCAT(IF(LEFT(TRIM(A11),1)="*", "*R", "R"), 1+RIGHT(TRIM(A11),1)) -> R4 | B12: =B11 -> TLMCGSLC11 | C12: =C11 -> TL.GSL.MC.CONV.2011 | D12: =D11 -> bn-vmt, bn-vmt/a | E12: =E11 -> TLGSL | F12: =F11 -> TL | G12: Mini car | H12: GSL | I12: 1 | J12: =CONCATENATE(G12,"-",H12) -> Mini car-GSL | K12: =$I12*IF($G12="Pickup", SUMIFS(NewEmisData!E:E, NewEmisData!$A:$A, "Pickup", NewEmisData!$B:$B, $A12, NewEmisData!$C:$C, $H12, NewEmisData!$D:$D, K$2), SUMIFS(NewEmisData!E:E, NewEmisData!$A:$A, "LDV", NewEmisData!$B:$B, $A12, NewEmisData!$C:$C, $H12, NewEmisData!$D:$D, K$2)) -> 605.35194 | L12: =$I12*IF($G12="Pickup", SUMIFS(NewEmisData!F:F, NewEmisData!$A:$A, "Pickup", NewEmisData!$B:$B, $A12, NewEmisData!$C:$C, $H12, NewEmisData!$D:$D, L$2), SUMIFS(NewEmisData!F:F, NewEmisData!$A:$A, "LDV", NewEmisData!$B:$B, $A12, NewEmisData!$C:$C, $H12, NewEmisData!$D:$D, L$2)) -> 575.43678 | M12: =$I12*IF($G12="Pickup", SUMIFS(NewEmisData!G:G, NewEmisData!$A:$A, "Pickup", NewEmisData!$B:$B, $A12, NewEmisData!$C:$C, $H12, NewEmisData!$D:$D, M$2), SUMIFS(NewEmisData!G:G, NewEmisData!$A:$A, "LDV", NewEmisData!$B:$B, $A12, NewEmisData!$C:$C, $H12, NewEmisData!$D:$D, M$2)) -> 447.50307 | N12: =$I12*IF($G12="Pickup", SUMIFS(NewEmisData!H:H, NewEmisData!$A:$A, "Pickup", NewEmisData!$B:$B, $A12, NewEmisData!$C:$C, $H12, NewEmisData!$D:$D, N$2), SUMIFS(NewEmisData!H:H, NewEmisData!$A:$A, "LDV", NewEmisData!$B:$B, $A12, NewEmisData!$C:$C, $H12, NewEmisData!$D:$D, N$2)) -> 380.32749 | O12: =$I12*IF($G12="Pickup", SUMIFS(NewEmisData!I:I, NewEmisData!$A:$A, "Pickup", NewEmisData!$B:$B, $A12, NewEmisData!$C:$C, $H12, NewEmisData!$D:$D, O$2), SUMIFS(NewEmisData!I:I, NewEmisData!$A:$A, "LDV", NewEmisData!$B:$B, $A12, NewEmisData!$C:$C, $H12, NewEmisData!$D:$D, O$2)) -> 328.85087 | P12: =$I12*IF($G12="Pickup", SUMIFS(NewEmisData!J:J, NewEmisData!$A:$A, "Pickup", NewEmisData!$B:$B, $A12, NewEmisData!$C:$C, $H12, NewEmisData!$D:$D, P$2), SUMIFS(NewEmisData!J:J, NewEmisData!$A:$A, "LDV", NewEmisData!$B:$B, $A12, NewEmisData!$C:$C, $H12, NewEmisData!$D:$D, P$2)) -> 299.87343 | Q12: =$I12*IF($G12="Pickup", SUMIFS(NewEmisData!K:K, NewEmisData!$A:$A, "Pickup", NewEmisData!$B:$B, $A12, NewEmisData!$C:$C, $H12, NewEmisData!$D:$D, Q$2), SUMIFS(NewEmisData!K:K, NewEmisData!$A:$A, "LDV", NewEmisData!$B:$B, $A12, NewEmisData!$C:$C, $H12, NewEmisData!$D:$D, Q$2)) -> 286.96646 | R12: =$I12*IF($G12="Pickup", SUMIFS(NewEmisData!L:L, NewEmisData!$A:$A, "Pickup", NewEmisData!$B:$B, $A12, NewEmisData!$C:$C, $H12, NewEmisData!$D:$D, R$2), SUMIFS(NewEmisData!L:L, NewEmisData!$A:$A, "LDV", NewEmisData!$B:$B, $A12, NewEmisData!$C:$C, $H12, NewEmisData!$D:$D, R$2)) -> 282.38592 | S12: =$I12*IF($G12="Pickup", SUMIFS(NewEmisData!M:M, NewEmisData!$A:$A, "Pickup", NewEmisData!$B:$B, $A12, NewEmisData!$C:$C, $H12, NewEmisData!$D:$D, S$2), SUMIFS(NewEmisData!M:M, NewEmisData!$A:$A, "LDV", NewEmisData!$B:$B, $A12, NewEmisData!$C:$C, $H12, NewEmisData!$D:$D, S$2)) -> 280.69816 | T12: 0.20692409 | U12: =$I12*IF($G12="Pickup", SUMIFS(NewEmisData!E:E, NewEmisData!$A:$A, "Pickup", NewEmisData!$B:$B, $A12, NewEmisData!$C:$C, $H12, NewEmisData!$D:$D, U$2), SUMIFS(NewEmisData!E:E, NewEmisData!$A:$A, "LDV", NewEmisData!$B:$B, $A12, NewEmisData!$C:$C, $H12, NewEmisData!$D:$D, U$2)) -> 0.73999494 | V12: =$I12*IF($G12="Pickup", SUMIFS(NewEmisData!F:F, NewEmisData!$A:$A, "Pickup", NewEmisData!$B:$B, $A12, NewEmisData!$C:$C, $H12, NewEmisData!$D:$D, V$2), SUMIFS(NewEmisData!F:F, NewEmisData!$A:$A, "LDV", NewEmisData!$B:$B, $A12, NewEmisData!$C:$C, $H12, NewEmisData!$D:$D, V$2)) -> 0.3533524 | W12: =$I12*IF($G12="Pickup", SUMIFS(NewEmisData!G:G, NewEmisData!$A:$A, "Pickup", NewEmisData!$B:$B, $A12, NewEmisData!$C:$C, $H12, NewEmisData!$D:$D, W$2), SUMIFS(NewEmisData!G:G, NewEmisData!$A:$A, "LDV", NewEmisData!$B:$B, $A12, NewEmisData!$C:$C, $H12, NewEmisData!$D:$D, W$2)) -> 0.18897755 | X12: =$I12*IF($G12="Pickup", SUMIFS(NewEmisData!H:H, NewEmisData!$A:$A, "Pickup", NewEmisData!$B:$B, $A12, NewEmisData!$C:$C, $H12, NewEmisData!$D:$D, X$2), SUMIFS(NewEmisData!H:H, NewEmisData!$A:$A, "LDV", NewEmisData!$B:$B, $A12, NewEmisData!$C:$C, $H12, NewEmisData!$D:$D, X$2)) -> 0.12218818 | Y12: =$I12*IF($G12="Pickup", SUMIFS(NewEmisData!I:I, NewEmisData!$A:$A, "Pickup", NewEmisData!$B:$B, $A12, NewEmisData!$C:$C, $H12, NewEmisData!$D:$D, Y$2), SUMIFS(NewEmisData!I:I, NewEmisData!$A:$A, "LDV", NewEmisData!$B:$B, $A12, NewEmisData!$C:$C, $H12, NewEmisData!$D:$D, Y$2)) -> 0.073060825 | Z12: =$I12*IF($G12="Pickup", SUMIFS(NewEmisData!J:J, NewEmisData!$A:$A, "Pickup", NewEmisData!$B:$B, $A12, NewEmisData!$C:$C, $H12, NewEmisData!$D:$D, Z$2), SUMIFS(NewEmisData!J:J, NewEmisData!$A:$A, "LDV", NewEmisData!$B:$B, $A12, NewEmisData!$C:$C, $H12, NewEmisData!$D:$D, Z$2)) -> 0.053764321 | AA12: =$I12*IF($G12="Pickup", SUMIFS(NewEmisData!K:K, NewEmisData!$A:$A, "Pickup", NewEmisData!$B:$B, $A12, NewEmisData!$C:$C, $H12, NewEmisData!$D:$D, AA$2), SUMIFS(NewEmisData!K:K, NewEmisData!$A:$A, "LDV", NewEmisData!$B:$B, $A12, NewEmisData!$C:$C, $H12, NewEmisData!$D:$D, AA$2)) -> 0.045765874 | AB12: =$I12*IF($G12="Pickup", SUMIFS(NewEmisData!L:L, NewEmisData!$A:$A, "Pickup", NewEmisData!$B:$B, $A12, NewEmisData!$C:$C, $H12, NewEmisData!$D:$D, AB$2), SUMIFS(NewEmisData!L:L, NewEmisData!$A:$A, "LDV", NewEmisData!$B:$B, $A12, NewEmisData!$C:$C, $H12, NewEmisData!$D:$D, AB$2)) -> 0.043548109 | AC12: =$I12*IF($G12="Pickup", SUMIFS(NewEmisData!M:M, NewEmisData!$A:$A, "Pickup", NewEmisData!$B:$B, $A12, NewEmisData!$C:$C, $H12, NewEmisData!$D:$D, AC$2), SUMIFS(NewEmisData!M:M, NewEmisData!$A:$A, "LDV", NewEmisData!$B:$B, $A12, NewEmisData!$C:$C, $H12, NewEmisData!$D:$D, AC$2)) -> 0.042460978 | AD12: 0.055587066 | AE12: =$I12*IF($G12="Pickup", SUMIFS(NewEmisData!E:E, NewEmisData!$A:$A, "Pickup", NewEmisData!$B:$B, $A12, NewEmisData!$C:$C, $H12, NewEmisData!$D:$D, AE$2), SUMIFS(NewEmisData!E:E, NewEmisData!$A:$A, "LDV", NewEmisData!$B:$B, $A12, NewEmisData!$C:$C, $H12, NewEmisData!$D:$D, AE$2)) -> 0.010474716 | AF12: =$I12*IF($G12="Pickup", SUMIFS(NewEmisData!F:F, NewEmisData!$A:$A, "Pickup", NewEmisData!$B:$B, $A12, NewEmisData!$C:$C, $H12, NewEmisData!$D:$D, AF$2), SUMIFS(NewEmisData!F:F, NewEmisData!$A:$A, "LDV", NewEmisData!$B:$B, $A12, NewEmisData!$C:$C, $H12, NewEmisData!$D:$D, AF$2)) -> 0.0099570765 | AG12: =$I12*IF($G12="Pickup", SUMIFS(NewEmisData!G:G, NewEmisData!$A:$A, "Pickup", NewEmisData!$B:$B, $A12, NewEmisData!$C:$C, $H12, NewEmisData!$D:$D, AG$2), SUMIFS(NewEmisData!G:G, NewEmisData!$A:$A, "LDV", NewEmisData!$B:$B, $A12, NewEmisData!$C:$C, $H12, NewEmisData!$D:$D, AG$2)) -> 0.0064196649 | AH12: =$I12*IF($G12="Pickup", SUMIFS(NewEmisData!H:H, NewEmisData!$A:$A, "Pickup", NewEmisData!$B:$B, $A12, NewEmisData!$C:$C, $H12, NewEmisData!$D:$D, AH$2), SUMIFS(NewEmisData!H:H, NewEmisData!$A:$A, "LDV", NewEmisData!$B:$B, $A12, NewEmisData!$C:$C, $H12, NewEmisData!$D:$D, AH$2)) -> 0.0054559953 | AI12: =$I12*IF($G12="Pickup", SUMIFS(NewEmisData!I:I, NewEmisData!$A:$A, "Pickup", NewEmisData!$B:$B, $A12, NewEmisData!$C:$C, $H12, NewEmisData!$D:$D, AI$2), SUMIFS(NewEmisData!I:I, NewEmisData!$A:$A, "LDV", NewEmisData!$B:$B, $A12, NewEmisData!$C:$C, $H12, NewEmisData!$D:$D, AI$2)) -> 0.0047175365 | AJ12: =$I12*IF($G12="Pickup", SUMIFS(NewEmisData!J:J, NewEmisData!$A:$A, "Pickup", NewEmisData!$B:$B, $A12, NewEmisData!$C:$C, $H12, NewEmisData!$D:$D, AJ$2), SUMIFS(NewEmisData!J:J, NewEmisData!$A:$A, "LDV", NewEmisData!$B:$B, $A12, NewEmisData!$C:$C, $H12, NewEmisData!$D:$D, AJ$2)) -> 0.0043018392 | AK12: =$I12*IF($G12="Pickup", SUMIFS(NewEmisData!K:K, NewEmisData!$A:$A, "Pickup", NewEmisData!$B:$B, $A12, NewEmisData!$C:$C, $H12, NewEmisData!$D:$D, AK$2), SUMIFS(NewEmisData!K:K, NewEmisData!$A:$A, "LDV", NewEmisData!$B:$B, $A12, NewEmisData!$C:$C, $H12, NewEmisData!$D:$D, AK$2)) -> 0.0041166816 | AL12: =$I12*IF($G12="Pickup", SUMIFS(NewEmisData!L:L, NewEmisData!$A:$A, "Pickup", NewEmisData!$B:$B, $A12, NewEmisData!$C:$C, $H12, NewEmisData!$D:$D, AL$2), SUMIFS(NewEmisData!L:L, NewEmisData!$A:$A, "LDV", NewEmisData!$B:$B, $A12, NewEmisData!$C:$C, $H12, NewEmisData!$D:$D, AL$2)) -> 0.0040509726 | AM12: =$I12*IF($G12="Pickup", SUMIFS(NewEmisData!M:M, NewEmisData!$A:$A, "Pickup", NewEmisData!$B:$B, $A12, NewEmisData!$C:$C, $H12, NewEmisData!$D:$D, AM$2), SUMIFS(NewEmisData!M:M, NewEmisData!$A:$A, "LDV", NewEmisData!$B:$B, $A12, NewEmisData!$C:$C, $H12, NewEmisData!$D:$D, AM$2)) -> 0.0040267597 | AN12: 0.0013041984 | AO12: =$I12*IF($G12="Pickup", SUMIFS(NewEmisData!E:E, NewEmisData!$A:$A, "Pickup", NewEmisData!$B:$B, $A12, NewEmisData!$C:$C, $H12, NewEmisData!$D:$D, AO$2), SUMIFS(NewEmisData!E:E, NewEmisData!$A:$A, "LDV", NewEmisData!$B:$B, $A12, NewEmisData!$C:$C, $H12, NewEmisData!$D:$D, AO$2)) -> 0.11252984 | AP12: =$I12*IF($G12="Pickup", SUMIFS(NewEmisData!F:F, NewEmisData!$A:$A, "Pickup", NewEmisData!$B:$B, $A12, NewEmisData!$C:$C, $H12, NewEmisData!$D:$D, AP$2), SUMIFS(NewEmisData!F:F, NewEmisData!$A:$A, "LDV", NewEmisData!$B:$B, $A12, NewEmisData!$C:$C, $H12, NewEmisData!$D:$D, AP$2)) -> 0.10376481 | AQ12: =$I12*IF($G12="Pickup", SUMIFS(NewEmisData!G:G, NewEmisData!$A:$A, "Pickup", NewEmisData!$B:$B, $A12, NewEmisData!$C:$C, $H12, NewEmisData!$D:$D, AQ$2), SUMIFS(NewEmisData!G:G, NewEmisData!$A:$A, "LDV", NewEmisData!$B:$B, $A12, NewEmisData!$C:$C, $H12, NewEmisData!$D:$D, AQ$2)) -> 0.08190401 | AR12: =$I12*IF($G12="Pickup", SUMIFS(NewEmisData!H:H, NewEmisData!$A:$A, "Pickup", NewEmisData!$B:$B, $A12, NewEmisData!$C:$C, $H12, NewEmisData!$D:$D, AR$2), SUMIFS(NewEmisData!H:H, NewEmisData!$A:$A, "LDV", NewEmisData!$B:$B, $A12, NewEmisData!$C:$C, $H12, NewEmisData!$D:$D, AR$2)) -> 0.080372811 | AS12: =$I12*IF($G12="Pickup", SUMIFS(NewEmisData!I:I, NewEmisData!$A:$A, "Pickup", NewEmisData!$B:$B, $A12, NewEmisData!$C:$C, $H12, NewEmisData!$D:$D, AS$2), SUMIFS(NewEmisData!I:I, NewEmisData!$A:$A, "LDV", NewEmisData!$B:$B, $A12, NewEmisData!$C:$C, $H12, NewEmisData!$D:$D, AS$2)) -> 0.078826851 | AT12: =$I12*IF($G12="Pickup", SUMIFS(NewEmisData!J:J, NewEmisData!$A:$A, "Pickup", NewEmisData!$B:$B, $A12, NewEmisData!$C:$C, $H12, NewEmisData!$D:$D, AT$2), SUMIFS(NewEmisData!J:J, NewEmisData!$A:$A, "LDV", NewEmisData!$B:$B, $A12, NewEmisData!$C:$C, $H12, NewEmisData!$D:$D, AT$2)) -> 0.077629472 | AU12: =$I12*IF($G12="Pickup", SUMIFS(NewEmisData!K:K, NewEmisData!$A:$A, "Pickup", NewEmisData!$B:$B, $A12, NewEmisData!$C:$C, $H12, NewEmisData!$D:$D, AU$2), SUMIFS(NewEmisData!K:K, NewEmisData!$A:$A, "LDV", NewEmisData!$B:$B, $A12, NewEmisData!$C:$C, $H12, NewEmisData!$D:$D, AU$2)) -> 0.076869255 | AV12: =$I12*IF($G12="Pickup", SUMIFS(NewEmisData!L:L, NewEmisData!$A:$A, "Pickup", NewEmisData!$B:$B, $A12, NewEmisData!$C:$C, $H12, NewEmisData!$D:$D, AV$2), SUMIFS(NewEmisData!L:L, NewEmisData!$A:$A, "LDV", NewEmisData!$B:$B, $A12, NewEmisData!$C:$C, $H12, NewEmisData!$D:$D, AV$2)) -> 0.076489801 | AW12: =$I12*IF($G12="Pickup", SUMIFS(NewEmisData!M:M, NewEmisData!$A:$A, "Pickup", NewEmisData!$B:$B, $A12, NewEmisData!$C:$C, $H12, NewEmisData!$D:$D, AW$2), SUMIFS(NewEmisData!M:M, NewEmisData!$A:$A, "LDV", NewEmisData!$B:$B, $A12, NewEmisData!$C:$C, $H12, NewEmisData!$D:$D, AW$2)) -> 0.07627589 | AX12: 0.032948539 | AY12: =$I12*IF($G12="Pickup", SUMIFS(NewEmisData!E:E, NewEmisData!$A:$A, "Pickup", NewEmisData!$B:$B, $A12, NewEmisData!$C:$C, $H12, NewEmisData!$D:$D, AY$2), SUMIFS(NewEmisData!E:E, NewEmisData!$A:$A, "LDV", NewEmisData!$B:$B, $A12, NewEmisData!$C:$C, $H12, NewEmisData!$D:$D, AY$2)) -> 0.029314011 | AZ12: =$I12*IF($G12="Pickup", SUMIFS(NewEmisData!F:F, NewEmisData!$A:$A, "Pickup", NewEmisData!$B:$B, $A12, NewEmisData!$C:$C, $H12, NewEmisData!$D:$D, AZ$2), SUMIFS(NewEmisData!F:F, NewEmisData!$A:$A, "LDV", NewEmisData!$B:$B, $A12, NewEmisData!$C:$C, $H12, NewEmisData!$D:$D, AZ$2)) -> 0.021560332 | BA12: =$I12*IF($G12="Pickup", SUMIFS(NewEmisData!G:G, NewEmisData!$A:$A, "Pickup", NewEmisData!$B:$B, $A12, NewEmisData!$C:$C, $H12, NewEmisData!$D:$D, BA$2), SUMIFS(NewEmisData!G:G, NewEmisData!$A:$A, "LDV", NewEmisData!$B:$B, $A12, NewEmisData!$C:$C, $H12, NewEmisData!$D:$D, BA$2)) -> 0.016135954 | BB12: =$I12*IF($G12="Pickup", SUMIFS(NewEmisData!H:H, NewEmisData!$A:$A, "Pickup", NewEmisData!$B:$B, $A12, NewEmisData!$C:$C, $H12, NewEmisData!$D:$D, BB$2), SUMIFS(NewEmisData!H:H, NewEmisData!$A:$A, "LDV", NewEmisData!$B:$B, $A12, NewEmisData!$C:$C, $H12, NewEmisData!$D:$D, BB$2)) -> 0.014781439 | BC12: =$I12*IF($G12="Pickup", SUMIFS(NewEmisData!I:I, NewEmisData!$A:$A, "Pickup", NewEmisData!$B:$B, $A12, NewEmisData!$C:$C, $H12, NewEmisData!$D:$D, BC$2), SUMIFS(NewEmisData!I:I, NewEmisData!$A:$A, "LDV", NewEmisData!$B:$B, $A12, NewEmisData!$C:$C, $H12, NewEmisData!$D:$D, BC$2)) -> 0.013413838 | BD12: =$I12*IF($G12="Pickup", SUMIFS(NewEmisData!J:J, NewEmisData!$A:$A, "Pickup", NewEmisData!$B:$B, $A12, NewEmisData!$C:$C, $H12, NewEmisData!$D:$D, BD$2), SUMIFS(NewEmisData!J:J, NewEmisData!$A:$A, "LDV", NewEmisData!$B:$B, $A12, NewEmisData!$C:$C, $H12, NewEmisData!$D:$D, BD$2)) -> 0.012354573 | BE12: =$I12*IF($G12="Pickup", SUMIFS(NewEmisData!K:K, NewEmisData!$A:$A, "Pickup", NewEmisData!$B:$B, $A12, NewEmisData!$C:$C, $H12, NewEmisData!$D:$D, BE$2), SUMIFS(NewEmisData!K:K, NewEmisData!$A:$A, "LDV", NewEmisData!$B:$B, $A12, NewEmisData!$C:$C, $H12, NewEmisData!$D:$D, BE$2)) -> 0.011682065 | BF12: =$I12*IF($G12="Pickup", SUMIFS(NewEmisData!L:L, NewEmisData!$A:$A, "Pickup", NewEmisData!$B:$B, $A12, NewEmisData!$C:$C, $H12, NewEmisData!$D:$D, BF$2), SUMIFS(NewEmisData!L:L, NewEmisData!$A:$A, "LDV", NewEmisData!$B:$B, $A12, NewEmisData!$C:$C, $H12, NewEmisData!$D:$D, BF$2)) -> 0.011346346 | BG12: =$I12*IF($G12="Pickup", SUMIFS(NewEmisData!M:M, NewEmisData!$A:$A, "Pickup", NewEmisData!$B:$B, $A12, NewEmisData!$C:$C, $H12, NewEmisData!$D:$D, BG$2), SUMIFS(NewEmisData!M:M, NewEmisData!$A:$A, "LDV", NewEmisData!$B:$B, $A12, NewEmisData!$C:$C, $H12, NewEmisData!$D:$D, BG$2)) -> 0.011157149 | BH12: 0.0066026126 | BI12: =$I12*IF($G12="Pickup", SUMIFS(NewEmisData!E:E, NewEmisData!$A:$A, "Pickup", NewEmisData!$B:$B, $A12, NewEmisData!$C:$C, $H12, NewEmisData!$D:$D, BI$2), SUMIFS(NewEmisData!E:E, NewEmisData!$A:$A, "LDV", NewEmisData!$B:$B, $A12, NewEmisData!$C:$C, $H12, NewEmisData!$D:$D, BI$2)) -> 7.7707306 | BJ12: =$I12*IF($G12="Pickup", SUMIFS(NewEmisData!F:F, NewEmisData!$A:$A, "Pickup", NewEmisData!$B:$B, $A12, NewEmisData!$C:$C, $H12, NewEmisData!$D:$D, BJ$2), SUMIFS(NewEmisData!F:F, NewEmisData!$A:$A, "LDV", NewEmisData!$B:$B, $A12, NewEmisData!$C:$C, $H12, NewEmisData!$D:$D, BJ$2)) -> 4.4247869 | BK12: =$I12*IF($G12="Pickup", SUMIFS(NewEmisData!G:G, NewEmisData!$A:$A, "Pickup", NewEmisData!$B:$B, $A12, NewEmisData!$C:$C, $H12, NewEmisData!$D:$D, BK$2), SUMIFS(NewEmisData!G:G, NewEmisData!$A:$A, "LDV", NewEmisData!$B:$B, $A12, NewEmisData!$C:$C, $H12, NewEmisData!$D:$D, BK$2)) -> 2.6540718 | BL12: =$I12*IF($G12="Pickup", SUMIFS(NewEmisData!H:H, NewEmisData!$A:$A, "Pickup", NewEmisData!$B:$B, $A12, NewEmisData!$C:$C, $H12, NewEmisData!$D:$D, BL$2), SUMIFS(NewEmisData!H:H, NewEmisData!$A:$A, "LDV", NewEmisData!$B:$B, $A12, NewEmisData!$C:$C, $H12, NewEmisData!$D:$D, BL$2)) -> 2.0604732 | BM12: =$I12*IF($G12="Pickup", SUMIFS(NewEmisData!I:I, NewEmisData!$A:$A, "Pickup", NewEmisData!$B:$B, $A12, NewEmisData!$C:$C, $H12, NewEmisData!$D:$D, BM$2), SUMIFS(NewEmisData!I:I, NewEmisData!$A:$A, "LDV", NewEmisData!$B:$B, $A12, NewEmisData!$C:$C, $H12, NewEmisData!$D:$D, BM$2)) -> 1.4768703 | BN12: =$I12*IF($G12="Pickup", SUMIFS(NewEmisData!J:J, NewEmisData!$A:$A, "Pickup", NewEmisData!$B:$B, $A12, NewEmisData!$C:$C, $H12, NewEmisData!$D:$D, BN$2), SUMIFS(NewEmisData!J:J, NewEmisData!$A:$A, "LDV", NewEmisData!$B:$B, $A12, NewEmisData!$C:$C, $H12, NewEmisData!$D:$D, BN$2)) -> 1.1597746 | BO12: =$I12*IF($G12="Pickup", SUMIFS(NewEmisData!K:K, NewEmisData!$A:$A, "Pickup", NewEmisData!$B:$B, $A12, NewEmisData!$C:$C, $H12, NewEmisData!$D:$D, BO$2), SUMIFS(NewEmisData!K:K, NewEmisData!$A:$A, "LDV", NewEmisData!$B:$B, $A12, NewEmisData!$C:$C, $H12, NewEmisData!$D:$D, BO$2)) -> 1.0179564 | BP12: =$I12*IF($G12="Pickup", SUMIFS(NewEmisData!L:L, NewEmisData!$A:$A, "Pickup", NewEmisData!$B:$B, $A12, NewEmisData!$C:$C, $H12, NewEmisData!$D:$D, BP$2), SUMIFS(NewEmisData!L:L, NewEmisData!$A:$A, "LDV", NewEmisData!$B:$B, $A12, NewEmisData!$C:$C, $H12, NewEmisData!$D:$D, BP$2)) -> 0.97243112 | BQ12: =$I12*IF($G12="Pickup", SUMIFS(NewEmisData!M:M, NewEmisData!$A:$A, "Pickup", NewEmisData!$B:$B, $A12, NewEmisData!$C:$C, $H12, NewEmisData!$D:$D, BQ$2), SUMIFS(NewEmisData!M:M, NewEmisData!$A:$A, "LDV", NewEmisData!$B:$B, $A12, NewEmisData!$C:$C, $H12, NewEmisData!$D:$D, BQ$2)) -> 0.94396289 | BR12: 1.5622002 | BS12: =$I12*IF($G12="Pickup", SUMIFS(NewEmisData!E:E, NewEmisData!$A:$A, "Pickup", NewEmisData!$B:$B, $A12, NewEmisData!$C:$C, $H12, NewEmisData!$D:$D, BS$2), SUMIFS(NewEmisData!E:E, NewEmisData!$A:$A, "LDV", NewEmisData!$B:$B, $A12, NewEmisData!$C:$C, $H12, NewEmisData!$D:$D, BS$2)) -> 0.86893952 | BT12: =$I12*IF($G12="Pickup", SUMIFS(NewEmisData!F:F, NewEmisData!$A:$A, "Pickup", NewEmisData!$B:$B, $A12, NewEmisData!$C:$C, $H12, NewEmisData!$D:$D, BT$2), SUMIFS(NewEmisData!F:F, NewEmisData!$A:$A, "LDV", NewEmisData!$B:$B, $A12, NewEmisData!$C:$C, $H12, NewEmisData!$D:$D, BT$2)) -> 0.46984847 | BU12: =$I12*IF($G12="Pickup", SUMIFS(NewEmisData!G:G, NewEmisData!$A:$A, "Pickup", NewEmisData!$B:$B, $A12, NewEmisData!$C:$C, $H12, NewEmisData!$D:$D, BU$2), SUMIFS(NewEmisData!G:G, NewEmisData!$A:$A, "LDV", NewEmisData!$B:$B, $A12, NewEmisData!$C:$C, $H12, NewEmisData!$D:$D, BU$2)) -> 0.25380787 | BV12: =$I12*IF($G12="Pickup", SUMIFS(NewEmisData!H:H, NewEmisData!$A:$A, "Pickup", NewEmisData!$B:$B, $A12, NewEmisData!$C:$C, $H12, NewEmisData!$D:$D, BV$2), SUMIFS(NewEmisData!H:H, NewEmisData!$A:$A, "LDV", NewEmisData!$B:$B, $A12, NewEmisData!$C:$C, $H12, NewEmisData!$D:$D, BV$2)) -> 0.20500079 | BW12: =$I12*IF($G12="Pickup", SUMIFS(NewEmisData!I:I, NewEmisData!$A:$A, "Pickup", NewEmisData!$B:$B, $A12, NewEmisData!$C:$C, $H12, NewEmisData!$D:$D, BW$2), SUMIFS(NewEmisData!I:I, NewEmisData!$A:$A, "LDV", NewEmisData!$B:$B, $A12, NewEmisData!$C:$C, $H12, NewEmisData!$D:$D, BW$2)) -> 0.15182918 | BX12: =$I12*IF($G12="Pickup", SUMIFS(NewEmisData!J:J, NewEmisData!$A:$A, "Pickup", NewEmisData!$B:$B, $A12, NewEmisData!$C:$C, $H12, NewEmisData!$D:$D, BX$2), SUMIFS(NewEmisData!J:J, NewEmisData!$A:$A, "LDV", NewEmisData!$B:$B, $A12, NewEmisData!$C:$C, $H12, NewEmisData!$D:$D, BX$2)) -> 0.12865137 | BY12: =$I12*IF($G12="Pickup", SUMIFS(NewEmisData!K:K, NewEmisData!$A:$A, "Pickup", NewEmisData!$B:$B, $A12, NewEmisData!$C:$C, $H12, NewEmisData!$D:$D, BY$2), SUMIFS(NewEmisData!K:K, NewEmisData!$A:$A, "LDV", NewEmisData!$B:$B, $A12, NewEmisData!$C:$C, $H12, NewEmisData!$D:$D, BY$2)) -> 0.11591502 | BZ12: =$I12*IF($G12="Pickup", SUMIFS(NewEmisData!L:L, NewEmisData!$A:$A, "Pickup", NewEmisData!$B:$B, $A12, NewEmisData!$C:$C, $H12, NewEmisData!$D:$D, BZ$2), SUMIFS(NewEmisData!L:L, NewEmisData!$A:$A, "LDV", NewEmisData!$B:$B, $A12, NewEmisData!$C:$C, $H12, NewEmisData!$D:$D, BZ$2)) -> 0.11095133 | CA12: =$I12*IF($G12="Pickup", SUMIFS(NewEmisData!M:M, NewEmisData!$A:$A, "Pickup", NewEmisData!$B:$B, $A12, NewEmisData!$C:$C, $H12, NewEmisData!$D:$D, CA$2), SUMIFS(NewEmisData!M:M, NewEmisData!$A:$A, "LDV", NewEmisData!$B:$B, $A12, NewEmisData!$C:$C, $H12, NewEmisData!$D:$D, CA$2)) -> 0.10699337 | CB12: 0.11295847 | CC12: =$I12*IF($G12="Pickup", SUMIFS(NewEmisData!E:E, NewEmisData!$A:$A, "Pickup", NewEmisData!$B:$B, $A12, NewEmisData!$C:$C, $H12, NewEmisData!$D:$D, CC$2), SUMIFS(NewEmisData!E:E, NewEmisData!$A:$A, "LDV", NewEmisData!$B:$B, $A12, NewEmisData!$C:$C, $H12, NewEmisData!$D:$D, CC$2)) -> 0.051125584 | CD12: =$I12*IF($G12="Pickup", SUMIFS(NewEmisData!F:F, NewEmisData!$A:$A, "Pickup", NewEmisData!$B:$B, $A12, NewEmisData!$C:$C, $H12, NewEmisData!$D:$D, CD$2), SUMIFS(NewEmisData!F:F, NewEmisData!$A:$A, "LDV", NewEmisData!$B:$B, $A12, NewEmisData!$C:$C, $H12, NewEmisData!$D:$D, CD$2)) -> 0.037154394 | CE12: =$I12*IF($G12="Pickup", SUMIFS(NewEmisData!G:G, NewEmisData!$A:$A, "Pickup", NewEmisData!$B:$B, $A12, NewEmisData!$C:$C, $H12, NewEmisData!$D:$D, CE$2), SUMIFS(NewEmisData!G:G, NewEmisData!$A:$A, "LDV", NewEmisData!$B:$B, $A12, NewEmisData!$C:$C, $H12, NewEmisData!$D:$D, CE$2)) -> 0.028853651 | CF12: =$I12*IF($G12="Pickup", SUMIFS(NewEmisData!H:H, NewEmisData!$A:$A, "Pickup", NewEmisData!$B:$B, $A12, NewEmisData!$C:$C, $H12, NewEmisData!$D:$D, CF$2), SUMIFS(NewEmisData!H:H, NewEmisData!$A:$A, "LDV", NewEmisData!$B:$B, $A12, NewEmisData!$C:$C, $H12, NewEmisData!$D:$D, CF$2)) -> 0.027537521 | CG12: =$I12*IF($G12="Pickup", SUMIFS(NewEmisData!I:I, NewEmisData!$A:$A, "Pickup", NewEmisData!$B:$B, $A12, NewEmisData!$C:$C, $H12, NewEmisData!$D:$D, CG$2), SUMIFS(NewEmisData!I:I, NewEmisData!$A:$A, "LDV", NewEmisData!$B:$B, $A12, NewEmisData!$C:$C, $H12, NewEmisData!$D:$D, CG$2)) -> 0.026666634 | CH12: =$I12*IF($G12="Pickup", SUMIFS(NewEmisData!J:J, NewEmisData!$A:$A, "Pickup", NewEmisData!$B:$B, $A12, NewEmisData!$C:$C, $H12, NewEmisData!$D:$D, CH$2), SUMIFS(NewEmisData!J:J, NewEmisData!$A:$A, "LDV", NewEmisData!$B:$B, $A12, NewEmisData!$C:$C, $H12, NewEmisData!$D:$D, CH$2)) -> 0.025980349 | CI12: =$I12*IF($G12="Pickup", SUMIFS(NewEmisData!K:K, NewEmisData!$A:$A, "Pickup", NewEmisData!$B:$B, $A12, NewEmisData!$C:$C, $H12, NewEmisData!$D:$D, CI$2), SUMIFS(NewEmisData!K:K, NewEmisData!$A:$A, "LDV", NewEmisData!$B:$B, $A12, NewEmisData!$C:$C, $H12, NewEmisData!$D:$D, CI$2)) -> 0.025978185 | CJ12: =$I12*IF($G12="Pickup", SUMIFS(NewEmisData!L:L, NewEmisData!$A:$A, "Pickup", NewEmisData!$B:$B, $A12, NewEmisData!$C:$C, $H12, NewEmisData!$D:$D, CJ$2), SUMIFS(NewEmisData!L:L, NewEmisData!$A:$A, "LDV", NewEmisData!$B:$B, $A12, NewEmisData!$C:$C, $H12, NewEmisData!$D:$D, CJ$2)) -> 0.025977589 | CK12: =$I12*IF($G12="Pickup", SUMIFS(NewEmisData!M:M, NewEmisData!$A:$A, "Pickup", NewEmisData!$B:$B, $A12, NewEmisData!$C:$C, $H12, NewEmisData!$D:$D, CK$2), SUMIFS(NewEmisData!M:M, NewEmisData!$A:$A, "LDV", NewEmisData!$B:$B, $A12, NewEmisData!$C:$C, $H12, NewEmisData!$D:$D, CK$2)) -> 0.025976994 | CL12: 0.020846549 | CM12: =$I12*IF($G12="Pickup", SUMIFS(NewEmisData!E:E, NewEmisData!$A:$A, "Pickup", NewEmisData!$B:$B, $A12, NewEmisData!$C:$C, $H12, NewEmisData!$D:$D, CM$2), SUMIFS(NewEmisData!E:E, NewEmisData!$A:$A, "LDV", NewEmisData!$B:$B, $A12, NewEmisData!$C:$C, $H12, NewEmisData!$D:$D, CM$2)) -> 0.022752592 | CN12: =$I12*IF($G12="Pickup", SUMIFS(NewEmisData!F:F, NewEmisData!$A:$A, "Pickup", NewEmisData!$B:$B, $A12, NewEmisData!$C:$C, $H12, NewEmisData!$D:$D, CN$2), SUMIFS(NewEmisData!F:F, NewEmisData!$A:$A, "LDV", NewEmisData!$B:$B, $A12, NewEmisData!$C:$C, $H12, NewEmisData!$D:$D, CN$2)) -> 0.014156662 | CO12: =$I12*IF($G12="Pickup", SUMIFS(NewEmisData!G:G, NewEmisData!$A:$A, "Pickup", NewEmisData!$B:$B, $A12, NewEmisData!$C:$C, $H12, NewEmisData!$D:$D, CO$2), SUMIFS(NewEmisData!G:G, NewEmisData!$A:$A, "LDV", NewEmisData!$B:$B, $A12, NewEmisData!$C:$C, $H12, NewEmisData!$D:$D, CO$2)) -> 0.0092962854 | CP12: =$I12*IF($G12="Pickup", SUMIFS(NewEmisData!H:H, NewEmisData!$A:$A, "Pickup", NewEmisData!$B:$B, $A12, NewEmisData!$C:$C, $H12, NewEmisData!$D:$D, CP$2), SUMIFS(NewEmisData!H:H, NewEmisData!$A:$A, "LDV", NewEmisData!$B:$B, $A12, NewEmisData!$C:$C, $H12, NewEmisData!$D:$D, CP$2)) -> 0.0076962231 | CQ12: =$I12*IF($G12="Pickup", SUMIFS(NewEmisData!I:I, NewEmisData!$A:$A, "Pickup", NewEmisData!$B:$B, $A12, NewEmisData!$C:$C, $H12, NewEmisData!$D:$D, CQ$2), SUMIFS(NewEmisData!I:I, NewEmisData!$A:$A, "LDV", NewEmisData!$B:$B, $A12, NewEmisData!$C:$C, $H12, NewEmisData!$D:$D, CQ$2)) -> 0.0069434858 | CR12: =$I12*IF($G12="Pickup", SUMIFS(NewEmisData!J:J, NewEmisData!$A:$A, "Pickup", NewEmisData!$B:$B, $A12, NewEmisData!$C:$C, $H12, NewEmisData!$D:$D, CR$2), SUMIFS(NewEmisData!J:J, NewEmisData!$A:$A, "LDV", NewEmisData!$B:$B, $A12, NewEmisData!$C:$C, $H12, NewEmisData!$D:$D, CR$2)) -> 0.0066235502 | CS12: =$I12*IF($G12="Pickup", SUMIFS(NewEmisData!K:K, NewEmisData!$A:$A, "Pickup", NewEmisData!$B:$B, $A12, NewEmisData!$C:$C, $H12, NewEmisData!$D:$D, CS$2), SUMIFS(NewEmisData!K:K, NewEmisData!$A:$A, "LDV", NewEmisData!$B:$B, $A12, NewEmisData!$C:$C, $H12, NewEmisData!$D:$D, CS$2)) -> 0.0065909545 | CT12: =$I12*IF($G12="Pickup", SUMIFS(NewEmisData!L:L, NewEmisData!$A:$A, "Pickup", NewEmisData!$B:$B, $A12, NewEmisData!$C:$C, $H12, NewEmisData!$D:$D, CT$2), SUMIFS(NewEmisData!L:L, NewEmisData!$A:$A, "LDV", NewEmisData!$B:$B, $A12, NewEmisData!$C:$C, $H12, NewEmisData!$D:$D, CT$2)) -> 0.0065377802 | CU12: =$I12*IF($G12="Pickup", SUMIFS(NewEmisData!M:M, NewEmisData!$A:$A, "Pickup", NewEmisData!$B:$B, $A12, NewEmisData!$C:$C, $H12, NewEmisData!$D:$D, CU$2), SUMIFS(NewEmisData!M:M, NewEmisData!$A:$A, "LDV", NewEmisData!$B:$B, $A12, NewEmisData!$C:$C, $H12, NewEmisData!$D:$D, CU$2)) -> 0.0065374276 | CV12: 0.0052030688 | CW12: 0.0030448047 | CX12: 0.0018865909 | CY12: 0.0015570268 | CZ12: 0.0012432183 | DA12: 0.00092522519 | DB12: 0.00072309457 | DC12: 0.00068940707 | DD12: 0.00068441484 | DE12: 0.00068634617 | DF12: 0.00068634617 | DG12: =$I12*IF($G12="Pickup", SUMIFS(NewEmisData!E:E, NewEmisData!$A:$A, "Pickup", NewEmisData!$B:$B, $A12, NewEmisData!$C:$C, $H12, NewEmisData!$D:$D, DG$2), SUMIFS(NewEmisData!E:E, NewEmisData!$A:$A, "LDV", NewEmisData!$B:$B, $A12, NewEmisData!$C:$C, $H12, NewEmisData!$D:$D, DG$2)) -> 0 | DH12: =$I12*IF($G12="Pickup", SUMIFS(NewEmisData!F:F, NewEmisData!$A:$A, "Pickup", NewEmisData!$B:$B, $A12, NewEmisData!$C:$C, $H12, NewEmisData!$D:$D, DH$2), SUMIFS(NewEmisData!F:F, NewEmisData!$A:$A, "LDV", NewEmisData!$B:$B, $A12, NewEmisData!$C:$C, $H12, NewEmisData!$D:$D, DH$2)) -> 0 | DI12: =$I12*IF($G12="Pickup", SUMIFS(NewEmisData!G:G, NewEmisData!$A:$A, "Pickup", NewEmisData!$B:$B, $A12, NewEmisData!$C:$C, $H12, NewEmisData!$D:$D, DI$2), SUMIFS(NewEmisData!G:G, NewEmisData!$A:$A, "LDV", NewEmisData!$B:$B, $A12, NewEmisData!$C:$C, $H12, NewEmisData!$D:$D, DI$2)) -> 0 | DJ12: =$I12*IF($G12="Pickup", SUMIFS(NewEmisData!H:H, NewEmisData!$A:$A, "Pickup", NewEmisData!$B:$B, $A12, NewEmisData!$C:$C, $H12, NewEmisData!$D:$D, DJ$2), SUMIFS(NewEmisData!H:H, NewEmisData!$A:$A, "LDV", NewEmisData!$B:$B, $A12, NewEmisData!$C:$C, $H12, NewEmisData!$D:$D, DJ$2)) -> 0 | DK12: =$I12*IF($G12="Pickup", SUMIFS(NewEmisData!I:I, NewEmisData!$A:$A, "Pickup", NewEmisData!$B:$B, $A12, NewEmisData!$C:$C, $H12, NewEmisData!$D:$D, DK$2), SUMIFS(NewEmisData!I:I, NewEmisData!$A:$A, "LDV", NewEmisData!$B:$B, $A12, NewEmisData!$C:$C, $H12, NewEmisData!$D:$D, DK$2)) -> 0 | DL12: =$I12*IF($G12="Pickup", SUMIFS(NewEmisData!J:J, NewEmisData!$A:$A, "Pickup", NewEmisData!$B:$B, $A12, NewEmisData!$C:$C, $H12, NewEmisData!$D:$D, DL$2), SUMIFS(NewEmisData!J:J, NewEmisData!$A:$A, "LDV", NewEmisData!$B:$B, $A12, NewEmisData!$C:$C, $H12, NewEmisData!$D:$D, DL$2)) -> 0 | DM12: =$I12*IF($G12="Pickup", SUMIFS(NewEmisData!K:K, NewEmisData!$A:$A, "Pickup", NewEmisData!$B:$B, $A12, NewEmisData!$C:$C, $H12, NewEmisData!$D:$D, DM$2), SUMIFS(NewEmisData!K:K, NewEmisData!$A:$A, "LDV", NewEmisData!$B:$B, $A12, NewEmisData!$C:$C, $H12, NewEmisData!$D:$D, DM$2)) -> 0 | DN12: =$I12*IF($G12="Pickup", SUMIFS(NewEmisData!L:L, NewEmisData!$A:$A, "Pickup", NewEmisData!$B:$B, $A12, NewEmisData!$C:$C, $H12, NewEmisData!$D:$D, DN$2), SUMIFS(NewEmisData!L:L, NewEmisData!$A:$A, "LDV", NewEmisData!$B:$B, $A12, NewEmisData!$C:$C, $H12, NewEmisData!$D:$D, DN$2)) -> 0 | DO12: =$I12*IF($G12="Pickup", SUMIFS(NewEmisData!M:M, NewEmisData!$A:$A, "Pickup", NewEmisData!$B:$B, $A12, NewEmisData!$C:$C, $H12, NewEmisData!$D:$D, DO$2), SUMIFS(NewEmisData!M:M, NewEmisData!$A:$A, "LDV", NewEmisData!$B:$B, $A12, NewEmisData!$C:$C, $H12, NewEmisData!$D:$D, DO$2)) -> 0 | DP12: 0.0013868758 | DQ12: =$I12*IF($G12="Pickup", SUMIFS(NewEmisData!E:E, NewEmisData!$A:$A, "Pickup", NewEmisData!$B:$B, $A12, NewEmisData!$C:$C, $H12, NewEmisData!$D:$D, DQ$2), SUMIFS(NewEmisData!E:E, NewEmisData!$A:$A, "LDV", NewEmisData!$B:$B, $A12, NewEmisData!$C:$C, $H12, NewEmisData!$D:$D, DQ$2)) -> 0.017231431 | DR12: =$I12*IF($G12="Pickup", SUMIFS(NewEmisData!F:F, NewEmisData!$A:$A, "Pickup", NewEmisData!$B:$B, $A12, NewEmisData!$C:$C, $H12, NewEmisData!$D:$D, DR$2), SUMIFS(NewEmisData!F:F, NewEmisData!$A:$A, "LDV", NewEmisData!$B:$B, $A12, NewEmisData!$C:$C, $H12, NewEmisData!$D:$D, DR$2)) -> 0.0089963646 | DS12: =$I12*IF($G12="Pickup", SUMIFS(NewEmisData!G:G, NewEmisData!$A:$A, "Pickup", NewEmisData!$B:$B, $A12, NewEmisData!$C:$C, $H12, NewEmisData!$D:$D, DS$2), SUMIFS(NewEmisData!G:G, NewEmisData!$A:$A, "LDV", NewEmisData!$B:$B, $A12, NewEmisData!$C:$C, $H12, NewEmisData!$D:$D, DS$2)) -> 0.0056961523 | DT12: =$I12*IF($G12="Pickup", SUMIFS(NewEmisData!H:H, NewEmisData!$A:$A, "Pickup", NewEmisData!$B:$B, $A12, NewEmisData!$C:$C, $H12, NewEmisData!$D:$D, DT$2), SUMIFS(NewEmisData!H:H, NewEmisData!$A:$A, "LDV", NewEmisData!$B:$B, $A12, NewEmisData!$C:$C, $H12, NewEmisData!$D:$D, DT$2)) -> 0.0043151144 | DU12: =$I12*IF($G12="Pickup", SUMIFS(NewEmisData!I:I, NewEmisData!$A:$A, "Pickup", NewEmisData!$B:$B, $A12, NewEmisData!$C:$C, $H12, NewEmisData!$D:$D, DU$2), SUMIFS(NewEmisData!I:I, NewEmisData!$A:$A, "LDV", NewEmisData!$B:$B, $A12, NewEmisData!$C:$C, $H12, NewEmisData!$D:$D, DU$2)) -> 0.0033502898 | DV12: =$I12*IF($G12="Pickup", SUMIFS(NewEmisData!J:J, NewEmisData!$A:$A, "Pickup", NewEmisData!$B:$B, $A12, NewEmisData!$C:$C, $H12, NewEmisData!$D:$D, DV$2), SUMIFS(NewEmisData!J:J, NewEmisData!$A:$A, "LDV", NewEmisData!$B:$B, $A12, NewEmisData!$C:$C, $H12, NewEmisData!$D:$D, DV$2)) -> 0.0029288859 | DW12: =$I12*IF($G12="Pickup", SUMIFS(NewEmisData!K:K, NewEmisData!$A:$A, "Pickup", NewEmisData!$B:$B, $A12, NewEmisData!$C:$C, $H12, NewEmisData!$D:$D, DW$2), SUMIFS(NewEmisData!K:K, NewEmisData!$A:$A, "LDV", NewEmisData!$B:$B, $A12, NewEmisData!$C:$C, $H12, NewEmisData!$D:$D, DW$2)) -> 0.0026889749 | DX12: =$I12*IF($G12="Pickup", SUMIFS(NewEmisData!L:L, NewEmisData!$A:$A, "Pickup", NewEmisData!$B:$B, $A12, NewEmisData!$C:$C, $H12, NewEmisData!$D:$D, DX$2), SUMIFS(NewEmisData!L:L, NewEmisData!$A:$A, "LDV", NewEmisData!$B:$B, $A12, NewEmisData!$C:$C, $H12, NewEmisData!$D:$D, DX$2)) -> 0.0026131015 | DY12: =$I12*IF($G12="Pickup", SUMIFS(NewEmisData!M:M, NewEmisData!$A:$A, "Pickup", NewEmisData!$B:$B, $A12, NewEmisData!$C:$C, $H12, NewEmisData!$D:$D, DY$2), SUMIFS(NewEmisData!M:M, NewEmisData!$A:$A, "LDV", NewEmisData!$B:$B, $A12, NewEmisData!$C:$C, $H12, NewEmisData!$D:$D, DY$2)) -> 0.0025757099 | DZ12: 0.0043350573 | EA12: =K12 -> 605.35194 | EB12: =L12 -> 575.43678 | EC12: =M12 -> 447.50307 | ED12: =N12 -> 380.32749 | EE12: =O12 -> 328.85087 | EF12: =P12 -> 299.87343 | EG12: =Q12 -> 286.96646 | EH12: =R12 -> 282.38592 | ... FX12: =BH12 -> 0.0066026126
