Workbook
Name _1995_Implicit_GDP_Deflator: 'RTEKTY Conv'!#REF!
Name _2001_Implicit_GDP_Deflator: 'RTEKTY Conv'!#REF!
Name avg_water_heater_PJ: #REF!
Name avg_water_heater_PJ: #REF!
Name avg_water_heater_PJ: #REF!
Name btu_per_watthr: 'RTEKTY Conv'!#REF!
Name btu_per_watthr: '[1]Conversion Factors'!$B$5
Name days_per_year: 'RTEKTY Conv'!#REF!
Name days_per_year: '[1]Conversion Factors'!$B$3
Name dollar____per__m: 'RTEKTY Conv'!#REF!
Name dollar____per__m: '[1]Conversion Factors'!$B$7
Name hours_per_day: 'RTEKTY Conv'!#REF!
Name hours_per_day: '[1]Conversion Factors'!$B$2
Name j_per_btu: 'RTEKTY Conv'!#REF!
Name j_per_btu: '[1]Conversion Factors'!$B$4
Name j_per_pj: 'RTEKTY Conv'!#REF!
Name j_per_pj: '[1]Conversion Factors'!$B$6
Name kwhr_per_j: 'RTEKTY Conv'!#REF!
Name lumens_per_billion_lumens: '[1]Conversion Factors'!$B$9
Name unit_per_million_unit: 'RTEKTY Conv'!#REF!

Sheet ANSv6.1-Commodities
A1: ANSWER-Commodities
B7: CommName | C7: CommDesc | D7: CommUnit | E7: Set Memberships | F7: Comment

Sheet ANSv6.1-Technologies
A1: ANSWER-Technologies
B7: TechName | C7: TechDesc | D7: TACTUnit | E7: TCAPUnit | F7: Set Memberships | G7: Comment

Sheet Commodities
B1: Commodities | D1: _GLOBAL,R0,R1,R2,R3,R4,R5,R6
B6: ~FI_Comm
B7: Region | C7: Csets | D7: CommName | E7: CommDesc | F7: Unit | G7: LimType | H7: CTSLvl | I7: PeakTS | J7: Ctype

Sheet Technologies
C1: _GLOBAL,R0,R1,R2,R3,R4,R5,R6 | K1: Technologies
B6: ~FI_Process
B7: Sets | C7: TechName | D7: TechDesc | E7: Tact | F7: Tcap | G7: PrimaryCG | H7: Vintage | I7: Tslvl | K7: Region
B8: *Space Heating
B9: *Electric Radiant Heating
B10: DMD | C10: =TechData_DMD!A10 -> RSHERDBS10 | D10: =TechData_DMD!B10 -> Electric Radiant Base.RSH.ELC.10 | E10: PJ | F10: PJ/a | K10: =TechData_DMD!BF10 -> R2,R3,R4,R5,R6
B11: DMD | C11: =TechData_DMD!A11 -> RSHERUV115 | D11: =TechData_DMD!B11 -> Electric Resistance Unit Heater Ver1.RSH.ELC.15 | E11: PJ | F11: PJ/a | K11: =TechData_DMD!BF11 -> R2,R3,R4,R5,R6
B12: DMD | C12: =TechData_DMD!A12 -> RSHERUV120 | D12: =TechData_DMD!B12 -> Electric Resistance Unit Heater Ver1.RSH.ELC.20 | E12: PJ | F12: PJ/a | K12: =TechData_DMD!BF12 -> R2,R3,R4,R5,R6
B13: DMD | C13: =TechData_DMD!A13 -> RSHERUV122 | D13: =TechData_DMD!B13 -> Electric Resistance Unit Heater Ver1.RSH.ELC.22 | E13: PJ | F13: PJ/a | K13: =TechData_DMD!BF13 -> R2,R3,R4,R5,R6
B14: *Electric Furnaces
B15: DMD | C15: =TechData_DMD!A15 -> RSHEFRV115 | D15: =TechData_DMD!B15 -> Electric Furnace Ver1.RSH.ELC.15 | E15: PJ | F15: PJ/a | K15: =TechData_DMD!BF15 -> R2,R3,R4,R5,R6
B16: DMD | C16: =TechData_DMD!A16 -> RSHEFRV120 | D16: =TechData_DMD!B16 -> Electric Furnace Ver1.RSH.ELC.20 | E16: PJ | F16: PJ/a | K16: =TechData_DMD!BF16 -> R2,R3,R4,R5,R6
B17: DMD | C17: =TechData_DMD!A17 -> RSHEFRV122 | D17: =TechData_DMD!B17 -> Electric Furnace Ver1.RSH.ELC.22 | E17: PJ | F17: PJ/a | K17: =TechData_DMD!BF17 -> R2,R3,R4,R5,R6
B18: *Electric Heat Pumps (Residential Air Source Heat Pumps)
B19: DMD | C19: =TechData_DMD!A19 -> RSHEHPBS15 | D19: =TechData_DMD!B19 -> Electric Heat Pump Base.RSH.ELC.15 | E19: PJ | F19: PJ/a | I19: DAYNITE | K19: =TechData_DMD!BF19 -> R2,R3,R4,R5,R6
B20: DMD | C20: =TechData_DMD!A22 -> RSHEHPB120 | D20: =TechData_DMD!B22 -> Electric Heat Pump Base.RSH.ELC.20 | E20: PJ | F20: PJ/a | I20: DAYNITE | K20: =TechData_DMD!BF22 -> R2,R3,R4,R5,R6
B21: DMD | C21: =TechData_DMD!A25 -> RSHEHPBS22 | D21: =TechData_DMD!B25 -> Electric Heat Pump Base.RSH.ELC.22 | E21: PJ | F21: PJ/a | I21: DAYNITE | K21: =TechData_DMD!BF25 -> R2,R3,R4,R5,R6
B22: DMD | C22: =TechData_DMD!A28 -> RSHEHPV122 | D22: =TechData_DMD!B28 -> Electric Heat Pump Ver1.RSH.ELC.22 | E22: PJ | F22: PJ/a | I22: DAYNITE | K22: R2,R3,R4,R5,R6
B23: DMD | C23: =TechData_DMD!A31 -> RSHEHPV123 | D23: =TechData_DMD!B31 -> Electric Heat Pump Ver1.RSH.ELC.23 | E23: PJ | F23: PJ/a | I23: DAYNITE | K23: =TechData_DMD!BF31 -> R2,R3,R4,R5,R6
B24: DMD | C24: =TechData_DMD!A34 -> RSHEHPV223 | D24: =TechData_DMD!B34 -> Electric Heat Pump Ver2.RSH.ELC.23 | E24: PJ | F24: PJ/a | I24: DAYNITE | K24: =TechData_DMD!BF34 -> R2,R3,R4,R5,R6
B25: DMD | C25: =TechData_DMD!A37 -> RSHEHPV323 | D25: =TechData_DMD!B37 -> Electric Heat Pump Ver3.RSH.ELC.23 | E25: PJ | F25: PJ/a | I25: DAYNITE | K25: =TechData_DMD!BF37 -> R2,R3,R4,R5,R6
B26: DMD | C26: =TechData_DMD!A40 -> RSHEHPV130 | D26: =TechData_DMD!B40 -> Electric Heat Pump Ver1.RSH.ELC.30 | E26: PJ | F26: PJ/a | I26: DAYNITE | K26: =TechData_DMD!BF40 -> R2,R3,R4,R5,R6
B27: DMD | C27: =TechData_DMD!A43 -> RSHEHPV230 | D27: =TechData_DMD!B43 -> Electric Heat Pump Ver2.RSH.ELC.30 | E27: PJ | F27: PJ/a | I27: DAYNITE | K27: =TechData_DMD!BF43 -> R2,R3,R4,R5,R6
B28: DMD | C28: =TechData_DMD!A46 -> RSHEHPV140 | D28: =TechData_DMD!B46 -> Electric Heat Pump Ver1.RSH.ELC.40 | E28: PJ | F28: PJ/a | I28: DAYNITE | K28: =TechData_DMD!BF46 -> R2,R3,R4,R5,R6
B29: DMD | C29: =TechData_DMD!A49 -> RSHEHPV240 | D29: =TechData_DMD!B49 -> Electric Heat Pump Ver2.RSH.ELC.40 | E29: PJ | F29: PJ/a | I29: DAYNITE | K29: R2,R3,R4,R5,R6
B30: DMD | C30: =TechData_DMD!A52 -> RSHEHPV150 | D30: =TechData_DMD!B52 -> Electric Heat Pump Ver1.RSH.ELC.50 | E30: PJ | F30: PJ/a | I30: DAYNITE | K30: =TechData_DMD!BF52 -> R2,R3,R4,R5,R6
B31: DMD | C31: =TechData_DMD!A55 -> RSHEHPV250 | D31: =TechData_DMD!B55 -> Electric Heat Pump Ver2.RSH.ELC.50 | E31: PJ | F31: PJ/a | I31: DAYNITE | K31: =TechData_DMD!BF55 -> R2,R3,R4,R5,R6
B32: *Natural Gas Furnaces (Residential Gas-Fired Furnaces - North)
B33: DMD | C33: =TechData_DMD!A59 -> RSHNFRBS15 | D33: =TechData_DMD!B59 -> Natural Gas Furnace Base.RSH.NGA.15 | E33: PJ | F33: PJ/a | K33: =TechData_DMD!BF59 -> R2,R3,R4,R5,R6
B34: DMD | C34: =TechData_DMD!A60 -> RSHNFRBS20 | D34: =TechData_DMD!B60 -> Natural Gas Furnace Base.RSH.NGA.20 | E34: PJ | F34: PJ/a | K34: =TechData_DMD!BF60 -> R2,R3,R4,R5,R6
B35: DMD | C35: =TechData_DMD!A61 -> RSHNFRV122 | D35: =TechData_DMD!B61 -> Natural Gas Furnace Ver1.RSH.NGA.22 | E35: PJ | F35: PJ/a | K35: =TechData_DMD!BF61 -> R2,R3,R4,R5,R6
B36: DMD | C36: =TechData_DMD!A62 -> RSHNFRV222 | D36: =TechData_DMD!B62 -> Natural Gas Furnace Ver2.RSH.NGA.22 | E36: PJ | F36: PJ/a | K36: =TechData_DMD!BF62 -> R2,R3,R4,R5,R6
B37: DMD | C37: =TechData_DMD!A63 -> RSHNFRV322 | D37: =TechData_DMD!B63 -> Natural Gas Furnace Ver3.RSH.NGA.22 | E37: PJ | F37: PJ/a | K37: =TechData_DMD!BF63 -> R2,R3,R4,R5,R6
B38: DMD | C38: =TechData_DMD!A64 -> RSHNFRV422 | D38: =TechData_DMD!B64 -> Natural Gas Furnace Ver4.RSH.NGA.22 | E38: PJ | F38: PJ/a | K38: =TechData_DMD!BF64 -> R2,R3,R4,R5,R6
B39: *Natural Gas Radiant Heating (Residential Gas-Fired Boiler Radiants)
B40: DMD | C40: =TechData_DMD!A66 -> RSHNBRBS15 | D40: =TechData_DMD!B66 -> Natural Gas Boiler Radiant Base.RSH.NGA.15 | E40: PJ | F40: PJ/a | K40: =TechData_DMD!BF66 -> R2,R3,R4,R5,R6
B41: DMD | C41: =TechData_DMD!A67 -> RSHNBRBS20 | D41: =TechData_DMD!B67 -> Natural Gas Boiler Radiant Base.RSH.NGA.20 | E41: PJ | F41: PJ/a | K41: =TechData_DMD!BF67 -> R2,R3,R4,R5,R6
B42: DMD | C42: =TechData_DMD!A68 -> RSHNBRV122 | D42: =TechData_DMD!B68 -> Natural Gas Boiler Radiant Ver 1.RSH.NGA.22 | E42: PJ | F42: PJ/a | K42: =TechData_DMD!BF68 -> R2,R3,R4,R5,R6
B43: DMD | C43: =TechData_DMD!A69 -> RSHNBRV222 | D43: =TechData_DMD!B69 -> Natural Gas Boiler Radiant Ver 2.RSH.NGA.22 | E43: PJ | F43: PJ/a | K43: =TechData_DMD!BF69 -> R2,R3,R4,R5,R6
B44: DMD | C44: =TechData_DMD!A70 -> RSHNBRV322 | D44: =TechData_DMD!B70 -> Natural Gas Boiler Radiant Ver 3.RSH.NGA.22 | E44: PJ | F44: PJ/a | K44: =TechData_DMD!BF70 -> R2,R3,R4,R5,R6
B45: DMD | C45: =TechData_DMD!A71 -> RSHNBRV422 | D45: =TechData_DMD!B71 -> Natural Gas Boiler Radiant Ver 4.RSH.NGA.22 | E45: PJ | F45: PJ/a | K45: =TechData_DMD!BF71 -> R2,R3,R4,R5,R6
B46: DMD | C46: =TechData_DMD!A72 -> RSHNBRV130 | D46: =TechData_DMD!B72 -> Natural Gas Boiler Radiant Ver 1.RSH.NGA.30 | E46: PJ | F46: PJ/a | K46: =TechData_DMD!BF72 -> R2,R3,R4,R5,R6
B47: DMD | C47: =TechData_DMD!A73 -> RSHNBRV230 | D47: =TechData_DMD!B73 -> Natural Gas Boiler Radiant Ver 2.RSH.NGA.30 | E47: PJ | F47: PJ/a | K47: =TechData_DMD!BF73 -> R2,R3,R4,R5,R6
B48: *Dfuel Oil (DSL) Radiant Space Heating
B49: DMD | C49: =TechData_DMD!A75 -> RSHDRDBS15 | D49: =TechData_DMD!B75 -> Distillate Radiant Base.RSH.DST.15 | E49: PJ | F49: PJ/a | K49: =TechData_DMD!BF75 -> R2,R3,R4,R5,R6
B50: DMD | C50: =TechData_DMD!A76 -> RSHDRDBS20 | D50: =TechData_DMD!B76 -> Distillate Radiant Ver1.RSH.DST.20 | E50: PJ | F50: PJ/a | K50: R2,R3,R4,R5,R6
B51: DMD | C51: =TechData_DMD!A77 -> RSHDRDV122 | D51: =TechData_DMD!B77 -> Distillate Radiant Ver1.RSH.DST.22 | E51: PJ | F51: PJ/a | K51: R2,R3,R4,R5,R6
B52: DMD | C52: =TechData_DMD!A78 -> RSHDRDV222 | D52: =TechData_DMD!B78 -> Distillate Radiant Ver2.RSH.DST.22 | E52: PJ | F52: PJ/a | K52: R2,R3,R4,R5,R6
B53: DMD | C53: =TechData_DMD!A79 -> RSHDRDV322 | D53: =TechData_DMD!B79 -> Distillate Radiant Ver3.RSH.DST.22 | E53: PJ | F53: PJ/a | K53: R2,R3,R4,R5,R6
B54: DMD | C54: =TechData_DMD!A80 -> RSHDRDV422 | D54: =TechData_DMD!B80 -> Distillate Radiant Ver4.RSH.DST.22 | E54: PJ | F54: PJ/a | K54: R2,R3,R4,R5,R6
B55: DMD | C55: =TechData_DMD!A81 -> RSHDRDV130 | D55: =TechData_DMD!B81 -> Distillate Radiant Ver1.RSH.DST.30 | E55: PJ | F55: PJ/a | K55: R2,R3,R4,R5,R6
B56: DMD | C56: =TechData_DMD!A82 -> RSHDRDV230 | D56: =TechData_DMD!B82 -> Distillate Radiant Ver2.RSH.DST.30 | E56: PJ | F56: PJ/a | K56: R2,R3,R4,R5,R6
B57: *Fuel Oil (DSL) Furnaces
B58: DMD | C58: =TechData_DMD!A84 -> RSHDFRBS15 | D58: =TechData_DMD!B84 -> Distillate Furnace Base.RSH.DST.15 | E58: PJ | F58: PJ/a | K58: R2,R3,R4,R5,R6
B59: DMD | C59: =TechData_DMD!A85 -> RSHDFRBS20 | D59: =TechData_DMD!B85 -> Distillate Furnace Base.RSH.DST.20 | E59: PJ | F59: PJ/a | K59: R2,R3,R4,R5,R6
B60: DMD | C60: =TechData_DMD!A86 -> RSHDFRV122 | D60: =TechData_DMD!B86 -> Distillate Furnace Ver1.RSH.DST.22 | E60: PJ | F60: PJ/a | K60: R2,R3,R4,R5,R6
B61: DMD | C61: =TechData_DMD!A87 -> RSHDFRV222 | D61: =TechData_DMD!B87 -> Distillate Furnace Ver2.RSH.DST.22 | E61: PJ | F61: PJ/a | K61: R2,R3,R4,R5,R6
B62: DMD | C62: =TechData_DMD!A88 -> RSHDFRV322 | D62: =TechData_DMD!B88 -> Distillate Furnace Ver3.RSH.DST.22 | E62: PJ | F62: PJ/a | K62: R2,R3,R4,R5,R6
B63: DMD | C63: =TechData_DMD!A89 -> RSHDFRV422 | D63: =TechData_DMD!B89 -> Distillate Furnace Ver4.RSH.DST.22 | E63: PJ | F63: PJ/a | K63: R2,R3,R4,R5,R6
B64: DMD | C64: =TechData_DMD!A90 -> RSHDFRV130 | D64: =TechData_DMD!B90 -> Distillate Furnace Ver1.RSH.DST.30 | E64: PJ | F64: PJ/a | K64: R2,R3,R4,R5,R6
B65: DMD | C65: =TechData_DMD!A91 -> RSHDFRV230 | D65: =TechData_DMD!B91 -> Distillate Furnace Ver2.RSH.DST.30 | E65: PJ | F65: PJ/a | K65: R2,R3,R4,R5,R6
B66: *Geothermal Heat Pumps
B67: DMD | C67: =TechData_DMD!A93 -> RSCGHPBS15 | D67: =TechData_DMD!B93 -> Ground Source Heat Pump Base.RSC.ELC.15 | E67: PJ | F67: PJ/a | I67: DAYNITE | K67: R2,R3,R4,R5,R6
B68: DMD | C68: =TechData_DMD!A96 -> RSCGHPBS20 | D68: =TechData_DMD!B96 -> Ground Source Heat Pump Base.RSC.ELC.20 | E68: PJ | F68: PJ/a | I68: DAYNITE | K68: R2,R3,R4,R5,R6
B69: DMD | C69: =TechData_DMD!A99 -> RSCGHPV122 | D69: =TechData_DMD!B99 -> Ground Source Heat Pump Ver1.RSC.ELC.22 | E69: PJ | F69: PJ/a | I69: DAYNITE | K69: R2,R3,R4,R5,R6
B70: DMD | C70: =TechData_DMD!A102 -> RSCGHPV222 | D70: =TechData_DMD!B102 -> Ground Source Heat Pump Ver2.RSC.ELC.22 | E70: PJ | F70: PJ/a | I70: DAYNITE | K70: R2,R3,R4,R5,R6
B71: DMD | C71: =TechData_DMD!A105 -> RSCGHPV322 | D71: =TechData_DMD!B105 -> Ground Source Heat Pump Ver3.RSC.ELC.22 | E71: PJ | F71: PJ/a | I71: DAYNITE | K71: R2,R3,R4,R5,R6
B72: DMD | C72: =TechData_DMD!A108 -> RSCGHPV422 | D72: =TechData_DMD!B108 -> Ground Source Heat Pump Ver4.RSC.ELC.22 | E72: PJ | F72: PJ/a | I72: DAYNITE | K72: R2,R3,R4,R5,R6
B73: DMD | C73: =TechData_DMD!A111 -> RSCGHPV130 | D73: =TechData_DMD!B111 -> Ground Source Heat Pump Ver1.RSC.ELC.30 | E73: PJ | F73: PJ/a | I73: DAYNITE | K73: R2,R3,R4,R5,R6
B74: DMD | C74: =TechData_DMD!A114 -> RSCGHPV230 | D74: =TechData_DMD!B114 -> Ground Source Heat Pump Ver2.RSC.ELC.30 | E74: PJ | F74: PJ/a | I74: DAYNITE | K74: R2,R3,R4,R5,R6
B75: *Natural Gas Heat Pumps (Residential Natural Gas Heat Pumps)
B76: DMD | C76: =TechData_DMD!A118 -> RSHNHPBS09 | D76: =TechData_DMD!B118 -> Natural Gas Heat Pump Base.RSH.NGA.09 | E76: PJ | F76: PJ/a | K76: R2,R3,R4,R5,R6
B77: DMD | C77: =TechData_DMD!A119 -> RSHNHPBS20 | D77: =TechData_DMD!B119 -> Natural Gas Heat Pump Base.RSH.NGA.20 | E77: PJ | F77: PJ/a | K77: R2,R3,R4,R5,R6
B78: DMD | C78: =TechData_DMD!A120 -> RSHNHPV122 | D78: =TechData_DMD!B120 -> Natural Gas Heat Pump Ver1.RSH.NGA.22 | E78: PJ | F78: PJ/a | K78: R2,R3,R4,R5,R6
B79: DMD | C79: =TechData_DMD!A121 -> RSHNHPV130 | D79: =TechData_DMD!B121 -> Natural Gas Heat Pump Ver1.RSH.NGA.30 | E79: PJ | F79: PJ/a | K79: R2,R3,R4,R5,R6
B80: DMD | C80: =TechData_DMD!A122 -> RSHNHPV140 | D80: =TechData_DMD!B122 -> Natural Gas Heat Pump Ver1.RSH.NGA.40 | E80: PJ | F80: PJ/a | K80: R2,R3,R4,R5,R6
B81: DMD | C81: =TechData_DMD!A123 -> RSHNHPV150 | D81: =TechData_DMD!B123 -> Natural Gas Heat Pump Ver1.RSH.NGA.50 | E81: PJ | F81: PJ/a | K81: R2,R3,R4,R5,R6
B82: =TechData_DMD!A124 -> *UTILITY SCALE CHP - SH
B83: DMD | C83: =TechData_DMD!A125 -> RSHNUTIBOI15 | D83: =TechData_DMD!B125 -> RSH.NG.UTILITY.BOILER | E83: PJ | F83: PJ/a | K83: R2,R3,R4,R5,R6
B84: DMD | C84: =TechData_DMD!A126 -> RSHNUTICHP15 | D84: =TechData_DMD!B126 -> RSH.NG.UTILITY.CHP | E84: PJ | F84: PJ/a | K84: R2,R3,R4,R5,R6
B85: DMD | C85: =TechData_DMD!A127 -> RSHBUTICHP15 | D85: =TechData_DMD!B127 -> RSH.DSL.UTILITY.CHP | E85: PJ | F85: PJ/a | K85: R2,R3,R4,R5,R6
B86: =TechData_DMD!A128 -> *Heating retrofit | E86: PJ | F86: PJ/a
B87: DMD | C87: =TechData_DMD!A129 -> RSHRETSMT | D87: =TechData_DMD!B129 -> Retrofit.Smart Thermostats | E87: PJ | F87: PJ/a | K87: R2,R3,R4,R5,R6
B88: DMD | C88: =TechData_DMD!A130 -> RSHRETVEO | D88: =TechData_DMD!B130 -> Retrofit.Ventilation Overhaul | E88: PJ | F88: PJ/a | K88: R2,R3,R4,R5,R6
B89: DMD | C89: =TechData_DMD!A131 -> RSHRETINR | D89: =TechData_DMD!B131 -> Retrofit.Insulation - roof | E89: PJ | F89: PJ/a | K89: R2,R3,R4,R5,R6
B90: DMD | C90: =TechData_DMD!A132 -> RSHRETWIR | D90: =TechData_DMD!B132 -> Retrofit.Window replacement | E90: PJ | F90: PJ/a | K90: R2,R3,R4,R5,R6
B91: DMD | C91: =TechData_DMD!A133 -> RSHRETINW | D91: =TechData_DMD!B133 -> Retrofit.Insulation - walls | E91: PJ | F91: PJ/a | K91: R2,R3,R4,R5,R6
B92: *Space Cooling
B93: *Room/Window AC (EIA EQ: Residential Room Air Conditioners)
B94: DMD | C94: =TechData_DMD!A136 -> RSCRACBS15 | D94: =TechData_DMD!B136 -> Room AC Base.RSC.ELC.15 | E94: PJ | F94: PJ/a | K94: R2,R3,R4,R5,R6
B95: DMD | C95: =TechData_DMD!A137 -> RSCRACBS20 | D95: =TechData_DMD!B137 -> Room AC Base.RSC.ELC.20 | E95: PJ | F95: PJ/a | K95: R2,R3,R4,R5,R6
B96: DMD | C96: =TechData_DMD!A138 -> RSCRACV122 | D96: =TechData_DMD!B138 -> Room AC Ver1.RSC.ELC.22 | E96: PJ | F96: PJ/a | K96: R2,R3,R4,R5,R6
B97: DMD | C97: =TechData_DMD!A139 -> RSCRACV222 | D97: =TechData_DMD!B139 -> Room AC Ver2.RSC.ELC.22 | E97: PJ | F97: PJ/a | K97: R2,R3,R4,R5,R6
B98: DMD | C98: =TechData_DMD!A140 -> RSCRACV322 | D98: =TechData_DMD!B140 -> Room AC Ver3.RSC.ELC.22 | E98: PJ | F98: PJ/a | K98: R2,R3,R4,R5,R6
B99: DMD | C99: =TechData_DMD!A141 -> RSCRACV422 | D99: =TechData_DMD!B141 -> Room AC Ver4.RSC.ELC.22 | E99: PJ | F99: PJ/a | K99: R2,R3,R4,R5,R6
B100: *Central AC Units (EIA EQ: Residential Central Air Conditioners (North (Not Hot-Dry or Hot-Humid)))
B101: DMD | C101: =TechData_DMD!A143 -> RSCCACBS15 | D101: =TechData_DMD!B143 -> Central AC Base.RSC.ELC.15 | E101: PJ | F101: PJ/a | K101: R2,R3,R4,R5,R6
B102: DMD | C102: =TechData_DMD!A144 -> RSCCACBS20 | D102: =TechData_DMD!B144 -> Central AC Base.RSC.ELC.20 | E102: PJ | F102: PJ/a | K102: R2,R3,R4,R5,R6
B103: DMD | C103: =TechData_DMD!A145 -> RSCCACV122 | D103: =TechData_DMD!B145 -> Central AC Ver1.RSC.ELC.22 | E103: PJ | F103: PJ/a | K103: R2,R3,R4,R5,R6
B104: DMD | C104: =TechData_DMD!A146 -> RSCCACV222 | D104: =TechData_DMD!B146 -> Central AC Ver2.RSC.ELC.22 | E104: PJ | F104: PJ/a | K104: R2,R3,R4,R5,R6
...

Sheet TechData_DMD
A1: _GLOBAL,R0,R1,R2,R3,R4,R5,R6 | K1: R2 | L1: R3 | M1: R4 | N1: R5 | O1: R6 | AO1: R2 | AP1: R3 | AQ1: R4 | AR1: R5 | AS1: R6 | AT1: R2 | AU1: R3 | AV1: R4 | AW1: R5 | AX1: R6 | AY1: R2 | AZ1: R3 | BA1: R4 | BB1: R5 | BC1: R6 | BF1: TechData
E6: ~FI_T
A7: TechName | B7: *TechDesc | C7: *Units | D7: CommIN | E7: CommOUT | F7: NCAP_START | G7: NCAP_TLIFE | H7: NCAP_COST | I7: EFF | J7: Share~UP | K7: NCAP_AF~R2 | L7: NCAP_AF~R3 | M7: NCAP_AF~R4 | N7: NCAP_AF~R5 | O7: NCAP_AF~R6 | P7: NCAP_FOM | Q7: NCAP_DRATE | R7: NCAP_BND~2010 | S7: NCAP_BND~2015 | T7: NCAP_BND~2020 | U7: NCAP_BND~2025 | V7: NCAP_BND~2030 | W7: NCAP_BND~2035 | X7: NCAP_BND~2040 | Y7: NCAP_BND~2045 | Z7: NCAP_BND~2050 | AA7: NCAP_BND~2055 | AD7: *GROWTH~2015 | AE7: *GROWTH~2020 | AF7: *GROWTH~2025 | AG7: *GROWTH~2030 | AH7: *GROWTH~2035 | AI7: *GROWTH~2040 | AJ7: *GROWTH~2045 | AK7: *GROWTH~2050 | AL7: *GROWTH~2055 | AO7: PRC_RESID~R2~2010 | AP7: PRC_RESID~R3~2010 | AQ7: PRC_RESID~R4~2010 | AR7: PRC_RESID~R5~2010 | AS7: PRC_RESID~R6~2010 | AT7: PRC_RESID~R2~2015 | AU7: PRC_RESID~R3~2015 | AV7: PRC_RESID~R4~2015 | AW7: PRC_RESID~R5~2015 | AX7: PRC_RESID~R6~2015 | AY7: PRC_RESID~R2~2020 | AZ7: PRC_RESID~R3~2020 | BA7: PRC_RESID~R4~2020 | BB7: PRC_RESID~R5~2020 | BC7: PRC_RESID~R6~2020 | BF7: Region
A8: *Space Heating | BF8: *Space Heating
A9: *Electric Radiant Heating | BF9: *Electric Radiant Heating
A10: ='EIA23 EQ Cost'!B8 -> RSHERDBS10 | B10: ='EIA23 EQ Cost'!C8 -> Electric Radiant Base.RSH.ELC.10 | C10: PJ | D10: RESELC | E10: RSH | F10: ='EIA23 EQ Cost'!G8 -> 2011 | G10: ='EIA23 EQ Cost'!H8 -> 22.5 | H10: ='EIA23 EQ Cost'!J8 -> 3.74 | I10: ='EIA23 EQ Cost'!K8 -> 1 | J10: 1 | K10: 0.16 | L10: 0.16 | M10: 0.16 | N10: 0.16 | O10: 0.16 | Q10: 0.18 | R10: 0 | S10: 0 | T10: =SUM(AT10:AX10)*1.12 -> #REF! | U10: =T10*1.12 -> #REF! | V10: =U10*1.12 -> #REF! | W10: =V10*1.12 -> #REF! | X10: =W10*1.12 -> #REF! | Y10: =X10*1.12 -> #REF! | Z10: =Y10*1.12 -> #REF! | AA10: =Z10*1.12 -> #REF! | AE10: 1.1 | AF10: =AE10 -> 1.1 | AG10: =AF10 -> 1.1 | AH10: =AG10 -> 1.1 | AI10: =AH10 -> 1.1 | AJ10: =AI10 -> 1.1 | AK10: =AJ10 -> 1.1 | AL10: =AK10 -> 1.1 | AO10: =Resid!V7 -> #REF! | AP10: =Resid!W7 -> #REF! | AQ10: =Resid!X7 -> #REF! | AR10: =Resid!Y7 -> #REF! | AS10: =Resid!Z7 -> #REF! | AT10: =AO10*15/20 -> #REF! | AU10: =AP10*15/20 -> #REF! | AV10: =AQ10*15/20 -> #REF! | AW10: =AR10*15/20 -> #REF! | AX10: =AS10*15/20 -> #REF! | BF10: R2,R3,R4,R5,R6
A11: ='EIA23 EQ Cost'!B9 -> RSHERUV115 | B11: ='EIA23 EQ Cost'!C9 -> Electric Resistance Unit Heater Ver1.RSH.ELC.15 | C11: PJ | D11: RESELC | E11: RSH | F11: ='EIA23 EQ Cost'!G9 -> 2015 | G11: ='EIA23 EQ Cost'!H9 -> 22.5 | H11: ='EIA23 EQ Cost'!J9 -> 3.4718966 | I11: ='EIA23 EQ Cost'!K9 -> 1 | J11: 1 | K11: 0.16 | L11: 0.16 | M11: 0.16 | N11: 0.16 | O11: 0.16 | Q11: 0.18 | BF11: R2,R3,R4,R5,R6
A12: ='EIA23 EQ Cost'!B10 -> RSHERUV120 | B12: ='EIA23 EQ Cost'!C10 -> Electric Resistance Unit Heater Ver1.RSH.ELC.20 | C12: PJ | D12: RESELC | E12: RSH | F12: ='EIA23 EQ Cost'!G10 -> 2020 | G12: ='EIA23 EQ Cost'!H10 -> 22.5 | H12: ='EIA23 EQ Cost'!J10 -> 3.4718966 | I12: ='EIA23 EQ Cost'!K10 -> 1 | J12: 1 | K12: 0.16 | L12: 0.16 | M12: 0.16 | N12: 0.16 | O12: 0.16 | Q12: 0.18 | BF12: R2,R3,R4,R5,R6
A13: ='EIA23 EQ Cost'!B11 -> RSHERUV122 | B13: ='EIA23 EQ Cost'!C11 -> Electric Resistance Unit Heater Ver1.RSH.ELC.22 | C13: PJ | D13: RESELC | E13: RSH | F13: ='EIA23 EQ Cost'!G11 -> 2022 | G13: ='EIA23 EQ Cost'!H11 -> 22.5 | H13: ='EIA23 EQ Cost'!J11 -> 8.0098408 | I13: ='EIA23 EQ Cost'!K11 -> 1 | J13: 1 | K13: 0.16 | L13: 0.16 | M13: 0.16 | N13: 0.16 | O13: 0.16 | Q13: 0.18 | BF13: R2,R3,R4,R5,R6
A14: ='EIA23 EQ Cost'!B12 -> *Electric Furnaces | BF14: =A14 -> *Electric Furnaces
A15: ='EIA23 EQ Cost'!B13 -> RSHEFRV115 | B15: ='EIA23 EQ Cost'!C13 -> Electric Furnace Ver1.RSH.ELC.15 | C15: PJ | D15: RESELC | E15: RSH | F15: ='EIA23 EQ Cost'!G13 -> 2015 | G15: ='EIA23 EQ Cost'!H13 -> 22.5 | H15: ='EIA23 EQ Cost'!J13 -> 0.98095202 | I15: ='EIA23 EQ Cost'!K13 -> 0.98 | J15: 1 | K15: 0.16 | L15: 0.16 | M15: 0.16 | N15: 0.16 | O15: 0.16 | Q15: 0.18 | BF15: R2,R3,R4,R5,R6
A16: ='EIA23 EQ Cost'!B14 -> RSHEFRV120 | B16: ='EIA23 EQ Cost'!C14 -> Electric Furnace Ver1.RSH.ELC.20 | C16: PJ | D16: RESELC | E16: RSH | F16: ='EIA23 EQ Cost'!G14 -> 2020 | G16: ='EIA23 EQ Cost'!H14 -> 22.5 | H16: ='EIA23 EQ Cost'!J14 -> 0.98095202 | I16: ='EIA23 EQ Cost'!K14 -> 0.98 | J16: 1 | K16: 0.16 | L16: 0.16 | M16: 0.16 | N16: 0.16 | O16: 0.16 | Q16: 0.18 | BF16: R2,R3,R4,R5,R6
A17: ='EIA23 EQ Cost'!B15 -> RSHEFRV122 | B17: ='EIA23 EQ Cost'!C15 -> Electric Furnace Ver1.RSH.ELC.22 | C17: PJ | D17: RESELC | E17: RSH | F17: ='EIA23 EQ Cost'!G15 -> 2022 | G17: ='EIA23 EQ Cost'!H15 -> 22.5 | H17: ='EIA23 EQ Cost'!J15 -> 1.1254333 | I17: ='EIA23 EQ Cost'!K15 -> 1 | J17: 1 | K17: 0.16 | L17: 0.16 | M17: 0.16 | N17: 0.16 | O17: 0.16 | Q17: 0.18 | BF17: R2,R3,R4,R5,R6
A18: ='EIA23 EQ Cost'!B16 -> *Electric Heat Pumps (Residential Air Source Heat Pumps) | BF18: =A18 -> *Electric Heat Pumps (Residential Air Source Heat Pumps)
A19: ='EIA23 EQ Cost'!B17 -> RSHEHPBS15 | B19: ='EIA23 EQ Cost'!C17 -> Electric Heat Pump Base.RSH.ELC.15 | C19: PJ | D19: RESELC | F19: ='EIA23 EQ Cost'!G17 -> 2015 | G19: ='EIA23 EQ Cost'!H17 -> 15.5 | H19: ='EIA23 EQ Cost'!J17 -> 8.3165467 | K19: =0.16*2 -> 0.32 | L19: =0.16*2 -> 0.32 | M19: =0.16*2 -> 0.32 | N19: =0.16*2 -> 0.32 | O19: =0.16*2 -> 0.32 | Q19: 0.18 | T19: 0 | U19: 0 | V19: 0 | W19: 0 | X19: 0 | Y19: 0 | Z19: 0 | AA19: 0 | AO19: =Resid!V10 -> #REF! | AP19: =Resid!W10 -> #REF! | AQ19: =Resid!X10 -> #REF! | AR19: =Resid!Y10 -> #REF! | AS19: =Resid!Z10 -> #REF! | AT19: =AO19 -> #REF! | AU19: =AP19 -> #REF! | AV19: =AQ19 -> #REF! | AW19: =AR19 -> #REF! | AX19: =AS19 -> #REF! | BF19: R2,R3,R4,R5,R6
E20: RSH | J20: 0.75
E21: RSC | J21: 0.5
A22: ='EIA23 EQ Cost'!B18 -> RSHEHPB120 | B22: ='EIA23 EQ Cost'!C18 -> Electric Heat Pump Base.RSH.ELC.20 | C22: PJ | D22: RESELC | F22: ='EIA23 EQ Cost'!G18 -> 2020 | G22: ='EIA23 EQ Cost'!H18 -> 15.5 | H22: ='EIA23 EQ Cost'!J18 -> 9.8821833 | K22: =0.16*2 -> 0.32 | L22: =0.16*2 -> 0.32 | M22: =0.16*2 -> 0.32 | N22: =0.16*2 -> 0.32 | O22: =0.16*2 -> 0.32 | Q22: 0.18 | U22: 0 | V22: 0 | W22: 0 | X22: 0 | Y22: 0 | Z22: 0 | AA22: 0 | BF22: R2,R3,R4,R5,R6
E23: RSH | J23: 0.75
E24: RSC | J24: 0.5
A25: ='EIA23 EQ Cost'!B19 -> RSHEHPBS22 | B25: ='EIA23 EQ Cost'!C19 -> Electric Heat Pump Base.RSH.ELC.22 | C25: PJ | D25: RESELC | F25: ='EIA23 EQ Cost'!G19 -> 2022 | G25: ='EIA23 EQ Cost'!H19 -> 15.5 | H25: ='EIA23 EQ Cost'!J19 -> 9.8821833 | K25: =0.16*2 -> 0.32 | L25: =0.16*2 -> 0.32 | M25: =0.16*2 -> 0.32 | N25: =0.16*2 -> 0.32 | O25: =0.16*2 -> 0.32 | Q25: 0.18 | V25: 0 | W25: 0 | X25: 0 | Y25: 0 | Z25: 0 | AA25: 0 | BF25: R2,R3,R4,R5,R6
E26: RSH | J26: 0.75
E27: RSC | J27: 0.5
A28: ='EIA23 EQ Cost'!B20 -> RSHEHPV122 | B28: ='EIA23 EQ Cost'!C20 -> Electric Heat Pump Ver1.RSH.ELC.22 | C28: PJ | D28: RESELC | F28: ='EIA23 EQ Cost'!G20 -> 2022 | G28: ='EIA23 EQ Cost'!H20 -> 15.5 | H28: ='EIA23 EQ Cost'!J20 -> 12.381456 | K28: =0.16*2 -> 0.32 | L28: =0.16*2 -> 0.32 | M28: =0.16*2 -> 0.32 | N28: =0.16*2 -> 0.32 | O28: =0.16*2 -> 0.32 | Q28: 0.18 | V28: 0 | W28: 0 | X28: 0 | Y28: 0 | Z28: 0 | AA28: 0
E29: RSH | J29: 0.75
E30: RSC | J30: 0.5
A31: ='EIA23 EQ Cost'!B21 -> RSHEHPV123 | B31: ='EIA23 EQ Cost'!C21 -> Electric Heat Pump Ver1.RSH.ELC.23 | C31: PJ | D31: RESELC | F31: ='EIA23 EQ Cost'!G21 -> 2023 | G31: ='EIA23 EQ Cost'!H21 -> 15.5 | H31: ='EIA23 EQ Cost'!J21 -> 9.7816379 | K31: =0.16*2 -> 0.32 | L31: =0.16*2 -> 0.32 | M31: =0.16*2 -> 0.32 | N31: =0.16*2 -> 0.32 | O31: =0.16*2 -> 0.32 | Q31: 0.18 | V31: 0 | W31: 0 | X31: 0 | Y31: 0 | Z31: 0 | AA31: 0 | BF31: R2,R3,R4,R5,R6
E32: RSH | J32: 0.75
E33: RSC | J33: 0.5
A34: ='EIA23 EQ Cost'!B22 -> RSHEHPV223 | B34: ='EIA23 EQ Cost'!C22 -> Electric Heat Pump Ver2.RSH.ELC.23 | C34: PJ | D34: RESELC | F34: ='EIA23 EQ Cost'!G22 -> 2023 | G34: ='EIA23 EQ Cost'!H22 -> 15.5 | H34: ='EIA23 EQ Cost'!J22 -> 9.9683652 | K34: =0.16*2 -> 0.32 | L34: =0.16*2 -> 0.32 | M34: =0.16*2 -> 0.32 | N34: =0.16*2 -> 0.32 | O34: =0.16*2 -> 0.32 | Q34: 0.18 | V34: 0 | W34: 0 | X34: 0 | Y34: 0 | Z34: 0 | AA34: 0 | BF34: R2,R3,R4,R5,R6
E35: RSH | J35: 0.75
E36: RSC | J36: 0.5
A37: ='EIA23 EQ Cost'!B23 -> RSHEHPV323 | B37: ='EIA23 EQ Cost'!C23 -> Electric Heat Pump Ver3.RSH.ELC.23 | C37: PJ | D37: RESELC | F37: ='EIA23 EQ Cost'!G23 -> 2023 | G37: ='EIA23 EQ Cost'!H23 -> 15.5 | H37: ='EIA23 EQ Cost'!J23 -> 12.381456 | K37: =0.16*2 -> 0.32 | L37: =0.16*2 -> 0.32 | M37: =0.16*2 -> 0.32 | N37: =0.16*2 -> 0.32 | O37: =0.16*2 -> 0.32 | Q37: 0.18 | V37: 0 | W37: 0 | X37: 0 | Y37: 0 | Z37: 0 | AA37: 0 | BF37: R2,R3,R4,R5,R6
E38: RSH | J38: 0.75
E39: RSC | J39: 0.5
A40: ='EIA23 EQ Cost'!B24 -> RSHEHPV130 | B40: ='EIA23 EQ Cost'!C24 -> Electric Heat Pump Ver1.RSH.ELC.30 | C40: PJ | D40: RESELC | F40: ='EIA23 EQ Cost'!G24 -> 2030 | G40: ='EIA23 EQ Cost'!H24 -> 15.5 | H40: ='EIA23 EQ Cost'!J24 -> 9.9683652 | K40: =0.16*2 -> 0.32 | L40: =0.16*2 -> 0.32 | M40: =0.16*2 -> 0.32 | N40: =0.16*2 -> 0.32 | O40: =0.16*2 -> 0.32 | Q40: 0.18 | X40: 0 | Y40: 0 | Z40: 0 | AA40: 0 | BF40: R2,R3,R4,R5,R6
E41: RSH | J41: 0.75
E42: RSC | J42: 0.5
A43: ='EIA23 EQ Cost'!B25 -> RSHEHPV230 | B43: ='EIA23 EQ Cost'!C25 -> Electric Heat Pump Ver2.RSH.ELC.30 | C43: PJ | D43: RESELC | F43: ='EIA23 EQ Cost'!G25 -> 2030 | G43: ='EIA23 EQ Cost'!H25 -> 15.5 | H43: ='EIA23 EQ Cost'!J25 -> 12.381456 | K43: =0.16*2 -> 0.32 | L43: =0.16*2 -> 0.32 | M43: =0.16*2 -> 0.32 | N43: =0.16*2 -> 0.32 | O43: =0.16*2 -> 0.32 | Q43: 0.18 | X43: 0 | Y43: 0 | Z43: 0 | AA43: 0 | BF43: R2,R3,R4,R5,R6
E44: RSH | J44: 0.75
E45: RSC | J45: 0.5
A46: ='EIA23 EQ Cost'!B26 -> RSHEHPV140 | B46: ='EIA23 EQ Cost'!C26 -> Electric Heat Pump Ver1.RSH.ELC.40 | C46: PJ | D46: RESELC | F46: ='EIA23 EQ Cost'!G26 -> 2040 | G46: ='EIA23 EQ Cost'!H26 -> 15.5 | H46: ='EIA23 EQ Cost'!J26 -> 10.399274 | K46: =0.16*2 -> 0.32 | L46: =0.16*2 -> 0.32 | M46: =0.16*2 -> 0.32 | N46: =0.16*2 -> 0.32 | O46: =0.16*2 -> 0.32 | Q46: 0.18 | Z46: 0 | AA46: 0 | BF46: R2,R3,R4,R5,R6
E47: RSH | J47: 0.75
E48: RSC | J48: 0.5
A49: ='EIA23 EQ Cost'!B27 -> RSHEHPV240 | B49: ='EIA23 EQ Cost'!C27 -> Electric Heat Pump Ver2.RSH.ELC.40 | C49: PJ | D49: RESELC | F49: ='EIA23 EQ Cost'!G27 -> 2040 | G49: ='EIA23 EQ Cost'!H27 -> 15.5 | H49: ='EIA23 EQ Cost'!J27 -> 12.381456 | K49: =0.16*2 -> 0.32 | L49: =0.16*2 -> 0.32 | M49: =0.16*2 -> 0.32 | N49: =0.16*2 -> 0.32 | O49: =0.16*2 -> 0.32 | Q49: 0.18 | Z49: 0 | AA49: 0 | BF49: R2,R3,R4,R5,R6
E50: RSH | J50: 0.75
E51: RSC | J51: 0.5
A52: ='EIA23 EQ Cost'!B28 -> RSHEHPV150 | B52: ='EIA23 EQ Cost'!C28 -> Electric Heat Pump Ver1.RSH.ELC.50 | C52: PJ | D52: RESELC | F52: ='EIA23 EQ Cost'!G28 -> 2050 | G52: ='EIA23 EQ Cost'!H28 -> 15.5 | H52: ='EIA23 EQ Cost'!J28 -> 10.528547 | K52: =0.16*2 -> 0.32 | L52: =0.16*2 -> 0.32 | M52: =0.16*2 -> 0.32 | N52: =0.16*2 -> 0.32 | O52: =0.16*2 -> 0.32 | Q52: 0.18 | BF52: R2,R3,R4,R5,R6
E53: RSH | J53: 0.75
E54: RSC | J54: 0.5
A55: ='EIA23 EQ Cost'!B29 -> RSHEHPV250 | B55: ='EIA23 EQ Cost'!C29 -> Electric Heat Pump Ver2.RSH.ELC.50 | C55: PJ | D55: RESELC | F55: ='EIA23 EQ Cost'!G29 -> 2050 | G55: ='EIA23 EQ Cost'!H29 -> 15.5 | H55: ='EIA23 EQ Cost'!J29 -> 12.381456 | K55: =0.16*2 -> 0.32 | L55: =0.16*2 -> 0.32 | M55: =0.16*2 -> 0.32 | N55: =0.16*2 -> 0.32 | O55: =0.16*2 -> 0.32 | Q55: 0.18 | BF55: R2,R3,R4,R5,R6
E56: RSH | J56: 0.75
E57: RSC | J57: 0.5
A58: ='EIA23 EQ Cost'!B30 -> *Natural Gas Furnaces (Residential Gas-Fired Furnaces - North) | BF58: =A58 -> *Natural Gas Furnaces (Residential Gas-Fired Furnaces - North)
A59: ='EIA23 EQ Cost'!B31 -> RSHNFRBS15 | B59: ='EIA23 EQ Cost'!C31 -> Natural Gas Furnace Base.RSH.NGA.15 | C59: PJ | D59: RESNGAEA | E59: RSH | F59: ='EIA23 EQ Cost'!G31 -> 2015 | G59: ='EIA23 EQ Cost'!H31 -> 21.5 | H59: ='EIA23 EQ Cost'!J31 -> 1.8615276 | I59: ='EIA23 EQ Cost'!K31 -> 0.8 | J59: 1 | K59: 0.16 | L59: 0.16 | M59: 0.16 | N59: 0.16 | O59: 0.16 | Q59: 0.18 | T59: 0 | U59: 0 | V59: 0 | W59: 0 | X59: 0 | Y59: 0 | Z59: 0 | AA59: 0 | AO59: =Resid!V25 -> #REF! | AP59: =Resid!W25 -> #REF! | AQ59: =Resid!X25 -> #REF! | AR59: =Resid!Y25 -> #REF! | AS59: =Resid!Z25 -> #REF! | AT59: =AO59*0.9 -> #REF! | AU59: =AP59*0.9 -> #REF! | AV59: =AQ59*0.9 -> #REF! | AW59: =AR59*0.9 -> #REF! | AX59: =AS59*0.9 -> #REF! | BF59: R2,R3,R4,R5,R6
A60: ='EIA23 EQ Cost'!B32 -> RSHNFRBS20 | B60: ='EIA23 EQ Cost'!C32 -> Natural Gas Furnace Base.RSH.NGA.20 | C60: PJ | D60: RESNGAEA | E60: RSH | F60: ='EIA23 EQ Cost'!G32 -> 2020 | G60: ='EIA23 EQ Cost'!H32 -> 21.5 | H60: ='EIA23 EQ Cost'!J32 -> 1.8615276 | I60: ='EIA23 EQ Cost'!K32 -> 0.8 | J60: 1 | K60: 0.16 | L60: 0.16 | M60: 0.16 | N60: 0.16 | O60: 0.16 | Q60: 0.18 | U60: 0 | V60: 0 | W60: 0 | X60: 0 | Y60: 0 | Z60: 0 | AA60: 0 | BF60: R2,R3,R4,R5,R6
A61: ='EIA23 EQ Cost'!B33 -> RSHNFRV122 | B61: ='EIA23 EQ Cost'!C33 -> Natural Gas Furnace Ver1.RSH.NGA.22 | C61: PJ | D61: RESNGAEA | E61: RSH | F61: ='EIA23 EQ Cost'!G33 -> 2022 | G61: ='EIA23 EQ Cost'!H33 -> 21.5 | H61: ='EIA23 EQ Cost'!J33 -> 2.3850822 | I61: ='EIA23 EQ Cost'!K33 -> 0.8 | J61: 1 | K61: 0.16 | L61: 0.16 | M61: 0.16 | N61: 0.16 | O61: 0.16 | Q61: 0.18 | BF61: R2,R3,R4,R5,R6
A62: ='EIA23 EQ Cost'!B34 -> RSHNFRV222 | B62: ='EIA23 EQ Cost'!C34 -> Natural Gas Furnace Ver2.RSH.NGA.22 | C62: PJ | D62: RESNGAEA | E62: RSH | F62: ='EIA23 EQ Cost'!G34 -> 2022 | G62: ='EIA23 EQ Cost'!H34 -> 21.5 | H62: ='EIA23 EQ Cost'!J34 -> 2.6694822 | I62: ='EIA23 EQ Cost'!K34 -> 0.9 | J62: 1 | K62: 0.16 | L62: 0.16 | M62: 0.16 | N62: 0.16 | O62: 0.16 | Q62: 0.18 | BF62: R2,R3,R4,R5,R6
A63: ='EIA23 EQ Cost'!B35 -> RSHNFRV322 | B63: ='EIA23 EQ Cost'!C35 -> Natural Gas Furnace Ver3.RSH.NGA.22 | C63: PJ | D63: RESNGAEA | E63: RSH | F63: ='EIA23 EQ Cost'!G35 -> 2022 | G63: ='EIA23 EQ Cost'!H35 -> 21.5 | H63: ='EIA23 EQ Cost'!J35 -> 2.6824095 | I63: ='EIA23 EQ Cost'!K35 -> 0.95 | J63: 1 | K63: 0.16 | L63: 0.16 | M63: 0.16 | N63: 0.16 | O63: 0.16 | Q63: 0.18 | BF63: R2,R3,R4,R5,R6
A64: ='EIA23 EQ Cost'!B36 -> RSHNFRV422 | B64: ='EIA23 EQ Cost'!C36 -> Natural Gas Furnace Ver4.RSH.NGA.22 | C64: PJ | D64: RESNGAEA | E64: RSH | F64: ='EIA23 EQ Cost'!G36 -> 2022 | G64: ='EIA23 EQ Cost'!H36 -> 21.5 | H64: ='EIA23 EQ Cost'!J36 -> 2.7922913 | I64: ='EIA23 EQ Cost'!K36 -> 0.99 | J64: 1 | K64: 0.16 | L64: 0.16 | M64: 0.16 | N64: 0.16 | O64: 0.16 | Q64: 0.18 | BF64: R2,R3,R4,R5,R6
A65: ='EIA23 EQ Cost'!B37 -> *Natural Gas Radiant Heating (Residential Gas-Fired Boiler Radiants) | BF65: =A65 -> *Natural Gas Radiant Heating (Residential Gas-Fired Boiler Radiants)
A66: ='EIA23 EQ Cost'!B38 -> RSHNBRBS15 | B66: ='EIA23 EQ Cost'!C38 -> Natural Gas Boiler Radiant Base.RSH.NGA.15 | C66: PJ | D66: RESNGAEA | E66: RSH | F66: ='EIA23 EQ Cost'!G38 -> 2015 | G66: ='EIA23 EQ Cost'!H38 -> 25 | H66: ='EIA23 EQ Cost'!J38 -> 4.0126261 | I66: ='EIA23 EQ Cost'!K38 -> 0.82 | J66: 1 | K66: 0.16 | L66: 0.16 | M66: 0.16 | N66: 0.16 | O66: 0.16 | Q66: 0.18 | T66: 0 | U66: 0 | V66: 0 | W66: 0 | X66: 0 | Y66: 0 | Z66: 0 | AA66: 0 | AO66: =Resid!V32 -> #REF! | AP66: =Resid!W32 -> #REF! | AQ66: =Resid!X32 -> #REF! | AR66: =Resid!Y32 -> #REF! | AS66: =Resid!Z32 -> #REF! | AT66: =AO66*0.9 -> #REF! | AU66: =AP66*0.9 -> #REF! | AV66: =AQ66*0.9 -> #REF! | AW66: =AR66*0.9 -> #REF! | AX66: =AS66*0.9 -> #REF! | BF66: R2,R3,R4,R5,R6
A67: ='EIA23 EQ Cost'!B39 -> RSHNBRBS20 | B67: ='EIA23 EQ Cost'!C39 -> Natural Gas Boiler Radiant Base.RSH.NGA.20 | C67: PJ | D67: RESNGAEA | E67: RSH | F67: ='EIA23 EQ Cost'!G39 -> 2020 | G67: ='EIA23 EQ Cost'!H39 -> 25 | H67: ='EIA23 EQ Cost'!J39 -> 3.0715205 | I67: ='EIA23 EQ Cost'!K39 -> 0.95 | J67: 1 | K67: 0.16 | L67: 0.16 | M67: 0.16 | N67: 0.16 | O67: 0.16 | Q67: 0.18 | U67: 0 | V67: 0 | W67: 0 | X67: 0 | Y67: 0 | Z67: 0 | AA67: 0 | BF67: R2,R3,R4,R5,R6
A68: ='EIA23 EQ Cost'!B40 -> RSHNBRV122 | B68: ='EIA23 EQ Cost'!C40 -> Natural Gas Boiler Radiant Ver 1.RSH.NGA.22 | C68: PJ | D68: RESNGAEA | E68: RSH | F68: ='EIA23 EQ Cost'!G40 -> 2022 | G68: ='EIA23 EQ Cost'!H40 -> 25 | H68: ='EIA23 EQ Cost'!J40 -> 4.4986916 | I68: ='EIA23 EQ Cost'!K40 -> 0.84 | J68: 1 | K68: 0.16 | L68: 0.16 | M68: 0.16 | N68: 0.16 | O68: 0.16 | Q68: 0.18 | V68: 0 | W68: 0 | X68: 0 | Y68: 0 | Z68: 0 | AA68: 0 | BF68: R2,R3,R4,R5,R6
A69: ='EIA23 EQ Cost'!B41 -> RSHNBRV222 | B69: ='EIA23 EQ Cost'!C41 -> Natural Gas Boiler Radiant Ver 2.RSH.NGA.22 | C69: PJ | D69: RESNGAEA | E69: RSH | F69: ='EIA23 EQ Cost'!G41 -> 2022 | G69: ='EIA23 EQ Cost'!H41 -> 25 | H69: ='EIA23 EQ Cost'!J41 -> 3.0715205 | I69: ='EIA23 EQ Cost'!K41 -> 0.95 | J69: 1 | K69: 0.16 | L69: 0.16 | M69: 0.16 | N69: 0.16 | O69: 0.16 | Q69: 0.18 | V69: 0 | W69: 0 | X69: 0 | Y69: 0 | Z69: 0 | AA69: 0 | BF69: R2,R3,R4,R5,R6
A70: ='EIA23 EQ Cost'!B42 -> RSHNBRV322 | B70: ='EIA23 EQ Cost'!C42 -> Natural Gas Boiler Radiant Ver 3.RSH.NGA.22 | C70: PJ | D70: RESNGAEA | E70: RSH | F70: ='EIA23 EQ Cost'!G42 -> 2022 | G70: ='EIA23 EQ Cost'!H42 -> 25 | H70: ='EIA23 EQ Cost'!J42 -> 3.4645096 | I70: ='EIA23 EQ Cost'!K42 -> 0.9 | J70: 1 | K70: 0.16 | L70: 0.16 | M70: 0.16 | N70: 0.16 | O70: 0.16 | Q70: 0.18 | V70: 0 | W70: 0 | X70: 0 | Y70: 0 | Z70: 0 | AA70: 0 | BF70: R2,R3,R4,R5,R6
A71: ='EIA23 EQ Cost'!B43 -> RSHNBRV422 | B71: ='EIA23 EQ Cost'!C43 -> Natural Gas Boiler Radiant Ver 4.RSH.NGA.22 | C71: PJ | D71: RESNGAEA | E71: RSH | F71: ='EIA23 EQ Cost'!G43 -> 2022 | G71: ='EIA23 EQ Cost'!H43 -> 25 | H71: ='EIA23 EQ Cost'!J43 -> 3.4696805 | I71: ='EIA23 EQ Cost'!K43 -> 0.96 | J71: 1 | K71: 0.16 | L71: 0.16 | M71: 0.16 | N71: 0.16 | O71: 0.16 | Q71: 0.18 | V71: 0 | W71: 0 | X71: 0 | Y71: 0 | Z71: 0 | AA71: 0 | BF71: R2,R3,R4,R5,R6
A72: ='EIA23 EQ Cost'!B44 -> RSHNBRV130 | B72: ='EIA23 EQ Cost'!C44 -> Natural Gas Boiler Radiant Ver 1.RSH.NGA.30 | C72: PJ | D72: RESNGAEA | E72: RSH | F72: ='EIA23 EQ Cost'!G44 -> 2030 | G72: ='EIA23 EQ Cost'!H44 -> 25 | H72: ='EIA23 EQ Cost'!J44 -> 3.0715205 | I72: ='EIA23 EQ Cost'!K44 -> 0.95 | J72: 1 | K72: 0.16 | L72: 0.16 | M72: 0.16 | N72: 0.16 | O72: 0.16 | Q72: 0.18 | BF72: R2,R3,R4,R5,R6
A73: ='EIA23 EQ Cost'!B45 -> RSHNBRV230 | B73: ='EIA23 EQ Cost'!C45 -> Natural Gas Boiler Radiant Ver 2.RSH.NGA.30 | C73: PJ | D73: RESNGAEA | E73: RSH | F73: ='EIA23 EQ Cost'!G45 -> 2030 | G73: ='EIA23 EQ Cost'!H45 -> 25 | H73: ='EIA23 EQ Cost'!J45 -> 3.4696805 | I73: ='EIA23 EQ Cost'!K45 -> 0.96 | J73: 1 | K73: 0.16 | L73: 0.16 | M73: 0.16 | N73: 0.16 | O73: 0.16 | Q73: 0.18 | BF73: R2,R3,R4,R5,R6
A74: ='EIA23 EQ Cost'!B46 -> *Dfuel Oil (DSL) Radiant Space Heating | BF74: =A74 -> *Dfuel Oil (DSL) Radiant Space Heating
A75: ='EIA23 EQ Cost'!B47 -> RSHDRDBS15 | B75: ='EIA23 EQ Cost'!C47 -> Distillate Radiant Base.RSH.DST.15 | C75: PJ | D75: RESDSLEA | E75: RSH | F75: ='EIA23 EQ Cost'!G47 -> 2015 | G75: ='EIA23 EQ Cost'!H47 -> 23 | H75: ='EIA23 EQ Cost'!J47 -> 3.6196369 | I75: ='EIA23 EQ Cost'!K47 -> 0.84 | J75: 1 | K75: 0.16 | L75: 0.16 | M75: 0.16 | N75: 0.16 | O75: 0.16 | Q75: 0.36 | T75: 0 | U75: 0 | V75: 0 | W75: 0 | X75: 0 | Y75: 0 | Z75: 0 | AA75: 0 | AO75: =Resid!V45 -> #REF! | AP75: =Resid!W45 -> #REF! | AQ75: =Resid!X45 -> #REF! | AR75: =Resid!Y45 -> #REF! | AS75: =Resid!Z45 -> #REF! | AT75: =AO75*0.9 -> #REF! | AU75: =AP75*0.9 -> #REF! | AV75: =AQ75*0.9 -> #REF! | AW75: =AR75*0.9 -> #REF! | AX75: =AS75*0.9 -> #REF! | BF75: R2,R3,R4,R5,R6
A76: ='EIA23 EQ Cost'!B48 -> RSHDRDBS20 | B76: ='EIA23 EQ Cost'!C48 -> Distillate Radiant Ver1.RSH.DST.20 | C76: PJ | D76: RESDSLEA | E76: RSH | F76: ='EIA23 EQ Cost'!G48 -> 2020 | G76: ='EIA23 EQ Cost'!H48 -> 23 | H76: ='EIA23 EQ Cost'!J48 -> 2.0351224 | I76: ='EIA23 EQ Cost'!K48 -> 0.86 | Q76: 0.36 | U76: 0 | V76: 0 | W76: 0 | X76: 0 | Y76: 0 | Z76: 0 | AA76: 0 | BF76: R2,R3,R4,R5,R6
A77: ='EIA23 EQ Cost'!B49 -> RSHDRDV122 | B77: ='EIA23 EQ Cost'!C49 -> Distillate Radiant Ver1.RSH.DST.22 | C77: PJ | D77: RESDSLEA | E77: RSH | F77: ='EIA23 EQ Cost'!G49 -> 2022 | G77: ='EIA23 EQ Cost'!H49 -> 23 | H77: ='EIA23 EQ Cost'!J49 -> 2.0351224 | I77: ='EIA23 EQ Cost'!K49 -> 0.86 | J77: 1 | K77: 0.16 | L77: 0.16 | M77: 0.16 | N77: 0.16 | O77: 0.16 | Q77: 0.36 | V77: 0 | W77: 0 | X77: 0 | Y77: 0 | Z77: 0 | AA77: 0 | BF77: R2,R3,R4,R5,R6
A78: ='EIA23 EQ Cost'!B50 -> RSHDRDV222 | B78: ='EIA23 EQ Cost'!C50 -> Distillate Radiant Ver2.RSH.DST.22 | C78: PJ | D78: RESDSLEA | E78: RSH | F78: ='EIA23 EQ Cost'!G50 -> 2022 | G78: ='EIA23 EQ Cost'!H50 -> 23 | H78: ='EIA23 EQ Cost'!J50 -> 2.0351224 | I78: ='EIA23 EQ Cost'!K50 -> 0.86 | J78: 1 | K78: 0.16 | L78: 0.16 | M78: 0.16 | N78: 0.16 | O78: 0.16 | Q78: 0.36 | V78: 0 | W78: 0 | X78: 0 | Y78: 0 | Z78: 0 | AA78: 0 | BF78: R2,R3,R4,R5,R6
A79: ='EIA23 EQ Cost'!B51 -> RSHDRDV322 | B79: ='EIA23 EQ Cost'!C51 -> Distillate Radiant Ver3.RSH.DST.22 | C79: PJ | D79: RESDSLEA | E79: RSH | F79: ='EIA23 EQ Cost'!G51 -> 2022 | G79: ='EIA23 EQ Cost'!H51 -> 23 | H79: ='EIA23 EQ Cost'!J51 -> 2.068364 | I79: ='EIA23 EQ Cost'!K51 -> 0.87 | J79: 1 | K79: 0.16 | L79: 0.16 | M79: 0.16 | N79: 0.16 | O79: 0.16 | Q79: 0.36 | V79: 0 | W79: 0 | X79: 0 | Y79: 0 | Z79: 0 | AA79: 0 | BF79: R2,R3,R4,R5,R6
A80: ='EIA23 EQ Cost'!B52 -> RSHDRDV422 | B80: ='EIA23 EQ Cost'!C52 -> Distillate Radiant Ver4.RSH.DST.22 | C80: PJ | D80: RESDSLEA | E80: RSH | F80: ='EIA23 EQ Cost'!G52 -> 2022 | G80: ='EIA23 EQ Cost'!H52 -> 23 | H80: ='EIA23 EQ Cost'!J52 -> 2.1016055 | I80: ='EIA23 EQ Cost'!K52 -> 0.88 | J80: 1 | K80: 0.16 | L80: 0.16 | M80: 0.16 | N80: 0.16 | O80: 0.16 | Q80: 0.36 | V80: 0 | W80: 0 | X80: 0 | Y80: 0 | Z80: 0 | AA80: 0 | BF80: R2,R3,R4,R5,R6
A81: ='EIA23 EQ Cost'!B53 -> RSHDRDV130 | B81: ='EIA23 EQ Cost'!C53 -> Distillate Radiant Ver1.RSH.DST.30 | C81: PJ | D81: RESDSLEA | E81: RSH | F81: ='EIA23 EQ Cost'!G53 -> 2030 | G81: ='EIA23 EQ Cost'!H53 -> 23 | H81: ='EIA23 EQ Cost'!J53 -> 2.0351224 | I81: ='EIA23 EQ Cost'!K53 -> 0.86 | J81: 1 | K81: 0.16 | L81: 0.16 | M81: 0.16 | N81: 0.16 | O81: 0.16 | Q81: 0.36 | BF81: R2,R3,R4,R5,R6
A82: ='EIA23 EQ Cost'!B54 -> RSHDRDV230 | B82: ='EIA23 EQ Cost'!C54 -> Distillate Radiant Ver2.RSH.DST.30 | C82: PJ | D82: RESDSLEA | E82: RSH | F82: ='EIA23 EQ Cost'!G54 -> 2030 | G82: ='EIA23 EQ Cost'!H54 -> 23 | H82: ='EIA23 EQ Cost'!J54 -> 2.1016055 | I82: ='EIA23 EQ Cost'!K54 -> 0.88 | J82: 1 | K82: 0.16 | L82: 0.16 | M82: 0.16 | N82: 0.16 | O82: 0.16 | Q82: 0.36 | BF82: R2,R3,R4,R5,R6
A83: ='EIA23 EQ Cost'!B55 -> *Fuel Oil (DSL) Furnaces | BF83: =A83 -> *Fuel Oil (DSL) Furnaces
A84: ='EIA23 EQ Cost'!B56 -> RSHDFRBS15 | B84: ='EIA23 EQ Cost'!C56 -> Distillate Furnace Base.RSH.DST.15 | C84: PJ | D84: RESDSLEA | E84: RSH | F84: ='EIA23 EQ Cost'!G56 -> 2015 | G84: ='EIA23 EQ Cost'!H56 -> 26.5 | H84: ='EIA23 EQ Cost'!J56 -> 2.4057043 | I84: ='EIA23 EQ Cost'!K56 -> 0.83 | J84: 1 | K84: 0.16 | L84: 0.16 | M84: 0.16 | N84: 0.16 | O84: 0.16 | Q84: 0.36 | T84: 0 | U84: 0 | V84: 0 | W84: 0 | X84: 0 | Y84: 0 | Z84: 0 | AA84: 0 | AO84: =Resid!V39 -> #REF! | AP84: =Resid!W39 -> #REF! | AQ84: =Resid!X39 -> #REF! | AR84: =Resid!Y39 -> #REF! | AS84: =Resid!Z39 -> #REF! | AT84: =AO84*0.9 -> #REF! | AU84: =AP84*0.9 -> #REF! | AV84: =AQ84*0.9 -> #REF! | AW84: =AR84*0.9 -> #REF! | AX84: =AS84*0.9 -> #REF! | BF84: R2,R3,R4,R5,R6
A85: ='EIA23 EQ Cost'!B57 -> RSHDFRBS20 | B85: ='EIA23 EQ Cost'!C57 -> Distillate Furnace Base.RSH.DST.20 | C85: PJ | D85: RESDSLEA | E85: RSH | F85: ='EIA23 EQ Cost'!G57 -> 2020 | G85: ='EIA23 EQ Cost'!H57 -> 26.5 | H85: ='EIA23 EQ Cost'!J57 -> 2.4057043 | I85: ='EIA23 EQ Cost'!K57 -> 0.83 | J85: 1 | K85: 0.16 | L85: 0.16 | M85: 0.16 | N85: 0.16 | O85: 0.16 | Q85: 0.36 | U85: 0 | V85: 0 | W85: 0 | X85: 0 | Y85: 0 | Z85: 0 | AA85: 0 | BF85: R2,R3,R4,R5,R6
A86: ='EIA23 EQ Cost'!B58 -> RSHDFRV122 | B86: ='EIA23 EQ Cost'!C58 -> Distillate Furnace Ver1.RSH.DST.22 | C86: PJ | D86: RESDSLEA | E86: RSH | F86: ='EIA23 EQ Cost'!G58 -> 2022 | G86: ='EIA23 EQ Cost'!H58 -> 26.5 | H86: ='EIA23 EQ Cost'!J58 -> 2.4057043 | I86: ='EIA23 EQ Cost'!K58 -> 0.83 | J86: 1 | K86: 0.16 | L86: 0.16 | M86: 0.16 | N86: 0.16 | O86: 0.16 | Q86: 0.36 | V86: 0 | W86: 0 | X86: 0 | Y86: 0 | Z86: 0 | AA86: 0 | BF86: R2,R3,R4,R5,R6
A87: ='EIA23 EQ Cost'!B59 -> RSHDFRV222 | B87: ='EIA23 EQ Cost'!C59 -> Distillate Furnace Ver2.RSH.DST.22 | C87: PJ | D87: RESDSLEA | E87: RSH | F87: ='EIA23 EQ Cost'!G59 -> 2022 | G87: ='EIA23 EQ Cost'!H59 -> 26.5 | H87: ='EIA23 EQ Cost'!J59 -> 2.5362082 | I87: ='EIA23 EQ Cost'!K59 -> 0.85 | J87: 1 | K87: 0.16 | L87: 0.16 | M87: 0.16 | N87: 0.16 | O87: 0.16 | Q87: 0.36 | V87: 0 | W87: 0 | X87: 0 | Y87: 0 | Z87: 0 | AA87: 0 | BF87: R2,R3,R4,R5,R6
A88: ='EIA23 EQ Cost'!B60 -> RSHDFRV322 | B88: ='EIA23 EQ Cost'!C60 -> Distillate Furnace Ver3.RSH.DST.22 | C88: PJ | D88: RESDSLEA | E88: RSH | F88: ='EIA23 EQ Cost'!G60 -> 2022 | G88: ='EIA23 EQ Cost'!H60 -> 26.5 | H88: ='EIA23 EQ Cost'!J60 -> 2.5362082 | I88: ='EIA23 EQ Cost'!K60 -> 0.85 | J88: 1 | K88: 0.16 | L88: 0.16 | M88: 0.16 | N88: 0.16 | O88: 0.16 | Q88: 0.36 | V88: 0 | W88: 0 | X88: 0 | Y88: 0 | Z88: 0 | AA88: 0 | BF88: R2,R3,R4,R5,R6
A89: ='EIA23 EQ Cost'!B61 -> RSHDFRV422 | B89: ='EIA23 EQ Cost'!C61 -> Distillate Furnace Ver4.RSH.DST.22 | C89: PJ | D89: RESDSLEA | E89: RSH | F89: ='EIA23 EQ Cost'!G61 -> 2022 | G89: ='EIA23 EQ Cost'!H61 -> 26.5 | H89: ='EIA23 EQ Cost'!J61 -> 3.7550655 | I89: ='EIA23 EQ Cost'!K61 -> 0.97 | J89: 1 | K89: 0.16 | L89: 0.16 | M89: 0.16 | N89: 0.16 | O89: 0.16 | Q89: 0.36 | V89: 0 | W89: 0 | X89: 0 | Y89: 0 | Z89: 0 | AA89: 0 | BF89: R2,R3,R4,R5,R6
A90: ='EIA23 EQ Cost'!B62 -> RSHDFRV130 | B90: ='EIA23 EQ Cost'!C62 -> Distillate Furnace Ver1.RSH.DST.30 | C90: PJ | D90: RESDSLEA | E90: RSH | F90: ='EIA23 EQ Cost'!G62 -> 2030 | G90: ='EIA23 EQ Cost'!H62 -> 26.5 | H90: ='EIA23 EQ Cost'!J62 -> 2.5362082 | I90: ='EIA23 EQ Cost'!K62 -> 0.85 | J90: 1 | K90: 0.16 | L90: 0.16 | M90: 0.16 | N90: 0.16 | O90: 0.16 | Q90: 0.36 | BF90: R2,R3,R4,R5,R6
A91: ='EIA23 EQ Cost'!B63 -> RSHDFRV230 | B91: ='EIA23 EQ Cost'!C63 -> Distillate Furnace Ver2.RSH.DST.30 | C91: PJ | D91: RESDSLEA | E91: RSH | F91: ='EIA23 EQ Cost'!G63 -> 2030 | G91: ='EIA23 EQ Cost'!H63 -> 26.5 | H91: ='EIA23 EQ Cost'!J63 -> 3.7550655 | I91: ='EIA23 EQ Cost'!K63 -> 0.97 | J91: 1 | K91: 0.16 | L91: 0.16 | M91: 0.16 | N91: 0.16 | O91: 0.16 | Q91: 0.36 | BF91: R2,R3,R4,R5,R6
A92: ='EIA23 EQ Cost'!B64 -> *Geothermal Heat Pumps | BF92: =A92 -> *Geothermal Heat Pumps
A93: ='EIA23 EQ Cost'!B65 -> RSCGHPBS15 | B93: ='EIA23 EQ Cost'!C65 -> Ground Source Heat Pump Base.RSC.ELC.15 | C93: PJ | D93: RESELC | F93: ='EIA23 EQ Cost'!G65 -> 2015 | G93: ='EIA23 EQ Cost'!H65 -> 14.5 | H93: ='EIA23 EQ Cost'!J65 -> 26.105913 | K93: =0.16*2 -> 0.32 | L93: =0.16*2 -> 0.32 | M93: =0.16*2 -> 0.32 | N93: =0.16*2 -> 0.32 | O93: =0.16*2 -> 0.32 | Q93: 0.36 | T93: 0 | U93: 0 | V93: 0 | W93: 0 | X93: 0 | Y93: 0 | Z93: 0 | AA93: 0 | BF93: R2,R3,R4,R5,R6
E94: RSH | J94: 0.75
E95: RSC | J95: 0.5
A96: ='EIA23 EQ Cost'!B66 -> RSCGHPBS20 | B96: ='EIA23 EQ Cost'!C66 -> Ground Source Heat Pump Base.RSC.ELC.20 | C96: PJ | D96: RESELC | F96: ='EIA23 EQ Cost'!G66 -> 2020 | G96: ='EIA23 EQ Cost'!H66 -> 14.5 | H96: ='EIA23 EQ Cost'!J66 -> 27.290913 | K96: =0.16*2 -> 0.32 | L96: =0.16*2 -> 0.32 | M96: =0.16*2 -> 0.32 | N96: =0.16*2 -> 0.32 | O96: =0.16*2 -> 0.32 | Q96: 0.36 | U96: 0 | V96: 0 | W96: 0 | X96: 0 | Y96: 0 | Z96: 0 | AA96: 0 | BF96: R2,R3,R4,R5,R6
E97: RSH | J97: 0.75
E98: RSC | J98: 0.5
A99: ='EIA23 EQ Cost'!B67 -> RSCGHPV122 | B99: ='EIA23 EQ Cost'!C67 -> Ground Source Heat Pump Ver1.RSC.ELC.22 | C99: PJ | D99: RESELC | F99: ='EIA23 EQ Cost'!G67 -> 2022 | G99: ='EIA23 EQ Cost'!H67 -> 14.5 | H99: ='EIA23 EQ Cost'!J67 -> 26.357277 | K99: =0.16*2 -> 0.32 | L99: =0.16*2 -> 0.32 | M99: =0.16*2 -> 0.32 | N99: =0.16*2 -> 0.32 | O99: =0.16*2 -> 0.32 | Q99: 0.36 | V99: 0 | W99: 0 | X99: 0 | Y99: 0 | Z99: 0 | AA99: 0 | BF99: R2,R3,R4,R5,R6
E100: RSH | J100: 0.75
E101: RSC | J101: 0.5
A102: ='EIA23 EQ Cost'!B68 -> RSCGHPV222 | B102: ='EIA23 EQ Cost'!C68 -> Ground Source Heat Pump Ver2.RSC.ELC.22 | C102: PJ | D102: RESELC | F102: ='EIA23 EQ Cost'!G68 -> 2022 | G102: ='EIA23 EQ Cost'!H68 -> 14.5 | H102: ='EIA23 EQ Cost'!J68 -> 27.290913 | K102: =0.16*2 -> 0.32 | L102: =0.16*2 -> 0.32 | M102: =0.16*2 -> 0.32 | N102: =0.16*2 -> 0.32 | O102: =0.16*2 -> 0.32 | Q102: 0.36 | V102: 0 | W102: 0 | X102: 0 | Y102: 0 | Z102: 0 | AA102: 0 | BF102: R2,R3,R4,R5,R6
E103: RSH | J103: 0.75
E104: RSC | J104: 0.5
...

Sheet TechData_SolarPV
A1: TechData | B1: _GLOBAL,R0,R1,R2,R3,R4,R5,R6
F4: ~FI_T
A5: Region | B5: TechName | C5: *TechDesc | D5: *Units | E5: CommIN | F5: CommOUT | G5: NCAP_START | H5: NCAP_TLIFE | I5: PRC_CAPACT | J5: EFF | K5: Peak | L5: NCAP_COST~2010 | M5: NCAP_COST~2015 | N5: NCAP_COST~2020 | O5: NCAP_COST~2025 | P5: NCAP_COST~2030 | Q5: NCAP_COST~2035 | R5: NCAP_COST~2040 | S5: NCAP_COST~2045 | T5: NCAP_COST~2050 | U5: NCAP_COST~2055 | V5: NCAP_FOM | W5: NCAP_AF~IDAM | X5: NCAP_AF~IDPM | Y5: *NCAP_AF~IP | Z5: NCAP_AF~IP | AA5: NCAP_AF~IN | AB5: NCAP_AF~SDAM | AC5: NCAP_AF~SDPM | AD5: *NCAP_AF~SP | AE5: NCAP_AF~SP | AF5: NCAP_AF~SN | AG5: NCAP_AF~WDAM | AH5: NCAP_AF~WDPM | AI5: *NCAP_AF~WP | AJ5: NCAP_AF~WP | AK5: NCAP_AF~WN | AL5: NCAP_DRATE | AN5: Input | AO5: Output | AQ5: ACT_BND~FX~2010 | AR5: ACT_BND~FX~2015 | AS5: ACT_BND~LO~2020 | AT5: ACT_BND~LO~2025 | AU5: ACT_BND~LO~2030 | AV5: ACT_BND~LO~2035 | AW5: ACT_BND~LO~2040 | AX5: ACT_BND~LO~2045 | AY5: ACT_BND~LO~2050 | AZ5: ACT_BND~LO~2055 | BA5: ACT_BND~UP~2020 | BB5: ACT_BND~UP~2025 | BC5: ACT_BND~UP~2030 | BD5: ACT_BND~UP~2035 | BE5: ACT_BND~UP~2040 | BF5: ACT_BND~UP~2045 | BG5: ACT_BND~UP~2050 | BH5: ACT_BND~UP~2055
A6: * Solar PV Technologies
A7: *R1 | B7: ="ESOLPVRES"&RIGHT(G7,2) -> ESOLPVRES11 | C7: Solar PV Distributed Residential Generation | E7: SOLRES | F7: RESELC | G7: 2011 | H7: 30 | I7: 31.536 | J7: =AO7/AN7 -> 0.34965035 | K7: 0.1 | L7: 6546.9995 | M7: 3903.1781 | N7: 3453.8021 | O7: 3004.4261 | P7: 2839.3022 | Q7: 2674.1784 | R7: 2596.418 | S7: 2558.6683 | T7: 2540.0679 | U7: 2530.8353 | V7: 10 | W7: 0 | X7: 0.31357247 | Y7: 0.31357247 | Z7: =Y7*0.2 -> 0.062714494 | AA7: 0 | AB7: 0.3060734 | AC7: 0.3060734 | AD7: 0.3060734 | AE7: =AD7*0.2 -> 0.061214679 | AF7: 0 | AG7: 0.3020009 | AH7: 0.3020009 | AI7: 0.3020009 | AJ7: =AI7*0.2 -> 0.06040018 | AK7: 0 | AL7: 0.15 | AN7: 2.86 | AO7: 1
A8: R2 | B8: ="ESOLPVRES"&RIGHT(G8,2) -> ESOLPVRES11 | C8: Solar PV Distributed Residential Generation | E8: SOLRES | F8: RESELC | G8: 2011 | H8: 30 | I8: 31.536 | J8: =AO8/AN8 -> 0.34965035 | K8: 0.1 | L8: 6546.9995 | M8: 3903.1781 | N8: 3453.8021 | O8: 3004.4261 | P8: 2839.3022 | Q8: 2674.1784 | R8: 2596.418 | S8: 2558.6683 | T8: 2540.0679 | U8: 2530.8353 | V8: 10 | W8: 0 | X8: 0.317351 | Y8: 0.317351 | Z8: =Y8*0.2 -> 0.0634702 | AA8: 0 | AB8: 0.30541737 | AC8: 0.30541737 | AD8: 0.30541737 | AE8: =AD8*0.2 -> 0.061083474 | AF8: 0 | AG8: 0.29271621 | AH8: 0.29271621 | AI8: 0.29271621 | AJ8: =AI8*0.2 -> 0.058543242 | AK8: 0 | AL8: 0.15 | AN8: 2.86 | AO8: 1 | AQ8: ='Rooftop Calc'!AC65 -> 0.0071945835 | AR8: ='Rooftop Calc'!AC71 -> 0.109328 | AS8: ='Rooftop Calc'!AC77 -> 0.24496493 | AT8: ='Rooftop Calc'!AC84 -> 0.43039234 | AU8: ='Rooftop Calc'!AC91 -> 0.61581975 | AV8: ='Rooftop Calc'!AC98 -> 0.80124716 | AW8: ='Rooftop Calc'!AC105 -> 0.98667458 | AX8: ='Rooftop Calc'!AC112 -> 1.1649074 | AY8: ='Rooftop Calc'!AC119 -> 1.2410068 | AZ8: ='Rooftop Calc'!AC126 -> 1.3072238 | BA8: ='Rooftop Calc'!AK77 -> 0.37640069 | BB8: ='Rooftop Calc'!AK84 -> 0.64269247 | BC8: ='Rooftop Calc'!AK91 -> 0.90976515 | BD8: ='Rooftop Calc'!AK98 -> 1.1760569 | BE8: ='Rooftop Calc'!AK105 -> 1.4431296 | BF8: ='Rooftop Calc'!AK112 -> 1.7094214 | BG8: ='Rooftop Calc'!AK119 -> 1.9764941 | BH8: ='Rooftop Calc'!AK126 -> 2.2427859
A9: R3 | B9: ="ESOLPVRES"&RIGHT(G9,2) -> ESOLPVRES11 | C9: Solar PV Distributed Residential Generation | E9: SOLRES | F9: RESELC | G9: 2011 | H9: 30 | I9: 31.536 | J9: =AO9/AN9 -> 0.34965035 | K9: 0.1 | L9: 6546.9995 | M9: 3903.1781 | N9: 3453.8021 | O9: 3004.4261 | P9: 2839.3022 | Q9: 2674.1784 | R9: 2596.418 | S9: 2558.6683 | T9: 2540.0679 | U9: 2530.8353 | V9: 10 | W9: 0 | X9: 0.29713464 | Y9: 0.29713464 | Z9: =Y9*0.2 -> 0.059426928 | AA9: 0 | AB9: 0.30672516 | AC9: 0.30672516 | AD9: 0.30672516 | AE9: =AD9*0.2 -> 0.061345033 | AF9: 0 | AG9: 0.26137287 | AH9: 0.26137287 | AI9: 0.26137287 | AJ9: =AI9*0.2 -> 0.052274574 | AK9: 0 | AL9: 0.15 | AN9: 2.86 | AO9: 1 | AQ9: ='Rooftop Calc'!AD65 -> 0.0037523355 | AR9: ='Rooftop Calc'!AD71 -> 0.073448493 | AS9: ='Rooftop Calc'!AD77 -> 0.13820064 | AT9: ='Rooftop Calc'!AD84 -> 0.20768834 | AU9: ='Rooftop Calc'!AD91 -> 0.27717603 | AV9: ='Rooftop Calc'!AD98 -> 0.34666373 | AW9: ='Rooftop Calc'!AD105 -> 0.41615142 | AX9: ='Rooftop Calc'!AD112 -> 0.48188678 | AY9: ='Rooftop Calc'!AD119 -> 0.47792598 | AZ9: ='Rooftop Calc'!AD126 -> 0.46631225 | BA9: ='Rooftop Calc'!AL77 -> 0.25287267 | BB9: ='Rooftop Calc'!AL84 -> 0.43177221 | BC9: ='Rooftop Calc'!AL91 -> 0.61119639 | BD9: ='Rooftop Calc'!AL98 -> 0.79009593 | BE9: ='Rooftop Calc'!AL105 -> 0.96952011 | BF9: ='Rooftop Calc'!AL112 -> 1.1484197 | BG9: ='Rooftop Calc'!AL119 -> 1.3278438 | BH9: ='Rooftop Calc'!AL126 -> 1.5067434
A10: R4 | B10: ="ESOLPVRES"&RIGHT(G10,2) -> ESOLPVRES11 | C10: Solar PV Distributed Residential Generation | E10: SOLRES | F10: RESELC | G10: 2011 | H10: 30 | I10: 31.536 | J10: =AO10/AN10 -> 0.34965035 | K10: 0.1 | L10: 6546.9995 | M10: 3903.1781 | N10: 3453.8021 | O10: 3004.4261 | P10: 2839.3022 | Q10: 2674.1784 | R10: 2596.418 | S10: 2558.6683 | T10: 2540.0679 | U10: 2530.8353 | V10: 10 | W10: 0 | X10: 0.33039362 | Y10: 0.33039362 | Z10: =Y10*0.2 -> 0.066078724 | AA10: 0 | AB10: 0.32440092 | AC10: 0.32440092 | AD10: 0.32440092 | AE10: =AD10*0.2 -> 0.064880183 | AF10: 0 | AG10: 0.34679382 | AH10: 0.34679382 | AI10: 0.34679382 | AJ10: =AI10*0.2 -> 0.069358764 | AK10: 0 | AL10: 0.15 | AN10: 2.86 | AO10: 1 | AQ10: ='Rooftop Calc'!AE65 -> 0.0011972254 | AR10: ='Rooftop Calc'!AE71 -> 0.0093117528 | AS10: ='Rooftop Calc'!AE77 -> 0.017877615 | AT10: ='Rooftop Calc'!AE84 -> 0.024528867 | AU10: ='Rooftop Calc'!AE91 -> 0.031180119 | AV10: ='Rooftop Calc'!AE98 -> 0.037831371 | AW10: ='Rooftop Calc'!AE105 -> 0.044482623 | AX10: ='Rooftop Calc'!AE112 -> 0.04993665 | AY10: ='Rooftop Calc'!AE119 -> 0.047276149 | AZ10: ='Rooftop Calc'!AE126 -> 0.042167162 | BA10: ='Rooftop Calc'!AM77 -> 0.032059035 | BB10: ='Rooftop Calc'!AM84 -> 0.054739804 | BC10: ='Rooftop Calc'!AM91 -> 0.077487086 | BD10: ='Rooftop Calc'!AM98 -> 0.10016786 | BE10: ='Rooftop Calc'!AM105 -> 0.12291514 | BF10: ='Rooftop Calc'!AM112 -> 0.14559591 | BG10: ='Rooftop Calc'!AM119 -> 0.16834319 | BH10: ='Rooftop Calc'!AM126 -> 0.19102396
A11: R5 | B11: ="ESOLPVRES"&RIGHT(G11,2) -> ESOLPVRES11 | C11: Solar PV Distributed Residential Generation | E11: SOLRES | F11: RESELC | G11: 2011 | H11: 30 | I11: 31.536 | J11: =AO11/AN11 -> 0.34965035 | K11: 0.1 | L11: 6546.9995 | M11: 3903.1781 | N11: 3453.8021 | O11: 3004.4261 | P11: 2839.3022 | Q11: 2674.1784 | R11: 2596.418 | S11: 2558.6683 | T11: 2540.0679 | U11: 2530.8353 | V11: 10 | W11: 0 | X11: 0.34379748 | Y11: 0.34379748 | Z11: =Y11*0.2 -> 0.068759495 | AA11: 0 | AB11: 0.29466039 | AC11: 0.29466039 | AD11: 0.29466039 | AE11: =AD11*0.2 -> 0.058932078 | AF11: 0 | AG11: 0.36077416 | AH11: 0.36077416 | AI11: 0.36077416 | AJ11: =AI11*0.2 -> 0.072154833 | AK11: 0 | AL11: 0.15 | AN11: 2.86 | AO11: 1 | AQ11: ='Rooftop Calc'!AF65 -> 0.0017437956 | AR11: ='Rooftop Calc'!AF71 -> 0.32034551 | AS11: ='Rooftop Calc'!AF77 -> 0.57042833 | AT11: ='Rooftop Calc'!AF84 -> 1.0833094 | AU11: ='Rooftop Calc'!AF91 -> 1.5961905 | AV11: ='Rooftop Calc'!AF98 -> 2.1090715 | AW11: ='Rooftop Calc'!AF105 -> 2.6219526 | AX11: ='Rooftop Calc'!AF112 -> 3.1330899 | AY11: ='Rooftop Calc'!AF119 -> 3.3256254 | AZ11: ='Rooftop Calc'!AF126 -> 3.7957449 | BA11: ='Rooftop Calc'!AN77 -> 1.1029038 | BB11: ='Rooftop Calc'!AN84 -> 1.883174 | BC11: ='Rooftop Calc'!AN91 -> 2.6657323 | BD11: ='Rooftop Calc'!AN98 -> 3.4460025 | BE11: ='Rooftop Calc'!AN105 -> 4.2285608 | BF11: ='Rooftop Calc'!AN112 -> 5.0088309 | BG11: ='Rooftop Calc'!AN119 -> 5.7913893 | BH11: ='Rooftop Calc'!AN126 -> 6.5716594
A12: R6 | B12: ="ESOLPVRES"&RIGHT(G12,2) -> ESOLPVRES11 | C12: Solar PV Distributed Residential Generation | E12: SOLRES | F12: RESELC | G12: 2011 | H12: 30 | I12: 31.536 | J12: =AO12/AN12 -> 0.34965035 | K12: 0.1 | L12: 6546.9995 | M12: 3903.1781 | N12: 3453.8021 | O12: 3004.4261 | P12: 2839.3022 | Q12: 2674.1784 | R12: 2596.418 | S12: 2558.6683 | T12: 2540.0679 | U12: 2530.8353 | V12: 10 | W12: 0 | X12: 0.34054374 | Y12: 0.34054374 | Z12: =Y12*0.2 -> 0.068108748 | AA12: 0 | AB12: 0.30737101 | AC12: 0.30737101 | AD12: 0.30737101 | AE12: =AD12*0.2 -> 0.061474202 | AF12: 0 | AG12: 0.32128124 | AH12: 0.32128124 | AI12: 0.32128124 | AJ12: =AI12*0.2 -> 0.064256247 | AK12: 0 | AL12: 0.15 | AN12: 2.86 | AO12: 1 | AQ12: ='Rooftop Calc'!AG65 -> 0.012993033 | AR12: ='Rooftop Calc'!AG71 -> 0.17523498 | AS12: ='Rooftop Calc'!AG77 -> 0.47194746 | AT12: ='Rooftop Calc'!AG84 -> 0.89934986 | AU12: ='Rooftop Calc'!AG91 -> 1.3267523 | AV12: ='Rooftop Calc'!AG98 -> 1.7541547 | AW12: ='Rooftop Calc'!AG105 -> 2.1815571 | AX12: ='Rooftop Calc'!AG112 -> 2.5959664 | AY12: ='Rooftop Calc'!AG119 -> 2.8481338 | AZ12: ='Rooftop Calc'!AG126 -> 3.138694 | BA12: ='Rooftop Calc'!AO77 -> 0.60330901 | BB12: ='Rooftop Calc'!AO84 -> 1.0301314 | BC12: ='Rooftop Calc'!AO91 -> 1.4582054 | BD12: ='Rooftop Calc'!AO98 -> 1.8850278 | BE12: ='Rooftop Calc'!AO105 -> 2.3131018 | BF12: ='Rooftop Calc'!AO112 -> 2.7399241 | BG12: ='Rooftop Calc'!AO119 -> 3.1679982 | BH12: ='Rooftop Calc'!AO126 -> 3.5948205
A13: * | AQ13: =SUM(AQ8:AQ12) -> 0.026880973 | AR13: =SUM(AR8:AR12) -> 0.68766875 | AS13: =SUM(AS8:AS12) -> 1.443419 | AT13: =SUM(AT8:AT12) -> 2.6452688 | AU13: =SUM(AU8:AU12) -> 3.8471186 | AV13: =SUM(AV8:AV12) -> 5.0489684 | AW13: =SUM(AW8:AW12) -> 6.2508183 | AX13: =SUM(AX8:AX12) -> 7.4257871 | ... BH13: =SUM(BH8:BH12) -> 14.107033
A14: *

Sheet TechData-Emis
A1: TechData | B1: _GLOBAL,R0,R1,R2,R3,R4,R5,R6
F4: FI_T
A5: Region | B5: TechName | C5: *TechDesc | D5: *Units | E5: CommIN | F5: CommOUT | G5: NCAP_START | H5: NCAP_LIFE | I5: EFF | J5: ENV_ACT~CO2~2010 | K5: ENV_ACT~CO2~2055 | L5: ENV_ACT~NOX~2010 | M5: ENV_ACT~NOX~2055 | N5: ENV_ACT~PM10~2010 | O5: ENV_ACT~PM10~2055 | P5: ENV_ACT~PM25~2010 | Q5: ENV_ACT~PM25~2055 | R5: ENV_ACT~VOC~2010 | S5: ENV_ACT~VOC~2055 | T5: ENV_ACT~CO~2010 | U5: ENV_ACT~CO~2055 | V5: ENV_ACT~CH4~2010 | W5: ENV_ACT~CH4~2055 | X5: ENV_ACT~N2O~2010 | Y5: ENV_ACT~N2O~2055 | Z5: ENV_ACT~BC~2010 | AA5: ENV_ACT~BC~2055 | AB5: ENV_ACT~OC~2010 | AC5: ENV_ACT~OC~2055 | AD5: ENV_ACT~SO2~2010 | AE5: ENV_ACT~SO2~2055 | AF5: ENV_ACT~CO2R | AG5: ENV_ACT~NOXR | AH5: ENV_ACT~PM10R | AI5: ENV_ACT~SO2R | AJ5: ENV_ACT~NOX2CR
A6: * Residential
A7: * | B7: SERESCOA | C7: Emissions: COA to RES | D7: PJ | E7: RESCOA | F7: RESCOAEA | G7: 2010 | H7: 55 | I7: 1 | J7: =EmisCO2Coef!D19 -> 0.10060378 | K7: =J7 -> 0.10060378
A8: R2,R3,R4,R5,R6 | B8: SERESNGA | C8: Emissions: NGA to RES | D8: PJ | E8: RESNGA | F8: RESNGAEA | G8: 2010 | H8: 55 | I8: 1 | J8: =EmisCO2Coef!D9 -> 0.055983606 | K8: =J8 -> 0.055983606 | L8: =EmisRes!H6 -> 0.039275865 | M8: =L8 -> 0.039275865 | N8: =EmisRes!I6 -> 0.00021727074 | O8: =N8 -> 0.00021727074 | P8: =EmisRes!J6 -> 0.00017966619 | Q8: =P8 -> 0.00017966619 | R8: =EmisRes!K6 -> 0.0022980559 | S8: =R8 -> 0.0022980559 | T8: =EmisRes!L6 -> 0.016713134 | U8: =T8 -> 0.016713134 | V8: =EmisRes!M6 -> 0.0047390856 | W8: =V8 -> 0.0047390856 | X8: =EmisRes!N6 -> 9.4781712e-05 | Y8: =X8 -> 9.4781712e-05 | Z8: =P8*#REF! -> #REF! | AA8: =Z8 -> #REF! | AB8: =R8*#REF! -> #REF! | AC8: =AB8 -> #REF! | AD8: =EmisRes!G6 -> 0.00025069701 | AE8: =AD8 -> 0.00025069701 | AF8: =J8*1000 -> 55.983606 | AG8: =L8 -> 0.039275865 | AH8: =N8 -> 0.00021727074 | AI8: =AD8 -> 0.00025069701 | AJ8: =AG8 -> 0.039275865
A9: * | B9: SERESBIO | C9: Emissions: BIO to RES | D9: PJ | E9: RESBIO | F9: RESBIOEA | G9: 2010 | H9: 55 | I9: 1 | L9: =EmisRes!H5 -> 0.12680826 | M9: =L9 -> 0.12680826 | N9: =EmisRes!I5 -> 0.70373709 | O9: =N9 -> 0.70373709 | P9: =EmisRes!J5 -> 0.6052139 | Q9: =P9 -> 0.6052139 | R9: =EmisRes!K5 -> 1.1519338 | S9: =R9 -> 1.1519338 | T9: =EmisRes!L5 -> 5.1881544 | U9: =T9 -> 5.1881544 | V9: =EmisRes!M5 -> 0.1872974 | W9: =V9 -> 0.1872974 | X9: =EmisRes!N5 -> 0.0039808319 | Y9: =X9 -> 0.0039808319 | Z9: =P9*#REF! -> #REF! | AA9: =Z9 -> #REF! | AB9: =R9*#REF! -> #REF! | AC9: =AB9 -> #REF! | AD9: =EmisRes!G5 -> 0.010748065 | AE9: =AD9 -> 0.010748065 | AF9: =J9*1000 -> 0 | AG9: =L9 -> 0.12680826 | AH9: =N9 -> 0.70373709 | AI9: =AD9 -> 0.010748065 | AJ9: =AG9 -> 0.12680826
A10: R2,R3,R4,R5,R6 | B10: SERESDSL | C10: Emissions: DSL to RES | D10: PJ | E10: RESDSL | F10: RESDSLEA | G10: 2010 | H10: 55 | I10: 1 | J10: =EmisCO2Coef!D10 -> 0.077180565 | K10: =J10 -> 0.077180565 | L10: =EmisRes!H7 -> 0.055800636 | M10: =L10 -> 0.055800636 | N10: =EmisRes!I7 -> 0.0073780841 | O10: =N10 -> 0.0073780841 | P10: =EmisRes!J7 -> 0.0066030752 | Q10: =P10 -> 0.0066030752 | R10: =EmisRes!K7 -> 0.0021700247 | S10: =R10 -> 0.0021700247 | T10: =EmisRes!L7 -> 0.015500177 | U10: =T10 -> 0.015500177 | V10: =EmisRes!M7 -> 0.0055180629 | W10: =V10 -> 0.0055180629 | X10: =EmisRes!N7 -> 0.00056869027 | Y10: =X10 -> 0.00056869027 | Z10: =P10*#REF! -> #REF! | AA10: =Z10 -> #REF! | AB10: =R10*#REF! -> #REF! | AC10: =AB10 -> #REF! | AD10: =EmisRes!G7 -> 0.1320615 | AE10: =AD10 -> 0.1320615 | AF10: =J10*1000 -> 77.180565 | AG10: =L10 -> 0.055800636 | AH10: =N10 -> 0.0073780841 | AI10: =AD10 -> 0.1320615 | AJ10: =AG10 -> 0.055800636
A11: * | B11: SERESKER | C11: Emissions: KER to RES | D11: PJ | E11: RESKER | F11: RESKEREA | G11: 2010 | H11: 55 | I11: 1 | J11: =EmisCO2Coef!D12 -> 0.076294281 | K11: =J11 -> 0.076294281 | L11: =EmisRes!H9 -> 0.05732605 | M11: =L11 -> 0.05732605 | N11: =EmisRes!I23 -> 0.0072612997 | O11: =N11 -> 0.0072612997 | P11: =EmisRes!J23 -> 0.0065288001 | Q11: =P11 -> 0.0065288001 | R11: =EmisRes!K23 -> 0.0021401725 | S11: =R11 -> 0.0021401725 | T11: =EmisRes!L23 -> 0.015923903 | U11: =T11 -> 0.015923903 | V11: =EmisRes!M23 -> 0.0056689094 | W11: =V11 -> 0.0056689094 | X11: =EmisRes!N23 -> 0.00056869027 | Y11: =X11 -> 0.00056869027 | Z11: =P11*#REF! -> #REF! | AA11: =Z11 -> #REF! | AB11: =R11*#REF! -> #REF! | AC11: =AB11 -> #REF! | AD11: =EmisRes!G23 -> 0.13567165 | AE11: =AD11 -> 0.13567165 | AF11: =J11*1000 -> 76.294281 | AG11: =L11 -> 0.05732605 | AH11: =N11 -> 0.0072612997 | AI11: =AD11 -> 0.13567165 | AJ11: =AG11 -> 0.05732605
A12: * | B12: SERESLPG | C12: Emissions: LPG to RES | D12: PJ | E12: RESLPG | F12: RESLPGEA | G12: 2010 | H12: 55 | I12: 1 | J12: =EmisCO2Coef!D13 -> 0.065711628 | K12: =J12 -> 0.065711628 | L12: =EmisRes!H8 -> 0.062863259 | M12: =L12 -> 0.062863259 | N12: =EmisRes!I22 -> 0.0002345644 | O12: =N12 -> 0.0002345644 | P12: =EmisRes!J22 -> 0.00018765152 | Q12: =P12 -> 0.00018765152 | R12: =EmisRes!K22 -> 0.0024394698 | S12: =R12 -> 0.0024394698 | T12: =EmisRes!L22 -> 0.017826894 | U12: =T12 -> 0.017826894 | V12: =EmisRes!M22 -> 0.010425988 | W12: =V12 -> 0.010425988 | X12: =EmisRes!N22 -> 0.00056869027 | Y12: =X12 -> 0.00056869027 | Z12: =P12*#REF! -> #REF! | AA12: =Z12 -> #REF! | AB12: =R12*#REF! -> #REF! | AC12: =AB12 -> #REF! | AD12: =EmisRes!G22 -> 0.00028147728 | AE12: =AD12 -> 0.00028147728 | AF12: =J12*1000 -> 65.711628 | AG12: =L12 -> 0.062863259 | AH12: =N12 -> 0.0002345644 | AI12: =AD12 -> 0.00028147728 | AJ12: =AG12 -> 0.062863259
A13: * Industrial

Sheet TechData_ZZ
A1: TechData | B1: _GLOBAL,R0,R1,R2,R3,R4,R5,R6
F4: FI_T
A5: Region | B5: TechName | C5: *TechDesc | D5: *Units | E5: CommIN | F5: CommOUT | G5: EFF | H5: ACT_COST
A6: * ZZ<dm>INFES Backstop Technologies
A7: R2,R3,R4,R5,R6 | B7: ZZRLT | C7: Residential Lighting - ZZINFES backstop | D7: PJ | E7: ZZDMY | F7: RLT | G7: 1 | H7: 9999
A8: *R2,R3,R4,R5,R6 | B8: ZZRFZ | C8: Residential Freezing - ZZINFES backstop | D8: PJ | E8: ZZDMY | F8: RFZ | G8: 1 | H8: 9999
A9: *R2,R3,R4,R5,R6 | B9: ZZRRF | C9: Residential Refrigeration - ZZINFES backstop | D9: PJ | E9: ZZDMY | F9: RRF | G9: 1 | H9: 9999
A10: R2,R3,R4,R5,R6 | B10: ZZRSC | C10: Residential Cooling - ZZINFES backstop | D10: PJ | E10: ZZDMY | F10: RSC | G10: 1 | H10: 9999
A11: *R2,R3,R4,R5,R6 | B11: ZZRSH | C11: Residential Heating - ZZINFES backstop | D11: PJ | E11: ZZDMY | F11: RSH | G11: 1 | H11: 9999
A12: R2,R3,R4,R5,R6 | B12: ZZRWH | C12: Residential Water Heating - ZZINFES backstop | D12: PJ | E12: ZZDMY | F12: RWH | G12: 1 | H12: 9999
A13: *
A14: * Dummy and Backstop Water Technologies
A15: *
A16: R2,R3,R4,R5,R6 | B16: ZZDMYRBLD | C16: Dummy RES Building to meet POPDM | D16: Mt, Mt/a | E16: ZZDMYH2O | F16: POPDMRES | G16: 1 | H16: 999999
A17: R2,R3,R4,R5,R6 | B17: ZZDMYRRFDM | C17: Dummy technology to meet RWROOFDM | D17: Mt, Mt/a | E17: ZZDMYH2O | F17: RWROOFDM | G17: 1 | H17: 999999
A18: *

Sheet TechData_SESC
A1: TechData | B1: _GLOBAL,R0,R1,R2,R3,R4,R5,R6
F4: FI_T
A5: Region | B5: TechName | C5: *TechDesc | D5: *Units | E5: CommIN | F5: CommOUT | G5: NCAP_START | H5: NCAP_TLIFE | I5: EFF | J5: Share~UP | K5: Share~UP | L5: Peak | M5: NCAP_AF | N5: PRC_CAPACT | O5: NCAP_COST | Q5: Input | R5: Output | S5: Input | T5: Output
A6: * Collectors
A7: * Emissions Accounting
A8: R2,R3,R4,R5,R6 | B8: SCRESELC | C8: Collector: ELC to RES | D8: PJ | E8: ELC | F8: RESELC | G8: 2010 | I8: =T8/S8 -> 1 | L8: 1 | M8: 1 | N8: 1 | S8: 1 | T8: 1
A9: *
A10: * Building Retrofit Collectors
A11: R2,R3,R4,R5,R6 | B11: XELCRBLD | C11: Collects ELC for use in buildings | D11: PJ | E11: RESELC | F11: RESELCBLD | G11: 2010 | I11: =T11/S11 -> 1 | L11: 1 | M11: 1 | N11: 1 | O11: 0 | S11: 1 | T11: 1
A12: R2,R3,R4,R5,R6 | B12: XNGARBLD | C12: Collects NGA for use in buildings | D12: PJ | E12: RESNGAEA | F12: RESNGABLD | G12: 2010 | M12: 1 | N12: 1 | O12: 0 | Q12: 1 | R12: 1
A13: *R2,R3,R4,R5,R6 | B13: XRFLRBLD | C13: Collects RFL for use in buildings | D13: PJ | E13: RESRFLEA | F13: RESRFLBLD | G13: 2010 | M13: 1 | N13: 1 | O13: 0 | Q13: 1 | R13: 1
A14: R2,R3,R4,R5,R6 | B14: XDSLRBLD | C14: Collects DSL for use in buildings | D14: PJ | E14: RESDSLEA | F14: RESDSLBLD | G14: 2010 | M14: 1 | N14: 1 | O14: 0 | Q14: 1 | R14: 1
A15: R2,R3,R4,R5,R6 | B15: RELCHE | C15: High efficiency building ELC without retrofits | D15: PJ | E15: RESELCBLD | F15: RESELCRB | G15: 2010 | I15: =T15/S15 -> 1 | L15: 1 | M15: 1 | N15: 1 | O15: 0 | S15: 1 | T15: 1
A16: R2,R3,R4,R5,R6 | B16: RBLDBAUHE | C16: High efficiency building energy without retrofits | D16: PJ | E16: RESNGABLD | G16: 2010 | I16: =SUM(R19,R20,R21)/SUM(Q16,Q17,Q18) -> 1 | J16: =Q16/SUM(Q16,Q17,Q18) -> 0.33333333 | M16: 1 | N16: 1 | O16: 0 | Q16: 1
E17: RESDSLBLD | J17: =Q17/SUM(Q16,Q17,Q18) -> 0.33333333 | Q17: 1
A18: * | E18: RESRFLBLD | J18: =Q18/SUM(Q16,Q17,Q18) -> 0.33333333 | Q18: 1
F19: RESNGARB | K19: =R19/SUM(R19,R20,R21) -> 0.33333333 | R19: 1
F20: RESDSLRB | K20: =R20/SUM(R19,R20,R21) -> 0.33333333 | R20: 1
A21: * | F21: RESRFLRB | K21: =R21/SUM(R19,R20,R21) -> 0.33333333 | R21: 1
A22: R2,R3,R4,R5,R6 | B22: RELCBAU | C22: Building ELC without retrofits | D22: PJ | E22: RESELCBLD | F22: RESELCRM | G22: 2010 | I22: =T22/S22 -> 1 | L22: 1 | M22: 1 | N22: 1 | O22: 0 | S22: 1 | T22: 1
A23: R2,R3,R4,R5,R6 | B23: RBLDBAU | C23: Building energy without retrofits | D23: PJ | E23: RESNGABLD | G23: 2010 | I23: =SUM(R26,R27,R28)/SUM(Q23,Q24,Q25) -> 1 | J23: =Q23/SUM(Q23,Q24,Q25) -> 0.33333333 | M23: 1 | N23: 1 | O23: 0 | Q23: 1
E24: RESDSLBLD | J24: =Q24/SUM(Q23,Q24,Q25) -> 0.33333333 | Q24: 1
A25: * | E25: RESRFLBLD | J25: =Q25/SUM(Q23,Q24,Q25) -> 0.33333333 | Q25: 1
F26: RESNGARM | K26: =R26/SUM(R26,R27,R28) -> 0.33333333 | R26: 1
F27: RESDSLRM | K27: =R27/SUM(R26,R27,R28) -> 0.33333333 | R27: 1
A28: * | F28: RESRFLRM | K28: =R28/SUM(R26,R27,R28) -> 0.33333333 | R28: 1
A29: R2,R3,R4,R5,R6 | B29: RELCR10 | C29: Building ELC retrofit for 10% energy reduction | D29: PJ | E29: RESELCBLD | F29: RESELCRB | G29: 2015 | I29: =T29/S29 -> 1 | L29: 1 | M29: 1 | N29: 1 | O29: 0.25 | S29: 1 | T29: 1
A30: R2,R3,R4,R5,R6 | B30: RBLDR10 | C30: Building retrofit for 10% energy reduction | D30: PJ | E30: RESNGABLD | G30: 2015 | I30: =SUM(R33,R34,R35)/SUM(Q30,Q31,Q32) -> 1.1 | J30: =Q30/SUM(Q30,Q31,Q32) -> 0.33333333 | M30: 1 | N30: 1 | O30: 0.25 | Q30: 1
E31: RESDSLBLD | J31: =Q31/SUM(Q30,Q31,Q32) -> 0.33333333 | Q31: 1
A32: * | E32: RESRFLBLD | J32: =Q32/SUM(Q30,Q31,Q32) -> 0.33333333 | Q32: 1
F33: RESNGARB | K33: =R33/SUM(R33,R34,R35) -> 0.33333333 | R33: 1.1
F34: RESDSLRB | K34: =R34/SUM(R33,R34,R35) -> 0.33333333 | R34: 1.1
A35: * | F35: RESRFLRB | K35: =R35/SUM(R33,R34,R35) -> 0.33333333 | R35: 1.1
A36: R2,R3,R4,R5,R6 | B36: RELCR25 | C36: Building ELC retrofit for 25% energy reduction | D36: PJ | E36: RESELCBLD | F36: RESELCRM | G36: 2020 | I36: =T36/S36 -> 1 | L36: 1 | M36: 1 | N36: 1 | O36: 0.5 | S36: 1 | T36: 1
A37: R2,R3,R4,R5,R6 | B37: RBLDR25 | C37: Building retrofit for 25% energy reduction | D37: PJ | E37: RESNGABLD | G37: 2020 | I37: =SUM(R40,R41,R42)/SUM(Q37,Q38,Q39) -> 1.25 | J37: =Q37/SUM(Q37,Q38,Q39) -> 0.33333333 | M37: 1 | N37: 1 | O37: 0.5 | Q37: 1
E38: RESDSLBLD | J38: =Q38/SUM(Q37,Q38,Q39) -> 0.33333333 | Q38: 1
A39: * | E39: RESRFLBLD | J39: =Q39/SUM(Q37,Q38,Q39) -> 0.33333333 | Q39: 1
F40: RESNGARM | K40: =R40/SUM(R40,R41,R42) -> 0.33333333 | R40: 1.25
F41: RESDSLRM | K41: =R41/SUM(R40,R41,R42) -> 0.33333333 | R41: 1.25
A42: * | F42: RESRFLRM | K42: =R42/SUM(R40,R41,R42) -> 0.33333333 | R42: 1.25
A43: R2,R3,R4,R5,R6 | B43: RELCR50 | C43: Building ELC retrofit for 50% energy reduction | D43: PJ | E43: RESELCBLD | F43: RESELCRM | G43: 2025 | I43: =T43/S43 -> 1 | L43: 1 | M43: 1 | N43: 1 | O43: 1 | S43: 1 | T43: 1
A44: R2,R3,R4,R5,R6 | B44: RBLDR50 | C44: Building retrofit for 50% energy reduction | D44: PJ | E44: RESNGABLD | G44: 2025 | I44: =SUM(R47,R48,R49)/SUM(Q44,Q45,Q46) -> 1.5 | J44: =Q44/SUM(Q44,Q45,Q46) -> 0.33333333 | M44: 1 | N44: 1 | O44: 1 | Q44: 1
E45: RESDSLBLD | J45: =Q45/SUM(Q44,Q45,Q46) -> 0.33333333 | Q45: 1
A46: * | E46: RESRFLBLD | J46: =Q46/SUM(Q44,Q45,Q46) -> 0.33333333 | Q46: 1
F47: RESNGARM | K47: =R47/SUM(R47,R48,R49) -> 0.33333333 | R47: 1.5
F48: RESDSLRM | K48: =R48/SUM(R47,R48,R49) -> 0.33333333 | R48: 1.5
A49: * | F49: RESRFLRM | K49: =R49/SUM(R47,R48,R49) -> 0.33333333 | R49: 1.5

Sheet Retrofit
B2: Measure No. | C2: Name | D2: Energy Demand Reduction (% kBtu/sqft) | E2: Cost per Sqft | F2: % of Residential Area Eligible | G2: Cost Calculation | H2: Restriction Calculation
B3: 1 | C3: Insulation – walls | D3: 0.1 | E3: 65.19 | F3: 0.267 | G3: $41.75 per square foot wall area; wall area calculated as average perimeter area times height in eligible single-family homes | H3: Only single-family homes built before 2005
B4: 2 | C4: Ventilation overhaul | D4: 0.03 | E4: 1 | F4: 0.482 | G4: $1 per sqft | H4: Only homes built after 1945
B5: 3 | C5: Smart thermostats | D5: 0.08 | E5: 0.52 | F5: 0.948 | G5: $500 / apartment (average size 962 sqft) | H5: All homes except steam-heated
B6: 4 | C6: Insulation – roof | D6: 0.05 | E6: 1.5 | F6: 0.897 | G6: $13 / roof area (90% of footprint); foot print is 0.129 of total area | H6: Only homes built before 2005
B7: 5 | C7: Window replacement | D7: 0.08 | E7: 5 | F7: 0.897 | G7: Cost given | H7: Only homes built before 2005
C10: 2005 Building eff (Btu / sqft )
C11: Brooklyn | D11: Bronx | E11: Manhattan | F11: Queens | G11: Staten Island | H11: NYC | K11: 2005 | L11: 2010 | M11: 2015 | N11: 2020 | O11: 2025 | P11: 2030 | Q11: 2035 | R11: 2040 | S11: 2045 | T11: 2050 | U11: 2055
C12: 51602.374 | D12: 55661.045 | E12: 62470.873 | F12: 32617.14 | G12: 56174.924 | H12: 50587.643 | J12: % of new build | K12: 0 | L12: 0.028275072 | M12: 0.055803665 | N12: 0.080498063 | O12: 0.09788161 | P12: 0.11446455 | Q12: 0.13106521 | R12: 0.14813324 | S12: 0.16193016 | T12: 0.1770404 | U12: 0.1916742
C14: Cost per Btu (M $ 2010 / PJa)
C15: Brooklyn | D15: Bronx | E15: Manhattan | F15: Queens | G15: Staten Island | H15: NYC | J15: Max penetration (% Btu) | K15: 2005 | L15: 2010 | M15: 2015 | N15: 2020 | O15: 2025 | P15: 2030 | Q15: 2035 | R15: 2040 | S15: 2045 | T15: 2050 | U15: 2055
B16: Smart thermostats | C16: =$E5/C$12/$U$28/$C$31*10^-6 -> 7.0017166 | D16: =$E5/D$12/$U$28/$C$31*10^-6 -> 6.4911681 | E16: =$E5/E$12/$U$28/$C$31*10^-6 -> 5.7835785 | F16: =$E5/F$12/$U$28/$C$31*10^-6 -> 11.077158 | G16: =$E5/G$12/$U$28/$C$31*10^-6 -> 6.431788 | H16: =$E5/H$12/$U$28/$C$31*10^-6 -> 7.1421631 | J16: Smart thermostats | K16: =$D$5*$F$5*(1-K$12) -> 0.07584 | L16: =$D$5*$F$5*(1-L$12) -> 0.073695619 | M16: =$D$5*$F$5*(1-M$12) -> 0.07160785 | N16: =$D$5*$F$5*(1-N$12) -> 0.069735027 | O16: =$D$5*$F$5*(1-O$12) -> 0.068416659 | P16: =$D$5*$F$5*(1-P$12) -> 0.067159008 | Q16: =$D$5*$F$5*(1-Q$12) -> 0.065900015 | R16: =$D$5*$F$5*(1-R$12) -> 0.064605575 | ... U16: =$D$5*$F$5*(1-U$12) -> 0.061303428
B17: Ventilation overhaul | C17: =$E4/C$12/$U$28/$C$31*10^-6 -> 13.46484 | D17: =$E4/D$12/$U$28/$C$31*10^-6 -> 12.483016 | E17: =$E4/E$12/$U$28/$C$31*10^-6 -> 11.122266 | F17: =$E4/F$12/$U$28/$C$31*10^-6 -> 21.302226 | G17: =$E4/G$12/$U$28/$C$31*10^-6 -> 12.368823 | H17: =$E4/H$12/$U$28/$C$31*10^-6 -> 13.734929 | J17: Ventilation overhaul | K17: =$D$4*$F$4*(1-K$12) -> 0.01446 | L17: =$D$4*$F$4*(1-L$12) -> 0.014051142 | M17: =$D$4*$F$4*(1-M$12) -> 0.013653079 | N17: =$D$4*$F$4*(1-N$12) -> 0.013295998 | O17: =$D$4*$F$4*(1-O$12) -> 0.013044632 | P17: =$D$4*$F$4*(1-P$12) -> 0.012804843 | Q17: =$D$4*$F$4*(1-Q$12) -> 0.012564797 | R17: =$D$4*$F$4*(1-R$12) -> 0.012317993 | ... U17: =$D$4*$F$4*(1-U$12) -> 0.011688391
B18: Insulation – roof | C18: =$E6/C$12/$U$28/$C$31*10^-6 -> 20.197259 | D18: =$E6/D$12/$U$28/$C$31*10^-6 -> 18.724523 | E18: =$E6/E$12/$U$28/$C$31*10^-6 -> 16.6834 | F18: =$E6/F$12/$U$28/$C$31*10^-6 -> 31.953339 | G18: =$E6/G$12/$U$28/$C$31*10^-6 -> 18.553234 | H18: =$E6/H$12/$U$28/$C$31*10^-6 -> 20.602393 | J18: Insulation – roof | K18: =$D$3*$F$3*(1-K$12) -> 0.0267 | L18: =$D$3*$F$3*(1-L$12) -> 0.025945056 | M18: =$D$3*$F$3*(1-M$12) -> 0.025210042 | N18: =$D$3*$F$3*(1-N$12) -> 0.024550702 | O18: =$D$3*$F$3*(1-O$12) -> 0.024086561 | P18: =$D$3*$F$3*(1-P$12) -> 0.023643796 | Q18: =$D$3*$F$3*(1-Q$12) -> 0.023200559 | R18: =$D$3*$F$3*(1-R$12) -> 0.022744842 | ... U18: =$D$3*$F$3*(1-U$12) -> 0.021582299
B19: Window replacement | C19: =$E7/C$12/$U$28/$C$31*10^-6 -> 67.324198 | D19: =$E7/D$12/$U$28/$C$31*10^-6 -> 62.415078 | E19: =$E7/E$12/$U$28/$C$31*10^-6 -> 55.611332 | F19: =$E7/F$12/$U$28/$C$31*10^-6 -> 106.51113 | G19: =$E7/G$12/$U$28/$C$31*10^-6 -> 61.844115 | H19: =$E7/H$12/$U$28/$C$31*10^-6 -> 68.674645 | J19: Window replacement | K19: =$D$7*$F$7*(1-K$12) -> 0.07176 | L19: =$D$7*$F$7*(1-L$12) -> 0.069730981 | M19: =$D$7*$F$7*(1-M$12) -> 0.067755529 | N19: =$D$7*$F$7*(1-N$12) -> 0.065983459 | O19: =$D$7*$F$7*(1-O$12) -> 0.064736016 | P19: =$D$7*$F$7*(1-P$12) -> 0.063546024 | Q19: =$D$7*$F$7*(1-Q$12) -> 0.062354761 | R19: =$D$7*$F$7*(1-R$12) -> 0.061129958 | ... U19: =$D$7*$F$7*(1-U$12) -> 0.058005459
B20: Insulation – walls | C20: =$E3/C$12/$U$28/$C$31*10^-6 -> 877.77289 | D20: =$E3/D$12/$U$28/$C$31*10^-6 -> 813.76779 | E20: =$E3/E$12/$U$28/$C$31*10^-6 -> 725.06054 | F20: =$E3/F$12/$U$28/$C$31*10^-6 -> 1388.6921 | G20: =$E3/G$12/$U$28/$C$31*10^-6 -> 806.32357 | H20: =$E3/H$12/$U$28/$C$31*10^-6 -> 895.38002 | J20: Insulation – walls | K20: =$D$6*$F$6*(1-K$12) -> 0.04485 | L20: =$D$6*$F$6*(1-L$12) -> 0.043581863 | M20: =$D$6*$F$6*(1-M$12) -> 0.042347206 | N20: =$D$6*$F$6*(1-N$12) -> 0.041239662 | O20: =$D$6*$F$6*(1-O$12) -> 0.04046001 | P20: =$D$6*$F$6*(1-P$12) -> 0.039716265 | Q20: =$D$6*$F$6*(1-Q$12) -> 0.038971725 | R20: =$D$6*$F$6*(1-R$12) -> 0.038206224 | ... U20: =$D$6*$F$6*(1-U$12) -> 0.036253412
B25: https://fred.stlouisfed.org/series/FPCPITOTLZGUSA
C26: 2005 | D26: 2006 | E26: 2007 | F26: 2008 | G26: 2009 | H26: 2010 | I26: 2011 | J26: 2012 | K26: 2013 | L26: 2014 | M26: 2015 | N26: 2016 | O26: 2017 | P26: 2018 | Q26: 2019 | R26: 2020 | S26: 2021 | T26: 2022 | U26: 2023
B27: Inflation | C27: 0.033927468 | D27: 0.032259441 | E27: 0.028526725 | F27: 0.038391003 | G27: -0.0035554627 | H27: 0.016400434 | I27: 0.031568416 | J27: 0.020693373 | K27: 0.014648327 | L27: 0.01622223 | M27: 0.0011862714 | N27: 0.012615832 | O27: 0.0213011 | P27: 0.024425833 | Q27: 0.018122101 | R27: 0.012335844 | S27: 0.046978589 | T27: 0.080027998 | U27: 0
B28: Cumulated ref 2010 | C28: 1.1358175 | D28: 1.0985466 | E28: 1.0642156 | F28: 1.034699 | G28: 0.99644454 | H28: 1 | I28: 1.0164004 | J28: 1.0484866 | K28: 1.0701833 | L28: 1.0858597 | M28: 1.1034748 | N28: 1.1047838 | O28: 1.1187216 | P28: 1.1425516 | Q28: 1.1704593 | R28: 1.1916705 | S28: 1.2063708 | T28: 1.2630444 | U28: 1.3641233
B31: Btu to PJ | C31: 1.055056e-12

Sheet EIA23 EQ Cost
A1: See 2023_COMET_Residential_Cost_Data for details
G3: START | H3: LIFE | I3: CAPITAL COST update wrt EIA | J3: INVCOST | K3: EFF | L3: Capacity | M3: CF
I4: 2005$/unit | L4: btu/hr
B5: TechName | C5: TechDesc | D5: Units | E5: CommIN | F5: CommOUT | G5: TID | H5: TID
A6: *Space Heating
A7: *Electric Radiant Heating | B7: =A7 -> *Electric Radiant Heating
A8: R2,R3,R4,R5,R6 | B8: RSHERDBS10 | C8: Electric Radiant Base.RSH.ELC.10 | D8: PJ | E8: RESELC | F8: RSH | G8: 2011 | H8: 22.5 | I8: 162.45802 | J8: 3.74 | K8: 1
A9: R2,R3,R4,R5,R6 | B9: RSHERUV115 | C9: Electric Resistance Unit Heater Ver1.RSH.ELC.15 | D9: PJ | E9: RESELC | F9: RSH | G9: 2015 | H9: 22.5 | I9: 162.45802 | J9: 3.4718966 | K9: 1 | L9: 3500
A10: R2,R3,R4,R5,R6 | B10: RSHERUV120 | C10: Electric Resistance Unit Heater Ver1.RSH.ELC.20 | D10: PJ | E10: RESELC | F10: RSH | G10: 2020 | H10: 22.5 | I10: 162.45802 | J10: 3.4718966 | K10: 1 | L10: 3500
A11: R2,R3,R4,R5,R6 | B11: RSHERUV122 | C11: Electric Resistance Unit Heater Ver1.RSH.ELC.22 | D11: PJ | E11: RESELC | F11: RSH | G11: 2022 | H11: 22.5 | I11: 546.13547 | J11: 8.0098408 | K11: 1 | L11: 5100
A12: *Electric Furnaces | B12: =A12 -> *Electric Furnaces
A13: R2,R3,R4,R5,R6 | B13: RSHEFRV115 | C13: Electric Furnace Ver1.RSH.ELC.15 | D13: Electric Furnace Ver1.RSH.ELC.15 | E13: RESELC | F13: RSH | G13: 2015 | H13: 22.5 | I13: 891.79083 | J13: 0.98095202 | K13: 0.98 | L13: 68000 | M13: 0.16
A14: R2,R3,R4,R5,R6 | B14: RSHEFRV120 | C14: Electric Furnace Ver1.RSH.ELC.20 | D14: Electric Furnace Ver1.RSH.ELC.20 | E14: RESELC | F14: RSH | G14: 2020 | H14: 22.5 | I14: 891.79083 | J14: 0.98095202 | K14: 0.98 | L14: 68000 | M14: 0.16
A15: R2,R3,R4,R5,R6 | B15: RSHEFRV122 | C15: Electric Furnace Ver1.RSH.ELC.22 | D15: Electric Furnace Ver1.RSH.ELC.22 | E15: RESELC | F15: RSH | G15: 2022 | H15: 22.5 | I15: 1023.1399 | J15: 1.1254333 | K15: 1 | L15: 68000 | M15: 0.16
A16: *Electric Heat Pumps (Residential Air Source Heat Pumps) | B16: =A16 -> *Electric Heat Pumps (Residential Air Source Heat Pumps)
A17: R2,R3,R4,R5,R6 | B17: RSHEHPBS15 | C17: Electric Heat Pump Base.RSH.ELC.15 | D17: PJ | E17: RESELC | F17: RSH | G17: 2015 | H17: 15.5 | I17: 4002.6891 | J17: 8.3165467 | K17: 6.7 | L17: 36000 | M17: 0.15
A18: R2,R3,R4,R5,R6 | B18: RSHEHPB120 | C18: Electric Heat Pump Base.RSH.ELC.20 | D18: PJ | E18: RESELC | F18: RSH | G18: 2020 | H18: 15.5 | I18: 4756.2178 | J18: 9.8821833 | K18: 7.3 | L18: 36000 | M18: 0.15
A19: R2,R3,R4,R5,R6 | B19: RSHEHPBS22 | C19: Electric Heat Pump Base.RSH.ELC.22 | D19: PJ | E19: RESELC | F19: RSH | G19: 2022 | H19: 15.5 | I19: 4756.2178 | J19: 9.8821833 | K19: 7.3 | L19: 36000 | M19: 0.15
A20: R2,R3,R4,R5,R6 | B20: RSHEHPV122 | C20: Electric Heat Pump Ver1.RSH.ELC.22 | D20: PJ | E20: RESELC | F20: RSH | G20: 2022 | H20: 15.5 | I20: 5959.0984 | J20: 12.381456 | K20: 10.6 | L20: 36000 | M20: 0.15
A21: R2,R3,R4,R5,R6 | B21: RSHEHPV123 | C21: Electric Heat Pump Ver1.RSH.ELC.23 | D21: PJ | E21: RESELC | F21: RSH | G21: 2023 | H21: 15.5 | I21: 4707.826 | J21: 9.7816379 | K21: 7.5 | L21: 36000 | M21: 0.15
A22: R2,R3,R4,R5,R6 | B22: RSHEHPV223 | C22: Electric Heat Pump Ver2.RSH.ELC.23 | D22: PJ | E22: RESELC | F22: RSH | G22: 2023 | H22: 15.5 | I22: 4797.6964 | J22: 9.9683652 | K22: 8.1 | L22: 36000
A23: R2,R3,R4,R5,R6 | B23: RSHEHPV323 | C23: Electric Heat Pump Ver3.RSH.ELC.23 | D23: PJ | E23: RESELC | F23: RSH | G23: 2023 | H23: 15.5 | I23: 5959.0984 | J23: 12.381456 | K23: 10.6 | L23: 36000 | M23: 0.15
A24: R2,R3,R4,R5,R6 | B24: RSHEHPV130 | C24: Electric Heat Pump Ver1.RSH.ELC.30 | D24: PJ | E24: RESELC | F24: RSH | G24: 2030 | H24: 15.5 | I24: 4797.6964 | J24: 9.9683652 | K24: 7.8 | L24: 36000
A25: R2,R3,R4,R5,R6 | B25: RSHEHPV230 | C25: Electric Heat Pump Ver2.RSH.ELC.30 | D25: PJ | E25: RESELC | F25: RSH | G25: 2030 | H25: 15.5 | I25: 5959.0984 | J25: 12.381456 | K25: 10.6 | L25: 36000 | M25: 0.15
A26: R2,R3,R4,R5,R6 | B26: RSHEHPV140 | C26: Electric Heat Pump Ver1.RSH.ELC.40 | D26: PJ | E26: RESELC | F26: RSH | G26: 2040 | H26: 15.5 | I26: 5005.0896 | J26: 10.399274 | K26: 7.9 | L26: 36000 | M26: 0.15
A27: R2,R3,R4,R5,R6 | B27: RSHEHPV240 | C27: Electric Heat Pump Ver2.RSH.ELC.40 | D27: PJ | E27: RESELC | F27: RSH | G27: 2040 | H27: 15.5 | I27: 5959.0984 | J27: 12.381456 | K27: 10.6 | L27: 36000 | M27: 0.15
A28: R2,R3,R4,R5,R6 | B28: RSHEHPV150 | C28: Electric Heat Pump Ver1.RSH.ELC.50 | D28: PJ | E28: RESELC | F28: RSH | G28: 2050 | H28: 15.5 | I28: 5067.3076 | J28: 10.528547 | K28: 7.9 | L28: 36000 | M28: 0.15
A29: R2,R3,R4,R5,R6 | B29: RSHEHPV250 | C29: Electric Heat Pump Ver2.RSH.ELC.50 | D29: PJ | E29: RESELC | F29: RSH | G29: 2050 | H29: 15.5 | I29: 5959.0984 | J29: 12.381456 | K29: 10.6 | L29: 36000
A30: *Natural Gas Furnaces (Residential Gas-Fired Furnaces - North) | B30: =A30 -> *Natural Gas Furnaces (Residential Gas-Fired Furnaces - North)
A31: R2,R3,R4,R5,R6 | B31: RSHNFRBS15 | C31: Natural Gas Furnace Base.RSH.NGA.15 | D31: PJ | E31: RESNGAEA | F31: RSH | G31: 2015 | H31: 21.5 | I31: 1990.9749 | J31: 1.8615276 | K31: 0.8 | L31: 80000
A32: R2,R3,R4,R5,R6 | B32: RSHNFRBS20 | C32: Natural Gas Furnace Base.RSH.NGA.20 | D32: PJ | E32: RESNGAEA | F32: RSH | G32: 2020 | H32: 21.5 | I32: 1990.9749 | J32: 1.8615276 | K32: 0.8 | L32: 80000
A33: R2,R3,R4,R5,R6 | B33: RSHNFRV122 | C33: Natural Gas Furnace Ver1.RSH.NGA.22 | D33: PJ | E33: RESNGAEA | F33: RSH | G33: 2022 | H33: 21.5 | I33: 2550.9366 | J33: 2.3850822 | K33: 0.8 | L33: 80000
A34: R2,R3,R4,R5,R6 | B34: RSHNFRV222 | C34: Natural Gas Furnace Ver2.RSH.NGA.22 | D34: PJ | E34: RESNGAEA | F34: RSH | G34: 2022 | H34: 21.5 | I34: 2855.1133 | J34: 2.6694822 | K34: 0.9 | L34: 80000
A35: R2,R3,R4,R5,R6 | B35: RSHNFRV322 | C35: Natural Gas Furnace Ver3.RSH.NGA.22 | D35: PJ | E35: RESNGAEA | F35: RSH | G35: 2022 | H35: 21.5 | I35: 2868.9395 | J35: 2.6824095 | K35: 0.95 | L35: 80000
A36: R2,R3,R4,R5,R6 | B36: RSHNFRV422 | C36: Natural Gas Furnace Ver4.RSH.NGA.22 | D36: PJ | E36: RESNGAEA | F36: RSH | G36: 2022 | H36: 21.5 | I36: 2986.4623 | J36: 2.7922913 | K36: 0.99 | L36: 80000
A37: *Natural Gas Radiant Heating (Residential Gas-Fired Boiler Radiants) | B37: =A37 -> *Natural Gas Radiant Heating (Residential Gas-Fired Boiler Radiants)
A38: R2,R3,R4,R5,R6 | B38: RSHNBRBS15 | C38: Natural Gas Boiler Radiant Base.RSH.NGA.15 | D38: PJ | E38: RESNGAEA | F38: RSH | G38: 2015 | H38: 25 | I38: 5364.5712 | J38: 4.0126261 | K38: 0.82 | L38: 100000
A39: R2,R3,R4,R5,R6 | B39: RSHNBRBS20 | C39: Natural Gas Boiler Radiant Base.RSH.NGA.20 | D39: PJ | E39: RESNGAEA | F39: RSH | G39: 2020 | H39: 25 | I39: 4106.3857 | J39: 3.0715205 | K39: 0.95 | L39: 100000
A40: R2,R3,R4,R5,R6 | B40: RSHNBRV122 | C40: Natural Gas Boiler Radiant Ver 1.RSH.NGA.22 | D40: PJ | E40: RESNGAEA | F40: RSH | G40: 2022 | H40: 25 | I40: 6014.4033 | J40: 4.4986916 | K40: 0.84 | L40: 100000
A41: R2,R3,R4,R5,R6 | B41: RSHNBRV222 | C41: Natural Gas Boiler Radiant Ver 2.RSH.NGA.22 | D41: PJ | E41: RESNGAEA | F41: RSH | G41: 2022 | H41: 25 | I41: 4106.3857 | J41: 3.0715205 | K41: 0.95 | L41: 100000
A42: R2,R3,R4,R5,R6 | B42: RSHNBRV322 | C42: Natural Gas Boiler Radiant Ver 3.RSH.NGA.22 | D42: PJ | E42: RESNGAEA | F42: RSH | G42: 2022 | H42: 25 | I42: 4631.7818 | J42: 3.4645096 | K42: 0.9 | L42: 100000
A43: R2,R3,R4,R5,R6 | B43: RSHNBRV422 | C43: Natural Gas Boiler Radiant Ver 4.RSH.NGA.22 | D43: PJ | E43: RESNGAEA | F43: RSH | G43: 2022 | H43: 25 | I43: 4638.695 | J43: 3.4696805 | K43: 0.96 | L43: 100000
A44: R2,R3,R4,R5,R6 | B44: RSHNBRV130 | C44: Natural Gas Boiler Radiant Ver 1.RSH.NGA.30 | D44: PJ | E44: RESNGAEA | F44: RSH | G44: 2030 | H44: 25 | I44: 4106.3857 | J44: 3.0715205 | K44: 0.95 | L44: 100000 | M44: 0.16
A45: R2,R3,R4,R5,R6 | B45: RSHNBRV230 | C45: Natural Gas Boiler Radiant Ver 2.RSH.NGA.30 | D45: PJ | E45: RESNGAEA | F45: RSH | G45: 2030 | H45: 25 | I45: 4638.695 | J45: 3.4696805 | K45: 0.96 | L45: 100000 | M45: 0.16
A46: *Dfuel Oil (DSL) Radiant Space Heating | B46: =A46 -> *Dfuel Oil (DSL) Radiant Space Heating
A47: R2,R3,R4,R5,R6 | B47: RSHDRDBS15 | C47: Distillate Radiant Base.RSH.DST.15 | D47: PJ | E47: RESDSLEA | F47: RSH | G47: 2015 | H47: 23 | I47: 6774.8451 | J47: 3.6196369 | K47: 0.84 | L47: 140000 | M47: 0.16
A48: R2,R3,R4,R5,R6 | B48: RSHDRDBS20 | C48: Distillate Radiant Ver1.RSH.DST.20 | D48: PJ | E48: RESDSLEA | F48: RSH | G48: 2020 | H48: 23 | I48: 3809.1221 | J48: 2.0351224 | K48: 0.86 | L48: 140000 | M48: 0.16
A49: R2,R3,R4,R5,R6 | B49: RSHDRDV122 | C49: Distillate Radiant Ver1.RSH.DST.22 | D49: PJ | E49: RESDSLEA | F49: RSH | G49: 2022 | H49: 23 | I49: 3809.1221 | J49: 2.0351224 | K49: 0.86 | L49: 140000 | M49: 0.16
A50: R2,R3,R4,R5,R6 | B50: RSHDRDV222 | C50: Distillate Radiant Ver2.RSH.DST.22 | D50: PJ | E50: RESDSLEA | F50: RSH | G50: 2022 | H50: 23 | I50: 3809.1221 | J50: 2.0351224 | K50: 0.86 | L50: 140000 | M50: 0.16
A51: R2,R3,R4,R5,R6 | B51: RSHDRDV322 | C51: Distillate Radiant Ver3.RSH.DST.22 | D51: PJ | E51: RESDSLEA | F51: RSH | G51: 2022 | H51: 23 | I51: 3871.3401 | J51: 2.068364 | K51: 0.87 | L51: 140000 | M51: 0.16
A52: R2,R3,R4,R5,R6 | B52: RSHDRDV422 | C52: Distillate Radiant Ver4.RSH.DST.22 | D52: PJ | E52: RESDSLEA | F52: RSH | G52: 2022 | H52: 23 | I52: 3933.558 | J52: 2.1016055 | K52: 0.88 | L52: 140000 | M52: 0.16
A53: R2,R3,R4,R5,R6 | B53: RSHDRDV130 | C53: Distillate Radiant Ver1.RSH.DST.30 | D53: PJ | E53: RESDSLEA | F53: RSH | G53: 2030 | H53: 23 | I53: 3809.1221 | J53: 2.0351224 | K53: 0.86 | L53: 140000 | M53: 0.16
A54: R2,R3,R4,R5,R6 | B54: RSHDRDV230 | C54: Distillate Radiant Ver2.RSH.DST.30 | D54: PJ | E54: RESDSLEA | F54: RSH | G54: 2030 | H54: 23 | I54: 3933.558 | J54: 2.1016055 | K54: 0.88 | L54: 140000 | M54: 0.16
A55: *Fuel Oil (DSL) Furnaces | B55: =A55 -> *Fuel Oil (DSL) Furnaces
A56: R2,R3,R4,R5,R6 | B56: RSHDFRBS15 | C56: Distillate Furnace Base.RSH.DST.15 | D56: PJ | E56: RESDSLEA | F56: RSH | G56: 2015 | H56: 26.5 | I56: 3377.0529 | J56: 2.4057043 | K56: 0.83 | L56: 105000 | M56: 0.16
A57: R2,R3,R4,R5,R6 | B57: RSHDFRBS20 | C57: Distillate Furnace Base.RSH.DST.20 | D57: PJ | E57: RESDSLEA | F57: RSH | G57: 2020 | H57: 26.5 | I57: 3377.0529 | J57: 2.4057043 | K57: 0.83 | L57: 105000 | M57: 0.16
A58: R2,R3,R4,R5,R6 | B58: RSHDFRV122 | C58: Distillate Furnace Ver1.RSH.DST.22 | D58: PJ | E58: RESDSLEA | F58: RSH | G58: 2022 | H58: 26.5 | I58: 3377.0529 | J58: 2.4057043 | K58: 0.83 | L58: 105000 | M58: 0.16
A59: R2,R3,R4,R5,R6 | B59: RSHDFRV222 | C59: Distillate Furnace Ver2.RSH.DST.22 | D59: PJ | E59: RESDSLEA | F59: RSH | G59: 2022 | H59: 26.5 | I59: 3560.2502 | J59: 2.5362082 | K59: 0.85 | L59: 105000 | M59: 0.16
A60: R2,R3,R4,R5,R6 | B60: RSHDFRV322 | C60: Distillate Furnace Ver3.RSH.DST.22 | D60: PJ | E60: RESDSLEA | F60: RSH | G60: 2022 | H60: 26.5 | I60: 3560.2502 | J60: 2.5362082 | K60: 0.85 | L60: 105000 | M60: 0.16
A61: R2,R3,R4,R5,R6 | B61: RSHDFRV422 | C61: Distillate Furnace Ver4.RSH.DST.22 | D61: PJ | E61: RESDSLEA | F61: RSH | G61: 2022 | H61: 26.5 | I61: 5271.2443 | J61: 3.7550655 | K61: 0.97 | L61: 105000 | M61: 0.16
A62: R2,R3,R4,R5,R6 | B62: RSHDFRV130 | C62: Distillate Furnace Ver1.RSH.DST.30 | D62: PJ | E62: RESDSLEA | F62: RSH | G62: 2030 | H62: 26.5 | I62: 3560.2502 | J62: 2.5362082 | K62: 0.85 | L62: 105000 | M62: 0.16
A63: R2,R3,R4,R5,R6 | B63: RSHDFRV230 | C63: Distillate Furnace Ver2.RSH.DST.30 | D63: PJ | E63: RESDSLEA | F63: RSH | G63: 2030 | H63: 26.5 | I63: 5271.2443 | J63: 3.7550655 | K63: 0.97 | L63: 105000 | M63: 0.16
A64: *Geothermal Heat Pumps | B64: =A64 -> *Geothermal Heat Pumps
A65: R2,R3,R4,R5,R6 | B65: RSCGHPBS15 | C65: Ground Source Heat Pump Base.RSC.ELC.15 | D65: PJ | E65: RESELC | F65: RSH | G65: 2015 | H65: 14.5 | I65: 12564.572 | J65: 26.105913 | K65: 3.1 | L65: 36000
A66: R2,R3,R4,R5,R6 | B66: RSCGHPBS20 | C66: Ground Source Heat Pump Base.RSC.ELC.20 | D66: PJ | E66: RESELC | F66: RSH | G66: 2020 | H66: 14.5 | I66: 13134.904 | J66: 27.290913 | K66: 3.7 | L66: 36000
A67: R2,R3,R4,R5,R6 | B67: RSCGHPV122 | C67: Ground Source Heat Pump Ver1.RSC.ELC.22 | D67: PJ | E67: RESELC | F67: RSH | G67: 2022 | H67: 14.5 | I67: 12685.552 | J67: 26.357277 | K67: 3.2 | L67: 36000
A68: R2,R3,R4,R5,R6 | B68: RSCGHPV222 | C68: Ground Source Heat Pump Ver2.RSC.ELC.22 | D68: PJ | E68: RESELC | F68: RSH | G68: 2022 | H68: 14.5 | I68: 13134.904 | J68: 27.290913 | K68: 3.6 | L68: 36000
A69: *R2,R3,R4,R5,R6 | B69: RSCGHPV322 | C69: Ground Source Heat Pump Ver3.RSC.ELC.22 | D69: PJ | E69: RESELC | F69: RSH | G69: 2022 | H69: 14.5 | I69: 13134.904 | J69: 27.290913 | K69: 3.6 | L69: 36000
A70: R2,R3,R4,R5,R6 | B70: RSCGHPV422 | C70: Ground Source Heat Pump Ver4.RSC.ELC.22 | D70: PJ | E70: RESELC | F70: RSH | G70: 2022 | H70: 14.5 | I70: 13864.237 | J70: 28.806277 | K70: 4.5 | L70: 36000
A71: R2,R3,R4,R5,R6 | B71: RSCGHPV130 | C71: Ground Source Heat Pump Ver1.RSC.ELC.30 | D71: PJ | E71: RESELC | F71: RSH | G71: 2030 | H71: 14.5 | I71: 13134.904 | J71: 27.290913 | K71: 3.7 | L71: 36000
A72: R2,R3,R4,R5,R6 | B72: RSCGHPV230 | C72: Ground Source Heat Pump Ver2.RSC.ELC.30 | D72: PJ | E72: RESELC | F72: RSH | G72: 2030 | H72: 14.5 | I72: 13864.237 | J72: 28.806277 | K72: 4.5 | L72: 36000
A73: *Natural Gas Heat Pumps (Residential Natural Gas Heat Pumps) | B73: =A73 -> *Natural Gas Heat Pumps (Residential Natural Gas Heat Pumps)
A74: R2,R3,R4,R5,R6 | B74: RSHNHPBS09 | C74: Natural Gas Heat Pump Base.RSH.NGA.09 | D74: PJ | E74: RESNGAEA | F74: RSH | G74: 2009 | H74: 15 | I74: 11057.515 | J74: 13.784784 | K74: 0.013 | L74: 60000
A75: R2,R3,R4,R5,R6 | B75: RSHNHPBS20 | C75: Natural Gas Heat Pump Base.RSH.NGA.20 | D75: PJ | E75: RESNGAEA | F75: RSH | G75: 2020 | H75: 15 | I75: 11057.515 | J75: 13.784784 | K75: 0.013 | L75: 60000
A76: R2,R3,R4,R5,R6 | B76: RSHNHPV122 | C76: Natural Gas Heat Pump Ver1.RSH.NGA.22 | D76: PJ | E76: RESNGAEA | F76: RSH | G76: 2022 | H76: 15 | I76: 11057.515 | J76: 13.784784 | K76: 0.013 | L76: 60000
A77: R2,R3,R4,R5,R6 | B77: RSHNHPV130 | C77: Natural Gas Heat Pump Ver1.RSH.NGA.30 | D77: PJ | E77: RESNGAEA | F77: RSH | G77: 2030 | H77: 15 | I77: 11057.515 | J77: 13.784784 | K77: 0.013 | L77: 60000
A78: R2,R3,R4,R5,R6 | B78: RSHNHPV140 | C78: Natural Gas Heat Pump Ver1.RSH.NGA.40 | D78: PJ | E78: RESNGAEA | F78: RSH | G78: 2040 | H78: 15 | I78: 11057.515 | J78: 13.784784 | K78: 0.013 | L78: 60000
A79: R2,R3,R4,R5,R6 | B79: RSHNHPV150 | C79: Natural Gas Heat Pump Ver1.RSH.NGA.50 | D79: PJ | E79: RESNGAEA | F79: RSH | G79: 2050 | H79: 15 | I79: 11057.515 | J79: 13.784784 | K79: 0.013 | L79: 60000
A80: *Space Cooling | B80: =A80 -> *Space Cooling
A81: *Room/Window AC (EIA EQ: Residential Room Air Conditioners) | B81: =A81 -> *Room/Window AC (EIA EQ: Residential Room Air Conditioners)
A82: R2,R3,R4,R5,R6 | B82: RSCRACBS15 | C82: Room AC Base.RSC.ELC.15 | D82: PJ | E82: RESELC | F82: RSH | G82: 2015 | H82: 9.5 | I82: 508.11338 | J82: 3.8006188 | K82: 10.9 | L82: 10000
A83: R2,R3,R4,R5,R6 | B83: RSCRACBS20 | C83: Room AC Base.RSC.ELC.20 | D83: PJ | E83: RESELC | F83: RSH | G83: 2020 | H83: 9.5 | I83: 387.13401 | J83: 2.8957095 | K83: 10.9 | L83: 10000
A84: R2,R3,R4,R5,R6 | B84: RSCRACV122 | C84: Room AC Ver1.RSC.ELC.22 | D84: PJ | E84: RESELC | F84: RSH | G84: 2022 | H84: 9.5 | I84: 387.13401 | J84: 2.8957095 | K84: 10.9 | L84: 10000
A85: R2,R3,R4,R5,R6 | B85: RSCRACV222 | C85: Room AC Ver2.RSC.ELC.22 | D85: PJ | E85: RESELC | F85: RSH | G85: 2022 | H85: 9.5 | I85: 390.59056 | J85: 2.9215641 | K85: 12 | L85: 10000
A86: *R2,R3,R4,R5,R6 | B86: RSCRACV322 | C86: Room AC Ver3.RSC.ELC.22 | D86: PJ | E86: RESELC | F86: RSH | G86: 2022 | H86: 9.5 | I86: 390.59056 | J86: 2.9215641 | K86: 12 | L86: 10000
A87: R2,R3,R4,R5,R6 | B87: RSCRACV422 | C87: Room AC Ver4.RSC.ELC.22 | D87: PJ | E87: RESELC | F87: RSH | G87: 2022 | H87: 9.5 | I87: 466.63474 | J87: 3.4903642 | K87: 15.7 | L87: 10000
A88: *Central AC Units (EIA EQ: Residential Central Air Conditioners (North (Not Hot-Dry or Hot-Humid))) | B88: =A88 -> *Central AC Units (EIA EQ: Residential Central Air Conditioners (North (Not Hot-Dry or Hot-Humid)))
A89: R2,R3,R4,R5,R6 | B89: RSCCACBS15 | C89: Central AC Base.RSC.ELC.15 | D89: PJ | E89: RESELC | F89: RSH | G89: 2015 | H89: 18 | I89: 2765.2429 | J89: 5.7454554 | K89: 12.5 | L89: 36000 | M89: 0.15
A90: R2,R3,R4,R5,R6 | B90: RSCCACBS20 | C90: Central AC Base.RSC.ELC.20 | D90: PJ | E90: RESELC | F90: RSH | G90: 2020 | H90: 18 | I90: 2972.6361 | J90: 6.1763646 | K90: 13.9 | L90: 36000 | M90: 0.15
A91: R2,R3,R4,R5,R6 | B91: RSCCACV122 | C91: Central AC Ver1.RSC.ELC.22 | D91: PJ | E91: RESELC | F91: RSH | G91: 2022 | H91: 18 | I91: 3629.3813 | J91: 7.5409103 | K91: 13 | L91: 36000 | M91: 0.15
A92: R2,R3,R4,R5,R6 | B92: RSCCACV222 | C92: Central AC Ver2.RSC.ELC.22 | D92: PJ | E92: RESELC | F92: RSH | G92: 2022 | H92: 18 | I92: 3677.773 | J92: 7.6414557 | K92: 14.1 | L92: 36000 | M92: 0.15
A93: R2,R3,R4,R5,R6 | B93: RSCCACV322 | C93: Central AC Ver3.RSC.ELC.22 | D93: PJ | E93: RESELC | F93: RSH | G93: 2022 | H93: 18 | I93: 3816.0352 | J93: 7.9287285 | K93: 15 | L93: 36000 | M93: 0.15
A94: R2,R3,R4,R5,R6 | B94: RSCCACV422 | C94: Central AC Ver4.RSC.ELC.22 | D94: PJ | E94: RESELC | F94: RSH | G94: 2022 | H94: 18 | I94: 4134.0381 | J94: 8.5894559 | K94: 17 | L94: 36000 | M94: 0.15
A95: R2,R3,R4,R5,R6 | B95: RSCCACV130 | C95: Central AC Ver1.RSC.ELC.30 | D95: PJ | E95: RESELC | F95: RSH | G95: 2030 | H95: 18 | I95: 3698.5124 | J95: 7.6845466 | K95: 14.4 | L95: 36000 | M95: 0.15
A96: R2,R3,R4,R5,R6 | B96: RSCCACV230 | C96: Central AC Ver2.RSC.ELC.30 | D96: PJ | E96: RESELC | F96: RSH | G96: 2030 | H96: 18 | I96: 4134.0381 | J96: 8.5894559 | K96: 17 | L96: 36000 | M96: 0.15
A97: *Portable AC Units (EIA EQ: Residential Portable Air Conditioners Ver1 Base, Ver2 Energy Star, Ver3 Typical Short, Ver4 Typical Long, Ver5 High Short Ver6 High Long) | B97: =A97 -> *Portable AC Units (EIA EQ: Residential Portable Air Conditioners Ver1 Base, Ver2 Energy Star, Ver3 Typical Short, Ver4 Typical Long, Ver5 High Short Ver6 High Long)
A98: R2,R3,R4,R5,R6 | B98: RSCCACP115 | C98: Portable AC Ver1.RSC.ELC.15 | D98: PJ | E98: RESELC | F98: RSH | G98: 2015 | H98: 9.5 | I98: 483.91751 | J98: 5.4842984 | K98: 5.6 | L98: 6600 | M98: 0.15
A99: R2,R3,R4,R5,R6 | B99: RSCCACP120 | C99: Portable AC Ver1.RSC.ELC.20 | D99: PJ | E99: RESELC | F99: RSH | G99: 2020 | H99: 9.5 | I99: 483.91751 | J99: 5.4842984 | K99: 5.6 | L99: 6600 | M99: 0.15
A100: R2,R3,R4,R5,R6 | B100: RSCCACP122 | C100: Portable AC Ver1.RSC.ELC.22 | D100: PJ | E100: RESELC | F100: RSH | G100: 2022 | H100: 9.5 | I100: 483.91751 | J100: 5.4842984 | K100: 5.6 | L100: 6600 | M100: 0.15
A101: R2,R3,R4,R5,R6 | B101: RSCCACP222 | C101: Portable AC Ver2.RSC.ELC.22 | D101: PJ | E101: RESELC | F101: RSH | G101: 2022 | H101: 9.5 | I101: 559.96169 | J101: 6.3461167 | K101: 7.6 | L101: 6600 | M101: 0.15
...

Sheet Resid
B1: TechName | C1: TechDesc | D1: Units | E1: CommIN | F1: CommOUT | G1: START | H1: LIFE | I1: INVCOST | J1: EFF | K1: MA(ENT) | L1: OUT(DM) | M1: CF | N1: FIXOM | O1: DISCRATE | P1: RESID EPAUS9r 2010 | Q1: RESID EPAUS9r (%) | R1: EFF | T1: Resid Total | U1: Demand Total | V1: RESID | AA1: DEMAND
A2: *Space Heating | V2: BR | W2: BX | X2: MN | Y2: SI | Z2: QN | AA2: BR | AB2: BX | AC2: MN | AD2: SI | AE2: QN
U3: =SUM(U5:U52) -> #REF! | AA3: =ResDemand!E19 -> #REF! | AB3: =ResDemand!E20 -> #REF! | AC3: =ResDemand!E21 -> #REF! | AD3: =ResDemand!E22 -> #REF! | AE3: =ResDemand!E23 -> #REF! | AF3: =SUM(AA3:AE3)-U3 -> #REF!
A4: ELC | M4: =M6 -> 0.16 | P4: =SUM(P5:P21) -> #REF! | Q4: =A4 -> ELC | T4: ='2010 Fuel Share'!C72 -> #REF! | AA4: =SUM(AA6:AA52) -> #REF! | AB4: =SUM(AB6:AB52) -> #REF! | AC4: =SUM(AC6:AC52) -> #REF! | AD4: =SUM(AD6:AD52) -> #REF! | AE4: =SUM(AE6:AE52) -> #REF!
A5: *Electric Radiant
A6: R1,R2,R3,R4,R5,R6 | B6: RSHERDBS05 | C6: Electric Radiant Base.RSH.ELC.05 | D6: PJ | E6: RESELC | F6: RSH | G6: 2005 | H6: 20 | J6: 1 | K6: 1 | L6: 1 | M6: 0.16 | O6: 0.18 | R6: =J6 -> 1
A7: R1,R2,R3,R4,R5,R6 | B7: RSHERDBS10 | C7: Electric Radiant Base.RSH.ELC.10 | D7: PJ | E7: RESELC | F7: RSH | G7: 2010 | H7: 20 | I7: 3.7369871 | J7: 1 | K7: 1 | L7: 1 | M7: 0.16 | O7: 0.18 | P7: =#REF! -> #REF! | Q7: =P7/$P$4 -> #REF! | R7: =J7 -> 1 | T7: =T4*$Q$7*$R$7/$M$7 -> #REF! | U7: =T7*$M$7 -> #REF! | V7: =$T7*AA$3/$U$3 -> #REF! | W7: =$T7*AB$3/$U$3 -> #REF! | X7: =$T7*AC$3/$U$3 -> #REF! | Y7: =$T7*AD$3/$U$3 -> #REF! | Z7: =$T7*AE$3/$U$3 -> #REF! | AA7: =$U7*AA3/$U$3 -> #REF! | AB7: =$U7*AB3/$U$3 -> #REF! | AC7: =$U7*AC3/$U$3 -> #REF! | AD7: =$U7*AD3/$U$3 -> #REF! | AE7: =$U7*AE3/$U$3 -> #REF!
A8: *Electric Heat Pump
A9: R1,R2,R3,R4,R5,R6 | B9: RSHEHPBS05 | C9: Electric Heat Pump Base.RSH.ELC.05 | D9: PJ | E9: RESELC | F9: RSH | G9: 2005 | H9: 15 | J9: 2.2657 | K9: 1 | L9: 1 | M9: 0.16 | O9: 0.18 | R9: =J9 -> 2.2657
A10: R1,R2,R3,R4,R5,R6 | B10: RSHEHPV110 | C10: Electric Heat Pump Ver1.RSH.ELC.10 | D10: PJ | E10: RESELC | F10: RSH | G10: 2010 | H10: 15 | I10: 6.5561178 | J10: 2.26 | K10: 1 | L10: 1 | M10: 0.16 | O10: 0.18 | P10: =#REF! -> #REF! | Q10: =P10/$P$4 -> #REF! | R10: =J10 -> 2.26 | T10: =T4*$Q$10*$R$10/$M$10 -> #REF! | U10: =T10*$M$10 -> #REF! | V10: =$T10*AA$3/$U$3 -> #REF! | W10: =$T10*AB$3/$U$3 -> #REF! | X10: =$T10*AC$3/$U$3 -> #REF! | Y10: =$T10*AD$3/$U$3 -> #REF! | Z10: =$T10*AE$3/$U$3 -> #REF! | AA10: =$U10*AA$3/$U$3 -> #REF! | AB10: =$U10*AB3/$U$3 -> #REF! | AC10: =$U10*AC3/$U$3 -> #REF! | AD10: =$U10*AD3/$U$3 -> #REF! | AE10: =$U10*AE3/$U$3 -> #REF!
A11: R1,R2,R3,R4,R5,R6 | B11: RSHEHPV115 | C11: Electric Heat Pump Ver1.RSH.ELC.15 | D11: PJ | E11: RESELC | F11: RSH | G11: 2015 | H11: 15 | I11: 6.7609965 | J11: 2.4 | K11: 1 | L11: 1 | M11: 0.16 | O11: 0.18 | R11: =J11 -> 2.4
A12: R1,R2,R3,R4,R5,R6 | B12: RSHEHPV210 | C12: Electric Heat Pump Ver2.RSH.ELC.10 | D12: PJ | E12: RESELC | F12: RSH | G12: 2010 | H12: 15 | I12: 8.8097833 | J12: 2.4 | K12: 1 | L12: 1 | M12: 0.16 | O12: 0.18 | R12: =J12 -> 2.4
A13: R1,R2,R3,R4,R5,R6 | B13: RSHEHPV215 | C13: Electric Heat Pump Ver2.RSH.ELC.15 | D13: PJ | E13: RESELC | F13: RSH | G13: 2015 | H13: 15 | I13: 9.3561264 | J13: 2.58 | K13: 1 | L13: 1 | M13: 0.16 | O13: 0.18 | R13: =J13 -> 2.58
A14: R1,R2,R3,R4,R5,R6 | B14: RSHEHPV310 | C14: Electric Heat Pump Ver3.RSH.ELC.10 | D14: PJ | E14: RESELC | F14: RSH | G14: 2010 | H14: 15 | I14: 9.7658838 | J14: 2.49 | K14: 1 | L14: 1 | M14: 0.16 | O14: 0.18 | R14: =J14 -> 2.49
A15: R1,R2,R3,R4,R5,R6 | B15: RSHEHPV315 | C15: Electric Heat Pump Ver3.RSH.ELC.15 | D15: PJ | E15: RESELC | F15: RSH | G15: 2015 | H15: 15 | I15: 9.7658838 | J15: 2.49 | K15: 1 | L15: 1 | M15: 0.16 | O15: 0.18 | R15: =J15 -> 2.49
A16: R1,R2,R3,R4,R5,R6 | B16: RSHEHPV320 | C16: Electric Heat Pump Ver3.RSH.ELC.20 | D16: PJ | E16: RESELC | F16: RSH | G16: 2020 | H16: 15 | I16: 10.243934 | J16: 2.78 | K16: 1 | L16: 1 | M16: 0.16 | O16: 0.18 | R16: =J16 -> 2.78
A17: R1,R2,R3,R4,R5,R6 | B17: RSHEHPV330 | C17: Electric Heat Pump Ver3.RSH.ELC.30 | D17: PJ | E17: RESELC | F17: RSH | G17: 2030 | H17: 15 | I17: 10.243934 | J17: 2.8 | K17: 1 | L17: 1 | M17: 0.16 | O17: 0.18 | R17: =J17 -> 2.8
A18: R1,R2,R3,R4,R5,R6 | B18: RSHEHPV410 | C18: Electric Heat Pump Ver4.RSH.ELC.10 | D18: PJ | E18: RESELC | F18: RSH | G18: 2010 | H18: 15 | I18: 10.926863 | J18: 3.14 | K18: 1 | L18: 1 | M18: 0.16 | O18: 0.18 | R18: =J18 -> 3.14
A19: R1,R2,R3,R4,R5,R6 | B19: RSHEHPV420 | C19: Electric Heat Pump Ver4.RSH.ELC.20 | D19: PJ | E19: RESELC | F19: RSH | G19: 2020 | H19: 15 | I19: 11.200035 | J19: 3.17 | K19: 1 | L19: 1 | M19: 0.16 | O19: 0.18 | R19: =J19 -> 3.17
A20: R1,R2,R3,R4,R5,R6 | B20: RSHEHPV430 | C20: Electric Heat Pump Ver4.RSH.ELC.30 | D20: PJ | E20: RESELC | F20: RSH | G20: 2030 | H20: 15 | I20: 11.268327 | J20: 3.22 | K20: 1 | L20: 1 | M20: 0.16 | O20: 0.18 | R20: =J20 -> 3.22
A21: R1,R2,R3,R4,R5,R6 | B21: RSHEHPV435 | C21: Electric Heat Pump Ver4.RSH.ELC.35 | D21: PJ | E21: RESELC | F21: RSH | G21: 2035 | H21: 15 | I21: 11.268327 | J21: 3.22 | K21: 1 | L21: 1 | M21: 0.16 | O21: 0.18 | R21: =J21 -> 3.22
A22: NGA | M22: =M24 -> 0.16 | P22: =SUM(P23:P35) -> #REF! | Q22: NGA | T22: ='2010 Fuel Share'!C73 -> #REF! | AF22: =(U25+U32+U39+U45)/U3 -> #REF!
A23: *Natural Gas Furnace
A24: R1,R2,R3,R4,R5,R6 | B24: RSHNFRBS05 | C24: Natural Gas Furnace Base.RSH.NGA.05 | D24: PJ | E24: RESNGAEA | F24: RSH | G24: 2005 | H24: 15 | J24: 0.81440002 | K24: 1 | L24: 1 | M24: 0.16 | O24: 0.18 | R24: =J24 -> 0.81440002
A25: R1,R2,R3,R4,R5,R6 | B25: RSHNFRV110 | C25: Natural Gas Furnace Ver1.RSH.NGA.10 | D25: PJ | E25: RESNGAEA | F25: RSH | G25: 2010 | H25: 15 | I25: 4.9170883 | J25: 0.78 | K25: 1 | L25: 1 | M25: 0.16 | O25: 0.18 | P25: =#REF! -> #REF! | Q25: =P25/$P$22 -> #REF! | R25: =J25 -> 0.78 | T25: =T22*$Q$25*$R$25/$M$25 -> #REF! | U25: =T22*$Q$25*$R$25 -> #REF! | V25: =$T25*AA$3/$U$3 -> #REF! | W25: =$T25*AB$3/$U$3 -> #REF! | X25: =$T25*AC$3/$U$3 -> #REF! | Y25: =$T25*AD$3/$U$3 -> #REF! | Z25: =$T25*AE$3/$U$3 -> #REF! | AA25: =$U25*AA$3/$U$3 -> #REF! | AB25: =$U25*AB$3/$U$3 -> #REF! | AC25: =$U25*AC$3/$U$3 -> #REF! | AD25: =$U25*AD$3/$U$3 -> #REF! | AE25: =$U25*AE$3/$U$3 -> #REF!
A26: R1,R2,R3,R4,R5,R6 | B26: RSHNFRV210 | C26: Natural Gas Furnace Ver2.RSH.NGA.10 | D26: PJ | E26: RESNGAEA | F26: RSH | G26: 2010 | H26: 15 | I26: 4.9170883 | J26: 0.8 | K26: 1 | L26: 1 | M26: 0.16 | O26: 0.18 | R26: =J26 -> 0.8
A27: R1,R2,R3,R4,R5,R6 | B27: RSHNFRV310 | C27: Natural Gas Furnace Ver3.RSH.NGA.10 | D27: PJ | E27: RESNGAEA | F27: RSH | G27: 2010 | H27: 20 | I27: 5.4087972 | J27: 0.9 | K27: 1 | L27: 1 | M27: 0.16 | O27: 0.18 | R27: =J27 -> 0.9
A28: R1,R2,R3,R4,R5,R6 | B28: RSHNFRV410 | C28: Natural Gas Furnace Ver4.RSH.NGA.10 | D28: PJ | E28: RESNGAEA | F28: RSH | G28: 2010 | H28: 20 | I28: 6.2938731 | J28: 0.95 | K28: 1 | L28: 1 | M28: 0.16 | O28: 0.18 | R28: =J28 -> 0.95
A29: R1,R2,R3,R4,R5,R6 | B29: RSHNFRV510 | C29: Natural Gas Furnace Ver5.RSH.NGA.10 | D29: PJ | E29: RESNGAEA | F29: RSH | G29: 2010 | H29: 20 | I29: 7.3756325 | J29: 0.98 | K29: 1 | L29: 1 | M29: 0.16 | O29: 0.18 | R29: =J29 -> 0.98
A30: *Natural Gas Radiant
A31: R1,R2,R3,R4,R5,R6 | B31: RSHNRDBS05 | C31: Natural Gas Radiant Base.RSH.NGA.05 | D31: PJ | E31: RESNGAEA | F31: RSH | G31: 2005 | H31: 20 | J31: 0.8 | K31: 1 | L31: 1 | M31: 0.16 | O31: 0.18 | R31: =J31 -> 0.8
A32: R1,R2,R3,R4,R5,R6 | B32: RSHNRDV110 | C32: Natural Gas Radiant Ver1.RSH.NGA.10 | D32: PJ | E32: RESNGAEA | F32: RSH | G32: 2010 | H32: 20 | I32: 6.4905566 | J32: 0.8 | K32: 1 | L32: 1 | M32: 0.16 | O32: 0.18 | P32: =#REF! -> #REF! | Q32: =P32/$P$22 -> #REF! | R32: =J32 -> 0.8 | T32: =T22*$Q$32*$R$32/$M$32 -> #REF! | U32: =T22*$Q$32*$R$32 -> #REF! | V32: =$T32*AA$3/$U$3 -> #REF! | W32: =$T32*AB$3/$U$3 -> #REF! | X32: =$T32*AC$3/$U$3 -> #REF! | Y32: =$T32*AD$3/$U$3 -> #REF! | Z32: =$T32*AE$3/$U$3 -> #REF! | AA32: =$U32*AA$3/$U$3 -> #REF! | AB32: =$U32*AB$3/$U$3 -> #REF! | AC32: =$U32*AC$3/$U$3 -> #REF! | AD32: =$U32*AD$3/$U$3 -> #REF! | AE32: =$U32*AE$3/$U$3 -> #REF!
A33: R1,R2,R3,R4,R5,R6 | B33: RSHNRDV115 | C33: Natural Gas Radiant Ver1.RSH.NGA.15 | D33: PJ | E33: RESNGAEA | F33: RSH | G33: 2015 | H33: 20 | I33: 6.8839237 | J33: 0.82 | K33: 1 | L33: 1 | M33: 0.16 | O33: 0.18 | R33: =J33 -> 0.82
A34: R1,R2,R3,R4,R5,R6 | B34: RSHNRDV210 | C34: Natural Gas Radiant Ver2.RSH.NGA.10 | D34: PJ | E34: RESNGAEA | F34: RSH | G34: 2010 | H34: 20 | I34: 8.3590502 | J34: 0.85 | K34: 1 | L34: 1 | M34: 0.16 | O34: 0.18 | R34: =J34 -> 0.85
A35: R1,R2,R3,R4,R5,R6 | B35: RSHNRDV310 | C35: Natural Gas Radiant Ver3.RSH.NGA.10 | D35: PJ | E35: RESNGAEA | F35: RSH | G35: 2010 | H35: 20 | I35: 7.8673413 | J35: 0.98 | K35: 1 | L35: 1 | M35: 0.16 | O35: 0.18 | R35: =J35 -> 0.98
A36: DSL | M36: =M38 -> 0.16 | P36: =SUM(P37:P52) -> #REF! | Q36: DSL | T36: ='2010 Fuel Share'!C74 -> #REF!
A37: *Distillate Furnace
A38: R1,R2,R3,R4,R5,R6 | B38: RSHDFRBS05 | C38: Distillate Furnace Base.RSH.DST.05 | D38: PJ | E38: RESDSLEA | F38: RSH | G38: 2005 | H38: 20 | J38: 0.81739998 | K38: 1 | L38: 1 | M38: 0.16 | O38: 0.45 | R38: =J38 -> 0.81739998
A39: R1,R2,R3,R4,R5,R6 | B39: RSHDFRV110 | C39: Distillate Furnace Ver1.RSH.DST.10 | D39: PJ | E39: RESDSLEA | F39: RSH | G39: 2010 | H39: 20 | I39: 6.3922148 | J39: =TechData_DMD!I150 -> 4.981 | K39: 1 | L39: 1 | M39: 0.16 | O39: 0.45 | P39: =#REF! -> #REF! | Q39: =P39/$P$36 -> #REF! | R39: =J39 -> 4.981 | T39: =T36*$Q$39*$R$39/$M$39 -> #REF! | U39: =T36*$Q$39*$R$39 -> #REF! | V39: =$T39*AA$3/$U$3 -> #REF! | W39: =$T39*AB$3/$U$3 -> #REF! | X39: =$T39*AC$3/$U$3 -> #REF! | Y39: =$T39*AD$3/$U$3 -> #REF! | Z39: =$T39*AE$3/$U$3 -> #REF! | AA39: =$U39*AA$3/$U$3 -> #REF! | AB39: =$U39*AB$3/$U$3 -> #REF! | AC39: =$U39*AC$3/$U$3 -> #REF! | AD39: =$U39*AD$3/$U$3 -> #REF! | AE39: =$U39*AE$3/$U$3 -> #REF!
A40: R1,R2,R3,R4,R5,R6 | B40: RSHDFRV115 | C40: Distillate Furnace Ver1.RSH.DST.15 | D40: PJ | E40: RESDSLEA | F40: RSH | G40: 2015 | H40: 20 | I40: 6.8839237 | J40: 0.83 | K40: 1 | L40: 1 | M40: 0.16 | O40: 0.45 | R40: =J40 -> 0.83
A41: R1,R2,R3,R4,R5,R6 | B41: RSHDFRV210 | C41: Distillate Furnace Ver2.RSH.DST.10 | D41: PJ | E41: RESDSLEA | F41: RSH | G41: 2010 | H41: 20 | I41: 9.3424678 | J41: 0.85 | K41: 1 | L41: 1 | M41: 0.16 | O41: 0.45 | R41: =J41 -> 0.85
A42: R1,R2,R3,R4,R5,R6 | B42: RSHDFRV310 | C42: Distillate Furnace Ver3.RSH.DST.10 | D42: PJ | E42: RESDSLEA | F42: RSH | G42: 2010 | H42: 20 | I42: 9.3424678 | J42: 0.98 | K42: 1 | L42: 1 | M42: 0.16 | O42: 0.45 | R42: =J42 -> 0.98
A43: *Distillate Radiant
A44: R1,R2,R3,R4,R5,R6 | B44: RSHDRDBS05 | C44: Distillate Radiant Base.RSH.DST.05 | D44: PJ | E44: RESDSLEA | F44: RSH | G44: 2005 | H44: 20 | J44: 0.8 | K44: 1 | L44: 1 | M44: 0.16 | O44: 0.45 | R44: =J44 -> 0.8
A45: R1,R2,R3,R4,R5,R6 | B45: RSHDRDV110 | C45: Distillate Radiant Ver1.RSH.DST.10 | D45: PJ | E45: RESDSLEA | F45: RSH | G45: 2010 | H45: 20 | I45: 9.014662 | J45: =TechData_DMD!I156 -> 1.9631 | K45: 1 | L45: 1 | M45: 0.16 | O45: 0.45 | P45: =#REF! -> #REF! | Q45: =P45/$P$36 -> #REF! | R45: =J45 -> 1.9631 | T45: =T36*$Q$45*$R$45/$M$45 -> #REF! | U45: =T36*$Q$45*$R$45 -> #REF! | V45: =$T45*AA$3/$U$3 -> #REF! | W45: =$T45*AB$3/$U$3 -> #REF! | X45: =$T45*AC$3/$U$3 -> #REF! | Y45: =$T45*AD$3/$U$3 -> #REF! | Z45: =$T45*AE$3/$U$3 -> #REF! | AA45: =$U45*AA$3/$U$3 -> #REF! | AB45: =$U45*AB$3/$U$3 -> #REF! | AC45: =$U45*AC$3/$U$3 -> #REF! | AD45: =$U45*AD$3/$U$3 -> #REF! | AE45: =$U45*AE$3/$U$3 -> #REF!
A46: R1,R2,R3,R4,R5,R6 | B46: RSHDRDV115 | C46: Distillate Radiant Ver1.RSH.DST.15 | D46: PJ | E46: RESDSLEA | F46: RSH | G46: 2015 | H46: 20 | I46: 9.5610051 | J46: 0.85 | K46: 1 | L46: 1 | M46: 0.16 | O46: 0.45 | R46: =J46 -> 0.85
A47: R1,R2,R3,R4,R5,R6 | B47: RSHDRDV210 | C47: Distillate Radiant Ver2.RSH.DST.10 | D47: PJ | E47: RESDSLEA | F47: RSH | G47: 2010 | H47: 20 | I47: 11.609792 | J47: 0.85 | K47: 1 | L47: 1 | M47: 0.16 | O47: 0.45 | R47: =J47 -> 0.85
A48: R1,R2,R3,R4,R5,R6 | B48: RSHDRDV310 | C48: Distillate Radiant Ver3.RSH.DST.10 | D48: PJ | E48: RESDSLEA | F48: RSH | G48: 2010 | H48: 20 | I48: 10.926863 | J48: 0.98 | K48: 1 | L48: 1 | M48: 0.16 | O48: 0.45 | R48: =J48 -> 0.98
A49: *Natural Gas Heat Pump
A50: R1,R2,R3,R4,R5,R6 | B50: RSHNHPBS05 | C50: Natural Gas Heat Pump Base.RSH.NGA.05 | D50: PJ | E50: RESNGAEA | F50: RSH | G50: 2005 | H50: 15 | J50: 1.3 | K50: 1 | L50: 1 | M50: 0.16 | O50: 0.18 | R50: =J50 -> 1.3
A51: R1,R2,R3,R4,R5,R6 | B51: RSHNHPV110 | C51: Natural Gas Heat Pump Ver1.RSH.NGA.10 | D51: PJ | E51: RESNGAEA | F51: RSH | G51: 2010 | H51: 15 | I51: 12.292721 | J51: 1.3 | K51: 1 | L51: 1 | M51: 0.16 | O51: 0.18 | R51: =J51 -> 1.3
A52: R1,R2,R3,R4,R5,R6 | B52: RSHNHPV120 | C52: Natural Gas Heat Pump Ver1.RSH.NGA.20 | D52: PJ | E52: RESNGAEA | F52: RSH | G52: 2020 | H52: 15 | I52: 12.292721 | J52: 1.4 | K52: 1 | L52: 1 | M52: 0.16 | O52: 0.18 | R52: =J52 -> 1.4
A53: *Space Cooling | U53: =SUM(U55:U91) -> #REF! | AA53: =ResDemand!E6 -> #REF! | AB53: =ResDemand!E7 -> #REF! | AC53: =ResDemand!E8 -> #REF! | AD53: =ResDemand!E9 -> #REF! | AE53: =ResDemand!E10 -> #REF! | AF53: =SUM(AA53:AE53)-U53 -> #REF!
A54: ELC | M54: =M56 -> 0.15 | P54: =SUM(P55:P86) -> 1098.7368 | Q54: ELC | T54: ='2010 Fuel Share'!E72 -> #REF! | AA54: =SUM(AA55:AA91) -> #REF! | AB54: =SUM(AB55:AB91) -> #REF! | AC54: =SUM(AC55:AC91) -> #REF! | AD54: =SUM(AD55:AD91) -> #REF! | AE54: =SUM(AE55:AE91) -> #REF!
A55: *Room AC
A56: R1,R2,R3,R4,R5,R6 | B56: RSCRACBS05 | C56: Room AC Base.RSC.ELC.05 | D56: PJ | E56: RESELC | F56: RSC | G56: 2005 | H56: 10 | J56: 2.7435958 | K56: 1 | L56: 1 | M56: 0.15 | O56: 0.6 | R56: =J56 -> 2.7435958
A57: R1,R2,R3,R4,R5,R6 | B57: RSCRACV110 | C57: Room AC Ver1.RSC.ELC.10 | D57: PJ | E57: RESELC | F57: RSC | G57: 2010 | H57: 10 | I57: 2.7043986 | J57: 2.74 | K57: 1 | L57: 1 | M57: 0.15 | O57: 0.6 | P57: 669.43392 | Q57: =P57/$P$54 -> 0.60927597 | R57: =J57 -> 2.74 | T57: =T54*$Q$57*$R$57/$M$57 -> #REF! | U57: =T54*$Q$57*$R$57 -> #REF! | V57: =$T57*AA$53/$U$53 -> #REF! | W57: =$T57*AB$53/$U$53 -> #REF! | X57: =$T57*AC$53/$U$53 -> #REF! | Y57: =$T57*AD$53/$U$53 -> #REF! | Z57: =$T57*AE$53/$U$53 -> #REF! | AA57: =$U57*AA53/$U$53 -> #REF! | AB57: =$U57*AB53/$U$53 -> #REF! | AC57: =$U57*AC53/$U$53 -> #REF! | AD57: =$U57*AD53/$U$53 -> #REF! | AE57: =$U57*AE53/$U$53 -> #REF!
A58: R1,R2,R3,R4,R5,R6 | B58: RSCRACV210 | C58: Room AC Ver2.RSC.ELC.10 | D58: PJ | E58: RESELC | F58: RSC | G58: 2010 | H58: 10 | I58: 2.8519112 | J58: 3.17 | K58: 1 | L58: 1 | M58: 0.15 | O58: 0.6 | R58: =J58 -> 3.17
A59: R1,R2,R3,R4,R5,R6 | B59: RSCRACV215 | C59: Room AC Ver2.RSC.ELC.15 | D59: PJ | E59: RESELC | F59: RSC | G59: 2015 | H59: 10 | I59: 2.9010821 | J59: 3.22 | K59: 1 | L59: 1 | M59: 0.15 | O59: 0.6 | R59: =J59 -> 3.22
A60: R1,R2,R3,R4,R5,R6 | B60: RSCRACV230 | C60: Room AC Ver2.RSC.ELC.30 | D60: PJ | E60: RESELC | F60: RSC | G60: 2030 | H60: 10 | I60: 2.9010821 | J60: 3.28 | K60: 1 | L60: 1 | M60: 0.15 | O60: 0.6 | R60: =J60 -> 3.28
A61: R1,R2,R3,R4,R5,R6 | B61: RSCRACV310 | C61: Room AC Ver3.RSC.ELC.10 | D61: PJ | E61: RESELC | F61: RSC | G61: 2010 | H61: 10 | I61: 4.4745504 | J61: 3.52 | K61: 1 | L61: 1 | M61: 0.15 | O61: 0.6 | R61: =J61 -> 3.52
A62: R1,R2,R3,R4,R5,R6 | B62: RSCRACV320 | C62: Room AC Ver3.RSC.ELC.20 | D62: PJ | E62: RESELC | F62: RSC | G62: 2020 | H62: 10 | I62: 5.064601 | J62: 3.81 | K62: 1 | L62: 1 | M62: 0.15 | O62: 0.6 | R62: =J62 -> 3.81
A63: *Central AC
A64: R1,R2,R3,R4,R5,R6 | B64: RSCCACBS05 | C64: Central AC Base.RSC.ELC.05 | D64: PJ | E64: RESELC | F64: RSC | G64: 2005 | H64: 15 | J64: 2.9175659 | K64: 1 | L64: 1 | M64: 0.15 | O64: 0.18 | R64: =J64 -> 2.9175659
A65: R1,R2,R3,R4,R5,R6 | B65: RSCCACV110 | C65: Central AC Ver1.RSC.ELC.10 | D65: PJ | E65: RESELC | F65: RSC | G65: 2010 | H65: 15 | I65: 8.7414904 | J65: 2.92 | K65: 1 | L65: 1 | M65: 0.15 | O65: 0.18 | P65: 429.30287 | Q65: =P65/$P$54 -> 0.39072403 | R65: =J65 -> 2.92 | T65: =T54*$Q$65*$R$65/$M$65 -> #REF! | U65: =T54*$Q$65*$R$65 -> #REF! | V65: =$T65*AA$53/$U$53 -> #REF! | W65: =$T65*AB$53/$U$53 -> #REF! | X65: =$T65*AC$53/$U$53 -> #REF! | Y65: =$T65*AD$53/$U$53 -> #REF! | Z65: =$T65*AE$53/$U$53 -> #REF! | AA65: =$U65*AA53/$U$53 -> #REF! | AB65: =$U65*AB53/$U$53 -> #REF! | AC65: =$U65*AC53/$U$53 -> #REF! | AD65: =$U65*AD53/$U$53 -> #REF! | AE65: =$U65*AE53/$U$53 -> #REF!
A66: R5,R6,R7,R9 | B66: RSCCACV115 | C66: Central AC Ver1.RSC.ELC.15 | D66: PJ | E66: RESELC | F66: RSC | G66: 2015 | H66: 15 | I66: 9.6975909 | J66: 4.1 | K66: 1 | L66: 1 | M66: 0.15 | O66: 0.18 | R66: =J66 -> 4.1
A67: R1,R2,R3,R4,R5,R6 | B67: RSCCACV220 | C67: Central AC Ver2.RSC.ELC.20 | D67: PJ | E67: RESELC | F67: RSC | G67: 2020 | H67: 15 | I67: 9.6975909 | J67: 4.1 | K67: 1 | L67: 1 | M67: 0.15 | O67: 0.18 | R67: =J67 -> 4.1
A68: R1,R2,R3,R4,R5,R6 | B68: RSCCACV310 | C68: Central AC Ver3.RSC.ELC.10 | D68: PJ | E68: RESELC | F68: RSC | G68: 2010 | H68: 15 | I68: 10.517106 | J68: 4.69 | K68: 1 | L68: 1 | M68: 0.15 | O68: 0.18 | R68: =J68 -> 4.69
A69: R1,R2,R3,R4,R5,R6 | B69: RSCCACV320 | C69: Central AC Ver3.RSC.ELC.20 | D69: PJ | E69: RESELC | F69: RSC | G69: 2020 | H69: 15 | I69: 10.107348 | J69: 4.69 | K69: 1 | L69: 1 | M69: 0.15 | O69: 0.18 | R69: =J69 -> 4.69
A70: R1,R2,R3,R4,R5,R6 | B70: RSCCACV410 | C70: Central AC Ver4.RSC.ELC.10 | D70: PJ | E70: RESELC | F70: RSC | G70: 2010 | H70: 15 | I70: 12.292721 | J70: 6.15 | K70: 1 | L70: 1 | M70: 0.15 | O70: 0.18 | R70: =J70 -> 6.15
A71: R1,R2,R3,R4,R5,R6 | B71: RSCCACV415 | C71: Central AC Ver4.RSC.ELC.15 | D71: PJ | E71: RESELC | F71: RSC | G71: 2015 | H71: 15 | I71: 16.390294 | J71: 7.03 | K71: 1 | L71: 1 | M71: 0.15 | O71: 0.18 | R71: =J71 -> 7.03
A72: R1,R2,R3,R4,R5,R6 | B72: RSCCACV420 | C72: Central AC Ver4.RSC.ELC.20 | D72: PJ | E72: RESELC | F72: RSC | G72: 2020 | H72: 15 | I72: 15.707366 | J72: 7.03 | K72: 1 | L72: 1 | M72: 0.15 | O72: 0.18 | R72: =J72 -> 7.03
A73: *Electric Heat Pump
A74: R1,R2,R3,R4,R5,R6 | B74: RSCEHPBS05 | C74: Electric Heat Pump Base.RSC.ELC.05 | D74: PJ | E74: RESELC | F74: RSC | G74: 2005 | H74: 15 | J74: 2.998007 | K74: 1 | L74: 1 | M74: 0.15 | O74: 0.45 | R74: =J74 -> 2.998007
A75: R1,R2,R3,R4,R5,R6 | B75: RSCEHPV110 | C75: Electric Heat Pump Ver1.RSC.ELC.10 | D75: PJ | E75: RESELC | F75: RSC | G75: 2010 | H75: 15 | I75: 6.5561178 | J75: 3 | K75: 1 | L75: 1 | M75: 0.15 | O75: 0.45 | P75: 0 | Q75: =P75/$P$54 -> 0 | R75: =J75 -> 3 | T75: =T54*$Q$75*$R$75/$M$75 -> #REF! | U75: =T54*$Q$75*$R$75 -> #REF! | V75: =$T75*AA$53/$U$53 -> #REF! | W75: =$T75*AB$53/$U$53 -> #REF! | X75: =$T75*AC$53/$U$53 -> #REF! | Y75: =$T75*AD$53/$U$53 -> #REF! | Z75: =$T75*AE$53/$U$53 -> #REF! | AA75: =$U75*AA53/$U$53 -> #REF! | AB75: =$U75*AB53/$U$53 -> #REF! | AC75: =$U75*AC53/$U$53 -> #REF! | AD75: =$U75*AD53/$U$53 -> #REF! | AE75: =$U75*AE53/$U$53 -> #REF!
A76: R1,R2,R3,R4,R5,R6 | B76: RSCEHPV115 | C76: Electric Heat Pump Ver1.RSC.ELC.15 | D76: PJ | E76: RESELC | F76: RSC | G76: 2015 | H76: 15 | I76: 6.7609965 | J76: 4.1 | K76: 1 | L76: 1 | M76: 0.15 | O76: 0.45 | R76: =J76 -> 4.1
A77: R1,R2,R3,R4,R5,R6 | B77: RSCEHPV210 | C77: Electric Heat Pump Ver2.RSC.ELC.10 | D77: PJ | E77: RESELC | F77: RSC | G77: 2010 | H77: 15 | I77: 9.4927122 | J77: 4.4 | K77: 1 | L77: 1 | M77: 0.15 | O77: 0.45 | R77: =J77 -> 4.4
A78: R1,R2,R3,R4,R5,R6 | B78: RSCEHPV215 | C78: Electric Heat Pump Ver2.RSC.ELC.15 | D78: PJ | E78: RESELC | F78: RSC | G78: 2015 | H78: 15 | I78: 9.4927122 | J78: 4.4 | K78: 1 | L78: 1 | M78: 0.15 | O78: 0.45 | R78: =J78 -> 4.4
A79: R1,R2,R3,R4,R5,R6 | B79: RSCEHPV310 | C79: Electric Heat Pump Ver3.RSC.ELC.10 | D79: PJ | E79: RESELC | F79: RSC | G79: 2010 | H79: 15 | I79: 9.8341767 | J79: 4.69 | K79: 1 | L79: 1 | M79: 0.15 | O79: 0.45 | R79: =J79 -> 4.69
A80: R1,R2,R3,R4,R5,R6 | B80: RSCEHPV315 | C80: Electric Heat Pump Ver3.RSC.ELC.15 | D80: PJ | E80: RESELC | F80: RSC | G80: 2015 | H80: 15 | I80: 8.6049046 | J80: 4.84 | K80: 1 | L80: 1 | M80: 0.15 | O80: 0.45 | R80: =J80 -> 4.84
A81: R1,R2,R3,R4,R5,R6 | B81: RSCEHPV320 | C81: Electric Heat Pump Ver3.RSC.ELC.20 | D81: PJ | E81: RESELC | F81: RSC | G81: 2020 | H81: 15 | I81: 8.6049046 | J81: 4.84 | K81: 1 | L81: 1 | M81: 0.15 | O81: 0.45 | R81: =J81 -> 4.84
A82: R1,R2,R3,R4,R5,R6 | B82: RSCEHPV330 | C82: Electric Heat Pump Ver3.RSC.ELC.30 | D82: PJ | E82: RESELC | F82: RSC | G82: 2030 | H82: 15 | I82: 8.6049046 | J82: 4.84 | K82: 1 | L82: 1 | M82: 0.15 | O82: 0.45 | R82: =J82 -> 4.84
A83: R1,R2,R3,R4,R5,R6 | B83: RSCEHPV410 | C83: Electric Heat Pump Ver4.RSC.ELC.10 | D83: PJ | E83: RESELC | F83: RSC | G83: 2010 | H83: 15 | I83: 10.85857 | J83: 6.45 | K83: 1 | L83: 1 | M83: 0.15 | O83: 0.45 | R83: =J83 -> 6.45
A84: R1,R2,R3,R4,R5,R6 | B84: RSCEHPV420 | C84: Electric Heat Pump Ver4.RSC.ELC.20 | D84: PJ | E84: RESELC | F84: RSC | G84: 2020 | H84: 15 | I84: 10.995156 | J84: 6.74 | K84: 1 | L84: 1 | M84: 0.15 | O84: 0.45 | R84: =J84 -> 6.74
A85: R1,R2,R3,R4,R5,R6 | B85: RSCEHPV430 | C85: Electric Heat Pump Ver4.RSC.ELC.30 | D85: PJ | E85: RESELC | F85: RSC | G85: 2030 | H85: 15 | I85: 11.268327 | J85: 7.03 | K85: 1 | L85: 1 | M85: 0.15 | O85: 0.45 | R85: =J85 -> 7.03
A86: R1,R2,R3,R4,R5,R6 | B86: RSCEHPV435 | C86: Electric Heat Pump Ver4.RSC.ELC.35 | D86: PJ | E86: RESELC | F86: RSC | G86: 2035 | H86: 15 | I86: 11.268327 | J86: 7.33 | K86: 1 | L86: 1 | M86: 0.15 | O86: 0.45 | R86: =J86 -> 7.33
A87: NGA | M87: =M89 -> 0.15 | P87: =SUM(P88:P91) -> 0 | Q87: NGA | T87: ='2010 Fuel Share'!E73 -> #REF!
A88: *Natural Gas Heat Pump
A89: R1,R2,R3,R4,R5,R6 | B89: RSCNHPBS05 | C89: Natural Gas Heat Pump Base.RSC.NGA.05 | D89: PJ | E89: RESNGAEA | F89: RSC | G89: 2005 | H89: 15 | I89: 0 | J89: 0.67000002 | K89: 1 | L89: 1 | M89: 0.15 | O89: 0.18 | R89: =J89 -> 0.67000002
A90: R1,R2,R3,R4,R5,R6 | B90: RSCNHPV110 | C90: Natural Gas Heat Pump Ver1.RSC.NGA.10 | D90: PJ | E90: RESNGAEA | F90: RSC | G90: 2010 | H90: 15 | I90: 12.292721 | J90: 0.6 | K90: 1 | L90: 1 | M90: 0.15 | O90: 0.18 | Q90: 1 | R90: =J90 -> 0.6 | T90: =T87*$Q$90*$R$90/$M$90 -> #REF! | U90: =T87*$Q$90*$R$90 -> #REF! | V90: =$T90*AA$53/$U$53 -> #REF! | W90: =$T90*AB$53/$U$53 -> #REF! | X90: =$T90*AC$53/$U$53 -> #REF! | Y90: =$T90*AD$53/$U$53 -> #REF! | Z90: =$T90*AE$53/$U$53 -> #REF! | AA90: =$U90*AA53/$U$53 -> #REF! | AB90: =$U90*AB53/$U$53 -> #REF! | AC90: =$U90*AC53/$U$53 -> #REF! | AD90: =$U90*AD53/$U$53 -> #REF! | AE90: =$U90*AE53/$U$53 -> #REF!
A91: R1,R2,R3,R4,R5,R6 | B91: RSCNHPV120 | C91: Natural Gas Heat Pump Ver1.RSC.NGA.20 | D91: PJ | E91: RESNGAEA | F91: RSC | G91: 2020 | H91: 15 | I91: 12.292721 | J91: 0.7 | K91: 1 | L91: 1 | M91: 0.15 | O91: 0.18 | R91: =J91 -> 0.7
A92: *Water Heating | U92: =SUM(U94:U114) -> #REF! | AA92: =ResDemand!E104 -> #REF! | AB92: =ResDemand!E105 -> #REF! | AC92: =ResDemand!E106 -> #REF! | AD92: =ResDemand!E107 -> #REF! | AE92: =ResDemand!E108 -> #REF! | AF92: =SUM(AA92:AE92)-U92 -> #REF!
A93: NGA | M93: =M94 -> 0.1 | P93: =SUM(P95:P100) -> 1190.0517 | Q93: NGA | T93: ='2010 Fuel Share'!D73 -> #REF! | AA93: =SUM(AA94:AA114) -> #REF! | AB93: =SUM(AB94:AB114) -> #REF! | AC93: =SUM(AC94:AC114) -> #REF! | AD93: =SUM(AD94:AD114) -> #REF! | AE93: =SUM(AE94:AE114) -> #REF!
A94: R1,R2,R3,R4,R5,R6 | B94: RWHNWHBS05 | C94: Natural Gas Base.RWH.NGA.05 | D94: PJ | E94: RESNGAEA | F94: RWH | G94: 2005 | H94: 10 | J94: 0.57569999 | K94: 1 | L94: 1 | M94: 0.1 | O94: 0.18 | R94: =J94 -> 0.57569999
A95: R1,R2,R3,R4,R5,R6 | B95: RWHNWHV110 | C95: Natural Gas Ver1.RWH.NGA.10 | D95: PJ | E95: RESNGAEA | F95: RWH | G95: 2010 | H95: 10 | I95: 7.6212655 | J95: =TechData_DMD!#REF! -> #REF! | K95: 1 | L95: 1 | M95: 0.1 | O95: 0.18 | P95: 1190.0517 | Q95: =P95/P93 -> 1 | R95: =J95 -> #REF! | T95: =T93*$Q$95*$R$95/M95 -> #REF! | U95: =T93*$Q$95*$R$95 -> #REF! | V95: =$T95*AA$92/$U$92 -> #REF! | W95: =$T95*AB$92/$U$92 -> #REF! | X95: =$T95*AC$92/$U$92 -> #REF! | Y95: =$T95*AD$92/$U$92 -> #REF! | Z95: =$T95*AE$92/$U$92 -> #REF! | AA95: =$U95*AA92/$U$92 -> #REF! | AB95: =$U95*AB92/$U$92 -> #REF! | AC95: =$U95*AC92/$U$92 -> #REF! | AD95: =$U95*AD92/$U$92 -> #REF! | AE95: =$U95*AE92/$U$92 -> #REF!
A96: R1,R2,R3,R4,R5,R6 | B96: RWHNWHV115 | C96: Natural Gas Ver1.RWH.NGA.15 | D96: PJ | E96: RESNGAEA | F96: RWH | G96: 2015 | H96: 10 | I96: 7.790627 | J96: 0.62 | K96: 1 | L96: 1 | M96: 0.1 | O96: 0.18 | R96: =J96 -> 0.62
A97: R1,R2,R3,R4,R5,R6 | B97: RWHNWHV210 | C97: Natural Gas Ver2.RWH.NGA.10 | D97: PJ | E97: RESNGAEA | F97: RWH | G97: 2010 | H97: 10 | I97: 10.585091 | J97: 0.67 | K97: 1 | L97: 1 | M97: 0.1 | O97: 0.18 | R97: =J97 -> 0.67
A98: R1,R2,R3,R4,R5,R6 | B98: RWHNWHV310 | C98: Natural Gas Ver3.RWH.NGA.10 | D98: PJ | E98: RESNGAEA | F98: RWH | G98: 2010 | H98: 10 | I98: 18.62976 | J98: 0.82 | K98: 1 | L98: 1 | M98: 0.1 | O98: 0.18 | R98: =J98 -> 0.82
A99: R1,R2,R3,R4,R5,R6 | B99: RWHNWHV320 | C99: Natural Gas Ver3.RWH.NGA.20 | D99: PJ | E99: RESNGAEA | F99: RWH | G99: 2020 | H99: 20 | I99: 17.782953 | J99: 0.9 | K99: 1 | L99: 1 | M99: 0.1 | O99: 0.18 | R99: =J99 -> 0.9
A100: R1,R2,R3,R4,R5,R6 | B100: RWHNWHV410 | C100: Natural Gas Ver4.RWH.NGA.10 | D100: PJ | E100: RESNGAEA | F100: RWH | G100: 2010 | H100: 20 | I100: 13.548917 | J100: 0.85 | K100: 1 | L100: 1 | M100: 0.1 | O100: 0.45 | R100: =J100 -> 0.85
...

Sheet ResDemand
A1: Regional Demand Projections
A3: Regional Cooling Demand PJ/a | I3: = cooling coefficient * sq ft of AC housing space * CDD | U3: = cooling coefficient * sq ft of AC housing space * CDD
C4: Region | D4: 2005 | E4: 2010 | F4: 2015 | G4: 2020 | H4: 2025 | I4: 2030 | J4: 2035 | K4: 2040 | L4: 2045 | M4: 2050 | N4: 2055 | P4: 2005 | Q4: 2010 | R4: 2015 | S4: 2020 | T4: 2025 | U4: 2030 | V4: 2035 | W4: 2040 | X4: 2045 | Y4: 2050 | Z4: 2055
A5: R1 | B5: NE | C5: New England | D5: =(1-ResCalc!D110)*ResCalc!D$89*ResCalc!D$62*ResCalc!D66*ResCalc!T44*ResCalc!D$86/'Conv Factors'!$B$17 -> #REF! | E5: =(1-ResCalc!E110)*ResCalc!E$89*ResCalc!E$62*ResCalc!E66*ResCalc!U44*ResCalc!E$86/'Conv Factors'!$B$17 -> #REF! | F5: =(1-ResCalc!F110)*ResCalc!F$89*ResCalc!F$62*ResCalc!F66*ResCalc!V44*ResCalc!F$86/'Conv Factors'!$B$17 -> #REF! | G5: =(1-ResCalc!G110)*ResCalc!G$89*ResCalc!G$62*ResCalc!G66*ResCalc!W44*ResCalc!G$86/'Conv Factors'!$B$17 -> #REF! | H5: =(1-ResCalc!H110)*ResCalc!H$89*ResCalc!H$62*ResCalc!H66*ResCalc!X44*ResCalc!H$86/'Conv Factors'!$B$17 -> #REF! | I5: =(1-ResCalc!I110)*ResCalc!I$89*ResCalc!I$62*ResCalc!I66*ResCalc!Y44*ResCalc!I$86/'Conv Factors'!$B$17 -> #REF! | J5: =(1-ResCalc!J110)*ResCalc!J$89*ResCalc!J$62*ResCalc!J66*ResCalc!Z44*ResCalc!J$86/'Conv Factors'!$B$17 -> #REF! | K5: =(1-ResCalc!K110)*ResCalc!K$89*ResCalc!K$62*ResCalc!K66*ResCalc!AA44*ResCalc!K$86/'Conv Factors'!$B$17 -> #REF! | ... N5: =(1-ResCalc!N110)*ResCalc!N$89*ResCalc!N$62*ResCalc!N66*ResCalc!AD44*ResCalc!N$86/'Conv Factors'!$B$17 -> #REF! | P5: 0 | Q5: 0 | R5: 0 | S5: 0 | T5: 0 | U5: 0 | V5: 0 | W5: 0 | X5: 0 | Y5: 0 | Z5: 0
C6: Brooklyn | D6: =(1-ResCalc!D$111)*ResCalc!D$89*ResCalc!D$62*ResCalc!D67*ResCalc!$I35*ResCalc!D86/'Conv Factors'!$B$17 -> #REF! | E6: =(1-ResCalc!E$111)*ResCalc!E$89*ResCalc!E$62*ResCalc!E67*ResCalc!$I35*ResCalc!E86/'Conv Factors'!$B$17 -> #REF! | F6: =(1-ResCalc!F$111)*ResCalc!F$89*ResCalc!F$62*ResCalc!F67*ResCalc!$I35*ResCalc!F86/'Conv Factors'!$B$17 -> #REF! | G6: =(1-ResCalc!G$111)*ResCalc!G$89*ResCalc!G$62*ResCalc!G67*ResCalc!$I35*ResCalc!G86/'Conv Factors'!$B$17 -> #REF! | H6: =(1-ResCalc!H$111)*ResCalc!H$89*ResCalc!H$62*ResCalc!H67*ResCalc!$I35*ResCalc!H86/'Conv Factors'!$B$17 -> #REF! | I6: =(1-ResCalc!I$111)*ResCalc!I$89*ResCalc!I$62*ResCalc!I67*ResCalc!$I35*ResCalc!I86/'Conv Factors'!$B$17 -> #REF! | J6: =(1-ResCalc!J$111)*ResCalc!J$89*ResCalc!J$62*ResCalc!J67*ResCalc!$I35*ResCalc!J86/'Conv Factors'!$B$17 -> #REF! | K6: =(1-ResCalc!K$111)*ResCalc!K$89*ResCalc!K$62*ResCalc!K67*ResCalc!$I35*ResCalc!K86/'Conv Factors'!$B$17 -> #REF! | ... N6: =(1-ResCalc!N$111)*ResCalc!N$89*ResCalc!N$62*ResCalc!N67*ResCalc!$I35*ResCalc!N86/'Conv Factors'!$B$17 -> #REF! | P6: 19.014618 | Q6: 19.857893 | R6: 19.753508 | S6: 20.76557 | T6: 22.351665 | U6: 23.989251 | V6: 26.123487 | W6: 28.444456 | X6: 30.669183 | Y6: 33.296053 | Z6: 36.146575
C7: Bronx | D7: =(1-ResCalc!D112)*ResCalc!D$89*ResCalc!D$62*ResCalc!D68*ResCalc!T46*ResCalc!D$86/'Conv Factors'!$B$17 -> #REF! | E7: =(1-ResCalc!E$111)*ResCalc!E$89*ResCalc!E$62*ResCalc!E68*ResCalc!$I36*ResCalc!E87/'Conv Factors'!$B$17 -> #REF! | F7: =(1-ResCalc!F$111)*ResCalc!F$89*ResCalc!F$62*ResCalc!F68*ResCalc!$I36*ResCalc!F87/'Conv Factors'!$B$17 -> #REF! | G7: =(1-ResCalc!G$111)*ResCalc!G$89*ResCalc!G$62*ResCalc!G68*ResCalc!$I36*ResCalc!G87/'Conv Factors'!$B$17 -> #REF! | H7: =(1-ResCalc!H$111)*ResCalc!H$89*ResCalc!H$62*ResCalc!H68*ResCalc!$I36*ResCalc!H87/'Conv Factors'!$B$17 -> #REF! | I7: =(1-ResCalc!I$111)*ResCalc!I$89*ResCalc!I$62*ResCalc!I68*ResCalc!$I36*ResCalc!I87/'Conv Factors'!$B$17 -> #REF! | J7: =(1-ResCalc!J$111)*ResCalc!J$89*ResCalc!J$62*ResCalc!J68*ResCalc!$I36*ResCalc!J87/'Conv Factors'!$B$17 -> #REF! | K7: =(1-ResCalc!K$111)*ResCalc!K$89*ResCalc!K$62*ResCalc!K68*ResCalc!$I36*ResCalc!K87/'Conv Factors'!$B$17 -> #REF! | L7: =(1-ResCalc!L$111)*ResCalc!L$89*ResCalc!L$62*ResCalc!L68*ResCalc!$I36*ResCalc!L87/'Conv Factors'!$B$17 -> #REF! | ... N7: =(1-ResCalc!N$111)*ResCalc!N$89*ResCalc!N$62*ResCalc!N68*ResCalc!$I36*ResCalc!N87/'Conv Factors'!$B$17 -> #REF! | P7: 10.319852 | Q7: 10.774103 | R7: 10.903684 | S7: 11.34375 | T7: 12.270381 | U7: 13.231483 | V7: 14.467141 | W7: 15.814247 | X7: 17.146671 | Y7: 18.682781 | Z7: 20.352993
C8: Manhattan | D8: =(1-ResCalc!D113)*ResCalc!D$89*ResCalc!D$62*ResCalc!D69*ResCalc!T47*ResCalc!D$86/'Conv Factors'!$B$17 -> #REF! | E8: =(1-ResCalc!E$113)*ResCalc!E$89*ResCalc!E$62*ResCalc!E69*ResCalc!$I37*ResCalc!E86/'Conv Factors'!$B$17 -> #REF! | F8: =(1-ResCalc!F$113)*ResCalc!F$89*ResCalc!F$62*ResCalc!F69*ResCalc!$I37*ResCalc!F86/'Conv Factors'!$B$17 -> #REF! | G8: =(1-ResCalc!G$113)*ResCalc!G$89*ResCalc!G$62*ResCalc!G69*ResCalc!$I37*ResCalc!G86/'Conv Factors'!$B$17 -> #REF! | H8: =(1-ResCalc!H$113)*ResCalc!H$89*ResCalc!H$62*ResCalc!H69*ResCalc!$I37*ResCalc!H86/'Conv Factors'!$B$17 -> #REF! | I8: =(1-ResCalc!I$113)*ResCalc!I$89*ResCalc!I$62*ResCalc!I69*ResCalc!$I37*ResCalc!I86/'Conv Factors'!$B$17 -> #REF! | J8: =(1-ResCalc!J$113)*ResCalc!J$89*ResCalc!J$62*ResCalc!J69*ResCalc!$I37*ResCalc!J86/'Conv Factors'!$B$17 -> #REF! | K8: =(1-ResCalc!K$113)*ResCalc!K$89*ResCalc!K$62*ResCalc!K69*ResCalc!$I37*ResCalc!K86/'Conv Factors'!$B$17 -> #REF! | L8: =(1-ResCalc!L$113)*ResCalc!L$89*ResCalc!L$62*ResCalc!L69*ResCalc!$I37*ResCalc!L86/'Conv Factors'!$B$17 -> #REF! | ... N8: =(1-ResCalc!N$113)*ResCalc!N$89*ResCalc!N$62*ResCalc!N69*ResCalc!$I37*ResCalc!N86/'Conv Factors'!$B$17 -> #REF! | P8: 12.112395 | Q8: 12.335759 | R8: 12.336515 | S8: 13.318347 | T8: 14.70742 | U8: 16.156357 | V8: 17.398601 | W8: 18.738405 | X8: 20.218227 | Y8: 21.820787 | Z8: 23.553442
C9: Staten Island | D9: =(1-ResCalc!D$114)*ResCalc!D$89*ResCalc!D$62*ResCalc!D70*ResCalc!$I38*ResCalc!D86/'Conv Factors'!$B$17 -> #REF! | E9: =(1-ResCalc!E$114)*ResCalc!E$89*ResCalc!E$62*ResCalc!E70*ResCalc!$I38*ResCalc!E86/'Conv Factors'!$B$17 -> #REF! | F9: =(1-ResCalc!F$114)*ResCalc!F$89*ResCalc!F$62*ResCalc!F70*ResCalc!$I38*ResCalc!F86/'Conv Factors'!$B$17 -> #REF! | G9: =(1-ResCalc!G$114)*ResCalc!G$89*ResCalc!G$62*ResCalc!G70*ResCalc!$I38*ResCalc!G86/'Conv Factors'!$B$17 -> #REF! | H9: =(1-ResCalc!H$114)*ResCalc!H$89*ResCalc!H$62*ResCalc!H70*ResCalc!$I38*ResCalc!H86/'Conv Factors'!$B$17 -> #REF! | I9: =(1-ResCalc!I$114)*ResCalc!I$89*ResCalc!I$62*ResCalc!I70*ResCalc!$I38*ResCalc!I86/'Conv Factors'!$B$17 -> #REF! | J9: =(1-ResCalc!J$114)*ResCalc!J$89*ResCalc!J$62*ResCalc!J70*ResCalc!$I38*ResCalc!J86/'Conv Factors'!$B$17 -> #REF! | K9: =(1-ResCalc!K$114)*ResCalc!K$89*ResCalc!K$62*ResCalc!K70*ResCalc!$I38*ResCalc!K86/'Conv Factors'!$B$17 -> #REF! | ... N9: =(1-ResCalc!N$114)*ResCalc!N$89*ResCalc!N$62*ResCalc!N70*ResCalc!$I38*ResCalc!N86/'Conv Factors'!$B$17 -> #REF! | P9: 3.5372955 | Q9: 3.64603 | R9: 3.559944 | S9: 3.9379155 | T9: 4.2010672 | U9: 4.4700174 | V9: 4.8085979 | W9: 5.1734315 | X9: 5.7507135 | Y9: 6.2547798 | Z9: 6.8023279
C10: Queens | D10: =(1-ResCalc!D115)*ResCalc!D$89*ResCalc!D$62*ResCalc!D71*ResCalc!T49*ResCalc!D$86/'Conv Factors'!$B$17 -> #REF! | E10: =(1-ResCalc!E$115)*ResCalc!E$89*ResCalc!E$62*ResCalc!E71*ResCalc!$I39*ResCalc!E86/'Conv Factors'!$B$17 -> #REF! | F10: =(1-ResCalc!F$115)*ResCalc!F$89*ResCalc!F$62*ResCalc!F71*ResCalc!$I39*ResCalc!F86/'Conv Factors'!$B$17 -> #REF! | G10: =(1-ResCalc!G$115)*ResCalc!G$89*ResCalc!G$62*ResCalc!G71*ResCalc!$I39*ResCalc!G86/'Conv Factors'!$B$17 -> #REF! | H10: =(1-ResCalc!H$115)*ResCalc!H$89*ResCalc!H$62*ResCalc!H71*ResCalc!$I39*ResCalc!H86/'Conv Factors'!$B$17 -> #REF! | I10: =(1-ResCalc!I$115)*ResCalc!I$89*ResCalc!I$62*ResCalc!I71*ResCalc!$I39*ResCalc!I86/'Conv Factors'!$B$17 -> #REF! | J10: =(1-ResCalc!J$115)*ResCalc!J$89*ResCalc!J$62*ResCalc!J71*ResCalc!$I39*ResCalc!J86/'Conv Factors'!$B$17 -> #REF! | K10: =(1-ResCalc!K$115)*ResCalc!K$89*ResCalc!K$62*ResCalc!K71*ResCalc!$I39*ResCalc!K86/'Conv Factors'!$B$17 -> #REF! | L10: =(1-ResCalc!L$115)*ResCalc!L$89*ResCalc!L$62*ResCalc!L71*ResCalc!$I39*ResCalc!L86/'Conv Factors'!$B$17 -> #REF! | ... N10: =(1-ResCalc!N$115)*ResCalc!N$89*ResCalc!N$62*ResCalc!N71*ResCalc!$I39*ResCalc!N86/'Conv Factors'!$B$17 -> #REF! | P10: 17.032266 | Q10: 17.501706 | R10: 17.547366 | S10: 18.94405 | T10: 20.869206 | U10: 22.870806 | V10: 24.722344 | W10: 26.725432 | X10: 29.123339 | Y10: 31.532659 | Z10: 34.142925
A11: R4 | C11: West North Central | D11: =(1-ResCalc!D116)*ResCalc!D$89*ResCalc!D$62*ResCalc!D72*ResCalc!T47*ResCalc!D$86/'Conv Factors'!$B$17 -> #REF! | E11: =(1-ResCalc!E116)*ResCalc!E$89*ResCalc!E$62*ResCalc!E72*ResCalc!U47*ResCalc!E$86/'Conv Factors'!$B$17 -> #REF! | F11: =(1-ResCalc!F116)*ResCalc!F$89*ResCalc!F$62*ResCalc!F72*ResCalc!V47*ResCalc!F$86/'Conv Factors'!$B$17 -> #REF! | G11: =(1-ResCalc!G116)*ResCalc!G$89*ResCalc!G$62*ResCalc!G72*ResCalc!W47*ResCalc!G$86/'Conv Factors'!$B$17 -> #REF! | H11: =(1-ResCalc!H116)*ResCalc!H$89*ResCalc!H$62*ResCalc!H72*ResCalc!X47*ResCalc!H$86/'Conv Factors'!$B$17 -> #REF! | I11: =(1-ResCalc!I116)*ResCalc!I$89*ResCalc!I$62*ResCalc!I72*ResCalc!Y47*ResCalc!I$86/'Conv Factors'!$B$17 -> #REF! | J11: =(1-ResCalc!J116)*ResCalc!J$89*ResCalc!J$62*ResCalc!J72*ResCalc!Z47*ResCalc!J$86/'Conv Factors'!$B$17 -> #REF! | K11: =(1-ResCalc!K116)*ResCalc!K$89*ResCalc!K$62*ResCalc!K72*ResCalc!AA47*ResCalc!K$86/'Conv Factors'!$B$17 -> #REF! | ... N11: =(1-ResCalc!N116)*ResCalc!N$89*ResCalc!N$62*ResCalc!N72*ResCalc!AD47*ResCalc!N$86/'Conv Factors'!$B$17 -> #REF! | P11: 0 | Q11: 0 | R11: 0 | S11: 0 | T11: 0 | U11: 0 | V11: 0 | W11: 0 | X11: 0 | Y11: 0 | Z11: 0
A12: R8 | B12: M | C12: Mountain | D12: =(1-ResCalc!D117)*ResCalc!D$89*ResCalc!D$62*ResCalc!D73*ResCalc!T51*ResCalc!D$86/'Conv Factors'!$B$17 -> #REF! | E12: =(1-ResCalc!E117)*ResCalc!E$89*ResCalc!E$62*ResCalc!E73*ResCalc!U51*ResCalc!E$86/'Conv Factors'!$B$17 -> #REF! | F12: =(1-ResCalc!F117)*ResCalc!F$89*ResCalc!F$62*ResCalc!F73*ResCalc!V51*ResCalc!F$86/'Conv Factors'!$B$17 -> #REF! | G12: =(1-ResCalc!G117)*ResCalc!G$89*ResCalc!G$62*ResCalc!G73*ResCalc!W51*ResCalc!G$86/'Conv Factors'!$B$17 -> #REF! | H12: =(1-ResCalc!H117)*ResCalc!H$89*ResCalc!H$62*ResCalc!H73*ResCalc!X51*ResCalc!H$86/'Conv Factors'!$B$17 -> #REF! | I12: =(1-ResCalc!I117)*ResCalc!I$89*ResCalc!I$62*ResCalc!I73*ResCalc!Y51*ResCalc!I$86/'Conv Factors'!$B$17 -> #REF! | J12: =(1-ResCalc!J117)*ResCalc!J$89*ResCalc!J$62*ResCalc!J73*ResCalc!Z51*ResCalc!J$86/'Conv Factors'!$B$17 -> #REF! | K12: =(1-ResCalc!K117)*ResCalc!K$89*ResCalc!K$62*ResCalc!K73*ResCalc!AA51*ResCalc!K$86/'Conv Factors'!$B$17 -> #REF! | ... N12: =(1-ResCalc!N117)*ResCalc!N$89*ResCalc!N$62*ResCalc!N73*ResCalc!AD51*ResCalc!N$86/'Conv Factors'!$B$17 -> #REF! | P12: 0 | Q12: 0 | R12: 0 | S12: 0 | T12: 0 | U12: 0 | V12: 0 | W12: 0 | X12: 0 | Y12: 0 | Z12: 0
A13: R9 | B13: P | C13: Pacific | D13: =(1-ResCalc!D118)*ResCalc!D$89*ResCalc!D$62*ResCalc!D74*ResCalc!T52*ResCalc!D$86/'Conv Factors'!$B$17 -> #REF! | E13: =(1-ResCalc!E118)*ResCalc!E$89*ResCalc!E$62*ResCalc!E74*ResCalc!U52*ResCalc!E$86/'Conv Factors'!$B$17 -> #REF! | F13: =(1-ResCalc!F118)*ResCalc!F$89*ResCalc!F$62*ResCalc!F74*ResCalc!V52*ResCalc!F$86/'Conv Factors'!$B$17 -> #REF! | G13: =(1-ResCalc!G118)*ResCalc!G$89*ResCalc!G$62*ResCalc!G74*ResCalc!W52*ResCalc!G$86/'Conv Factors'!$B$17 -> #REF! | H13: =(1-ResCalc!H118)*ResCalc!H$89*ResCalc!H$62*ResCalc!H74*ResCalc!X52*ResCalc!H$86/'Conv Factors'!$B$17 -> #REF! | I13: =(1-ResCalc!I118)*ResCalc!I$89*ResCalc!I$62*ResCalc!I74*ResCalc!Y52*ResCalc!I$86/'Conv Factors'!$B$17 -> #REF! | J13: =(1-ResCalc!J118)*ResCalc!J$89*ResCalc!J$62*ResCalc!J74*ResCalc!Z52*ResCalc!J$86/'Conv Factors'!$B$17 -> #REF! | K13: =(1-ResCalc!K118)*ResCalc!K$89*ResCalc!K$62*ResCalc!K74*ResCalc!AA52*ResCalc!K$86/'Conv Factors'!$B$17 -> #REF! | ... N13: =(1-ResCalc!N118)*ResCalc!N$89*ResCalc!N$62*ResCalc!N74*ResCalc!AD52*ResCalc!N$86/'Conv Factors'!$B$17 -> #REF! | P13: 0 | Q13: 0 | R13: 0 | S13: 0 | T13: 0 | U13: 0 | V13: 0 | W13: 0 | X13: 0 | Y13: 0 | Z13: 0
C14: Total NYC | D14: =SUM(D6:D10) -> #REF! | E14: =SUM(E6:E10) -> #REF! | F14: =SUM(F6:F10) -> #REF! | G14: =SUM(G6:G10) -> #REF! | H14: =SUM(H6:H10) -> #REF! | I14: =SUM(I6:I10) -> #REF! | J14: =SUM(J6:J10) -> #REF! | K14: =SUM(K6:K10) -> #REF! | ... N14: =SUM(N6:N10) -> #REF! | P14: 62.016425 | Q14: 64.115491 | R14: 64.101017 | S14: 68.309632 | T14: 74.39974 | U14: 80.717915 | V14: 87.520171 | W14: 94.895972 | X14: 102.90813 | Y14: 111.58706 | Z14: 120.99826
A15: Cooling demand can be changed through population (Pop:C4-N12) or cooling degree days(ResCalc:I37-I45) or Housholds without AC (ResCalc:C125-N133)
A17: Regional Heating Demand PJ/a | I17: = heating coefficient * sq ft of heated housing space * HDD | U17: = heating coefficient * sq ft of heated housing space * HDD
A18: R1 | B18: NE | C18: New England | D18: =ResCalc!D$90*ResCalc!D$62*ResCalc!D66*ResCalc!T32*ResCalc!D$87/'Conv Factors'!$B$17 -> #REF! | E18: =ResCalc!E$90*ResCalc!E$62*ResCalc!E66*ResCalc!U32*ResCalc!E$87/'Conv Factors'!$B$17 -> #REF! | F18: =ResCalc!F$90*ResCalc!F$62*ResCalc!F66*ResCalc!V32*ResCalc!F$87/'Conv Factors'!$B$17 -> #REF! | G18: =ResCalc!G$90*ResCalc!G$62*ResCalc!G66*ResCalc!W32*ResCalc!G$87/'Conv Factors'!$B$17 -> #REF! | H18: =ResCalc!H$90*ResCalc!H$62*ResCalc!H66*ResCalc!X32*ResCalc!H$87/'Conv Factors'!$B$17 -> #REF! | I18: =ResCalc!I$90*ResCalc!I$62*ResCalc!I66*ResCalc!Y32*ResCalc!I$87/'Conv Factors'!$B$17 -> #REF! | J18: =ResCalc!J$90*ResCalc!J$62*ResCalc!J66*ResCalc!Z32*ResCalc!J$87/'Conv Factors'!$B$17 -> #REF! | K18: =ResCalc!K$90*ResCalc!K$62*ResCalc!K66*ResCalc!AA32*ResCalc!K$87/'Conv Factors'!$B$17 -> #REF! | ... N18: =ResCalc!N$90*ResCalc!N$62*ResCalc!N66*ResCalc!AD32*ResCalc!N$87/'Conv Factors'!$B$17 -> #REF! | P18: 0 | Q18: 0 | R18: 0 | S18: 0 | T18: 0 | U18: 0 | V18: 0 | W18: 0 | X18: 0 | Y18: 0 | Z18: 0
C19: Brooklyn | D19: =ResCalc!D$90*ResCalc!D$62*ResCalc!D67*ResCalc!$J35*ResCalc!D87/'Conv Factors'!$B$17 -> #REF! | E19: ='2010 Fuel Share'!$Q$73*ResCalc!E$90*ResCalc!E$62*ResCalc!E67*ResCalc!$J35*ResCalc!E87/'Conv Factors'!$B$17 -> #REF! | F19: ='2010 Fuel Share'!$Q$73*ResCalc!F$90*ResCalc!F$62*ResCalc!F67*ResCalc!$J35*ResCalc!F87/'Conv Factors'!$B$17 -> #REF! | G19: ='2010 Fuel Share'!$Q$73*ResCalc!G$90*ResCalc!G$62*ResCalc!G67*ResCalc!$J35*ResCalc!G87/'Conv Factors'!$B$17 -> #REF! | H19: ='2010 Fuel Share'!$Q$73*ResCalc!H$90*ResCalc!H$62*ResCalc!H67*ResCalc!$J35*ResCalc!H87/'Conv Factors'!$B$17 -> #REF! | I19: ='2010 Fuel Share'!$Q$73*ResCalc!I$90*ResCalc!I$62*ResCalc!I67*ResCalc!$J35*ResCalc!I87/'Conv Factors'!$B$17 -> #REF! | J19: ='2010 Fuel Share'!$Q$73*ResCalc!J$90*ResCalc!J$62*ResCalc!J67*ResCalc!$J35*ResCalc!J87/'Conv Factors'!$B$17 -> #REF! | K19: ='2010 Fuel Share'!$Q$73*ResCalc!K$90*ResCalc!K$62*ResCalc!K67*ResCalc!$J35*ResCalc!K87/'Conv Factors'!$B$17 -> #REF! | L19: ='2010 Fuel Share'!$Q$73*ResCalc!L$90*ResCalc!L$62*ResCalc!L67*ResCalc!$J35*ResCalc!L87/'Conv Factors'!$B$17 -> #REF! | ... N19: ='2010 Fuel Share'!$Q$73*ResCalc!N$90*ResCalc!N$62*ResCalc!N67*ResCalc!$J35*ResCalc!N87/'Conv Factors'!$B$17 -> #REF! | P19: 49.117207 | Q19: 46.877785 | R19: 46.67418 | S19: 42.154374 | T19: 41.043591 | U19: 39.860924 | V19: 38.639627 | W19: 37.420208 | X19: 35.891524 | Y19: 34.658496 | Z19: 33.466633
C20: Bronx | D20: =ResCalc!D$90*ResCalc!D$62*ResCalc!D68*ResCalc!$J36*ResCalc!D87/'Conv Factors'!$B$17 -> #REF! | E20: ='2010 Fuel Share'!$R$73*ResCalc!E$90*ResCalc!E$62*ResCalc!E68*ResCalc!$J36*ResCalc!E87/'Conv Factors'!$B$17 -> #REF! | F20: ='2010 Fuel Share'!$R$73*ResCalc!F$90*ResCalc!F$62*ResCalc!F68*ResCalc!$J36*ResCalc!F87/'Conv Factors'!$B$17 -> #REF! | G20: ='2010 Fuel Share'!$R$73*ResCalc!G$90*ResCalc!G$62*ResCalc!G68*ResCalc!$J36*ResCalc!G87/'Conv Factors'!$B$17 -> #REF! | H20: ='2010 Fuel Share'!$R$73*ResCalc!H$90*ResCalc!H$62*ResCalc!H68*ResCalc!$J36*ResCalc!H87/'Conv Factors'!$B$17 -> #REF! | I20: ='2010 Fuel Share'!$R$73*ResCalc!I$90*ResCalc!I$62*ResCalc!I68*ResCalc!$J36*ResCalc!I87/'Conv Factors'!$B$17 -> #REF! | J20: ='2010 Fuel Share'!$R$73*ResCalc!J$90*ResCalc!J$62*ResCalc!J68*ResCalc!$J36*ResCalc!J87/'Conv Factors'!$B$17 -> #REF! | K20: ='2010 Fuel Share'!$R$73*ResCalc!K$90*ResCalc!K$62*ResCalc!K68*ResCalc!$J36*ResCalc!K87/'Conv Factors'!$B$17 -> #REF! | L20: ='2010 Fuel Share'!$R$73*ResCalc!L$90*ResCalc!L$62*ResCalc!L68*ResCalc!$J36*ResCalc!L87/'Conv Factors'!$B$17 -> #REF! | ... N20: ='2010 Fuel Share'!$R$73*ResCalc!N$90*ResCalc!N$62*ResCalc!N68*ResCalc!$J36*ResCalc!N87/'Conv Factors'!$B$17 -> #REF! | P20: 26.657506 | Q20: 27.321821 | R20: 27.675808 | S20: 24.737171 | T20: 24.204054 | U20: 23.617494 | V20: 22.98683 | W20: 22.34867 | X20: 21.555798 | Y20: 20.890705 | Z20: 20.242667
C21: Manhattan | D21: =ResCalc!D$90*ResCalc!D$62*ResCalc!D69*ResCalc!$J37*ResCalc!D87/'Conv Factors'!$B$17 -> #REF! | E21: ='2010 Fuel Share'!$S$73*ResCalc!E$90*ResCalc!E$62*ResCalc!E69*ResCalc!$J37*ResCalc!E87/'Conv Factors'!$B$17 -> #REF! | F21: ='2010 Fuel Share'!$S$73*ResCalc!F$90*ResCalc!F$62*ResCalc!F69*ResCalc!$J37*ResCalc!F87/'Conv Factors'!$B$17 -> #REF! | G21: ='2010 Fuel Share'!$S$73*ResCalc!G$90*ResCalc!G$62*ResCalc!G69*ResCalc!$J37*ResCalc!G87/'Conv Factors'!$B$17 -> #REF! | H21: ='2010 Fuel Share'!$S$73*ResCalc!H$90*ResCalc!H$62*ResCalc!H69*ResCalc!$J37*ResCalc!H87/'Conv Factors'!$B$17 -> #REF! | I21: ='2010 Fuel Share'!$S$73*ResCalc!I$90*ResCalc!I$62*ResCalc!I69*ResCalc!$J37*ResCalc!I87/'Conv Factors'!$B$17 -> #REF! | J21: ='2010 Fuel Share'!$S$73*ResCalc!J$90*ResCalc!J$62*ResCalc!J69*ResCalc!$J37*ResCalc!J87/'Conv Factors'!$B$17 -> #REF! | K21: ='2010 Fuel Share'!$S$73*ResCalc!K$90*ResCalc!K$62*ResCalc!K69*ResCalc!$J37*ResCalc!K87/'Conv Factors'!$B$17 -> #REF! | L21: ='2010 Fuel Share'!$S$73*ResCalc!L$90*ResCalc!L$62*ResCalc!L69*ResCalc!$J37*ResCalc!L87/'Conv Factors'!$B$17 -> #REF! | ... N21: ='2010 Fuel Share'!$S$73*ResCalc!N$90*ResCalc!N$62*ResCalc!N69*ResCalc!$J37*ResCalc!N87/'Conv Factors'!$B$17 -> #REF! | P21: 31.224199 | Q21: 45.245792 | R21: 45.230066 | S21: 40.515137 | T21: 39.130532 | U21: 37.706909 | V21: 36.146223 | W21: 34.624858 | X21: 33.233767 | Y21: 31.903195 | Z21: 30.629933
C22: Staten Island | D22: =ResCalc!D$90*ResCalc!D$62*ResCalc!D70*ResCalc!$J38*ResCalc!D87/'Conv Factors'!$B$17 -> #REF! | E22: ='2010 Fuel Share'!$U$73*ResCalc!E$90*ResCalc!E$62*ResCalc!E70*ResCalc!$J38*ResCalc!E87/'Conv Factors'!$B$17 -> #REF! | F22: ='2010 Fuel Share'!$U$73*ResCalc!F$90*ResCalc!F$62*ResCalc!F70*ResCalc!$J38*ResCalc!F87/'Conv Factors'!$B$17 -> #REF! | G22: ='2010 Fuel Share'!$U$73*ResCalc!G$90*ResCalc!G$62*ResCalc!G70*ResCalc!$J38*ResCalc!G87/'Conv Factors'!$B$17 -> #REF! | H22: ='2010 Fuel Share'!$U$73*ResCalc!H$90*ResCalc!H$62*ResCalc!H70*ResCalc!$J38*ResCalc!H87/'Conv Factors'!$B$17 -> #REF! | I22: ='2010 Fuel Share'!$U$73*ResCalc!I$90*ResCalc!I$62*ResCalc!I70*ResCalc!$J38*ResCalc!I87/'Conv Factors'!$B$17 -> #REF! | J22: ='2010 Fuel Share'!$U$73*ResCalc!J$90*ResCalc!J$62*ResCalc!J70*ResCalc!$J38*ResCalc!J87/'Conv Factors'!$B$17 -> #REF! | K22: ='2010 Fuel Share'!$U$73*ResCalc!K$90*ResCalc!K$62*ResCalc!K70*ResCalc!$J38*ResCalc!K87/'Conv Factors'!$B$17 -> #REF! | L22: ='2010 Fuel Share'!$U$73*ResCalc!L$90*ResCalc!L$62*ResCalc!L70*ResCalc!$J38*ResCalc!L87/'Conv Factors'!$B$17 -> #REF! | ... N22: ='2010 Fuel Share'!$U$73*ResCalc!N$90*ResCalc!N$62*ResCalc!N70*ResCalc!$J38*ResCalc!N87/'Conv Factors'!$B$17 -> #REF! | P22: 9.1372899 | Q22: 8.7463733 | R22: 8.5363725 | S22: 7.879371 | T22: 7.6036384 | U22: 7.3209298 | V22: 7.0104615 | W22: 6.7083178 | X22: 6.6334246 | Y22: 6.4173445 | Z22: 6.2076724
C23: Queens | D23: =ResCalc!D$90*ResCalc!D$62*ResCalc!D71*ResCalc!$J39*ResCalc!D87/'Conv Factors'!$B$17 -> #REF! | E23: ='2010 Fuel Share'!$T$73*ResCalc!E$90*ResCalc!E$62*ResCalc!E71*ResCalc!$J39*ResCalc!E87/'Conv Factors'!$B$17 -> #REF! | F23: ='2010 Fuel Share'!$T$73*ResCalc!F$90*ResCalc!F$62*ResCalc!F71*ResCalc!$J39*ResCalc!F87/'Conv Factors'!$B$17 -> #REF! | G23: ='2010 Fuel Share'!$T$73*ResCalc!G$90*ResCalc!G$62*ResCalc!G71*ResCalc!$J39*ResCalc!G87/'Conv Factors'!$B$17 -> #REF! | H23: ='2010 Fuel Share'!$T$73*ResCalc!H$90*ResCalc!H$62*ResCalc!H71*ResCalc!$J39*ResCalc!H87/'Conv Factors'!$B$17 -> #REF! | I23: ='2010 Fuel Share'!$T$73*ResCalc!I$90*ResCalc!I$62*ResCalc!I71*ResCalc!$J39*ResCalc!I87/'Conv Factors'!$B$17 -> #REF! | J23: ='2010 Fuel Share'!$T$73*ResCalc!J$90*ResCalc!J$62*ResCalc!J71*ResCalc!$J39*ResCalc!J87/'Conv Factors'!$B$17 -> #REF! | K23: ='2010 Fuel Share'!$T$73*ResCalc!K$90*ResCalc!K$62*ResCalc!K71*ResCalc!$J39*ResCalc!K87/'Conv Factors'!$B$17 -> #REF! | L23: ='2010 Fuel Share'!$T$73*ResCalc!L$90*ResCalc!L$62*ResCalc!L71*ResCalc!$J39*ResCalc!L87/'Conv Factors'!$B$17 -> #REF! | ... N23: ='2010 Fuel Share'!$T$73*ResCalc!N$90*ResCalc!N$62*ResCalc!N71*ResCalc!$J39*ResCalc!N87/'Conv Factors'!$B$17 -> #REF! | P23: 43.996536 | Q23: 23.543552 | R23: 23.595324 | S23: 21.13582 | T23: 20.364065 | U23: 19.576644 | V23: 18.837251 | W23: 18.111707 | X23: 17.557269 | Y23: 16.908445 | Z23: 16.284397
C24: West North Central | D24: =ResCalc!D$90*ResCalc!D$62*ResCalc!D72*ResCalc!T35*ResCalc!D$87/'Conv Factors'!$B$17 -> #REF! | E24: =ResCalc!E$90*ResCalc!E$62*ResCalc!E72*ResCalc!U35*ResCalc!E$87/'Conv Factors'!$B$17 -> #REF! | F24: =ResCalc!F$90*ResCalc!F$62*ResCalc!F72*ResCalc!V35*ResCalc!F$87/'Conv Factors'!$B$17 -> #REF! | G24: =ResCalc!G$90*ResCalc!G$62*ResCalc!G72*ResCalc!W35*ResCalc!G$87/'Conv Factors'!$B$17 -> #REF! | H24: =ResCalc!H$90*ResCalc!H$62*ResCalc!H72*ResCalc!X35*ResCalc!H$87/'Conv Factors'!$B$17 -> #REF! | I24: =ResCalc!I$90*ResCalc!I$62*ResCalc!I72*ResCalc!Y35*ResCalc!I$87/'Conv Factors'!$B$17 -> #REF! | J24: =ResCalc!J$90*ResCalc!J$62*ResCalc!J72*ResCalc!Z35*ResCalc!J$87/'Conv Factors'!$B$17 -> #REF! | K24: =ResCalc!K$90*ResCalc!K$62*ResCalc!K72*ResCalc!AA35*ResCalc!K$87/'Conv Factors'!$B$17 -> #REF! | ... N24: =ResCalc!N$90*ResCalc!N$62*ResCalc!N72*ResCalc!AD35*ResCalc!N$87/'Conv Factors'!$B$17 -> #REF! | P24: 0 | Q24: 0 | R24: 0 | S24: 0 | T24: 0 | U24: 0 | V24: 0 | W24: 0 | X24: 0 | Y24: 0 | Z24: 0
B25: M | C25: Mountain | D25: =ResCalc!D$90*ResCalc!D$62*ResCalc!D73*ResCalc!T39*ResCalc!D$87/'Conv Factors'!$B$17*0.9 -> #REF! | E25: =ResCalc!E$90*ResCalc!E$62*ResCalc!E73*ResCalc!U39*ResCalc!E$87/'Conv Factors'!$B$17*0.9 -> #REF! | F25: =ResCalc!F$90*ResCalc!F$62*ResCalc!F73*ResCalc!V39*ResCalc!F$87/'Conv Factors'!$B$17*0.9 -> #REF! | G25: =ResCalc!G$90*ResCalc!G$62*ResCalc!G73*ResCalc!W39*ResCalc!G$87/'Conv Factors'!$B$17*0.9 -> #REF! | H25: =ResCalc!H$90*ResCalc!H$62*ResCalc!H73*ResCalc!X39*ResCalc!H$87/'Conv Factors'!$B$17*0.9 -> #REF! | I25: =ResCalc!I$90*ResCalc!I$62*ResCalc!I73*ResCalc!Y39*ResCalc!I$87/'Conv Factors'!$B$17*0.9 -> #REF! | J25: =ResCalc!J$90*ResCalc!J$62*ResCalc!J73*ResCalc!Z39*ResCalc!J$87/'Conv Factors'!$B$17*0.9 -> #REF! | K25: =ResCalc!K$90*ResCalc!K$62*ResCalc!K73*ResCalc!AA39*ResCalc!K$87/'Conv Factors'!$B$17*0.9 -> #REF! | ... N25: =ResCalc!N$90*ResCalc!N$62*ResCalc!N73*ResCalc!AD39*ResCalc!N$87/'Conv Factors'!$B$17*0.9 -> #REF! | P25: 0 | Q25: 0 | R25: 0 | S25: 0 | T25: 0 | U25: 0 | V25: 0 | W25: 0 | X25: 0 | Y25: 0 | Z25: 0
B26: P | C26: Pacific | D26: =ResCalc!D$90*ResCalc!D$62*ResCalc!D74*ResCalc!T40*ResCalc!D$87/'Conv Factors'!$B$17*0.8 -> #REF! | E26: =ResCalc!E$90*ResCalc!E$62*ResCalc!E74*ResCalc!U40*ResCalc!E$87/'Conv Factors'!$B$17*0.8 -> #REF! | F26: =ResCalc!F$90*ResCalc!F$62*ResCalc!F74*ResCalc!V40*ResCalc!F$87/'Conv Factors'!$B$17*0.8 -> #REF! | G26: =ResCalc!G$90*ResCalc!G$62*ResCalc!G74*ResCalc!W40*ResCalc!G$87/'Conv Factors'!$B$17*0.8 -> #REF! | H26: =ResCalc!H$90*ResCalc!H$62*ResCalc!H74*ResCalc!X40*ResCalc!H$87/'Conv Factors'!$B$17*0.8 -> #REF! | I26: =ResCalc!I$90*ResCalc!I$62*ResCalc!I74*ResCalc!Y40*ResCalc!I$87/'Conv Factors'!$B$17*0.8 -> #REF! | J26: =ResCalc!J$90*ResCalc!J$62*ResCalc!J74*ResCalc!Z40*ResCalc!J$87/'Conv Factors'!$B$17*0.8 -> #REF! | K26: =ResCalc!K$90*ResCalc!K$62*ResCalc!K74*ResCalc!AA40*ResCalc!K$87/'Conv Factors'!$B$17*0.8 -> #REF! | ... N26: =ResCalc!N$90*ResCalc!N$62*ResCalc!N74*ResCalc!AD40*ResCalc!N$87/'Conv Factors'!$B$17*0.8 -> #REF! | P26: 0 | Q26: 0 | R26: 0 | S26: 0 | T26: 0 | U26: 0 | V26: 0 | W26: 0 | X26: 0 | Y26: 0 | Z26: 0
C27: Total NYC | D27: =SUM(D19:D23) -> #REF! | E27: =SUM(E19:E23) -> #REF! | F27: =SUM(F19:F23) -> #REF! | G27: =SUM(G19:G23) -> #REF! | H27: =SUM(H19:H23) -> #REF! | I27: =SUM(I19:I23) -> #REF! | J27: =SUM(J19:J23) -> #REF! | K27: =SUM(K19:K23) -> #REF! | ... N27: =SUM(N19:N23) -> #REF! | P27: 160.13274 | Q27: 151.73532 | R27: 151.71175 | S27: 136.42187 | T27: 132.34588 | U27: 128.0829 | V27: 123.62039 | W27: 119.21376 | X27: 114.87178 | Y27: 110.77819 | Z27: 106.8313
A28: Heating demand can be changed through population (Pop:C4-N12) or heating degree days(ResCalc:J37-J45)
A30: Regional Refrigeration Demand million units/yr | I30: = # households * # refrigerators/household | U30: = # households * # refrigerators/household
B31: NE | C31: New England | D31: =USDemand!C$11*ResCalc!D66/ResCalc!D$75 -> 0 | E31: =USDemand!D$11*ResCalc!E66/ResCalc!E$75 -> 0 | F31: =USDemand!E$11*ResCalc!F66/ResCalc!F$75 -> 0 | G31: =USDemand!F$11*ResCalc!G66/ResCalc!G$75 -> 0 | H31: =USDemand!G$11*ResCalc!H66/ResCalc!H$75 -> 0 | I31: =USDemand!H$11*ResCalc!I66/ResCalc!I$75 -> 0 | J31: =USDemand!I$11*ResCalc!J66/ResCalc!J$75 -> 0 | K31: =USDemand!J$11*ResCalc!K66/ResCalc!K$75 -> 0 | ... N31: =USDemand!M$11*ResCalc!N66/ResCalc!N$75 -> 0 | P31: 0 | Q31: 0 | R31: 0 | S31: 0 | T31: 0 | U31: 0 | V31: 0 | W31: 0 | X31: 0 | Y31: 0 | Z31: 0
B32: MA | C32: Middle Atlantic | D32: =USDemand!C$11*ResCalc!D67/ResCalc!D$75 -> 52.671675 | E32: =USDemand!D$11*ResCalc!E67/ResCalc!E$75 -> 58.611466 | F32: =USDemand!E$11*ResCalc!F67/ResCalc!F$75 -> 65.191962 | G32: =USDemand!F$11*ResCalc!G67/ResCalc!G$75 -> 71.75296 | H32: =USDemand!G$11*ResCalc!H67/ResCalc!H$75 -> 78.085431 | I32: =USDemand!H$11*ResCalc!I67/ResCalc!I$75 -> 84.686724 | J32: =USDemand!I$11*ResCalc!J67/ResCalc!J$75 -> 91.367017 | K32: =USDemand!J$11*ResCalc!K67/ResCalc!K$75 -> 95.651077 | ... N32: =USDemand!M$11*ResCalc!N67/ResCalc!N$75 -> 108.06303 | P32: 52.671675 | Q32: 58.611466 | R32: 65.191962 | S32: 71.75296 | T32: 78.085431 | U32: 84.686724 | V32: 91.367017 | W32: 95.651077 | X32: 99.175115 | Y32: 103.52558 | Z32: 108.06303
B33: SA | C33: South Atlantic | D33: =USDemand!C$11*ResCalc!D68/ResCalc!D$75 -> 28.586632 | E33: =USDemand!D$11*ResCalc!E68/ResCalc!E$75 -> 31.800251 | F33: =USDemand!E$11*ResCalc!F68/ResCalc!F$75 -> 35.985129 | G33: =USDemand!F$11*ResCalc!G68/ResCalc!G$75 -> 39.19698 | H33: =USDemand!G$11*ResCalc!H68/ResCalc!H$75 -> 42.866515 | I33: =USDemand!H$11*ResCalc!I68/ResCalc!I$75 -> 46.709711 | J33: =USDemand!I$11*ResCalc!J68/ResCalc!J$75 -> 50.598892 | K33: =USDemand!J$11*ResCalc!K68/ResCalc!K$75 -> 53.179072 | ... N33: =USDemand!M$11*ResCalc!N68/ResCalc!N$75 -> 60.84687 | P33: 28.586632 | Q33: 31.800251 | R33: 35.985129 | S33: 39.19698 | T33: 42.866515 | U33: 46.709711 | V33: 50.598892 | W33: 53.179072 | X33: 55.447288 | Y33: 58.089341 | Z33: 60.84687
B34: ESC | C34: East South Central | D34: =USDemand!C$11*ResCalc!D69/ResCalc!D$75 -> 33.483803 | E34: =USDemand!D$11*ResCalc!E69/ResCalc!E$75 -> 36.40955 | F34: =USDemand!E$11*ResCalc!F69/ResCalc!F$75 -> 40.65989 | G34: =USDemand!F$11*ResCalc!G69/ResCalc!G$75 -> 44.384988 | H34: =USDemand!G$11*ResCalc!H69/ResCalc!H$75 -> 47.913956 | I34: =USDemand!H$11*ResCalc!I69/ResCalc!I$75 -> 51.559717 | J34: =USDemand!I$11*ResCalc!J69/ResCalc!J$75 -> 55.009927 | K34: =USDemand!J$11*ResCalc!K69/ResCalc!K$75 -> 56.963057 | ... N34: =USDemand!M$11*ResCalc!N69/ResCalc!N$75 -> 63.655036 | P34: 33.483803 | Q34: 36.40955 | R34: 40.65989 | S34: 44.384988 | T34: 47.913956 | U34: 51.559717 | V34: 55.009927 | W34: 56.963057 | X34: 59.103336 | Y34: 61.332936 | Z34: 63.655036
B35: ENC | C35: East North Central | D35: =USDemand!C$11*ResCalc!D70/ResCalc!D$75 -> 9.7985289 | E35: =USDemand!D$11*ResCalc!E70/ResCalc!E$75 -> 10.761422 | F35: =USDemand!E$11*ResCalc!F70/ResCalc!F$75 -> 11.733211 | G35: =USDemand!F$11*ResCalc!G70/ResCalc!G$75 -> 13.198205 | H35: =USDemand!G$11*ResCalc!H70/ResCalc!H$75 -> 14.235485 | I35: =USDemand!H$11*ResCalc!I70/ResCalc!I$75 -> 15.305953 | J35: =USDemand!I$11*ResCalc!J70/ResCalc!J$75 -> 16.312829 | K35: =USDemand!J$11*ResCalc!K70/ResCalc!K$75 -> 16.87421 | ... N35: =USDemand!M$11*ResCalc!N70/ResCalc!N$75 -> 19.725138 | P35: 9.7985289 | Q35: 10.761422 | R35: 11.733211 | S35: 13.198205 | T35: 14.235485 | U35: 15.305953 | V35: 16.312829 | W35: 16.87421 | X35: 18.037434 | Y35: 18.863378 | Z35: 19.725138 | AA35: 219.39124
B36: WSC | C36: West South Central | D36: =USDemand!C$11*ResCalc!D71/ResCalc!D$75 -> 47.180437 | E36: =USDemand!D$11*ResCalc!E71/ResCalc!E$75 -> 51.657075 | F36: =USDemand!E$11*ResCalc!F71/ResCalc!F$75 -> 57.834321 | G36: =USDemand!F$11*ResCalc!G71/ResCalc!G$75 -> 63.133318 | H36: =USDemand!G$11*ResCalc!H71/ResCalc!H$75 -> 67.987875 | I36: =USDemand!H$11*ResCalc!I71/ResCalc!I$75 -> 72.98751 | J36: =USDemand!I$11*ResCalc!J71/ResCalc!J$75 -> 78.165727 | K36: =USDemand!J$11*ResCalc!K71/ResCalc!K$75 -> 81.242895 | ... N36: =USDemand!M$11*ResCalc!N71/ResCalc!N$75 -> 92.273951 | P36: 47.180437 | Q36: 51.657075 | R36: 57.834321 | S36: 63.133318 | T36: 67.987875 | U36: 72.98751 | V36: 78.165727 | W36: 81.242895 | X36: 85.135386 | Y36: 88.630653 | Z36: 92.273951 | AA36: 208.35668
B37: WNC | C37: West North Central | D37: =USDemand!C$11*ResCalc!D72/ResCalc!D$75 -> 0 | E37: =USDemand!D$11*ResCalc!E72/ResCalc!E$75 -> 0 | F37: =USDemand!E$11*ResCalc!F72/ResCalc!F$75 -> 0 | G37: =USDemand!F$11*ResCalc!G72/ResCalc!G$75 -> 0 | H37: =USDemand!G$11*ResCalc!H72/ResCalc!H$75 -> 0 | I37: =USDemand!H$11*ResCalc!I72/ResCalc!I$75 -> 0 | J37: =USDemand!I$11*ResCalc!J72/ResCalc!J$75 -> 0 | K37: =USDemand!J$11*ResCalc!K72/ResCalc!K$75 -> 0 | ... N37: =USDemand!M$11*ResCalc!N72/ResCalc!N$75 -> 0 | P37: 0 | Q37: 0 | R37: 0 | S37: 0 | T37: 0 | U37: 0 | V37: 0 | W37: 0 | X37: 0 | Y37: 0 | Z37: 0
B38: M | C38: Mountain | D38: =USDemand!C$11*ResCalc!D73/ResCalc!D$75 -> 0 | E38: =USDemand!D$11*ResCalc!E73/ResCalc!E$75 -> 0 | F38: =USDemand!E$11*ResCalc!F73/ResCalc!F$75 -> 0 | G38: =USDemand!F$11*ResCalc!G73/ResCalc!G$75 -> 0 | H38: =USDemand!G$11*ResCalc!H73/ResCalc!H$75 -> 0 | I38: =USDemand!H$11*ResCalc!I73/ResCalc!I$75 -> 0 | J38: =USDemand!I$11*ResCalc!J73/ResCalc!J$75 -> 0 | K38: =USDemand!J$11*ResCalc!K73/ResCalc!K$75 -> 0 | ... N38: =USDemand!M$11*ResCalc!N73/ResCalc!N$75 -> 0 | P38: 0 | Q38: 0 | R38: 0 | S38: 0 | T38: 0 | U38: 0 | V38: 0 | W38: 0 | X38: 0 | Y38: 0 | Z38: 0
B39: P | C39: Pacific | D39: =USDemand!C$11*ResCalc!D74/ResCalc!D$75 -> 0 | E39: =USDemand!D$11*ResCalc!E74/ResCalc!E$75 -> 0 | F39: =USDemand!E$11*ResCalc!F74/ResCalc!F$75 -> 0 | G39: =USDemand!F$11*ResCalc!G74/ResCalc!G$75 -> 0 | H39: =USDemand!G$11*ResCalc!H74/ResCalc!H$75 -> 0 | I39: =USDemand!H$11*ResCalc!I74/ResCalc!I$75 -> 0 | J39: =USDemand!I$11*ResCalc!J74/ResCalc!J$75 -> 0 | K39: =USDemand!J$11*ResCalc!K74/ResCalc!K$75 -> 0 | ... N39: =USDemand!M$11*ResCalc!N74/ResCalc!N$75 -> 0 | P39: 0 | Q39: 0 | R39: 0 | S39: 0 | T39: 0 | U39: 0 | V39: 0 | W39: 0 | X39: 0 | Y39: 0 | Z39: 0
C40: Total US | D40: =SUM(D31:D39) -> 171.72108 | E40: =SUM(E31:E39) -> 189.23976 | F40: =SUM(F31:F39) -> 211.40451 | G40: =SUM(G31:G39) -> 231.66645 | H40: =SUM(H31:H39) -> 251.08926 | I40: =SUM(I31:I39) -> 271.24961 | J40: =SUM(J31:J39) -> 291.45439 | K40: =SUM(K31:K39) -> 303.91031 | ... N40: =SUM(N31:N39) -> 344.56402 | P40: 171.72108 | Q40: 189.23976 | R40: 211.40451 | S40: 231.66645 | T40: 251.08926 | U40: 271.24961 | V40: 291.45439 | W40: 303.91031 | X40: 316.89856 | Y40: 330.44189 | Z40: 344.56402
C41: Check From AEO data | D41: =USDemand!C254 -> 137.59496 | E41: =USDemand!D254 -> 142.74478 | F41: =USDemand!E254 -> 146.25145 | G41: =USDemand!F254 -> 154.08333 | H41: =USDemand!G254 -> 161.34395 | I41: =USDemand!H254 -> 168.5638 | J41: =USDemand!I254 -> 175.27843 | P41: 137.59496 | Q41: 142.74478 | R41: 146.25145 | S41: 154.08333 | T41: 161.34395 | U41: 168.5638 | V41: 175.27843
A42: Regional Freezer Demand million units/yr | I42: = # households * # freezers/household | U42: = # households * # freezers/household
B43: NE | C43: New England | D43: =USDemand!C$5*ResCalc!D66/ResCalc!D$75 -> 0 | E43: =USDemand!D$5*ResCalc!E66/ResCalc!E$75 -> 0 | F43: =USDemand!E$5*ResCalc!F66/ResCalc!F$75 -> 0 | G43: =USDemand!F$5*ResCalc!G66/ResCalc!G$75 -> 0 | H43: =USDemand!G$5*ResCalc!H66/ResCalc!H$75 -> 0 | I43: =USDemand!H$5*ResCalc!I66/ResCalc!I$75 -> 0 | J43: =USDemand!I$5*ResCalc!J66/ResCalc!J$75 -> 0 | K43: =USDemand!J$5*ResCalc!K66/ResCalc!K$75 -> 0 | ... N43: =USDemand!M$5*ResCalc!N66/ResCalc!N$75 -> 0 | P43: 0 | Q43: 0 | R43: 0 | S43: 0 | T43: 0 | U43: 0 | V43: 0 | W43: 0 | X43: 0 | Y43: 0 | Z43: 0
B44: MA | C44: Middle Atlantic | D44: =USDemand!C$5*ResCalc!D67/ResCalc!D$75 -> 15.597742 | E44: =USDemand!D$5*ResCalc!E67/ResCalc!E$75 -> 15.764637 | F44: =USDemand!E$5*ResCalc!F67/ResCalc!F$75 -> 16.613028 | G44: =USDemand!F$5*ResCalc!G67/ResCalc!G$75 -> 17.403036 | H44: =USDemand!G$5*ResCalc!H67/ResCalc!H$75 -> 17.234363 | I44: =USDemand!H$5*ResCalc!I67/ResCalc!I$75 -> 17.144148 | J44: =USDemand!I$5*ResCalc!J67/ResCalc!J$75 -> 17.172291 | K44: =USDemand!J$5*ResCalc!K67/ResCalc!K$75 -> 17.468235 | ... N44: =USDemand!M$5*ResCalc!N67/ResCalc!N$75 -> 18.104953 | P44: 15.597742 | Q44: 15.764637 | R44: 16.613028 | S44: 17.403036 | T44: 17.234363 | U44: 17.144148 | V44: 17.172291 | W44: 17.468235 | X44: 17.598767 | Y44: 17.850384 | Z44: 18.104953
B45: SA | C45: South Atlantic | D45: =USDemand!C$5*ResCalc!D68/ResCalc!D$75 -> 8.465402 | E45: =USDemand!D$5*ResCalc!E68/ResCalc!E$75 -> 8.5532652 | F45: =USDemand!E$5*ResCalc!F68/ResCalc!F$75 -> 9.1701788 | G45: =USDemand!F$5*ResCalc!G68/ResCalc!G$75 -> 9.5068758 | H45: =USDemand!G$5*ResCalc!H68/ResCalc!H$75 -> 9.4611389 | I45: =USDemand!H$5*ResCalc!I68/ResCalc!I$75 -> 9.4560065 | J45: =USDemand!I$5*ResCalc!J68/ResCalc!J$75 -> 9.5099842 | K45: =USDemand!J$5*ResCalc!K68/ResCalc!K$75 -> 9.7118042 | ... N45: =USDemand!M$5*ResCalc!N68/ResCalc!N$75 -> 10.194326 | P45: 8.465402 | Q45: 8.5532652 | R45: 9.1701788 | S45: 9.5068758 | T45: 9.4611389 | U45: 9.4560065 | V45: 9.5099842 | W45: 9.7118042 | X45: 9.8392012 | Y45: 10.016047 | Z45: 10.194326
B46: ESC | C46: East South Central | D46: =USDemand!C$5*ResCalc!D69/ResCalc!D$75 -> 9.9156089 | E46: =USDemand!D$5*ResCalc!E69/ResCalc!E$75 -> 9.7930214 | F46: =USDemand!E$5*ResCalc!F69/ResCalc!F$75 -> 10.361459 | G46: =USDemand!F$5*ResCalc!G69/ResCalc!G$75 -> 10.765181 | H46: =USDemand!G$5*ResCalc!H69/ResCalc!H$75 -> 10.575168 | I46: =USDemand!H$5*ResCalc!I69/ResCalc!I$75 -> 10.437851 | J46: =USDemand!I$5*ResCalc!J69/ResCalc!J$75 -> 10.339031 | K46: =USDemand!J$5*ResCalc!K69/ResCalc!K$75 -> 10.402853 | ... N46: =USDemand!M$5*ResCalc!N69/ResCalc!N$75 -> 10.664808 | P46: 9.9156089 | Q46: 9.7930214 | R46: 10.361459 | S46: 10.765181 | T46: 10.575168 | U46: 10.437851 | V46: 10.339031 | W46: 10.402853 | X46: 10.487972 | Y46: 10.575323 | Z46: 10.664808
B47: ENC | C47: East North Central | D47: =USDemand!C$5*ResCalc!D70/ResCalc!D$75 -> 2.901653 | E47: =USDemand!D$5*ResCalc!E70/ResCalc!E$75 -> 2.8944833 | F47: =USDemand!E$5*ResCalc!F70/ResCalc!F$75 -> 2.9900028 | G47: =USDemand!F$5*ResCalc!G70/ResCalc!G$75 -> 3.2011062 | H47: =USDemand!G$5*ResCalc!H70/ResCalc!H$75 -> 3.1419373 | I47: =USDemand!H$5*ResCalc!I70/ResCalc!I$75 -> 3.0985675 | J47: =USDemand!I$5*ResCalc!J70/ResCalc!J$75 -> 3.0659712 | K47: =USDemand!J$5*ResCalc!K70/ResCalc!K$75 -> 3.081645 | ... N47: =USDemand!M$5*ResCalc!N70/ResCalc!N$75 -> 3.304763 | P47: 2.901653 | Q47: 2.8944833 | R47: 2.9900028 | S47: 3.2011062 | T47: 3.1419373 | U47: 3.0985675 | V47: 3.0659712 | W47: 3.081645 | X47: 3.2007687 | Y47: 3.2525154 | Z47: 3.304763
B48: WSC | C48: West South Central | D48: =USDemand!C$5*ResCalc!D71/ResCalc!D$75 -> 13.971613 | E48: =USDemand!D$5*ResCalc!E71/ResCalc!E$75 -> 13.894125 | F48: =USDemand!E$5*ResCalc!F71/ResCalc!F$75 -> 14.738062 | G48: =USDemand!F$5*ResCalc!G71/ResCalc!G$75 -> 15.31242 | H48: =USDemand!G$5*ResCalc!H71/ResCalc!H$75 -> 15.005715 | I48: =USDemand!H$5*ResCalc!I71/ResCalc!I$75 -> 14.775736 | J48: =USDemand!I$5*ResCalc!J71/ResCalc!J$75 -> 14.691129 | K48: =USDemand!J$5*ResCalc!K71/ResCalc!K$75 -> 14.836947 | ... N48: =USDemand!M$5*ResCalc!N71/ResCalc!N$75 -> 15.45964 | P48: 13.971613 | Q48: 13.894125 | R48: 14.738062 | S48: 15.31242 | T48: 15.005715 | U48: 14.775736 | V48: 14.691129 | W48: 14.836947 | X48: 15.107397 | Y48: 15.282129 | Z48: 15.45964
B49: WNC | C49: West North Central | D49: =USDemand!C$5*ResCalc!D72/ResCalc!D$75 -> 0 | E49: =USDemand!D$5*ResCalc!E72/ResCalc!E$75 -> 0 | F49: =USDemand!E$5*ResCalc!F72/ResCalc!F$75 -> 0 | G49: =USDemand!F$5*ResCalc!G72/ResCalc!G$75 -> 0 | H49: =USDemand!G$5*ResCalc!H72/ResCalc!H$75 -> 0 | I49: =USDemand!H$5*ResCalc!I72/ResCalc!I$75 -> 0 | J49: =USDemand!I$5*ResCalc!J72/ResCalc!J$75 -> 0 | K49: =USDemand!J$5*ResCalc!K72/ResCalc!K$75 -> 0 | ... N49: =USDemand!M$5*ResCalc!N72/ResCalc!N$75 -> 0 | P49: 0 | Q49: 0 | R49: 0 | S49: 0 | T49: 0 | U49: 0 | V49: 0 | W49: 0 | X49: 0 | Y49: 0 | Z49: 0
B50: M | C50: Mountain | D50: =USDemand!C$5*ResCalc!D73/ResCalc!D$75 -> 0 | E50: =USDemand!D$5*ResCalc!E73/ResCalc!E$75 -> 0 | F50: =USDemand!E$5*ResCalc!F73/ResCalc!F$75 -> 0 | G50: =USDemand!F$5*ResCalc!G73/ResCalc!G$75 -> 0 | H50: =USDemand!G$5*ResCalc!H73/ResCalc!H$75 -> 0 | I50: =USDemand!H$5*ResCalc!I73/ResCalc!I$75 -> 0 | J50: =USDemand!I$5*ResCalc!J73/ResCalc!J$75 -> 0 | K50: =USDemand!J$5*ResCalc!K73/ResCalc!K$75 -> 0 | ... N50: =USDemand!M$5*ResCalc!N73/ResCalc!N$75 -> 0 | P50: 0 | Q50: 0 | R50: 0 | S50: 0 | T50: 0 | U50: 0 | V50: 0 | W50: 0 | X50: 0 | Y50: 0 | Z50: 0
B51: P | C51: Pacific | D51: =USDemand!C$5*ResCalc!D74/ResCalc!D$75 -> 0 | E51: =USDemand!D$5*ResCalc!E74/ResCalc!E$75 -> 0 | F51: =USDemand!E$5*ResCalc!F74/ResCalc!F$75 -> 0 | G51: =USDemand!F$5*ResCalc!G74/ResCalc!G$75 -> 0 | H51: =USDemand!G$5*ResCalc!H74/ResCalc!H$75 -> 0 | I51: =USDemand!H$5*ResCalc!I74/ResCalc!I$75 -> 0 | J51: =USDemand!I$5*ResCalc!J74/ResCalc!J$75 -> 0 | K51: =USDemand!J$5*ResCalc!K74/ResCalc!K$75 -> 0 | ... N51: =USDemand!M$5*ResCalc!N74/ResCalc!N$75 -> 0 | P51: 0 | Q51: 0 | R51: 0 | S51: 0 | T51: 0 | U51: 0 | V51: 0 | W51: 0 | X51: 0 | Y51: 0 | Z51: 0
C52: Total US | D52: =SUM(D43:D51) -> 50.85202 | E52: =SUM(E43:E51) -> 50.899532 | F52: =SUM(F43:F51) -> 53.87273 | G52: =SUM(G43:G51) -> 56.188619 | H52: =SUM(H43:H51) -> 55.418323 | I52: =SUM(I43:I51) -> 54.91231 | J52: =SUM(J43:J51) -> 54.778406 | K52: =SUM(K43:K51) -> 55.501484 | ... N52: =SUM(N43:N51) -> 57.72849 | P52: 50.85202 | Q52: 50.899532 | R52: 53.87273 | S52: 56.188619 | T52: 55.418323 | U52: 54.91231 | V52: 54.778406 | W52: 55.501484 | X52: 56.234106 | Y52: 56.976399 | Z52: 57.72849
C53: Check From AEO data | D53: =USDemand!C255 -> 38.425449 | E53: =USDemand!D255 -> 38.009281 | F53: =USDemand!E255 -> 38.799267 | G53: =USDemand!F255 -> 40.689968 | H53: =USDemand!G255 -> 42.401108 | I53: =USDemand!H255 -> 44.059566 | J53: =USDemand!I255 -> 45.560253 | P53: 38.425449 | Q53: 38.009281 | R53: 38.799267 | S53: 40.689968 | T53: 42.401108 | U53: 44.059566 | V53: 45.560253
A54: Regional Lighting Demand billion lumens/yr | I54: = Nat'l lighting demand * Regional % of total households | U54: = Nat'l lighting demand * Regional % of total households
C55: New England | D55: =USDemand!C$7*ResCalc!D66/ResCalc!D$75 -> 0 | E55: =USDemand!D$7*ResCalc!E66/ResCalc!E$75 -> 0 | F55: =USDemand!E$7*ResCalc!F66/ResCalc!F$75 -> 0 | G55: =USDemand!F$7*ResCalc!G66/ResCalc!G$75 -> 0 | H55: =USDemand!G$7*ResCalc!H66/ResCalc!H$75 -> 0 | I55: =USDemand!H$7*ResCalc!I66/ResCalc!I$75 -> 0 | J55: =USDemand!I$7*ResCalc!J66/ResCalc!J$75 -> 0 | K55: =USDemand!J$7*ResCalc!K66/ResCalc!K$75 -> 0 | ... N55: =USDemand!M$7*ResCalc!N66/ResCalc!N$75 -> 0 | P55: 0 | Q55: 0 | R55: 0 | S55: 0 | T55: 0 | U55: 0 | V55: 0 | W55: 0 | X55: 0 | Y55: 0 | Z55: 0
C56: Brooklyn | D56: ='2010 Fuel Share'!Q49*DmdCalc!C$7*ResCalc!D67/ResCalc!D$75 -> #REF! | E56: =D56 -> #REF! | F56: ='2010 Fuel Share'!$Q$49*DmdCalc!E$7*ResCalc!F67/ResCalc!F$75 -> #REF! | G56: ='2010 Fuel Share'!$Q$49*DmdCalc!F$7*ResCalc!G67/ResCalc!G$75 -> #REF! | H56: ='2010 Fuel Share'!$Q$49*DmdCalc!G$7*ResCalc!H67/ResCalc!H$75 -> #REF! | I56: ='2010 Fuel Share'!$Q$49*DmdCalc!H$7*ResCalc!I67/ResCalc!I$75 -> #REF! | J56: ='2010 Fuel Share'!$Q$49*DmdCalc!I$7*ResCalc!J67/ResCalc!J$75 -> #REF! | K56: ='2010 Fuel Share'!$Q$49*DmdCalc!J$7*ResCalc!K67/ResCalc!K$75 -> #REF! | L56: ='2010 Fuel Share'!$Q$49*DmdCalc!K$7*ResCalc!L67/ResCalc!L$75 -> #REF! | M56: ='2010 Fuel Share'!$Q$49*DmdCalc!L$7*ResCalc!M67/ResCalc!M$75 -> #REF! | N56: ='2010 Fuel Share'!$Q$49*DmdCalc!M$7*ResCalc!N67/ResCalc!N$75 -> #REF! | P56: 7.0373899 | Q56: 7.0373899 | R56: 7.2078728 | S56: 7.4575657 | T56: 7.7889377 | U56: 8.1118099 | V56: 8.3818928 | W56: 8.6559025 | X56: 9.0126024 | Y56: 9.3269118 | Z56: 9.6492914
C57: Bronx | D57: ='2010 Fuel Share'!R49*DmdCalc!C$7*ResCalc!D68/ResCalc!D$75 -> #REF! | E57: =D57 -> #REF! | F57: ='2010 Fuel Share'!$R$49*DmdCalc!E$7*ResCalc!F68/ResCalc!F$75 -> #REF! | G57: ='2010 Fuel Share'!$R$49*DmdCalc!F$7*ResCalc!G68/ResCalc!G$75 -> #REF! | H57: ='2010 Fuel Share'!$R$49*DmdCalc!G$7*ResCalc!H68/ResCalc!H$75 -> #REF! | I57: ='2010 Fuel Share'!$R$49*DmdCalc!H$7*ResCalc!I68/ResCalc!I$75 -> #REF! | J57: ='2010 Fuel Share'!$R$49*DmdCalc!I$7*ResCalc!J68/ResCalc!J$75 -> #REF! | K57: ='2010 Fuel Share'!$R$49*DmdCalc!J$7*ResCalc!K68/ResCalc!K$75 -> #REF! | L57: ='2010 Fuel Share'!$R$49*DmdCalc!K$7*ResCalc!L68/ResCalc!L$75 -> #REF! | M57: ='2010 Fuel Share'!$R$49*DmdCalc!L$7*ResCalc!M68/ResCalc!M$75 -> #REF! | N57: ='2010 Fuel Share'!$R$49*DmdCalc!M$7*ResCalc!N68/ResCalc!N$75 -> #REF! | P57: 4.0583317 | Q57: 4.0583317 | R57: 4.2275252 | S57: 4.3287246 | T57: 4.543353 | U57: 4.7540056 | V57: 4.9322347 | W57: 5.1134419 | X57: 5.3539941 | Y57: 5.560793 | Z57: 5.7730673
C58: Manhattan | D58: ='2010 Fuel Share'!S49*DmdCalc!C$7*ResCalc!D69/ResCalc!D$75 -> #REF! | E58: =D58 -> #REF! | F58: ='2010 Fuel Share'!$S$49*DmdCalc!E$7*ResCalc!F69/ResCalc!F$75 -> #REF! | G58: ='2010 Fuel Share'!$S$49*DmdCalc!F$7*ResCalc!G69/ResCalc!G$75 -> #REF! | H58: ='2010 Fuel Share'!$S$49*DmdCalc!G$7*ResCalc!H69/ResCalc!H$75 -> #REF! | I58: ='2010 Fuel Share'!$S$49*DmdCalc!H$7*ResCalc!I69/ResCalc!I$75 -> #REF! | J58: ='2010 Fuel Share'!$S$49*DmdCalc!I$7*ResCalc!J69/ResCalc!J$75 -> #REF! | K58: ='2010 Fuel Share'!$S$49*DmdCalc!J$7*ResCalc!K69/ResCalc!K$75 -> #REF! | L58: ='2010 Fuel Share'!$S$49*DmdCalc!K$7*ResCalc!L69/ResCalc!L$75 -> #REF! | M58: ='2010 Fuel Share'!$S$49*DmdCalc!L$7*ResCalc!M69/ResCalc!M$75 -> #REF! | N58: ='2010 Fuel Share'!$S$49*DmdCalc!M$7*ResCalc!N69/ResCalc!N$75 -> #REF! | P58: 6.7984074 | Q58: 6.7984074 | R58: 6.8315174 | S58: 7.0102143 | T58: 7.2628684 | U58: 7.5050031 | V58: 7.6688747 | W58: 7.8334612 | X58: 8.1620156 | Y58: 8.396956 | Z58: 8.6375185
C59: Staten Island | D59: ='2010 Fuel Share'!U49*DmdCalc!C$7*ResCalc!D70/ResCalc!D$75 -> #REF! | E59: =D59 -> #REF! | F59: ='2010 Fuel Share'!$U$49*DmdCalc!E$7*ResCalc!F70/ResCalc!F$75 -> #REF! | G59: ='2010 Fuel Share'!$U$49*DmdCalc!F$7*ResCalc!G70/ResCalc!G$75 -> #REF! | H59: ='2010 Fuel Share'!$U$49*DmdCalc!G$7*ResCalc!H70/ResCalc!H$75 -> #REF! | I59: ='2010 Fuel Share'!$U$49*DmdCalc!H$7*ResCalc!I70/ResCalc!I$75 -> #REF! | J59: ='2010 Fuel Share'!$U$49*DmdCalc!I$7*ResCalc!J70/ResCalc!J$75 -> #REF! | K59: ='2010 Fuel Share'!$U$49*DmdCalc!J$7*ResCalc!K70/ResCalc!K$75 -> #REF! | L59: ='2010 Fuel Share'!$U$49*DmdCalc!K$7*ResCalc!L70/ResCalc!L$75 -> #REF! | M59: ='2010 Fuel Share'!$U$49*DmdCalc!L$7*ResCalc!M70/ResCalc!M$75 -> #REF! | N59: ='2010 Fuel Share'!$U$49*DmdCalc!M$7*ResCalc!N70/ResCalc!N$75 -> #REF! | P59: 1.3693955 | Q59: 1.3693955 | R59: 1.3569488 | S59: 1.4348473 | T59: 1.4852995 | U59: 1.5335444 | V59: 1.5653645 | W59: 1.5972742 | X59: 1.7145723 | Y59: 1.7776375 | Z59: 1.842349
C60: Queens | D60: ='2010 Fuel Share'!T49*DmdCalc!C$7*ResCalc!D71/ResCalc!D$75 -> #REF! | E60: =D60 -> #REF! | F60: ='2010 Fuel Share'!$T$49*DmdCalc!E$7*ResCalc!F71/ResCalc!F$75 -> #REF! | G60: ='2010 Fuel Share'!$T$49*DmdCalc!F$7*ResCalc!G71/ResCalc!G$75 -> #REF! | H60: ='2010 Fuel Share'!$T$49*DmdCalc!G$7*ResCalc!H71/ResCalc!H$75 -> #REF! | I60: ='2010 Fuel Share'!$T$49*DmdCalc!H$7*ResCalc!I71/ResCalc!I$75 -> #REF! | J60: ='2010 Fuel Share'!$T$49*DmdCalc!I$7*ResCalc!J71/ResCalc!J$75 -> #REF! | K60: ='2010 Fuel Share'!$T$49*DmdCalc!J$7*ResCalc!K71/ResCalc!K$75 -> #REF! | L60: ='2010 Fuel Share'!$T$49*DmdCalc!K$7*ResCalc!L71/ResCalc!L$75 -> #REF! | M60: ='2010 Fuel Share'!$T$49*DmdCalc!L$7*ResCalc!M71/ResCalc!M$75 -> #REF! | N60: ='2010 Fuel Share'!$T$49*DmdCalc!M$7*ResCalc!N71/ResCalc!N$75 -> #REF! | P60: 3.5974889 | Q60: 3.5974889 | R60: 3.6492341 | S60: 3.7447162 | T60: 3.8702829 | U60: 3.9898264 | V60: 4.0923432 | W60: 4.1957626 | X60: 4.4153042 | Y60: 4.5569805 | Z60: 4.7021929
C61: West North Central | D61: =USDemand!C$7*ResCalc!D72/ResCalc!D$75 -> 0 | E61: =USDemand!D$7*ResCalc!E72/ResCalc!E$75 -> 0 | F61: =USDemand!E$7*ResCalc!F72/ResCalc!F$75 -> 0 | G61: =USDemand!F$7*ResCalc!G72/ResCalc!G$75 -> 0 | H61: =USDemand!G$7*ResCalc!H72/ResCalc!H$75 -> 0 | I61: =USDemand!H$7*ResCalc!I72/ResCalc!I$75 -> 0 | J61: =USDemand!I$7*ResCalc!J72/ResCalc!J$75 -> 0 | K61: =USDemand!J$7*ResCalc!K72/ResCalc!K$75 -> 0 | ... N61: =USDemand!M$7*ResCalc!N72/ResCalc!N$75 -> 0 | P61: 0 | Q61: 0 | R61: 0 | S61: 0 | T61: 0 | U61: 0 | V61: 0 | W61: 0 | X61: 0 | Y61: 0 | Z61: 0
C62: Mountain | D62: =USDemand!C$7*ResCalc!D73/ResCalc!D$75 -> 0 | E62: =USDemand!D$7*ResCalc!E73/ResCalc!E$75 -> 0 | F62: =USDemand!E$7*ResCalc!F73/ResCalc!F$75 -> 0 | G62: =USDemand!F$7*ResCalc!G73/ResCalc!G$75 -> 0 | H62: =USDemand!G$7*ResCalc!H73/ResCalc!H$75 -> 0 | I62: =USDemand!H$7*ResCalc!I73/ResCalc!I$75 -> 0 | J62: =USDemand!I$7*ResCalc!J73/ResCalc!J$75 -> 0 | K62: =USDemand!J$7*ResCalc!K73/ResCalc!K$75 -> 0 | ... N62: =USDemand!M$7*ResCalc!N73/ResCalc!N$75 -> 0 | P62: 0 | Q62: 0 | R62: 0 | S62: 0 | T62: 0 | U62: 0 | V62: 0 | W62: 0 | X62: 0 | Y62: 0 | Z62: 0
C63: Pacific | D63: =USDemand!C$7*ResCalc!D74/ResCalc!D$75 -> 0 | E63: =USDemand!D$7*ResCalc!E74/ResCalc!E$75 -> 0 | F63: =USDemand!E$7*ResCalc!F74/ResCalc!F$75 -> 0 | G63: =USDemand!F$7*ResCalc!G74/ResCalc!G$75 -> 0 | H63: =USDemand!G$7*ResCalc!H74/ResCalc!H$75 -> 0 | I63: =USDemand!H$7*ResCalc!I74/ResCalc!I$75 -> 0 | J63: =USDemand!I$7*ResCalc!J74/ResCalc!J$75 -> 0 | K63: =USDemand!J$7*ResCalc!K74/ResCalc!K$75 -> 0 | ... N63: =USDemand!M$7*ResCalc!N74/ResCalc!N$75 -> 0 | P63: 0 | Q63: 0 | R63: 0 | S63: 0 | T63: 0 | U63: 0 | V63: 0 | W63: 0 | X63: 0 | Y63: 0 | Z63: 0
C64: Total NYC | D64: =SUM(D55:D60) -> #REF! | E64: =SUM(E56:E60) -> #REF! | F64: =SUM(F55:F60) -> #REF! | G64: =SUM(G55:G60) -> #REF! | H64: =SUM(H55:H60) -> #REF! | I64: =SUM(I55:I60) -> #REF! | J64: =SUM(J55:J60) -> #REF! | K64: =SUM(K55:K60) -> #REF! | L64: =SUM(L55:L60) -> #REF! | M64: =SUM(M55:M60) -> #REF! | N64: =SUM(N55:N60) -> #REF! | P64: 22.861013 | Q64: 22.861013 | R64: 23.273098 | S64: 23.976068 | T64: 24.950741 | U64: 25.894189 | V64: 26.64071 | W64: 27.395842 | X64: 28.658489 | Y64: 29.619279 | Z64: 30.604419
A66: Regional Miscellaneous Electric Demand PJ/a | I66: = Nat'l misc electric demand * Regional % of total households | U66: = Nat'l misc electric demand * Regional % of total households
B67: NE | C67: New England | D67: =ResCalc!D$136*ResCalc!D66 -> #REF! | E67: =ResCalc!E$136*ResCalc!E66 -> #REF! | F67: =ResCalc!F$136*ResCalc!F66 -> #REF! | G67: =ResCalc!G$136*ResCalc!G66 -> #REF! | H67: =ResCalc!H$136*ResCalc!H66 -> #REF! | I67: =ResCalc!I$136*ResCalc!I66 -> #REF! | J67: =ResCalc!J$136*ResCalc!J66 -> #REF! | K67: =ResCalc!K$136*ResCalc!K66 -> #REF! | ... N67: =ResCalc!N$136*ResCalc!N66 -> #REF! | P67: 0 | Q67: 0 | R67: 0 | S67: 0 | T67: 0 | U67: 0 | V67: 0 | W67: 0 | X67: 0 | Y67: 0 | Z67: 0
C68: Brooklyn | D68: =ResCalc!D$136*ResCalc!D67 -> #REF! | E68: ='2010 Fuel Share'!$Q$55*ResCalc!E$136*ResCalc!E67 -> #REF! | F68: ='2010 Fuel Share'!$Q$55*ResCalc!F$136*ResCalc!F67 -> #REF! | G68: ='2010 Fuel Share'!$Q$55*ResCalc!G$136*ResCalc!G67 -> #REF! | H68: ='2010 Fuel Share'!$Q$55*ResCalc!H$136*ResCalc!H67 -> #REF! | I68: ='2010 Fuel Share'!$Q$55*ResCalc!I$136*ResCalc!I67 -> #REF! | J68: ='2010 Fuel Share'!$Q$55*ResCalc!J$136*ResCalc!J67 -> #REF! | K68: ='2010 Fuel Share'!$Q$55*ResCalc!K$136*ResCalc!K67 -> #REF! | L68: ='2010 Fuel Share'!$Q$55*ResCalc!L$136*ResCalc!L67 -> #REF! | ... N68: ='2010 Fuel Share'!$Q$55*ResCalc!N$136*ResCalc!N67 -> #REF! | P68: 20.487801 | Q68: 24.192461 | R68: 24.588712 | S68: 24.015685 | T68: 23.642352 | U68: 22.801475 | V68: 22.475701 | W68: 22.152181 | X68: 21.623808 | Y68: 21.25103 | Z68: 20.883932
C69: Bronx | D69: =ResCalc!D$136*ResCalc!D68 -> #REF! | E69: ='2010 Fuel Share'!$R$55*ResCalc!E$136*ResCalc!E68 -> #REF! | F69: ='2010 Fuel Share'!$R$55*ResCalc!F$136*ResCalc!F68 -> #REF! | G69: ='2010 Fuel Share'!$R$55*ResCalc!G$136*ResCalc!G68 -> #REF! | H69: ='2010 Fuel Share'!$R$55*ResCalc!H$136*ResCalc!H68 -> #REF! | I69: ='2010 Fuel Share'!$R$55*ResCalc!I$136*ResCalc!I68 -> #REF! | J69: ='2010 Fuel Share'!$R$55*ResCalc!J$136*ResCalc!J68 -> #REF! | K69: ='2010 Fuel Share'!$R$55*ResCalc!K$136*ResCalc!K68 -> #REF! | L69: ='2010 Fuel Share'!$R$55*ResCalc!L$136*ResCalc!L68 -> #REF! | ... N69: ='2010 Fuel Share'!$R$55*ResCalc!N$136*ResCalc!N68 -> #REF! | P69: 11.119396 | Q69: 12.175903 | R69: 12.590355 | S69: 12.16973 | T69: 12.039599 | U69: 11.666161 | V69: 11.546171 | W69: 11.424588 | X69: 11.214578 | Y69: 11.061192 | Z69: 10.908036
C70: Manhattan | D70: =ResCalc!D$136*ResCalc!D69 -> #REF! | E70: ='2010 Fuel Share'!$S$55*ResCalc!E$136*ResCalc!E69 -> #REF! | F70: ='2010 Fuel Share'!$S$55*ResCalc!F$136*ResCalc!F69 -> #REF! | G70: ='2010 Fuel Share'!$S$55*ResCalc!G$136*ResCalc!G69 -> #REF! | H70: ='2010 Fuel Share'!$S$55*ResCalc!H$136*ResCalc!H69 -> #REF! | I70: ='2010 Fuel Share'!$S$55*ResCalc!I$136*ResCalc!I69 -> #REF! | J70: ='2010 Fuel Share'!$S$55*ResCalc!J$136*ResCalc!J69 -> #REF! | K70: ='2010 Fuel Share'!$S$55*ResCalc!K$136*ResCalc!K69 -> #REF! | L70: ='2010 Fuel Share'!$S$55*ResCalc!L$136*ResCalc!L69 -> #REF! | ... N70: ='2010 Fuel Share'!$S$55*ResCalc!N$136*ResCalc!N69 -> #REF! | P70: 13.024258 | Q70: 16.911722 | R70: 17.257703 | S70: 16.717307 | T70: 16.325172 | U70: 15.621876 | V70: 15.227897 | W70: 14.845505 | X70: 14.50162 | Y70: 14.167758 | Z70: 13.843406
C71: Staten Island | D71: =ResCalc!D$136*ResCalc!D70 -> #REF! | E71: ='2010 Fuel Share'!$U$55*ResCalc!E$136*ResCalc!E70 -> #REF! | F71: ='2010 Fuel Share'!$U$55*ResCalc!F$136*ResCalc!F70 -> #REF! | G71: ='2010 Fuel Share'!$U$55*ResCalc!G$136*ResCalc!G70 -> #REF! | H71: ='2010 Fuel Share'!$U$55*ResCalc!H$136*ResCalc!H70 -> #REF! | I71: ='2010 Fuel Share'!$U$55*ResCalc!I$136*ResCalc!I70 -> #REF! | J71: ='2010 Fuel Share'!$U$55*ResCalc!J$136*ResCalc!J70 -> #REF! | K71: ='2010 Fuel Share'!$U$55*ResCalc!K$136*ResCalc!K70 -> #REF! | L71: ='2010 Fuel Share'!$U$55*ResCalc!L$136*ResCalc!L70 -> #REF! | ... N71: ='2010 Fuel Share'!$U$55*ResCalc!N$136*ResCalc!N70 -> #REF! | P71: 3.8113523 | Q71: 6.1772862 | R71: 6.1544493 | S71: 6.1432847 | T71: 5.9940939 | U71: 5.7311079 | V71: 5.5806358 | W71: 5.4347639 | X71: 5.4693389 | Y71: 5.3849586 | Z71: 5.3013416
C72: Queens | D72: =ResCalc!D$136*ResCalc!D71 -> #REF! | E72: ='2010 Fuel Share'!$T$55*ResCalc!E$136*ResCalc!E71 -> #REF! | F72: ='2010 Fuel Share'!$T$55*ResCalc!F$136*ResCalc!F71 -> #REF! | G72: ='2010 Fuel Share'!$T$55*ResCalc!G$136*ResCalc!G71 -> #REF! | H72: ='2010 Fuel Share'!$T$55*ResCalc!H$136*ResCalc!H71 -> #REF! | I72: ='2010 Fuel Share'!$T$55*ResCalc!I$136*ResCalc!I71 -> #REF! | J72: ='2010 Fuel Share'!$T$55*ResCalc!J$136*ResCalc!J71 -> #REF! | K72: ='2010 Fuel Share'!$T$55*ResCalc!K$136*ResCalc!K71 -> #REF! | L72: ='2010 Fuel Share'!$T$55*ResCalc!L$136*ResCalc!L71 -> #REF! | ... N72: ='2010 Fuel Share'!$T$55*ResCalc!N$136*ResCalc!N71 -> #REF! | P72: 18.351864 | Q72: 12.377185 | R72: 12.662573 | S72: 12.266153 | T72: 11.949417 | U72: 11.407507 | V72: 11.161814 | W72: 10.922112 | X72: 10.775419 | Y72: 10.561141 | Z72: 10.351633
C73: West North Central | D73: =ResCalc!D$136*ResCalc!D72 -> #REF! | E73: =ResCalc!E$136*ResCalc!E72 -> #REF! | F73: =ResCalc!F$136*ResCalc!F72 -> #REF! | G73: =ResCalc!G$136*ResCalc!G72 -> #REF! | H73: =ResCalc!H$136*ResCalc!H72 -> #REF! | I73: =ResCalc!I$136*ResCalc!I72 -> #REF! | J73: =ResCalc!J$136*ResCalc!J72 -> #REF! | K73: =ResCalc!K$136*ResCalc!K72 -> #REF! | ... N73: =ResCalc!N$136*ResCalc!N72 -> #REF! | P73: 0 | Q73: 0 | R73: 0 | S73: 0 | T73: 0 | U73: 0 | V73: 0 | W73: 0 | X73: 0 | Y73: 0 | Z73: 0
C74: Mountain | D74: =ResCalc!D$136*ResCalc!D73 -> #REF! | E74: =ResCalc!E$136*ResCalc!E73 -> #REF! | F74: =ResCalc!F$136*ResCalc!F73 -> #REF! | G74: =ResCalc!G$136*ResCalc!G73 -> #REF! | H74: =ResCalc!H$136*ResCalc!H73 -> #REF! | I74: =ResCalc!I$136*ResCalc!I73 -> #REF! | J74: =ResCalc!J$136*ResCalc!J73 -> #REF! | K74: =ResCalc!K$136*ResCalc!K73 -> #REF! | ... N74: =ResCalc!N$136*ResCalc!N73 -> #REF! | P74: 0 | Q74: 0 | R74: 0 | S74: 0 | T74: 0 | U74: 0 | V74: 0 | W74: 0 | X74: 0 | Y74: 0 | Z74: 0
C75: Pacific | D75: =ResCalc!D$136*ResCalc!D74*0.7 -> #REF! | E75: =ResCalc!E$136*ResCalc!E74*0.7 -> #REF! | F75: =ResCalc!F$136*ResCalc!F74*0.7 -> #REF! | G75: =ResCalc!G$136*ResCalc!G74*0.7 -> #REF! | H75: =ResCalc!H$136*ResCalc!H74*0.7 -> #REF! | I75: =ResCalc!I$136*ResCalc!I74*0.7 -> #REF! | J75: =ResCalc!J$136*ResCalc!J74*0.7 -> #REF! | K75: =ResCalc!K$136*ResCalc!K74*0.7 -> #REF! | ... N75: =ResCalc!N$136*ResCalc!N74*0.7 -> #REF! | P75: 0 | Q75: 0 | R75: 0 | S75: 0 | T75: 0 | U75: 0 | V75: 0 | W75: 0 | X75: 0 | Y75: 0 | Z75: 0
C76: Total NYC | D76: =SUM(D68:D72) -> #REF! | E76: =SUM(E68:E72) -> #REF! | F76: =SUM(F68:F72) -> #REF! | G76: =SUM(G68:G72) -> #REF! | H76: =SUM(H68:H72) -> #REF! | I76: =SUM(I68:I72) -> #REF! | J76: =SUM(J68:J72) -> #REF! | K76: =SUM(K68:K72) -> #REF! | ... N76: =SUM(N68:N72) -> #REF! | P76: 66.794671 | Q76: 71.834556 | R76: 73.253792 | S76: 71.312159 | T76: 69.950634 | U76: 67.228127 | V76: 65.992218 | W76: 64.77915 | X76: 63.584765 | Y76: 62.426079 | Z76: 61.288348
A78: Regional Miscellaneous Gas Demand PJ/a | I78: = Nat'l misc NG demand * Regional % of total households | U78: = Nat'l misc NG demand * Regional % of total households
C79: New England | D79: =ResCalc!D$137*ResCalc!D66 -> #REF! | E79: =ResCalc!E$137*ResCalc!E66 -> #REF! | F79: =ResCalc!F$137*ResCalc!F66 -> #REF! | G79: =ResCalc!G$137*ResCalc!G66 -> #REF! | H79: =ResCalc!H$137*ResCalc!H66 -> #REF! | I79: =ResCalc!I$137*ResCalc!I66 -> #REF! | J79: =ResCalc!J$137*ResCalc!J66 -> #REF! | K79: =ResCalc!K$137*ResCalc!K66 -> #REF! | ... N79: =ResCalc!N$137*ResCalc!N66 -> #REF! | P79: 0 | Q79: 0 | R79: 0 | S79: 0 | T79: 0 | U79: 0 | V79: 0 | W79: 0 | X79: 0 | Y79: 0 | Z79: 0
C80: Brooklyn | D80: =ResCalc!D$137*ResCalc!D67 -> #REF! | E80: ='2010 Fuel Share'!$Q$61*ResCalc!E$137*ResCalc!E67 -> #REF! | F80: ='2010 Fuel Share'!$Q$61*ResCalc!F$137*ResCalc!F67 -> #REF! | G80: ='2010 Fuel Share'!$Q$61*ResCalc!G$137*ResCalc!G67 -> #REF! | H80: ='2010 Fuel Share'!$Q$61*ResCalc!H$137*ResCalc!H67 -> #REF! | I80: ='2010 Fuel Share'!$Q$61*ResCalc!I$137*ResCalc!I67 -> #REF! | J80: ='2010 Fuel Share'!$Q$61*ResCalc!J$137*ResCalc!J67 -> #REF! | K80: ='2010 Fuel Share'!$Q$61*ResCalc!K$137*ResCalc!K67 -> #REF! | L80: ='2010 Fuel Share'!$Q$61*ResCalc!L$137*ResCalc!L67 -> #REF! | ... N80: ='2010 Fuel Share'!$Q$61*ResCalc!N$137*ResCalc!N67 -> #REF! | P80: 0.76256327 | Q80: 0.65454183 | R80: 0.9162367 | S80: 0.91112268 | T80: 0.90350501 | U80: 0.89236308 | V80: 0.87424001 | W80: 0.85455323 | X80: 0.84972254 | Y80: 0.85064288 | Z80: 0.85153379
C81: Bronx | D81: =ResCalc!D$137*ResCalc!D68 -> #REF! | E81: ='2010 Fuel Share'!$R$61*ResCalc!E$137*ResCalc!E68 -> #REF! | F81: ='2010 Fuel Share'!$R$61*ResCalc!F$137*ResCalc!F68 -> #REF! | G81: ='2010 Fuel Share'!$R$61*ResCalc!G$137*ResCalc!G68 -> #REF! | H81: ='2010 Fuel Share'!$R$61*ResCalc!H$137*ResCalc!H68 -> #REF! | I81: ='2010 Fuel Share'!$R$61*ResCalc!I$137*ResCalc!I68 -> #REF! | J81: ='2010 Fuel Share'!$R$61*ResCalc!J$137*ResCalc!J68 -> #REF! | K81: ='2010 Fuel Share'!$R$61*ResCalc!K$137*ResCalc!K68 -> #REF! | L81: ='2010 Fuel Share'!$R$61*ResCalc!L$137*ResCalc!L68 -> #REF! | ... N81: ='2010 Fuel Share'!$R$61*ResCalc!N$137*ResCalc!N68 -> #REF! | P81: 0.41386789 | Q81: 0.49073984 | R81: 0.69888006 | S81: 0.68778959 | T81: 0.68540092 | U81: 0.68014168 | V81: 0.669034 | W81: 0.6565321 | X81: 0.65647877 | Y81: 0.65957168 | Z81: 0.66256571
C82: Manhattan | D82: =ResCalc!D$137*ResCalc!D69 -> #REF! | E82: ='2010 Fuel Share'!$S$61*ResCalc!E$137*ResCalc!E69 -> #REF! | F82: ='2010 Fuel Share'!$S$61*ResCalc!F$137*ResCalc!F69 -> #REF! | G82: ='2010 Fuel Share'!$S$61*ResCalc!G$137*ResCalc!G69 -> #REF! | H82: ='2010 Fuel Share'!$S$61*ResCalc!H$137*ResCalc!H69 -> #REF! | I82: ='2010 Fuel Share'!$S$61*ResCalc!I$137*ResCalc!I69 -> #REF! | J82: ='2010 Fuel Share'!$S$61*ResCalc!J$137*ResCalc!J69 -> #REF! | K82: ='2010 Fuel Share'!$S$61*ResCalc!K$137*ResCalc!K69 -> #REF! | L82: ='2010 Fuel Share'!$S$61*ResCalc!L$137*ResCalc!L69 -> #REF! | ... N82: ='2010 Fuel Share'!$S$61*ResCalc!N$137*ResCalc!N69 -> #REF! | P82: 0.48476754 | Q82: 0.99731969 | R82: 1.4016645 | S82: 1.3824117 | T82: 1.359837 | U82: 1.3326038 | V82: 1.2910604 | W82: 1.248265 | X82: 1.2420832 | Y82: 1.2361114 | Z82: 1.2303305
C83: Staten Island | D83: =ResCalc!D$137*ResCalc!D70 -> #REF! | E83: ='2010 Fuel Share'!$T$61*ResCalc!E$137*ResCalc!E70 -> #REF! | F83: ='2010 Fuel Share'!$T$61*ResCalc!F$137*ResCalc!F70 -> #REF! | G83: ='2010 Fuel Share'!$T$61*ResCalc!G$137*ResCalc!G70 -> #REF! | H83: ='2010 Fuel Share'!$T$61*ResCalc!H$137*ResCalc!H70 -> #REF! | I83: ='2010 Fuel Share'!$T$61*ResCalc!I$137*ResCalc!I70 -> #REF! | J83: ='2010 Fuel Share'!$T$61*ResCalc!J$137*ResCalc!J70 -> #REF! | K83: ='2010 Fuel Share'!$T$61*ResCalc!K$137*ResCalc!K70 -> #REF! | L83: ='2010 Fuel Share'!$T$61*ResCalc!L$137*ResCalc!L70 -> #REF! | ... N83: ='2010 Fuel Share'!$T$61*ResCalc!N$137*ResCalc!N70 -> #REF! | P83: 0.14185989 | Q83: 0.065798581 | R83: 0.090286443 | S83: 0.091758005 | T83: 0.09018304 | U83: 0.088303656 | V83: 0.085459935 | W83: 0.082540055 | X83: 0.084613807 | Y83: 0.084861578 | Z83: 0.08510143
C84: Queens | D84: =ResCalc!D$137*ResCalc!D71 -> #REF! | E84: ='2010 Fuel Share'!$U$61*ResCalc!E$137*ResCalc!E71 -> #REF! | F84: ='2010 Fuel Share'!$U$61*ResCalc!F$137*ResCalc!F71 -> #REF! | G84: ='2010 Fuel Share'!$U$61*ResCalc!G$137*ResCalc!G71 -> #REF! | H84: ='2010 Fuel Share'!$U$61*ResCalc!H$137*ResCalc!H71 -> #REF! | I84: ='2010 Fuel Share'!$U$61*ResCalc!I$137*ResCalc!I71 -> #REF! | J84: ='2010 Fuel Share'!$U$61*ResCalc!J$137*ResCalc!J71 -> #REF! | K84: ='2010 Fuel Share'!$U$61*ResCalc!K$137*ResCalc!K71 -> #REF! | L84: ='2010 Fuel Share'!$U$61*ResCalc!L$137*ResCalc!L71 -> #REF! | ... N84: ='2010 Fuel Share'!$U$61*ResCalc!N$137*ResCalc!N71 -> #REF! | P84: 0.68306292 | Q84: 0.13283715 | R84: 0.18716911 | S84: 0.18459952 | T84: 0.18114524 | U84: 0.17709639 | V84: 0.17222354 | W84: 0.16713583 | X84: 0.16796525 | Y84: 0.16769436 | Z84: 0.16743213
C85: West North Central | D85: =ResCalc!D$137*ResCalc!D72 -> #REF! | E85: =ResCalc!E$137*ResCalc!E72 -> #REF! | F85: =ResCalc!F$137*ResCalc!F72 -> #REF! | G85: =ResCalc!G$137*ResCalc!G72 -> #REF! | H85: =ResCalc!H$137*ResCalc!H72 -> #REF! | I85: =ResCalc!I$137*ResCalc!I72 -> #REF! | J85: =ResCalc!J$137*ResCalc!J72 -> #REF! | K85: =ResCalc!K$137*ResCalc!K72 -> #REF! | ... N85: =ResCalc!N$137*ResCalc!N72 -> #REF! | P85: 0 | Q85: 0 | R85: 0 | S85: 0 | T85: 0 | U85: 0 | V85: 0 | W85: 0 | X85: 0 | Y85: 0 | Z85: 0
C86: Mountain | D86: =ResCalc!D$137*ResCalc!D73 -> #REF! | E86: =ResCalc!E$137*ResCalc!E73 -> #REF! | F86: =ResCalc!F$137*ResCalc!F73 -> #REF! | G86: =ResCalc!G$137*ResCalc!G73 -> #REF! | H86: =ResCalc!H$137*ResCalc!H73 -> #REF! | I86: =ResCalc!I$137*ResCalc!I73 -> #REF! | J86: =ResCalc!J$137*ResCalc!J73 -> #REF! | K86: =ResCalc!K$137*ResCalc!K73 -> #REF! | ... N86: =ResCalc!N$137*ResCalc!N73 -> #REF! | P86: 0 | Q86: 0 | R86: 0 | S86: 0 | T86: 0 | U86: 0 | V86: 0 | W86: 0 | X86: 0 | Y86: 0 | Z86: 0
C87: Pacific | D87: =ResCalc!D$137*ResCalc!D74 -> #REF! | E87: =ResCalc!E$137*ResCalc!E74 -> #REF! | F87: =ResCalc!F$137*ResCalc!F74 -> #REF! | G87: =ResCalc!G$137*ResCalc!G74 -> #REF! | H87: =ResCalc!H$137*ResCalc!H74 -> #REF! | I87: =ResCalc!I$137*ResCalc!I74 -> #REF! | J87: =ResCalc!J$137*ResCalc!J74 -> #REF! | K87: =ResCalc!K$137*ResCalc!K74 -> #REF! | ... N87: =ResCalc!N$137*ResCalc!N74 -> #REF! | P87: 0 | Q87: 0 | R87: 0 | S87: 0 | T87: 0 | U87: 0 | V87: 0 | W87: 0 | X87: 0 | Y87: 0 | Z87: 0
C88: Total NYC | D88: =SUM(D80:D84) -> #REF! | E88: =SUM(E80:E84) -> #REF! | F88: =SUM(F80:F84) -> #REF! | G88: =SUM(G80:G84) -> #REF! | H88: =SUM(H80:H84) -> #REF! | I88: =SUM(I80:I84) -> #REF! | J88: =SUM(J80:J84) -> #REF! | K88: =SUM(K80:K84) -> #REF! | ... N88: =SUM(N80:N84) -> #REF! | P88: 2.4861215 | Q88: 2.3412371 | R88: 3.2942369 | S88: 3.2576815 | T88: 3.2200712 | U88: 3.1705086 | V88: 3.0920179 | W88: 3.0090262 | X88: 3.0008636 | Y88: 2.9988819 | Z88: 2.9969636
A90: Regional Miscellaneous LPG Demand PJ/a | I90: = Nat'l misc NG demand * Regional % of total households | U90: = Nat'l misc NG demand * Regional % of total households
B91: NE | C91: New England | D91: =ResCalc!D$138*ResCalc!D66 -> 0 | E91: =ResCalc!E$138*ResCalc!E66 -> 0 | F91: =ResCalc!F$138*ResCalc!F66 -> 0 | G91: =ResCalc!G$138*ResCalc!G66 -> 0 | H91: =ResCalc!H$138*ResCalc!H66 -> 0 | I91: =ResCalc!I$138*ResCalc!I66 -> 0 | J91: =ResCalc!J$138*ResCalc!J66 -> 0 | K91: =ResCalc!K$138*ResCalc!K66 -> 0 | ... N91: =ResCalc!N$138*ResCalc!N66 -> 0 | P91: 0 | Q91: 0 | R91: 0 | S91: 0 | T91: 0 | U91: 0 | V91: 0 | W91: 0 | X91: 0 | Y91: 0 | Z91: 0
B92: MA | C92: Middle Atlantic | D92: =ResCalc!D$138*ResCalc!D67 -> 12.943925 | E92: =ResCalc!E$138*ResCalc!E67 -> 12.968264 | F92: =ResCalc!F$138*ResCalc!F67 -> 13.925686 | G92: =ResCalc!G$138*ResCalc!G67 -> 15.228658 | H92: =ResCalc!H$138*ResCalc!H67 -> 16.508227 | I92: =ResCalc!I$138*ResCalc!I67 -> 17.832363 | J92: =ResCalc!J$138*ResCalc!J67 -> 19.135937 | K92: =ResCalc!K$138*ResCalc!K67 -> 20.53258 | ... N92: =ResCalc!N$138*ResCalc!N67 -> 24.97531 | P92: 12.943925 | Q92: 12.968264 | R92: 13.925686 | S92: 15.228658 | T92: 16.508227 | U92: 17.832363 | V92: 19.135937 | W92: 20.53258 | X92: 21.819748 | Y92: 23.344688 | Z92: 24.97531
B93: SA | C93: South Atlantic | D93: =ResCalc!D$138*ResCalc!D68 -> 7.0250891 | E93: =ResCalc!E$138*ResCalc!E68 -> 7.0360647 | F93: =ResCalc!F$138*ResCalc!F68 -> 7.6868008 | G93: =ResCalc!G$138*ResCalc!G68 -> 8.3190634 | H93: =ResCalc!H$138*ResCalc!H68 -> 9.0625123 | I93: =ResCalc!I$138*ResCalc!I68 -> 9.8355973 | J93: =ResCalc!J$138*ResCalc!J68 -> 10.597448 | K93: =ResCalc!K$138*ResCalc!K68 -> 11.415486 | ... N93: =ResCalc!N$138*ResCalc!N68 -> 14.062807 | P93: 7.0250891 | Q93: 7.0360647 | R93: 7.6868008 | S93: 8.3190634 | T93: 9.0625123 | U93: 9.8355973 | V93: 10.597448 | W93: 11.415486 | X93: 12.199087 | Y93: 13.098961 | Z93: 14.062807
B94: ESC | C94: East South Central | D94: =ResCalc!D$138*ResCalc!D69 -> 8.2285561 | E94: =ResCalc!E$138*ResCalc!E69 -> 8.0559097 | F94: =ResCalc!F$138*ResCalc!F69 -> 8.6853787 | G94: =ResCalc!G$138*ResCalc!G69 -> 9.4201525 | H94: =ResCalc!H$138*ResCalc!H69 -> 10.129604 | I94: =ResCalc!I$138*ResCalc!I69 -> 10.856856 | J94: =ResCalc!J$138*ResCalc!J69 -> 11.521296 | K94: =ResCalc!K$138*ResCalc!K69 -> 12.227761 | ... N94: =ResCalc!N$138*ResCalc!N69 -> 14.711824 | P94: 8.2285561 | Q94: 8.0559097 | R94: 8.6853787 | S94: 9.4201525 | T94: 10.129604 | U94: 10.856856 | V94: 11.521296 | W94: 12.227761 | X94: 13.003463 | Y94: 13.830381 | Z94: 14.711824
B95: ENC | C95: East North Central | D95: =ResCalc!D$138*ResCalc!D70 -> 2.4079625 | E95: =ResCalc!E$138*ResCalc!E70 -> 2.3810523 | F95: =ResCalc!F$138*ResCalc!F70 -> 2.5063368 | G95: =ResCalc!G$138*ResCalc!G70 -> 2.8011522 | H95: =ResCalc!H$138*ResCalc!H70 -> 3.0095579 | I95: =ResCalc!I$138*ResCalc!I70 -> 3.2229527 | J95: =ResCalc!J$138*ResCalc!J70 -> 3.4165641 | K95: =ResCalc!K$138*ResCalc!K70 -> 3.622239 | ... N95: =ResCalc!N$138*ResCalc!N70 -> 4.5588343 | P95: 2.4079625 | Q95: 2.3810523 | R95: 2.5063368 | S95: 2.8011522 | T95: 3.0095579 | U95: 3.2229527 | V95: 3.4165641 | W95: 3.622239 | X95: 3.968458 | Y95: 4.2536314 | Z95: 4.5588343
B96: WSC | C96: West South Central | D96: =ResCalc!D$138*ResCalc!D71 -> 11.594468 | E96: =ResCalc!E$138*ResCalc!E71 -> 11.429549 | F96: =ResCalc!F$138*ResCalc!F71 -> 12.354017 | G96: =ResCalc!G$138*ResCalc!G71 -> 13.399249 | H96: =ResCalc!H$138*ResCalc!H71 -> 14.373479 | I96: =ResCalc!I$138*ResCalc!I71 -> 15.368876 | J96: =ResCalc!J$138*ResCalc!J71 -> 16.371055 | K96: =ResCalc!K$138*ResCalc!K71 -> 17.439701 | ... N96: =ResCalc!N$138*ResCalc!N71 -> 21.326171 | P96: 11.594468 | Q96: 11.429549 | R96: 12.354017 | S96: 13.399249 | T96: 14.373479 | U96: 15.368876 | V96: 16.371055 | W96: 17.439701 | X96: 18.730835 | Y96: 19.985929 | Z96: 21.326171
B97: WNC | C97: West North Central | D97: =ResCalc!D$138*ResCalc!D72 -> 0 | E97: =ResCalc!E$138*ResCalc!E72 -> 0 | F97: =ResCalc!F$138*ResCalc!F72 -> 0 | G97: =ResCalc!G$138*ResCalc!G72 -> 0 | H97: =ResCalc!H$138*ResCalc!H72 -> 0 | I97: =ResCalc!I$138*ResCalc!I72 -> 0 | J97: =ResCalc!J$138*ResCalc!J72 -> 0 | K97: =ResCalc!K$138*ResCalc!K72 -> 0 | ... N97: =ResCalc!N$138*ResCalc!N72 -> 0 | P97: 0 | Q97: 0 | R97: 0 | S97: 0 | T97: 0 | U97: 0 | V97: 0 | W97: 0 | X97: 0 | Y97: 0 | Z97: 0
B98: M | C98: Mountain | D98: =ResCalc!D$138*ResCalc!D73 -> 0 | E98: =ResCalc!E$138*ResCalc!E73 -> 0 | F98: =ResCalc!F$138*ResCalc!F73 -> 0 | G98: =ResCalc!G$138*ResCalc!G73 -> 0 | H98: =ResCalc!H$138*ResCalc!H73 -> 0 | I98: =ResCalc!I$138*ResCalc!I73 -> 0 | J98: =ResCalc!J$138*ResCalc!J73 -> 0 | K98: =ResCalc!K$138*ResCalc!K73 -> 0 | ... N98: =ResCalc!N$138*ResCalc!N73 -> 0 | P98: 0 | Q98: 0 | R98: 0 | S98: 0 | T98: 0 | U98: 0 | V98: 0 | W98: 0 | X98: 0 | Y98: 0 | Z98: 0
B99: P | C99: Pacific | D99: =ResCalc!D$138*ResCalc!D74 -> 0 | E99: =ResCalc!E$138*ResCalc!E74 -> 0 | F99: =ResCalc!F$138*ResCalc!F74 -> 0 | G99: =ResCalc!G$138*ResCalc!G74 -> 0 | H99: =ResCalc!H$138*ResCalc!H74 -> 0 | I99: =ResCalc!I$138*ResCalc!I74 -> 0 | J99: =ResCalc!J$138*ResCalc!J74 -> 0 | K99: =ResCalc!K$138*ResCalc!K74 -> 0 | ... N99: =ResCalc!N$138*ResCalc!N74 -> 0 | P99: 0 | Q99: 0 | R99: 0 | S99: 0 | T99: 0 | U99: 0 | V99: 0 | W99: 0 | X99: 0 | Y99: 0 | Z99: 0
C100: Total US | D100: =SUM(D91:D99) -> 42.2 | E100: =SUM(E91:E99) -> 41.87084 | F100: =SUM(F91:F99) -> 45.15822 | G100: =SUM(G91:G99) -> 49.168275 | H100: =SUM(H91:H99) -> 53.08338 | I100: =SUM(I91:I99) -> 57.116645 | J100: =SUM(J91:J99) -> 61.0423 | K100: =SUM(K91:K99) -> 65.237767 | ... N100: =SUM(N91:N99) -> 79.634946 | P100: 42.2 | Q100: 41.87084 | R100: 45.15822 | S100: 49.168275 | T100: 53.08338 | U100: 57.116645 | V100: 61.0423 | W100: 65.237767 | X100: 69.721591 | Y100: 74.51359 | Z100: 79.634946
A102: Regional Water Heating Demand PJ/a | I102: = Nat'l water heating demand * Regional % of total households | U102: = Nat'l water heating demand * Regional % of total households
D103: =ResCalc!D$139*ResCalc!D66 -> #REF! | E103: =ResCalc!E$139*ResCalc!E66 -> #REF! | F103: =ResCalc!F$139*ResCalc!F66 -> #REF! | G103: =ResCalc!G$139*ResCalc!G66 -> #REF! | H103: =ResCalc!H$139*ResCalc!H66 -> #REF! | I103: =ResCalc!I$139*ResCalc!I66 -> #REF! | J103: =ResCalc!J$139*ResCalc!J66 -> #REF! | K103: =ResCalc!K$139*ResCalc!K66 -> #REF! | ... N103: =ResCalc!N$139*ResCalc!N66 -> #REF! | P103: 0 | Q103: 0 | R103: 0 | S103: 0 | T103: 0 | U103: 0 | V103: 0 | W103: 0 | X103: 0 | Y103: 0 | Z103: 0
C104: Brooklyn | D104: =ResCalc!D$139*ResCalc!D67 -> #REF! | E104: ='2010 Fuel Share'!$Q$67*ResCalc!E$139*ResCalc!E67 -> #REF! | F104: ='2010 Fuel Share'!$Q$67*ResCalc!F$139*ResCalc!F67 -> #REF! | G104: ='2010 Fuel Share'!$Q$67*ResCalc!G$139*ResCalc!G67 -> #REF! | H104: ='2010 Fuel Share'!$Q$67*ResCalc!H$139*ResCalc!H67 -> #REF! | I104: ='2010 Fuel Share'!$Q$67*ResCalc!I$139*ResCalc!I67 -> #REF! | J104: ='2010 Fuel Share'!$Q$67*ResCalc!J$139*ResCalc!J67 -> #REF! | K104: ='2010 Fuel Share'!$Q$67*ResCalc!K$139*ResCalc!K67 -> #REF! | L104: ='2010 Fuel Share'!$Q$67*ResCalc!L$139*ResCalc!L67 -> #REF! | ... N104: ='2010 Fuel Share'!$Q$67*ResCalc!N$139*ResCalc!N67 -> #REF! | P104: 11.803917 | Q104: 13.21464 | R104: 13.387632 | S104: 13.91071 | T104: 14.443143 | U104: 14.725541 | V104: 14.608126 | W104: 14.430818 | X104: 14.052795 | Y104: 13.777377 | Z104: 13.506876
C105: Bronx | D105: =ResCalc!D$139*ResCalc!D68 -> #REF! | E105: ='2010 Fuel Share'!$R$67*ResCalc!E$139*ResCalc!E68 -> #REF! | F105: ='2010 Fuel Share'!$R$67*ResCalc!F$139*ResCalc!F68 -> #REF! | G105: ='2010 Fuel Share'!$R$67*ResCalc!G$139*ResCalc!G68 -> #REF! | H105: ='2010 Fuel Share'!$R$67*ResCalc!H$139*ResCalc!H68 -> #REF! | I105: ='2010 Fuel Share'!$R$67*ResCalc!I$139*ResCalc!I68 -> #REF! | J105: ='2010 Fuel Share'!$R$67*ResCalc!J$139*ResCalc!J68 -> #REF! | K105: ='2010 Fuel Share'!$R$67*ResCalc!K$139*ResCalc!K68 -> #REF! | L105: ='2010 Fuel Share'!$R$67*ResCalc!L$139*ResCalc!L68 -> #REF! | ... N105: ='2010 Fuel Share'!$R$67*ResCalc!N$139*ResCalc!N68 -> #REF! | P105: 6.4063698 | Q105: 7.9304093 | R105: 8.1738208 | S105: 8.405323 | T105: 8.7700528 | U105: 8.9837037 | V105: 8.9482558 | W105: 8.8743012 | X105: 8.6902569 | Y105: 8.5508178 | Z105: 8.4121758
C106: Manhattan | D106: =ResCalc!D$139*ResCalc!D69 -> #REF! | E106: ='2010 Fuel Share'!$S$67*ResCalc!E$139*ResCalc!E69 -> #REF! | F106: ='2010 Fuel Share'!$S$67*ResCalc!F$139*ResCalc!F69 -> #REF! | G106: ='2010 Fuel Share'!$S$67*ResCalc!G$139*ResCalc!G69 -> #REF! | H106: ='2010 Fuel Share'!$S$67*ResCalc!H$139*ResCalc!H69 -> #REF! | I106: ='2010 Fuel Share'!$S$67*ResCalc!I$139*ResCalc!I69 -> #REF! | J106: ='2010 Fuel Share'!$S$67*ResCalc!J$139*ResCalc!J69 -> #REF! | K106: ='2010 Fuel Share'!$S$67*ResCalc!K$139*ResCalc!K69 -> #REF! | L106: ='2010 Fuel Share'!$S$67*ResCalc!L$139*ResCalc!L69 -> #REF! | ... N106: ='2010 Fuel Share'!$S$67*ResCalc!N$139*ResCalc!N69 -> #REF! | P106: 7.5038441 | Q106: 13.519191 | R106: 13.751136 | S106: 14.171253 | T106: 14.595413 | U106: 14.764852 | V106: 14.484676 | W106: 14.153278 | X106: 13.792235 | Y106: 13.442353 | Z106: 13.103074
C107: Staten Island | D107: =ResCalc!D$139*ResCalc!D70 -> #REF! | E107: ='2010 Fuel Share'!$U$67*ResCalc!E$139*ResCalc!E70 -> #REF! | F107: ='2010 Fuel Share'!$U$67*ResCalc!F$139*ResCalc!F70 -> #REF! | G107: ='2010 Fuel Share'!$U$67*ResCalc!G$139*ResCalc!G70 -> #REF! | H107: ='2010 Fuel Share'!$U$67*ResCalc!H$139*ResCalc!H70 -> #REF! | I107: ='2010 Fuel Share'!$U$67*ResCalc!I$139*ResCalc!I70 -> #REF! | J107: ='2010 Fuel Share'!$U$67*ResCalc!J$139*ResCalc!J70 -> #REF! | K107: ='2010 Fuel Share'!$U$67*ResCalc!K$139*ResCalc!K70 -> #REF! | L107: ='2010 Fuel Share'!$U$67*ResCalc!L$139*ResCalc!L70 -> #REF! | ... N107: ='2010 Fuel Share'!$U$67*ResCalc!N$139*ResCalc!N70 -> #REF! | P107: 2.1958865 | Q107: 2.2680153 | R107: 2.2523204 | S107: 2.3918169 | T107: 2.4613171 | U107: 2.4878253 | V107: 2.4380237 | W107: 2.3797324 | X107: 2.389122 | Y107: 2.3466155 | Z107: 2.3046311
...

Sheet ResCalc
A1: Seasonal Distribution of Heating and Cooling Loads
A2: Data (10 year average for 1998-2008) from NOAA's Historical Climatography Series No. 5.1 (HDD) and 5.2 (CDD)
E4: Summer | H4: Intermediate | K4: Winter | N4: Intermediate
A5: Region | B5: MARKAL # | C5: Degree Day | D5: Jun | E5: Jul | F5: Aug | G5: Sept | H5: Oct | I5: Nov | J5: Dec | K5: Jan | L5: Feb | M5: Mar | N5: Apr | O5: May
A6: NE | B6: 1 | C6: HDD | D6: 43.5 | E6: 8.4 | F6: 15.6 | G6: 93.9 | H6: 431.3 | I6: 685.5 | J6: 1046.4 | K6: 1215.4 | L6: 1042 | M6: 916.1 | N6: 553.5 | O6: 270.8 | P6: =SUM(D6:O6) -> 6322.4
C7: CDD | D7: 85.1 | E7: 198.7 | F7: 177.3 | G7: 43.9 | H7: 0.8 | I7: 0 | J7: 0 | K7: 0 | L7: 0 | M7: 0 | N7: 0 | O7: 5.4 | P7: =SUM(D7:O7) -> 511.2
A8: MA | B8: 2 | C8: HDD | D8: 21.1 | E8: 5.1 | F8: 8 | G8: 64.8 | H8: 363 | I8: 610.9 | J8: 970.8 | K8: 1100.1 | L8: 957.3 | M8: 818.9 | N8: 453 | O8: 204.9 | P8: =SUM(D8:O8) -> 5577.9
C9: CDD | D9: 147.3 | E9: 260.8 | F9: 243 | G9: 84.2 | H9: 5.1 | I9: 0 | J9: 0 | K9: 0 | L9: 0 | M9: 0 | N9: 0 | O9: 26.1 | P9: =SUM(D9:O9) -> 766.5
A10: ENC | B10: 3 | C10: HDD | D10: 37 | E10: 6.2 | F10: 17.5 | G10: 88.7 | H10: 396.6 | I10: 693 | J10: 1129.4 | K10: 1212.1 | L10: 1046.7 | M10: 865.5 | N10: 447.8 | O10: 224.3 | P10: =SUM(D10:O10) -> 6164.8
C11: CDD | D11: 159.7 | E11: 264.4 | F11: 221.3 | G11: 78.9 | H11: 8 | I11: 0 | J11: 0 | K11: 0.1 | L11: 0 | M11: 0.7 | N11: 1.5 | O11: 50.3 | P11: =SUM(D11:O11) -> 784.9
A12: WNC | B12: 4 | C12: HDD | D12: 42.1 | E12: 7.2 | F12: 19.7 | G12: 107.9 | H12: 404.6 | I12: 744.2 | J12: 1195.9 | K12: 1273.5 | L12: 1071.3 | M12: 846.9 | N12: 427.7 | O12: 195 | P12: =SUM(D12:O12) -> 6336
C13: CDD | D13: 188.7 | E13: 333.2 | F13: 284.8 | G13: 99.5 | H13: 11.1 | I13: 0.2 | J13: 0 | K13: 0.2 | L13: 0.1 | M13: 2.9 | N13: 7.4 | O13: 68 | P13: =SUM(D13:O13) -> 996.1
A14: SA | B14: 5 | C14: HDD | D14: 2.5 | E14: 0.2 | F14: 0.3 | G14: 16.2 | H14: 144.3 | I14: 319.1 | J14: 554.9 | K14: 612.1 | L14: 500 | M14: 369.3 | N14: 157.4 | O14: 54.4 | P14: =SUM(D14:O14) -> 2730.7
C15: CDD | D15: 333.8 | E15: 425.7 | F15: 427.1 | G15: 268 | H15: 128.5 | I15: 49.4 | J15: 33.4 | K15: 30.5 | L15: 31.2 | M15: 52.9 | N15: 75.7 | O15: 185.2 | P15: =SUM(D15:O15) -> 2041.4
A16: ESC | B16: 6 | C16: HDD | D16: 2 | E16: 0 | F16: 0.3 | G16: 19.5 | H16: 174.9 | I16: 413 | J16: 720 | K16: 754.7 | L16: 611.9 | M16: 443.5 | N16: 174.4 | O16: 56.7 | P16: =SUM(D16:O16) -> 3370.9
C17: CDD | D17: 308.5 | E17: 417 | F17: 423.6 | G17: 229.2 | H17: 61.8 | I17: 6.1 | J17: 1.9 | K17: 7.6 | L17: 3.6 | M17: 18.8 | N17: 39.2 | O17: 153.6 | P17: =SUM(D17:O17) -> 1670.9
A18: WSC | B18: 7 | C18: HDD | D18: 0.9 | E18: 0 | F18: 0.1 | G18: 5.2 | H18: 66.2 | I18: 248.6 | J18: 516.3 | K18: 532.9 | L18: 403.1 | M18: 254.9 | N18: 73.2 | O18: 8.3 | P18: =SUM(D18:O18) -> 2109.7
C19: CDD | D19: 440.3 | E19: 543.2 | F19: 566.5 | G19: 358.7 | H19: 147.3 | I19: 37.9 | J19: 7.6 | K19: 17.2 | L19: 17.1 | M19: 55.1 | N19: 118.9 | O19: 284.4 | P19: =SUM(D19:O19) -> 2594.2
A20: M | B20: 8 | C20: HDD | D20: 66.8 | E20: 6.6 | F20: 17.8 | G20: 116 | H20: 327.1 | I20: 609.7 | J20: 902.8 | K20: 889.9 | L20: 732.1 | M20: 595.9 | N20: 389 | O20: 195.4 | P20: =SUM(D20:O20) -> 4849.1
C21: CDD | D21: 267.9 | E21: 416.4 | F21: 344.7 | G21: 196.2 | H21: 69.9 | I21: 11.4 | J21: 0 | K21: 1.1 | L21: 2.9 | M21: 15.3 | N21: 43 | O21: 131 | P21: =SUM(D21:O21) -> 1499.8
A22: P | B22: 9 | C22: HDD | D22: 62.6 | E22: 15.2 | F22: 15.5 | G22: 53.4 | H22: 173.6 | I22: 364 | J22: 542.2 | K22: 543.6 | L22: 445.8 | M22: 393.1 | N22: 301.5 | O22: 155 | P22: =SUM(D22:O22) -> 3065.5
C23: CDD | D23: 117.2 | E23: 221.7 | F23: 208.7 | G23: 132.2 | H23: 41.2 | I23: 6.4 | J23: 0 | K23: 2.2 | L23: 0.3 | M23: 6.8 | N23: 12.7 | O23: 51.7 | P23: =SUM(D23:O23) -> 801.1
M25: Day | N25: Night
B26: Residential | E26: For Cooling degree days assume that day/night load distribution is 70%/30%. | M26: 0.7 | N26: 0.3
F27: In winter, assume CDD distribution is 80%/20%. | M27: 0.8 | N27: 0.2
E28: For Heating degree days assume the day night distribution is 45%/55%. | M28: 0.45 | N28: 0.55
F29: In summer, assume the HDD day/night distribution is 20%/80% | M29: 0.2 | N29: 0.8 | U29: * AEO2014 Data (2011 used to approximate 2010 because previous reports with 2010 data were significantly different)
T30: 2005 | U30: 2010 | V30: 2015 | W30: 2020 | X30: 2025 | Y30: 2030 | Z30: 2035 | AA30: 2040 | AB30: 2045 | AC30: 2050 | AD30: 2055
S31: Heating Degree Days
B32: Heating and Cooling Degree Days | I32: In Calculations | S32: New England | T32: =J34 -> 4376 | U32: 6082 | V32: 6115 | W32: 6045 | X32: 5975 | Y32: 5905 | Z32: 5835 | AA32: 5763 | AB32: =AA32*(AA32/Z32) -> 5691.8884 | AC32: =AB32*(AB32/AA32) -> 5621.6543 | AD32: =AC32*(AC32/AB32) -> 5552.2869
B33: Region | C33: CDD* | D33: HDD* | E33: Ratio C/H | I33: CDD | J33: HDD | S33: Middle Atlantic | T33: =J35 -> 4376 | U33: 5405 | V33: 5384 | W33: 5307 | X33: 5229 | Y33: 5152 | Z33: 5076 | AA33: 5000 | AB33: =AA33*(AA33/Z33) -> 4925.1379 | AC33: =AB33*(AB33/AA33) -> 4851.3967 | AD33: =AC33*(AC33/AB33) -> 4778.7595
B34: Brooklyn | C34: 1112 | D34: 4376 | E34: =C34/D34 -> 0.25411335 | I34: =C34 -> 1112 | J34: =D34 -> 4376 | K34: =I34/I$43 -> 0.11111111 | L34: =J34/J$43 -> 0.11111111 | S34: East North Central | T34: =J38 -> 4376 | U34: 6163 | V34: 5999 | W34: 5933 | X34: 5867 | Y34: 5801 | Z34: 5735 | AA34: 5669 | AB34: =AA34*(AA34/Z34) -> 5603.7595 | AC34: =AB34*(AB34/AA34) -> 5539.2699 | AD34: =AC34*(AC34/AB34) -> 5475.5224
B35: Bronx | C35: =C34 -> 1112 | D35: =D34 -> 4376 | E35: =C35/D35 -> 0.25411335 | I35: =C35 -> 1112 | J35: =D35 -> 4376 | K35: =I35/I$43 -> 0.11111111 | L35: =J35/J$43 -> 0.11111111 | S35: West North Central | T35: =U35*U35/V35 -> 7012.3009 | U35: 6635 | V35: 6278 | W35: 6226 | X35: 6170 | Y35: 6112 | Z35: 6053 | AA35: 5992 | AB35: =AA35*(AA35/Z35) -> 5931.6147 | AC35: =AB35*(AB35/AA35) -> 5871.838 | AD35: =AC35*(AC35/AB35) -> 5812.6637
B36: Manhattan | C36: =C35 -> 1112 | D36: =D35 -> 4376 | E36: =C36/D36 -> 0.25411335 | I36: =C36 -> 1112 | J36: =D36 -> 4376 | K36: =I36/I$43 -> 0.11111111 | L36: =J36/J$43 -> 0.11111111 | S36: South Atlantic | T36: =U36*U36/V36 -> 2513.1951 | U36: 2568 | V36: 2624 | W36: 2588 | X36: 2551 | Y36: 2516 | Z36: 2481 | AA36: 2448 | AB36: =AA36*(AA36/Z36) -> 2415.4389 | AC36: =AB36*(AB36/AA36) -> 2383.311 | AD36: =AC36*(AC36/AB36) -> 2351.6103
B37: Staten Island | C37: =C36 -> 1112 | D37: =D36 -> 4376 | E37: =C37/D37 -> 0.25411335 | I37: =C37 -> 1112 | J37: =D37 -> 4376 | K37: =I37/I$43 -> 0.11111111 | L37: =J37/J$43 -> 0.11111111 | S37: East South Central | T37: =J37 -> 4376 | U37: 3358 | V37: 3298 | W37: 3258 | X37: 3218 | Y37: 3177 | Z37: 3135 | AA37: 3093 | AB37: =AA37*(AA37/Z37) -> 3051.5627 | AC37: =AB37*(AB37/AA37) -> 3010.6805 | AD37: =AC37*(AC37/AB37) -> 2970.346
B38: Queens | C38: =C37 -> 1112 | D38: =D37 -> 4376 | E38: =C38/D38 -> 0.25411335 | I38: =C38 -> 1112 | J38: =D38 -> 4376 | K38: =I38/I$43 -> 0.11111111 | L38: =J38/J$43 -> 0.11111111 | S38: West South Central | T38: =J39 -> 4376 | U38: 2145 | V38: 1979 | W38: 1924 | X38: 1870 | Y38: 1815 | Z38: 1761 | AA38: 1707 | AB38: =AA38*(AA38/Z38) -> 1654.6559 | AC38: =AB38*(AB38/AA38) -> 1603.9169 | AD38: =AC38*(AC38/AB38) -> 1554.7337
B39: NYC | C39: =C38 -> 1112 | D39: =D38 -> 4376 | E39: =C39/D39 -> 0.25411335 | I39: =C39 -> 1112 | J39: =D39 -> 4376 | K39: =I39/I$43 -> 0.11111111 | L39: =J39/J$43 -> 0.11111111 | S39: Mountain | T39: =U39*U39/V39 -> 5777.1557 | U39: 5223 | V39: 4722 | W39: 4660 | X39: 4586 | Y39: 4508 | Z39: 4428 | AA39: 4347 | AB39: =AA39*(AA39/Z39) -> 4267.4817 | AC39: =AB39*(AB39/AA39) -> 4189.418 | AD39: =AC39*(AC39/AB39) -> 4112.7823
B40: West North Central | C40: =C39 -> 1112 | D40: =D39 -> 4376 | E40: =C40/D40 -> 0.25411335 | I40: =C40 -> 1112 | J40: =D40 -> 4376 | K40: =I40/I$43 -> 0.11111111 | L40: =J40/J$43 -> 0.11111111 | S40: Pacific | T40: =U40*U40/V40 -> 3876.6389 | U40: 3532 | V40: 3218 | W40: 3244 | X40: 3267 | Y40: 3290 | Z40: 3314 | AA40: 3339 | AB40: =AA40*(AA40/Z40) -> 3364.1886 | AC40: =AB40*(AB40/AA40) -> 3389.5672 | AD40: =AC40*(AC40/AB40) -> 3415.1373
B41: Mountain | C41: =C40 -> 1112 | D41: =D40 -> 4376 | E41: =C41/D41 -> 0.25411335 | I41: =C41 -> 1112 | J41: =D41 -> 4376 | K41: =I41/I$43 -> 0.11111111 | L41: =J41/J$43 -> 0.11111111 | S41: United States | U41: 4257.6396 | V41: 4085.9526 | W41: 4015.4521 | X41: 3945.3782 | Y41: 3877.0732 | Z41: 3810.3362 | AA41: 3744.6064 | AB41: =AA41*(AA41/Z41) -> 3680.0106 | AC41: =AB41*(AB41/AA41) -> 3616.529 | AD41: =AC41*(AC41/AB41) -> 3554.1425
B42: Pacific | C42: =C41 -> 1112 | D42: =D41 -> 4376 | E42: =C42/D42 -> 0.25411335 | I42: =C42 -> 1112 | J42: =D42 -> 4376 | K42: =I42/I$43 -> 0.11111111 | L42: =J42/J$43 -> 0.11111111
A43: *Data from 10yrAVG.xls | H43: Total | I43: =SUM(I34:I42) -> 10008 | J43: =SUM(J34:J42) -> 39384 | K43: =SUM(K34:K42) -> 1 | L43: =SUM(L34:L42) -> 1 | S43: Cooling Degree Days
A44: 10-yr average (1998-2008) weighted by XXXX population. | S44: New England | T44: =I34 -> 1112 | U44: 568 | V44: 546 | W44: 565 | X44: 583 | Y44: 601 | Z44: 620 | AA44: 638 | AB44: =AA44*(AA44/Z44) -> 656.52258 | AC44: =AB44*(AB44/AA44) -> 675.58291 | AD44: =AC44*(AC44/AB44) -> 695.19661
S45: Middle Atlantic | T45: =I35 -> 1112 | U45: 885 | V45: 821 | W45: 848 | X45: 875 | Y45: 903 | Z45: 929 | AA45: 956 | AB45: =AA45*(AA45/Z45) -> 983.78471 | AC45: =AB45*(AB45/AA45) -> 1012.377 | AD45: =AC45*(AC45/AB45) -> 1041.8002
S46: East North Central | T46: =I38 -> 1112 | U46: 855 | V46: 814 | W46: 825 | X46: 835 | Y46: 846 | Z46: 856 | AA46: 867 | AB46: =AA46*(AA46/Z46) -> 878.14136 | AC46: =AB46*(AB46/AA46) -> 889.42588 | AD46: =AC46*(AC46/AB46) -> 900.85542
A47: AEO 2014 | B47: Table 4. Residential Sector Key Indicators and Consumption | S47: West North Central | T47: =U47*U47/V47 -> 1114.2677 | U47: 1064 | V47: 1016 | W47: 1024 | X47: 1032 | Y47: 1041 | Z47: 1051 | AA47: 1061 | AB47: =AA47*(AA47/Z47) -> 1071.0951 | AC47: =AB47*(AB47/AA47) -> 1081.2863 | AD47: =AC47*(AC47/AB47) -> 1091.5745
B48: (quadrillion Btu, unless otherwise noted) | S48: South Atlantic | T48: =U48*U48/V48 -> 2366.1552 | U48: 2267 | V48: 2172 | W48: 2208 | X48: 2244 | Y48: 2280 | Z48: 2316 | AA48: 2350 | AB48: =AA48*(AA48/Z48) -> 2384.4991 | AC48: =AB48*(AB48/AA48) -> 2419.5047 | AD48: =AC48*(AC48/AB48) -> 2455.0242
S49: East South Central | T49: =I37 -> 1112 | U49: 1740 | V49: 1761 | W49: 1795 | X49: 1829 | Y49: 1863 | Z49: 1897 | AA49: 1931 | AB49: =AA49*(AA49/Z49) -> 1965.6094 | AC49: =AB49*(AB49/AA49) -> 2000.8391 | AD49: =AC49*(AC49/AB49) -> 2036.7002
B50: Key Indicators and Consumption | D50: 2007 | E50: 2010 | F50: 2015 | G50: 2020 | H50: 2025 | I50: 2030 | J50: 2035 | K50: 2040 | S50: West South Central | T50: =U50*U50/V50 -> 3346.3141 | U50: 3067 | V50: 2811 | W50: 2880 | X50: 2948 | Y50: 3017 | Z50: 3086 | AA50: 3155 | AB50: =AA50*(AA50/Z50) -> 3225.5428 | AC50: =AB50*(AB50/AA50) -> 3297.6628 | AD50: =AC50*(AC50/AB50) -> 3371.3954
S51: Mountain | T51: =U51*U51/V51 -> 1406.9702 | U51: 1506 | V51: 1612 | W51: 1661 | X51: 1719 | Y51: 1779 | Z51: 1841 | AA51: 1905 | AB51: =AA51*(AA51/Z51) -> 1971.2249 | AC51: =AB51*(AB51/AA51) -> 2039.752 | AD51: =AC51*(AC51/AB51) -> 2110.6613
B52: Key Indicators | S52: Pacific | T52: =U52*U52/V52 -> 684.05698 | U52: 767 | V52: 860 | W52: 860 | X52: 861 | Y52: 861 | Z52: 861 | AA52: 861 | AB52: =AA52*(AA52/Z52) -> 861 | AC52: =AB52*(AB52/AA52) -> 861 | AD52: =AC52*(AC52/AB52) -> 861
B53: Households (millions) | S53: United States | U53: 1480.6302 | V53: 1447.297 | W53: 1488.2861 | X53: 1529.6455 | Y53: 1571.5615 | Z53: 1613.6486 | AA53: 1656.1577 | AB53: =AA53*(AA53/Z53) -> 1699.7867 | AC53: =AB53*(AB53/AA53) -> 1744.565 | AD53: =AC53*(AC53/AB53) -> 1790.523
B54: Single-Family | D54: 80.794464 | E54: 82.108704 | F54: 81.206581 | G54: 85.713097 | H54: 89.733536 | I54: 93.555962 | J54: 96.987389 | K54: 100.37368
