Workbook
Name AnswerData: #REF!
Name AnswerData: #REF!
Name AnswerData: #REF!
Name AnswerData: #REF!
Name AnswerData: #REF!
Name BDSEFF: [1]TechInfo!$J$33
Name BFBEFF: [1]TechInfo!$J$32
Name BFCEFF: [1]TechInfo!$J$34
Name blah: #REF!
Name bprint: #REF!
Name bprint: #REF!
Name bprint: #REF!
Name bprint: #REF!
Name BSGEFF: [1]TechInfo!$J$35
Name BSOEFF: [1]TechInfo!$J$31
Name BST_AF: [1]CHPData!$B$40
Name BST2_INV: [1]CHPData!$C$66
Name BST3_INV: [1]CHPData!$D$66
Name CCT_AF: [1]CHPData!$B$81
Name CCT2_INV: [1]CHPData!$C$91
Name CCT3_INV: [1]CHPData!$D$91
Name CCT4_INV: [1]CHPData!$E$91
Name CCT5_INV: [1]CHPData!$F$91
Name CFBEFF: [1]TechInfo!$J$29
Name CMM_SUPPLY_CRV_TABLE: [2]cum2025curves!#REF!
Name CMM_SUPPLY_CRV_TABLE: [2]cum2025curves!#REF!
Name CMM_SUPPLY_CRV_TABLE: [2]cum2025curves!#REF!
Name CMM_SUPPLY_CRV_TABLE: [2]cum2025curves!#REF!
Name cprint: #REF!
Name cprint: #REF!
Name cprint: #REF!
Name cprint: #REF!
Name CPVEFF: [1]TechInfo!$J$27
Name CSOEFF: [1]TechInfo!$J$28
Name DSTEFF: [1]TechInfo!$J$37
Name exch_rate: #REF!
Name exch_rate: #REF!
Name exch_rate: #REF!
Name exch_rate: #REF!
Name exch_rate: #REF!
Name FCL_AF: [1]CHPData!$B$154
Name FCL2_INV: [1]CHPData!$C$163
Name FCL3_INV: [1]CHPData!$D$163
Name fitfile: [3]MODEL!$D$38
Name INF: [3]MODEL!$H$14
Name million_short_tons_to_short_ton: [4]Steps!$Y$5
Name MMBTU_to_PJ: [4]Steps!$Y$6
Name MT2_INV: [1]CHPData!$C$141
Name MT3_INV: [1]CHPData!$D$141
Name neb: #REF!
Name PPP: [3]MODEL!$D$12
Name PPPEX: [3]MODEL!$D$13
Name rail_coal: #REF!
Name rail_coal: #REF!
Name rail_coal: #REF!
Name rail_coal: #REF!
Name rail_coal: #REF!
Name REG1_AF: [1]CHPData!$B$107
Name REG1_INV: [1]CHPData!$B$117
Name REG2_AF: [1]CHPData!$C$107

Sheet UC_OIL
A3: Maximum trade of oil product
A4: ~UC_Sets: R_E: AllRegions
E5: ~UC_T: UC_RHSRTS~UP
A6: UC_N | B6: Pset_PN | C6: Pset_CI | D6: Cset_CN | E6: Year | F6: UC_FLO | G6: UC_RHSRTS~UP~0 | H6: R0 | I6: R1 | J6: R2 | K6: R3 | L6: R4 | M6: R5 | N6: R6 | O6: UC_Desc
A7: UC_TRADEOILR2 | B7: X* | C7: GSCR1,GSRR1,DSHR1,DSLR1,DSUR1,RFLR1 | D7: GSCR1,GSRR1,DSHR1,DSLR1,DSUR1,RFLR1 | E7: 2010 | F7: 1 | G7: 15 | J7: =#REF!*Conv!$C$46*Conv!$I$5*365*10^3 -> #REF! | K7: =#REF!*Conv!$C$46*Conv!$I$5*365*10^3 -> #REF! | L7: =#REF!*Conv!$C$46*Conv!$I$5*365*10^3 -> #REF! | M7: =#REF!*Conv!$C$46*Conv!$I$5*365*10^3 -> #REF! | N7: =#REF!*Conv!$C$46*Conv!$I$5*365*10^3 -> #REF!
B8: X* | C8: GSCR1,GSRR1,DSHR1,DSLR1,DSUR1,RFLR1 | D8: GSCR1,GSRR1,DSHR1,DSLR1,DSUR1,RFLR1 | E8: 2015 | F8: 1 | J8: =J7 -> #REF! | K8: =K7 -> #REF! | L8: =L7 -> #REF! | M8: =M7 -> #REF! | N8: =N7 -> #REF!
B9: X* | C9: GSCR1,GSRR1,DSHR1,DSLR1,DSUR1,RFLR1 | D9: GSCR1,GSRR1,DSHR1,DSLR1,DSUR1,RFLR1 | E9: 2020 | F9: 1 | J9: =J8 -> #REF! | K9: =K8 -> #REF! | L9: =L8 -> #REF! | M9: =M8 -> #REF! | N9: =N8 -> #REF!
B10: X* | C10: GSCR1,GSRR1,DSHR1,DSLR1,DSUR1,RFLR1 | D10: GSCR1,GSRR1,DSHR1,DSLR1,DSUR1,RFLR1 | E10: 2025 | F10: 1 | J10: =J9 -> #REF! | K10: =K9 -> #REF! | L10: =L9 -> #REF! | M10: =M9 -> #REF! | N10: =N9 -> #REF!
B11: X* | C11: GSCR1,GSRR1,DSHR1,DSLR1,DSUR1,RFLR1 | D11: GSCR1,GSRR1,DSHR1,DSLR1,DSUR1,RFLR1 | E11: 2030 | F11: 1 | J11: =J10 -> #REF! | K11: =K10 -> #REF! | L11: =L10 -> #REF! | M11: =M10 -> #REF! | N11: =N10 -> #REF!
B12: X* | C12: GSCR1,GSRR1,DSHR1,DSLR1,DSUR1,RFLR1 | D12: GSCR1,GSRR1,DSHR1,DSLR1,DSUR1,RFLR1 | E12: 2035 | F12: 1 | J12: =J11 -> #REF! | K12: =K11 -> #REF! | L12: =L11 -> #REF! | M12: =M11 -> #REF! | N12: =N11 -> #REF!
B13: X* | C13: GSCR1,GSRR1,DSHR1,DSLR1,DSUR1,RFLR1 | D13: GSCR1,GSRR1,DSHR1,DSLR1,DSUR1,RFLR1 | E13: 2040 | F13: 1 | J13: =J12 -> #REF! | K13: =K12 -> #REF! | L13: =L12 -> #REF! | M13: =M12 -> #REF! | N13: =N12 -> #REF!
B14: X* | C14: GSCR1,GSRR1,DSHR1,DSLR1,DSUR1,RFLR1 | D14: GSCR1,GSRR1,DSHR1,DSLR1,DSUR1,RFLR1 | E14: 2045 | F14: 1 | J14: =J13 -> #REF! | K14: =K13 -> #REF! | L14: =L13 -> #REF! | M14: =M13 -> #REF! | N14: =N13 -> #REF!
B15: X* | C15: GSCR1,GSRR1,DSHR1,DSLR1,DSUR1,RFLR1 | D15: GSCR1,GSRR1,DSHR1,DSLR1,DSUR1,RFLR1 | E15: 2050 | F15: 1 | J15: =J14 -> #REF! | K15: =K14 -> #REF! | L15: =L14 -> #REF! | M15: =M14 -> #REF! | N15: =N14 -> #REF!
B16: X* | C16: GSCR1,GSRR1,DSHR1,DSLR1,DSUR1,RFLR1 | D16: GSCR1,GSRR1,DSHR1,DSLR1,DSUR1,RFLR1 | E16: 2055 | F16: 1 | J16: =J15 -> #REF! | K16: =K15 -> #REF! | L16: =L15 -> #REF! | M16: =M15 -> #REF! | N16: =N15 -> #REF!

Sheet UC_OIL2
A2: Maximum capacity technology growth:
A3: ~UC_Sets: R_E: R1
A4: ~UC_Sets: T_SUC:
G5: ~UC_T
A6: UC_N | B6: Pset_PN | C6: Pset_CI | D6: Pset_CO | E6: UC_ATTR | F6: Year | G6: LimType | H6: UC_CAP~2010 | I6: UC_CAP~2015 | J6: UC_CAP~2020 | K6: UC_CAP~2025 | L6: UC_CAP~2030 | M6: UC_CAP~2035 | N6: UC_CAP~2040 | O6: UC_CAP~2045 | P6: UC_CAP~2050 | Q6: UC_CAP~2055 | R6: UC_CAP~RHS | S6: UC_RHSRTS | T6: UC_RHSRTS~0 | U6: UC_Desc
A7: UC_GrowthOfOILUP1 | B7: =TechData_R0!C9 -> MINOILD1 | E7: CAP, GROWTH | G7: UP | H7: =TechData_R0!J9 -> 1.005 | I7: =H7 -> 1.005 | J7: =I7 -> 1.005 | K7: =J7 -> 1.005 | L7: =K7 -> 1.005 | M7: =L7 -> 1.005 | N7: =M7 -> 1.005 | O7: =N7 -> 1.005 | P7: =O7 -> 1.005 | Q7: =P7 -> 1.005 | R7: =IF(TechData_R0!H9="",1,TechData_R0!H9) -> 1 | T7: 5
A8: UC_GrowthOfOILUP2 | B8: =TechData_R0!C10 -> MINOILD2 | E8: CAP, GROWTH | G8: UP | H8: =TechData_R0!J10 -> 1.005 | I8: =H8 -> 1.005 | J8: =I8 -> 1.005 | K8: =J8 -> 1.005 | L8: =K8 -> 1.005 | M8: =L8 -> 1.005 | N8: =M8 -> 1.005 | O8: =N8 -> 1.005 | P8: =O8 -> 1.005 | Q8: =P8 -> 1.005 | R8: =IF(TechData_R0!H10="",1,TechData_R0!H10) -> 1 | T8: 5
A9: UC_GrowthOfOILUP3 | B9: =TechData_R0!C11 -> MINOILD3 | E9: CAP, GROWTH | G9: UP | H9: =TechData_R0!J11 -> 1.005 | I9: =H9 -> 1.005 | J9: =I9 -> 1.005 | K9: =J9 -> 1.005 | L9: =K9 -> 1.005 | M9: =L9 -> 1.005 | N9: =M9 -> 1.005 | O9: =N9 -> 1.005 | P9: =O9 -> 1.005 | Q9: =P9 -> 1.005 | R9: =IF(TechData_R0!H11="",1,TechData_R0!H11) -> 1 | T9: 5
A10: UC_GrowthOfOILUP4 | B10: =TechData_R0!C12 -> MINOILD4 | E10: CAP, GROWTH | G10: UP | H10: =TechData_R0!J12 -> 1.005 | I10: =H10 -> 1.005 | J10: =I10 -> 1.005 | K10: =J10 -> 1.005 | L10: =K10 -> 1.005 | M10: =L10 -> 1.005 | N10: =M10 -> 1.005 | O10: =N10 -> 1.005 | P10: =O10 -> 1.005 | Q10: =P10 -> 1.005 | R10: =IF(TechData_R0!H12="",1,TechData_R0!H12) -> 0.50462412 | T10: 5
A11: UC_GrowthOfOILUP5 | B11: =TechData_R0!C13 -> MINOILD5 | E11: CAP, GROWTH | G11: UP | H11: =TechData_R0!J13 -> 1.005 | I11: =H11 -> 1.005 | J11: =I11 -> 1.005 | K11: =J11 -> 1.005 | L11: =K11 -> 1.005 | M11: =L11 -> 1.005 | N11: =M11 -> 1.005 | O11: =N11 -> 1.005 | P11: =O11 -> 1.005 | Q11: =P11 -> 1.005 | R11: =IF(TechData_R0!H13="",1,TechData_R0!H13) -> 0.75693618 | T11: 5
A12: UC_GrowthOfOILUP6 | B12: =TechData_R0!C32 -> IMPOILHH13 | E12: CAP, GROWTH | G12: UP | H12: =TechData_R0!J32 -> 1.005 | I12: =H12 -> 1.005 | J12: =I12 -> 1.005 | K12: =J12 -> 1.005 | L12: =K12 -> 1.005 | M12: =L12 -> 1.005 | N12: =M12 -> 1.005 | O12: =N12 -> 1.005 | P12: =O12 -> 1.005 | Q12: =P12 -> 1.005 | R12: =IF(TechData_R0!H32="",1,TechData_R0!H32) -> 1 | T12: 5
A13: UC_GrowthOfOILUP7 | B13: =TechData_R0!C33 -> IMPOILHH11 | E13: CAP, GROWTH | G13: UP | H13: =TechData_R0!J33 -> 1.005 | I13: =H13 -> 1.005 | J13: =I13 -> 1.005 | K13: =J13 -> 1.005 | L13: =K13 -> 1.005 | M13: =L13 -> 1.005 | N13: =M13 -> 1.005 | O13: =N13 -> 1.005 | P13: =O13 -> 1.005 | Q13: =P13 -> 1.005 | R13: =IF(TechData_R0!H33="",1,TechData_R0!H33) -> 1 | T13: 5
A14: UC_GrowthOfOILUP8 | B14: =TechData_R0!C34 -> IMPOILHH12 | E14: CAP, GROWTH | G14: UP | H14: =TechData_R0!J34 -> 1.005 | I14: =H14 -> 1.005 | J14: =I14 -> 1.005 | K14: =J14 -> 1.005 | L14: =K14 -> 1.005 | M14: =L14 -> 1.005 | N14: =M14 -> 1.005 | O14: =N14 -> 1.005 | P14: =O14 -> 1.005 | Q14: =P14 -> 1.005 | R14: =IF(TechData_R0!H34="",1,TechData_R0!H34) -> 1 | T14: 5
A15: UC_GrowthOfOILUP9 | B15: =TechData_R0!C35 -> IMPOILHH14 | E15: CAP, GROWTH | G15: UP | H15: =TechData_R0!J35 -> 1.005 | I15: =H15 -> 1.005 | J15: =I15 -> 1.005 | K15: =J15 -> 1.005 | L15: =K15 -> 1.005 | M15: =L15 -> 1.005 | N15: =M15 -> 1.005 | O15: =N15 -> 1.005 | P15: =O15 -> 1.005 | Q15: =P15 -> 1.005 | R15: =IF(TechData_R0!H35="",1,TechData_R0!H35) -> 1 | T15: 5
A16: UC_GrowthOfOILUP10 | B16: =TechData_R0!C36 -> IMPOILHH15 | E16: CAP, GROWTH | G16: UP | H16: =TechData_R0!J36 -> 1.005 | I16: =H16 -> 1.005 | J16: =I16 -> 1.005 | K16: =J16 -> 1.005 | L16: =K16 -> 1.005 | M16: =L16 -> 1.005 | N16: =M16 -> 1.005 | O16: =N16 -> 1.005 | P16: =O16 -> 1.005 | Q16: =P16 -> 1.005 | R16: =IF(TechData_R0!H36="",1,TechData_R0!H36) -> 1 | T16: 5
A17: UC_GrowthOfOILUP11 | B17: =TechData_R0!C37 -> IMPOILHL13 | E17: CAP, GROWTH | G17: UP | H17: =TechData_R0!J37 -> 1.005 | I17: =H17 -> 1.005 | J17: =I17 -> 1.005 | K17: =J17 -> 1.005 | L17: =K17 -> 1.005 | M17: =L17 -> 1.005 | N17: =M17 -> 1.005 | O17: =N17 -> 1.005 | P17: =O17 -> 1.005 | Q17: =P17 -> 1.005 | R17: =IF(TechData_R0!H37="",1,TechData_R0!H37) -> 1 | T17: 5
A18: UC_GrowthOfOILUP12 | B18: =TechData_R0!C38 -> IMPOILHL11 | E18: CAP, GROWTH | G18: UP | H18: =TechData_R0!J38 -> 1.005 | I18: =H18 -> 1.005 | J18: =I18 -> 1.005 | K18: =J18 -> 1.005 | L18: =K18 -> 1.005 | M18: =L18 -> 1.005 | N18: =M18 -> 1.005 | O18: =N18 -> 1.005 | P18: =O18 -> 1.005 | Q18: =P18 -> 1.005 | R18: =IF(TechData_R0!H38="",1,TechData_R0!H38) -> 1 | T18: 5
A19: UC_GrowthOfOILUP13 | B19: =TechData_R0!C39 -> IMPOILHL12 | E19: CAP, GROWTH | G19: UP | H19: =TechData_R0!J39 -> 1.005 | I19: =H19 -> 1.005 | J19: =I19 -> 1.005 | K19: =J19 -> 1.005 | L19: =K19 -> 1.005 | M19: =L19 -> 1.005 | N19: =M19 -> 1.005 | O19: =N19 -> 1.005 | P19: =O19 -> 1.005 | Q19: =P19 -> 1.005 | R19: =IF(TechData_R0!H39="",1,TechData_R0!H39) -> 1 | T19: 5
A20: UC_GrowthOfOILUP14 | B20: =TechData_R0!C40 -> IMPOILHL14 | E20: CAP, GROWTH | G20: UP | H20: =TechData_R0!J40 -> 1.005 | I20: =H20 -> 1.005 | J20: =I20 -> 1.005 | K20: =J20 -> 1.005 | L20: =K20 -> 1.005 | M20: =L20 -> 1.005 | N20: =M20 -> 1.005 | O20: =N20 -> 1.005 | P20: =O20 -> 1.005 | Q20: =P20 -> 1.005 | R20: =IF(TechData_R0!H40="",1,TechData_R0!H40) -> 1 | T20: 5
A21: UC_GrowthOfOILUP15 | B21: =TechData_R0!C41 -> IMPOILHL15 | E21: CAP, GROWTH | G21: UP | H21: =TechData_R0!J41 -> 1.005 | I21: =H21 -> 1.005 | J21: =I21 -> 1.005 | K21: =J21 -> 1.005 | L21: =K21 -> 1.005 | M21: =L21 -> 1.005 | N21: =M21 -> 1.005 | O21: =N21 -> 1.005 | P21: =O21 -> 1.005 | Q21: =P21 -> 1.005 | R21: =IF(TechData_R0!H41="",1,TechData_R0!H41) -> 1 | T21: 5
A22: UC_GrowthOfOILUP16 | B22: =TechData_R0!C42 -> IMPOILHV13 | E22: CAP, GROWTH | G22: UP | H22: =TechData_R0!J42 -> 1.005 | I22: =H22 -> 1.005 | J22: =I22 -> 1.005 | K22: =J22 -> 1.005 | L22: =K22 -> 1.005 | M22: =L22 -> 1.005 | N22: =M22 -> 1.005 | O22: =N22 -> 1.005 | P22: =O22 -> 1.005 | Q22: =P22 -> 1.005 | R22: =IF(TechData_R0!H42="",1,TechData_R0!H42) -> 1 | T22: 5
A23: UC_GrowthOfOILUP17 | B23: =TechData_R0!C43 -> IMPOILHV11 | E23: CAP, GROWTH | G23: UP | H23: =TechData_R0!J43 -> 1.005 | I23: =H23 -> 1.005 | J23: =I23 -> 1.005 | K23: =J23 -> 1.005 | L23: =K23 -> 1.005 | M23: =L23 -> 1.005 | N23: =M23 -> 1.005 | O23: =N23 -> 1.005 | P23: =O23 -> 1.005 | Q23: =P23 -> 1.005 | R23: =IF(TechData_R0!H43="",1,TechData_R0!H43) -> 1 | T23: 5
... A36: UC_GrowthOfOILUP30 | B36: =TechData_R0!C56 -> IMPOILMH15 | E36: CAP, GROWTH | G36: UP | H36: =TechData_R0!J56 -> 1.005 | I36: =H36 -> 1.005 | J36: =I36 -> 1.005 | K36: =J36 -> 1.005 | L36: =K36 -> 1.005 | M36: =L36 -> 1.005 | N36: =M36 -> 1.005 | O36: =N36 -> 1.005 | P36: =O36 -> 1.005 | Q36: =P36 -> 1.005 | R36: =IF(TechData_R0!H56="",1,TechData_R0!H56) -> 1 | T36: 5
A37: UC_GrowthOfOILUP31 | B37: =TechData_R0!C58 -> IMPOILHH23 | E37: CAP, GROWTH | G37: UP | H37: =TechData_R0!J58 -> 1.005 | I37: =H37 -> 1.005 | J37: =I37 -> 1.005 | K37: =J37 -> 1.005 | L37: =K37 -> 1.005 | M37: =L37 -> 1.005 | N37: =M37 -> 1.005 | O37: =N37 -> 1.005 | P37: =O37 -> 1.005 | Q37: =P37 -> 1.005 | R37: =IF(TechData_R0!H57="",1,TechData_R0!H57) -> 1 | T37: 5
A38: UC_GrowthOfOILUP32 | B38: =TechData_R0!C59 -> IMPOILHH21 | E38: CAP, GROWTH | G38: UP | H38: =TechData_R0!J59 -> 1.005 | I38: =H38 -> 1.005 | J38: =I38 -> 1.005 | K38: =J38 -> 1.005 | L38: =K38 -> 1.005 | M38: =L38 -> 1.005 | N38: =M38 -> 1.005 | O38: =N38 -> 1.005 | P38: =O38 -> 1.005 | Q38: =P38 -> 1.005 | R38: =IF(TechData_R0!H58="",1,TechData_R0!H58) -> 1 | T38: 5
A39: UC_GrowthOfOILUP33 | B39: =TechData_R0!C60 -> IMPOILHH22 | E39: CAP, GROWTH | G39: UP | H39: =TechData_R0!J60 -> 1.005 | I39: =H39 -> 1.005 | J39: =I39 -> 1.005 | K39: =J39 -> 1.005 | L39: =K39 -> 1.005 | M39: =L39 -> 1.005 | N39: =M39 -> 1.005 | O39: =N39 -> 1.005 | P39: =O39 -> 1.005 | Q39: =P39 -> 1.005 | R39: =IF(TechData_R0!H59="",1,TechData_R0!H59) -> 1 | T39: 5
A40: UC_GrowthOfOILUP34 | B40: =TechData_R0!C61 -> IMPOILHH24 | E40: CAP, GROWTH | G40: UP | H40: =TechData_R0!J61 -> 1.005 | I40: =H40 -> 1.005 | J40: =I40 -> 1.005 | K40: =J40 -> 1.005 | L40: =K40 -> 1.005 | M40: =L40 -> 1.005 | N40: =M40 -> 1.005 | O40: =N40 -> 1.005 | P40: =O40 -> 1.005 | Q40: =P40 -> 1.005 | R40: =IF(TechData_R0!H60="",1,TechData_R0!H60) -> 1 | T40: 5
A41: UC_GrowthOfOILUP35 | B41: =TechData_R0!C62 -> IMPOILHH25 | E41: CAP, GROWTH | G41: UP | H41: =TechData_R0!J62 -> 1.005 | I41: =H41 -> 1.005 | J41: =I41 -> 1.005 | K41: =J41 -> 1.005 | L41: =K41 -> 1.005 | M41: =L41 -> 1.005 | N41: =M41 -> 1.005 | O41: =N41 -> 1.005 | P41: =O41 -> 1.005 | Q41: =P41 -> 1.005 | R41: =IF(TechData_R0!H61="",1,TechData_R0!H61) -> 1 | T41: 5
A42: UC_GrowthOfOILUP36 | B42: =TechData_R0!C63 -> IMPOILHL23 | E42: CAP, GROWTH | G42: UP | H42: =TechData_R0!J63 -> 1.005 | I42: =H42 -> 1.005 | J42: =I42 -> 1.005 | K42: =J42 -> 1.005 | L42: =K42 -> 1.005 | M42: =L42 -> 1.005 | N42: =M42 -> 1.005 | O42: =N42 -> 1.005 | P42: =O42 -> 1.005 | Q42: =P42 -> 1.005 | R42: =IF(TechData_R0!H62="",1,TechData_R0!H62) -> 1 | T42: 5
A43: UC_GrowthOfOILUP37 | B43: =TechData_R0!C64 -> IMPOILHL21 | E43: CAP, GROWTH | G43: UP | H43: =TechData_R0!J64 -> 1.005 | I43: =H43 -> 1.005 | J43: =I43 -> 1.005 | K43: =J43 -> 1.005 | L43: =K43 -> 1.005 | M43: =L43 -> 1.005 | N43: =M43 -> 1.005 | O43: =N43 -> 1.005 | P43: =O43 -> 1.005 | Q43: =P43 -> 1.005 | R43: =IF(TechData_R0!H63="",1,TechData_R0!H63) -> 1 | T43: 5
A44: UC_GrowthOfOILUP38 | B44: =TechData_R0!C65 -> IMPOILHL22 | E44: CAP, GROWTH | G44: UP | H44: =TechData_R0!J65 -> 1.005 | I44: =H44 -> 1.005 | J44: =I44 -> 1.005 | K44: =J44 -> 1.005 | L44: =K44 -> 1.005 | M44: =L44 -> 1.005 | N44: =M44 -> 1.005 | O44: =N44 -> 1.005 | P44: =O44 -> 1.005 | Q44: =P44 -> 1.005 | R44: =IF(TechData_R0!H64="",1,TechData_R0!H64) -> 1 | T44: 5
A45: UC_GrowthOfOILUP39 | B45: =TechData_R0!C66 -> IMPOILHL24 | E45: CAP, GROWTH | G45: UP | H45: =TechData_R0!J66 -> 1.005 | I45: =H45 -> 1.005 | J45: =I45 -> 1.005 | K45: =J45 -> 1.005 | L45: =K45 -> 1.005 | M45: =L45 -> 1.005 | N45: =M45 -> 1.005 | O45: =N45 -> 1.005 | P45: =O45 -> 1.005 | Q45: =P45 -> 1.005 | R45: =IF(TechData_R0!H65="",1,TechData_R0!H65) -> 1 | T45: 5
A46: UC_GrowthOfOILUP40 | B46: =TechData_R0!C67 -> IMPOILHL25 | E46: CAP, GROWTH | G46: UP | H46: =TechData_R0!J67 -> 1.005 | I46: =H46 -> 1.005 | J46: =I46 -> 1.005 | K46: =J46 -> 1.005 | L46: =K46 -> 1.005 | M46: =L46 -> 1.005 | N46: =M46 -> 1.005 | O46: =N46 -> 1.005 | P46: =O46 -> 1.005 | Q46: =P46 -> 1.005 | R46: =IF(TechData_R0!H66="",1,TechData_R0!H66) -> 1 | T46: 5
A47: UC_GrowthOfOILUP41 | B47: =TechData_R0!C68 -> IMPOILHV23 | E47: CAP, GROWTH | G47: UP | H47: =TechData_R0!J68 -> 1.005 | I47: =H47 -> 1.005 | J47: =I47 -> 1.005 | K47: =J47 -> 1.005 | L47: =K47 -> 1.005 | M47: =L47 -> 1.005 | N47: =M47 -> 1.005 | O47: =N47 -> 1.005 | P47: =O47 -> 1.005 | Q47: =P47 -> 1.005 | R47: =IF(TechData_R0!H67="",1,TechData_R0!H67) -> 1 | T47: 5
A48: UC_GrowthOfOILUP42 | B48: =TechData_R0!C69 -> IMPOILHV21 | E48: CAP, GROWTH | G48: UP | H48: =TechData_R0!J69 -> 1.005 | I48: =H48 -> 1.005 | J48: =I48 -> 1.005 | K48: =J48 -> 1.005 | L48: =K48 -> 1.005 | M48: =L48 -> 1.005 | N48: =M48 -> 1.005 | O48: =N48 -> 1.005 | P48: =O48 -> 1.005 | Q48: =P48 -> 1.005 | R48: =IF(TechData_R0!H68="",1,TechData_R0!H68) -> 1 | T48: 5
... A61: UC_GrowthOfOILUP55 | B61: =TechData_R0!C82 -> IMPOILMH25 | E61: CAP, GROWTH | G61: UP | H61: =TechData_R0!J82 -> 1.005 | I61: =H61 -> 1.005 | J61: =I61 -> 1.005 | K61: =J61 -> 1.005 | L61: =K61 -> 1.005 | M61: =L61 -> 1.005 | N61: =M61 -> 1.005 | O61: =N61 -> 1.005 | P61: =O61 -> 1.005 | Q61: =P61 -> 1.005 | R61: =IF(TechData_R0!H81="",1,TechData_R0!H81) -> 1 | T61: 5
A62: UC_GrowthOfOILUP56 | B62: =TechData_R0!C84 -> IMPOILHH33 | E62: CAP, GROWTH | G62: UP | H62: =TechData_R0!J84 -> 1.005 | I62: =H62 -> 1.005 | J62: =I62 -> 1.005 | K62: =J62 -> 1.005 | L62: =K62 -> 1.005 | M62: =L62 -> 1.005 | N62: =M62 -> 1.005 | O62: =N62 -> 1.005 | P62: =O62 -> 1.005 | Q62: =P62 -> 1.005 | R62: =IF(TechData_R0!H82="",1,TechData_R0!H82) -> 1 | T62: 5
A63: UC_GrowthOfOILUP57 | B63: =TechData_R0!C85 -> IMPOILHH31 | E63: CAP, GROWTH | G63: UP | H63: =TechData_R0!J85 -> 1.005 | I63: =H63 -> 1.005 | J63: =I63 -> 1.005 | K63: =J63 -> 1.005 | L63: =K63 -> 1.005 | M63: =L63 -> 1.005 | N63: =M63 -> 1.005 | O63: =N63 -> 1.005 | P63: =O63 -> 1.005 | Q63: =P63 -> 1.005 | R63: =IF(TechData_R0!H83="",1,TechData_R0!H83) -> 1 | T63: 5
A64: UC_GrowthOfOILUP58 | B64: =TechData_R0!C86 -> IMPOILHH32 | E64: CAP, GROWTH | G64: UP | H64: =TechData_R0!J86 -> 1.005 | I64: =H64 -> 1.005 | J64: =I64 -> 1.005 | K64: =J64 -> 1.005 | L64: =K64 -> 1.005 | M64: =L64 -> 1.005 | N64: =M64 -> 1.005 | O64: =N64 -> 1.005 | P64: =O64 -> 1.005 | Q64: =P64 -> 1.005 | R64: =IF(TechData_R0!H84="",1,TechData_R0!H84) -> 1 | T64: 5
A65: UC_GrowthOfOILUP59 | B65: =TechData_R0!C87 -> IMPOILHH34 | E65: CAP, GROWTH | G65: UP | H65: =TechData_R0!J87 -> 1.005 | I65: =H65 -> 1.005 | J65: =I65 -> 1.005 | K65: =J65 -> 1.005 | L65: =K65 -> 1.005 | M65: =L65 -> 1.005 | N65: =M65 -> 1.005 | O65: =N65 -> 1.005 | P65: =O65 -> 1.005 | Q65: =P65 -> 1.005 | R65: =IF(TechData_R0!H85="",1,TechData_R0!H85) -> 1 | T65: 5
A66: UC_GrowthOfOILUP60 | B66: =TechData_R0!C88 -> IMPOILHH35 | E66: CAP, GROWTH | G66: UP | H66: =TechData_R0!J88 -> 1.005 | I66: =H66 -> 1.005 | J66: =I66 -> 1.005 | K66: =J66 -> 1.005 | L66: =K66 -> 1.005 | M66: =L66 -> 1.005 | N66: =M66 -> 1.005 | O66: =N66 -> 1.005 | P66: =O66 -> 1.005 | Q66: =P66 -> 1.005 | R66: =IF(TechData_R0!H86="",1,TechData_R0!H86) -> 1 | T66: 5
A67: UC_GrowthOfOILUP61 | B67: =TechData_R0!C89 -> IMPOILHL33 | E67: CAP, GROWTH | G67: UP | H67: =TechData_R0!J89 -> 1.005 | I67: =H67 -> 1.005 | J67: =I67 -> 1.005 | K67: =J67 -> 1.005 | L67: =K67 -> 1.005 | M67: =L67 -> 1.005 | N67: =M67 -> 1.005 | O67: =N67 -> 1.005 | P67: =O67 -> 1.005 | Q67: =P67 -> 1.005 | R67: =IF(TechData_R0!H87="",1,TechData_R0!H87) -> 1 | T67: 5
A68: UC_GrowthOfOILUP62 | B68: =TechData_R0!C90 -> IMPOILHL31 | E68: CAP, GROWTH | G68: UP | H68: =TechData_R0!J90 -> 1.005 | I68: =H68 -> 1.005 | J68: =I68 -> 1.005 | K68: =J68 -> 1.005 | L68: =K68 -> 1.005 | M68: =L68 -> 1.005 | N68: =M68 -> 1.005 | O68: =N68 -> 1.005 | P68: =O68 -> 1.005 | Q68: =P68 -> 1.005 | R68: =IF(TechData_R0!H88="",1,TechData_R0!H88) -> 1 | T68: 5
A69: UC_GrowthOfOILUP63 | B69: =TechData_R0!C91 -> IMPOILHL32 | E69: CAP, GROWTH | G69: UP | H69: =TechData_R0!J91 -> 1.005 | I69: =H69 -> 1.005 | J69: =I69 -> 1.005 | K69: =J69 -> 1.005 | L69: =K69 -> 1.005 | M69: =L69 -> 1.005 | N69: =M69 -> 1.005 | O69: =N69 -> 1.005 | P69: =O69 -> 1.005 | Q69: =P69 -> 1.005 | R69: =IF(TechData_R0!H89="",1,TechData_R0!H89) -> 1 | T69: 5
A70: UC_GrowthOfOILUP64 | B70: =TechData_R0!C92 -> IMPOILHL34 | E70: CAP, GROWTH | G70: UP | H70: =TechData_R0!J92 -> 1.005 | I70: =H70 -> 1.005 | J70: =I70 -> 1.005 | K70: =J70 -> 1.005 | L70: =K70 -> 1.005 | M70: =L70 -> 1.005 | N70: =M70 -> 1.005 | O70: =N70 -> 1.005 | P70: =O70 -> 1.005 | Q70: =P70 -> 1.005 | R70: =IF(TechData_R0!H90="",1,TechData_R0!H90) -> 1 | T70: 5
A71: UC_GrowthOfOILUP65 | B71: =TechData_R0!C93 -> IMPOILHL35 | E71: CAP, GROWTH | G71: UP | H71: =TechData_R0!J93 -> 1.005 | I71: =H71 -> 1.005 | J71: =I71 -> 1.005 | K71: =J71 -> 1.005 | L71: =K71 -> 1.005 | M71: =L71 -> 1.005 | N71: =M71 -> 1.005 | O71: =N71 -> 1.005 | P71: =O71 -> 1.005 | Q71: =P71 -> 1.005 | R71: =IF(TechData_R0!H91="",1,TechData_R0!H91) -> 1 | T71: 5
A72: UC_GrowthOfOILUP66 | B72: =TechData_R0!C94 -> IMPOILHV33 | E72: CAP, GROWTH | G72: UP | H72: =TechData_R0!J94 -> 1.005 | I72: =H72 -> 1.005 | J72: =I72 -> 1.005 | K72: =J72 -> 1.005 | L72: =K72 -> 1.005 | M72: =L72 -> 1.005 | N72: =M72 -> 1.005 | O72: =N72 -> 1.005 | P72: =O72 -> 1.005 | Q72: =P72 -> 1.005 | R72: =IF(TechData_R0!H92="",1,TechData_R0!H92) -> 1 | T72: 5
A73: UC_GrowthOfOILUP67 | B73: =TechData_R0!C95 -> IMPOILHV31 | E73: CAP, GROWTH | G73: UP | H73: =TechData_R0!J95 -> 1.005 | I73: =H73 -> 1.005 | J73: =I73 -> 1.005 | K73: =J73 -> 1.005 | L73: =K73 -> 1.005 | M73: =L73 -> 1.005 | N73: =M73 -> 1.005 | O73: =N73 -> 1.005 | P73: =O73 -> 1.005 | Q73: =P73 -> 1.005 | R73: =IF(TechData_R0!H93="",1,TechData_R0!H93) -> 1 | T73: 5
... A86: UC_GrowthOfOILUP80 | B86: =TechData_R0!C108 -> IMPOILMH35 | E86: CAP, GROWTH | G86: UP | H86: =TechData_R0!J108 -> 1.005 | I86: =H86 -> 1.005 | J86: =I86 -> 1.005 | K86: =J86 -> 1.005 | L86: =K86 -> 1.005 | M86: =L86 -> 1.005 | N86: =M86 -> 1.005 | O86: =N86 -> 1.005 | P86: =O86 -> 1.005 | Q86: =P86 -> 1.005 | R86: =IF(TechData_R0!H106="",1,TechData_R0!H106) -> 1 | T86: 5
A87: UC_GrowthOfOILUP81 | B87: =TechData_R0!C198 -> IMPJTFP13 | E87: CAP, GROWTH | G87: UP | H87: =TechData_R0!I198 -> 1.005 | I87: =H87 -> 1.005 | J87: =I87 -> 1.005 | K87: =J87 -> 1.005 | L87: =K87 -> 1.005 | M87: =L87 -> 1.005 | N87: =M87 -> 1.005 | O87: =N87 -> 1.005 | P87: =O87 -> 1.005 | Q87: =P87 -> 1.005 | R87: =IF(TechData_R0!G198="",1,TechData_R0!G198) -> 1 | T87: 5
A88: UC_GrowthOfOILUP82 | B88: =TechData_R0!C199 -> IMPJTFP11 | E88: CAP, GROWTH | G88: UP | H88: =TechData_R0!I199 -> 1.005 | I88: =H88 -> 1.005 | J88: =I88 -> 1.005 | K88: =J88 -> 1.005 | L88: =K88 -> 1.005 | M88: =L88 -> 1.005 | N88: =M88 -> 1.005 | O88: =N88 -> 1.005 | P88: =O88 -> 1.005 | Q88: =P88 -> 1.005 | R88: =IF(TechData_R0!G199="",1,TechData_R0!G199) -> 1 | T88: 5
A89: UC_GrowthOfOILUP83 | B89: =TechData_R0!C200 -> IMPJTFP12 | E89: CAP, GROWTH | G89: UP | H89: =TechData_R0!I200 -> 1.005 | I89: =H89 -> 1.005 | J89: =I89 -> 1.005 | K89: =J89 -> 1.005 | L89: =K89 -> 1.005 | M89: =L89 -> 1.005 | N89: =M89 -> 1.005 | O89: =N89 -> 1.005 | P89: =O89 -> 1.005 | Q89: =P89 -> 1.005 | R89: =IF(TechData_R0!G200="",1,TechData_R0!G200) -> 1 | T89: 5
A90: UC_GrowthOfOILUP84 | B90: =TechData_R0!C201 -> IMPJTFP14 | E90: CAP, GROWTH | G90: UP | H90: =TechData_R0!I201 -> 1.005 | I90: =H90 -> 1.005 | J90: =I90 -> 1.005 | K90: =J90 -> 1.005 | L90: =K90 -> 1.005 | M90: =L90 -> 1.005 | N90: =M90 -> 1.005 | O90: =N90 -> 1.005 | P90: =O90 -> 1.005 | Q90: =P90 -> 1.005 | R90: =IF(TechData_R0!G201="",1,TechData_R0!G201) -> 1 | T90: 5
A91: UC_GrowthOfOILUP85 | B91: =TechData_R0!C202 -> IMPJTFP15 | E91: CAP, GROWTH | G91: UP | H91: =TechData_R0!I202 -> 1.005 | I91: =H91 -> 1.005 | J91: =I91 -> 1.005 | K91: =J91 -> 1.005 | L91: =K91 -> 1.005 | M91: =L91 -> 1.005 | N91: =M91 -> 1.005 | O91: =N91 -> 1.005 | P91: =O91 -> 1.005 | Q91: =P91 -> 1.005 | R91: =IF(TechData_R0!G202="",1,TechData_R0!G202) -> 1 | T91: 5
A92: UC_GrowthOfOILUP86 | B92: =TechData_R0!C203 -> IMPDSHP13 | E92: CAP, GROWTH | G92: UP | H92: =TechData_R0!I203 -> 1.005 | I92: =H92 -> 1.005 | J92: =I92 -> 1.005 | K92: =J92 -> 1.005 | L92: =K92 -> 1.005 | M92: =L92 -> 1.005 | N92: =M92 -> 1.005 | O92: =N92 -> 1.005 | P92: =O92 -> 1.005 | Q92: =P92 -> 1.005 | R92: =IF(TechData_R0!G203="",1,TechData_R0!G203) -> 1 | T92: 5
A93: UC_GrowthOfOILUP87 | B93: =TechData_R0!C204 -> IMPDSHP11 | E93: CAP, GROWTH | G93: UP | H93: =TechData_R0!I204 -> 1.005 | I93: =H93 -> 1.005 | J93: =I93 -> 1.005 | K93: =J93 -> 1.005 | L93: =K93 -> 1.005 | M93: =L93 -> 1.005 | N93: =M93 -> 1.005 | O93: =N93 -> 1.005 | P93: =O93 -> 1.005 | Q93: =P93 -> 1.005 | R93: =IF(TechData_R0!G204="",1,TechData_R0!G204) -> 1 | T93: 5
A94: UC_GrowthOfOILUP88 | B94: =TechData_R0!C205 -> IMPDSHP12 | E94: CAP, GROWTH | G94: UP | H94: =TechData_R0!I205 -> 1.005 | I94: =H94 -> 1.005 | J94: =I94 -> 1.005 | K94: =J94 -> 1.005 | L94: =K94 -> 1.005 | M94: =L94 -> 1.005 | N94: =M94 -> 1.005 | O94: =N94 -> 1.005 | P94: =O94 -> 1.005 | Q94: =P94 -> 1.005 | R94: =IF(TechData_R0!G205="",1,TechData_R0!G205) -> 1 | T94: 5
A95: UC_GrowthOfOILUP89 | B95: =TechData_R0!C206 -> IMPDSHP14 | E95: CAP, GROWTH | G95: UP | H95: =TechData_R0!I206 -> 1.005 | I95: =H95 -> 1.005 | J95: =I95 -> 1.005 | K95: =J95 -> 1.005 | L95: =K95 -> 1.005 | M95: =L95 -> 1.005 | N95: =M95 -> 1.005 | O95: =N95 -> 1.005 | P95: =O95 -> 1.005 | Q95: =P95 -> 1.005 | R95: =IF(TechData_R0!G206="",1,TechData_R0!G206) -> 1 | T95: 5
A96: UC_GrowthOfOILUP90 | B96: =TechData_R0!C207 -> IMPDSHP15 | E96: CAP, GROWTH | G96: UP | H96: =TechData_R0!I207 -> 1.005 | I96: =H96 -> 1.005 | J96: =I96 -> 1.005 | K96: =J96 -> 1.005 | L96: =K96 -> 1.005 | M96: =L96 -> 1.005 | N96: =M96 -> 1.005 | O96: =N96 -> 1.005 | P96: =O96 -> 1.005 | Q96: =P96 -> 1.005 | R96: =IF(TechData_R0!G207="",1,TechData_R0!G207) -> 1 | T96: 5
A97: UC_GrowthOfOILUP91 | B97: =TechData_R0!C208 -> IMPJTFP23 | E97: CAP, GROWTH | G97: UP | H97: =TechData_R0!I208 -> 1.005 | I97: =H97 -> 1.005 | J97: =I97 -> 1.005 | K97: =J97 -> 1.005 | L97: =K97 -> 1.005 | M97: =L97 -> 1.005 | N97: =M97 -> 1.005 | O97: =N97 -> 1.005 | P97: =O97 -> 1.005 | Q97: =P97 -> 1.005 | R97: =IF(TechData_R0!G208="",1,TechData_R0!G208) -> 1 | T97: 5
A98: UC_GrowthOfOILUP92 | B98: =TechData_R0!C209 -> IMPJTFP21 | E98: CAP, GROWTH | G98: UP | H98: =TechData_R0!I209 -> 1.005 | I98: =H98 -> 1.005 | J98: =I98 -> 1.005 | K98: =J98 -> 1.005 | L98: =K98 -> 1.005 | M98: =L98 -> 1.005 | N98: =M98 -> 1.005 | O98: =N98 -> 1.005 | P98: =O98 -> 1.005 | Q98: =P98 -> 1.005 | R98: =IF(TechData_R0!G209="",1,TechData_R0!G209) -> 1 | T98: 5
... A116: UC_GrowthOfOILUP110 | B116: =TechData_R0!C227 -> IMPDSHP35 | E116: CAP, GROWTH | G116: UP | H116: =TechData_R0!I227 -> 1.005 | I116: =H116 -> 1.005 | J116: =I116 -> 1.005 | K116: =J116 -> 1.005 | L116: =K116 -> 1.005 | M116: =L116 -> 1.005 | N116: =M116 -> 1.005 | O116: =N116 -> 1.005 | P116: =O116 -> 1.005 | Q116: =P116 -> 1.005 | R116: =IF(TechData_R0!G227="",1,TechData_R0!G227) -> 1 | T116: 5
A126: Maximum capacity technology decrease:
A127: ~UC_Sets: R_E: R1
A128: ~UC_Sets: T_SUC:
G129: ~UC_T
A130: UC_N | B130: Pset_PN | C130: Pset_CI | D130: Pset_CO | E130: UC_ATTR | F130: Year | G130: LimType | H130: UC_CAP~2010 | I130: UC_CAP~2015 | J130: UC_CAP~2020 | K130: UC_CAP~2025 | L130: UC_CAP~2030 | M130: UC_CAP~2035 | N130: UC_CAP~2040 | O130: UC_CAP~2045 | P130: UC_CAP~2050 | Q130: UC_CAP~2055 | R130: UC_CAP~RHS | S130: UC_RHSRTS | T130: UC_RHSRTS~0 | U130: UC_Desc
A131: UC_DeayOfOILUP1 | B131: =TechData_R0!C9 -> MINOILD1 | E131: CAP, GROWTH | G131: LO | H131: =1-TechData_R0!K9+1 -> 0.99 | I131: =H131 -> 0.99 | J131: =I131 -> 0.99 | K131: =J131 -> 0.99 | L131: =K131 -> 0.99 | M131: =L131 -> 0.99 | N131: =M131 -> 0.99 | O131: =N131 -> 0.99 | P131: =O131 -> 0.99 | Q131: =P131 -> 0.99 | R131: 1 | T131: 5
A132: UC_DeayOfOILUP2 | B132: =TechData_R0!C10 -> MINOILD2 | E132: CAP, GROWTH | G132: LO | H132: =1-TechData_R0!K10+1 -> 0.99 | I132: =H132 -> 0.99 | J132: =I132 -> 0.99 | K132: =J132 -> 0.99 | L132: =K132 -> 0.99 | M132: =L132 -> 0.99 | N132: =M132 -> 0.99 | O132: =N132 -> 0.99 | P132: =O132 -> 0.99 | Q132: =P132 -> 0.99 | R132: 1 | T132: 5
A133: UC_DeayOfOILUP3 | B133: =TechData_R0!C11 -> MINOILD3 | E133: CAP, GROWTH | G133: LO | H133: =1-TechData_R0!K11+1 -> 0.99 | I133: =H133 -> 0.99 | J133: =I133 -> 0.99 | K133: =J133 -> 0.99 | L133: =K133 -> 0.99 | M133: =L133 -> 0.99 | N133: =M133 -> 0.99 | O133: =N133 -> 0.99 | P133: =O133 -> 0.99 | Q133: =P133 -> 0.99 | R133: 1 | T133: 5
A134: UC_DeayOfOILUP4 | B134: =TechData_R0!C12 -> MINOILD4 | E134: CAP, GROWTH | G134: LO | H134: =1-TechData_R0!K12+1 -> 0.99 | I134: =H134 -> 0.99 | J134: =I134 -> 0.99 | K134: =J134 -> 0.99 | L134: =K134 -> 0.99 | M134: =L134 -> 0.99 | N134: =M134 -> 0.99 | O134: =N134 -> 0.99 | P134: =O134 -> 0.99 | Q134: =P134 -> 0.99 | R134: 1 | T134: 5
A135: UC_DeayOfOILUP5 | B135: =TechData_R0!C13 -> MINOILD5 | E135: CAP, GROWTH | G135: LO | H135: =1-TechData_R0!K13+1 -> 0.99 | I135: =H135 -> 0.99 | J135: =I135 -> 0.99 | K135: =J135 -> 0.99 | L135: =K135 -> 0.99 | M135: =L135 -> 0.99 | N135: =M135 -> 0.99 | O135: =N135 -> 0.99 | P135: =O135 -> 0.99 | Q135: =P135 -> 0.99 | R135: 1 | T135: 5
A136: UC_DeayOfOILUP6 | B136: =TechData_R0!C32 -> IMPOILHH13 | E136: CAP, GROWTH | G136: LO | H136: =1-TechData_R0!K32+1 -> 0.995 | I136: =H136 -> 0.995 | J136: =I136 -> 0.995 | K136: =J136 -> 0.995 | L136: =K136 -> 0.995 | M136: =L136 -> 0.995 | N136: =M136 -> 0.995 | O136: =N136 -> 0.995 | P136: =O136 -> 0.995 | Q136: =P136 -> 0.995 | R136: 1 | T136: 5
A137: UC_DeayOfOILUP7 | B137: =TechData_R0!C33 -> IMPOILHH11 | E137: CAP, GROWTH | G137: LO | H137: =1-TechData_R0!K33+1 -> 0.995 | I137: =H137 -> 0.995 | J137: =I137 -> 0.995 | K137: =J137 -> 0.995 | L137: =K137 -> 0.995 | M137: =L137 -> 0.995 | N137: =M137 -> 0.995 | O137: =N137 -> 0.995 | P137: =O137 -> 0.995 | Q137: =P137 -> 0.995 | R137: 1 | T137: 5
A138: UC_DeayOfOILUP8 | B138: =TechData_R0!C34 -> IMPOILHH12 | E138: CAP, GROWTH | G138: LO | H138: =1-TechData_R0!K34+1 -> 0.995 | I138: =H138 -> 0.995 | J138: =I138 -> 0.995 | K138: =J138 -> 0.995 | L138: =K138 -> 0.995 | M138: =L138 -> 0.995 | N138: =M138 -> 0.995 | O138: =N138 -> 0.995 | P138: =O138 -> 0.995 | Q138: =P138 -> 0.995 | R138: 1 | T138: 5
A139: UC_DeayOfOILUP9 | B139: =TechData_R0!C35 -> IMPOILHH14 | E139: CAP, GROWTH | G139: LO | H139: =1-TechData_R0!K35+1 -> 0.995 | I139: =H139 -> 0.995 | J139: =I139 -> 0.995 | K139: =J139 -> 0.995 | L139: =K139 -> 0.995 | M139: =L139 -> 0.995 | N139: =M139 -> 0.995 | O139: =N139 -> 0.995 | P139: =O139 -> 0.995 | Q139: =P139 -> 0.995 | R139: 1 | T139: 5
A140: UC_DeayOfOILUP10 | B140: =TechData_R0!C36 -> IMPOILHH15 | E140: CAP, GROWTH | G140: LO | H140: =1-TechData_R0!K36+1 -> 0.995 | I140: =H140 -> 0.995 | J140: =I140 -> 0.995 | K140: =J140 -> 0.995 | L140: =K140 -> 0.995 | M140: =L140 -> 0.995 | N140: =M140 -> 0.995 | O140: =N140 -> 0.995 | P140: =O140 -> 0.995 | Q140: =P140 -> 0.995 | R140: 1 | T140: 5
A141: UC_DeayOfOILUP11 | B141: =TechData_R0!C37 -> IMPOILHL13 | E141: CAP, GROWTH | G141: LO | H141: =1-TechData_R0!K37+1 -> 0.995 | I141: =H141 -> 0.995 | J141: =I141 -> 0.995 | K141: =J141 -> 0.995 | L141: =K141 -> 0.995 | M141: =L141 -> 0.995 | N141: =M141 -> 0.995 | O141: =N141 -> 0.995 | P141: =O141 -> 0.995 | Q141: =P141 -> 0.995 | R141: 1 | T141: 5
A142: UC_DeayOfOILUP12 | B142: =TechData_R0!C38 -> IMPOILHL11 | E142: CAP, GROWTH | G142: LO | H142: =1-TechData_R0!K38+1 -> 0.995 | I142: =H142 -> 0.995 | J142: =I142 -> 0.995 | K142: =J142 -> 0.995 | L142: =K142 -> 0.995 | M142: =L142 -> 0.995 | N142: =M142 -> 0.995 | O142: =N142 -> 0.995 | P142: =O142 -> 0.995 | Q142: =P142 -> 0.995 | R142: 1 | T142: 5
A143: UC_DeayOfOILUP13 | B143: =TechData_R0!C39 -> IMPOILHL12 | E143: CAP, GROWTH | G143: LO | H143: =1-TechData_R0!K39+1 -> 0.995 | I143: =H143 -> 0.995 | J143: =I143 -> 0.995 | K143: =J143 -> 0.995 | L143: =K143 -> 0.995 | M143: =L143 -> 0.995 | N143: =M143 -> 0.995 | O143: =N143 -> 0.995 | P143: =O143 -> 0.995 | Q143: =P143 -> 0.995 | R143: 1 | T143: 5
A144: UC_DeayOfOILUP14 | B144: =TechData_R0!C40 -> IMPOILHL14 | E144: CAP, GROWTH | G144: LO | H144: =1-TechData_R0!K40+1 -> 0.995 | I144: =H144 -> 0.995 | J144: =I144 -> 0.995 | K144: =J144 -> 0.995 | L144: =K144 -> 0.995 | M144: =L144 -> 0.995 | N144: =M144 -> 0.995 | O144: =N144 -> 0.995 | P144: =O144 -> 0.995 | Q144: =P144 -> 0.995 | R144: 1 | T144: 5
A145: UC_DeayOfOILUP15 | B145: =TechData_R0!C41 -> IMPOILHL15 | E145: CAP, GROWTH | G145: LO | H145: =1-TechData_R0!K41+1 -> 0.995 | I145: =H145 -> 0.995 | J145: =I145 -> 0.995 | K145: =J145 -> 0.995 | L145: =K145 -> 0.995 | M145: =L145 -> 0.995 | N145: =M145 -> 0.995 | O145: =N145 -> 0.995 | P145: =O145 -> 0.995 | Q145: =P145 -> 0.995 | R145: 1 | T145: 5
A146: UC_DeayOfOILUP16 | B146: =TechData_R0!C42 -> IMPOILHV13 | E146: CAP, GROWTH | G146: LO | H146: =1-TechData_R0!K42+1 -> 0.995 | I146: =H146 -> 0.995 | J146: =I146 -> 0.995 | K146: =J146 -> 0.995 | L146: =K146 -> 0.995 | M146: =L146 -> 0.995 | N146: =M146 -> 0.995 | O146: =N146 -> 0.995 | P146: =O146 -> 0.995 | Q146: =P146 -> 0.995 | R146: 1 | T146: 5
A147: UC_DeayOfOILUP17 | B147: =TechData_R0!C43 -> IMPOILHV11 | E147: CAP, GROWTH | G147: LO | H147: =1-TechData_R0!K43+1 -> 0.995 | I147: =H147 -> 0.995 | J147: =I147 -> 0.995 | K147: =J147 -> 0.995 | L147: =K147 -> 0.995 | M147: =L147 -> 0.995 | N147: =M147 -> 0.995 | O147: =N147 -> 0.995 | P147: =O147 -> 0.995 | Q147: =P147 -> 0.995 | R147: 1 | T147: 5
... A160: UC_DeayOfOILUP30 | B160: =TechData_R0!C56 -> IMPOILMH15 | E160: CAP, GROWTH | G160: LO | H160: =1-TechData_R0!K56+1 -> 0.995 | I160: =H160 -> 0.995 | J160: =I160 -> 0.995 | K160: =J160 -> 0.995 | L160: =K160 -> 0.995 | M160: =L160 -> 0.995 | N160: =M160 -> 0.995 | O160: =N160 -> 0.995 | P160: =O160 -> 0.995 | Q160: =P160 -> 0.995 | R160: 1 | T160: 5
A161: UC_DeayOfOILUP31 | B161: =TechData_R0!C58 -> IMPOILHH23 | E161: CAP, GROWTH | G161: LO | H161: =1-TechData_R0!K58+1 -> 0.995 | I161: =H161 -> 0.995 | J161: =I161 -> 0.995 | K161: =J161 -> 0.995 | L161: =K161 -> 0.995 | M161: =L161 -> 0.995 | N161: =M161 -> 0.995 | O161: =N161 -> 0.995 | P161: =O161 -> 0.995 | Q161: =P161 -> 0.995 | R161: 1 | T161: 5
A162: UC_DeayOfOILUP32 | B162: =TechData_R0!C59 -> IMPOILHH21 | E162: CAP, GROWTH | G162: LO | H162: =1-TechData_R0!K59+1 -> 0.995 | I162: =H162 -> 0.995 | J162: =I162 -> 0.995 | K162: =J162 -> 0.995 | L162: =K162 -> 0.995 | M162: =L162 -> 0.995 | N162: =M162 -> 0.995 | O162: =N162 -> 0.995 | P162: =O162 -> 0.995 | Q162: =P162 -> 0.995 | R162: 1 | T162: 5
A163: UC_DeayOfOILUP33 | B163: =TechData_R0!C60 -> IMPOILHH22 | E163: CAP, GROWTH | G163: LO | H163: =1-TechData_R0!K60+1 -> 0.995 | I163: =H163 -> 0.995 | J163: =I163 -> 0.995 | K163: =J163 -> 0.995 | L163: =K163 -> 0.995 | M163: =L163 -> 0.995 | N163: =M163 -> 0.995 | O163: =N163 -> 0.995 | P163: =O163 -> 0.995 | Q163: =P163 -> 0.995 | R163: 1 | T163: 5
A164: UC_DeayOfOILUP34 | B164: =TechData_R0!C61 -> IMPOILHH24 | E164: CAP, GROWTH | G164: LO | H164: =1-TechData_R0!K61+1 -> 0.995 | I164: =H164 -> 0.995 | J164: =I164 -> 0.995 | K164: =J164 -> 0.995 | L164: =K164 -> 0.995 | M164: =L164 -> 0.995 | N164: =M164 -> 0.995 | O164: =N164 -> 0.995 | P164: =O164 -> 0.995 | Q164: =P164 -> 0.995 | R164: 1 | T164: 5
A165: UC_DeayOfOILUP35 | B165: =TechData_R0!C62 -> IMPOILHH25 | E165: CAP, GROWTH | G165: LO | H165: =1-TechData_R0!K62+1 -> 0.995 | I165: =H165 -> 0.995 | J165: =I165 -> 0.995 | K165: =J165 -> 0.995 | L165: =K165 -> 0.995 | M165: =L165 -> 0.995 | N165: =M165 -> 0.995 | O165: =N165 -> 0.995 | P165: =O165 -> 0.995 | Q165: =P165 -> 0.995 | R165: 1 | T165: 5
A166: UC_DeayOfOILUP36 | B166: =TechData_R0!C63 -> IMPOILHL23 | E166: CAP, GROWTH | G166: LO | H166: =1-TechData_R0!K63+1 -> 0.995 | I166: =H166 -> 0.995 | J166: =I166 -> 0.995 | K166: =J166 -> 0.995 | L166: =K166 -> 0.995 | M166: =L166 -> 0.995 | N166: =M166 -> 0.995 | O166: =N166 -> 0.995 | P166: =O166 -> 0.995 | Q166: =P166 -> 0.995 | R166: 1 | T166: 5
A167: UC_DeayOfOILUP37 | B167: =TechData_R0!C64 -> IMPOILHL21 | E167: CAP, GROWTH | G167: LO | H167: =1-TechData_R0!K64+1 -> 0.995 | I167: =H167 -> 0.995 | J167: =I167 -> 0.995 | K167: =J167 -> 0.995 | L167: =K167 -> 0.995 | M167: =L167 -> 0.995 | N167: =M167 -> 0.995 | O167: =N167 -> 0.995 | P167: =O167 -> 0.995 | Q167: =P167 -> 0.995 | R167: 1 | T167: 5
A168: UC_DeayOfOILUP38 | B168: =TechData_R0!C65 -> IMPOILHL22 | E168: CAP, GROWTH | G168: LO | H168: =1-TechData_R0!K65+1 -> 0.995 | I168: =H168 -> 0.995 | J168: =I168 -> 0.995 | K168: =J168 -> 0.995 | L168: =K168 -> 0.995 | M168: =L168 -> 0.995 | N168: =M168 -> 0.995 | O168: =N168 -> 0.995 | P168: =O168 -> 0.995 | Q168: =P168 -> 0.995 | R168: 1 | T168: 5
A169: UC_DeayOfOILUP39 | B169: =TechData_R0!C66 -> IMPOILHL24 | E169: CAP, GROWTH | G169: LO | H169: =1-TechData_R0!K66+1 -> 0.995 | I169: =H169 -> 0.995 | J169: =I169 -> 0.995 | K169: =J169 -> 0.995 | L169: =K169 -> 0.995 | M169: =L169 -> 0.995 | N169: =M169 -> 0.995 | O169: =N169 -> 0.995 | P169: =O169 -> 0.995 | Q169: =P169 -> 0.995 | R169: 1 | T169: 5
A170: UC_DeayOfOILUP40 | B170: =TechData_R0!C67 -> IMPOILHL25 | E170: CAP, GROWTH | G170: LO | H170: =1-TechData_R0!K67+1 -> 0.995 | I170: =H170 -> 0.995 | J170: =I170 -> 0.995 | K170: =J170 -> 0.995 | L170: =K170 -> 0.995 | M170: =L170 -> 0.995 | N170: =M170 -> 0.995 | O170: =N170 -> 0.995 | P170: =O170 -> 0.995 | Q170: =P170 -> 0.995 | R170: 1 | T170: 5
A171: UC_DeayOfOILUP41 | B171: =TechData_R0!C68 -> IMPOILHV23 | E171: CAP, GROWTH | G171: LO | H171: =1-TechData_R0!K68+1 -> 0.995 | I171: =H171 -> 0.995 | J171: =I171 -> 0.995 | K171: =J171 -> 0.995 | L171: =K171 -> 0.995 | M171: =L171 -> 0.995 | N171: =M171 -> 0.995 | O171: =N171 -> 0.995 | P171: =O171 -> 0.995 | Q171: =P171 -> 0.995 | R171: 1 | T171: 5
A172: UC_DeayOfOILUP42 | B172: =TechData_R0!C69 -> IMPOILHV21 | E172: CAP, GROWTH | G172: LO | H172: =1-TechData_R0!K69+1 -> 0.995 | I172: =H172 -> 0.995 | J172: =I172 -> 0.995 | K172: =J172 -> 0.995 | L172: =K172 -> 0.995 | M172: =L172 -> 0.995 | N172: =M172 -> 0.995 | O172: =N172 -> 0.995 | P172: =O172 -> 0.995 | Q172: =P172 -> 0.995 | R172: 1 | T172: 5
... A185: UC_DeayOfOILUP55 | B185: =TechData_R0!C82 -> IMPOILMH25 | E185: CAP, GROWTH | G185: LO | H185: =1-TechData_R0!K82+1 -> 0.995 | I185: =H185 -> 0.995 | J185: =I185 -> 0.995 | K185: =J185 -> 0.995 | L185: =K185 -> 0.995 | M185: =L185 -> 0.995 | N185: =M185 -> 0.995 | O185: =N185 -> 0.995 | P185: =O185 -> 0.995 | Q185: =P185 -> 0.995 | R185: 1 | T185: 5
A186: UC_DeayOfOILUP56 | B186: =TechData_R0!C84 -> IMPOILHH33 | E186: CAP, GROWTH | G186: LO | H186: =1-TechData_R0!K84+1 -> 0.995 | I186: =H186 -> 0.995 | J186: =I186 -> 0.995 | K186: =J186 -> 0.995 | L186: =K186 -> 0.995 | M186: =L186 -> 0.995 | N186: =M186 -> 0.995 | O186: =N186 -> 0.995 | P186: =O186 -> 0.995 | Q186: =P186 -> 0.995 | R186: 1 | T186: 5
A187: UC_DeayOfOILUP57 | B187: =TechData_R0!C85 -> IMPOILHH31 | E187: CAP, GROWTH | G187: LO | H187: =1-TechData_R0!K85+1 -> 0.995 | I187: =H187 -> 0.995 | J187: =I187 -> 0.995 | K187: =J187 -> 0.995 | L187: =K187 -> 0.995 | M187: =L187 -> 0.995 | N187: =M187 -> 0.995 | O187: =N187 -> 0.995 | P187: =O187 -> 0.995 | Q187: =P187 -> 0.995 | R187: 1 | T187: 5
...

Sheet UC_OIL3
A2: Maximum import PADD
A3: ~UC_Sets: R_S: AllRegions
F4: ~UC_T:UC_RHST
A5: UC_N | B5: Pset_PN | C5: Pset_CI | D5: Cset_CN | E5: UC_ACT | F5: UC_RHST~UP~0 | G5: UC_RHST~UP~2010 | H5: UC_RHST~UP~2015 | I5: UC_RHST~UP~2020 | J5: UC_RHST~UP~2025 | K5: UC_RHST~UP~2030 | L5: UC_RHST~UP~2035 | M5: UC_RHST~UP~2040 | N5: UC_RHST~UP~2045 | O5: UC_RHST~UP~2050 | P5: UC_RHST~UP~2055 | Q5: UC_Desc
A6: UC_IMPPADDUP1 | B6: IMPJTFP13 | E6: 1 | F6: 1 | G6: =IF(TechData_R0!W198="","",TechData_R0!W198) -> 218348.9 | H6: =IF(TechData_R0!X198="","",TechData_R0!X198) -> 218348.9 | I6: =IF(TechData_R0!Y198="","",TechData_R0!Y198) -> 218348.9 | J6: =IF(TechData_R0!Z198="","",TechData_R0!Z198) | K6: =IF(TechData_R0!AA198="","",TechData_R0!AA198) | L6: =IF(TechData_R0!AB198="","",TechData_R0!AB198) | M6: =IF(TechData_R0!AC198="","",TechData_R0!AC198) | N6: =IF(TechData_R0!AD198="","",TechData_R0!AD198) | ... P6: =IF(TechData_R0!AF198="","",TechData_R0!AF198)
A7: UC_IMPPADDUP2 | B7: IMPJTFP11 | E7: 1 | F7: 1 | G7: =IF(TechData_R0!W199="","",TechData_R0!W199) -> 1746791.2 | H7: =IF(TechData_R0!X199="","",TechData_R0!X199) -> 1746791.2 | I7: =IF(TechData_R0!Y199="","",TechData_R0!Y199) -> 1746791.2 | J7: =IF(TechData_R0!Z199="","",TechData_R0!Z199) | K7: =IF(TechData_R0!AA199="","",TechData_R0!AA199) | L7: =IF(TechData_R0!AB199="","",TechData_R0!AB199) | M7: =IF(TechData_R0!AC199="","",TechData_R0!AC199) | N7: =IF(TechData_R0!AD199="","",TechData_R0!AD199) | ... P7: =IF(TechData_R0!AF199="","",TechData_R0!AF199)
A8: UC_IMPPADDUP3 | B8: IMPJTFP12 | E8: 1 | F8: 1 | G8: =IF(TechData_R0!W200="","",TechData_R0!W200) -> 218348.9 | H8: =IF(TechData_R0!X200="","",TechData_R0!X200) -> 218348.9 | I8: =IF(TechData_R0!Y200="","",TechData_R0!Y200) -> 218348.9 | J8: =IF(TechData_R0!Z200="","",TechData_R0!Z200) | K8: =IF(TechData_R0!AA200="","",TechData_R0!AA200) | L8: =IF(TechData_R0!AB200="","",TechData_R0!AB200) | M8: =IF(TechData_R0!AC200="","",TechData_R0!AC200) | N8: =IF(TechData_R0!AD200="","",TechData_R0!AD200) | ... P8: =IF(TechData_R0!AF200="","",TechData_R0!AF200)
A9: UC_IMPPADDUP4 | B9: IMPJTFP14 | E9: 1 | F9: 1 | G9: =IF(TechData_R0!W201="","",TechData_R0!W201) -> 436697.79 | H9: =IF(TechData_R0!X201="","",TechData_R0!X201) -> 436697.79 | I9: =IF(TechData_R0!Y201="","",TechData_R0!Y201) -> 436697.79 | J9: =IF(TechData_R0!Z201="","",TechData_R0!Z201) | K9: =IF(TechData_R0!AA201="","",TechData_R0!AA201) | L9: =IF(TechData_R0!AB201="","",TechData_R0!AB201) | M9: =IF(TechData_R0!AC201="","",TechData_R0!AC201) | N9: =IF(TechData_R0!AD201="","",TechData_R0!AD201) | ... P9: =IF(TechData_R0!AF201="","",TechData_R0!AF201)
A10: UC_IMPPADDUP5 | B10: IMPJTFP15 | E10: 1 | F10: 1 | G10: =IF(TechData_R0!W202="","",TechData_R0!W202) -> 1746791.2 | H10: =IF(TechData_R0!X202="","",TechData_R0!X202) -> 1746791.2 | I10: =IF(TechData_R0!Y202="","",TechData_R0!Y202) -> 1746791.2 | J10: =IF(TechData_R0!Z202="","",TechData_R0!Z202) | K10: =IF(TechData_R0!AA202="","",TechData_R0!AA202) | L10: =IF(TechData_R0!AB202="","",TechData_R0!AB202) | M10: =IF(TechData_R0!AC202="","",TechData_R0!AC202) | N10: =IF(TechData_R0!AD202="","",TechData_R0!AD202) | ... P10: =IF(TechData_R0!AF202="","",TechData_R0!AF202)
A11: UC_IMPPADDUP6 | B11: IMPDSHP13 | E11: 1 | F11: 1 | G11: =IF(TechData_R0!W203="","",TechData_R0!W203) -> 224317.87 | H11: =IF(TechData_R0!X203="","",TechData_R0!X203) -> 224317.87 | I11: =IF(TechData_R0!Y203="","",TechData_R0!Y203) -> 224317.87 | J11: =IF(TechData_R0!Z203="","",TechData_R0!Z203) | K11: =IF(TechData_R0!AA203="","",TechData_R0!AA203) | L11: =IF(TechData_R0!AB203="","",TechData_R0!AB203) | M11: =IF(TechData_R0!AC203="","",TechData_R0!AC203) | N11: =IF(TechData_R0!AD203="","",TechData_R0!AD203) | ... P11: =IF(TechData_R0!AF203="","",TechData_R0!AF203)
A12: UC_IMPPADDUP7 | B12: IMPDSHP11 | E12: 1 | F12: 1 | G12: =IF(TechData_R0!W204="","",TechData_R0!W204) -> 1794543 | H12: =IF(TechData_R0!X204="","",TechData_R0!X204) -> 1794543 | I12: =IF(TechData_R0!Y204="","",TechData_R0!Y204) -> 1794543 | J12: =IF(TechData_R0!Z204="","",TechData_R0!Z204) | K12: =IF(TechData_R0!AA204="","",TechData_R0!AA204) | L12: =IF(TechData_R0!AB204="","",TechData_R0!AB204) | M12: =IF(TechData_R0!AC204="","",TechData_R0!AC204) | N12: =IF(TechData_R0!AD204="","",TechData_R0!AD204) | ... P12: =IF(TechData_R0!AF204="","",TechData_R0!AF204)
A13: UC_IMPPADDUP8 | B13: IMPDSHP12 | E13: 1 | F13: 1 | G13: =IF(TechData_R0!W205="","",TechData_R0!W205) -> 224317.87 | H13: =IF(TechData_R0!X205="","",TechData_R0!X205) -> 224317.87 | I13: =IF(TechData_R0!Y205="","",TechData_R0!Y205) -> 224317.87 | J13: =IF(TechData_R0!Z205="","",TechData_R0!Z205) | K13: =IF(TechData_R0!AA205="","",TechData_R0!AA205) | L13: =IF(TechData_R0!AB205="","",TechData_R0!AB205) | M13: =IF(TechData_R0!AC205="","",TechData_R0!AC205) | N13: =IF(TechData_R0!AD205="","",TechData_R0!AD205) | ... P13: =IF(TechData_R0!AF205="","",TechData_R0!AF205)
A14: UC_IMPPADDUP9 | B14: IMPDSHP14 | E14: 1 | F14: 1 | G14: =IF(TechData_R0!W206="","",TechData_R0!W206) -> 448635.74 | H14: =IF(TechData_R0!X206="","",TechData_R0!X206) -> 448635.74 | I14: =IF(TechData_R0!Y206="","",TechData_R0!Y206) -> 448635.74 | J14: =IF(TechData_R0!Z206="","",TechData_R0!Z206) | K14: =IF(TechData_R0!AA206="","",TechData_R0!AA206) | L14: =IF(TechData_R0!AB206="","",TechData_R0!AB206) | M14: =IF(TechData_R0!AC206="","",TechData_R0!AC206) | N14: =IF(TechData_R0!AD206="","",TechData_R0!AD206) | ... P14: =IF(TechData_R0!AF206="","",TechData_R0!AF206)
A15: UC_IMPPADDUP10 | B15: IMPDSHP15 | E15: 1 | F15: 1 | G15: =IF(TechData_R0!W207="","",TechData_R0!W207) -> 1794543 | H15: =IF(TechData_R0!X207="","",TechData_R0!X207) -> 1794543 | I15: =IF(TechData_R0!Y207="","",TechData_R0!Y207) -> 1794543 | J15: =IF(TechData_R0!Z207="","",TechData_R0!Z207) | K15: =IF(TechData_R0!AA207="","",TechData_R0!AA207) | L15: =IF(TechData_R0!AB207="","",TechData_R0!AB207) | M15: =IF(TechData_R0!AC207="","",TechData_R0!AC207) | N15: =IF(TechData_R0!AD207="","",TechData_R0!AD207) | ... P15: =IF(TechData_R0!AF207="","",TechData_R0!AF207)
A16: UC_IMPPADDUP11 | B16: IMPJTFP23 | E16: 1 | F16: 1 | G16: =IF(TechData_R0!W208="","",TechData_R0!W208) -> 218348.9 | H16: =IF(TechData_R0!X208="","",TechData_R0!X208) -> 218348.9 | I16: =IF(TechData_R0!Y208="","",TechData_R0!Y208) -> 218348.9 | J16: =IF(TechData_R0!Z208="","",TechData_R0!Z208) -> 218348.9 | K16: =IF(TechData_R0!AA208="","",TechData_R0!AA208) -> 218348.9 | L16: =IF(TechData_R0!AB208="","",TechData_R0!AB208) -> 218348.9 | M16: =IF(TechData_R0!AC208="","",TechData_R0!AC208) -> 218348.9 | N16: =IF(TechData_R0!AD208="","",TechData_R0!AD208) -> 0 | ... P16: =IF(TechData_R0!AF208="","",TechData_R0!AF208) -> 0
A17: UC_IMPPADDUP12 | B17: IMPJTFP21 | E17: 1 | F17: 1 | G17: =IF(TechData_R0!W209="","",TechData_R0!W209) -> 1746791.2 | H17: =IF(TechData_R0!X209="","",TechData_R0!X209) -> 1746791.2 | I17: =IF(TechData_R0!Y209="","",TechData_R0!Y209) -> 1746791.2 | J17: =IF(TechData_R0!Z209="","",TechData_R0!Z209) -> 1746791.2 | K17: =IF(TechData_R0!AA209="","",TechData_R0!AA209) -> 1746791.2 | L17: =IF(TechData_R0!AB209="","",TechData_R0!AB209) -> 1746791.2 | M17: =IF(TechData_R0!AC209="","",TechData_R0!AC209) -> 1746791.2 | N17: =IF(TechData_R0!AD209="","",TechData_R0!AD209) -> 0 | ... P17: =IF(TechData_R0!AF209="","",TechData_R0!AF209) -> 0
... A35: UC_IMPPADDUP30 | B35: IMPDSHP35 | E35: 1 | F35: 1 | G35: =IF(TechData_R0!W227="","",TechData_R0!W227) -> 1794543 | H35: =IF(TechData_R0!X227="","",TechData_R0!X227) -> 1794543 | I35: =IF(TechData_R0!Y227="","",TechData_R0!Y227) -> 1794543 | J35: =IF(TechData_R0!Z227="","",TechData_R0!Z227) | K35: =IF(TechData_R0!AA227="","",TechData_R0!AA227) | L35: =IF(TechData_R0!AB227="","",TechData_R0!AB227) | M35: =IF(TechData_R0!AC227="","",TechData_R0!AC227) | N35: =IF(TechData_R0!AD227="","",TechData_R0!AD227) | ... P35: =IF(TechData_R0!AF227="","",TechData_R0!AF227)

Sheet TechData_R0
B1: TechData | C1: R0,R1,R2,R3,R4,R5,R6 | Z1: * | AA1: * | AB1: * | AC1: =$AB1 -> * | AD1: =$AB1 -> * | AE1: =$AB1 -> * | AF1: =$AB1 -> * | AG1: =$AB1 -> * | AH1: =$AB1 -> * | AI1: =$AB1 -> * | AJ1: =$AB1 -> * | AK1: =$AB1 -> *
B7: Region | C7: TechName | D7: TechDesc | E7: CommOUT | F7: EFF | G7: *GROWTHr | H7: *GROWTH_TIDr | I7: *DECAYr | J7: *GROWTHr~2010-2055 | K7: *DECAYr~2010-2055 | L7: COST~2010 | M7: COST~2015 | N7: COST~2020 | O7: COST~2025 | P7: COST~2030 | Q7: COST~2035 | R7: COST~2040 | S7: COST~2045 | T7: COST~2050 | U7: COST~2055 | V7: CUM | W7: ACT_BND~LO~2010 | X7: ACT_BND~UP~2005 | Y7: ACT_BND~UP~2010 | Z7: ACT_BND~UP~2015 | AA7: ACT_BND~UP~2020 | AB7: ACT_BND~UP~2025 | AC7: ACT_BND~UP~2030 | AD7: ACT_BND~UP~2035 | AE7: ACT_BND~UP~2040 | AF7: ACT_BND~UP~2045 | AG7: ACT_BND~UP~2050 | AH7: ACT_BND~UP~2055 | AI7: AFA
B8: *Oil mining
B9: =Technologies!B9 -> R1 | C9: =Technologies!C9 -> MINOILD1 | D9: Domestic crude oil - step 1 | E9: =Commodities!$C$10 -> OILD0 | F9: 1 | J9: 1.005 | K9: 1.01 | L9: =L11*'Imp Crude'!$C$5 -> 10.985033 | M9: =M11*'Imp Crude'!$C$5 -> 12.023779 | N9: =N11*'Imp Crude'!$C$5 -> 11.97627 | O9: =O11*'Imp Crude'!$C$5 -> 13.651597 | P9: =P11*'Imp Crude'!$C$5 -> 14.902155 | Q9: =Q11*'Imp Crude'!$C$5 -> 16.322528 | R9: =R11*'Imp Crude'!$C$5 -> 17.862997 | S9: =S11*'Imp Crude'!$C$5 -> 19.548851 | ... U9: =U11*'Imp Crude'!$C$5 -> 23.412892 | V9: =Y9/SUM($Y$9:$Y$13)*'Domestic Crude Oil CUM'!$J$7 -> 177.08864 | W9: =Y9*0.9 -> 2.2708085 | X9: ='Domestic Crude Oil Prod'!B47 -> 2.1943305 | Y9: ='Domestic Crude Oil Prod'!B62 -> 2.5231206
B10: =Technologies!B10 -> R1 | C10: =Technologies!C10 -> MINOILD2 | D10: Domestic crude oil - step 2 | E10: =Commodities!$C$10 -> OILD0 | F10: 1 | J10: 1.005 | K10: 1.01 | L10: =L11*'Imp Crude'!$C$6 -> 11.595313 | M10: =M11*'Imp Crude'!$C$6 -> 12.691766 | N10: =N11*'Imp Crude'!$C$6 -> 12.641618 | O10: =O11*'Imp Crude'!$C$6 -> 14.410019 | P10: =P11*'Imp Crude'!$C$6 -> 15.730053 | Q10: =Q11*'Imp Crude'!$C$6 -> 17.229335 | R10: =R11*'Imp Crude'!$C$6 -> 18.855386 | S10: =S11*'Imp Crude'!$C$6 -> 20.634898 | ... U10: =U11*'Imp Crude'!$C$6 -> 24.713608 | V10: =Y10/SUM($Y$9:$Y$13)*'Domestic Crude Oil CUM'!$J$7 -> 177.08864 | W10: =Y10*0.9 -> 2.2708085 | X10: ='Domestic Crude Oil Prod'!B48 -> 2.1943305 | Y10: ='Domestic Crude Oil Prod'!B63 -> 2.5231206
B11: =Technologies!B11 -> R1 | C11: =Technologies!C11 -> MINOILD3 | D11: Domestic crude oil - step 3 | E11: =Commodities!$C$10 -> OILD0 | F11: 1 | J11: 1.005 | K11: 1.01 | L11: ='Domestic Crude Oil Prices'!M31*'Imp Crude'!$J$5 -> 12.205592 | M11: ='Domestic Crude Oil Prices'!N31*'Imp Crude'!$J$5 -> 13.359754 | N11: ='Domestic Crude Oil Prices'!O31*'Imp Crude'!$J$5 -> 13.306966 | O11: ='Domestic Crude Oil Prices'!P31*'Imp Crude'!$J$5 -> 15.168441 | P11: ='Domestic Crude Oil Prices'!Q31*'Imp Crude'!$J$5 -> 16.55795 | Q11: ='Domestic Crude Oil Prices'!R31*'Imp Crude'!$J$5 -> 18.136142 | R11: ='Domestic Crude Oil Prices'!S31*'Imp Crude'!$J$5 -> 19.847774 | S11: =R11*'Domestic Crude Oil Prices'!$T$30 -> 21.720945 | T11: =S11*'Domestic Crude Oil Prices'!$T$30 -> 23.770901 | U11: =T11*'Domestic Crude Oil Prices'!$T$30 -> 26.014324 | V11: =Y11/SUM($Y$9:$Y$13)*'Domestic Crude Oil CUM'!$J$7 -> 1416.7091 | W11: =Y11*0.9 -> 18.166468 | X11: ='Domestic Crude Oil Prod'!B49 -> 17.554644 | Y11: ='Domestic Crude Oil Prod'!B64 -> 20.184965
B12: =Technologies!B12 -> R1 | C12: =Technologies!C12 -> MINOILD4 | D12: Domestic crude oil - step 4 | E12: =Commodities!$C$10 -> OILD0 | F12: 1 | H12: =Y12*0.1 -> 0.50462412 | J12: 1.005 | K12: 1.01 | L12: =L11*'Imp Crude'!$C$8 -> 12.815872 | M12: =M11*'Imp Crude'!$C$8 -> 14.027742 | N12: =N11*'Imp Crude'!$C$8 -> 13.972315 | O12: =O11*'Imp Crude'!$C$8 -> 15.926863 | P12: =P11*'Imp Crude'!$C$8 -> 17.385848 | Q12: =Q11*'Imp Crude'!$C$8 -> 19.042949 | R12: =R11*'Imp Crude'!$C$8 -> 20.840163 | S12: =S11*'Imp Crude'!$C$8 -> 22.806993 | ... U12: =U11*'Imp Crude'!$C$8 -> 27.31504 | V12: =Y12/SUM($Y$9:$Y$13)*'Domestic Crude Oil CUM'!$J$7 -> 354.17728 | X12: ='Domestic Crude Oil Prod'!B50 -> 4.3886609 | Y12: ='Domestic Crude Oil Prod'!B65 -> 5.0462412
B13: =Technologies!B13 -> R1 | C13: =Technologies!C13 -> MINOILD5 | D13: Domestic crude oil - step 5 | E13: =Commodities!$C$10 -> OILD0 | F13: 1 | H13: =Y13*0.1 -> 0.75693618 | J13: 1.005 | K13: 1.01 | L13: =L12*'Imp Crude'!$C$9 -> 16.660633 | M13: =M12*'Imp Crude'!$C$9 -> 18.236064 | N13: =N12*'Imp Crude'!$C$9 -> 18.164009 | O13: =O12*'Imp Crude'!$C$9 -> 20.704922 | P13: =P12*'Imp Crude'!$C$9 -> 22.601602 | Q13: =Q12*'Imp Crude'!$C$9 -> 24.755834 | R13: =R12*'Imp Crude'!$C$9 -> 27.092212 | S13: =S12*'Imp Crude'!$C$9 -> 29.649091 | ... U13: =U12*'Imp Crude'!$C$9 -> 35.509552 | V13: =Y13/SUM($Y$9:$Y$13)*'Domestic Crude Oil CUM'!$J$7 -> 531.26592 | X13: 0 | Y13: ='Domestic Crude Oil Prod'!B66 -> 7.5693618
B17: Region | C17: TechName | D17: TechDesc | E17: CommIN | F17: CommOUT | G17: EFF | H17: ACT_BND~LO~2010 | I17: ACT_BND~UP~2005 | J17: ACT_BND~UP~2010 | K17: ACT_BND~UP~2015 | L17: ACT_BND~UP~2020 | M17: ACT_BND~UP~2025 | N17: ACT_BND~UP~2030 | O17: ACT_BND~UP~2035 | P17: ACT_BND~UP~2040 | Q17: ACT_BND~UP~2045 | R17: ACT_BND~UP~2050 | S17: ACT_BND~UP~2055 | T17: AFA | X17: ENV_ACT~VOC | Y17: ENV_ACT~CO | Z17: ENV_ACT~NOX | AA17: ENV_ACT~PM10 | AB17: ENV_ACT~PM25 | AC17: ENV_ACT~SO2 | AD17: ENV_ACT~CH4 | AE17: ENV_ACT~N2O | AF17: ENV_ACT~CO2 | AG17: ENV_ACT~OC | AH17: ENV_ACT~BC
B18: * Oil extraction
B19: =Technologies!B$18 -> R1 | C19: =Technologies!C$18 -> SCMINOILD | D19: Collector: MINOILD | E19: =Commodities!$C$10 -> OILD0 | F19: =Commodities!C11 -> OILD1 | G19: 1
B20: * | C20: =Technologies!C$18 -> SCMINOILD | D20: Collector: MINOILD | E20: =Commodities!$C$10 -> OILD0 | F20: =Commodities!C12 -> OILD2 | G20: 1 | X20: =Emissions!D6 -> 0.0010994635 | Y20: =Emissions!E6 -> 0.0029382215 | Z20: =Emissions!F6 -> 0.0092506587 | AA20: =Emissions!G6 -> 0.0011184198 | AB20: =Emissions!H6 -> 0.00038860349 | AC20: =Emissions!I6 -> 0.0019524956 | AD20: =Emissions!C75 -> 0.080620207 | AE20: =Emissions!K6 -> 4.3599416e-05 | AF20: =Emissions!B75/1000 -> 0.0022133809 | AG20: =Emissions!M6 -> 3.1277842e-05 | AH20: =Emissions!N6 -> 1.2321574e-05
B21: * | C21: =Technologies!C$18 -> SCMINOILD | D21: Collector: MINOILD | E21: =Commodities!$C$10 -> OILD0 | F21: =Commodities!C13 -> OILD3 | G21: 1 | X21: =X20 -> 0.0010994635 | Y21: =Y20 -> 0.0029382215 | Z21: =Z20 -> 0.0092506587 | AA21: =AA20 -> 0.0011184198 | AB21: =AB20 -> 0.00038860349 | AC21: =AC20 -> 0.0019524956 | AD21: =AD20 -> 0.080620207 | AE21: =AE20 -> 4.3599416e-05 | ... AH21: =AH20 -> 1.2321574e-05
B22: * | C22: =Technologies!C$18 -> SCMINOILD | D22: Collector: MINOILD | E22: =Commodities!$C$10 -> OILD0 | F22: =Commodities!C14 -> OILD4 | G22: 1 | X22: =X21 -> 0.0010994635 | Y22: =Y21 -> 0.0029382215 | Z22: =Z21 -> 0.0092506587 | AA22: =AA21 -> 0.0011184198 | AB22: =AB21 -> 0.00038860349 | AC22: =AC21 -> 0.0019524956 | AD22: =AD21 -> 0.080620207 | AE22: =AE21 -> 4.3599416e-05 | ... AH22: =AH21 -> 1.2321574e-05
B23: * | C23: =Technologies!C$18 -> SCMINOILD | D23: Collector: MINOILD | E23: =Commodities!$C$10 -> OILD0 | F23: =Commodities!C15 -> OILD5 | G23: 1 | X23: =X22 -> 0.0010994635 | Y23: =Y22 -> 0.0029382215 | Z23: =Z22 -> 0.0092506587 | AA23: =AA22 -> 0.0011184198 | AB23: =AB22 -> 0.00038860349 | AC23: =AC22 -> 0.0019524956 | AD23: =AD22 -> 0.080620207 | AE23: =AE22 -> 4.3599416e-05 | ... AH23: =AH22 -> 1.2321574e-05
B24: * | C24: =Technologies!C$18 -> SCMINOILD | D24: Collector: MINOILD | E24: =Commodities!$C$10 -> OILD0 | F24: =Commodities!C16 -> OILD6 | G24: 1 | X24: =X23 -> 0.0010994635 | Y24: =Y23 -> 0.0029382215 | Z24: =Z23 -> 0.0092506587 | AA24: =AA23 -> 0.0011184198 | AB24: =AB23 -> 0.00038860349 | AC24: =AC23 -> 0.0019524956 | AD24: =AD23 -> 0.080620207 | AE24: =AE23 -> 4.3599416e-05 | ... AH24: =AH23 -> 1.2321574e-05
B25: *
B30: Region | C30: TechName | D30: TechDesc | E30: CommOUT | F30: EFF | G30: *GROWTHr | H30: *GROWTH_TIDr | I30: *DECAYr | J30: *GROWTHr~2010-2055 | K30: *DECAYr~2010-2055 | L30: COST~2010 | M30: COST~2015 | N30: COST~2020 | O30: COST~2025 | P30: COST~2030 | Q30: COST~2035 | R30: COST~2040 | S30: COST~2045 | T30: COST~2050 | U30: COST~2055 | V30: CUM | W30: ACT_BND~LO~2010 | X30: ACT_BND~UP~2005 | Y30: ACT_BND~UP~2010 | Z30: ACT_BND~UP~2015 | AA30: ACT_BND~UP~2020 | AB30: ACT_BND~UP~2025 | AC30: ACT_BND~UP~2030 | AD30: ACT_BND~UP~2035 | AE30: ACT_BND~UP~2040 | AF30: ACT_BND~UP~2045 | AG30: ACT_BND~UP~2050 | AH30: ACT_BND~UP~2055 | AI30: AFA | AJ30: NCAP_TLIFE
B31: *Imported crude supply
B32: =Technologies!B25 -> R1 | C32: ='Imp Crude'!B13 -> IMPOILHH13 | D32: ='Imp Crude'!C13 -> Imported Imported Oil-High Sulfur, Heavy G, PADD 1, Step 3 | E32: ='Imp Crude'!D13 -> OILHH1 | F32: 1 | J32: 1.005 | K32: 1.005 | L32: ='Imp Crude'!L13 -> 11.163537 | M32: ='Imp Crude'!M13 -> #REF! | N32: ='Imp Crude'!N13 -> #REF! | O32: ='Imp Crude'!O13 -> #REF! | P32: ='Imp Crude'!P13 -> #REF! | Q32: ='Imp Crude'!Q13 -> #REF! | R32: ='Imp Crude'!R13 -> #REF! | S32: ='Imp Crude'!S13 -> #REF! | ... U32: ='Imp Crude'!U13 -> #REF! | X32: ='Imp Crude'!AE13 -> 477.40444 | Y32: ='Imp Crude'!AF13 -> 239.79184
B33: =Technologies!B26 -> R1 | C33: ='Imp Crude'!B14 -> IMPOILHH11 | D33: ='Imp Crude'!C14 -> Imported Imported Oil-High Sulfur, Heavy G, PADD 1, Step 1 | E33: ='Imp Crude'!D14 -> OILHH1 | F33: 1 | J33: 1.005 | K33: 1.005 | L33: ='Imp Crude'!L14 -> 10.047183 | M33: ='Imp Crude'!M14 -> #REF! | N33: ='Imp Crude'!N14 -> #REF! | O33: ='Imp Crude'!O14 -> #REF! | P33: ='Imp Crude'!P14 -> #REF! | Q33: ='Imp Crude'!Q14 -> #REF! | R33: ='Imp Crude'!R14 -> #REF! | S33: ='Imp Crude'!S14 -> #REF! | ... U33: ='Imp Crude'!U14 -> #REF! | X33: ='Imp Crude'!AE14 -> 59.675555 | Y33: ='Imp Crude'!AF14 -> 29.973981
B34: =Technologies!B27 -> R1 | C34: ='Imp Crude'!B15 -> IMPOILHH12 | D34: ='Imp Crude'!C15 -> Imported Imported Oil-High Sulfur, Heavy G, PADD 1, Step 2 | E34: ='Imp Crude'!D15 -> OILHH1 | F34: 1 | J34: 1.005 | K34: 1.005 | L34: ='Imp Crude'!L15 -> 10.60536 | M34: ='Imp Crude'!M15 -> #REF! | N34: ='Imp Crude'!N15 -> #REF! | O34: ='Imp Crude'!O15 -> #REF! | P34: ='Imp Crude'!P15 -> #REF! | Q34: ='Imp Crude'!Q15 -> #REF! | R34: ='Imp Crude'!R15 -> #REF! | S34: ='Imp Crude'!S15 -> #REF! | ... U34: ='Imp Crude'!U15 -> #REF! | X34: ='Imp Crude'!AE15 -> 59.675555 | Y34: ='Imp Crude'!AF15 -> 29.973981
B35: =Technologies!B28 -> R1 | C35: ='Imp Crude'!B16 -> IMPOILHH14 | D35: ='Imp Crude'!C16 -> Imported Imported Oil-High Sulfur, Heavy G, PADD 1, Step 4 | E35: ='Imp Crude'!D16 -> OILHH1 | F35: 1 | J35: 1.005 | K35: 1.005 | L35: ='Imp Crude'!L16 -> 11.721714 | M35: ='Imp Crude'!M16 -> #REF! | N35: ='Imp Crude'!N16 -> #REF! | O35: ='Imp Crude'!O16 -> #REF! | P35: ='Imp Crude'!P16 -> #REF! | Q35: ='Imp Crude'!Q16 -> #REF! | R35: ='Imp Crude'!R16 -> #REF! | S35: ='Imp Crude'!S16 -> #REF! | ... U35: ='Imp Crude'!U16 -> #REF! | X35: ='Imp Crude'!AE16 -> 119.35111 | Y35: ='Imp Crude'!AF16 -> 59.947961
B36: =Technologies!B29 -> R1 | C36: ='Imp Crude'!B17 -> IMPOILHH15 | D36: ='Imp Crude'!C17 -> Imported Imported Oil-High Sulfur, Heavy G, PADD 1, Step 5 | E36: ='Imp Crude'!D17 -> OILHH1 | F36: 1 | J36: 1.005 | K36: 1.005 | L36: ='Imp Crude'!L17 -> 14.512598 | M36: ='Imp Crude'!M17 -> #REF! | N36: ='Imp Crude'!N17 -> #REF! | O36: ='Imp Crude'!O17 -> #REF! | P36: ='Imp Crude'!P17 -> #REF! | Q36: ='Imp Crude'!Q17 -> #REF! | R36: ='Imp Crude'!R17 -> #REF! | S36: ='Imp Crude'!S17 -> #REF! | ... U36: ='Imp Crude'!U17 -> #REF! | X36: ='Imp Crude'!AE17 -> 59.675555 | Y36: ='Imp Crude'!AF17 -> 29.973981
B37: =Technologies!B30 -> R1 | C37: ='Imp Crude'!B18 -> IMPOILHL13 | D37: ='Imp Crude'!C18 -> Imported Imported Oil-High Sulfur, Low G, PADD 1, Step 3 | E37: ='Imp Crude'!D18 -> OILHL1 | F37: 1 | J37: 1.005 | K37: 1.005 | L37: ='Imp Crude'!L18 -> 12.073159 | M37: ='Imp Crude'!M18 -> #REF! | N37: ='Imp Crude'!N18 -> #REF! | O37: ='Imp Crude'!O18 -> #REF! | P37: ='Imp Crude'!P18 -> #REF! | Q37: ='Imp Crude'!Q18 -> #REF! | R37: ='Imp Crude'!R18 -> #REF! | S37: ='Imp Crude'!S18 -> #REF! | ... U37: ='Imp Crude'!U18 -> #REF! | X37: ='Imp Crude'!AE18 -> 174.82416 | Y37: ='Imp Crude'!AF18 -> 148.71043
B38: =Technologies!B31 -> R1 | C38: ='Imp Crude'!B19 -> IMPOILHL11 | D38: ='Imp Crude'!C19 -> Imported Imported Oil-High Sulfur, Low G, PADD 1, Step 1 | E38: ='Imp Crude'!D19 -> OILHL1 | F38: 1 | J38: 1.005 | K38: 1.005 | L38: ='Imp Crude'!L19 -> 10.865843 | M38: ='Imp Crude'!M19 -> #REF! | N38: ='Imp Crude'!N19 -> #REF! | O38: ='Imp Crude'!O19 -> #REF! | P38: ='Imp Crude'!P19 -> #REF! | Q38: ='Imp Crude'!Q19 -> #REF! | R38: ='Imp Crude'!R19 -> #REF! | S38: ='Imp Crude'!S19 -> #REF! | ... U38: ='Imp Crude'!U19 -> #REF! | X38: ='Imp Crude'!AE19 -> 21.85302 | Y38: ='Imp Crude'!AF19 -> 18.588804
B39: =Technologies!B32 -> R1 | C39: ='Imp Crude'!B20 -> IMPOILHL12 | D39: ='Imp Crude'!C20 -> Imported Imported Oil-High Sulfur, Low G, PADD 1, Step 2 | E39: ='Imp Crude'!D20 -> OILHL1 | F39: 1 | J39: 1.005 | K39: 1.005 | L39: ='Imp Crude'!L20 -> 11.469501 | M39: ='Imp Crude'!M20 -> #REF! | N39: ='Imp Crude'!N20 -> #REF! | O39: ='Imp Crude'!O20 -> #REF! | P39: ='Imp Crude'!P20 -> #REF! | Q39: ='Imp Crude'!Q20 -> #REF! | R39: ='Imp Crude'!R20 -> #REF! | S39: ='Imp Crude'!S20 -> #REF! | ... U39: ='Imp Crude'!U20 -> #REF! | X39: ='Imp Crude'!AE20 -> 21.85302 | Y39: ='Imp Crude'!AF20 -> 18.588804
B40: =Technologies!B33 -> R1 | C40: ='Imp Crude'!B21 -> IMPOILHL14 | D40: ='Imp Crude'!C21 -> Imported Imported Oil-High Sulfur, Low G, PADD 1, Step 4 | E40: ='Imp Crude'!D21 -> OILHL1 | F40: 1 | J40: 1.005 | K40: 1.005 | L40: ='Imp Crude'!L21 -> 12.676817 | M40: ='Imp Crude'!M21 -> #REF! | N40: ='Imp Crude'!N21 -> #REF! | O40: ='Imp Crude'!O21 -> #REF! | P40: ='Imp Crude'!P21 -> #REF! | Q40: ='Imp Crude'!Q21 -> #REF! | R40: ='Imp Crude'!R21 -> #REF! | S40: ='Imp Crude'!S21 -> #REF! | ... U40: ='Imp Crude'!U21 -> #REF! | X40: ='Imp Crude'!AE21 -> 43.70604 | Y40: ='Imp Crude'!AF21 -> 37.177608
B41: =Technologies!B34 -> R1 | C41: ='Imp Crude'!B22 -> IMPOILHL15 | D41: ='Imp Crude'!C22 -> Imported Imported Oil-High Sulfur, Low G, PADD 1, Step 5 | E41: ='Imp Crude'!D22 -> OILHL1 | F41: 1 | J41: 1.005 | K41: 1.005 | L41: ='Imp Crude'!L22 -> 15.695106 | M41: ='Imp Crude'!M22 -> #REF! | N41: ='Imp Crude'!N22 -> #REF! | O41: ='Imp Crude'!O22 -> #REF! | P41: ='Imp Crude'!P22 -> #REF! | Q41: ='Imp Crude'!Q22 -> #REF! | R41: ='Imp Crude'!R22 -> #REF! | S41: ='Imp Crude'!S22 -> #REF! | ... U41: ='Imp Crude'!U22 -> #REF! | X41: ='Imp Crude'!AE22 -> 21.85302 | Y41: ='Imp Crude'!AF22 -> 18.588804
B42: =Technologies!B35 -> R1 | C42: ='Imp Crude'!B23 -> IMPOILHV13 | D42: ='Imp Crude'!C23 -> Imported Imported Oil-High Sulfur, Very HG, PADD 1, Step 3 | E42: ='Imp Crude'!D23 -> OILHV1 | F42: 1 | J42: 1.005 | K42: 1.005 | L42: ='Imp Crude'!L23 -> 11.064306 | M42: ='Imp Crude'!M23 -> #REF! | N42: ='Imp Crude'!N23 -> #REF! | O42: ='Imp Crude'!O23 -> #REF! | P42: ='Imp Crude'!P23 -> #REF! | Q42: ='Imp Crude'!Q23 -> #REF! | R42: ='Imp Crude'!R23 -> #REF! | S42: ='Imp Crude'!S23 -> #REF! | ... U42: ='Imp Crude'!U23 -> #REF! | X42: ='Imp Crude'!AE23 -> 229.6779 | Y42: ='Imp Crude'!AF23 -> 117.94019
B43: =Technologies!B36 -> R1 | C43: ='Imp Crude'!B24 -> IMPOILHV11 | D43: ='Imp Crude'!C24 -> Imported Imported Oil-High Sulfur, Very HG, PADD 1, Step 1 | E43: ='Imp Crude'!D24 -> OILHV1 | F43: 1 | J43: 1.005 | K43: 1.005 | L43: ='Imp Crude'!L24 -> 9.9578751 | M43: ='Imp Crude'!M24 -> #REF! | N43: ='Imp Crude'!N24 -> #REF! | O43: ='Imp Crude'!O24 -> #REF! | P43: ='Imp Crude'!P24 -> #REF! | Q43: ='Imp Crude'!Q24 -> #REF! | R43: ='Imp Crude'!R24 -> #REF! | S43: ='Imp Crude'!S24 -> #REF! | ... U43: ='Imp Crude'!U24 -> #REF! | X43: ='Imp Crude'!AE24 -> 28.709737 | Y43: ='Imp Crude'!AF24 -> 14.742523
... B56: =Technologies!B49 -> R1 | C56: ='Imp Crude'!B37 -> IMPOILMH15 | D56: ='Imp Crude'!C37 -> Imported Imported Oil-Medium Sulfur, HG, PADD 1, Step 5 | E56: ='Imp Crude'!D37 -> OILMH1 | F56: 1 | J56: 1.005 | K56: 1.005 | L56: ='Imp Crude'!L37 -> 15.669306 | M56: ='Imp Crude'!M37 -> #REF! | N56: ='Imp Crude'!N37 -> #REF! | O56: ='Imp Crude'!O37 -> #REF! | P56: ='Imp Crude'!P37 -> #REF! | Q56: ='Imp Crude'!Q37 -> #REF! | R56: ='Imp Crude'!R37 -> #REF! | S56: ='Imp Crude'!S37 -> #REF! | ... U56: ='Imp Crude'!U37 -> #REF! | X56: ='Imp Crude'!AE37 -> 12.281556 | Y56: ='Imp Crude'!AF37 -> 11.843843
B57: *
B58: =Technologies!B51 -> R1 | C58: ='Imp Crude'!B39 -> IMPOILHH23 | D58: ='Imp Crude'!C39 -> Imported Imported Oil-High Sulfur, Heavy G, PADD 2, Step 3 | E58: ='Imp Crude'!D39 -> OILHH2 | F58: 1 | J58: 1.005 | K58: 1.005 | L58: ='Imp Crude'!L39 -> 11.163537 | M58: ='Imp Crude'!M39 -> #REF! | N58: ='Imp Crude'!N39 -> #REF! | O58: ='Imp Crude'!O39 -> #REF! | P58: ='Imp Crude'!P39 -> #REF! | Q58: ='Imp Crude'!Q39 -> #REF! | R58: ='Imp Crude'!R39 -> #REF! | S58: ='Imp Crude'!S39 -> #REF! | ... U58: ='Imp Crude'!U39 -> #REF! | X58: ='Imp Crude'!AE39 -> 424.2643 | Y58: ='Imp Crude'!AF39 -> 454.15912
B59: =Technologies!B52 -> R1 | C59: ='Imp Crude'!B40 -> IMPOILHH21 | D59: ='Imp Crude'!C40 -> Imported Imported Oil-High Sulfur, Heavy G, PADD 2, Step 1 | E59: ='Imp Crude'!D40 -> OILHH2 | F59: 1 | J59: 1.005 | K59: 1.005 | L59: ='Imp Crude'!L40 -> 10.047183 | M59: ='Imp Crude'!M40 -> #REF! | N59: ='Imp Crude'!N40 -> #REF! | O59: ='Imp Crude'!O40 -> #REF! | P59: ='Imp Crude'!P40 -> #REF! | Q59: ='Imp Crude'!Q40 -> #REF! | R59: ='Imp Crude'!R40 -> #REF! | S59: ='Imp Crude'!S40 -> #REF! | ... U59: ='Imp Crude'!U40 -> #REF! | X59: ='Imp Crude'!AE40 -> 53.033038 | Y59: ='Imp Crude'!AF40 -> 56.76989
B60: =Technologies!B53 -> R1 | C60: ='Imp Crude'!B41 -> IMPOILHH22 | D60: ='Imp Crude'!C41 -> Imported Imported Oil-High Sulfur, Heavy G, PADD 2, Step 2 | E60: ='Imp Crude'!D41 -> OILHH2 | F60: 1 | J60: 1.005 | K60: 1.005 | L60: ='Imp Crude'!L41 -> 10.60536 | M60: ='Imp Crude'!M41 -> #REF! | N60: ='Imp Crude'!N41 -> #REF! | O60: ='Imp Crude'!O41 -> #REF! | P60: ='Imp Crude'!P41 -> #REF! | Q60: ='Imp Crude'!Q41 -> #REF! | R60: ='Imp Crude'!R41 -> #REF! | S60: ='Imp Crude'!S41 -> #REF! | ... U60: ='Imp Crude'!U41 -> #REF! | X60: ='Imp Crude'!AE41 -> 53.033038 | Y60: ='Imp Crude'!AF41 -> 56.76989
B61: =Technologies!B54 -> R1 | C61: ='Imp Crude'!B42 -> IMPOILHH24 | D61: ='Imp Crude'!C42 -> Imported Imported Oil-High Sulfur, Heavy G, PADD 2, Step 4 | E61: ='Imp Crude'!D42 -> OILHH2 | F61: 1 | J61: 1.005 | K61: 1.005 | L61: ='Imp Crude'!L42 -> 11.721714 | M61: ='Imp Crude'!M42 -> #REF! | N61: ='Imp Crude'!N42 -> #REF! | O61: ='Imp Crude'!O42 -> #REF! | P61: ='Imp Crude'!P42 -> #REF! | Q61: ='Imp Crude'!Q42 -> #REF! | R61: ='Imp Crude'!R42 -> #REF! | S61: ='Imp Crude'!S42 -> #REF! | ... U61: ='Imp Crude'!U42 -> #REF! | X61: ='Imp Crude'!AE42 -> 106.06608 | Y61: ='Imp Crude'!AF42 -> 113.53978
B62: =Technologies!B55 -> R1 | C62: ='Imp Crude'!B43 -> IMPOILHH25 | D62: ='Imp Crude'!C43 -> Imported Imported Oil-High Sulfur, Heavy G, PADD 2, Step 5 | E62: ='Imp Crude'!D43 -> OILHH2 | F62: 1 | J62: 1.005 | K62: 1.005 | L62: ='Imp Crude'!L43 -> 14.512598 | M62: ='Imp Crude'!M43 -> #REF! | N62: ='Imp Crude'!N43 -> #REF! | O62: ='Imp Crude'!O43 -> #REF! | P62: ='Imp Crude'!P43 -> #REF! | Q62: ='Imp Crude'!Q43 -> #REF! | R62: ='Imp Crude'!R43 -> #REF! | S62: ='Imp Crude'!S43 -> #REF! | ... U62: ='Imp Crude'!U43 -> #REF! | X62: ='Imp Crude'!AE43 -> 53.033038 | Y62: ='Imp Crude'!AF43 -> 56.76989
B63: =Technologies!B56 -> R1 | C63: ='Imp Crude'!B44 -> IMPOILHL23 | D63: ='Imp Crude'!C44 -> Imported Imported Oil-High Sulfur, Low G, PADD 2, Step 3 | E63: ='Imp Crude'!D44 -> OILHL2 | F63: 1 | J63: 1.005 | K63: 1.005 | L63: ='Imp Crude'!L44 -> 12.073159 | M63: ='Imp Crude'!M44 -> #REF! | N63: ='Imp Crude'!N44 -> #REF! | O63: ='Imp Crude'!O44 -> #REF! | P63: ='Imp Crude'!P44 -> #REF! | Q63: ='Imp Crude'!Q44 -> #REF! | R63: ='Imp Crude'!R44 -> #REF! | S63: ='Imp Crude'!S44 -> #REF! | ... U63: ='Imp Crude'!U44 -> #REF! | X63: ='Imp Crude'!AE44 -> 276.11265 | Y63: ='Imp Crude'!AF44 -> 221.25892
B64: =Technologies!B57 -> R1 | C64: ='Imp Crude'!B45 -> IMPOILHL21 | D64: ='Imp Crude'!C45 -> Imported Imported Oil-High Sulfur, Low G, PADD 2, Step 1 | E64: ='Imp Crude'!D45 -> OILHL2 | F64: 1 | J64: 1.005 | K64: 1.005 | L64: ='Imp Crude'!L45 -> 10.865843 | M64: ='Imp Crude'!M45 -> #REF! | N64: ='Imp Crude'!N45 -> #REF! | O64: ='Imp Crude'!O45 -> #REF! | P64: ='Imp Crude'!P45 -> #REF! | Q64: ='Imp Crude'!Q45 -> #REF! | R64: ='Imp Crude'!R45 -> #REF! | S64: ='Imp Crude'!S45 -> #REF! | ... U64: ='Imp Crude'!U45 -> #REF! | X64: ='Imp Crude'!AE45 -> 34.514082 | Y64: ='Imp Crude'!AF45 -> 27.657365
B65: =Technologies!B58 -> R1 | C65: ='Imp Crude'!B46 -> IMPOILHL22 | D65: ='Imp Crude'!C46 -> Imported Imported Oil-High Sulfur, Low G, PADD 2, Step 2 | E65: ='Imp Crude'!D46 -> OILHL2 | F65: 1 | J65: 1.005 | K65: 1.005 | L65: ='Imp Crude'!L46 -> 11.469501 | M65: ='Imp Crude'!M46 -> #REF! | N65: ='Imp Crude'!N46 -> #REF! | O65: ='Imp Crude'!O46 -> #REF! | P65: ='Imp Crude'!P46 -> #REF! | Q65: ='Imp Crude'!Q46 -> #REF! | R65: ='Imp Crude'!R46 -> #REF! | S65: ='Imp Crude'!S46 -> #REF! | ... U65: ='Imp Crude'!U46 -> #REF! | X65: ='Imp Crude'!AE46 -> 34.514082 | Y65: ='Imp Crude'!AF46 -> 27.657365
B66: =Technologies!B59 -> R1 | C66: ='Imp Crude'!B47 -> IMPOILHL24 | D66: ='Imp Crude'!C47 -> Imported Imported Oil-High Sulfur, Low G, PADD 2, Step 4 | E66: ='Imp Crude'!D47 -> OILHL2 | F66: 1 | J66: 1.005 | K66: 1.005 | L66: ='Imp Crude'!L47 -> 12.676817 | M66: ='Imp Crude'!M47 -> #REF! | N66: ='Imp Crude'!N47 -> #REF! | O66: ='Imp Crude'!O47 -> #REF! | P66: ='Imp Crude'!P47 -> #REF! | Q66: ='Imp Crude'!Q47 -> #REF! | R66: ='Imp Crude'!R47 -> #REF! | S66: ='Imp Crude'!S47 -> #REF! | ... U66: ='Imp Crude'!U47 -> #REF! | X66: ='Imp Crude'!AE47 -> 69.028163 | Y66: ='Imp Crude'!AF47 -> 55.31473
B67: =Technologies!B60 -> R1 | C67: ='Imp Crude'!B48 -> IMPOILHL25 | D67: ='Imp Crude'!C48 -> Imported Imported Oil-High Sulfur, Low G, PADD 2, Step 5 | E67: ='Imp Crude'!D48 -> OILHL2 | F67: 1 | J67: 1.005 | K67: 1.005 | L67: ='Imp Crude'!L48 -> 15.695106 | M67: ='Imp Crude'!M48 -> #REF! | N67: ='Imp Crude'!N48 -> #REF! | O67: ='Imp Crude'!O48 -> #REF! | P67: ='Imp Crude'!P48 -> #REF! | Q67: ='Imp Crude'!Q48 -> #REF! | R67: ='Imp Crude'!R48 -> #REF! | S67: ='Imp Crude'!S48 -> #REF! | ... U67: ='Imp Crude'!U48 -> #REF! | X67: ='Imp Crude'!AE48 -> 34.514082 | Y67: ='Imp Crude'!AF48 -> 27.657365
B68: =Technologies!B61 -> R1 | C68: ='Imp Crude'!B49 -> IMPOILHV23 | D68: ='Imp Crude'!C49 -> Imported Imported Oil-High Sulfur, Very HG, PADD 2, Step 3 | E68: ='Imp Crude'!D49 -> OILHV2 | F68: 1 | J68: 1.005 | K68: 1.005 | L68: ='Imp Crude'!L49 -> 11.064306 | M68: ='Imp Crude'!M49 -> #REF! | N68: ='Imp Crude'!N49 -> #REF! | O68: ='Imp Crude'!O49 -> #REF! | P68: ='Imp Crude'!P49 -> #REF! | Q68: ='Imp Crude'!Q49 -> #REF! | R68: ='Imp Crude'!R49 -> #REF! | S68: ='Imp Crude'!S49 -> #REF! | ... U68: ='Imp Crude'!U49 -> #REF! | X68: ='Imp Crude'!AE49 -> 1086.7 | Y68: ='Imp Crude'!AF49 -> 1302.1662
B69: =Technologies!B62 -> R1 | C69: ='Imp Crude'!B50 -> IMPOILHV21 | D69: ='Imp Crude'!C50 -> Imported Imported Oil-High Sulfur, Very HG, PADD 2, Step 1 | E69: ='Imp Crude'!D50 -> OILHV2 | F69: 1 | J69: 1.005 | K69: 1.005 | L69: ='Imp Crude'!L50 -> 9.9578751 | M69: ='Imp Crude'!M50 -> #REF! | N69: ='Imp Crude'!N50 -> #REF! | O69: ='Imp Crude'!O50 -> #REF! | P69: ='Imp Crude'!P50 -> #REF! | Q69: ='Imp Crude'!Q50 -> #REF! | R69: ='Imp Crude'!R50 -> #REF! | S69: ='Imp Crude'!S50 -> #REF! | ... U69: ='Imp Crude'!U50 -> #REF! | X69: ='Imp Crude'!AE50 -> 135.8375 | Y69: ='Imp Crude'!AF50 -> 162.77077
... B82: =Technologies!B75 -> R1 | C82: ='Imp Crude'!B63 -> IMPOILMH25 | D82: ='Imp Crude'!C63 -> Imported Imported Oil-Medium Sulfur, HG, PADD 2, Step 5 | E82: ='Imp Crude'!D63 -> OILMH2 | F82: 1 | J82: 1.005 | K82: 1.005 | L82: ='Imp Crude'!L63 -> 15.669306 | M82: ='Imp Crude'!M63 -> #REF! | N82: ='Imp Crude'!N63 -> #REF! | O82: ='Imp Crude'!O63 -> #REF! | P82: ='Imp Crude'!P63 -> #REF! | Q82: ='Imp Crude'!Q63 -> #REF! | R82: ='Imp Crude'!R63 -> #REF! | S82: ='Imp Crude'!S63 -> #REF! | ... U82: ='Imp Crude'!U63 -> #REF! | X82: ='Imp Crude'!AE63 -> 52.974831 | Y82: ='Imp Crude'!AF63 -> 8.1279452
B83: *
B84: =Technologies!B77 -> R1 | C84: ='Imp Crude'!B65 -> IMPOILHH33 | D84: ='Imp Crude'!C65 -> Imported Imported Oil-High Sulfur, Heavy G, PADD 3, Step 3 | E84: ='Imp Crude'!D65 -> OILHH3 | F84: 1 | J84: 1.005 | K84: 1.005 | L84: ='Imp Crude'!L65 -> 11.163537 | M84: ='Imp Crude'!M65 -> #REF! | N84: ='Imp Crude'!N65 -> #REF! | O84: ='Imp Crude'!O65 -> #REF! | P84: ='Imp Crude'!P65 -> #REF! | Q84: ='Imp Crude'!Q65 -> #REF! | R84: ='Imp Crude'!R65 -> #REF! | S84: ='Imp Crude'!S65 -> #REF! | ... U84: ='Imp Crude'!U65 -> #REF! | X84: ='Imp Crude'!AE65 -> 2841.2372 | Y84: ='Imp Crude'!AF65 -> 2009.6397
B85: =Technologies!B78 -> R1 | C85: ='Imp Crude'!B66 -> IMPOILHH31 | D85: ='Imp Crude'!C66 -> Imported Imported Oil-High Sulfur, Heavy G, PADD 3, Step 1 | E85: ='Imp Crude'!D66 -> OILHH3 | F85: 1 | J85: 1.005 | K85: 1.005 | L85: ='Imp Crude'!L66 -> 10.047183 | M85: ='Imp Crude'!M66 -> #REF! | N85: ='Imp Crude'!N66 -> #REF! | O85: ='Imp Crude'!O66 -> #REF! | P85: ='Imp Crude'!P66 -> #REF! | Q85: ='Imp Crude'!Q66 -> #REF! | R85: ='Imp Crude'!R66 -> #REF! | S85: ='Imp Crude'!S66 -> #REF! | ... U85: ='Imp Crude'!U66 -> #REF! | X85: ='Imp Crude'!AE66 -> 355.15465 | Y85: ='Imp Crude'!AF66 -> 251.20496
B86: =Technologies!B79 -> R1 | C86: ='Imp Crude'!B67 -> IMPOILHH32 | D86: ='Imp Crude'!C67 -> Imported Imported Oil-High Sulfur, Heavy G, PADD 3, Step 2 | E86: ='Imp Crude'!D67 -> OILHH3 | F86: 1 | J86: 1.005 | K86: 1.005 | L86: ='Imp Crude'!L67 -> 10.60536 | M86: ='Imp Crude'!M67 -> #REF! | N86: ='Imp Crude'!N67 -> #REF! | O86: ='Imp Crude'!O67 -> #REF! | P86: ='Imp Crude'!P67 -> #REF! | Q86: ='Imp Crude'!Q67 -> #REF! | R86: ='Imp Crude'!R67 -> #REF! | S86: ='Imp Crude'!S67 -> #REF! | ... U86: ='Imp Crude'!U67 -> #REF! | X86: ='Imp Crude'!AE67 -> 355.15465 | Y86: ='Imp Crude'!AF67 -> 251.20496
B87: =Technologies!B80 -> R1 | C87: ='Imp Crude'!B68 -> IMPOILHH34 | D87: ='Imp Crude'!C68 -> Imported Imported Oil-High Sulfur, Heavy G, PADD 3, Step 4 | E87: ='Imp Crude'!D68 -> OILHH3 | F87: 1 | J87: 1.005 | K87: 1.005 | L87: ='Imp Crude'!L68 -> 11.721714 | M87: ='Imp Crude'!M68 -> #REF! | N87: ='Imp Crude'!N68 -> #REF! | O87: ='Imp Crude'!O68 -> #REF! | P87: ='Imp Crude'!P68 -> #REF! | Q87: ='Imp Crude'!Q68 -> #REF! | R87: ='Imp Crude'!R68 -> #REF! | S87: ='Imp Crude'!S68 -> #REF! | ... U87: ='Imp Crude'!U68 -> #REF! | X87: ='Imp Crude'!AE68 -> 710.3093 | Y87: ='Imp Crude'!AF68 -> 502.40992
B88: =Technologies!B81 -> R1 | C88: ='Imp Crude'!B69 -> IMPOILHH35 | D88: ='Imp Crude'!C69 -> Imported Imported Oil-High Sulfur, Heavy G, PADD 3, Step 5 | E88: ='Imp Crude'!D69 -> OILHH3 | F88: 1 | J88: 1.005 | K88: 1.005 | L88: ='Imp Crude'!L69 -> 14.512598 | M88: ='Imp Crude'!M69 -> #REF! | N88: ='Imp Crude'!N69 -> #REF! | O88: ='Imp Crude'!O69 -> #REF! | P88: ='Imp Crude'!P69 -> #REF! | Q88: ='Imp Crude'!Q69 -> #REF! | R88: ='Imp Crude'!R69 -> #REF! | S88: ='Imp Crude'!S69 -> #REF! | ... U88: ='Imp Crude'!U69 -> #REF! | X88: ='Imp Crude'!AE69 -> 355.15465 | Y88: ='Imp Crude'!AF69 -> 251.20496
B89: =Technologies!B82 -> R1 | C89: ='Imp Crude'!B70 -> IMPOILHL33 | D89: ='Imp Crude'!C70 -> Imported Imported Oil-High Sulfur, Low G, PADD 3, Step 3 | E89: ='Imp Crude'!D70 -> OILHL3 | F89: 1 | J89: 1.005 | K89: 1.005 | L89: ='Imp Crude'!L70 -> 12.073159 | M89: ='Imp Crude'!M70 -> #REF! | N89: ='Imp Crude'!N70 -> #REF! | O89: ='Imp Crude'!O70 -> #REF! | P89: ='Imp Crude'!P70 -> #REF! | Q89: ='Imp Crude'!Q70 -> #REF! | R89: ='Imp Crude'!R70 -> #REF! | S89: ='Imp Crude'!S70 -> #REF! | ... U89: ='Imp Crude'!U70 -> #REF! | X89: ='Imp Crude'!AE70 -> 503.29466 | Y89: ='Imp Crude'!AF70 -> 612.21983
B90: =Technologies!B83 -> R1 | C90: ='Imp Crude'!B71 -> IMPOILHL31 | D90: ='Imp Crude'!C71 -> Imported Imported Oil-High Sulfur, Low G, PADD 3, Step 1 | E90: ='Imp Crude'!D71 -> OILHL3 | F90: 1 | J90: 1.005 | K90: 1.005 | L90: ='Imp Crude'!L71 -> 10.865843 | M90: ='Imp Crude'!M71 -> #REF! | N90: ='Imp Crude'!N71 -> #REF! | O90: ='Imp Crude'!O71 -> #REF! | P90: ='Imp Crude'!P71 -> #REF! | Q90: ='Imp Crude'!Q71 -> #REF! | R90: ='Imp Crude'!R71 -> #REF! | S90: ='Imp Crude'!S71 -> #REF! | ... U90: ='Imp Crude'!U71 -> #REF! | X90: ='Imp Crude'!AE71 -> 62.911832 | Y90: ='Imp Crude'!AF71 -> 76.527479
B91: =Technologies!B84 -> R1 | C91: ='Imp Crude'!B72 -> IMPOILHL32 | D91: ='Imp Crude'!C72 -> Imported Imported Oil-High Sulfur, Low G, PADD 3, Step 2 | E91: ='Imp Crude'!D72 -> OILHL3 | F91: 1 | J91: 1.005 | K91: 1.005 | L91: ='Imp Crude'!L72 -> 11.469501 | M91: ='Imp Crude'!M72 -> #REF! | N91: ='Imp Crude'!N72 -> #REF! | O91: ='Imp Crude'!O72 -> #REF! | P91: ='Imp Crude'!P72 -> #REF! | Q91: ='Imp Crude'!Q72 -> #REF! | R91: ='Imp Crude'!R72 -> #REF! | S91: ='Imp Crude'!S72 -> #REF! | ... U91: ='Imp Crude'!U72 -> #REF! | X91: ='Imp Crude'!AE72 -> 62.911832 | Y91: ='Imp Crude'!AF72 -> 76.527479
B92: =Technologies!B85 -> R1 | C92: ='Imp Crude'!B73 -> IMPOILHL34 | D92: ='Imp Crude'!C73 -> Imported Imported Oil-High Sulfur, Low G, PADD 3, Step 4 | E92: ='Imp Crude'!D73 -> OILHL3 | F92: 1 | J92: 1.005 | K92: 1.005 | L92: ='Imp Crude'!L73 -> 12.676817 | M92: ='Imp Crude'!M73 -> #REF! | N92: ='Imp Crude'!N73 -> #REF! | O92: ='Imp Crude'!O73 -> #REF! | P92: ='Imp Crude'!P73 -> #REF! | Q92: ='Imp Crude'!Q73 -> #REF! | R92: ='Imp Crude'!R73 -> #REF! | S92: ='Imp Crude'!S73 -> #REF! | ... U92: ='Imp Crude'!U73 -> #REF! | X92: ='Imp Crude'!AE73 -> 125.82366 | Y92: ='Imp Crude'!AF73 -> 153.05496
B93: =Technologies!B86 -> R1 | C93: ='Imp Crude'!B74 -> IMPOILHL35 | D93: ='Imp Crude'!C74 -> Imported Imported Oil-High Sulfur, Low G, PADD 3, Step 5 | E93: ='Imp Crude'!D74 -> OILHL3 | F93: 1 | J93: 1.005 | K93: 1.005 | L93: ='Imp Crude'!L74 -> 15.695106 | M93: ='Imp Crude'!M74 -> #REF! | N93: ='Imp Crude'!N74 -> #REF! | O93: ='Imp Crude'!O74 -> #REF! | P93: ='Imp Crude'!P74 -> #REF! | Q93: ='Imp Crude'!Q74 -> #REF! | R93: ='Imp Crude'!R74 -> #REF! | S93: ='Imp Crude'!S74 -> #REF! | ... U93: ='Imp Crude'!U74 -> #REF! | X93: ='Imp Crude'!AE74 -> 62.911832 | Y93: ='Imp Crude'!AF74 -> 76.527479
B94: =Technologies!B87 -> R1 | C94: ='Imp Crude'!B75 -> IMPOILHV33 | D94: ='Imp Crude'!C75 -> Imported Imported Oil-High Sulfur, Very HG, PADD 3, Step 3 | E94: ='Imp Crude'!D75 -> OILHV3 | F94: 1 | J94: 1.005 | K94: 1.005 | L94: ='Imp Crude'!L75 -> 11.064306 | M94: ='Imp Crude'!M75 -> #REF! | N94: ='Imp Crude'!N75 -> #REF! | O94: ='Imp Crude'!O75 -> #REF! | P94: ='Imp Crude'!P75 -> #REF! | Q94: ='Imp Crude'!Q75 -> #REF! | R94: ='Imp Crude'!R75 -> #REF! | S94: ='Imp Crude'!S75 -> #REF! | ... U94: ='Imp Crude'!U75 -> #REF! | X94: ='Imp Crude'!AE75 -> 3820.5207 | Y94: ='Imp Crude'!AF75 -> 3880.627
B95: =Technologies!B88 -> R1 | C95: ='Imp Crude'!B76 -> IMPOILHV31 | D95: ='Imp Crude'!C76 -> Imported Imported Oil-High Sulfur, Very HG, PADD 3, Step 1 | E95: ='Imp Crude'!D76 -> OILHV3 | F95: 1 | J95: 1.005 | K95: 1.005 | L95: ='Imp Crude'!L76 -> 9.9578751 | M95: ='Imp Crude'!M76 -> #REF! | N95: ='Imp Crude'!N76 -> #REF! | O95: ='Imp Crude'!O76 -> #REF! | P95: ='Imp Crude'!P76 -> #REF! | Q95: ='Imp Crude'!Q76 -> #REF! | R95: ='Imp Crude'!R76 -> #REF! | S95: ='Imp Crude'!S76 -> #REF! | ... U95: ='Imp Crude'!U76 -> #REF! | X95: ='Imp Crude'!AE76 -> 477.56509 | Y95: ='Imp Crude'!AF76 -> 485.07837
... B108: =Technologies!B101 -> R1 | C108: ='Imp Crude'!B89 -> IMPOILMH35 | D108: ='Imp Crude'!C89 -> Imported Imported Oil-Medium Sulfur, HG, PADD 3, Step 5 | E108: ='Imp Crude'!D89 -> OILMH3 | F108: 1 | J108: 1.005 | K108: 1.005 | L108: ='Imp Crude'!L89 -> 15.669306 | M108: ='Imp Crude'!M89 -> #REF! | N108: ='Imp Crude'!N89 -> #REF! | O108: ='Imp Crude'!O89 -> #REF! | P108: ='Imp Crude'!P89 -> #REF! | Q108: ='Imp Crude'!Q89 -> #REF! | R108: ='Imp Crude'!R89 -> #REF! | S108: ='Imp Crude'!S89 -> #REF! | ... U108: ='Imp Crude'!U89 -> #REF! | X108: ='Imp Crude'!AE89 -> 127.0623 | Y108: ='Imp Crude'!AF89 -> 98.978861
B109: *
B110: * | C110: ='Imp Crude'!B91 -> IMPOILHH43 | D110: ='Imp Crude'!C91 -> Imported Imported Oil-High Sulfur, Heavy G, PADD 4, Step 3 | E110: ='Imp Crude'!D91 -> OILHH4 | F110: 1 | J110: 1.005 | K110: 1.005 | L110: ='Imp Crude'!L91 -> 11.163537 | M110: ='Imp Crude'!M91 -> #REF! | N110: ='Imp Crude'!N91 -> #REF! | O110: ='Imp Crude'!O91 -> #REF! | P110: ='Imp Crude'!P91 -> #REF! | Q110: ='Imp Crude'!Q91 -> #REF! | R110: ='Imp Crude'!R91 -> #REF! | S110: ='Imp Crude'!S91 -> #REF! | ... U110: ='Imp Crude'!U91 -> #REF! | X110: ='Imp Crude'!AE91 -> 36.674704 | Y110: ='Imp Crude'!AF91 -> 80.7067
B111: * | C111: ='Imp Crude'!B92 -> IMPOILHH41 | D111: ='Imp Crude'!C92 -> Imported Imported Oil-High Sulfur, Heavy G, PADD 4, Step 1 | E111: ='Imp Crude'!D92 -> OILHH4 | F111: 1 | J111: 1.005 | K111: 1.005 | L111: ='Imp Crude'!L92 -> 10.047183 | M111: ='Imp Crude'!M92 -> #REF! | N111: ='Imp Crude'!N92 -> #REF! | O111: ='Imp Crude'!O92 -> #REF! | P111: ='Imp Crude'!P92 -> #REF! | Q111: ='Imp Crude'!Q92 -> #REF! | R111: ='Imp Crude'!R92 -> #REF! | S111: ='Imp Crude'!S92 -> #REF! | ... U111: ='Imp Crude'!U92 -> #REF! | X111: ='Imp Crude'!AE92 -> 4.584338 | Y111: ='Imp Crude'!AF92 -> 10.088338
B112: * | C112: ='Imp Crude'!B93 -> IMPOILHH42 | D112: ='Imp Crude'!C93 -> Imported Imported Oil-High Sulfur, Heavy G, PADD 4, Step 2 | E112: ='Imp Crude'!D93 -> OILHH4 | F112: 1 | J112: 1.005 | K112: 1.005 | L112: ='Imp Crude'!L93 -> 10.60536 | M112: ='Imp Crude'!M93 -> #REF! | N112: ='Imp Crude'!N93 -> #REF! | O112: ='Imp Crude'!O93 -> #REF! | P112: ='Imp Crude'!P93 -> #REF! | Q112: ='Imp Crude'!Q93 -> #REF! | R112: ='Imp Crude'!R93 -> #REF! | S112: ='Imp Crude'!S93 -> #REF! | ... U112: ='Imp Crude'!U93 -> #REF! | X112: ='Imp Crude'!AE93 -> 4.584338 | Y112: ='Imp Crude'!AF93 -> 10.088338
B113: * | C113: ='Imp Crude'!B94 -> IMPOILHH44 | D113: ='Imp Crude'!C94 -> Imported Imported Oil-High Sulfur, Heavy G, PADD 4, Step 4 | E113: ='Imp Crude'!D94 -> OILHH4 | F113: 1 | J113: 1.005 | K113: 1.005 | L113: ='Imp Crude'!L94 -> 11.721714 | M113: ='Imp Crude'!M94 -> #REF! | N113: ='Imp Crude'!N94 -> #REF! | O113: ='Imp Crude'!O94 -> #REF! | P113: ='Imp Crude'!P94 -> #REF! | Q113: ='Imp Crude'!Q94 -> #REF! | R113: ='Imp Crude'!R94 -> #REF! | S113: ='Imp Crude'!S94 -> #REF! | ... U113: ='Imp Crude'!U94 -> #REF! | X113: ='Imp Crude'!AE94 -> 9.168676 | Y113: ='Imp Crude'!AF94 -> 20.176675
B114: * | C114: ='Imp Crude'!B95 -> IMPOILHH45 | D114: ='Imp Crude'!C95 -> Imported Imported Oil-High Sulfur, Heavy G, PADD 4, Step 5 | E114: ='Imp Crude'!D95 -> OILHH4 | F114: 1 | J114: 1.005 | K114: 1.005 | L114: ='Imp Crude'!L95 -> 14.512598 | M114: ='Imp Crude'!M95 -> #REF! | N114: ='Imp Crude'!N95 -> #REF! | O114: ='Imp Crude'!O95 -> #REF! | P114: ='Imp Crude'!P95 -> #REF! | Q114: ='Imp Crude'!Q95 -> #REF! | R114: ='Imp Crude'!R95 -> #REF! | S114: ='Imp Crude'!S95 -> #REF! | ... U114: ='Imp Crude'!U95 -> #REF! | X114: ='Imp Crude'!AE95 -> 4.584338 | Y114: ='Imp Crude'!AF95 -> 10.088338
B115: * | C115: ='Imp Crude'!B96 -> IMPOILHL43 | D115: ='Imp Crude'!C96 -> Imported Imported Oil-High Sulfur, Low G, PADD 4, Step 3 | E115: ='Imp Crude'!D96 -> OILHL4 | F115: 1 | J115: 1.005 | K115: 1.005 | L115: ='Imp Crude'!L96 -> 12.073159 | M115: ='Imp Crude'!M96 -> #REF! | N115: ='Imp Crude'!N96 -> #REF! | O115: ='Imp Crude'!O96 -> #REF! | P115: ='Imp Crude'!P96 -> #REF! | Q115: ='Imp Crude'!Q96 -> #REF! | R115: ='Imp Crude'!R96 -> #REF! | S115: ='Imp Crude'!S96 -> #REF! | ... U115: ='Imp Crude'!U96 -> #REF! | X115: ='Imp Crude'!AE96 -> 4.5633837 | Y115: ='Imp Crude'!AF96 -> 2.4027612
B116: * | C116: ='Imp Crude'!B97 -> IMPOILHL41 | D116: ='Imp Crude'!C97 -> Imported Imported Oil-High Sulfur, Low G, PADD 4, Step 1 | E116: ='Imp Crude'!D97 -> OILHL4 | F116: 1 | J116: 1.005 | K116: 1.005 | L116: ='Imp Crude'!L97 -> 10.865843 | M116: ='Imp Crude'!M97 -> #REF! | N116: ='Imp Crude'!N97 -> #REF! | O116: ='Imp Crude'!O97 -> #REF! | P116: ='Imp Crude'!P97 -> #REF! | Q116: ='Imp Crude'!Q97 -> #REF! | R116: ='Imp Crude'!R97 -> #REF! | S116: ='Imp Crude'!S97 -> #REF! | ... U116: ='Imp Crude'!U97 -> #REF! | X116: ='Imp Crude'!AE97 -> 0.57042296 | Y116: ='Imp Crude'!AF97 -> 0.30034515
B117: * | C117: ='Imp Crude'!B98 -> IMPOILHL42 | D117: ='Imp Crude'!C98 -> Imported Imported Oil-High Sulfur, Low G, PADD 4, Step 2 | E117: ='Imp Crude'!D98 -> OILHL4 | F117: 1 | J117: 1.005 | K117: 1.005 | L117: ='Imp Crude'!L98 -> 11.469501 | M117: ='Imp Crude'!M98 -> #REF! | N117: ='Imp Crude'!N98 -> #REF! | O117: ='Imp Crude'!O98 -> #REF! | P117: ='Imp Crude'!P98 -> #REF! | Q117: ='Imp Crude'!Q98 -> #REF! | R117: ='Imp Crude'!R98 -> #REF! | S117: ='Imp Crude'!S98 -> #REF! | ... U117: ='Imp Crude'!U98 -> #REF! | X117: ='Imp Crude'!AE98 -> 0.57042296 | Y117: ='Imp Crude'!AF98 -> 0.30034515
B118: * | C118: ='Imp Crude'!B99 -> IMPOILHL44 | D118: ='Imp Crude'!C99 -> Imported Imported Oil-High Sulfur, Low G, PADD 4, Step 4 | E118: ='Imp Crude'!D99 -> OILHL4 | F118: 1 | J118: 1.005 | K118: 1.005 | L118: ='Imp Crude'!L99 -> 12.676817 | M118: ='Imp Crude'!M99 -> #REF! | N118: ='Imp Crude'!N99 -> #REF! | O118: ='Imp Crude'!O99 -> #REF! | P118: ='Imp Crude'!P99 -> #REF! | Q118: ='Imp Crude'!Q99 -> #REF! | R118: ='Imp Crude'!R99 -> #REF! | S118: ='Imp Crude'!S99 -> #REF! | ... U118: ='Imp Crude'!U99 -> #REF! | X118: ='Imp Crude'!AE99 -> 1.1408459 | Y118: ='Imp Crude'!AF99 -> 0.6006903
B119: * | C119: ='Imp Crude'!B100 -> IMPOILHL45 | D119: ='Imp Crude'!C100 -> Imported Imported Oil-High Sulfur, Low G, PADD 4, Step 5 | E119: ='Imp Crude'!D100 -> OILHL4 | F119: 1 | J119: 1.005 | K119: 1.005 | L119: ='Imp Crude'!L100 -> 15.695106 | M119: ='Imp Crude'!M100 -> #REF! | N119: ='Imp Crude'!N100 -> #REF! | O119: ='Imp Crude'!O100 -> #REF! | P119: ='Imp Crude'!P100 -> #REF! | Q119: ='Imp Crude'!Q100 -> #REF! | R119: ='Imp Crude'!R100 -> #REF! | S119: ='Imp Crude'!S100 -> #REF! | ... U119: ='Imp Crude'!U100 -> #REF! | X119: ='Imp Crude'!AE100 -> 0.57042296 | Y119: ='Imp Crude'!AF100 -> 0.30034515
B120: * | C120: ='Imp Crude'!B101 -> IMPOILHV43 | D120: ='Imp Crude'!C101 -> Imported Imported Oil-High Sulfur, Very HG, PADD 4, Step 3 | E120: ='Imp Crude'!D101 -> OILHV4 | F120: 1 | J120: 1.005 | K120: 1.005 | L120: ='Imp Crude'!L101 -> 11.064306 | M120: ='Imp Crude'!M101 -> #REF! | N120: ='Imp Crude'!N101 -> #REF! | O120: ='Imp Crude'!O101 -> #REF! | P120: ='Imp Crude'!P101 -> #REF! | Q120: ='Imp Crude'!Q101 -> #REF! | R120: ='Imp Crude'!R101 -> #REF! | S120: ='Imp Crude'!S101 -> #REF! | ... U120: ='Imp Crude'!U101 -> #REF! | X120: ='Imp Crude'!AE101 -> 252.02916 | Y120: ='Imp Crude'!AF101 -> 215.65248
B121: * | C121: ='Imp Crude'!B102 -> IMPOILHV41 | D121: ='Imp Crude'!C102 -> Imported Imported Oil-High Sulfur, Very HG, PADD 4, Step 1 | E121: ='Imp Crude'!D102 -> OILHV4 | F121: 1 | J121: 1.005 | K121: 1.005 | L121: ='Imp Crude'!L102 -> 9.9578751 | M121: ='Imp Crude'!M102 -> #REF! | N121: ='Imp Crude'!N102 -> #REF! | O121: ='Imp Crude'!O102 -> #REF! | P121: ='Imp Crude'!P102 -> #REF! | Q121: ='Imp Crude'!Q102 -> #REF! | R121: ='Imp Crude'!R102 -> #REF! | S121: ='Imp Crude'!S102 -> #REF! | ... U121: ='Imp Crude'!U102 -> #REF! | X121: ='Imp Crude'!AE102 -> 31.503645 | Y121: ='Imp Crude'!AF102 -> 26.956559
... B134: * | C134: ='Imp Crude'!B115 -> IMPOILMH45 | D134: ='Imp Crude'!C115 -> Imported Imported Oil-Medium Sulfur, HG, PADD 4, Step 5 | E134: ='Imp Crude'!D115 -> OILMH4 | F134: 1 | J134: 1.005 | K134: 1.005 | L134: ='Imp Crude'!L115 -> 15.669306 | M134: ='Imp Crude'!M115 -> #REF! | N134: ='Imp Crude'!N115 -> #REF! | O134: ='Imp Crude'!O115 -> #REF! | P134: ='Imp Crude'!P115 -> #REF! | Q134: ='Imp Crude'!Q115 -> #REF! | R134: ='Imp Crude'!R115 -> #REF! | S134: ='Imp Crude'!S115 -> #REF! | ... U134: ='Imp Crude'!U115 -> #REF! | X134: ='Imp Crude'!AE115 -> 11.864798 | Y134: ='Imp Crude'!AF115 -> 5.8485816
B135: *
B136: * | C136: ='Imp Crude'!B117 -> IMPOILHH53 | D136: ='Imp Crude'!C117 -> Imported Imported Oil-High Sulfur, Heavy G, PADD 5, Step 3 | E136: ='Imp Crude'!D117 -> OILHH5 | F136: 1 | J136: 1.005 | K136: 1.005 | L136: ='Imp Crude'!L117 -> 11.163537 | M136: ='Imp Crude'!M117 -> #REF! | N136: ='Imp Crude'!N117 -> #REF! | O136: ='Imp Crude'!O117 -> #REF! | P136: ='Imp Crude'!P117 -> #REF! | Q136: ='Imp Crude'!Q117 -> #REF! | R136: ='Imp Crude'!R117 -> #REF! | S136: ='Imp Crude'!S117 -> #REF! | ... U136: ='Imp Crude'!U117 -> #REF! | X136: ='Imp Crude'!AE117 -> 627.38144 | Y136: ='Imp Crude'!AF117 -> 457.02753
B137: * | C137: ='Imp Crude'!B118 -> IMPOILHH51 | D137: ='Imp Crude'!C118 -> Imported Imported Oil-High Sulfur, Heavy G, PADD 5, Step 1 | E137: ='Imp Crude'!D118 -> OILHH5 | F137: 1 | J137: 1.005 | K137: 1.005 | L137: ='Imp Crude'!L118 -> 10.047183 | M137: ='Imp Crude'!M118 -> #REF! | N137: ='Imp Crude'!N118 -> #REF! | O137: ='Imp Crude'!O118 -> #REF! | P137: ='Imp Crude'!P118 -> #REF! | Q137: ='Imp Crude'!Q118 -> #REF! | R137: ='Imp Crude'!R118 -> #REF! | S137: ='Imp Crude'!S118 -> #REF! | ... U137: ='Imp Crude'!U118 -> #REF! | X137: ='Imp Crude'!AE118 -> 78.42268 | Y137: ='Imp Crude'!AF118 -> 57.128442
B138: * | C138: ='Imp Crude'!B119 -> IMPOILHH52 | D138: ='Imp Crude'!C119 -> Imported Imported Oil-High Sulfur, Heavy G, PADD 5, Step 2 | E138: ='Imp Crude'!D119 -> OILHH5 | F138: 1 | J138: 1.005 | K138: 1.005 | L138: ='Imp Crude'!L119 -> 10.60536 | M138: ='Imp Crude'!M119 -> #REF! | N138: ='Imp Crude'!N119 -> #REF! | O138: ='Imp Crude'!O119 -> #REF! | P138: ='Imp Crude'!P119 -> #REF! | Q138: ='Imp Crude'!Q119 -> #REF! | R138: ='Imp Crude'!R119 -> #REF! | S138: ='Imp Crude'!S119 -> #REF! | ... U138: ='Imp Crude'!U119 -> #REF! | X138: ='Imp Crude'!AE119 -> 78.42268 | Y138: ='Imp Crude'!AF119 -> 57.128442
B139: * | C139: ='Imp Crude'!B120 -> IMPOILHH54 | D139: ='Imp Crude'!C120 -> Imported Imported Oil-High Sulfur, Heavy G, PADD 5, Step 4 | E139: ='Imp Crude'!D120 -> OILHH5 | F139: 1 | J139: 1.005 | K139: 1.005 | L139: ='Imp Crude'!L120 -> 11.721714 | M139: ='Imp Crude'!M120 -> #REF! | N139: ='Imp Crude'!N120 -> #REF! | O139: ='Imp Crude'!O120 -> #REF! | P139: ='Imp Crude'!P120 -> #REF! | Q139: ='Imp Crude'!Q120 -> #REF! | R139: ='Imp Crude'!R120 -> #REF! | S139: ='Imp Crude'!S120 -> #REF! | ... U139: ='Imp Crude'!U120 -> #REF! | X139: ='Imp Crude'!AE120 -> 156.84536 | Y139: ='Imp Crude'!AF120 -> 114.25688
B140: * | C140: ='Imp Crude'!B121 -> IMPOILHH55 | D140: ='Imp Crude'!C121 -> Imported Imported Oil-High Sulfur, Heavy G, PADD 5, Step 5 | E140: ='Imp Crude'!D121 -> OILHH5 | F140: 1 | J140: 1.005 | K140: 1.005 | L140: ='Imp Crude'!L121 -> 14.512598 | M140: ='Imp Crude'!M121 -> #REF! | N140: ='Imp Crude'!N121 -> #REF! | O140: ='Imp Crude'!O121 -> #REF! | P140: ='Imp Crude'!P121 -> #REF! | Q140: ='Imp Crude'!Q121 -> #REF! | R140: ='Imp Crude'!R121 -> #REF! | S140: ='Imp Crude'!S121 -> #REF! | ... U140: ='Imp Crude'!U121 -> #REF! | X140: ='Imp Crude'!AE121 -> 78.42268 | Y140: ='Imp Crude'!AF121 -> 57.128442
B141: * | C141: ='Imp Crude'!B122 -> IMPOILHL53 | D141: ='Imp Crude'!C122 -> Imported Imported Oil-High Sulfur, Low G, PADD 5, Step 3 | E141: ='Imp Crude'!D122 -> OILHL5 | F141: 1 | J141: 1.005 | K141: 1.005 | L141: ='Imp Crude'!L122 -> 12.073159 | M141: ='Imp Crude'!M122 -> #REF! | N141: ='Imp Crude'!N122 -> #REF! | O141: ='Imp Crude'!O122 -> #REF! | P141: ='Imp Crude'!P122 -> #REF! | Q141: ='Imp Crude'!Q122 -> #REF! | R141: ='Imp Crude'!R122 -> #REF! | S141: ='Imp Crude'!S122 -> #REF! | ... U141: ='Imp Crude'!U122 -> #REF! | X141: ='Imp Crude'!AE122 -> 222.04121 | Y141: ='Imp Crude'!AF122 -> 381.20086
B142: * | C142: ='Imp Crude'!B123 -> IMPOILHL51 | D142: ='Imp Crude'!C123 -> Imported Imported Oil-High Sulfur, Low G, PADD 5, Step 1 | E142: ='Imp Crude'!D123 -> OILHL5 | F142: 1 | J142: 1.005 | K142: 1.005 | L142: ='Imp Crude'!L123 -> 10.865843 | M142: ='Imp Crude'!M123 -> #REF! | N142: ='Imp Crude'!N123 -> #REF! | O142: ='Imp Crude'!O123 -> #REF! | P142: ='Imp Crude'!P123 -> #REF! | Q142: ='Imp Crude'!Q123 -> #REF! | R142: ='Imp Crude'!R123 -> #REF! | S142: ='Imp Crude'!S123 -> #REF! | ... U142: ='Imp Crude'!U123 -> #REF! | X142: ='Imp Crude'!AE123 -> 27.755152 | Y142: ='Imp Crude'!AF123 -> 47.650108
B143: * | C143: ='Imp Crude'!B124 -> IMPOILHL52 | D143: ='Imp Crude'!C124 -> Imported Imported Oil-High Sulfur, Low G, PADD 5, Step 2 | E143: ='Imp Crude'!D124 -> OILHL5 | F143: 1 | J143: 1.005 | K143: 1.005 | L143: ='Imp Crude'!L124 -> 11.469501 | M143: ='Imp Crude'!M124 -> #REF! | N143: ='Imp Crude'!N124 -> #REF! | O143: ='Imp Crude'!O124 -> #REF! | P143: ='Imp Crude'!P124 -> #REF! | Q143: ='Imp Crude'!Q124 -> #REF! | R143: ='Imp Crude'!R124 -> #REF! | S143: ='Imp Crude'!S124 -> #REF! | ... U143: ='Imp Crude'!U124 -> #REF! | X143: ='Imp Crude'!AE124 -> 27.755152 | Y143: ='Imp Crude'!AF124 -> 47.650108
B144: * | C144: ='Imp Crude'!B125 -> IMPOILHL54 | D144: ='Imp Crude'!C125 -> Imported Imported Oil-High Sulfur, Low G, PADD 5, Step 4 | E144: ='Imp Crude'!D125 -> OILHL5 | F144: 1 | J144: 1.005 | K144: 1.005 | L144: ='Imp Crude'!L125 -> 12.676817 | M144: ='Imp Crude'!M125 -> #REF! | N144: ='Imp Crude'!N125 -> #REF! | O144: ='Imp Crude'!O125 -> #REF! | P144: ='Imp Crude'!P125 -> #REF! | Q144: ='Imp Crude'!Q125 -> #REF! | R144: ='Imp Crude'!R125 -> #REF! | S144: ='Imp Crude'!S125 -> #REF! | ... U144: ='Imp Crude'!U125 -> #REF! | X144: ='Imp Crude'!AE125 -> 55.510303 | Y144: ='Imp Crude'!AF125 -> 95.300215
B145: * | C145: ='Imp Crude'!B126 -> IMPOILHL55 | D145: ='Imp Crude'!C126 -> Imported Imported Oil-High Sulfur, Low G, PADD 5, Step 5 | E145: ='Imp Crude'!D126 -> OILHL5 | F145: 1 | J145: 1.005 | K145: 1.005 | L145: ='Imp Crude'!L126 -> 15.695106 | M145: ='Imp Crude'!M126 -> #REF! | N145: ='Imp Crude'!N126 -> #REF! | O145: ='Imp Crude'!O126 -> #REF! | P145: ='Imp Crude'!P126 -> #REF! | Q145: ='Imp Crude'!Q126 -> #REF! | R145: ='Imp Crude'!R126 -> #REF! | S145: ='Imp Crude'!S126 -> #REF! | ... U145: ='Imp Crude'!U126 -> #REF! | X145: ='Imp Crude'!AE126 -> 27.755152 | Y145: ='Imp Crude'!AF126 -> 47.650108
B146: * | C146: ='Imp Crude'!B127 -> IMPOILHV53 | D146: ='Imp Crude'!C127 -> Imported Imported Oil-High Sulfur, Very HG, PADD 5, Step 3 | E146: ='Imp Crude'!D127 -> OILHV5 | F146: 1 | J146: 1.005 | K146: 1.005 | L146: ='Imp Crude'!L127 -> 11.064306 | M146: ='Imp Crude'!M127 -> #REF! | N146: ='Imp Crude'!N127 -> #REF! | O146: ='Imp Crude'!O127 -> #REF! | P146: ='Imp Crude'!P127 -> #REF! | Q146: ='Imp Crude'!Q127 -> #REF! | R146: ='Imp Crude'!R127 -> #REF! | S146: ='Imp Crude'!S127 -> #REF! | ... U146: ='Imp Crude'!U127 -> #REF! | X146: ='Imp Crude'!AE127 -> 335.23175 | Y146: ='Imp Crude'!AF127 -> 345.08494
B147: * | C147: ='Imp Crude'!B128 -> IMPOILHV51 | D147: ='Imp Crude'!C128 -> Imported Imported Oil-High Sulfur, Very HG, PADD 5, Step 1 | E147: ='Imp Crude'!D128 -> OILHV5 | F147: 1 | J147: 1.005 | K147: 1.005 | L147: ='Imp Crude'!L128 -> 9.9578751 | M147: ='Imp Crude'!M128 -> #REF! | N147: ='Imp Crude'!N128 -> #REF! | O147: ='Imp Crude'!O128 -> #REF! | P147: ='Imp Crude'!P128 -> #REF! | Q147: ='Imp Crude'!Q128 -> #REF! | R147: ='Imp Crude'!R128 -> #REF! | S147: ='Imp Crude'!S128 -> #REF! | ... U147: ='Imp Crude'!U128 -> #REF! | X147: ='Imp Crude'!AE128 -> 41.903969 | Y147: ='Imp Crude'!AF128 -> 43.135617
... B160: * | C160: ='Imp Crude'!B141 -> IMPOILMH55 | D160: ='Imp Crude'!C141 -> Imported Imported Oil-Medium Sulfur, HG, PADD 5, Step 5 | E160: ='Imp Crude'!D141 -> OILMH5 | F160: 1 | J160: 1.005 | K160: 1.005 | L160: ='Imp Crude'!L141 -> 15.669306 | M160: ='Imp Crude'!M141 -> #REF! | N160: ='Imp Crude'!N141 -> #REF! | O160: ='Imp Crude'!O141 -> #REF! | P160: ='Imp Crude'!P141 -> #REF! | Q160: ='Imp Crude'!Q141 -> #REF! | R160: ='Imp Crude'!R141 -> #REF! | S160: ='Imp Crude'!S141 -> #REF! | ... U160: ='Imp Crude'!U141 -> #REF! | X160: ='Imp Crude'!AE141 -> 39.650217 | Y160: ='Imp Crude'!AF141 -> 28.62592
B165: Region | C165: TechName | D165: TechDesc | E165: CommIN | F165: CommOUT | G165: AFA | H165: EFF | I165: NCAP_TLIFE
B166: *Change names on Imported crude supply
B167: =Technologies!B155 -> R1 | C167: =Technologies!C155 -> XOILHH1 | D167: =Technologies!D155 -> Convert OILHH1 to OILIP1 | E167: =Commodities!C22 -> OILHH1 | F167: =Commodities!C17 -> OILIP1 | G167: 1 | H167: 1 | I167: 50
B168: =Technologies!B156 -> R1 | C168: =Technologies!C156 -> XOILHH2 | D168: =Technologies!D156 -> Convert OILHH2 to OILIP2 | E168: =Commodities!C23 -> OILHH2 | F168: =Commodities!C18 -> OILIP2 | G168: 1 | H168: 1 | I168: 50
B169: =Technologies!B157 -> R1 | C169: =Technologies!C157 -> XOILHH3 | D169: =Technologies!D157 -> Convert OILHH3 to OILIP3 | E169: =Commodities!C24 -> OILHH3 | F169: =Commodities!C19 -> OILIP3 | G169: 1 | H169: 1 | I169: 50
B170: =Technologies!B158 -> * | C170: =Technologies!C158 -> XOILHH4 | D170: =Technologies!D158 -> Convert OILHH4 to OILIP4 | E170: =Commodities!C25 -> OILHH4 | F170: =RIGHT(Technologies!D158,6) -> OILIP4 | G170: 1 | H170: 1 | I170: 50
B171: =Technologies!B159 -> * | C171: =Technologies!C159 -> XOILHH5 | D171: =Technologies!D159 -> Convert OILHH5 to OILIP5 | E171: =Commodities!C26 -> OILHH5 | F171: =RIGHT(Technologies!D159,6) -> OILIP5 | G171: 1 | H171: 1 | I171: 50
B172: =Technologies!B160 -> R1 | C172: =Technologies!C160 -> XOILHL1 | D172: =Technologies!D160 -> Convert OILHL1 to OILIP1 | E172: =Commodities!C27 -> OILHL1 | F172: =F167 -> OILIP1 | G172: 1 | H172: 1 | I172: 50
B173: =Technologies!B161 -> R1 | C173: =Technologies!C161 -> XOILHL2 | D173: =Technologies!D161 -> Convert OILHL2 to OILIP2 | E173: =Commodities!C28 -> OILHL2 | F173: =F168 -> OILIP2 | G173: 1 | H173: 1 | I173: 50
B174: =Technologies!B162 -> R1 | C174: =Technologies!C162 -> XOILHL3 | D174: =Technologies!D162 -> Convert OILHL3 to OILIP3 | E174: =Commodities!C29 -> OILHL3 | F174: =F169 -> OILIP3 | G174: 1 | H174: 1 | I174: 50
B175: =Technologies!B163 -> * | C175: =Technologies!C163 -> XOILHL4 | D175: =Technologies!D163 -> Convert OILHL4 to OILIP4 | E175: =Commodities!C30 -> OILHL4 | F175: =RIGHT(Technologies!D163,6) -> OILIP4 | G175: 1 | H175: 1 | I175: 50
B176: =Technologies!B164 -> * | C176: =Technologies!C164 -> XOILHL5 | D176: =Technologies!D164 -> Convert OILHL5 to OILIP5 | E176: =Commodities!C31 -> OILHL5 | F176: =RIGHT(Technologies!D164,6) -> OILIP5 | G176: 1 | H176: 1 | I176: 50
...

Sheet >> Not used

Sheet Commodities
B1: Commodities | C1: R0,R1,R2,R3,R4,R5,R6
B7: Region | C7: CommName | D7: CommDesc | E7: Unit | F7: Csets | G7: LimType | H7: CTSLvl | I7: PeakTS | J7: Ctype | O7: Comment
B8: * Crude Oil Supply Commodities - Domestic and Imported
B9: R0,R1 | C9: OIL | D9: Crude Oil-All Sources | E9: PJ | F9: NRG
B10: R1 | C10: OILD0 | D10: Domestic Crude Oil - 0 | E10: PJ
B11: R1 | C11: OILD1 | D11: Domestic Crude Oil - R1 | E11: PJ
B12: *R0,R1,R2,R3,R4,R5,R6 | C12: OILD2 | D12: Domestic Crude Oil - R2 | E12: PJ
B13: *R0,R1,R2,R3,R4,R5,R6 | C13: OILD3 | D13: Domestic Crude Oil - R3 | E13: PJ
B14: *R0,R1,R2,R3,R4,R5,R6 | C14: OILD4 | D14: Domestic Crude Oil - R4 | E14: PJ
B15: *R0,R1,R2,R3,R4,R5,R6 | C15: OILD5 | D15: Domestic Crude Oil - R5 | E15: PJ
B16: *R0,R1,R2,R3,R4,R5,R6 | C16: OILD6 | D16: Domestic Crude Oil - R6 | E16: PJ
B17: R1 | C17: OILIP1 | D17: =CONCATENATE("Imported Oil Supply - All types, ","PADD 1") -> Imported Oil Supply - All types, PADD 1 | E17: PJ
B18: R1 | C18: =SUBSTITUTE(C17,1,2) -> OILIP2 | D18: =SUBSTITUTE(D17,1,2) -> Imported Oil Supply - All types, PADD 2 | E18: PJ
B19: R1 | C19: =SUBSTITUTE(C18,2,3) -> OILIP3 | D19: =SUBSTITUTE(D18,2,3) -> Imported Oil Supply - All types, PADD 3 | E19: PJ
B20: *R0 | C20: =SUBSTITUTE(C19,3,4) -> OILIP4 | D20: =SUBSTITUTE(D19,3,4) -> Imported Oil Supply - All types, PADD 4 | E20: PJ
B21: *R0 | C21: =SUBSTITUTE(C20,4,5) -> OILIP5 | D21: =SUBSTITUTE(D20,4,5) -> Imported Oil Supply - All types, PADD 5 | E21: PJ
B22: R1 | C22: OILHH1 | D22: Imported Imported Oil-High Sulfur, Heavy G, PADD 1 | E22: PJ
B23: R1 | C23: OILHH2 | D23: Imported Imported Oil-High Sulfur, Heavy G, PADD 2 | E23: PJ
B24: R1 | C24: OILHH3 | D24: Imported Imported Oil-High Sulfur, Heavy G, PADD 3 | E24: PJ
B25: *R0 | C25: OILHH4 | D25: Imported Imported Oil-High Sulfur, Heavy G, PADD 4 | E25: PJ
B26: *R0 | C26: OILHH5 | D26: Imported Imported Oil-High Sulfur, Heavy G, PADD 5 | E26: PJ
B27: R1 | C27: OILHL1 | D27: Imported Imported Oil-High Sulfur, Low G, PADD 1 | E27: PJ
B28: R1 | C28: OILHL2 | D28: Imported Imported Oil-High Sulfur, Low G, PADD 2 | E28: PJ
B29: R1 | C29: OILHL3 | D29: Imported Imported Oil-High Sulfur, Low G, PADD 3 | E29: PJ
B30: *R0 | C30: OILHL4 | D30: Imported Imported Oil-High Sulfur, Low G, PADD 4 | E30: PJ
B31: *R0 | C31: OILHL5 | D31: Imported Imported Oil-High Sulfur, Low G, PADD 5 | E31: PJ
B32: R1 | C32: OILHV1 | D32: Imported Imported Oil-High Sulfur, Very HG, PADD 1 | E32: PJ
B33: R1 | C33: OILHV2 | D33: Imported Imported Oil-High Sulfur, Very HG, PADD 2 | E33: PJ
... B46: *R0 | C46: OILMH5 | D46: Imported Imported Oil-Medium Sulfur, HG, PADD 5 | E46: PJ
B47: * Refined Oil Product Commodities
B48: R0,R1,R2,R3,R4,R5,R6 | C48: GSC | D48: Conventional Gasoline | E48: PJ | F48: NRG
B49: R0,R1,R2,R3,R4,R5,R6 | C49: GSR | D49: Reformulated Gasoline | E49: PJ
B50: R1 | C50: DSH | D50: Distillate-Heating Oil No. 2 | E50: PJ
B51: R0,R1,R2,R3,R4,R5,R6 | C51: DSL | D51: Distillate-Low Sulfur Highway Diesel (500 ppm) | E51: PJ
B52: R0,R1,R2,R3,R4,R5,R6 | C52: DSU | D52: Distillate-Ultralow Sulfur Highway Diesel (15 ppm) | E52: PJ
B53: *R1,R2,R3,R4,R5,R6 | C53: JTF | D53: Jet Fuel | E53: PJ
B54: *R1,R2,R3,R4,R5,R6 | C54: KER | D54: Kerosene and Other Refined Products | E54: PJ
B55: *R1,R2,R3,R4,R5,R6 | C55: LPG | D55: LPG | E55: PJ
B56: *R1,R2,R3,R4,R5,R6 | C56: MTH | D56: Methanol | E56: PJ
B57: *R1,R2,R3,R4,R5,R6 | C57: PFS | D57: Petrochemical Feedstocks | E57: PJ
B58: *R1,R2,R3,R4,R5,R6 | C58: RFH | D58: High Sulfur Residual Fuel Oil | E58: PJ
B59: R0,R1,R2,R3,R4,R5,R6 | C59: RFL | D59: Low Sulfur Residual Fuel Oil | E59: PJ
B60: *R1,R2,R3,R4,R5,R6 | C60: ASP | D60: Asphalt | E60: PJ
... B62: *R1,R2,R3,R4,R5,R6 | C62: ETH | D62: Ethanol | E62: PJ
B63: * Imported Refined Oil Product Commodities (R0 to R1, NYC Regions 2-6 Import from R1)
B64: R0,R1,R2,R3,R4,R5,R6 | C64: =CONCATENATE(Types!B2,"P1") -> DSHP1 | D64: =CONCATENATE(Types!C2,", PADD 1") -> Distillate-Heating Oil No. 2, PADD 1 | F64: NRG
B65: R0,R1,R2,R3,R4,R5,R6 | C65: =CONCATENATE(Types!B3,"P1") -> DSLP1 | D65: =CONCATENATE(Types!C3,", PADD 1") -> Distillate-Low Sulfur Highway Diesel (500 ppm), PADD 1
B66: R0,R1,R2,R3,R4,R5,R6 | C66: =CONCATENATE(Types!B4,"P1") -> DSUP1 | D66: =CONCATENATE(Types!C4,", PADD 1") -> Distillate-Ultralow Sulfur Highway Diesel (15 ppm), PADD 1
B67: R0,R1,R2,R3,R4,R5,R6 | C67: =CONCATENATE(Types!B5,"P1") -> GSCP1 | D67: =CONCATENATE(Types!C5,", PADD 1") -> Conventional Gasoline, PADD 1
B68: R0,R1,R2,R3,R4,R5,R6 | C68: =CONCATENATE(Types!B6,"P1") -> GSRP1 | D68: =CONCATENATE(Types!C6,", PADD 1") -> Reformulated Gasoline, PADD 1
B69: =IF(OR(G$63="*",LEFT(B$53,1)="*"),"*R0,R1,R2,R3,R4,R5,R6","R0,R1,R2,R3,R4,R5,R6") -> *R0,R1,R2,R3,R4,R5,R6 | C69: =CONCATENATE(Types!B7,"P1") -> JTFP1 | D69: =CONCATENATE(Types!C7,", PADD 1") -> Jet Fuel, PADD 1
B70: =IF(OR(G$63="*",LEFT(B$54,1)="*"),"*R0,R1,R2,R3,R4,R5,R6","R0,R1,R2,R3,R4,R5,R6") -> *R0,R1,R2,R3,R4,R5,R6 | C70: =CONCATENATE(Types!B8,"P1") -> KERP1 | D70: =CONCATENATE(Types!C8,", PADD 1") -> Kerosene and Other Refined Products, PADD 1
B71: =IF(OR(G$63="*",LEFT(B$55,1)="*"),"*R0,R1,R2,R3,R4,R5,R6","R0,R1,R2,R3,R4,R5,R6") -> *R0,R1,R2,R3,R4,R5,R6 | C71: =CONCATENATE(Types!B9,"P1") -> LPGP1 | D71: =CONCATENATE(Types!C9,", PADD 1") -> LPG, PADD 1
B72: =IF(OR(G$63="*",LEFT(B$56,1)="*"),"*R0,R1,R2,R3,R4,R5,R6","R0,R1,R2,R3,R4,R5,R6") -> *R0,R1,R2,R3,R4,R5,R6 | C72: =CONCATENATE(Types!B10,"P1") -> MTHP1 | D72: =CONCATENATE(Types!C10,", PADD 1") -> Methanol, PADD 1
B73: =IF(OR(G$63="*",LEFT(B$57,1)="*"),"*R0,R1,R2,R3,R4,R5,R6","R0,R1,R2,R3,R4,R5,R6") -> *R0,R1,R2,R3,R4,R5,R6 | C73: =CONCATENATE(Types!B11,"P1") -> PFSP1 | D73: =CONCATENATE(Types!C11,", PADD 1") -> Petrochemical Feedstocks, PADD 1
B74: =IF(OR(G$63="*",LEFT(B$58,1)="*"),"*R0,R1,R2,R3,R4,R5,R6","R0,R1,R2,R3,R4,R5,R6") -> *R0,R1,R2,R3,R4,R5,R6 | C74: =CONCATENATE(Types!B12,"P1") -> RFHP1 | D74: =CONCATENATE(Types!C12,", PADD 1") -> High Sulfur Residual Fuel Oil, PADD 1
B75: =IF(OR(G$63="*",LEFT(B$59,1)="*"),"*R0,R1,R2,R3,R4,R5,R6","R0,R1,R2,R3,R4,R5,R6") -> R0,R1,R2,R3,R4,R5,R6 | C75: =CONCATENATE(Types!B13,"P1") -> RFLP1 | D75: =CONCATENATE(Types!C13,", PADD 1") -> Low Sulfur Residual Fuel Oil, PADD 1
B76: =IF(OR(G$63="*",LEFT(B$60,1)="*"),"*R0,R1,R2,R3,R4,R5,R6","R0,R1,R2,R3,R4,R5,R6") -> *R0,R1,R2,R3,R4,R5,R6 | C76: ASPP1 | D76: Ashpalt, PADD1
B77: R0,R1,R2,R3,R4,R5,R6 | C77: =CONCATENATE(Types!B2,"P2") -> DSHP2 | D77: =CONCATENATE(Types!C2,", PADD 2") -> Distillate-Heating Oil No. 2, PADD 2
B78: R0,R1,R2,R3,R4,R5,R6 | C78: =CONCATENATE(Types!B3,"P2") -> DSLP2 | D78: =CONCATENATE(Types!C3,", PADD 2") -> Distillate-Low Sulfur Highway Diesel (500 ppm), PADD 2
B79: R0,R1,R2,R3,R4,R5,R6 | C79: =CONCATENATE(Types!B4,"P2") -> DSUP2 | D79: =CONCATENATE(Types!C4,", PADD 2") -> Distillate-Ultralow Sulfur Highway Diesel (15 ppm), PADD 2
B80: R0,R1,R2,R3,R4,R5,R6 | C80: =CONCATENATE(Types!B5,"P2") -> GSCP2 | D80: =CONCATENATE(Types!C5,", PADD 2") -> Conventional Gasoline, PADD 2
B81: R0,R1,R2,R3,R4,R5,R6 | C81: =CONCATENATE(Types!B6,"P2") -> GSRP2 | D81: =CONCATENATE(Types!C6,", PADD 2") -> Reformulated Gasoline, PADD 2
B82: =IF(OR(G$63="*",LEFT(B$53,1)="*"),"*R0,R1,R2,R3,R4,R5,R6","R0,R1,R2,R3,R4,R5,R6") -> *R0,R1,R2,R3,R4,R5,R6 | C82: =CONCATENATE(Types!B7,"P2") -> JTFP2 | D82: =CONCATENATE(Types!C7,", PADD 2") -> Jet Fuel, PADD 2
B83: =IF(OR(G$63="*",LEFT(B$54,1)="*"),"*R0,R1,R2,R3,R4,R5,R6","R0,R1,R2,R3,R4,R5,R6") -> *R0,R1,R2,R3,R4,R5,R6 | C83: =CONCATENATE(Types!B8,"P2") -> KERP2 | D83: =CONCATENATE(Types!C8,", PADD 2") -> Kerosene and Other Refined Products, PADD 2
B84: =IF(OR(G$63="*",LEFT(B$55,1)="*"),"*R0,R1,R2,R3,R4,R5,R6","R0,R1,R2,R3,R4,R5,R6") -> *R0,R1,R2,R3,R4,R5,R6 | C84: =CONCATENATE(Types!B9,"P2") -> LPGP2 | D84: =CONCATENATE(Types!C9,", PADD 2") -> LPG, PADD 2
B85: =IF(OR(G$63="*",LEFT(B$56,1)="*"),"*R0,R1,R2,R3,R4,R5,R6","R0,R1,R2,R3,R4,R5,R6") -> *R0,R1,R2,R3,R4,R5,R6 | C85: =CONCATENATE(Types!B10,"P2") -> MTHP2 | D85: =CONCATENATE(Types!C10,", PADD 2") -> Methanol, PADD 2
B86: =IF(OR(G$63="*",LEFT(B$57,1)="*"),"*R0,R1,R2,R3,R4,R5,R6","R0,R1,R2,R3,R4,R5,R6") -> *R0,R1,R2,R3,R4,R5,R6 | C86: =CONCATENATE(Types!B11,"P2") -> PFSP2 | D86: =CONCATENATE(Types!C11,", PADD 2") -> Petrochemical Feedstocks, PADD 2
B87: =IF(OR(G$63="*",LEFT(B$58,1)="*"),"*R0,R1,R2,R3,R4,R5,R6","R0,R1,R2,R3,R4,R5,R6") -> *R0,R1,R2,R3,R4,R5,R6 | C87: =CONCATENATE(Types!B12,"P2") -> RFHP2 | D87: =CONCATENATE(Types!C12,", PADD 2") -> High Sulfur Residual Fuel Oil, PADD 2
B88: =IF(OR(G$63="*",LEFT(B$59,1)="*"),"*R0,R1,R2,R3,R4,R5,R6","R0,R1,R2,R3,R4,R5,R6") -> R0,R1,R2,R3,R4,R5,R6 | C88: =CONCATENATE(Types!B13,"P2") -> RFLP2 | D88: =CONCATENATE(Types!C13,", PADD 2") -> Low Sulfur Residual Fuel Oil, PADD 2
B89: =IF(OR(G$63="*",LEFT(B$60,1)="*"),"*R0,R1,R2,R3,R4,R5,R6","R0,R1,R2,R3,R4,R5,R6") -> *R0,R1,R2,R3,R4,R5,R6 | C89: ASPP2 | D89: Ashpalt, PADD2
B90: R0,R1,R2,R3,R4,R5,R6 | C90: =CONCATENATE(Types!B2,"P3") -> DSHP3 | D90: =CONCATENATE(Types!C2,", PADD 3") -> Distillate-Heating Oil No. 2, PADD 3
B91: R0,R1,R2,R3,R4,R5,R6 | C91: =CONCATENATE(Types!B3,"P3") -> DSLP3 | D91: =CONCATENATE(Types!C3,", PADD 3") -> Distillate-Low Sulfur Highway Diesel (500 ppm), PADD 3
B92: R0,R1,R2,R3,R4,R5,R6 | C92: =CONCATENATE(Types!B4,"P3") -> DSUP3 | D92: =CONCATENATE(Types!C4,", PADD 3") -> Distillate-Ultralow Sulfur Highway Diesel (15 ppm), PADD 3
B93: R0,R1,R2,R3,R4,R5,R6 | C93: =CONCATENATE(Types!B5,"P3") -> GSCP3 | D93: =CONCATENATE(Types!C5,", PADD 3") -> Conventional Gasoline, PADD 3
B94: R0,R1,R2,R3,R4,R5,R6 | C94: =CONCATENATE(Types!B6,"P3") -> GSRP3 | D94: =CONCATENATE(Types!C6,", PADD 3") -> Reformulated Gasoline, PADD 3
B95: =IF(OR(G$63="*",LEFT(B$53,1)="*"),"*R0,R1,R2,R3,R4,R5,R6","R0,R1,R2,R3,R4,R5,R6") -> *R0,R1,R2,R3,R4,R5,R6 | C95: =CONCATENATE(Types!B7,"P3") -> JTFP3 | D95: =CONCATENATE(Types!C7,", PADD 3") -> Jet Fuel, PADD 3
B96: =IF(OR(G$63="*",LEFT(B$54,1)="*"),"*R0,R1,R2,R3,R4,R5,R6","R0,R1,R2,R3,R4,R5,R6") -> *R0,R1,R2,R3,R4,R5,R6 | C96: =CONCATENATE(Types!B8,"P3") -> KERP3 | D96: =CONCATENATE(Types!C8,", PADD 3") -> Kerosene and Other Refined Products, PADD 3
B97: =IF(OR(G$63="*",LEFT(B$55,1)="*"),"*R0,R1,R2,R3,R4,R5,R6","R0,R1,R2,R3,R4,R5,R6") -> *R0,R1,R2,R3,R4,R5,R6 | C97: =CONCATENATE(Types!B9,"P3") -> LPGP3 | D97: =CONCATENATE(Types!C9,", PADD 3") -> LPG, PADD 3
B98: =IF(OR(G$63="*",LEFT(B$56,1)="*"),"*R0,R1,R2,R3,R4,R5,R6","R0,R1,R2,R3,R4,R5,R6") -> *R0,R1,R2,R3,R4,R5,R6 | C98: =CONCATENATE(Types!B10,"P3") -> MTHP3 | D98: =CONCATENATE(Types!C10,", PADD 3") -> Methanol, PADD 3
B99: =IF(OR(G$63="*",LEFT(B$57,1)="*"),"*R0,R1,R2,R3,R4,R5,R6","R0,R1,R2,R3,R4,R5,R6") -> *R0,R1,R2,R3,R4,R5,R6 | C99: =CONCATENATE(Types!B11,"P3") -> PFSP3 | D99: =CONCATENATE(Types!C11,", PADD 3") -> Petrochemical Feedstocks, PADD 3
B100: =IF(OR(G$63="*",LEFT(B$58,1)="*"),"*R0,R1,R2,R3,R4,R5,R6","R0,R1,R2,R3,R4,R5,R6") -> *R0,R1,R2,R3,R4,R5,R6 | C100: =CONCATENATE(Types!B12,"P3") -> RFHP3 | D100: =CONCATENATE(Types!C12,", PADD 3") -> High Sulfur Residual Fuel Oil, PADD 3
B101: =IF(OR(G$63="*",LEFT(B$59,1)="*"),"*R0,R1,R2,R3,R4,R5,R6","R0,R1,R2,R3,R4,R5,R6") -> R0,R1,R2,R3,R4,R5,R6 | C101: =CONCATENATE(Types!B13,"P3") -> RFLP3 | D101: =CONCATENATE(Types!C13,", PADD 3") -> Low Sulfur Residual Fuel Oil, PADD 3
B102: =IF(OR(G$63="*",LEFT(B$60,1)="*"),"*R0,R1,R2,R3,R4,R5,R6","R0,R1,R2,R3,R4,R5,R6") -> *R0,R1,R2,R3,R4,R5,R6 | C102: ASPP3 | D102: Ashpalt, PADD3
B103: * | C103: =CONCATENATE(Types!B2,"P4") -> DSHP4 | D103: =CONCATENATE(Types!C2,", PADD 4") -> Distillate-Heating Oil No. 2, PADD 4
B104: * | C104: =CONCATENATE(Types!B3,"P4") -> DSLP4 | D104: =CONCATENATE(Types!C3,", PADD 4") -> Distillate-Low Sulfur Highway Diesel (500 ppm), PADD 4
B105: * | C105: =CONCATENATE(Types!B4,"P4") -> DSUP4 | D105: =CONCATENATE(Types!C4,", PADD 4") -> Distillate-Ultralow Sulfur Highway Diesel (15 ppm), PADD 4
B106: * | C106: =CONCATENATE(Types!B5,"P4") -> GSCP4 | D106: =CONCATENATE(Types!C5,", PADD 4") -> Conventional Gasoline, PADD 4
B107: * | C107: =CONCATENATE(Types!B6,"P4") -> GSRP4 | D107: =CONCATENATE(Types!C6,", PADD 4") -> Reformulated Gasoline, PADD 4
B108: * | C108: =CONCATENATE(Types!B7,"P4") -> JTFP4 | D108: =CONCATENATE(Types!C7,", PADD 4") -> Jet Fuel, PADD 4
B109: * | C109: =CONCATENATE(Types!B8,"P4") -> KERP4 | D109: =CONCATENATE(Types!C8,", PADD 4") -> Kerosene and Other Refined Products, PADD 4
B110: * | C110: =CONCATENATE(Types!B9,"P4") -> LPGP4 | D110: =CONCATENATE(Types!C9,", PADD 4") -> LPG, PADD 4
B111: * | C111: =CONCATENATE(Types!B10,"P4") -> MTHP4 | D111: =CONCATENATE(Types!C10,", PADD 4") -> Methanol, PADD 4
B112: * | C112: =CONCATENATE(Types!B11,"P4") -> PFSP4 | D112: =CONCATENATE(Types!C11,", PADD 4") -> Petrochemical Feedstocks, PADD 4
B113: * | C113: =CONCATENATE(Types!B12,"P4") -> RFHP4 | D113: =CONCATENATE(Types!C12,", PADD 4") -> High Sulfur Residual Fuel Oil, PADD 4
B114: * | C114: =CONCATENATE(Types!B13,"P4") -> RFLP4 | D114: =CONCATENATE(Types!C13,", PADD 4") -> Low Sulfur Residual Fuel Oil, PADD 4
B115: * | C115: ASPP4 | D115: Ashpalt, PADD4
B116: * | C116: =CONCATENATE(Types!B2,"P5") -> DSHP5 | D116: =CONCATENATE(Types!C2,", PADD 5") -> Distillate-Heating Oil No. 2, PADD 5
B117: * | C117: =CONCATENATE(Types!B3,"P5") -> DSLP5 | D117: =CONCATENATE(Types!C3,", PADD 5") -> Distillate-Low Sulfur Highway Diesel (500 ppm), PADD 5
B118: * | C118: =CONCATENATE(Types!B4,"P5") -> DSUP5 | D118: =CONCATENATE(Types!C4,", PADD 5") -> Distillate-Ultralow Sulfur Highway Diesel (15 ppm), PADD 5
...

Sheet Technologies
B1: Technologies | C1: R0,R1,R2,R3,R4,R5,R6
B7: Region | C7: TechName | D7: TechDesc | E7: Tact | F7: Tcap | G7: Sets | H7: PrimaryCG | I7: Vintage | O7: Comment
B8: *Domestic oil supply and transport technologies
B9: =IF(LEFT(Commodities!B$10,1)="*","*R1","R1") -> R1 | C9: MINOILD1 | D9: Domestic crude oil - step 1 | E9: PJ | F9: PJ/a | G9: MIN
B10: =IF(LEFT(Commodities!B$10,1)="*","*R1","R1") -> R1 | C10: MINOILD2 | D10: Domestic crude oil - step 2 | E10: PJ | F10: PJ/a
B11: =IF(LEFT(Commodities!B$10,1)="*","*R1","R1") -> R1 | C11: MINOILD3 | D11: Domestic crude oil - step 3 | E11: PJ | F11: PJ/a
B12: =IF(LEFT(Commodities!B$10,1)="*","*R1","R1") -> R1 | C12: MINOILD4 | D12: Domestic crude oil - step 4 | E12: PJ | F12: PJ/a
B13: =IF(LEFT(Commodities!B$10,1)="*","*R1","R1") -> R1 | C13: MINOILD5 | D13: Domestic crude oil - step 5 | E13: PJ | F13: PJ/a
B14: * | C14: MINOILD6 | D14: Domestic crude oil - step 6 | E14: PJ | F14: PJ/a
B15: * | C15: MINOILD7 | D15: Domestic crude oil - step 7 | E15: PJ | F15: PJ/a
B16: * | C16: MINOILD8 | D16: Domestic crude oil - step 8 | E16: PJ | F16: PJ/a
B17: * | C17: MINOILD9 | D17: Domestic crude oil - step 9 | E17: PJ | F17: PJ/a
B18: =IF(LEFT(Commodities!B$10,1)="*","*R1","R1") -> R1 | C18: SCMINOILD | D18: Collector: MINOILD | E18: PJ | F18: PJ/a | G18: PRE
B19: =IF(LEFT(Commodities!B$10,1)="*","*R1","R1") -> R1 | C19: XOILD1 | D19: Domestic crude delivery charge from R1 | E19: PJ | F19: PJ/a
B20: *R3 | C20: XOILD3 | D20: Domestic crude delivery charge from R3 | E20: PJ | F20: PJ/a
B21: *R4 | C21: XOILD4 | D21: Domestic crude delivery charge from R4 | E21: PJ | F21: PJ/a
B22: *R5 | C22: XOILD5 | D22: Domestic crude delivery charge from R5 | E22: PJ | F22: PJ/a
B23: *R6 | C23: XOILD6 | D23: Domestic crude delivery charge from R6 | E23: PJ | F23: PJ/a
B24: *Imported crude supply from PADDs
B25: R1 | C25: =TechData_R0!C32 -> IMPOILHH13 | D25: =TechData_R0!D32 -> Imported Imported Oil-High Sulfur, Heavy G, PADD 1, Step 3 | E25: PJ | F25: PJ/a | G25: IMP
B26: R1 | C26: =TechData_R0!C33 -> IMPOILHH11 | D26: =TechData_R0!D33 -> Imported Imported Oil-High Sulfur, Heavy G, PADD 1, Step 1 | E26: PJ | F26: PJ/a
B27: R1 | C27: =TechData_R0!C34 -> IMPOILHH12 | D27: =TechData_R0!D34 -> Imported Imported Oil-High Sulfur, Heavy G, PADD 1, Step 2 | E27: PJ | F27: PJ/a
B28: R1 | C28: =TechData_R0!C35 -> IMPOILHH14 | D28: =TechData_R0!D35 -> Imported Imported Oil-High Sulfur, Heavy G, PADD 1, Step 4 | E28: PJ | F28: PJ/a
B29: R1 | C29: =TechData_R0!C36 -> IMPOILHH15 | D29: =TechData_R0!D36 -> Imported Imported Oil-High Sulfur, Heavy G, PADD 1, Step 5 | E29: PJ | F29: PJ/a
B30: R1 | C30: =TechData_R0!C37 -> IMPOILHL13 | D30: =TechData_R0!D37 -> Imported Imported Oil-High Sulfur, Low G, PADD 1, Step 3 | E30: PJ | F30: PJ/a
B31: R1 | C31: =TechData_R0!C38 -> IMPOILHL11 | D31: =TechData_R0!D38 -> Imported Imported Oil-High Sulfur, Low G, PADD 1, Step 1 | E31: PJ | F31: PJ/a
B32: R1 | C32: =TechData_R0!C39 -> IMPOILHL12 | D32: =TechData_R0!D39 -> Imported Imported Oil-High Sulfur, Low G, PADD 1, Step 2 | E32: PJ | F32: PJ/a
B33: R1 | C33: =TechData_R0!C40 -> IMPOILHL14 | D33: =TechData_R0!D40 -> Imported Imported Oil-High Sulfur, Low G, PADD 1, Step 4 | E33: PJ | F33: PJ/a
B34: R1 | C34: =TechData_R0!C41 -> IMPOILHL15 | D34: =TechData_R0!D41 -> Imported Imported Oil-High Sulfur, Low G, PADD 1, Step 5 | E34: PJ | F34: PJ/a
B35: R1 | C35: =TechData_R0!C42 -> IMPOILHV13 | D35: =TechData_R0!D42 -> Imported Imported Oil-High Sulfur, Very HG, PADD 1, Step 3 | E35: PJ | F35: PJ/a
B36: R1 | C36: =TechData_R0!C43 -> IMPOILHV11 | D36: =TechData_R0!D43 -> Imported Imported Oil-High Sulfur, Very HG, PADD 1, Step 1 | E36: PJ | F36: PJ/a
B37: R1 | C37: =TechData_R0!C44 -> IMPOILHV12 | D37: =TechData_R0!D44 -> Imported Imported Oil-High Sulfur, Very HG, PADD 1, Step 2 | E37: PJ | F37: PJ/a
... B49: R1 | C49: =TechData_R0!C56 -> IMPOILMH15 | D49: =TechData_R0!D56 -> Imported Imported Oil-Medium Sulfur, HG, PADD 1, Step 5 | E49: PJ | F49: PJ/a
B50: *
B51: R1 | C51: =TechData_R0!C58 -> IMPOILHH23 | D51: =TechData_R0!D58 -> Imported Imported Oil-High Sulfur, Heavy G, PADD 2, Step 3 | E51: PJ | F51: PJ/a
B52: R1 | C52: =TechData_R0!C59 -> IMPOILHH21 | D52: =TechData_R0!D59 -> Imported Imported Oil-High Sulfur, Heavy G, PADD 2, Step 1 | E52: PJ | F52: PJ/a
B53: R1 | C53: =TechData_R0!C60 -> IMPOILHH22 | D53: =TechData_R0!D60 -> Imported Imported Oil-High Sulfur, Heavy G, PADD 2, Step 2 | E53: PJ | F53: PJ/a
B54: R1 | C54: =TechData_R0!C61 -> IMPOILHH24 | D54: =TechData_R0!D61 -> Imported Imported Oil-High Sulfur, Heavy G, PADD 2, Step 4 | E54: PJ | F54: PJ/a
B55: R1 | C55: =TechData_R0!C62 -> IMPOILHH25 | D55: =TechData_R0!D62 -> Imported Imported Oil-High Sulfur, Heavy G, PADD 2, Step 5 | E55: PJ | F55: PJ/a
B56: R1 | C56: =TechData_R0!C63 -> IMPOILHL23 | D56: =TechData_R0!D63 -> Imported Imported Oil-High Sulfur, Low G, PADD 2, Step 3 | E56: PJ | F56: PJ/a
B57: R1 | C57: =TechData_R0!C64 -> IMPOILHL21 | D57: =TechData_R0!D64 -> Imported Imported Oil-High Sulfur, Low G, PADD 2, Step 1 | E57: PJ | F57: PJ/a
B58: R1 | C58: =TechData_R0!C65 -> IMPOILHL22 | D58: =TechData_R0!D65 -> Imported Imported Oil-High Sulfur, Low G, PADD 2, Step 2 | E58: PJ | F58: PJ/a
B59: R1 | C59: =TechData_R0!C66 -> IMPOILHL24 | D59: =TechData_R0!D66 -> Imported Imported Oil-High Sulfur, Low G, PADD 2, Step 4 | E59: PJ | F59: PJ/a
B60: R1 | C60: =TechData_R0!C67 -> IMPOILHL25 | D60: =TechData_R0!D67 -> Imported Imported Oil-High Sulfur, Low G, PADD 2, Step 5 | E60: PJ | F60: PJ/a
B61: R1 | C61: =TechData_R0!C68 -> IMPOILHV23 | D61: =TechData_R0!D68 -> Imported Imported Oil-High Sulfur, Very HG, PADD 2, Step 3 | E61: PJ | F61: PJ/a
B62: R1 | C62: =TechData_R0!C69 -> IMPOILHV21 | D62: =TechData_R0!D69 -> Imported Imported Oil-High Sulfur, Very HG, PADD 2, Step 1 | E62: PJ | F62: PJ/a
... B75: R1 | C75: =TechData_R0!C82 -> IMPOILMH25 | D75: =TechData_R0!D82 -> Imported Imported Oil-Medium Sulfur, HG, PADD 2, Step 5 | E75: PJ | F75: PJ/a
B76: *
B77: R1 | C77: =TechData_R0!C84 -> IMPOILHH33 | D77: =TechData_R0!D84 -> Imported Imported Oil-High Sulfur, Heavy G, PADD 3, Step 3 | E77: PJ | F77: PJ/a
B78: R1 | C78: =TechData_R0!C85 -> IMPOILHH31 | D78: =TechData_R0!D85 -> Imported Imported Oil-High Sulfur, Heavy G, PADD 3, Step 1 | E78: PJ | F78: PJ/a
B79: R1 | C79: =TechData_R0!C86 -> IMPOILHH32 | D79: =TechData_R0!D86 -> Imported Imported Oil-High Sulfur, Heavy G, PADD 3, Step 2 | E79: PJ | F79: PJ/a
B80: R1 | C80: =TechData_R0!C87 -> IMPOILHH34 | D80: =TechData_R0!D87 -> Imported Imported Oil-High Sulfur, Heavy G, PADD 3, Step 4 | E80: PJ | F80: PJ/a
B81: R1 | C81: =TechData_R0!C88 -> IMPOILHH35 | D81: =TechData_R0!D88 -> Imported Imported Oil-High Sulfur, Heavy G, PADD 3, Step 5 | E81: PJ | F81: PJ/a
B82: R1 | C82: =TechData_R0!C89 -> IMPOILHL33 | D82: =TechData_R0!D89 -> Imported Imported Oil-High Sulfur, Low G, PADD 3, Step 3 | E82: PJ | F82: PJ/a
B83: R1 | C83: =TechData_R0!C90 -> IMPOILHL31 | D83: =TechData_R0!D90 -> Imported Imported Oil-High Sulfur, Low G, PADD 3, Step 1 | E83: PJ | F83: PJ/a
B84: R1 | C84: =TechData_R0!C91 -> IMPOILHL32 | D84: =TechData_R0!D91 -> Imported Imported Oil-High Sulfur, Low G, PADD 3, Step 2 | E84: PJ | F84: PJ/a
B85: R1 | C85: =TechData_R0!C92 -> IMPOILHL34 | D85: =TechData_R0!D92 -> Imported Imported Oil-High Sulfur, Low G, PADD 3, Step 4 | E85: PJ | F85: PJ/a
B86: R1 | C86: =TechData_R0!C93 -> IMPOILHL35 | D86: =TechData_R0!D93 -> Imported Imported Oil-High Sulfur, Low G, PADD 3, Step 5 | E86: PJ | F86: PJ/a
B87: R1 | C87: =TechData_R0!C94 -> IMPOILHV33 | D87: =TechData_R0!D94 -> Imported Imported Oil-High Sulfur, Very HG, PADD 3, Step 3 | E87: PJ | F87: PJ/a
B88: R1 | C88: =TechData_R0!C95 -> IMPOILHV31 | D88: =TechData_R0!D95 -> Imported Imported Oil-High Sulfur, Very HG, PADD 3, Step 1 | E88: PJ | F88: PJ/a
... B101: R1 | C101: =TechData_R0!C108 -> IMPOILMH35 | D101: =TechData_R0!D108 -> Imported Imported Oil-Medium Sulfur, HG, PADD 3, Step 5 | E101: PJ | F101: PJ/a
B102: *
B103: *R0 | C103: =TechData_R0!C110 -> IMPOILHH43 | D103: =TechData_R0!D110 -> Imported Imported Oil-High Sulfur, Heavy G, PADD 4, Step 3 | E103: PJ | F103: PJ/a
B104: *R0 | C104: =TechData_R0!C111 -> IMPOILHH41 | D104: =TechData_R0!D111 -> Imported Imported Oil-High Sulfur, Heavy G, PADD 4, Step 1 | E104: PJ | F104: PJ/a
B105: *R0 | C105: =TechData_R0!C112 -> IMPOILHH42 | D105: =TechData_R0!D112 -> Imported Imported Oil-High Sulfur, Heavy G, PADD 4, Step 2 | E105: PJ | F105: PJ/a
B106: *R0 | C106: =TechData_R0!C113 -> IMPOILHH44 | D106: =TechData_R0!D113 -> Imported Imported Oil-High Sulfur, Heavy G, PADD 4, Step 4 | E106: PJ | F106: PJ/a
B107: *R0 | C107: =TechData_R0!C114 -> IMPOILHH45 | D107: =TechData_R0!D114 -> Imported Imported Oil-High Sulfur, Heavy G, PADD 4, Step 5 | E107: PJ | F107: PJ/a
B108: *R0 | C108: =TechData_R0!C115 -> IMPOILHL43 | D108: =TechData_R0!D115 -> Imported Imported Oil-High Sulfur, Low G, PADD 4, Step 3 | E108: PJ | F108: PJ/a
B109: *R0 | C109: =TechData_R0!C116 -> IMPOILHL41 | D109: =TechData_R0!D116 -> Imported Imported Oil-High Sulfur, Low G, PADD 4, Step 1 | E109: PJ | F109: PJ/a
B110: *R0 | C110: =TechData_R0!C117 -> IMPOILHL42 | D110: =TechData_R0!D117 -> Imported Imported Oil-High Sulfur, Low G, PADD 4, Step 2 | E110: PJ | F110: PJ/a
B111: *R0 | C111: =TechData_R0!C118 -> IMPOILHL44 | D111: =TechData_R0!D118 -> Imported Imported Oil-High Sulfur, Low G, PADD 4, Step 4 | E111: PJ | F111: PJ/a
B112: *R0 | C112: =TechData_R0!C119 -> IMPOILHL45 | D112: =TechData_R0!D119 -> Imported Imported Oil-High Sulfur, Low G, PADD 4, Step 5 | E112: PJ | F112: PJ/a
B113: *R0 | C113: =TechData_R0!C120 -> IMPOILHV43 | D113: =TechData_R0!D120 -> Imported Imported Oil-High Sulfur, Very HG, PADD 4, Step 3 | E113: PJ | F113: PJ/a
B114: *R0 | C114: =TechData_R0!C121 -> IMPOILHV41 | D114: =TechData_R0!D121 -> Imported Imported Oil-High Sulfur, Very HG, PADD 4, Step 1 | E114: PJ | F114: PJ/a
... B127: *R0 | C127: =TechData_R0!C134 -> IMPOILMH45 | D127: =TechData_R0!D134 -> Imported Imported Oil-Medium Sulfur, HG, PADD 4, Step 5 | E127: PJ | F127: PJ/a
B128: *
B129: *R0 | C129: =TechData_R0!C136 -> IMPOILHH53 | D129: =TechData_R0!D136 -> Imported Imported Oil-High Sulfur, Heavy G, PADD 5, Step 3 | E129: PJ | F129: PJ/a
B130: *R0 | C130: =TechData_R0!C137 -> IMPOILHH51 | D130: =TechData_R0!D137 -> Imported Imported Oil-High Sulfur, Heavy G, PADD 5, Step 1 | E130: PJ | F130: PJ/a
B131: *R0 | C131: =TechData_R0!C138 -> IMPOILHH52 | D131: =TechData_R0!D138 -> Imported Imported Oil-High Sulfur, Heavy G, PADD 5, Step 2 | E131: PJ | F131: PJ/a
B132: *R0 | C132: =TechData_R0!C139 -> IMPOILHH54 | D132: =TechData_R0!D139 -> Imported Imported Oil-High Sulfur, Heavy G, PADD 5, Step 4 | E132: PJ | F132: PJ/a
B133: *R0 | C133: =TechData_R0!C140 -> IMPOILHH55 | D133: =TechData_R0!D140 -> Imported Imported Oil-High Sulfur, Heavy G, PADD 5, Step 5 | E133: PJ | F133: PJ/a
B134: *R0 | C134: =TechData_R0!C141 -> IMPOILHL53 | D134: =TechData_R0!D141 -> Imported Imported Oil-High Sulfur, Low G, PADD 5, Step 3 | E134: PJ | F134: PJ/a
B135: *R0 | C135: =TechData_R0!C142 -> IMPOILHL51 | D135: =TechData_R0!D142 -> Imported Imported Oil-High Sulfur, Low G, PADD 5, Step 1 | E135: PJ | F135: PJ/a
B136: *R0 | C136: =TechData_R0!C143 -> IMPOILHL52 | D136: =TechData_R0!D143 -> Imported Imported Oil-High Sulfur, Low G, PADD 5, Step 2 | E136: PJ | F136: PJ/a
B137: *R0 | C137: =TechData_R0!C144 -> IMPOILHL54 | D137: =TechData_R0!D144 -> Imported Imported Oil-High Sulfur, Low G, PADD 5, Step 4 | E137: PJ | F137: PJ/a
B138: *R0 | C138: =TechData_R0!C145 -> IMPOILHL55 | D138: =TechData_R0!D145 -> Imported Imported Oil-High Sulfur, Low G, PADD 5, Step 5 | E138: PJ | F138: PJ/a
B139: *R0 | C139: =TechData_R0!C146 -> IMPOILHV53 | D139: =TechData_R0!D146 -> Imported Imported Oil-High Sulfur, Very HG, PADD 5, Step 3 | E139: PJ | F139: PJ/a
B140: *R0 | C140: =TechData_R0!C147 -> IMPOILHV51 | D140: =TechData_R0!D147 -> Imported Imported Oil-High Sulfur, Very HG, PADD 5, Step 1 | E140: PJ | F140: PJ/a
... B153: *R0 | C153: =TechData_R0!C160 -> IMPOILMH55 | D153: =TechData_R0!D160 -> Imported Imported Oil-Medium Sulfur, HG, PADD 5, Step 5 | E153: PJ | F153: PJ/a
B154: *Change names on Imported crude supply
B155: =IF(LEFT(Commodities!B17,1)="*","*R1","R1") -> R1 | C155: =CONCATENATE("X",Commodities!C22) -> XOILHH1 | D155: =CONCATENATE("Convert ",Commodities!C22," to OILIP",RIGHT(Commodities!C22)) -> Convert OILHH1 to OILIP1 | E155: PJ | F155: PJ/a | G155: PRE
B156: =IF(LEFT(Commodities!B18,1)="*","*R1","R1") -> R1 | C156: =CONCATENATE("X",Commodities!C23) -> XOILHH2 | D156: =CONCATENATE("Convert ",Commodities!C23," to OILIP",RIGHT(Commodities!C23)) -> Convert OILHH2 to OILIP2 | E156: PJ | F156: PJ/a
B157: =IF(LEFT(Commodities!B19,1)="*","*R1","R1") -> R1 | C157: =CONCATENATE("X",Commodities!C24) -> XOILHH3 | D157: =CONCATENATE("Convert ",Commodities!C24," to OILIP",RIGHT(Commodities!C24)) -> Convert OILHH3 to OILIP3 | E157: PJ | F157: PJ/a
B158: * | C158: =CONCATENATE("X",Commodities!C25) -> XOILHH4 | D158: =CONCATENATE("Convert ",Commodities!C25," to OILIP",RIGHT(Commodities!C25)) -> Convert OILHH4 to OILIP4 | E158: PJ | F158: PJ/a
B159: * | C159: =CONCATENATE("X",Commodities!C26) -> XOILHH5 | D159: =CONCATENATE("Convert ",Commodities!C26," to OILIP",RIGHT(Commodities!C26)) -> Convert OILHH5 to OILIP5 | E159: PJ | F159: PJ/a
B160: =IF(LEFT(Commodities!B22,1)="*","*R1","R1") -> R1 | C160: =CONCATENATE("X",Commodities!C27) -> XOILHL1 | D160: =CONCATENATE("Convert ",Commodities!C27," to OILIP",RIGHT(Commodities!C27)) -> Convert OILHL1 to OILIP1 | E160: PJ | F160: PJ/a
B161: =IF(LEFT(Commodities!B23,1)="*","*R1","R1") -> R1 | C161: =CONCATENATE("X",Commodities!C28) -> XOILHL2 | D161: =CONCATENATE("Convert ",Commodities!C28," to OILIP",RIGHT(Commodities!C28)) -> Convert OILHL2 to OILIP2 | E161: PJ | F161: PJ/a
B162: =IF(LEFT(Commodities!B24,1)="*","*R1","R1") -> R1 | C162: =CONCATENATE("X",Commodities!C29) -> XOILHL3 | D162: =CONCATENATE("Convert ",Commodities!C29," to OILIP",RIGHT(Commodities!C29)) -> Convert OILHL3 to OILIP3 | E162: PJ | F162: PJ/a
B163: * | C163: =CONCATENATE("X",Commodities!C30) -> XOILHL4 | D163: =CONCATENATE("Convert ",Commodities!C30," to OILIP",RIGHT(Commodities!C30)) -> Convert OILHL4 to OILIP4 | E163: PJ | F163: PJ/a
B164: * | C164: =CONCATENATE("X",Commodities!C31) -> XOILHL5 | D164: =CONCATENATE("Convert ",Commodities!C31," to OILIP",RIGHT(Commodities!C31)) -> Convert OILHL5 to OILIP5 | E164: PJ | F164: PJ/a
...

Sheet TechData_DelOILNYC
B1: TechData | C1: R0,R1,R2,R3,R4,R5,R6
B5: Region | C5: TechName | D5: TechDesc | E5: CommIN | F5: CommOUT | G5: EFF | H5: NCAP_FOM~2010 | I5: NCAP_FOM~2015 | J5: NCAP_FOM~2020 | K5: NCAP_FOM~2025 | L5: NCAP_FOM~2030 | M5: NCAP_FOM~2035 | N5: NCAP_FOM~2040 | O5: NCAP_FOM~2045 | P5: NCAP_FOM~2050 | Q5: NCAP_FOM~2055
B6: *Domestic crude delivery to refineries in PADD
B7: =Technologies!B19 -> R1 | C7: =Technologies!C19 -> XOILD1 | D7: =Technologies!D19 -> Domestic crude delivery charge from R1 | E7: =Commodities!C11 -> OILD1 | F7: =Commodities!$C$9 -> OIL | G7: 1 | H7: =#REF!*#REF!^5/(Conv!$I$5*Conv!$D$46)/10^6 -> #REF! | I7: =#REF!*#REF!^5/(Conv!$I$5*Conv!$D$46)/10^6 -> #REF! | J7: =#REF!*#REF!^5/(Conv!$I$5*Conv!$D$46)/10^6 -> #REF! | K7: =#REF!*#REF!^5/(Conv!$I$5*Conv!$D$46)/10^6 -> #REF! | L7: =#REF!*#REF!^5/(Conv!$I$5*Conv!$D$46)/10^6 -> #REF! | M7: =#REF!*#REF!^5/(Conv!$I$5*Conv!$D$46)/10^6 -> #REF! | N7: =#REF!*#REF!^5/(Conv!$I$5*Conv!$D$46)/10^6 -> #REF! | O7: =#REF!*#REF!^5/(Conv!$I$5*Conv!$D$46)/10^6 -> #REF! | ... Q7: =#REF!*#REF!^5/(Conv!$I$5*Conv!$D$46)/10^6 -> #REF!
B8: =Technologies!B20 -> *R3 | C8: =Technologies!C20 -> XOILD3 | D8: =Technologies!D20 -> Domestic crude delivery charge from R3 | E8: =Commodities!C13 -> OILD3 | F8: =Commodities!$C$9 -> OIL | G8: 1 | H8: =#REF!*#REF!^5/(Conv!$I$5*Conv!$D$46)/10^6 -> #REF! | I8: =#REF!*#REF!^5/(Conv!$I$5*Conv!$D$46)/10^6 -> #REF! | J8: =#REF!*#REF!^5/(Conv!$I$5*Conv!$D$46)/10^6 -> #REF! | K8: =#REF!*#REF!^5/(Conv!$I$5*Conv!$D$46)/10^6 -> #REF! | L8: =#REF!*#REF!^5/(Conv!$I$5*Conv!$D$46)/10^6 -> #REF! | M8: =#REF!*#REF!^5/(Conv!$I$5*Conv!$D$46)/10^6 -> #REF! | N8: =#REF!*#REF!^5/(Conv!$I$5*Conv!$D$46)/10^6 -> #REF! | O8: =#REF!*#REF!^5/(Conv!$I$5*Conv!$D$46)/10^6 -> #REF! | ... Q8: =#REF!*#REF!^5/(Conv!$I$5*Conv!$D$46)/10^6 -> #REF!
B9: =Technologies!B21 -> *R4 | C9: =Technologies!C21 -> XOILD4 | D9: =Technologies!D21 -> Domestic crude delivery charge from R4 | E9: =Commodities!C14 -> OILD4 | F9: =Commodities!$C$9 -> OIL | G9: 1 | H9: =H8 -> #REF! | I9: =I8 -> #REF! | J9: =J8 -> #REF! | K9: =K8 -> #REF! | L9: =L8 -> #REF! | M9: =M8 -> #REF! | N9: =N8 -> #REF! | O9: =O8 -> #REF! | ... Q9: =Q8 -> #REF!
B10: =Technologies!B22 -> *R5 | C10: =Technologies!C22 -> XOILD5 | D10: =Technologies!D22 -> Domestic crude delivery charge from R5 | E10: =Commodities!C15 -> OILD5 | F10: =Commodities!$C$9 -> OIL | G10: 1 | H10: =H7 -> #REF! | I10: =I7 -> #REF! | J10: =J7 -> #REF! | K10: =K7 -> #REF! | L10: =L7 -> #REF! | M10: =M7 -> #REF! | N10: =N7 -> #REF! | O10: =O7 -> #REF! | ... Q10: =Q7 -> #REF!
B11: =Technologies!B23 -> *R6 | C11: =Technologies!C23 -> XOILD6 | D11: =Technologies!D23 -> Domestic crude delivery charge from R6 | E11: =Commodities!C16 -> OILD6 | F11: =Commodities!$C$9 -> OIL | G11: 1 | H11: =#REF!*#REF!^5/(Conv!$I$5*Conv!$D$46)/10^6 -> #REF! | I11: =#REF!*#REF!^5/(Conv!$I$5*Conv!$D$46)/10^6 -> #REF! | J11: =#REF!*#REF!^5/(Conv!$I$5*Conv!$D$46)/10^6 -> #REF! | K11: =#REF!*#REF!^5/(Conv!$I$5*Conv!$D$46)/10^6 -> #REF! | L11: =#REF!*#REF!^5/(Conv!$I$5*Conv!$D$46)/10^6 -> #REF! | M11: =#REF!*#REF!^5/(Conv!$I$5*Conv!$D$46)/10^6 -> #REF! | N11: =#REF!*#REF!^5/(Conv!$I$5*Conv!$D$46)/10^6 -> #REF! | O11: =#REF!*#REF!^5/(Conv!$I$5*Conv!$D$46)/10^6 -> #REF! | ... Q11: =#REF!*#REF!^5/(Conv!$I$5*Conv!$D$46)/10^6 -> #REF!
B15: Region | C15: TechName | D15: TechDesc | E15: CommIN | F15: CommOUT | G15: EFF | H15: NCAP_FOM~2010 | I15: NCAP_FOM~2015 | J15: NCAP_FOM~2020 | K15: NCAP_FOM~2025 | L15: NCAP_FOM~2030 | M15: NCAP_FOM~2035 | N15: NCAP_FOM~2040 | O15: NCAP_FOM~2045 | P15: NCAP_FOM~2050 | Q15: NCAP_FOM~2055
B16: *Imported crude delivery to refineries in PADD
B17: =Technologies!$B181 -> R1 | C17: =Technologies!$C181 -> XOILIP1 | D17: =Technologies!$D181 -> Imported crude delivery charge from PADD 1 | E17: =Commodities!C17 -> OILIP1 | F17: =Commodities!$C$9 -> OIL | G17: 1 | H17: =H7+2.5 -> #REF! | I17: =I7+2.5 -> #REF! | J17: =J7+2.5 -> #REF! | K17: =K7+2.5 -> #REF! | L17: =L7+2.5 -> #REF! | M17: =M7+2.5 -> #REF! | N17: =N7+2.5 -> #REF! | O17: =O7+2.5 -> #REF! | ... Q17: =Q7+2.5 -> #REF!
B18: =Technologies!$B182 -> R1 | C18: =Technologies!$C182 -> XOILIP2 | D18: =Technologies!$D182 -> Imported crude delivery charge from PADD 2 | E18: =Commodities!C18 -> OILIP2 | F18: =Commodities!$C$9 -> OIL | G18: 1 | H18: =H8+2.5 -> #REF! | I18: =I8+2.5 -> #REF! | J18: =J8+2.5 -> #REF! | K18: =K8+2.5 -> #REF! | L18: =L8+2.5 -> #REF! | M18: =M8+2.5 -> #REF! | N18: =N8+2.5 -> #REF! | O18: =O8+2.5 -> #REF! | ... Q18: =Q8+2.5 -> #REF!
B19: =Technologies!$B183 -> R1 | C19: =Technologies!$C183 -> XOILIP3 | D19: =Technologies!$D183 -> Imported crude delivery charge from PADD 3 | E19: =Commodities!C19 -> OILIP3 | F19: =Commodities!$C$9 -> OIL | G19: 1 | H19: =H9+2.5 -> #REF! | I19: =I9+2.5 -> #REF! | J19: =J9+2.5 -> #REF! | K19: =K9+2.5 -> #REF! | L19: =L9+2.5 -> #REF! | M19: =M9+2.5 -> #REF! | N19: =N9+2.5 -> #REF! | O19: =O9+2.5 -> #REF! | ... Q19: =Q9+2.5 -> #REF!
B20: =Technologies!$B184 -> * | C20: =Technologies!$C184 -> XOILIP4 | D20: =Technologies!$D184 -> Imported crude delivery charge from PADD 4 | E20: =Commodities!C20 -> OILIP4 | F20: =Commodities!$C$9 -> OIL | G20: 1 | H20: =H10+2.5 -> #REF! | I20: =I10+2.5 -> #REF! | J20: =J10+2.5 -> #REF! | K20: =K10+2.5 -> #REF! | L20: =L10+2.5 -> #REF! | M20: =M10+2.5 -> #REF! | N20: =N10+2.5 -> #REF! | O20: =O10+2.5 -> #REF! | ... Q20: =Q10+2.5 -> #REF!
B21: =Technologies!$B185 -> *
B25: Region | C25: TechName | D25: TechDesc | E25: CommIN | F25: CommOUT | G25: EFF | H25: NCAP_FOM~2010 | I25: NCAP_FOM~2015 | J25: NCAP_FOM~2020 | K25: NCAP_FOM~2025 | L25: NCAP_FOM~2030 | M25: NCAP_FOM~2035 | N25: NCAP_FOM~2040 | O25: NCAP_FOM~2045 | P25: NCAP_FOM~2050 | Q25: NCAP_FOM~2055
B26: R1 | C26: ="X"&E26 -> XGSC | D26: ="Convert "&E26&" to "&F26 -> Convert GSC to GSCR1 | E26: =Commodities!C48 -> GSC | F26: =E26&"R1" -> GSCR1 | G26: 1
B27: R1 | C27: ="X"&E27 -> XGSR | D27: ="Convert "&E27&" to "&F27 -> Convert GSR to GSRR1 | E27: =Commodities!C49 -> GSR | F27: =E27&"R1" -> GSRR1 | G27: 1
B28: R1 | C28: ="X"&E28 -> XDSH | D28: ="Convert "&E28&" to "&F28 -> Convert DSH to DSHR1 | E28: =Commodities!C50 -> DSH | F28: =E28&"R1" -> DSHR1 | G28: 1
B29: R1 | C29: ="X"&E29 -> XDSL | D29: ="Convert "&E29&" to "&F29 -> Convert DSL to DSLR1 | E29: =Commodities!C51 -> DSL | F29: =E29&"R1" -> DSLR1 | G29: 1
B30: R1 | C30: ="X"&E30 -> XDSU | D30: ="Convert "&E30&" to "&F30 -> Convert DSU to DSUR1 | E30: =Commodities!C52 -> DSU | F30: =E30&"R1" -> DSUR1 | G30: 1
B31: R1 | C31: ="X"&E31 -> XRFL | D31: ="Convert "&E31&" to "&F31 -> Convert RFL to RFLR1 | E31: =Commodities!C59 -> RFL | F31: =E31&"R1" -> RFLR1 | G31: 1
B36: Region | C36: TechName | D36: TechDesc | E36: CommIN | F36: CommOUT | G36: EFF | H36: NCAP_FOM~2010 | I36: NCAP_FOM~2015 | J36: NCAP_FOM~2020 | K36: NCAP_FOM~2025 | L36: NCAP_FOM~2030 | M36: NCAP_FOM~2035 | N36: NCAP_FOM~2040 | O36: NCAP_FOM~2045 | P36: NCAP_FOM~2050 | Q36: NCAP_FOM~2055
B37: * Trade Pipeline Products delivery to End-Use demands
B38: =IF(LEFT(Technologies!B$585,1)="*","*R2","R2") -> R2 | C38: =Technologies!C$585 -> #REF! | D38: =Technologies!D$585 -> #REF! | E38: =Commodities!C$130 -> GSCR1 | F38: =Commodities!C$222 -> #REF! | G38: 1 | H38: =H168 -> #REF! | I38: =I168 -> #REF! | J38: =J168 -> #REF! | K38: =K168 -> #REF! | L38: =L168 -> #REF! | M38: =M168 -> #REF! | N38: =N168 -> #REF! | O38: =O168 -> #REF! | ... Q38: =Q168 -> #REF!
B39: =IF(LEFT(Technologies!B$586,1)="*","*R2","R2") -> R2 | C39: =Technologies!C$586 -> #REF! | D39: =Technologies!D$586 -> #REF! | E39: =Commodities!C$131 -> GSRR1 | F39: =Commodities!C$223 -> #REF! | G39: 1 | H39: =H169 -> #REF! | I39: =I169 -> #REF! | J39: =J169 -> #REF! | K39: =K169 -> #REF! | L39: =L169 -> #REF! | M39: =M169 -> #REF! | N39: =N169 -> #REF! | O39: =O169 -> #REF! | ... Q39: =Q169 -> #REF!
B40: =IF(LEFT(Technologies!B$587,1)="*","*R2","R2") -> R2 | C40: =Technologies!C$587 -> #REF! | D40: =Technologies!D$587 -> #REF! | E40: =Commodities!C$132 -> DSHR1 | F40: =Commodities!C$224 -> #REF! | G40: 1 | H40: =H170 -> #REF! | I40: =I170 -> #REF! | J40: =J170 -> #REF! | K40: =K170 -> #REF! | L40: =L170 -> #REF! | M40: =M170 -> #REF! | N40: =N170 -> #REF! | O40: =O170 -> #REF! | ... Q40: =Q170 -> #REF!
B41: =IF(LEFT(Technologies!B$588,1)="*","*R2","R2") -> R2 | C41: =Technologies!C$588 -> #REF! | D41: =Technologies!D$588 -> #REF! | E41: =Commodities!C$132 -> DSHR1 | F41: =Commodities!C$225 -> #REF! | G41: 1 | H41: =H171 -> #REF! | I41: =I171 -> #REF! | J41: =J171 -> #REF! | K41: =K171 -> #REF! | L41: =L171 -> #REF! | M41: =M171 -> #REF! | N41: =N171 -> #REF! | O41: =O171 -> #REF! | ... Q41: =Q171 -> #REF!
B42: =IF(LEFT(Technologies!B$589,1)="*","*R2","R2") -> *R2 | C42: =Technologies!C$589 -> #REF! | D42: =Technologies!D$589 -> #REF! | E42: =Commodities!C$132 -> DSHR1 | F42: =Commodities!C$226 -> #REF! | G42: 1 | H42: =H172 -> #REF! | I42: =I172 -> #REF! | J42: =J172 -> #REF! | K42: =K172 -> #REF! | L42: =L172 -> #REF! | M42: =M172 -> #REF! | N42: =N172 -> #REF! | O42: =O172 -> #REF! | ... Q42: =Q172 -> #REF!
B43: =IF(LEFT(Technologies!B$590,1)="*","*R2","R2") -> R2 | C43: =Technologies!C$590 -> #REF! | D43: =Technologies!D$590 -> #REF! | E43: =Commodities!C$132 -> DSHR1 | F43: =Commodities!C$227 -> #REF! | G43: 1 | H43: =H173 -> #REF! | I43: =I173 -> #REF! | J43: =J173 -> #REF! | K43: =K173 -> #REF! | L43: =L173 -> #REF! | M43: =M173 -> #REF! | N43: =N173 -> #REF! | O43: =O173 -> #REF! | ... Q43: =Q173 -> #REF!
B44: =IF(LEFT(Technologies!B$591,1)="*","*R2","R2") -> R2 | C44: =Technologies!C$591 -> #REF! | D44: =Technologies!D$591 -> #REF! | E44: =Commodities!C$133 -> DSLR1 | F44: =Commodities!C$228 -> #REF! | G44: 1 | H44: =H174 -> #REF! | I44: =I174 -> #REF! | J44: =J174 -> #REF! | K44: =K174 -> #REF! | L44: =L174 -> #REF! | M44: =M174 -> #REF! | N44: =N174 -> #REF! | O44: =O174 -> #REF! | ... Q44: =Q174 -> #REF!
B45: =IF(LEFT(Technologies!B$592,1)="*","*R2","R2") -> R2 | C45: =Technologies!C$592 -> #REF! | D45: =Technologies!D$592 -> #REF! | E45: =Commodities!C$134 -> DSUR1 | F45: =Commodities!C$229 -> #REF! | G45: 1 | H45: =H175 -> #REF! | I45: =I175 -> #REF! | J45: =J175 -> #REF! | K45: =K175 -> #REF! | L45: =L175 -> #REF! | M45: =M175 -> #REF! | N45: =N175 -> #REF! | O45: =O175 -> #REF! | ... Q45: =Q175 -> #REF!
B46: =IF(LEFT(Technologies!B$593,1)="*","*R2","R2") -> *R2 | C46: =Technologies!C$593 -> #REF! | D46: =Technologies!D$593 -> #REF! | E46: =Commodities!C$135 -> JTFR1 | F46: =Commodities!C$230 -> #REF! | G46: 1 | H46: =H176 -> #REF! | I46: =I176 -> #REF! | J46: =J176 -> #REF! | K46: =K176 -> #REF! | L46: =L176 -> #REF! | M46: =M176 -> #REF! | N46: =N176 -> #REF! | O46: =O176 -> #REF! | ... Q46: =Q176 -> #REF!
B47: =IF(LEFT(Technologies!B$594,1)="*","*R2","R2") -> *R2 | C47: =Technologies!C$594 -> #REF! | D47: =Technologies!D$594 -> #REF! | E47: =Commodities!C$136 -> KERR1 | F47: =Commodities!C$231 -> #REF! | G47: 1 | H47: =H177 -> #REF! | I47: =I177 -> #REF! | J47: =J177 -> #REF! | K47: =K177 -> #REF! | L47: =L177 -> #REF! | M47: =M177 -> #REF! | N47: =N177 -> #REF! | O47: =O177 -> #REF! | ... Q47: =Q177 -> #REF!
B48: =IF(LEFT(Technologies!B$595,1)="*","*R2","R2") -> *R2 | C48: =Technologies!C$595 -> #REF! | D48: =Technologies!D$595 -> #REF! | E48: =Commodities!C$136 -> KERR1 | F48: =Commodities!C$232 -> #REF! | G48: 1 | H48: =H178 -> #REF! | I48: =I178 -> #REF! | J48: =J178 -> #REF! | K48: =K178 -> #REF! | L48: =L178 -> #REF! | M48: =M178 -> #REF! | N48: =N178 -> #REF! | O48: =O178 -> #REF! | ... Q48: =Q178 -> #REF!
B49: =IF(LEFT(Technologies!B$596,1)="*","*R2","R2") -> *R2 | C49: =Technologies!C$596 -> #REF! | D49: =Technologies!D$596 -> #REF! | E49: =Commodities!C$136 -> KERR1 | F49: =Commodities!C$233 -> #REF! | G49: 1 | H49: =H179 -> #REF! | I49: =I179 -> #REF! | J49: =J179 -> #REF! | K49: =K179 -> #REF! | L49: =L179 -> #REF! | M49: =M179 -> #REF! | N49: =N179 -> #REF! | O49: =O179 -> #REF! | ... Q49: =Q179 -> #REF!
B50: =IF(LEFT(Technologies!B$597,1)="*","*R2","R2") -> *R2 | C50: =Technologies!C$597 -> #REF! | D50: =Technologies!D$597 -> #REF! | E50: =Commodities!C$137 -> LPGR1 | F50: =Commodities!C$234 -> #REF! | G50: 1 | H50: =H180 -> #REF! | I50: =I180 -> #REF! | J50: =J180 -> #REF! | K50: =K180 -> #REF! | L50: =L180 -> #REF! | M50: =M180 -> #REF! | N50: =N180 -> #REF! | O50: =O180 -> #REF! | ... Q50: =Q180 -> #REF!
B51: =IF(LEFT(Technologies!B$598,1)="*","*R2","R2") -> *R2 | C51: =Technologies!C$598 -> #REF! | D51: =Technologies!D$598 -> #REF! | E51: =Commodities!C$137 -> LPGR1 | F51: =Commodities!C$235 -> #REF! | G51: 1 | H51: =H181 -> #REF! | I51: =I181 -> #REF! | J51: =J181 -> #REF! | K51: =K181 -> #REF! | L51: =L181 -> #REF! | M51: =M181 -> #REF! | N51: =N181 -> #REF! | O51: =O181 -> #REF! | ... Q51: =Q181 -> #REF!
B52: =IF(LEFT(Technologies!B$599,1)="*","*R2","R2") -> *R2 | C52: =Technologies!C$599 -> #REF! | D52: =Technologies!D$599 -> #REF! | E52: =Commodities!C$137 -> LPGR1 | F52: =Commodities!C$236 -> #REF! | G52: 1 | H52: =H182 -> #REF! | I52: =I182 -> #REF! | J52: =J182 -> #REF! | K52: =K182 -> #REF! | L52: =L182 -> #REF! | M52: =M182 -> #REF! | N52: =N182 -> #REF! | O52: =O182 -> #REF! | ... Q52: =Q182 -> #REF!
B53: =IF(LEFT(Technologies!B$600,1)="*","*R2","R2") -> *R2 | C53: =Technologies!C$600 -> #REF! | D53: =Technologies!D$600 -> #REF! | E53: =Commodities!C$137 -> LPGR1 | F53: =Commodities!C$237 -> #REF! | G53: 1 | H53: =H183 -> #REF! | I53: =I183 -> #REF! | J53: =J183 -> #REF! | K53: =K183 -> #REF! | L53: =L183 -> #REF! | M53: =M183 -> #REF! | N53: =N183 -> #REF! | O53: =O183 -> #REF! | ... Q53: =Q183 -> #REF!
B54: =IF(LEFT(Technologies!B$601,1)="*","*R2","R2") -> *R2 | C54: =Technologies!C$601 -> #REF! | D54: =Technologies!D$601 -> #REF! | E54: =Commodities!C$138 -> MTHR1 | F54: =Commodities!C$238 -> #REF! | G54: 1 | H54: =H184 -> #REF! | I54: =I184 -> #REF! | J54: =J184 -> #REF! | K54: =K184 -> #REF! | L54: =L184 -> #REF! | M54: =M184 -> #REF! | N54: =N184 -> #REF! | O54: =O184 -> #REF! | ... Q54: =Q184 -> #REF!
B55: =IF(LEFT(Technologies!B$602,1)="*","*R2","R2") -> *R2 | C55: =Technologies!C$602 -> #REF! | D55: =Technologies!D$602 -> #REF! | E55: =Commodities!C$139 -> PFSR1 | F55: =Commodities!C$239 -> #REF! | G55: 1 | H55: =H185 -> #REF! | I55: =I185 -> #REF! | J55: =J185 -> #REF! | K55: =K185 -> #REF! | L55: =L185 -> #REF! | M55: =M185 -> #REF! | N55: =N185 -> #REF! | O55: =O185 -> #REF! | ... Q55: =Q185 -> #REF!
B56: =IF(LEFT(Technologies!B$603,1)="*","*R2","R2") -> *R2 | C56: =Technologies!C$603 -> #REF! | D56: =Technologies!D$603 -> #REF! | E56: =Commodities!C$141 -> RFLR1 | F56: =Commodities!C$240 -> RESRFL | G56: 1 | H56: =H186 -> #REF! | I56: =I186 -> #REF! | J56: =J186 -> #REF! | K56: =K186 -> #REF! | L56: =L186 -> #REF! | M56: =M186 -> #REF! | N56: =N186 -> #REF! | O56: =O186 -> #REF! | ... Q56: =Q186 -> #REF!
B57: =IF(LEFT(Technologies!B$604,1)="*","*R2","R2") -> *R2 | C57: =Technologies!C$604 -> #REF! | D57: =Technologies!D$604 -> #REF! | E57: =Commodities!C$141 -> RFLR1 | F57: =Commodities!C$241 -> #REF! | G57: 1 | H57: =H187 -> #REF! | I57: =I187 -> #REF! | J57: =J187 -> #REF! | K57: =K187 -> #REF! | L57: =L187 -> #REF! | M57: =M187 -> #REF! | N57: =N187 -> #REF! | O57: =O187 -> #REF! | ... Q57: =Q187 -> #REF!
B58: =IF(LEFT(Technologies!B$605,1)="*","*R2","R2") -> R2 | C58: =Technologies!C$605 -> #REF! | D58: =Technologies!D$605 -> #REF! | E58: =Commodities!C$141 -> RFLR1 | F58: =Commodities!C$242 -> #REF! | G58: 1 | H58: =H188 -> #REF! | I58: =I188 -> #REF! | J58: =J188 -> #REF! | K58: =K188 -> #REF! | L58: =L188 -> #REF! | M58: =M188 -> #REF! | N58: =N188 -> #REF! | O58: =O188 -> #REF! | ... Q58: =Q188 -> #REF!
B59: =IF(LEFT(Technologies!B$606,1)="*","*R2","R2") -> *R2 | C59: =Technologies!C$606 -> #REF! | D59: =Technologies!D$606 -> #REF! | E59: =Commodities!C$141 -> RFLR1 | F59: =Commodities!C$243 -> #REF! | G59: 1 | H59: =H189 -> #REF! | I59: =I189 -> #REF! | J59: =J189 -> #REF! | K59: =K189 -> #REF! | L59: =L189 -> #REF! | M59: =M189 -> #REF! | N59: =N189 -> #REF! | O59: =O189 -> #REF! | ... Q59: =Q189 -> #REF!
B60: =IF(LEFT(Technologies!B$607,1)="*","*R2","R2") -> *R2 | C60: =Technologies!C$607 -> #REF! | D60: =Technologies!D$607 -> #REF! | E60: =Commodities!C$140 -> RFHR1 | F60: =Commodities!C$244 -> #REF! | G60: 1 | H60: =H190 -> #REF! | I60: =I190 -> #REF! | J60: =J190 -> #REF! | K60: =K190 -> #REF! | L60: =L190 -> #REF! | M60: =M190 -> #REF! | N60: =N190 -> #REF! | O60: =O190 -> #REF! | ... Q60: =Q190 -> #REF!
B61: =IF(LEFT(Technologies!B$608,1)="*","*R2","R2") -> *R2 | C61: =Technologies!C$608 -> #REF! | D61: =Technologies!D$608 -> #REF! | E61: =Commodities!C$140 -> RFHR1 | F61: =Commodities!C$245 -> #REF! | G61: 1 | H61: =H191 -> #REF! | I61: =I191 -> #REF! | J61: =J191 -> #REF! | K61: =K191 -> #REF! | L61: =L191 -> #REF! | M61: =M191 -> #REF! | N61: =N191 -> #REF! | O61: =O191 -> #REF! | ... Q61: =Q191 -> #REF!
B62: =IF(LEFT(Technologies!B$609,1)="*","*R2","R2") -> *R2 | C62: =Technologies!C$609 -> #REF! | D62: =Technologies!D$609 -> #REF! | E62: =Commodities!C$142 -> ASPR1 | F62: =Commodities!C$246 -> #REF! | G62: 1 | H62: =H192 -> #REF! | I62: =I192 -> #REF! | J62: =J192 -> #REF! | K62: =K192 -> #REF! | L62: =L192 -> #REF! | M62: =M192 -> #REF! | N62: =N192 -> #REF! | O62: =O192 -> #REF! | ... Q62: =Q192 -> #REF!
B63: *
B64: =IF(LEFT(Technologies!B$585,1)="*","*R3","R3") -> R3 | C64: =Technologies!C$585 -> #REF! | D64: =Technologies!D$585 -> #REF! | E64: =Commodities!C$130 -> GSCR1 | F64: =Commodities!C$222 -> #REF! | G64: 1 | H64: =H38 -> #REF! | I64: =I38 -> #REF! | J64: =J38 -> #REF! | K64: =K38 -> #REF! | L64: =L38 -> #REF! | M64: =M38 -> #REF! | N64: =N38 -> #REF! | O64: =O38 -> #REF! | ... Q64: =Q38 -> #REF!
B65: =IF(LEFT(Technologies!B$586,1)="*","*R3","R3") -> R3 | C65: =Technologies!C$586 -> #REF! | D65: =Technologies!D$586 -> #REF! | E65: =Commodities!C$131 -> GSRR1 | F65: =Commodities!C$223 -> #REF! | G65: 1 | H65: =H39 -> #REF! | I65: =I39 -> #REF! | J65: =J39 -> #REF! | K65: =K39 -> #REF! | L65: =L39 -> #REF! | M65: =M39 -> #REF! | N65: =N39 -> #REF! | O65: =O39 -> #REF! | ... Q65: =Q39 -> #REF!
B66: =IF(LEFT(Technologies!B$587,1)="*","*R3","R3") -> R3 | C66: =Technologies!C$587 -> #REF! | D66: =Technologies!D$587 -> #REF! | E66: =Commodities!C$132 -> DSHR1 | F66: =Commodities!C$224 -> #REF! | G66: 1 | H66: =H40 -> #REF! | I66: =I40 -> #REF! | J66: =J40 -> #REF! | K66: =K40 -> #REF! | L66: =L40 -> #REF! | M66: =M40 -> #REF! | N66: =N40 -> #REF! | O66: =O40 -> #REF! | ... Q66: =Q40 -> #REF!
B67: =IF(LEFT(Technologies!B$588,1)="*","*R3","R3") -> R3 | C67: =Technologies!C$588 -> #REF! | D67: =Technologies!D$588 -> #REF! | E67: =Commodities!C$132 -> DSHR1 | F67: =Commodities!C$225 -> #REF! | G67: 1 | H67: =H41 -> #REF! | I67: =I41 -> #REF! | J67: =J41 -> #REF! | K67: =K41 -> #REF! | L67: =L41 -> #REF! | M67: =M41 -> #REF! | N67: =N41 -> #REF! | O67: =O41 -> #REF! | ... Q67: =Q41 -> #REF!
B68: =IF(LEFT(Technologies!B$589,1)="*","*R3","R3") -> *R3 | C68: =Technologies!C$589 -> #REF! | D68: =Technologies!D$589 -> #REF! | E68: =Commodities!C$132 -> DSHR1 | F68: =Commodities!C$226 -> #REF! | G68: 1 | H68: =H42 -> #REF! | I68: =I42 -> #REF! | J68: =J42 -> #REF! | K68: =K42 -> #REF! | L68: =L42 -> #REF! | M68: =M42 -> #REF! | N68: =N42 -> #REF! | O68: =O42 -> #REF! | ... Q68: =Q42 -> #REF!
B69: =IF(LEFT(Technologies!B$590,1)="*","*R3","R3") -> R3 | C69: =Technologies!C$590 -> #REF! | D69: =Technologies!D$590 -> #REF! | E69: =Commodities!C$132 -> DSHR1 | F69: =Commodities!C$227 -> #REF! | G69: 1 | H69: =H43 -> #REF! | I69: =I43 -> #REF! | J69: =J43 -> #REF! | K69: =K43 -> #REF! | L69: =L43 -> #REF! | M69: =M43 -> #REF! | N69: =N43 -> #REF! | O69: =O43 -> #REF! | ... Q69: =Q43 -> #REF!
B70: =IF(LEFT(Technologies!B$591,1)="*","*R3","R3") -> R3 | C70: =Technologies!C$591 -> #REF! | D70: =Technologies!D$591 -> #REF! | E70: =Commodities!C$133 -> DSLR1 | F70: =Commodities!C$228 -> #REF! | G70: 1 | H70: =H44 -> #REF! | I70: =I44 -> #REF! | J70: =J44 -> #REF! | K70: =K44 -> #REF! | L70: =L44 -> #REF! | M70: =M44 -> #REF! | N70: =N44 -> #REF! | O70: =O44 -> #REF! | ... Q70: =Q44 -> #REF!
B71: =IF(LEFT(Technologies!B$592,1)="*","*R3","R3") -> R3 | C71: =Technologies!C$592 -> #REF! | D71: =Technologies!D$592 -> #REF! | E71: =Commodities!C$134 -> DSUR1 | F71: =Commodities!C$229 -> #REF! | G71: 1 | H71: =H45 -> #REF! | I71: =I45 -> #REF! | J71: =J45 -> #REF! | K71: =K45 -> #REF! | L71: =L45 -> #REF! | M71: =M45 -> #REF! | N71: =N45 -> #REF! | O71: =O45 -> #REF! | ... Q71: =Q45 -> #REF!
B72: =IF(LEFT(Technologies!B$593,1)="*","*R3","R3") -> *R3 | C72: =Technologies!C$593 -> #REF! | D72: =Technologies!D$593 -> #REF! | E72: =Commodities!C$135 -> JTFR1 | F72: =Commodities!C$230 -> #REF! | G72: 1 | H72: =H46 -> #REF! | I72: =I46 -> #REF! | J72: =J46 -> #REF! | K72: =K46 -> #REF! | L72: =L46 -> #REF! | M72: =M46 -> #REF! | N72: =N46 -> #REF! | O72: =O46 -> #REF! | ... Q72: =Q46 -> #REF!
B73: =IF(LEFT(Technologies!B$594,1)="*","*R3","R3") -> *R3 | C73: =Technologies!C$594 -> #REF! | D73: =Technologies!D$594 -> #REF! | E73: =Commodities!C$136 -> KERR1 | F73: =Commodities!C$231 -> #REF! | G73: 1 | H73: =H47 -> #REF! | I73: =I47 -> #REF! | J73: =J47 -> #REF! | K73: =K47 -> #REF! | L73: =L47 -> #REF! | M73: =M47 -> #REF! | N73: =N47 -> #REF! | O73: =O47 -> #REF! | ... Q73: =Q47 -> #REF!
B74: =IF(LEFT(Technologies!B$595,1)="*","*R3","R3") -> *R3 | C74: =Technologies!C$595 -> #REF! | D74: =Technologies!D$595 -> #REF! | E74: =Commodities!C$136 -> KERR1 | F74: =Commodities!C$232 -> #REF! | G74: 1 | H74: =H48 -> #REF! | I74: =I48 -> #REF! | J74: =J48 -> #REF! | K74: =K48 -> #REF! | L74: =L48 -> #REF! | M74: =M48 -> #REF! | N74: =N48 -> #REF! | O74: =O48 -> #REF! | ... Q74: =Q48 -> #REF!
B75: =IF(LEFT(Technologies!B$596,1)="*","*R3","R3") -> *R3 | C75: =Technologies!C$596 -> #REF! | D75: =Technologies!D$596 -> #REF! | E75: =Commodities!C$136 -> KERR1 | F75: =Commodities!C$233 -> #REF! | G75: 1 | H75: =H49 -> #REF! | I75: =I49 -> #REF! | J75: =J49 -> #REF! | K75: =K49 -> #REF! | L75: =L49 -> #REF! | M75: =M49 -> #REF! | N75: =N49 -> #REF! | O75: =O49 -> #REF! | ... Q75: =Q49 -> #REF!
B76: =IF(LEFT(Technologies!B$597,1)="*","*R3","R3") -> *R3 | C76: =Technologies!C$597 -> #REF! | D76: =Technologies!D$597 -> #REF! | E76: =Commodities!C$137 -> LPGR1 | F76: =Commodities!C$234 -> #REF! | G76: 1 | H76: =H50 -> #REF! | I76: =I50 -> #REF! | J76: =J50 -> #REF! | K76: =K50 -> #REF! | L76: =L50 -> #REF! | M76: =M50 -> #REF! | N76: =N50 -> #REF! | O76: =O50 -> #REF! | ... Q76: =Q50 -> #REF!
B77: =IF(LEFT(Technologies!B$598,1)="*","*R3","R3") -> *R3 | C77: =Technologies!C$598 -> #REF! | D77: =Technologies!D$598 -> #REF! | E77: =Commodities!C$137 -> LPGR1 | F77: =Commodities!C$235 -> #REF! | G77: 1 | H77: =H51 -> #REF! | I77: =I51 -> #REF! | J77: =J51 -> #REF! | K77: =K51 -> #REF! | L77: =L51 -> #REF! | M77: =M51 -> #REF! | N77: =N51 -> #REF! | O77: =O51 -> #REF! | ... Q77: =Q51 -> #REF!
B78: =IF(LEFT(Technologies!B$599,1)="*","*R3","R3") -> *R3 | C78: =Technologies!C$599 -> #REF! | D78: =Technologies!D$599 -> #REF! | E78: =Commodities!C$137 -> LPGR1 | F78: =Commodities!C$236 -> #REF! | G78: 1 | H78: =H52 -> #REF! | I78: =I52 -> #REF! | J78: =J52 -> #REF! | K78: =K52 -> #REF! | L78: =L52 -> #REF! | M78: =M52 -> #REF! | N78: =N52 -> #REF! | O78: =O52 -> #REF! | ... Q78: =Q52 -> #REF!
B79: =IF(LEFT(Technologies!B$600,1)="*","*R3","R3") -> *R3 | C79: =Technologies!C$600 -> #REF! | D79: =Technologies!D$600 -> #REF! | E79: =Commodities!C$137 -> LPGR1 | F79: =Commodities!C$237 -> #REF! | G79: 1 | H79: =H53 -> #REF! | I79: =I53 -> #REF! | J79: =J53 -> #REF! | K79: =K53 -> #REF! | L79: =L53 -> #REF! | M79: =M53 -> #REF! | N79: =N53 -> #REF! | O79: =O53 -> #REF! | ... Q79: =Q53 -> #REF!
B80: =IF(LEFT(Technologies!B$601,1)="*","*R3","R3") -> *R3 | C80: =Technologies!C$601 -> #REF! | D80: =Technologies!D$601 -> #REF! | E80: =Commodities!C$138 -> MTHR1 | F80: =Commodities!C$238 -> #REF! | G80: 1 | H80: =H54 -> #REF! | I80: =I54 -> #REF! | J80: =J54 -> #REF! | K80: =K54 -> #REF! | L80: =L54 -> #REF! | M80: =M54 -> #REF! | N80: =N54 -> #REF! | O80: =O54 -> #REF! | ... Q80: =Q54 -> #REF!
B81: =IF(LEFT(Technologies!B$602,1)="*","*R3","R3") -> *R3 | C81: =Technologies!C$602 -> #REF! | D81: =Technologies!D$602 -> #REF! | E81: =Commodities!C$139 -> PFSR1 | F81: =Commodities!C$239 -> #REF! | G81: 1 | H81: =H55 -> #REF! | I81: =I55 -> #REF! | J81: =J55 -> #REF! | K81: =K55 -> #REF! | L81: =L55 -> #REF! | M81: =M55 -> #REF! | N81: =N55 -> #REF! | O81: =O55 -> #REF! | ... Q81: =Q55 -> #REF!
B82: =IF(LEFT(Technologies!B$603,1)="*","*R3","R3") -> *R3 | C82: =Technologies!C$603 -> #REF! | D82: =Technologies!D$603 -> #REF! | E82: =Commodities!C$141 -> RFLR1 | F82: =Commodities!C$240 -> RESRFL | G82: 1 | H82: =H56 -> #REF! | I82: =I56 -> #REF! | J82: =J56 -> #REF! | K82: =K56 -> #REF! | L82: =L56 -> #REF! | M82: =M56 -> #REF! | N82: =N56 -> #REF! | O82: =O56 -> #REF! | ... Q82: =Q56 -> #REF!
B83: =IF(LEFT(Technologies!B$604,1)="*","*R3","R3") -> *R3 | C83: =Technologies!C$604 -> #REF! | D83: =Technologies!D$604 -> #REF! | E83: =Commodities!C$141 -> RFLR1 | F83: =Commodities!C$241 -> #REF! | G83: 1 | H83: =H57 -> #REF! | I83: =I57 -> #REF! | J83: =J57 -> #REF! | K83: =K57 -> #REF! | L83: =L57 -> #REF! | M83: =M57 -> #REF! | N83: =N57 -> #REF! | O83: =O57 -> #REF! | ... Q83: =Q57 -> #REF!
B84: =IF(LEFT(Technologies!B$605,1)="*","*R3","R3") -> R3 | C84: =Technologies!C$605 -> #REF! | D84: =Technologies!D$605 -> #REF! | E84: =Commodities!C$141 -> RFLR1 | F84: =Commodities!C$242 -> #REF! | G84: 1 | H84: =H58 -> #REF! | I84: =I58 -> #REF! | J84: =J58 -> #REF! | K84: =K58 -> #REF! | L84: =L58 -> #REF! | M84: =M58 -> #REF! | N84: =N58 -> #REF! | O84: =O58 -> #REF! | ... Q84: =Q58 -> #REF!
B85: =IF(LEFT(Technologies!B$606,1)="*","*R3","R3") -> *R3 | C85: =Technologies!C$606 -> #REF! | D85: =Technologies!D$606 -> #REF! | E85: =Commodities!C$141 -> RFLR1 | F85: =Commodities!C$243 -> #REF! | G85: 1 | H85: =H59 -> #REF! | I85: =I59 -> #REF! | J85: =J59 -> #REF! | K85: =K59 -> #REF! | L85: =L59 -> #REF! | M85: =M59 -> #REF! | N85: =N59 -> #REF! | O85: =O59 -> #REF! | ... Q85: =Q59 -> #REF!
B86: =IF(LEFT(Technologies!B$607,1)="*","*R3","R3") -> *R3 | C86: =Technologies!C$607 -> #REF! | D86: =Technologies!D$607 -> #REF! | E86: =Commodities!C$140 -> RFHR1 | F86: =Commodities!C$244 -> #REF! | G86: 1 | H86: =H60 -> #REF! | I86: =I60 -> #REF! | J86: =J60 -> #REF! | K86: =K60 -> #REF! | L86: =L60 -> #REF! | M86: =M60 -> #REF! | N86: =N60 -> #REF! | O86: =O60 -> #REF! | ... Q86: =Q60 -> #REF!
B87: =IF(LEFT(Technologies!B$608,1)="*","*R3","R3") -> *R3 | C87: =Technologies!C$608 -> #REF! | D87: =Technologies!D$608 -> #REF! | E87: =Commodities!C$140 -> RFHR1 | F87: =Commodities!C$245 -> #REF! | G87: 1 | H87: =H61 -> #REF! | I87: =I61 -> #REF! | J87: =J61 -> #REF! | K87: =K61 -> #REF! | L87: =L61 -> #REF! | M87: =M61 -> #REF! | N87: =N61 -> #REF! | O87: =O61 -> #REF! | ... Q87: =Q61 -> #REF!
B88: =IF(LEFT(Technologies!B$609,1)="*","*R3","R3") -> *R3 | C88: =Technologies!C$609 -> #REF! | D88: =Technologies!D$609 -> #REF! | E88: =Commodities!C$142 -> ASPR1 | F88: =Commodities!C$246 -> #REF! | G88: 1 | H88: =H62 -> #REF! | I88: =I62 -> #REF! | J88: =J62 -> #REF! | K88: =K62 -> #REF! | L88: =L62 -> #REF! | M88: =M62 -> #REF! | N88: =N62 -> #REF! | O88: =O62 -> #REF! | ... Q88: =Q62 -> #REF!
B89: *
B90: =IF(LEFT(Technologies!B$585,1)="*","*R4","R4") -> R4 | C90: =Technologies!C$585 -> #REF! | D90: =Technologies!D$585 -> #REF! | E90: =Commodities!C$130 -> GSCR1 | F90: =Commodities!C$222 -> #REF! | G90: 1 | H90: =H64 -> #REF! | I90: =I64 -> #REF! | J90: =J64 -> #REF! | K90: =K64 -> #REF! | L90: =L64 -> #REF! | M90: =M64 -> #REF! | N90: =N64 -> #REF! | O90: =O64 -> #REF! | ... Q90: =Q64 -> #REF!
B91: =IF(LEFT(Technologies!B$586,1)="*","*R4","R4") -> R4 | C91: =Technologies!C$586 -> #REF! | D91: =Technologies!D$586 -> #REF! | E91: =Commodities!C$131 -> GSRR1 | F91: =Commodities!C$223 -> #REF! | G91: 1 | H91: =H65 -> #REF! | I91: =I65 -> #REF! | J91: =J65 -> #REF! | K91: =K65 -> #REF! | L91: =L65 -> #REF! | M91: =M65 -> #REF! | N91: =N65 -> #REF! | O91: =O65 -> #REF! | ... Q91: =Q65 -> #REF!
B92: =IF(LEFT(Technologies!B$587,1)="*","*R4","R4") -> R4 | C92: =Technologies!C$587 -> #REF! | D92: =Technologies!D$587 -> #REF! | E92: =Commodities!C$132 -> DSHR1 | F92: =Commodities!C$224 -> #REF! | G92: 1 | H92: =H66 -> #REF! | I92: =I66 -> #REF! | J92: =J66 -> #REF! | K92: =K66 -> #REF! | L92: =L66 -> #REF! | M92: =M66 -> #REF! | N92: =N66 -> #REF! | O92: =O66 -> #REF! | ... Q92: =Q66 -> #REF!
B93: =IF(LEFT(Technologies!B$588,1)="*","*R4","R4") -> R4 | C93: =Technologies!C$588 -> #REF! | D93: =Technologies!D$588 -> #REF! | E93: =Commodities!C$132 -> DSHR1 | F93: =Commodities!C$225 -> #REF! | G93: 1 | H93: =H67 -> #REF! | I93: =I67 -> #REF! | J93: =J67 -> #REF! | K93: =K67 -> #REF! | L93: =L67 -> #REF! | M93: =M67 -> #REF! | N93: =N67 -> #REF! | O93: =O67 -> #REF! | ... Q93: =Q67 -> #REF!
B94: =IF(LEFT(Technologies!B$589,1)="*","*R4","R4") -> *R4 | C94: =Technologies!C$589 -> #REF! | D94: =Technologies!D$589 -> #REF! | E94: =Commodities!C$132 -> DSHR1 | F94: =Commodities!C$226 -> #REF! | G94: 1 | H94: =H68 -> #REF! | I94: =I68 -> #REF! | J94: =J68 -> #REF! | K94: =K68 -> #REF! | L94: =L68 -> #REF! | M94: =M68 -> #REF! | N94: =N68 -> #REF! | O94: =O68 -> #REF! | ... Q94: =Q68 -> #REF!
B95: =IF(LEFT(Technologies!B$590,1)="*","*R4","R4") -> R4 | C95: =Technologies!C$590 -> #REF! | D95: =Technologies!D$590 -> #REF! | E95: =Commodities!C$132 -> DSHR1 | F95: =Commodities!C$227 -> #REF! | G95: 1 | H95: =H69 -> #REF! | I95: =I69 -> #REF! | J95: =J69 -> #REF! | K95: =K69 -> #REF! | L95: =L69 -> #REF! | M95: =M69 -> #REF! | N95: =N69 -> #REF! | O95: =O69 -> #REF! | ... Q95: =Q69 -> #REF!
B96: =IF(LEFT(Technologies!B$591,1)="*","*R4","R4") -> R4 | C96: =Technologies!C$591 -> #REF! | D96: =Technologies!D$591 -> #REF! | E96: =Commodities!C$133 -> DSLR1 | F96: =Commodities!C$228 -> #REF! | G96: 1 | H96: =H70 -> #REF! | I96: =I70 -> #REF! | J96: =J70 -> #REF! | K96: =K70 -> #REF! | L96: =L70 -> #REF! | M96: =M70 -> #REF! | N96: =N70 -> #REF! | O96: =O70 -> #REF! | ... Q96: =Q70 -> #REF!
B97: =IF(LEFT(Technologies!B$592,1)="*","*R4","R4") -> R4 | C97: =Technologies!C$592 -> #REF! | D97: =Technologies!D$592 -> #REF! | E97: =Commodities!C$134 -> DSUR1 | F97: =Commodities!C$229 -> #REF! | G97: 1 | H97: =H71 -> #REF! | I97: =I71 -> #REF! | J97: =J71 -> #REF! | K97: =K71 -> #REF! | L97: =L71 -> #REF! | M97: =M71 -> #REF! | N97: =N71 -> #REF! | O97: =O71 -> #REF! | ... Q97: =Q71 -> #REF!
B98: =IF(LEFT(Technologies!B$593,1)="*","*R4","R4") -> *R4 | C98: =Technologies!C$593 -> #REF! | D98: =Technologies!D$593 -> #REF! | E98: =Commodities!C$135 -> JTFR1 | F98: =Commodities!C$230 -> #REF! | G98: 1 | H98: =H72 -> #REF! | I98: =I72 -> #REF! | J98: =J72 -> #REF! | K98: =K72 -> #REF! | L98: =L72 -> #REF! | M98: =M72 -> #REF! | N98: =N72 -> #REF! | O98: =O72 -> #REF! | ... Q98: =Q72 -> #REF!
B99: =IF(LEFT(Technologies!B$594,1)="*","*R4","R4") -> *R4 | C99: =Technologies!C$594 -> #REF! | D99: =Technologies!D$594 -> #REF! | E99: =Commodities!C$136 -> KERR1 | F99: =Commodities!C$231 -> #REF! | G99: 1 | H99: =H73 -> #REF! | I99: =I73 -> #REF! | J99: =J73 -> #REF! | K99: =K73 -> #REF! | L99: =L73 -> #REF! | M99: =M73 -> #REF! | N99: =N73 -> #REF! | O99: =O73 -> #REF! | ... Q99: =Q73 -> #REF!
B100: =IF(LEFT(Technologies!B$595,1)="*","*R4","R4") -> *R4 | C100: =Technologies!C$595 -> #REF! | D100: =Technologies!D$595 -> #REF! | E100: =Commodities!C$136 -> KERR1 | F100: =Commodities!C$232 -> #REF! | G100: 1 | H100: =H74 -> #REF! | I100: =I74 -> #REF! | J100: =J74 -> #REF! | K100: =K74 -> #REF! | L100: =L74 -> #REF! | M100: =M74 -> #REF! | N100: =N74 -> #REF! | O100: =O74 -> #REF! | ... Q100: =Q74 -> #REF!
B101: =IF(LEFT(Technologies!B$596,1)="*","*R4","R4") -> *R4 | C101: =Technologies!C$596 -> #REF! | D101: =Technologies!D$596 -> #REF! | E101: =Commodities!C$136 -> KERR1 | F101: =Commodities!C$233 -> #REF! | G101: 1 | H101: =H75 -> #REF! | I101: =I75 -> #REF! | J101: =J75 -> #REF! | K101: =K75 -> #REF! | L101: =L75 -> #REF! | M101: =M75 -> #REF! | N101: =N75 -> #REF! | O101: =O75 -> #REF! | ... Q101: =Q75 -> #REF!
B102: =IF(LEFT(Technologies!B$597,1)="*","*R4","R4") -> *R4 | C102: =Technologies!C$597 -> #REF! | D102: =Technologies!D$597 -> #REF! | E102: =Commodities!C$137 -> LPGR1 | F102: =Commodities!C$234 -> #REF! | G102: 1 | H102: =H76 -> #REF! | I102: =I76 -> #REF! | J102: =J76 -> #REF! | K102: =K76 -> #REF! | L102: =L76 -> #REF! | M102: =M76 -> #REF! | N102: =N76 -> #REF! | O102: =O76 -> #REF! | ... Q102: =Q76 -> #REF!
B103: =IF(LEFT(Technologies!B$598,1)="*","*R4","R4") -> *R4 | C103: =Technologies!C$598 -> #REF! | D103: =Technologies!D$598 -> #REF! | E103: =Commodities!C$137 -> LPGR1 | F103: =Commodities!C$235 -> #REF! | G103: 1 | H103: =H77 -> #REF! | I103: =I77 -> #REF! | J103: =J77 -> #REF! | K103: =K77 -> #REF! | L103: =L77 -> #REF! | M103: =M77 -> #REF! | N103: =N77 -> #REF! | O103: =O77 -> #REF! | ... Q103: =Q77 -> #REF!
B104: =IF(LEFT(Technologies!B$599,1)="*","*R4","R4") -> *R4 | C104: =Technologies!C$599 -> #REF! | D104: =Technologies!D$599 -> #REF! | E104: =Commodities!C$137 -> LPGR1 | F104: =Commodities!C$236 -> #REF! | G104: 1 | H104: =H78 -> #REF! | I104: =I78 -> #REF! | J104: =J78 -> #REF! | K104: =K78 -> #REF! | L104: =L78 -> #REF! | M104: =M78 -> #REF! | N104: =N78 -> #REF! | O104: =O78 -> #REF! | ... Q104: =Q78 -> #REF!
B105: =IF(LEFT(Technologies!B$600,1)="*","*R4","R4") -> *R4 | C105: =Technologies!C$600 -> #REF! | D105: =Technologies!D$600 -> #REF! | E105: =Commodities!C$137 -> LPGR1 | F105: =Commodities!C$237 -> #REF! | G105: 1 | H105: =H79 -> #REF! | I105: =I79 -> #REF! | J105: =J79 -> #REF! | K105: =K79 -> #REF! | L105: =L79 -> #REF! | M105: =M79 -> #REF! | N105: =N79 -> #REF! | O105: =O79 -> #REF! | ... Q105: =Q79 -> #REF!
B106: =IF(LEFT(Technologies!B$601,1)="*","*R4","R4") -> *R4 | C106: =Technologies!C$601 -> #REF! | D106: =Technologies!D$601 -> #REF! | E106: =Commodities!C$138 -> MTHR1 | F106: =Commodities!C$238 -> #REF! | G106: 1 | H106: =H80 -> #REF! | I106: =I80 -> #REF! | J106: =J80 -> #REF! | K106: =K80 -> #REF! | L106: =L80 -> #REF! | M106: =M80 -> #REF! | N106: =N80 -> #REF! | O106: =O80 -> #REF! | ... Q106: =Q80 -> #REF!
B107: =IF(LEFT(Technologies!B$602,1)="*","*R4","R4") -> *R4 | C107: =Technologies!C$602 -> #REF! | D107: =Technologies!D$602 -> #REF! | E107: =Commodities!C$139 -> PFSR1 | F107: =Commodities!C$239 -> #REF! | G107: 1 | H107: =H81 -> #REF! | I107: =I81 -> #REF! | J107: =J81 -> #REF! | K107: =K81 -> #REF! | L107: =L81 -> #REF! | M107: =M81 -> #REF! | N107: =N81 -> #REF! | O107: =O81 -> #REF! | ... Q107: =Q81 -> #REF!
B108: =IF(LEFT(Technologies!B$603,1)="*","*R4","R4") -> *R4 | C108: =Technologies!C$603 -> #REF! | D108: =Technologies!D$603 -> #REF! | E108: =Commodities!C$141 -> RFLR1 | F108: =Commodities!C$240 -> RESRFL | G108: 1 | H108: =H82 -> #REF! | I108: =I82 -> #REF! | J108: =J82 -> #REF! | K108: =K82 -> #REF! | L108: =L82 -> #REF! | M108: =M82 -> #REF! | N108: =N82 -> #REF! | O108: =O82 -> #REF! | ... Q108: =Q82 -> #REF!
B109: =IF(LEFT(Technologies!B$604,1)="*","*R4","R4") -> *R4 | C109: =Technologies!C$604 -> #REF! | D109: =Technologies!D$604 -> #REF! | E109: =Commodities!C$141 -> RFLR1 | F109: =Commodities!C$241 -> #REF! | G109: 1 | H109: =H83 -> #REF! | I109: =I83 -> #REF! | J109: =J83 -> #REF! | K109: =K83 -> #REF! | L109: =L83 -> #REF! | M109: =M83 -> #REF! | N109: =N83 -> #REF! | O109: =O83 -> #REF! | ... Q109: =Q83 -> #REF!
B110: =IF(LEFT(Technologies!B$605,1)="*","*R4","R4") -> R4 | C110: =Technologies!C$605 -> #REF! | D110: =Technologies!D$605 -> #REF! | E110: =Commodities!C$141 -> RFLR1 | F110: =Commodities!C$242 -> #REF! | G110: 1 | H110: =H84 -> #REF! | I110: =I84 -> #REF! | J110: =J84 -> #REF! | K110: =K84 -> #REF! | L110: =L84 -> #REF! | M110: =M84 -> #REF! | N110: =N84 -> #REF! | O110: =O84 -> #REF! | ... Q110: =Q84 -> #REF!
B111: =IF(LEFT(Technologies!B$606,1)="*","*R4","R4") -> *R4 | C111: =Technologies!C$606 -> #REF! | D111: =Technologies!D$606 -> #REF! | E111: =Commodities!C$141 -> RFLR1 | F111: =Commodities!C$243 -> #REF! | G111: 1 | H111: =H85 -> #REF! | I111: =I85 -> #REF! | J111: =J85 -> #REF! | K111: =K85 -> #REF! | L111: =L85 -> #REF! | M111: =M85 -> #REF! | N111: =N85 -> #REF! | O111: =O85 -> #REF! | ... Q111: =Q85 -> #REF!
B112: =IF(LEFT(Technologies!B$607,1)="*","*R4","R4") -> *R4 | C112: =Technologies!C$607 -> #REF! | D112: =Technologies!D$607 -> #REF! | E112: =Commodities!C$140 -> RFHR1 | F112: =Commodities!C$244 -> #REF! | G112: 1 | H112: =H86 -> #REF! | I112: =I86 -> #REF! | J112: =J86 -> #REF! | K112: =K86 -> #REF! | L112: =L86 -> #REF! | M112: =M86 -> #REF! | N112: =N86 -> #REF! | O112: =O86 -> #REF! | ... Q112: =Q86 -> #REF!
B113: =IF(LEFT(Technologies!B$608,1)="*","*R4","R4") -> *R4 | C113: =Technologies!C$608 -> #REF! | D113: =Technologies!D$608 -> #REF! | E113: =Commodities!C$140 -> RFHR1 | F113: =Commodities!C$245 -> #REF! | G113: 1 | H113: =H87 -> #REF! | I113: =I87 -> #REF! | J113: =J87 -> #REF! | K113: =K87 -> #REF! | L113: =L87 -> #REF! | M113: =M87 -> #REF! | N113: =N87 -> #REF! | O113: =O87 -> #REF! | ... Q113: =Q87 -> #REF!
...

Sheet Domestic Crude Prod Trends
A1: Back to Contents | B1: Data 1: Crude Oil Production
A2: Sourcekey | B2: MCRFPUS1 | D2: MCRFPP11 | F2: MCRFPFL1 | G2: MCRFPNY1 | H2: MCRFPPA1 | I2: MCRFPVA1 | J2: MCRFPWV1 | K2: MCRFPP21 | M2: MCRFPIL1 | N2: MCRFPIN1 | O2: MCRFPKS1 | P2: MCRFPKY1 | Q2: MCRFP_SMI_1 | R2: MCRFPMO1 | S2: MCRFPNE1 | T2: MCRFPND1 | U2: MCRFPOH1 | V2: MCRFPOK1 | W2: MCRFPSD1 | X2: MCRFPTN1 | Y2: MCRFPP31 | AA2: MCRFPAL1 | AB2: MCRFPAR1 | AC2: MCRFPLA1 | AD2: MCRFPMS1 | AE2: MCRFPNM1 | AF2: MCRFPTX1 | AG2: MCRFP3FM1 | AH2: MCRFPP41 | AJ2: MCRFPCO1 | AK2: MCRFPMT1 | AL2: MCRFPUT1 | AM2: MCRFPWY1 | AN2: MCRFPP51 | AP2: MCRFPAK1 | AQ2: MCRFPAKS1 | AR2: MANFPAK1 | AS2: MCRFPAZ1 | AT2: MCRFPCA1 | AU2: MCRFPNV1 | AV2: MCRFP5F1
A3: Date | B3: U.S. Field Production of Crude Oil (Thousand Barrels) | D3: East Coast (PADD 1) Field Production of Crude Oil (Thousand Barrels) | F3: Florida Field Production of Crude Oil (Thousand Barrels) | G3: New York Field Production of Crude Oil (Thousand Barrels) | H3: Pennsylvania Field Production of Crude Oil (Thousand Barrels) | I3: Virginia Field Production of Crude Oil (Thousand Barrels) | J3: West Virginia Field Production of Crude Oil (Thousand Barrels) | K3: Midwest (PADD 2) Field Production of Crude Oil (Thousand Barrels) | M3: Illinois Field Production of Crude Oil (Thousand Barrels) | N3: Indiana Field Production of Crude Oil (Thousand Barrels) | O3: Kansas Field Production of Crude Oil (Thousand Barrels) | P3: Kentucky Field Production of Crude Oil (Thousand Barrels) | Q3: Michigan Field Production of Crude Oil (Thousand Barrels) | R3: Missouri Field Production of Crude Oil (Thousand Barrels) | S3: Nebraska Field Production of Crude Oil (Thousand Barrels) | T3: North Dakota Field Production of Crude Oil (Thousand Barrels) | U3: Ohio Field Production of Crude Oil (Thousand Barrels) | V3: Oklahoma Field Production of Crude Oil (Thousand Barrels) | W3: South Dakota Field Production of Crude Oil (Thousand Barrels) | X3: Tennessee Field Production of Crude Oil (Thousand Barrels) | Y3: Gulf Coast (PADD 3) Field Production of Crude Oil (Thousand Barrels) | AA3: Alabama Field Production of Crude Oil (Thousand Barrels) | AB3: Arkansas Field Production of Crude Oil (Thousand Barrels) | AC3: Louisiana Field Production of Crude Oil (Thousand Barrels) | AD3: Mississippi Field Production of Crude Oil (Thousand Barrels) | AE3: New Mexico Field Production of Crude Oil (Thousand Barrels) | AF3: Texas Field Production of Crude Oil (Thousand Barrels) | AG3: Federal Offshore--Gulf of Mexico Field Production of Crude Oil (Thousand Barrels) | AH3: Rocky Mountain (PADD 4) Field Production of Crude Oil (Thousand Barrels) | AJ3: Colorado Field Production of Crude Oil (Thousand Barrels) | AK3: Montana Field Production of Crude Oil (Thousand Barrels) | AL3: Utah Field Production of Crude Oil (Thousand Barrels) | AM3: Wyoming Field Production of Crude Oil (Thousand Barrels) | AN3: West Coast (PADD 5) Field Production of Crude Oil (Thousand Barrels) | AP3: Alaska Field Production of Crude Oil (Thousand Barrels) | AQ3: Alaska South Field Production of Crude Oil (Thousand Barrels) | AR3: Alaska North Slope Crude Oil Production (Thousand Barrels) | AS3: Arizona Field Production of Crude Oil (Thousand Barrels) | AT3: California Field Production of Crude Oil (Thousand Barrels) | AU3: Nevada Field Production of Crude Oil (Thousand Barrels) | AV3: Federal Offshore California Field Production of Crude Oil (Thousand Barrels)
A4: 29767 | B4: 3128624 | D4: 42829 | F4: 34773 | G4: 841 | H4: 3729 | I4: 13 | J4: 3473 | K4: 355653 | M4: 24090 | N4: 4721 | O4: 65810 | P4: 6548 | Q4: 32665 | R4: 226 | S4: 6671 | T4: 45424 | U4: 13551 | V4: 154056 | W4: 973 | X4: 918 | Y4: 1539251 | AA4: 20680 | AB4: 18352 | AC4: 199579 | AD4: 34204 | AE4: 71568 | AF4: 932350 | AG4: 262518 | AH4: 217539 | AJ4: 30303 | AK4: 30813 | AL4: 25860 | AM4: 130563 | AN4: 973352 | AP4: 587337 | AQ4: 31072 | AR4: 556265 | AS4: 357 | AT4: 365370 | AU4: 700 | AV4: 19588
A5: 30132 | B5: 3156715 | C5: =(B5-B4)/B4 -> 0.0089787076 | D5: 34018 | E5: =(D5-D4)/D4 -> -0.20572509 | F5: 25626 | G5: 834 | H5: 4282 | I5: 49 | J5: 3227 | K5: 372436 | L5: =(K5-K4)/K4 -> 0.047189255 | M5: 27710 | N5: 5563 | O5: 70525 | P5: 7349 | Q5: 31462 | R5: 202 | S5: 6872 | T5: 47271 | U5: 14571 | V5: 158621 | W5: 1158 | X5: 1132 | Y5: 1526625 | Z5: =(Y5-Y4)/Y4 -> -0.0082026908 | AA5: 20014 | AB5: 18849 | AC5: 188749 | AD5: 33047 | AE5: 71024 | AF5: 908217 | AG5: 286725 | AH5: 202206 | AI5: =(AH5-AH4)/AH4 -> -0.070483913 | AJ5: 30545 | AK5: 30921 | AL5: 22440 | AM5: 118300 | AN5: 1021430 | AO5: =(AN5-AN4)/AN4 -> 0.049394258 | AP5: 618910 | AQ5: 27404 | AR5: 591506 | AS5: 335 | AT5: 373176 | AU5: 613 | AV5: 28396
A6: 30497 | B6: 3170999 | C6: =(B6-B5)/B5 -> 0.0045249571 | D6: 28282 | E6: =(D6-D5)/D5 -> -0.16861661 | F6: 19476 | G6: 831 | H6: 4282 | I6: 65 | J6: 3628 | K6: 378879 | L6: =(K6-K5)/K5 -> 0.017299617 | M6: 29200 | N6: 5321 | O6: 71594 | P6: 7886 | Q6: 31736 | R6: 269 | S6: 6380 | T6: 50690 | U6: 14971 | V6: 158604 | W6: 1172 | X6: 1056 | Y6: 1526464 | Z6: =(Y6-Y5)/Y5 -> -0.00010546139 | AA6: 18746 | AB6: 18849 | AC6: 179617 | AD6: 31455 | AE6: 75169 | AF6: 882911 | AG6: 319717 | AH6: 206112 | AI6: =(AH6-AH5)/AH5 -> 0.019316934 | AJ6: 29050 | AK6: 29225 | AL6: 29534 | AM6: 118303 | AN6: 1031262 | AO6: =(AN6-AN5)/AN5 -> 0.0096257208 | AP6: 625527 | AQ6: 24769 | AR6: 600758 | AS6: 237 | AT6: 374161 | AU6: 810 | AV6: 30527
A7: 30863 | B7: 3249696 | C7: =(B7-B6)/B6 -> 0.024817731 | D7: 23142 | E7: =(D7-D6)/D6 -> -0.18174104 | F7: 14462 | G7: 840 | H7: 4284 | I7: 32 | J7: 3524 | K7: 393759 | L7: =(K7-K6)/K6 -> 0.039273752 | M7: 28868 | N7: 5526 | O7: 75729 | P7: 7777 | Q7: 30554 | R7: 285 | S7: 6452 | T7: 52652 | U7: 15271 | V7: 168385 | W7: 1340 | X7: 920 | Y7: 1570688 | Z7: =(Y7-Y6)/Y6 -> 0.028971532 | AA7: 19804 | AB7: 18730 | AC7: 187011 | AD7: 32776 | AE7: 79336 | AF7: 883174 | AG7: 349857 | AH7: 217564 | AI7: =(AH7-AH6)/AH6 -> 0.055562025 | AJ7: 28845 | AK7: 29761 | AL7: 34689 | AM7: 124269 | AN7: 1044543 | AO7: =(AN7-AN6)/AN6 -> 0.012878396 | AP7: 630401 | AQ7: 21983 | AR7: 608418 | AS7: 215 | AT7: 381621 | AU7: 1907 | AV7: 30399
A8: 31228 | B8: 3274553 | C8: =(B8-B7)/B7 -> 0.0076490232 | D8: 20961 | E8: =(D8-D7)/D7 -> -0.094244231 | F8: 11458 | G8: 1071 | H8: 4851 | I8: 26 | J8: 3555 | K8: 384082 | L8: =(K8-K7)/K7 -> -0.024575946 | M8: 30265 | N8: 5168 | O8: 75407 | P8: 7790 | Q8: 27300 | R8: 243 | S8: 6943 | T8: 50857 | U8: 14988 | V8: 162739 | W8: 1596 | X8: 786 | Y8: 1546866 | Z8: =(Y8-Y7)/Y7 -> -0.015166602 | AA8: 21581 | AB8: 19044 | AC8: 184409 | AD8: 30641 | AE8: 78530 | AF8: 869218 | AG8: 343443 | AH8: 229320 | AI8: =(AH8-AH7)/AH7 -> 0.054034675 | AJ8: 30246 | AK8: 29768 | AL8: 40792 | AM8: 128514 | AN8: 1093324 | AO8: =(AN8-AN7)/AN7 -> 0.046700806 | AP8: 666233 | AQ8: 16946 | AR8: 649287 | AS8: 175 | AT8: 394002 | AU8: 3039 | AV8: 29875
A9: 31593 | B9: 3168252 | C9: =(B9-B8)/B8 -> -0.032462751 | D9: 17182 | E9: =(D9-D8)/D8 -> -0.1802872 | F9: 9383 | G9: 853 | H9: 3783 | I9: 18 | J9: 3145 | K9: 348814 | L9: =(K9-K8)/K8 -> -0.091824142 | M9: 27245 | N9: 4759 | O9: 67034 | P9: 6475 | Q9: 25688 | R9: 110 | S9: 7098 | T9: 45628 | U9: 13442 | V9: 149105 | W9: 1586 | X9: 644 | Y9: 1494323 | Z9: =(Y9-Y8)/Y8 -> -0.03396739 | AA9: 21122 | AB9: 15778 | AC9: 181791 | AD9: 29997 | AE9: 75712 | AF9: 819595 | AG9: 350328 | AH9: 216888 | AI9: =(AH9-AH8)/AH8 -> -0.054212454 | AJ9: 29309 | AK9: 27072 | AL9: 39172 | AM9: 121337 | AN9: 1091043 | AO9: =(AN9-AN8)/AN8 -> -0.0020862983 | AP9: 681310 | AQ9: 17574 | AR9: 663736 | AS9: 161 | AT9: 378059 | AU9: 2907 | AV9: 28606
A10: 31958 | B10: 3047378 | C10: =(B10-B9)/B9 -> -0.038151637 | D10: 15134 | E10: =(D10-D9)/D9 -> -0.11919451 | F10: 8270 | G10: 710 | H10: 3302 | I10: 17 | J10: 2835 | K10: 315661 | L10: =(K10-K9)/K9 -> -0.095044924 | M10: 23980 | N10: 3738 | O10: 59884 | P10: 5743 | Q10: 25972 | R10: 110 | S10: 6091 | T10: 41351 | U10: 12153 | V10: 134378 | W10: 1644 | X10: 614 | Y10: 1396774 | Z10: =(Y10-Y9)/Y9 -> -0.065279729 | AA10: 20607 | AB10: 14230 | AC10: 175027 | AD10: 28103 | AE10: 72328 | AF10: 760962 | AG10: 325517 | AH10: 204915 | AI10: =(AH10-AH9)/AH9 -> -0.055203607 | AJ10: 28802 | AK10: 25059 | AL10: 35788 | AM10: 115267 | AN10: 1114892 | AO10: =(AN10-AN9)/AN9 -> 0.0218589 | AP10: 715955 | AQ10: 16150 | AR10: 699807 | AS10: 131 | AT10: 364608 | AU10: 3112 | AV10: 31090
A11: 32324 | B11: 2979123 | C11: =(B11-B10)/B10 -> -0.022397943 | D11: 13788 | E11: =(D11-D10)/D10 -> -0.088938813 | F11: 7746 | G11: 566 | H11: 2830 | I11: 25 | J11: 2621 | K11: 301994 | L11: =(K11-K10)/K10 -> -0.043296448 | M11: 22476 | N11: 3665 | O11: 58824 | P11: 5458 | Q11: 23250 | R11: 156 | S11: 5978 | T11: 39343 | U11: 11711 | V11: 128874 | W11: 1657 | X11: 601 | Y11: 1333151 | Z11: =(Y11-Y10)/Y10 -> -0.04554996 | AA11: 20797 | AB11: 13606 | AC11: 165006 | AD11: 27553 | AE11: 71235 | AF11: 735495 | AG11: 299460 | AH11: 202694 | AI11: =(AH11-AH10)/AH10 -> -0.01083864 | AJ11: 32352 | AK11: 23338 | AL11: 33018 | AM11: 113985 | AN11: 1127500 | AO11: =(AN11-AN10)/AN10 -> 0.011308719 | AP11: 738143 | AQ11: 15697 | AR11: 722447 | AS11: 113 | AT11: 354730 | AU11: 3230 | AV11: 31284
A12: 32689 | B12: 2778773 | C12: =(B12-B11)/B11 -> -0.067251335 | D12: 12751 | E12: =(D12-D11)/D11 -> -0.075210328 | F12: 7289 | G12: 498 | H12: 2698 | I12: 23 | J12: 2243 | K12: 279117 | L12: =(K12-K11)/K11 -> -0.075753161 | M12: 20378 | N12: 3311 | O12: 55485 | P12: 5414 | Q12: 21568 | R12: 133 | S12: 6230 | T12: 36744 | U12: 10215 | V12: 117493 | W12: 1612 | X12: 532 | Y12: 1247579 | Z12: =(Y12-Y11)/Y11 -> -0.064187778 | AA12: 19813 | AB12: 11261 | AC12: 153295 | AD12: 27403 | AE12: 68714 | AF12: 688169 | AG12: 278927 | AH12: 187739 | AI12: =(AH12-AH11)/AH11 -> -0.073781168 | AJ12: 30655 | AK12: 20956 | AL12: 28415 | AM12: 107715 | AN12: 1051585 | AO12: =(AN12-AN11)/AN11 -> -0.067330377 | AP12: 683979 | AQ12: 15370 | AR12: 668612 | AS12: 137 | AT12: 331174 | AU12: 3216 | AV12: 33076
A13: 33054 | B13: 2684687 | C13: =(B13-B12)/B12 -> -0.033858829 | D13: 10894 | E13: =(D13-D12)/D12 -> -0.14563564 | F13: 5675 | G13: 415 | H13: 2641 | I13: 16 | J13: 2143 | K13: 270657 | L13: =(K13-K12)/K12 -> -0.03030987 | M13: 19954 | N13: 3000 | O13: 55428 | P13: 5409 | Q13: 19676 | R13: 146 | S13: 5889 | T13: 36717 | U13: 10008 | V13: 112273 | W13: 1648 | X13: 506 | Y13: 1219071 | Z13: =(Y13-Y12)/Y12 -> -0.022850657 | AA13: 18538 | AB13: 10386 | AC13: 147582 | AD13: 27034 | AE13: 67250 | AF13: 678478 | AG13: 269804 | AH13: 181723 | AI13: =(AH13-AH12)/AH12 -> -0.032044487 | AJ13: 30453 | AK13: 19810 | AL13: 27604 | AM13: 103856 | AN13: 1002344 | AO13: =(AN13-AN12)/AN12 -> -0.046825506 | AP13: 647309 | AQ13: 11147 | AR13: 636165 | AS13: 121 | AT13: 320868 | AU13: 4011 | AV13: 30031
A14: 33419 | B14: 2707039 | C14: =(B14-B13)/B13 -> 0.0083257378 | D14: 9661 | E14: =(D14-D13)/D13 -> -0.11318157 | F14: 4725 | G14: 427 | H14: 2531 | I14: 13 | J14: 1963 | K14: 263286 | L14: =(K14-K13)/K13 -> -0.027233731 | M14: 19068 | N14: 3014 | O14: 56928 | P14: 5485 | Q14: 17520 | R14: 149 | S14: 5832 | T14: 35891 | U14: 9156 | V14: 108094 | W14: 1662 | X14: 485 | Y14: 1247848 | Z14: =(Y14-Y13)/Y13 -> 0.02360568 | AA14: 18637 | AB14: 10305 | AC14: 147070 | AD14: 27055 | AE14: 70417 | AF14: 682616 | AG14: 291755 | AH14: 175356 | AI14: =(AH14-AH13)/AH13 -> -0.035036842 | AJ14: 31382 | AK14: 19579 | AL14: 24467 | AM14: 99928 | AN14: 1010886 | AO14: =(AN14-AN13)/AN13 -> 0.0085220244 | AP14: 656349 | AQ14: 15338 | AR14: 641007 | AS14: 111 | AT14: 319497 | AU14: 3413 | AV14: 31519
A15: 33785 | B15: 2624632 | C15: =(B15-B14)/B14 -> -0.030441748 | D15: 10043 | E15: =(D15-D14)/D14 -> 0.03954042 | F15: 5425 | G15: 404 | H15: 2137 | I15: 12 | J15: 2068 | K15: 248565 | L15: =(K15-K14)/K14 -> -0.055912582 | M15: 19303 | N15: 3016 | O15: 53613 | P15: 5479 | Q15: 15579 | R15: 143 | S15: 5474 | T15: 32894 | U15: 9197 | V15: 101807 | W15: 1557 | X15: 501 | Y15: 1219046 | Z15: =(Y15-Y14)/Y14 -> -0.023081337 | AA15: 19025 | AB15: 10260 | AC15: 143075 | AD15: 25182 | AE15: 69972 | AF15: 650623 | AG15: 300909 | AH15: 167799 | AI15: =(AH15-AH14)/AH14 -> -0.043095189 | AJ15: 29787 | AK15: 18482 | AL15: 22720 | AM15: 96810 | AN15: 979179 | AO15: =(AN15-AN14)/AN14 -> -0.031365555 | AP15: 627322 | AQ15: 15204 | AR15: 612119 | AS15: 94 | AT15: 305488 | AU15: 3721 | AV15: 42552
A16: 34150 | B16: 2499033 | C16: =(B16-B15)/B15 -> -0.047853947 | D16: 10032 | E16: =(D16-D15)/D15 -> -0.0010952903 | F16: 5604 | G16: 335 | H16: 2036 | I16: 12 | J16: 2048 | K16: 230927 | L16: =(K16-K15)/K15 -> -0.070959306 | M16: 17406 | N16: 2761 | O16: 49625 | P16: 4595 | Q16: 13799 | R16: 135 | S16: 4868 | T16: 30915 | U16: 8282 | V16: 96625 | W16: 1500 | X16: 419 | Y16: 1178566 | Z16: =(Y16-Y15)/Y15 -> -0.033206294 | AA16: 18677 | AB16: 9975 | AC16: 138673 | AD16: 22613 | AE16: 68422 | AF16: 619090 | AG16: 301118 | AH16: 156332 | AI16: =(AH16-AH15)/AH15 -> -0.068337714 | AJ16: 29398 | AK16: 17448 | AL16: 21821 | AM16: 87667 | AN16: 923174 | AO16: =(AN16-AN15)/AN15 -> -0.057195875 | AP16: 577495 | AQ16: 13849 | AR16: 563647 | AS16: 73 | AT16: 293090 | AU16: 1880 | AV16: 50639
... A34: 40724 | B34: 2078479 | C34: =(B34-B33)/B33 -> 0.038677575 | D34: 8002 | E34: =(D34-D33)/D33 -> 0.1246662 | F34: 2015 | G34: 370 | H34: 3460 | I34: 10 | J34: 2146 | K34: 298264 | L34: =(K34-K33)/K33 -> 0.19040378 | M34: 9239 | N34: 1987 | O34: 41486 | P34: 2323 | Q34: 6554 | R34: 118 | S34: 2504 | T34: 152985 | U34: 4891 | V34: 74319 | W34: 1613 | X34: 246 | Y34: 1202930 | Z34: =(Y34-Y33)/Y33 -> 0.033002175 | AA34: 8374 | AB34: 5877 | AC34: 68952 | AD34: 23329 | AE34: 71454 | AF34: 544155 | AG34: 480788 | AH34: 144083 | AI34: =(AH34-AH33)/AH33 -> 0.060814442 | AJ34: 38996 | AK34: 24149 | AL34: 26251 | AM34: 54687 | AN34: 425199 | AO34: =(AN34-AN33)/AN33 -> -0.040375636 | AP34: 208749 | AQ34: 3691 | AR34: 205058 | AS34: 37 | AT34: 196189 | AU34: 408 | AV34: 19817

Sheet Domestic Crude Oil CUM
A1: Data from EIA U.S. Crude Oil, Natural Gas, and Natural Gas Liquids Proved Reserves, 2011
A2: Table 7: Crude oil proved reserves, reserves changes, and production, 2011
A3: http://www.eia.gov/naturalgas/crudeoilreserves/pdf/table_7.pdf
C5: Millions Barrels | F5: EPAUS9R Crude Reserves
A6: State | B6: MARKAL Region | C6: Proved Reserves as of 12/31/11 | F6: Region | G6: Reserves by Region | J6: Reserves PJ
A7: Pennsylvania | B7: 2 | C7: 24 | D7: =C7/$C$35 -> 0.00090415913 | F7: R2 | G7: =C7 -> 24 | H7: =G7/$C$35 -> 0.00090415913 | J7: =G7*Conv!$I$4*Conv!$D$46/Conv!$I$5/1000000*20 -> 2656.3296
A8: Illinois | B8: 3 | C8: 54 | D8: =C8/$C$35 -> 0.002034358 | F8: R3 | G8: =SUM(C8:C11) -> 146 | H8: =G8/$C$35 -> 0.0055003014 | J8: =G8*Conv!$I$4*Conv!$D$46/Conv!$I$5/1000000*20 -> 16159.338
A9: Indiana | B9: 3 | C9: 7 | D9: =C9/$C$35 -> 0.00026371308 | F9: R4 | G9: =SUM(C12:C14) -> 3006 | H9: =G9/$C$35 -> 0.11324593 | J9: =G9*Conv!$I$4*Conv!$D$46/Conv!$I$5/1000000*20 -> 332705.28
A10: Michigan | B10: 3 | C10: 44 | D10: =C10/$C$35 -> 0.0016576251 | F10: R5 | G10: =SUM(C15:C16) -> 43 | H10: =G10/$C$35 -> 0.0016199518 | J10: =G10*Conv!$I$4*Conv!$D$46/Conv!$I$5/1000000*20 -> 4759.2572
A11: Ohio | B11: 3 | C11: 41 | D11: =C11/$C$35 -> 0.0015446052 | F11: R6 | G11: =SUM(C17:C19) -> 301 | H11: =G11/$C$35 -> 0.011339662 | J11: =G11*Conv!$I$4*Conv!$D$46/Conv!$I$5/1000000*20 -> 33314.8
A12: Kansas | B12: 4 | C12: 343 | D12: =C12/$C$35 -> 0.012921941 | F12: R7 | G12: =SUM(C20:C25) -> 12974 | H12: =G12/$C$35 -> 0.48877336 | J12: =G12*Conv!$I$4*Conv!$D$46/Conv!$I$5/1000000*20 -> 1435967.5
A13: Nebraska | B13: 4 | C13: 14 | D13: =C13/$C$35 -> 0.00052742616 | F13: R8 | G13: =SUM(C26:C30) -> 2837 | H13: =G13/$C$35 -> 0.10687914 | J13: =G13*Conv!$I$4*Conv!$D$46/Conv!$I$5/1000000*20 -> 314000.29
A14: North Dakota | B14: 4 | C14: 2649 | D14: =C14/$C$35 -> 0.099796564 | F14: R9 | G14: =SUM(C31:C33) -> 7171 | H14: =G14/$C$35 -> 0.27015521 | J14: =G14*Conv!$I$4*Conv!$D$46/Conv!$I$5/1000000*20 -> 793689.15
A15: Florida | B15: 5 | C15: 22 | D15: =C15/$C$35 -> 0.00082881254 | H15: =SUM(H7:H14) -> 0.99841772 | J15: =SUM(J7:J14) -> 2933252
A16: West Virginia | B16: 5 | C16: 21 | D16: =C16/$C$35 -> 0.00079113924
A17: Alabama | B17: 6 | C17: 46 | D17: =C17/$C$35 -> 0.0017329717 | F17: NYC MARKAL Crude Reserves
A18: Kentucky | B18: 6 | C18: 17 | D18: =C18/$C$35 -> 0.00064044605 | F18: Region | G18: Reserves by Region | J18: Reserves PJ
A19: Mississippi | B19: 6 | C19: 238 | D19: =C19/$C$35 -> 0.0089662447 | F19: R1 | G19: =C19 -> 238 | H19: =G19/$C$35 -> 0.0089662447 | J19: =J7 -> 2656.3296
A20: Arkansas | B20: 7 | C20: 38 | D20: =C20/$C$35 -> 0.0014315853 | F20: R2 | G20: =SUM(C20:C23) -> 8348 | H20: =G20/$C$35 -> 0.31449668
A21: Louisiana | B21: 7 | C21: 417 | D21: =C21/$C$35 -> 0.015709765 | F21: R3 | G21: =SUM(C24:C26) -> 5049 | H21: =G21/$C$35 -> 0.19021248
A22: Oklahoma | B22: 7 | C22: 879 | D22: =C22/$C$35 -> 0.033114828 | F22: R4 | G22: =SUM(C27:C28) -> 1250 | H22: =G22/$C$35 -> 0.047091621
A23: Texas | B23: 7 | C23: 7014 | D23: =C23/$C$35 -> 0.26424051 | F23: R5 | G23: =SUM(C29:C31) -> 4980 | H23: =G23/$C$35 -> 0.18761302
A24: Fed Offshore: Louisianna | B24: 7 | C24: 4438 | D24: =C24/$C$35 -> 0.16719409 | F24: R6 | G24: =SUM(C32:C37) -> 29941 | H24: =G24/$C$35 -> 1.1279762
A25: Fed Offshore: Texas | B25: 7 | C25: 188 | D25: =C25/$C$35 -> 0.0070825799 | F25: Blank | G25: =SUM(C38:C42) -> 0 | H25: =G25/$C$35 -> 0
A26: Colorado | B26: 8 | C26: 423 | D26: =C26/$C$35 -> 0.015935805 | F26: Blank | G26: =SUM(C43:C45) -> 0 | H26: =G26/$C$35 -> 0
A27: Montana | B27: 8 | C27: 384 | D27: =C27/$C$35 -> 0.014466546 | F27: Total | H27: =SUM(H19:H26) -> 1.8763562 | J27: =SUM(J19:J26) -> 2656.3296
A28: New Mexico | B28: 8 | C28: 866 | D28: =C28/$C$35 -> 0.032625075 | F28: * R1 in the NYC model is NE & MA regions in EPAUS9R
A29: Utah | B29: 8 | C29: 504 | D29: =C29/$C$35 -> 0.018987342
A30: Wyoming | B30: 8 | C30: 660 | D30: =C30/$C$35 -> 0.024864376
A31: Alaska | B31: 9 | C31: 3816 | D31: =C31/$C$35 -> 0.1437613
A32: California | B32: 9 | C32: 3005 | D32: =C32/$C$35 -> 0.11320826
A33: Fed Offshore: California | B33: 9 | C33: 350 | D33: =C33/$C$35 -> 0.013185654
A34: Misc* | C34: 42 | D34: =C34/$C$35 -> 0.0015822785
C35: =SUM(C7:C34) -> 26544 | D35: =SUM(D7:D34) -> 1
A39: * Includes Arizona, Missouri, Nevada, New York, South Dakota, Tenessee, Virginia

Sheet Domestic Crude Oil Prices
A1: AEO2014 Lower 48 Crude Oil Production and Wellhead Prices by Supply Region, Reference case
A4: Region | B4: 2005 | C4: 2010 | D4: 2015 | E4: 2020 | F4: 2025 | G4: 2030 | H4: 2035 | I4: 2040
A6: Production 1/
A7: (million barrels per day)
A8: Lower 48 Total | B8: 4.3269997 | C8: 4.9 | D8: 8.574966 | E8: 9.115398 | F8: 8.677514 | G8: 8.064343 | H8: 7.494101 | I8: 7.220181
A10: Lower 48 Onshore | D10: 6.94377 | E10: 7.212075 | F10: 7.040334 | G10: 6.383477 | H10: 5.791162 | I10: 5.231455
A11: Northeast | B11: 0.085000001 | C11: 0.085 | D11: 0.052458 | E11: 0.037771 | F11: 0.030844 | G11: 0.022286 | H11: 0.0191 | I11: 0.029056
A12: Gulf Coast | B12: 0.537 | C12: 0.527 | D12: 2.423465 | E12: 2.510413 | F12: 2.224121 | G12: 2.07325 | H12: 1.843749 | I12: 1.572722
A13: Midcontinent | B13: 0.30700001 | C13: 0.344 | D13: 0.394037 | E13: 0.38031 | F13: 0.46188 | G13: 0.36359 | H13: 0.318279 | I13: 0.297892
A14: Southwest | B14: 0.94599998 | C14: 0.94 | D14: 1.826651 | E14: 1.982252 | F14: 1.96632 | G14: 1.722773 | H14: 1.60502 | I14: 1.539118
A15: Rocky Mountain | B15: 0.45100001 | C15: 0.685 | D15: 1.705978 | E15: 1.795065 | F15: 1.841 | G15: 1.689474 | H15: 1.490282 | I15: 1.286249
A16: West Coast | B16: 0.58600003 | C16: 0.53 | D16: 0.541181 | E16: 0.506264 | F16: 0.51617 | G16: 0.512102 | H16: 0.514732 | I16: 0.506418
A18: Lower 48 Offshore | D18: 1.631196 | E18: 1.903324 | F18: 1.63718 | G18: 1.680866 | H18: 1.702939 | I18: 1.988725
A19: Gulf | B19: 1.3 | C19: 1.698 | D19: 1.571857 | E19: 1.853971 | F19: 1.59384 | G19: 1.584825 | H19: 1.54986 | I19: 1.698679
A20: Shallow | B20: 0.3303304 | C20: 0.323602 | D20: 0.144269 | E20: 0.131409 | F20: 0.144515 | G20: 0.143921 | H20: 0.1337 | I20: 0.119727
A21: Deep | B21: 0.96966952 | C21: 1.374398 | D21: 1.427588 | E21: 1.722562 | F21: 1.449324 | G21: 1.440904 | H21: 1.416159 | I21: 1.578953
A22: Pacific | B22: 0.115 | C22: 0.091 | D22: 0.059339 | E22: 0.049353 | F22: 0.04334 | G22: 0.070796 | H22: 0.136281 | I22: 0.175838
A23: Atlantic | B23: 0 | C23: 0 | D23: 0 | E23: 0 | F23: 0 | G23: 0.025246 | H23: 0.016798 | I23: 0.114207
A25: Wellhead Prices (2012 dollars per barrel)
A27: Lower 48 Average | B27: 52.372932 | C27: 78.62236 | D27: 93.152596 | E27: 92.93071 | F27: 104.90037 | G27: 114.69336 | H27: 125.59007 | I27: 137.62721 | L27: =B27/Conv!$C$46/Conv!$I$5/1000000*Conv!$J$39 -> 8.2483996 | M27: =C27/Conv!$C$46/Conv!$I$5/1000000*Conv!$J$42 -> 11.740853 | N27: =D27/Conv!$C$46/Conv!$I$5/1000000*Conv!$J$45 -> 13.24802 | O27: =E27/Conv!$C$46/Conv!$I$5/1000000*Conv!$J$45 -> 13.216464 | P27: =F27/Conv!$C$46/Conv!$I$5/1000000*Conv!$J$45 -> 14.918771 | Q27: =G27/Conv!$C$46/Conv!$I$5/1000000*Conv!$J$45 -> 16.311515 | R27: =H27/Conv!$C$46/Conv!$I$5/1000000*Conv!$J$45 -> 17.861229 | S27: =I27/Conv!$C$46/Conv!$I$5/1000000*Conv!$J$45 -> 19.573133
A29: Lower 48 Onshore | L29: 2005 | M29: 2010 | N29: 2015 | O29: 2020 | P29: 2025 | Q29: 2030 | R29: 2035 | S29: 2040 | T29: Growth 2045+
A30: Northeast | B30: 54.113808 | C30: 77.842354 | D30: 89.464996 | E30: 89.111496 | F30: 101.57706 | G30: 110.88205 | H30: 121.45058 | I30: 132.9127 | K30: R1 | L30: =B30/Conv!$C$46/Conv!$I$5/1000000*Conv!$J$39 -> 8.5225763 | M30: =C30/Conv!$C$46/Conv!$I$5/1000000*Conv!$J$42 -> 11.624373 | N30: =D30/Conv!$C$46/Conv!$I$5/1000000*Conv!$J$45 -> 12.723575 | O30: =E30/Conv!$C$46/Conv!$I$5/1000000*Conv!$J$45 -> 12.673301 | P30: =F30/Conv!$C$46/Conv!$I$5/1000000*Conv!$J$45 -> 14.446134 | Q30: =G30/Conv!$C$46/Conv!$I$5/1000000*Conv!$J$45 -> 15.769476 | R30: =H30/Conv!$C$46/Conv!$I$5/1000000*Conv!$J$45 -> 17.272516 | S30: =I30/Conv!$C$46/Conv!$I$5/1000000*Conv!$J$45 -> 18.902642 | T30: =1+(S30-R30)/R30 -> 1.0943769
A31: Gulf Coast | B31: 54.577995 | C31: 77.609558 | D31: 96.386139 | E31: 96.451653 | F31: 108.72755 | G31: 118.38062 | H31: 129.07098 | I31: 140.40346 | K31: R2 | L31: =B30/Conv!$C$46/Conv!$I$5/1000000*Conv!$J$39 -> 8.5225763 | M31: =C30/Conv!$C$46/Conv!$I$5/1000000*Conv!$J$42 -> 11.624373 | N31: =D30/Conv!$C$46/Conv!$I$5/1000000*Conv!$J$45 -> 12.723575 | O31: =E30/Conv!$C$46/Conv!$I$5/1000000*Conv!$J$45 -> 12.673301 | P31: =F30/Conv!$C$46/Conv!$I$5/1000000*Conv!$J$45 -> 14.446134 | Q31: =G30/Conv!$C$46/Conv!$I$5/1000000*Conv!$J$45 -> 15.769476 | R31: =H30/Conv!$C$46/Conv!$I$5/1000000*Conv!$J$45 -> 17.272516 | S31: =I30/Conv!$C$46/Conv!$I$5/1000000*Conv!$J$45 -> 18.902642 | T31: =1+(S31-R31)/R31 -> 1.0943769
A32: Midcontinent | B32: 55.465111 | C32: 74.92894 | D32: 90.162102 | E32: 89.530052 | F32: 101.84438 | G32: 111.83901 | H32: 124.4508 | I32: 137.41544 | K32: R3 | L32: =B32/Conv!$C$46/Conv!$I$5/1000000*Conv!$J$39 -> 8.7353978 | M32: =C32/Conv!$C$46/Conv!$I$5/1000000*Conv!$J$42 -> 11.189307 | N32: =D32/Conv!$C$46/Conv!$I$5/1000000*Conv!$J$45 -> 12.822717 | O32: =E32/Conv!$C$46/Conv!$I$5/1000000*Conv!$J$45 -> 12.732828 | P32: =F32/Conv!$C$46/Conv!$I$5/1000000*Conv!$J$45 -> 14.484153 | Q32: =G32/Conv!$C$46/Conv!$I$5/1000000*Conv!$J$45 -> 15.905574 | R32: =H32/Conv!$C$46/Conv!$I$5/1000000*Conv!$J$45 -> 17.699203 | S32: =I32/Conv!$C$46/Conv!$I$5/1000000*Conv!$J$45 -> 19.543014 | T32: =1+(S32-R32)/R32 -> 1.1041748
A33: Southwest | B33: 54.309799 | C33: 75.461891 | D33: 92.778984 | E33: 91.732101 | F33: 103.95422 | G33: 113.66377 | H33: 124.9257 | I33: 137.87936 | K33: R4 | L33: =B32/Conv!$C$46/Conv!$I$5/1000000*Conv!$J$39 -> 8.7353978 | M33: =C32/Conv!$C$46/Conv!$I$5/1000000*Conv!$J$42 -> 11.189307 | N33: =D32/Conv!$C$46/Conv!$I$5/1000000*Conv!$J$45 -> 12.822717 | O33: =E32/Conv!$C$46/Conv!$I$5/1000000*Conv!$J$45 -> 12.732828 | P33: =F32/Conv!$C$46/Conv!$I$5/1000000*Conv!$J$45 -> 14.484153 | Q33: =G32/Conv!$C$46/Conv!$I$5/1000000*Conv!$J$45 -> 15.905574 | R33: =H32/Conv!$C$46/Conv!$I$5/1000000*Conv!$J$45 -> 17.699203 | S33: =I32/Conv!$C$46/Conv!$I$5/1000000*Conv!$J$45 -> 19.543014 | T33: =1+(S33-R33)/R33 -> 1.1041748
A34: Rocky Mountain | B34: 52.484001 | C34: 83.080177 | D34: 86.387299 | E34: 85.80587 | F34: 97.814186 | G34: 107.20132 | H34: 117.59627 | I34: 129.98877 | K34: R5 | L34: =B30/Conv!$C$46/Conv!$I$5/1000000*Conv!$J$39 -> 8.5225763 | M34: =C30/Conv!$C$46/Conv!$I$5/1000000*Conv!$J$42 -> 11.624373 | N34: =D30/Conv!$C$46/Conv!$I$5/1000000*Conv!$J$45 -> 12.723575 | O34: =E30/Conv!$C$46/Conv!$I$5/1000000*Conv!$J$45 -> 12.673301 | P34: =F30/Conv!$C$46/Conv!$I$5/1000000*Conv!$J$45 -> 14.446134 | Q34: =G30/Conv!$C$46/Conv!$I$5/1000000*Conv!$J$45 -> 15.769476 | R34: =H30/Conv!$C$46/Conv!$I$5/1000000*Conv!$J$45 -> 17.272516 | S34: =I30/Conv!$C$46/Conv!$I$5/1000000*Conv!$J$45 -> 18.902642 | T34: =1+(S34-R34)/R34 -> 1.0943769
A35: West Coast | B35: 48.564205 | C35: 76.567749 | D35: 94.27951 | E35: 95.1558 | F35: 108.13189 | G35: 118.0797 | H35: 127.97588 | I35: 137.8952 | K35: R6 | L35: =B33/Conv!$C$46/Conv!$I$5/1000000*Conv!$J$39 -> 8.5534437 | M35: =C33/Conv!$C$46/Conv!$I$5/1000000*Conv!$J$42 -> 11.268894 | N35: =D33/Conv!$C$46/Conv!$I$5/1000000*Conv!$J$45 -> 13.194886 | O35: =E33/Conv!$C$46/Conv!$I$5/1000000*Conv!$J$45 -> 13.046 | P35: =F33/Conv!$C$46/Conv!$I$5/1000000*Conv!$J$45 -> 14.784211 | Q35: =G33/Conv!$C$46/Conv!$I$5/1000000*Conv!$J$45 -> 16.165089 | R35: =H33/Conv!$C$46/Conv!$I$5/1000000*Conv!$J$45 -> 17.766742 | S35: =I33/Conv!$C$46/Conv!$I$5/1000000*Conv!$J$45 -> 19.608993 | T35: =1+(S35-R35)/R35 -> 1.103691
K36: R7 | L36: =AVERAGE((B33*B14+B38*B19)/(B14+B19))/Conv!$C$46/Conv!$I$5/1000000*Conv!$J$39 -> 8.2910939 | M36: =AVERAGE((C33*C14+C38*C19)/(C14+C19))/Conv!$C$46/Conv!$I$5/1000000*Conv!$J$42 -> 11.773723 | N36: =AVERAGE((D33*D14+D38*D19)/(D14+D19))/Conv!$C$46/Conv!$I$5/1000000*Conv!$J$45 -> 13.432157 | O36: =AVERAGE((E33*E14+E38*E19)/(E14+E19))/Conv!$C$46/Conv!$I$5/1000000*Conv!$J$45 -> 13.370381 | P36: =AVERAGE((F33*F14+F38*F19)/(F14+F19))/Conv!$C$46/Conv!$I$5/1000000*Conv!$J$45 -> 15.088127 | Q36: =AVERAGE((G33*G14+G38*G19)/(G14+G19))/Conv!$C$46/Conv!$I$5/1000000*Conv!$J$45 -> 16.486511 | R36: =AVERAGE((H33*H14+H38*H19)/(H14+H19))/Conv!$C$46/Conv!$I$5/1000000*Conv!$J$45 -> 18.056357 | S36: =AVERAGE((I33*I14+I38*I19)/(I14+I19))/Conv!$C$46/Conv!$I$5/1000000*Conv!$J$45 -> 19.797325 | T36: =1+(S36-R36)/R36 -> 1.0964186
A37: Lower 48 Offshore | K37: R8 | L37: =B34/Conv!$C$46/Conv!$I$5/1000000*Conv!$J$39 -> 8.2658922 | M37: =C34/Conv!$C$46/Conv!$I$5/1000000*Conv!$J$42 -> 12.406549 | N37: =D34/Conv!$C$46/Conv!$I$5/1000000*Conv!$J$45 -> 12.28587 | O37: =E34/Conv!$C$46/Conv!$I$5/1000000*Conv!$J$45 -> 12.20318 | P37: =F34/Conv!$C$46/Conv!$I$5/1000000*Conv!$J$45 -> 13.910984 | Q37: =G34/Conv!$C$46/Conv!$I$5/1000000*Conv!$J$45 -> 15.246009 | R37: =H34/Conv!$C$46/Conv!$I$5/1000000*Conv!$J$45 -> 16.724362 | S37: =I34/Conv!$C$46/Conv!$I$5/1000000*Conv!$J$45 -> 18.486805 | T37: =1+(S37-R37)/R37 -> 1.1053818
A38: Gulf | B38: 51.431843 | C38: 80.713936 | D38: 96.386139 | E38: 96.451653 | F38: 108.72755 | G38: 118.38062 | H38: 129.07098 | I38: 140.40346 | K38: R9 | L38: =AVERAGE((B35*B16+B39*B22+B71*B62)/(B16+B22+B71))/Conv!$C$46/Conv!$I$5/1000000*Conv!$J$39 -> 8.2247109 | M38: =AVERAGE((C35*C16+C39*C22+C71*C62)/(C16+C22+C71))/Conv!$C$46/Conv!$I$5/1000000*Conv!$J$42 -> 11.726426 | N38: =AVERAGE((D35*D16+D39*D22+D71*D62)/(D16+D22+D71))/Conv!$C$46/Conv!$I$5/1000000*Conv!$J$45 -> 13.33853 | O38: =AVERAGE((E35*E16+E39*E22+E71*E62)/(E16+E22+E71))/Conv!$C$46/Conv!$I$5/1000000*Conv!$J$45 -> 13.393571 | P38: =AVERAGE((F35*F16+F39*F22+F71*F62)/(F16+F22+F71))/Conv!$C$46/Conv!$I$5/1000000*Conv!$J$45 -> 15.208938 | Q38: =AVERAGE((G35*G16+G39*G22+G71*G62)/(G16+G22+G71))/Conv!$C$46/Conv!$I$5/1000000*Conv!$J$45 -> 16.652501 | R38: =AVERAGE((H35*H16+H39*H22+H71*H62)/(H16+H22+H71))/Conv!$C$46/Conv!$I$5/1000000*Conv!$J$45 -> 18.075859 | S38: =AVERAGE((I35*I16+I39*I22+I71*I62)/(I16+I22+I71))/Conv!$C$46/Conv!$I$5/1000000*Conv!$J$45 -> 19.600729 | T38: =1+(S38-R38)/R38 -> 1.0843595
A39: Pacific | B39: 46.212326 | C39: 71.208015 | D39: 94.27951 | E39: 95.1558 | F39: 108.13189 | G39: 118.0797 | H39: 127.97588 | I39: 137.8952
A40: Atlantic | B40: - - | C40: 77.842354 | D40: 96.192085 | E40: 95.612595 | F40: 107.33659 | G40: 118.33994 | H40: 128.86078 | I40: 140.8842
A42: 1/ Includes lease condensate.
A43: - - = Not applicable.
A44: Note: Oil and Gas Supply Model regions are defined in Appendix F of the Annual Energy Outlook. Totals may not equal sum of
A45: components due to independent rounding. Data for 2009 and 2010
A46: may differ slightly from official EIA data
A47: reports due to internal conversion factors within the AEO2012 National Energy Modeling System.
A48: Sources: 2009 and 2010: U.S. Energy Information Administration (EIA), Petroleum Supply
A49: Annual 2010, DOE/EIA-0340(2010)/1 (Washington, DC, July 2011); EIA, Petroleum Marketing Monthly, DOE/EIA-0380(2011/08) (Washington, DC, August 2011);
A50: and EIA, Office of Energy Analysis. Projections: EIA, AEO2012 National Energy Modeling System.
A55: AEO2014 Oil and Gas Supply, Reference case
A57: Production and Supply | B57: 2005 | C57: 2010 | D57: 2015 | E57: 2020 | F57: 2025 | G57: 2030 | H57: 2035 | I57: 2040
A59: Crude Oil
A61: Lower 48 Average Wellhead Price 1/
A62: (2010 dollars per barrel) | B62: 52.372932 | C62: 78.62236 | D62: 93.152596 | E62: 92.93071 | F62: 104.90037 | G62: 114.69336 | H62: 125.59007 | I62: 137.62721
A64: Production (million barrels per day) 2/
A65: United States Total | B65: 5.191 | C65: 5.51 | D65: 9.037802 | E65: 9.552541 | F65: 9.004183 | G65: 8.304715 | H65: 7.872269 | I65: 7.480168
A66: Lower 48 Onshore | B66: 2.9119999 | C66: 3.111 | D66: 6.94377 | E66: 7.212075 | F66: 7.040334 | G66: 6.383478 | H66: 5.791162 | I66: 5.231456
A67: Tight Oil 3/ | B67: 1.415 | C67: 1.789 | D67: 4.49443 | E67: 4.788713 | F67: 4.541762 | G67: 4.168042 | H67: 3.688242 | I67: 3.196477
A68: Carbon Dioxide Enhanced Oil Recovery | B68: 0.86400002 | C68: 0.61 | D68: 0.285286 | E68: 0.363147 | F68: 0.471589 | G68: 0.580677 | H68: 0.661234 | I68: 0.740367
A69: Other | D69: 2.164054 | E69: 2.060216 | F69: 2.026984 | G69: 1.63476 | H69: 1.441686 | I69: 1.294612
A70: Lower 48 Offshore | D70: 1.631196 | E70: 1.903324 | F70: 1.63718 | G70: 1.680866 | H70: 1.702939 | I70: 1.988725
A71: Alaska | B71: 18.848001 | C71: 17.634153 | D71: 0.462835 | E71: 0.437142 | F71: 0.326669 | G71: 0.240371 | H71: 0.378168 | I71: 0.259987
A73: Lower 48 End of Year Reserves 2/
A74: (billion barrels) | B74: 18.75 | C74: 18.33 | D74: 28.010019 | E74: 31.779066 | F74: 33.012753 | G74: 34.422798 | H74: 34.579945 | I74: 35.445549

Sheet Domestic Crude Oil Prod
A1: Back to Contents | B1: Data 1: Crude Oil Production
A2: Sourcekey | B2: MCRFPUS1 | C2: MCRFPP11 | D2: MCRFPFL1 | E2: MCRFPNY1 | F2: MCRFPPA1 | G2: MCRFPVA1 | H2: MCRFPWV1 | I2: MCRFPP21 | J2: MCRFPIL1 | K2: MCRFPIN1 | L2: MCRFPKS1 | M2: MCRFPKY1 | N2: MCRFP_SMI_1 | O2: MCRFPMO1 | P2: MCRFPNE1 | Q2: MCRFPND1 | R2: MCRFPOH1 | S2: MCRFPOK1 | T2: MCRFPSD1 | U2: MCRFPTN1 | V2: MCRFPP31 | W2: MCRFPAL1 | X2: MCRFPAR1 | Y2: MCRFPLA1 | Z2: MCRFPMS1 | AA2: MCRFPNM1 | AB2: MCRFPTX1 | AC2: MCRFP3FM1 | AD2: MCRFPP41 | AE2: MCRFPCO1 | AF2: MCRFPMT1 | AG2: MCRFPUT1 | AH2: MCRFPWY1 | AI2: MCRFPP51 | AJ2: MCRFPAK1 | AK2: MCRFPAKS1 | AL2: MANFPAK1 | AM2: MCRFPAZ1 | AN2: MCRFPCA1 | AO2: MCRFPNV1 | AP2: MCRFP5F1
A3: Date | B3: U.S. Field Production of Crude Oil (Thousand Barrels) | C3: East Coast (PADD 1) Field Production of Crude Oil (Thousand Barrels) | D3: Florida Field Production of Crude Oil (Thousand Barrels) | E3: New York Field Production of Crude Oil (Thousand Barrels) | F3: Pennsylvania Field Production of Crude Oil (Thousand Barrels) | G3: Virginia Field Production of Crude Oil (Thousand Barrels) | H3: West Virginia Field Production of Crude Oil (Thousand Barrels) | I3: Midwest (PADD 2) Field Production of Crude Oil (Thousand Barrels) | J3: Illinois Field Production of Crude Oil (Thousand Barrels) | K3: Indiana Field Production of Crude Oil (Thousand Barrels) | L3: Kansas Field Production of Crude Oil (Thousand Barrels) | M3: Kentucky Field Production of Crude Oil (Thousand Barrels) | N3: Michigan Field Production of Crude Oil (Thousand Barrels) | O3: Missouri Field Production of Crude Oil (Thousand Barrels) | P3: Nebraska Field Production of Crude Oil (Thousand Barrels) | Q3: North Dakota Field Production of Crude Oil (Thousand Barrels) | R3: Ohio Field Production of Crude Oil (Thousand Barrels) | S3: Oklahoma Field Production of Crude Oil (Thousand Barrels) | T3: South Dakota Field Production of Crude Oil (Thousand Barrels) | U3: Tennessee Field Production of Crude Oil (Thousand Barrels) | V3: Gulf Coast (PADD 3) Field Production of Crude Oil (Thousand Barrels) | W3: Alabama Field Production of Crude Oil (Thousand Barrels) | X3: Arkansas Field Production of Crude Oil (Thousand Barrels) | Y3: Louisiana Field Production of Crude Oil (Thousand Barrels) | Z3: Mississippi Field Production of Crude Oil (Thousand Barrels) | AA3: New Mexico Field Production of Crude Oil (Thousand Barrels) | AB3: Texas Field Production of Crude Oil (Thousand Barrels) | AC3: Federal Offshore--Gulf of Mexico Field Production of Crude Oil (Thousand Barrels) | AD3: Rocky Mountain (PADD 4) Field Production of Crude Oil (Thousand Barrels) | AE3: Colorado Field Production of Crude Oil (Thousand Barrels) | AF3: Montana Field Production of Crude Oil (Thousand Barrels) | AG3: Utah Field Production of Crude Oil (Thousand Barrels) | AH3: Wyoming Field Production of Crude Oil (Thousand Barrels) | AI3: West Coast (PADD 5) Field Production of Crude Oil (Thousand Barrels) | AJ3: Alaska Field Production of Crude Oil (Thousand Barrels) | AK3: Alaska South Field Production of Crude Oil (Thousand Barrels) | AL3: Alaska North Slope Crude Oil Production (Thousand Barrels) | AM3: Arizona Field Production of Crude Oil (Thousand Barrels) | AN3: California Field Production of Crude Oil (Thousand Barrels) | AO3: Nevada Field Production of Crude Oil (Thousand Barrels) | AP3: Federal Offshore California Field Production of Crude Oil (Thousand Barrels)
D4: 5 | E4: 2 | F4: 2 | G4: 5 | H4: 5 | J4: 3 | K4: 3 | L4: 4 | M4: 6 | N4: 3 | O4: 4 | P4: 4 | Q4: 4 | R4: 3 | S4: 7 | T4: 4 | U4: 6 | W4: 6 | X4: 7 | Y4: 7 | Z4: 6 | AA4: 8 | AB4: 7 | AC4: 7 | AE4: 8 | AF4: 8 | AG4: 8 | AH4: 8 | AJ4: 9 | AM4: 8 | AN4: 9 | AO4: 8 | AP4: 9
A5: 37437 | B5: 2097124 | C5: 7458 | D5: 3656 | E5: 165 | F5: 2233 | G5: 22 | H5: 1382 | I5: 164635 | J5: 12051 | K5: 1962 | L5: 32721 | M5: 2679 | N5: 7219 | O5: 95 | P5: 2779 | Q5: 30993 | R5: 6004 | S5: 66642 | T5: 1214 | U5: 275 | V5: 1174305 | W5: 8631 | X5: 7344 | Y5: 93477 | Z5: 18015 | AA5: 67041 | AB5: 411985 | AC5: 567810 | AD5: 102982 | AE5: 17734 | AF5: 16855 | AG5: 13676 | AH5: 54717 | AI5: 647745 | AJ5: 359335 | AK5: 11302 | AL5: 348034 | AM5: 63 | AN5: 258010 | AO5: 553 | AP5: 29783
A6: 37802 | B6: 2073453 | C6: 7170 | D6: 3262 | E6: 144 | F6: 2425 | G6: 5 | H6: 1334 | I6: 161360 | J6: 11696 | K6: 1865 | L6: 33944 | M6: 2538 | N6: 6524 | O6: 82 | P6: 2755 | Q6: 29406 | R6: 5647 | S6: 65356 | T6: 1237 | U6: 311 | V6: 1162869 | W6: 7877 | X6: 7226 | Y6: 90111 | Z6: 16593 | AA6: 66130 | AB6: 405801 | AC6: 569131 | AD6: 105931 | AE6: 21109 | AF6: 19320 | AG6: 13096 | AH6: 52407 | AI6: 636123 | AJ6: 355582 | AK6: 10056 | AL6: 345526 | AM6: 47 | AN6: 250000 | AO6: 493 | AP6: 30000
A7: 38168 | B7: 1983302 | C7: 6941 | D7: 2875 | E7: 170 | F7: 2538 | G7: 19 | H7: 1339 | I7: 159309 | J7: 10984 | K7: 1755 | L7: 33858 | M7: 2548 | N7: 6409 | O7: 88 | P7: 2507 | Q7: 31154 | R7: 5785 | S7: 62502 | T7: 1357 | U7: 361 | V7: 1103743 | W7: 7443 | X7: 6732 | Y7: 83411 | Z7: 17153 | AA7: 64236 | AB7: 392867 | AC7: 531900 | AD7: 113069 | AE7: 22097 | AF7: 24724 | AG7: 14629 | AH7: 51619 | AI7: 600239 | AJ7: 332465 | AK7: 8225 | AL7: 324241 | AM7: 52 | AN7: 240206 | AO7: 463 | AP7: 27054
A8: 38533 | B8: 1890106 | C8: 8299 | D8: 2585 | E8: 197 | F8: 3947 | G8: 8 | H8: 1563 | I8: 161587 | J8: 10207 | K8: 1727 | L8: 33823 | M8: 2535 | N8: 5549 | O8: 85 | P8: 2413 | Q8: 35660 | R8: 5652 | S8: 62142 | T8: 1469 | U8: 324 | V8: 1023499 | W8: 7861 | X8: 6344 | Y8: 75483 | Z8: 17695 | AA8: 60660 | AB8: 387680 | AC8: 467776 | AD8: 123956 | AE8: 22823 | AF8: 32855 | AG8: 16651 | AH8: 51626 | AI8: 572765 | AJ8: 315420 | AK8: 7110 | AL8: 308311 | AM8: 50 | AN8: 230294 | AO8: 447 | AP8: 26554
A9: 38898 | B9: 1862259 | C9: 8062 | D9: 2360 | E9: 319 | F9: 3626 | G9: 7 | H9: 1749 | I9: 167298 | J9: 10323 | K9: 1731 | L9: 35651 | M9: 2340 | N9: 5093 | O9: 87 | P9: 2313 | Q9: 39911 | R9: 5422 | S9: 62841 | T9: 1394 | U9: 192 | V9: 1035904 | W9: 7531 | X9: 6104 | Y9: 73876 | Z9: 17356 | AA9: 59818 | AB9: 397220 | AC9: 474000 | AD9: 130466 | AE9: 23390 | AF9: 36262 | AG9: 17910 | AH9: 52904 | AI9: 520529 | AJ9: 270486 | AK9: 6231 | AL9: 264255 | AM9: 55 | AN9: 223449 | AO9: 426 | AP9: 26113
A10: 39263 | B10: 1848450 | C10: 7703 | D10: 2078 | E10: 380 | F10: 3653 | G10: 18 | H10: 1574 | I10: 171521 | J10: 9609 | K10: 1727 | L10: 36490 | M10: 2666 | N10: 5201 | O10: 80 | P10: 2334 | Q10: 45058 | R10: 5455 | S10: 60952 | T10: 1665 | U10: 284 | V10: 1032088 | W10: 7173 | X10: 6031 | Y10: 76651 | Z10: 20396 | AA10: 58831 | AB10: 396894 | AC10: 466112 | AD10: 131716 | AE10: 23237 | AF10: 34829 | AG10: 19520 | AH10: 54130 | AI10: 505423 | AJ10: 263595 | AK10: 5488 | AL10: 258107 | AM10: 43 | AN10: 216778 | AO10: 408 | AP10: 24600
