Workbook
Name _1995_Implicit_GDP_Deflator: 'RTEKTY Conv'!#REF!
Name _2001_Implicit_GDP_Deflator: 'RTEKTY Conv'!#REF!
Name avg_water_heater_PJ: #REF!
Name avg_water_heater_PJ: #REF!
Name avg_water_heater_PJ: #REF!
Name avg_water_heater_PJ: #REF!
Name btu_per_watthr: 'RTEKTY Conv'!#REF!
Name btu_per_watthr: '[1]Conversion Factors'!$B$5
Name days_per_year: 'RTEKTY Conv'!#REF!
Name days_per_year: '[1]Conversion Factors'!$B$3
Name dollar____per__m: 'RTEKTY Conv'!#REF!
Name dollar____per__m: '[1]Conversion Factors'!$B$7
Name hours_per_day: 'RTEKTY Conv'!#REF!
Name hours_per_day: '[1]Conversion Factors'!$B$2
Name j_per_btu: 'RTEKTY Conv'!#REF!
Name j_per_btu: '[1]Conversion Factors'!$B$4
Name j_per_pj: 'RTEKTY Conv'!#REF!
Name j_per_pj: '[1]Conversion Factors'!$B$6
Name kwhr_per_j: 'RTEKTY Conv'!#REF!
Name lumens_per_billion_lumens: '[1]Conversion Factors'!$B$9
Name unit_per_million_unit: 'RTEKTY Conv'!#REF!

Sheet ANSv6.1-Commodities
A1: ANSWER-Commodities
B7: CommName | C7: CommDesc | D7: CommUnit | E7: Set Memberships | F7: Comment

Sheet ANSv6.1-Technologies
A1: ANSWER-Technologies
B7: TechName | C7: TechDesc | D7: TACTUnit | E7: TCAPUnit | F7: Set Memberships | G7: Comment

Sheet UC_SOL
A1: Minimum production of decentralized Commercial PV
A2: ~UC_Sets: R_E: AllRegions
E3: ~UC_T: UC_RHSRTS~LO
A4: UC_N | B4: Pset_PN | C4: Pset_CI | D4: Cset_CN | E4: Year | F4: UC_FLO | G4: UC_RHSRTS~LO~0 | H4: R0 | I4: R1 | J4: R2 | K4: R3 | L4: R4 | M4: R5 | N4: R6 | O4: UC_Desc
A5: UC_SOLRESELCactLO | B5: ESOLPVRES* | C5: SOLRES | D5: RESELC | E5: 2010 | F5: 1 | G5: 15 | J5: ='Rooftop Calc'!AC$65 -> 0.0071945835 | K5: ='Rooftop Calc'!AD$65 -> 0.0037523355 | L5: ='Rooftop Calc'!AE$65 -> 0.0011972254 | M5: ='Rooftop Calc'!AF$65 -> 0.0017437956 | N5: ='Rooftop Calc'!AG$65 -> 0.012993033 | Q5: =SUM(J5:N5) -> 0.026880973
B6: ESOLPVRES* | C6: SOLRES | D6: RESELC | E6: 2015 | F6: 1 | J6: ='Rooftop Calc'!AC$71 -> 0.109328 | K6: ='Rooftop Calc'!AD$71 -> 0.073448493 | L6: ='Rooftop Calc'!AE$71 -> 0.0093117528 | M6: ='Rooftop Calc'!AF$71 -> 0.32034551 | N6: ='Rooftop Calc'!AG$71 -> 0.17523498 | Q6: =SUM(J6:N6) -> 0.68766875
B7: ESOLPVRES* | C7: SOLRES | D7: RESELC | E7: 2020 | F7: 1 | J7: ='Rooftop Calc'!AC$77 -> 0.24496493 | K7: ='Rooftop Calc'!AD$77 -> 0.13820064 | L7: ='Rooftop Calc'!AE$77 -> 0.017877615 | M7: ='Rooftop Calc'!AF$77 -> 0.57042833 | N7: ='Rooftop Calc'!AG$77 -> 0.47194746 | Q7: =SUM(J7:N7) -> 1.443419
B8: ESOLPVRES* | C8: SOLRES | D8: RESELC | E8: 2025 | F8: 1 | J8: ='Rooftop Calc'!AC$84 -> 0.43039234 | K8: ='Rooftop Calc'!AD$84 -> 0.20768834 | L8: ='Rooftop Calc'!AE$84 -> 0.024528867 | M8: ='Rooftop Calc'!AF$84 -> 1.0833094 | N8: ='Rooftop Calc'!AG$84 -> 0.89934986 | Q8: =SUM(J8:N8) -> 2.6452688
B9: ESOLPVRES* | C9: SOLRES | D9: RESELC | E9: 2030 | F9: 1 | J9: ='Rooftop Calc'!AC$91 -> 0.61581975 | K9: ='Rooftop Calc'!AD$91 -> 0.27717603 | L9: ='Rooftop Calc'!AE$91 -> 0.031180119 | M9: ='Rooftop Calc'!AF$91 -> 1.5961905 | N9: ='Rooftop Calc'!AG$91 -> 1.3267523 | Q9: =SUM(J9:N9) -> 3.8471186
B10: ESOLPVRES* | C10: SOLRES | D10: RESELC | E10: 2035 | F10: 1 | J10: ='Rooftop Calc'!AC$98 -> 0.80124716 | K10: ='Rooftop Calc'!AD$98 -> 0.34666373 | L10: ='Rooftop Calc'!AE$98 -> 0.037831371 | M10: ='Rooftop Calc'!AF$98 -> 2.1090715 | N10: ='Rooftop Calc'!AG$98 -> 1.7541547 | Q10: =SUM(J10:N10) -> 5.0489684
B11: ESOLPVRES* | C11: SOLRES | D11: RESELC | E11: 2040 | F11: 1 | J11: ='Rooftop Calc'!AC$105 -> 0.98667458 | K11: ='Rooftop Calc'!AD$105 -> 0.41615142 | L11: ='Rooftop Calc'!AE$105 -> 0.044482623 | M11: ='Rooftop Calc'!AF$105 -> 2.6219526 | N11: ='Rooftop Calc'!AG$105 -> 2.1815571 | Q11: =SUM(J11:N11) -> 6.2508183
B12: ESOLPVRES* | C12: SOLRES | D12: RESELC | E12: 2045 | F12: 1 | J12: ='Rooftop Calc'!AC$112 -> 1.1649074 | K12: ='Rooftop Calc'!AD$112 -> 0.48188678 | L12: ='Rooftop Calc'!AE$112 -> 0.04993665 | M12: ='Rooftop Calc'!AF$112 -> 3.1330899 | N12: ='Rooftop Calc'!AG$112 -> 2.5959664 | Q12: =SUM(J12:N12) -> 7.4257871
B13: ESOLPVRES* | C13: SOLRES | D13: RESELC | E13: 2050 | F13: 1 | J13: ='Rooftop Calc'!AC$119 -> 1.2410068 | K13: ='Rooftop Calc'!AD$119 -> 0.47792598 | L13: ='Rooftop Calc'!AE$119 -> 0.047276149 | M13: ='Rooftop Calc'!AF$119 -> 3.3256254 | N13: ='Rooftop Calc'!AG$119 -> 2.8481338 | Q13: =SUM(J13:N13) -> 7.9399682
B14: ESOLPVRES* | C14: SOLRES | D14: RESELC | E14: 2055 | F14: 1 | J14: ='Rooftop Calc'!AC$126 -> 1.3072238 | K14: ='Rooftop Calc'!AD$126 -> 0.46631225 | L14: ='Rooftop Calc'!AE$126 -> 0.042167162 | M14: ='Rooftop Calc'!AF$126 -> 3.7957449 | N14: ='Rooftop Calc'!AG$126 -> 3.138694 | Q14: =SUM(J14:N14) -> 8.7501421
A18: Maximum production of decentralized Commercial PV
A19: ~UC_Sets: R_E: AllRegions
E20: ~UC_T: UC_RHSRTS~UP
A21: UC_N | B21: Pset_PN | C21: Pset_CI | D21: Cset_CN | E21: Year | F21: UC_FLO | G21: UC_RHSRTS~UP~0 | H21: R0 | I21: R1 | J21: R2 | K21: R3 | L21: R4 | M21: R5 | N21: R6 | O21: UC_Desc
A22: UC_SOLRESELCactUP | B22: ESOLPVRES* | C22: SOLRES | D22: RESELC | E22: 2010 | F22: 1 | G22: 15 | J22: ='Rooftop Calc'!AC$65 -> 0.0071945835 | K22: ='Rooftop Calc'!AD$65 -> 0.0037523355 | L22: ='Rooftop Calc'!AE$65 -> 0.0011972254 | M22: ='Rooftop Calc'!AF$65 -> 0.0017437956 | N22: ='Rooftop Calc'!AG$65 -> 0.012993033
B23: ESOLPVRES* | C23: SOLRES | D23: RESELC | E23: 2015 | F23: 1 | J23: ='Rooftop Calc'!AC$71 -> 0.109328 | K23: ='Rooftop Calc'!AD$71 -> 0.073448493 | L23: ='Rooftop Calc'!AE$71 -> 0.0093117528 | M23: ='Rooftop Calc'!AF$71 -> 0.32034551 | N23: ='Rooftop Calc'!AG$71 -> 0.17523498
B24: ESOLPVRES* | C24: SOLRES | D24: RESELC | E24: 2020 | F24: 1 | J24: ='Rooftop Calc'!AK$77 -> 0.37640069 | K24: ='Rooftop Calc'!AL$77 -> 0.25287267 | L24: ='Rooftop Calc'!AM$77 -> 0.032059035 | M24: ='Rooftop Calc'!AN$77 -> 1.1029038 | N24: ='Rooftop Calc'!AO$77 -> 0.60330901
B25: ESOLPVRES* | C25: SOLRES | D25: RESELC | E25: 2025 | F25: 1 | J25: ='Rooftop Calc'!AK$84 -> 0.64269247 | K25: ='Rooftop Calc'!AL$84 -> 0.43177221 | L25: ='Rooftop Calc'!AM$84 -> 0.054739804 | M25: ='Rooftop Calc'!AN$84 -> 1.883174 | N25: ='Rooftop Calc'!AO$84 -> 1.0301314
B26: ESOLPVRES* | C26: SOLRES | D26: RESELC | E26: 2030 | F26: 1 | J26: ='Rooftop Calc'!AK$91 -> 0.90976515 | K26: ='Rooftop Calc'!AL$91 -> 0.61119639 | L26: ='Rooftop Calc'!AM$91 -> 0.077487086 | M26: ='Rooftop Calc'!AN$91 -> 2.6657323 | N26: ='Rooftop Calc'!AO$91 -> 1.4582054
B27: ESOLPVRES* | C27: SOLRES | D27: RESELC | E27: 2035 | F27: 1 | J27: ='Rooftop Calc'!AK$98 -> 1.1760569 | K27: ='Rooftop Calc'!AL$98 -> 0.79009593 | L27: ='Rooftop Calc'!AM$98 -> 0.10016786 | M27: ='Rooftop Calc'!AN$98 -> 3.4460025 | N27: ='Rooftop Calc'!AO$98 -> 1.8850278
B28: ESOLPVRES* | C28: SOLRES | D28: RESELC | E28: 2040 | F28: 1 | J28: ='Rooftop Calc'!AK$105 -> 1.4431296 | K28: ='Rooftop Calc'!AL$105 -> 0.96952011 | L28: ='Rooftop Calc'!AM$105 -> 0.12291514 | M28: ='Rooftop Calc'!AN$105 -> 4.2285608 | N28: ='Rooftop Calc'!AO$105 -> 2.3131018
B29: ESOLPVRES* | C29: SOLRES | D29: RESELC | E29: 2045 | F29: 1 | J29: ='Rooftop Calc'!AK$112 -> 1.7094214 | K29: ='Rooftop Calc'!AL$112 -> 1.1484197 | L29: ='Rooftop Calc'!AM$112 -> 0.14559591 | M29: ='Rooftop Calc'!AN$112 -> 5.0088309 | N29: ='Rooftop Calc'!AO$112 -> 2.7399241
B30: ESOLPVRES* | C30: SOLRES | D30: RESELC | E30: 2050 | F30: 1 | J30: ='Rooftop Calc'!AK$119 -> 1.9764941 | K30: ='Rooftop Calc'!AL$119 -> 1.3278438 | L30: ='Rooftop Calc'!AM$119 -> 0.16834319 | M30: ='Rooftop Calc'!AN$119 -> 5.7913893 | N30: ='Rooftop Calc'!AO$119 -> 3.1679982
B31: ESOLPVRES* | C31: SOLRES | D31: RESELC | E31: 2055 | F31: 1 | J31: ='Rooftop Calc'!AK$126 -> 2.2427859 | K31: ='Rooftop Calc'!AL$126 -> 1.5067434 | L31: ='Rooftop Calc'!AM$126 -> 0.19102396 | M31: ='Rooftop Calc'!AN$126 -> 6.5716594 | N31: ='Rooftop Calc'!AO$126 -> 3.5948205
A34: Maximum capacity of decentralized Residential PV
A35: ~UC_Sets: R_E: AllRegions
E36: ~UC_T: UC_RHSRTS~UP
A37: UC_N | B37: Pset_PN | C37: Pset_CI | D37: Cset_CN | E37: Year | F37: UC_CAP | G37: UC_RHSRTS~UP~0 | H37: R0 | I37: R1 | J37: R2 | K37: R3 | L37: R4 | M37: R5 | N37: R6 | O37: UC_Desc
A38: UC_SOLRESELCCAPUP | B38: ESOLPVRES* | E38: 2025 | F38: 1 | G38: 5 | J38: =J39 -> 0.47406169 | K38: =K39 -> 0.31848306 | L38: =L39 -> 0.040377078 | M38: =M39 -> 1.3890635 | N38: =N39 -> 0.75984369
B39: ESOLPVRES* | E39: 2050 | F39: 1 | J39: =J31/31.54/0.15 -> 0.47406169 | K39: =K31/31.54/0.15 -> 0.31848306 | L39: =L31/31.54/0.15 -> 0.040377078 | M39: =M31/31.54/0.15 -> 1.3890635 | N39: =N31/31.54/0.15 -> 0.75984369

Sheet UC_RET
A1: Maximum Retrofit penetration
B3: ~UC_Sets: R_E: AllRegions
G5: ~UC_T: UC_COMPRD
B6: UC_N | C6: Pset_PN | D6: Pset_PD | E6: Pset_CI | F6: Cset_CN | G6: Year | H6: UC_FLO | I6: UC_RHSRTS~UP | J6: UC_RHSRTS~UP~0 | K6: R0 | L6: R1 | M6: R2 | N6: R3 | O6: R4 | P6: R5 | Q6: R6
B7: ="UC_"&F7&RIGHT(C7,6)&"UP" -> UC_RSHRETSMTUP | C7: RSHRETSMT | F7: RSH | G7: 2025 | H7: 1 | I7: 0 | J7: 5 | M7: 0 | N7: 0 | O7: 0 | P7: 0 | Q7: 0
C8: RSHRETSMT | F8: RSH | G8: 2050 | M8: =-Retrofit!$U$16 -> -0.061303428 | N8: =-Retrofit!$U$16 -> -0.061303428 | O8: =-Retrofit!$U$16 -> -0.061303428 | P8: =-Retrofit!$U$16 -> -0.061303428 | Q8: =-Retrofit!$U$16 -> -0.061303428
C9: RSHRETSMT | F9: RSH | G9: 2055 | M9: =M8 -> -0.061303428 | N9: =N8 -> -0.061303428 | O9: =O8 -> -0.061303428 | P9: =P8 -> -0.061303428 | Q9: =Q8 -> -0.061303428
B10: ="UC_"&F10&RIGHT(C10,6)&"UP" -> UC_RSHRETVEOUP | C10: RSHRETVEO | F10: RSH | G10: 2025 | H10: 1 | I10: 0 | J10: 5 | M10: 0 | N10: 0 | O10: 0 | P10: 0 | Q10: 0
C11: RSHRETVEO | F11: RSH | G11: 2050 | M11: =-Retrofit!$U$17 -> -0.011688391 | N11: =-Retrofit!$U$17 -> -0.011688391 | O11: =-Retrofit!$U$17 -> -0.011688391 | P11: =-Retrofit!$U$17 -> -0.011688391 | Q11: =-Retrofit!$U$17 -> -0.011688391
C12: RSHRETVEO | F12: RSH | G12: 2055 | M12: =M11 -> -0.011688391 | N12: =N11 -> -0.011688391 | O12: =O11 -> -0.011688391 | P12: =P11 -> -0.011688391 | Q12: =Q11 -> -0.011688391
B13: ="UC_"&F13&RIGHT(C13,6)&"UP" -> UC_RSHRETINRUP | C13: RSHRETINR | F13: RSH | G13: 2025 | H13: 1 | I13: 0 | J13: 5 | M13: 0 | N13: 0 | O13: 0 | P13: 0 | Q13: 0
C14: RSHRETINR | F14: RSH | G14: 2050 | M14: =-Retrofit!$U$18 -> -0.021582299 | N14: =-Retrofit!$U$18 -> -0.021582299 | O14: =-Retrofit!$U$18 -> -0.021582299 | P14: =-Retrofit!$U$18 -> -0.021582299 | Q14: =-Retrofit!$U$18 -> -0.021582299
C15: RSHRETINR | F15: RSH | G15: 2055 | M15: =M14 -> -0.021582299 | N15: =N14 -> -0.021582299 | O15: =O14 -> -0.021582299 | P15: =P14 -> -0.021582299 | Q15: =Q14 -> -0.021582299
B16: ="UC_"&F16&RIGHT(C16,6)&"UP" -> UC_RSHRETWIRUP | C16: RSHRETWIR | F16: RSH | G16: 2025 | H16: 1 | I16: 0 | J16: 5 | M16: 0 | N16: 0 | O16: 0 | P16: 0 | Q16: 0
C17: RSHRETWIR | F17: RSH | G17: 2050 | M17: =-Retrofit!$U$19 -> -0.058005459 | N17: =-Retrofit!$U$19 -> -0.058005459 | O17: =-Retrofit!$U$19 -> -0.058005459 | P17: =-Retrofit!$U$19 -> -0.058005459 | Q17: =-Retrofit!$U$19 -> -0.058005459
C18: RSHRETWIR | F18: RSH | G18: 2055 | M18: =M17 -> -0.058005459 | N18: =N17 -> -0.058005459 | O18: =O17 -> -0.058005459 | P18: =P17 -> -0.058005459 | Q18: =Q17 -> -0.058005459
B19: ="UC_"&F19&RIGHT(C19,6)&"UP" -> UC_RSHRETINWUP | C19: RSHRETINW | F19: RSH | G19: 2025 | H19: 1 | I19: 0 | J19: 5 | M19: 0 | N19: 0 | O19: 0 | P19: 0 | Q19: 0
C20: RSHRETINW | F20: RSH | G20: 2050 | M20: =-Retrofit!$U$20 -> -0.036253412 | N20: =-Retrofit!$U$20 -> -0.036253412 | O20: =-Retrofit!$U$20 -> -0.036253412 | P20: =-Retrofit!$U$20 -> -0.036253412 | Q20: =-Retrofit!$U$20 -> -0.036253412
C21: RSHRETINW | F21: RSH | G21: 2055 | M21: =M20 -> -0.036253412 | N21: =N20 -> -0.036253412 | O21: =O20 -> -0.036253412 | P21: =P20 -> -0.036253412 | Q21: =Q20 -> -0.036253412

Sheet UC_DMD
A3: Minimum capacity technology growth:
A4: ~UC_Sets: R_E: R2,R3,R4,R5,R6
A5: ~UC_Sets: T_SUC:
G6: ~UC_T
A7: UC_N | B7: Pset_PN | C7: Pset_CI | D7: Pset_CO | E7: UC_ATTR | F7: Year | G7: LimType | H7: UC_CAP~2015 | I7: UC_CAP~2020 | J7: UC_CAP~2025 | K7: UC_CAP~2030 | L7: UC_CAP~2035 | M7: UC_CAP~2040 | N7: UC_CAP~2045 | O7: UC_CAP~2050 | P7: UC_CAP~2055 | Q7: UC_CAP~RHS | R7: UC_RHSRTS | S7: UC_RHSRTS~0 | T7: UC_Desc
A8: UC_GrowthOfRES1 | B8: RSHERDV1* | E8: CAP, GROWTH | G8: UP | I8: 1.1 | J8: =I8 -> 1.1 | K8: =J8 -> 1.1 | L8: =K8 -> 1.1 | M8: =L8 -> 1.1 | N8: =M8 -> 1.1 | O8: =N8 -> 1.1 | P8: =O8 -> 1.1 | Q8: 1 | S8: 5
A9: UC_GrowthOfRES2 | B9: RWHDWHBS* | E9: CAP, GROWTH | G9: UP | H9: 1.1 | I9: =H9 -> 1.1 | J9: =I9 -> 1.1 | K9: =J9 -> 1.1 | L9: =K9 -> 1.1 | M9: =L9 -> 1.1 | N9: =M9 -> 1.1 | O9: =N9 -> 1.1 | P9: =O9 -> 1.1 | Q9: 1 | S9: 5
A10: UC_GrowthOfRES3 | B10: RWHDWHV1* | E10: CAP, GROWTH | G10: UP | H10: 1.1 | I10: =H10 -> 1.1 | J10: =I10 -> 1.1 | K10: =J10 -> 1.1 | L10: =K10 -> 1.1 | M10: =L10 -> 1.1 | N10: =M10 -> 1.1 | O10: =N10 -> 1.1 | P10: =O10 -> 1.1 | Q10: 1 | S10: 5
A11: UC_GrowthOfRES4 | B11: RWHDWHV2* | E11: CAP, GROWTH | G11: UP | H11: 1.1 | I11: =H11 -> 1.1 | J11: =I11 -> 1.1 | K11: =J11 -> 1.1 | L11: =K11 -> 1.1 | M11: =L11 -> 1.1 | N11: =M11 -> 1.1 | O11: =N11 -> 1.1 | P11: =O11 -> 1.1 | Q11: 1 | S11: 5
A12: UC_GrowthOfRES5 | B12: RWHDWHV3* | E12: CAP, GROWTH | G12: UP | H12: 1.1 | I12: =H12 -> 1.1 | J12: =I12 -> 1.1 | K12: =J12 -> 1.1 | L12: =K12 -> 1.1 | M12: =L12 -> 1.1 | N12: =M12 -> 1.1 | O12: =N12 -> 1.1 | P12: =O12 -> 1.1 | Q12: 1 | S12: 5
A13: UC_GrowthOfRES6 | B13: RLTGCFLBS* | E13: CAP, GROWTH | G13: UP | I13: 1.15 | J13: =I13 -> 1.15 | K13: =J13 -> 1.15 | L13: =K13 -> 1.15 | M13: =L13 -> 1.15 | N13: =M13 -> 1.15 | O13: =N13 -> 1.15 | P13: =O13 -> 1.15 | Q13: 1 | S13: 5
A14: UC_GrowthOfRES7 | B14: RLTGCFL10,RLTGCFL11 | E14: CAP, GROWTH | G14: UP | I14: 1.15 | J14: =I14 -> 1.15 | K14: =J14 -> 1.15 | L14: =K14 -> 1.15 | M14: =L14 -> 1.15 | N14: =M14 -> 1.15 | O14: =N14 -> 1.15 | P14: =O14 -> 1.15 | Q14: 1 | S14: 5
A15: UC_GrowthOfRES8 | B15: RLTGCFL15 | E15: CAP, GROWTH | G15: UP | I15: 1.15 | J15: =I15 -> 1.15 | K15: =J15 -> 1.15 | L15: =K15 -> 1.15 | M15: =L15 -> 1.15 | N15: =M15 -> 1.15 | O15: =N15 -> 1.15 | P15: =O15 -> 1.15 | Q15: 1 | S15: 5
A16: UC_GrowthOfRES9 | B16: RLTGCFL20 | E16: CAP, GROWTH | G16: UP | I16: 1.15 | J16: =I16 -> 1.15 | K16: =J16 -> 1.15 | L16: =K16 -> 1.15 | M16: =L16 -> 1.15 | N16: =M16 -> 1.15 | O16: =N16 -> 1.15 | P16: =O16 -> 1.15 | Q16: 1 | S16: 5
A17: UC_GrowthOfRES10 | B17: RLTGCFL30 | E17: CAP, GROWTH | G17: UP | I17: 1.15 | J17: =I17 -> 1.15 | K17: =J17 -> 1.15 | L17: =K17 -> 1.15 | M17: =L17 -> 1.15 | N17: =M17 -> 1.15 | O17: =N17 -> 1.15 | P17: =O17 -> 1.15 | Q17: 1 | S17: 5
A18: UC_GrowthOfRES11 | B18: RLTGCFL40 | E18: CAP, GROWTH | G18: UP | I18: 1.15 | J18: =I18 -> 1.15 | K18: =J18 -> 1.15 | L18: =K18 -> 1.15 | M18: =L18 -> 1.15 | N18: =M18 -> 1.15 | O18: =N18 -> 1.15 | P18: =O18 -> 1.15 | Q18: 1 | S18: 5
A19: UC_GrowthOfRES12 | B19: RLTGLED10,RLTGLED11 | E19: CAP, GROWTH | G19: UP | I19: 1.15 | J19: =I19 -> 1.15 | K19: =J19 -> 1.15 | L19: =K19 -> 1.15 | M19: =L19 -> 1.15 | N19: =M19 -> 1.15 | O19: =N19 -> 1.15 | P19: =O19 -> 1.15 | Q19: 1 | S19: 5
A20: UC_GrowthOfRES13 | B20: RLTGLED15 | E20: CAP, GROWTH | G20: UP | I20: 1.15 | J20: =I20 -> 1.15 | K20: =J20 -> 1.15 | L20: =K20 -> 1.15 | M20: =L20 -> 1.15 | N20: =M20 -> 1.15 | O20: =N20 -> 1.15 | P20: =O20 -> 1.15 | Q20: 1 | S20: 5
A21: UC_GrowthOfRES14 | B21: RLTGLED20 | E21: CAP, GROWTH | G21: UP | I21: 1.15 | J21: =I21 -> 1.15 | K21: =J21 -> 1.15 | L21: =K21 -> 1.15 | M21: =L21 -> 1.15 | N21: =M21 -> 1.15 | O21: =N21 -> 1.15 | P21: =O21 -> 1.15 | Q21: 1 | S21: 5
A22: UC_GrowthOfRES15 | B22: RLTGLED25 | E22: CAP, GROWTH | G22: UP | I22: 1.15 | J22: =I22 -> 1.15 | K22: =J22 -> 1.15 | L22: =K22 -> 1.15 | M22: =L22 -> 1.15 | N22: =M22 -> 1.15 | O22: =N22 -> 1.15 | P22: =O22 -> 1.15 | Q22: 1 | S22: 5
A23: UC_GrowthOfRES16 | B23: RLTGLED30 | E23: CAP, GROWTH | G23: UP | I23: 1.15 | J23: =I23 -> 1.15 | K23: =J23 -> 1.15 | L23: =K23 -> 1.15 | M23: =L23 -> 1.15 | N23: =M23 -> 1.15 | O23: =N23 -> 1.15 | P23: =O23 -> 1.15 | Q23: 1 | S23: 5
A24: UC_GrowthOfRES17 | B24: RLTGLED40 | E24: CAP, GROWTH | G24: UP | I24: 1.15 | J24: =I24 -> 1.15 | K24: =J24 -> 1.15 | L24: =K24 -> 1.15 | M24: =L24 -> 1.15 | N24: =M24 -> 1.15 | O24: =N24 -> 1.15 | P24: =O24 -> 1.15 | Q24: 1 | S24: 5
... A31: UC_GrowthOfRES24 | B31: RLTECFL40 | E31: CAP, GROWTH | G31: UP | I31: 1.15 | J31: =I31 -> 1.15 | K31: =J31 -> 1.15 | L31: =K31 -> 1.15 | M31: =L31 -> 1.15 | N31: =M31 -> 1.15 | O31: =N31 -> 1.15 | P31: =O31 -> 1.15 | Q31: 1 | S31: 5

Sheet UC_RES
B2: ~UC_Sets: R_E: AllRegions | M2: 0.73 | N2: 0.73 | O2: 0.73 | P2: 0.73 | Q2: 0.73
G4: ~UC_T: UC_COMPRD
B5: UC_N | C5: Pset_PN | D5: Pset_PD | E5: Pset_CI | F5: Cset_CN | G5: Year | H5: UC_FLO | I5: UC_RHSRTS~LO | J5: UC_RHSRTS~LO~0 | K5: R0 | L5: R1 | M5: R2 | N5: R3 | O5: R4 | P5: R5 | Q5: R6
B6: ="UC_"&F6&RIGHT(E6,5)&"LO" -> UC_RSHDSLEALO | C6: RSH* | E6: RESDSLEA | F6: RSH | G6: 2015 | H6: 1 | I6: 0 | J6: 5 | M6: =-SUM(Original!$M$3:$M$12)/SUM(Original!$AS$3:$AS$12)*0.95 -> -0.17414271 | N6: =M6 -> -0.17414271 | O6: =N6 -> -0.17414271 | P6: =O6 -> -0.17414271 | Q6: =P6 -> -0.17414271
C7: RSH* | E7: RESDSLEA | F7: RSH | G7: 2020 | H7: 1 | M7: =M49 -> -0.12333941 | N7: =N49 -> -0.12333941 | O7: =O49 -> -0.12333941 | P7: =P49 -> -0.12333941 | Q7: =Q49 -> -0.12333941
C8: =C7 -> RSH* | E8: =E7 -> RESDSLEA | F8: =F7 -> RSH | G8: 2025 | H8: 1 | M8: =M7*0.95 -> -0.11717244 | N8: =N7*0.95 -> -0.11717244 | O8: =O7*0.95 -> -0.11717244 | P8: =P7*0.95 -> -0.11717244 | Q8: =Q7*0.95 -> -0.11717244
C9: RSH* | E9: RESDSLEA | F9: RSH | G9: 2055 | H9: 1 | M9: 0 | N9: 0 | O9: 0 | P9: 0 | Q9: 0
B10: ="UC_"&F10&RIGHT(E10,5)&"LO" -> UC_RSHESELCLO | C10: RSH* | E10: RESELC | F10: RSH | G10: 2015 | H10: 1 | I10: 0 | J10: 5 | M10: =-SUM(Original!$U$3:$U$12)/SUM(Original!$AS$3:$AS$12)*0.5 -> -0.0090098107 | N10: =M10 -> -0.0090098107 | O10: =N10 -> -0.0090098107 | P10: =O10 -> -0.0090098107 | Q10: =P10 -> -0.0090098107
C11: RSH* | E11: RESELC | F11: RSH | G11: 2020 | H11: 1 | M11: =M10 -> -0.0090098107 | N11: =N10 -> -0.0090098107 | O11: =O10 -> -0.0090098107 | P11: =P10 -> -0.0090098107 | Q11: =Q10 -> -0.0090098107
C12: =C11 -> RSH* | E12: =E11 -> RESELC | F12: =F11 -> RSH | G12: 2025 | H12: 1 | M12: =M11*0.95 -> -0.0085593202 | N12: =N11*0.95 -> -0.0085593202 | O12: =O11*0.95 -> -0.0085593202 | P12: =P11*0.95 -> -0.0085593202 | Q12: =Q11*0.95 -> -0.0085593202
C13: RSH* | E13: RESELC | F13: RSH | G13: 2055 | H13: 1 | M13: -0.003 | N13: =M13 -> -0.003 | O13: =N13 -> -0.003 | P13: =O13 -> -0.003 | Q13: =P13 -> -0.003
B14: ="UC_"&F14&RIGHT(E14,5)&"LO" -> UC_RSHNGAEALO | C14: RSH* | E14: RESNGAEA | F14: RSH | G14: 2015 | H14: 1 | I14: 0 | J14: 5 | M14: =-SUM(Original!$AC$3:$AC$12)/SUM(Original!$AS$3:$AS$12)*0.95 -> -0.73385435 | N14: =M14 -> -0.73385435 | O14: =N14 -> -0.73385435 | P14: =O14 -> -0.73385435 | Q14: =P14 -> -0.73385435
C15: RSH* | E15: RESNGAEA | F15: RSH | G15: 2020 | H15: 1 | M15: =M14 -> -0.73385435 | N15: =N14 -> -0.73385435 | O15: =O14 -> -0.73385435 | P15: =P14 -> -0.73385435 | Q15: =Q14 -> -0.73385435
C16: =C15 -> RSH* | E16: =E15 -> RESNGAEA | F16: =F15 -> RSH | G16: 2025 | H16: 1 | M16: =M15*0.95 -> -0.69716163 | N16: =N15*0.95 -> -0.69716163 | O16: =O15*0.95 -> -0.69716163 | P16: =P15*0.95 -> -0.69716163 | Q16: =Q15*0.95 -> -0.69716163
C17: RSH* | E17: RESNGAEA | F17: RSH | G17: 2055 | H17: 1 | M17: 0 | N17: 0 | O17: 0 | P17: 0 | Q17: 0
B18: ="UC_"&F18&RIGHT(E18,5)&"Furnace"&"LO" -> UC_RSHFurnaceLO | C18: RSH* | D18: *Furnace* | F18: RSH | G18: 2015 | H18: 1 | I18: 0 | J18: 5 | M18: =-'RECS RESID'!$AL$16*0.9 -> -0.46637561 | N18: =M18 -> -0.46637561 | O18: =N18 -> -0.46637561 | P18: =O18 -> -0.46637561 | Q18: =P18 -> -0.46637561
C19: RSH* | D19: *Furnace* | F19: RSH | G19: 2025 | H19: 1 | M19: =M18*0.9 -> -0.41973805 | N19: =N18*0.9 -> -0.41973805 | O19: =O18*0.9 -> -0.41973805 | P19: =P18*0.9 -> -0.41973805 | Q19: =Q18*0.9 -> -0.41973805
C20: RSH* | D20: *Furnace* | F20: RSH | G20: 2055 | H20: 1 | M20: =M18*M$2 -> -0.34045419 | N20: =N18*N$2 -> -0.34045419 | O20: =O18*O$2 -> -0.34045419 | P20: =P18*P$2 -> -0.34045419 | Q20: =Q18*Q$2 -> -0.34045419
B21: ="UC_"&F21&RIGHT(D21,5)&"LO" -> UC_RSHPump*LO | C21: RSH* | D21: *Heat Pump* | F21: RSH | G21: 2015 | H21: 1 | I21: 0 | J21: 5 | M21: -0.006448043 | N21: =M21 -> -0.006448043 | O21: =N21 -> -0.006448043 | P21: =O21 -> -0.006448043 | Q21: =P21 -> -0.006448043
C22: RSH* | D22: *Heat Pump* | F22: RSH | G22: 2025 | H22: 1 | M22: =M21*0.9 -> -0.0058032387 | N22: =N21*0.9 -> -0.0058032387 | O22: =O21*0.9 -> -0.0058032387 | P22: =P21*0.9 -> -0.0058032387 | Q22: =Q21*0.9 -> -0.0058032387
C23: RSH* | D23: *Heat Pump* | F23: RSH | G23: 2055 | H23: 1 | M23: =M21*M$2 -> -0.0047070714 | N23: =N21*N$2 -> -0.0047070714 | O23: =O21*O$2 -> -0.0047070714 | P23: =P21*P$2 -> -0.0047070714 | Q23: =Q21*Q$2 -> -0.0047070714
B24: ="UC_"&F24&RIGHT(E24,5)&"LO" -> UC_RSHLO | C24: RSH* | D24: *Radiant* | F24: RSH | G24: 2015 | H24: 1 | I24: 0 | J24: 5 | M24: =-'RECS RESID'!$AL$18*0.9 -> -0.42703251 | N24: =M24 -> -0.42703251 | O24: =N24 -> -0.42703251 | P24: =O24 -> -0.42703251 | Q24: =P24 -> -0.42703251
C25: RSH* | D25: *Radiant* | F25: RSH | G25: 2025 | H25: 1 | M25: =M24*0.9 -> -0.38432926 | N25: =N24*0.9 -> -0.38432926 | O25: =O24*0.9 -> -0.38432926 | P25: =P24*0.9 -> -0.38432926 | Q25: =Q24*0.9 -> -0.38432926
C26: RSH* | D26: *Radiant* | F26: RSH | G26: 2055 | H26: 1 | M26: =M24*M$2 -> -0.31173374 | N26: =N24*N$2 -> -0.31173374 | O26: =O24*O$2 -> -0.31173374 | P26: =P24*P$2 -> -0.31173374 | Q26: =Q24*Q$2 -> -0.31173374
B27: ="UC_"&F27&"UTI"&"LO" -> UC_RSHUTILO | C27: RSH*UTI* | F27: RSH | G27: 2015 | H27: 1 | I27: 0 | J27: 5 | M27: 0 | N27: 0 | O27: =-25.03*0.16/58 -> -0.069048276 | P27: 0 | Q27: 0
C28: RSH*UTI* | F28: RSH | G28: 2025 | H28: 1 | M28: 0 | N28: 0 | O28: =O52*0.95 -> -0.065595862 | P28: 0 | Q28: 0
C29: RSH*UTI* | F29: RSH | G29: 2055 | H29: 1 | M29: 0 | N29: 0 | O29: =O53*O2 -> -0.075607862 | P29: 0 | Q29: 0
M31: ='2010 GHG Emissions'!$M$2 -> 0.61168452 | N31: =M31 -> 0.61168452 | O31: =N31 -> 0.61168452 | P31: =O31 -> 0.61168452 | Q31: =P31 -> 0.61168452
M32: 1.2 | N32: 1.2 | O32: 1.2 | P32: 1.2 | Q32: 1.2
M33: 1.5 | N33: 1.5 | O33: 1.5 | P33: 1.5 | Q33: 1.5
B35: ~UC_Sets: R_E: AllRegions
G37: ~UC_T: UC_COMPRD
B38: UC_N | C38: Pset_PN | D38: Pset_PD | E38: Pset_CI | F38: Cset_CN | G38: Year | H38: UC_FLO | I38: UC_RHSRTS~UP | J38: UC_RHSRTS~UP~0 | K38: R0 | L38: R1 | M38: R2 | N38: R3 | O38: R4 | P38: R5 | Q38: R6
B39: ="UC_"&F39&RIGHT(E39,5)&"Furnace"&"UP" -> UC_RSHDSLEAFurnaceUP | C39: RSH* | D39: *Furnace* | E39: RESDSLEA | F39: RSH | G39: 2015 | H39: 1 | I39: 0 | J39: 5 | M39: =-0.15 -> -0.15 | N39: =M39 -> -0.15 | O39: =N39 -> -0.15 | P39: =O39 -> -0.15 | Q39: =P39 -> -0.15
C40: RSH* | D40: *Furnace* | E40: RESDSLEA | F40: RSH | G40: 2025 | H40: 1 | M40: =M39*M$31 -> -0.091752678 | N40: =N39*N$31 -> -0.091752678 | O40: =O39*O$31 -> -0.091752678 | P40: =P39*P$31 -> -0.091752678 | Q40: =Q39*Q$31 -> -0.091752678
C41: RSH* | D41: *Furnace* | E41: RESDSLEA | F41: RSH | G41: 2055 | H41: 1 | M41: =M40 -> -0.091752678 | N41: =N40 -> -0.091752678 | O41: =O40 -> -0.091752678 | P41: =P40 -> -0.091752678 | Q41: =Q40 -> -0.091752678
B42: ="UC_"&F42&RIGHT(E42,5)&"Furnace"&"UP" -> UC_RSHESELCFurnaceUP | C42: RSH* | D42: *Furnace* | E42: RESELC | F42: RSH | G42: 2020 | H42: 1 | I42: 0 | J42: 5 | M42: =-1.1*Assumptions_MI!$K$34 -> -0.044 | N42: =M42 -> -0.044 | O42: =N42 -> -0.044 | P42: =O42 -> -0.044 | Q42: =P42 -> -0.044
C43: RSH* | D43: *Furnace* | E43: RESELC | F43: RSH | G43: 2030 | H43: 1 | M43: =M42 -> -0.044 | N43: =N42 -> -0.044 | O43: =O42 -> -0.044 | P43: =P42 -> -0.044 | Q43: =Q42 -> -0.044
C44: RSH* | D44: *Furnace* | E44: RESELC | F44: RSH | G44: 2055 | H44: 1 | M44: =M43*M$33 -> -0.066 | N44: =N43*N$33 -> -0.066 | O44: =O43*O$33 -> -0.066 | P44: =P43*P$33 -> -0.066 | Q44: =Q43*Q$33 -> -0.066
B45: ="UC_"&F45&RIGHT(E45,5)&"UP" -> UC_RSHESELCUP | C45: RSH* | E45: RESELC | F45: RSH | G45: 2015 | H45: 1 | I45: 0 | J45: 5 | M45: =-SUM(Original!$U$3:$U$12)/SUM(Original!$AS$3:$AS$12) -> -0.018019621 | N45: =M45 -> -0.018019621 | O45: =N45 -> -0.018019621 | P45: =O45 -> -0.018019621 | Q45: =P45 -> -0.018019621
C46: RSH* | E46: RESELC | F46: RSH | G46: 2025 | H46: 1 | M46: =M45*M$32 -> -0.021623546 | N46: =N45*N$32 -> -0.021623546 | O46: =O45*O$32 -> -0.021623546 | P46: =P45*P$32 -> -0.021623546 | Q46: =Q45*Q$32 -> -0.021623546
C47: RSH* | E47: RESELC | F47: RSH | G47: 2055 | H47: 1 | M47: -1 | N47: -1 | O47: -1 | P47: -1 | Q47: -1
B48: ="UC_"&F48&RIGHT(E48,5)&"UP" -> UC_RSHDSLEAUP | C48: RSH* | E48: RESDSLEA | F48: RSH | G48: 2015 | H48: 1 | I48: 0 | J48: 5 | M48: =-SUM(Original!$M$3:$M$12)/SUM(Original!$AS$3:$AS$12)*1.1 -> -0.20163892 | N48: =M48 -> -0.20163892 | O48: =N48 -> -0.20163892 | P48: =O48 -> -0.20163892 | Q48: =P48 -> -0.20163892
C49: RSH* | E49: RESDSLEA | F49: RSH | G49: 2020 | H49: 1 | M49: =M48*M$31 -> -0.12333941 | N49: =N48*N$31 -> -0.12333941 | O49: =O48*O$31 -> -0.12333941 | P49: =P48*P$31 -> -0.12333941 | Q49: =Q48*Q$31 -> -0.12333941
C50: RSH* | E50: RESDSLEA | F50: RSH | G50: 2055 | H50: 1 | M50: =M49 -> -0.12333941 | N50: =N49 -> -0.12333941 | O50: =O49 -> -0.12333941 | P50: =P49 -> -0.12333941 | Q50: =Q49 -> -0.12333941
B51: ="UC_"&F51&"UTI"&"UP" -> UC_RSHUTIUP | C51: RSH*UTI* | F51: RSH | G51: 2015 | H51: 1 | I51: 0 | J51: 5 | M51: 0 | N51: 0 | O51: =-25.03*0.16/58 -> -0.069048276 | P51: 0 | Q51: 0
C52: RSH*UTI* | F52: RSH | G52: 2025 | H52: 1 | M52: 0 | N52: 0 | O52: =O51 -> -0.069048276 | P52: 0 | Q52: 0
C53: RSH*UTI* | F53: RSH | G53: 2055 | H53: 1 | M53: =M51*M$2 -> 0 | N53: =N51*N$2 -> 0 | O53: =O51*O33 -> -0.10357241 | P53: =P51*P$2 -> 0 | Q53: =Q51*Q$2 -> 0
M56: ='2010 GHG Emissions'!$M$2*0.5 -> 0.30584226 | N56: ='2010 GHG Emissions'!$M$2*0.5 -> 0.30584226 | O56: ='2010 GHG Emissions'!$M$2*0.5 -> 0.30584226 | P56: ='2010 GHG Emissions'!$M$2*0.5 -> 0.30584226 | Q56: ='2010 GHG Emissions'!$M$2*0.5 -> 0.30584226
M57: 0.73 | N57: 0.73 | O57: 0.73 | P57: 0.73 | Q57: 0.73
B59: ~UC_Sets: R_E: AllRegions
G61: ~UC_T: UC_COMPRD
B62: UC_N | C62: Pset_PN | D62: Pset_PD | E62: Pset_CI | F62: Cset_CN | G62: Year | H62: UC_FLO | I62: UC_RHSRTS~LO | J62: UC_RHSRTS~LO~0 | K62: R0 | L62: R1 | M62: R2 | N62: R3 | O62: R4 | P62: R5 | Q62: R6
B63: ="UC_"&F63&RIGHT(E63,5)&"LO" -> UC_RWHESELCLO | C63: RWHE* | E63: RESELC | F63: RWH | G63: 2015 | H63: 1 | I63: 0 | J63: 5 | M63: =-Resid!$T$103/(Resid!$T$95+Resid!$T$103+Resid!$T$112)*0.95 -> -0.027755475 | N63: =M63 -> -0.027755475 | O63: =N63 -> -0.027755475 | P63: =O63 -> -0.027755475 | Q63: =P63 -> -0.027755475
C64: RWHE* | E64: RESELC | F64: RWH | G64: 2025 | H64: 1 | M64: =M63 -> -0.027755475 | N64: =N63 -> -0.027755475 | O64: =O63 -> -0.027755475 | P64: =P63 -> -0.027755475 | Q64: =Q63 -> -0.027755475
C65: RWHE* | E65: RESELC | F65: RWH | G65: 2055 | H65: 1 | M65: =M63*M$57 -> -0.020261497 | N65: =N63*N$57 -> -0.020261497 | O65: =O63*O$57 -> -0.020261497 | P65: =P63*P$57 -> -0.020261497 | Q65: =Q63*Q$57 -> -0.020261497
B66: ="UC_"&F67&RIGHT(E67,5)&"LO" -> UC_RWHNGAEALO | C66: RWH* | E66: RESNGAEA | F66: RWH | G66: 2015 | H66: 1 | I66: 0 | J66: 5 | M66: =-SUM(Original!$AD$3:$AD$12)/SUM(Original!$AT$3:$AT$12) -> -0.81590531 | N66: =-SUM(Original!$AD$3:$AD$12)/SUM(Original!$AT$3:$AT$12) -> -0.81590531 | O66: =-SUM(Original!$AD$3:$AD$12)/SUM(Original!$AT$3:$AT$12)+9.1*0.1/13.5 -> -0.7484979 | P66: =-SUM(Original!$AD$3:$AD$12)/SUM(Original!$AT$3:$AT$12) -> -0.81590531 | Q66: =-SUM(Original!$AD$3:$AD$12)/SUM(Original!$AT$3:$AT$12) -> -0.81590531
C67: RWH* | E67: RESNGAEA | F67: RWH | G67: 2025 | H67: 1 | M67: =-SUM(Original!$AD$3:$AD$12)*M57/SUM(Original!$AT$3:$AT$12) -> -0.59561087 | N67: =M67 -> -0.59561087 | O67: =N67 -> -0.59561087 | P67: =O67 -> -0.59561087 | Q67: =P67 -> -0.59561087
C68: RWH* | E68: RESNGAEA | F68: RWH | G68: 2050 | H68: 1 | M68: 0 | N68: 0 | O68: 0 | P68: 0 | Q68: 0
B69: ="UC_"&F69&RIGHT(E69,5)&"LO" -> UC_RWHSOLLO | C69: RWH* | E69: SOL | F69: RWH | G69: 2015 | H69: 1 | I69: 0 | J69: 5 | M69: 0 | N69: =M69 -> 0 | O69: =N69 -> 0 | P69: =O69 -> 0 | Q69: =P69 -> 0
C70: RWH* | E70: SOL | F70: RWH | G70: 2025 | H70: 1 | M70: =M69 -> 0 | N70: =N69 -> 0 | O70: =O69 -> 0 | P70: =P69 -> 0 | Q70: =Q69 -> 0
C71: RWH* | E71: SOL | F71: RWH | G71: 2055 | H71: 1 | M71: =M69 -> 0 | N71: =N69 -> 0 | O71: =O69 -> 0 | P71: =P69 -> 0 | Q71: =Q69 -> 0
B72: ="UC_"&F72&RIGHT(E72,5)&"LO" -> UC_RWHDSLEALO | C72: RWH* | E72: RESDSLEA | F72: RWH | G72: 2015 | H72: 1 | I72: 0 | J72: 5 | M72: =-Resid!$T$112/(Resid!$T$95+Resid!$T$103+Resid!$T$112)*0.45 -> -0.13437753 | N72: =M72 -> -0.13437753 | O72: =N72 -> -0.13437753 | P72: =N72 -> -0.13437753 | Q72: =P72 -> -0.13437753
C73: RWH* | E73: RESDSLEA | F73: RWH | G73: 2020 | H73: 1 | M73: =M72*M$56 -> -0.041098326 | N73: =N72*N$56 -> -0.041098326 | O73: =O72*O$56 -> -0.041098326 | P73: =P72*P$56 -> -0.041098326 | Q73: =Q72*Q$56 -> -0.041098326
C74: RWH* | E74: RESDSLEA | F74: RWH | G74: 2030 | H74: 1 | M74: 0 | N74: 0 | O74: 0 | P74: 0 | Q74: 0
C75: RWH* | E75: RESDSLEA | F75: RWH | G75: 2055 | H75: 1 | M75: 0 | N75: 0 | O75: 0 | P75: 0 | Q75: 0
B76: ="UC_"&F76&"UTI"&"LO" -> UC_RWHUTILO | C76: RWH*UTI* | F76: RWH | G76: 2015 | H76: 1 | I76: 0 | J76: 5 | M76: 0 | N76: 0 | O76: =-9.1*0.1/13.5 -> -0.067407407 | P76: 0 | Q76: 0
C77: RWH*UTI* | F77: RWH | G77: 2025 | H77: 1 | M77: =M75*M$2 -> 0 | N77: =N75*N$2 -> 0 | O77: =O76 -> -0.067407407 | P77: =P75*P$2 -> 0 | Q77: =Q75*Q$2 -> 0
C78: RWH*UTI* | F78: RWH | G78: 2055 | H78: 1 | M78: =M76*M$2 -> 0 | N78: =N76*N$2 -> 0 | O78: =O76*O57 -> -0.049207407 | P78: =P76*P$2 -> 0 | Q78: =Q76*Q$2 -> 0
B80: ="UC_"&F80&RIGHT(E80,5)&"LO" -> UC_RWHLO | C80: RWH* | D80: *Instantaneaous* | F80: RWH | G80: 2015 | H80: 1 | I80: 0 | J80: 5 | M80: -0.02 | N80: =M80 -> -0.02 | O80: =N80 -> -0.02 | P80: =O80 -> -0.02 | Q80: =P80 -> -0.02
C81: RWH* | D81: *Instantaneaous* | F81: RWH | G81: 2055 | H81: 1 | M81: =M80 -> -0.02 | N81: =N80 -> -0.02 | O81: =O80 -> -0.02 | P81: =P80 -> -0.02 | Q81: =Q80 -> -0.02
M84: ='2010 GHG Emissions'!$M$2 -> 0.61168452 | N84: ='2010 GHG Emissions'!$M$2 -> 0.61168452 | O84: ='2010 GHG Emissions'!$M$2 -> 0.61168452 | P84: ='2010 GHG Emissions'!$M$2 -> 0.61168452 | Q84: ='2010 GHG Emissions'!$M$2 -> 0.61168452
B86: ~UC_Sets: R_E: AllRegions
G88: ~UC_T: UC_COMPRD
B89: UC_N | C89: Pset_PN | D89: Pset_PD | E89: Pset_CI | F89: Cset_CN | G89: Year | H89: UC_FLO | I89: UC_RHSRTS~UP | J89: UC_RHSRTS~UP~0 | K89: R0 | L89: R1 | M89: R2 | N89: R3 | O89: R4 | P89: R5 | Q89: R6
B90: ="UC_"&F90&RIGHT(E90,5)&"UP" -> UC_RWHESELCUP | C90: RWHE* | E90: RESELC | F90: RWH | G90: 2015 | H90: 1 | I90: 0 | J90: 5 | M90: =-Resid!$T$103/(Resid!$T$95+Resid!$T$103+Resid!$T$112)*1.2 -> -0.035059547 | N90: =M90 -> -0.035059547 | O90: =N90 -> -0.035059547 | P90: =O90 -> -0.035059547 | Q90: =P90 -> -0.035059547
C91: RWHE* | E91: RESELC | F91: RWH | G91: 2020 | H91: 1 | M91: -0.5 | N91: -0.5 | O91: -0.5 | P91: -0.5 | Q91: -0.5
C92: RWHE* | E92: RESELC | F92: RWH | G92: 2055 | H92: 1 | M92: -1 | N92: -1 | O92: -1 | P92: -1 | Q92: -1
B93: ="UC_"&F93&RIGHT(E93,5)&"UP" -> UC_RWHDSLEAUP | C93: RWH* | E93: RESDSLEA | F93: RWH | G93: 2015 | H93: 1 | I93: 0 | J93: 5 | M93: =-Resid!$T$112/(Resid!$T$95+Resid!$T$103+Resid!$T$112) -> -0.29861672 | N93: =M93 -> -0.29861672 | O93: =N93 -> -0.29861672 | P93: =O93 -> -0.29861672 | Q93: =P93 -> -0.29861672
C94: RWH* | E94: RESDSLEA | F94: RWH | G94: 2020 | H94: 1 | M94: =M93*M$84 -> -0.18265923 | N94: =N93*N$84 -> -0.18265923 | O94: =O93*O$84 -> -0.18265923 | P94: =P93*P$84 -> -0.18265923 | Q94: =Q93*Q$84 -> -0.18265923
C95: RWH* | E95: RESDSLEA | F95: RWH | G95: 2055 | H95: 1 | M95: 0 | N95: 0 | O95: 0 | P95: 0 | Q95: 0
B96: ="UC_"&F96&RIGHT(E96,5)&"UP" -> UC_RWHSOLUP | C96: RWH* | E96: SOL | F96: RWH | G96: 2010 | H96: 1 | I96: 0 | J96: 5 | M96: 0 | N96: =M96 -> 0 | O96: =N96 -> 0 | P96: =O96 -> 0 | Q96: =P96 -> 0
C97: RWH* | E97: SOL | F97: RWH | G97: 2020 | H97: 1 | M97: =M96 -> 0 | N97: =N96 -> 0 | O97: =O96 -> 0 | P97: =P96 -> 0 | Q97: =Q96 -> 0
C98: RWH* | E98: SOL | F98: RWH | G98: 2050 | H98: 1 | M98: -0.1 | N98: -0.1 | O98: -0.1 | P98: -0.1 | Q98: -0.1
B99: ="UC_"&F99&"UTI"&"UP" -> UC_RWHUTIUP | C99: RWH*UTI* | F99: RWH | G99: 2015 | H99: 1 | I99: 0 | J99: 5 | M99: 0 | N99: 0 | O99: =O76 -> -0.067407407 | P99: 0 | Q99: 0
C100: RWH*UTI* | F100: RWH | G100: 2055 | H100: 1 | M100: =M99*M$2 -> 0 | N100: =N99*N$2 -> 0 | O100: =O99/O84 -> -0.11019963 | P100: =P99*P$2 -> 0 | Q100: =Q99*Q$2 -> 0
M102: 0.73 | N102: 0.73 | O102: 0.73 | P102: 0.73 | Q102: 0.73
B104: ~UC_Sets: R_E: AllRegions
G106: ~UC_T: UC_COMPRD
B107: UC_N | C107: Pset_PN | D107: Pset_PD | E107: Pset_CI | F107: Cset_CN | G107: Year | H107: UC_FLO | I107: UC_RHSRTS~LO | J107: UC_RHSRTS~LO~0 | K107: R0 | L107: R1 | M107: R2 | N107: R3 | O107: R4 | P107: R5 | Q107: R6
B108: ="UC_"&F108&RIGHT(E108,5)&"HeatPump"&"LO" -> UC_RSCHeatPumpLO | C108: RSC*,RSH* | D108: *Heat Pump* | F108: RSC | G108: 2015 | H108: 1 | I108: 0 | J108: 5 | M108: =-('RECS RESID'!$W$27/'RECS RESID'!$W$30)*0.9 -> -0.022934384 | N108: =M108 -> -0.022934384 | O108: =N108 -> -0.022934384 | P108: =O108 -> -0.022934384 | Q108: =P108 -> -0.022934384
C109: RSC*,RSH* | D109: *Heat Pump* | F109: RSC | G109: 2025 | H109: 1 | M109: =M108 -> -0.022934384 | N109: =N108 -> -0.022934384 | O109: =O108 -> -0.022934384 | P109: =P108 -> -0.022934384 | Q109: =Q108 -> -0.022934384
C110: RSC*,RSH* | D110: *Heat Pump* | F110: RSC | G110: 2055 | H110: 1 | M110: =M108*M$102 -> -0.016742101 | N110: =N108*N$102 -> -0.016742101 | O110: =O108*O$102 -> -0.016742101 | P110: =P108*P$102 -> -0.016742101 | Q110: =Q108*Q$102 -> -0.016742101
B111: ="UC_"&F111&RIGHT(E111,5)&"Central"&"LO" -> UC_RSCCentralLO | C111: RSCCAC* | F111: RSC | G111: 2015 | H111: 1 | I111: 0 | J111: 5 | M111: =-'RECS RESID'!$W$26/'RECS RESID'!$W$30 -> -0.38076735 | N111: =M111 -> -0.38076735 | O111: =N111 -> -0.38076735 | P111: =O111 -> -0.38076735 | Q111: =P111 -> -0.38076735
C112: RSCCAC* | F112: RSC | G112: 2025 | H112: 1 | M112: =M111 -> -0.38076735 | N112: =N111 -> -0.38076735 | O112: =O111 -> -0.38076735 | P112: =P111 -> -0.38076735 | Q112: =Q111 -> -0.38076735
C113: RSCCAC* | F113: RSC | G113: 2055 | H113: 1 | M113: =M111*M$102 -> -0.27796017 | N113: =N111*N$102 -> -0.27796017 | O113: =O111*O$102 -> -0.27796017 | P113: =P111*P$102 -> -0.27796017 | Q113: =Q111*Q$102 -> -0.27796017
B114: ="UC_"&F114&RIGHT(E114,5)&"Room"&"LO" -> UC_RSCRoomLO | C114: RSCRAC* | F114: RSC | G114: 2015 | H114: 1 | I114: 0 | J114: 5 | M114: =-'RECS RESID'!$W$25/'RECS RESID'!$W$30 -> -0.59375 | N114: =M114 -> -0.59375 | O114: =N114 -> -0.59375 | P114: =O114 -> -0.59375 | Q114: =P114 -> -0.59375
C115: RSCRAC* | F115: RSC | G115: 2025 | H115: 1 | M115: =M114 -> -0.59375 | N115: =N114 -> -0.59375 | O115: =O114 -> -0.59375 | P115: =P114 -> -0.59375 | Q115: =Q114 -> -0.59375
C116: RSCRAC* | F116: RSC | G116: 2055 | H116: 1 | M116: =M114*M$102 -> -0.4334375 | N116: =N114*N$102 -> -0.4334375 | O116: =O114*O$102 -> -0.4334375 | P116: =P114*P$102 -> -0.4334375 | Q116: =Q114*Q$102 -> -0.4334375
M119: 0.73 | N119: 0.73 | O119: 0.73 | P119: 0.73 | Q119: 0.73
...

Sheet TechData_SolarPV
A1: TechData | B1: _GLOBAL,R0,R1,R2,R3,R4,R5,R6
F4: ~FI_T
A5: Region | B5: TechName | C5: *TechDesc | D5: *Units | E5: CommIN | F5: CommOUT | G5: NCAP_START | H5: NCAP_TLIFE | I5: PRC_CAPACT | J5: EFF | K5: Peak | L5: PRC_RESID~2010 | M5: NCAP_COST~2010 | N5: NCAP_COST~2015 | O5: NCAP_COST~2020 | P5: NCAP_COST~2025 | Q5: NCAP_COST~2030 | R5: NCAP_COST~2035 | S5: NCAP_COST~2040 | T5: NCAP_COST~2045 | U5: NCAP_COST~2050 | V5: NCAP_COST~2055 | W5: NCAP_FOM | X5: NCAP_AF~IDAM | Y5: NCAP_AF~IDPM | Z5: NCAP_AF~IP | AA5: NCAP_AF~IN | AB5: NCAP_AF~SDAM | AC5: NCAP_AF~SDPM | AD5: NCAP_AF~SP | AE5: NCAP_AF~SN | AF5: NCAP_AF~WDAM | AG5: NCAP_AF~WDPM | AH5: NCAP_AF~WP | AI5: NCAP_AF~WN | AJ5: NCAP_DRATE | AL5: Input | AM5: Output | AO5: ACT_BND~FX~2010 | AP5: ACT_BND~FX~2015 | AQ5: ACT_BND~LO~2020 | AR5: ACT_BND~LO~2025 | AS5: ACT_BND~LO~2030 | AT5: ACT_BND~LO~2035 | AU5: ACT_BND~LO~2040 | AV5: ACT_BND~LO~2045 | AW5: ACT_BND~LO~2050 | AX5: ACT_BND~LO~2055 | AY5: ACT_BND~UP~2020 | AZ5: ACT_BND~UP~2025 | BA5: ACT_BND~UP~2030 | BB5: ACT_BND~UP~2035 | BC5: ACT_BND~UP~2040 | BD5: ACT_BND~UP~2045 | BE5: ACT_BND~UP~2050 | BF5: ACT_BND~UP~2055
A6: * Solar PV Technologies
A7: *R1 | B7: ESOLPVRES | C7: Solar PV Distributed Residential Generation | E7: SOLRES | F7: ELC | G7: 2010 | H7: 30 | I7: 31.536 | J7: =AM7/AL7 -> 0.34965035 | K7: 0.3 | L7: =AO7/I7 -> 0 | M7: 6546.9995 | N7: 3903.1781 | O7: 3453.8021 | P7: 3004.4261 | Q7: 2839.3022 | R7: 2674.1784 | S7: 2596.418 | T7: 2558.6683 | U7: 2540.0679 | V7: 2530.8353 | W7: 10 | X7: 0 | Y7: 0.31357247 | Z7: 0.31357247 | AA7: 0 | AB7: 0.3060734 | AC7: 0.3060734 | AD7: 0.3060734 | AE7: 0 | AF7: 0.3020009 | AG7: 0.3020009 | AH7: 0.3020009 | AI7: 0 | AJ7: 0.15 | AL7: 2.86 | AM7: 1
A8: R2 | B8: ESOLPVRES | C8: Solar PV Distributed Residential Generation | E8: SOLRES | F8: ELC | G8: 2010 | H8: 30 | I8: 31.536 | J8: =AM8/AL8 -> 0.34965035 | K8: 0.3 | L8: =AO8/I8 -> 0.00022813875 | M8: 6546.9995 | N8: 3903.1781 | O8: 3453.8021 | P8: 3004.4261 | Q8: 2839.3022 | R8: 2674.1784 | S8: 2596.418 | T8: 2558.6683 | U8: 2540.0679 | V8: 2530.8353 | W8: 10 | X8: 0 | Y8: 0.317351 | Z8: 0.317351 | AA8: 0 | AB8: 0.30541737 | AC8: 0.30541737 | AD8: 0.30541737 | AE8: 0 | AF8: 0.29271621 | AG8: 0.29271621 | AH8: 0.29271621 | AI8: 0 | AJ8: 0.15 | AL8: 2.86 | AM8: 1 | AO8: ='Rooftop Calc'!AC65 -> 0.0071945835 | AP8: ='Rooftop Calc'!AC71 -> 0.109328 | AQ8: ='Rooftop Calc'!AC77 -> 0.24496493 | AR8: ='Rooftop Calc'!AC84 -> 0.43039234 | AS8: ='Rooftop Calc'!AC91 -> 0.61581975 | AT8: ='Rooftop Calc'!AC98 -> 0.80124716 | AU8: ='Rooftop Calc'!AC105 -> 0.98667458 | AV8: ='Rooftop Calc'!AC112 -> 1.1649074 | AW8: ='Rooftop Calc'!AC119 -> 1.2410068 | AX8: ='Rooftop Calc'!AC126 -> 1.3072238 | AY8: ='Rooftop Calc'!AK77 -> 0.37640069 | AZ8: ='Rooftop Calc'!AK84 -> 0.64269247 | BA8: ='Rooftop Calc'!AK91 -> 0.90976515 | BB8: ='Rooftop Calc'!AK98 -> 1.1760569 | BC8: ='Rooftop Calc'!AK105 -> 1.4431296 | BD8: ='Rooftop Calc'!AK112 -> 1.7094214 | BE8: ='Rooftop Calc'!AK119 -> 1.9764941 | BF8: ='Rooftop Calc'!AK126 -> 2.2427859
A9: R3 | B9: ESOLPVRES | C9: Solar PV Distributed Residential Generation | E9: SOLRES | F9: ELC | G9: 2010 | H9: 30 | I9: 31.536 | J9: =AM9/AL9 -> 0.34965035 | K9: 0.3 | L9: =AO9/I9 -> 0.00011898578 | M9: 6546.9995 | N9: 3903.1781 | O9: 3453.8021 | P9: 3004.4261 | Q9: 2839.3022 | R9: 2674.1784 | S9: 2596.418 | T9: 2558.6683 | U9: 2540.0679 | V9: 2530.8353 | W9: 10 | X9: 0 | Y9: 0.29713464 | Z9: 0.29713464 | AA9: 0 | AB9: 0.30672516 | AC9: 0.30672516 | AD9: 0.30672516 | AE9: 0 | AF9: 0.26137287 | AG9: 0.26137287 | AH9: 0.26137287 | AI9: 0 | AJ9: 0.15 | AL9: 2.86 | AM9: 1 | AO9: ='Rooftop Calc'!AD65 -> 0.0037523355 | AP9: ='Rooftop Calc'!AD71 -> 0.073448493 | AQ9: ='Rooftop Calc'!AD77 -> 0.13820064 | AR9: ='Rooftop Calc'!AD84 -> 0.20768834 | AS9: ='Rooftop Calc'!AD91 -> 0.27717603 | AT9: ='Rooftop Calc'!AD98 -> 0.34666373 | AU9: ='Rooftop Calc'!AD105 -> 0.41615142 | AV9: ='Rooftop Calc'!AD112 -> 0.48188678 | AW9: ='Rooftop Calc'!AD119 -> 0.47792598 | AX9: ='Rooftop Calc'!AD126 -> 0.46631225 | AY9: ='Rooftop Calc'!AL77 -> 0.25287267 | AZ9: ='Rooftop Calc'!AL84 -> 0.43177221 | BA9: ='Rooftop Calc'!AL91 -> 0.61119639 | BB9: ='Rooftop Calc'!AL98 -> 0.79009593 | BC9: ='Rooftop Calc'!AL105 -> 0.96952011 | BD9: ='Rooftop Calc'!AL112 -> 1.1484197 | BE9: ='Rooftop Calc'!AL119 -> 1.3278438 | BF9: ='Rooftop Calc'!AL126 -> 1.5067434
A10: R4 | B10: ESOLPVRES | C10: Solar PV Distributed Residential Generation | E10: SOLRES | F10: ELC | G10: 2010 | H10: 30 | I10: 31.536 | J10: =AM10/AL10 -> 0.34965035 | K10: 0.3 | L10: =AO10/I10 -> 3.7963767e-05 | M10: 6546.9995 | N10: 3903.1781 | O10: 3453.8021 | P10: 3004.4261 | Q10: 2839.3022 | R10: 2674.1784 | S10: 2596.418 | T10: 2558.6683 | U10: 2540.0679 | V10: 2530.8353 | W10: 10 | X10: 0 | Y10: 0.33039362 | Z10: 0.33039362 | AA10: 0 | AB10: 0.32440092 | AC10: 0.32440092 | AD10: 0.32440092 | AE10: 0 | AF10: 0.34679382 | AG10: 0.34679382 | AH10: 0.34679382 | AI10: 0 | AJ10: 0.15 | AL10: 2.86 | AM10: 1 | AO10: ='Rooftop Calc'!AE65 -> 0.0011972254 | AP10: ='Rooftop Calc'!AE71 -> 0.0093117528 | AQ10: ='Rooftop Calc'!AE77 -> 0.017877615 | AR10: ='Rooftop Calc'!AE84 -> 0.024528867 | AS10: ='Rooftop Calc'!AE91 -> 0.031180119 | AT10: ='Rooftop Calc'!AE98 -> 0.037831371 | AU10: ='Rooftop Calc'!AE105 -> 0.044482623 | AV10: ='Rooftop Calc'!AE112 -> 0.04993665 | AW10: ='Rooftop Calc'!AE119 -> 0.047276149 | AX10: ='Rooftop Calc'!AE126 -> 0.042167162 | AY10: ='Rooftop Calc'!AM77 -> 0.032059035 | AZ10: ='Rooftop Calc'!AM84 -> 0.054739804 | BA10: ='Rooftop Calc'!AM91 -> 0.077487086 | BB10: ='Rooftop Calc'!AM98 -> 0.10016786 | BC10: ='Rooftop Calc'!AM105 -> 0.12291514 | BD10: ='Rooftop Calc'!AM112 -> 0.14559591 | BE10: ='Rooftop Calc'!AM119 -> 0.16834319 | BF10: ='Rooftop Calc'!AM126 -> 0.19102396
A11: R5 | B11: ESOLPVRES | C11: Solar PV Distributed Residential Generation | E11: SOLRES | F11: ELC | G11: 2010 | H11: 30 | I11: 31.536 | J11: =AM11/AL11 -> 0.34965035 | K11: 0.3 | L11: =AO11/I11 -> 5.5295397e-05 | M11: 6546.9995 | N11: 3903.1781 | O11: 3453.8021 | P11: 3004.4261 | Q11: 2839.3022 | R11: 2674.1784 | S11: 2596.418 | T11: 2558.6683 | U11: 2540.0679 | V11: 2530.8353 | W11: 10 | X11: 0 | Y11: 0.34379748 | Z11: 0.34379748 | AA11: 0 | AB11: 0.29466039 | AC11: 0.29466039 | AD11: 0.29466039 | AE11: 0 | AF11: 0.36077416 | AG11: 0.36077416 | AH11: 0.36077416 | AI11: 0 | AJ11: 0.15 | AL11: 2.86 | AM11: 1 | AO11: ='Rooftop Calc'!AF65 -> 0.0017437956 | AP11: ='Rooftop Calc'!AF71 -> 0.32034551 | AQ11: ='Rooftop Calc'!AF77 -> 0.57042833 | AR11: ='Rooftop Calc'!AF84 -> 1.0833094 | AS11: ='Rooftop Calc'!AF91 -> 1.5961905 | AT11: ='Rooftop Calc'!AF98 -> 2.1090715 | AU11: ='Rooftop Calc'!AF105 -> 2.6219526 | AV11: ='Rooftop Calc'!AF112 -> 3.1330899 | AW11: ='Rooftop Calc'!AF119 -> 3.3256254 | AX11: ='Rooftop Calc'!AF126 -> 3.7957449 | AY11: ='Rooftop Calc'!AN77 -> 1.1029038 | AZ11: ='Rooftop Calc'!AN84 -> 1.883174 | BA11: ='Rooftop Calc'!AN91 -> 2.6657323 | BB11: ='Rooftop Calc'!AN98 -> 3.4460025 | BC11: ='Rooftop Calc'!AN105 -> 4.2285608 | BD11: ='Rooftop Calc'!AN112 -> 5.0088309 | BE11: ='Rooftop Calc'!AN119 -> 5.7913893 | BF11: ='Rooftop Calc'!AN126 -> 6.5716594
A12: R6 | B12: ESOLPVRES | C12: Solar PV Distributed Residential Generation | E12: SOLRES | F12: ELC | G12: 2010 | H12: 30 | I12: 31.536 | J12: =AM12/AL12 -> 0.34965035 | K12: 0.3 | L12: =AO12/I12 -> 0.00041200637 | M12: 6546.9995 | N12: 3903.1781 | O12: 3453.8021 | P12: 3004.4261 | Q12: 2839.3022 | R12: 2674.1784 | S12: 2596.418 | T12: 2558.6683 | U12: 2540.0679 | V12: 2530.8353 | W12: 10 | X12: 0 | Y12: 0.34054374 | Z12: 0.34054374 | AA12: 0 | AB12: 0.30737101 | AC12: 0.30737101 | AD12: 0.30737101 | AE12: 0 | AF12: 0.32128124 | AG12: 0.32128124 | AH12: 0.32128124 | AI12: 0 | AJ12: 0.15 | AL12: 2.86 | AM12: 1 | AO12: ='Rooftop Calc'!AG65 -> 0.012993033 | AP12: ='Rooftop Calc'!AG71 -> 0.17523498 | AQ12: ='Rooftop Calc'!AG77 -> 0.47194746 | AR12: ='Rooftop Calc'!AG84 -> 0.89934986 | AS12: ='Rooftop Calc'!AG91 -> 1.3267523 | AT12: ='Rooftop Calc'!AG98 -> 1.7541547 | AU12: ='Rooftop Calc'!AG105 -> 2.1815571 | AV12: ='Rooftop Calc'!AG112 -> 2.5959664 | AW12: ='Rooftop Calc'!AG119 -> 2.8481338 | AX12: ='Rooftop Calc'!AG126 -> 3.138694 | AY12: ='Rooftop Calc'!AO77 -> 0.60330901 | AZ12: ='Rooftop Calc'!AO84 -> 1.0301314 | BA12: ='Rooftop Calc'!AO91 -> 1.4582054 | BB12: ='Rooftop Calc'!AO98 -> 1.8850278 | BC12: ='Rooftop Calc'!AO105 -> 2.3131018 | BD12: ='Rooftop Calc'!AO112 -> 2.7399241 | BE12: ='Rooftop Calc'!AO119 -> 3.1679982 | BF12: ='Rooftop Calc'!AO126 -> 3.5948205
A13: * | AO13: =SUM(AO8:AO12) -> 0.026880973 | AP13: =SUM(AP8:AP12) -> 0.68766875 | AQ13: =SUM(AQ8:AQ12) -> 1.443419 | AR13: =SUM(AR8:AR12) -> 2.6452688 | AS13: =SUM(AS8:AS12) -> 3.8471186 | AT13: =SUM(AT8:AT12) -> 5.0489684 | AU13: =SUM(AU8:AU12) -> 6.2508183 | AV13: =SUM(AV8:AV12) -> 7.4257871 | ... BF13: =SUM(BF8:BF12) -> 14.107033
A14: *

Sheet TechData_DMD
A1: TechData | B1: _GLOBAL,R0,R1,R2,R3,R4,R5,R6 | L1: R2 | M1: R3 | N1: R4 | O1: R5 | P1: R6 | S1: R2 | T1: R3 | U1: R4 | V1: R5 | W1: R6 | X1: R2 | Y1: R3 | Z1: R4 | AA1: R5 | AB1: R6 | AC1: R2 | AD1: R3 | AE1: R4 | AF1: R5 | AG1: R6
A7: Region | B7: TechName | C7: *TechDesc | D7: *Units | E7: CommIN | F7: CommOUT | G7: NCAP_START | H7: NCAP_TLIFE | I7: NCAP_COST | J7: EFF | K7: Share~UP | L7: NCAP_AF~R2 | M7: NCAP_AF~R3 | N7: NCAP_AF~R4 | O7: NCAP_AF~R5 | P7: NCAP_AF~R6 | Q7: NCAP_FOM | R7: NCAP_DRATE | S7: PRC_RESID~R2~2010 | T7: PRC_RESID~R3~2010 | U7: PRC_RESID~R4~2010 | V7: PRC_RESID~R5~2010 | W7: PRC_RESID~R6~2010 | X7: PRC_RESID~R2~2015 | Y7: PRC_RESID~R3~2015 | Z7: PRC_RESID~R4~2015 | AA7: PRC_RESID~R5~2015 | AB7: PRC_RESID~R6~2015 | AC7: PRC_RESID~R2~2020 | AD7: PRC_RESID~R3~2020 | AE7: PRC_RESID~R4~2020 | AF7: PRC_RESID~R5~2020 | AG7: PRC_RESID~R6~2020 | AH7: NCAP_BND~2010 | AI7: NCAP_BND~2015 | AJ7: NCAP_BND~2020 | AK7: NCAP_BND~2025 | AL7: NCAP_BND~2030 | AM7: NCAP_BND~2035 | AN7: NCAP_BND~2040 | AO7: NCAP_BND~2045 | AP7: NCAP_BND~2050 | AQ7: NCAP_BND~2055 | AT7: *GROWTH~2015 | AU7: *GROWTH~2020 | AV7: *GROWTH~2025 | AW7: *GROWTH~2030 | AX7: *GROWTH~2035 | AY7: *GROWTH~2040 | AZ7: *GROWTH~2045 | BA7: *GROWTH~2050 | BB7: *GROWTH~2055
A8: *Space Heating
A9: *Electric Radiant Heating
A10: * | B10: RSHERDBS05 | C10: Electric Radiant Base.RSH.ELC.05 | D10: PJ | E10: RESELC | F10: =Commodities!$D$11 -> RSH | G10: 2010 | H10: 20 | J10: 1 | K10: 1 | L10: 0.16 | M10: 0.16 | N10: 0.16 | O10: 0.16 | P10: 0.16 | R10: 0.18 | AH10: 0 | AI10: 0 | AJ10: 0 | AK10: 0 | AL10: 0 | AM10: 0 | AN10: 0 | AO10: 0 | AP10: 0 | AQ10: 0
A11: R2,R3,R4,R5,R6 | B11: RSHERDV110 | C11: Electric Radiant Ver1.RSH.ELC.10 | D11: PJ | E11: RESELC | F11: =Commodities!$D$11 -> RSH | G11: 2010 | H11: 20 | I11: 3.7369871 | J11: 1 | K11: 1 | L11: 0.16 | M11: 0.16 | N11: 0.16 | O11: 0.16 | P11: 0.16 | R11: 0.18 | S11: =Resid!V7 -> 4.748916 | T11: =Resid!W7 -> 2.7595598 | U11: =Resid!X7 -> 4.555966 | V11: =Resid!Y7 -> 0.89318094 | W11: =Resid!Z7 -> 2.386034 | X11: =S11*15/20 -> 3.561687 | Y11: =T11*15/20 -> 2.0696698 | Z11: =U11*15/20 -> 3.4169745 | AA11: =V11*15/20 -> 0.66988571 | AB11: =W11*15/20 -> 1.7895255 | AH11: 0 | AI11: 0 | AJ11: =SUM(X11:AB11)*1.12 -> 12.888672 | AK11: =AJ11*1.12 -> 14.435312 | AL11: =AK11*1.12 -> 16.16755 | AM11: =AL11*1.12 -> 18.107656 | AN11: =AM11*1.12 -> 20.280574 | AO11: =AN11*1.12 -> 22.714243 | AP11: =AO11*1.12 -> 25.439952 | AQ11: =AP11*1.12 -> 28.492747 | AU11: 1.1 | AV11: =AU11 -> 1.1 | AW11: =AV11 -> 1.1 | AX11: =AW11 -> 1.1 | AY11: =AX11 -> 1.1 | AZ11: =AY11 -> 1.1 | BA11: =AZ11 -> 1.1 | BB11: =BA11 -> 1.1
A12: *Electric Resistance Furnaces
A13: * | B13: RSHEFRV120 | C13: Electric Resistance Furnace Ver1.RSH.ELC.20 | D13: PJ | E13: RESELC | F13: =Commodities!$D$11 -> RSH | G13: 2020 | H13: 15 | I13: 2.775407 | J13: 0.98 | K13: 1 | L13: 0.16 | M13: 0.16 | N13: 0.16 | O13: 0.16 | P13: 0.16 | R13: 0.18
A14: * | B14: RSHEFRV130 | C14: Electric Resistance Furnace Ver1.RSH.ELC.30 | D14: PJ | E14: RESELC | F14: =Commodities!$D$11 -> RSH | G14: 2030 | H14: 15 | I14: 2.775407 | J14: 0.98 | K14: 1 | L14: 0.16 | M14: 0.16 | N14: 0.16 | O14: 0.16 | P14: 0.16 | R14: 0.18
A15: * | B15: RSHEFRV230 | C15: Electric Resistance Furnace Ver2.RSH.ELC.30 | D15: PJ | E15: RESELC | F15: =Commodities!$D$11 -> RSH | G15: 2030 | H15: 30 | I15: 3.2831034 | J15: 0.98 | K15: 1 | L15: 0.16 | M15: 0.16 | N15: 0.16 | O15: 0.16 | P15: 0.16 | R15: 0.18
A16: * | B16: RSHEFRV140 | C16: Electric Resistance Furnace Ver1.RSH.ELC.40 | D16: PJ | E16: RESELC | F16: =Commodities!$D$11 -> RSH | G16: 2040 | H16: 15 | I16: 2.775407 | J16: 0.98 | K16: 1 | L16: 0.16 | M16: 0.16 | N16: 0.16 | O16: 0.16 | P16: 0.16 | R16: 0.18
A17: * | B17: RSHEFRV240 | C17: Electric Resistance Furnace Ver2.RSH.ELC.40 | D17: PJ | E17: RESELC | F17: =Commodities!$D$11 -> RSH | G17: 2040 | H17: 30 | I17: 3.2831034 | J17: 0.98 | K17: 1 | L17: 0.16 | M17: 0.16 | N17: 0.16 | O17: 0.16 | P17: 0.16 | R17: 0.18
A18: * | B18: RSHEFRV250 | C18: Electric Resistance Furnace Ver2.RSH.ELC.50 | D18: PJ | E18: RESELC | F18: =Commodities!$D$11 -> RSH | G18: 2050 | H18: 30 | I18: 3.2831034 | J18: 0.98 | K18: 1 | L18: 0.16 | M18: 0.16 | N18: 0.16 | O18: 0.16 | P18: 0.16 | R18: 0.18
A19: * | B19: RSHEFRV220 | C19: Electric Resistance Furnace Ver2.RSH.ELC.20 | D19: PJ | E19: RESELC | F19: =Commodities!$D$11 -> RSH | G19: 2020 | H19: 30 | I19: 2.2343255 | J19: 0.98 | K19: 1 | L19: 0.16 | M19: 0.16 | N19: 0.16 | O19: 0.16 | P19: 0.16 | R19: 0.18
A20: * | B20: RSHEFRV130 | C20: Electric Resistance Furnace Ver1.RSH.ELC.30 | D20: PJ | E20: RESELC | F20: =Commodities!$D$11 -> RSH | G20: 2030 | H20: 15 | I20: 1.8619379 | J20: 0.98 | K20: 1 | L20: 0.16 | M20: 0.16 | N20: 0.16 | O20: 0.16 | P20: 0.16 | R20: 0.18
A21: * | B21: RSHEFRV230 | C21: Electric Resistance Furnace Ver2.RSH.ELC.30 | D21: PJ | E21: RESELC | F21: =Commodities!$D$11 -> RSH | G21: 2030 | H21: 30 | I21: 2.2343255 | J21: 0.98 | K21: 1 | L21: 0.16 | M21: 0.16 | N21: 0.16 | O21: 0.16 | P21: 0.16 | R21: 0.18
A22: * | B22: RSHEFRV140 | C22: Electric Resistance Furnace Ver1.RSH.ELC.40 | D22: PJ | E22: RESELC | F22: =Commodities!$D$11 -> RSH | G22: 2040 | H22: 15 | I22: 1.8619379 | J22: 0.98 | K22: 1 | L22: 0.16 | M22: 0.16 | N22: 0.16 | O22: 0.16 | P22: 0.16 | R22: 0.18
A23: * | B23: RSHEFRV240 | C23: Electric Resistance Furnace Ver2.RSH.ELC.40 | D23: PJ | E23: RESELC | F23: =Commodities!$D$11 -> RSH | G23: 2040 | H23: 30 | I23: 2.2343255 | J23: 0.98 | K23: 1 | L23: 0.16 | M23: 0.16 | N23: 0.16 | O23: 0.16 | P23: 0.16 | R23: 0.18
A24: * | B24: RSHEFRV150 | C24: Electric Resistance Furnace Ver1.RSH.ELC.50 | D24: PJ | E24: RESELC | F24: =Commodities!$D$11 -> RSH | G24: 2050 | H24: 15 | I24: 1.8619379 | J24: 0.98 | K24: 1 | L24: 0.16 | M24: 0.16 | N24: 0.16 | O24: 0.16 | P24: 0.16 | R24: 0.18
A25: * | B25: RSHEFRV250 | C25: Electric Resistance Furnace Ver2.RSH.ELC.50 | D25: PJ | E25: RESELC | F25: =Commodities!$D$11 -> RSH | G25: 2050 | H25: 30 | I25: 2.2343255 | J25: 0.98 | K25: 1 | L25: 0.16 | M25: 0.16 | N25: 0.16 | O25: 0.16 | P25: 0.16 | R25: 0.18
A26: *Electric Heat Pumps
A27: * | B27: RSHEHPBS05 | C27: Electric Heat Pump Base.RSH.ELC.05 | D27: PJ | E27: RESELC | F27: =Commodities!$D$11 -> RSH | G27: 2010 | H27: 15 | I27: 4.0729892 | J27: 2.2657 | K27: 1 | L27: 0.16 | M27: 0.16 | N27: 0.16 | O27: 0.16 | P27: 0.16 | R27: 0.18 | AJ27: 0 | AK27: 0 | AL27: 0 | AM27: 0 | AN27: 0 | AO27: 0 | AP27: 0 | AQ27: 0
A28: R2,R3,R4,R5,R6 | B28: RSHEHPV110 | C28: Electric Heat Pump Ver1.RSH.ELC.10 | D28: PJ | E28: RESELC | F28: =Commodities!$D$11 -> RSH | G28: 2010 | H28: 15 | I28: 4.0729892 | J28: 2.26 | K28: 1 | L28: 0.16 | M28: 0.16 | N28: 0.16 | O28: 0.16 | P28: 0.16 | R28: 0.18 | S28: =Resid!V10 -> 2.4354858 | T28: =Resid!W10 -> 1.4152427 | U28: =Resid!X10 -> 2.3365312 | V28: =Resid!Y10 -> 0.45806863 | W28: =Resid!Z10 -> 1.2236797 | AH28: 0 | AI28: 0 | AJ28: 0 | AK28: 0 | AL28: 0 | AM28: 0 | AN28: 0 | AO28: 0 | AP28: 0 | AQ28: 0
A29: * | B29: RSHEHPV115 | C29: Electric Heat Pump Ver1.RSH.ELC.15 | D29: PJ | E29: RESELC | F29: =Commodities!$D$11 -> RSH | G29: 2015 | H29: 15 | I29: 4.0729892 | J29: 2.26 | K29: 1 | L29: 0.16 | M29: 0.16 | N29: 0.16 | O29: 0.16 | P29: 0.16 | R29: 0.18 | AH29: 0
A30: * | B30: RSHEHPV215 | C30: Electric Heat Pump Ver2.RSH.ELC.15 | D30: PJ | E30: RESELC | F30: =Commodities!$D$11 -> RSH | G30: 2015 | H30: 15 | I30: 6.1935761 | J30: 2.7442857 | K30: 1 | L30: 0.16 | M30: 0.16 | N30: 0.16 | O30: 0.16 | P30: 0.16 | R30: 0.18
A31: * | B31: RSHEHPV320 | C31: Electric Heat Pump Ver3.RSH.ELC.20 | D31: PJ | E31: RESELC | F31: =Commodities!$D$11 -> RSH | G31: 2020 | H31: 9 | I31: 6.3763853 | J31: 2.7765714 | K31: 1 | L31: 0.16 | M31: 0.16 | N31: 0.16 | O31: 0.16 | P31: 0.16 | R31: 0.18
A32: * | B32: RSHEHPV520 | C32: Electric Heat Pump Ver5.RSH.ELC.20 | D32: PJ | E32: RESELC | F32: =Commodities!$D$11 -> RSH | G32: 2020 | H32: 9 | I32: 7.8022972 | J32: 2.9057143 | K32: 1 | L32: 0.16 | M32: 0.16 | N32: 0.16 | O32: 0.16 | P32: 0.16 | R32: 0.18
A33: * | B33: RSHEHPV430 | C33: Electric Heat Pump Ver4.RSH.ELC.30 | D33: PJ | E33: RESELC | F33: =Commodities!$D$11 -> RSH | G33: 2030 | H33: 22 | I33: 6.5628507 | J33: 2.8411429 | K33: 1 | L33: 0.16 | M33: 0.16 | N33: 0.16 | O33: 0.16 | P33: 0.16 | R33: 0.18
A34: * | B34: RSHEHPV630 | C34: Electric Heat Pump Ver6.RSH.ELC.30 | D34: PJ | E34: RESELC | F34: =Commodities!$D$11 -> RSH | G34: 2030 | H34: 22 | I34: 7.879077 | J34: 2.9057143 | K34: 1 | L34: 0.16 | M34: 0.16 | N34: 0.16 | O34: 0.16 | P34: 0.16 | R34: 0.18
A35: * | B35: RSHEHPV440 | C35: Electric Heat Pump Ver4.RSH.ELC.40 | D35: PJ | E35: RESELC | F35: =Commodities!$D$11 -> RSH | G35: 2040 | H35: 22 | I35: 6.5628507 | J35: 2.8411429 | K35: 1 | L35: 0.16 | M35: 0.16 | N35: 0.16 | O35: 0.16 | P35: 0.16 | R35: 0.18
A36: * | B36: RSHEHPV640 | C36: Electric Heat Pump Ver6.RSH.ELC.40 | D36: PJ | E36: RESELC | F36: =Commodities!$D$11 -> RSH | G36: 2040 | H36: 22 | I36: 7.8022972 | J36: 2.9057143 | K36: 1 | L36: 0.16 | M36: 0.16 | N36: 0.16 | O36: 0.16 | P36: 0.16 | R36: 0.18
A37: * | B37: RSHEHPV210 | C37: Electric Heat Pump Ver2.RSH.ELC.10 | D37: PJ | E37: RESELC | F37: =Commodities!$D$11 -> RSH | G37: 2010 | H37: 15 | I37: 8.8097833 | J37: 2.4 | K37: 1 | L37: 0.16 | M37: 0.16 | N37: 0.16 | O37: 0.16 | P37: 0.16 | R37: 0.18 | AH37: 0 | AI37: 0 | AJ37: 0 | AK37: 0 | AL37: 0 | AM37: 0 | AN37: 0 | AO37: 0 | AP37: 0 | AQ37: 0
A38: * | B38: RSHEHPV215 | C38: Electric Heat Pump Ver2.RSH.ELC.15 | D38: PJ | E38: RESELC | F38: =Commodities!$D$11 -> RSH | G38: 2015 | H38: 15 | I38: 9.3561264 | J38: 2.58 | K38: 1 | L38: 0.16 | M38: 0.16 | N38: 0.16 | O38: 0.16 | P38: 0.16 | R38: 0.18 | AH38: 0
A39: * | B39: RSHEHPV310 | C39: Electric Heat Pump Ver3.RSH.ELC.10 | D39: PJ | E39: RESELC | F39: =Commodities!$D$11 -> RSH | G39: 2010 | H39: 15 | I39: 9.7658838 | J39: 2.49 | K39: 1 | L39: 0.16 | M39: 0.16 | N39: 0.16 | O39: 0.16 | P39: 0.16 | R39: 0.18 | AH39: 0 | AI39: 0 | AJ39: 0 | AK39: 0 | AL39: 0 | AM39: 0 | AN39: 0 | AO39: 0 | AP39: 0 | AQ39: 0
A40: * | B40: RSHEHPV315 | C40: Electric Heat Pump Ver3.RSH.ELC.15 | D40: PJ | E40: RESELC | F40: =Commodities!$D$11 -> RSH | G40: 2015 | H40: 15 | I40: 9.7658838 | J40: 2.49 | K40: 1 | L40: 0.16 | M40: 0.16 | N40: 0.16 | O40: 0.16 | P40: 0.16 | R40: 0.18 | AH40: 0 | AK40: 0 | AL40: 0 | AM40: 0 | AN40: 0 | AO40: 0 | AP40: 0 | AQ40: 0
A41: * | B41: RSHEHPV320 | C41: Electric Heat Pump Ver3.RSH.ELC.20 | D41: PJ | E41: RESELC | F41: =Commodities!$D$11 -> RSH | G41: 2020 | H41: 15 | I41: 10.243934 | J41: 2.78 | K41: 1 | L41: 0.16 | M41: 0.16 | N41: 0.16 | O41: 0.16 | P41: 0.16 | R41: 0.18 | AH41: 0 | AL41: 0 | AM41: 0 | AN41: 0 | AO41: 0 | AP41: 0 | AQ41: 0
A42: * | B42: RSHEHPV330 | C42: Electric Heat Pump Ver3.RSH.ELC.30 | D42: PJ | E42: RESELC | F42: =Commodities!$D$11 -> RSH | G42: 2030 | H42: 15 | I42: 10.243934 | J42: 2.8 | K42: 1 | L42: 0.16 | M42: 0.16 | N42: 0.16 | O42: 0.16 | P42: 0.16 | R42: 0.18 | AH42: 0
A43: * | B43: RSHEHPV410 | C43: Electric Heat Pump Ver4.RSH.ELC.10 | D43: PJ | E43: RESELC | F43: =Commodities!$D$11 -> RSH | G43: 2010 | H43: 15 | I43: 10.926863 | J43: 3.14 | K43: 1 | L43: 0.16 | M43: 0.16 | N43: 0.16 | O43: 0.16 | P43: 0.16 | R43: 0.18 | AH43: 0 | AJ43: 0 | AK43: 0 | AL43: 0 | AM43: 0 | AN43: 0 | AO43: 0 | AP43: 0 | AQ43: 0
A44: * | B44: RSHEHPV420 | C44: Electric Heat Pump Ver4.RSH.ELC.20 | D44: PJ | E44: RESELC | F44: =Commodities!$D$11 -> RSH | G44: 2020 | H44: 15 | I44: 11.200035 | J44: 3.17 | K44: 1 | L44: 0.16 | M44: 0.16 | N44: 0.16 | O44: 0.16 | P44: 0.16 | R44: 0.18 | AH44: 0 | AL44: 0 | AM44: 0 | AN44: 0 | AO44: 0 | AP44: 0 | AQ44: 0
A45: * | B45: RSHEHPV430 | C45: Electric Heat Pump Ver4.RSH.ELC.30 | D45: PJ | E45: RESELC | F45: =Commodities!$D$11 -> RSH | G45: 2030 | H45: 15 | I45: 11.268327 | J45: 3.22 | K45: 1 | L45: 0.16 | M45: 0.16 | N45: 0.16 | O45: 0.16 | P45: 0.16 | R45: 0.18 | AH45: 0 | AM45: 0 | AN45: 0 | AO45: 0 | AP45: 0 | AQ45: 0
A46: * | B46: RSHEHPV435 | C46: Electric Heat Pump Ver4.RSH.ELC.35 | D46: PJ | E46: RESELC | F46: =Commodities!$D$11 -> RSH | G46: 2035 | H46: 15 | I46: 11.268327 | J46: 3.22 | K46: 1 | L46: 0.16 | M46: 0.16 | N46: 0.16 | O46: 0.16 | P46: 0.16 | R46: 0.18 | AH46: 0
A47: *Natural Gas Furnaces
A48: * | B48: RSHNFRBS05 | C48: Natural Gas Furnace Base.RSH.NGA.05 | D48: PJ | E48: RESNGAEA | F48: =Commodities!$D$11 -> RSH | G48: 2010 | H48: 15 | J48: 0.81440002 | K48: 1 | L48: 0.16 | M48: 0.16 | N48: 0.16 | O48: 0.16 | P48: 0.16 | R48: 0.15 | AH48: 0 | AI48: 0 | AJ48: 0 | AK48: 0 | AL48: 0 | AM48: 0 | AN48: 0 | AO48: 0 | AP48: 0 | AQ48: 0
A49: R2,R3,R4,R5,R6 | B49: RSHNFRV110 | C49: Natural Gas Furnace Ver1.RSH.NGA.10 | D49: PJ | E49: RESNGAEA | F49: =Commodities!$D$11 -> RSH | G49: 2010 | H49: 15 | I49: 3.5376821 | J49: 0.78 | K49: 1 | L49: 0.16 | M49: 0.16 | N49: 0.16 | O49: 0.16 | P49: 0.16 | R49: 0.15 | S49: =Resid!V25 -> 100.23486 | T49: =Resid!W25 -> 58.245734 | U49: =Resid!X25 -> 96.162288 | V49: =Resid!Y25 -> 18.852275 | W49: =Resid!Z25 -> 50.361766 | X49: =S49*2/3 -> 66.823243 | Y49: =T49*2/3 -> 38.830489 | Z49: =U49*2/3 -> 64.108192 | AA49: =V49*2/3 -> 12.568183 | AB49: =W49*2/3 -> 33.574511 | AC49: =U49*1/3 -> 32.054096 | AD49: =V49*1/3 -> 6.2840917 | AE49: =W49*1/3 -> 16.787255 | AF49: =X49*1/3 -> 22.274414 | AG49: =Y49*1/3 -> 12.943496 | AH49: 0
A50: * | B50: RSHNFRV115 | C50: Natural Gas Furnace Ver1.RSH.NGA.15 | D50: PJ | E50: RESNGAEA | F50: =Commodities!$D$11 -> RSH | G50: 2015 | H50: 15 | I50: 3.5376821 | J50: 0.78 | K50: 1 | L50: 0.16 | M50: 0.16 | N50: 0.16 | O50: 0.16 | P50: 0.16 | R50: 0.15
A51: * | B51: RSHNFRV215 | C51: Natural Gas Furnace Ver2.RSH.NGA.15 | D51: PJ | E51: RESNGAEA | F51: =Commodities!$D$11 -> RSH | G51: 2015 | H51: 15 | I51: 5.0362835 | J51: 0.92625 | K51: 1 | L51: 0.16 | M51: 0.16 | N51: 0.16 | O51: 0.16 | P51: 0.16 | R51: 0.15
A52: * | B52: RSHNFRV320 | C52: Natural Gas Furnace Ver3.RSH.NGA.20 | D52: PJ | E52: RESNGAEA | F52: =Commodities!$D$11 -> RSH | G52: 2020 | H52: 16 | I52: 5.085418 | J52: 0.897 | K52: 1 | L52: 0.16 | M52: 0.16 | N52: 0.16 | O52: 0.16 | P52: 0.16 | R52: 0.15
A53: * | B53: RSHNFRV520 | C53: Natural Gas Furnace Ver5.RSH.NGA.20 | D53: PJ | E53: RESNGAEA | F53: =Commodities!$D$11 -> RSH | G53: 2020 | H53: 16 | I53: 5.7733006 | J53: 0.96525 | K53: 1 | L53: 0.16 | M53: 0.16 | N53: 0.16 | O53: 0.16 | P53: 0.16 | R53: 0.15
A54: * | B54: RSHNFRV430 | C54: Natural Gas Furnace Ver4.RSH.NGA.30 | D54: PJ | E54: RESNGAEA | F54: =Commodities!$D$11 -> RSH | G54: 2030 | H54: 27 | I54: 5.085418 | J54: 0.897 | K54: 1 | L54: 0.16 | M54: 0.16 | N54: 0.16 | O54: 0.16 | P54: 0.16 | R54: 0.15
A55: * | B55: RSHNFRV630 | C55: Natural Gas Furnace Ver6.RSH.NGA.30 | D55: PJ | E55: RESNGAEA | F55: =Commodities!$D$11 -> RSH | G55: 2030 | H55: 27 | I55: 5.7733006 | J55: 0.96525 | K55: 1 | L55: 0.16 | M55: 0.16 | N55: 0.16 | O55: 0.16 | P55: 0.16 | R55: 0.15
A56: * | B56: RSHNFRV440 | C56: Natural Gas Furnace Ver4.RSH.NGA.40 | D56: PJ | E56: RESNGAEA | F56: =Commodities!$D$11 -> RSH | G56: 2040 | H56: 27 | I56: 5.085418 | J56: 0.897 | K56: 1 | L56: 0.16 | M56: 0.16 | N56: 0.16 | O56: 0.16 | P56: 0.16 | R56: 0.15
A57: * | B57: RSHNFRV640 | C57: Natural Gas Furnace Ver6.RSH.NGA.40 | D57: PJ | E57: RESNGAEA | F57: =Commodities!$D$11 -> RSH | G57: 2040 | H57: 27 | I57: 5.7733006 | J57: 0.96525 | K57: 1 | L57: 0.16 | M57: 0.16 | N57: 0.16 | O57: 0.16 | P57: 0.16 | R57: 0.15
A58: * | B58: RSHNFRV210 | C58: Natural Gas Furnace Ver2.RSH.NGA.10 | D58: PJ | E58: RESNGAEA | F58: =Commodities!$D$11 -> RSH | G58: 2010 | H58: 15 | I58: 4.9170883 | J58: 0.8 | K58: 1 | L58: 0.16 | M58: 0.16 | N58: 0.16 | O58: 0.16 | P58: 0.16 | R58: 0.15 | AH58: 0
A59: * | B59: RSHNFRV310 | C59: Natural Gas Furnace Ver3.RSH.NGA.10 | D59: PJ | E59: RESNGAEA | F59: =Commodities!$D$11 -> RSH | G59: 2010 | H59: 20 | I59: 5.4087972 | J59: 0.9 | K59: 1 | L59: 0.16 | M59: 0.16 | N59: 0.16 | O59: 0.16 | P59: 0.16 | R59: 0.15 | AH59: 0
A60: * | B60: RSHNFRV410 | C60: Natural Gas Furnace Ver4.RSH.NGA.10 | D60: PJ | E60: RESNGAEA | F60: =Commodities!$D$11 -> RSH | G60: 2010 | H60: 20 | I60: 6.2938731 | J60: 0.95 | K60: 1 | L60: 0.16 | M60: 0.16 | N60: 0.16 | O60: 0.16 | P60: 0.16 | R60: 0.15 | AH60: 0 | AI60: 0
A61: * | B61: RSHNFRV510 | C61: Natural Gas Furnace Ver5.RSH.NGA.10 | D61: PJ | E61: RESNGAEA | F61: =Commodities!$D$11 -> RSH | G61: 2010 | H61: 20 | I61: 7.3756325 | J61: 0.98 | K61: 1 | L61: 0.16 | M61: 0.16 | N61: 0.16 | O61: 0.16 | P61: 0.16 | R61: 0.15 | AH61: 0 | AI61: 0
A62: * | B62: RSHNFRV120 | C62: Natural Gas Furnace Ver1.RSH.NGA.20 | D62: PJ | E62: RESNGAEA | F62: =Commodities!$D$11 -> RSH | G62: 2020 | H62: 27 | I62: 5.1389487 | J62: 0.92 | K62: 1 | L62: 0.16 | M62: 0.16 | N62: 0.16 | O62: 0.16 | P62: 0.16 | R62: 0.15 | AH62: 0 | AI62: 0
A63: * | B63: RSHNFRV220 | C63: Natural Gas Furnace Ver2.RSH.NGA.20 | D63: PJ | E63: RESNGAEA | F63: =Commodities!$D$11 -> RSH | G63: 2020 | H63: 27 | I63: 5.6602913 | J63: 0.99 | K63: 1 | L63: 0.16 | M63: 0.16 | N63: 0.16 | O63: 0.16 | P63: 0.16 | R63: 0.15 | AH63: 0 | AI63: 0
A64: * | B64: RSHNFRV130 | C64: Natural Gas Furnace Ver1.RSH.NGA.30 | D64: PJ | E64: RESNGAEA | F64: =Commodities!$D$11 -> RSH | G64: 2030 | H64: 27 | I64: 5.1389487 | J64: 0.92 | K64: 1 | L64: 0.16 | M64: 0.16 | N64: 0.16 | O64: 0.16 | P64: 0.16 | R64: 0.15 | AH64: 0 | AI64: 0
A65: * | B65: RSHNFRV230 | C65: Natural Gas Furnace Ver1.RSH.NGA.30 | D65: PJ | E65: RESNGAEA | F65: =Commodities!$D$11 -> RSH | G65: 2030 | H65: 27 | I65: 5.6602913 | J65: 0.99 | K65: 1 | L65: 0.16 | M65: 0.16 | N65: 0.16 | O65: 0.16 | P65: 0.16 | R65: 0.15 | AH65: 0 | AI65: 0
A66: * | B66: RSHNFRV140 | C66: Natural Gas Furnace Ver1.RSH.NGA.40 | D66: PJ | E66: RESNGAEA | F66: =Commodities!$D$11 -> RSH | G66: 2040 | H66: 27 | I66: 5.1389487 | J66: 0.92 | K66: 1 | L66: 0.16 | M66: 0.16 | N66: 0.16 | O66: 0.16 | P66: 0.16 | R66: 0.15 | AH66: 0 | AI66: 0
A67: * | B67: RSHNFRV240 | C67: Natural Gas Furnace Ver1.RSH.NGA.40 | D67: PJ | E67: RESNGAEA | F67: =Commodities!$D$11 -> RSH | G67: 2040 | H67: 27 | I67: 5.6602913 | J67: 0.99 | K67: 1 | L67: 0.16 | M67: 0.16 | N67: 0.16 | O67: 0.16 | P67: 0.16 | R67: 0.15 | AH67: 0 | AI67: 0
A68: * | B68: RSHNFRV150 | C68: Natural Gas Furnace Ver1.RSH.NGA.50 | D68: PJ | E68: RESNGAEA | F68: =Commodities!$D$11 -> RSH | G68: 2050 | H68: 27 | I68: 5.1389487 | J68: 0.93 | K68: 1 | L68: 0.16 | M68: 0.16 | N68: 0.16 | O68: 0.16 | P68: 0.16 | R68: 0.15 | AH68: 0 | AI68: 0
A69: * | B69: RSHNFRV250 | C69: Natural Gas Furnace Ver1.RSH.NGA.50 | D69: PJ | E69: RESNGAEA | F69: =Commodities!$D$11 -> RSH | G69: 2050 | H69: 27 | I69: 5.6602913 | J69: 0.99 | K69: 1 | L69: 0.16 | M69: 0.16 | N69: 0.16 | O69: 0.16 | P69: 0.16 | R69: 0.15 | AH69: 0 | AI69: 0
A70: *Natural Gas Radiant Heating
A71: * | B71: RSHNRDBS05 | C71: Natural Gas Radiant Base.RSH.NGA.05 | D71: PJ | E71: RESNGAEA | F71: =Commodities!$D$11 -> RSH | G71: 2010 | H71: 20 | J71: 0.8 | K71: 1 | L71: 0.16 | M71: 0.16 | N71: 0.16 | O71: 0.16 | P71: 0.16 | R71: 0.15 | AH71: 0 | AI71: 0 | AJ71: 0 | AK71: 0 | AL71: 0 | AM71: 0 | AN71: 0 | AO71: 0 | AP71: 0 | AQ71: 0
A72: R2,R3,R4,R5,R6 | B72: RSHNRDV110 | C72: Natural Gas Radiant Ver1.RSH.NGA.10 | D72: PJ | E72: RESNGAEA | F72: =Commodities!$D$11 -> RSH | G72: 2010 | H72: 20 | I72: 8.2856238 | J72: 0.8 | K72: 1 | L72: 0.16 | M72: 0.16 | N72: 0.16 | O72: 0.16 | P72: 0.16 | R72: 0.15 | S72: =Resid!V32 -> 58.812533 | T72: =Resid!W32 -> 34.175525 | U72: =Resid!X32 -> 56.42296 | V72: =Resid!Y32 -> 11.061521 | W72: =Resid!Z32 -> 29.549629 | X72: =S72*2/3 -> 39.208355 | Y72: =T72*2/3 -> 22.783684 | Z72: =U72*2/3 -> 37.615307 | AA72: =V72*2/3 -> 7.3743473 | AB72: =W72*2/3 -> 19.699753 | AC72: =U72*1/3 -> 18.807653 | AD72: =V72*1/3 -> 3.6871737 | AE72: =W72*1/3 -> 9.8498763 | AF72: =X72*1/3 -> 13.069452 | AG72: =Y72*1/3 -> 7.5945612 | AH72: 0 | AJ72: 0 | AK72: 0 | AL72: 0 | AM72: 0 | AN72: 0 | AO72: 0 | AP72: 0 | AQ72: 0
A73: * | B73: RSHNRDV115 | C73: Natural Gas Radiant Ver1.RSH.NGA.15 | D73: PJ | E73: RESNGAEA | F73: =Commodities!$D$11 -> RSH | G73: 2015 | H73: 20 | I73: 8.2856238 | J73: 0.82 | K73: 1 | L73: 0.16 | M73: 0.16 | N73: 0.16 | O73: 0.16 | P73: 0.16 | R73: 0.15 | AH73: 0
A74: * | B74: RSHNRDV120 | C74: Natural Gas Radiant Ver1.RSH.NGA.20 | D74: PJ | E74: RESNGAEA | F74: =Commodities!$D$11 -> RSH | G74: 2020 | H74: 20 | I74: 9.4958835 | J74: 0.85 | K74: 1 | L74: 0.16 | M74: 0.16 | N74: 0.16 | O74: 0.16 | P74: 0.16 | R74: 0.15
A75: * | B75: RSHNRDV215 | C75: Natural Gas Radiant Ver2.RSH.NGA.15 | D75: PJ | E75: RESNGAEA | F75: =Commodities!$D$11 -> RSH | G75: 2015 | H75: 20 | I75: 11.916403 | J75: 0.98 | K75: 1 | L75: 0.16 | M75: 0.16 | N75: 0.16 | O75: 0.16 | P75: 0.16 | R75: 0.15
A76: * | B76: RSHNRDV220 | C76: Natural Gas Radiant Ver2.RSH.NGA.20 | D76: PJ | E76: RESNGAEA | F76: =Commodities!$D$11 -> RSH | G76: 2020 | H76: 20 | I76: 12.987017 | J76: 0.9 | K76: 1 | L76: 0.16 | M76: 0.16 | N76: 0.16 | O76: 0.16 | P76: 0.16 | R76: 0.15
A77: * | B77: RSHNRDV315 | C77: Natural Gas Radiant Ver3.RSH.NGA.15 | D77: PJ | E77: RESNGAEA | F77: =Commodities!$D$11 -> RSH | G77: 2015 | H77: 20 | I77: 12.988879 | J77: 0.96 | K77: 1 | L77: 0.16 | M77: 0.16 | N77: 0.16 | O77: 0.16 | P77: 0.16 | R77: 0.15
A78: * | B78: RSHNRDV210 | C78: Natural Gas Radiant Ver2.RSH.NGA.10 | D78: PJ | E78: RESNGAEA | F78: =Commodities!$D$11 -> RSH | G78: 2010 | H78: 20 | I78: 8.3590502 | J78: 0.85 | K78: 1 | L78: 0.16 | M78: 0.16 | N78: 0.16 | O78: 0.16 | P78: 0.16 | R78: 0.15 | AH78: 0 | AI78: 0
A79: * | B79: RSHNRDV310 | C79: Natural Gas Radiant Ver3.RSH.NGA.10 | D79: PJ | E79: RESNGAEA | F79: =Commodities!$D$11 -> RSH | G79: 2010 | H79: 20 | I79: 7.8673413 | J79: 0.98 | K79: 1 | L79: 0.16 | M79: 0.16 | N79: 0.16 | O79: 0.16 | P79: 0.16 | R79: 0.15 | AH79: 0 | AI79: 0 | AJ79: 0 | AK79: 0 | AL79: 0 | AM79: 0 | AN79: 0 | AO79: 0 | AP79: 0 | AQ79: 0
A80: *Kerosene Furnaces
A81: * | B81: RSHKFRBS05 | C81: Kerosene Furnace Base.RSH.KER.05 | D81: PJ | E81: RESKEREA | F81: =Commodities!$D$11 -> RSH | G81: 2010 | H81: 20 | J81: 0.8 | K81: 1 | L81: 0.16 | M81: 0.16 | N81: 0.16 | O81: 0.16 | P81: 0.16 | R81: 0.45 | AJ81: 0 | AK81: 0 | AL81: 0 | AM81: 0 | AN81: 0 | AO81: 0 | AP81: 0 | AQ81: 0
A82: * | B82: RSHKFRV110 | C82: Kerosene Furnace Ver1.RSH.KER.10 | D82: PJ | E82: RESKEREA | F82: =Commodities!$D$11 -> RSH | G82: 2010 | H82: 20 | I82: 6.3922148 | J82: 0.8 | K82: 1 | L82: 0.16 | M82: 0.16 | N82: 0.16 | O82: 0.16 | P82: 0.16 | R82: 0.45 | AJ82: 0 | AK82: 0 | AL82: 0 | AM82: 0 | AN82: 0 | AO82: 0 | AP82: 0 | AQ82: 0
A83: * | B83: RSHKFRV115 | C83: Kerosene Furnace Ver1.RSH.KER.15 | D83: PJ | E83: RESKEREA | F83: =Commodities!$D$11 -> RSH | G83: 2015 | H83: 20 | I83: 6.8839237 | J83: 0.83 | K83: 1 | L83: 0.16 | M83: 0.16 | N83: 0.16 | O83: 0.16 | P83: 0.16 | R83: 0.45
A84: * | B84: RSHKFRV210 | C84: Kerosene Furnace Ver2.RSH.KER.10 | D84: PJ | E84: RESKEREA | F84: =Commodities!$D$11 -> RSH | G84: 2010 | H84: 20 | I84: 7.3756325 | J84: 0.85 | K84: 1 | L84: 0.16 | M84: 0.16 | N84: 0.16 | O84: 0.16 | P84: 0.16 | R84: 0.45
A85: * | B85: RSHKFRV310 | C85: Kerosene Furnace Ver3.RSH.KER.10 | D85: PJ | E85: RESKEREA | F85: =Commodities!$D$11 -> RSH | G85: 2010 | H85: 20 | I85: 9.3424678 | J85: 0.98 | K85: 1 | L85: 0.16 | M85: 0.16 | N85: 0.16 | O85: 0.16 | P85: 0.16 | R85: 0.45
A86: *LPG Furnaces
A87: * | B87: RSHLFRBS05 | C87: Liquid Gas Furnace Base.RSH.LPG.05 | D87: PJ | E87: RESLPGEA | F87: =Commodities!$D$11 -> RSH | G87: 2010 | H87: 20 | J87: 0.78 | K87: 1 | L87: 0.16 | M87: 0.16 | N87: 0.16 | O87: 0.16 | P87: 0.16 | R87: 0.45 | AJ87: 0 | AK87: 0 | AL87: 0 | AM87: 0 | AN87: 0 | AO87: 0 | AP87: 0 | AQ87: 0
A88: * | B88: RSHLFRV110 | C88: Liquid Gas Furnace Ver1.RSH.LPG.10 | D88: PJ | E88: RESLPGEA | F88: =Commodities!$D$11 -> RSH | G88: 2010 | H88: 20 | I88: 4.9170883 | J88: 0.78 | K88: 1 | L88: 0.16 | M88: 0.16 | N88: 0.16 | O88: 0.16 | P88: 0.16 | R88: 0.45
A89: * | B89: RSHLFRV210 | C89: Liquid Gas Furnace Ver2.RSH.LPG.10 | D89: PJ | E89: RESLPGEA | F89: =Commodities!$D$11 -> RSH | G89: 2010 | H89: 20 | I89: 4.9170883 | J89: 0.8 | K89: 1 | L89: 0.16 | M89: 0.16 | N89: 0.16 | O89: 0.16 | P89: 0.16 | R89: 0.45
A90: * | B90: RSHLFRV310 | C90: Liquid Gas Furnace Ver3.RSH.LPG.10 | D90: PJ | E90: RESLPGEA | F90: =Commodities!$D$11 -> RSH | G90: 2010 | H90: 20 | I90: 5.4087972 | J90: 0.9 | K90: 1 | L90: 0.16 | M90: 0.16 | N90: 0.16 | O90: 0.16 | P90: 0.16 | R90: 0.45
A91: * | B91: RSHLFRV410 | C91: Liquid Gas Furnace Ver4.RSH.LPG.10 | D91: PJ | E91: RESLPGEA | F91: =Commodities!$D$11 -> RSH | G91: 2010 | H91: 20 | I91: 6.2938731 | J91: 0.95 | K91: 1 | L91: 0.16 | M91: 0.16 | N91: 0.16 | O91: 0.16 | P91: 0.16 | R91: 0.45
A92: * | B92: RSHLFRV510 | C92: Liquid Gas Furnace Ver5.RSH.LPG.10 | D92: PJ | E92: RESLPGEA | F92: =Commodities!$D$11 -> RSH | G92: 2010 | H92: 20 | I92: 7.3756325 | J92: 0.98 | K92: 1 | L92: 0.16 | M92: 0.16 | N92: 0.16 | O92: 0.16 | P92: 0.16 | R92: 0.45
A93: *Fuel Oil (DSL) Furnaces
A94: * | B94: RSHDFRBS05 | C94: Distillate Furnace Base.RSH.DST.05 | D94: PJ | E94: RESDSLEA | F94: =Commodities!$D$11 -> RSH | G94: 2010 | H94: 20 | J94: 0.81739998 | K94: 1 | L94: 0.16 | M94: 0.16 | N94: 0.16 | O94: 0.16 | P94: 0.16 | R94: 0.18 | AH94: 0 | AI94: 0 | AJ94: 0 | AK94: 0 | AL94: 0 | AM94: 0 | AN94: 0 | AO94: 0 | AP94: 0 | AQ94: 0
A95: R2,R3,R4,R5,R6 | B95: RSHDFRV110 | C95: Distillate Furnace Ver1.RSH.DST.10 | D95: PJ | E95: RESDSLEA | F95: =Commodities!$D$11 -> RSH | G95: 2010 | H95: 20 | I95: 6.3922148 | J95: 0.8 | K95: 1 | L95: 0.16 | M95: 0.16 | N95: 0.16 | O95: 0.16 | P95: 0.16 | R95: 0.18 | S95: =Resid!V39 -> 35.586069 | T95: =Resid!W39 -> 20.6788 | U95: =Resid!X39 -> 34.140195 | V95: =Resid!Y39 -> 6.693064 | W95: =Resid!Z39 -> 17.87978 | AH95: 0 | AJ95: 0 | AK95: 0 | AL95: 0 | AM95: 0 | AN95: 0 | AO95: 0 | AP95: 0 | AQ95: 0
A96: * | B96: RSHDFRV115 | C96: Distillate Furnace Ver1.RSH.DST.15 | D96: PJ | E96: RESDSLEA | F96: =Commodities!$D$11 -> RSH | G96: 2015 | H96: 20 | I96: 6.8839237 | J96: 0.83 | K96: 1 | L96: 0.16 | M96: 0.16 | N96: 0.16 | O96: 0.16 | P96: 0.16 | R96: 0.18 | AH96: 0 | AK96: 0 | AL96: 0 | AM96: 0 | AN96: 0 | AO96: 0 | AP96: 0 | AQ96: 0
A97: R2,R3,R4,R5,R6 | B97: RSHDFRV210 | C97: Distillate Furnace Ver2.RSH.DST.10 | D97: PJ | E97: RESDSLEA | F97: =Commodities!$D$11 -> RSH | G97: 2010 | H97: 20 | I97: 9.3424678 | J97: 0.85 | K97: 1 | L97: 0.16 | M97: 0.16 | N97: 0.16 | O97: 0.16 | P97: 0.16 | R97: 0.18 | AH97: 0 | AK97: 0 | AL97: 0 | AM97: 0 | AN97: 0 | AO97: 0 | AP97: 0 | AQ97: 0
A98: R2,R3,R4,R5,R6 | B98: RSHDFRV310 | C98: Distillate Furnace Ver3.RSH.DST.10 | D98: PJ | E98: RESDSLEA | F98: =Commodities!$D$11 -> RSH | G98: 2010 | H98: 20 | I98: 9.3424678 | J98: 0.98 | K98: 1 | L98: 0.16 | M98: 0.16 | N98: 0.16 | O98: 0.16 | P98: 0.16 | R98: 0.18 | AH98: 0 | AK98: 0 | AL98: 0 | AM98: 0 | AN98: 0 | AO98: 0 | AP98: 0 | AQ98: 0
A99: *Dfuel Oil (DSL) Radiant Space Heating
A100: * | B100: RSHDRDBS05 | C100: Distillate Radiant Base.RSH.DST.05 | D100: PJ | E100: RESDSLEA | F100: =Commodities!$D$11 -> RSH | G100: 2010 | H100: 20 | J100: 0.8 | K100: 1 | L100: 0.16 | M100: 0.16 | N100: 0.16 | O100: 0.16 | P100: 0.16 | R100: 0.18 | AH100: 0 | AI100: 0 | AJ100: 0 | AK100: 0 | AL100: 0 | AM100: 0 | AN100: 0 | AO100: 0 | AP100: 0 | AQ100: 0
A101: R2,R3,R4,R5,R6 | B101: RSHDRDV110 | C101: Distillate Radiant Ver1.RSH.DST.10 | D101: PJ | E101: RESDSLEA | F101: =Commodities!$D$11 -> RSH | G101: 2010 | H101: 20 | I101: 11.507811 | J101: 0.85 | K101: 1 | L101: 0.16 | M101: 0.16 | N101: 0.16 | O101: 0.16 | P101: 0.16 | R101: 0.18 | S101: =Resid!V45 -> 80.824588 | T101: =Resid!W45 -> 46.966567 | U101: =Resid!X45 -> 77.540659 | V101: =Resid!Y45 -> 15.201571 | W101: =Resid!Z45 -> 40.609314 | AH101: 0 | AJ101: 0 | AK101: 0 | AL101: 0 | AM101: 0 | AN101: 0 | AO101: 0 | AP101: 0 | AQ101: 0
A102: * | B102: RSHDRDV115 | C102: Distillate Radiant Ver1.RSH.DST.15 | D102: PJ | E102: RESDSLEA | F102: =Commodities!$D$11 -> RSH | G102: 2015 | H102: 20 | I102: 13.705932 | J102: 0.85 | K102: 1 | L102: 0.16 | M102: 0.16 | N102: 0.16 | O102: 0.16 | P102: 0.16 | R102: 0.18 | AH102: 0 | AK102: 0 | AL102: 0 | AM102: 0 | AN102: 0 | AO102: 0 | AP102: 0 | AQ102: 0
A103: R2,R3,R4,R5,R6 | B103: RSHDRDV210 | C103: Distillate Radiant Ver2.RSH.DST.10 | D103: PJ | E103: RESDSLEA | F103: =Commodities!$D$11 -> RSH | G103: 2010 | H103: 20 | I103: 13.705932 | J103: 0.85 | K103: 1 | L103: 0.16 | M103: 0.16 | N103: 0.16 | O103: 0.16 | P103: 0.16 | R103: 0.18 | AH103: 0 | AK103: 0 | AL103: 0 | AM103: 0 | AN103: 0 | AO103: 0 | AP103: 0 | AQ103: 0
A104: R2,R3,R4,R5,R6 | B104: RSHDRDV310 | C104: Distillate Radiant Ver3.RSH.DST.10 | D104: PJ | E104: RESDSLEA | F104: =Commodities!$D$11 -> RSH | G104: 2010 | H104: 20 | I104: 17.391018 | J104: 0.98 | K104: 1 | L104: 0.16 | M104: 0.16 | N104: 0.16 | O104: 0.16 | P104: 0.16 | R104: 0.18 | AH104: 0 | AK104: 0 | AL104: 0 | AM104: 0 | AN104: 0 | AO104: 0 | AP104: 0 | AQ104: 0
A105: *Wood Fired Furnaces
...

Sheet Not used>>

Sheet Commodities
B1: Commodities | D1: _GLOBAL,R0,R1,R2,R3,R4,R5,R6
B7: Region | C7: Csets | D7: CommName | E7: CommDesc | F7: Unit | G7: LimType | H7: CTSLvl | I7: PeakTS | J7: Ctype
B8: *Demands
B9: R2,R3,R4,R5,R6 | C9: DEM | D9: RSC | E9: Residential Cooling | F9: PJ
B10: * | C10: DEM | D10: RFZ | E10: Residential Freezing | F10: PJ
B11: R2,R3,R4,R5,R6 | C11: DEM | D11: RSH | E11: Residential Heating | F11: PJ
B12: R2,R3,R4,R5,R6 | C12: DEM | D12: RLT | E12: Residential Lighting | F12: bn-lum-yr
B13: R2,R3,R4,R5,R6 | C13: DEM | D13: ROE | E13: Residential Other Appliances - ELC | F13: PJ
B14: R2,R3,R4,R5,R6 | C14: DEM | D14: ROG | E14: Residential Other Appliances - NGA | F14: PJ
B15: * | C15: DEM | D15: ROL | E15: Residential Other Appliances - LPG | F15: PJ
B16: * | C16: DEM | D16: RRF | E16: Residential Refrigeration | F16: PJ
B17: R2,R3,R4,R5,R6 | C17: DEM | D17: RWH | E17: Residential Water Heating | F17: PJ
B18: *Energy Carriers
B19: R2,R3,R4,R5,R6 | C19: NRG | D19: RESELC | E19: Electricity to Residential Sector | F19: PJ
B20: R2,R3,R4,R5,R6 | C20: NRG | D20: RESNGAEA | E20: Natural Gas to Residential Sector | F20: PJ
B21: R2,R3,R4,R5,R6 | C21: NRG | D21: RESDSLEA | E21: Diesel to Residential Sector | F21: PJ
B22: *R2,R3,R4,R5,R6 | C22: NRG | D22: RESKEREA | E22: Kerosene to Residential Sector | F22: PJ
B23: *R2,R3,R4,R5,R6 | C23: NRG | D23: RESLPGEA | E23: LPG to Residential Sector | F23: PJ
B24: *R2,R3,R4,R5,R6 | C24: NRG | D24: RESBIOEA | E24: Biomass-wood to Residential Sector after emissions | F24: PJ
B25: *Residential End Use Water Commodities for Demand Pass Through Technologies
B26: R2,R3,R4,R5,R6 | C26: MAT | D26: RBLDLEDMY | E26: Dummy water commodity for low eff buildings | F26: Mt
B27: *R2,R3,R4,R5,R6 | C27: MAT | D27: RBLDMEDMY | E27: Dummy water commodity for medium eff buildings | F27: Mt
B28: R2,R3,R4,R5,R6 | C28: MAT | D28: RBLDHEDMY | E28: Dummy water commodity for high eff buildings | F28: Mt
B29: R2,R3,R4,R5,R6 | C29: MAT | D29: RBROOFDMY | E29: Dummy water commodity for black roofs | F29: Mt
B30: R2,R3,R4,R5,R6 | C30: MAT | D30: RWTROOFDMY | E30: Dummy water commodity for white roofs | F30: Mt
B31: R2,R3,R4,R5,R6 | C31: MAT | D31: RGRF6DMY | E31: Dummy water commodity for green roofs | F31: Mt
B32: R2,R3,R4,R5,R6 | C32: MAT | D32: RGRF12DMY | E32: Dummy water commodity for green roofs | F32: Mt
B33: *Roof/GI Heating & Cooling Commodities
B34: *R2,R3,R4,R5,R6 | C34: NRG | D34: RHCRFBLK | E34: Heating/cooling from black roofs | F34: PJ
B35: *R2,R3,R4,R5,R6 | C35: NRG | D35: RHCRFWT | E35: Heating/cooling from white roofs | F35: PJ
B36: *R2,R3,R4,R5,R6 | C36: NRG | D36: RHCRFG6 | E36: Heating/cooling from 6 inch green roof | F36: PJ
B37: *R2,R3,R4,R5,R6 | C37: NRG | D37: RHCRFG12 | E37: Heating/cooling from 12 inch green roof | F37: PJ
B38: *Demand Commodities for NYC Population
B39: *
B40: R2,R3,R4,R5,R6 | C40: DEM | D40: POPDMRES | E40: Water Energy Demand per Capita | F40: Mt
B41: *R2,R3,R4,R5,R6 | C41: DEM | D41: POPBKRES | E41: Population Brooklyn | F41: Mt
B42: *R2,R3,R4,R5,R6 | C42: DEM | D42: POPBXRES | E42: Population Bronx | F42: Mt
B43: *R2,R3,R4,R5,R6 | C43: DEM | D43: POPMHRES | E43: Population Manhattan | F43: Mt
B44: *R2,R3,R4,R5,R6 | C44: DEM | D44: POPSIRES | E44: Population Staten Island | F44: Mt
B45: *R2,R3,R4,R5,R6 | C45: DEM | D45: POPQNRES | E45: Population Queens | F45: Mt
B46: *
B62: *Energy Carriers
B63: R2,R3,R4,R5,R6 | C63: NRG | D63: ELC | E63: Electricity | F63: PJ
B64: R2,R3,R4,R5,R6 | C64: NRG | D64: RESNGA | E64: Natural Gas to Residential Sector | F64: PJ
B65: R2,R3,R4,R5,R6 | C65: NRG | D65: RESDSL | E65: Distillate-Heating Oil No. 2 to the Residential Sector | F65: PJ
B66: *R2,R3,R4,R5,R6 | C66: NRG | D66: RESCOA | E66: Coal to Residential Sector | F66: PJ
B67: R2,R3,R4,R5,R6 | C67: NRG | D67: SOL | E67: Solar Energy | F67: PJ
B68: R2,R3,R4,R5,R6 | C68: NRG | D68: SOLRES | E68: Solar Energy for Residential Sector | F68: PJ
B69: *INFES Backstop
B70: R2,R3,R4,R5,R6 | C70: NRG | D70: ZZDMY | E70: Dummy commodity for the ZZ-backstop no-INFES processes | F70: PJ
B71: *Emissions
B72: R2,R3,R4,R5,R6 | C72: ENV | D72: CO2 | E72: Carbon dioxide | F72: Mt
B73: R2,R3,R4,R5,R6 | C73: ENV | D73: NOX | E73: Nitrogen oxide | F73: kt
B74: R2,R3,R4,R5,R6 | C74: ENV | D74: PM10 | E74: Particulate matter | F74: kt
B75: R2,R3,R4,R5,R6 | C75: ENV | D75: PM25 | E75: Fine particulate matter | F75: kt
B76: R2,R3,R4,R5,R6 | C76: ENV | D76: VOC | E76: Volatile organic compounds | F76: kt
B77: R2,R3,R4,R5,R6 | C77: ENV | D77: CO | E77: Carbon monoxide | F77: kt
B78: R2,R3,R4,R5,R6 | C78: ENV | D78: CH4 | E78: Methane | F78: kt
B79: R2,R3,R4,R5,R6 | C79: ENV | D79: N2O | E79: N2O | F79: kt
B80: R2,R3,R4,R5,R6 | C80: ENV | D80: BC | E80: Black carbon | F80: kt
B81: R2,R3,R4,R5,R6 | C81: ENV | D81: OC | E81: Organic carbon | F81: kt
B82: R2,R3,R4,R5,R6 | C82: ENV | D82: SO2 | E82: Sulfur dioxide | F82: kt
B83: R2,R3,R4,R5,R6 | C83: ENV | D83: CO2R | E83: CO2 from the residential sector | F83: kt
... B87: R2,R3,R4,R5,R6 | C87: ENV | D87: NOX2CR | E87: Nox species for emission tracking | F87: kt
B88: *
B89: *R2,R3,R4,R5,R6 | C89: NRG | D89: RESCOAEA | E89: COA to RES after Emissions Accounting | F89: PJ
B90: *R2,R3,R4,R5,R6 | C90: NRG | D90: RESBIO | E90: Biomass to Residential | F90: PJ
B91: *R2,R3,R4,R5,R6 | C91: NRG | D91: RESKER | E91: Kerosene and Other Refined Products to the Residential Sector | F91: PJ
B92: *R2,R3,R4,R5,R6 | C92: NRG | D92: RESLPG | E92: LPG to the Residential Sector | F92: PJ
B93: *R2,R3,R4,R5,R6 | C93: MAT | D93: WCRT | E93: Water supply from the Croton System | F93: Mt
B94: *R2,R3,R4,R5,R6 | C94: MAT | D94: WCTDE | E94: Water supply from the Catskill-Delaware System | F94: Mt
B95: *R2,R3,R4,R5,R6 | C95: MAT | D95: WFLT | E95: Water filtered for end use purposes | F95: Mt
B96: *R2,R3,R4,R5,R6 | C96: MAT | D96: WSLT | E96: Saline or greywater supply from NYC Harbor and Rivers | F96: Mt
B97: R2,R3,R4,R5,R6 | C97: MAT | D97: WRAIN | E97: Annual rainfall as an initial supply material | F97: Mt
B98: *R2,R3,R4,R5,R6 | C98: MAT | D98: WROOF | E98: Rain falling on NYC rooftops | F98: Mt
B99: R2,R3,R4,R5,R6 | C99: MAT | D99: WDRK | E99: Treated water used by end use customers | F99: Mt
B100: *R2,R3,R4,R5,R6 | C100: MAT | D100: WSWR | E100: Stormwater flowing to pump stations | F100: Mt
... B106: R2,R3,R4,R5,R6 | C106: MAT | D106: ZZDMYH2O | E106: Dummy water commodity to meet INFES demand | F106: Mt
B107: *
B108: *Industrial End Use Water Demand
B109: *
B110: *R2,R3,R4,R5,R6 | C110: DEM | D110: IWROOFDM | E110: Demand for rainfall on roofs | F110: Mt
B111: *R2,R3,R4,R5,R6 | C111: MAT | D111: IWROOF | E111: Rain on industrial roofs | F111: Mt
B112: *R2,R3,R4,R5,R6 | C112: MAT | D112: IWDRK | E112: Drinking water | F112: Mt
B113: *R2,R3,R4,R5,R6 | C113: MAT | D113: IWDSGTRT | E113: Discharged wastewater | F113: Mt
B114: *R2,R3,R4,R5,R6 | C114: MAT | D114: IWCW | E114: Industrial clothes washing demand | F114: Mt
B115: *R2,R3,R4,R5,R6 | C115: MAT | D115: IWSHR | E115: Industrial shower demand | F115: Mt
B116: *R2,R3,R4,R5,R6 | C116: MAT | D116: IWFCT | E116: Industrial faucet demand | F116: Mt
B117: *R2,R3,R4,R5,R6 | C117: MAT | D117: IWDW | E117: Industrial dishwashing demand | F117: Mt
B118: *R2,R3,R4,R5,R6 | C118: MAT | D118: IWTF | E118: Industrial toilets demand | F118: Mt
B119: *R2,R3,R4,R5,R6 | C119: MAT | D119: IWLK | E119: Industrial leaks/other demand | F119: Mt
B120: *R2,R3,R4,R5,R6 | C120: MAT | D120: IWHVAC | E120: Industrial HVAC water demand | F120: Mt
B121: *R2,R3,R4,R5,R6 | C121: MAT | D121: IWSWR | E121: Treated water flowing from buildings to sewers | F121: Mt
B122: *
B123: *Industrial End Use Water Commodities for Demand Pass Through Technologies
B124: *
B125: *R2,R3,R4,R5,R6 | C125: MAT | D125: ICWLEDMY | E125: Dummy water commodity for clothes washing | F125: Mt
B126: *R2,R3,R4,R5,R6 | C126: MAT | D126: ICWHEDMY | E126: Dummy water commodity for clothes washing | F126: Mt
B127: *R2,R3,R4,R5,R6 | C127: MAT | D127: IDWLEDMY | E127: Dummy water commodity for dish washing | F127: Mt
B128: *R2,R3,R4,R5,R6 | C128: MAT | D128: IDWHEDMY | E128: Dummy water commodity for dish washing | F128: Mt
...

Sheet Technologies
B1: Technologies | D1: _GLOBAL,R0,R1,R2,R3,R4,R5,R6
B7: Region | C7: Sets | D7: TechName | E7: TechDesc | F7: Tact | G7: Tcap | H7: PrimaryCG | I7: Vintage
B8: *Space Heating
B9: *Electric Radiant
B10: =TechData_DMD!A10 -> * | C10: DMD | D10: =TechData_DMD!B10 -> RSHERDBS05 | E10: =TechData_DMD!C10 -> Electric Radiant Base.RSH.ELC.05 | F10: PJ | G10: PJ/a
B11: =TechData_DMD!A11 -> R2,R3,R4,R5,R6 | C11: DMD | D11: =TechData_DMD!B11 -> RSHERDV110 | E11: =TechData_DMD!C11 -> Electric Radiant Ver1.RSH.ELC.10 | F11: PJ | G11: PJ/a
B12: *Electric Resistance Furnaces
B13: =TechData_DMD!A13 -> * | C13: DMD | D13: =TechData_DMD!B13 -> RSHEFRV120 | E13: =TechData_DMD!C13 -> Electric Resistance Furnace Ver1.RSH.ELC.20 | F13: PJ | G13: PJ/a
B14: =TechData_DMD!A14 -> * | C14: DMD | D14: =TechData_DMD!B14 -> RSHEFRV130 | E14: =TechData_DMD!C14 -> Electric Resistance Furnace Ver1.RSH.ELC.30 | F14: PJ | G14: PJ/a
B15: =TechData_DMD!A15 -> * | C15: DMD | D15: =TechData_DMD!B15 -> RSHEFRV230 | E15: =TechData_DMD!C15 -> Electric Resistance Furnace Ver2.RSH.ELC.30 | F15: PJ | G15: PJ/a
B16: =TechData_DMD!A16 -> * | C16: DMD | D16: =TechData_DMD!B16 -> RSHEFRV140 | E16: =TechData_DMD!C16 -> Electric Resistance Furnace Ver1.RSH.ELC.40 | F16: PJ | G16: PJ/a
B17: =TechData_DMD!A17 -> * | C17: DMD | D17: =TechData_DMD!B17 -> RSHEFRV240 | E17: =TechData_DMD!C17 -> Electric Resistance Furnace Ver2.RSH.ELC.40 | F17: PJ | G17: PJ/a
B18: =TechData_DMD!A18 -> * | C18: DMD | D18: =TechData_DMD!B18 -> RSHEFRV250 | E18: =TechData_DMD!C18 -> Electric Resistance Furnace Ver2.RSH.ELC.50 | F18: PJ | G18: PJ/a
B19: =TechData_DMD!A19 -> * | C19: DMD | D19: =TechData_DMD!B19 -> RSHEFRV220 | E19: =TechData_DMD!C19 -> Electric Resistance Furnace Ver2.RSH.ELC.20 | F19: PJ | G19: PJ/a
B20: =TechData_DMD!A20 -> * | C20: DMD | D20: =TechData_DMD!B20 -> RSHEFRV130 | E20: =TechData_DMD!C20 -> Electric Resistance Furnace Ver1.RSH.ELC.30 | F20: PJ | G20: PJ/a
B21: =TechData_DMD!A21 -> * | C21: DMD | D21: =TechData_DMD!B21 -> RSHEFRV230 | E21: =TechData_DMD!C21 -> Electric Resistance Furnace Ver2.RSH.ELC.30 | F21: PJ | G21: PJ/a
B22: =TechData_DMD!A22 -> * | C22: DMD | D22: =TechData_DMD!B22 -> RSHEFRV140 | E22: =TechData_DMD!C22 -> Electric Resistance Furnace Ver1.RSH.ELC.40 | F22: PJ | G22: PJ/a
B23: =TechData_DMD!A23 -> * | C23: DMD | D23: =TechData_DMD!B23 -> RSHEFRV240 | E23: =TechData_DMD!C23 -> Electric Resistance Furnace Ver2.RSH.ELC.40 | F23: PJ | G23: PJ/a
B24: =TechData_DMD!A24 -> * | C24: DMD | D24: =TechData_DMD!B24 -> RSHEFRV150 | E24: =TechData_DMD!C24 -> Electric Resistance Furnace Ver1.RSH.ELC.50 | F24: PJ | G24: PJ/a
B25: =TechData_DMD!A25 -> * | C25: DMD | D25: =TechData_DMD!B25 -> RSHEFRV250 | E25: =TechData_DMD!C25 -> Electric Resistance Furnace Ver2.RSH.ELC.50 | F25: PJ | G25: PJ/a
B26: *Electric Heat Pump
B27: =TechData_DMD!A27 -> * | C27: DMD | D27: =TechData_DMD!B27 -> RSHEHPBS05 | E27: =TechData_DMD!C27 -> Electric Heat Pump Base.RSH.ELC.05 | F27: PJ | G27: PJ/a
B28: =TechData_DMD!A28 -> R2,R3,R4,R5,R6 | C28: DMD | D28: =TechData_DMD!B28 -> RSHEHPV110 | E28: =TechData_DMD!C28 -> Electric Heat Pump Ver1.RSH.ELC.10 | F28: PJ | G28: PJ/a
B29: =TechData_DMD!A29 -> * | C29: DMD | D29: =TechData_DMD!B29 -> RSHEHPV115 | E29: =TechData_DMD!C29 -> Electric Heat Pump Ver1.RSH.ELC.15 | F29: PJ | G29: PJ/a
B30: =TechData_DMD!A30 -> * | C30: DMD | D30: =TechData_DMD!B30 -> RSHEHPV215 | E30: =TechData_DMD!C30 -> Electric Heat Pump Ver2.RSH.ELC.15 | F30: PJ | G30: PJ/a
B31: =TechData_DMD!A31 -> * | C31: DMD | D31: =TechData_DMD!B31 -> RSHEHPV320 | E31: =TechData_DMD!C31 -> Electric Heat Pump Ver3.RSH.ELC.20 | F31: PJ | G31: PJ/a
B32: =TechData_DMD!A32 -> * | C32: DMD | D32: =TechData_DMD!B32 -> RSHEHPV520 | E32: =TechData_DMD!C32 -> Electric Heat Pump Ver5.RSH.ELC.20 | F32: PJ | G32: PJ/a
B33: =TechData_DMD!A33 -> * | C33: DMD | D33: =TechData_DMD!B33 -> RSHEHPV430 | E33: =TechData_DMD!C33 -> Electric Heat Pump Ver4.RSH.ELC.30 | F33: PJ | G33: PJ/a
B34: =TechData_DMD!A34 -> * | C34: DMD | D34: =TechData_DMD!B34 -> RSHEHPV630 | E34: =TechData_DMD!C34 -> Electric Heat Pump Ver6.RSH.ELC.30 | F34: PJ | G34: PJ/a
B35: =TechData_DMD!A35 -> * | C35: DMD | D35: =TechData_DMD!B35 -> RSHEHPV440 | E35: =TechData_DMD!C35 -> Electric Heat Pump Ver4.RSH.ELC.40 | F35: PJ | G35: PJ/a
B36: =TechData_DMD!A36 -> * | C36: DMD | D36: =TechData_DMD!B36 -> RSHEHPV640 | E36: =TechData_DMD!C36 -> Electric Heat Pump Ver6.RSH.ELC.40 | F36: PJ | G36: PJ/a
B37: =TechData_DMD!A37 -> * | C37: DMD | D37: =TechData_DMD!B37 -> RSHEHPV210 | E37: =TechData_DMD!C37 -> Electric Heat Pump Ver2.RSH.ELC.10 | F37: PJ | G37: PJ/a
B38: =TechData_DMD!A38 -> * | C38: DMD | D38: =TechData_DMD!B38 -> RSHEHPV215 | E38: =TechData_DMD!C38 -> Electric Heat Pump Ver2.RSH.ELC.15 | F38: PJ | G38: PJ/a
... B46: =TechData_DMD!A46 -> * | C46: DMD | D46: =TechData_DMD!B46 -> RSHEHPV435 | E46: =TechData_DMD!C46 -> Electric Heat Pump Ver4.RSH.ELC.35 | F46: PJ | G46: PJ/a
B47: *Natural Gas Furnace
B48: =TechData_DMD!A48 -> * | C48: DMD | D48: =TechData_DMD!B48 -> RSHNFRBS05 | E48: =TechData_DMD!C48 -> Natural Gas Furnace Base.RSH.NGA.05 | F48: PJ | G48: PJ/a
B49: =TechData_DMD!A49 -> R2,R3,R4,R5,R6 | C49: DMD | D49: =TechData_DMD!B49 -> RSHNFRV110 | E49: =TechData_DMD!C49 -> Natural Gas Furnace Ver1.RSH.NGA.10 | F49: PJ | G49: PJ/a
B50: =TechData_DMD!A50 -> * | C50: DMD | D50: =TechData_DMD!B50 -> RSHNFRV115 | E50: =TechData_DMD!C50 -> Natural Gas Furnace Ver1.RSH.NGA.15 | F50: PJ | G50: PJ/a
B51: =TechData_DMD!A51 -> * | C51: DMD | D51: =TechData_DMD!B51 -> RSHNFRV215 | E51: =TechData_DMD!C51 -> Natural Gas Furnace Ver2.RSH.NGA.15 | F51: PJ | G51: PJ/a
B52: =TechData_DMD!A52 -> * | C52: DMD | D52: =TechData_DMD!B52 -> RSHNFRV320 | E52: =TechData_DMD!C52 -> Natural Gas Furnace Ver3.RSH.NGA.20 | F52: PJ | G52: PJ/a
B53: =TechData_DMD!A53 -> * | C53: DMD | D53: =TechData_DMD!B53 -> RSHNFRV520 | E53: =TechData_DMD!C53 -> Natural Gas Furnace Ver5.RSH.NGA.20 | F53: PJ | G53: PJ/a
B54: =TechData_DMD!A54 -> * | C54: DMD | D54: =TechData_DMD!B54 -> RSHNFRV430 | E54: =TechData_DMD!C54 -> Natural Gas Furnace Ver4.RSH.NGA.30 | F54: PJ | G54: PJ/a
B55: =TechData_DMD!A55 -> * | C55: DMD | D55: =TechData_DMD!B55 -> RSHNFRV630 | E55: =TechData_DMD!C55 -> Natural Gas Furnace Ver6.RSH.NGA.30 | F55: PJ | G55: PJ/a
B56: =TechData_DMD!A56 -> * | C56: DMD | D56: =TechData_DMD!B56 -> RSHNFRV440 | E56: =TechData_DMD!C56 -> Natural Gas Furnace Ver4.RSH.NGA.40 | F56: PJ | G56: PJ/a
B57: =TechData_DMD!A57 -> * | C57: DMD | D57: =TechData_DMD!B57 -> RSHNFRV640 | E57: =TechData_DMD!C57 -> Natural Gas Furnace Ver6.RSH.NGA.40 | F57: PJ | G57: PJ/a
B58: =TechData_DMD!A58 -> * | C58: DMD | D58: =TechData_DMD!B58 -> RSHNFRV210 | E58: =TechData_DMD!C58 -> Natural Gas Furnace Ver2.RSH.NGA.10 | F58: PJ | G58: PJ/a
B59: =TechData_DMD!A59 -> * | C59: DMD | D59: =TechData_DMD!B59 -> RSHNFRV310 | E59: =TechData_DMD!C59 -> Natural Gas Furnace Ver3.RSH.NGA.10 | F59: PJ | G59: PJ/a
... B69: =TechData_DMD!A69 -> * | C69: DMD | D69: =TechData_DMD!B69 -> RSHNFRV250 | E69: =TechData_DMD!C69 -> Natural Gas Furnace Ver1.RSH.NGA.50 | F69: PJ | G69: PJ/a
B70: *Natural Gas Radiant
B71: =TechData_DMD!A71 -> * | C71: DMD | D71: =TechData_DMD!B71 -> RSHNRDBS05 | E71: =TechData_DMD!C71 -> Natural Gas Radiant Base.RSH.NGA.05 | F71: PJ | G71: PJ/a
B72: =TechData_DMD!A72 -> R2,R3,R4,R5,R6 | C72: DMD | D72: =TechData_DMD!B72 -> RSHNRDV110 | E72: =TechData_DMD!C72 -> Natural Gas Radiant Ver1.RSH.NGA.10 | F72: PJ | G72: PJ/a
B73: =TechData_DMD!A73 -> * | C73: DMD | D73: =TechData_DMD!B73 -> RSHNRDV115 | E73: =TechData_DMD!C73 -> Natural Gas Radiant Ver1.RSH.NGA.15 | F73: PJ | G73: PJ/a
B74: =TechData_DMD!A74 -> * | C74: DMD | D74: =TechData_DMD!B74 -> RSHNRDV120 | E74: =TechData_DMD!C74 -> Natural Gas Radiant Ver1.RSH.NGA.20 | F74: PJ | G74: PJ/a
B75: =TechData_DMD!A75 -> * | C75: DMD | D75: =TechData_DMD!B75 -> RSHNRDV215 | E75: =TechData_DMD!C75 -> Natural Gas Radiant Ver2.RSH.NGA.15 | F75: PJ | G75: PJ/a
B76: =TechData_DMD!A76 -> * | C76: DMD | D76: =TechData_DMD!B76 -> RSHNRDV220 | E76: =TechData_DMD!C76 -> Natural Gas Radiant Ver2.RSH.NGA.20 | F76: PJ | G76: PJ/a
B77: =TechData_DMD!A77 -> * | C77: DMD | D77: =TechData_DMD!B77 -> RSHNRDV315 | E77: =TechData_DMD!C77 -> Natural Gas Radiant Ver3.RSH.NGA.15 | F77: PJ | G77: PJ/a
B78: =TechData_DMD!A78 -> * | C78: DMD | D78: =TechData_DMD!B78 -> RSHNRDV210 | E78: =TechData_DMD!C78 -> Natural Gas Radiant Ver2.RSH.NGA.10 | F78: PJ | G78: PJ/a
B79: =TechData_DMD!A79 -> * | C79: DMD | D79: =TechData_DMD!B79 -> RSHNRDV310 | E79: =TechData_DMD!C79 -> Natural Gas Radiant Ver3.RSH.NGA.10 | F79: PJ | G79: PJ/a
B80: *Kerosene Furnace
B81: =TechData_DMD!A81 -> * | C81: DMD | D81: =TechData_DMD!B81 -> RSHKFRBS05 | E81: =TechData_DMD!C81 -> Kerosene Furnace Base.RSH.KER.05 | F81: PJ | G81: PJ/a
B82: =TechData_DMD!A82 -> * | C82: DMD | D82: =TechData_DMD!B82 -> RSHKFRV110 | E82: =TechData_DMD!C82 -> Kerosene Furnace Ver1.RSH.KER.10 | F82: PJ | G82: PJ/a
B83: =TechData_DMD!A83 -> * | C83: DMD | D83: =TechData_DMD!B83 -> RSHKFRV115 | E83: =TechData_DMD!C83 -> Kerosene Furnace Ver1.RSH.KER.15 | F83: PJ | G83: PJ/a
B84: =TechData_DMD!A84 -> * | C84: DMD | D84: =TechData_DMD!B84 -> RSHKFRV210 | E84: =TechData_DMD!C84 -> Kerosene Furnace Ver2.RSH.KER.10 | F84: PJ | G84: PJ/a
B85: =TechData_DMD!A85 -> * | C85: DMD | D85: =TechData_DMD!B85 -> RSHKFRV310 | E85: =TechData_DMD!C85 -> Kerosene Furnace Ver3.RSH.KER.10 | F85: PJ | G85: PJ/a
B86: *Liquid Gas Furnace
B87: =TechData_DMD!A87 -> * | C87: DMD | D87: =TechData_DMD!B87 -> RSHLFRBS05 | E87: =TechData_DMD!C87 -> Liquid Gas Furnace Base.RSH.LPG.05 | F87: PJ | G87: PJ/a
B88: =TechData_DMD!A88 -> * | C88: DMD | D88: =TechData_DMD!B88 -> RSHLFRV110 | E88: =TechData_DMD!C88 -> Liquid Gas Furnace Ver1.RSH.LPG.10 | F88: PJ | G88: PJ/a
B89: =TechData_DMD!A89 -> * | C89: DMD | D89: =TechData_DMD!B89 -> RSHLFRV210 | E89: =TechData_DMD!C89 -> Liquid Gas Furnace Ver2.RSH.LPG.10 | F89: PJ | G89: PJ/a
B90: =TechData_DMD!A90 -> * | C90: DMD | D90: =TechData_DMD!B90 -> RSHLFRV310 | E90: =TechData_DMD!C90 -> Liquid Gas Furnace Ver3.RSH.LPG.10 | F90: PJ | G90: PJ/a
B91: =TechData_DMD!A91 -> * | C91: DMD | D91: =TechData_DMD!B91 -> RSHLFRV410 | E91: =TechData_DMD!C91 -> Liquid Gas Furnace Ver4.RSH.LPG.10 | F91: PJ | G91: PJ/a
B92: =TechData_DMD!A92 -> * | C92: DMD | D92: =TechData_DMD!B92 -> RSHLFRV510 | E92: =TechData_DMD!C92 -> Liquid Gas Furnace Ver5.RSH.LPG.10 | F92: PJ | G92: PJ/a
B93: *Distillate Furnace
B94: =TechData_DMD!A94 -> * | C94: DMD | D94: =TechData_DMD!B94 -> RSHDFRBS05 | E94: =TechData_DMD!C94 -> Distillate Furnace Base.RSH.DST.05 | F94: PJ | G94: PJ/a
B95: =TechData_DMD!A95 -> R2,R3,R4,R5,R6 | C95: DMD | D95: =TechData_DMD!B95 -> RSHDFRV110 | E95: =TechData_DMD!C95 -> Distillate Furnace Ver1.RSH.DST.10 | F95: PJ | G95: PJ/a
B96: =TechData_DMD!A96 -> * | C96: DMD | D96: =TechData_DMD!B96 -> RSHDFRV115 | E96: =TechData_DMD!C96 -> Distillate Furnace Ver1.RSH.DST.15 | F96: PJ | G96: PJ/a
B97: =TechData_DMD!A97 -> R2,R3,R4,R5,R6 | C97: DMD | D97: =TechData_DMD!B97 -> RSHDFRV210 | E97: =TechData_DMD!C97 -> Distillate Furnace Ver2.RSH.DST.10 | F97: PJ | G97: PJ/a
B98: =TechData_DMD!A98 -> R2,R3,R4,R5,R6 | C98: DMD | D98: =TechData_DMD!B98 -> RSHDFRV310 | E98: =TechData_DMD!C98 -> Distillate Furnace Ver3.RSH.DST.10 | F98: PJ | G98: PJ/a
B99: *Distillate Radiant
B100: =TechData_DMD!A100 -> * | C100: DMD | D100: =TechData_DMD!B100 -> RSHDRDBS05 | E100: =TechData_DMD!C100 -> Distillate Radiant Base.RSH.DST.05 | F100: PJ | G100: PJ/a
B101: =TechData_DMD!A101 -> R2,R3,R4,R5,R6 | C101: DMD | D101: =TechData_DMD!B101 -> RSHDRDV110 | E101: =TechData_DMD!C101 -> Distillate Radiant Ver1.RSH.DST.10 | F101: PJ | G101: PJ/a
B102: =TechData_DMD!A102 -> * | C102: DMD | D102: =TechData_DMD!B102 -> RSHDRDV115 | E102: =TechData_DMD!C102 -> Distillate Radiant Ver1.RSH.DST.15 | F102: PJ | G102: PJ/a
B103: =TechData_DMD!A103 -> R2,R3,R4,R5,R6 | C103: DMD | D103: =TechData_DMD!B103 -> RSHDRDV210 | E103: =TechData_DMD!C103 -> Distillate Radiant Ver2.RSH.DST.10 | F103: PJ | G103: PJ/a
B104: =TechData_DMD!A104 -> R2,R3,R4,R5,R6 | C104: DMD | D104: =TechData_DMD!B104 -> RSHDRDV310 | E104: =TechData_DMD!C104 -> Distillate Radiant Ver3.RSH.DST.10 | F104: PJ | G104: PJ/a
B105: *Wood
B106: =TechData_DMD!A106 -> * | C106: DMD | D106: =TechData_DMD!B106 -> RSHWDHBS05 | E106: =TechData_DMD!C106 -> Wood Heat Base.RSH.BWD.05 | F106: PJ | G106: PJ/a
B107: =TechData_DMD!A107 -> * | C107: DMD | D107: =TechData_DMD!B107 -> RSHWDHV110 | E107: =TechData_DMD!C107 -> Wood Heat Ver1.RSH.BWD.10 | F107: PJ | G107: PJ/a
B108: *Geothermal Heat Pump
B109: =TechData_DMD!A109 -> * | C109: DMD | D109: =TechData_DMD!B109 -> RSHGHPBS05 | E109: =TechData_DMD!C109 -> Geothermal Heat Pump Base.RSH.ELC.05 | F109: PJ | G109: PJ/a
B110: =TechData_DMD!A110 -> * | C110: DMD | D110: =TechData_DMD!B110 -> RSHGHPV110 | E110: =TechData_DMD!C110 -> Geothermal Heat Pump Ver1.RSH.ELC.10 | F110: PJ | G110: PJ/a
B111: =TechData_DMD!A111 -> * | C111: DMD | D111: =TechData_DMD!B111 -> RSHGHPV210 | E111: =TechData_DMD!C111 -> Geothermal Heat Pump Ver2.RSH.ELC.10 | F111: PJ | G111: PJ/a
B112: =TechData_DMD!A112 -> * | C112: DMD | D112: =TechData_DMD!B112 -> RSHGHPV220 | E112: =TechData_DMD!C112 -> Geothermal Heat Pump Ver2.RSH.ELC.20 | F112: PJ | G112: PJ/a
B113: *Natural Gas Heat Pump
B114: =TechData_DMD!A114 -> * | C114: DMD | D114: =TechData_DMD!B114 -> RSHNHPBS05 | E114: =TechData_DMD!C114 -> Natural Gas Heat Pump Base.RSH.NGA.05 | F114: PJ | G114: PJ/a
B115: =TechData_DMD!A115 -> R2,R3,R4,R5,R6 | C115: DMD | D115: =TechData_DMD!B115 -> RSHNHPV110 | E115: =TechData_DMD!C115 -> Natural Gas Heat Pump Ver1.RSH.NGA.10 | F115: PJ | G115: PJ/a
B116: =TechData_DMD!A116 -> * | C116: DMD | D116: =TechData_DMD!B116 -> RSHNHPV120 | E116: =TechData_DMD!C116 -> Natural Gas Heat Pump Ver1.RSH.NGA.20 | F116: PJ | G116: PJ/a
B117: =TechData_DMD!A117 -> * | C117: DMD | D117: =TechData_DMD!B117 -> RSHNHPV220 | E117: =TechData_DMD!C117 -> Natural Gas Heat Pump Ver2.RSH.NGA.20 | F117: PJ | G117: PJ/a
B118: =TechData_DMD!A118 -> * | C118: DMD | D118: =TechData_DMD!B118 -> RSHNHPV130 | E118: =TechData_DMD!C118 -> Natural Gas Heat Pump Ver1.RSH.NGA.30 | F118: PJ | G118: PJ/a
B119: =TechData_DMD!A119 -> * | C119: DMD | D119: =TechData_DMD!B119 -> RSHNHPV230 | E119: =TechData_DMD!C119 -> Natural Gas Heat Pump Ver2.RSH.NGA.30 | F119: PJ | G119: PJ/a
B120: =TechData_DMD!A120 -> * | C120: DMD | D120: =TechData_DMD!B120 -> RSHNHPV140 | E120: =TechData_DMD!C120 -> Natural Gas Heat Pump Ver1.RSH.NGA.40 | F120: PJ | G120: PJ/a
B121: =TechData_DMD!A121 -> * | C121: DMD | D121: =TechData_DMD!B121 -> RSHNHPV240 | E121: =TechData_DMD!C121 -> Natural Gas Heat Pump Ver2.RSH.NGA.40 | F121: PJ | G121: PJ/a
...

Sheet Retrofit
B2: Measure No. | C2: Name | D2: Energy Demand Reduction (% kBtu/sqft) | E2: Cost per Sqft | F2: % of Residential Area Eligible | G2: Cost Calculation | H2: Restriction Calculation
B3: 1 | C3: Insulation – walls | D3: 0.1 | E3: 65.19 | F3: 0.267 | G3: $41.75 per square foot wall area; wall area calculated as average perimeter area times height in eligible single-family homes | H3: Only single-family homes built before 2005
B4: 2 | C4: Ventilation overhaul | D4: 0.03 | E4: 1 | F4: 0.482 | G4: $1 per sqft | H4: Only homes built after 1945
B5: 3 | C5: Smart thermostats | D5: 0.08 | E5: 0.52 | F5: 0.948 | G5: $500 / apartment (average size 962 sqft) | H5: All homes except steam-heated
B6: 4 | C6: Insulation – roof | D6: 0.05 | E6: 1.5 | F6: 0.897 | G6: $13 / roof area (90% of footprint); foot print is 0.129 of total area | H6: Only homes built before 2005
B7: 5 | C7: Window replacement | D7: 0.08 | E7: 5 | F7: 0.897 | G7: Cost given | H7: Only homes built before 2005
C10: 2005 Building eff (Btu / sqft )
C11: Brooklyn | D11: Bronx | E11: Manhattan | F11: Queens | G11: Staten Island | H11: NYC | K11: 2005 | L11: 2010 | M11: 2015 | N11: 2020 | O11: 2025 | P11: 2030 | Q11: 2035 | R11: 2040 | S11: 2045 | T11: 2050 | U11: 2055
C12: 51602.374 | D12: 55661.045 | E12: 62470.873 | F12: 32617.14 | G12: 56174.924 | H12: 50587.643 | J12: % of new build | K12: 0 | L12: 0.028275072 | M12: 0.055803665 | N12: 0.080498063 | O12: 0.09788161 | P12: 0.11446455 | Q12: 0.13106521 | R12: 0.14813324 | S12: 0.16193016 | T12: 0.1770404 | U12: 0.1916742
C14: Cost per Btu (M $ 2010 / PJa)
C15: Brooklyn | D15: Bronx | E15: Manhattan | F15: Queens | G15: Staten Island | H15: NYC | J15: Max penetration (% Btu) | K15: 2005 | L15: 2010 | M15: 2015 | N15: 2020 | O15: 2025 | P15: 2030 | Q15: 2035 | R15: 2040 | S15: 2045 | T15: 2050 | U15: 2055
B16: Smart thermostats | C16: =$E5/C$12/$U$28/$C$31*10^-6 -> 7.0017166 | D16: =$E5/D$12/$U$28/$C$31*10^-6 -> 6.4911681 | E16: =$E5/E$12/$U$28/$C$31*10^-6 -> 5.7835785 | F16: =$E5/F$12/$U$28/$C$31*10^-6 -> 11.077158 | G16: =$E5/G$12/$U$28/$C$31*10^-6 -> 6.431788 | H16: =$E5/H$12/$U$28/$C$31*10^-6 -> 7.1421631 | J16: Smart thermostats | K16: =$D$5*$F$5*(1-K$12) -> 0.07584 | L16: =$D$5*$F$5*(1-L$12) -> 0.073695619 | M16: =$D$5*$F$5*(1-M$12) -> 0.07160785 | N16: =$D$5*$F$5*(1-N$12) -> 0.069735027 | O16: =$D$5*$F$5*(1-O$12) -> 0.068416659 | P16: =$D$5*$F$5*(1-P$12) -> 0.067159008 | Q16: =$D$5*$F$5*(1-Q$12) -> 0.065900015 | R16: =$D$5*$F$5*(1-R$12) -> 0.064605575 | ... U16: =$D$5*$F$5*(1-U$12) -> 0.061303428
B17: Ventilation overhaul | C17: =$E4/C$12/$U$28/$C$31*10^-6 -> 13.46484 | D17: =$E4/D$12/$U$28/$C$31*10^-6 -> 12.483016 | E17: =$E4/E$12/$U$28/$C$31*10^-6 -> 11.122266 | F17: =$E4/F$12/$U$28/$C$31*10^-6 -> 21.302226 | G17: =$E4/G$12/$U$28/$C$31*10^-6 -> 12.368823 | H17: =$E4/H$12/$U$28/$C$31*10^-6 -> 13.734929 | J17: Ventilation overhaul | K17: =$D$4*$F$4*(1-K$12) -> 0.01446 | L17: =$D$4*$F$4*(1-L$12) -> 0.014051142 | M17: =$D$4*$F$4*(1-M$12) -> 0.013653079 | N17: =$D$4*$F$4*(1-N$12) -> 0.013295998 | O17: =$D$4*$F$4*(1-O$12) -> 0.013044632 | P17: =$D$4*$F$4*(1-P$12) -> 0.012804843 | Q17: =$D$4*$F$4*(1-Q$12) -> 0.012564797 | R17: =$D$4*$F$4*(1-R$12) -> 0.012317993 | ... U17: =$D$4*$F$4*(1-U$12) -> 0.011688391
B18: Insulation – roof | C18: =$E6/C$12/$U$28/$C$31*10^-6 -> 20.197259 | D18: =$E6/D$12/$U$28/$C$31*10^-6 -> 18.724523 | E18: =$E6/E$12/$U$28/$C$31*10^-6 -> 16.6834 | F18: =$E6/F$12/$U$28/$C$31*10^-6 -> 31.953339 | G18: =$E6/G$12/$U$28/$C$31*10^-6 -> 18.553234 | H18: =$E6/H$12/$U$28/$C$31*10^-6 -> 20.602393 | J18: Insulation – roof | K18: =$D$3*$F$3*(1-K$12) -> 0.0267 | L18: =$D$3*$F$3*(1-L$12) -> 0.025945056 | M18: =$D$3*$F$3*(1-M$12) -> 0.025210042 | N18: =$D$3*$F$3*(1-N$12) -> 0.024550702 | O18: =$D$3*$F$3*(1-O$12) -> 0.024086561 | P18: =$D$3*$F$3*(1-P$12) -> 0.023643796 | Q18: =$D$3*$F$3*(1-Q$12) -> 0.023200559 | R18: =$D$3*$F$3*(1-R$12) -> 0.022744842 | ... U18: =$D$3*$F$3*(1-U$12) -> 0.021582299
B19: Window replacement | C19: =$E7/C$12/$U$28/$C$31*10^-6 -> 67.324198 | D19: =$E7/D$12/$U$28/$C$31*10^-6 -> 62.415078 | E19: =$E7/E$12/$U$28/$C$31*10^-6 -> 55.611332 | F19: =$E7/F$12/$U$28/$C$31*10^-6 -> 106.51113 | G19: =$E7/G$12/$U$28/$C$31*10^-6 -> 61.844115 | H19: =$E7/H$12/$U$28/$C$31*10^-6 -> 68.674645 | J19: Window replacement | K19: =$D$7*$F$7*(1-K$12) -> 0.07176 | L19: =$D$7*$F$7*(1-L$12) -> 0.069730981 | M19: =$D$7*$F$7*(1-M$12) -> 0.067755529 | N19: =$D$7*$F$7*(1-N$12) -> 0.065983459 | O19: =$D$7*$F$7*(1-O$12) -> 0.064736016 | P19: =$D$7*$F$7*(1-P$12) -> 0.063546024 | Q19: =$D$7*$F$7*(1-Q$12) -> 0.062354761 | R19: =$D$7*$F$7*(1-R$12) -> 0.061129958 | ... U19: =$D$7*$F$7*(1-U$12) -> 0.058005459
B20: Insulation – walls | C20: =$E3/C$12/$U$28/$C$31*10^-6 -> 877.77289 | D20: =$E3/D$12/$U$28/$C$31*10^-6 -> 813.76779 | E20: =$E3/E$12/$U$28/$C$31*10^-6 -> 725.06054 | F20: =$E3/F$12/$U$28/$C$31*10^-6 -> 1388.6921 | G20: =$E3/G$12/$U$28/$C$31*10^-6 -> 806.32357 | H20: =$E3/H$12/$U$28/$C$31*10^-6 -> 895.38002 | J20: Insulation – walls | K20: =$D$6*$F$6*(1-K$12) -> 0.04485 | L20: =$D$6*$F$6*(1-L$12) -> 0.043581863 | M20: =$D$6*$F$6*(1-M$12) -> 0.042347206 | N20: =$D$6*$F$6*(1-N$12) -> 0.041239662 | O20: =$D$6*$F$6*(1-O$12) -> 0.04046001 | P20: =$D$6*$F$6*(1-P$12) -> 0.039716265 | Q20: =$D$6*$F$6*(1-Q$12) -> 0.038971725 | R20: =$D$6*$F$6*(1-R$12) -> 0.038206224 | ... U20: =$D$6*$F$6*(1-U$12) -> 0.036253412
B25: https://fred.stlouisfed.org/series/FPCPITOTLZGUSA
C26: 2005 | D26: 2006 | E26: 2007 | F26: 2008 | G26: 2009 | H26: 2010 | I26: 2011 | J26: 2012 | K26: 2013 | L26: 2014 | M26: 2015 | N26: 2016 | O26: 2017 | P26: 2018 | Q26: 2019 | R26: 2020 | S26: 2021 | T26: 2022 | U26: 2023
B27: Inflation | C27: 0.033927468 | D27: 0.032259441 | E27: 0.028526725 | F27: 0.038391003 | G27: -0.0035554627 | H27: 0.016400434 | I27: 0.031568416 | J27: 0.020693373 | K27: 0.014648327 | L27: 0.01622223 | M27: 0.0011862714 | N27: 0.012615832 | O27: 0.0213011 | P27: 0.024425833 | Q27: 0.018122101 | R27: 0.012335844 | S27: 0.046978589 | T27: 0.080027998 | U27: 0
B28: Cumulated ref 2010 | C28: 1.1358175 | D28: 1.0985466 | E28: 1.0642156 | F28: 1.034699 | G28: 0.99644454 | H28: 1 | I28: 1.0164004 | J28: 1.0484866 | K28: 1.0701833 | L28: 1.0858597 | M28: 1.1034748 | N28: 1.1047838 | O28: 1.1187216 | P28: 1.1425516 | Q28: 1.1704593 | R28: 1.1916705 | S28: 1.2063708 | T28: 1.2630444 | U28: 1.3641233
B31: Btu to PJ | C31: 1.055056e-12

Sheet Resid
B1: TechName | C1: TechDesc | D1: Units | E1: CommIN | F1: CommOUT | G1: START | H1: LIFE | I1: INVCOST | J1: EFF | K1: MA(ENT) | L1: OUT(DM) | M1: CF | N1: FIXOM | O1: DISCRATE | P1: RESID EPAUS9r 2010 | Q1: RESID EPAUS9r (%) | R1: EFF | T1: Resid Total | U1: Demand Total | V1: RESID | AA1: DEMAND
A2: *Space Heating | V2: BR | W2: BX | X2: MN | Y2: SI | Z2: QN | AA2: BR | AB2: BX | AC2: MN | AD2: SI | AE2: QN
U3: =SUM(U5:U52) -> 146.11398 | AA3: =ResDemand!E19 -> 45.222793 | AB3: =ResDemand!E20 -> 26.278629 | AC3: =ResDemand!E21 -> 43.385376 | AD3: =ResDemand!E22 -> 8.5055488 | AE3: =ResDemand!E23 -> 22.721632 | AF3: =SUM(AA3:AE3)-U3 -> 0
A4: ELC | M4: =M6 -> 0.16 | P4: =SUM(P5:P21) -> 165.6963 | Q4: =A4 -> ELC | T4: ='2010 Fuel Share'!C72 -> 3.012083 | AA4: =SUM(AA6:AA52) -> 45.222793 | AB4: =SUM(AB6:AB52) -> 26.278629 | AC4: =SUM(AC6:AC52) -> 43.385376 | AD4: =SUM(AD6:AD52) -> 8.5055488 | AE4: =SUM(AE6:AE52) -> 22.721632
A5: *Electric Radiant
A6: R1,R2,R3,R4,R5,R6 | B6: RSHERDBS05 | C6: Electric Radiant Base.RSH.ELC.05 | D6: PJ | E6: RESELC | F6: RSH | G6: 2005 | H6: 20 | J6: 1 | K6: 1 | L6: 1 | M6: 0.16 | O6: 0.18 | R6: =J6 -> 1
A7: R1,R2,R3,R4,R5,R6 | B7: RSHERDV110 | C7: Electric Radiant Ver1.RSH.ELC.10 | D7: PJ | E7: RESELC | F7: RSH | G7: 2010 | H7: 20 | I7: 3.7369871 | J7: 1 | K7: 1 | L7: 1 | M7: 0.16 | O7: 0.18 | P7: ='RECS RESID'!W9 -> 135.05004 | Q7: =P7/$P$4 -> 0.81504563 | R7: =J7 -> 1 | T7: =T4*$Q$7*$R$7/$M$7 -> 15.343657 | U7: =T7*$M$7 -> 2.4549851 | V7: =$T7*AA$3/$U$3 -> 4.748916 | W7: =$T7*AB$3/$U$3 -> 2.7595598 | X7: =$T7*AC$3/$U$3 -> 4.555966 | Y7: =$T7*AD$3/$U$3 -> 0.89318094 | Z7: =$T7*AE$3/$U$3 -> 2.386034 | AA7: =$U7*AA3/$U$3 -> 0.75982656 | AB7: =$U7*AB3/$U$3 -> 0.44152956 | AC7: =$U7*AC3/$U$3 -> 0.72895455 | AD7: =$U7*AD3/$U$3 -> 0.14290895 | AE7: =$U7*AE3/$U$3 -> 0.38176545
A8: *Electric Heat Pump
A9: R1,R2,R3,R4,R5,R6 | B9: RSHEHPBS05 | C9: Electric Heat Pump Base.RSH.ELC.05 | D9: PJ | E9: RESELC | F9: RSH | G9: 2005 | H9: 15 | J9: 2.2657 | K9: 1 | L9: 1 | M9: 0.16 | O9: 0.18 | R9: =J9 -> 2.2657
A10: R1,R2,R3,R4,R5,R6 | B10: RSHEHPV110 | C10: Electric Heat Pump Ver1.RSH.ELC.10 | D10: PJ | E10: RESELC | F10: RSH | G10: 2010 | H10: 15 | I10: 6.5561178 | J10: 2.26 | K10: 1 | L10: 1 | M10: 0.16 | O10: 0.18 | P10: ='RECS RESID'!W10 -> 30.646254 | Q10: =P10/$P$4 -> 0.18495437 | R10: =J10 -> 2.26 | T10: =T4*$Q$10*$R$10/$M$10 -> 7.8690079 | U10: =T10*$M$10 -> 1.2590413 | V10: =$T10*AA$3/$U$3 -> 2.4354858 | W10: =$T10*AB$3/$U$3 -> 1.4152427 | X10: =$T10*AC$3/$U$3 -> 2.3365312 | Y10: =$T10*AD$3/$U$3 -> 0.45806863 | Z10: =$T10*AE$3/$U$3 -> 1.2236797 | AA10: =$U10*AA$3/$U$3 -> 0.38967772 | AB10: =$U10*AB3/$U$3 -> 0.22643882 | AC10: =$U10*AC3/$U$3 -> 0.37384499 | AD10: =$U10*AD3/$U$3 -> 0.073290981 | AE10: =$U10*AE3/$U$3 -> 0.19578875
A11: R1,R2,R3,R4,R5,R6 | B11: RSHEHPV115 | C11: Electric Heat Pump Ver1.RSH.ELC.15 | D11: PJ | E11: RESELC | F11: RSH | G11: 2015 | H11: 15 | I11: 6.7609965 | J11: 2.4 | K11: 1 | L11: 1 | M11: 0.16 | O11: 0.18 | R11: =J11 -> 2.4
A12: R1,R2,R3,R4,R5,R6 | B12: RSHEHPV210 | C12: Electric Heat Pump Ver2.RSH.ELC.10 | D12: PJ | E12: RESELC | F12: RSH | G12: 2010 | H12: 15 | I12: 8.8097833 | J12: 2.4 | K12: 1 | L12: 1 | M12: 0.16 | O12: 0.18 | R12: =J12 -> 2.4
A13: R1,R2,R3,R4,R5,R6 | B13: RSHEHPV215 | C13: Electric Heat Pump Ver2.RSH.ELC.15 | D13: PJ | E13: RESELC | F13: RSH | G13: 2015 | H13: 15 | I13: 9.3561264 | J13: 2.58 | K13: 1 | L13: 1 | M13: 0.16 | O13: 0.18 | R13: =J13 -> 2.58
A14: R1,R2,R3,R4,R5,R6 | B14: RSHEHPV310 | C14: Electric Heat Pump Ver3.RSH.ELC.10 | D14: PJ | E14: RESELC | F14: RSH | G14: 2010 | H14: 15 | I14: 9.7658838 | J14: 2.49 | K14: 1 | L14: 1 | M14: 0.16 | O14: 0.18 | R14: =J14 -> 2.49
A15: R1,R2,R3,R4,R5,R6 | B15: RSHEHPV315 | C15: Electric Heat Pump Ver3.RSH.ELC.15 | D15: PJ | E15: RESELC | F15: RSH | G15: 2015 | H15: 15 | I15: 9.7658838 | J15: 2.49 | K15: 1 | L15: 1 | M15: 0.16 | O15: 0.18 | R15: =J15 -> 2.49
A16: R1,R2,R3,R4,R5,R6 | B16: RSHEHPV320 | C16: Electric Heat Pump Ver3.RSH.ELC.20 | D16: PJ | E16: RESELC | F16: RSH | G16: 2020 | H16: 15 | I16: 10.243934 | J16: 2.78 | K16: 1 | L16: 1 | M16: 0.16 | O16: 0.18 | R16: =J16 -> 2.78
A17: R1,R2,R3,R4,R5,R6 | B17: RSHEHPV330 | C17: Electric Heat Pump Ver3.RSH.ELC.30 | D17: PJ | E17: RESELC | F17: RSH | G17: 2030 | H17: 15 | I17: 10.243934 | J17: 2.8 | K17: 1 | L17: 1 | M17: 0.16 | O17: 0.18 | R17: =J17 -> 2.8
A18: R1,R2,R3,R4,R5,R6 | B18: RSHEHPV410 | C18: Electric Heat Pump Ver4.RSH.ELC.10 | D18: PJ | E18: RESELC | F18: RSH | G18: 2010 | H18: 15 | I18: 10.926863 | J18: 3.14 | K18: 1 | L18: 1 | M18: 0.16 | O18: 0.18 | R18: =J18 -> 3.14
A19: R1,R2,R3,R4,R5,R6 | B19: RSHEHPV420 | C19: Electric Heat Pump Ver4.RSH.ELC.20 | D19: PJ | E19: RESELC | F19: RSH | G19: 2020 | H19: 15 | I19: 11.200035 | J19: 3.17 | K19: 1 | L19: 1 | M19: 0.16 | O19: 0.18 | R19: =J19 -> 3.17
A20: R1,R2,R3,R4,R5,R6 | B20: RSHEHPV430 | C20: Electric Heat Pump Ver4.RSH.ELC.30 | D20: PJ | E20: RESELC | F20: RSH | G20: 2030 | H20: 15 | I20: 11.268327 | J20: 3.22 | K20: 1 | L20: 1 | M20: 0.16 | O20: 0.18 | R20: =J20 -> 3.22
A21: R1,R2,R3,R4,R5,R6 | B21: RSHEHPV435 | C21: Electric Heat Pump Ver4.RSH.ELC.35 | D21: PJ | E21: RESELC | F21: RSH | G21: 2035 | H21: 15 | I21: 11.268327 | J21: 3.22 | K21: 1 | L21: 1 | M21: 0.16 | O21: 0.18 | R21: =J21 -> 3.22
A22: NGA | M22: =M24 -> 0.16 | P22: =SUM(P23:P35) -> 2796.2102 | Q22: NGA | T22: ='2010 Fuel Share'!C73 -> 104.43662 | AF22: =(U25+U32+U39+U45)/U3 -> 0.97458131
A23: *Natural Gas Furnace
A24: R1,R2,R3,R4,R5,R6 | B24: RSHNFRBS05 | C24: Natural Gas Furnace Base.RSH.NGA.05 | D24: PJ | E24: RESNGAEA | F24: RSH | G24: 2005 | H24: 15 | J24: 0.81440002 | K24: 1 | L24: 1 | M24: 0.16 | O24: 0.18 | R24: =J24 -> 0.81440002
A25: R1,R2,R3,R4,R5,R6 | B25: RSHNFRV110 | C25: Natural Gas Furnace Ver1.RSH.NGA.10 | D25: PJ | E25: RESNGAEA | F25: RSH | G25: 2010 | H25: 15 | I25: 4.9170883 | J25: 0.78 | K25: 1 | L25: 1 | M25: 0.16 | O25: 0.18 | P25: ='RECS RESID'!W11 -> 1778.6707 | Q25: =P25/$P$22 -> 0.63610051 | R25: =J25 -> 0.78 | T25: =T22*$Q$25*$R$25/$M$25 -> 323.85693 | U25: =T22*$Q$25*$R$25 -> 51.817108 | V25: =$T25*AA$3/$U$3 -> 100.23486 | W25: =$T25*AB$3/$U$3 -> 58.245734 | X25: =$T25*AC$3/$U$3 -> 96.162288 | Y25: =$T25*AD$3/$U$3 -> 18.852275 | Z25: =$T25*AE$3/$U$3 -> 50.361766 | AA25: =$U25*AA$3/$U$3 -> 16.037578 | AB25: =$U25*AB$3/$U$3 -> 9.3193174 | AC25: =$U25*AC$3/$U$3 -> 15.385966 | AD25: =$U25*AD$3/$U$3 -> 3.016364 | AE25: =$U25*AE$3/$U$3 -> 8.0578826
A26: R1,R2,R3,R4,R5,R6 | B26: RSHNFRV210 | C26: Natural Gas Furnace Ver2.RSH.NGA.10 | D26: PJ | E26: RESNGAEA | F26: RSH | G26: 2010 | H26: 15 | I26: 4.9170883 | J26: 0.8 | K26: 1 | L26: 1 | M26: 0.16 | O26: 0.18 | R26: =J26 -> 0.8
A27: R1,R2,R3,R4,R5,R6 | B27: RSHNFRV310 | C27: Natural Gas Furnace Ver3.RSH.NGA.10 | D27: PJ | E27: RESNGAEA | F27: RSH | G27: 2010 | H27: 20 | I27: 5.4087972 | J27: 0.9 | K27: 1 | L27: 1 | M27: 0.16 | O27: 0.18 | R27: =J27 -> 0.9
A28: R1,R2,R3,R4,R5,R6 | B28: RSHNFRV410 | C28: Natural Gas Furnace Ver4.RSH.NGA.10 | D28: PJ | E28: RESNGAEA | F28: RSH | G28: 2010 | H28: 20 | I28: 6.2938731 | J28: 0.95 | K28: 1 | L28: 1 | M28: 0.16 | O28: 0.18 | R28: =J28 -> 0.95
A29: R1,R2,R3,R4,R5,R6 | B29: RSHNFRV510 | C29: Natural Gas Furnace Ver5.RSH.NGA.10 | D29: PJ | E29: RESNGAEA | F29: RSH | G29: 2010 | H29: 20 | I29: 7.3756325 | J29: 0.98 | K29: 1 | L29: 1 | M29: 0.16 | O29: 0.18 | R29: =J29 -> 0.98
A30: *Natural Gas Radiant
A31: R1,R2,R3,R4,R5,R6 | B31: RSHNRDBS05 | C31: Natural Gas Radiant Base.RSH.NGA.05 | D31: PJ | E31: RESNGAEA | F31: RSH | G31: 2005 | H31: 20 | J31: 0.8 | K31: 1 | L31: 1 | M31: 0.16 | O31: 0.18 | R31: =J31 -> 0.8
A32: R1,R2,R3,R4,R5,R6 | B32: RSHNRDV110 | C32: Natural Gas Radiant Ver1.RSH.NGA.10 | D32: PJ | E32: RESNGAEA | F32: RSH | G32: 2010 | H32: 20 | I32: 6.4905566 | J32: 0.8 | K32: 1 | L32: 1 | M32: 0.16 | O32: 0.18 | P32: ='RECS RESID'!W12 -> 1017.5394 | Q32: =P32/$P$22 -> 0.36389949 | R32: =J32 -> 0.8 | T32: =T22*$Q$32*$R$32/$M$32 -> 190.02217 | U32: =T22*$Q$32*$R$32 -> 30.403547 | V32: =$T32*AA$3/$U$3 -> 58.812533 | W32: =$T32*AB$3/$U$3 -> 34.175525 | X32: =$T32*AC$3/$U$3 -> 56.42296 | Y32: =$T32*AD$3/$U$3 -> 11.061521 | Z32: =$T32*AE$3/$U$3 -> 29.549629 | AA32: =$U32*AA$3/$U$3 -> 9.4100053 | AB32: =$U32*AB$3/$U$3 -> 5.4680841 | AC32: =$U32*AC$3/$U$3 -> 9.0276737 | AD32: =$U32*AD$3/$U$3 -> 1.7698434 | AE32: =$U32*AE$3/$U$3 -> 4.7279406
A33: R1,R2,R3,R4,R5,R6 | B33: RSHNRDV115 | C33: Natural Gas Radiant Ver1.RSH.NGA.15 | D33: PJ | E33: RESNGAEA | F33: RSH | G33: 2015 | H33: 20 | I33: 6.8839237 | J33: 0.82 | K33: 1 | L33: 1 | M33: 0.16 | O33: 0.18 | R33: =J33 -> 0.82
A34: R1,R2,R3,R4,R5,R6 | B34: RSHNRDV210 | C34: Natural Gas Radiant Ver2.RSH.NGA.10 | D34: PJ | E34: RESNGAEA | F34: RSH | G34: 2010 | H34: 20 | I34: 8.3590502 | J34: 0.85 | K34: 1 | L34: 1 | M34: 0.16 | O34: 0.18 | R34: =J34 -> 0.85
A35: R1,R2,R3,R4,R5,R6 | B35: RSHNRDV310 | C35: Natural Gas Radiant Ver3.RSH.NGA.10 | D35: PJ | E35: RESNGAEA | F35: RSH | G35: 2010 | H35: 20 | I35: 7.8673413 | J35: 0.98 | K35: 1 | L35: 1 | M35: 0.16 | O35: 0.18 | R35: =J35 -> 0.98
A36: DSL | M36: =M38 -> 0.16 | P36: =SUM(P37:P52) -> 1222.2783 | Q36: DSL | T36: ='2010 Fuel Share'!C74 -> 72.151854
A37: *Distillate Furnace
A38: R1,R2,R3,R4,R5,R6 | B38: RSHDFRBS05 | C38: Distillate Furnace Base.RSH.DST.05 | D38: PJ | E38: RESDSLEA | F38: RSH | G38: 2005 | H38: 20 | J38: 0.81739998 | K38: 1 | L38: 1 | M38: 0.16 | O38: 0.45 | R38: =J38 -> 0.81739998
A39: R1,R2,R3,R4,R5,R6 | B39: RSHDFRV110 | C39: Distillate Furnace Ver1.RSH.DST.10 | D39: PJ | E39: RESDSLEA | F39: RSH | G39: 2010 | H39: 20 | I39: 6.3922148 | J39: =TechData_DMD!J95 -> 0.8 | K39: 1 | L39: 1 | M39: 0.16 | O39: 0.45 | P39: ='RECS RESID'!W15 -> 389.55339 | Q39: =P39/$P$36 -> 0.31871089 | R39: =J39 -> 0.8 | T39: =T36*$Q$39*$R$39/$M$39 -> 114.97791 | U39: =T36*$Q$39*$R$39 -> 18.396465 | V39: =$T39*AA$3/$U$3 -> 35.586069 | W39: =$T39*AB$3/$U$3 -> 20.6788 | X39: =$T39*AC$3/$U$3 -> 34.140195 | Y39: =$T39*AD$3/$U$3 -> 6.693064 | Z39: =$T39*AE$3/$U$3 -> 17.87978 | AA39: =$U39*AA$3/$U$3 -> 5.693771 | AB39: =$U39*AB$3/$U$3 -> 3.308608 | AC39: =$U39*AC$3/$U$3 -> 5.4624312 | AD39: =$U39*AD$3/$U$3 -> 1.0708902 | AE39: =$U39*AE$3/$U$3 -> 2.8607647
A40: R1,R2,R3,R4,R5,R6 | B40: RSHDFRV115 | C40: Distillate Furnace Ver1.RSH.DST.15 | D40: PJ | E40: RESDSLEA | F40: RSH | G40: 2015 | H40: 20 | I40: 6.8839237 | J40: 0.83 | K40: 1 | L40: 1 | M40: 0.16 | O40: 0.45 | R40: =J40 -> 0.83
A41: R1,R2,R3,R4,R5,R6 | B41: RSHDFRV210 | C41: Distillate Furnace Ver2.RSH.DST.10 | D41: PJ | E41: RESDSLEA | F41: RSH | G41: 2010 | H41: 20 | I41: 9.3424678 | J41: 0.85 | K41: 1 | L41: 1 | M41: 0.16 | O41: 0.45 | R41: =J41 -> 0.85
A42: R1,R2,R3,R4,R5,R6 | B42: RSHDFRV310 | C42: Distillate Furnace Ver3.RSH.DST.10 | D42: PJ | E42: RESDSLEA | F42: RSH | G42: 2010 | H42: 20 | I42: 9.3424678 | J42: 0.98 | K42: 1 | L42: 1 | M42: 0.16 | O42: 0.45 | R42: =J42 -> 0.98
A43: *Distillate Radiant
A44: R1,R2,R3,R4,R5,R6 | B44: RSHDRDBS05 | C44: Distillate Radiant Base.RSH.DST.05 | D44: PJ | E44: RESDSLEA | F44: RSH | G44: 2005 | H44: 20 | J44: 0.8 | K44: 1 | L44: 1 | M44: 0.16 | O44: 0.45 | R44: =J44 -> 0.8
A45: R1,R2,R3,R4,R5,R6 | B45: RSHDRDV110 | C45: Distillate Radiant Ver1.RSH.DST.10 | D45: PJ | E45: RESDSLEA | F45: RSH | G45: 2010 | H45: 20 | I45: 9.014662 | J45: =TechData_DMD!J101 -> 0.85 | K45: 1 | L45: 1 | M45: 0.16 | O45: 0.45 | P45: ='RECS RESID'!W16 -> 832.72488 | Q45: =P45/$P$36 -> 0.68128911 | R45: =J45 -> 0.85 | T45: =T36*$Q$45*$R$45/$M$45 -> 261.1427 | U45: =T36*$Q$45*$R$45 -> 41.782832 | V45: =$T45*AA$3/$U$3 -> 80.824588 | W45: =$T45*AB$3/$U$3 -> 46.966567 | X45: =$T45*AC$3/$U$3 -> 77.540659 | Y45: =$T45*AD$3/$U$3 -> 15.201571 | Z45: =$T45*AE$3/$U$3 -> 40.609314 | AA45: =$U45*AA$3/$U$3 -> 12.931934 | AB45: =$U45*AB$3/$U$3 -> 7.5146507 | AC45: =$U45*AC$3/$U$3 -> 12.406505 | AD45: =$U45*AD$3/$U$3 -> 2.4322513 | AE45: =$U45*AE$3/$U$3 -> 6.4974902
A46: R1,R2,R3,R4,R5,R6 | B46: RSHDRDV115 | C46: Distillate Radiant Ver1.RSH.DST.15 | D46: PJ | E46: RESDSLEA | F46: RSH | G46: 2015 | H46: 20 | I46: 9.5610051 | J46: 0.85 | K46: 1 | L46: 1 | M46: 0.16 | O46: 0.45 | R46: =J46 -> 0.85
A47: R1,R2,R3,R4,R5,R6 | B47: RSHDRDV210 | C47: Distillate Radiant Ver2.RSH.DST.10 | D47: PJ | E47: RESDSLEA | F47: RSH | G47: 2010 | H47: 20 | I47: 11.609792 | J47: 0.85 | K47: 1 | L47: 1 | M47: 0.16 | O47: 0.45 | R47: =J47 -> 0.85
A48: R1,R2,R3,R4,R5,R6 | B48: RSHDRDV310 | C48: Distillate Radiant Ver3.RSH.DST.10 | D48: PJ | E48: RESDSLEA | F48: RSH | G48: 2010 | H48: 20 | I48: 10.926863 | J48: 0.98 | K48: 1 | L48: 1 | M48: 0.16 | O48: 0.45 | R48: =J48 -> 0.98
A49: *Natural Gas Heat Pump
A50: R1,R2,R3,R4,R5,R6 | B50: RSHNHPBS05 | C50: Natural Gas Heat Pump Base.RSH.NGA.05 | D50: PJ | E50: RESNGAEA | F50: RSH | G50: 2005 | H50: 15 | J50: 1.3 | K50: 1 | L50: 1 | M50: 0.16 | O50: 0.18 | R50: =J50 -> 1.3
A51: R1,R2,R3,R4,R5,R6 | B51: RSHNHPV110 | C51: Natural Gas Heat Pump Ver1.RSH.NGA.10 | D51: PJ | E51: RESNGAEA | F51: RSH | G51: 2010 | H51: 15 | I51: 12.292721 | J51: 1.3 | K51: 1 | L51: 1 | M51: 0.16 | O51: 0.18 | R51: =J51 -> 1.3
A52: R1,R2,R3,R4,R5,R6 | B52: RSHNHPV120 | C52: Natural Gas Heat Pump Ver1.RSH.NGA.20 | D52: PJ | E52: RESNGAEA | F52: RSH | G52: 2020 | H52: 15 | I52: 12.292721 | J52: 1.4 | K52: 1 | L52: 1 | M52: 0.16 | O52: 0.18 | R52: =J52 -> 1.4
A53: *Space Cooling | U53: =SUM(U55:U91) -> 25.941014 | AA53: =ResDemand!E6 -> 8.0344681 | AB53: =ResDemand!E7 -> 4.3591829 | AC53: =ResDemand!E8 -> 4.9910264 | AD53: =ResDemand!E9 -> 1.4751773 | AE53: =ResDemand!E10 -> 7.0811593 | AF53: =SUM(AA53:AE53)-U53 -> 0
A54: ELC | M54: =M56 -> 0.15 | P54: =SUM(P55:P86) -> 1127.4677 | Q54: ELC | T54: ='2010 Fuel Share'!E72 -> 8.959302 | AA54: =SUM(AA55:AA91) -> 8.0344681 | AB54: =SUM(AB55:AB91) -> 4.3591829 | AC54: =SUM(AC55:AC91) -> 4.9910264 | AD54: =SUM(AD55:AD91) -> 1.4751773 | AE54: =SUM(AE55:AE91) -> 7.0811593
A55: *Room AC
A56: R1,R2,R3,R4,R5,R6 | B56: RSCRACBS05 | C56: Room AC Base.RSC.ELC.05 | D56: PJ | E56: RESELC | F56: RSC | G56: 2005 | H56: 10 | J56: 2.7435958 | K56: 1 | L56: 1 | M56: 0.15 | O56: 0.6 | R56: =J56 -> 2.7435958
A57: R1,R2,R3,R4,R5,R6 | B57: RSCRACV110 | C57: Room AC Ver1.RSC.ELC.10 | D57: PJ | E57: RESELC | F57: RSC | G57: 2010 | H57: 10 | I57: 2.7043986 | J57: 2.74 | K57: 1 | L57: 1 | M57: 0.15 | O57: 0.6 | P57: 669.43392 | Q57: =P57/$P$54 -> 0.59375 | R57: =J57 -> 2.74 | T57: =T54*$Q$57*$R$57/$M$57 -> 97.171096 | U57: =T54*$Q$57*$R$57 -> 14.575664 | V57: =$T57*AA$53/$U$53 -> 30.095897 | W57: =$T57*AB$53/$U$53 -> 16.328837 | X57: =$T57*AC$53/$U$53 -> 18.695626 | Y57: =$T57*AD$53/$U$53 -> 5.5257898 | Z57: =$T57*AE$53/$U$53 -> 26.524947 | AA57: =$U57*AA53/$U$53 -> 4.5143845 | AB57: =$U57*AB53/$U$53 -> 2.4493255 | AC57: =$U57*AC53/$U$53 -> 2.8043439 | AD57: =$U57*AD53/$U$53 -> 0.82886848 | AE57: =$U57*AE53/$U$53 -> 3.978742
A58: R1,R2,R3,R4,R5,R6 | B58: RSCRACV210 | C58: Room AC Ver2.RSC.ELC.10 | D58: PJ | E58: RESELC | F58: RSC | G58: 2010 | H58: 10 | I58: 2.8519112 | J58: 3.17 | K58: 1 | L58: 1 | M58: 0.15 | O58: 0.6 | R58: =J58 -> 3.17
A59: R1,R2,R3,R4,R5,R6 | B59: RSCRACV215 | C59: Room AC Ver2.RSC.ELC.15 | D59: PJ | E59: RESELC | F59: RSC | G59: 2015 | H59: 10 | I59: 2.9010821 | J59: 3.22 | K59: 1 | L59: 1 | M59: 0.15 | O59: 0.6 | R59: =J59 -> 3.22
A60: R1,R2,R3,R4,R5,R6 | B60: RSCRACV230 | C60: Room AC Ver2.RSC.ELC.30 | D60: PJ | E60: RESELC | F60: RSC | G60: 2030 | H60: 10 | I60: 2.9010821 | J60: 3.28 | K60: 1 | L60: 1 | M60: 0.15 | O60: 0.6 | R60: =J60 -> 3.28
A61: R1,R2,R3,R4,R5,R6 | B61: RSCRACV310 | C61: Room AC Ver3.RSC.ELC.10 | D61: PJ | E61: RESELC | F61: RSC | G61: 2010 | H61: 10 | I61: 4.4745504 | J61: 3.52 | K61: 1 | L61: 1 | M61: 0.15 | O61: 0.6 | R61: =J61 -> 3.52
A62: R1,R2,R3,R4,R5,R6 | B62: RSCRACV320 | C62: Room AC Ver3.RSC.ELC.20 | D62: PJ | E62: RESELC | F62: RSC | G62: 2020 | H62: 10 | I62: 5.064601 | J62: 3.81 | K62: 1 | L62: 1 | M62: 0.15 | O62: 0.6 | R62: =J62 -> 3.81
A63: *Central AC
A64: R1,R2,R3,R4,R5,R6 | B64: RSCCACBS05 | C64: Central AC Base.RSC.ELC.05 | D64: PJ | E64: RESELC | F64: RSC | G64: 2005 | H64: 15 | J64: 2.9175659 | K64: 1 | L64: 1 | M64: 0.15 | O64: 0.18 | R64: =J64 -> 2.9175659
A65: R1,R2,R3,R4,R5,R6 | B65: RSCCACV110 | C65: Central AC Ver1.RSC.ELC.10 | D65: PJ | E65: RESELC | F65: RSC | G65: 2010 | H65: 15 | I65: 8.7414904 | J65: 2.92 | K65: 1 | L65: 1 | M65: 0.15 | O65: 0.18 | P65: 429.30287 | Q65: =P65/$P$54 -> 0.38076735 | R65: =J65 -> 2.92 | T65: =T54*$Q$65*$R$65/$M$65 -> 66.408775 | U65: =T54*$Q$65*$R$65 -> 9.9613163 | V65: =$T65*AA$53/$U$53 -> 20.56817 | W65: =$T65*AB$53/$U$53 -> 11.159471 | X65: =$T65*AC$53/$U$53 -> 12.776985 | Y65: =$T65*AD$53/$U$53 -> 3.7764412 | Z65: =$T65*AE$53/$U$53 -> 18.127707 | AA65: =$U65*AA53/$U$53 -> 3.0852255 | AB65: =$U65*AB53/$U$53 -> 1.6739207 | AC65: =$U65*AC53/$U$53 -> 1.9165478 | AD65: =$U65*AD53/$U$53 -> 0.56646619 | AE65: =$U65*AE53/$U$53 -> 2.7191561
A66: R5,R6,R7,R9 | B66: RSCCACV115 | C66: Central AC Ver1.RSC.ELC.15 | D66: PJ | E66: RESELC | F66: RSC | G66: 2015 | H66: 15 | I66: 9.6975909 | J66: 4.1 | K66: 1 | L66: 1 | M66: 0.15 | O66: 0.18 | R66: =J66 -> 4.1
A67: R1,R2,R3,R4,R5,R6 | B67: RSCCACV220 | C67: Central AC Ver2.RSC.ELC.20 | D67: PJ | E67: RESELC | F67: RSC | G67: 2020 | H67: 15 | I67: 9.6975909 | J67: 4.1 | K67: 1 | L67: 1 | M67: 0.15 | O67: 0.18 | R67: =J67 -> 4.1
A68: R1,R2,R3,R4,R5,R6 | B68: RSCCACV310 | C68: Central AC Ver3.RSC.ELC.10 | D68: PJ | E68: RESELC | F68: RSC | G68: 2010 | H68: 15 | I68: 10.517106 | J68: 4.69 | K68: 1 | L68: 1 | M68: 0.15 | O68: 0.18 | R68: =J68 -> 4.69
A69: R1,R2,R3,R4,R5,R6 | B69: RSCCACV320 | C69: Central AC Ver3.RSC.ELC.20 | D69: PJ | E69: RESELC | F69: RSC | G69: 2020 | H69: 15 | I69: 10.107348 | J69: 4.69 | K69: 1 | L69: 1 | M69: 0.15 | O69: 0.18 | R69: =J69 -> 4.69
A70: R1,R2,R3,R4,R5,R6 | B70: RSCCACV410 | C70: Central AC Ver4.RSC.ELC.10 | D70: PJ | E70: RESELC | F70: RSC | G70: 2010 | H70: 15 | I70: 12.292721 | J70: 6.15 | K70: 1 | L70: 1 | M70: 0.15 | O70: 0.18 | R70: =J70 -> 6.15
A71: R1,R2,R3,R4,R5,R6 | B71: RSCCACV415 | C71: Central AC Ver4.RSC.ELC.15 | D71: PJ | E71: RESELC | F71: RSC | G71: 2015 | H71: 15 | I71: 16.390294 | J71: 7.03 | K71: 1 | L71: 1 | M71: 0.15 | O71: 0.18 | R71: =J71 -> 7.03
A72: R1,R2,R3,R4,R5,R6 | B72: RSCCACV420 | C72: Central AC Ver4.RSC.ELC.20 | D72: PJ | E72: RESELC | F72: RSC | G72: 2020 | H72: 15 | I72: 15.707366 | J72: 7.03 | K72: 1 | L72: 1 | M72: 0.15 | O72: 0.18 | R72: =J72 -> 7.03
A73: *Electric Heat Pump
A74: R1,R2,R3,R4,R5,R6 | B74: RSCEHPBS05 | C74: Electric Heat Pump Base.RSC.ELC.05 | D74: PJ | E74: RESELC | F74: RSC | G74: 2005 | H74: 15 | J74: 2.998007 | K74: 1 | L74: 1 | M74: 0.15 | O74: 0.45 | R74: =J74 -> 2.998007
A75: R1,R2,R3,R4,R5,R6 | B75: RSCEHPV110 | C75: Electric Heat Pump Ver1.RSC.ELC.10 | D75: PJ | E75: RESELC | F75: RSC | G75: 2010 | H75: 15 | I75: 6.5561178 | J75: 3 | K75: 1 | L75: 1 | M75: 0.15 | O75: 0.45 | P75: 28.730863 | Q75: =P75/$P$54 -> 0.025482649 | R75: =J75 -> 3 | T75: =T54*$Q$75*$R$75/$M$75 -> 4.566135 | U75: =T54*$Q$75*$R$75 -> 0.68492026 | V75: =$T75*AA$53/$U$53 -> 1.4142264 | W75: =$T75*AB$53/$U$53 -> 0.76730301 | X75: =$T75*AC$53/$U$53 -> 0.87852003 | Y75: =$T75*AD$53/$U$53 -> 0.25966057 | Z75: =$T75*AE$53/$U$53 -> 1.246425 | AA75: =$U75*AA53/$U$53 -> 0.21213396 | AB75: =$U75*AB53/$U$53 -> 0.11509545 | AC75: =$U75*AC53/$U$53 -> 0.131778 | AD75: =$U75*AD53/$U$53 -> 0.038949086 | AE75: =$U75*AE53/$U$53 -> 0.18696376
A76: R1,R2,R3,R4,R5,R6 | B76: RSCEHPV115 | C76: Electric Heat Pump Ver1.RSC.ELC.15 | D76: PJ | E76: RESELC | F76: RSC | G76: 2015 | H76: 15 | I76: 6.7609965 | J76: 4.1 | K76: 1 | L76: 1 | M76: 0.15 | O76: 0.45 | R76: =J76 -> 4.1
A77: R1,R2,R3,R4,R5,R6 | B77: RSCEHPV210 | C77: Electric Heat Pump Ver2.RSC.ELC.10 | D77: PJ | E77: RESELC | F77: RSC | G77: 2010 | H77: 15 | I77: 9.4927122 | J77: 4.4 | K77: 1 | L77: 1 | M77: 0.15 | O77: 0.45 | R77: =J77 -> 4.4
A78: R1,R2,R3,R4,R5,R6 | B78: RSCEHPV215 | C78: Electric Heat Pump Ver2.RSC.ELC.15 | D78: PJ | E78: RESELC | F78: RSC | G78: 2015 | H78: 15 | I78: 9.4927122 | J78: 4.4 | K78: 1 | L78: 1 | M78: 0.15 | O78: 0.45 | R78: =J78 -> 4.4
A79: R1,R2,R3,R4,R5,R6 | B79: RSCEHPV310 | C79: Electric Heat Pump Ver3.RSC.ELC.10 | D79: PJ | E79: RESELC | F79: RSC | G79: 2010 | H79: 15 | I79: 9.8341767 | J79: 4.69 | K79: 1 | L79: 1 | M79: 0.15 | O79: 0.45 | R79: =J79 -> 4.69
A80: R1,R2,R3,R4,R5,R6 | B80: RSCEHPV315 | C80: Electric Heat Pump Ver3.RSC.ELC.15 | D80: PJ | E80: RESELC | F80: RSC | G80: 2015 | H80: 15 | I80: 8.6049046 | J80: 4.84 | K80: 1 | L80: 1 | M80: 0.15 | O80: 0.45 | R80: =J80 -> 4.84
A81: R1,R2,R3,R4,R5,R6 | B81: RSCEHPV320 | C81: Electric Heat Pump Ver3.RSC.ELC.20 | D81: PJ | E81: RESELC | F81: RSC | G81: 2020 | H81: 15 | I81: 8.6049046 | J81: 4.84 | K81: 1 | L81: 1 | M81: 0.15 | O81: 0.45 | R81: =J81 -> 4.84
A82: R1,R2,R3,R4,R5,R6 | B82: RSCEHPV330 | C82: Electric Heat Pump Ver3.RSC.ELC.30 | D82: PJ | E82: RESELC | F82: RSC | G82: 2030 | H82: 15 | I82: 8.6049046 | J82: 4.84 | K82: 1 | L82: 1 | M82: 0.15 | O82: 0.45 | R82: =J82 -> 4.84
A83: R1,R2,R3,R4,R5,R6 | B83: RSCEHPV410 | C83: Electric Heat Pump Ver4.RSC.ELC.10 | D83: PJ | E83: RESELC | F83: RSC | G83: 2010 | H83: 15 | I83: 10.85857 | J83: 6.45 | K83: 1 | L83: 1 | M83: 0.15 | O83: 0.45 | R83: =J83 -> 6.45
A84: R1,R2,R3,R4,R5,R6 | B84: RSCEHPV420 | C84: Electric Heat Pump Ver4.RSC.ELC.20 | D84: PJ | E84: RESELC | F84: RSC | G84: 2020 | H84: 15 | I84: 10.995156 | J84: 6.74 | K84: 1 | L84: 1 | M84: 0.15 | O84: 0.45 | R84: =J84 -> 6.74
A85: R1,R2,R3,R4,R5,R6 | B85: RSCEHPV430 | C85: Electric Heat Pump Ver4.RSC.ELC.30 | D85: PJ | E85: RESELC | F85: RSC | G85: 2030 | H85: 15 | I85: 11.268327 | J85: 7.03 | K85: 1 | L85: 1 | M85: 0.15 | O85: 0.45 | R85: =J85 -> 7.03
A86: R1,R2,R3,R4,R5,R6 | B86: RSCEHPV435 | C86: Electric Heat Pump Ver4.RSC.ELC.35 | D86: PJ | E86: RESELC | F86: RSC | G86: 2035 | H86: 15 | I86: 11.268327 | J86: 7.33 | K86: 1 | L86: 1 | M86: 0.15 | O86: 0.45 | R86: =J86 -> 7.33
A87: NGA | M87: =M89 -> 0.15 | P87: =SUM(P88:P91) -> 0 | Q87: NGA | T87: ='2010 Fuel Share'!E73 -> 1.1985217
A88: *Natural Gas Heat Pump
A89: R1,R2,R3,R4,R5,R6 | B89: RSCNHPBS05 | C89: Natural Gas Heat Pump Base.RSC.NGA.05 | D89: PJ | E89: RESNGAEA | F89: RSC | G89: 2005 | H89: 15 | I89: 0 | J89: 0.67000002 | K89: 1 | L89: 1 | M89: 0.15 | O89: 0.18 | R89: =J89 -> 0.67000002
A90: R1,R2,R3,R4,R5,R6 | B90: RSCNHPV110 | C90: Natural Gas Heat Pump Ver1.RSC.NGA.10 | D90: PJ | E90: RESNGAEA | F90: RSC | G90: 2010 | H90: 15 | I90: 12.292721 | J90: 0.6 | K90: 1 | L90: 1 | M90: 0.15 | O90: 0.18 | Q90: 1 | R90: =J90 -> 0.6 | T90: =T87*$Q$90*$R$90/$M$90 -> 4.7940868 | U90: =T87*$Q$90*$R$90 -> 0.71911302 | V90: =$T90*AA$53/$U$53 -> 1.4848278 | W90: =$T90*AB$53/$U$53 -> 0.8056085 | X90: =$T90*AC$53/$U$53 -> 0.92237773 | Y90: =$T90*AD$53/$U$53 -> 0.27262341 | Z90: =$T90*AE$53/$U$53 -> 1.3086494 | AA90: =$U90*AA53/$U$53 -> 0.22272416 | AB90: =$U90*AB53/$U$53 -> 0.12084128 | AC90: =$U90*AC53/$U$53 -> 0.13835666 | AD90: =$U90*AD53/$U$53 -> 0.040893512 | AE90: =$U90*AE53/$U$53 -> 0.19629741
A91: R1,R2,R3,R4,R5,R6 | B91: RSCNHPV120 | C91: Natural Gas Heat Pump Ver1.RSC.NGA.20 | D91: PJ | E91: RESNGAEA | F91: RSC | G91: 2020 | H91: 15 | I91: 12.292721 | J91: 0.7 | K91: 1 | L91: 1 | M91: 0.15 | O91: 0.18 | R91: =J91 -> 0.7
A92: *Water Heating | U92: =SUM(U94:U114) -> 41.698225 | AA92: =ResDemand!E104 -> 12.609344 | AB92: =ResDemand!E105 -> 7.6119136 | AC92: =ResDemand!E106 -> 13.049702 | AD92: =ResDemand!E107 -> 2.1254368 | AE92: =ResDemand!E108 -> 6.3018289 | AF92: =SUM(AA92:AE92)-U92 -> 0
A93: NGA | M93: =M94 -> 0.1 | P93: =SUM(P95:P100) -> 1190.0517 | Q93: NGA | T93: ='2010 Fuel Share'!D73 -> 47.505374 | AA93: =SUM(AA94:AA114) -> 12.609344 | AB93: =SUM(AB94:AB114) -> 7.6119136 | AC93: =SUM(AC94:AC114) -> 13.049702 | AD93: =SUM(AD94:AD114) -> 2.1254368 | AE93: =SUM(AE94:AE114) -> 6.3018289
A94: R1,R2,R3,R4,R5,R6 | B94: RWHNWHBS05 | C94: Natural Gas Base.RWH.NGA.05 | D94: PJ | E94: RESNGAEA | F94: RWH | G94: 2005 | H94: 10 | J94: 0.57569999 | K94: 1 | L94: 1 | M94: 0.1 | O94: 0.18 | R94: =J94 -> 0.57569999
A95: R1,R2,R3,R4,R5,R6 | B95: RWHNWHV110 | C95: Natural Gas Ver1.RWH.NGA.10 | D95: PJ | E95: RESNGAEA | F95: RWH | G95: 2010 | H95: 10 | I95: 7.6212655 | J95: =TechData_DMD!J222 -> 0.59 | K95: 1 | L95: 1 | M95: 0.1 | O95: 0.18 | P95: 1190.0517 | Q95: =P95/P93 -> 1 | R95: =J95 -> 0.59 | T95: =T93*$Q$95*$R$95/M95 -> 280.2817 | U95: =T93*$Q$95*$R$95 -> 28.02817 | V95: =$T95*AA$92/$U$92 -> 84.755846 | W95: =$T95*AB$92/$U$92 -> 51.16477 | X95: =$T95*AC$92/$U$92 -> 87.715789 | Y95: =$T95*AD$92/$U$92 -> 14.286484 | Z95: =$T95*AE$92/$U$92 -> 42.358814 | AA95: =$U95*AA92/$U$92 -> 8.4755846 | AB95: =$U95*AB92/$U$92 -> 5.116477 | AC95: =$U95*AC92/$U$92 -> 8.7715789 | AD95: =$U95*AD92/$U$92 -> 1.4286484 | AE95: =$U95*AE92/$U$92 -> 4.2358814
A96: R1,R2,R3,R4,R5,R6 | B96: RWHNWHV115 | C96: Natural Gas Ver1.RWH.NGA.15 | D96: PJ | E96: RESNGAEA | F96: RWH | G96: 2015 | H96: 10 | I96: 7.790627 | J96: 0.62 | K96: 1 | L96: 1 | M96: 0.1 | O96: 0.18 | R96: =J96 -> 0.62
A97: R1,R2,R3,R4,R5,R6 | B97: RWHNWHV210 | C97: Natural Gas Ver2.RWH.NGA.10 | D97: PJ | E97: RESNGAEA | F97: RWH | G97: 2010 | H97: 10 | I97: 10.585091 | J97: 0.67 | K97: 1 | L97: 1 | M97: 0.1 | O97: 0.18 | R97: =J97 -> 0.67
A98: R1,R2,R3,R4,R5,R6 | B98: RWHNWHV310 | C98: Natural Gas Ver3.RWH.NGA.10 | D98: PJ | E98: RESNGAEA | F98: RWH | G98: 2010 | H98: 10 | I98: 18.62976 | J98: 0.82 | K98: 1 | L98: 1 | M98: 0.1 | O98: 0.18 | R98: =J98 -> 0.82
A99: R1,R2,R3,R4,R5,R6 | B99: RWHNWHV320 | C99: Natural Gas Ver3.RWH.NGA.20 | D99: PJ | E99: RESNGAEA | F99: RWH | G99: 2020 | H99: 20 | I99: 17.782953 | J99: 0.9 | K99: 1 | L99: 1 | M99: 0.1 | O99: 0.18 | R99: =J99 -> 0.9
A100: R1,R2,R3,R4,R5,R6 | B100: RWHNWHV410 | C100: Natural Gas Ver4.RWH.NGA.10 | D100: PJ | E100: RESNGAEA | F100: RWH | G100: 2010 | H100: 20 | I100: 13.548917 | J100: 0.85 | K100: 1 | L100: 1 | M100: 0.1 | O100: 0.45 | R100: =J100 -> 0.85
...

Sheet ResDemand
A1: Regional Demand Projections
A3: Regional Cooling Demand PJ/a | I3: = cooling coefficient * sq ft of AC housing space * CDD | U3: = cooling coefficient * sq ft of AC housing space * CDD
C4: Region | D4: 2005 | E4: 2010 | F4: 2015 | G4: 2020 | H4: 2025 | I4: 2030 | J4: 2035 | K4: 2040 | L4: 2045 | M4: 2050 | N4: 2055 | P4: 2005 | Q4: 2010 | R4: 2015 | S4: 2020 | T4: 2025 | U4: 2030 | V4: 2035 | W4: 2040 | X4: 2045 | Y4: 2050 | Z4: 2055
A5: R1 | B5: NE | C5: New England | D5: =(1-ResCalc!D110)*ResCalc!D$89*ResCalc!D$62*ResCalc!D66*ResCalc!T44*ResCalc!D$86/'Conv Factors'!$B$17 -> 0 | E5: =(1-ResCalc!E110)*ResCalc!E$89*ResCalc!E$62*ResCalc!E66*ResCalc!U44*ResCalc!E$86/'Conv Factors'!$B$17 -> 0 | F5: =(1-ResCalc!F110)*ResCalc!F$89*ResCalc!F$62*ResCalc!F66*ResCalc!V44*ResCalc!F$86/'Conv Factors'!$B$17 -> 0 | G5: =(1-ResCalc!G110)*ResCalc!G$89*ResCalc!G$62*ResCalc!G66*ResCalc!W44*ResCalc!G$86/'Conv Factors'!$B$17 -> 0 | H5: =(1-ResCalc!H110)*ResCalc!H$89*ResCalc!H$62*ResCalc!H66*ResCalc!X44*ResCalc!H$86/'Conv Factors'!$B$17 -> 0 | I5: =(1-ResCalc!I110)*ResCalc!I$89*ResCalc!I$62*ResCalc!I66*ResCalc!Y44*ResCalc!I$86/'Conv Factors'!$B$17 -> 0 | J5: =(1-ResCalc!J110)*ResCalc!J$89*ResCalc!J$62*ResCalc!J66*ResCalc!Z44*ResCalc!J$86/'Conv Factors'!$B$17 -> 0 | K5: =(1-ResCalc!K110)*ResCalc!K$89*ResCalc!K$62*ResCalc!K66*ResCalc!AA44*ResCalc!K$86/'Conv Factors'!$B$17 -> 0 | ... N5: =(1-ResCalc!N110)*ResCalc!N$89*ResCalc!N$62*ResCalc!N66*ResCalc!AD44*ResCalc!N$86/'Conv Factors'!$B$17 -> 0 | P5: 0 | Q5: 0 | R5: 0 | S5: 0 | T5: 0 | U5: 0 | V5: 0 | W5: 0 | X5: 0 | Y5: 0 | Z5: 0
C6: Brooklyn | D6: =(1-ResCalc!D$111)*ResCalc!D$89*ResCalc!D$62*ResCalc!D67*ResCalc!$I35*ResCalc!D86/'Conv Factors'!$B$17 -> 7.6932806 | E6: =(1-ResCalc!E$111)*ResCalc!E$89*ResCalc!E$62*ResCalc!E67*ResCalc!$I35*ResCalc!E86/'Conv Factors'!$B$17 -> 8.0344681 | F6: =(1-ResCalc!F$111)*ResCalc!F$89*ResCalc!F$62*ResCalc!F67*ResCalc!$I35*ResCalc!F86/'Conv Factors'!$B$17 -> 7.9922343 | G6: =(1-ResCalc!G$111)*ResCalc!G$89*ResCalc!G$62*ResCalc!G67*ResCalc!$I35*ResCalc!G86/'Conv Factors'!$B$17 -> 8.4017127 | H6: =(1-ResCalc!H$111)*ResCalc!H$89*ResCalc!H$62*ResCalc!H67*ResCalc!$I35*ResCalc!H86/'Conv Factors'!$B$17 -> 9.0434443 | I6: =(1-ResCalc!I$111)*ResCalc!I$89*ResCalc!I$62*ResCalc!I67*ResCalc!$I35*ResCalc!I86/'Conv Factors'!$B$17 -> 9.7060084 | J6: =(1-ResCalc!J$111)*ResCalc!J$89*ResCalc!J$62*ResCalc!J67*ResCalc!$I35*ResCalc!J86/'Conv Factors'!$B$17 -> 10.569517 | K6: =(1-ResCalc!K$111)*ResCalc!K$89*ResCalc!K$62*ResCalc!K67*ResCalc!$I35*ResCalc!K86/'Conv Factors'!$B$17 -> 11.508576 | ... N6: =(1-ResCalc!N$111)*ResCalc!N$89*ResCalc!N$62*ResCalc!N67*ResCalc!$I35*ResCalc!N86/'Conv Factors'!$B$17 -> 14.62484 | P6: 19.014618 | Q6: 19.857893 | R6: 19.753508 | S6: 20.76557 | T6: 22.351665 | U6: 23.989251 | V6: 26.123487 | W6: 28.444456 | X6: 30.669183 | Y6: 33.296053 | Z6: 36.146575
C7: Bronx | D7: =(1-ResCalc!D112)*ResCalc!D$89*ResCalc!D$62*ResCalc!D68*ResCalc!T46*ResCalc!D$86/'Conv Factors'!$B$17 -> 4.1753937 | E7: =(1-ResCalc!E$111)*ResCalc!E$89*ResCalc!E$62*ResCalc!E68*ResCalc!$I36*ResCalc!E87/'Conv Factors'!$B$17 -> 4.3591829 | F7: =(1-ResCalc!F$111)*ResCalc!F$89*ResCalc!F$62*ResCalc!F68*ResCalc!$I36*ResCalc!F87/'Conv Factors'!$B$17 -> 4.4116111 | G7: =(1-ResCalc!G$111)*ResCalc!G$89*ResCalc!G$62*ResCalc!G68*ResCalc!$I36*ResCalc!G87/'Conv Factors'!$B$17 -> 4.5896611 | H7: =(1-ResCalc!H$111)*ResCalc!H$89*ResCalc!H$62*ResCalc!H68*ResCalc!$I36*ResCalc!H87/'Conv Factors'!$B$17 -> 4.9645745 | I7: =(1-ResCalc!I$111)*ResCalc!I$89*ResCalc!I$62*ResCalc!I68*ResCalc!$I36*ResCalc!I87/'Conv Factors'!$B$17 -> 5.3534347 | J7: =(1-ResCalc!J$111)*ResCalc!J$89*ResCalc!J$62*ResCalc!J68*ResCalc!$I36*ResCalc!J87/'Conv Factors'!$B$17 -> 5.8533796 | K7: =(1-ResCalc!K$111)*ResCalc!K$89*ResCalc!K$62*ResCalc!K68*ResCalc!$I36*ResCalc!K87/'Conv Factors'!$B$17 -> 6.3984164 | L7: =(1-ResCalc!L$111)*ResCalc!L$89*ResCalc!L$62*ResCalc!L68*ResCalc!$I36*ResCalc!L87/'Conv Factors'!$B$17 -> 6.9375125 | ... N7: =(1-ResCalc!N$111)*ResCalc!N$89*ResCalc!N$62*ResCalc!N68*ResCalc!$I36*ResCalc!N87/'Conv Factors'!$B$17 -> 8.2347848 | P7: 10.319852 | Q7: 10.774103 | R7: 10.903684 | S7: 11.34375 | T7: 12.270381 | U7: 13.231483 | V7: 14.467141 | W7: 15.814247 | X7: 17.146671 | Y7: 18.682781 | Z7: 20.352993
C8: Manhattan | D8: =(1-ResCalc!D113)*ResCalc!D$89*ResCalc!D$62*ResCalc!D69*ResCalc!T47*ResCalc!D$86/'Conv Factors'!$B$17 -> 4.9006534 | E8: =(1-ResCalc!E$113)*ResCalc!E$89*ResCalc!E$62*ResCalc!E69*ResCalc!$I37*ResCalc!E86/'Conv Factors'!$B$17 -> 4.9910264 | F8: =(1-ResCalc!F$113)*ResCalc!F$89*ResCalc!F$62*ResCalc!F69*ResCalc!$I37*ResCalc!F86/'Conv Factors'!$B$17 -> 4.9913321 | G8: =(1-ResCalc!G$113)*ResCalc!G$89*ResCalc!G$62*ResCalc!G69*ResCalc!$I37*ResCalc!G86/'Conv Factors'!$B$17 -> 5.3885796 | H8: =(1-ResCalc!H$113)*ResCalc!H$89*ResCalc!H$62*ResCalc!H69*ResCalc!$I37*ResCalc!H86/'Conv Factors'!$B$17 -> 5.9505961 | I8: =(1-ResCalc!I$113)*ResCalc!I$89*ResCalc!I$62*ResCalc!I69*ResCalc!$I37*ResCalc!I86/'Conv Factors'!$B$17 -> 6.5368335 | J8: =(1-ResCalc!J$113)*ResCalc!J$89*ResCalc!J$62*ResCalc!J69*ResCalc!$I37*ResCalc!J86/'Conv Factors'!$B$17 -> 7.0394433 | K8: =(1-ResCalc!K$113)*ResCalc!K$89*ResCalc!K$62*ResCalc!K69*ResCalc!$I37*ResCalc!K86/'Conv Factors'!$B$17 -> 7.5815256 | L8: =(1-ResCalc!L$113)*ResCalc!L$89*ResCalc!L$62*ResCalc!L69*ResCalc!$I37*ResCalc!L86/'Conv Factors'!$B$17 -> 8.1802587 | ... N8: =(1-ResCalc!N$113)*ResCalc!N$89*ResCalc!N$62*ResCalc!N69*ResCalc!$I37*ResCalc!N86/'Conv Factors'!$B$17 -> 9.5296807 | P8: 12.112395 | Q8: 12.335759 | R8: 12.336515 | S8: 13.318347 | T8: 14.70742 | U8: 16.156357 | V8: 17.398601 | W8: 18.738405 | X8: 20.218227 | Y8: 21.820787 | Z8: 23.553442
C9: Staten Island | D9: =(1-ResCalc!D$114)*ResCalc!D$89*ResCalc!D$62*ResCalc!D70*ResCalc!$I38*ResCalc!D86/'Conv Factors'!$B$17 -> 1.4311835 | E9: =(1-ResCalc!E$114)*ResCalc!E$89*ResCalc!E$62*ResCalc!E70*ResCalc!$I38*ResCalc!E86/'Conv Factors'!$B$17 -> 1.4751773 | F9: =(1-ResCalc!F$114)*ResCalc!F$89*ResCalc!F$62*ResCalc!F70*ResCalc!$I38*ResCalc!F86/'Conv Factors'!$B$17 -> 1.440347 | G9: =(1-ResCalc!G$114)*ResCalc!G$89*ResCalc!G$62*ResCalc!G70*ResCalc!$I38*ResCalc!G86/'Conv Factors'!$B$17 -> 1.5932736 | H9: =(1-ResCalc!H$114)*ResCalc!H$89*ResCalc!H$62*ResCalc!H70*ResCalc!$I38*ResCalc!H86/'Conv Factors'!$B$17 -> 1.6997444 | I9: =(1-ResCalc!I$114)*ResCalc!I$89*ResCalc!I$62*ResCalc!I70*ResCalc!$I38*ResCalc!I86/'Conv Factors'!$B$17 -> 1.8085611 | J9: =(1-ResCalc!J$114)*ResCalc!J$89*ResCalc!J$62*ResCalc!J70*ResCalc!$I38*ResCalc!J86/'Conv Factors'!$B$17 -> 1.9455502 | K9: =(1-ResCalc!K$114)*ResCalc!K$89*ResCalc!K$62*ResCalc!K70*ResCalc!$I38*ResCalc!K86/'Conv Factors'!$B$17 -> 2.0931612 | ... N9: =(1-ResCalc!N$114)*ResCalc!N$89*ResCalc!N$62*ResCalc!N70*ResCalc!$I38*ResCalc!N86/'Conv Factors'!$B$17 -> 2.7522098 | P9: 3.5372955 | Q9: 3.64603 | R9: 3.559944 | S9: 3.9379155 | T9: 4.2010672 | U9: 4.4700174 | V9: 4.8085979 | W9: 5.1734315 | X9: 5.7507135 | Y9: 6.2547798 | Z9: 6.8023279
C10: Queens | D10: =(1-ResCalc!D115)*ResCalc!D$89*ResCalc!D$62*ResCalc!D71*ResCalc!T49*ResCalc!D$86/'Conv Factors'!$B$17 -> 6.8912245 | E10: =(1-ResCalc!E$115)*ResCalc!E$89*ResCalc!E$62*ResCalc!E71*ResCalc!$I39*ResCalc!E86/'Conv Factors'!$B$17 -> 7.0811593 | F10: =(1-ResCalc!F$115)*ResCalc!F$89*ResCalc!F$62*ResCalc!F71*ResCalc!$I39*ResCalc!F86/'Conv Factors'!$B$17 -> 7.0996332 | G10: =(1-ResCalc!G$115)*ResCalc!G$89*ResCalc!G$62*ResCalc!G71*ResCalc!$I39*ResCalc!G86/'Conv Factors'!$B$17 -> 7.6647291 | H10: =(1-ResCalc!H$115)*ResCalc!H$89*ResCalc!H$62*ResCalc!H71*ResCalc!$I39*ResCalc!H86/'Conv Factors'!$B$17 -> 8.4436438 | I10: =(1-ResCalc!I$115)*ResCalc!I$89*ResCalc!I$62*ResCalc!I71*ResCalc!$I39*ResCalc!I86/'Conv Factors'!$B$17 -> 9.2534876 | J10: =(1-ResCalc!J$115)*ResCalc!J$89*ResCalc!J$62*ResCalc!J71*ResCalc!$I39*ResCalc!J86/'Conv Factors'!$B$17 -> 10.002617 | K10: =(1-ResCalc!K$115)*ResCalc!K$89*ResCalc!K$62*ResCalc!K71*ResCalc!$I39*ResCalc!K86/'Conv Factors'!$B$17 -> 10.813062 | L10: =(1-ResCalc!L$115)*ResCalc!L$89*ResCalc!L$62*ResCalc!L71*ResCalc!$I39*ResCalc!L86/'Conv Factors'!$B$17 -> 11.783251 | ... N10: =(1-ResCalc!N$115)*ResCalc!N$89*ResCalc!N$62*ResCalc!N71*ResCalc!$I39*ResCalc!N86/'Conv Factors'!$B$17 -> 13.814167 | P10: 17.032266 | Q10: 17.501706 | R10: 17.547366 | S10: 18.94405 | T10: 20.869206 | U10: 22.870806 | V10: 24.722344 | W10: 26.725432 | X10: 29.123339 | Y10: 31.532659 | Z10: 34.142925
A11: R4 | C11: West North Central | D11: =(1-ResCalc!D116)*ResCalc!D$89*ResCalc!D$62*ResCalc!D72*ResCalc!T47*ResCalc!D$86/'Conv Factors'!$B$17 -> 0 | E11: =(1-ResCalc!E116)*ResCalc!E$89*ResCalc!E$62*ResCalc!E72*ResCalc!U47*ResCalc!E$86/'Conv Factors'!$B$17 -> 0 | F11: =(1-ResCalc!F116)*ResCalc!F$89*ResCalc!F$62*ResCalc!F72*ResCalc!V47*ResCalc!F$86/'Conv Factors'!$B$17 -> 0 | G11: =(1-ResCalc!G116)*ResCalc!G$89*ResCalc!G$62*ResCalc!G72*ResCalc!W47*ResCalc!G$86/'Conv Factors'!$B$17 -> 0 | H11: =(1-ResCalc!H116)*ResCalc!H$89*ResCalc!H$62*ResCalc!H72*ResCalc!X47*ResCalc!H$86/'Conv Factors'!$B$17 -> 0 | I11: =(1-ResCalc!I116)*ResCalc!I$89*ResCalc!I$62*ResCalc!I72*ResCalc!Y47*ResCalc!I$86/'Conv Factors'!$B$17 -> 0 | J11: =(1-ResCalc!J116)*ResCalc!J$89*ResCalc!J$62*ResCalc!J72*ResCalc!Z47*ResCalc!J$86/'Conv Factors'!$B$17 -> 0 | K11: =(1-ResCalc!K116)*ResCalc!K$89*ResCalc!K$62*ResCalc!K72*ResCalc!AA47*ResCalc!K$86/'Conv Factors'!$B$17 -> 0 | ... N11: =(1-ResCalc!N116)*ResCalc!N$89*ResCalc!N$62*ResCalc!N72*ResCalc!AD47*ResCalc!N$86/'Conv Factors'!$B$17 -> 0 | P11: 0 | Q11: 0 | R11: 0 | S11: 0 | T11: 0 | U11: 0 | V11: 0 | W11: 0 | X11: 0 | Y11: 0 | Z11: 0
A12: R8 | B12: M | C12: Mountain | D12: =(1-ResCalc!D117)*ResCalc!D$89*ResCalc!D$62*ResCalc!D73*ResCalc!T51*ResCalc!D$86/'Conv Factors'!$B$17 -> 0 | E12: =(1-ResCalc!E117)*ResCalc!E$89*ResCalc!E$62*ResCalc!E73*ResCalc!U51*ResCalc!E$86/'Conv Factors'!$B$17 -> 0 | F12: =(1-ResCalc!F117)*ResCalc!F$89*ResCalc!F$62*ResCalc!F73*ResCalc!V51*ResCalc!F$86/'Conv Factors'!$B$17 -> 0 | G12: =(1-ResCalc!G117)*ResCalc!G$89*ResCalc!G$62*ResCalc!G73*ResCalc!W51*ResCalc!G$86/'Conv Factors'!$B$17 -> 0 | H12: =(1-ResCalc!H117)*ResCalc!H$89*ResCalc!H$62*ResCalc!H73*ResCalc!X51*ResCalc!H$86/'Conv Factors'!$B$17 -> 0 | I12: =(1-ResCalc!I117)*ResCalc!I$89*ResCalc!I$62*ResCalc!I73*ResCalc!Y51*ResCalc!I$86/'Conv Factors'!$B$17 -> 0 | J12: =(1-ResCalc!J117)*ResCalc!J$89*ResCalc!J$62*ResCalc!J73*ResCalc!Z51*ResCalc!J$86/'Conv Factors'!$B$17 -> 0 | K12: =(1-ResCalc!K117)*ResCalc!K$89*ResCalc!K$62*ResCalc!K73*ResCalc!AA51*ResCalc!K$86/'Conv Factors'!$B$17 -> 0 | ... N12: =(1-ResCalc!N117)*ResCalc!N$89*ResCalc!N$62*ResCalc!N73*ResCalc!AD51*ResCalc!N$86/'Conv Factors'!$B$17 -> 0 | P12: 0 | Q12: 0 | R12: 0 | S12: 0 | T12: 0 | U12: 0 | V12: 0 | W12: 0 | X12: 0 | Y12: 0 | Z12: 0
A13: R9 | B13: P | C13: Pacific | D13: =(1-ResCalc!D118)*ResCalc!D$89*ResCalc!D$62*ResCalc!D74*ResCalc!T52*ResCalc!D$86/'Conv Factors'!$B$17 -> 0 | E13: =(1-ResCalc!E118)*ResCalc!E$89*ResCalc!E$62*ResCalc!E74*ResCalc!U52*ResCalc!E$86/'Conv Factors'!$B$17 -> 0 | F13: =(1-ResCalc!F118)*ResCalc!F$89*ResCalc!F$62*ResCalc!F74*ResCalc!V52*ResCalc!F$86/'Conv Factors'!$B$17 -> 0 | G13: =(1-ResCalc!G118)*ResCalc!G$89*ResCalc!G$62*ResCalc!G74*ResCalc!W52*ResCalc!G$86/'Conv Factors'!$B$17 -> 0 | H13: =(1-ResCalc!H118)*ResCalc!H$89*ResCalc!H$62*ResCalc!H74*ResCalc!X52*ResCalc!H$86/'Conv Factors'!$B$17 -> 0 | I13: =(1-ResCalc!I118)*ResCalc!I$89*ResCalc!I$62*ResCalc!I74*ResCalc!Y52*ResCalc!I$86/'Conv Factors'!$B$17 -> 0 | J13: =(1-ResCalc!J118)*ResCalc!J$89*ResCalc!J$62*ResCalc!J74*ResCalc!Z52*ResCalc!J$86/'Conv Factors'!$B$17 -> 0 | K13: =(1-ResCalc!K118)*ResCalc!K$89*ResCalc!K$62*ResCalc!K74*ResCalc!AA52*ResCalc!K$86/'Conv Factors'!$B$17 -> 0 | ... N13: =(1-ResCalc!N118)*ResCalc!N$89*ResCalc!N$62*ResCalc!N74*ResCalc!AD52*ResCalc!N$86/'Conv Factors'!$B$17 -> 0 | P13: 0 | Q13: 0 | R13: 0 | S13: 0 | T13: 0 | U13: 0 | V13: 0 | W13: 0 | X13: 0 | Y13: 0 | Z13: 0
C14: Total NYC | D14: =SUM(D6:D10) -> 25.091736 | E14: =SUM(E6:E10) -> 25.941014 | F14: =SUM(F6:F10) -> 25.935158 | G14: =SUM(G6:G10) -> 27.637956 | H14: =SUM(H6:H10) -> 30.102003 | I14: =SUM(I6:I10) -> 32.658325 | J14: =SUM(J6:J10) -> 35.410506 | K14: =SUM(K6:K10) -> 38.394742 | ... N14: =SUM(N6:N10) -> 48.955683 | P14: 62.016425 | Q14: 64.115491 | R14: 64.101017 | S14: 68.309632 | T14: 74.39974 | U14: 80.717915 | V14: 87.520171 | W14: 94.895972 | X14: 102.90813 | Y14: 111.58706 | Z14: 120.99826
A15: Cooling demand can be changed through population (Pop:C4-N12) or cooling degree days(ResCalc:I37-I45) or Housholds without AC (ResCalc:C125-N133)
A17: Regional Heating Demand PJ/a | I17: = heating coefficient * sq ft of heated housing space * HDD | U17: = heating coefficient * sq ft of heated housing space * HDD
A18: R1 | B18: NE | C18: New England | D18: =ResCalc!D$90*ResCalc!D$62*ResCalc!D66*ResCalc!T32*ResCalc!D$87/'Conv Factors'!$B$17 -> 0 | E18: =ResCalc!E$90*ResCalc!E$62*ResCalc!E66*ResCalc!U32*ResCalc!E$87/'Conv Factors'!$B$17 -> 0 | F18: =ResCalc!F$90*ResCalc!F$62*ResCalc!F66*ResCalc!V32*ResCalc!F$87/'Conv Factors'!$B$17 -> 0 | G18: =ResCalc!G$90*ResCalc!G$62*ResCalc!G66*ResCalc!W32*ResCalc!G$87/'Conv Factors'!$B$17 -> 0 | H18: =ResCalc!H$90*ResCalc!H$62*ResCalc!H66*ResCalc!X32*ResCalc!H$87/'Conv Factors'!$B$17 -> 0 | I18: =ResCalc!I$90*ResCalc!I$62*ResCalc!I66*ResCalc!Y32*ResCalc!I$87/'Conv Factors'!$B$17 -> 0 | J18: =ResCalc!J$90*ResCalc!J$62*ResCalc!J66*ResCalc!Z32*ResCalc!J$87/'Conv Factors'!$B$17 -> 0 | K18: =ResCalc!K$90*ResCalc!K$62*ResCalc!K66*ResCalc!AA32*ResCalc!K$87/'Conv Factors'!$B$17 -> 0 | ... N18: =ResCalc!N$90*ResCalc!N$62*ResCalc!N66*ResCalc!AD32*ResCalc!N$87/'Conv Factors'!$B$17 -> 0 | P18: 0 | Q18: 0 | R18: 0 | S18: 0 | T18: 0 | U18: 0 | V18: 0 | W18: 0 | X18: 0 | Y18: 0 | Z18: 0
C19: Brooklyn | D19: =ResCalc!D$90*ResCalc!D$62*ResCalc!D67*ResCalc!$J35*ResCalc!D87/'Conv Factors'!$B$17 -> 47.297559 | E19: ='2010 Fuel Share'!$Q$73*ResCalc!E$90*ResCalc!E$62*ResCalc!E67*ResCalc!$J35*ResCalc!E87/'Conv Factors'!$B$17 -> 45.222793 | F19: ='2010 Fuel Share'!$Q$73*ResCalc!F$90*ResCalc!F$62*ResCalc!F67*ResCalc!$J35*ResCalc!F87/'Conv Factors'!$B$17 -> 45.026376 | G19: ='2010 Fuel Share'!$Q$73*ResCalc!G$90*ResCalc!G$62*ResCalc!G67*ResCalc!$J35*ResCalc!G87/'Conv Factors'!$B$17 -> 40.666139 | H19: ='2010 Fuel Share'!$Q$73*ResCalc!H$90*ResCalc!H$62*ResCalc!H67*ResCalc!$J35*ResCalc!H87/'Conv Factors'!$B$17 -> 39.594571 | I19: ='2010 Fuel Share'!$Q$73*ResCalc!I$90*ResCalc!I$62*ResCalc!I67*ResCalc!$J35*ResCalc!I87/'Conv Factors'!$B$17 -> 38.453657 | J19: ='2010 Fuel Share'!$Q$73*ResCalc!J$90*ResCalc!J$62*ResCalc!J67*ResCalc!$J35*ResCalc!J87/'Conv Factors'!$B$17 -> 37.275478 | K19: ='2010 Fuel Share'!$Q$73*ResCalc!K$90*ResCalc!K$62*ResCalc!K67*ResCalc!$J35*ResCalc!K87/'Conv Factors'!$B$17 -> 36.09911 | L19: ='2010 Fuel Share'!$Q$73*ResCalc!L$90*ResCalc!L$62*ResCalc!L67*ResCalc!$J35*ResCalc!L87/'Conv Factors'!$B$17 -> 34.624395 | ... N19: ='2010 Fuel Share'!$Q$73*ResCalc!N$90*ResCalc!N$62*ResCalc!N67*ResCalc!$J35*ResCalc!N87/'Conv Factors'!$B$17 -> 32.285113 | P19: 49.117207 | Q19: 46.877785 | R19: 46.67418 | S19: 42.154374 | T19: 41.043591 | U19: 39.860924 | V19: 38.639627 | W19: 37.420208 | X19: 35.891524 | Y19: 34.658496 | Z19: 33.466633
C20: Bronx | D20: =ResCalc!D$90*ResCalc!D$62*ResCalc!D68*ResCalc!$J36*ResCalc!D87/'Conv Factors'!$B$17 -> 25.669924 | E20: ='2010 Fuel Share'!$R$73*ResCalc!E$90*ResCalc!E$62*ResCalc!E68*ResCalc!$J36*ResCalc!E87/'Conv Factors'!$B$17 -> 26.278629 | F20: ='2010 Fuel Share'!$R$73*ResCalc!F$90*ResCalc!F$62*ResCalc!F68*ResCalc!$J36*ResCalc!F87/'Conv Factors'!$B$17 -> 26.6191 | G20: ='2010 Fuel Share'!$R$73*ResCalc!G$90*ResCalc!G$62*ResCalc!G68*ResCalc!$J36*ResCalc!G87/'Conv Factors'!$B$17 -> 23.792665 | H20: ='2010 Fuel Share'!$R$73*ResCalc!H$90*ResCalc!H$62*ResCalc!H68*ResCalc!$J36*ResCalc!H87/'Conv Factors'!$B$17 -> 23.279903 | I20: ='2010 Fuel Share'!$R$73*ResCalc!I$90*ResCalc!I$62*ResCalc!I68*ResCalc!$J36*ResCalc!I87/'Conv Factors'!$B$17 -> 22.715738 | J20: ='2010 Fuel Share'!$R$73*ResCalc!J$90*ResCalc!J$62*ResCalc!J68*ResCalc!$J36*ResCalc!J87/'Conv Factors'!$B$17 -> 22.109154 | K20: ='2010 Fuel Share'!$R$73*ResCalc!K$90*ResCalc!K$62*ResCalc!K68*ResCalc!$J36*ResCalc!K87/'Conv Factors'!$B$17 -> 21.495361 | L20: ='2010 Fuel Share'!$R$73*ResCalc!L$90*ResCalc!L$62*ResCalc!L68*ResCalc!$J36*ResCalc!L87/'Conv Factors'!$B$17 -> 20.732761 | ... N20: ='2010 Fuel Share'!$R$73*ResCalc!N$90*ResCalc!N$62*ResCalc!N68*ResCalc!$J36*ResCalc!N87/'Conv Factors'!$B$17 -> 19.469769 | P20: 26.657506 | Q20: 27.321821 | R20: 27.675808 | S20: 24.737171 | T20: 24.204054 | U20: 23.617494 | V20: 22.98683 | W20: 22.34867 | X20: 21.555798 | Y20: 20.890705 | Z20: 20.242667
C21: Manhattan | D21: =ResCalc!D$90*ResCalc!D$62*ResCalc!D69*ResCalc!$J37*ResCalc!D87/'Conv Factors'!$B$17 -> 30.067435 | E21: ='2010 Fuel Share'!$S$73*ResCalc!E$90*ResCalc!E$62*ResCalc!E69*ResCalc!$J37*ResCalc!E87/'Conv Factors'!$B$17 -> 43.385376 | F21: ='2010 Fuel Share'!$S$73*ResCalc!F$90*ResCalc!F$62*ResCalc!F69*ResCalc!$J37*ResCalc!F87/'Conv Factors'!$B$17 -> 43.370297 | G21: ='2010 Fuel Share'!$S$73*ResCalc!G$90*ResCalc!G$62*ResCalc!G69*ResCalc!$J37*ResCalc!G87/'Conv Factors'!$B$17 -> 38.849236 | H21: ='2010 Fuel Share'!$S$73*ResCalc!H$90*ResCalc!H$62*ResCalc!H69*ResCalc!$J37*ResCalc!H87/'Conv Factors'!$B$17 -> 37.521563 | I21: ='2010 Fuel Share'!$S$73*ResCalc!I$90*ResCalc!I$62*ResCalc!I69*ResCalc!$J37*ResCalc!I87/'Conv Factors'!$B$17 -> 36.156476 | J21: ='2010 Fuel Share'!$S$73*ResCalc!J$90*ResCalc!J$62*ResCalc!J69*ResCalc!$J37*ResCalc!J87/'Conv Factors'!$B$17 -> 34.659963 | K21: ='2010 Fuel Share'!$S$73*ResCalc!K$90*ResCalc!K$62*ResCalc!K69*ResCalc!$J37*ResCalc!K87/'Conv Factors'!$B$17 -> 33.201153 | L21: ='2010 Fuel Share'!$S$73*ResCalc!L$90*ResCalc!L$62*ResCalc!L69*ResCalc!$J37*ResCalc!L87/'Conv Factors'!$B$17 -> 31.867261 | ... N21: ='2010 Fuel Share'!$S$73*ResCalc!N$90*ResCalc!N$62*ResCalc!N69*ResCalc!$J37*ResCalc!N87/'Conv Factors'!$B$17 -> 29.370492 | P21: 31.224199 | Q21: 45.245792 | R21: 45.230066 | S21: 40.515137 | T21: 39.130532 | U21: 37.706909 | V21: 36.146223 | W21: 34.624858 | X21: 33.233767 | Y21: 31.903195 | Z21: 30.629933
C22: Staten Island | D22: =ResCalc!D$90*ResCalc!D$62*ResCalc!D70*ResCalc!$J38*ResCalc!D87/'Conv Factors'!$B$17 -> 8.7987803 | E22: ='2010 Fuel Share'!$U$73*ResCalc!E$90*ResCalc!E$62*ResCalc!E70*ResCalc!$J38*ResCalc!E87/'Conv Factors'!$B$17 -> 8.5055488 | F22: ='2010 Fuel Share'!$U$73*ResCalc!F$90*ResCalc!F$62*ResCalc!F70*ResCalc!$J38*ResCalc!F87/'Conv Factors'!$B$17 -> 8.3013303 | G22: ='2010 Fuel Share'!$U$73*ResCalc!G$90*ResCalc!G$62*ResCalc!G70*ResCalc!$J38*ResCalc!G87/'Conv Factors'!$B$17 -> 7.6624188 | H22: ='2010 Fuel Share'!$U$73*ResCalc!H$90*ResCalc!H$62*ResCalc!H70*ResCalc!$J38*ResCalc!H87/'Conv Factors'!$B$17 -> 7.3942783 | I22: ='2010 Fuel Share'!$U$73*ResCalc!I$90*ResCalc!I$62*ResCalc!I70*ResCalc!$J38*ResCalc!I87/'Conv Factors'!$B$17 -> 7.1193539 | J22: ='2010 Fuel Share'!$U$73*ResCalc!J$90*ResCalc!J$62*ResCalc!J70*ResCalc!$J38*ResCalc!J87/'Conv Factors'!$B$17 -> 6.817434 | K22: ='2010 Fuel Share'!$U$73*ResCalc!K$90*ResCalc!K$62*ResCalc!K70*ResCalc!$J38*ResCalc!K87/'Conv Factors'!$B$17 -> 6.5236096 | L22: ='2010 Fuel Share'!$U$73*ResCalc!L$90*ResCalc!L$62*ResCalc!L70*ResCalc!$J38*ResCalc!L87/'Conv Factors'!$B$17 -> 6.4507785 | ... N22: ='2010 Fuel Share'!$U$73*ResCalc!N$90*ResCalc!N$62*ResCalc!N70*ResCalc!$J38*ResCalc!N87/'Conv Factors'!$B$17 -> 6.0367491 | P22: 9.1372899 | Q22: 8.7463733 | R22: 8.5363725 | S22: 7.879371 | T22: 7.6036384 | U22: 7.3209298 | V22: 7.0104615 | W22: 6.7083178 | X22: 6.6334246 | Y22: 6.4173445 | Z22: 6.2076724
C23: Queens | D23: =ResCalc!D$90*ResCalc!D$62*ResCalc!D71*ResCalc!$J39*ResCalc!D87/'Conv Factors'!$B$17 -> 42.366595 | E23: ='2010 Fuel Share'!$T$73*ResCalc!E$90*ResCalc!E$62*ResCalc!E71*ResCalc!$J39*ResCalc!E87/'Conv Factors'!$B$17 -> 22.721632 | F23: ='2010 Fuel Share'!$T$73*ResCalc!F$90*ResCalc!F$62*ResCalc!F71*ResCalc!$J39*ResCalc!F87/'Conv Factors'!$B$17 -> 22.771598 | G23: ='2010 Fuel Share'!$T$73*ResCalc!G$90*ResCalc!G$62*ResCalc!G71*ResCalc!$J39*ResCalc!G87/'Conv Factors'!$B$17 -> 20.397956 | H23: ='2010 Fuel Share'!$T$73*ResCalc!H$90*ResCalc!H$62*ResCalc!H71*ResCalc!$J39*ResCalc!H87/'Conv Factors'!$B$17 -> 19.653143 | I23: ='2010 Fuel Share'!$T$73*ResCalc!I$90*ResCalc!I$62*ResCalc!I71*ResCalc!$J39*ResCalc!I87/'Conv Factors'!$B$17 -> 18.893211 | J23: ='2010 Fuel Share'!$T$73*ResCalc!J$90*ResCalc!J$62*ResCalc!J71*ResCalc!$J39*ResCalc!J87/'Conv Factors'!$B$17 -> 18.179631 | K23: ='2010 Fuel Share'!$T$73*ResCalc!K$90*ResCalc!K$62*ResCalc!K71*ResCalc!$J39*ResCalc!K87/'Conv Factors'!$B$17 -> 17.479417 | L23: ='2010 Fuel Share'!$T$73*ResCalc!L$90*ResCalc!L$62*ResCalc!L71*ResCalc!$J39*ResCalc!L87/'Conv Factors'!$B$17 -> 16.944334 | ... N23: ='2010 Fuel Share'!$T$73*ResCalc!N$90*ResCalc!N$62*ResCalc!N71*ResCalc!$J39*ResCalc!N87/'Conv Factors'!$B$17 -> 15.715899 | P23: 43.996536 | Q23: 23.543552 | R23: 23.595324 | S23: 21.13582 | T23: 20.364065 | U23: 19.576644 | V23: 18.837251 | W23: 18.111707 | X23: 17.557269 | Y23: 16.908445 | Z23: 16.284397
C24: West North Central | D24: =ResCalc!D$90*ResCalc!D$62*ResCalc!D72*ResCalc!T35*ResCalc!D$87/'Conv Factors'!$B$17 -> 0 | E24: =ResCalc!E$90*ResCalc!E$62*ResCalc!E72*ResCalc!U35*ResCalc!E$87/'Conv Factors'!$B$17 -> 0 | F24: =ResCalc!F$90*ResCalc!F$62*ResCalc!F72*ResCalc!V35*ResCalc!F$87/'Conv Factors'!$B$17 -> 0 | G24: =ResCalc!G$90*ResCalc!G$62*ResCalc!G72*ResCalc!W35*ResCalc!G$87/'Conv Factors'!$B$17 -> 0 | H24: =ResCalc!H$90*ResCalc!H$62*ResCalc!H72*ResCalc!X35*ResCalc!H$87/'Conv Factors'!$B$17 -> 0 | I24: =ResCalc!I$90*ResCalc!I$62*ResCalc!I72*ResCalc!Y35*ResCalc!I$87/'Conv Factors'!$B$17 -> 0 | J24: =ResCalc!J$90*ResCalc!J$62*ResCalc!J72*ResCalc!Z35*ResCalc!J$87/'Conv Factors'!$B$17 -> 0 | K24: =ResCalc!K$90*ResCalc!K$62*ResCalc!K72*ResCalc!AA35*ResCalc!K$87/'Conv Factors'!$B$17 -> 0 | ... N24: =ResCalc!N$90*ResCalc!N$62*ResCalc!N72*ResCalc!AD35*ResCalc!N$87/'Conv Factors'!$B$17 -> 0 | P24: 0 | Q24: 0 | R24: 0 | S24: 0 | T24: 0 | U24: 0 | V24: 0 | W24: 0 | X24: 0 | Y24: 0 | Z24: 0
B25: M | C25: Mountain | D25: =ResCalc!D$90*ResCalc!D$62*ResCalc!D73*ResCalc!T39*ResCalc!D$87/'Conv Factors'!$B$17*0.9 -> 0 | E25: =ResCalc!E$90*ResCalc!E$62*ResCalc!E73*ResCalc!U39*ResCalc!E$87/'Conv Factors'!$B$17*0.9 -> 0 | F25: =ResCalc!F$90*ResCalc!F$62*ResCalc!F73*ResCalc!V39*ResCalc!F$87/'Conv Factors'!$B$17*0.9 -> 0 | G25: =ResCalc!G$90*ResCalc!G$62*ResCalc!G73*ResCalc!W39*ResCalc!G$87/'Conv Factors'!$B$17*0.9 -> 0 | H25: =ResCalc!H$90*ResCalc!H$62*ResCalc!H73*ResCalc!X39*ResCalc!H$87/'Conv Factors'!$B$17*0.9 -> 0 | I25: =ResCalc!I$90*ResCalc!I$62*ResCalc!I73*ResCalc!Y39*ResCalc!I$87/'Conv Factors'!$B$17*0.9 -> 0 | J25: =ResCalc!J$90*ResCalc!J$62*ResCalc!J73*ResCalc!Z39*ResCalc!J$87/'Conv Factors'!$B$17*0.9 -> 0 | K25: =ResCalc!K$90*ResCalc!K$62*ResCalc!K73*ResCalc!AA39*ResCalc!K$87/'Conv Factors'!$B$17*0.9 -> 0 | ... N25: =ResCalc!N$90*ResCalc!N$62*ResCalc!N73*ResCalc!AD39*ResCalc!N$87/'Conv Factors'!$B$17*0.9 -> 0 | P25: 0 | Q25: 0 | R25: 0 | S25: 0 | T25: 0 | U25: 0 | V25: 0 | W25: 0 | X25: 0 | Y25: 0 | Z25: 0
B26: P | C26: Pacific | D26: =ResCalc!D$90*ResCalc!D$62*ResCalc!D74*ResCalc!T40*ResCalc!D$87/'Conv Factors'!$B$17*0.8 -> 0 | E26: =ResCalc!E$90*ResCalc!E$62*ResCalc!E74*ResCalc!U40*ResCalc!E$87/'Conv Factors'!$B$17*0.8 -> 0 | F26: =ResCalc!F$90*ResCalc!F$62*ResCalc!F74*ResCalc!V40*ResCalc!F$87/'Conv Factors'!$B$17*0.8 -> 0 | G26: =ResCalc!G$90*ResCalc!G$62*ResCalc!G74*ResCalc!W40*ResCalc!G$87/'Conv Factors'!$B$17*0.8 -> 0 | H26: =ResCalc!H$90*ResCalc!H$62*ResCalc!H74*ResCalc!X40*ResCalc!H$87/'Conv Factors'!$B$17*0.8 -> 0 | I26: =ResCalc!I$90*ResCalc!I$62*ResCalc!I74*ResCalc!Y40*ResCalc!I$87/'Conv Factors'!$B$17*0.8 -> 0 | J26: =ResCalc!J$90*ResCalc!J$62*ResCalc!J74*ResCalc!Z40*ResCalc!J$87/'Conv Factors'!$B$17*0.8 -> 0 | K26: =ResCalc!K$90*ResCalc!K$62*ResCalc!K74*ResCalc!AA40*ResCalc!K$87/'Conv Factors'!$B$17*0.8 -> 0 | ... N26: =ResCalc!N$90*ResCalc!N$62*ResCalc!N74*ResCalc!AD40*ResCalc!N$87/'Conv Factors'!$B$17*0.8 -> 0 | P26: 0 | Q26: 0 | R26: 0 | S26: 0 | T26: 0 | U26: 0 | V26: 0 | W26: 0 | X26: 0 | Y26: 0 | Z26: 0
C27: Total NYC | D27: =SUM(D19:D23) -> 154.20029 | E27: =SUM(E19:E23) -> 146.11398 | F27: =SUM(F19:F23) -> 146.0887 | G27: =SUM(G19:G23) -> 131.36842 | H27: =SUM(H19:H23) -> 127.44346 | I27: =SUM(I19:I23) -> 123.33844 | J27: =SUM(J19:J23) -> 119.04166 | K27: =SUM(K19:K23) -> 114.79865 | ... N27: =SUM(N19:N23) -> 102.87802 | P27: 160.13274 | Q27: 151.73532 | R27: 151.71175 | S27: 136.42187 | T27: 132.34588 | U27: 128.0829 | V27: 123.62039 | W27: 119.21376 | X27: 114.87178 | Y27: 110.77819 | Z27: 106.8313
A28: Heating demand can be changed through population (Pop:C4-N12) or heating degree days(ResCalc:J37-J45)
A30: Regional Refrigeration Demand million units/yr | I30: = # households * # refrigerators/household | U30: = # households * # refrigerators/household
B31: NE | C31: New England | D31: =USDemand!C$11*ResCalc!D66/ResCalc!D$75 -> 0 | E31: =USDemand!D$11*ResCalc!E66/ResCalc!E$75 -> 0 | F31: =USDemand!E$11*ResCalc!F66/ResCalc!F$75 -> 0 | G31: =USDemand!F$11*ResCalc!G66/ResCalc!G$75 -> 0 | H31: =USDemand!G$11*ResCalc!H66/ResCalc!H$75 -> 0 | I31: =USDemand!H$11*ResCalc!I66/ResCalc!I$75 -> 0 | J31: =USDemand!I$11*ResCalc!J66/ResCalc!J$75 -> 0 | K31: =USDemand!J$11*ResCalc!K66/ResCalc!K$75 -> 0 | ... N31: =USDemand!M$11*ResCalc!N66/ResCalc!N$75 -> 0 | P31: 0 | Q31: 0 | R31: 0 | S31: 0 | T31: 0 | U31: 0 | V31: 0 | W31: 0 | X31: 0 | Y31: 0 | Z31: 0
B32: MA | C32: Middle Atlantic | D32: =USDemand!C$11*ResCalc!D67/ResCalc!D$75 -> 52.671675 | E32: =USDemand!D$11*ResCalc!E67/ResCalc!E$75 -> 58.611466 | F32: =USDemand!E$11*ResCalc!F67/ResCalc!F$75 -> 65.191962 | G32: =USDemand!F$11*ResCalc!G67/ResCalc!G$75 -> 71.75296 | H32: =USDemand!G$11*ResCalc!H67/ResCalc!H$75 -> 78.085431 | I32: =USDemand!H$11*ResCalc!I67/ResCalc!I$75 -> 84.686724 | J32: =USDemand!I$11*ResCalc!J67/ResCalc!J$75 -> 91.367017 | K32: =USDemand!J$11*ResCalc!K67/ResCalc!K$75 -> 95.651077 | ... N32: =USDemand!M$11*ResCalc!N67/ResCalc!N$75 -> 108.06303 | P32: 52.671675 | Q32: 58.611466 | R32: 65.191962 | S32: 71.75296 | T32: 78.085431 | U32: 84.686724 | V32: 91.367017 | W32: 95.651077 | X32: 99.175115 | Y32: 103.52558 | Z32: 108.06303
B33: SA | C33: South Atlantic | D33: =USDemand!C$11*ResCalc!D68/ResCalc!D$75 -> 28.586632 | E33: =USDemand!D$11*ResCalc!E68/ResCalc!E$75 -> 31.800251 | F33: =USDemand!E$11*ResCalc!F68/ResCalc!F$75 -> 35.985129 | G33: =USDemand!F$11*ResCalc!G68/ResCalc!G$75 -> 39.19698 | H33: =USDemand!G$11*ResCalc!H68/ResCalc!H$75 -> 42.866515 | I33: =USDemand!H$11*ResCalc!I68/ResCalc!I$75 -> 46.709711 | J33: =USDemand!I$11*ResCalc!J68/ResCalc!J$75 -> 50.598892 | K33: =USDemand!J$11*ResCalc!K68/ResCalc!K$75 -> 53.179072 | ... N33: =USDemand!M$11*ResCalc!N68/ResCalc!N$75 -> 60.84687 | P33: 28.586632 | Q33: 31.800251 | R33: 35.985129 | S33: 39.19698 | T33: 42.866515 | U33: 46.709711 | V33: 50.598892 | W33: 53.179072 | X33: 55.447288 | Y33: 58.089341 | Z33: 60.84687
B34: ESC | C34: East South Central | D34: =USDemand!C$11*ResCalc!D69/ResCalc!D$75 -> 33.483803 | E34: =USDemand!D$11*ResCalc!E69/ResCalc!E$75 -> 36.40955 | F34: =USDemand!E$11*ResCalc!F69/ResCalc!F$75 -> 40.65989 | G34: =USDemand!F$11*ResCalc!G69/ResCalc!G$75 -> 44.384988 | H34: =USDemand!G$11*ResCalc!H69/ResCalc!H$75 -> 47.913956 | I34: =USDemand!H$11*ResCalc!I69/ResCalc!I$75 -> 51.559717 | J34: =USDemand!I$11*ResCalc!J69/ResCalc!J$75 -> 55.009927 | K34: =USDemand!J$11*ResCalc!K69/ResCalc!K$75 -> 56.963057 | ... N34: =USDemand!M$11*ResCalc!N69/ResCalc!N$75 -> 63.655036 | P34: 33.483803 | Q34: 36.40955 | R34: 40.65989 | S34: 44.384988 | T34: 47.913956 | U34: 51.559717 | V34: 55.009927 | W34: 56.963057 | X34: 59.103336 | Y34: 61.332936 | Z34: 63.655036
B35: ENC | C35: East North Central | D35: =USDemand!C$11*ResCalc!D70/ResCalc!D$75 -> 9.7985289 | E35: =USDemand!D$11*ResCalc!E70/ResCalc!E$75 -> 10.761422 | F35: =USDemand!E$11*ResCalc!F70/ResCalc!F$75 -> 11.733211 | G35: =USDemand!F$11*ResCalc!G70/ResCalc!G$75 -> 13.198205 | H35: =USDemand!G$11*ResCalc!H70/ResCalc!H$75 -> 14.235485 | I35: =USDemand!H$11*ResCalc!I70/ResCalc!I$75 -> 15.305953 | J35: =USDemand!I$11*ResCalc!J70/ResCalc!J$75 -> 16.312829 | K35: =USDemand!J$11*ResCalc!K70/ResCalc!K$75 -> 16.87421 | ... N35: =USDemand!M$11*ResCalc!N70/ResCalc!N$75 -> 19.725138 | P35: 9.7985289 | Q35: 10.761422 | R35: 11.733211 | S35: 13.198205 | T35: 14.235485 | U35: 15.305953 | V35: 16.312829 | W35: 16.87421 | X35: 18.037434 | Y35: 18.863378 | Z35: 19.725138 | AA35: 219.39124
B36: WSC | C36: West South Central | D36: =USDemand!C$11*ResCalc!D71/ResCalc!D$75 -> 47.180437 | E36: =USDemand!D$11*ResCalc!E71/ResCalc!E$75 -> 51.657075 | F36: =USDemand!E$11*ResCalc!F71/ResCalc!F$75 -> 57.834321 | G36: =USDemand!F$11*ResCalc!G71/ResCalc!G$75 -> 63.133318 | H36: =USDemand!G$11*ResCalc!H71/ResCalc!H$75 -> 67.987875 | I36: =USDemand!H$11*ResCalc!I71/ResCalc!I$75 -> 72.98751 | J36: =USDemand!I$11*ResCalc!J71/ResCalc!J$75 -> 78.165727 | K36: =USDemand!J$11*ResCalc!K71/ResCalc!K$75 -> 81.242895 | ... N36: =USDemand!M$11*ResCalc!N71/ResCalc!N$75 -> 92.273951 | P36: 47.180437 | Q36: 51.657075 | R36: 57.834321 | S36: 63.133318 | T36: 67.987875 | U36: 72.98751 | V36: 78.165727 | W36: 81.242895 | X36: 85.135386 | Y36: 88.630653 | Z36: 92.273951 | AA36: 208.35668
B37: WNC | C37: West North Central | D37: =USDemand!C$11*ResCalc!D72/ResCalc!D$75 -> 0 | E37: =USDemand!D$11*ResCalc!E72/ResCalc!E$75 -> 0 | F37: =USDemand!E$11*ResCalc!F72/ResCalc!F$75 -> 0 | G37: =USDemand!F$11*ResCalc!G72/ResCalc!G$75 -> 0 | H37: =USDemand!G$11*ResCalc!H72/ResCalc!H$75 -> 0 | I37: =USDemand!H$11*ResCalc!I72/ResCalc!I$75 -> 0 | J37: =USDemand!I$11*ResCalc!J72/ResCalc!J$75 -> 0 | K37: =USDemand!J$11*ResCalc!K72/ResCalc!K$75 -> 0 | ... N37: =USDemand!M$11*ResCalc!N72/ResCalc!N$75 -> 0 | P37: 0 | Q37: 0 | R37: 0 | S37: 0 | T37: 0 | U37: 0 | V37: 0 | W37: 0 | X37: 0 | Y37: 0 | Z37: 0
B38: M | C38: Mountain | D38: =USDemand!C$11*ResCalc!D73/ResCalc!D$75 -> 0 | E38: =USDemand!D$11*ResCalc!E73/ResCalc!E$75 -> 0 | F38: =USDemand!E$11*ResCalc!F73/ResCalc!F$75 -> 0 | G38: =USDemand!F$11*ResCalc!G73/ResCalc!G$75 -> 0 | H38: =USDemand!G$11*ResCalc!H73/ResCalc!H$75 -> 0 | I38: =USDemand!H$11*ResCalc!I73/ResCalc!I$75 -> 0 | J38: =USDemand!I$11*ResCalc!J73/ResCalc!J$75 -> 0 | K38: =USDemand!J$11*ResCalc!K73/ResCalc!K$75 -> 0 | ... N38: =USDemand!M$11*ResCalc!N73/ResCalc!N$75 -> 0 | P38: 0 | Q38: 0 | R38: 0 | S38: 0 | T38: 0 | U38: 0 | V38: 0 | W38: 0 | X38: 0 | Y38: 0 | Z38: 0
B39: P | C39: Pacific | D39: =USDemand!C$11*ResCalc!D74/ResCalc!D$75 -> 0 | E39: =USDemand!D$11*ResCalc!E74/ResCalc!E$75 -> 0 | F39: =USDemand!E$11*ResCalc!F74/ResCalc!F$75 -> 0 | G39: =USDemand!F$11*ResCalc!G74/ResCalc!G$75 -> 0 | H39: =USDemand!G$11*ResCalc!H74/ResCalc!H$75 -> 0 | I39: =USDemand!H$11*ResCalc!I74/ResCalc!I$75 -> 0 | J39: =USDemand!I$11*ResCalc!J74/ResCalc!J$75 -> 0 | K39: =USDemand!J$11*ResCalc!K74/ResCalc!K$75 -> 0 | ... N39: =USDemand!M$11*ResCalc!N74/ResCalc!N$75 -> 0 | P39: 0 | Q39: 0 | R39: 0 | S39: 0 | T39: 0 | U39: 0 | V39: 0 | W39: 0 | X39: 0 | Y39: 0 | Z39: 0
C40: Total US | D40: =SUM(D31:D39) -> 171.72108 | E40: =SUM(E31:E39) -> 189.23976 | F40: =SUM(F31:F39) -> 211.40451 | G40: =SUM(G31:G39) -> 231.66645 | H40: =SUM(H31:H39) -> 251.08926 | I40: =SUM(I31:I39) -> 271.24961 | J40: =SUM(J31:J39) -> 291.45439 | K40: =SUM(K31:K39) -> 303.91031 | ... N40: =SUM(N31:N39) -> 344.56402 | P40: 171.72108 | Q40: 189.23976 | R40: 211.40451 | S40: 231.66645 | T40: 251.08926 | U40: 271.24961 | V40: 291.45439 | W40: 303.91031 | X40: 316.89856 | Y40: 330.44189 | Z40: 344.56402
C41: Check From AEO data | D41: =USDemand!C254 -> 137.59496 | E41: =USDemand!D254 -> 142.74478 | F41: =USDemand!E254 -> 146.25145 | G41: =USDemand!F254 -> 154.08333 | H41: =USDemand!G254 -> 161.34395 | I41: =USDemand!H254 -> 168.5638 | J41: =USDemand!I254 -> 175.27843 | P41: 137.59496 | Q41: 142.74478 | R41: 146.25145 | S41: 154.08333 | T41: 161.34395 | U41: 168.5638 | V41: 175.27843
A42: Regional Freezer Demand million units/yr | I42: = # households * # freezers/household | U42: = # households * # freezers/household
B43: NE | C43: New England | D43: =USDemand!C$5*ResCalc!D66/ResCalc!D$75 -> 0 | E43: =USDemand!D$5*ResCalc!E66/ResCalc!E$75 -> 0 | F43: =USDemand!E$5*ResCalc!F66/ResCalc!F$75 -> 0 | G43: =USDemand!F$5*ResCalc!G66/ResCalc!G$75 -> 0 | H43: =USDemand!G$5*ResCalc!H66/ResCalc!H$75 -> 0 | I43: =USDemand!H$5*ResCalc!I66/ResCalc!I$75 -> 0 | J43: =USDemand!I$5*ResCalc!J66/ResCalc!J$75 -> 0 | K43: =USDemand!J$5*ResCalc!K66/ResCalc!K$75 -> 0 | ... N43: =USDemand!M$5*ResCalc!N66/ResCalc!N$75 -> 0 | P43: 0 | Q43: 0 | R43: 0 | S43: 0 | T43: 0 | U43: 0 | V43: 0 | W43: 0 | X43: 0 | Y43: 0 | Z43: 0
B44: MA | C44: Middle Atlantic | D44: =USDemand!C$5*ResCalc!D67/ResCalc!D$75 -> 15.597742 | E44: =USDemand!D$5*ResCalc!E67/ResCalc!E$75 -> 15.764637 | F44: =USDemand!E$5*ResCalc!F67/ResCalc!F$75 -> 16.613028 | G44: =USDemand!F$5*ResCalc!G67/ResCalc!G$75 -> 17.403036 | H44: =USDemand!G$5*ResCalc!H67/ResCalc!H$75 -> 17.234363 | I44: =USDemand!H$5*ResCalc!I67/ResCalc!I$75 -> 17.144148 | J44: =USDemand!I$5*ResCalc!J67/ResCalc!J$75 -> 17.172291 | K44: =USDemand!J$5*ResCalc!K67/ResCalc!K$75 -> 17.468235 | ... N44: =USDemand!M$5*ResCalc!N67/ResCalc!N$75 -> 18.104953 | P44: 15.597742 | Q44: 15.764637 | R44: 16.613028 | S44: 17.403036 | T44: 17.234363 | U44: 17.144148 | V44: 17.172291 | W44: 17.468235 | X44: 17.598767 | Y44: 17.850384 | Z44: 18.104953
B45: SA | C45: South Atlantic | D45: =USDemand!C$5*ResCalc!D68/ResCalc!D$75 -> 8.465402 | E45: =USDemand!D$5*ResCalc!E68/ResCalc!E$75 -> 8.5532652 | F45: =USDemand!E$5*ResCalc!F68/ResCalc!F$75 -> 9.1701788 | G45: =USDemand!F$5*ResCalc!G68/ResCalc!G$75 -> 9.5068758 | H45: =USDemand!G$5*ResCalc!H68/ResCalc!H$75 -> 9.4611389 | I45: =USDemand!H$5*ResCalc!I68/ResCalc!I$75 -> 9.4560065 | J45: =USDemand!I$5*ResCalc!J68/ResCalc!J$75 -> 9.5099842 | K45: =USDemand!J$5*ResCalc!K68/ResCalc!K$75 -> 9.7118042 | ... N45: =USDemand!M$5*ResCalc!N68/ResCalc!N$75 -> 10.194326 | P45: 8.465402 | Q45: 8.5532652 | R45: 9.1701788 | S45: 9.5068758 | T45: 9.4611389 | U45: 9.4560065 | V45: 9.5099842 | W45: 9.7118042 | X45: 9.8392012 | Y45: 10.016047 | Z45: 10.194326
B46: ESC | C46: East South Central | D46: =USDemand!C$5*ResCalc!D69/ResCalc!D$75 -> 9.9156089 | E46: =USDemand!D$5*ResCalc!E69/ResCalc!E$75 -> 9.7930214 | F46: =USDemand!E$5*ResCalc!F69/ResCalc!F$75 -> 10.361459 | G46: =USDemand!F$5*ResCalc!G69/ResCalc!G$75 -> 10.765181 | H46: =USDemand!G$5*ResCalc!H69/ResCalc!H$75 -> 10.575168 | I46: =USDemand!H$5*ResCalc!I69/ResCalc!I$75 -> 10.437851 | J46: =USDemand!I$5*ResCalc!J69/ResCalc!J$75 -> 10.339031 | K46: =USDemand!J$5*ResCalc!K69/ResCalc!K$75 -> 10.402853 | ... N46: =USDemand!M$5*ResCalc!N69/ResCalc!N$75 -> 10.664808 | P46: 9.9156089 | Q46: 9.7930214 | R46: 10.361459 | S46: 10.765181 | T46: 10.575168 | U46: 10.437851 | V46: 10.339031 | W46: 10.402853 | X46: 10.487972 | Y46: 10.575323 | Z46: 10.664808
B47: ENC | C47: East North Central | D47: =USDemand!C$5*ResCalc!D70/ResCalc!D$75 -> 2.901653 | E47: =USDemand!D$5*ResCalc!E70/ResCalc!E$75 -> 2.8944833 | F47: =USDemand!E$5*ResCalc!F70/ResCalc!F$75 -> 2.9900028 | G47: =USDemand!F$5*ResCalc!G70/ResCalc!G$75 -> 3.2011062 | H47: =USDemand!G$5*ResCalc!H70/ResCalc!H$75 -> 3.1419373 | I47: =USDemand!H$5*ResCalc!I70/ResCalc!I$75 -> 3.0985675 | J47: =USDemand!I$5*ResCalc!J70/ResCalc!J$75 -> 3.0659712 | K47: =USDemand!J$5*ResCalc!K70/ResCalc!K$75 -> 3.081645 | ... N47: =USDemand!M$5*ResCalc!N70/ResCalc!N$75 -> 3.304763 | P47: 2.901653 | Q47: 2.8944833 | R47: 2.9900028 | S47: 3.2011062 | T47: 3.1419373 | U47: 3.0985675 | V47: 3.0659712 | W47: 3.081645 | X47: 3.2007687 | Y47: 3.2525154 | Z47: 3.304763
B48: WSC | C48: West South Central | D48: =USDemand!C$5*ResCalc!D71/ResCalc!D$75 -> 13.971613 | E48: =USDemand!D$5*ResCalc!E71/ResCalc!E$75 -> 13.894125 | F48: =USDemand!E$5*ResCalc!F71/ResCalc!F$75 -> 14.738062 | G48: =USDemand!F$5*ResCalc!G71/ResCalc!G$75 -> 15.31242 | H48: =USDemand!G$5*ResCalc!H71/ResCalc!H$75 -> 15.005715 | I48: =USDemand!H$5*ResCalc!I71/ResCalc!I$75 -> 14.775736 | J48: =USDemand!I$5*ResCalc!J71/ResCalc!J$75 -> 14.691129 | K48: =USDemand!J$5*ResCalc!K71/ResCalc!K$75 -> 14.836947 | ... N48: =USDemand!M$5*ResCalc!N71/ResCalc!N$75 -> 15.45964 | P48: 13.971613 | Q48: 13.894125 | R48: 14.738062 | S48: 15.31242 | T48: 15.005715 | U48: 14.775736 | V48: 14.691129 | W48: 14.836947 | X48: 15.107397 | Y48: 15.282129 | Z48: 15.45964
B49: WNC | C49: West North Central | D49: =USDemand!C$5*ResCalc!D72/ResCalc!D$75 -> 0 | E49: =USDemand!D$5*ResCalc!E72/ResCalc!E$75 -> 0 | F49: =USDemand!E$5*ResCalc!F72/ResCalc!F$75 -> 0 | G49: =USDemand!F$5*ResCalc!G72/ResCalc!G$75 -> 0 | H49: =USDemand!G$5*ResCalc!H72/ResCalc!H$75 -> 0 | I49: =USDemand!H$5*ResCalc!I72/ResCalc!I$75 -> 0 | J49: =USDemand!I$5*ResCalc!J72/ResCalc!J$75 -> 0 | K49: =USDemand!J$5*ResCalc!K72/ResCalc!K$75 -> 0 | ... N49: =USDemand!M$5*ResCalc!N72/ResCalc!N$75 -> 0 | P49: 0 | Q49: 0 | R49: 0 | S49: 0 | T49: 0 | U49: 0 | V49: 0 | W49: 0 | X49: 0 | Y49: 0 | Z49: 0
B50: M | C50: Mountain | D50: =USDemand!C$5*ResCalc!D73/ResCalc!D$75 -> 0 | E50: =USDemand!D$5*ResCalc!E73/ResCalc!E$75 -> 0 | F50: =USDemand!E$5*ResCalc!F73/ResCalc!F$75 -> 0 | G50: =USDemand!F$5*ResCalc!G73/ResCalc!G$75 -> 0 | H50: =USDemand!G$5*ResCalc!H73/ResCalc!H$75 -> 0 | I50: =USDemand!H$5*ResCalc!I73/ResCalc!I$75 -> 0 | J50: =USDemand!I$5*ResCalc!J73/ResCalc!J$75 -> 0 | K50: =USDemand!J$5*ResCalc!K73/ResCalc!K$75 -> 0 | ... N50: =USDemand!M$5*ResCalc!N73/ResCalc!N$75 -> 0 | P50: 0 | Q50: 0 | R50: 0 | S50: 0 | T50: 0 | U50: 0 | V50: 0 | W50: 0 | X50: 0 | Y50: 0 | Z50: 0
B51: P | C51: Pacific | D51: =USDemand!C$5*ResCalc!D74/ResCalc!D$75 -> 0 | E51: =USDemand!D$5*ResCalc!E74/ResCalc!E$75 -> 0 | F51: =USDemand!E$5*ResCalc!F74/ResCalc!F$75 -> 0 | G51: =USDemand!F$5*ResCalc!G74/ResCalc!G$75 -> 0 | H51: =USDemand!G$5*ResCalc!H74/ResCalc!H$75 -> 0 | I51: =USDemand!H$5*ResCalc!I74/ResCalc!I$75 -> 0 | J51: =USDemand!I$5*ResCalc!J74/ResCalc!J$75 -> 0 | K51: =USDemand!J$5*ResCalc!K74/ResCalc!K$75 -> 0 | ... N51: =USDemand!M$5*ResCalc!N74/ResCalc!N$75 -> 0 | P51: 0 | Q51: 0 | R51: 0 | S51: 0 | T51: 0 | U51: 0 | V51: 0 | W51: 0 | X51: 0 | Y51: 0 | Z51: 0
C52: Total US | D52: =SUM(D43:D51) -> 50.85202 | E52: =SUM(E43:E51) -> 50.899532 | F52: =SUM(F43:F51) -> 53.87273 | G52: =SUM(G43:G51) -> 56.188619 | H52: =SUM(H43:H51) -> 55.418323 | I52: =SUM(I43:I51) -> 54.91231 | J52: =SUM(J43:J51) -> 54.778406 | K52: =SUM(K43:K51) -> 55.501484 | ... N52: =SUM(N43:N51) -> 57.72849 | P52: 50.85202 | Q52: 50.899532 | R52: 53.87273 | S52: 56.188619 | T52: 55.418323 | U52: 54.91231 | V52: 54.778406 | W52: 55.501484 | X52: 56.234106 | Y52: 56.976399 | Z52: 57.72849
C53: Check From AEO data | D53: =USDemand!C255 -> 38.425449 | E53: =USDemand!D255 -> 38.009281 | F53: =USDemand!E255 -> 38.799267 | G53: =USDemand!F255 -> 40.689968 | H53: =USDemand!G255 -> 42.401108 | I53: =USDemand!H255 -> 44.059566 | J53: =USDemand!I255 -> 45.560253 | P53: 38.425449 | Q53: 38.009281 | R53: 38.799267 | S53: 40.689968 | T53: 42.401108 | U53: 44.059566 | V53: 45.560253
A54: Regional Lighting Demand billion lumens/yr | I54: = Nat'l lighting demand * Regional % of total households | U54: = Nat'l lighting demand * Regional % of total households
C55: New England | D55: =USDemand!C$7*ResCalc!D66/ResCalc!D$75 -> 0 | E55: =USDemand!D$7*ResCalc!E66/ResCalc!E$75 -> 0 | F55: =USDemand!E$7*ResCalc!F66/ResCalc!F$75 -> 0 | G55: =USDemand!F$7*ResCalc!G66/ResCalc!G$75 -> 0 | H55: =USDemand!G$7*ResCalc!H66/ResCalc!H$75 -> 0 | I55: =USDemand!H$7*ResCalc!I66/ResCalc!I$75 -> 0 | J55: =USDemand!I$7*ResCalc!J66/ResCalc!J$75 -> 0 | K55: =USDemand!J$7*ResCalc!K66/ResCalc!K$75 -> 0 | ... N55: =USDemand!M$7*ResCalc!N66/ResCalc!N$75 -> 0 | P55: 0 | Q55: 0 | R55: 0 | S55: 0 | T55: 0 | U55: 0 | V55: 0 | W55: 0 | X55: 0 | Y55: 0 | Z55: 0
C56: Brooklyn | D56: ='2010 Fuel Share'!Q49*DmdCalc!C$7*ResCalc!D67/ResCalc!D$75 -> 2.7997869 | E56: =D56 -> 2.7997869 | F56: ='2010 Fuel Share'!$Q$49*DmdCalc!E$7*ResCalc!F67/ResCalc!F$75 -> 2.814824 | G56: ='2010 Fuel Share'!$Q$49*DmdCalc!F$7*ResCalc!G67/ResCalc!G$75 -> 2.9669516 | H56: ='2010 Fuel Share'!$Q$49*DmdCalc!G$7*ResCalc!H67/ResCalc!H$75 -> 3.0987861 | I56: ='2010 Fuel Share'!$Q$49*DmdCalc!H$7*ResCalc!I67/ResCalc!I$75 -> 3.2272391 | J56: ='2010 Fuel Share'!$Q$49*DmdCalc!I$7*ResCalc!J67/ResCalc!J$75 -> 3.33469 | K56: ='2010 Fuel Share'!$Q$49*DmdCalc!J$7*ResCalc!K67/ResCalc!K$75 -> 3.4437033 | L56: ='2010 Fuel Share'!$Q$49*DmdCalc!K$7*ResCalc!L67/ResCalc!L$75 -> 3.5856144 | M56: ='2010 Fuel Share'!$Q$49*DmdCalc!L$7*ResCalc!M67/ResCalc!M$75 -> 3.7106607 | N56: ='2010 Fuel Share'!$Q$49*DmdCalc!M$7*ResCalc!N67/ResCalc!N$75 -> 3.8389176 | P56: 7.0373899 | Q56: 7.0373899 | R56: 7.2078728 | S56: 7.4575657 | T56: 7.7889377 | U56: 8.1118099 | V56: 8.3818928 | W56: 8.6559025 | X56: 9.0126024 | Y56: 9.3269118 | Z56: 9.6492914
C57: Bronx | D57: ='2010 Fuel Share'!R49*DmdCalc!C$7*ResCalc!D68/ResCalc!D$75 -> 1.614585 | E57: =D57 -> 1.614585 | F57: ='2010 Fuel Share'!$R$49*DmdCalc!E$7*ResCalc!F68/ResCalc!F$75 -> 1.6509364 | G57: ='2010 Fuel Share'!$R$49*DmdCalc!F$7*ResCalc!G68/ResCalc!G$75 -> 1.7221593 | H57: ='2010 Fuel Share'!$R$49*DmdCalc!G$7*ResCalc!H68/ResCalc!H$75 -> 1.807548 | I57: ='2010 Fuel Share'!$R$49*DmdCalc!H$7*ResCalc!I68/ResCalc!I$75 -> 1.891355 | J57: ='2010 Fuel Share'!$R$49*DmdCalc!I$7*ResCalc!J68/ResCalc!J$75 -> 1.9622625 | K57: ='2010 Fuel Share'!$R$49*DmdCalc!J$7*ResCalc!K68/ResCalc!K$75 -> 2.0343548 | L57: ='2010 Fuel Share'!$R$49*DmdCalc!K$7*ResCalc!L68/ResCalc!L$75 -> 2.1300572 | M57: ='2010 Fuel Share'!$R$49*DmdCalc!L$7*ResCalc!M68/ResCalc!M$75 -> 2.212331 | N57: ='2010 Fuel Share'!$R$49*DmdCalc!M$7*ResCalc!N68/ResCalc!N$75 -> 2.2967831 | P57: 4.0583317 | Q57: 4.0583317 | R57: 4.2275252 | S57: 4.3287246 | T57: 4.543353 | U57: 4.7540056 | V57: 4.9322347 | W57: 5.1134419 | X57: 5.3539941 | Y57: 5.560793 | Z57: 5.7730673
C58: Manhattan | D58: ='2010 Fuel Share'!S49*DmdCalc!C$7*ResCalc!D69/ResCalc!D$75 -> 2.7047091 | E58: =D58 -> 2.7047091 | F58: ='2010 Fuel Share'!$S$49*DmdCalc!E$7*ResCalc!F69/ResCalc!F$75 -> 2.6678495 | G58: ='2010 Fuel Share'!$S$49*DmdCalc!F$7*ResCalc!G69/ResCalc!G$75 -> 2.7889753 | H58: ='2010 Fuel Share'!$S$49*DmdCalc!G$7*ResCalc!H69/ResCalc!H$75 -> 2.8894923 | I58: ='2010 Fuel Share'!$S$49*DmdCalc!H$7*ResCalc!I69/ResCalc!I$75 -> 2.9858243 | J58: ='2010 Fuel Share'!$S$49*DmdCalc!I$7*ResCalc!J69/ResCalc!J$75 -> 3.0510197 | K58: ='2010 Fuel Share'!$S$49*DmdCalc!J$7*ResCalc!K69/ResCalc!K$75 -> 3.1164996 | L58: ='2010 Fuel Share'!$S$49*DmdCalc!K$7*ResCalc!L69/ResCalc!L$75 -> 3.2472131 | M58: ='2010 Fuel Share'!$S$49*DmdCalc!L$7*ResCalc!M69/ResCalc!M$75 -> 3.3406828 | N58: ='2010 Fuel Share'!$S$49*DmdCalc!M$7*ResCalc!N69/ResCalc!N$75 -> 3.4363893 | P58: 6.7984074 | Q58: 6.7984074 | R58: 6.8315174 | S58: 7.0102143 | T58: 7.2628684 | U58: 7.5050031 | V58: 7.6688747 | W58: 7.8334612 | X58: 8.1620156 | Y58: 8.396956 | Z58: 8.6375185
C59: Staten Island | D59: ='2010 Fuel Share'!U49*DmdCalc!C$7*ResCalc!D70/ResCalc!D$75 -> 0.54480649 | E59: =D59 -> 0.54480649 | F59: ='2010 Fuel Share'!$U$49*DmdCalc!E$7*ResCalc!F70/ResCalc!F$75 -> 0.52991671 | G59: ='2010 Fuel Share'!$U$49*DmdCalc!F$7*ResCalc!G70/ResCalc!G$75 -> 0.57084613 | H59: ='2010 Fuel Share'!$U$49*DmdCalc!G$7*ResCalc!H70/ResCalc!H$75 -> 0.59091826 | I59: ='2010 Fuel Share'!$U$49*DmdCalc!H$7*ResCalc!I70/ResCalc!I$75 -> 0.61011222 | J59: ='2010 Fuel Share'!$U$49*DmdCalc!I$7*ResCalc!J70/ResCalc!J$75 -> 0.62277168 | K59: ='2010 Fuel Share'!$U$49*DmdCalc!J$7*ResCalc!K70/ResCalc!K$75 -> 0.63546679 | L59: ='2010 Fuel Share'!$U$49*DmdCalc!K$7*ResCalc!L70/ResCalc!L$75 -> 0.68213319 | M59: ='2010 Fuel Share'!$U$49*DmdCalc!L$7*ResCalc!M70/ResCalc!M$75 -> 0.70722333 | N59: ='2010 Fuel Share'!$U$49*DmdCalc!M$7*ResCalc!N70/ResCalc!N$75 -> 0.73296842 | P59: 1.3693955 | Q59: 1.3693955 | R59: 1.3569488 | S59: 1.4348473 | T59: 1.4852995 | U59: 1.5335444 | V59: 1.5653645 | W59: 1.5972742 | X59: 1.7145723 | Y59: 1.7776375 | Z59: 1.842349
C60: Queens | D60: ='2010 Fuel Share'!T49*DmdCalc!C$7*ResCalc!D71/ResCalc!D$75 -> 1.4312412 | E60: =D60 -> 1.4312412 | F60: ='2010 Fuel Share'!$T$49*DmdCalc!E$7*ResCalc!F71/ResCalc!F$75 -> 1.4251017 | G60: ='2010 Fuel Share'!$T$49*DmdCalc!F$7*ResCalc!G71/ResCalc!G$75 -> 1.4898148 | H60: ='2010 Fuel Share'!$T$49*DmdCalc!G$7*ResCalc!H71/ResCalc!H$75 -> 1.5397708 | I60: ='2010 Fuel Share'!$T$49*DmdCalc!H$7*ResCalc!I71/ResCalc!I$75 -> 1.5873305 | J60: ='2010 Fuel Share'!$T$49*DmdCalc!I$7*ResCalc!J71/ResCalc!J$75 -> 1.6281163 | K60: ='2010 Fuel Share'!$T$49*DmdCalc!J$7*ResCalc!K71/ResCalc!K$75 -> 1.6692611 | L60: ='2010 Fuel Share'!$T$49*DmdCalc!K$7*ResCalc!L71/ResCalc!L$75 -> 1.7566046 | M60: ='2010 Fuel Share'!$T$49*DmdCalc!L$7*ResCalc!M71/ResCalc!M$75 -> 1.8129697 | N60: ='2010 Fuel Share'!$T$49*DmdCalc!M$7*ResCalc!N71/ResCalc!N$75 -> 1.8707417 | P60: 3.5974889 | Q60: 3.5974889 | R60: 3.6492341 | S60: 3.7447162 | T60: 3.8702829 | U60: 3.9898264 | V60: 4.0923432 | W60: 4.1957626 | X60: 4.4153042 | Y60: 4.5569805 | Z60: 4.7021929
C61: West North Central | D61: =USDemand!C$7*ResCalc!D72/ResCalc!D$75 -> 0 | E61: =USDemand!D$7*ResCalc!E72/ResCalc!E$75 -> 0 | F61: =USDemand!E$7*ResCalc!F72/ResCalc!F$75 -> 0 | G61: =USDemand!F$7*ResCalc!G72/ResCalc!G$75 -> 0 | H61: =USDemand!G$7*ResCalc!H72/ResCalc!H$75 -> 0 | I61: =USDemand!H$7*ResCalc!I72/ResCalc!I$75 -> 0 | J61: =USDemand!I$7*ResCalc!J72/ResCalc!J$75 -> 0 | K61: =USDemand!J$7*ResCalc!K72/ResCalc!K$75 -> 0 | ... N61: =USDemand!M$7*ResCalc!N72/ResCalc!N$75 -> 0 | P61: 0 | Q61: 0 | R61: 0 | S61: 0 | T61: 0 | U61: 0 | V61: 0 | W61: 0 | X61: 0 | Y61: 0 | Z61: 0
C62: Mountain | D62: =USDemand!C$7*ResCalc!D73/ResCalc!D$75 -> 0 | E62: =USDemand!D$7*ResCalc!E73/ResCalc!E$75 -> 0 | F62: =USDemand!E$7*ResCalc!F73/ResCalc!F$75 -> 0 | G62: =USDemand!F$7*ResCalc!G73/ResCalc!G$75 -> 0 | H62: =USDemand!G$7*ResCalc!H73/ResCalc!H$75 -> 0 | I62: =USDemand!H$7*ResCalc!I73/ResCalc!I$75 -> 0 | J62: =USDemand!I$7*ResCalc!J73/ResCalc!J$75 -> 0 | K62: =USDemand!J$7*ResCalc!K73/ResCalc!K$75 -> 0 | ... N62: =USDemand!M$7*ResCalc!N73/ResCalc!N$75 -> 0 | P62: 0 | Q62: 0 | R62: 0 | S62: 0 | T62: 0 | U62: 0 | V62: 0 | W62: 0 | X62: 0 | Y62: 0 | Z62: 0
C63: Pacific | D63: =USDemand!C$7*ResCalc!D74/ResCalc!D$75 -> 0 | E63: =USDemand!D$7*ResCalc!E74/ResCalc!E$75 -> 0 | F63: =USDemand!E$7*ResCalc!F74/ResCalc!F$75 -> 0 | G63: =USDemand!F$7*ResCalc!G74/ResCalc!G$75 -> 0 | H63: =USDemand!G$7*ResCalc!H74/ResCalc!H$75 -> 0 | I63: =USDemand!H$7*ResCalc!I74/ResCalc!I$75 -> 0 | J63: =USDemand!I$7*ResCalc!J74/ResCalc!J$75 -> 0 | K63: =USDemand!J$7*ResCalc!K74/ResCalc!K$75 -> 0 | ... N63: =USDemand!M$7*ResCalc!N74/ResCalc!N$75 -> 0 | P63: 0 | Q63: 0 | R63: 0 | S63: 0 | T63: 0 | U63: 0 | V63: 0 | W63: 0 | X63: 0 | Y63: 0 | Z63: 0
C64: Total NYC | D64: =SUM(D55:D60) -> 9.0951287 | E64: =SUM(E56:E60) -> 9.0951287 | F64: =SUM(F55:F60) -> 9.0886283 | G64: =SUM(G55:G60) -> 9.5387471 | H64: =SUM(H55:H60) -> 9.9265155 | I64: =SUM(I55:I60) -> 10.301861 | J64: =SUM(J55:J60) -> 10.59886 | K64: =SUM(K55:K60) -> 10.899286 | L64: =SUM(L55:L60) -> 11.401622 | M64: =SUM(M55:M60) -> 11.783867 | N64: =SUM(N55:N60) -> 12.1758 | P64: 22.861013 | Q64: 22.861013 | R64: 23.273098 | S64: 23.976068 | T64: 24.950741 | U64: 25.894189 | V64: 26.64071 | W64: 27.395842 | X64: 28.658489 | Y64: 29.619279 | Z64: 30.604419
A66: Regional Miscellaneous Electric Demand PJ/a | I66: = Nat'l misc electric demand * Regional % of total households | U66: = Nat'l misc electric demand * Regional % of total households
B67: NE | C67: New England | D67: =ResCalc!D$136*ResCalc!D66 -> 0 | E67: =ResCalc!E$136*ResCalc!E66 -> 0 | F67: =ResCalc!F$136*ResCalc!F66 -> 0 | G67: =ResCalc!G$136*ResCalc!G66 -> 0 | H67: =ResCalc!H$136*ResCalc!H66 -> 0 | I67: =ResCalc!I$136*ResCalc!I66 -> 0 | J67: =ResCalc!J$136*ResCalc!J66 -> 0 | K67: =ResCalc!K$136*ResCalc!K66 -> 0 | ... N67: =ResCalc!N$136*ResCalc!N66 -> 0 | P67: 0 | Q67: 0 | R67: 0 | S67: 0 | T67: 0 | U67: 0 | V67: 0 | W67: 0 | X67: 0 | Y67: 0 | Z67: 0
C68: Brooklyn | D68: =ResCalc!D$136*ResCalc!D67 -> 8.1509592 | E68: ='2010 Fuel Share'!$Q$55*ResCalc!E$136*ResCalc!E67 -> 9.6248377 | F68: ='2010 Fuel Share'!$Q$55*ResCalc!F$136*ResCalc!F67 -> 9.583034 | G68: ='2010 Fuel Share'!$Q$55*ResCalc!G$136*ResCalc!G67 -> 9.3597064 | H68: ='2010 Fuel Share'!$Q$55*ResCalc!H$136*ResCalc!H67 -> 9.2142061 | I68: ='2010 Fuel Share'!$Q$55*ResCalc!I$136*ResCalc!I67 -> 8.8864886 | J68: ='2010 Fuel Share'!$Q$55*ResCalc!J$136*ResCalc!J67 -> 8.7595237 | K68: ='2010 Fuel Share'!$Q$55*ResCalc!K$136*ResCalc!K67 -> 8.6334373 | L68: ='2010 Fuel Share'!$Q$55*ResCalc!L$136*ResCalc!L67 -> 8.4275129 | ... N68: ='2010 Fuel Share'!$Q$55*ResCalc!N$136*ResCalc!N67 -> 8.1391585 | P68: 20.487801 | Q68: 24.192461 | R68: 24.588712 | S68: 24.015685 | T68: 23.642352 | U68: 22.801475 | V68: 22.475701 | W68: 22.152181 | X68: 21.623808 | Y68: 21.25103 | Z68: 20.883932
C69: Bronx | D69: =ResCalc!D$136*ResCalc!D68 -> 4.4237907 | E69: ='2010 Fuel Share'!$R$55*ResCalc!E$136*ResCalc!E68 -> 4.8441161 | F69: ='2010 Fuel Share'!$R$55*ResCalc!F$136*ResCalc!F68 -> 4.9068774 | G69: ='2010 Fuel Share'!$R$55*ResCalc!G$136*ResCalc!G68 -> 4.742946 | H69: ='2010 Fuel Share'!$R$55*ResCalc!H$136*ResCalc!H68 -> 4.6922296 | I69: ='2010 Fuel Share'!$R$55*ResCalc!I$136*ResCalc!I68 -> 4.5466884 | J69: ='2010 Fuel Share'!$R$55*ResCalc!J$136*ResCalc!J68 -> 4.4999243 | K69: ='2010 Fuel Share'!$R$55*ResCalc!K$136*ResCalc!K68 -> 4.4525397 | L69: ='2010 Fuel Share'!$R$55*ResCalc!L$136*ResCalc!L68 -> 4.3706918 | ... N69: ='2010 Fuel Share'!$R$55*ResCalc!N$136*ResCalc!N68 -> 4.251222 | P69: 11.119396 | Q69: 12.175903 | R69: 12.590355 | S69: 12.16973 | T69: 12.039599 | U69: 11.666161 | V69: 11.546171 | W69: 11.424588 | X69: 11.214578 | Y69: 11.061192 | Z69: 10.908036
C70: Manhattan | D70: =ResCalc!D$136*ResCalc!D69 -> 5.1816297 | E70: ='2010 Fuel Share'!$S$55*ResCalc!E$136*ResCalc!E69 -> 6.7282357 | F70: ='2010 Fuel Share'!$S$55*ResCalc!F$136*ResCalc!F69 -> 6.7258973 | G70: ='2010 Fuel Share'!$S$55*ResCalc!G$136*ResCalc!G69 -> 6.5152872 | H70: ='2010 Fuel Share'!$S$55*ResCalc!H$136*ResCalc!H69 -> 6.362459 | I70: ='2010 Fuel Share'!$S$55*ResCalc!I$136*ResCalc!I69 -> 6.0883614 | J70: ='2010 Fuel Share'!$S$55*ResCalc!J$136*ResCalc!J69 -> 5.9348147 | K70: ='2010 Fuel Share'!$S$55*ResCalc!K$136*ResCalc!K69 -> 5.785784 | L70: ='2010 Fuel Share'!$S$55*ResCalc!L$136*ResCalc!L69 -> 5.6517607 | ... N70: ='2010 Fuel Share'!$S$55*ResCalc!N$136*ResCalc!N69 -> 5.395233 | P70: 13.024258 | Q70: 16.911722 | R70: 17.257703 | S70: 16.717307 | T70: 16.325172 | U70: 15.621876 | V70: 15.227897 | W70: 14.845505 | X70: 14.50162 | Y70: 14.167758 | Z70: 13.843406
C71: Staten Island | D71: =ResCalc!D$136*ResCalc!D70 -> 1.5163256 | E71: ='2010 Fuel Share'!$U$55*ResCalc!E$136*ResCalc!E70 -> 2.4575994 | F71: ='2010 Fuel Share'!$U$55*ResCalc!F$136*ResCalc!F70 -> 2.3985924 | G71: ='2010 Fuel Share'!$U$55*ResCalc!G$136*ResCalc!G70 -> 2.3942411 | H71: ='2010 Fuel Share'!$U$55*ResCalc!H$136*ResCalc!H70 -> 2.3360965 | I71: ='2010 Fuel Share'!$U$55*ResCalc!I$136*ResCalc!I70 -> 2.2336022 | J71: ='2010 Fuel Share'!$U$55*ResCalc!J$136*ResCalc!J70 -> 2.1749583 | K71: ='2010 Fuel Share'!$U$55*ResCalc!K$136*ResCalc!K70 -> 2.1181072 | L71: ='2010 Fuel Share'!$U$55*ResCalc!L$136*ResCalc!L70 -> 2.1315822 | ... N71: ='2010 Fuel Share'!$U$55*ResCalc!N$136*ResCalc!N70 -> 2.0661081 | P71: 3.8113523 | Q71: 6.1772862 | R71: 6.1544493 | S71: 6.1432847 | T71: 5.9940939 | U71: 5.7311079 | V71: 5.5806358 | W71: 5.4347639 | X71: 5.4693389 | Y71: 5.3849586 | Z71: 5.3013416
C72: Queens | D72: =ResCalc!D$136*ResCalc!D71 -> 7.3011883 | E72: ='2010 Fuel Share'!$T$55*ResCalc!E$136*ResCalc!E71 -> 4.9241949 | F72: ='2010 Fuel Share'!$T$55*ResCalc!F$136*ResCalc!F71 -> 4.9350233 | G72: ='2010 Fuel Share'!$T$55*ResCalc!G$136*ResCalc!G71 -> 4.7805252 | H72: ='2010 Fuel Share'!$T$55*ResCalc!H$136*ResCalc!H71 -> 4.6570829 | I72: ='2010 Fuel Share'!$T$55*ResCalc!I$136*ResCalc!I71 -> 4.4458826 | J72: ='2010 Fuel Share'!$T$55*ResCalc!J$136*ResCalc!J71 -> 4.3501277 | K72: ='2010 Fuel Share'!$T$55*ResCalc!K$136*ResCalc!K71 -> 4.256708 | L72: ='2010 Fuel Share'!$T$55*ResCalc!L$136*ResCalc!L71 -> 4.199537 | ... N72: ='2010 Fuel Share'!$T$55*ResCalc!N$136*ResCalc!N71 -> 4.0343734 | P72: 18.351864 | Q72: 12.377185 | R72: 12.662573 | S72: 12.266153 | T72: 11.949417 | U72: 11.407507 | V72: 11.161814 | W72: 10.922112 | X72: 10.775419 | Y72: 10.561141 | Z72: 10.351633
C73: West North Central | D73: =ResCalc!D$136*ResCalc!D72 -> 0 | E73: =ResCalc!E$136*ResCalc!E72 -> 0 | F73: =ResCalc!F$136*ResCalc!F72 -> 0 | G73: =ResCalc!G$136*ResCalc!G72 -> 0 | H73: =ResCalc!H$136*ResCalc!H72 -> 0 | I73: =ResCalc!I$136*ResCalc!I72 -> 0 | J73: =ResCalc!J$136*ResCalc!J72 -> 0 | K73: =ResCalc!K$136*ResCalc!K72 -> 0 | ... N73: =ResCalc!N$136*ResCalc!N72 -> 0 | P73: 0 | Q73: 0 | R73: 0 | S73: 0 | T73: 0 | U73: 0 | V73: 0 | W73: 0 | X73: 0 | Y73: 0 | Z73: 0
C74: Mountain | D74: =ResCalc!D$136*ResCalc!D73 -> 0 | E74: =ResCalc!E$136*ResCalc!E73 -> 0 | F74: =ResCalc!F$136*ResCalc!F73 -> 0 | G74: =ResCalc!G$136*ResCalc!G73 -> 0 | H74: =ResCalc!H$136*ResCalc!H73 -> 0 | I74: =ResCalc!I$136*ResCalc!I73 -> 0 | J74: =ResCalc!J$136*ResCalc!J73 -> 0 | K74: =ResCalc!K$136*ResCalc!K73 -> 0 | ... N74: =ResCalc!N$136*ResCalc!N73 -> 0 | P74: 0 | Q74: 0 | R74: 0 | S74: 0 | T74: 0 | U74: 0 | V74: 0 | W74: 0 | X74: 0 | Y74: 0 | Z74: 0
C75: Pacific | D75: =ResCalc!D$136*ResCalc!D74*0.7 -> 0 | E75: =ResCalc!E$136*ResCalc!E74*0.7 -> 0 | F75: =ResCalc!F$136*ResCalc!F74*0.7 -> 0 | G75: =ResCalc!G$136*ResCalc!G74*0.7 -> 0 | H75: =ResCalc!H$136*ResCalc!H74*0.7 -> 0 | I75: =ResCalc!I$136*ResCalc!I74*0.7 -> 0 | J75: =ResCalc!J$136*ResCalc!J74*0.7 -> 0 | K75: =ResCalc!K$136*ResCalc!K74*0.7 -> 0 | ... N75: =ResCalc!N$136*ResCalc!N74*0.7 -> 0 | P75: 0 | Q75: 0 | R75: 0 | S75: 0 | T75: 0 | U75: 0 | V75: 0 | W75: 0 | X75: 0 | Y75: 0 | Z75: 0
C76: Total NYC | D76: =SUM(D68:D72) -> 26.573893 | E76: =SUM(E68:E72) -> 28.578984 | F76: =SUM(F68:F72) -> 28.549424 | G76: =SUM(G68:G72) -> 27.792706 | H76: =SUM(H68:H72) -> 27.262074 | I76: =SUM(I68:I72) -> 26.201023 | J76: =SUM(J68:J72) -> 25.719349 | K76: =SUM(K68:K72) -> 25.246576 | ... N76: =SUM(N68:N72) -> 23.886095 | P76: 66.794671 | Q76: 71.834556 | R76: 73.253792 | S76: 71.312159 | T76: 69.950634 | U76: 67.228127 | V76: 65.992218 | W76: 64.77915 | X76: 63.584765 | Y76: 62.426079 | Z76: 61.288348
A78: Regional Miscellaneous Gas Demand PJ/a | I78: = Nat'l misc NG demand * Regional % of total households | U78: = Nat'l misc NG demand * Regional % of total households
C79: New England | D79: =ResCalc!D$137*ResCalc!D66 -> 0 | E79: =ResCalc!E$137*ResCalc!E66 -> 0 | F79: =ResCalc!F$137*ResCalc!F66 -> #REF! | G79: =ResCalc!G$137*ResCalc!G66 -> #REF! | H79: =ResCalc!H$137*ResCalc!H66 -> #REF! | I79: =ResCalc!I$137*ResCalc!I66 -> #REF! | J79: =ResCalc!J$137*ResCalc!J66 -> #REF! | K79: =ResCalc!K$137*ResCalc!K66 -> #REF! | ... N79: =ResCalc!N$137*ResCalc!N66 -> #REF! | P79: 0 | Q79: 0 | R79: 0 | S79: 0 | T79: 0 | U79: 0 | V79: 0 | W79: 0 | X79: 0 | Y79: 0 | Z79: 0
C80: Brooklyn | D80: =ResCalc!D$137*ResCalc!D67 -> 0.76256327 | E80: ='2010 Fuel Share'!$Q$61*ResCalc!E$137*ResCalc!E67 -> 0.65454183 | F80: ='2010 Fuel Share'!$Q$61*ResCalc!F$137*ResCalc!F67 -> #REF! | G80: ='2010 Fuel Share'!$Q$61*ResCalc!G$137*ResCalc!G67 -> #REF! | H80: ='2010 Fuel Share'!$Q$61*ResCalc!H$137*ResCalc!H67 -> #REF! | I80: ='2010 Fuel Share'!$Q$61*ResCalc!I$137*ResCalc!I67 -> #REF! | J80: ='2010 Fuel Share'!$Q$61*ResCalc!J$137*ResCalc!J67 -> #REF! | K80: ='2010 Fuel Share'!$Q$61*ResCalc!K$137*ResCalc!K67 -> #REF! | L80: ='2010 Fuel Share'!$Q$61*ResCalc!L$137*ResCalc!L67 -> #REF! | ... N80: ='2010 Fuel Share'!$Q$61*ResCalc!N$137*ResCalc!N67 -> #REF! | P80: 0.76256327 | Q80: 0.65454183 | R80: 0.9162367 | S80: 0.91112268 | T80: 0.90350501 | U80: 0.89236308 | V80: 0.87424001 | W80: 0.85455323 | X80: 0.84972254 | Y80: 0.85064288 | Z80: 0.85153379
C81: Bronx | D81: =ResCalc!D$137*ResCalc!D68 -> 0.41386789 | E81: ='2010 Fuel Share'!$R$61*ResCalc!E$137*ResCalc!E68 -> 0.49073984 | F81: ='2010 Fuel Share'!$R$61*ResCalc!F$137*ResCalc!F68 -> #REF! | G81: ='2010 Fuel Share'!$R$61*ResCalc!G$137*ResCalc!G68 -> #REF! | H81: ='2010 Fuel Share'!$R$61*ResCalc!H$137*ResCalc!H68 -> #REF! | I81: ='2010 Fuel Share'!$R$61*ResCalc!I$137*ResCalc!I68 -> #REF! | J81: ='2010 Fuel Share'!$R$61*ResCalc!J$137*ResCalc!J68 -> #REF! | K81: ='2010 Fuel Share'!$R$61*ResCalc!K$137*ResCalc!K68 -> #REF! | L81: ='2010 Fuel Share'!$R$61*ResCalc!L$137*ResCalc!L68 -> #REF! | ... N81: ='2010 Fuel Share'!$R$61*ResCalc!N$137*ResCalc!N68 -> #REF! | P81: 0.41386789 | Q81: 0.49073984 | R81: 0.69888006 | S81: 0.68778959 | T81: 0.68540092 | U81: 0.68014168 | V81: 0.669034 | W81: 0.6565321 | X81: 0.65647877 | Y81: 0.65957168 | Z81: 0.66256571
C82: Manhattan | D82: =ResCalc!D$137*ResCalc!D69 -> 0.48476754 | E82: ='2010 Fuel Share'!$S$61*ResCalc!E$137*ResCalc!E69 -> 0.99731969 | F82: ='2010 Fuel Share'!$S$61*ResCalc!F$137*ResCalc!F69 -> #REF! | G82: ='2010 Fuel Share'!$S$61*ResCalc!G$137*ResCalc!G69 -> #REF! | H82: ='2010 Fuel Share'!$S$61*ResCalc!H$137*ResCalc!H69 -> #REF! | I82: ='2010 Fuel Share'!$S$61*ResCalc!I$137*ResCalc!I69 -> #REF! | J82: ='2010 Fuel Share'!$S$61*ResCalc!J$137*ResCalc!J69 -> #REF! | K82: ='2010 Fuel Share'!$S$61*ResCalc!K$137*ResCalc!K69 -> #REF! | L82: ='2010 Fuel Share'!$S$61*ResCalc!L$137*ResCalc!L69 -> #REF! | ... N82: ='2010 Fuel Share'!$S$61*ResCalc!N$137*ResCalc!N69 -> #REF! | P82: 0.48476754 | Q82: 0.99731969 | R82: 1.4016645 | S82: 1.3824117 | T82: 1.359837 | U82: 1.3326038 | V82: 1.2910604 | W82: 1.248265 | X82: 1.2420832 | Y82: 1.2361114 | Z82: 1.2303305
C83: Staten Island | D83: =ResCalc!D$137*ResCalc!D70 -> 0.14185989 | E83: ='2010 Fuel Share'!$T$61*ResCalc!E$137*ResCalc!E70 -> 0.065798581 | F83: ='2010 Fuel Share'!$T$61*ResCalc!F$137*ResCalc!F70 -> #REF! | G83: ='2010 Fuel Share'!$T$61*ResCalc!G$137*ResCalc!G70 -> #REF! | H83: ='2010 Fuel Share'!$T$61*ResCalc!H$137*ResCalc!H70 -> #REF! | I83: ='2010 Fuel Share'!$T$61*ResCalc!I$137*ResCalc!I70 -> #REF! | J83: ='2010 Fuel Share'!$T$61*ResCalc!J$137*ResCalc!J70 -> #REF! | K83: ='2010 Fuel Share'!$T$61*ResCalc!K$137*ResCalc!K70 -> #REF! | L83: ='2010 Fuel Share'!$T$61*ResCalc!L$137*ResCalc!L70 -> #REF! | ... N83: ='2010 Fuel Share'!$T$61*ResCalc!N$137*ResCalc!N70 -> #REF! | P83: 0.14185989 | Q83: 0.065798581 | R83: 0.090286443 | S83: 0.091758005 | T83: 0.09018304 | U83: 0.088303656 | V83: 0.085459935 | W83: 0.082540055 | X83: 0.084613807 | Y83: 0.084861578 | Z83: 0.08510143
C84: Queens | D84: =ResCalc!D$137*ResCalc!D71 -> 0.68306292 | E84: ='2010 Fuel Share'!$U$61*ResCalc!E$137*ResCalc!E71 -> 0.13283715 | F84: ='2010 Fuel Share'!$U$61*ResCalc!F$137*ResCalc!F71 -> #REF! | G84: ='2010 Fuel Share'!$U$61*ResCalc!G$137*ResCalc!G71 -> #REF! | H84: ='2010 Fuel Share'!$U$61*ResCalc!H$137*ResCalc!H71 -> #REF! | I84: ='2010 Fuel Share'!$U$61*ResCalc!I$137*ResCalc!I71 -> #REF! | J84: ='2010 Fuel Share'!$U$61*ResCalc!J$137*ResCalc!J71 -> #REF! | K84: ='2010 Fuel Share'!$U$61*ResCalc!K$137*ResCalc!K71 -> #REF! | L84: ='2010 Fuel Share'!$U$61*ResCalc!L$137*ResCalc!L71 -> #REF! | ... N84: ='2010 Fuel Share'!$U$61*ResCalc!N$137*ResCalc!N71 -> #REF! | P84: 0.68306292 | Q84: 0.13283715 | R84: 0.18716911 | S84: 0.18459952 | T84: 0.18114524 | U84: 0.17709639 | V84: 0.17222354 | W84: 0.16713583 | X84: 0.16796525 | Y84: 0.16769436 | Z84: 0.16743213
C85: West North Central | D85: =ResCalc!D$137*ResCalc!D72 -> 0 | E85: =ResCalc!E$137*ResCalc!E72 -> 0 | F85: =ResCalc!F$137*ResCalc!F72 -> #REF! | G85: =ResCalc!G$137*ResCalc!G72 -> #REF! | H85: =ResCalc!H$137*ResCalc!H72 -> #REF! | I85: =ResCalc!I$137*ResCalc!I72 -> #REF! | J85: =ResCalc!J$137*ResCalc!J72 -> #REF! | K85: =ResCalc!K$137*ResCalc!K72 -> #REF! | ... N85: =ResCalc!N$137*ResCalc!N72 -> #REF! | P85: 0 | Q85: 0 | R85: 0 | S85: 0 | T85: 0 | U85: 0 | V85: 0 | W85: 0 | X85: 0 | Y85: 0 | Z85: 0
C86: Mountain | D86: =ResCalc!D$137*ResCalc!D73 -> 0 | E86: =ResCalc!E$137*ResCalc!E73 -> 0 | F86: =ResCalc!F$137*ResCalc!F73 -> #REF! | G86: =ResCalc!G$137*ResCalc!G73 -> #REF! | H86: =ResCalc!H$137*ResCalc!H73 -> #REF! | I86: =ResCalc!I$137*ResCalc!I73 -> #REF! | J86: =ResCalc!J$137*ResCalc!J73 -> #REF! | K86: =ResCalc!K$137*ResCalc!K73 -> #REF! | ... N86: =ResCalc!N$137*ResCalc!N73 -> #REF! | P86: 0 | Q86: 0 | R86: 0 | S86: 0 | T86: 0 | U86: 0 | V86: 0 | W86: 0 | X86: 0 | Y86: 0 | Z86: 0
C87: Pacific | D87: =ResCalc!D$137*ResCalc!D74 -> 0 | E87: =ResCalc!E$137*ResCalc!E74 -> 0 | F87: =ResCalc!F$137*ResCalc!F74 -> #REF! | G87: =ResCalc!G$137*ResCalc!G74 -> #REF! | H87: =ResCalc!H$137*ResCalc!H74 -> #REF! | I87: =ResCalc!I$137*ResCalc!I74 -> #REF! | J87: =ResCalc!J$137*ResCalc!J74 -> #REF! | K87: =ResCalc!K$137*ResCalc!K74 -> #REF! | ... N87: =ResCalc!N$137*ResCalc!N74 -> #REF! | P87: 0 | Q87: 0 | R87: 0 | S87: 0 | T87: 0 | U87: 0 | V87: 0 | W87: 0 | X87: 0 | Y87: 0 | Z87: 0
C88: Total NYC | D88: =SUM(D80:D84) -> 2.4861215 | E88: =SUM(E80:E84) -> 2.3412371 | F88: =SUM(F80:F84) -> #REF! | G88: =SUM(G80:G84) -> #REF! | H88: =SUM(H80:H84) -> #REF! | I88: =SUM(I80:I84) -> #REF! | J88: =SUM(J80:J84) -> #REF! | K88: =SUM(K80:K84) -> #REF! | ... N88: =SUM(N80:N84) -> #REF! | P88: 2.4861215 | Q88: 2.3412371 | R88: 3.2942369 | S88: 3.2576815 | T88: 3.2200712 | U88: 3.1705086 | V88: 3.0920179 | W88: 3.0090262 | X88: 3.0008636 | Y88: 2.9988819 | Z88: 2.9969636
A90: Regional Miscellaneous LPG Demand PJ/a | I90: = Nat'l misc NG demand * Regional % of total households | U90: = Nat'l misc NG demand * Regional % of total households
B91: NE | C91: New England | D91: =ResCalc!D$138*ResCalc!D66 -> 0 | E91: =ResCalc!E$138*ResCalc!E66 -> 0 | F91: =ResCalc!F$138*ResCalc!F66 -> 0 | G91: =ResCalc!G$138*ResCalc!G66 -> 0 | H91: =ResCalc!H$138*ResCalc!H66 -> 0 | I91: =ResCalc!I$138*ResCalc!I66 -> 0 | J91: =ResCalc!J$138*ResCalc!J66 -> 0 | K91: =ResCalc!K$138*ResCalc!K66 -> 0 | ... N91: =ResCalc!N$138*ResCalc!N66 -> 0 | P91: 0 | Q91: 0 | R91: 0 | S91: 0 | T91: 0 | U91: 0 | V91: 0 | W91: 0 | X91: 0 | Y91: 0 | Z91: 0
B92: MA | C92: Middle Atlantic | D92: =ResCalc!D$138*ResCalc!D67 -> 12.943925 | E92: =ResCalc!E$138*ResCalc!E67 -> 12.968264 | F92: =ResCalc!F$138*ResCalc!F67 -> 13.925686 | G92: =ResCalc!G$138*ResCalc!G67 -> 15.228658 | H92: =ResCalc!H$138*ResCalc!H67 -> 16.508227 | I92: =ResCalc!I$138*ResCalc!I67 -> 17.832363 | J92: =ResCalc!J$138*ResCalc!J67 -> 19.135937 | K92: =ResCalc!K$138*ResCalc!K67 -> 20.53258 | ... N92: =ResCalc!N$138*ResCalc!N67 -> 24.97531 | P92: 12.943925 | Q92: 12.968264 | R92: 13.925686 | S92: 15.228658 | T92: 16.508227 | U92: 17.832363 | V92: 19.135937 | W92: 20.53258 | X92: 21.819748 | Y92: 23.344688 | Z92: 24.97531
B93: SA | C93: South Atlantic | D93: =ResCalc!D$138*ResCalc!D68 -> 7.0250891 | E93: =ResCalc!E$138*ResCalc!E68 -> 7.0360647 | F93: =ResCalc!F$138*ResCalc!F68 -> 7.6868008 | G93: =ResCalc!G$138*ResCalc!G68 -> 8.3190634 | H93: =ResCalc!H$138*ResCalc!H68 -> 9.0625123 | I93: =ResCalc!I$138*ResCalc!I68 -> 9.8355973 | J93: =ResCalc!J$138*ResCalc!J68 -> 10.597448 | K93: =ResCalc!K$138*ResCalc!K68 -> 11.415486 | ... N93: =ResCalc!N$138*ResCalc!N68 -> 14.062807 | P93: 7.0250891 | Q93: 7.0360647 | R93: 7.6868008 | S93: 8.3190634 | T93: 9.0625123 | U93: 9.8355973 | V93: 10.597448 | W93: 11.415486 | X93: 12.199087 | Y93: 13.098961 | Z93: 14.062807
B94: ESC | C94: East South Central | D94: =ResCalc!D$138*ResCalc!D69 -> 8.2285561 | E94: =ResCalc!E$138*ResCalc!E69 -> 8.0559097 | F94: =ResCalc!F$138*ResCalc!F69 -> 8.6853787 | G94: =ResCalc!G$138*ResCalc!G69 -> 9.4201525 | H94: =ResCalc!H$138*ResCalc!H69 -> 10.129604 | I94: =ResCalc!I$138*ResCalc!I69 -> 10.856856 | J94: =ResCalc!J$138*ResCalc!J69 -> 11.521296 | K94: =ResCalc!K$138*ResCalc!K69 -> 12.227761 | ... N94: =ResCalc!N$138*ResCalc!N69 -> 14.711824 | P94: 8.2285561 | Q94: 8.0559097 | R94: 8.6853787 | S94: 9.4201525 | T94: 10.129604 | U94: 10.856856 | V94: 11.521296 | W94: 12.227761 | X94: 13.003463 | Y94: 13.830381 | Z94: 14.711824
B95: ENC | C95: East North Central | D95: =ResCalc!D$138*ResCalc!D70 -> 2.4079625 | E95: =ResCalc!E$138*ResCalc!E70 -> 2.3810523 | F95: =ResCalc!F$138*ResCalc!F70 -> 2.5063368 | G95: =ResCalc!G$138*ResCalc!G70 -> 2.8011522 | H95: =ResCalc!H$138*ResCalc!H70 -> 3.0095579 | I95: =ResCalc!I$138*ResCalc!I70 -> 3.2229527 | J95: =ResCalc!J$138*ResCalc!J70 -> 3.4165641 | K95: =ResCalc!K$138*ResCalc!K70 -> 3.622239 | ... N95: =ResCalc!N$138*ResCalc!N70 -> 4.5588343 | P95: 2.4079625 | Q95: 2.3810523 | R95: 2.5063368 | S95: 2.8011522 | T95: 3.0095579 | U95: 3.2229527 | V95: 3.4165641 | W95: 3.622239 | X95: 3.968458 | Y95: 4.2536314 | Z95: 4.5588343
B96: WSC | C96: West South Central | D96: =ResCalc!D$138*ResCalc!D71 -> 11.594468 | E96: =ResCalc!E$138*ResCalc!E71 -> 11.429549 | F96: =ResCalc!F$138*ResCalc!F71 -> 12.354017 | G96: =ResCalc!G$138*ResCalc!G71 -> 13.399249 | H96: =ResCalc!H$138*ResCalc!H71 -> 14.373479 | I96: =ResCalc!I$138*ResCalc!I71 -> 15.368876 | J96: =ResCalc!J$138*ResCalc!J71 -> 16.371055 | K96: =ResCalc!K$138*ResCalc!K71 -> 17.439701 | ... N96: =ResCalc!N$138*ResCalc!N71 -> 21.326171 | P96: 11.594468 | Q96: 11.429549 | R96: 12.354017 | S96: 13.399249 | T96: 14.373479 | U96: 15.368876 | V96: 16.371055 | W96: 17.439701 | X96: 18.730835 | Y96: 19.985929 | Z96: 21.326171
B97: WNC | C97: West North Central | D97: =ResCalc!D$138*ResCalc!D72 -> 0 | E97: =ResCalc!E$138*ResCalc!E72 -> 0 | F97: =ResCalc!F$138*ResCalc!F72 -> 0 | G97: =ResCalc!G$138*ResCalc!G72 -> 0 | H97: =ResCalc!H$138*ResCalc!H72 -> 0 | I97: =ResCalc!I$138*ResCalc!I72 -> 0 | J97: =ResCalc!J$138*ResCalc!J72 -> 0 | K97: =ResCalc!K$138*ResCalc!K72 -> 0 | ... N97: =ResCalc!N$138*ResCalc!N72 -> 0 | P97: 0 | Q97: 0 | R97: 0 | S97: 0 | T97: 0 | U97: 0 | V97: 0 | W97: 0 | X97: 0 | Y97: 0 | Z97: 0
B98: M | C98: Mountain | D98: =ResCalc!D$138*ResCalc!D73 -> 0 | E98: =ResCalc!E$138*ResCalc!E73 -> 0 | F98: =ResCalc!F$138*ResCalc!F73 -> 0 | G98: =ResCalc!G$138*ResCalc!G73 -> 0 | H98: =ResCalc!H$138*ResCalc!H73 -> 0 | I98: =ResCalc!I$138*ResCalc!I73 -> 0 | J98: =ResCalc!J$138*ResCalc!J73 -> 0 | K98: =ResCalc!K$138*ResCalc!K73 -> 0 | ... N98: =ResCalc!N$138*ResCalc!N73 -> 0 | P98: 0 | Q98: 0 | R98: 0 | S98: 0 | T98: 0 | U98: 0 | V98: 0 | W98: 0 | X98: 0 | Y98: 0 | Z98: 0
B99: P | C99: Pacific | D99: =ResCalc!D$138*ResCalc!D74 -> 0 | E99: =ResCalc!E$138*ResCalc!E74 -> 0 | F99: =ResCalc!F$138*ResCalc!F74 -> 0 | G99: =ResCalc!G$138*ResCalc!G74 -> 0 | H99: =ResCalc!H$138*ResCalc!H74 -> 0 | I99: =ResCalc!I$138*ResCalc!I74 -> 0 | J99: =ResCalc!J$138*ResCalc!J74 -> 0 | K99: =ResCalc!K$138*ResCalc!K74 -> 0 | ... N99: =ResCalc!N$138*ResCalc!N74 -> 0 | P99: 0 | Q99: 0 | R99: 0 | S99: 0 | T99: 0 | U99: 0 | V99: 0 | W99: 0 | X99: 0 | Y99: 0 | Z99: 0
C100: Total US | D100: =SUM(D91:D99) -> 42.2 | E100: =SUM(E91:E99) -> 41.87084 | F100: =SUM(F91:F99) -> 45.15822 | G100: =SUM(G91:G99) -> 49.168275 | H100: =SUM(H91:H99) -> 53.08338 | I100: =SUM(I91:I99) -> 57.116645 | J100: =SUM(J91:J99) -> 61.0423 | K100: =SUM(K91:K99) -> 65.237767 | ... N100: =SUM(N91:N99) -> 79.634946 | P100: 42.2 | Q100: 41.87084 | R100: 45.15822 | S100: 49.168275 | T100: 53.08338 | U100: 57.116645 | V100: 61.0423 | W100: 65.237767 | X100: 69.721591 | Y100: 74.51359 | Z100: 79.634946
A102: Regional Water Heating Demand PJ/a | I102: = Nat'l water heating demand * Regional % of total households | U102: = Nat'l water heating demand * Regional % of total households
D103: =ResCalc!D$139*ResCalc!D66 -> 0 | E103: =ResCalc!E$139*ResCalc!E66 -> 0 | F103: =ResCalc!F$139*ResCalc!F66 -> 0 | G103: =ResCalc!G$139*ResCalc!G66 -> 0 | H103: =ResCalc!H$139*ResCalc!H66 -> 0 | I103: =ResCalc!I$139*ResCalc!I66 -> 0 | J103: =ResCalc!J$139*ResCalc!J66 -> 0 | K103: =ResCalc!K$139*ResCalc!K66 -> 0 | ... N103: =ResCalc!N$139*ResCalc!N66 -> 0 | P103: 0 | Q103: 0 | R103: 0 | S103: 0 | T103: 0 | U103: 0 | V103: 0 | W103: 0 | X103: 0 | Y103: 0 | Z103: 0
C104: Brooklyn | D104: =ResCalc!D$139*ResCalc!D67 -> 11.30405 | E104: ='2010 Fuel Share'!$Q$67*ResCalc!E$139*ResCalc!E67 -> 12.609344 | F104: ='2010 Fuel Share'!$Q$67*ResCalc!F$139*ResCalc!F67 -> 12.554577 | G104: ='2010 Fuel Share'!$Q$67*ResCalc!G$139*ResCalc!G67 -> 13.045106 | H104: ='2010 Fuel Share'!$Q$67*ResCalc!H$139*ResCalc!H67 -> 13.544408 | I104: ='2010 Fuel Share'!$Q$67*ResCalc!I$139*ResCalc!I67 -> 13.809234 | J104: ='2010 Fuel Share'!$Q$67*ResCalc!J$139*ResCalc!J67 -> 13.699125 | K104: ='2010 Fuel Share'!$Q$67*ResCalc!K$139*ResCalc!K67 -> 13.53285 | L104: ='2010 Fuel Share'!$Q$67*ResCalc!L$139*ResCalc!L67 -> 13.178349 | ... N104: ='2010 Fuel Share'!$Q$67*ResCalc!N$139*ResCalc!N67 -> 12.666401 | P104: 11.803917 | Q104: 13.21464 | R104: 13.387632 | S104: 13.91071 | T104: 14.443143 | U104: 14.725541 | V104: 14.608126 | W104: 14.430818 | X104: 14.052795 | Y104: 13.777377 | Z104: 13.506876
C105: Bronx | D105: =ResCalc!D$139*ResCalc!D68 -> 6.1350758 | E105: ='2010 Fuel Share'!$R$67*ResCalc!E$139*ResCalc!E68 -> 7.6119136 | F105: ='2010 Fuel Share'!$R$67*ResCalc!F$139*ResCalc!F68 -> 7.7105351 | G105: ='2010 Fuel Share'!$R$67*ResCalc!G$139*ResCalc!G68 -> 7.9289159 | H105: ='2010 Fuel Share'!$R$67*ResCalc!H$139*ResCalc!H68 -> 8.2729731 | I105: ='2010 Fuel Share'!$R$67*ResCalc!I$139*ResCalc!I68 -> 8.4745144 | J105: ='2010 Fuel Share'!$R$67*ResCalc!J$139*ResCalc!J68 -> 8.4410757 | K105: ='2010 Fuel Share'!$R$67*ResCalc!K$139*ResCalc!K68 -> 8.3713128 | L105: ='2010 Fuel Share'!$R$67*ResCalc!L$139*ResCalc!L68 -> 8.1977 | ... N105: ='2010 Fuel Share'!$R$67*ResCalc!N$139*ResCalc!N68 -> 7.9353803 | P105: 6.4063698 | Q105: 7.9304093 | R105: 8.1738208 | S105: 8.405323 | T105: 8.7700528 | U105: 8.9837037 | V105: 8.9482558 | W105: 8.8743012 | X105: 8.6902569 | Y105: 8.5508178 | Z105: 8.4121758
C106: Manhattan | D106: =ResCalc!D$139*ResCalc!D69 -> 7.1860747 | E106: ='2010 Fuel Share'!$S$67*ResCalc!E$139*ResCalc!E69 -> 13.049702 | F106: ='2010 Fuel Share'!$S$67*ResCalc!F$139*ResCalc!F69 -> 13.045166 | G106: ='2010 Fuel Share'!$S$67*ResCalc!G$139*ResCalc!G69 -> 13.443715 | H106: ='2010 Fuel Share'!$S$67*ResCalc!H$139*ResCalc!H69 -> 13.846099 | I106: ='2010 Fuel Share'!$S$67*ResCalc!I$139*ResCalc!I69 -> 14.006839 | J106: ='2010 Fuel Share'!$S$67*ResCalc!J$139*ResCalc!J69 -> 13.741047 | K106: ='2010 Fuel Share'!$S$67*ResCalc!K$139*ResCalc!K69 -> 13.426663 | L106: ='2010 Fuel Share'!$S$67*ResCalc!L$139*ResCalc!L69 -> 13.084155 | ... N106: ='2010 Fuel Share'!$S$67*ResCalc!N$139*ResCalc!N69 -> 12.430376 | P106: 7.5038441 | Q106: 13.519191 | R106: 13.751136 | S106: 14.171253 | T106: 14.595413 | U106: 14.764852 | V106: 14.484676 | W106: 14.153278 | X106: 13.792235 | Y106: 13.442353 | Z106: 13.103074
