Workbook
Name __HDV50: #REF!
Name __LDV50: #REF!
Name _1995_Implicit_GDP_Deflator: #REF!
Name _1995_Implicit_GDP_Deflator: #REF!
Name _2001_Implicit_GDP_Deflator: #REF!
Name _2001_Implicit_GDP_Deflator: #REF!
Name _HDV50: #REF!
Name _HDV50: #REF!
Name _LDV50: #REF!
Name _LDV50: #REF!
Name Age_of_car: #REF!
Name Age_of_car: #REF!
Name avg_water_heater_PJ: '[1]AEO HW'!$B$33
Name Aviation_Detail_Table: '[2]Marine and Aviation'!$I$27:$Z$31
Name Aviation_Detail_Table_Years: '[2]Marine and Aviation'!$I$27:$Z$27
Name btu_per_watthr: #REF!
Name btu_per_watthr: #REF!
Name CH4GWP_20YR: '[2]RELA TABLE'!$D$8
Name ConEd_Steam_Table: '[2]ConEd Steam'!$I$11:$Z$15
Name ConEd_Steam_Years: '[2]ConEd Steam'!$I$11:$Z$11
Name conv: #REF!
Name conv: #REF!
Name Convert_MMbtu_to_GJ: '[2]Unit conversions'!$F$25
Name days_per_year: #REF!
Name days_per_year: #REF!
Name Diesel_Car_CO: #REF!
Name Diesel_Car_CO: #REF!
Name Diesel_Car_Nox: #REF!
Name Diesel_Car_Nox: #REF!
Name Diesel_Car_PM: #REF!
Name Diesel_Car_PM: #REF!
Name Diesel_Car_VOCs: #REF!
Name Diesel_Car_VOCs: #REF!
Name Diesel_HDT_CO: #REF!
Name Diesel_HDT_CO: #REF!
Name Diesel_HDT_NOx: #REF!
Name Diesel_HDT_NOx: #REF!
Name Diesel_HDT_PM: #REF!
Name Diesel_HDT_PM: #REF!
Name Diesel_HDT_SO2: #REF!
Name Diesel_HDT_SO2: #REF!
Name Diesel_HDT_VOCs: #REF!
Name Diesel_HDT_VOCs: #REF!
Name Diesel_LDT_CO: #REF!
Name Diesel_LDT_CO: #REF!
Name Diesel_LDT_Nox: #REF!
Name Diesel_LDT_Nox: #REF!
Name Diesel_LDT_PM: #REF!
Name Diesel_LDT_PM: #REF!
Name Diesel_LDT_VOCs: #REF!
Name Diesel_LDT_VOCs: #REF!
Name Diesel_Rail_Table: [2]Transit!$I$26:$Z$29
Name Diesel_Rail_Table_Years: [2]Transit!$I$26:$Z$26
Name dollar____per__m: #REF!
Name dollar____per__m: #REF!
Name EF_table_electricity_and_steam: '[2]EF EL and Steam'!$D$5:$Z$81
Name EF_table_road_trans: '[2]EF road transport'!$J$25:$AA$2225
Name Elec_Vehicle_Assump: '[2]EF road transport'!$B$16:$C$23
Name Electric_Traction_Summary_Table: [2]Transit!$I$12:$Z$22
Name Electric_Traction_Summary_Table_Years: [2]Transit!$I$12:$Z$12

Sheet ANSv6.0-Commodities
A1: ANSWER-Commodities
B7: CommName | C7: CommDesc | D7: CommUnit | E7: Set Memberships | F7: Comment

Sheet UC_TRNHDV
B3: ~UC_Sets: R_E: AllRegions
H5: ~UC_T: UC_COMPRD
B6: UC_N | C6: Pset_PN | D6: Pset_PD | E6: Pset_CI | F6: Pset_CO | G6: Cset_CN | H6: Year | I6: LimType | J6: UC_FLO | K6: UC_RHSRTS | L6: UC_RHSRTS~0 | M6: R0 | N6: R1 | O6: R2 | P6: R3 | Q6: R4 | R6: R5 | S6: R6
B8: ="UC_"&G8&RIGHT(E8,3)&I8 -> UC_TBCNGUP | C8: TB* | E8: TBCNG | F8: TB | G8: TB | H8: 2020 | I8: UP | J8: 1 | K8: 0 | L8: 15 | O8: -0.2 | P8: =O8 -> -0.2 | Q8: =P8 -> -0.2 | R8: =Q8 -> -0.2 | S8: =R8 -> -0.2
C9: TB* | E9: TBCNG | F9: TB | G9: TB | H9: 2025 | J9: 1 | O9: -0.23571429 | P9: =O9 -> -0.23571429 | Q9: =P9 -> -0.23571429 | R9: =Q9 -> -0.23571429 | S9: =R9 -> -0.23571429
C10: TB* | E10: TBCNG | F10: TB | G10: TB | H10: 2030 | J10: 1 | O10: -0.27142857 | P10: =O10 -> -0.27142857 | Q10: =P10 -> -0.27142857 | R10: =Q10 -> -0.27142857 | S10: =R10 -> -0.27142857
C11: TB* | E11: TBCNG | F11: TB | G11: TB | H11: 2035 | J11: 1 | O11: -0.30714286 | P11: =O11 -> -0.30714286 | Q11: =P11 -> -0.30714286 | R11: =Q11 -> -0.30714286 | S11: =R11 -> -0.30714286
C12: TB* | E12: TBCNG | F12: TB | G12: TB | H12: 2040 | J12: 1 | O12: -0.34285714 | P12: =O12 -> -0.34285714 | Q12: =P12 -> -0.34285714 | R12: =Q12 -> -0.34285714 | S12: =R12 -> -0.34285714
C13: TB* | E13: TBCNG | F13: TB | G13: TB | H13: 2045 | J13: 1 | O13: -0.38452381 | P13: =O13 -> -0.38452381 | Q13: =P13 -> -0.38452381 | R13: =Q13 -> -0.38452381 | S13: =R13 -> -0.38452381
C14: TB* | E14: TBCNG | F14: TB | G14: TB | H14: 2050 | J14: 1 | O14: -0.42619048 | P14: =O14 -> -0.42619048 | Q14: =P14 -> -0.42619048 | R14: =Q14 -> -0.42619048 | S14: =R14 -> -0.42619048
C15: TB* | E15: TBCNG | F15: TB | G15: TB | H15: 2055 | J15: 1 | O15: =O14 -> -0.42619048 | P15: =P14 -> -0.42619048 | Q15: =Q14 -> -0.42619048 | R15: =R14 -> -0.42619048 | S15: =S14 -> -0.42619048
B16: ="UC_"&G16&RIGHT(E16,3)&I16 -> UC_TBDSLLO | C16: TB* | E16: TBDSL | F16: TB | G16: TB | H16: 2015 | I16: LO | J16: 1 | K16: 0 | L16: 15 | O16: =-('2010 GHG'!$I$6+'2010 GHG'!$I$10)*0.95/('2010 GHG'!$I$2+'2010 GHG'!$I$6+'2010 GHG'!$I$10) -> -0.79953404 | P16: =O16 -> -0.79953404 | Q16: =P16 -> -0.79953404 | R16: =Q16 -> -0.79953404 | S16: =R16 -> -0.79953404
C17: TB* | E17: TBDSL | F17: TB | G17: TB | H17: 2020 | J17: 1 | O17: =O16*U17 -> -0.63962723 | P17: =O17 -> -0.63962723 | Q17: =P17 -> -0.63962723 | R17: =Q17 -> -0.63962723 | S17: =R17 -> -0.63962723 | U17: 0.8
C18: TB* | E18: TBDSL | F18: TB | G18: TB | H18: 2025 | J18: 1 | O18: =O17*U18 -> -0.51170178 | P18: =O18 -> -0.51170178 | Q18: =P18 -> -0.51170178 | R18: =Q18 -> -0.51170178 | S18: =R18 -> -0.51170178 | U18: 0.8
C19: TB* | E19: TBDSL | F19: TB | G19: TB | H19: 2030 | J19: 1 | O19: =O18*U19 -> -0.38377634 | P19: =O19 -> -0.38377634 | Q19: =P19 -> -0.38377634 | R19: =Q19 -> -0.38377634 | S19: =R19 -> -0.38377634 | U19: 0.75
C20: TB* | E20: TBDSL | F20: TB | G20: TB | H20: 2035 | J20: 1 | O20: =O19*U20 -> -0.30702107 | P20: =O20 -> -0.30702107 | Q20: =P20 -> -0.30702107 | R20: =Q20 -> -0.30702107 | S20: =R20 -> -0.30702107 | U20: 0.8
C21: TB* | E21: TBDSL | F21: TB | G21: TB | H21: 2040 | J21: 1 | O21: =O20*U21 -> -0.24561686 | P21: =O21 -> -0.24561686 | Q21: =P21 -> -0.24561686 | R21: =Q21 -> -0.24561686 | S21: =R21 -> -0.24561686 | U21: 0.8
C22: TB* | E22: TBDSL | F22: TB | G22: TB | H22: 2045 | J22: 1 | O22: =O21*U22 -> -0.19649348 | P22: =O22 -> -0.19649348 | Q22: =P22 -> -0.19649348 | R22: =Q22 -> -0.19649348 | S22: =R22 -> -0.19649348 | U22: 0.8
C23: TB* | E23: TBDSL | F23: TB | G23: TB | H23: 2050 | J23: 1 | O23: =O22*U23 -> -0.15719479 | P23: =O23 -> -0.15719479 | Q23: =P23 -> -0.15719479 | R23: =Q23 -> -0.15719479 | S23: =R23 -> -0.15719479 | U23: 0.8
C24: TB* | E24: TBDSL | F24: TB | G24: TB | H24: 2055 | J24: 1 | O24: =O23*U24 -> -0.12575583 | P24: =O24 -> -0.12575583 | Q24: =P24 -> -0.12575583 | R24: =Q24 -> -0.12575583 | S24: =R24 -> -0.12575583 | U24: 0.8
B25: ="UC_"&G25&RIGHT(E25,3)&I25 -> UC_TBELCLO | C25: TB* | E25: TRNELC | F25: TB | G25: TB | H25: 2015 | I25: LO | J25: 1 | K25: 0 | L25: 15 | O25: 0 | P25: 0 | Q25: 0 | R25: 0 | S25: 0
C26: TB* | E26: TRNELC | F26: TB | G26: TB | H26: 2020 | J26: 1 | O26: 0 | P26: 0 | Q26: 0 | R26: 0 | S26: 0 | U26: 0.8
C27: TB* | E27: TRNELC | F27: TB | G27: TB | H27: 2025 | J27: 1 | O27: -0.00031 | P27: -0.00031 | Q27: -0.00031 | R27: -0.00031 | S27: -0.00031 | U27: 0.8
C28: TB* | E28: TRNELC | F28: TB | G28: TB | H28: 2030 | J28: 1 | O28: -0.00031 | P28: -0.00031 | Q28: -0.00031 | R28: -0.00031 | S28: -0.00031 | U28: 0.75
C29: TB* | E29: TRNELC | F29: TB | G29: TB | H29: 2035 | J29: 1 | O29: -0.00031 | P29: -0.00031 | Q29: -0.00031 | R29: -0.00031 | S29: -0.00031 | U29: 0.8
C30: TB* | E30: TRNELC | F30: TB | G30: TB | H30: 2040 | J30: 1 | O30: -0.00031 | P30: -0.00031 | Q30: -0.00031 | R30: -0.00031 | S30: -0.00031 | U30: 0.8
C31: TB* | E31: TRNELC | F31: TB | G31: TB | H31: 2045 | J31: 1 | O31: -0.00031 | P31: -0.00031 | Q31: -0.00031 | R31: -0.00031 | S31: -0.00031 | U31: 0.8
C32: TB* | E32: TRNELC | F32: TB | G32: TB | H32: 2050 | J32: 1 | O32: -0.00031 | P32: -0.00031 | Q32: -0.00031 | R32: -0.00031 | S32: -0.00031 | U32: 0.8
C33: TB* | E33: TRNELC | F33: TB | G33: TB | H33: 2055 | J33: 1 | O33: -0.00031 | P33: -0.00031 | Q33: -0.00031 | R33: -0.00031 | S33: -0.00031 | U33: 0.8
B34: ="UC_"&G34&"Commuter"&I34 -> UC_TRPCommuterLO | C34: TP* | D34: *Commuter* | F34: TRP | G34: TRP | H34: 2010 | I34: LO | J34: 1 | K34: 0 | L34: 15 | O34: 0 | P34: =O34 -> 0 | Q34: =P34 -> 0 | R34: =Q34 -> 0 | S34: =R34 -> 0 | U34: 0.5
C35: TP* | D35: *Commuter* | F35: TRP | G35: TRP | H35: 2015 | J35: 1 | O35: =-TRP!$H$6 -> -0.0042418397 | P35: =O35 -> -0.0042418397 | Q35: =P35 -> -0.0042418397 | R35: =Q35 -> -0.0042418397 | S35: =R35 -> -0.0042418397
C36: TP* | D36: *Commuter* | F36: TRP | G36: TRP | H36: 2020 | J36: 1
C37: TP* | D37: *Commuter* | F37: TRP | G37: TRP | H37: 2025 | J37: 1
C38: TP* | D38: *Commuter* | F38: TRP | G38: TRP | H38: 2030 | J38: 1
C39: TP* | D39: *Commuter* | F39: TRP | G39: TRP | H39: 2035 | J39: 1
C40: TP* | D40: *Commuter* | F40: TRP | G40: TRP | H40: 2040 | J40: 1
C41: TP* | D41: *Commuter* | F41: TRP | G41: TRP | H41: 2045 | J41: 1
C42: TP* | D42: *Commuter* | F42: TRP | G42: TRP | H42: 2050 | J42: 1
C43: TP* | D43: *Commuter* | F43: TRP | G43: TRP | H43: 2055 | J43: 1 | O43: =O35 -> -0.0042418397 | P43: =O43 -> -0.0042418397 | Q43: =P43 -> -0.0042418397 | R43: =Q43 -> -0.0042418397 | S43: =R43 -> -0.0042418397
B44: ="UC_"&G44&RIGHT(E44,3)&I44 -> UC_THSGSLLO | C44: THS* | E44: THGSL | F44: THS | G44: THS | H44: 2010 | I44: LO | J44: 1 | K44: 0 | L44: 15 | O44: 0 | P44: =O44 -> 0 | Q44: =P44 -> 0 | R44: =Q44 -> 0 | S44: =R44 -> 0
C45: THS* | E45: THGSL | F45: THS | G45: THS | H45: 2015 | J45: 1 | O45: 0 | P45: 0 | Q45: 0 | R45: 0 | S45: 0
C46: THS* | E46: THGSL | F46: THS | G46: THS | H46: 2020 | J46: 1 | O46: =-1.72% -> -0.0172 | P46: =O46 -> -0.0172 | Q46: =P46 -> -0.0172 | R46: =Q46 -> -0.0172 | S46: =R46 -> -0.0172
C47: THS* | E47: THGSL | F47: THS | G47: THS | H47: 2025 | J47: 1 | O47: =O46 -> -0.0172 | P47: =O47 -> -0.0172 | Q47: =P47 -> -0.0172 | R47: =Q47 -> -0.0172 | S47: =R47 -> -0.0172
C48: THS* | E48: THGSL | F48: THS | G48: THS | H48: 2030 | J48: 1 | O48: =O47/2 -> -0.0086 | P48: =O48 -> -0.0086 | Q48: =P48 -> -0.0086 | R48: =Q48 -> -0.0086 | S48: =R48 -> -0.0086
C49: THS* | E49: THGSL | F49: THS | G49: THS | H49: 2035 | J49: 1 | O49: =O48/2 -> -0.0043 | P49: =O49 -> -0.0043 | Q49: =P49 -> -0.0043 | R49: =Q49 -> -0.0043 | S49: =R49 -> -0.0043
C50: THS* | E50: THGSL | F50: THS | G50: THS | H50: 2040 | J50: 1 | O50: =O49/2 -> -0.00215 | P50: =O50 -> -0.00215 | Q50: =P50 -> -0.00215 | R50: =Q50 -> -0.00215 | S50: =R50 -> -0.00215
C51: THS* | E51: THGSL | F51: THS | G51: THS | H51: 2045 | J51: 1 | O51: =O50/2 -> -0.001075 | P51: =O51 -> -0.001075 | Q51: =P51 -> -0.001075 | R51: =Q51 -> -0.001075 | S51: =R51 -> -0.001075 | U51: =(1+'AEO Data'!$J$173)^5 -> 1.0215687
C52: THS* | E52: THGSL | F52: THS | G52: THS | H52: 2050 | J52: 1 | O52: 0 | P52: =O52 -> 0 | Q52: =P52 -> 0 | R52: =Q52 -> 0 | S52: =R52 -> 0 | U52: 1.2
C53: THS* | E53: THGSL | F53: THS | G53: THS | H53: 2055 | J53: 1 | O53: =O52/2 -> 0 | P53: =O53 -> 0 | Q53: =P53 -> 0 | R53: =Q53 -> 0 | S53: =R53 -> 0 | U53: 1
B54: ="UC_"&G54&RIGHT(E54,3)&I54 -> UC_THSGSLUP | C54: THS* | E54: THGSL | F54: THS | G54: THS | H54: 2010 | I54: UP | J54: 1 | K54: 0 | L54: 15 | O54: 0 | P54: =O54 -> 0 | Q54: =P54 -> 0 | R54: =Q54 -> 0 | S54: =R54 -> 0
C55: THS* | E55: THGSL | F55: THS | G55: THS | H55: 2015 | J55: 1 | O55: 0 | P55: 0 | Q55: 0 | R55: 0 | S55: 0
C56: THS* | E56: THGSL | F56: THS | G56: THS | H56: 2020 | J56: 1 | O56: =O46 -> -0.0172 | P56: =O56 -> -0.0172 | Q56: =P56 -> -0.0172 | R56: =Q56 -> -0.0172 | S56: =R56 -> -0.0172
C57: THS* | E57: THGSL | F57: THS | G57: THS | H57: 2025 | J57: 1 | O57: =O47 -> -0.0172 | P57: =O57 -> -0.0172 | Q57: =P57 -> -0.0172 | R57: =Q57 -> -0.0172 | S57: =R57 -> -0.0172
C58: THS* | E58: THGSL | F58: THS | G58: THS | H58: 2030 | J58: 1 | O58: =O48*1.2 -> -0.01032 | P58: =O58 -> -0.01032 | Q58: =P58 -> -0.01032 | R58: =Q58 -> -0.01032 | S58: =R58 -> -0.01032
C59: THS* | E59: THGSL | F59: THS | G59: THS | H59: 2035 | J59: 1 | O59: =O49*1.2 -> -0.00516 | P59: =O59 -> -0.00516 | Q59: =P59 -> -0.00516 | R59: =Q59 -> -0.00516 | S59: =R59 -> -0.00516
C60: THS* | E60: THGSL | F60: THS | G60: THS | H60: 2040 | J60: 1 | O60: =O50*1.2 -> -0.00258 | P60: =O60 -> -0.00258 | Q60: =P60 -> -0.00258 | R60: =Q60 -> -0.00258 | S60: =R60 -> -0.00258
C61: THS* | E61: THGSL | F61: THS | G61: THS | H61: 2045 | J61: 1 | O61: =O51*1.2 -> -0.00129 | P61: =O61 -> -0.00129 | Q61: =P61 -> -0.00129 | R61: =Q61 -> -0.00129 | S61: =R61 -> -0.00129 | U61: =(1+'AEO Data'!$J$173)^5 -> 1.0215687
C62: THS* | E62: THGSL | F62: THS | G62: THS | H62: 2050 | J62: 1 | O62: =O52*1.2 -> 0 | P62: =O62 -> 0 | Q62: =P62 -> 0 | R62: =Q62 -> 0 | S62: =R62 -> 0 | U62: 1.2
C63: THS* | E63: THGSL | F63: THS | G63: THS | H63: 2055 | J63: 1 | O63: =O53*1.2 -> 0 | P63: =O63 -> 0 | Q63: =P63 -> 0 | R63: =Q63 -> 0 | S63: =R63 -> 0 | U63: 1
B64: ="UC_"&G64&RIGHT(E64,3)&I64 -> UC_THSCNGLO | C64: THS* | E64: THCNG | F64: THS | G64: THS | H64: 2010 | I64: LO | J64: 1 | K64: 0 | L64: 15 | O64: 0 | P64: =O64 -> 0 | Q64: =P64 -> 0 | R64: =Q64 -> 0 | S64: =R64 -> 0
C65: THS* | E65: THCNG | F65: THS | G65: THS | H65: 2015 | J65: 1 | O65: 0 | P65: 0 | Q65: 0 | R65: 0 | S65: 0
C66: THS* | E66: THCNG | F66: THS | G66: THS | H66: 2020 | J66: 1 | O66: =-0.81% -> -0.0081 | P66: =O66 -> -0.0081 | Q66: =P66 -> -0.0081 | R66: =Q66 -> -0.0081 | S66: =R66 -> -0.0081
C67: THS* | E67: THCNG | F67: THS | G67: THS | H67: 2025 | J67: 1 | O67: =O66 -> -0.0081 | P67: =O67 -> -0.0081 | Q67: =P67 -> -0.0081 | R67: =Q67 -> -0.0081 | S67: =R67 -> -0.0081
C68: THS* | E68: THCNG | F68: THS | G68: THS | H68: 2030 | J68: 1 | O68: =O67 -> -0.0081 | P68: =O68 -> -0.0081 | Q68: =P68 -> -0.0081 | R68: =Q68 -> -0.0081 | S68: =R68 -> -0.0081
C69: THS* | E69: THCNG | F69: THS | G69: THS | H69: 2035 | J69: 1 | O69: =O68 -> -0.0081 | P69: =O69 -> -0.0081 | Q69: =P69 -> -0.0081 | R69: =Q69 -> -0.0081 | S69: =R69 -> -0.0081
C70: THS* | E70: THCNG | F70: THS | G70: THS | H70: 2040 | J70: 1 | O70: =O69 -> -0.0081 | P70: =O70 -> -0.0081 | Q70: =P70 -> -0.0081 | R70: =Q70 -> -0.0081 | S70: =R70 -> -0.0081
C71: THS* | E71: THCNG | F71: THS | G71: THS | H71: 2045 | J71: 1 | O71: =O70 -> -0.0081 | P71: =O71 -> -0.0081 | Q71: =P71 -> -0.0081 | R71: =Q71 -> -0.0081 | S71: =R71 -> -0.0081 | U71: =(1+'AEO Data'!$J$173)^5 -> 1.0215687
C72: THS* | E72: THCNG | F72: THS | G72: THS | H72: 2050 | J72: 1 | O72: =O71 -> -0.0081 | P72: =O72 -> -0.0081 | Q72: =P72 -> -0.0081 | R72: =Q72 -> -0.0081 | S72: =R72 -> -0.0081 | U72: 1.2
C73: THS* | E73: THCNG | F73: THS | G73: THS | H73: 2055 | J73: 1 | O73: =O72 -> -0.0081 | P73: =O73 -> -0.0081 | Q73: =P73 -> -0.0081 | R73: =Q73 -> -0.0081 | S73: =R73 -> -0.0081 | U73: 1
B74: ="UC_"&G74&RIGHT(E74,3)&I74 -> UC_THSCNGUP | C74: THS* | E74: THCNG | F74: THS | G74: THS | H74: 2010 | I74: UP | J74: 1 | K74: 0 | L74: 15 | O74: 0 | P74: =O74 -> 0 | Q74: =P74 -> 0 | R74: =Q74 -> 0 | S74: =R74 -> 0
C75: THS* | E75: THCNG | F75: THS | G75: THS | H75: 2015 | J75: 1 | O75: 0 | P75: 0 | Q75: 0 | R75: 0 | S75: 0
C76: THS* | E76: THCNG | F76: THS | G76: THS | H76: 2020 | J76: 1 | O76: =O66 -> -0.0081 | P76: =O76 -> -0.0081 | Q76: =P76 -> -0.0081 | R76: =Q76 -> -0.0081 | S76: =R76 -> -0.0081
C77: THS* | E77: THCNG | F77: THS | G77: THS | H77: 2025 | J77: 1 | O77: =O78 -> -0.049109025 | P77: =O77 -> -0.049109025 | Q77: =P77 -> -0.049109025 | R77: =Q77 -> -0.049109025 | S77: =R77 -> -0.049109025
C78: THS* | E78: THCNG | F78: THS | G78: THS | H78: 2030 | J78: 1 | O78: =O79 -> -0.049109025 | P78: =O78 -> -0.049109025 | Q78: =P78 -> -0.049109025 | R78: =Q78 -> -0.049109025 | S78: =R78 -> -0.049109025
C79: THS* | E79: THCNG | F79: THS | G79: THS | H79: 2035 | J79: 1 | O79: =-'AEO Data'!$Q$172*1.2 -> -0.049109025 | P79: =O79 -> -0.049109025 | Q79: =P79 -> -0.049109025 | R79: =Q79 -> -0.049109025 | S79: =R79 -> -0.049109025
C80: THS* | E80: THCNG | F80: THS | G80: THS | H80: 2040 | J80: 1 | O80: =-'AEO Data'!$R$172*1.4 -> -0.11871549 | P80: =O80 -> -0.11871549 | Q80: =P80 -> -0.11871549 | R80: =Q80 -> -0.11871549 | S80: =R80 -> -0.11871549
C81: THS* | E81: THCNG | F81: THS | G81: THS | H81: 2045 | J81: 1 | O81: =O80*U81 -> -0.12127603 | P81: =O81 -> -0.12127603 | Q81: =P81 -> -0.12127603 | R81: =Q81 -> -0.12127603 | S81: =R81 -> -0.12127603 | U81: =(1+'AEO Data'!$J$173)^5 -> 1.0215687
C82: THS* | E82: THCNG | F82: THS | G82: THS | H82: 2050 | J82: 1 | O82: =O81*U82 -> -0.14553124 | P82: =O82 -> -0.14553124 | Q82: =P82 -> -0.14553124 | R82: =Q82 -> -0.14553124 | S82: =R82 -> -0.14553124 | U82: 1.2
C83: THS* | E83: THCNG | F83: THS | G83: THS | H83: 2055 | J83: 1 | O83: =O82*U83 -> -0.14553124 | P83: =O83 -> -0.14553124 | Q83: =P83 -> -0.14553124 | R83: =Q83 -> -0.14553124 | S83: =R83 -> -0.14553124 | U83: 1
B84: ="UC_"&G84&RIGHT(E84,3)&I84 -> UC_TMCNGLO | C84: TM* | E84: TMCNG | F84: TM | G84: TM | H84: 2020 | I84: LO | J84: 1 | K84: 0 | L84: 15 | O84: =-'AEO Data'!$AI$17*0.9 -> -0.0069313329 | P84: =O84 -> -0.0069313329 | Q84: =P84 -> -0.0069313329 | R84: =Q84 -> -0.0069313329 | S84: =R84 -> -0.0069313329
C85: TM* | E85: TMCNG | F85: TM | G85: TM | H85: 2025 | J85: 1
C86: TM* | E86: TMCNG | F86: TM | G86: TM | H86: 2030 | J86: 1
C87: TM* | E87: TMCNG | F87: TM | G87: TM | H87: 2035 | J87: 1 | O87: =-'AEO Data'!$AJ$17*0.99 -> -0.017617566 | P87: =O87 -> -0.017617566 | Q87: =P87 -> -0.017617566 | R87: =Q87 -> -0.017617566 | S87: =R87 -> -0.017617566
C88: TM* | E88: TMCNG | F88: TM | G88: TM | H88: 2040 | J88: 1
C89: TM* | E89: TMCNG | F89: TM | G89: TM | H89: 2045 | J89: 1
C90: TM* | E90: TMCNG | F90: TM | G90: TM | H90: 2050 | J90: 1
C91: TM* | E91: TMCNG | F91: TM | G91: TM | H91: 2055 | J91: 1 | O91: =O87*U91 -> -0.015855809 | P91: =O91 -> -0.015855809 | Q91: =P91 -> -0.015855809 | R91: =Q91 -> -0.015855809 | S91: =R91 -> -0.015855809 | U91: 0.9
B92: ="UC_"&G92&RIGHT(E92,3)&I92 -> UC_TMCNGUP | C92: TM* | E92: TMCNG | F92: TM | G92: TM | H92: 2015 | I92: UP | J92: 1 | K92: 0 | L92: 15 | O92: -0.0033659472 | P92: =O92 -> -0.0033659472 | Q92: =P92 -> -0.0033659472 | R92: =Q92 -> -0.0033659472 | S92: =R92 -> -0.0033659472
C93: TM* | E93: TMCNG | F93: TM | G93: TM | H93: 2020 | J93: 1 | O93: =-'AEO Data'!$O$172*1.1 -> -0.0077966711 | P93: =O93 -> -0.0077966711 | Q93: =P93 -> -0.0077966711 | R93: =Q93 -> -0.0077966711 | S93: =R93 -> -0.0077966711
C94: TM* | E94: TMCNG | F94: TM | G94: TM | H94: 2025 | J94: 1
C95: TM* | E95: TMCNG | F95: TM | G95: TM | H95: 2030 | J95: 1
C96: TM* | E96: TMCNG | F96: TM | G96: TM | H96: 2035 | J96: 1 | O96: =-'AEO Data'!$Q$172*1.15 -> -0.047062816 | P96: =O96 -> -0.047062816 | Q96: =P96 -> -0.047062816 | R96: =Q96 -> -0.047062816 | S96: =R96 -> -0.047062816
C97: TM* | E97: TMCNG | F97: TM | G97: TM | H97: 2040 | J97: 1 | O97: =-'AEO Data'!$R$172*1.15 -> -0.097516295 | P97: =O97 -> -0.097516295 | Q97: =P97 -> -0.097516295 | R97: =Q97 -> -0.097516295 | S97: =R97 -> -0.097516295
C98: TM* | E98: TMCNG | F98: TM | G98: TM | H98: 2045 | J98: 1
C99: TM* | E99: TMCNG | F99: TM | G99: TM | H99: 2050 | J99: 1
C100: TM* | E100: TMCNG | F100: TM | G100: TM | H100: 2055 | J100: 1 | O100: =O97*U100 -> -0.11214374 | P100: =O100 -> -0.11214374 | Q100: =P100 -> -0.11214374 | R100: =Q100 -> -0.11214374 | S100: =R100 -> -0.11214374 | U100: 1.15
B101: ="UC_"&G101&RIGHT(E101,3)&I101 -> UC_TMELCLO | C101: TM* | E101: TRNELC | F101: TM | G101: TM | H101: 2020 | I101: LO | J101: 1 | K101: 0 | L101: 15 | O101: 0 | P101: 0 | Q101: 0 | R101: 0 | S101: 0
C102: TM* | E102: TRNELC | F102: TM | G102: TM | H102: 2025 | J102: 1 | O102: =-0.91% -> -0.0091 | P102: =-0.91% -> -0.0091 | Q102: =-0.91% -> -0.0091 | R102: =-0.91% -> -0.0091 | S102: =-0.91% -> -0.0091
C103: TM* | E103: TRNELC | F103: TM | G103: TM | H103: 2030 | J103: 1 | O103: =O102 -> -0.0091 | P103: =P102 -> -0.0091 | Q103: =Q102 -> -0.0091 | R103: =R102 -> -0.0091 | S103: =S102 -> -0.0091
C104: TM* | E104: TRNELC | F104: TM | G104: TM | H104: 2035 | J104: 1 | O104: =O103 -> -0.0091 | P104: =P103 -> -0.0091 | Q104: =Q103 -> -0.0091 | R104: =R103 -> -0.0091 | S104: =S103 -> -0.0091
...

Sheet UC_TRNHDVb
A1: Heavy duty vehicle historical boundary calibration
F5: ~UC_Sets: R_S: AllRegions
K7: ~UC_T: UC_FLO
F8: UC_N | G8: Pset_PN | H8: Pset_PD | I8: Pset_CI | J8: Cset_CN | K8: Year | L8: LimType | M8: UC_RHSRT | N8: UC_RHSRT~0 | O8: AllRegions
A9: 2015 | B9: ='ON-Road Historical share'!L21 -> THS | C9: ='ON-Road Historical share'!M21 -> CNG | F9: ="UC_"&J9&C9&"FX"&A9 -> UC_THSCNGFX2015 | G9: =IF(D9="",B9&"*"&C9&"*",B9&"*"&C9&"*"&",-"&B9&"*"&D9) -> THS*CNG* | J9: =B9 -> THS | K9: =A9 -> 2015 | L9: FX | M9: 0 | N9: -1 | O9: =O10-1 -> -1
G10: =IF(D9="",B9&"*"&",-"&B9&"*"&C9&"*",B9&"*"&",-"&B9&"*"&C9&"*"&","&B9&"*"&D9&"*") -> THS*,-THS*CNG* | J10: =J9 -> THS | K10: =K9 -> 2015 | O10: ='ON-Road Historical share'!U21 -> 0
A11: 2020 | B11: =B9 -> THS | C11: =C9 -> CNG | F11: ="UC_"&J11&C11&"FX"&A11 -> UC_THSCNGFX2020 | G11: =IF(D11="",B11&"*"&C11&"*",B11&"*"&C11&"*"&",-"&B11&"*"&D11) -> THS*CNG* | J11: =B11 -> THS | K11: =A11 -> 2020 | L11: FX | M11: 0 | N11: -1 | O11: =O12-1 -> -0.99326135
G12: =IF(D11="",B11&"*"&",-"&B11&"*"&C11&"*",B11&"*"&",-"&B11&"*"&C11&"*"&","&B11&"*"&D11&"*") -> THS*,-THS*CNG* | J12: =J11 -> THS | K12: =K11 -> 2020 | O12: ='ON-Road Historical share'!V21 -> 0.0067386512
A13: 2025 | B13: =B11 -> THS | C13: =C11 -> CNG | F13: ="UC_"&J13&C13&"FX"&A13 -> UC_THSCNGFX2025 | G13: =IF(D13="",B13&"*"&C13&"*",B13&"*"&C13&"*"&",-"&B13&"*"&D13) -> THS*CNG* | J13: =B13 -> THS | K13: =A13 -> 2025 | L13: FX | M13: 0 | N13: -1 | O13: =O14-1 -> -0.99057703
G14: =IF(D13="",B13&"*"&",-"&B13&"*"&C13&"*",B13&"*"&",-"&B13&"*"&C13&"*"&","&B13&"*"&D13&"*") -> THS*,-THS*CNG* | J14: =J13 -> THS | K14: =K13 -> 2025 | O14: ='ON-Road Historical share'!W21 -> 0.0094229723
A15: =A9 -> 2015 | B15: ='ON-Road Historical share'!L22 -> THS | C15: ='ON-Road Historical share'!M22 -> DSL | D15: ='ON-Road Historical share'!N36 -> DHEV | F15: ="UC_"&J15&C15&"FX"&A15 -> UC_THSDSLFX2015 | G15: =IF(D15="",B15&"*"&C15&"*",B15&"*"&C15&"*"&",-"&B15&"*"&D15&"*") -> THS*DSL*,-THS*DHEV* | J15: =B15 -> THS | K15: =A15 -> 2015 | L15: FX | M15: 0 | N15: -1 | O15: =O16-1 -> 0
G16: =IF(D15="",B15&"*"&",-"&B15&"*"&C15&"*",B15&"*"&",-"&B15&"*"&C15&"*"&","&B15&"*"&D15&"*") -> THS*,-THS*DSL*,THS*DHEV* | J16: =J15 -> THS | K16: =K15 -> 2015 | O16: ='ON-Road Historical share'!U22 -> 1
A17: =A11 -> 2020 | B17: =B15 -> THS | C17: =C15 -> DSL | D17: =D15 -> DHEV | F17: ="UC_"&J17&C17&"FX"&A17 -> UC_THSDSLFX2020 | G17: =IF(D17="",B17&"*"&C17&"*",B17&"*"&C17&"*"&",-"&B17&"*"&D17&"*") -> THS*DSL*,-THS*DHEV* | J17: =B17 -> THS | K17: =A17 -> 2020 | L17: FX | M17: 0 | N17: -1 | O17: =O18-1 -> -0.022539545
G18: =IF(D17="",B17&"*"&",-"&B17&"*"&C17&"*",B17&"*"&",-"&B17&"*"&C17&"*"&","&B17&"*"&D17&"*") -> THS*,-THS*DSL*,THS*DHEV* | J18: =J17 -> THS | K18: =K17 -> 2020 | O18: ='ON-Road Historical share'!V22 -> 0.97746046
A19: =A13 -> 2025 | B19: =B17 -> THS | C19: =C17 -> DSL | D19: =D17 -> DHEV | F19: ="UC_"&J19&C19&"FX"&A19 -> UC_THSDSLFX2025 | G19: =IF(D19="",B19&"*"&C19&"*",B19&"*"&C19&"*"&",-"&B19&"*"&D19&"*") -> THS*DSL*,-THS*DHEV* | J19: =B19 -> THS | K19: =A19 -> 2025 | L19: FX | M19: 0 | N19: -1 | O19: =O20-1 -> -0.031457208
G20: =IF(D19="",B19&"*"&",-"&B19&"*"&C19&"*",B19&"*"&",-"&B19&"*"&C19&"*"&","&B19&"*"&D19&"*") -> THS*,-THS*DSL*,THS*DHEV* | J20: =J19 -> THS | K20: =K19 -> 2025 | O20: ='ON-Road Historical share'!W22 -> 0.96854279
A21: =A15 -> 2015 | B21: ='ON-Road Historical share'!L23 -> THS | C21: ='ON-Road Historical share'!M23 -> DSLH | F21: ="UC_"&J21&C21&"FX"&A21 -> UC_THSDSLHFX2015 | G21: =IF(D21="",B21&"*"&C21&"*",B21&"*"&C21&"*"&",-"&B21&"*"&D21) -> THS*DSLH* | J21: =B21 -> THS | K21: =A21 -> 2015 | L21: FX | M21: 0 | N21: -1 | O21: =O22-1 -> -1
G22: =IF(D21="",B21&"*"&",-"&B21&"*"&C21&"*",B21&"*"&",-"&B21&"*"&C21&"*"&","&B21&"*"&D21&"*") -> THS*,-THS*DSLH* | J22: =J21 -> THS | K22: =K21 -> 2015 | O22: ='ON-Road Historical share'!U23 -> 0
A23: =A17 -> 2020 | B23: =B21 -> THS | C23: =C21 -> DSLH | F23: ="UC_"&J23&C23&"FX"&A23 -> UC_THSDSLHFX2020 | G23: =IF(D23="",B23&"*"&C23&"*",B23&"*"&C23&"*"&",-"&B23&"*"&D23) -> THS*DSLH* | J23: =B23 -> THS | K23: =A23 -> 2020 | L23: FX | M23: 0 | N23: -1 | O23: =O24-1 -> -0.99855748
G24: =IF(D23="",B23&"*"&",-"&B23&"*"&C23&"*",B23&"*"&",-"&B23&"*"&C23&"*"&","&B23&"*"&D23&"*") -> THS*,-THS*DSLH* | J24: =J23 -> THS | K24: =K23 -> 2020 | O24: ='ON-Road Historical share'!V23 -> 0.0014425177
A25: =A19 -> 2025 | B25: =B23 -> THS | C25: =C23 -> DSLH | F25: ="UC_"&J25&C25&"FX"&A25 -> UC_THSDSLHFX2025 | G25: =IF(D25="",B25&"*"&C25&"*",B25&"*"&C25&"*"&",-"&B25&"*"&D25) -> THS*DSLH* | J25: =B25 -> THS | K25: =A25 -> 2025 | L25: FX | M25: 0 | N25: -1 | O25: =O26-1 -> -0.99798378
G26: =IF(D25="",B25&"*"&",-"&B25&"*"&C25&"*",B25&"*"&",-"&B25&"*"&C25&"*"&","&B25&"*"&D25&"*") -> THS*,-THS*DSLH* | J26: =J25 -> THS | K26: =K25 -> 2025 | O26: ='ON-Road Historical share'!W23 -> 0.0020162159
A27: =A21 -> 2015 | B27: ='ON-Road Historical share'!L24 -> THS | C27: ='ON-Road Historical share'!M24 -> ELC | F27: ="UC_"&J27&C27&"FX"&A27 -> UC_THSELCFX2015 | G27: =IF(D27="",B27&"*"&C27&"*",B27&"*"&C27&"*"&",-"&B27&"*"&D27) -> THS*ELC* | J27: =B27 -> THS | K27: =A27 -> 2015 | L27: FX | M27: 0 | N27: -1 | O27: =O28-1 -> -1
G28: =IF(D27="",B27&"*"&",-"&B27&"*"&C27&"*",B27&"*"&",-"&B27&"*"&C27&"*"&","&B27&"*"&D27&"*") -> THS*,-THS*ELC* | J28: =J27 -> THS | K28: =K27 -> 2015 | O28: ='ON-Road Historical share'!U24 -> 0
A29: =A23 -> 2020 | B29: =B27 -> THS | C29: =C27 -> ELC | F29: ="UC_"&J29&C29&"FX"&A29 -> UC_THSELCFX2020 | G29: =IF(D29="",B29&"*"&C29&"*",B29&"*"&C29&"*"&",-"&B29&"*"&D29) -> THS*ELC* | J29: =B29 -> THS | K29: =A29 -> 2020 | L29: FX | M29: 0 | N29: -1 | O29: =O30-1 -> -1
G30: =IF(D29="",B29&"*"&",-"&B29&"*"&C29&"*",B29&"*"&",-"&B29&"*"&C29&"*"&","&B29&"*"&D29&"*") -> THS*,-THS*ELC* | J30: =J29 -> THS | K30: =K29 -> 2020 | O30: ='ON-Road Historical share'!V24 -> 0
A31: =A25 -> 2025 | B31: =B29 -> THS | C31: =C29 -> ELC | F31: ="UC_"&J31&C31&"FX"&A31 -> UC_THSELCFX2025 | G31: =IF(D31="",B31&"*"&C31&"*",B31&"*"&C31&"*"&",-"&B31&"*"&D31) -> THS*ELC* | J31: =B31 -> THS | K31: =A31 -> 2025 | L31: FX | M31: 0 | N31: -1 | O31: =O32-1 -> -1
G32: =IF(D31="",B31&"*"&",-"&B31&"*"&C31&"*",B31&"*"&",-"&B31&"*"&C31&"*"&","&B31&"*"&D31&"*") -> THS*,-THS*ELC* | J32: =J31 -> THS | K32: =K31 -> 2025 | O32: ='ON-Road Historical share'!W24 -> 0
A33: =A27 -> 2015 | B33: ='ON-Road Historical share'!L25 -> THS | C33: ='ON-Road Historical share'!M25 -> GSL | D33: ='ON-Road Historical share'!N25 -> GSLH | F33: ="UC_"&J33&C33&"FX"&A33 -> UC_THSGSLFX2015 | G33: =IF(D33="",B33&"*"&C33&"*",B33&"*"&C33&"*"&",-"&B33&"*"&D33&"*") -> THS*GSL*,-THS*GSLH* | J33: =B33 -> THS | K33: =A33 -> 2015 | L33: FX | M33: 0 | N33: -1 | O33: =O34-1 -> -1
G34: =IF(D33="",B33&"*"&",-"&B33&"*"&C33&"*",B33&"*"&",-"&B33&"*"&C33&"*"&","&B33&"*"&D33&"*") -> THS*,-THS*GSL*,THS*GSLH* | J34: =J33 -> THS | K34: =K33 -> 2015 | O34: ='ON-Road Historical share'!U25 -> 0
A35: =A29 -> 2020 | B35: =B33 -> THS | C35: =C33 -> GSL | D35: =D33 -> GSLH | F35: ="UC_"&J35&C35&"FX"&A35 -> UC_THSGSLFX2020 | G35: =IF(D35="",B35&"*"&C35&"*",B35&"*"&C35&"*"&",-"&B35&"*"&D35&"*") -> THS*GSL*,-THS*GSLH* | J35: =B35 -> THS | K35: =A35 -> 2020 | L35: FX | M35: 0 | N35: -1 | O35: =O36-1 -> -0.98564162
G36: =IF(D35="",B35&"*"&",-"&B35&"*"&C35&"*",B35&"*"&",-"&B35&"*"&C35&"*"&","&B35&"*"&D35&"*") -> THS*,-THS*GSL*,THS*GSLH* | J36: =J35 -> THS | K36: =K35 -> 2020 | O36: ='ON-Road Historical share'!V25 -> 0.014358376
A37: =A31 -> 2025 | B37: =B35 -> THS | C37: =C35 -> GSL | D37: =D35 -> GSLH | F37: ="UC_"&J37&C37&"FX"&A37 -> UC_THSGSLFX2025 | G37: =IF(D37="",B37&"*"&C37&"*",B37&"*"&C37&"*"&",-"&B37&"*"&D37&"*") -> THS*GSL*,-THS*GSLH* | J37: =B37 -> THS | K37: =A37 -> 2025 | L37: FX | M37: 0 | N37: -1 | O37: =O38-1 -> -0.97998198
G38: =IF(D37="",B37&"*"&",-"&B37&"*"&C37&"*",B37&"*"&",-"&B37&"*"&C37&"*"&","&B37&"*"&D37&"*") -> THS*,-THS*GSL*,THS*GSLH* | J38: =J37 -> THS | K38: =K37 -> 2025 | O38: ='ON-Road Historical share'!W25 -> 0.02001802
A39: =A33 -> 2015 | B39: =B33 -> THS | C39: =D33 -> GSLH | F39: ="UC_"&J39&C39&"FX"&A39 -> UC_THSGSLHFX2015 | G39: =IF(D39="",B39&"*"&C39&"*",B39&"*"&C39&"*"&",-"&B39&"*"&D39&"*") -> THS*GSLH* | J39: =B39 -> THS | K39: =A39 -> 2015 | L39: FX | M39: 0 | N39: -1 | O39: =O40-1 -> -1
G40: =IF(D39="",B39&"*"&",-"&B39&"*"&C39&"*",B39&"*"&",-"&B39&"*"&C39&"*"&","&B39&"*"&D39&"*") -> THS*,-THS*GSLH* | J40: =J39 -> THS | K40: =K39 -> 2015 | O40: 0
A41: =A35 -> 2020 | B41: =B39 -> THS | C41: =C39 -> GSLH | F41: ="UC_"&J41&C41&"FX"&A41 -> UC_THSGSLHFX2020 | G41: =IF(D41="",B41&"*"&C41&"*",B41&"*"&C41&"*"&",-"&B41&"*"&D41&"*") -> THS*GSLH* | J41: =B41 -> THS | K41: =A41 -> 2020 | L41: FX | M41: 0 | N41: -1 | O41: =O42-1 -> -1
G42: =IF(D41="",B41&"*"&",-"&B41&"*"&C41&"*",B41&"*"&",-"&B41&"*"&C41&"*"&","&B41&"*"&D41&"*") -> THS*,-THS*GSLH* | J42: =J41 -> THS | K42: =K41 -> 2020 | O42: 0
A43: =A37 -> 2025 | B43: =B41 -> THS | C43: =C41 -> GSLH | F43: ="UC_"&J43&C43&"FX"&A43 -> UC_THSGSLHFX2025 | G43: =IF(D43="",B43&"*"&C43&"*",B43&"*"&C43&"*"&",-"&B43&"*"&D43&"*") -> THS*GSLH* | J43: =B43 -> THS | K43: =A43 -> 2025 | L43: FX | M43: 0 | N43: -1 | O43: =O44-1 -> -1
G44: =IF(D43="",B43&"*"&",-"&B43&"*"&C43&"*",B43&"*"&",-"&B43&"*"&C43&"*"&","&B43&"*"&D43&"*") -> THS*,-THS*GSLH* | J44: =J43 -> THS | K44: =K43 -> 2025 | O44: 0
A45: =A33 -> 2015 | B45: =B37 -> THS | C45: H2G | F45: ="UC_"&J45&C45&"FX"&A45 -> UC_THSH2GFX2015 | G45: =IF(D45="",B45&"*"&C45&"*",B45&"*"&C45&"*"&",-"&B45&"*"&D45&"*") -> THS*H2G* | J45: =B45 -> THS | K45: =A45 -> 2015 | L45: FX | M45: 0 | N45: -1 | O45: =O46-1 -> -1
G46: =IF(D45="",B45&"*"&",-"&B45&"*"&C45&"*",B45&"*"&",-"&B45&"*"&C45&"*"&","&B45&"*"&D45&"*") -> THS*,-THS*H2G* | J46: =J45 -> THS | K46: =K45 -> 2015 | O46: 0
A47: =A35 -> 2020 | B47: =B45 -> THS | C47: =C45 -> H2G | F47: ="UC_"&J47&C47&"FX"&A47 -> UC_THSH2GFX2020 | G47: =IF(D47="",B47&"*"&C47&"*",B47&"*"&C47&"*"&",-"&B47&"*"&D47&"*") -> THS*H2G* | J47: =B47 -> THS | K47: =A47 -> 2020 | L47: FX | M47: 0 | N47: -1 | O47: =O48-1 -> -1
G48: =IF(D47="",B47&"*"&",-"&B47&"*"&C47&"*",B47&"*"&",-"&B47&"*"&C47&"*"&","&B47&"*"&D47&"*") -> THS*,-THS*H2G* | J48: =J47 -> THS | K48: =K47 -> 2020 | O48: 0
A49: =A37 -> 2025 | B49: =B47 -> THS | C49: =C47 -> H2G | F49: ="UC_"&J49&C49&"FX"&A49 -> UC_THSH2GFX2025 | G49: =IF(D49="",B49&"*"&C49&"*",B49&"*"&C49&"*"&",-"&B49&"*"&D49&"*") -> THS*H2G* | J49: =B49 -> THS | K49: =A49 -> 2025 | L49: FX | M49: 0 | N49: -1 | O49: =O50-1 -> -1
G50: =IF(D49="",B49&"*"&",-"&B49&"*"&C49&"*",B49&"*"&",-"&B49&"*"&C49&"*"&","&B49&"*"&D49&"*") -> THS*,-THS*H2G* | J50: =J49 -> THS | K50: =K49 -> 2025 | O50: 0
A51: =A33 -> 2015 | B51: ='ON-Road Historical share'!L26 -> TM | C51: ='ON-Road Historical share'!M26 -> CNG | F51: ="UC_"&J51&C51&"FX"&A51 -> UC_TMCNGFX2015 | G51: =IF(D51="",B51&"*"&C51&"*",B51&"*"&C51&"*"&",-"&B51&"*"&D51) -> TM*CNG* | J51: =B51 -> TM | K51: =A51 -> 2015 | L51: FX | M51: 0 | N51: -1 | O51: =O52-1 -> -0.99595976
G52: =IF(D51="",B51&"*"&",-"&B51&"*"&C51&"*",B51&"*"&",-"&B51&"*"&C51&"*"&","&B51&"*"&D51&"*") -> TM*,-TM*CNG* | J52: =J51 -> TM | K52: =K51 -> 2015 | O52: ='ON-Road Historical share'!U26 -> 0.0040402438
A53: =A35 -> 2020 | B53: =B51 -> TM | C53: =C51 -> CNG | F53: ="UC_"&J53&C53&"FX"&A53 -> UC_TMCNGFX2020 | G53: =IF(D53="",B53&"*"&C53&"*",B53&"*"&C53&"*"&",-"&B53&"*"&D53) -> TM*CNG* | J53: =B53 -> TM | K53: =A53 -> 2020 | L53: FX | M53: 0 | N53: -1 | O53: =O54-1 -> -0.99858323
G54: =IF(D53="",B53&"*"&",-"&B53&"*"&C53&"*",B53&"*"&",-"&B53&"*"&C53&"*"&","&B53&"*"&D53&"*") -> TM*,-TM*CNG* | J54: =J53 -> TM | K54: =K53 -> 2020 | O54: ='ON-Road Historical share'!V26 -> 0.0014167659
A55: =A37 -> 2025 | B55: =B53 -> TM | C55: =C53 -> CNG | F55: ="UC_"&J55&C55&"FX"&A55 -> UC_TMCNGFX2025 | G55: =IF(D55="",B55&"*"&C55&"*",B55&"*"&C55&"*"&",-"&B55&"*"&D55) -> TM*CNG* | J55: =B55 -> TM | K55: =A55 -> 2025 | L55: FX | M55: 0 | N55: -1 | O55: =O56-1 -> -0.99965705
G56: =IF(D55="",B55&"*"&",-"&B55&"*"&C55&"*",B55&"*"&",-"&B55&"*"&C55&"*"&","&B55&"*"&D55&"*") -> TM*,-TM*CNG* | J56: =J55 -> TM | K56: =K55 -> 2025 | O56: ='ON-Road Historical share'!W26 -> 0.00034295117
A57: =A51 -> 2015 | B57: ='ON-Road Historical share'!L27 -> TM | C57: ='ON-Road Historical share'!M27 -> DSL | D57: ='ON-Road Historical share'!N27 -> DSLAH | F57: ="UC_"&J57&C57&"FX"&A57 -> UC_TMDSLFX2015 | G57: =IF(D57="",B57&"*"&C57&"*",B57&"*"&C57&"*"&",-"&B57&"*"&D57&"*") -> TM*DSL*,-TM*DSLAH* | J57: =B57 -> TM | K57: =A57 -> 2015 | L57: FX | M57: 0 | N57: -1 | O57: =O58-1 -> -0.70703805
G58: =IF(D57="",B57&"*"&",-"&B57&"*"&C57&"*",B57&"*"&",-"&B57&"*"&C57&"*"&","&B57&"*"&D57&"*") -> TM*,-TM*DSL*,TM*DSLAH* | J58: =J57 -> TM | K58: =K57 -> 2015 | O58: ='ON-Road Historical share'!U27 -> 0.29296195
A59: =A53 -> 2020 | B59: =B57 -> TM | C59: =C57 -> DSL | D59: =D57 -> DSLAH | F59: ="UC_"&J59&C59&"FX"&A59 -> UC_TMDSLFX2020 | G59: =IF(D59="",B59&"*"&C59&"*",B59&"*"&C59&"*"&",-"&B59&"*"&D59&"*") -> TM*DSL*,-TM*DSLAH* | J59: =B59 -> TM | K59: =A59 -> 2020 | L59: FX | M59: 0 | N59: -1 | O59: =O60-1 -> -0.86653309
G60: =IF(D59="",B59&"*"&",-"&B59&"*"&C59&"*",B59&"*"&",-"&B59&"*"&C59&"*"&","&B59&"*"&D59&"*") -> TM*,-TM*DSL*,TM*DSLAH* | J60: =J59 -> TM | K60: =K59 -> 2020 | O60: ='ON-Road Historical share'!V27 -> 0.13346691
A61: =A55 -> 2025 | B61: =B59 -> TM | C61: =C59 -> DSL | D61: =D59 -> DSLAH | F61: ="UC_"&J61&C61&"FX"&A61 -> UC_TMDSLFX2025 | G61: =IF(D61="",B61&"*"&C61&"*",B61&"*"&C61&"*"&",-"&B61&"*"&D61&"*") -> TM*DSL*,-TM*DSLAH* | J61: =B61 -> TM | K61: =A61 -> 2025 | L61: FX | M61: 0 | N61: -1 | O61: =O62-1 -> -0.93181958
G62: =IF(D61="",B61&"*"&",-"&B61&"*"&C61&"*",B61&"*"&",-"&B61&"*"&C61&"*"&","&B61&"*"&D61&"*") -> TM*,-TM*DSL*,TM*DSLAH* | J62: =J61 -> TM | K62: =K61 -> 2025 | O62: ='ON-Road Historical share'!W27 -> 0.068180423
A63: =A57 -> 2015 | B63: =B57 -> TM | C63: DSLAH | F63: ="UC_"&J63&C63&"FX"&A63 -> UC_TMDSLAHFX2015 | G63: =IF(D63="",B63&"*"&C63&"*",B63&"*"&C63&"*"&",-"&B63&"*"&D63&"*") -> TM*DSLAH* | J63: =B63 -> TM | K63: =A63 -> 2015 | L63: FX | M63: 0 | N63: -1 | O63: =O64-1 -> -1
G64: =IF(D63="",B63&"*"&",-"&B63&"*"&C63&"*",B63&"*"&",-"&B63&"*"&C63&"*"&","&B63&"*"&D63&"*") -> TM*,-TM*DSLAH* | J64: =J63 -> TM | K64: =K63 -> 2015 | O64: 0
A65: =A59 -> 2020 | B65: =B63 -> TM | C65: =C63 -> DSLAH | F65: ="UC_"&J65&C65&"FX"&A65 -> UC_TMDSLAHFX2020 | G65: =IF(D65="",B65&"*"&C65&"*",B65&"*"&C65&"*"&",-"&B65&"*"&D65&"*") -> TM*DSLAH* | J65: =B65 -> TM | K65: =A65 -> 2020 | L65: FX | M65: 0 | N65: -1 | O65: =O66-1 -> -1
G66: =IF(D65="",B65&"*"&",-"&B65&"*"&C65&"*",B65&"*"&",-"&B65&"*"&C65&"*"&","&B65&"*"&D65&"*") -> TM*,-TM*DSLAH* | J66: =J65 -> TM | K66: =K65 -> 2020 | O66: 0
A67: =A61 -> 2025 | B67: =B65 -> TM | C67: =C65 -> DSLAH | F67: ="UC_"&J67&C67&"FX"&A67 -> UC_TMDSLAHFX2025 | G67: =IF(D67="",B67&"*"&C67&"*",B67&"*"&C67&"*"&",-"&B67&"*"&D67&"*") -> TM*DSLAH* | J67: =B67 -> TM | K67: =A67 -> 2025 | L67: FX | M67: 0 | N67: -1 | O67: =O68-1 -> -1
G68: =IF(D67="",B67&"*"&",-"&B67&"*"&C67&"*",B67&"*"&",-"&B67&"*"&C67&"*"&","&B67&"*"&D67&"*") -> TM*,-TM*DSLAH* | J68: =J67 -> TM | K68: =K67 -> 2025 | O68: 0
A69: =A57 -> 2015 | B69: ='ON-Road Historical share'!L28 -> TM | C69: ='ON-Road Historical share'!M28 -> ELC | F69: ="UC_"&J69&C69&"FX"&A69 -> UC_TMELCFX2015 | G69: =IF(D69="",B69&"*"&C69&"*",B69&"*"&C69&"*"&",-"&B69&"*"&D69) -> TM*ELC* | J69: =B69 -> TM | K69: =A69 -> 2015 | L69: FX | M69: 0 | N69: -1 | O69: =O70-1 -> -1
G70: =IF(D69="",B69&"*"&",-"&B69&"*"&C69&"*",B69&"*"&",-"&B69&"*"&C69&"*"&","&B69&"*"&D69&"*") -> TM*,-TM*ELC* | J70: =J69 -> TM | K70: =K69 -> 2015 | O70: ='ON-Road Historical share'!U28 -> 0
A71: =A59 -> 2020 | B71: =B69 -> TM | C71: =C69 -> ELC | F71: ="UC_"&J71&C71&"FX"&A71 -> UC_TMELCFX2020 | G71: =IF(D71="",B71&"*"&C71&"*",B71&"*"&C71&"*"&",-"&B71&"*"&D71) -> TM*ELC* | J71: =B71 -> TM | K71: =A71 -> 2020 | L71: FX | M71: 0 | N71: -1 | O71: =O72-1 -> -0.99249297
G72: =IF(D71="",B71&"*"&",-"&B71&"*"&C71&"*",B71&"*"&",-"&B71&"*"&C71&"*"&","&B71&"*"&D71&"*") -> TM*,-TM*ELC* | J72: =J71 -> TM | K72: =K71 -> 2020 | O72: ='ON-Road Historical share'!V28 -> 0.0075070265
A73: =A61 -> 2025 | B73: =B71 -> TM | C73: =C71 -> ELC | F73: ="UC_"&J73&C73&"FX"&A73 -> UC_TMELCFX2025 | G73: =IF(D73="",B73&"*"&C73&"*",B73&"*"&C73&"*"&",-"&B73&"*"&D73) -> TM*ELC* | J73: =B73 -> TM | K73: =A73 -> 2025 | L73: FX | M73: 0 | N73: -1 | O73: =O74-1 -> -0.98934446
G74: =IF(D73="",B73&"*"&",-"&B73&"*"&C73&"*",B73&"*"&",-"&B73&"*"&C73&"*"&","&B73&"*"&D73&"*") -> TM*,-TM*ELC* | J74: =J73 -> TM | K74: =K73 -> 2025 | O74: ='ON-Road Historical share'!W28 -> 0.010655537
A75: =A69 -> 2015 | B75: ='ON-Road Historical share'!L29 -> TM | C75: ='ON-Road Historical share'!M29 -> GSL | D75: ='ON-Road Historical share'!N29 -> GSLAH | F75: ="UC_"&J75&C75&"FX"&A75 -> UC_TMGSLFX2015 | G75: =IF(D75="",B75&"*"&C75&"*",B75&"*"&C75&"*"&",-"&B75&"*"&D75&"*") -> TM*GSL*,-TM*GSLAH* | J75: =B75 -> TM | K75: =A75 -> 2015 | L75: FX | M75: 0 | N75: -1 | O75: =O76-1 -> -0.29700219
G76: =IF(D75="",B75&"*"&",-"&B75&"*"&C75&"*",B75&"*"&",-"&B75&"*"&C75&"*"&","&B75&"*"&D75&"*") -> TM*,-TM*GSL*,TM*GSLAH* | J76: =J75 -> TM | K76: =K75 -> 2015 | O76: ='ON-Road Historical share'!U29 -> 0.70299781
A77: =A71 -> 2020 | B77: =B75 -> TM | C77: =C75 -> GSL | D77: =D75 -> GSLAH | F77: ="UC_"&J77&C77&"FX"&A77 -> UC_TMGSLFX2020 | G77: =IF(D77="",B77&"*"&C77&"*",B77&"*"&C77&"*"&",-"&B77&"*"&D77&"*") -> TM*GSL*,-TM*GSLAH* | J77: =B77 -> TM | K77: =A77 -> 2020 | L77: FX | M77: 0 | N77: -1 | O77: =O78-1 -> -0.14458101
G78: =IF(D77="",B77&"*"&",-"&B77&"*"&C77&"*",B77&"*"&",-"&B77&"*"&C77&"*"&","&B77&"*"&D77&"*") -> TM*,-TM*GSL*,TM*GSLAH* | J78: =J77 -> TM | K78: =K77 -> 2020 | O78: ='ON-Road Historical share'!V29 -> 0.85541899
A79: =A73 -> 2025 | B79: =B77 -> TM | C79: =C77 -> GSL | D79: =D77 -> GSLAH | F79: ="UC_"&J79&C79&"FX"&A79 -> UC_TMGSLFX2025 | G79: =IF(D79="",B79&"*"&C79&"*",B79&"*"&C79&"*"&",-"&B79&"*"&D79&"*") -> TM*GSL*,-TM*GSLAH* | J79: =B79 -> TM | K79: =A79 -> 2025 | L79: FX | M79: 0 | N79: -1 | O79: =O80-1 -> -0.082265472
G80: =IF(D79="",B79&"*"&",-"&B79&"*"&C79&"*",B79&"*"&",-"&B79&"*"&C79&"*"&","&B79&"*"&D79&"*") -> TM*,-TM*GSL*,TM*GSLAH* | J80: =J79 -> TM | K80: =K79 -> 2025 | O80: ='ON-Road Historical share'!W29 -> 0.91773453
A81: =A75 -> 2015 | B81: ='ON-Road Historical share'!L30 -> TM | C81: ='ON-Road Historical share'!M30 -> GSLAH | F81: ="UC_"&J81&C81&"FX"&A81 -> UC_TMGSLAHFX2015 | G81: =IF(D81="",B81&"*"&C81&"*",B81&"*"&C81&"*"&",-"&B81&"*"&D81) -> TM*GSLAH* | J81: =B81 -> TM | K81: =A81 -> 2015 | L81: FX | M81: 0 | N81: -1 | O81: =O82-1 -> -1
G82: =IF(D81="",B81&"*"&",-"&B81&"*"&C81&"*",B81&"*"&",-"&B81&"*"&C81&"*"&","&B81&"*"&D81&"*") -> TM*,-TM*GSLAH* | J82: =J81 -> TM | K82: =K81 -> 2015 | O82: ='ON-Road Historical share'!U30 -> 0
A83: =A77 -> 2020 | B83: =B81 -> TM | C83: =C81 -> GSLAH | F83: ="UC_"&J83&C83&"FX"&A83 -> UC_TMGSLAHFX2020 | G83: =IF(D83="",B83&"*"&C83&"*",B83&"*"&C83&"*"&",-"&B83&"*"&D83) -> TM*GSLAH* | J83: =B83 -> TM | K83: =A83 -> 2020 | L83: FX | M83: 0 | N83: -1 | O83: =O84-1 -> -0.99780969
G84: =IF(D83="",B83&"*"&",-"&B83&"*"&C83&"*",B83&"*"&",-"&B83&"*"&C83&"*"&","&B83&"*"&D83&"*") -> TM*,-TM*GSLAH* | J84: =J83 -> TM | K84: =K83 -> 2020 | O84: ='ON-Road Historical share'!V30 -> 0.0021903059
A85: =A79 -> 2025 | B85: =B83 -> TM | C85: =C83 -> GSLAH | F85: ="UC_"&J85&C85&"FX"&A85 -> UC_TMGSLAHFX2025 | G85: =IF(D85="",B85&"*"&C85&"*",B85&"*"&C85&"*"&",-"&B85&"*"&D85) -> TM*GSLAH* | J85: =B85 -> TM | K85: =A85 -> 2025 | L85: FX | M85: 0 | N85: -1 | O85: =O86-1 -> -0.99691344
G86: =IF(D85="",B85&"*"&",-"&B85&"*"&C85&"*",B85&"*"&",-"&B85&"*"&C85&"*"&","&B85&"*"&D85&"*") -> TM*,-TM*GSLAH* | J86: =J85 -> TM | K86: =K85 -> 2025 | O86: ='ON-Road Historical share'!W30 -> 0.0030865605
A87: =A81 -> 2015 | B87: =B85 -> TM | C87: H2G | F87: ="UC_"&J87&C87&"FX"&A87 -> UC_TMH2GFX2015 | G87: =IF(D87="",B87&"*"&C87&"*",B87&"*"&C87&"*"&",-"&B87&"*"&D87&"*") -> TM*H2G* | J87: =B87 -> TM | K87: =A87 -> 2015 | L87: FX | M87: 0 | N87: -1 | O87: =O88-1 -> -1
G88: =IF(D87="",B87&"*"&",-"&B87&"*"&C87&"*",B87&"*"&",-"&B87&"*"&C87&"*"&","&B87&"*"&D87&"*") -> TM*,-TM*H2G* | J88: =J87 -> TM | K88: =K87 -> 2015 | O88: 0
A89: =A83 -> 2020 | B89: =B87 -> TM | C89: =C87 -> H2G | F89: ="UC_"&J89&C89&"FX"&A89 -> UC_TMH2GFX2020 | G89: =IF(D89="",B89&"*"&C89&"*",B89&"*"&C89&"*"&",-"&B89&"*"&D89&"*") -> TM*H2G* | J89: =B89 -> TM | K89: =A89 -> 2020 | L89: FX | M89: 0 | N89: -1 | O89: =O90-1 -> -1
G90: =IF(D89="",B89&"*"&",-"&B89&"*"&C89&"*",B89&"*"&",-"&B89&"*"&C89&"*"&","&B89&"*"&D89&"*") -> TM*,-TM*H2G* | J90: =J89 -> TM | K90: =K89 -> 2020 | O90: 0
A91: =A85 -> 2025 | B91: =B89 -> TM | C91: =C89 -> H2G | F91: ="UC_"&J91&C91&"FX"&A91 -> UC_TMH2GFX2025 | G91: =IF(D91="",B91&"*"&C91&"*",B91&"*"&C91&"*"&",-"&B91&"*"&D91&"*") -> TM*H2G* | J91: =B91 -> TM | K91: =A91 -> 2025 | L91: FX | M91: 0 | N91: -1 | O91: =O92-1 -> -1
G92: =IF(D91="",B91&"*"&",-"&B91&"*"&C91&"*",B91&"*"&",-"&B91&"*"&C91&"*"&","&B91&"*"&D91&"*") -> TM*,-TM*H2G* | J92: =J91 -> TM | K92: =K91 -> 2025 | O92: 0
A93: =A81 -> 2015 | B93: ='ON-Road Historical share'!L31 -> TB | C93: ='ON-Road Historical share'!M31 -> DSL | D93: ='ON-Road Historical share'!N31 -> DSLAH | F93: ="UC_"&J93&C93&"FX"&A93 -> UC_TBDSLFX2015 | G93: =IF(D93="",B93&"*"&C93&"*",B93&"*"&C93&"*"&",-"&B93&"*"&D93&"*") -> TB*DSL*,-TB*DSLAH* | J93: =B93 -> TB | K93: =A93 -> 2015 | L93: FX | M93: 0 | N93: -1 | O93: =O94-1 -> -0.1128798
G94: =IF(D93="",B93&"*"&",-"&B93&"*"&C93&"*",B93&"*"&",-"&B93&"*"&C93&"*"&","&B93&"*"&D93&"*") -> TB*,-TB*DSL*,TB*DSLAH* | J94: =J93 -> TB | K94: =K93 -> 2015 | O94: ='ON-Road Historical share'!U31 -> 0.8871202
A95: =A83 -> 2020 | B95: =B93 -> TB | C95: =C93 -> DSL | D95: =D93 -> DSLAH | F95: ="UC_"&J95&C95&"FX"&A95 -> UC_TBDSLFX2020 | G95: =IF(D95="",B95&"*"&C95&"*",B95&"*"&C95&"*"&",-"&B95&"*"&D95&"*") -> TB*DSL*,-TB*DSLAH* | J95: =B95 -> TB | K95: =A95 -> 2020 | L95: FX | M95: 0 | N95: -1 | O95: =O96-1 -> -0.20913357
G96: =IF(D95="",B95&"*"&",-"&B95&"*"&C95&"*",B95&"*"&",-"&B95&"*"&C95&"*"&","&B95&"*"&D95&"*") -> TB*,-TB*DSL*,TB*DSLAH* | J96: =J95 -> TB | K96: =K95 -> 2020 | O96: ='ON-Road Historical share'!V31 -> 0.79086643
A97: =A85 -> 2025 | B97: =B95 -> TB | C97: =C95 -> DSL | D97: =D95 -> DSLAH | F97: ="UC_"&J97&C97&"FX"&A97 -> UC_TBDSLFX2025 | G97: =IF(D97="",B97&"*"&C97&"*",B97&"*"&C97&"*"&",-"&B97&"*"&D97&"*") -> TB*DSL*,-TB*DSLAH* | J97: =B97 -> TB | K97: =A97 -> 2025 | L97: FX | M97: 0 | N97: -1 | O97: =O98-1 -> -0.2859124
G98: =IF(D97="",B97&"*"&",-"&B97&"*"&C97&"*",B97&"*"&",-"&B97&"*"&C97&"*"&","&B97&"*"&D97&"*") -> TB*,-TB*DSL*,TB*DSLAH* | J98: =J97 -> TB | K98: =K97 -> 2025 | O98: ='ON-Road Historical share'!W31 -> 0.7140876
A99: =A93 -> 2015 | B99: ='ON-Road Historical share'!L32 -> TB | C99: ='ON-Road Historical share'!M32 -> ELC | F99: ="UC_"&J99&C99&"FX"&A99 -> UC_TBELCFX2015 | G99: =IF(D99="",B99&"*"&C99&"*",B99&"*"&C99&"*"&",-"&B99&"*"&D99) -> TB*ELC* | J99: =B99 -> TB | K99: =A99 -> 2015 | L99: FX | M99: 0 | N99: -1 | O99: =O100-1 -> -1
G100: =IF(D99="",B99&"*"&",-"&B99&"*"&C99&"*",B99&"*"&",-"&B99&"*"&C99&"*"&","&B99&"*"&D99&"*") -> TB*,-TB*ELC* | J100: =J99 -> TB | K100: =K99 -> 2015 | O100: ='ON-Road Historical share'!U32 -> 0
A101: =A95 -> 2020 | B101: =B99 -> TB | C101: =C99 -> ELC | F101: ="UC_"&J101&C101&"FX"&A101 -> UC_TBELCFX2020 | G101: =IF(D101="",B101&"*"&C101&"*",B101&"*"&C101&"*"&",-"&B101&"*"&D101) -> TB*ELC* | J101: =B101 -> TB | K101: =A101 -> 2020 | L101: FX | M101: 0 | N101: -1 | O101: =O102-1 -> -1
G102: =IF(D101="",B101&"*"&",-"&B101&"*"&C101&"*",B101&"*"&",-"&B101&"*"&C101&"*"&","&B101&"*"&D101&"*") -> TB*,-TB*ELC* | J102: =J101 -> TB | K102: =K101 -> 2020 | O102: ='ON-Road Historical share'!V32 -> 0
A103: =A97 -> 2025 | B103: =B101 -> TB | C103: =C101 -> ELC | F103: ="UC_"&J103&C103&"FX"&A103 -> UC_TBELCFX2025 | G103: =IF(D103="",B103&"*"&C103&"*",B103&"*"&C103&"*"&",-"&B103&"*"&D103) -> TB*ELC* | J103: =B103 -> TB | K103: =A103 -> 2025 | L103: FX | M103: 0 | N103: -1 | O103: =O104-1 -> -0.99992933
G104: =IF(D103="",B103&"*"&",-"&B103&"*"&C103&"*",B103&"*"&",-"&B103&"*"&C103&"*"&","&B103&"*"&D103&"*") -> TB*,-TB*ELC* | J104: =J103 -> TB | K104: =K103 -> 2025 | O104: ='ON-Road Historical share'!W32 -> 7.0673338e-05
...

Sheet ON-Road Historical share
Z2: On-road transportation
Z4: Header key | AC4: NOTE
Z5: Feeds | AA5: Community tab via INDEX | AC5: Table 3 of this tab should be populated by values from "On Road Transportation Summary 20XX" workbook. Use the VMT values in "table 3" of the "20XX Summary" tab
Z6: Feeds | AA6: Historical tab via 'aggregate tag'
Z7: Feeds | AA7: Both Community and Historical tab
AC9: 1000 | AF9: This step is required to correct the the fact that, to avoid problems when dividing by zero. the model set some cells to values fractionally higher than zero.
AC10: 0.001 | AF10: Lower bound for percentage of VMT to utilize - anything with a percentage below this will be set to 0 VMT
Z11: Table 1
Y12: Aggregate tag | Z12: Data source | AA12: GPC Sector | AB12: GPC Sub-sector | AC12: GPC Sub-sector class | AD12: GPC Sub-sector class agg | AE12: Address/service | AF12: Fuel type | AG12: Reported units | AH12: CY2022 | AI12: CY2021 | AJ12: CY2020 | AK12: CY2019 | AL12: CY2018 | AM12: CY2017 | AN12: CY2016 | AO12: CY2015 | AP12: CY2014 | AQ12: CY2013 | AR12: CY2012 | AS12: CY2011 | AT12: CY2010 | AU12: CY2009 | AV12: CY2008 | AW12: CY2007 | AX12: CY2006 | AY12: CY2005
Y13: Heavy duty trucks(private)CNG | Z13: NYMTC BPM | AA13: Transportation | AB13: On-road | AC13: Heavy duty trucks | AD13: Heavy duty trucks | AE13: (private) | AF13: CNG | AG13: VMT | AH13: 6398791.5 | AI13: 5317833.8 | AJ13: 4068498.7 | AK13: 3481673.7 | AL13: 2552442.9 | AM13: 1633232.8 | AN13: 805661.85 | AO13: 0 | AP13: 0 | AQ13: 0 | AR13: 0 | AS13: 0 | AT13: 0 | AU13: 0 | AV13: 0 | AW13: 0 | AX13: 0 | AY13: 0
Y14: Heavy duty trucks(private)Diesel | Z14: NYMTC BPM | AA14: Transportation | AB14: On-road | AC14: Heavy duty trucks | AD14: Heavy duty trucks | AE14: (private) | AF14: Diesel | AG14: VMT | AH14: 5.5015747e+08 | AI14: 5.3597055e+08 | AJ14: 4.9440372e+08 | AK14: 5.3136798e+08 | AL14: 5.2184428e+08 | AM14: 5.0321127e+08 | AN14: 4.9875703e+08 | AO14: 4.9188555e+08 | AP14: 4.8019396e+08 | AQ14: 4.9395273e+08 | AR14: 4.9204316e+08 | AS14: 5.0093796e+08 | AT14: 5.0243622e+08 | AU14: 4.5058508e+08 | AV14: 4.9222673e+08 | AW14: 5.1459198e+08 | AX14: 5.0452045e+08 | AY14: 4.9340266e+08
Y15: Heavy duty trucks(private)Electricity | Z15: NYMTC BPM | AA15: Transportation | AB15: On-road | AC15: Heavy duty trucks | AD15: Heavy duty trucks | AE15: (private) | AF15: Electricity | AG15: VMT | AH15: 0 | AI15: 0 | AJ15: 0 | AK15: 0 | AL15: 0 | AM15: 0 | AN15: 0 | AO15: 0 | AP15: 0 | AQ15: 0 | AR15: 0 | AS15: 0 | AT15: 0 | AU15: 0 | AV15: 0 | AW15: 0 | AX15: 0 | AY15: 0
Q16: 2019 | Y16: Heavy duty trucks(private)Gasoline | Z16: NYMTC BPM | AA16: Transportation | AB16: On-road | AC16: Heavy duty trucks | AD16: Heavy duty trucks | AE16: (private) | AF16: Gasoline | AG16: VMT | AH16: 11503965 | AI16: 9560569.4 | AJ16: 7314461.9 | AK16: 6259434 | AL16: 4588820.1 | AM16: 2936223.3 | AN16: 1448377.6 | AO16: 0 | AP16: 0 | AQ16: 0 | AR16: 0 | AS16: 0 | AT16: 0 | AU16: 0 | AV16: 0 | AW16: 0 | AX16: 0 | AY16: 0
O17: 2010 | P17: 2015 | Q17: 2021 | R17: 2022 | Y17: Heavy duty trucks(public)Diesel | Z17: NYMTC BPM | AA17: Transportation | AB17: On-road | AC17: Heavy duty trucks | AD17: Heavy duty trucks | AE17: (public) | AF17: Diesel | AG17: VMT | AH17: 1.0149074e+08 | AI17: 98705425 | AJ17: 90896735 | AK17: 97529071 | AL17: 95621910 | AM17: 92055591 | AN17: 91091462 | AO17: 89690607 | AP17: 87558751 | AQ17: 90067524 | AR17: 89719324 | AS17: 91341199 | AT17: 91614385 | AU17: 91587216 | AV17: 1.0005141e+08 | AW17: 1.0459742e+08 | AX17: 1.0255025e+08 | AY17: 1.0029041e+08
Y18: Heavy duty trucks(public)Diesel Hybrid | Z18: NYMTC BPM | AA18: Transportation | AB18: On-road | AC18: Heavy duty trucks | AD18: Heavy duty trucks | AE18: (public) | AF18: Diesel Hybrid | AG18: VMT | AH18: 1348977.7 | AI18: 1121090.5 | AJ18: 857706.76 | AK18: 733991.13 | AL18: 538090.85 | AM18: 344303.41 | AN18: 169834.93 | AO18: 0 | AP18: 0 | AQ18: 0 | AR18: 0 | AS18: 0 | AT18: 0 | AU18: 0 | AV18: 0 | AW18: 0 | AX18: 0 | AY18: 0
O19: Billion VMT | P19: Billion VMT | Q19: Billion VMT | R19: Billion VMT | S19: Billion VMT | Y19: Heavy duty trucks(public)Gasoline | Z19: NYMTC BPM | AA19: Transportation | AB19: On-road | AC19: Heavy duty trucks | AD19: Heavy duty trucks | AE19: (public) | AF19: Gasoline | AG19: VMT | AH19: 793516.32 | AI19: 659465.01 | AJ19: 504533.39 | AK19: 431759.49 | AL19: 316524.03 | AM19: 202531.41 | AN19: 99902.898 | AO19: 0 | AP19: 0 | AQ19: 0 | AR19: 0 | AS19: 0 | AT19: 0 | AU19: 0 | AV19: 0 | AW19: 0 | AX19: 0 | AY19: 0
B20: Row Labels | C20: Sum of CY2010 | D20: Sum of CY2015 | E20: Sum of CY2019 | F20: Sum of CY2021 | G20: Sum of CY2022 | O20: 2010 | P20: 2015 | Q20: 2020 | R20: 2022 | S20: 2025 | T20: Share 2010 | U20: Share 2015 | V20: Share 2020 | W20: Share 2025 | Y20: Medium duty trucks(private)CNG | Z20: NYMTC BPM | AA20: Transportation | AB20: On-road | AC20: Medium duty trucks | AD20: Medium duty trucks | AE20: (private) | AF20: CNG | AG20: VMT | AH20: 0 | AI20: 0 | AJ20: 0 | AK20: 0 | AL20: 0 | AM20: 0 | AN20: 0 | AO20: 0 | AP20: 0 | AQ20: 0 | AR20: 0 | AS20: 0 | AT20: 0 | AU20: 0 | AV20: 0 | AW20: 0 | AX20: 0 | AY20: 0
B21: Transportation | C21: 2.1148664e+10 | D21: 2.1182701e+10 | E21: 2.3114015e+10 | F21: 2.1741184e+10 | G21: 2.2959328e+10 | J21: Heavy duty trucks | K21: CNG | L21: THS | M21: CNG | O21: =(GETPIVOTDATA("Sum of CY"&$O$17,$B$20,"GPC Sector","Transportation","GPC Sub-sector","On-road","GPC Sub-sector class agg",$J21,"Fuel type",$K21))/10^6 -> 0 | P21: =(GETPIVOTDATA("Sum of CY"&$P$17,$B$20,"GPC Sector","Transportation","GPC Sub-sector","On-road","GPC Sub-sector class agg",$J21,"Fuel type",$K21))/10^6 -> 0 | Q21: =(GETPIVOTDATA("Sum of CY"&$Q$17,$B$20,"GPC Sector","Transportation","GPC Sub-sector","On-road","GPC Sub-sector class agg",$J21,"Fuel type",$K21)+GETPIVOTDATA("Sum of CY"&$Q$16,$B$20,"GPC Sector","Transportation","GPC Sub-sector","On-road","GPC Sub-sector class agg",$J21,"Fuel type",$K21))/2/10^6 -> 4.6241466 | R21: =(GETPIVOTDATA("Sum of CY"&$R$17,$B$20,"GPC Sector","Transportation","GPC Sub-sector","On-road","GPC Sub-sector class agg",$J21,"Fuel type",$K21))/10^6 -> 6.7146953 | S21: =IF(Q21+(R21-Q21)*5/2<0,0,Q21+(R21-Q21)*5/2) -> 9.8505182 | T21: =O21/SUMIFS(O:O,$L:$L,$L21) -> 0 | U21: =P21/SUMIFS(P:P,$L:$L,$L21) -> 0 | V21: =Q21/SUMIFS(Q:Q,$L:$L,$L21) -> 0.0067386512 | W21: =R21/SUMIFS(R:R,$L:$L,$L21) -> 0.0094229723 | Y21: Medium duty trucks(private)Diesel | Z21: NYMTC BPM | AA21: Transportation | AB21: On-road | AC21: Medium duty trucks | AD21: Medium duty trucks | AE21: (private) | AF21: Diesel | AG21: VMT | AH21: 11279307 | AI21: 27518399 | AJ21: 40144153 | AK21: 65719096 | AL21: 82839477 | AM21: 97508882 | AN21: 1.1235775e+08 | AO21: 1.2758889e+08 | AP21: 1.2048793e+08 | AQ21: 1.1411586e+08 | AR21: 1.0810908e+08 | AS21: 1.0605027e+08 | AT21: 1.054526e+08 | AU21: 1.0180514e+08 | AV21: 1.0463898e+08 | AW21: 1.0318043e+08 | AX21: 98103289 | AY21: 92375248
B22: On-road | C22: 2.1148664e+10 | D22: 2.1182701e+10 | E22: 2.3114015e+10 | F22: 2.1741184e+10 | G22: 2.2959328e+10 | J22: Heavy duty trucks | K22: Diesel | L22: THS | M22: DSL | N22: DSLH | O22: =(GETPIVOTDATA("Sum of CY"&$O$17,$B$20,"GPC Sector","Transportation","GPC Sub-sector","On-road","GPC Sub-sector class agg",$J22,"Fuel type",$K22))/10^6 -> 633.35834 | P22: =(GETPIVOTDATA("Sum of CY"&$P$17,$B$20,"GPC Sector","Transportation","GPC Sub-sector","On-road","GPC Sub-sector class agg",$J22,"Fuel type",$K22))/10^6 -> 621.59706 | Q22: =(GETPIVOTDATA("Sum of CY"&$Q$17,$B$20,"GPC Sector","Transportation","GPC Sub-sector","On-road","GPC Sub-sector class agg",$J22,"Fuel type",$K22)+GETPIVOTDATA("Sum of CY"&$Q$16,$B$20,"GPC Sector","Transportation","GPC Sub-sector","On-road","GPC Sub-sector class agg",$J22,"Fuel type",$K22))/2/10^6 -> 670.74557 | R22: =(GETPIVOTDATA("Sum of CY"&$R$17,$B$20,"GPC Sector","Transportation","GPC Sub-sector","On-road","GPC Sub-sector class agg",$J22,"Fuel type",$K22))/10^6 -> 690.1718 | S22: =IF(Q22+(R22-Q22)*5/2<0,0,Q22+(R22-Q22)*5/2) -> 719.31114 | T22: =O22/SUMIFS(O:O,$L:$L,$L22) -> 1 | U22: =P22/SUMIFS(P:P,$L:$L,$L22) -> 1 | V22: =Q22/SUMIFS(Q:Q,$L:$L,$L22) -> 0.97746046 | W22: =R22/SUMIFS(R:R,$L:$L,$L22) -> 0.96854279 | Y22: Medium duty trucks(private)Electricity | Z22: NYMTC BPM | AA22: Transportation | AB22: On-road | AC22: Medium duty trucks | AD22: Medium duty trucks | AE22: (private) | AF22: Electricity | AG22: VMT | AH22: 6205269.6 | AI22: 4937836.3 | AJ22: 3706644.4 | AK22: 3511328.2 | AL22: 2600150.9 | AM22: 1676984.2 | AN22: 820134.07 | AO22: 0 | AP22: 0 | AQ22: 0 | AR22: 0 | AS22: 0 | AT22: 0 | AU22: 0 | AV22: 0 | AW22: 0 | AX22: 0 | AY22: 0
B23: Buses | C23: 3.6282221e+08 | D23: 3.5717938e+08 | E23: 3.2287465e+08 | F23: 3.1066619e+08 | G23: 3.3052685e+08 | J23: Heavy duty trucks | K23: Diesel Hybrid | L23: THS | M23: DSLH | O23: =(GETPIVOTDATA("Sum of CY"&$O$17,$B$20,"GPC Sector","Transportation","GPC Sub-sector","On-road","GPC Sub-sector class agg",$J23,"Fuel type",$K23))/10^6 -> 0 | P23: =(GETPIVOTDATA("Sum of CY"&$P$17,$B$20,"GPC Sector","Transportation","GPC Sub-sector","On-road","GPC Sub-sector class agg",$J23,"Fuel type",$K23))/10^6 -> 0 | Q23: =(GETPIVOTDATA("Sum of CY"&$Q$17,$B$20,"GPC Sector","Transportation","GPC Sub-sector","On-road","GPC Sub-sector class agg",$J23,"Fuel type",$K23)+GETPIVOTDATA("Sum of CY"&$Q$16,$B$20,"GPC Sector","Transportation","GPC Sub-sector","On-road","GPC Sub-sector class agg",$J23,"Fuel type",$K23))/2/10^6 -> 0.98987368 | R23: =(GETPIVOTDATA("Sum of CY"&$R$17,$B$20,"GPC Sector","Transportation","GPC Sub-sector","On-road","GPC Sub-sector class agg",$J23,"Fuel type",$K23))/10^6 -> 1.4367309 | S23: =IF(Q23+(R23-Q23)*5/2<0,0,Q23+(R23-Q23)*5/2) -> 2.1070167 | T23: =O23/SUMIFS(O:O,$L:$L,$L23) -> 0 | U23: =P23/SUMIFS(P:P,$L:$L,$L23) -> 0 | V23: =Q23/SUMIFS(Q:Q,$L:$L,$L23) -> 0.0014425177 | W23: =R23/SUMIFS(R:R,$L:$L,$L23) -> 0.0020162159 | Y23: Medium duty trucks(private)Gasoline | Z23: NYMTC BPM | AA23: Transportation | AB23: On-road | AC23: Medium duty trucks | AD23: Medium duty trucks | AE23: (private) | AF23: Gasoline | AG23: VMT | AH23: 5.0550421e+08 | AI23: 4.5310636e+08 | AJ23: 3.9357101e+08 | AK23: 4.4877002e+08 | AL23: 4.2603506e+08 | AM23: 3.9566163e+08 | AN23: 3.7085217e+08 | AO23: 3.4990353e+08 | AP23: 3.3939282e+08 | AQ23: 3.3027735e+08 | AR23: 3.2160736e+08 | AS23: 3.2439318e+08 | AT23: 3.3180789e+08 | AU23: 3.2964821e+08 | AV23: 3.4883299e+08 | AW23: 3.5429561e+08 | AX23: 3.4714298e+08 | AY23: 3.3702346e+08
B24: CNG | C24: 37590232 | D24: 40318337 | E24: 30250532 | F24: 33248656 | G24: 43719634 | J24: Heavy duty trucks | K24: Electricity | L24: THS | M24: ELC | O24: =(GETPIVOTDATA("Sum of CY"&$O$17,$B$20,"GPC Sector","Transportation","GPC Sub-sector","On-road","GPC Sub-sector class agg",$J24,"Fuel type",$K24))/10^6 -> 0 | P24: =(GETPIVOTDATA("Sum of CY"&$P$17,$B$20,"GPC Sector","Transportation","GPC Sub-sector","On-road","GPC Sub-sector class agg",$J24,"Fuel type",$K24))/10^6 -> 0 | Q24: =(GETPIVOTDATA("Sum of CY"&$Q$17,$B$20,"GPC Sector","Transportation","GPC Sub-sector","On-road","GPC Sub-sector class agg",$J24,"Fuel type",$K24)+GETPIVOTDATA("Sum of CY"&$Q$16,$B$20,"GPC Sector","Transportation","GPC Sub-sector","On-road","GPC Sub-sector class agg",$J24,"Fuel type",$K24))/2/10^6 -> 0 | R24: =(GETPIVOTDATA("Sum of CY"&$R$17,$B$20,"GPC Sector","Transportation","GPC Sub-sector","On-road","GPC Sub-sector class agg",$J24,"Fuel type",$K24))/10^6 -> 0 | S24: =IF(Q24+(R24-Q24)*5/2<0,0,Q24+(R24-Q24)*5/2) -> 0 | T24: =O24/SUMIFS(O:O,$L:$L,$L24) -> 0 | U24: =P24/SUMIFS(P:P,$L:$L,$L24) -> 0 | V24: =Q24/SUMIFS(Q:Q,$L:$L,$L24) -> 0 | W24: =R24/SUMIFS(R:R,$L:$L,$L24) -> 0 | Y24: Medium duty trucks(public)CNG | Z24: NYMTC BPM | AA24: Transportation | AB24: On-road | AC24: Medium duty trucks | AD24: Medium duty trucks | AE24: (public) | AF24: CNG | AG24: VMT | AH24: 203240.43 | AI24: 479415.07 | AJ24: 693742.48 | AK24: 1131591.1 | AL24: 1423438.4 | AM24: 1673275 | AN24: 1926293.1 | AO24: 2185919.8 | AP24: 1892491.4 | AQ24: 1625562.1 | AR24: 1375390.8 | AS24: 1180900.9 | AT24: 999669.21 | AU24: 804110.87 | AV24: 633860.62 | AW24: 426304.96 | AX24: 207454.24 | AY24: 0
B25: Diesel | C25: 3.2523198e+08 | D25: 3.1686105e+08 | E25: 2.6569582e+08 | F25: 2.3535036e+08 | G25: 2.3602512e+08 | J25: Heavy duty trucks | K25: Gasoline | L25: THS | M25: GSL | N25: GSLH | O25: =(GETPIVOTDATA("Sum of CY"&$O$17,$B$20,"GPC Sector","Transportation","GPC Sub-sector","On-road","GPC Sub-sector class agg",$J25,"Fuel type",$K25))/10^6 -> 0 | P25: =(GETPIVOTDATA("Sum of CY"&$P$17,$B$20,"GPC Sector","Transportation","GPC Sub-sector","On-road","GPC Sub-sector class agg",$J25,"Fuel type",$K25))/10^6 -> 0 | Q25: =(GETPIVOTDATA("Sum of CY"&$Q$17,$B$20,"GPC Sector","Transportation","GPC Sub-sector","On-road","GPC Sub-sector class agg",$J25,"Fuel type",$K25)+GETPIVOTDATA("Sum of CY"&$Q$16,$B$20,"GPC Sector","Transportation","GPC Sub-sector","On-road","GPC Sub-sector class agg",$J25,"Fuel type",$K25))/2/10^6 -> 9.8528969 | R25: =(GETPIVOTDATA("Sum of CY"&$R$17,$B$20,"GPC Sector","Transportation","GPC Sub-sector","On-road","GPC Sub-sector class agg",$J25,"Fuel type",$K25))/10^6 -> 14.264597 | S25: =IF(Q25+(R25-Q25)*5/2<0,0,Q25+(R25-Q25)*5/2) -> 20.882147 | T25: =O25/SUMIFS(O:O,$L:$L,$L25) -> 0 | U25: =P25/SUMIFS(P:P,$L:$L,$L25) -> 0 | V25: =Q25/SUMIFS(Q:Q,$L:$L,$L25) -> 0.014358376 | W25: =R25/SUMIFS(R:R,$L:$L,$L25) -> 0.02001802 | Y25: Medium duty trucks(public)Diesel | Z25: NYMTC BPM | AA25: Transportation | AB25: On-road | AC25: Medium duty trucks | AD25: Medium duty trucks | AE25: (public) | AF25: Diesel | AG25: VMT | AH25: 29125917 | AI25: 27669746 | AJ25: 25492232 | AK25: 30858138 | AL25: 31130769 | AM25: 30758549 | AN25: 30711878 | AO25: 30914243 | AP25: 29858653 | AQ25: 28932714 | AR25: 28054156 | AS25: 28178739 | AT25: 28703354 | AU25: 28939167 | AV25: 30498827 | AW25: 30851646 | AX25: 30108174 | AY25: 29114935
B26: Electricity | C26: 0 | D26: 0 | E26: 0 | F26: 0 | G26: 23359.435 | J26: Medium duty trucks | K26: CNG | L26: TM | M26: CNG | O26: =(GETPIVOTDATA("Sum of CY"&$O$17,$B$20,"GPC Sector","Transportation","GPC Sub-sector","On-road","GPC Sub-sector class agg",$J26,"Fuel type",$K26))/10^6 -> 0.99966921 | P26: =(GETPIVOTDATA("Sum of CY"&$P$17,$B$20,"GPC Sector","Transportation","GPC Sub-sector","On-road","GPC Sub-sector class agg",$J26,"Fuel type",$K26))/10^6 -> 2.1859198 | Q26: =(GETPIVOTDATA("Sum of CY"&$Q$17,$B$20,"GPC Sector","Transportation","GPC Sub-sector","On-road","GPC Sub-sector class agg",$J26,"Fuel type",$K26)+GETPIVOTDATA("Sum of CY"&$Q$16,$B$20,"GPC Sector","Transportation","GPC Sub-sector","On-road","GPC Sub-sector class agg",$J26,"Fuel type",$K26))/2/10^6 -> 0.80550309 | R26: =(GETPIVOTDATA("Sum of CY"&$R$17,$B$20,"GPC Sector","Transportation","GPC Sub-sector","On-road","GPC Sub-sector class agg",$J26,"Fuel type",$K26))/10^6 -> 0.20324043 | S26: =IF(Q26+(R26-Q26)*5/2<0,0,Q26+(R26-Q26)*5/2) -> 0 | T26: =O26/SUMIFS(O:O,$L:$L,$L26) -> 0.002017697 | U26: =P26/SUMIFS(P:P,$L:$L,$L26) -> 0.0040402438 | V26: =Q26/SUMIFS(Q:Q,$L:$L,$L26) -> 0.0014167659 | W26: =R26/SUMIFS(R:R,$L:$L,$L26) -> 0.00034295117 | Y26: Medium duty trucks(public)Electricity | Z26: NYMTC BPM | AA26: Transportation | AB26: On-road | AC26: Medium duty trucks | AD26: Medium duty trucks | AE26: (public) | AF26: Electricity | AG26: VMT | AH26: 109437.16 | AI26: 87084.344 | AJ26: 65370.721 | AK26: 0 | AL26: 0 | AM26: 0 | AN26: 0 | AO26: 0 | AP26: 0 | AQ26: 0 | AR26: 0 | AS26: 0 | AT26: 0 | AU26: 0 | AV26: 0 | AW26: 0 | AX26: 0 | AY26: 0
B27: Gasoline | C27: 0 | D27: 0 | E27: 26928292 | F27: 42067176 | G27: 50758730 | J27: Medium duty trucks | K27: Diesel | L27: TM | M27: DSL | N27: DSLAH | O27: =(GETPIVOTDATA("Sum of CY"&$O$17,$B$20,"GPC Sector","Transportation","GPC Sub-sector","On-road","GPC Sub-sector class agg",$J27,"Fuel type",$K27))/10^6 -> 134.15595 | P27: =(GETPIVOTDATA("Sum of CY"&$P$17,$B$20,"GPC Sector","Transportation","GPC Sub-sector","On-road","GPC Sub-sector class agg",$J27,"Fuel type",$K27))/10^6 -> 158.50314 | Q27: =(GETPIVOTDATA("Sum of CY"&$Q$17,$B$20,"GPC Sector","Transportation","GPC Sub-sector","On-road","GPC Sub-sector class agg",$J27,"Fuel type",$K27)+GETPIVOTDATA("Sum of CY"&$Q$16,$B$20,"GPC Sector","Transportation","GPC Sub-sector","On-road","GPC Sub-sector class agg",$J27,"Fuel type",$K27))/2/10^6 -> 75.88269 | R27: =(GETPIVOTDATA("Sum of CY"&$R$17,$B$20,"GPC Sector","Transportation","GPC Sub-sector","On-road","GPC Sub-sector class agg",$J27,"Fuel type",$K27))/10^6 -> 40.405224 | S27: =IF(Q27+(R27-Q27)*5/2<0,0,Q27+(R27-Q27)*5/2) -> 0 | T27: =O27/SUMIFS(O:O,$L:$L,$L27) -> 0.27077563 | U27: =P27/SUMIFS(P:P,$L:$L,$L27) -> 0.29296195 | V27: =Q27/SUMIFS(Q:Q,$L:$L,$L27) -> 0.13346691 | W27: =R27/SUMIFS(R:R,$L:$L,$L27) -> 0.068180423 | Y27: Medium duty trucks(public)Gasoline | Z27: NYMTC BPM | AA27: Transportation | AB27: On-road | AC27: Medium duty trucks | AD27: Medium duty trucks | AE27: (public) | AF27: Gasoline | AG27: VMT | AH27: 38365540 | AI27: 34953813 | AJ27: 30888269 | AK27: 35867768 | AL27: 34714445 | AM27: 32907375 | AN27: 31524379 | AO27: 30444016 | AP27: 29449261 | AQ27: 28581066 | AR27: 27756626 | AS27: 27923282 | AT27: 28487102 | AU27: 28765219 | AV27: 30361708 | AW27: 30759426 | AX27: 30063296 | AY27: 29114935
B28: Heavy duty trucks | C28: 6.3335834e+08 | D28: 6.2159706e+08 | E28: 6.8032162e+08 | F28: 6.9210336e+08 | G28: 7.1258782e+08 | J28: Medium duty trucks | K28: Electricity | L28: TM | M28: ELC | O28: =(GETPIVOTDATA("Sum of CY"&$O$17,$B$20,"GPC Sector","Transportation","GPC Sub-sector","On-road","GPC Sub-sector class agg",$J28,"Fuel type",$K28))/10^6 -> 0 | P28: =(GETPIVOTDATA("Sum of CY"&$P$17,$B$20,"GPC Sector","Transportation","GPC Sub-sector","On-road","GPC Sub-sector class agg",$J28,"Fuel type",$K28))/10^6 -> 0 | Q28: =(GETPIVOTDATA("Sum of CY"&$Q$17,$B$20,"GPC Sector","Transportation","GPC Sub-sector","On-road","GPC Sub-sector class agg",$J28,"Fuel type",$K28)+GETPIVOTDATA("Sum of CY"&$Q$16,$B$20,"GPC Sector","Transportation","GPC Sub-sector","On-road","GPC Sub-sector class agg",$J28,"Fuel type",$K28))/2/10^6 -> 4.2681244 | R28: =(GETPIVOTDATA("Sum of CY"&$R$17,$B$20,"GPC Sector","Transportation","GPC Sub-sector","On-road","GPC Sub-sector class agg",$J28,"Fuel type",$K28))/10^6 -> 6.3147068 | S28: =IF(Q28+(R28-Q28)*5/2<0,0,Q28+(R28-Q28)*5/2) -> 9.3845804 | T28: =O28/SUMIFS(O:O,$L:$L,$L28) -> 0 | U28: =P28/SUMIFS(P:P,$L:$L,$L28) -> 0 | V28: =Q28/SUMIFS(Q:Q,$L:$L,$L28) -> 0.0075070265 | W28: =R28/SUMIFS(R:R,$L:$L,$L28) -> 0.010655537
B29: CNG | C29: 0 | D29: 0 | E29: 3660521.7 | F29: 5587771.6 | G29: 6714695.3 | J29: Medium duty trucks | K29: Gasoline | L29: TM | M29: GSL | N29: GSLAH | O29: =(GETPIVOTDATA("Sum of CY"&$O$17,$B$20,"GPC Sector","Transportation","GPC Sub-sector","On-road","GPC Sub-sector class agg",$J29,"Fuel type",$K29))/10^6 -> 360.29499 | P29: =(GETPIVOTDATA("Sum of CY"&$P$17,$B$20,"GPC Sector","Transportation","GPC Sub-sector","On-road","GPC Sub-sector class agg",$J29,"Fuel type",$K29))/10^6 -> 380.34755 | Q29: =(GETPIVOTDATA("Sum of CY"&$Q$17,$B$20,"GPC Sector","Transportation","GPC Sub-sector","On-road","GPC Sub-sector class agg",$J29,"Fuel type",$K29)+GETPIVOTDATA("Sum of CY"&$Q$16,$B$20,"GPC Sector","Transportation","GPC Sub-sector","On-road","GPC Sub-sector class agg",$J29,"Fuel type",$K29))/2/10^6 -> 486.34898 | R29: =(GETPIVOTDATA("Sum of CY"&$R$17,$B$20,"GPC Sector","Transportation","GPC Sub-sector","On-road","GPC Sub-sector class agg",$J29,"Fuel type",$K29))/10^6 -> 543.86975 | S29: =IF(Q29+(R29-Q29)*5/2<0,0,Q29+(R29-Q29)*5/2) -> 630.15089 | T29: =O29/SUMIFS(O:O,$L:$L,$L29) -> 0.72720667 | U29: =P29/SUMIFS(P:P,$L:$L,$L29) -> 0.70299781 | V29: =Q29/SUMIFS(Q:Q,$L:$L,$L29) -> 0.85541899 | W29: =R29/SUMIFS(R:R,$L:$L,$L29) -> 0.91773453 | Y29: Medium duty trucks(public)Gasoline Hybrid | Z29: NYMTC BPM | AA29: Transportation | AB29: On-road | AC29: Medium duty trucks | AD29: Medium duty trucks | AE29: (public) | AF29: Gasoline Hybrid | AG29: VMT | AH29: 1829163.9 | AI29: 1455552.6 | AJ29: 1092624.9 | AK29: 1035046.9 | AL29: 766451.24 | AM29: 494321.78 | AN29: 241740.79 | AO29: 0 | AP29: 0 | AQ29: 0 | AR29: 0 | AS29: 0 | AT29: 0 | AU29: 0 | AV29: 0 | AW29: 0 | AX29: 0 | AY29: 0
B30: Diesel | C30: 6.3335834e+08 | D30: 6.2159706e+08 | E30: 6.6807256e+08 | F30: 6.7341859e+08 | G30: 6.901718e+08 | J30: Medium duty trucks | K30: Gasoline Hybrid | L30: TM | M30: GSLAH | O30: =(GETPIVOTDATA("Sum of CY"&$O$17,$B$20,"GPC Sector","Transportation","GPC Sub-sector","On-road","GPC Sub-sector class agg",$J30,"Fuel type",$K30))/10^6 -> 0 | P30: =(GETPIVOTDATA("Sum of CY"&$P$17,$B$20,"GPC Sector","Transportation","GPC Sub-sector","On-road","GPC Sub-sector class agg",$J30,"Fuel type",$K30))/10^6 -> 0 | Q30: =(GETPIVOTDATA("Sum of CY"&$Q$17,$B$20,"GPC Sector","Transportation","GPC Sub-sector","On-road","GPC Sub-sector class agg",$J30,"Fuel type",$K30)+GETPIVOTDATA("Sum of CY"&$Q$16,$B$20,"GPC Sector","Transportation","GPC Sub-sector","On-road","GPC Sub-sector class agg",$J30,"Fuel type",$K30))/2/10^6 -> 1.2452997 | R30: =(GETPIVOTDATA("Sum of CY"&$R$17,$B$20,"GPC Sector","Transportation","GPC Sub-sector","On-road","GPC Sub-sector class agg",$J30,"Fuel type",$K30))/10^6 -> 1.8291639 | S30: =IF(Q30+(R30-Q30)*5/2<0,0,Q30+(R30-Q30)*5/2) -> 2.7049601 | T30: =O30/SUMIFS(O:O,$L:$L,$L30) -> 0 | U30: =P30/SUMIFS(P:P,$L:$L,$L30) -> 0 | V30: =Q30/SUMIFS(Q:Q,$L:$L,$L30) -> 0.0021903059 | W30: =R30/SUMIFS(R:R,$L:$L,$L30) -> 0.0030865605 | Y30: Passenger cars(private)CNG | Z30: NYMTC BPM | AA30: Transportation | AB30: On-road | AC30: Passenger cars | AD30: Passenger cars | AE30: (private) | AF30: CNG | AG30: VMT | AH30: 0 | AI30: 0 | AJ30: 0 | AK30: 0 | AL30: 0 | AM30: 0 | AN30: 0 | AO30: 0 | AP30: 0 | AQ30: 0 | AR30: 0 | AS30: 0 | AT30: 0 | AU30: 0 | AV30: 0 | AW30: 0 | AX30: 0 | AY30: 0
B31: Diesel Hybrid | C31: 0 | D31: 0 | E31: 783672.32 | F31: 1196075 | G31: 1436730.9 | J31: Buses | K31: Diesel | L31: TB | M31: DSL | N31: DSLAH | O31: =(GETPIVOTDATA("Sum of CY"&$O$17,$B$20,"GPC Sector","Transportation","GPC Sub-sector","On-road","GPC Sub-sector class agg",$J31,"Fuel type",$K31))/10^6 -> 325.23198 | P31: =(GETPIVOTDATA("Sum of CY"&$P$17,$B$20,"GPC Sector","Transportation","GPC Sub-sector","On-road","GPC Sub-sector class agg",$J31,"Fuel type",$K31))/10^6 -> 316.86105 | Q31: =(GETPIVOTDATA("Sum of CY"&$Q$17,$B$20,"GPC Sector","Transportation","GPC Sub-sector","On-road","GPC Sub-sector class agg",$J31,"Fuel type",$K31)+GETPIVOTDATA("Sum of CY"&$Q$16,$B$20,"GPC Sector","Transportation","GPC Sub-sector","On-road","GPC Sub-sector class agg",$J31,"Fuel type",$K31))/2/10^6 -> 250.52309 | R31: =(GETPIVOTDATA("Sum of CY"&$R$17,$B$20,"GPC Sector","Transportation","GPC Sub-sector","On-road","GPC Sub-sector class agg",$J31,"Fuel type",$K31))/10^6 -> 236.02512 | S31: =IF(Q31+(R31-Q31)*5/2<0,0,Q31+(R31-Q31)*5/2) -> 214.27817 | T31: =O31/SUMIFS(O:O,$L:$L,$L31) -> 0.8963949 | U31: =P31/SUMIFS(P:P,$L:$L,$L31) -> 0.8871202 | V31: =Q31/SUMIFS(Q:Q,$L:$L,$L31) -> 0.79086643 | W31: =R31/SUMIFS(R:R,$L:$L,$L31) -> 0.7140876 | Y31: Passenger cars(private)Diesel | Z31: NYMTC BPM | AA31: Transportation | AB31: On-road | AC31: Passenger cars | AD31: Passenger cars | AE31: (private) | AF31: Diesel | AG31: VMT | AH31: 1.35695e+08 | AI31: 1.4437044e+08 | AJ31: 1.3173031e+08 | AK31: 1.8782774e+08 | AL31: 2.0056401e+08 | AM31: 2.1055994e+08 | AN31: 2.2449686e+08 | AO31: 2.3373521e+08 | AP31: 2.1338913e+08 | AQ31: 2.0071866e+08 | AR31: 1.8734238e+08 | AS31: 1.7681504e+08 | AT31: 1.6846715e+08 | AU31: 1.477483e+08 | AV31: 1.3670816e+08 | AW31: 1.2828366e+08 | AX31: 1.1487412e+08 | AY31: 1.0151048e+08
B32: Electricity | C32: 0 | D32: 0 | E32: 0 | F32: 0 | G32: 0 | J32: Buses | K32: Electricity | L32: TB | M32: ELC | O32: =(GETPIVOTDATA("Sum of CY"&$O$17,$B$20,"GPC Sector","Transportation","GPC Sub-sector","On-road","GPC Sub-sector class agg",$J32,"Fuel type",$K32))/10^6 -> 0 | P32: =(GETPIVOTDATA("Sum of CY"&$P$17,$B$20,"GPC Sector","Transportation","GPC Sub-sector","On-road","GPC Sub-sector class agg",$J32,"Fuel type",$K32))/10^6 -> 0 | Q32: =(GETPIVOTDATA("Sum of CY"&$Q$17,$B$20,"GPC Sector","Transportation","GPC Sub-sector","On-road","GPC Sub-sector class agg",$J32,"Fuel type",$K32)+GETPIVOTDATA("Sum of CY"&$Q$16,$B$20,"GPC Sector","Transportation","GPC Sub-sector","On-road","GPC Sub-sector class agg",$J32,"Fuel type",$K32))/2/10^6 -> 0 | R32: =(GETPIVOTDATA("Sum of CY"&$R$17,$B$20,"GPC Sector","Transportation","GPC Sub-sector","On-road","GPC Sub-sector class agg",$J32,"Fuel type",$K32))/10^6 -> 0.023359436 | S32: =IF(Q32+(R32-Q32)*5/2<0,0,Q32+(R32-Q32)*5/2) -> 0.058398589 | T32: =O32/SUMIFS(O:O,$L:$L,$L32) -> 0 | U32: =P32/SUMIFS(P:P,$L:$L,$L32) -> 0 | V32: =Q32/SUMIFS(Q:Q,$L:$L,$L32) -> 0 | W32: =R32/SUMIFS(R:R,$L:$L,$L32) -> 7.0673338e-05 | Y32: Passenger cars(private)Diesel Hybrid | Z32: NYMTC BPM | AA32: Transportation | AB32: On-road | AC32: Passenger cars | AD32: Passenger cars | AE32: (private) | AF32: Diesel Hybrid | AG32: VMT | AH32: 0 | AI32: 0 | AJ32: 0 | AK32: 0 | AL32: 0 | AM32: 0 | AN32: 0 | AO32: 0 | AP32: 0 | AQ32: 0 | AR32: 0 | AS32: 0 | AT32: 0 | AU32: 0 | AV32: 0 | AW32: 0 | AX32: 0 | AY32: 0
B33: Gasoline | C33: 0 | D33: 0 | E33: 7804870.5 | F33: 11900923 | G33: 14264597 | J33: Buses | K33: Gasoline | L33: TB | M33: GSL | N33: GSLAH | O33: =(GETPIVOTDATA("Sum of CY"&$O$17,$B$20,"GPC Sector","Transportation","GPC Sub-sector","On-road","GPC Sub-sector class agg",$J33,"Fuel type",$K33))/10^6 -> 0 | P33: =(GETPIVOTDATA("Sum of CY"&$P$17,$B$20,"GPC Sector","Transportation","GPC Sub-sector","On-road","GPC Sub-sector class agg",$J33,"Fuel type",$K33))/10^6 -> 0 | Q33: =(GETPIVOTDATA("Sum of CY"&$Q$17,$B$20,"GPC Sector","Transportation","GPC Sub-sector","On-road","GPC Sub-sector class agg",$J33,"Fuel type",$K33)+GETPIVOTDATA("Sum of CY"&$Q$16,$B$20,"GPC Sector","Transportation","GPC Sub-sector","On-road","GPC Sub-sector class agg",$J33,"Fuel type",$K33))/2/10^6 -> 34.497734 | R33: =(GETPIVOTDATA("Sum of CY"&$R$17,$B$20,"GPC Sector","Transportation","GPC Sub-sector","On-road","GPC Sub-sector class agg",$J33,"Fuel type",$K33))/10^6 -> 50.75873 | S33: =IF(Q33+(R33-Q33)*5/2<0,0,Q33+(R33-Q33)*5/2) -> 75.150223 | T33: =O33/SUMIFS(O:O,$L:$L,$L33) -> 0 | U33: =P33/SUMIFS(P:P,$L:$L,$L33) -> 0 | V33: =Q33/SUMIFS(Q:Q,$L:$L,$L33) -> 0.10890453 | W33: =R33/SUMIFS(R:R,$L:$L,$L33) -> 0.15356916 | Y33: Passenger cars(private)Electricity | Z33: NYMTC BPM | AA33: Transportation | AB33: On-road | AC33: Passenger cars | AD33: Passenger cars | AE33: (private) | AF33: Electricity | AG33: VMT | AH33: 5.1605221e+08 | AI33: 4.2124991e+08 | AJ33: 2.9089884e+08 | AK33: 3.0556262e+08 | AL33: 2.2896976e+08 | AM33: 1.5384059e+08 | AN33: 84861122 | AO33: 0 | AP33: 0 | AQ33: 0 | AR33: 0 | AS33: 0 | AT33: 0 | AU33: 0 | AV33: 0 | AW33: 0 | AX33: 0 | AY33: 0
B34: Medium duty trucks | C34: 4.9545061e+08 | D34: 5.410366e+08 | E34: 5.8689299e+08 | F34: 5.502082e+08 | G34: 5.9262208e+08 | J34: Buses | K34: CNG | L34: TB | M34: CNG | O34: =(GETPIVOTDATA("Sum of CY"&$O$17,$B$20,"GPC Sector","Transportation","GPC Sub-sector","On-road","GPC Sub-sector class agg",$J34,"Fuel type",$K34))/10^6 -> 37.590232 | P34: =(GETPIVOTDATA("Sum of CY"&$P$17,$B$20,"GPC Sector","Transportation","GPC Sub-sector","On-road","GPC Sub-sector class agg",$J34,"Fuel type",$K34))/10^6 -> 40.318337 | Q34: =(GETPIVOTDATA("Sum of CY"&$Q$17,$B$20,"GPC Sector","Transportation","GPC Sub-sector","On-road","GPC Sub-sector class agg",$J34,"Fuel type",$K34)+GETPIVOTDATA("Sum of CY"&$Q$16,$B$20,"GPC Sector","Transportation","GPC Sub-sector","On-road","GPC Sub-sector class agg",$J34,"Fuel type",$K34))/2/10^6 -> 31.749594 | R34: =(GETPIVOTDATA("Sum of CY"&$R$17,$B$20,"GPC Sector","Transportation","GPC Sub-sector","On-road","GPC Sub-sector class agg",$J34,"Fuel type",$K34))/10^6 -> 43.719634 | S34: =IF(Q34+(R34-Q34)*5/2<0,0,Q34+(R34-Q34)*5/2) -> 61.674693 | T34: =O34/SUMIFS(O:O,$L:$L,$L34) -> 0.1036051 | U34: =P34/SUMIFS(P:P,$L:$L,$L34) -> 0.1128798 | V34: =Q34/SUMIFS(Q:Q,$L:$L,$L34) -> 0.10022904 | W34: =R34/SUMIFS(R:R,$L:$L,$L34) -> 0.13227256 | Y34: Passenger cars(private)Fuel Cell | Z34: NYMTC BPM | AA34: Transportation | AB34: On-road | AC34: Passenger cars | AD34: Passenger cars | AE34: (private) | AF34: Fuel Cell | AG34: VMT | AH34: 0 | AI34: 0 | AJ34: 0 | AK34: 0 | AL34: 0 | AM34: 0 | AN34: 0 | AO34: 0 | AP34: 0 | AQ34: 0 | AR34: 0 | AS34: 0 | AT34: 0 | AU34: 0 | AV34: 0 | AW34: 0 | AX34: 0 | AY34: 0
B35: CNG | C35: 999669.21 | D35: 2185919.8 | E35: 1131591.1 | F35: 479415.07 | G35: 203240.43 | J35: Passenger cars | K35: CNG | L35: TL | M35: CNG | O35: =(GETPIVOTDATA("Sum of CY"&$O$17,$B$20,"GPC Sector","Transportation","GPC Sub-sector","On-road","GPC Sub-sector class agg",$J35,"Fuel type",$K35))/10^6 -> 0 | P35: =(GETPIVOTDATA("Sum of CY"&$P$17,$B$20,"GPC Sector","Transportation","GPC Sub-sector","On-road","GPC Sub-sector class agg",$J35,"Fuel type",$K35))/10^6 -> 0 | Q35: =(GETPIVOTDATA("Sum of CY"&$Q$17,$B$20,"GPC Sector","Transportation","GPC Sub-sector","On-road","GPC Sub-sector class agg",$J35,"Fuel type",$K35)+GETPIVOTDATA("Sum of CY"&$Q$16,$B$20,"GPC Sector","Transportation","GPC Sub-sector","On-road","GPC Sub-sector class agg",$J35,"Fuel type",$K35))/2/10^6 -> 0 | R35: =(GETPIVOTDATA("Sum of CY"&$R$17,$B$20,"GPC Sector","Transportation","GPC Sub-sector","On-road","GPC Sub-sector class agg",$J35,"Fuel type",$K35))/10^6 -> 0 | S35: =IF(Q35+(R35-Q35)*5/2<0,0,Q35+(R35-Q35)*5/2) -> 0 | T35: =O35/SUMIFS(O:O,$L:$L,$L35) -> 0 | U35: =P35/SUMIFS(P:P,$L:$L,$L35) -> 0 | V35: =Q35/SUMIFS(Q:Q,$L:$L,$L35) -> 0 | W35: =R35/SUMIFS(R:R,$L:$L,$L35) -> 0 | Y35: Passenger cars(private)Gasoline | Z35: NYMTC BPM | AA35: Transportation | AB35: On-road | AC35: Passenger cars | AD35: Passenger cars | AE35: (private) | AF35: Gasoline | AG35: VMT | AH35: 1.941655e+10 | AI35: 1.8575339e+10 | AJ35: 1.5425812e+10 | AK35: 2.0215104e+10 | AL35: 2.0000031e+10 | AM35: 1.9586529e+10 | AN35: 1.9592916e+10 | AO35: 1.92342e+10 | AP35: 1.8617848e+10 | AQ35: 1.8632353e+10 | AR35: 1.8575946e+10 | AS35: 1.8811296e+10 | AT35: 1.9330346e+10 | AU35: 1.839386e+10 | AV35: 1.8596344e+10 | AW35: 1.922786e+10 | AX35: 1.9165763e+10 | AY35: 1.909094e+10
B36: Diesel | C36: 1.3415595e+08 | D36: 1.5850314e+08 | E36: 96577234 | F36: 55188145 | G36: 40405224 | J36: Passenger cars | K36: Diesel | L36: TL | M36: DSL | N36: DHEV | O36: =(GETPIVOTDATA("Sum of CY"&$O$17,$B$20,"GPC Sector","Transportation","GPC Sub-sector","On-road","GPC Sub-sector class agg",$J36,"Fuel type",$K36))/10^6 -> 168.46715 | P36: =(GETPIVOTDATA("Sum of CY"&$P$17,$B$20,"GPC Sector","Transportation","GPC Sub-sector","On-road","GPC Sub-sector class agg",$J36,"Fuel type",$K36))/10^6 -> 233.73521 | Q36: =(GETPIVOTDATA("Sum of CY"&$Q$17,$B$20,"GPC Sector","Transportation","GPC Sub-sector","On-road","GPC Sub-sector class agg",$J36,"Fuel type",$K36)+GETPIVOTDATA("Sum of CY"&$Q$16,$B$20,"GPC Sector","Transportation","GPC Sub-sector","On-road","GPC Sub-sector class agg",$J36,"Fuel type",$K36))/2/10^6 -> 166.58711 | R36: =(GETPIVOTDATA("Sum of CY"&$R$17,$B$20,"GPC Sector","Transportation","GPC Sub-sector","On-road","GPC Sub-sector class agg",$J36,"Fuel type",$K36))/10^6 -> 136.39804 | S36: =IF(Q36+(R36-Q36)*5/2<0,0,Q36+(R36-Q36)*5/2) -> 91.114447 | T36: =O36/SUMIFS(O:O,$L:$L,$L36) -> 0.0085703245 | U36: =P36/SUMIFS(P:P,$L:$L,$L36) -> 0.011887125 | V36: =Q36/SUMIFS(Q:Q,$L:$L,$L36) -> 0.0079874655 | W36: =R36/SUMIFS(R:R,$L:$L,$L36) -> 0.0063965792 | Y36: Passenger cars(private)Gasoline Hybrid | Z36: NYMTC BPM | AA36: Transportation | AB36: On-road | AC36: Passenger cars | AD36: Passenger cars | AE36: (private) | AF36: Gasoline Hybrid | AG36: VMT | AH36: 1.1234244e+09 | AI36: 9.2239951e+08 | AJ36: 6.4207891e+08 | AK36: 6.8232775e+08 | AL36: 5.2082815e+08 | AM36: 3.6201683e+08 | AN36: 2.1696355e+08 | AO36: 73260466 | AP36: 63748539 | AQ36: 56644696 | AR36: 49357650 | AS36: 42793719 | AT36: 36603697 | AU36: 27832626 | AV36: 21080315 | AW36: 0 | AX36: 0 | AY36: 0
B37: Electricity | C37: 0 | D37: 0 | E37: 3511328.2 | F37: 5024920.7 | G37: 6314706.8 | J37: Passenger cars | K37: Diesel Hybrid | L37: TL | M37: DHEV | O37: =(GETPIVOTDATA("Sum of CY"&$O$17,$B$20,"GPC Sector","Transportation","GPC Sub-sector","On-road","GPC Sub-sector class agg",$J37,"Fuel type",$K37))/10^6 -> 0 | P37: =(GETPIVOTDATA("Sum of CY"&$P$17,$B$20,"GPC Sector","Transportation","GPC Sub-sector","On-road","GPC Sub-sector class agg",$J37,"Fuel type",$K37))/10^6 -> 0 | Q37: =(GETPIVOTDATA("Sum of CY"&$Q$17,$B$20,"GPC Sector","Transportation","GPC Sub-sector","On-road","GPC Sub-sector class agg",$J37,"Fuel type",$K37)+GETPIVOTDATA("Sum of CY"&$Q$16,$B$20,"GPC Sector","Transportation","GPC Sub-sector","On-road","GPC Sub-sector class agg",$J37,"Fuel type",$K37))/2/10^6 -> 0 | R37: =(GETPIVOTDATA("Sum of CY"&$R$17,$B$20,"GPC Sector","Transportation","GPC Sub-sector","On-road","GPC Sub-sector class agg",$J37,"Fuel type",$K37))/10^6 -> 0 | S37: =IF(Q37+(R37-Q37)*5/2<0,0,Q37+(R37-Q37)*5/2) -> 0 | T37: =O37/SUMIFS(O:O,$L:$L,$L37) -> 0 | U37: =P37/SUMIFS(P:P,$L:$L,$L37) -> 0 | V37: =Q37/SUMIFS(Q:Q,$L:$L,$L37) -> 0 | W37: =R37/SUMIFS(R:R,$L:$L,$L37) -> 0 | Y37: Passenger cars(public)Diesel | Z37: NYMTC BPM | AA37: Transportation | AB37: On-road | AC37: Passenger cars | AD37: Passenger cars | AE37: (public) | AF37: Diesel | AG37: VMT | AH37: 703039.39 | AI37: 570519.24 | AJ37: 390768.72 | AK37: 405511.25 | AL37: 297871.47 | AM37: 192538.86 | AN37: 0 | AO37: 0 | AP37: 0 | AQ37: 0 | AR37: 0 | AS37: 0 | AT37: 0 | AU37: 0 | AV37: 0 | AW37: 0 | AX37: 0 | AY37: 0
B38: Gasoline | C38: 3.6029499e+08 | D38: 3.8034755e+08 | E38: 4.8463779e+08 | F38: 4.8806017e+08 | G38: 5.4386975e+08 | J38: Passenger cars | K38: Electricity | L38: TL | M38: ELC | O38: =(GETPIVOTDATA("Sum of CY"&$O$17,$B$20,"GPC Sector","Transportation","GPC Sub-sector","On-road","GPC Sub-sector class agg",$J38,"Fuel type",$K38))/10^6 -> 0.90905831 | P38: =(GETPIVOTDATA("Sum of CY"&$P$17,$B$20,"GPC Sector","Transportation","GPC Sub-sector","On-road","GPC Sub-sector class agg",$J38,"Fuel type",$K38))/10^6 -> 1.8133946 | Q38: =(GETPIVOTDATA("Sum of CY"&$Q$17,$B$20,"GPC Sector","Transportation","GPC Sub-sector","On-road","GPC Sub-sector class agg",$J38,"Fuel type",$K38)+GETPIVOTDATA("Sum of CY"&$Q$16,$B$20,"GPC Sector","Transportation","GPC Sub-sector","On-road","GPC Sub-sector class agg",$J38,"Fuel type",$K38))/2/10^6 -> 381.67212 | R38: =(GETPIVOTDATA("Sum of CY"&$R$17,$B$20,"GPC Sector","Transportation","GPC Sub-sector","On-road","GPC Sub-sector class agg",$J38,"Fuel type",$K38))/10^6 -> 541.56249 | S38: =IF(Q38+(R38-Q38)*5/2<0,0,Q38+(R38-Q38)*5/2) -> 781.39806 | T38: =O38/SUMIFS(O:O,$L:$L,$L38) -> 4.6245957e-05 | U38: =P38/SUMIFS(P:P,$L:$L,$L38) -> 9.2224224e-05 | V38: =Q38/SUMIFS(Q:Q,$L:$L,$L38) -> 0.018300293 | W38: =R38/SUMIFS(R:R,$L:$L,$L38) -> 0.025397339 | Y38: Passenger cars(public)Electricity | Z38: NYMTC BPM | AA38: Transportation | AB38: On-road | AC38: Passenger cars | AD38: Passenger cars | AE38: (public) | AF38: Electricity | AG38: VMT | AH38: 25510287 | AI38: 20967448 | AJ38: 14616172 | AK38: 15564262 | AL38: 11918473 | AM38: 8331686 | AN38: 5058829.9 | AO38: 1813394.6 | AP38: 1583208.3 | AQ38: 1406782.3 | AR38: 1225806.5 | AS38: 1062789.4 | AT38: 909058.31 | AU38: 726947.08 | AV38: 550585.47 | AW38: 379090.94 | AX38: 188719.02 | AY38: 0
B39: Gasoline Hybrid | C39: 0 | D39: 0 | E39: 1035046.9 | F39: 1455552.6 | G39: 1829163.9 | J39: Passenger cars | K39: Fuel Cell | L39: TL | M39: FCH | O39: =(GETPIVOTDATA("Sum of CY"&$O$17,$B$20,"GPC Sector","Transportation","GPC Sub-sector","On-road","GPC Sub-sector class agg",$J39,"Fuel type",$K39))/10^6 -> 0 | P39: =(GETPIVOTDATA("Sum of CY"&$P$17,$B$20,"GPC Sector","Transportation","GPC Sub-sector","On-road","GPC Sub-sector class agg",$J39,"Fuel type",$K39))/10^6 -> 0 | Q39: =(GETPIVOTDATA("Sum of CY"&$Q$17,$B$20,"GPC Sector","Transportation","GPC Sub-sector","On-road","GPC Sub-sector class agg",$J39,"Fuel type",$K39)+GETPIVOTDATA("Sum of CY"&$Q$16,$B$20,"GPC Sector","Transportation","GPC Sub-sector","On-road","GPC Sub-sector class agg",$J39,"Fuel type",$K39))/2/10^6 -> 0 | R39: =(GETPIVOTDATA("Sum of CY"&$R$17,$B$20,"GPC Sector","Transportation","GPC Sub-sector","On-road","GPC Sub-sector class agg",$J39,"Fuel type",$K39))/10^6 -> 0 | S39: =IF(Q39+(R39-Q39)*5/2<0,0,Q39+(R39-Q39)*5/2) -> 0 | T39: =O39/SUMIFS(O:O,$L:$L,$L39) -> 0 | U39: =P39/SUMIFS(P:P,$L:$L,$L39) -> 0 | V39: =Q39/SUMIFS(Q:Q,$L:$L,$L39) -> 0 | W39: =R39/SUMIFS(R:R,$L:$L,$L39) -> 0 | Y39: Passenger cars(public)Gasoline | Z39: NYMTC BPM | AA39: Transportation | AB39: On-road | AC39: Passenger cars | AD39: Passenger cars | AE39: (public) | AF39: Gasoline | AG39: VMT | AH39: 60193563 | AI39: 64760164 | AJ39: 59615495 | AK39: 85616592 | AL39: 91969012 | AM39: 97039031 | AN39: 1.0390693e+08 | AO39: 1.0858461e+08 | AP39: 1.0625847e+08 | AQ39: 1.074871e+08 | AR39: 1.0830146e+08 | AS39: 1.1082517e+08 | AT39: 1.1506377e+08 | AU39: 1.1632625e+08 | AV39: 1.1879588e+08 | AW39: 1.2405676e+08 | AX39: 1.2487605e+08 | AY39: 1.2560096e+08
B40: Passenger cars | C40: 1.9657033e+10 | D40: 1.9662888e+10 | E40: 2.1523925e+10 | F40: 2.0188206e+10 | G40: 2.1323592e+10 | J40: Passenger cars | K40: Gasoline | L40: TL | M40: GSL | N40: G*HEV | O40: =(GETPIVOTDATA("Sum of CY"&$O$17,$B$20,"GPC Sector","Transportation","GPC Sub-sector","On-road","GPC Sub-sector class agg",$J40,"Fuel type",$K40))/10^6 -> 19445.41 | P40: =(GETPIVOTDATA("Sum of CY"&$P$17,$B$20,"GPC Sector","Transportation","GPC Sub-sector","On-road","GPC Sub-sector class agg",$J40,"Fuel type",$K40))/10^6 -> 19342.785 | Q40: =(GETPIVOTDATA("Sum of CY"&$Q$17,$B$20,"GPC Sector","Transportation","GPC Sub-sector","On-road","GPC Sub-sector class agg",$J40,"Fuel type",$K40)+GETPIVOTDATA("Sum of CY"&$Q$16,$B$20,"GPC Sector","Transportation","GPC Sub-sector","On-road","GPC Sub-sector class agg",$J40,"Fuel type",$K40))/2/10^6 -> 19470.41 | R40: =(GETPIVOTDATA("Sum of CY"&$R$17,$B$20,"GPC Sector","Transportation","GPC Sub-sector","On-road","GPC Sub-sector class agg",$J40,"Fuel type",$K40))/10^6 -> 19476.743 | S40: =IF(Q40+(R40-Q40)*5/2<0,0,Q40+(R40-Q40)*5/2) -> 19486.244 | T40: =O40/SUMIFS(O:O,$L:$L,$L40) -> 0.98923424 | U40: =P40/SUMIFS(P:P,$L:$L,$L40) -> 0.98372044 | V40: =Q40/SUMIFS(Q:Q,$L:$L,$L40) -> 0.93356102 | W40: =R40/SUMIFS(R:R,$L:$L,$L40) -> 0.91338944 | Y40: Passenger cars(public)Gasoline Hybrid | Z40: NYMTC BPM | AA40: Transportation | AB40: On-road | AC40: Passenger cars | AD40: Passenger cars | AE40: (public) | AF40: Gasoline Hybrid | AG40: VMT | AH40: 45463214 | AI40: 38548714 | AJ40: 27990497 | AK40: 31516999 | AL40: 26175605 | AM40: 20829477 | AN40: 16124534 | AO40: 11294162 | AP40: 9827839.5 | AQ40: 8732667.2 | AR40: 7609251.2 | AS40: 6597314.8 | AT40: 5643022 | AU40: 4512558 | AV40: 3417785.1 | AW40: 2353224.7 | AX40: 1171482.1 | AY40: 0
B41: CNG | C41: 0 | D41: 0 | E41: 0 | F41: 0 | G41: 0 | J41: Passenger cars | K41: Gasoline Hybrid | L41: TL | M41: G*HEV | O41: =(GETPIVOTDATA("Sum of CY"&$O$17,$B$20,"GPC Sector","Transportation","GPC Sub-sector","On-road","GPC Sub-sector class agg",$J41,"Fuel type",$K41))/10^6 -> 42.246719 | P41: =(GETPIVOTDATA("Sum of CY"&$P$17,$B$20,"GPC Sector","Transportation","GPC Sub-sector","On-road","GPC Sub-sector class agg",$J41,"Fuel type",$K41))/10^6 -> 84.554628 | Q41: =(GETPIVOTDATA("Sum of CY"&$Q$17,$B$20,"GPC Sector","Transportation","GPC Sub-sector","On-road","GPC Sub-sector class agg",$J41,"Fuel type",$K41)+GETPIVOTDATA("Sum of CY"&$Q$16,$B$20,"GPC Sector","Transportation","GPC Sub-sector","On-road","GPC Sub-sector class agg",$J41,"Fuel type",$K41))/2/10^6 -> 837.39649 | R41: =(GETPIVOTDATA("Sum of CY"&$R$17,$B$20,"GPC Sector","Transportation","GPC Sub-sector","On-road","GPC Sub-sector class agg",$J41,"Fuel type",$K41))/10^6 -> 1168.8876 | S41: =IF(Q41+(R41-Q41)*5/2<0,0,Q41+(R41-Q41)*5/2) -> 1666.1243 | T41: =O41/SUMIFS(O:O,$L:$L,$L41) -> 0.002149191 | U41: =P41/SUMIFS(P:P,$L:$L,$L41) -> 0.004300214 | V41: =Q41/SUMIFS(Q:Q,$L:$L,$L41) -> 0.040151221 | W41: =R41/SUMIFS(R:R,$L:$L,$L41) -> 0.054816639 | Y41: School Bus(private)Diesel | Z41: NYMTC BPM | AA41: Transportation | AB41: On-road | AC41: School Bus | AD41: Buses | AE41: (private) | AF41: Diesel | AG41: VMT | AH41: 27085733 | AI41: 33218126 | AJ41: 39431287 | AK41: 45357985 | AL41: 51012827 | AM41: 56388434 | AN41: 61478026 | AO41: 66295314 | AP41: 64796685 | AQ41: 63298056 | AR41: 61799427 | AS41: 60300798 | AT41: 58802169 | AU41: 57303540 | AV41: 55804912 | AW41: 54306283 | AX41: 52807654 | AY41: 51309025
B42: Diesel | C42: 1.6846715e+08 | D42: 2.3373521e+08 | E42: 1.8823325e+08 | F42: 1.4494096e+08 | G42: 1.3639804e+08 | J42: Rail | K42: Electricity | L42: TRP | M42: ELC | O42: =(GETPIVOTDATA("Sum of CY"&$O$17,$B$20,"GPC Sector","Transportation","GPC Sub-sector","Rail","GPC Sub-sector class agg",$J42,"Fuel type",$K42))/10^6 -> 9.8781726e-07 | P42: =(GETPIVOTDATA("Sum of CY"&$P$17,$B$20,"GPC Sector","Transportation","GPC Sub-sector","Rail","GPC Sub-sector class agg",$J42,"Fuel type",$K42))/10^6 -> 9.8781726e-07 | Q42: =(GETPIVOTDATA("Sum of CY"&$Q$17,$B$20,"GPC Sector","Transportation","GPC Sub-sector","Rail","GPC Sub-sector class agg",$J42,"Fuel type",$K42)+GETPIVOTDATA("Sum of CY"&$Q$16,$B$20,"GPC Sector","Transportation","GPC Sub-sector","Rail","GPC Sub-sector class agg",$J42,"Fuel type",$K42))/2/10^6 -> 9.8781726e-07 | R42: =(GETPIVOTDATA("Sum of CY"&$R$17,$B$20,"GPC Sector","Transportation","GPC Sub-sector","Rail","GPC Sub-sector class agg",$J42,"Fuel type",$K42))/10^6 -> 9.8781726e-07 | S42: =IF(Q42+(R42-Q42)*5/2<0,0,Q42+(R42-Q42)*5/2) -> 9.8781726e-07 | T42: =O42/SUMIFS(O:O,$L:$L,$L42) -> 0.98781726 | U42: =P42/SUMIFS(P:P,$L:$L,$L42) -> 0.98659511 | V42: =Q42/SUMIFS(Q:Q,$L:$L,$L42) -> 0.98495261 | W42: =R42/SUMIFS(R:R,$L:$L,$L42) -> 0.98489949 | Y42: School Bus(private)Electricity | Z42: NYMTC BPM | AA42: Transportation | AB42: On-road | AC42: School Bus | AD42: Buses | AE42: (private) | AF42: Electricity | AG42: VMT | AH42: 23359.435 | AI42: 0 | AJ42: 0 | AK42: 0 | AL42: 0 | AM42: 0 | AN42: 0 | AO42: 0 | AP42: 0 | AQ42: 0 | AR42: 0 | AS42: 0 | AT42: 0 | AU42: 0 | AV42: 0 | AW42: 0 | AX42: 0 | AY42: 0
B43: Diesel Hybrid | C43: 0 | D43: 0 | E43: 0 | F43: 0 | G43: 0 | J43: Rail | K43: Diesel | L43: TRP | M43: DSL | O43: =(GETPIVOTDATA("Sum of CY"&$O$17,$B$20,"GPC Sector","Transportation","GPC Sub-sector","Rail","GPC Sub-sector class agg",$J43,"Fuel type",$K43))/10^6 -> 1.2182741e-08 | P43: =(GETPIVOTDATA("Sum of CY"&$P$17,$B$20,"GPC Sector","Transportation","GPC Sub-sector","Rail","GPC Sub-sector class agg",$J43,"Fuel type",$K43))/10^6 -> 1.34215e-08 | Q43: =(GETPIVOTDATA("Sum of CY"&$Q$17,$B$20,"GPC Sector","Transportation","GPC Sub-sector","Rail","GPC Sub-sector class agg",$J43,"Fuel type",$K43)+GETPIVOTDATA("Sum of CY"&$Q$16,$B$20,"GPC Sector","Transportation","GPC Sub-sector","Rail","GPC Sub-sector class agg",$J43,"Fuel type",$K43))/2/10^6 -> 1.5091151e-08 | R43: =(GETPIVOTDATA("Sum of CY"&$R$17,$B$20,"GPC Sector","Transportation","GPC Sub-sector","Rail","GPC Sub-sector class agg",$J43,"Fuel type",$K43))/10^6 -> 1.5145247e-08 | S43: =IF(Q43+(R43-Q43)*5/2<0,0,Q43+(R43-Q43)*5/2) -> 1.5226392e-08 | T43: =O43/SUMIFS(O:O,$L:$L,$L43) -> 0.012182741 | U43: =P43/SUMIFS(P:P,$L:$L,$L43) -> 0.013404894 | V43: =Q43/SUMIFS(Q:Q,$L:$L,$L43) -> 0.015047387 | W43: =R43/SUMIFS(R:R,$L:$L,$L43) -> 0.015100512 | Y43: School Bus(private)Gasoline | Z43: NYMTC BPM | AA43: Transportation | AB43: On-road | AC43: School Bus | AD43: Buses | AE43: (private) | AF43: Gasoline | AG43: VMT | AH43: 50758730 | AI43: 42067176 | AJ43: 34358172 | AK43: 26928292 | AL43: 19777534 | AM43: 12905900 | AN43: 6313388.4 | AO43: 0 | AP43: 0 | AQ43: 0 | AR43: 0 | AS43: 0 | AT43: 0 | AU43: 0 | AV43: 0 | AW43: 0 | AX43: 0 | AY43: 0
B44: Electricity | C44: 909058.31 | D44: 1813394.6 | E44: 3.2112688e+08 | F44: 4.4221735e+08 | G44: 5.4156249e+08 | Y44: SWCV(private)CNG | Z44: NYMTC BPM | AA44: Transportation | AB44: On-road | AC44: SWCV | AD44: Heavy duty trucks | AE44: (private) | AF44: CNG | AG44: VMT | AH44: 74582.603 | AI44: 63730.381 | AJ44: 52944.523 | AK44: 42224.722 | AL44: 31570.672 | AM44: 0 | AN44: 0 | AO44: 0 | AP44: 0 | AQ44: 0 | AR44: 0 | AS44: 0 | AT44: 0 | AU44: 0 | AV44: 0 | AW44: 0 | AX44: 0 | AY44: 0
B45: Fuel Cell | C45: 0 | D45: 0 | E45: 0 | F45: 0 | G45: 0 | Y45: SWCV(private)Diesel | Z45: NYMTC BPM | AA45: Transportation | AB45: On-road | AC45: SWCV | AD45: Heavy duty trucks | AE45: (private) | AF45: Diesel | AG45: VMT | AH45: 21989438 | AI45: 22212693 | AJ45: 22434359 | AK45: 22654443 | AL45: 22872952 | AM45: 23089894 | AN45: 23305277 | AO45: 23519108 | AP45: 23433919 | AQ45: 23351481 | AR45: 23267667 | AS45: 23183853 | AT45: 23100000 | AU45: 23016329 | AV45: 22932961 | AW45: 22849895 | AX45: 22767130 | AY45: 22684664
B46: Gasoline | C46: 1.944541e+10 | D46: 1.9342785e+10 | E46: 2.030072e+10 | F46: 1.8640099e+10 | G46: 1.9476743e+10 | Y46: SWCV(private)Gasoline | Z46: NYMTC BPM | AA46: Transportation | AB46: On-road | AC46: SWCV | AD46: Heavy duty trucks | AE46: (private) | AF46: Gasoline | AG46: VMT | AH46: 1967116.2 | AI46: 1680888.8 | AJ46: 1396411.8 | AK46: 1113677 | AL46: 832676.48 | AM46: 553402.11 | AN46: 275845.93 | AO46: 0 | AP46: 0 | AQ46: 0 | AR46: 0 | AS46: 0 | AT46: 0 | AU46: 0 | AV46: 0 | AW46: 0 | AX46: 0 | AY46: 0
B47: Gasoline Hybrid | C47: 42246719 | D47: 84554628 | E47: 7.1384475e+08 | F47: 9.6094823e+08 | G47: 1.1688876e+09 | Y47: SWCV(public)CNG | Z47: NYMTC BPM | AA47: Transportation | AB47: On-road | AC47: SWCV | AD47: Heavy duty trucks | AE47: (public) | AF47: CNG | AG47: VMT | AH47: 241321.17 | AI47: 206207.47 | AJ47: 171308.51 | AK47: 136623.27 | AL47: 102150.79 | AM47: 67890.065 | AN47: 33840.128 | AO47: 0 | AP47: 0 | AQ47: 0 | AR47: 0 | AS47: 0 | AT47: 0 | AU47: 0 | AV47: 0 | AW47: 0 | AX47: 0 | AY47: 0
B48: Rail | C48: 1 | D48: 1.0012388 | E48: 1.0030634 | F48: 1.0027534 | G48: 1.0029625 | Y48: SWCV(public)Diesel | Z48: NYMTC BPM | AA48: Transportation | AB48: On-road | AC48: SWCV | AD48: Heavy duty trucks | AE48: (public) | AF48: Diesel | AG48: VMT | AH48: 16534157 | AI48: 16529924 | AJ48: 16525560 | AK48: 16521066 | AL48: 16516441 | AM48: 16511687 | AN48: 16506804 | AO48: 16501794 | AP48: 16442023 | AQ48: 16384181 | AR48: 16325375 | AS48: 16266568 | AT48: 16207734 | AU48: 16149028 | AV48: 16090534 | AW48: 16032252 | AX48: 15974181 | AY48: 15916321
B49: Rail | C49: 1 | D49: 1.0012388 | E49: 1.0030634 | F49: 1.0027534 | G49: 1.0029625 | Y49: SWCV(public)Diesel Hybrid | Z49: NYMTC BPM | AA49: Transportation | AB49: On-road | AC49: SWCV | AD49: Heavy duty trucks | AE49: (public) | AF49: Diesel Hybrid | AG49: VMT | AH49: 87753.153 | AI49: 74984.536 | AJ49: 62294.002 | AK49: 49681.19 | AL49: 37145.741 | AM49: 24687.296 | AN49: 0 | AO49: 0 | AP49: 0 | AQ49: 0 | AR49: 0 | AS49: 0 | AT49: 0 | AU49: 0 | AV49: 0 | AW49: 0 | AX49: 0 | AY49: 0
B50: Diesel | C50: 0.012182741 | D50: 0.0134215 | E50: 0.015246186 | F50: 0.014936116 | G50: 0.015145247 | AA50: Transportation | AB50: On-road | AC50: Transit Bus | AD50: Buses | AE50: (public) | AF50: Diesel | AG50: VMT | AH50: 2.0893939e+08 | AI50: 202132232 | AJ50: 173681282 | AK50: 220337838 | AL50: 240132445 | AM50: 238732893 | AN50: 243438549 | AO50: 250565732 | AP50: 259790075 | AQ50: 253820640 | AR50: 253623587 | AS50: 252812611 | AT50: 266429810 | AU50: 267982573 | AV50: 270725155 | AW50: 323209653 | AX50: 322626656 | AY50: 339477974
B51: Electricity | C51: 0.98781726 | D51: 0.98781726 | E51: 0.98781726 | F51: 0.98781726 | G51: 0.98781726 | AA51: Transportation | AB51: On-road | AC51: Transit Bus | AD51: Buses | AE51: (public) | AF51: CNG | AG51: VMT | AH51: 43719634 | AI51: 33248656 | AJ51: 21419168 | AK51: 30250532 | AL51: 39251095 | AM51: 36798317 | AN51: 40655650 | AO51: 40318337 | AP51: 39662226 | AQ51: 38351609 | AR51: 37340822 | AS51: 36192538 | AT51: 37590232 | AU51: 40570785 | AV51: 42055202 | AW51: 40484747 | AX51: 6537035 | AY51: 6523813
B52: Grand Total | C52: 2.1148664e+10 | D52: 2.1182701e+10 | E52: 2.3114015e+10 | F52: 2.1741184e+10 | G52: 2.2959328e+10 | AA52: Transportation | AB52: Rail | AC52: Commuter Rail | AD52: Rail | AF52: Diesel | AG52: PMT | AH52: =AI52*AH55/AI55 -> 0.015145247 | AI52: =AJ52*AI55/AJ55 -> 0.014936116 | AJ52: =AK52*AJ55/AK55 -> 0.014047505 | AK52: =AL52*AK55/AL55 -> 0.015246186 | AL52: =AM52*AL55/AM55 -> 0.013417954 | AM52: =AN52*AM55/AN55 -> 0.013661006 | AN52: =AO52*AN55/AO55 -> 0.01260013 | AO52: =AP52*AO55/AP55 -> 0.0134215 | ... AS52: =AT52*AS55/AT55 -> 0.013077177 | AT52: =0.12/(9.73+0.12) -> 0.012182741
AA53: Transportation | AB53: Rail | AC53: Subway | AD53: Rail | AF53: Electricity | AG53: PMT | AH53: =AI53 -> 0.98781726 | AI53: =AJ53 -> 0.98781726 | AJ53: =AK53 -> 0.98781726 | AK53: =AL53 -> 0.98781726 | AL53: =AM53 -> 0.98781726 | AM53: =AN53 -> 0.98781726 | AN53: =AO53 -> 0.98781726 | AO53: =AP53 -> 0.98781726 | ... AS53: =AT53 -> 0.98781726 | AT53: =1-AT52 -> 0.98781726
AH55: 0.027198409 | AI55: 0.026822843 | AJ55: 0.025227042 | AK55: 0.027379678 | AL55: 0.02409647 | AM55: 0.024532952 | AN55: 0.02262779 | AO55: 0.024102838 | AP55: 0.024285231 | AQ55: 0.023607623 | AR55: 0.020933033 | AS55: 0.02348449 | AT55: 0.021878228

Sheet TRP
A1: ='2010 GHG'!A1 -> GHG Emissions 2010 | B1: ='2010 GHG'!B1 -> Exp. | C1: ='2010 GHG'!C1 -> Nom. | D1: ='2010 GHG'!D1 -> Sector | E1: ='2010 GHG'!E1 -> Fuel Type | F1: ='2010 GHG'!F1 -> Units | G1: ='2010 GHG'!G1 -> Consumed | H1: ='2010 GHG'!H1 -> MgCO2e | I1: ='2010 GHG'!I1 -> Source GJ | J1: Source PJ
A2: ='2010 GHG'!A3 -> commuter rail | B2: ='2010 GHG'!B3 -> commuter rail | C2: ='2010 GHG'!C3 -> TRP | D2: ='2010 GHG'!D3 -> transportation | E2: ='2010 GHG'!E3 -> Diesel | F2: ='2010 GHG'!F3 -> liters | G2: ='2010 GHG'!G3 -> 5064028 | H2: ='2010 GHG'!H3 -> 13789 | I2: ='2010 GHG'!I3 -> 195751 | J2: =I2*0.000001 -> 0.195751
A3: ='2010 GHG'!A11 -> subway and commuter rail | B3: ='2010 GHG'!B11 -> subway and commuter rail | C3: ='2010 GHG'!C11 -> TRP | D3: ='2010 GHG'!D11 -> transportation | E3: ='2010 GHG'!E11 -> Electricity | F3: ='2010 GHG'!F11 -> GJ | G3: ='2010 GHG'!G11 -> 10118346 | H3: ='2010 GHG'!H11 -> 889291 | I3: ='2010 GHG'!I11 -> 25432916 | J3: =I3*0.000001 -> 25.432916
F5: eff | G5: dmd
A6: =TechData!B28 -> TPDSLCR | B6: =TechData!C28 -> Commuter Rail, Diesel | C6: bn-pass-miles, bn-pmt/a | D6: =TechData!E28 -> TRNDSL | E6: =NewTech!F137 -> THL | F6: =TechData!L28 -> 0.63495882 | G6: =F6*J2 -> 0.12429382 | H6: =G6/(G6+G7) -> 0.0042418397
A7: =TechData!B29 -> TPELCSUB | B7: =TechData!C29 -> Subways and Streetcars, Electricity | C7: bn-pass-miles, bn-pmt/a | D7: =TechData!E29 -> TRNELC | E7: =NewTech!F139 -> THL | F7: =TechData!L29 -> 1.1472366 | G7: =F7*J3 -> 29.177573 | H7: =1-H6 -> 0.99575816
G9: =G6+G7 -> 29.301867
A11: Population | B11: 2010 | C11: 2015 | D11: 2020 | E11: 2025 | F11: 2030 | G11: 2035 | H11: 2040 | I11: 2045 | J11: 2050 | K11: 2055
A12: Bronx | B12: 1385108 | C12: 1455444 | D12: 1446788 | E12: 1482893 | F12: 1518998 | G12: 1549121.5 | H12: 1579245 | I12: 1625955 | J12: 1660587.6 | K12: 1695220.2
A13: Brooklyn | B13: 2552911 | C13: 2636735 | D13: 2648452 | E13: 2701230.5 | F13: 2754009 | G13: 2797267 | H13: 2840525 | I13: 2908244.5 | J13: 2959463.7 | K13: 3010682.8
A14: Manhattan | B14: 1585873 | C14: 1644518 | D14: 1638281 | E14: 1657500.5 | F14: 1676720 | G14: 1684168.5 | H14: 1691617 | I14: 1733166.2 | J14: 1753311.6 | K14: 1773457
A15: Queens | B15: 2250002 | C15: 2339150 | D15: 2330295 | E15: 2351923 | F15: 2373551 | G15: 2393100 | H15: 2412649 | I15: 2496538.8 | J15: 2533665.6 | K15: 2570792.4
A16: Staten Island | B16: 468730 | C16: 474558 | D16: 487155 | E16: 492452 | F16: 497749 | G16: 499429 | H16: 501109 | I16: 528935.8 | J16: 539243.36 | K16: 549550.91
A17: NYC | B17: =SUM(B12:B16) -> 8242624 | C17: =SUM(C12:C16) -> 8550405 | D17: =SUM(D12:D16) -> 8550971 | E17: =SUM(E12:E16) -> 8685999 | F17: =SUM(F12:F16) -> 8821027 | G17: =SUM(G12:G16) -> 8923086 | H17: =SUM(H12:H16) -> 9025145 | I17: =SUM(I12:I16) -> 9292840.2 | ... K17: =SUM(K12:K16) -> 9599703.4
A18: DMD | B18: =G9 -> 29.301867 | C18: =B18*C17/B17 -> 30.396004 | D18: =C18*D17/C17 -> 30.398016 | E18: =D18*E17/D17 -> 30.87803 | F18: =E18*F17/E17 -> 31.358043 | G18: =F18*G17/F17 -> 31.720855 | H18: =G18*H17/G17 -> 32.083666 | I18: =H18*I17/H17 -> 33.035301 | J18: =I18*J17/I17 -> 33.580738 | K18: =J18*K17/J17 -> 34.126175
A20: TRP DMD | B20: 2010 | C20: 2015 | D20: 2020 | E20: 2025 | F20: 2030 | G20: 2035 | H20: 2040 | I20: 2045 | J20: 2050 | K20: 2055
A21: Bronx | B21: =$B$18*B12/$B$17 -> 4.9239478 | C21: =$C$18*C12/$C$17 -> 5.1739867 | D21: =$D$18*D12/$D$17 -> 5.1432153 | E21: =$E$18*E12/$E$17 -> 5.2715656 | F21: =$F$18*F12/$F$17 -> 5.399916 | G21: =$G$18*G12/$G$17 -> 5.5070026 | H21: =$H$18*H12/$H$17 -> 5.6140893 | I21: =$I$18*I12/$I$17 -> 5.7801395 | J21: =$J$18*J12/$J$17 -> 5.9032557 | K21: =$K$18*K12/$K$17 -> 6.0263719
A22: Brooklyn | B22: =$B$18*B13/$B$17 -> 9.0753938 | C22: =$C$18*C13/$C$17 -> 9.3733814 | D22: =$D$18*D13/$D$17 -> 9.4150344 | E22: =$E$18*E13/$E$17 -> 9.6026577 | F22: =$F$18*F13/$F$17 -> 9.790281 | G22: =$G$18*G13/$G$17 -> 9.9440598 | H22: =$H$18*H13/$H$17 -> 10.097838 | I22: =$I$18*I13/$I$17 -> 10.338576 | J22: =$J$18*J13/$J$17 -> 10.520656 | K22: =$K$18*K13/$K$17 -> 10.702736
A23: Manhattan | B23: =$B$18*B14/$B$17 -> 5.6376513 | C23: =$C$18*C14/$C$17 -> 5.8461296 | D23: =$D$18*D14/$D$17 -> 5.8239575 | E23: =$E$18*E14/$E$17 -> 5.8922813 | F23: =$F$18*F14/$F$17 -> 5.9606051 | G23: =$G$18*G14/$G$17 -> 5.9870839 | H23: =$H$18*H14/$H$17 -> 6.0135627 | I23: =$I$18*I14/$I$17 -> 6.1612667 | J23: =$J$18*J14/$J$17 -> 6.232882 | K23: =$K$18*K14/$K$17 -> 6.3044973
A24: Queens | B24: =$B$18*B15/$B$17 -> 7.9985766 | C24: =$C$18*C15/$C$17 -> 8.3154906 | D24: =$D$18*D15/$D$17 -> 8.2840118 | E24: =$E$18*E15/$E$17 -> 8.3608976 | F24: =$F$18*F15/$F$17 -> 8.4377834 | G24: =$G$18*G15/$G$17 -> 8.5072785 | H24: =$H$18*H15/$H$17 -> 8.5767736 | I24: =$I$18*I15/$I$17 -> 8.874995 | J24: =$J$18*J15/$J$17 -> 9.0069778 | K24: =$K$18*K15/$K$17 -> 9.1389607
A25: Staten Island | B25: =$B$18*B16/$B$17 -> 1.6662975 | C25: =$C$18*C16/$C$17 -> 1.6870156 | D25: =$D$18*D16/$D$17 -> 1.7317969 | E25: =$E$18*E16/$E$17 -> 1.7506274 | F25: =$F$18*F16/$F$17 -> 1.7694578 | G25: =$G$18*G16/$G$17 -> 1.77543 | H25: =$H$18*H16/$H$17 -> 1.7814023 | I25: =$I$18*I16/$I$17 -> 1.8803243 | J25: =$J$18*J16/$J$17 -> 1.9169669 | K25: =$K$18*K16/$K$17 -> 1.9536094
B26: =SUM(B21:B25)-B18 -> 0 | C26: =SUM(C21:C25)-C18 -> 0 | D26: =SUM(D21:D25)-D18 -> 0 | E26: =SUM(E21:E25)-E18 -> 0 | F26: =SUM(F21:F25)-F18 -> 0 | G26: =SUM(G21:G25)-G18 -> 0 | H26: =SUM(H21:H25)-H18 -> 0 | I26: =SUM(I21:I25)-I18 -> 0 | ... K26: =SUM(K21:K25)-K18 -> 0
A28: =A6 -> TPDSLCR | C28: 2010 | D28: 2015 | E28: 2020 | F28: 2025 | G28: 2030 | H28: 2035 | I28: 2040 | J28: 2045 | K28: 2050 | L28: 2055
C29: =SUM(C30:C34) -> 0.12429382 | D29: =SUM(D30:D34) -> 0.12893498 | E29: =SUM(E30:E34) -> 0.12894351 | F29: =SUM(F30:F34) -> 0.13097965 | G29: =SUM(G30:G34) -> 0.13301579 | H29: =SUM(H30:H34) -> 0.13455478 | I29: =SUM(I30:I34) -> 0.13609377 | J29: =SUM(J30:J34) -> 0.14013045 | ... L29: =SUM(L30:L34) -> 0.14475777
A30: Bronx | C30: =B21*$H$6 -> 0.020886597 | D30: =C21*$H$6 -> 0.021947222 | E30: =D21*$H$6 -> 0.021816695 | F30: =E21*$H$6 -> 0.022361137 | G30: =F21*$H$6 -> 0.022905578 | H30: =G21*$H$6 -> 0.023359823 | I30: =H21*$H$6 -> 0.023814067 | J30: =I21*$H$6 -> 0.024518425 | ... L30: =K21*$H$6 -> 0.025562904
A31: Brooklyn | C31: =B22*$H$6 -> 0.038496366 | D31: =C22*$H$6 -> 0.039760381 | E31: =D22*$H$6 -> 0.039937067 | F31: =E22*$H$6 -> 0.040732935 | G31: =F22*$H$6 -> 0.041528803 | H31: =G22*$H$6 -> 0.042181108 | I31: =H22*$H$6 -> 0.042833412 | J31: =I22*$H$6 -> 0.043854582 | ... L31: =K22*$H$6 -> 0.045399291
A32: Manhattan | C32: =B23*$H$6 -> 0.023914013 | D32: =C23*$H$6 -> 0.024798345 | E32: =D23*$H$6 -> 0.024704294 | F32: =E23*$H$6 -> 0.024994113 | G32: =F23*$H$6 -> 0.025283931 | H32: =G23*$H$6 -> 0.02539625 | I32: =H23*$H$6 -> 0.025508569 | J32: =I23*$H$6 -> 0.026135106 | ... L32: =K23*$H$6 -> 0.026742667
A33: Queens | C33: =B24*$H$6 -> 0.03392868 | D33: =C24*$H$6 -> 0.035272978 | E33: =D24*$H$6 -> 0.03513945 | F33: =E24*$H$6 -> 0.035465587 | G33: =F24*$H$6 -> 0.035791725 | H33: =G24*$H$6 -> 0.036086512 | I33: =H24*$H$6 -> 0.036381299 | J33: =I24*$H$6 -> 0.037646306 | ... L33: =K24*$H$6 -> 0.038766006
A34: Staten Island | C34: =B25*$H$6 -> 0.0070681671 | D34: =C25*$H$6 -> 0.0071560499 | E34: =D25*$H$6 -> 0.0073460051 | F34: =E25*$H$6 -> 0.0074258806 | G34: =F25*$H$6 -> 0.0075057562 | H34: =G25*$H$6 -> 0.0075310896 | I34: =H25*$H$6 -> 0.007556423 | J34: =I25*$H$6 -> 0.0079760345 | ... L34: =K25*$H$6 -> 0.008286898
A36: =A7 -> TPELCSUB | C36: 2010 | D36: 2015 | E36: 2020 | F36: 2025 | G36: 2030 | H36: 2035 | I36: 2040 | J36: 2045 | K36: 2050 | L36: 2055
C37: =SUM(C38:C41) -> 27.518344 | D37: =SUM(D38:D41) -> 28.587209 | E37: =SUM(E38:E41) -> 28.544621 | F37: =SUM(F38:F41) -> 29.003848 | G37: =SUM(G38:G41) -> 29.463075 | H37: =SUM(H38:H41) -> 29.818401 | I37: =SUM(I38:I41) -> 30.173727 | J37: =SUM(J38:J41) -> 31.022823 | ... L37: =SUM(L38:L41) -> 32.036095
A38: Bronx | C38: =B21*$H$7 -> 4.9030612 | D38: =C21*$H$7 -> 5.1520394 | E38: =D21*$H$7 -> 5.1213986 | F38: =E21*$H$7 -> 5.2492045 | G38: =F21*$H$7 -> 5.3770104 | H38: =G21*$H$7 -> 5.4836428 | I38: =H21*$H$7 -> 5.5902752 | J38: =I21*$H$7 -> 5.7556211 | ... L38: =K21*$H$7 -> 6.000809
A39: Brooklyn | C39: =B22*$H$7 -> 9.0368974 | D39: =C22*$H$7 -> 9.333621 | E39: =D22*$H$7 -> 9.3750973 | F39: =E22*$H$7 -> 9.5619248 | G39: =F22*$H$7 -> 9.7487522 | H39: =G22*$H$7 -> 9.9018787 | I39: =H22*$H$7 -> 10.055005 | J39: =I22*$H$7 -> 10.294721 | ... L39: =K22*$H$7 -> 10.657337
A40: Manhattan | C40: =B23*$H$7 -> 5.6137373 | D40: =C23*$H$7 -> 5.8213312 | E40: =D23*$H$7 -> 5.7992532 | F40: =E23*$H$7 -> 5.8672872 | G40: =F23*$H$7 -> 5.9353211 | H40: =G23*$H$7 -> 5.9616876 | I40: =H23*$H$7 -> 5.9880541 | J40: =I23*$H$7 -> 6.1351316 | ... L40: =K23*$H$7 -> 6.2777546
A41: Queens | C41: =B24*$H$7 -> 7.9646479 | D41: =C24*$H$7 -> 8.2802176 | E41: =D24*$H$7 -> 8.2488723 | F41: =E24*$H$7 -> 8.325432 | G41: =F24*$H$7 -> 8.4019917 | H41: =G24*$H$7 -> 8.471192 | I41: =H24*$H$7 -> 8.5403923 | J41: =I24*$H$7 -> 8.8373487 | ... L41: =K24*$H$7 -> 9.1001947
A42: Staten Island | C42: =B25*$H$7 -> 1.6592294 | D42: =C25*$H$7 -> 1.6798596 | E42: =D25*$H$7 -> 1.7244509 | F42: =E25*$H$7 -> 1.7432015 | G42: =F25*$H$7 -> 1.761952 | H42: =G25*$H$7 -> 1.7678989 | I42: =H25*$H$7 -> 1.7738459 | J42: =I25*$H$7 -> 1.8723483 | ... L42: =K25*$H$7 -> 1.9453225

Sheet >>> Not used

Sheet NewTech
A1: TechData | B1: R1,R2,R3,R4,R5,R6
A6: Region | B6: TechName | C6: *TechDesc | D6: *Units | E6: CommIN | F6: CommOUT | G6: Share~UP | H6: NCAP_START | I6: NCAP_TLIFE | J6: NCAP_DRATE | K6: EFF | L6: EFF~2010 | M6: EFF~2015 | N6: EFF~2020 | O6: EFF~2025 | P6: EFF~2030 | Q6: EFF~2035 | R6: EFF~2040 | S6: EFF~2045 | T6: EFF~2050 | U6: EFF~2055 | V6: NCAP_COST~2010 | W6: NCAP_COST~2015 | X6: NCAP_COST~2020 | Y6: NCAP_COST~2025 | Z6: NCAP_COST~2030 | AA6: NCAP_COST~2035 | AB6: NCAP_COST~2040 | AC6: NCAP_COST~2045 | AD6: NCAP_COST~2050 | AE6: NCAP_COST~2055 | AF6: NCAP_FOM | AG6: PRC_RESID~R2~2010 | AH6: PRC_RESID~R3~2010 | AI6: PRC_RESID~R4~2010 | AJ6: PRC_RESID~R5~2010 | AK6: PRC_RESID~R6~2010 | AL6: NACP_AFA | AM6: NCAP_BND~2010 | AN6: NCAP_BND~2015 | AO6: NCAP_BND~2020 | AP6: NCAP_BND~2025 | AQ6: NCAP_BND~2030 | AR6: NCAP_BND~2035 | AS6: NCAP_BND~2040 | AT6: NCAP_BND~2045 | AU6: NCAP_BND~2050 | AV6: NCAP_BND~2055 | AZ6: NCAP_TLIFE
A7: *Aviation
A8: =Technologies!B49 -> R2,R3,R4,R5,R6 | B8: =Technologies!C49 -> TAJ10 | C8: =Technologies!D49 -> Air Jet, Passenger 2010 | D8: bn-pass-miles, bn-pmt/a | E8: =Commodities!C31 -> TRNJTF1 | F8: TA | G8: 1 | H8: ='Air&Marine'!F7 -> 2010 | I8: =AZ8+5 -> 30 | J8: 0.18 | K8: ='Air&Marine'!J7 -> 0.45147637 | V8: ='Air&Marine'!H7 -> 814.53239 | W8: =V8 -> 814.53239 | X8: =W8 -> 814.53239 | Y8: =X8 -> 814.53239 | Z8: =Y8 -> 814.53239 | AA8: =Z8 -> 814.53239 | AB8: =AA8 -> 814.53239 | AC8: =AB8 -> 814.53239 | AD8: =AC8 -> 814.53239 | AE8: =AD8 -> 814.53239 | AF8: ='Air&Marine'!I7 -> 7.462576 | AL8: 1 | AM8: 0 | AN8: 0 | AZ8: ='Air&Marine'!G7 -> 25
A9: =Technologies!B50 -> R2,R3,R4,R5,R6 | B9: =Technologies!C50 -> TAJSYN10 | C9: =Technologies!D50 -> Air Jet, Passenger, Syn fuel, 2010 | D9: bn-pass-miles, bn-pmt/a | E9: =Commodities!C31 -> TRNJTF1 | F9: TA | G9: 1 | H9: ='Air&Marine'!F8 -> 2010 | I9: =AZ9+5 -> 30 | K9: ='Air&Marine'!J8 -> 0.42712996 | V9: ='Air&Marine'!H8 -> 814.53239 | W9: =V9 -> 814.53239 | X9: =W9 -> 814.53239 | Y9: =X9 -> 814.53239 | Z9: =Y9 -> 814.53239 | AA9: =Z9 -> 814.53239 | AB9: =AA9 -> 814.53239 | AC9: =AB9 -> 814.53239 | AD9: =AC9 -> 814.53239 | AE9: =AD9 -> 814.53239 | AF9: ='Air&Marine'!I8 -> 7.462576 | AL9: 1 | AM9: 0 | AN9: 0 | AZ9: ='Air&Marine'!G8 -> 25
A10: =Technologies!B51 -> R2,R3,R4,R5,R6 | B10: =Technologies!C51 -> TAJWT10 | C10: =Technologies!D51 -> Air Jet, Passenger (Wing tips),2010 | D10: bn-pass-miles, bn-pmt/a | E10: =Commodities!C$31 -> TRNJTF1 | F10: TA | G10: 1 | H10: ='Air&Marine'!F9 -> 2010 | I10: =AZ10+5 -> 30 | J10: 0.2 | K10: ='Air&Marine'!J9 -> 0.47275012 | V10: ='Air&Marine'!H9 -> 820.68444 | W10: =V10 -> 820.68444 | X10: =W10 -> 820.68444 | Y10: =X10 -> 820.68444 | Z10: =Y10 -> 820.68444 | AA10: =Z10 -> 820.68444 | AB10: =AA10 -> 820.68444 | AC10: =AB10 -> 820.68444 | AD10: =AC10 -> 820.68444 | AE10: =AD10 -> 820.68444 | AF10: ='Air&Marine'!I9 -> 7.462576 | AL10: 1 | AM10: 0 | AN10: 0 | AZ10: ='Air&Marine'!G9 -> 25
A11: =Technologies!B52 -> R2,R3,R4,R5,R6 | B11: =Technologies!C52 -> TAJAPU15 | C11: =Technologies!D52 -> Air Jet Passeneger (APU) 2015 | D11: bn-pass-miles, bn-pmt/a | E11: =Commodities!C$31 -> TRNJTF1 | F11: TA | G11: 1 | H11: ='Air&Marine'!F11 -> 2015 | I11: =AZ11+5 -> 30 | J11: 0.2 | K11: ='Air&Marine'!J11 -> 0.45358554 | V11: ='Air&Marine'!H11 -> 815.46191 | W11: =V11 -> 815.46191 | X11: =W11 -> 815.46191 | Y11: =X11 -> 815.46191 | Z11: =Y11 -> 815.46191 | AA11: =Z11 -> 815.46191 | AB11: =AA11 -> 815.46191 | AC11: =AB11 -> 815.46191 | AD11: =AC11 -> 815.46191 | AE11: =AD11 -> 815.46191 | AF11: ='Air&Marine'!I11 -> 7.5083155 | AL11: 1 | AM11: 0 | AN11: 0 | AZ11: ='Air&Marine'!G10 -> 25
A12: =Technologies!B53 -> R2,R3,R4,R5,R6 | B12: =Technologies!C53 -> TAJBW30 | C12: =Technologies!D53 -> Air Jet, Passenger(blended wing), 2030 | D12: bn-pass-miles, bn-pmt/a | E12: =Commodities!C$31 -> TRNJTF1 | F12: TA | G12: 1 | H12: ='Air&Marine'!F12 -> 2030 | I12: =AZ12+5 -> 30 | J12: 0.24 | K12: ='Air&Marine'!J12 -> 0.64496624 | V12: ='Air&Marine'!H12 -> 1127.6931 | W12: =V12 -> 1127.6931 | X12: =W12 -> 1127.6931 | Y12: =X12 -> 1127.6931 | Z12: =Y12 -> 1127.6931 | AA12: =Z12 -> 1127.6931 | AB12: =AA12 -> 1127.6931 | AC12: =AB12 -> 1127.6931 | AD12: =AC12 -> 1127.6931 | AE12: =AD12 -> 1127.6931 | AF12: ='Air&Marine'!I12 -> 7.462576 | AL12: 1 | AM12: 0 | AN12: 0 | AZ12: ='Air&Marine'!G12 -> 25
A13: =Technologies!B54 -> R2,R3,R4,R5,R6 | B13: =Technologies!C54 -> TAJAE30 | C13: =Technologies!D54 -> Air Jet, Passenger (improved aero), 2030 | D13: bn-pass-miles, bn-pmt/a | E13: =Commodities!C$31 -> TRNJTF1 | F13: TA | G13: 1 | H13: ='Air&Marine'!F13 -> 2030 | I13: =AZ13+5 -> 30 | J13: 0.24 | K13: ='Air&Marine'!J13 -> 0.50164041 | V13: ='Air&Marine'!H13 -> 895.98562 | W13: =V13 -> 895.98562 | X13: =W13 -> 895.98562 | Y13: =X13 -> 895.98562 | Z13: =Y13 -> 895.98562 | AA13: =Z13 -> 895.98562 | AB13: =AA13 -> 895.98562 | AC13: =AB13 -> 895.98562 | AD13: =AC13 -> 895.98562 | AE13: =AD13 -> 895.98562 | AF13: ='Air&Marine'!I13 -> 7.462576 | AL13: 1 | AM13: 0 | AN13: 0 | AZ13: ='Air&Marine'!G13 -> 25
A14: =Technologies!B55 -> R2,R3,R4,R5,R6 | B14: =Technologies!C55 -> TAJGE15 | C14: =Technologies!D55 -> Air Jet Passenger, (geared engine), 2015 | D14: bn-pass-miles, bn-pmt/a | E14: =Commodities!C$31 -> TRNJTF1 | F14: TA | G14: 1 | H14: ='Air&Marine'!F15 -> 2015 | I14: =AZ14+5 -> 30 | J14: 0.2 | K14: ='Air&Marine'!J15 -> 0.51597299 | V14: ='Air&Marine'!H15 -> 929.6172 | W14: =V14 -> 929.6172 | X14: =W14 -> 929.6172 | Y14: =X14 -> 929.6172 | Z14: =Y14 -> 929.6172 | AA14: =Z14 -> 929.6172 | AB14: =AA14 -> 929.6172 | AC14: =AB14 -> 929.6172 | AD14: =AC14 -> 929.6172 | AE14: =AD14 -> 929.6172 | AF14: ='Air&Marine'!I15 -> 8.5169591 | AL14: 1 | AM14: 0 | AN14: 0 | AZ14: ='Air&Marine'!G15 -> 25
A15: * | B15: =Technologies!C56 -> TAP10 | C15: =Technologies!D56 -> Airplane, General Aviation - 2010 | D15: bn-pass-miles, bn-pmt/a | E15: TRGSLB | F15: TA | G15: 1 | H15: 2010 | I15: =AZ15+5 -> 25 | J15: 0.18 | V15: ='Air&Marine'!H18 -> 17.511 | W15: =V15 -> 17.511 | X15: =W15 -> 17.511 | Y15: =X15 -> 17.511 | Z15: =Y15 -> 17.511 | AA15: =Z15 -> 17.511 | AB15: =AA15 -> 17.511 | AC15: =AB15 -> 17.511 | AD15: =AC15 -> 17.511 | AE15: =AD15 -> 17.511 | AF15: ='Air&Marine'!I18 -> 1.7511 | AL15: 1 | AZ15: 20
A16: *BUSES
A17: =Technologies!B60 -> R2,R3,R4,R5,R6 | B17: =Technologies!C60 -> TBDSLC10 | C17: =Technologies!D60 -> Bus, Conventional Diesel, 2010 | D17: bn-vmt, bn-vmt/a | E17: =Commodities!C$41 -> TBDSL | F17: TB | G17: 1 | H17: 2010 | I17: =AZ17+5 -> 17 | J17: 0.18 | K17: ='Rail&Bus2'!$L7 -> 0.031791784 | V17: ='Rail&Bus2'!T7 -> 10426.657 | AF17: ='Rail&Bus2'!H11 -> 555.05381 | AL17: 1 | AM17: 0 | AN17: 0 | AO17: 0 | AP17: 0 | AQ17: 0 | AR17: 0 | AS17: 0 | AT17: 0 | AU17: 0 | AV17: 0 | AZ17: 12
A18: =Technologies!B61 -> R2,R3,R4,R5,R6 | B18: =Technologies!C61 -> TBDSLC | C18: ='Rail&Bus2'!B11 -> Bus, Conventional Diesel | D18: bn-vmt, bn-vmt/a | E18: =Commodities!C$41 -> TBDSL | F18: TB | G18: 1 | H18: 2015 | I18: =AZ18+5 -> 17 | J18: 0.18 | M18: ='Rail&Bus2'!$I11 -> 0.033488882 | N18: ='Rail&Bus2'!$I12 -> 0.034986321 | O18: =N18 -> 0.034986321 | P18: =O18 -> 0.034986321 | Q18: =P18 -> 0.034986321 | R18: =Q18 -> 0.034986321 | S18: =R18 -> 0.034986321 | T18: =S18 -> 0.034986321 | U18: =T18 -> 0.034986321 | W18: ='Rail&Bus2'!G11 -> 10488.439 | X18: ='Rail&Bus2'!G12 -> 10598.81 | Y18: =X18 -> 10598.81 | Z18: =Y18 -> 10598.81 | AA18: =Z18 -> 10598.81 | AB18: =AA18 -> 10598.81 | AC18: =AB18 -> 10598.81 | AD18: =AC18 -> 10598.81 | AE18: =AD18 -> 10598.81 | AF18: ='Rail&Bus2'!H11 -> 555.05381 | AL18: 1 | AM18: 0 | AZ18: ='Rail&Bus2'!F11 -> 12
A19: =Technologies!B62 -> R2,R3,R4,R5,R6 | B19: =Technologies!C62 -> TBDSLIM | C19: =Technologies!D62 -> Bus, Improved Diesel | D19: bn-vmt, bn-vmt/a | E19: =Commodities!C$41 -> TBDSL | F19: TB | G19: 1 | H19: 2025 | I19: =AZ19+5 -> 17 | J19: 0.24 | K19: ='Rail&Bus2'!I13 -> 0.03909468 | W19: =X19 -> 10598.81 | X19: =Y19 -> 10598.81 | Y19: ='Rail&Bus2'!V7 -> 10598.81 | Z19: =Y19 -> 10598.81 | AA19: =Z19 -> 10598.81 | AB19: =AA19 -> 10598.81 | AC19: =AB19 -> 10598.81 | AD19: =AC19 -> 10598.81 | AE19: =AD19 -> 10598.81 | AF19: ='Rail&Bus2'!H12 -> 555.05381 | AL19: 1 | AM19: 0 | AZ19: 12
A20: =Technologies!B63 -> R2,R3,R4,R5,R6 | B20: =Technologies!C63 -> TBDSLADV | C20: ='Rail&Bus2'!B14 -> Bus, Advanced Tech Diesel | D20: bn-vmt, bn-vmt/a | E20: =Commodities!C$41 -> TBDSL | F20: TB | G20: 1 | H20: ='Rail&Bus2'!E14 -> 2015 | I20: =AZ20+5 -> 17 | J20: 0.28 | M20: ='Rail&Bus2'!I14 -> 0.037727787 | N20: =M20 -> 0.037727787 | O20: ='Rail&Bus2'!$I15 -> 0.03909468 | P20: =O20 -> 0.03909468 | Q20: =P20 -> 0.03909468 | R20: ='Rail&Bus2'!I16 -> 0.039355772 | S20: =R20 -> 0.039355772 | T20: =S20 -> 0.039355772 | U20: =T20 -> 0.039355772 | W20: ='Rail&Bus2'!G14 -> 10807.968 | X20: =W20 -> 10807.968 | Y20: ='Rail&Bus2'!G15 -> 10912.547 | Z20: =Y20 -> 10912.547 | AA20: =Z20 -> 10912.547 | AB20: ='Rail&Bus2'!G16 -> 11236.002 | AC20: =AB20 -> 11236.002 | AD20: =AC20 -> 11236.002 | AE20: =AD20 -> 11236.002 | AF20: ='Rail&Bus2'!H14 -> 555.05381 | AL20: 1 | AM20: 0 | AZ20: ='Rail&Bus2'!F14 -> 12
A21: =Technologies!B64 -> R2,R3,R4,R5,R6 | B21: =Technologies!C64 -> TBDSLAH | C21: ='Rail&Bus2'!B17 -> Bus, Advanced Hybrid Diesel | D21: bn-vmt, bn-vmt/a | E21: =Commodities!C$41 -> TBDSL | F21: TB | G21: 1 | H21: ='Rail&Bus2'!$E$17 -> 2015 | I21: =AZ21+5 -> 17 | J21: 0.28 | M21: ='Rail&Bus2'!I17 -> 0.05389245 | N21: =M21 -> 0.05389245 | O21: ='Rail&Bus2'!$I18 -> 0.05585064 | P21: =O21 -> 0.05585064 | Q21: =P21 -> 0.05585064 | R21: ='Rail&Bus2'!I19 -> 0.056557124 | S21: =R21 -> 0.056557124 | T21: =S21 -> 0.056557124 | U21: =T21 -> 0.056557124 | W21: ='Rail&Bus2'!G17 -> 17887.168 | X21: =W21 -> 17887.168 | Y21: ='Rail&Bus2'!G18 -> 15563.582 | Z21: =Y21 -> 15563.582 | AA21: =Z21 -> 15563.582 | AB21: ='Rail&Bus2'!G19 -> 15887.037 | AC21: =AB21 -> 15887.037 | AD21: =AC21 -> 15887.037 | AE21: =AD21 -> 15887.037 | AF21: ='Rail&Bus2'!H17 -> 564.4615 | AL21: 1 | AM21: 0 | AZ21: ='Rail&Bus2'!F17 -> 12
A22: * | B22: =Technologies!C65 -> TBB20C10 | C22: =Technologies!D65 -> Bus, Conventional Biodiesel, 2010 | D22: bn-vmt, bn-vmt/a | E22: TBB20X | F22: TB | G22: 1 | H22: 2010 | I22: =AZ22+5 -> 17 | J22: 0.18 | K22: ='Rail&Bus2'!$L9 -> 0.031770687 | V22: ='Rail&Bus2'!T9 -> 10426.657 | AF22: ='Rail&Bus2'!H20 -> 524.22213 | AL22: 1 | AN22: 0 | AO22: 0 | AP22: 0 | AQ22: 0 | AR22: 0 | AS22: 0 | AT22: 0 | AU22: 0 | AV22: 0 | AZ22: 12
A23: * | B23: =Technologies!C66 -> TBB20C | C23: ='Rail&Bus2'!B21 -> Bus, Conventional B20 | D23: bn-vmt, bn-vmt/a | E23: TBB20X | F23: TB | G23: 1 | H23: 2015 | I23: =AZ23+5 -> 17 | J23: 0.18 | M23: ='Rail&Bus2'!I11 -> 0.033488882 | N23: ='Rail&Bus2'!$I22 -> 0.034963103 | O23: =N23 -> 0.034963103 | P23: =O23 -> 0.034963103 | Q23: =P23 -> 0.034963103 | R23: =Q23 -> 0.034963103 | S23: =R23 -> 0.034963103 | T23: =S23 -> 0.034963103 | U23: =T23 -> 0.034963103 | W23: ='Rail&Bus2'!G21 -> 10488.439 | X23: ='Rail&Bus2'!G22 -> 10749.404 | Y23: =X23 -> 10749.404 | Z23: =Y23 -> 10749.404 | AA23: =Z23 -> 10749.404 | AB23: =AA23 -> 10749.404 | AC23: =AB23 -> 10749.404 | AD23: =AC23 -> 10749.404 | AE23: =AD23 -> 10749.404 | AF23: ='Rail&Bus2'!H21 -> 524.22213 | AL23: 1 | AZ23: ='Rail&Bus2'!F21 -> 12
A24: * | B24: =Technologies!C67 -> TBB20IM | C24: =Technologies!D67 -> Bus, B20, Improved Biodiesel | D24: bn-vmt, bn-vmt/a | E24: TBB20X | F24: TB | G24: 1 | H24: 2025 | I24: =AZ24+5 -> 17 | J24: 0.24 | K24: ='Rail&Bus2'!I23 -> 0.039068736 | Y24: ='Rail&Bus2'!G23 -> 11404.873 | Z24: =Y24 -> 11404.873 | AA24: =Z24 -> 11404.873 | AB24: =AA24 -> 11404.873 | AC24: =AB24 -> 11404.873 | AD24: =AC24 -> 11404.873 | AE24: =AD24 -> 11404.873 | AF24: ='Rail&Bus2'!H22 -> 524.22213 | AL24: 1 | AZ24: 12
A25: * | B25: =Technologies!C68 -> TBB20ADV | C25: ='Rail&Bus2'!B24 -> Bus, Advanced Tech B20 | D25: bn-vmt, bn-vmt/a | E25: TBB20X | F25: TB | G25: 1 | H25: 2015 | I25: =AZ25+5 -> 17 | J25: 0.28 | M25: ='Rail&Bus2'!I24 -> 0.037700577 | N25: =M25 -> 0.037700577 | O25: ='Rail&Bus2'!I25 -> 0.039067956 | P25: =O25 -> 0.039067956 | Q25: =P25 -> 0.039067956 | R25: ='Rail&Bus2'!I26 -> 0.039562487 | S25: =R25 -> 0.039562487 | T25: =S25 -> 0.039562487 | U25: =T25 -> 0.039562487 | W25: ='Rail&Bus2'!G24 -> 10807.968 | X25: =W25 -> 10807.968 | Y25: ='Rail&Bus2'!G25 -> 10912.547 | Z25: =Y25 -> 10912.547 | AA25: =Z25 -> 10912.547 | AB25: ='Rail&Bus2'!G26 -> 11236.005 | AC25: =AB25 -> 11236.005 | AD25: =AC25 -> 11236.005 | AE25: =AD25 -> 11236.005 | AF25: ='Rail&Bus2'!H23 -> 524.22213 | AL25: 1 | AZ25: 12
A26: * | B26: =Technologies!C69 -> TBB20AH | C26: ='Rail&Bus2'!B27 -> Bus, Advanced Hybrid B20 | D26: bn-vmt, bn-vmt/a | E26: TBB20X | F26: TB | G26: 1 | H26: 2015 | I26: =AZ26+5 -> 17 | J26: 0.28 | M26: ='Rail&Bus2'!I27 -> 0.053857967 | N26: =M26 -> 0.053857967 | O26: ='Rail&Bus2'!I28 -> 0.055811365 | P26: =O26 -> 0.055811365 | Q26: =P26 -> 0.055811365 | R26: ='Rail&Bus2'!I29 -> 0.056517838 | S26: =R26 -> 0.056517838 | T26: =S26 -> 0.056517838 | U26: =T26 -> 0.056517838 | W26: ='Rail&Bus2'!G27 -> 17887.168 | X26: =W26 -> 17887.168 | Y26: ='Rail&Bus2'!G28 -> 15563.582 | Z26: =Y26 -> 15563.582 | AA26: =Z26 -> 15563.582 | AB26: ='Rail&Bus2'!G29 -> 15887.04 | AC26: =AB26 -> 15887.04 | AD26: =AC26 -> 15887.04 | AE26: =AD26 -> 15887.04 | AF26: ='Rail&Bus2'!H27 -> 564.4615 | AL26: 1 | AZ26: 12
A27: =Technologies!B70 -> R2,R3,R4,R5,R6 | B27: =Technologies!C70 -> TBCNGC10 | C27: =Technologies!D70 -> Bus, Conventional CNG, 2010 | D27: bn-vmt, bn-vmt/a | E27: =Commodities!C$55 -> TBCNG | F27: TB | G27: 1 | H27: 2010 | I27: =AZ27+5 -> 17 | J27: 0.18 | K27: ='Rail&Bus2'!$L10 -> 0.027030696 | V27: ='Rail&Bus2'!T10 -> 12020.947 | AF27: ='Rail&Bus2'!H30 -> 639.72304 | AL27: 1 | AM27: 0 | AN27: 0 | AO27: 0 | AP27: 0 | AQ27: 0 | AR27: 0 | AS27: 0 | AT27: 0 | AU27: 0 | AV27: 0 | AZ27: 12
A28: =Technologies!B71 -> R2,R3,R4,R5,R6 | B28: =Technologies!C71 -> TBCNGC | C28: ='Rail&Bus2'!B31 -> Bus, Conventional CNG | D28: bn-vmt, bn-vmt/a | E28: =Commodities!C$55 -> TBCNG | F28: TB | G28: 1 | H28: 2015 | I28: =AZ28+5 -> 17 | J28: 0.18 | M28: ='Rail&Bus2'!$I31 -> 0.028412947 | N28: ='Rail&Bus2'!$I32 -> 0.029718407 | O28: =N28 -> 0.029718407 | P28: =O28 -> 0.029718407 | Q28: =P28 -> 0.029718407 | R28: =Q28 -> 0.029718407 | S28: =R28 -> 0.029718407 | T28: =S28 -> 0.029718407 | U28: =T28 -> 0.029718407 | W28: ='Rail&Bus2'!G31 -> 12033.046 | X28: ='Rail&Bus2'!G32 -> 12046.85 | Y28: =X28 -> 12046.85 | Z28: =Y28 -> 12046.85 | AA28: =Z28 -> 12046.85 | AB28: =AA28 -> 12046.85 | AC28: =AB28 -> 12046.85 | AD28: =AC28 -> 12046.85 | AE28: =AD28 -> 12046.85 | AF28: ='Rail&Bus2'!H31 -> 639.72304 | AL28: 1 | AM28: 0 | AZ28: ='Rail&Bus2'!F31 -> 12
A29: =Technologies!B72 -> R2,R3,R4,R5,R6 | B29: =Technologies!C72 -> TBCNGIM | C29: =Technologies!D72 -> Bus, Improved CNG | D29: bn-vmt, bn-vmt/a | E29: =Commodities!C$55 -> TBCNG | F29: TB | G29: 1 | H29: 2025 | I29: =AZ29+5 -> 17 | J29: 0.24 | K29: ='Rail&Bus2'!I33 -> 0.031231205 | Y29: ='Rail&Bus2'!G33 -> 12573.414 | Z29: =Y29 -> 12573.414 | AA29: =Z29 -> 12573.414 | AB29: =AA29 -> 12573.414 | AC29: =AB29 -> 12573.414 | AD29: =AC29 -> 12573.414 | AE29: =AD29 -> 12573.414 | AF29: ='Rail&Bus2'!H32 -> 639.72304 | AL29: 1 | AM29: 0 | AZ29: 12
A30: =Technologies!B73 -> R2,R3,R4,R5,R6 | B30: =Technologies!C73 -> TBCNGADV | C30: ='Rail&Bus2'!B34 -> Bus, Advanced Tech CNG | D30: bn-vmt, bn-vmt/a | E30: =Commodities!C$55 -> TBCNG | F30: TB | G30: 1 | H30: ='Rail&Bus2'!E34 -> 2015 | I30: =AZ30+5 -> 17 | J30: 0.28 | M30: ='Rail&Bus2'!I34 -> 0.030225233 | N30: =M30 -> 0.030225233 | O30: ='Rail&Bus2'!$I35 -> 0.030839567 | P30: =O30 -> 0.030839567 | Q30: =P30 -> 0.030839567 | R30: ='Rail&Bus2'!$I36 -> 0.031231205 | S30: =R30 -> 0.031231205 | T30: =S30 -> 0.031231205 | U30: =T30 -> 0.031231205 | W30: ='Rail&Bus2'!G34 -> 12097.885 | X30: =W30 -> 12097.885 | Y30: ='Rail&Bus2'!G35 -> 12081.088 | Z30: =Y30 -> 12081.088 | AA30: =Z30 -> 12081.088 | AB30: ='Rail&Bus2'!G36 -> 12404.543 | AC30: =AB30 -> 12404.543 | AD30: =AC30 -> 12404.543 | AE30: =AD30 -> 12404.543 | AF30: ='Rail&Bus2'!H34 -> 639.72304 | AL30: 1 | AM30: 0 | AZ30: ='Rail&Bus2'!F34 -> 12
A31: =Technologies!B74 -> R2,R3,R4,R5,R6 | B31: =Technologies!C74 -> TBCNGAH | C31: ='Rail&Bus2'!B37 -> Bus, Advanced Hybird CNG | D31: bn-vmt, bn-vmt/a | E31: =Commodities!C$55 -> TBCNG | F31: TB | G31: 1 | H31: 2015 | I31: =AZ31+5 -> 17 | J31: 0.28 | M31: ='Rail&Bus2'!I37 -> 0.04030031 | N31: =M31 -> 0.04030031 | O31: ='Rail&Bus2'!$I38 -> 0.041121982 | P31: =O31 -> 0.041121982 | Q31: =P31 -> 0.041121982 | R31: ='Rail&Bus2'!$I39 -> 0.041644166 | S31: =R31 -> 0.041644166 | T31: =S31 -> 0.041644166 | U31: =T31 -> 0.041644166 | W31: ='Rail&Bus2'!G37 -> 18533.521 | X31: =W31 -> 18533.521 | Y31: ='Rail&Bus2'!G38 -> 16309.301 | Z31: =Y31 -> 16309.301 | AA31: =Z31 -> 16309.301 | AB31: ='Rail&Bus2'!G39 -> 16632.756 | AC31: =AB31 -> 16632.756 | AD31: =AC31 -> 16632.756 | AE31: =AD31 -> 16632.756 | AF31: ='Rail&Bus2'!H37 -> 649.13073 | AL31: 1 | AM31: 0 | AZ31: ='Rail&Bus2'!F35 -> 12
A32: =Technologies!B75 -> R2,R3,R4,R5,R6 | B32: =Technologies!C75 -> TBH2FC | C32: ='Rail&Bus2'!B40 -> Bus, Hydrogen Fuel Cell | D32: bn-vmt, bn-vmt/a | E32: =Commodities!C$53 -> TRNH2 | F32: TB | G32: 1 | H32: ='Rail&Bus2'!E40 -> 2010 | I32: =AZ32+5 -> 17 | J32: 0.24 | K32: ='Rail&Bus2'!I40 -> 0.027477594 | V32: ='Rail&Bus2'!T12 -> 63771.6 | W32: ='Rail&Bus2'!U12 -> 51017.28 | X32: =W32 -> 51017.28 | Y32: ='Rail&Bus2'!V12 -> 31885.8 | Z32: =Y32 -> 31885.8 | AA32: =Z32 -> 31885.8 | AB32: ='Rail&Bus2'!W12 -> 19131.48 | AC32: =AB32 -> 19131.48 | AD32: =AC32 -> 19131.48 | AE32: =AD32 -> 19131.48 | AF32: ='Rail&Bus2'!H43 -> 1317.0768 | AL32: 1 | AM32: 0 | AZ32: ='Rail&Bus2'!F40 -> 12
A33: =Technologies!B76 -> R2,R3,R4,R5,R6 | B33: =Technologies!C76 -> TBH2HYB | C33: ='Rail&Bus2'!B44 -> Bus, Hydrogen Fuel Cell Hybrid | D33: bn-vmt, bn-vmt/a | E33: =Commodities!C$53 -> TRNH2 | F33: TB | G33: 1 | H33: ='Rail&Bus2'!E44 -> 2010 | I33: =AZ33+5 -> 17 | J33: 0.24 | K33: ='Rail&Bus2'!I44 -> 0.049930713 | V33: =V32 -> 63771.6 | W33: ='Rail&Bus2'!U13 -> 51017.28 | X33: =W33 -> 51017.28 | Y33: ='Rail&Bus2'!V13 -> 31885.8 | Z33: =Y33 -> 31885.8 | AA33: =Z33 -> 31885.8 | AB33: ='Rail&Bus2'!W13 -> 19131.48 | AC33: =AB33 -> 19131.48 | AD33: =AC33 -> 19131.48 | AE33: =AD33 -> 19131.48 | AF33: ='Rail&Bus2'!H44 -> 1317.0768 | AL33: 1 | AZ33: ='Rail&Bus2'!F44 -> 12
A34: =Technologies!B77 -> R2,R3,R4,R5,R6 | B34: =Technologies!C77 -> TBELC | C34: =Technologies!D77 -> Bus, Conventional ELC | D34: bn-vmt, bn-vmt/a | E34: TRNELC | F34: TB | G34: 1 | H34: 2020 | I34: 17 | J34: 0.28 | K34: 0.0811 | W34: 16379.979 | X34: 16379.979 | Y34: 16379.979 | Z34: 16379.979 | AA34: 16379.979 | AB34: 16379.979 | AC34: 16379.979 | AD34: 16379.979 | AE34: 16379.979 | AF34: 333.0323 | AL34: 1 | AZ34: 12
A35: =Technologies!B78 -> R2,R3,R4,R5,R6 | B35: =Technologies!C78 -> TBELCIM | C35: =Technologies!D78 -> Bus, Improved ELC | D35: bn-vmt, bn-vmt/a | E35: TRNELC | F35: TB | G35: 1 | H35: 2025 | I35: 17 | J35: 0.28 | L35: 0.0892 | M35: 0.0892 | N35: 0.0892 | O35: 0.0892 | P35: 0.0892 | Q35: 0.0892 | R35: 0.0892 | S35: 0.0937 | T35: 0.0937 | U35: 0.0984 | W35: 16379.979 | X35: 16379.979 | Y35: 16379.979 | Z35: 16379.979 | AA35: 16379.979 | AB35: 16379.979 | AC35: 16379.979 | AD35: 16379.979 | AE35: 16379.979 | AF35: 333.0323 | AL35: 1 | AZ35: 12
A36: *Commercial Trucks | AM36: 0
A37: * | B37: =Technologies!C81 -> TCGSLC10 | C37: =Technologies!D81 -> Commercial Truck, Gasoline 2010 | D37: bn-vmt, bn-vmt/a | E37: TCGSL | F37: =Commodities!C$18 -> TC | G37: 1 | H37: 2010 | I37: =AZ37+5 -> 20.5 | J37: 0.18 | K37: =Trucks!H7 -> 0.11893076 | V37: =Trucks!F7 -> 1113.4943 | W37: =V37 -> 1113.4943 | AF37: =Trucks!G8 -> 56.323061 | AL37: 1 | AN37: 0 | AO37: 0 | AP37: 0 | AQ37: 0 | AR37: 0 | AS37: 0 | AT37: 0 | AU37: 0 | AV37: 0 | AZ37: =Trucks!E67 -> 15.5
A38: * | B38: =Technologies!C82 -> TCGSLC | C38: =Technologies!D82 -> Commercial Truck, Conventional Gasoline | D38: bn-vmt, bn-vmt/a | E38: TCGSL | F38: =Commodities!C$18 -> TC | G38: 1 | H38: 2015 | I38: =AZ38+5 -> 20.5 | J38: 0.18 | M38: =Trucks!H8 -> 0.12946583 | N38: =Trucks!H9 -> 0.13360732 | O38: =N38 -> 0.13360732 | P38: =O38 -> 0.13360732 | Q38: =P38 -> 0.13360732 | R38: =Q38 -> 0.13360732 | S38: =R38 -> 0.13360732 | T38: =S38 -> 0.13360732 | U38: =T38 -> 0.13360732 | W38: =Trucks!F8 -> 1122.3649 | X38: =Trucks!F9 -> 1130.932 | Y38: =X38 -> 1130.932 | Z38: =Y38 -> 1130.932 | AA38: =Z38 -> 1130.932 | AB38: =AA38 -> 1130.932 | AC38: =AB38 -> 1130.932 | AD38: =AC38 -> 1130.932 | AE38: =AD38 -> 1130.932 | AF38: =Trucks!G8 -> 56.323061 | AL38: 1 | AZ38: =Trucks!E8 -> 15.5
A39: * | B39: =Technologies!C83 -> TCGSLIM | C39: =Technologies!D83 -> Commercial Truck, Improved Gasoline | D39: bn-vmt, bn-vmt/a | E39: TCGSL | F39: =Commodities!C$18 -> TC | G39: 1 | H39: 2025 | I39: =AZ39+5 -> 20.5 | J39: 0.24 | O39: =Trucks!H10 -> 0.14372909 | P39: =O39 -> 0.14372909 | Q39: =P39 -> 0.14372909 | R39: =Trucks!H11 -> 0.15823696 | S39: =R39 -> 0.15823696 | T39: =S39 -> 0.15823696 | U39: =T39 -> 0.15823696 | Y39: =Trucks!F10 -> 1170.8328 | Z39: =Y39 -> 1170.8328 | AA39: =Z39 -> 1170.8328 | AB39: =Trucks!F11 -> 1207.5097 | AC39: =AB39 -> 1207.5097 | AD39: =AC39 -> 1207.5097 | AE39: =AD39 -> 1207.5097 | AF39: =AF38 -> 56.323061 | AL39: 1 | AZ39: 15.5
A40: * | B40: =Technologies!C84 -> TCGSLADV | C40: =Technologies!D84 -> Commercial Truck, Advanced Tech Gasoline | D40: bn-vmt, bn-vmt/a | E40: TCGSL | F40: =Commodities!C$18 -> TC | G40: 1 | H40: =Trucks!D12 -> 2015 | I40: =AZ40+5 -> 20.5 | J40: 0.28 | M40: =Trucks!H12 -> 0.1888553 | N40: =M40 -> 0.1888553 | O40: =Trucks!H13 -> 0.23592152 | P40: =O40 -> 0.23592152 | Q40: =P40 -> 0.23592152 | R40: =Q40 -> 0.23592152 | S40: =R40 -> 0.23592152 | T40: =S40 -> 0.23592152 | U40: =T40 -> 0.23592152 | W40: =Trucks!F12 -> 1215.2079 | X40: =W40 -> 1215.2079 | Y40: =Trucks!F13 -> 1256.5737 | Z40: =Y40 -> 1256.5737 | AA40: =Z40 -> 1256.5737 | AB40: =AA40 -> 1256.5737 | AC40: =AB40 -> 1256.5737 | AD40: =AC40 -> 1256.5737 | AE40: =AD40 -> 1256.5737 | AF40: =Trucks!G12 -> 56.323061 | AL40: 1 | AZ40: =Trucks!E12 -> 15.5
A41: * | B41: =Technologies!C85 -> TCGSLAH | C41: =Technologies!D85 -> Commercial Truck, Advanced Hybrid Tech Gasoline | D41: bn-vmt, bn-vmt/a | E41: TCGSL | F41: =Commodities!C$18 -> TC | G41: 1 | H41: =Trucks!D14 -> 2015 | I41: =AZ41+5 -> 20.5 | J41: 0.28 | M41: =Trucks!H14 -> 0.23111368 | N41: =M41 -> 0.23111368 | O41: =Trucks!H15 -> 0.2887234 | P41: =O41 -> 0.2887234 | Q41: =P41 -> 0.2887234 | R41: =Trucks!H16 -> 0.29184428 | S41: =R41 -> 0.29184428 | T41: =S41 -> 0.29184428 | U41: =T41 -> 0.29184428 | W41: =Trucks!F14 -> 1476.4571 | X41: =W41 -> 1476.4571 | Y41: =Trucks!F15 -> 1517.8299 | Z41: =Y41 -> 1517.8299 | AA41: =Z41 -> 1517.8299 | AB41: =Trucks!F16 -> 1524.404 | AC41: =AB41 -> 1524.404 | AD41: =AC41 -> 1524.404 | AE41: =AD41 -> 1524.404 | AF41: =Trucks!G14 -> 56.323061 | AL41: 1 | AZ41: =Trucks!E14 -> 15.5
A42: * | B42: =Technologies!C86 -> TCDSLC10 | C42: =Technologies!D86 -> Commercial Truck, Diesel 2010 | D42: bn-vmt, bn-vmt/a | E42: TCDSL | F42: =Commodities!C$18 -> TC | G42: 1 | H42: 2010 | I42: =AZ42+5 -> 20.5 | J42: 0.18 | K42: =Trucks!H17 -> 0.13584461 | V42: =Trucks!F17 -> 1393.1309 | AF42: =Trucks!G17 -> 30.977683 | AL42: 1 | AN42: 0 | AO42: 0 | AP42: 0 | AQ42: 0 | AR42: 0 | AS42: 0 | AT42: 0 | AU42: 0 | AV42: 0 | AZ42: 15.5
A43: * | B43: =Technologies!C87 -> TCDSLC | C43: =Technologies!D87 -> Commercial Truck, Conventional Diesel | D43: bn-vmt, bn-vmt/a | E43: TCDSL | F43: =Commodities!C$18 -> TC | G43: 1 | H43: 2015 | I43: =AZ43+5 -> 20.5 | J43: 0.18 | M43: =Trucks!H18 -> 0.14846917 | N43: =Trucks!H19 -> 0.15596404 | O43: =N43 -> 0.15596404 | P43: =O43 -> 0.15596404 | Q43: =P43 -> 0.15596404 | R43: =Q43 -> 0.15596404 | S43: =R43 -> 0.15596404 | T43: =S43 -> 0.15596404 | U43: =T43 -> 0.15596404 | W43: =Trucks!F18 -> 1403.6763 | X43: =Trucks!F19 -> 1413.3892 | Y43: =X43 -> 1413.3892 | Z43: =Y43 -> 1413.3892 | AA43: =Z43 -> 1413.3892 | AB43: =AA43 -> 1413.3892 | AC43: =AB43 -> 1413.3892 | AD43: =AC43 -> 1413.3892 | AE43: =AD43 -> 1413.3892 | AF43: =Trucks!G18 -> 30.977683 | AL43: 1 | AZ43: =Trucks!E18 -> 15.5
A44: * | B44: =Technologies!C88 -> TCDSLIM | C44: =Technologies!D88 -> Commercial Truck, Improved Diesel | D44: bn-vmt, bn-vmt/a | E44: TCDSL | F44: =Commodities!C$18 -> TC | G44: 1 | H44: 2025 | I44: =AZ44+5 -> 20.5 | J44: 0.24 | K44: =Trucks!H20 -> 0.1774427 | Y44: =Trucks!F20 -> 1460.5131 | Z44: =Y44 -> 1460.5131 | AA44: =Z44 -> 1460.5131 | AB44: =AA44 -> 1460.5131 | AC44: =AB44 -> 1460.5131 | AD44: =AC44 -> 1460.5131 | AE44: =AD44 -> 1460.5131 | AF44: =AF43 -> 30.977683 | AL44: 1 | AZ44: 15.5
A45: * | B45: =Technologies!C89 -> TCDSLAH | C45: =Technologies!D89 -> Commercial Truck, Advanced Hybrid Diesel | D45: bn-vmt, bn-vmt/a | E45: TCDSL | F45: =Commodities!C$18 -> TC | G45: 1 | H45: =Trucks!D21 -> 2015 | I45: =AZ45+5 -> 20.5 | J45: 0.28 | M45: =Trucks!H21 -> 0.21639147 | N45: =M45 -> 0.21639147 | O45: =Trucks!H22 -> 0.25348957 | P45: =O45 -> 0.25348957 | Q45: =P45 -> 0.25348957 | R45: =Trucks!H23 -> 0.25348957 | S45: =R45 -> 0.25348957 | T45: =S45 -> 0.25348957 | U45: =T45 -> 0.25348957 | W45: =Trucks!F21 -> 1905.3811 | X45: =W45 -> 1905.3811 | Y45: =Trucks!F22 -> 1905.3811 | Z45: =Y45 -> 1905.3811 | AA45: =Z45 -> 1905.3811 | AB45: =Trucks!F23 -> 1905.3811 | AC45: =AB45 -> 1905.3811 | AD45: =AC45 -> 1905.3811 | AE45: =AD45 -> 1905.3811 | AF45: =Trucks!G21 -> 30.977683 | AL45: 1 | AZ45: =Trucks!E21 -> 15.5
A46: * | B46: =Technologies!C90 -> TCB20C10 | C46: =Technologies!D90 -> Commercial Truck, B20 2010 | D46: bn-vmt, bn-vmt/a | E46: TCB20X | F46: =Commodities!C$18 -> TC | G46: 1 | H46: 2010 | I46: =AZ46+5 -> 20.5 | J46: 0.18 | K46: =Trucks!H24 -> 0.1357487 | V46: =Trucks!F24 -> 1393.1309 | AF46: =Trucks!G24 -> 30.977683 | AL46: 1 | AN46: 0 | AO46: 0 | AP46: 0 | AQ46: 0 | AR46: 0 | AS46: 0 | AT46: 0 | AU46: 0 | AV46: 0 | AZ46: 15.5
A47: * | B47: =Technologies!C91 -> TCB20C | C47: =Technologies!D91 -> Commercial Truck, Conventional B20 | D47: bn-vmt, bn-vmt/a | E47: TCB20X | F47: =Commodities!C$18 -> TC | G47: 1 | H47: 2015 | I47: =AZ47+5 -> 20.5 | J47: 0.18 | M47: =Trucks!H25 -> 0.14836435 | N47: =Trucks!H26 -> 0.15585394 | O47: =N47 -> 0.15585394 | P47: =O47 -> 0.15585394 | Q47: =P47 -> 0.15585394 | R47: =Q47 -> 0.15585394 | S47: =R47 -> 0.15585394 | T47: =S47 -> 0.15585394 | U47: =T47 -> 0.15585394 | W47: =Trucks!F25 -> 1403.6763 | X47: =Trucks!F26 -> 1413.3892 | Y47: =X47 -> 1413.3892 | Z47: =Y47 -> 1413.3892 | AA47: =Z47 -> 1413.3892 | AB47: =AA47 -> 1413.3892 | AC47: =AB47 -> 1413.3892 | AD47: =AC47 -> 1413.3892 | AE47: =AD47 -> 1413.3892 | AF47: =Trucks!G25 -> 30.977683 | AL47: 1 | AZ47: =Trucks!E25 -> 15.5
A48: * | B48: =Technologies!C92 -> TCB20IM | C48: =Technologies!D92 -> Commercial Truck, Improved B20 | D48: bn-vmt, bn-vmt/a | E48: TCB20X | F48: =Commodities!C$18 -> TC | G48: 1 | H48: 2025 | I48: =AZ48+5 -> 20.5 | J48: 0.24 | K48: =Trucks!H27 -> 0.17744838 | Y48: =Trucks!F27 -> 1460.5131 | Z48: =Y48 -> 1460.5131 | AA48: =Z48 -> 1460.5131 | AB48: =AA48 -> 1460.5131 | AC48: =AB48 -> 1460.5131 | AD48: =AC48 -> 1460.5131 | AE48: =AD48 -> 1460.5131 | AF48: =Trucks!G27 -> 30.977683 | AL48: 1 | AZ48: 15.5
A49: * | B49: =Technologies!C93 -> TCB20AH | C49: =Technologies!D93 -> Commerical Truck, Advanced Hybrid B20 | D49: bn-vmt, bn-vmt/a | E49: TCB20X | F49: =Commodities!C$18 -> TC | G49: 1 | H49: 2015 | I49: =AZ49+5 -> 20.5 | J49: 0.28 | M49: =Trucks!H28 -> 0.21639841 | N49: =M49 -> 0.21639841 | O49: =Trucks!H29 -> 0.25349769 | P49: =O49 -> 0.25349769 | Q49: =P49 -> 0.25349769 | R49: =Trucks!H30 -> 0.25349769 | S49: =R49 -> 0.25349769 | T49: =S49 -> 0.25349769 | U49: =T49 -> 0.25349769 | W49: =Trucks!F28 -> 1905.3811 | X49: =W49 -> 1905.3811 | Y49: =Trucks!F29 -> 1905.3811 | Z49: =Y49 -> 1905.3811 | AA49: =Z49 -> 1905.3811 | AB49: =Trucks!F30 -> 1905.3811 | AC49: =AB49 -> 1905.3811 | AD49: =AC49 -> 1905.3811 | AE49: =AD49 -> 1905.3811 | AF49: =Trucks!G28 -> 30.977683 | AL49: 1 | AZ49: 15.5
A50: * | B50: =Technologies!C94 -> TCCNGC10 | C50: =Technologies!D94 -> Commercial Truck, CNG 2010 | D50: bn-vmt, bn-vmt/a | E50: =Commodities!C$56 -> TCCNG | F50: =Commodities!C$18 -> TC | G50: 1 | H50: 2010 | I50: =AZ50+5 -> 20.5 | J50: 0.18 | K50: =Trucks!H31 -> 0.12808843 | V50: =Trucks!F31 -> 1441.6321 | AF50: =Trucks!G31 -> 56.323061 | AL50: 1 | AN50: 0 | AO50: 0 | AP50: 0 | AQ50: 0 | AR50: 0 | AS50: 0 | AT50: 0 | AU50: 0 | AV50: 0 | AZ50: 15.5
A51: * | B51: =Technologies!C95 -> TCCNGC | C51: =Technologies!D95 -> Commercial Truck, Conventional CNG | D51: bn-vmt, bn-vmt/a | E51: =Commodities!C$56 -> TCCNG | F51: =Commodities!C$18 -> TC | G51: 1 | H51: 2015 | I51: =AZ51+5 -> 20.5 | J51: 0.18 | M51: =Trucks!H32 -> 0.1394347 | N51: =Trucks!H33 -> 0.14271413 | O51: =N51 -> 0.14271413 | P51: =O51 -> 0.14271413 | Q51: =P51 -> 0.14271413 | R51: =Q51 -> 0.14271413 | S51: =R51 -> 0.14271413 | T51: =S51 -> 0.14271413 | U51: =T51 -> 0.14271413 | W51: =Trucks!F32 -> 1453.1169 | X51: =Trucks!F33 -> 1464.2086 | Y51: =X51 -> 1464.2086 | Z51: =Y51 -> 1464.2086 | AA51: =Z51 -> 1464.2086 | AB51: =AA51 -> 1464.2086 | AC51: =AB51 -> 1464.2086 | AD51: =AC51 -> 1464.2086 | AE51: =AD51 -> 1464.2086 | AF51: =Trucks!G32 -> 56.323061 | AL51: 1 | AZ51: =Trucks!E32 -> 15.5
A52: * | B52: =Technologies!C96 -> TCCNGIM | C52: =Technologies!D96 -> Commercial Truck, Improved CNG | D52: bn-vmt, bn-vmt/a | E52: =Commodities!C$56 -> TCCNG | F52: =Commodities!C$18 -> TC | G52: 1 | H52: 2025 | I52: =AZ52+5 -> 20.5 | J52: 0.24 | O52: =Trucks!H34 -> 0.18738156 | P52: =O52 -> 0.18738156 | Q52: =P52 -> 0.18738156 | R52: =Trucks!H35 -> 0.21329903 | S52: =R52 -> 0.21329903 | T52: =S52 -> 0.21329903 | U52: =T52 -> 0.21329903 | Y52: =Trucks!F34 -> 1503.8621 | Z52: =Y52 -> 1503.8621 | AA52: =Z52 -> 1503.8621 | AB52: =Trucks!F35 -> 1581.2056 | AC52: =AB52 -> 1581.2056 | AD52: =AC52 -> 1581.2056 | AE52: =AD52 -> 1581.2056 | AF52: =AF51 -> 56.323061 | AL52: 1 | AZ52: 15.5
A53: * | B53: =Technologies!C97 -> TCCNGADV | C53: =Technologies!D97 -> Commerical Truck, Advanced CNG | D53: bn-vmt, bn-vmt/a | E53: =Commodities!C$56 -> TCCNG | F53: =Commodities!C$18 -> TC | G53: 1 | H53: 2015 | I53: =AZ53+5 -> 20.5 | J53: 0.28 | M53: =Trucks!H36 -> 0.22501753 | N53: =M53 -> 0.22501753 | O53: =Trucks!H37 -> 0.28110087 | P53: =O53 -> 0.28110087 | Q53: =P53 -> 0.28110087 | R53: =Trucks!H38 -> 0.28415431 | S53: =R53 -> 0.28415431 | T53: =S53 -> 0.28415431 | U53: =T53 -> 0.28415431 | W53: =Trucks!F36 -> 1508.0083 | X53: =W53 -> 1508.0083 | Y53: =Trucks!F37 -> 1549.3743 | Z53: =Y53 -> 1549.3743 | AA53: =Z53 -> 1549.3743 | AB53: =Trucks!F38 -> 1555.9665 | AC53: =AB53 -> 1555.9665 | AD53: =AC53 -> 1555.9665 | AE53: =AD53 -> 1555.9665 | AF53: =Trucks!G36 -> 56.323061 | AL53: 1 | AZ53: 15.5
A54: * | B54: =Technologies!C98 -> TCCNGAH | C54: =Technologies!D98 -> Commerical Truck, Advanced Hybrid CNG | D54: bn-vmt, bn-vmt/a | E54: =Commodities!C$56 -> TCCNG | F54: =Commodities!C$18 -> TC | G54: 1 | H54: 2015 | I54: =AZ54+5 -> 20.5 | J54: 0.28 | M54: =Trucks!H39 -> 0.31614963 | N54: =M54 -> 0.31614963 | O54: =Trucks!H40 -> 0.39494672 | P54: =O54 -> 0.39494672 | Q54: =P54 -> 0.39494672 | R54: =Trucks!H41 -> 0.3992368 | S54: =R54 -> 0.3992368 | T54: =S54 -> 0.3992368 | U54: =T54 -> 0.3992368 | W54: =Trucks!F39 -> 1804.5869 | X54: =W54 -> 1804.5869 | Y54: =Trucks!F40 -> 1845.953 | Z54: =Y54 -> 1845.953 | AA54: =Z54 -> 1845.953 | AB54: =Trucks!F41 -> 1852.5452 | AC54: =AB54 -> 1852.5452 | AD54: =AC54 -> 1852.5452 | AE54: =AD54 -> 1852.5452 | AF54: =Trucks!G39 -> 56.323061 | AL54: 1 | AZ54: 15.5
A55: * | B55: =Technologies!C99 -> TCE85C10 | C55: =Technologies!D99 -> Commercial Truck, E85 2010 | D55: bn-vmt, bn-vmt/a | E55: TCE85X | F55: =Commodities!C$18 -> TC | G55: 1 | H55: 2010 | I55: =AZ55+5 -> 20.5 | J55: 0.18 | K55: =Trucks!H42 -> 0.10181148 | V55: =Trucks!F42 -> 1154.5364 | AF55: =Trucks!G42 -> 56.323061 | AL55: 1 | AN55: 0 | AO55: 0 | AP55: 0 | AQ55: 0 | AR55: 0 | AS55: 0 | AT55: 0 | AU55: 0 | AV55: 0 | AZ55: 15.5
A56: * | B56: =Technologies!C100 -> TCE85C | C56: =Technologies!D100 -> Commercial Truck, Conventional E85 | D56: bn-vmt, bn-vmt/a | E56: TCE85X | F56: =Commodities!C$18 -> TC | G56: 1 | H56: 2015 | I56: =AZ56+5 -> 20.5 | J56: 0.18 | M56: =Trucks!H43 -> 0.1108301 | N56: =Trucks!H44 -> 0.11437545 | O56: =N56 -> 0.11437545 | P56: =O56 -> 0.11437545 | Q56: =P56 -> 0.11437545 | R56: =Q56 -> 0.11437545 | S56: =R56 -> 0.11437545 | T56: =S56 -> 0.11437545 | U56: =T56 -> 0.11437545 | W56: =Trucks!F43 -> 1163.4071 | X56: =Trucks!F44 -> 1136.2853 | Y56: =X56 -> 1136.2853 | Z56: =Y56 -> 1136.2853 | AA56: =Z56 -> 1136.2853 | AB56: =AA56 -> 1136.2853 | AC56: =AB56 -> 1136.2853 | AD56: =AC56 -> 1136.2853 | AE56: =AD56 -> 1136.2853 | AF56: =Trucks!G43 -> 56.323061 | AL56: 1 | AZ56: =Trucks!E43 -> 15.5
A57: * | B57: =Technologies!C101 -> TCE85IM | C57: =Technologies!D101 -> Commercial Truck, Improved E85 | D57: bn-vmt, bn-vmt/a | E57: TCE85X | F57: =Commodities!C$18 -> TC | G57: 1 | H57: 2025 | I57: =AZ57+5 -> 20.5 | J57: 0.24 | O57: =Trucks!H45 -> 0.12304026 | P57: =O57 -> 0.12304026 | Q57: =P57 -> 0.12304026 | R57: =Trucks!H46 -> 0.13545981 | S57: =R57 -> 0.13545981 | T57: =S57 -> 0.13545981 | U57: =T57 -> 0.13545981 | Y57: =Trucks!F45 -> 1176.1861 | Z57: =Y57 -> 1176.1861 | AA57: =Z57 -> 1176.1861 | AB57: =Trucks!F46 -> 1212.863 | AC57: =AB57 -> 1212.863 | AD57: =AC57 -> 1212.863 | AE57: =AD57 -> 1212.863 | AF57: =AF56 -> 56.323061 | AL57: 1 | AZ57: 15.5
A58: * | B58: =Technologies!C102 -> TCE85ADV | C58: =Technologies!D102 -> Commercial Truck, Advanced E85 | D58: bn-vmt, bn-vmt/a | E58: TCE85X | F58: =Commodities!C$18 -> TC | G58: 1 | H58: 2015 | I58: =AZ58+5 -> 20.5 | J58: 0.28 | M58: =Trucks!H47 -> 0.17885587 | N58: =M58 -> 0.17885587 | O58: =Trucks!H48 -> 0.22343388 | P58: =O58 -> 0.22343388 | Q58: =P58 -> 0.22343388 | R58: =Trucks!H49 -> 0.22586092 | S58: =R58 -> 0.22586092 | T58: =S58 -> 0.22586092 | U58: =T58 -> 0.22586092 | W58: =Trucks!F47 -> 1184.7542 | X58: =W58 -> 1184.7542 | Y58: =Trucks!F48 -> 1226.1202 | Z58: =Y58 -> 1226.1202 | AA58: =Z58 -> 1226.1202 | AB58: =Trucks!F49 -> 1232.7124 | AC58: =AB58 -> 1232.7124 | AD58: =AC58 -> 1232.7124 | AE58: =AD58 -> 1232.7124 | AF58: =AF57 -> 56.323061 | AL58: 1 | AZ58: 15.5
A59: * | B59: =Technologies!C103 -> TCE85AH | C59: =Technologies!D103 -> Commerical Truck, Hybrid E85 | D59: bn-vmt, bn-vmt/a | E59: TCE85X | F59: =Commodities!C$18 -> TC | G59: 1 | H59: 2015 | I59: =AZ59+5 -> 20.5 | J59: 0.28 | M59: =Trucks!H50 -> 0.2512925 | N59: =M59 -> 0.2512925 | O59: =Trucks!H51 -> 0.3139246 | P59: =O59 -> 0.3139246 | Q59: =P59 -> 0.3139246 | R59: =Trucks!H52 -> 0.31733459 | S59: =R59 -> 0.31733459 | T59: =S59 -> 0.31733459 | U59: =T59 -> 0.31733459 | W59: =Trucks!F50 -> 1481.3328 | X59: =W59 -> 1481.3328 | Y59: =Trucks!F51 -> 1522.6989 | Z59: =Y59 -> 1522.6989 | AA59: =Z59 -> 1522.6989 | AB59: =Trucks!F52 -> 1529.2911 | AC59: =AB59 -> 1529.2911 | AD59: =AC59 -> 1529.2911 | AE59: =AD59 -> 1529.2911 | AF59: =AF58 -> 56.323061 | AL59: 1 | AZ59: 15.5
A60: * | B60: =Technologies!C104 -> TCLPGC10 | C60: =Technologies!D104 -> Commercial Truck, LPG 2010 | D60: bn-vmt, bn-vmt/a | E60: =Commodities!C29 -> TRNLPG1 | F60: =Commodities!C$18 -> TC | G60: 1 | H60: 2010 | I60: =AZ60+5 -> 20.5 | J60: 0.18 | K60: =Trucks!H53 -> 0.11401158 | V60: =Trucks!F53 -> 1397.7833 | AF60: =Trucks!G53 -> 56.323061 | AL60: 1 | AN60: 0 | AO60: 0 | AP60: 0 | AQ60: 0 | AR60: 0 | AS60: 0 | AT60: 0 | AU60: 0 | AV60: 0 | AZ60: 15.5
A61: * | B61: =Technologies!C105 -> TCLPGC | C61: =Technologies!D105 -> Commercial Truck, Conventional LPG | D61: bn-vmt, bn-vmt/a | E61: =Commodities!C29 -> TRNLPG1 | F61: =Commodities!C$18 -> TC | G61: 1 | H61: 2015 | I61: =AZ61+5 -> 20.5 | J61: 0.18 | M61: =Trucks!H54 -> 0.12411091 | N61: =Trucks!H55 -> 0.1280811 | O61: =N61 -> 0.1280811 | P61: =O61 -> 0.1280811 | Q61: =P61 -> 0.1280811 | R61: =Q61 -> 0.1280811 | S61: =R61 -> 0.1280811 | T61: =S61 -> 0.1280811 | U61: =T61 -> 0.1280811 | W61: =Trucks!F54 -> 1408.9187 | X61: =Trucks!F55 -> 1419.673 | Y61: =X61 -> 1419.673 | Z61: =Y61 -> 1419.673 | AA61: =Z61 -> 1419.673 | AB61: =AA61 -> 1419.673 | AC61: =AB61 -> 1419.673 | AD61: =AC61 -> 1419.673 | AE61: =AD61 -> 1419.673 | AF61: =Trucks!G54 -> 56.323061 | AL61: 1 | AZ61: =Trucks!E54 -> 15.5
A62: * | B62: =Technologies!C106 -> TCLPGIM | C62: =Technologies!D106 -> Commercial Truck, Improved LPG | D62: bn-vmt, bn-vmt/a | E62: =Commodities!C29 -> TRNLPG1 | F62: =Commodities!C$18 -> TC | G62: 1 | H62: 2025 | I62: =AZ62+5 -> 20.5 | J62: 0.24 | O62: =Trucks!H56 -> 0.16678843 | P62: =O62 -> 0.16678843 | Q62: =P62 -> 0.16678843 | R62: =Trucks!H57 -> 0.18985759 | S62: =R62 -> 0.18985759 | T62: =S62 -> 0.18985759 | U62: =T62 -> 0.18985759 | Y62: =Trucks!F56 -> 1458.1205 | Z62: =Y62 -> 1458.1205 | AA62: =Z62 -> 1458.1205 | AB62: =Trucks!F57 -> 1533.1114 | AC62: =AB62 -> 1533.1114 | AD62: =AC62 -> 1533.1114 | AE62: =AD62 -> 1533.1114 | AF62: =AF61 -> 56.323061 | AL62: 1 | AZ62: 15.5
A63: * | B63: =Technologies!C107 -> TCLPGADV | C63: =Technologies!D107 -> Commercial Truck, Advanced LPG | D63: bn-vmt, bn-vmt/a | E63: =Commodities!C29 -> TRNLPG1 | F63: =Commodities!C$18 -> TC | G63: 1 | H63: 2015 | I63: =AZ63+5 -> 20.5 | J63: 0.28 | M63: =Trucks!H58 -> 0.20028823 | N63: =M63 -> 0.20028823 | O63: =Trucks!H59 -> 0.25020804 | P63: =O63 -> 0.25020804 | Q63: =P63 -> 0.25020804 | R63: =Trucks!H60 -> 0.25292591 | S63: =R63 -> 0.25292591 | T63: =S63 -> 0.25292591 | U63: =T63 -> 0.25292591 | W63: =Trucks!F58 -> 1464.1594 | X63: =W63 -> 1464.1594 | Y63: =Trucks!F60 -> 1512.1177 | Z63: =Y63 -> 1512.1177 | AA63: =Z63 -> 1512.1177 | AB63: =Trucks!F60 -> 1512.1177 | AC63: =AB63 -> 1512.1177 | AD63: =AC63 -> 1512.1177 | AE63: =AD63 -> 1512.1177 | AF63: =AF62 -> 56.323061 | AL63: 1 | AZ63: 15.5
A64: * | B64: =Technologies!C108 -> TCLPGAH | C64: =Technologies!D108 -> Commercial Truck, Hybrid LPG | D64: bn-vmt, bn-vmt/a | E64: =Commodities!C29 -> TRNLPG1 | F64: =Commodities!C$18 -> TC | G64: 1 | H64: 2015 | I64: =AZ64+5 -> 20.5 | J64: 0.28 | M64: =Trucks!H61 -> 0.28140496 | N64: =M64 -> 0.28140496 | O64: =Trucks!H62 -> 0.35154229 | P64: =O64 -> 0.35154229 | Q64: =P64 -> 0.35154229 | R64: =Trucks!H63 -> 0.3553609 | S64: =R64 -> 0.3553609 | T64: =S64 -> 0.3553609 | U64: =T64 -> 0.3553609 | W64: =Trucks!F61 -> 1760.7381 | X64: =W64 -> 1760.7381 | Y64: =Trucks!F62 -> 1802.1041 | Z64: =Y64 -> 1802.1041 | AA64: =Z64 -> 1802.1041 | AB64: =Trucks!F63 -> 1808.6964 | AC64: =AB64 -> 1808.6964 | AD64: =AC64 -> 1808.6964 | AE64: =AD64 -> 1808.6964 | AF64: =AF63 -> 56.323061 | AL64: 1 | AZ64: 15.5
A65: * | B65: =Technologies!C109 -> TCH2FC | C65: =Technologies!D109 -> Commercial Truck, Hydrogen Fuel Cell | D65: bn-vmt, bn-vmt/a | E65: =Commodities!C53 -> TRNH2 | F65: =Commodities!C$18 -> TC | G65: 1 | H65: =Trucks!D64 -> 2025 | I65: =AZ65+5 -> 20.5 | J65: 0.24 | O65: =Trucks!H64 -> 0.34109858 | P65: =O65 -> 0.34109858 | Q65: =P65 -> 0.34109858 | R65: =Trucks!H65 -> 0.34109858 | S65: =R65 -> 0.34109858 | T65: =S65 -> 0.34109858 | U65: =T65 -> 0.34109858 | Y65: =Trucks!F64 -> 2696.3939 | Z65: =Y65 -> 2696.3939 | AA65: =Z65 -> 2696.3939 | AB65: =Trucks!F65 -> 2696.3939 | AC65: =AB65 -> 2696.3939 | AD65: =AC65 -> 2696.3939 | AE65: =AD65 -> 2696.3939 | AF65: =Trucks!G64 -> 15.488842 | AL65: 1 | AZ65: =Trucks!E64 -> 15.5
A66: *Medium Duty Trucks
A67: =Technologies!B114 -> R2,R3,R4,R5,R6 | B67: =Technologies!C114 -> TMGSLC10 | C67: =Technologies!D114 -> Medium Duty Truck, Gasoline, 2010 | D67: bn-vmt, bn-vmt/a | E67: =Commodities!C$39 -> TMGSL | F67: =Commodities!C$11 -> TM | G67: 1 | H67: 2010 | I67: =AZ67+5 -> 24 | J67: 0.18 | K67: =Trucks!H88 -> 0.062417563 | V67: =Trucks!F88 -> 5812.2034 | AF67: =Trucks!G88 -> 248.8047 | AL67: 1 | AM67: 0 | AN67: 0 | AO67: 0 | AP67: 0 | AQ67: 0 | AR67: 0 | AS67: 0 | AT67: 0 | AU67: 0 | AV67: 0 | AZ67: 19
A68: =Technologies!B115 -> R2,R3,R4,R5,R6 | B68: =Technologies!C115 -> TMGSLC | C68: =Technologies!D115 -> Medium Duty Truck, Conventional Gasoline | D68: bn-vmt, bn-vmt/a | E68: =Commodities!C$39 -> TMGSL | F68: =Commodities!C$11 -> TM | G68: 1 | H68: 2015 | I68: =AZ68+5 -> 24 | J68: 0.18 | M68: =Trucks!H89 -> 0.064948005 | N68: =Trucks!H90 -> 0.06973054 | O68: =N68 -> 0.06973054 | P68: =O68 -> 0.06973054 | Q68: =P68 -> 0.06973054 | R68: =Q68 -> 0.06973054 | S68: =R68 -> 0.06973054 | T68: =S68 -> 0.06973054 | U68: =T68 -> 0.06973054 | W68: =Trucks!F89 -> 5834.9327 | X68: =Trucks!F90 -> 5908.6664 | Y68: =Trucks!F90 -> 5908.6664 | Z68: =Y68 -> 5908.6664 | AA68: =Z68 -> 5908.6664 | AB68: =AA68 -> 5908.6664 | AC68: =AB68 -> 5908.6664 | AD68: =AC68 -> 5908.6664 | AE68: =AD68 -> 5908.6664 | AF68: =Trucks!G88 -> 248.8047 | AG68: 0 | AH68: 0 | AI68: 0 | AJ68: 0 | AK68: 0 | AL68: 1 | AM68: 0 | AO68: 0 | AP68: 0 | AQ68: 0 | AR68: 0 | AS68: 0 | AT68: 0 | AU68: 0 | AV68: 0 | AZ68: 19
A69: =Technologies!B116 -> R2,R3,R4,R5,R6 | B69: =Technologies!C116 -> TMGSLIM | C69: =Technologies!D116 -> Medium Duty Truck, Improved Gasoline | D69: bn-vmt, bn-vmt/a | E69: =Commodities!C$39 -> TMGSL | F69: =Commodities!C$11 -> TM | G69: 1 | H69: 2025 | I69: =AZ69+5 -> 24 | J69: 0.24 | K69: =Trucks!H91 -> 0.075246903 | Y69: =Trucks!F91 -> 6443.5419 | Z69: =Y69 -> 6443.5419 | AA69: =Z69 -> 6443.5419 | AB69: =AA69 -> 6443.5419 | AC69: =AB69 -> 6443.5419 | AD69: =AC69 -> 6443.5419 | AE69: =AD69 -> 6443.5419 | AF69: =Trucks!G89 -> 248.8047 | AG69: 0 | AH69: 0 | AI69: 0 | AJ69: 0 | AK69: 0 | AL69: 1 | AM69: 0 | AN69: 0 | AZ69: 19
A70: =Technologies!B117 -> R2,R3,R4,R5,R6 | B70: =Technologies!C117 -> TMGSLAH | C70: =Technologies!D117 -> Medium Duty Truck, Advanced Hybrid Gasoline | D70: bn-vmt, bn-vmt/a | E70: =Commodities!C$39 -> TMGSL | F70: =Commodities!C$11 -> TM | G70: 1 | H70: =Trucks!D92 -> 2015 | I70: =AZ70+5 -> 24 | J70: 0.28 | M70: =Trucks!H92 -> 0.078865434 | N70: =M70 -> 0.078865434 | O70: =Trucks!H93 -> 0.099615057 | P70: =O70 -> 0.099615057 | Q70: =P70 -> 0.099615057 | R70: =Trucks!H94 -> 0.10749317 | S70: =R70 -> 0.10749317 | T70: =S70 -> 0.10749317 | U70: =T70 -> 0.10749317 | W70: =Trucks!F92 -> 6616.01 | X70: =W70 -> 6616.01 | Y70: =Trucks!F93 -> 6935.0019 | Z70: =Y70 -> 6935.0019 | AA70: =Z70 -> 6935.0019 | AB70: =Trucks!F94 -> 7469.8773 | AC70: =AB70 -> 7469.8773 | AD70: =AC70 -> 7469.8773 | AE70: =AD70 -> 7469.8773 | AF70: =Trucks!G92 -> 237.85729 | AG70: 0 | AH70: 0 | AI70: 0 | AJ70: 0 | AK70: 0 | AL70: 1 | AM70: 0 | AN70: 0 | AZ70: =Trucks!E92 -> 19
A71: =Technologies!B118 -> R2,R3,R4,R5,R6 | B71: =Technologies!C118 -> TMDSLC10 | C71: =Technologies!D118 -> Medium Duty Truck, Diesel, 2010 | D71: bn-vmt, bn-vmt/a | E71: =Commodities!C$42 -> TMDSL | F71: =Commodities!C$11 -> TM | G71: 1 | H71: 2010 | I71: =AZ71+5 -> 24 | J71: 0.18 | K71: =TechData!K19 -> 0.06089011 | V71: =Trucks!F78 -> 6276.5914 | AF71: =Trucks!G78 -> 136.84259 | AG71: 0 | AH71: 0 | AI71: 0 | AJ71: 0 | AK71: 0 | AL71: 1 | AM71: 0 | AN71: 0 | AO71: 0 | AP71: 0 | AQ71: 0 | AR71: 0 | AS71: 0 | AT71: 0 | AU71: 0 | AV71: 0 | AZ71: 19
A72: =Technologies!B119 -> R2,R3,R4,R5,R6 | B72: =Technologies!C119 -> TMDSLC | C72: =Technologies!D119 -> Medium Duty Truck, Conventional Diesel | D72: bn-vmt, bn-vmt/a | E72: =Commodities!C$42 -> TMDSL | F72: =Commodities!C$11 -> TM | G72: 1 | H72: 2015 | I72: =AZ72+5 -> 24 | J72: 0.18 | M72: =Trucks!H79 -> 0.075263594 | N72: =Trucks!H80 -> 0.082850619 | O72: =N72 -> 0.082850619 | P72: =O72 -> 0.082850619 | Q72: =P72 -> 0.082850619 | R72: =Q72 -> 0.082850619 | S72: =R72 -> 0.082850619 | T72: =S72 -> 0.082850619 | U72: =T72 -> 0.082850619 | W72: =Trucks!F79 -> 6295.5716 | X72: =Trucks!F80 -> 6469.2832 | Y72: =X72 -> 6469.2832 | Z72: =Y72 -> 6469.2832 | AA72: =Z72 -> 6469.2832 | AB72: =AA72 -> 6469.2832 | AC72: =AB72 -> 6469.2832 | AD72: =AC72 -> 6469.2832 | AE72: =AD72 -> 6469.2832 | AF72: =Trucks!G78 -> 136.84259 | AG72: 0 | AH72: 0 | AI72: 0 | AJ72: 0 | AK72: 0 | AL72: 1 | AM72: 0 | AZ72: 19
A73: =Technologies!B120 -> R2,R3,R4,R5,R6 | B73: =Technologies!C120 -> TMDSLIM | C73: =Technologies!D120 -> Medium Duty Truck, Improved Diesel | D73: bn-vmt, bn-vmt/a | E73: =Commodities!C$42 -> TMDSL | F73: =Commodities!C$11 -> TM | G73: 1 | H73: 2025 | I73: =AZ73+5 -> 24 | J73: 0.24 | K73: =Trucks!H81 -> 0.084286625 | Y73: =Trucks!F81 -> 6691.9683 | Z73: =Y73 -> 6691.9683 | AA73: =Z73 -> 6691.9683 | AB73: =AA73 -> 6691.9683 | AC73: =AB73 -> 6691.9683 | AD73: =AC73 -> 6691.9683 | AE73: =AD73 -> 6691.9683 | AF73: =AF72 -> 136.84259 | AG73: 0 | AH73: 0 | AI73: 0 | AJ73: 0 | AK73: 0 | AL73: 1 | AM73: 0 | AN73: 0 | AZ73: 19
A74: =Technologies!B121 -> R2,R3,R4,R5,R6 | B74: =Technologies!C121 -> TMDSLADV | C74: =Technologies!D121 -> Medium Duty Truck, Advanced Diesel | D74: bn-vmt, bn-vmt/a | E74: =Commodities!C$42 -> TMDSL | F74: =Commodities!C$11 -> TM | G74: 1 | H74: 2015 | I74: =AZ74+5 -> 24 | J74: 0.28 | M74: =Trucks!H82 -> 0.084286625 | N74: =M74 -> 0.084286625 | O74: =Trucks!H83 -> 0.087074165 | P74: =O74 -> 0.087074165 | Q74: =P74 -> 0.087074165 | R74: =Trucks!H84 -> 0.087074165 | S74: =R74 -> 0.087074165 | T74: =S74 -> 0.087074165 | U74: =T74 -> 0.087074165 | W74: =Trucks!F82 -> 6767.5657 | X74: =W74 -> 6767.5657 | Y74: =Trucks!F83 -> 6936.7579 | Z74: =Y74 -> 6936.7579 | AA74: =Z74 -> 6936.7579 | AB74: =Trucks!F84 -> 6936.7579 | AC74: =AB74 -> 6936.7579 | AD74: =AC74 -> 6936.7579 | AE74: =AD74 -> 6936.7579 | AF74: =AF73 -> 136.84259 | AG74: 0 | AH74: 0 | AI74: 0 | AJ74: 0 | AK74: 0 | AL74: 1 | AM74: 0 | AN74: 0 | AZ74: 19
A75: =Technologies!B122 -> R2,R3,R4,R5,R6 | B75: =Technologies!C122 -> TMDSLAH | C75: =Technologies!D122 -> Medium Duty Truck, Advanced Hybrid Diesel | D75: bn-vmt, bn-vmt/a | E75: =Commodities!C$42 -> TMDSL | F75: =Commodities!C$11 -> TM | G75: 1 | H75: =Trucks!D85 -> 2015 | I75: =AZ75+5 -> 24 | J75: 0.28 | M75: =Trucks!H85 -> 0.12040946 | N75: =M75 -> 0.12040946 | O75: =Trucks!H86 -> 0.12438728 | P75: =O75 -> 0.12438728 | Q75: =P75 -> 0.12438728 | R75: =Trucks!H87 -> 0.12438728 | S75: =R75 -> 0.12438728 | T75: =S75 -> 0.12438728 | U75: =T75 -> 0.12438728 | W75: =Trucks!F85 -> 8334.2222 | X75: =W75 -> 8334.2222 | Y75: =Trucks!F86 -> 7963.0153 | Z75: =Y75 -> 7963.0153 | AA75: =Z75 -> 7963.0153 | AB75: =Trucks!F87 -> 7963.0153 | AC75: =AB75 -> 7963.0153 | AD75: =AC75 -> 7963.0153 | AE75: =AD75 -> 7963.0153 | AF75: =Trucks!G85 -> 125.89518 | AG75: 0 | AH75: 0 | AI75: 0 | AJ75: 0 | AK75: 0 | AL75: 1 | AM75: 0 | AN75: 0 | AZ75: =Trucks!E85 -> 19
A76: * | B76: =Technologies!C123 -> TMB20C10 | C76: =Technologies!D123 -> Medium Duty Truck, B20, 2010 | D76: bn-vmt, bn-vmt/a | E76: =Commodities!C$63 -> TMB20X | F76: =Commodities!C$11 -> TM | G76: 1 | H76: 2010 | I76: =AZ76+5 -> 24 | J76: 0.18 | K76: =Trucks!H95 -> 0.071504036 | V76: =Trucks!F95 -> 6276.5914 | AF76: =Trucks!G95 -> 136.84259 | AL76: 1 | AN76: 0 | AO76: 0 | AP76: 0 | AQ76: 0 | AR76: 0 | AS76: 0 | AT76: 0 | AU76: 0 | AV76: 0 | AZ76: 19
A77: * | B77: =Technologies!C124 -> TMB20C | C77: =Technologies!D124 -> Medium Duty Truck, Conventional B20 | D77: bn-vmt, bn-vmt/a | E77: =Commodities!C$63 -> TMB20X | F77: =Commodities!C$11 -> TM | G77: 1 | H77: 2015 | I77: =AZ77+5 -> 24 | J77: 0.18 | M77: =Trucks!H96 -> 0.075210459 | N77: =Trucks!H97 -> 0.077965337 | O77: =N77 -> 0.077965337 | P77: =O77 -> 0.077965337 | Q77: =P77 -> 0.077965337 | R77: =Q77 -> 0.077965337 | S77: =R77 -> 0.077965337 | T77: =S77 -> 0.077965337 | U77: =T77 -> 0.077965337 | W77: =Trucks!F96 -> 6295.5716 | X77: =Trucks!F97 -> 6347.8257 | Y77: =X77 -> 6347.8257 | Z77: =Y77 -> 6347.8257 | AA77: =Z77 -> 6347.8257 | AB77: =AA77 -> 6347.8257 | AC77: =AB77 -> 6347.8257 | AD77: =AC77 -> 6347.8257 | AE77: =AD77 -> 6347.8257 | AF77: =Trucks!G96 -> 136.84259 | AL77: 1 | AZ77: 19
A78: * | B78: =Technologies!C125 -> TMB20IM | C78: =Technologies!D125 -> Medium Duty Truck, Improved B20 | D78: bn-vmt, bn-vmt/a | E78: =Commodities!C$63 -> TMB20X | F78: =Commodities!C$11 -> TM | G78: 1 | H78: 2025 | I78: =AZ78+5 -> 24 | J78: 0.24 | K78: =Trucks!H98 -> 0.083060709 | Y78: =Trucks!F98 -> 6469.2832 | Z78: =Y78 -> 6469.2832 | AA78: =Z78 -> 6469.2832 | AB78: =AA78 -> 6469.2832 | AC78: =AB78 -> 6469.2832 | AD78: =AC78 -> 6469.2832 | AE78: =AD78 -> 6469.2832 | AF78: =AF77 -> 136.84259 | AL78: 1 | AZ78: 19
A79: * | B79: =Technologies!C126 -> TMB20ADV | C79: =Technologies!D126 -> Medium Duty Truck, Advanced Tech B20 | D79: bn-vmt, bn-vmt/a | E79: =Commodities!C$63 -> TMB20X | F79: =Commodities!C$11 -> TM | G79: 1 | H79: =Trucks!D99 -> 2015 | I79: =AZ79+5 -> 24 | J79: 0.28 | M79: =Trucks!H99 -> 0.084287694 | N79: =M79 -> 0.084287694 | O79: =Trucks!H100 -> 0.087074064 | P79: =O79 -> 0.087074064 | Q79: =P79 -> 0.087074064 | R79: =Trucks!H101 -> 0.087074064 | S79: =R79 -> 0.087074064 | T79: =S79 -> 0.087074064 | U79: =T79 -> 0.087074064 | W79: =Trucks!F99 -> 6772.0678 | X79: =W79 -> 6772.0678 | Y79: =Trucks!F100 -> 6936.7571 | Z79: =Y79 -> 6936.7571 | AA79: =Z79 -> 6936.7571 | AB79: =Trucks!F101 -> 6936.7571 | AC79: =AB79 -> 6936.7571 | AD79: =AC79 -> 6936.7571 | AE79: =AD79 -> 6936.7571 | AF79: =AF78 -> 136.84259 | AL79: 1 | AZ79: 19
A80: * | B80: =Technologies!C127 -> TMB20AH | C80: =Technologies!D127 -> Medium Duty Truck, Advanced Hybrid B20 | D80: bn-vmt, bn-vmt/a | E80: =Commodities!C$63 -> TMB20X | F80: =Commodities!C$11 -> TM | G80: 1 | H80: =Trucks!D102 -> 2015 | I80: =AZ80+5 -> 24 | J80: 0.28 | M80: =Trucks!H102 -> 0.12041099 | N80: =M80 -> 0.12041099 | O80: =Trucks!H103 -> 0.12439152 | P80: =O80 -> 0.12439152 | Q80: =P80 -> 0.12439152 | R80: =Trucks!H104 -> 0.12439152 | S80: =R80 -> 0.12439152 | T80: =S80 -> 0.12439152 | U80: =T80 -> 0.12439152 | W80: =Trucks!F102 -> 8334.2222 | X80: =W80 -> 8334.2222 | Y80: =Trucks!F103 -> 7963.0926 | Z80: =Y80 -> 7963.0926 | AA80: =Z80 -> 7963.0926 | AB80: =Trucks!F104 -> 7963.0926 | AC80: =AB80 -> 7963.0926 | AD80: =AC80 -> 7963.0926 | AE80: =AD80 -> 7963.0926 | AF80: =Trucks!G102 -> 125.89518 | AL80: 1 | AZ80: 19
A81: =Technologies!B128 -> R2,R3,R4,R5,R6 | B81: =Technologies!C128 -> TMCNGC10 | C81: =Technologies!D128 -> Medium Duty Truck, CNG, 2010 | D81: bn-vmt, bn-vmt/a | E81: =Commodities!C$57 -> TMCNG | F81: =Commodities!C$11 -> TM | G81: 1 | H81: 2010 | I81: =AZ81+5 -> 24 | J81: 0.18 | K81: =Trucks!H105 -> 0.052445275 | V81: =Trucks!F105 -> 6575.7618 | AF81: =Trucks!G105 -> 248.8047 | AG81: 0 | AH81: 0 | AI81: 0 | AJ81: 0 | AK81: 0 | AL81: 1 | AM81: 0 | AO81: 0 | AP81: 0 | AQ81: 0 | AR81: 0 | AS81: 0 | AT81: 0 | AU81: 0 | AV81: 0 | AZ81: 19
A82: =Technologies!B129 -> R2,R3,R4,R5,R6 | B82: =Technologies!C129 -> TMCNGC | C82: =Technologies!D129 -> Medium Duty Truck, Conventional CNG | D82: bn-vmt, bn-vmt/a | E82: =Commodities!C$57 -> TMCNG | F82: =Commodities!C$11 -> TM | G82: 1 | H82: 2015 | I82: =AZ82+5 -> 24 | J82: 0.18 | M82: =Trucks!H106 -> 0.055163784 | N82: =Trucks!H107 -> 0.06092162 | O82: =N82 -> 0.06092162 | P82: =O82 -> 0.06092162 | Q82: =P82 -> 0.06092162 | R82: =Q82 -> 0.06092162 | S82: =R82 -> 0.06092162 | T82: =S82 -> 0.06092162 | U82: =T82 -> 0.06092162 | W82: =Trucks!F106 -> 6601.4772 | X82: =Trucks!F107 -> 6684.8974 | Y82: =X82 -> 6684.8974 | Z82: =Y82 -> 6684.8974 | AA82: =Z82 -> 6684.8974 | AB82: =AA82 -> 6684.8974 | AC82: =AB82 -> 6684.8974 | AD82: =AC82 -> 6684.8974 | AE82: =AD82 -> 6684.8974 | AF82: =Trucks!G106 -> 248.8047 | AG82: 0 | AH82: 0 | AI82: 0 | AJ82: 0 | AK82: 0 | AL82: 1 | AM82: 0 | AN82: 0 | AZ82: 19
A83: =Technologies!B130 -> R2,R3,R4,R5,R6 | B83: =Technologies!C130 -> TMCNGIM | C83: =Technologies!D130 -> Medium Duty Truck, Improved CNG | D83: bn-vmt, bn-vmt/a | E83: =Commodities!C$57 -> TMCNG | F83: =Commodities!C$11 -> TM | G83: 1 | H83: 2025 | I83: =AZ83+5 -> 24 | J83: 0.24 | K83: =Trucks!H108 -> 0.063820237 | Y83: =Trucks!F108 -> 7290.0402 | Z83: =Y83 -> 7290.0402 | AA83: =Z83 -> 7290.0402 | AB83: =AA83 -> 7290.0402 | AC83: =AB83 -> 7290.0402 | AD83: =AC83 -> 7290.0402 | AE83: =AD83 -> 7290.0402 | AF83: =AF82 -> 248.8047 | AG83: 0 | AH83: 0 | AI83: 0 | AJ83: 0 | AK83: 0 | AL83: 1 | AM83: 0 | AN83: 0 | AZ83: 19
A84: =Technologies!B131 -> R2,R3,R4,R5,R6 | B84: =Technologies!C131 -> TMCNGAH | C84: =Technologies!D131 -> Medium Duty Truck, Advanced Hybrid CNG | D84: bn-vmt, bn-vmt/a | E84: =Commodities!C$57 -> TMCNG | F84: =Commodities!C$11 -> TM | G84: 1 | H84: =Trucks!D109 -> 2015 | I84: =AZ84+5 -> 24 | J84: 0.28 | M84: =Trucks!H109 -> 0.066447591 | N84: =M84 -> 0.066447591 | O84: =Trucks!H110 -> 0.083923483 | P84: =O84 -> 0.083923483 | Q84: =P84 -> 0.083923483 | R84: =Trucks!H111 -> 0.09056101 | S84: =R84 -> 0.09056101 | T84: =S84 -> 0.09056101 | U84: =T84 -> 0.09056101 | W84: =Trucks!F109 -> 7843.9564 | X84: =W84 -> 7843.9564 | Y84: =Trucks!F110 -> 8162.9154 | Z84: =Y84 -> 8162.9154 | AA84: =Z84 -> 8162.9154 | AB84: =Trucks!F111 -> 8697.8237 | AC84: =AB84 -> 8697.8237 | AD84: =AC84 -> 8697.8237 | AE84: =AD84 -> 8697.8237 | AF84: =Trucks!G109 -> 237.85729 | AG84: 0 | AH84: 0 | AI84: 0 | AJ84: 0 | AK84: 0 | AL84: 1 | AM84: 0 | AN84: 0 | AZ84: 19
A85: * | B85: =Technologies!C132 -> TMLPGC10 | C85: =Technologies!D132 -> Medium Duty Truck, LPG, 2010 | D85: bn-vmt, bn-vmt/a | E85: =Commodities!C29 -> TRNLPG1 | F85: =Commodities!C$11 -> TM | G85: 1 | H85: 2010 | I85: =AZ85+5 -> 24 | J85: 0.18 | K85: =Trucks!H112 -> 0.067978151 | V85: =Trucks!F112 -> 6193.9826 | AF85: =Trucks!G112 -> 248.8047 | AL85: 1 | AN85: 0 | AO85: 0 | AP85: 0 | AQ85: 0 | AR85: 0 | AS85: 0 | AT85: 0 | AU85: 0 | AV85: 0 | AZ85: 19
A86: * | B86: =Technologies!C133 -> TMLPGC | C86: =Technologies!D133 -> Medium Duty Truck, Conventional LPG | D86: bn-vmt, bn-vmt/a | E86: =Commodities!C29 -> TRNLPG1 | F86: =Commodities!C$11 -> TM | G86: 1 | H86: 2015 | I86: =AZ86+5 -> 24 | J86: 0.18 | M86: =Trucks!H113 -> 0.071501809 | N86: =Trucks!H114 -> 0.078964961 | O86: =N86 -> 0.078964961 | P86: =O86 -> 0.078964961 | Q86: =P86 -> 0.078964961 | R86: =Q86 -> 0.078964961 | S86: =R86 -> 0.078964961 | T86: =S86 -> 0.078964961 | U86: =T86 -> 0.078964961 | W86: =Trucks!F113 -> 6218.205 | X86: =Trucks!F114 -> 6296.7819 | Y86: =X86 -> 6296.7819 | Z86: =Y86 -> 6296.7819 | AA86: =Z86 -> 6296.7819 | AB86: =AA86 -> 6296.7819 | AC86: =AB86 -> 6296.7819 | AD86: =AC86 -> 6296.7819 | AE86: =AD86 -> 6296.7819 | AF86: =Trucks!G113 -> 248.8047 | AL86: 1 | AZ86: 19
A87: * | B87: =Technologies!C134 -> TMLPGIM | C87: =Technologies!D134 -> Medium Duty Truck, Improved LPG | D87: bn-vmt, bn-vmt/a | E87: =Commodities!C29 -> TRNLPG1 | F87: =Commodities!C$11 -> TM | G87: 1 | H87: 2025 | I87: =AZ87+5 -> 24 | J87: 0.24 | K87: =Trucks!H115 -> 0.082722071 | Y87: =Trucks!F115 -> 6866.7911 | Z87: =Y87 -> 6866.7911 | AA87: =Z87 -> 6866.7911 | AB87: =AA87 -> 6866.7911 | AC87: =AB87 -> 6866.7911 | AD87: =AC87 -> 6866.7911 | AE87: =AD87 -> 6866.7911 | AF87: =AF86 -> 248.8047 | AL87: 1 | AZ87: 19
A88: * | B88: =Technologies!C135 -> TMLPGAH | C88: =Technologies!D135 -> Medium Duty Truck, Advanced Hybrid LPG | D88: bn-vmt, bn-vmt/a | E88: =Commodities!C29 -> TRNLPG1 | F88: =Commodities!C$11 -> TM | G88: 1 | H88: =Trucks!D116 -> 2015 | I88: =AZ88+5 -> 24 | J88: 0.28 | M88: =Trucks!H116 -> 0.086127577 | N88: =M88 -> 0.086127577 | O88: =Trucks!H117 -> 0.10877936 | P88: =O88 -> 0.10877936 | Q88: =P88 -> 0.10877936 | R88: =Trucks!H118 -> 0.11738274 | S88: =R88 -> 0.11738274 | T88: =S88 -> 0.11738274 | U88: =T88 -> 0.11738274 | W88: =Trucks!F116 -> 6997.7892 | X88: =W88 -> 6997.7892 | Y88: =Trucks!F117 -> 7316.7482 | Z88: =Y88 -> 7316.7482 | AA88: =Z88 -> 7316.7482 | AB88: =Trucks!F118 -> 7851.6564 | AC88: =AB88 -> 7851.6564 | AD88: =AC88 -> 7851.6564 | AE88: =AD88 -> 7851.6564 | AF88: =Trucks!G116 -> 237.85729 | AL88: 1 | AZ88: 19
A89: *Heavy Duty Trucks
A90: * | B90: =Technologies!C150 -> THSGSL102 | C90: =Technologies!D150 -> Heavy Truck, Short Haul, Gasoline, 2010 | D90: bn-vmt, bn-vmt/a | E90: =Commodities!$C$46 -> TWDSL | F90: =Commodities!$C$16 -> TSW | G90: 1 | H90: 2010 | I90: 24 | J90: 0.18 | K90: 0.038084191 | V90: 4265.2943 | W90: 4265.2943 | X90: 4265.2943 | Y90: 4265.2943 | Z90: 4265.2943 | AA90: 4265.2943 | AB90: 4265.2943 | AC90: 4265.2943 | AD90: 4265.2943 | AE90: 4265.2943 | AF90: 301.42015 | AL90: 1 | AM90: 0 | AN90: 0 | AZ90: 19
A91: * | B91: =Technologies!C151 -> THSDSLC102 | C91: =Technologies!D151 -> Heavy Truck, Short Haul, Conventional Diesel 2010 | D91: bn-vmt, bn-vmt/a | E91: =Commodities!$C$46 -> TWDSL | F91: =Commodities!$C$16 -> TSW | G91: 1 | H91: 2010 | I91: 24 | J91: 0.18 | K91: 0.040092266 | V91: 4606.0861 | AF91: 165.78108 | AL91: 1 | AM91: 0 | AN91: 0 | AS91: 0 | AT91: 0 | AU91: 0 | AV91: 0 | AZ91: 19
A92: * | B92: =Technologies!C152 -> THSDSLC2 | C92: =Technologies!D152 -> Heavy Truck, Short Haul, Conv. Diesel | D92: bn-vmt, bn-vmt/a | E92: =Commodities!$C$46 -> TWDSL | F92: =Commodities!$C$16 -> TSW | G92: 1 | H92: 2015 | I92: 24 | J92: 0.18 | M92: 0.043863448 | N92: 0.043863448 | O92: 0.043863448 | P92: 0.043863448 | Q92: 0.043863448 | R92: 0.043863448 | S92: 0.043863448 | T92: 0.043863448 | U92: 0.043863448 | W92: 4701.3381 | X92: 4701.3381 | Y92: 4701.3381 | Z92: 4701.3381 | AA92: 4701.3381 | AB92: 4701.3381 | AC92: 4701.3381 | AD92: 4701.3381 | AE92: 4701.3381 | AF92: 165.78108 | AL92: 1 | AM92: 0 | AN92: 0 | AZ92: 19
A93: * | B93: =Technologies!C153 -> THSDSLIM2 | C93: =Technologies!D153 -> Heavy Truck, Short Haul, Improved Diesel | D93: bn-vmt, bn-vmt/a | E93: =Commodities!$C$46 -> TWDSL | F93: =Commodities!$C$16 -> TSW | G93: 1 | H93: 2025 | I93: 24 | J93: 0.24 | O93: 0.045383924 | P93: 0.045383924 | Q93: 0.045383924 | R93: 0.046305425 | S93: 0.046305425 | T93: 0.046305425 | U93: 0.046305425 | Y93: 4729.3692 | Z93: 4729.3692 | AA93: 4729.3692 | AB93: 4767.6178 | AC93: 4767.6178 | AD93: 4767.6178 | AE93: 4767.6178 | AF93: 166 | AL93: 1 | AM93: 0 | AN93: 0 | AZ93: 19
A94: * | B94: =Technologies!C154 -> THSDSLADV2 | C94: =Technologies!D154 -> Heavy Truck, Short Haul, Advanced Diesel | D94: bn-vmt, bn-vmt/a | E94: =Commodities!$C$46 -> TWDSL | F94: =Commodities!$C$16 -> TSW | G94: 1 | H94: 2015 | I94: 24 | J94: 0.28 | M94: 0.045998258 | N94: 0.045998258 | O94: 0.046689384 | P94: 0.046689384 | Q94: 0.046689384 | R94: 0.046689384 | S94: 0.046689384 | T94: 0.046689384 | U94: 0.046689384 | W94: 4831.9482 | X94: 4831.9482 | Y94: 5078.3127 | Z94: 5078.3127 | AA94: 5078.3127 | AB94: 5078.3127 | AC94: 5078.3127 | AD94: 5078.3127 | AE94: 5078.3127 | AF94: 165.78108 | AL94: 1 | AM94: 0 | AN94: 0 | AZ94: 19
A95: * | B95: =Technologies!C155 -> THSDSLAH2 | C95: =Technologies!D155 -> Heavy Truck, Short Haul, Hybrid Diesel | D95: bn-vmt, bn-vmt/a | E95: =Commodities!$C$46 -> TWDSL | F95: =Commodities!$C$16 -> TSW | G95: 1 | H95: 2025 | I95: 24 | J95: 0.28 | M95: 0.061126233 | N95: 0.061126233 | O95: 0.061126233 | P95: 0.061126233 | Q95: 0.061126233 | R95: 0.062047734 | S95: 0.062047734 | T95: 0.062047734 | U95: 0.062047734 | W95: 5813.3727 | X95: 5813.3727 | Y95: 5399.9645 | Z95: 5399.9645 | AA95: 5399.9645 | AB95: 5723.2632 | AC95: 5723.2632 | AD95: 5723.2632 | AE95: 5723.2632 | AF95: 165.78108 | AL95: 1 | AM95: 0 | AN95: 0 | AZ95: 19
A96: =Technologies!B139 -> R2,R3,R4,R5,R6 | B96: =Technologies!C139 -> THSCNGE | C96: =Technologies!D139 -> Heavy Truck, Short Haul, CNG exisiting | D96: bn-vmt, bn-vmt/a | E96: =Commodities!C58 -> THCNG | F96: =Commodities!C$12 -> THS | G96: 1 | H96: 2010 | I96: =AZ96+5 -> 24 | K96: =Trucks!H164 -> #REF! | AF96: =Trucks!G164 -> 248.8047 | AL96: 1 | AM96: 0 | AN96: 0 | AO96: 0 | AP96: 0 | AQ96: 0 | AR96: 0 | AS96: 0 | AT96: 0 | AU96: 0 | AV96: 0 | AZ96: =Trucks!E164 -> 19
A97: * | B97: =Technologies!C141 -> THSLPGE | C97: =Technologies!D141 -> Heavy Truck, Short Haul, LPG exisiting | D97: bn-vmt, bn-vmt/a | E97: =Commodities!C29 -> TRNLPG1 | F97: =Commodities!C$12 -> THS | G97: 1 | H97: 2010 | I97: =AZ97+5 -> 24 | J97: 0.18 | K97: =Trucks!H165 -> #REF! | AF97: =Trucks!G165 -> 248.8047 | AL97: 1 | AM97: 0 | AN97: 0 | AO97: 0 | AP97: 0 | AQ97: 0 | AR97: 0 | AS97: 0 | AT97: 0 | AU97: 0 | AV97: 0 | AZ97: =Trucks!E165 -> 19
A98: * | B98: =Technologies!C142 -> THSB20E | C98: =Technologies!D142 -> Heavy Truck, Short Haul, B20exisiting | D98: bn-vmt, bn-vmt/a | E98: =Commodities!C62 -> THB20X | F98: =Commodities!C$12 -> THS | G98: 1 | H98: 2010 | I98: =AZ98+5 -> 24 | K98: =TechData!K24 -> #REF! | AF98: =TechData!AF24 -> 165.78108 | AL98: 1 | AM98: 0 | AN98: 0 | AO98: 0 | AP98: 0 | AQ98: 0 | AR98: 0 | AS98: 0 | AT98: 0 | AU98: 0 | AV98: 0 | AZ98: 19
A99: =Technologies!B143 -> R2,R3,R4,R5,R6 | B99: =Technologies!C143 -> THSGSL10 | C99: =Technologies!D143 -> Heavy Truck, Short Haul, Gasoline, 2010 | D99: bn-vmt, bn-vmt/a | E99: =Commodities!C47 -> THGSL | F99: =Commodities!C$12 -> THS | G99: 1 | H99: =Trucks!D166 -> 2010 | I99: =AZ99+5 -> 24 | J99: 0.18 | K99: =Trucks!H166 -> #REF! | V99: =Trucks!F166 -> 4265.2943 | W99: =V99 -> 4265.2943 | X99: =W99 -> 4265.2943 | Y99: =X99 -> 4265.2943 | Z99: =Y99 -> 4265.2943 | AA99: =Z99 -> 4265.2943 | AB99: =AA99 -> 4265.2943 | AC99: =AB99 -> 4265.2943 | AD99: =AC99 -> 4265.2943 | AE99: =AD99 -> 4265.2943 | AF99: =Trucks!G166 -> 301.42015 | AL99: 1 | AM99: 0 | AN99: 0 | AZ99: =Trucks!E166 -> 19
A100: * | B100: =Technologies!C144 -> THSGSL102 | C100: =Technologies!D144 -> Heavy Truck, Short Haul, Gasoline, 2010 | D100: bn-vmt, bn-vmt/a | E100: =Commodities!$C$48 -> TWGSL | F100: =Commodities!$C$16 -> TSW | G100: 1 | H100: =H99 -> 2010 | I100: =AZ100+5 -> 24 | J100: 0.18 | K100: =K99 -> #REF! | V100: =V99 -> 4265.2943 | W100: =W99 -> 4265.2943 | X100: =X99 -> 4265.2943 | Y100: =Y99 -> 4265.2943 | Z100: =Z99 -> 4265.2943 | AA100: =AA99 -> 4265.2943 | AB100: =AB99 -> 4265.2943 | AC100: =AC99 -> 4265.2943 | ... AF100: =AF99 -> 301.42015 | AL100: 1 | AM100: 0 | AZ100: =AZ99 -> 19
A101: =Technologies!B145 -> R2,R3,R4,R5,R6 | B101: =Technologies!C145 -> THSDSLC10 | C101: =Technologies!D145 -> Heavy Truck, Short Haul, Conventional Diesel 2010 | D101: bn-vmt, bn-vmt/a | E101: =Commodities!C44 -> THDSL | F101: =Commodities!C$12 -> THS | G101: 1 | H101: 2010 | I101: =AZ101+5 -> 24 | J101: 0.18 | K101: =Trucks!H131 -> #REF! | V101: =Trucks!F131 -> 4606.0861 | AF101: =Trucks!G131 -> 165.78108 | AL101: 1 | AM101: 0 | AO101: 0 | AP101: 0 | AQ101: 0 | AR101: 0 | AS101: 0 | AT101: 0 | AU101: 0 | AV101: 0 | AZ101: 19
A102: =Technologies!B146 -> R2,R3,R4,R5,R6 | B102: =Technologies!C146 -> THSDSLC | C102: =Technologies!D146 -> Heavy Truck, Short Haul, Conv. Diesel | D102: bn-vmt, bn-vmt/a | E102: =Commodities!C44 -> THDSL | F102: =Commodities!C$12 -> THS | G102: 1 | H102: 2015 | I102: =AZ102+5 -> 24 | J102: 0.18 | M102: =Trucks!H132 -> #REF! | N102: =M102 -> #REF! | O102: =N102 -> #REF! | P102: =O102 -> #REF! | Q102: =P102 -> #REF! | R102: =Q102 -> #REF! | S102: =R102 -> #REF! | T102: =S102 -> #REF! | U102: =T102 -> #REF! | W102: =Trucks!F132 -> 4701.3381 | X102: =W102 -> 4701.3381 | Y102: =X102 -> 4701.3381 | Z102: =Y102 -> 4701.3381 | AA102: =Z102 -> 4701.3381 | AB102: =AA102 -> 4701.3381 | AC102: =AB102 -> 4701.3381 | AD102: =AC102 -> 4701.3381 | AE102: =AD102 -> 4701.3381 | AF102: =Trucks!G132 -> 165.78108 | AL102: 1 | AM102: 0 | AN102: 0 | AZ102: =Trucks!E132 -> 19
A103: =Technologies!B147 -> R2,R3,R4,R5,R6 | B103: =Technologies!C147 -> THSDSLIM | C103: =Technologies!D147 -> Heavy Truck, Short Haul, Improved Diesel | D103: bn-vmt, bn-vmt/a | E103: =Commodities!C44 -> THDSL | F103: =Commodities!C$12 -> THS | G103: 1 | H103: 2025 | I103: =AZ103+5 -> 24 | J103: 0.24 | O103: =Trucks!H134 -> #REF! | P103: =O103 -> #REF! | Q103: =P103 -> #REF! | R103: =Trucks!H135 -> #REF! | S103: =R103 -> #REF! | T103: =S103 -> #REF! | U103: =T103 -> #REF! | Y103: =Trucks!F134 -> 4729.3692 | Z103: =Y103 -> 4729.3692 | AA103: =Z103 -> 4729.3692 | AB103: =Trucks!F135 -> 4767.6178 | AC103: =AB103 -> 4767.6178 | AD103: =AC103 -> 4767.6178 | AE103: =AD103 -> 4767.6178 | AF103: 166 | AL103: 1 | AM103: 0 | AN103: 0 | AZ103: 19
A104: =Technologies!B148 -> R2,R3,R4,R5,R6 | B104: =Technologies!C148 -> THSDSLADV | C104: =Technologies!D148 -> Heavy Truck, Short Haul, Advanced Diesel | D104: bn-vmt, bn-vmt/a | E104: =Commodities!C44 -> THDSL | F104: =Commodities!C$12 -> THS | G104: 1 | H104: =Trucks!D136 -> 2015 | I104: =AZ104+5 -> 24 | J104: 0.28 | M104: =Trucks!H136 -> #REF! | N104: =M104 -> #REF! | O104: =Trucks!H137 -> #REF! | P104: =O104 -> #REF! | Q104: =P104 -> #REF! | R104: =Q104 -> #REF! | S104: =R104 -> #REF! | T104: =S104 -> #REF! | U104: =T104 -> #REF! | W104: =Trucks!F136 -> 4831.9482 | X104: =W104 -> 4831.9482 | Y104: =Trucks!F137 -> 5078.3127 | Z104: =Y104 -> 5078.3127 | AA104: =Z104 -> 5078.3127 | AB104: =AA104 -> 5078.3127 | AC104: =AB104 -> 5078.3127 | AD104: =AC104 -> 5078.3127 | AE104: =AD104 -> 5078.3127 | AF104: =Trucks!G136 -> 165.78108 | AL104: 1 | AM104: 0 | AN104: 0 | AZ104: =Trucks!E136 -> 19
...

Sheet Commodities
B1: Commodities | C1: R1,R2,R3,R4,R5,R6
B7: Region | C7: CommName | D7: CommDesc | E7: Unit | F7: Csets | G7: LimType | H7: CTSLvl | I7: PeakTS | J7: Ctype | O7: Comment
B8: *Demands
B9: R1,R2,R3,R4,R5,R6 | C9: TA | D9: TRN.AIR | E9: bn-pass-miles | F9: DEM
B10: R2,R3,R4,R5,R6 | C10: TB | D10: TRN.BUS | E10: bn-vmt | F10: DEM
B11: R2,R3,R4,R5,R6 | C11: TM | D11: TRN.Medium Duty Trucks | E11: bn-vmt | F11: DEM
B12: R2,R3,R4,R5,R6 | C12: THS | D12: TRN.HDV Short Haul | E12: bn-vmt | F12: DEM
B13: *R1,R2,R3,R4,R5,R6 | C13: THL | D13: TRN.HDV Long Haul | E13: bn-vmt | F13: DEM
B14: R1,R2,R3,R4,R5,R6 | C14: TS | D14: TRN.SHIP | E14: bn-t-m | F14: DEM
B15: *R2,R3,R4,R5,R6 | C15: TRF | D15: TRN.RAIL.FREIGHT | E15: bn-t-m | F15: DEM
B16: *R2,R3,R4,R5,R6 | C16: TSW | D16: TRN.MSW | E16: bn-vmt | F16: DEM
B17: R2,R3,R4,R5,R6 | C17: TRP | D17: TRN.RAIL.PASS | E17: bn-pass-miles | F17: DEM
B18: *R2,R3,R4,R5,R6 | C18: TC | D18: TRN.TRUCK.COMMERCIAL | E18: bn-vmt | F18: DEM
B26: *Energy Carriers
B27: R1,R2,R3,R4,R5,R6 | C27: TRNELC | D27: ELC to TRN | E27: PJ | F27: NRG
B28: *R1,R2,R3,R4,R5,R6 | C28: TRNDSL | D28: DSL to rail emissions collector | E28: PJ | F28: NRG
B29: *R1,R2,R3,R4,R5,R6 | C29: TRNLPG1 | D29: LPG to TRN after Collection | E29: PJ | F29: NRG
B30: *R1,R2,R3,R4,R5,R6 | C30: TRNLPG | D30: LPG after collection | E30: PJ | F30: NRG
B31: R1,R2,R3,R4,R5,R6 | C31: TRNJTF1 | D31: JTF to TRN after Collection | E31: PJ | F31: NRG
B32: R1,R2,R3,R4,R5,R6 | C32: TRNJTF | D32: JTF after collection | E32: PJ | F32: NRG
B33: *R1,R2,R3,R4,R5,R6 | C33: TRNRFH | D33: High Sulfur Residual Fuel Oil to Transportation Sector | E33: PJ | F33: NRG
B34: R1,R2,R3,R4,R5,R6 | C34: TRNRFH1 | D34: RFH to TRN after collector | E34: PJ | F34: NRG
B35: R1,R2,R3,R4,R5,R6 | C35: TRNGSL | D35: GSL to TRN | E35: PJ | F35: NRG
B36: R1,R2,R3,R4,R5,R6 | C36: TRNGSLB | D36: GSLB to TRN | E36: PJ | F36: NRG
B37: R1,R2,R3,R4,R5,R6 | C37: TBGSL | D37: GSL to TB | E37: PJ | F37: NRG
B38: R1,R2,R3,R4,R5,R6 | C38: TCGSL | D38: GSL to TC | E38: PJ | F38: NRG
... B65: *R1,R2,R3,R4,R5,R6 | C65: TSB20X | D65: B20X to TS | E65: PJ | F65: NRG
B66: *Emissions Commodities
B67: * | C67: CARBON | D67: Carbon Emissions | E67: Mt | F67: ENV
B68: R2,R3,R4,R5,R6 | C68: SULFUR | D68: Sulfur Emissions | E68: kt | F68: ENV
B69: R2,R3,R4,R5,R6 | C69: SO2T | D69: Sulfur Emissions -Transportation | E69: kt | F69: ENV
B70: R2,R3,R4,R5,R6 | C70: NOXT | D70: NOX Emissions -Transportation | E70: kt | F70: ENV
B71: R2,R3,R4,R5,R6 | C71: PM10T | D71: PM10 Emissions -Transportation | E71: kt | F71: ENV
B72: R2,R3,R4,R5,R6 | C72: VOCT | D72: VOC Emissions - Transportation | E72: kt | F72: ENV
B73: R2,R3,R4,R5,R6 | C73: PM25T | D73: PM25 Emissions - Trasportation | E73: kt | F73: ENV
B74: R2,R3,R4,R5,R6 | C74: CO2 | D74: Carbon dioxide emissions | E74: Mt | F74: ENV
B75: R2,R3,R4,R5,R6 | C75: SO2 | D75: Sulfur emissions | E75: kt | F75: ENV
B76: R2,R3,R4,R5,R6 | C76: NOX | D76: NOX Emissions | E76: kt | F76: ENV
B77: R2,R3,R4,R5,R6 | C77: PM10 | D77: PM10 Emissions | E77: kt | F77: ENV
B78: R2,R3,R4,R5,R6 | C78: VOC | D78: VOC Emissions | E78: kt | F78: ENV
... B85: R2,R3,R4,R5,R6 | C85: NH3 | D85: Ammonia | E85: kt | F85: ENV

Sheet ANSv6.0-Technologies
A1: ANSWER-Technologies
B7: TechName | C7: TechDesc | D7: TACTUnit | E7: TCAPUnit | F7: Set Memberships | G7: Comment

Sheet ANSv6.0-Constraints
A1: ANSWER-Constraints
B7: ConstrName | C7: ConstrDesc | D7: Units | E7: Set Memberships | F7: Comment

Sheet ANSv6.0-CommData
A1: ANSWER-CommData
B7: CommName | C7: CommDesc | D7: Units

Sheet ANSv6.0-TechData
A1: ANSWER-TechData
B7: TechName | C7: TechDesc | D7: Units | E7: CommIN | F7: CommOUT

Sheet ANSv6.0-ConstrData
A1: ANSWER-ConstrData
B7: ConstrName | C7: ConstrDesc | D7: Units | E7: TechName

Sheet Technologies
B1: Technologies | C1: R1,R2,R3,R4,R5,R6
B7: Region | C7: TechName | D7: TechDesc | E7: Tact | F7: Tcap | G7: Sets | H7: PrimaryCG | I7: Vintage
B8: * Existing Technologies
B9: =TechData!A8 -> R2,R3,R4,R5,R6 | C9: =TechData!B8 -> TAJE | D9: =TechData!C8 -> Air Jet, Passenger Existing | E9: bn-pass-miles | F9: bn-pmt/a | G9: DMD
B10: =TechData!A9 -> * | C10: =TechData!B9 -> TAPE | D10: =TechData!C9 -> Airplane, General Aviation, exisiting | E10: bn-pass-miles | F10: bn-pmt/a | G10: DMD
B11: =TechData!A11 -> R2,R3,R4,R5,R6 | C11: =TechData!B11 -> TBDSLE | D11: =TechData!C11 -> Bus, Exisiting Diesel | E11: bn-vmt | F11: bn-vmt/a | G11: DMD
B12: =TechData!A12 -> * | C12: =TechData!B12 -> TBGSLE | D12: =TechData!C12 -> Bus, Exisiting Gasoline | E12: bn-vmt | F12: bn-vmt/a | G12: DMD
B13: =TechData!A13 -> R2,R3,R4,R5,R6 | C13: =TechData!B13 -> TBCNGE | D13: =TechData!C13 -> Bus, Exisiting CNG | E13: bn-vmt | F13: bn-vmt/a | G13: DMD
B14: =TechData!A15 -> * | C14: =TechData!B15 -> TCGSLE | D14: =TechData!C15 -> Truck, Commerical, Exisiting Gasoline | E14: bn-vmt | F14: bn-vmt/a | G14: DMD
B15: =TechData!A16 -> * | C15: =TechData!B16 -> TCDSLE | D15: =TechData!C16 -> Truck, Commerical, Existing Diesel | E15: bn-vmt | F15: bn-vmt/a | G15: DMD
B16: =TechData!A18 -> R2,R3,R4,R5,R6 | C16: =TechData!B18 -> TMGSLE | D16: =TechData!C18 -> Medium Duty Truck, Existing Gasoline | E16: bn-vmt | F16: bn-vmt/a | G16: DMD
B17: =TechData!A19 -> R2,R3,R4,R5,R6 | C17: =TechData!B19 -> TMDSLE | D17: =TechData!C19 -> Medium Duty Truck, Existing Diesel | E17: bn-vmt | F17: bn-vmt/a | G17: DMD
B18: =TechData!A20 -> R2,R3,R4,R5,R6 | C18: =TechData!B20 -> TMCNGE | D18: =TechData!C20 -> Medium Duty Truck, Existing CNG | E18: bn-vmt | F18: bn-vmt/a | G18: DMD
B19: =TechData!A21 -> * | C19: =TechData!B21 -> TMLPGE | D19: =TechData!C21 -> Medium Duty Truck, Existing LPG | E19: bn-vmt | F19: bn-vmt/a | G19: DMD
B20: =TechData!A23 -> R2,R3,R4,R5,R6 | C20: =TechData!B23 -> THSGSLE | D20: =TechData!C23 -> Heavy Truck, Short Haul, Gasoline exisiting | E20: bn-vmt | F20: bn-vmt/a | G20: DMD
B21: =TechData!A24 -> R2,R3,R4,R5,R6 | C21: =TechData!B24 -> THSDSLE | D21: =TechData!C24 -> Heavy Truck, Short Haul, Diesel exisiting | E21: bn-vmt | F21: bn-vmt/a | G21: DMD
B22: =TechData!A25 -> * | C22: =TechData!B25 -> THSDSLE2 | D22: =TechData!C25 -> Heavy Truck, Short Haul, Diesel exisiting MSW | E22: bn-vmt | F22: bn-vmt/a | G22: DMD
B23: =TechData!A26 -> * | C23: =TechData!B26 -> THSCNGE2 | D23: =TechData!C26 -> Heavy Truck, Short Haul, CNG exisiting MSW | E23: bn-vmt | F23: bn-vmt/a | G23: DMD
B24: =TechData!A28 -> R2,R3,R4,R5,R6 | C24: =TechData!B28 -> TPDSLCR | D24: =TechData!C28 -> Commuter Rail, Diesel | E24: bn-pass-miles | F24: bn-pmt/a | G24: DMD
B25: =TechData!A29 -> R2,R3,R4,R5,R6 | C25: =TechData!B29 -> TPELCSUB | D25: =TechData!C29 -> Subways and Streetcars, Electricity | E25: bn-pass-miles | F25: bn-pmt/a | G25: DMD
B26: =TechData!A31 -> * | C26: =TechData!B31 -> TRFDSLE | D26: =TechData!C31 -> Rail Freight, Diesel Existing | E26: bn-t-m | F26: bn-ton-m/a | G26: DMD
B27: =TechData!A32 -> * | C27: =TechData!B32 -> TRFDSLE2 | D27: =TechData!C32 -> Rail Freight, Diesel Existing-MSW | E27: bn-vmt | F27: bn-vmt/a | G27: DMD
B28: =TechData!A33 -> R2,R3,R4,R5,R6 | C28: =TechData!B33 -> TSDSLE | D28: =TechData!C33 -> Water Shipping, Diesel exisiting | E28: bn-t-m | F28: bn-ton-m/a | G28: DMD
B33: =#REF! -> #REF! | C33: =#REF! -> #REF! | E33: PJ | F33: Pja | G33: PRE
B34: =#REF! -> #REF! | C34: =#REF! -> #REF! | E34: PJ | F34: Pja | G34: PRE
B35: =#REF! -> #REF! | C35: =#REF! -> #REF! | E35: PJ | F35: Pja | G35: PRE
B36: =#REF! -> #REF! | C36: =#REF! -> #REF! | E36: PJ | F36: Pja | G36: PRE
B37: =#REF! -> #REF! | C37: =#REF! -> #REF! | E37: PJ | F37: Pja | G37: PRE
B38: =#REF! -> #REF! | C38: =#REF! -> #REF! | E38: PJ | F38: Pja | G38: PRE
B39: =#REF! -> #REF! | C39: =#REF! -> #REF! | E39: PJ | F39: Pja | G39: PRE
B40: =#REF! -> #REF! | C40: =#REF! -> #REF! | E40: PJ | F40: Pja | G40: PRE
B41: =#REF! -> #REF! | C41: =#REF! -> #REF! | E41: PJ | F41: Pja | G41: PRE
B42: =#REF! -> #REF! | C42: =#REF! -> #REF! | E42: PJ | F42: Pja | G42: PRE
B47: R2,R3,R4,R5,R6 | C47: TAJE | D47: ='Air&Marine'!B6 -> Air Jet, Passenger Existing | E47: bn-pass-miles | F47: bn-pmt/a | G47: DMD
B48: *R2,R3,R4,R5,R6 | C48: TAPE | D48: Airplane, General Aviation, exisiting | E48: bn-pass-miles | F48: bn-pmt/a | G48: DMD
B49: R2,R3,R4,R5,R6 | C49: TAJ10 | D49: ='Air&Marine'!B7 -> Air Jet, Passenger 2010 | E49: bn-pass-miles | F49: bn-pmt/a | G49: DMD
B50: R2,R3,R4,R5,R6 | C50: TAJSYN10 | D50: ='Air&Marine'!B8 -> Air Jet, Passenger, Syn fuel, 2010 | E50: bn-pass-miles | F50: bn-pmt/a | G50: DMD
B51: R2,R3,R4,R5,R6 | C51: TAJWT10 | D51: ='Air&Marine'!B9 -> Air Jet, Passenger (Wing tips),2010 | E51: bn-pass-miles | F51: bn-pmt/a | G51: DMD
B52: R2,R3,R4,R5,R6 | C52: TAJAPU15 | D52: ='Air&Marine'!B11 -> Air Jet Passeneger (APU) 2015 | E52: bn-pass-miles | F52: bn-pmt/a | G52: DMD
B53: R2,R3,R4,R5,R6 | C53: TAJBW30 | D53: ='Air&Marine'!B12 -> Air Jet, Passenger(blended wing), 2030 | E53: bn-pass-miles | F53: bn-pmt/a | G53: DMD
B54: R2,R3,R4,R5,R6 | C54: TAJAE30 | D54: ='Air&Marine'!B13 -> Air Jet, Passenger (improved aero), 2030 | E54: bn-pass-miles | F54: bn-pmt/a | G54: DMD
B55: R2,R3,R4,R5,R6 | C55: TAJGE15 | D55: ='Air&Marine'!B15 -> Air Jet Passenger, (geared engine), 2015 | E55: bn-pass-miles | F55: bn-pmt/a | G55: DMD
B56: *R2,R3,R4,R5,R6 | C56: TAP10 | D56: Airplane, General Aviation - 2010 | E56: bn-pass-miles | F56: bn-pmt/a | G56: DMD
B57: R2,R3,R4,R5,R6 | C57: TBDSLE | D57: =TechData!C11 -> Bus, Exisiting Diesel | E57: bn-vmt | F57: bn-vmt/a | G57: DMD
B58: *R2,R3,R4,R5,R6 | C58: TBGSLE | D58: =TechData!C12 -> Bus, Exisiting Gasoline | E58: bn-vmt | F58: bn-vmt/a | G58: DMD
B59: R2,R3,R4,R5,R6 | C59: TBCNGE | D59: =TechData!C13 -> Bus, Exisiting CNG | E59: bn-vmt | F59: bn-vmt/a | G59: DMD
B60: R2,R3,R4,R5,R6 | C60: TBDSLC10 | D60: Bus, Conventional Diesel, 2010 | E60: bn-vmt | F60: bn-vmt/a | G60: DMD
B61: R2,R3,R4,R5,R6 | C61: TBDSLC | D61: =NewTech!C18 -> Bus, Conventional Diesel | E61: bn-vmt | F61: bn-vmt/a | G61: DMD
B62: R2,R3,R4,R5,R6 | C62: TBDSLIM | D62: Bus, Improved Diesel | E62: bn-vmt | F62: bn-vmt/a | G62: DMD
B63: R2,R3,R4,R5,R6 | C63: TBDSLADV | D63: =NewTech!C20 -> Bus, Advanced Tech Diesel | E63: bn-vmt | F63: bn-vmt/a | G63: DMD
B64: R2,R3,R4,R5,R6 | C64: TBDSLAH | D64: =NewTech!C21 -> Bus, Advanced Hybrid Diesel | E64: bn-vmt | F64: bn-vmt/a | G64: DMD
B65: *R2,R3,R4,R5,R6 | C65: TBB20C10 | D65: Bus, Conventional Biodiesel, 2010 | E65: bn-vmt | F65: bn-vmt/a | G65: DMD
B66: *R2,R3,R4,R5,R6 | C66: TBB20C | D66: =NewTech!C23 -> Bus, Conventional B20 | E66: bn-vmt | F66: bn-vmt/a | G66: DMD
B67: *R2,R3,R4,R5,R6 | C67: TBB20IM | D67: Bus, B20, Improved Biodiesel | E67: bn-vmt | F67: bn-vmt/a | G67: DMD
B68: *R2,R3,R4,R5,R6 | C68: TBB20ADV | D68: =NewTech!C25 -> Bus, Advanced Tech B20 | E68: bn-vmt | F68: bn-vmt/a | G68: DMD
B69: *R2,R3,R4,R5,R6 | C69: TBB20AH | D69: =NewTech!C26 -> Bus, Advanced Hybrid B20 | E69: bn-vmt | F69: bn-vmt/a | G69: DMD
B70: R2,R3,R4,R5,R6 | C70: TBCNGC10 | D70: Bus, Conventional CNG, 2010 | E70: bn-vmt | F70: bn-vmt/a | G70: DMD
B71: R2,R3,R4,R5,R6 | C71: TBCNGC | D71: =NewTech!C28 -> Bus, Conventional CNG | E71: bn-vmt | F71: bn-vmt/a | G71: DMD
B72: R2,R3,R4,R5,R6 | C72: TBCNGIM | D72: Bus, Improved CNG | E72: bn-vmt | F72: bn-vmt/a | G72: DMD
B73: R2,R3,R4,R5,R6 | C73: TBCNGADV | D73: =NewTech!C30 -> Bus, Advanced Tech CNG | E73: bn-vmt | F73: bn-vmt/a | G73: DMD
B74: R2,R3,R4,R5,R6 | C74: TBCNGAH | D74: =NewTech!C31 -> Bus, Advanced Hybird CNG | E74: bn-vmt | F74: bn-vmt/a | G74: DMD
B75: R2,R3,R4,R5,R6 | C75: TBH2FC | D75: =NewTech!C32 -> Bus, Hydrogen Fuel Cell | E75: bn-vmt | F75: bn-vmt/a | G75: DMD
B76: R2,R3,R4,R5,R6 | C76: TBH2HYB | D76: =NewTech!C33 -> Bus, Hydrogen Fuel Cell Hybrid | E76: bn-vmt | F76: bn-vmt/a | G76: DMD
B77: R2,R3,R4,R5,R6 | C77: TBELC | D77: Bus, Conventional ELC | E77: bn-vmt | F77: bn-vmt/a | G77: DMD
B78: R2,R3,R4,R5,R6 | C78: TBELCIM | D78: Bus, Improved ELC | E78: bn-vmt | F78: bn-vmt/a | G78: DMD
B79: *R2,R3,R4,R5,R6 | C79: TCGSLE | D79: Truck, Commerical, Exisiting Gasoline | E79: bn-vmt | F79: bn-vmt/a | G79: DMD
B80: *R2,R3,R4,R5,R6 | C80: TCDSLE | D80: Truck, Commerical, Existing Diesel | E80: bn-vmt | F80: bn-vmt/a | G80: DMD
B81: *R2,R3,R4,R5,R6 | C81: TCGSLC10 | D81: =Trucks!A7 -> Commercial Truck, Gasoline 2010 | E81: bn-vmt | F81: bn-vmt/a | G81: DMD
B82: *R2,R3,R4,R5,R6 | C82: TCGSLC | D82: =Trucks!A8 -> Commercial Truck, Conventional Gasoline | E82: bn-vmt | F82: bn-vmt/a | G82: DMD
B83: *R2,R3,R4,R5,R6 | C83: TCGSLIM | D83: =Trucks!A10 -> Commercial Truck, Improved Gasoline | E83: bn-vmt | F83: bn-vmt/a | G83: DMD
B84: *R2,R3,R4,R5,R6 | C84: TCGSLADV | D84: =Trucks!A12 -> Commercial Truck, Advanced Tech Gasoline | E84: bn-vmt | F84: bn-vmt/a | G84: DMD
B85: *R2,R3,R4,R5,R6 | C85: TCGSLAH | D85: =Trucks!A14 -> Commercial Truck, Advanced Hybrid Tech Gasoline | E85: bn-vmt | F85: bn-vmt/a | G85: DMD
B86: *R2,R3,R4,R5,R6 | C86: TCDSLC10 | D86: =Trucks!A17 -> Commercial Truck, Diesel 2010 | E86: bn-vmt | F86: bn-vmt/a | G86: DMD
B87: *R2,R3,R4,R5,R6 | C87: TCDSLC | D87: =Trucks!A18 -> Commercial Truck, Conventional Diesel | E87: bn-vmt | F87: bn-vmt/a | G87: DMD
B88: *R2,R3,R4,R5,R6 | C88: TCDSLIM | D88: =Trucks!A20 -> Commercial Truck, Improved Diesel | E88: bn-vmt | F88: bn-vmt/a | G88: DMD
B89: *R2,R3,R4,R5,R6 | C89: TCDSLAH | D89: =Trucks!A21 -> Commercial Truck, Advanced Hybrid Diesel | E89: bn-vmt | F89: bn-vmt/a | G89: DMD
B90: *R2,R3,R4,R5,R6 | C90: TCB20C10 | D90: =Trucks!A24 -> Commercial Truck, B20 2010 | E90: bn-vmt | F90: bn-vmt/a | G90: DMD
B91: *R2,R3,R4,R5,R6 | C91: TCB20C | D91: =Trucks!A25 -> Commercial Truck, Conventional B20 | E91: bn-vmt | F91: bn-vmt/a | G91: DMD
B92: *R2,R3,R4,R5,R6 | C92: TCB20IM | D92: =Trucks!A27 -> Commercial Truck, Improved B20 | E92: bn-vmt | F92: bn-vmt/a | G92: DMD
B93: *R2,R3,R4,R5,R6 | C93: TCB20AH | D93: =Trucks!A28 -> Commerical Truck, Advanced Hybrid B20 | E93: bn-vmt | F93: bn-vmt/a | G93: DMD
B94: *R2,R3,R4,R5,R6 | C94: TCCNGC10 | D94: =Trucks!A31 -> Commercial Truck, CNG 2010 | E94: bn-vmt | F94: bn-vmt/a | G94: DMD
B95: *R2,R3,R4,R5,R6 | C95: TCCNGC | D95: =Trucks!A32 -> Commercial Truck, Conventional CNG | E95: bn-vmt | F95: bn-vmt/a | G95: DMD
B96: *R2,R3,R4,R5,R6 | C96: TCCNGIM | D96: =Trucks!A34 -> Commercial Truck, Improved CNG | E96: bn-vmt | F96: bn-vmt/a | G96: DMD
B97: *R2,R3,R4,R5,R6 | C97: TCCNGADV | D97: =Trucks!A36 -> Commerical Truck, Advanced CNG | E97: bn-vmt | F97: bn-vmt/a | G97: DMD
B98: *R2,R3,R4,R5,R6 | C98: TCCNGAH | D98: =Trucks!A39 -> Commerical Truck, Advanced Hybrid CNG | E98: bn-vmt | F98: bn-vmt/a | G98: DMD
B99: *R2,R3,R4,R5,R6 | C99: TCE85C10 | D99: =Trucks!A42 -> Commercial Truck, E85 2010 | E99: bn-vmt | F99: bn-vmt/a | G99: DMD
B100: *R2,R3,R4,R5,R6 | C100: TCE85C | D100: =Trucks!A43 -> Commercial Truck, Conventional E85 | E100: bn-vmt | F100: bn-vmt/a | G100: DMD
B101: *R2,R3,R4,R5,R6 | C101: TCE85IM | D101: =Trucks!A45 -> Commercial Truck, Improved E85 | E101: bn-vmt | F101: bn-vmt/a | G101: DMD
B102: *R2,R3,R4,R5,R6 | C102: TCE85ADV | D102: =Trucks!A47 -> Commercial Truck, Advanced E85 | E102: bn-vmt | F102: bn-vmt/a | G102: DMD
B103: *R2,R3,R4,R5,R6 | C103: TCE85AH | D103: =Trucks!A50 -> Commerical Truck, Hybrid E85 | E103: bn-vmt | F103: bn-vmt/a | G103: DMD
B104: *R2,R3,R4,R5,R6 | C104: TCLPGC10 | D104: =Trucks!A53 -> Commercial Truck, LPG 2010 | E104: bn-vmt | F104: bn-vmt/a | G104: DMD
B105: *R2,R3,R4,R5,R6 | C105: TCLPGC | D105: =Trucks!A54 -> Commercial Truck, Conventional LPG | E105: bn-vmt | F105: bn-vmt/a | G105: DMD
B106: *R2,R3,R4,R5,R6 | C106: TCLPGIM | D106: =Trucks!A56 -> Commercial Truck, Improved LPG | E106: bn-vmt | F106: bn-vmt/a | G106: DMD
B107: *R2,R3,R4,R5,R6 | C107: TCLPGADV | D107: =Trucks!A58 -> Commercial Truck, Advanced LPG | E107: bn-vmt | F107: bn-vmt/a | G107: DMD
B108: *R2,R3,R4,R5,R6 | C108: TCLPGAH | D108: =Trucks!A61 -> Commercial Truck, Hybrid LPG | E108: bn-vmt | F108: bn-vmt/a | G108: DMD
B109: *R2,R3,R4,R5,R6 | C109: TCH2FC | D109: =Trucks!A64 -> Commercial Truck, Hydrogen Fuel Cell | E109: bn-vmt | F109: bn-vmt/a | G109: DMD
B110: R2,R3,R4,R5,R6 | C110: TMGSLE | D110: =Trucks!A119 -> Medium Duty Truck, Existing Gasoline | E110: bn-vmt | F110: bn-vmt/a | G110: DMD
B111: R2,R3,R4,R5,R6 | C111: TMDSLE | D111: =Trucks!A120 -> Medium Duty Truck, Existing Diesel | E111: bn-vmt | F111: bn-vmt/a | G111: DMD
B112: R2,R3,R4,R5,R6 | C112: TMCNGE | D112: =Trucks!A122 -> Medium Duty Truck, Existing CNG | E112: bn-vmt | F112: bn-vmt/a | G112: DMD
B113: *R2,R3,R4,R5,R6 | C113: TMLPGE | D113: =Trucks!A121 -> Medium Duty Truck, Existing LPG | E113: bn-vmt | F113: bn-vmt/a | G113: DMD
...

Sheet CommData
A1: CommData | B1: R1,R2,R3,R4,R5,R6
A4: Region | B4: CommName | C4: *CommDesc | D4: *Units | E4: *COM_PROJ~2005 | F4: COM_PROJ~2010 | G4: COM_PROJ~2015 | H4: COM_PROJ~2020 | I4: COM_PROJ~2025 | J4: COM_PROJ~2030 | K4: COM_PROJ~2035 | L4: COM_PROJ~2040 | M4: COM_PROJ~2045 | N4: COM_PROJ~2050 | O4: COM_PROJ~2055
A5: *Energy Demands by End Use
A6: * | B6: =B16 -> TA | C6: =C16 -> TRN.AIR | D6: =D16 -> bn-pass-miles | E6: =E16+E26+E37+E48+E59+E70 -> #REF! | F6: =F16+F26+F37+F48+F59+F70 -> #REF! | G6: =G16+G26+G37+G48+G59+G70 -> #REF! | H6: =H16+H26+H37+H48+H59+H70 -> #REF! | I6: =I16+I26+I37+I48+I59+I70 -> #REF! | J6: =J16+J26+J37+J48+J59+J70 -> #REF! | K6: =K16+K26+K37+K48+K59+K70 -> #REF! | L6: =L16+L26+L37+L48+L59+L70 -> #REF! | ... O6: =O16+O26+O37+O48+O59+O70 -> #REF!
A7: * | B7: =B17 -> TB | C7: =C17 -> TRN.BUS | D7: =D17 -> bn-vmt | E7: =E17+E27+E38+E49+E60+E71 -> #REF! | F7: =F17+F27+F38+F49+F60+F71 -> #REF! | G7: =G17+G27+G38+G49+G60+G71 -> #REF! | H7: =H17+H27+H38+H49+H60+H71 -> #REF! | I7: =I17+I27+I38+I49+I60+I71 -> #REF! | J7: =J17+J27+J38+J49+J60+J71 -> #REF! | K7: =K17+K27+K38+K49+K60+K71 -> #REF! | L7: =L17+L27+L38+L49+L60+L71 -> #REF! | ... O7: =O17+O27+O38+O49+O60+O71 -> #REF!
A8: * | B8: TM | C8: TRN.MDV | D8: bn-vmt | E8: =E18+E28+E39+E50+E61+E72 -> #REF! | F8: =F18+F28+F39+F50+F61+F72 -> #REF! | G8: =G18+G28+G39+G50+G61+G72 -> #REF! | H8: =H18+H28+H39+H50+H61+H72 -> #REF! | I8: =I18+I28+I39+I50+I61+I72 -> #REF! | J8: =J18+J28+J39+J50+J61+J72 -> #REF! | K8: =K18+K28+K39+K50+K61+K72 -> #REF! | L8: =L18+L28+L39+L50+L61+L72 -> #REF! | ... O8: =O18+O28+O39+O50+O61+O72 -> #REF!
A9: * | B9: =B19 -> THS | C9: =C19 -> TRN.HDV Short Haul | D9: =D19 -> bn-vmt | E9: =E19+E29+E40+E51+E62+E73 -> #REF! | F9: =F19+F29+F40+F51+F62+F73 -> #REF! | G9: =G19+G29+G40+G51+G62+G73 -> #REF! | H9: =H19+H29+H40+H51+H62+H73 -> #REF! | I9: =I19+I29+I40+I51+I62+I73 -> #REF! | J9: =J19+J29+J40+J51+J62+J73 -> #REF! | K9: =K19+K29+K40+K51+K62+K73 -> #REF! | L9: =L19+L29+L40+L51+L62+L73 -> #REF! | ... O9: =O19+O29+O40+O51+O62+O73 -> #REF!
A10: * | B10: =B20 -> THL | C10: =C20 -> TRN.HDV Long Haul | D10: =D9 -> bn-vmt | E10: =E20+E30+E41+E52+E63+E74 -> #REF! | F10: =F20+F30+F41+F52+F63+F74 -> #REF! | G10: =G20+G30+G41+G52+G63+G74 -> #REF! | H10: =H20+H30+H41+H52+H63+H74 -> #REF! | I10: =I20+I30+I41+I52+I63+I74 -> #REF! | J10: =J20+J30+J41+J52+J63+J74 -> #REF! | K10: =K20+K30+K41+K52+K63+K74 -> #REF! | L10: =L20+L30+L41+L52+L63+L74 -> #REF! | ... O10: =O20+O30+O41+O52+O63+O74 -> #REF!
A11: * | B11: =B21 -> TRF | C11: =C21 -> TRN.RAIL.FREIGHT | D11: =D21 -> bn-t-m | E11: =E21+E31+E42+E53+E64+E75 -> #REF! | F11: =F21+F31+F42+F53+F64+F75 -> #REF! | G11: =G21+G31+G42+G53+G64+G75 -> #REF! | H11: =H21+H31+H42+H53+H64+H75 -> #REF! | I11: =I21+I31+I42+I53+I64+I75 -> #REF! | J11: =J21+J31+J42+J53+J64+J75 -> #REF! | K11: =K21+K31+K42+K53+K64+K75 -> #REF! | L11: =L21+L31+L42+L53+L64+L75 -> #REF! | ... O11: =O21+O31+O42+O53+O64+O75 -> #REF!
A12: * | B12: =B22 -> TRP | C12: =C22 -> TRN.RAIL.PASS | D12: =D22 -> bn-pass-miles | E12: =E22+E32+E43+E54+E65+E76 -> #REF! | F12: =F22+F32+F43+F54+F65+F76 -> #REF! | G12: =G22+G32+G43+G54+G65+G76 -> #REF! | H12: =H22+H32+H43+H54+H65+H76 -> #REF! | I12: =I22+I32+I43+I54+I65+I76 -> #REF! | J12: =J22+J32+J43+J54+J65+J76 -> #REF! | K12: =K22+K32+K43+K54+K65+K76 -> #REF! | L12: =L22+L32+L43+L54+L65+L76 -> #REF! | ... O12: =O22+O32+O43+O54+O65+O76 -> #REF!
A13: * | B13: =B23 -> TS | C13: =C23 -> TRN.SHIP | D13: =D23 -> bn-t-m | E13: =E23+E33+E44+E55+E66+E77 -> #REF! | F13: =F23+F33+F44+F55+F66+F77 -> #REF! | G13: =G23+G33+G44+G55+G66+G77 -> #REF! | H13: =H23+H33+H44+H55+H66+H77 -> #REF! | I13: =I23+I33+I44+I55+I66+I77 -> #REF! | J13: =J23+J33+J44+J55+J66+J77 -> #REF! | K13: =K23+K33+K44+K55+K66+K77 -> #REF! | L13: =L23+L33+L44+L55+L66+L77 -> #REF! | ... O13: =O23+O33+O44+O55+O66+O77 -> #REF!
A14: * | B14: =B24 -> TC | C14: =C24 -> TRN.TRUCK.COMMERCIAL | D14: =D24 -> bn-vmt | E14: =E24+E34+E45+E56+E67+E78 -> #REF! | F14: =F24+F34+F45+F56+F67+F78 -> #REF! | G14: =G24+G34+G45+G56+G67+G78 -> #REF! | H14: =H24+H34+H45+H56+H67+H78 -> #REF! | I14: =I24+I34+I45+I56+I67+I78 -> #REF! | J14: =J24+J34+J45+J56+J67+J78 -> #REF! | K14: =K24+K34+K45+K56+K67+K78 -> #REF! | L14: =L24+L34+L45+L56+L67+L78 -> #REF! | ... O14: =O24+O34+O45+O56+O67+O78 -> #REF!
A15: *
A16: *R1 | B16: TA | C16: TRN.AIR | D16: bn-pass-miles | E16: =#REF! -> #REF! | F16: =#REF! -> #REF! | G16: =#REF! -> #REF! | H16: =#REF! -> #REF! | I16: =#REF! -> #REF! | J16: =#REF! -> #REF! | K16: =#REF! -> #REF! | L16: =#REF! -> #REF! | ... O16: =#REF! -> #REF!
A17: *R1 | B17: TB | C17: TRN.BUS | D17: bn-vmt | E17: =#REF! -> #REF! | F17: =#REF! -> #REF! | G17: =#REF! -> #REF! | H17: =#REF! -> #REF! | I17: =#REF! -> #REF! | J17: =#REF! -> #REF! | K17: =#REF! -> #REF! | L17: =#REF! -> #REF! | ... O17: =#REF! -> #REF!
A18: *R1 | B18: TM | C18: TRN.MDV | D18: bn-vmt | E18: =#REF! -> #REF! | F18: =#REF! -> #REF! | G18: =#REF! -> #REF! | H18: =#REF! -> #REF! | I18: =#REF! -> #REF! | J18: =#REF! -> #REF! | K18: =#REF! -> #REF! | L18: =#REF! -> #REF! | ... O18: =#REF! -> #REF!
A19: *R1 | B19: =Commodities!$C$12 -> THS | C19: =Commodities!$D$12 -> TRN.HDV Short Haul | D19: bn-vmt | E19: =#REF! -> #REF! | F19: =#REF! -> #REF! | G19: =#REF! -> #REF! | H19: =#REF! -> #REF! | I19: =#REF! -> #REF! | J19: =#REF! -> #REF! | K19: =#REF! -> #REF! | L19: =#REF! -> #REF! | ... O19: =#REF! -> #REF!
A20: *R1 | B20: =Commodities!$C$13 -> THL | C20: =Commodities!$D$13 -> TRN.HDV Long Haul | D20: bn-vmt | E20: =#REF! -> #REF! | F20: =#REF! -> #REF! | G20: =#REF! -> #REF! | H20: =#REF! -> #REF! | I20: =#REF! -> #REF! | J20: =#REF! -> #REF! | K20: =#REF! -> #REF! | L20: =#REF! -> #REF! | ... O20: =#REF! -> #REF!
A21: *R1 | B21: TRF | C21: TRN.RAIL.FREIGHT | D21: bn-t-m | E21: =#REF! -> #REF! | F21: =#REF! -> #REF! | G21: =#REF! -> #REF! | H21: =#REF! -> #REF! | I21: =#REF! -> #REF! | J21: =#REF! -> #REF! | K21: =#REF! -> #REF! | L21: =#REF! -> #REF! | ... O21: =#REF! -> #REF!
A22: *R1 | B22: TRP | C22: TRN.RAIL.PASS | D22: bn-pass-miles | E22: =#REF! -> #REF! | F22: =#REF! -> #REF! | G22: =#REF! -> #REF! | H22: =#REF! -> #REF! | I22: =#REF! -> #REF! | J22: =#REF! -> #REF! | K22: =#REF! -> #REF! | L22: =#REF! -> #REF! | ... O22: =#REF! -> #REF!
A23: *R1 | B23: TS | C23: TRN.SHIP | D23: bn-t-m | E23: =#REF! -> #REF! | F23: =#REF! -> #REF! | G23: =#REF! -> #REF! | H23: =#REF! -> #REF! | I23: =#REF! -> #REF! | J23: =#REF! -> #REF! | K23: =#REF! -> #REF! | L23: =#REF! -> #REF! | ... O23: =#REF! -> #REF!
A24: *R1 | B24: TC | C24: =Commodities!D18 -> TRN.TRUCK.COMMERCIAL | D24: bn-vmt | E24: =#REF! -> #REF! | F24: =#REF! -> #REF! | G24: =#REF! -> #REF! | H24: =#REF! -> #REF! | I24: =#REF! -> #REF! | J24: =#REF! -> #REF! | K24: =#REF! -> #REF! | L24: =#REF! -> #REF! | ... O24: =#REF! -> #REF!
A25: *R2
A26: *R2 | B26: =Commodities!C$9 -> TA | C26: =Commodities!D$9 -> TRN.AIR | D26: bn-pass-miles | E26: =#REF! -> #REF! | F26: =#REF! -> #REF! | G26: =#REF! -> #REF! | H26: =#REF! -> #REF! | I26: =#REF! -> #REF! | J26: =#REF! -> #REF! | K26: =#REF! -> #REF! | L26: =#REF! -> #REF! | ... O26: =#REF! -> #REF!
A27: =IF(LEFT(Commodities!B$10,1)="*",A$25,RIGHT(A$25,2)) -> R2 | B27: =Commodities!C$10 -> TB | C27: =Commodities!D$10 -> TRN.BUS | D27: bn-vmt | E27: =#REF! -> #REF! | F27: =#REF! -> #REF! | G27: =#REF! -> #REF! | H27: =#REF! -> #REF! | I27: =#REF! -> #REF! | J27: =#REF! -> #REF! | K27: =#REF! -> #REF! | L27: =#REF! -> #REF! | ... O27: =#REF! -> #REF!
A28: R2 | B28: =Commodities!C$11 -> TM | C28: =Commodities!D$11 -> TRN.Medium Duty Trucks | D28: bn-vmt | E28: =#REF! -> #REF! | F28: =#REF! -> #REF! | G28: =#REF! -> #REF! | H28: =#REF! -> #REF! | I28: =#REF! -> #REF! | J28: =#REF! -> #REF! | K28: =#REF! -> #REF! | L28: =#REF! -> #REF! | ... O28: =#REF! -> #REF!
A29: =IF(LEFT(Commodities!B$12,1)="*",A$25,RIGHT(A$25,2)) -> R2 | B29: =Commodities!C$12 -> THS | C29: =Commodities!$D$12 -> TRN.HDV Short Haul | D29: bn-vmt | E29: =#REF! -> #REF! | F29: =#REF! -> #REF! | G29: =#REF! -> #REF! | H29: =#REF! -> #REF! | I29: =#REF! -> #REF! | J29: =#REF! -> #REF! | K29: =#REF! -> #REF! | L29: =#REF! -> #REF! | ... O29: =#REF! -> #REF!
A30: =IF(LEFT(Commodities!B$13,1)="*",A$25,RIGHT(A$25,2)) -> *R2 | B30: =Commodities!C$13 -> THL | C30: =Commodities!$D$13 -> TRN.HDV Long Haul | D30: bn-vmt | E30: =#REF! -> #REF! | F30: =#REF! -> #REF! | G30: =#REF! -> #REF! | H30: =#REF! -> #REF! | I30: =#REF! -> #REF! | J30: =#REF! -> #REF! | K30: =#REF! -> #REF! | L30: =#REF! -> #REF! | ... O30: =#REF! -> #REF!
A31: =IF(LEFT(Commodities!B$15,1)="*",A$25,RIGHT(A$25,2)) -> *R2 | B31: =Commodities!C$15 -> TRF | C31: =Commodities!D$15 -> TRN.RAIL.FREIGHT | D31: bn-t-m | E31: =#REF! -> #REF! | F31: =#REF! -> #REF! | G31: =#REF! -> #REF! | H31: =#REF! -> #REF! | I31: =#REF! -> #REF! | J31: =#REF! -> #REF! | K31: =#REF! -> #REF! | L31: =#REF! -> #REF! | ... O31: =#REF! -> #REF!
A32: =IF(LEFT(Commodities!B$17,1)="*",A$25,RIGHT(A$25,2)) -> R2 | B32: =Commodities!C$17 -> TRP | C32: =Commodities!D$17 -> TRN.RAIL.PASS | D32: bn-pass-miles | E32: =#REF! -> #REF! | F32: =#REF! -> #REF! | G32: =#REF! -> #REF! | H32: =#REF! -> #REF! | I32: =#REF! -> #REF! | J32: =#REF! -> #REF! | K32: =#REF! -> #REF! | L32: =#REF! -> #REF! | ... O32: =#REF! -> #REF!
A33: =IF(LEFT(Commodities!B$14,1)="*",A$25,RIGHT(A$25,2)) -> R2 | B33: =Commodities!C$14 -> TS | C33: =Commodities!D$14 -> TRN.SHIP | D33: bn-t-m | E33: =#REF! -> #REF! | F33: =#REF! -> #REF! | G33: =#REF! -> #REF! | H33: =#REF! -> #REF! | I33: =#REF! -> #REF! | J33: =#REF! -> #REF! | K33: =#REF! -> #REF! | L33: =#REF! -> #REF! | ... O33: =#REF! -> #REF!
A34: =IF(LEFT(Commodities!B$18,1)="*",A$25,RIGHT(A$25,2)) -> *R2 | B34: =Commodities!C$18 -> TC | C34: =Commodities!D$18 -> TRN.TRUCK.COMMERCIAL | D34: bn-vmt | E34: =#REF! -> #REF! | F34: =#REF! -> #REF! | G34: =#REF! -> #REF! | H34: =#REF! -> #REF! | I34: =#REF! -> #REF! | J34: =#REF! -> #REF! | K34: =#REF! -> #REF! | L34: =#REF! -> #REF! | ... O34: =#REF! -> #REF!
A35: =IF(LEFT(Commodities!B16,1)="*",A$25,RIGHT(A$25,2)) -> *R2 | B35: =Commodities!C16 -> TSW | C35: =Commodities!D16 -> TRN.MSW | D35: =Commodities!E16 -> bn-vmt
A36: *R3
A37: *R3 | B37: =Commodities!C$9 -> TA | C37: =Commodities!D$9 -> TRN.AIR | D37: bn-pass-miles | E37: =#REF! -> #REF! | F37: =#REF! -> #REF! | G37: =#REF! -> #REF! | H37: =#REF! -> #REF! | I37: =#REF! -> #REF! | J37: =#REF! -> #REF! | K37: =#REF! -> #REF! | L37: =#REF! -> #REF! | ... O37: =#REF! -> #REF!
A38: =IF(LEFT(Commodities!B$10,1)="*",A$36,RIGHT(A$36,2)) -> R3 | B38: =Commodities!C$10 -> TB | C38: =Commodities!D$10 -> TRN.BUS | D38: bn-vmt | E38: =#REF! -> #REF! | F38: =#REF! -> #REF! | G38: =#REF! -> #REF! | H38: =#REF! -> #REF! | I38: =#REF! -> #REF! | J38: =#REF! -> #REF! | K38: =#REF! -> #REF! | L38: =#REF! -> #REF! | ... O38: =#REF! -> #REF!
A39: R3 | B39: =Commodities!C$11 -> TM | C39: =Commodities!D$11 -> TRN.Medium Duty Trucks | D39: bn-vmt | E39: =#REF! -> #REF! | F39: =#REF! -> #REF! | G39: =#REF! -> #REF! | H39: =#REF! -> #REF! | I39: =#REF! -> #REF! | J39: =#REF! -> #REF! | K39: =#REF! -> #REF! | L39: =#REF! -> #REF! | ... O39: =#REF! -> #REF!
A40: =IF(LEFT(Commodities!B$12,1)="*",A$36,RIGHT(A$36,2)) -> R3 | B40: =Commodities!C$12 -> THS | C40: =Commodities!$D$12 -> TRN.HDV Short Haul | D40: bn-vmt | E40: =#REF! -> #REF! | F40: =#REF! -> #REF! | G40: =#REF! -> #REF! | H40: =#REF! -> #REF! | I40: =#REF! -> #REF! | J40: =#REF! -> #REF! | K40: =#REF! -> #REF! | L40: =#REF! -> #REF! | ... O40: =#REF! -> #REF!
A41: =IF(LEFT(Commodities!B$13,1)="*",A$36,RIGHT(A$36,2)) -> *R3 | B41: =Commodities!C$13 -> THL | C41: =Commodities!$D$13 -> TRN.HDV Long Haul | D41: bn-vmt | E41: =#REF! -> #REF! | F41: =#REF! -> #REF! | G41: =#REF! -> #REF! | H41: =#REF! -> #REF! | I41: =#REF! -> #REF! | J41: =#REF! -> #REF! | K41: =#REF! -> #REF! | L41: =#REF! -> #REF! | ... O41: =#REF! -> #REF!
A42: =IF(LEFT(Commodities!B$15,1)="*",A$36,RIGHT(A$36,2)) -> *R3 | B42: =Commodities!C$15 -> TRF | C42: =Commodities!D$15 -> TRN.RAIL.FREIGHT | D42: bn-t-m | E42: =#REF! -> #REF! | F42: =#REF! -> #REF! | G42: =#REF! -> #REF! | H42: =#REF! -> #REF! | I42: =#REF! -> #REF! | J42: =#REF! -> #REF! | K42: =#REF! -> #REF! | L42: =#REF! -> #REF! | ... O42: =#REF! -> #REF!
A43: =IF(LEFT(Commodities!B$17,1)="*",A$36,RIGHT(A$36,2)) -> R3 | B43: =Commodities!C$17 -> TRP | C43: =Commodities!D$17 -> TRN.RAIL.PASS | D43: bn-pass-miles | E43: =#REF! -> #REF! | F43: =#REF! -> #REF! | G43: =#REF! -> #REF! | H43: =#REF! -> #REF! | I43: =#REF! -> #REF! | J43: =#REF! -> #REF! | K43: =#REF! -> #REF! | L43: =#REF! -> #REF! | ... O43: =#REF! -> #REF!
A44: =IF(LEFT(Commodities!B$14,1)="*",A$36,RIGHT(A$36,2)) -> R3 | B44: =Commodities!C$14 -> TS | C44: =Commodities!D$14 -> TRN.SHIP | D44: bn-t-m | E44: =#REF! -> #REF! | F44: =#REF! -> #REF! | G44: =#REF! -> #REF! | H44: =#REF! -> #REF! | I44: =#REF! -> #REF! | J44: =#REF! -> #REF! | K44: =#REF! -> #REF! | L44: =#REF! -> #REF! | ... O44: =#REF! -> #REF!
A45: =IF(LEFT(Commodities!B$18,1)="*",A$36,RIGHT(A$36,2)) -> *R3 | B45: =Commodities!C$18 -> TC | C45: =Commodities!D$18 -> TRN.TRUCK.COMMERCIAL | D45: bn-vmt | E45: =#REF! -> #REF! | F45: =#REF! -> #REF! | G45: =#REF! -> #REF! | H45: =#REF! -> #REF! | I45: =#REF! -> #REF! | J45: =#REF! -> #REF! | K45: =#REF! -> #REF! | L45: =#REF! -> #REF! | ... O45: =#REF! -> #REF!
A46: =IF(LEFT(Commodities!B$16,1)="*",A$36,RIGHT(A$36,2)) -> *R3 | B46: =Commodities!C16 -> TSW | C46: =Commodities!D16 -> TRN.MSW | D46: =Commodities!E16 -> bn-vmt
A47: *R4
A48: *R4 | B48: =Commodities!C$9 -> TA | C48: =Commodities!D$9 -> TRN.AIR | D48: bn-pass-miles | E48: =#REF! -> #REF! | F48: =#REF! -> #REF! | G48: =#REF! -> #REF! | H48: =#REF! -> #REF! | I48: =#REF! -> #REF! | J48: =#REF! -> #REF! | K48: =#REF! -> #REF! | L48: =#REF! -> #REF! | ... O48: =#REF! -> #REF!
A49: =IF(LEFT(Commodities!B$10,1)="*",A$47,RIGHT(A$47,2)) -> R4 | B49: =Commodities!C$10 -> TB | C49: =Commodities!D$10 -> TRN.BUS | D49: bn-vmt | E49: =#REF! -> #REF! | F49: =#REF! -> #REF! | G49: =#REF! -> #REF! | H49: =#REF! -> #REF! | I49: =#REF! -> #REF! | J49: =#REF! -> #REF! | K49: =#REF! -> #REF! | L49: =#REF! -> #REF! | ... O49: =#REF! -> #REF!
A50: R4 | B50: =Commodities!C$11 -> TM | C50: =Commodities!D$11 -> TRN.Medium Duty Trucks | D50: bn-vmt | E50: =#REF! -> #REF! | F50: =#REF! -> #REF! | G50: =#REF! -> #REF! | H50: =#REF! -> #REF! | I50: =#REF! -> #REF! | J50: =#REF! -> #REF! | K50: =#REF! -> #REF! | L50: =#REF! -> #REF! | ... O50: =#REF! -> #REF!
A51: =IF(LEFT(Commodities!B$12,1)="*",A$47,RIGHT(A$47,2)) -> R4 | B51: =Commodities!C$12 -> THS | C51: =Commodities!$D$12 -> TRN.HDV Short Haul | D51: bn-vmt | E51: =#REF! -> #REF! | F51: =#REF! -> #REF! | G51: =#REF! -> #REF! | H51: =#REF! -> #REF! | I51: =#REF! -> #REF! | J51: =#REF! -> #REF! | K51: =#REF! -> #REF! | L51: =#REF! -> #REF! | ... O51: =#REF! -> #REF!
A52: =IF(LEFT(Commodities!B$13,1)="*",A$47,RIGHT(A$47,2)) -> *R4 | B52: =Commodities!C$13 -> THL | C52: =Commodities!$D$13 -> TRN.HDV Long Haul | D52: bn-vmt | E52: =#REF! -> #REF! | F52: =#REF! -> #REF! | G52: =#REF! -> #REF! | H52: =#REF! -> #REF! | I52: =#REF! -> #REF! | J52: =#REF! -> #REF! | K52: =#REF! -> #REF! | L52: =#REF! -> #REF! | ... O52: =#REF! -> #REF!
A53: =IF(LEFT(Commodities!B$15,1)="*",A$47,RIGHT(A$47,2)) -> *R4 | B53: =Commodities!C$15 -> TRF | C53: =Commodities!D$15 -> TRN.RAIL.FREIGHT | D53: bn-t-m | E53: =#REF! -> #REF! | F53: =#REF! -> #REF! | G53: =#REF! -> #REF! | H53: =#REF! -> #REF! | I53: =#REF! -> #REF! | J53: =#REF! -> #REF! | K53: =#REF! -> #REF! | L53: =#REF! -> #REF! | ... O53: =#REF! -> #REF!
