Workbook
Name AnswerData: #REF!
Name AnswerData: #REF!
Name bprint: #REF!
Name bprint: #REF!
Name CMM_ANN_COAL_PRODUCTION: #REF!
Name CMM_BASE_YR_SUPPLY_CURVE: Types!$A$3:$AA$43
Name CMM_CENSUS_DMD_SHARE_FCTR: #REF!
Name CMM_ORIGIN_DEST_RATE: #REF!
Name CMM_SUPPLY_CRV_TABLE: [1]cum2025curves!#REF!
Name CMM_SUPPLY_CRV_TABLE: [2]cum2025curves!#REF!
Name CMM_TRAN_RATE_ESC_COMP: 'Rate esc'!$B$3:$D$2274
Name cprint: #REF!
Name cprint: #REF!
Name exch_rate: #REF!
Name exch_rate: #REF!
Name fitfile: [3]MODEL!$D$38
Name fitfile: [4]MODEL!$D$38
Name INF: [3]MODEL!$H$14
Name INF: [4]MODEL!$H$14
Name million_short_tons_to_short_ton: [5]Steps!$Y$5
Name million_short_tons_to_short_ton: [6]Steps!$Y$5
Name MMBTU_to_PJ: [5]Steps!$Y$6
Name MMBTU_to_PJ: [6]Steps!$Y$6
Name PPP: [3]MODEL!$D$12
Name PPP: [4]MODEL!$D$12
Name PPPEX: [3]MODEL!$D$13
Name PPPEX: [4]MODEL!$D$13
Name rail_coal: #REF!
Name rail_coal: #REF!

Sheet ANSv6.1-Commodities
A1: ANSWER-Commodities
B7: CommName | C7: CommDesc | D7: CommUnit | E7: Set Memberships | F7: Comment

Sheet UC_COA
A2: Maximum capacity technology growth:
A3: ~UC_Sets: R_E: R0
A4: ~UC_Sets: T_SUC:
G5: ~UC_T
A6: UC_N | B6: Pset_PN | C6: Pset_CI | D6: Pset_CO | E6: UC_ATTR | F6: Year | G6: LimType | H6: UC_CAP~2010 | I6: UC_CAP~2015 | J6: UC_CAP~2020 | K6: UC_CAP~2025 | L6: UC_CAP~2030 | M6: UC_CAP~2035 | N6: UC_CAP~2040 | O6: UC_CAP~2045 | P6: UC_CAP~2050 | Q6: UC_CAP~2055 | R6: UC_CAP~RHS | S6: UC_RHSRTS | T6: UC_RHSRTS~0 | U6: UC_Desc
A7: UC_GrowthOfCOAUP1 | B7: =TechData_R0!B13 -> MINCNAPMU1 | E7: CAP, GROWTH | G7: UP | H7: =TechData_R0!G13 -> 1.05 | I7: =H7 -> 1.05 | J7: =I7 -> 1.05 | K7: =J7 -> 1.05 | L7: =K7 -> 1.05 | M7: =L7 -> 1.05 | N7: =M7 -> 1.05 | O7: =N7 -> 1.05 | P7: =O7 -> 1.05 | Q7: =P7 -> 1.05 | R7: =MAX(TechData_R0!F13,1) -> 1 | T7: 5
A8: UC_GrowthOfCOAUP2 | B8: =TechData_R0!B14 -> MINCNAPMU2 | E8: CAP, GROWTH | G8: UP | H8: =TechData_R0!G14 -> 1.05 | I8: =H8 -> 1.05 | J8: =I8 -> 1.05 | K8: =J8 -> 1.05 | L8: =K8 -> 1.05 | M8: =L8 -> 1.05 | N8: =M8 -> 1.05 | O8: =N8 -> 1.05 | P8: =O8 -> 1.05 | Q8: =P8 -> 1.05 | R8: =MAX(TechData_R0!F14,1) -> 1 | T8: 5
A9: UC_GrowthOfCOAUP3 | B9: =TechData_R0!B15 -> MINCNAPMU3 | E9: CAP, GROWTH | G9: UP | H9: =TechData_R0!G15 -> 1.05 | I9: =H9 -> 1.05 | J9: =I9 -> 1.05 | K9: =J9 -> 1.05 | L9: =K9 -> 1.05 | M9: =L9 -> 1.05 | N9: =M9 -> 1.05 | O9: =N9 -> 1.05 | P9: =O9 -> 1.05 | Q9: =P9 -> 1.05 | R9: =MAX(TechData_R0!F15,1) -> 1 | T9: 5
A10: UC_GrowthOfCOAUP4 | B10: =TechData_R0!B16 -> MINCNAPMU4 | E10: CAP, GROWTH | G10: UP | H10: =TechData_R0!G16 -> 1.05 | I10: =H10 -> 1.05 | J10: =I10 -> 1.05 | K10: =J10 -> 1.05 | L10: =K10 -> 1.05 | M10: =L10 -> 1.05 | N10: =M10 -> 1.05 | O10: =N10 -> 1.05 | P10: =O10 -> 1.05 | Q10: =P10 -> 1.05 | R10: =MAX(TechData_R0!F16,1) -> 1 | T10: 5
A11: UC_GrowthOfCOAUP5 | B11: =TechData_R0!B17 -> MINCNAPMU5 | E11: CAP, GROWTH | G11: UP | H11: =TechData_R0!G17 -> 1.05 | I11: =H11 -> 1.05 | J11: =I11 -> 1.05 | K11: =J11 -> 1.05 | L11: =K11 -> 1.05 | M11: =L11 -> 1.05 | N11: =M11 -> 1.05 | O11: =N11 -> 1.05 | P11: =O11 -> 1.05 | Q11: =P11 -> 1.05 | R11: =MAX(TechData_R0!F17,1) -> 5.0108652 | T11: 5
A12: UC_GrowthOfCOAUP6 | B12: =TechData_R0!B18 -> MINCNAPMU6 | E12: CAP, GROWTH | G12: UP | H12: =TechData_R0!G18 -> 1.05 | I12: =H12 -> 1.05 | J12: =I12 -> 1.05 | K12: =J12 -> 1.05 | L12: =K12 -> 1.05 | M12: =L12 -> 1.05 | N12: =M12 -> 1.05 | O12: =N12 -> 1.05 | P12: =O12 -> 1.05 | Q12: =P12 -> 1.05 | R12: =MAX(TechData_R0!F18,1) -> 5.567628 | T12: 5
A13: UC_GrowthOfCOAUP8 | B13: =TechData_R0!B20 -> MINCNABMU1 | E13: CAP, GROWTH | G13: UP | H13: =TechData_R0!G20 -> 1.05 | I13: =H13 -> 1.05 | J13: =I13 -> 1.05 | K13: =J13 -> 1.05 | L13: =K13 -> 1.05 | M13: =L13 -> 1.05 | N13: =M13 -> 1.05 | O13: =N13 -> 1.05 | P13: =O13 -> 1.05 | Q13: =P13 -> 1.05 | R13: =MAX(TechData_R0!F19,1) -> 1 | T13: 5
A14: UC_GrowthOfCOAUP9 | B14: =TechData_R0!B21 -> MINCNABMU2 | E14: CAP, GROWTH | G14: UP | H14: =TechData_R0!G21 -> 1.05 | I14: =H14 -> 1.05 | J14: =I14 -> 1.05 | K14: =J14 -> 1.05 | L14: =K14 -> 1.05 | M14: =L14 -> 1.05 | N14: =M14 -> 1.05 | O14: =N14 -> 1.05 | P14: =O14 -> 1.05 | Q14: =P14 -> 1.05 | R14: =MAX(TechData_R0!F20,1) -> 1 | T14: 5
A15: UC_GrowthOfCOAUP10 | B15: =TechData_R0!B22 -> MINCNABMU3 | E15: CAP, GROWTH | G15: UP | H15: =TechData_R0!G22 -> 1.05 | I15: =H15 -> 1.05 | J15: =I15 -> 1.05 | K15: =J15 -> 1.05 | L15: =K15 -> 1.05 | M15: =L15 -> 1.05 | N15: =M15 -> 1.05 | O15: =N15 -> 1.05 | P15: =O15 -> 1.05 | Q15: =P15 -> 1.05 | R15: =MAX(TechData_R0!F21,1) -> 1 | T15: 5
A16: UC_GrowthOfCOAUP11 | B16: =TechData_R0!B23 -> MINCNABMU4 | E16: CAP, GROWTH | G16: UP | H16: =TechData_R0!G23 -> 1.05 | I16: =H16 -> 1.05 | J16: =I16 -> 1.05 | K16: =J16 -> 1.05 | L16: =K16 -> 1.05 | M16: =L16 -> 1.05 | N16: =M16 -> 1.05 | O16: =N16 -> 1.05 | P16: =O16 -> 1.05 | Q16: =P16 -> 1.05 | R16: =MAX(TechData_R0!F22,1) -> 1 | T16: 5
A17: UC_GrowthOfCOAUP12 | B17: =TechData_R0!B24 -> MINCNABMU5 | E17: CAP, GROWTH | G17: UP | H17: =TechData_R0!G24 -> 1.05 | I17: =H17 -> 1.05 | J17: =I17 -> 1.05 | K17: =J17 -> 1.05 | L17: =K17 -> 1.05 | M17: =L17 -> 1.05 | N17: =M17 -> 1.05 | O17: =N17 -> 1.05 | P17: =O17 -> 1.05 | Q17: =P17 -> 1.05 | R17: =MAX(TechData_R0!F23,1) -> 1 | T17: 5
A18: UC_GrowthOfCOAUP13 | B18: =TechData_R0!B25 -> MINCNABMU6 | E18: CAP, GROWTH | G18: UP | H18: =TechData_R0!G25 -> 1.05 | I18: =H18 -> 1.05 | J18: =I18 -> 1.05 | K18: =J18 -> 1.05 | L18: =K18 -> 1.05 | M18: =L18 -> 1.05 | N18: =M18 -> 1.05 | O18: =N18 -> 1.05 | P18: =O18 -> 1.05 | Q18: =P18 -> 1.05 | R18: =MAX(TechData_R0!F24,1) -> 7.146641 | T18: 5
A19: UC_GrowthOfCOAUP15 | B19: =TechData_R0!B27 -> MINCNABMS1 | E19: CAP, GROWTH | G19: UP | H19: =TechData_R0!G27 -> 1.05 | I19: =H19 -> 1.05 | J19: =I19 -> 1.05 | K19: =J19 -> 1.05 | L19: =K19 -> 1.05 | M19: =L19 -> 1.05 | N19: =M19 -> 1.05 | O19: =N19 -> 1.05 | P19: =O19 -> 1.05 | Q19: =P19 -> 1.05 | R19: =MAX(TechData_R0!F26,1) -> 1 | T19: 5
A20: UC_GrowthOfCOAUP16 | B20: =TechData_R0!B28 -> MINCNABMS2 | E20: CAP, GROWTH | G20: UP | H20: =TechData_R0!G28 -> 1.05 | I20: =H20 -> 1.05 | J20: =I20 -> 1.05 | K20: =J20 -> 1.05 | L20: =K20 -> 1.05 | M20: =L20 -> 1.05 | N20: =M20 -> 1.05 | O20: =N20 -> 1.05 | P20: =O20 -> 1.05 | Q20: =P20 -> 1.05 | R20: =MAX(TechData_R0!F27,1) -> 1 | T20: 5
A21: UC_GrowthOfCOAUP17 | B21: =TechData_R0!B29 -> MINCNABMS3 | E21: CAP, GROWTH | G21: UP | H21: =TechData_R0!G29 -> 1.05 | I21: =H21 -> 1.05 | J21: =I21 -> 1.05 | K21: =J21 -> 1.05 | L21: =K21 -> 1.05 | M21: =L21 -> 1.05 | N21: =M21 -> 1.05 | O21: =N21 -> 1.05 | P21: =O21 -> 1.05 | Q21: =P21 -> 1.05 | R21: =MAX(TechData_R0!F28,1) -> 1 | T21: 5
A22: UC_GrowthOfCOAUP18 | B22: =TechData_R0!B30 -> MINCNABMS4 | E22: CAP, GROWTH | G22: UP | H22: =TechData_R0!G30 -> 1.05 | I22: =H22 -> 1.05 | J22: =I22 -> 1.05 | K22: =J22 -> 1.05 | L22: =K22 -> 1.05 | M22: =L22 -> 1.05 | N22: =M22 -> 1.05 | O22: =N22 -> 1.05 | P22: =O22 -> 1.05 | Q22: =P22 -> 1.05 | R22: =MAX(TechData_R0!F29,1) -> 1 | T22: 5
A23: UC_GrowthOfCOAUP19 | B23: =TechData_R0!B31 -> MINCNABMS5 | E23: CAP, GROWTH | G23: UP | H23: =TechData_R0!G31 -> 1.05 | I23: =H23 -> 1.05 | J23: =I23 -> 1.05 | K23: =J23 -> 1.05 | L23: =K23 -> 1.05 | M23: =L23 -> 1.05 | N23: =M23 -> 1.05 | O23: =N23 -> 1.05 | P23: =O23 -> 1.05 | Q23: =P23 -> 1.05 | R23: =MAX(TechData_R0!F30,1) -> 1 | T23: 5
A24: UC_GrowthOfCOAUP20 | B24: =TechData_R0!B32 -> MINCNABMS6 | E24: CAP, GROWTH | G24: UP | H24: =TechData_R0!G32 -> 1.05 | I24: =H24 -> 1.05 | J24: =I24 -> 1.05 | K24: =J24 -> 1.05 | L24: =K24 -> 1.05 | M24: =L24 -> 1.05 | N24: =M24 -> 1.05 | O24: =N24 -> 1.05 | P24: =O24 -> 1.05 | Q24: =P24 -> 1.05 | R24: =MAX(TechData_R0!F31,1) -> 2.4977947 | T24: 5
A25: UC_GrowthOfCOAUP22 | B25: =TechData_R0!B34 -> MINCNABHU1 | E25: CAP, GROWTH | G25: UP | H25: =TechData_R0!G34 -> 1.05 | I25: =H25 -> 1.05 | J25: =I25 -> 1.05 | K25: =J25 -> 1.05 | L25: =K25 -> 1.05 | M25: =L25 -> 1.05 | N25: =M25 -> 1.05 | O25: =N25 -> 1.05 | P25: =O25 -> 1.05 | Q25: =P25 -> 1.05 | R25: =MAX(TechData_R0!F33,1) -> 1 | T25: 5
A26: UC_GrowthOfCOAUP23 | B26: =TechData_R0!B35 -> MINCNABHU2 | E26: CAP, GROWTH | G26: UP | H26: =TechData_R0!G35 -> 1.05 | I26: =H26 -> 1.05 | J26: =I26 -> 1.05 | K26: =J26 -> 1.05 | L26: =K26 -> 1.05 | M26: =L26 -> 1.05 | N26: =M26 -> 1.05 | O26: =N26 -> 1.05 | P26: =O26 -> 1.05 | Q26: =P26 -> 1.05 | R26: =MAX(TechData_R0!F34,1) -> 1 | T26: 5
A27: UC_GrowthOfCOAUP24 | B27: =TechData_R0!B36 -> MINCNABHU3 | E27: CAP, GROWTH | G27: UP | H27: =TechData_R0!G36 -> 1.05 | I27: =H27 -> 1.05 | J27: =I27 -> 1.05 | K27: =J27 -> 1.05 | L27: =K27 -> 1.05 | M27: =L27 -> 1.05 | N27: =M27 -> 1.05 | O27: =N27 -> 1.05 | P27: =O27 -> 1.05 | Q27: =P27 -> 1.05 | R27: =MAX(TechData_R0!F35,1) -> 1 | T27: 5
A28: UC_GrowthOfCOAUP25 | B28: =TechData_R0!B37 -> MINCNABHU4 | E28: CAP, GROWTH | G28: UP | H28: =TechData_R0!G37 -> 1.05 | I28: =H28 -> 1.05 | J28: =I28 -> 1.05 | K28: =J28 -> 1.05 | L28: =K28 -> 1.05 | M28: =L28 -> 1.05 | N28: =M28 -> 1.05 | O28: =N28 -> 1.05 | P28: =O28 -> 1.05 | Q28: =P28 -> 1.05 | R28: =MAX(TechData_R0!F36,1) -> 1 | T28: 5
A29: UC_GrowthOfCOAUP26 | B29: =TechData_R0!B38 -> MINCNABHU5 | E29: CAP, GROWTH | G29: UP | H29: =TechData_R0!G38 -> 1.05 | I29: =H29 -> 1.05 | J29: =I29 -> 1.05 | K29: =J29 -> 1.05 | L29: =K29 -> 1.05 | M29: =L29 -> 1.05 | N29: =M29 -> 1.05 | O29: =N29 -> 1.05 | P29: =O29 -> 1.05 | Q29: =P29 -> 1.05 | R29: =MAX(TechData_R0!F37,1) -> 1 | T29: 5
A30: UC_GrowthOfCOAUP27 | B30: =TechData_R0!B39 -> MINCNABHU6 | E30: CAP, GROWTH | G30: UP | H30: =TechData_R0!G39 -> 1.05 | I30: =H30 -> 1.05 | J30: =I30 -> 1.05 | K30: =J30 -> 1.05 | L30: =K30 -> 1.05 | M30: =L30 -> 1.05 | N30: =M30 -> 1.05 | O30: =N30 -> 1.05 | P30: =O30 -> 1.05 | Q30: =P30 -> 1.05 | R30: =MAX(TechData_R0!F38,1) -> 16.153404 | T30: 5
A31: UC_GrowthOfCOAUP29 | B31: =TechData_R0!B41 -> MINCNABHS1 | E31: CAP, GROWTH | G31: UP | H31: =TechData_R0!G41 -> 1.05 | I31: =H31 -> 1.05 | J31: =I31 -> 1.05 | K31: =J31 -> 1.05 | L31: =K31 -> 1.05 | M31: =L31 -> 1.05 | N31: =M31 -> 1.05 | O31: =N31 -> 1.05 | P31: =O31 -> 1.05 | Q31: =P31 -> 1.05 | R31: =MAX(TechData_R0!F40,1) -> 1 | T31: 5
A32: UC_GrowthOfCOAUP30 | B32: =TechData_R0!B42 -> MINCNABHS2 | E32: CAP, GROWTH | G32: UP | H32: =TechData_R0!G42 -> 1.05 | I32: =H32 -> 1.05 | J32: =I32 -> 1.05 | K32: =J32 -> 1.05 | L32: =K32 -> 1.05 | M32: =L32 -> 1.05 | N32: =M32 -> 1.05 | O32: =N32 -> 1.05 | P32: =O32 -> 1.05 | Q32: =P32 -> 1.05 | R32: =MAX(TechData_R0!F41,1) -> 1 | T32: 5
A33: UC_GrowthOfCOAUP31 | B33: =TechData_R0!B43 -> MINCNABHS3 | E33: CAP, GROWTH | G33: UP | H33: =TechData_R0!G43 -> 1.05 | I33: =H33 -> 1.05 | J33: =I33 -> 1.05 | K33: =J33 -> 1.05 | L33: =K33 -> 1.05 | M33: =L33 -> 1.05 | N33: =M33 -> 1.05 | O33: =N33 -> 1.05 | P33: =O33 -> 1.05 | Q33: =P33 -> 1.05 | R33: =MAX(TechData_R0!F42,1) -> 1 | T33: 5
A34: UC_GrowthOfCOAUP32 | B34: =TechData_R0!B44 -> MINCNABHS4 | E34: CAP, GROWTH | G34: UP | H34: =TechData_R0!G44 -> 1.05 | I34: =H34 -> 1.05 | J34: =I34 -> 1.05 | K34: =J34 -> 1.05 | L34: =K34 -> 1.05 | M34: =L34 -> 1.05 | N34: =M34 -> 1.05 | O34: =N34 -> 1.05 | P34: =O34 -> 1.05 | Q34: =P34 -> 1.05 | R34: =MAX(TechData_R0!F43,1) -> 1 | T34: 5
A35: UC_GrowthOfCOAUP33 | B35: =TechData_R0!B45 -> MINCNABHS5 | E35: CAP, GROWTH | G35: UP | H35: =TechData_R0!G45 -> 1.05 | I35: =H35 -> 1.05 | J35: =I35 -> 1.05 | K35: =J35 -> 1.05 | L35: =K35 -> 1.05 | M35: =L35 -> 1.05 | N35: =M35 -> 1.05 | O35: =N35 -> 1.05 | P35: =O35 -> 1.05 | Q35: =P35 -> 1.05 | R35: =MAX(TechData_R0!F44,1) -> 1 | T35: 5
A36: UC_GrowthOfCOAUP34 | B36: =TechData_R0!B46 -> MINCNABHS6 | E36: CAP, GROWTH | G36: UP | H36: =TechData_R0!G46 -> 1.05 | I36: =H36 -> 1.05 | J36: =I36 -> 1.05 | K36: =J36 -> 1.05 | L36: =K36 -> 1.05 | M36: =L36 -> 1.05 | N36: =M36 -> 1.05 | O36: =N36 -> 1.05 | P36: =O36 -> 1.05 | Q36: =P36 -> 1.05 | R36: =MAX(TechData_R0!F45,1) -> 3.9360356 | T36: 5
A37: UC_GrowthOfCOAUP36 | B37: =TechData_R0!B48 -> MINCCAPMU1 | E37: CAP, GROWTH | G37: UP | H37: =TechData_R0!G48 -> 1.05 | I37: =H37 -> 1.05 | J37: =I37 -> 1.05 | K37: =J37 -> 1.05 | L37: =K37 -> 1.05 | M37: =L37 -> 1.05 | N37: =M37 -> 1.05 | O37: =N37 -> 1.05 | P37: =O37 -> 1.05 | Q37: =P37 -> 1.05 | R37: =MAX(TechData_R0!F47,1) -> 1 | T37: 5
A38: UC_GrowthOfCOAUP37 | B38: =TechData_R0!B49 -> MINCCAPMU2 | E38: CAP, GROWTH | G38: UP | H38: =TechData_R0!G49 -> 1.05 | I38: =H38 -> 1.05 | J38: =I38 -> 1.05 | K38: =J38 -> 1.05 | L38: =K38 -> 1.05 | M38: =L38 -> 1.05 | N38: =M38 -> 1.05 | O38: =N38 -> 1.05 | P38: =O38 -> 1.05 | Q38: =P38 -> 1.05 | R38: =MAX(TechData_R0!F48,1) -> 1 | T38: 5
A39: UC_GrowthOfCOAUP38 | B39: =TechData_R0!B50 -> MINCCAPMU3 | E39: CAP, GROWTH | G39: UP | H39: =TechData_R0!G50 -> 1.05 | I39: =H39 -> 1.05 | J39: =I39 -> 1.05 | K39: =J39 -> 1.05 | L39: =K39 -> 1.05 | M39: =L39 -> 1.05 | N39: =M39 -> 1.05 | O39: =N39 -> 1.05 | P39: =O39 -> 1.05 | Q39: =P39 -> 1.05 | R39: =MAX(TechData_R0!F49,1) -> 1 | T39: 5
A40: UC_GrowthOfCOAUP39 | B40: =TechData_R0!B51 -> MINCCAPMU4 | E40: CAP, GROWTH | G40: UP | H40: =TechData_R0!G51 -> 1.05 | I40: =H40 -> 1.05 | J40: =I40 -> 1.05 | K40: =J40 -> 1.05 | L40: =K40 -> 1.05 | M40: =L40 -> 1.05 | N40: =M40 -> 1.05 | O40: =N40 -> 1.05 | P40: =O40 -> 1.05 | Q40: =P40 -> 1.05 | R40: =MAX(TechData_R0!F50,1) -> 1 | T40: 5
A41: UC_GrowthOfCOAUP40 | B41: =TechData_R0!B52 -> MINCCAPMU5 | E41: CAP, GROWTH | G41: UP | H41: =TechData_R0!G52 -> 1.05 | I41: =H41 -> 1.05 | J41: =I41 -> 1.05 | K41: =J41 -> 1.05 | L41: =K41 -> 1.05 | M41: =L41 -> 1.05 | N41: =M41 -> 1.05 | O41: =N41 -> 1.05 | P41: =O41 -> 1.05 | Q41: =P41 -> 1.05 | R41: =MAX(TechData_R0!F51,1) -> 1 | T41: 5
A42: UC_GrowthOfCOAUP41 | B42: =TechData_R0!B53 -> MINCCAPMU6 | E42: CAP, GROWTH | G42: UP | H42: =TechData_R0!G53 -> 1.05 | I42: =H42 -> 1.05 | J42: =I42 -> 1.05 | K42: =J42 -> 1.05 | L42: =K42 -> 1.05 | M42: =L42 -> 1.05 | N42: =M42 -> 1.05 | O42: =N42 -> 1.05 | P42: =O42 -> 1.05 | Q42: =P42 -> 1.05 | R42: =MAX(TechData_R0!F52,1) -> 16.940503 | T42: 5
A43: UC_GrowthOfCOAUP43 | B43: =TechData_R0!B55 -> MINCCABLU1 | E43: CAP, GROWTH | G43: UP | H43: =TechData_R0!G55 -> 1.05 | I43: =H43 -> 1.05 | J43: =I43 -> 1.05 | K43: =J43 -> 1.05 | L43: =K43 -> 1.05 | M43: =L43 -> 1.05 | N43: =M43 -> 1.05 | O43: =N43 -> 1.05 | P43: =O43 -> 1.05 | Q43: =P43 -> 1.05 | R43: =MAX(TechData_R0!F54,1) -> 1 | T43: 5
A44: UC_GrowthOfCOAUP44 | B44: =TechData_R0!B56 -> MINCCABLU2 | E44: CAP, GROWTH | G44: UP | H44: =TechData_R0!G56 -> 1.05 | I44: =H44 -> 1.05 | J44: =I44 -> 1.05 | K44: =J44 -> 1.05 | L44: =K44 -> 1.05 | M44: =L44 -> 1.05 | N44: =M44 -> 1.05 | O44: =N44 -> 1.05 | P44: =O44 -> 1.05 | Q44: =P44 -> 1.05 | R44: =MAX(TechData_R0!F55,1) -> 1 | T44: 5
A45: UC_GrowthOfCOAUP45 | B45: =TechData_R0!B57 -> MINCCABLU3 | E45: CAP, GROWTH | G45: UP | H45: =TechData_R0!G57 -> 1.05 | I45: =H45 -> 1.05 | J45: =I45 -> 1.05 | K45: =J45 -> 1.05 | L45: =K45 -> 1.05 | M45: =L45 -> 1.05 | N45: =M45 -> 1.05 | O45: =N45 -> 1.05 | P45: =O45 -> 1.05 | Q45: =P45 -> 1.05 | R45: =MAX(TechData_R0!F56,1) -> 1 | T45: 5
A46: UC_GrowthOfCOAUP46 | B46: =TechData_R0!B58 -> MINCCABLU4 | E46: CAP, GROWTH | G46: UP | H46: =TechData_R0!G58 -> 1.05 | I46: =H46 -> 1.05 | J46: =I46 -> 1.05 | K46: =J46 -> 1.05 | L46: =K46 -> 1.05 | M46: =L46 -> 1.05 | N46: =M46 -> 1.05 | O46: =N46 -> 1.05 | P46: =O46 -> 1.05 | Q46: =P46 -> 1.05 | R46: =MAX(TechData_R0!F57,1) -> 1 | T46: 5
A47: UC_GrowthOfCOAUP47 | B47: =TechData_R0!B59 -> MINCCABLU5 | E47: CAP, GROWTH | G47: UP | H47: =TechData_R0!G59 -> 1.05 | I47: =H47 -> 1.05 | J47: =I47 -> 1.05 | K47: =J47 -> 1.05 | L47: =K47 -> 1.05 | M47: =L47 -> 1.05 | N47: =M47 -> 1.05 | O47: =N47 -> 1.05 | P47: =O47 -> 1.05 | Q47: =P47 -> 1.05 | R47: =MAX(TechData_R0!F58,1) -> 1 | T47: 5
A48: UC_GrowthOfCOAUP48 | B48: =TechData_R0!B60 -> MINCCABLU6 | E48: CAP, GROWTH | G48: UP | H48: =TechData_R0!G60 -> 1.05 | I48: =H48 -> 1.05 | J48: =I48 -> 1.05 | K48: =J48 -> 1.05 | L48: =K48 -> 1.05 | M48: =L48 -> 1.05 | N48: =M48 -> 1.05 | O48: =N48 -> 1.05 | P48: =O48 -> 1.05 | Q48: =P48 -> 1.05 | R48: =MAX(TechData_R0!F59,1) -> 1 | T48: 5
A49: UC_GrowthOfCOAUP50 | B49: =TechData_R0!B62 -> MINCCABLS1 | E49: CAP, GROWTH | G49: UP | H49: =TechData_R0!G62 -> 1.05 | I49: =H49 -> 1.05 | J49: =I49 -> 1.05 | K49: =J49 -> 1.05 | L49: =K49 -> 1.05 | M49: =L49 -> 1.05 | N49: =M49 -> 1.05 | O49: =N49 -> 1.05 | P49: =O49 -> 1.05 | Q49: =P49 -> 1.05 | R49: =MAX(TechData_R0!F61,1) -> 1 | T49: 5
A50: UC_GrowthOfCOAUP51 | B50: =TechData_R0!B63 -> MINCCABLS2 | E50: CAP, GROWTH | G50: UP | H50: =TechData_R0!G63 -> 1.05 | I50: =H50 -> 1.05 | J50: =I50 -> 1.05 | K50: =J50 -> 1.05 | L50: =K50 -> 1.05 | M50: =L50 -> 1.05 | N50: =M50 -> 1.05 | O50: =N50 -> 1.05 | P50: =O50 -> 1.05 | Q50: =P50 -> 1.05 | R50: =MAX(TechData_R0!F62,1) -> 1 | T50: 5
A51: UC_GrowthOfCOAUP52 | B51: =TechData_R0!B64 -> MINCCABLS3 | E51: CAP, GROWTH | G51: UP | H51: =TechData_R0!G64 -> 1.05 | I51: =H51 -> 1.05 | J51: =I51 -> 1.05 | K51: =J51 -> 1.05 | L51: =K51 -> 1.05 | M51: =L51 -> 1.05 | N51: =M51 -> 1.05 | O51: =N51 -> 1.05 | P51: =O51 -> 1.05 | Q51: =P51 -> 1.05 | R51: =MAX(TechData_R0!F63,1) -> 1 | T51: 5
A52: UC_GrowthOfCOAUP53 | B52: =TechData_R0!B65 -> MINCCABLS4 | E52: CAP, GROWTH | G52: UP | H52: =TechData_R0!G65 -> 1.05 | I52: =H52 -> 1.05 | J52: =I52 -> 1.05 | K52: =J52 -> 1.05 | L52: =K52 -> 1.05 | M52: =L52 -> 1.05 | N52: =M52 -> 1.05 | O52: =N52 -> 1.05 | P52: =O52 -> 1.05 | Q52: =P52 -> 1.05 | R52: =MAX(TechData_R0!F64,1) -> 1 | T52: 5
A53: UC_GrowthOfCOAUP54 | B53: =TechData_R0!B66 -> MINCCABLS5 | E53: CAP, GROWTH | G53: UP | H53: =TechData_R0!G66 -> 1.05 | I53: =H53 -> 1.05 | J53: =I53 -> 1.05 | K53: =J53 -> 1.05 | L53: =K53 -> 1.05 | M53: =L53 -> 1.05 | N53: =M53 -> 1.05 | O53: =N53 -> 1.05 | P53: =O53 -> 1.05 | Q53: =P53 -> 1.05 | R53: =MAX(TechData_R0!F65,1) -> 1 | T53: 5
A54: UC_GrowthOfCOAUP55 | B54: =TechData_R0!B67 -> MINCCABLS6 | E54: CAP, GROWTH | G54: UP | H54: =TechData_R0!G67 -> 1.05 | I54: =H54 -> 1.05 | J54: =I54 -> 1.05 | K54: =J54 -> 1.05 | L54: =K54 -> 1.05 | M54: =L54 -> 1.05 | N54: =M54 -> 1.05 | O54: =N54 -> 1.05 | P54: =O54 -> 1.05 | Q54: =P54 -> 1.05 | R54: =MAX(TechData_R0!F66,1) -> 2.9342976 | T54: 5
A55: UC_GrowthOfCOAUP57 | B55: =TechData_R0!B69 -> MINCCABMU1 | E55: CAP, GROWTH | G55: UP | H55: =TechData_R0!G69 -> 1.05 | I55: =H55 -> 1.05 | J55: =I55 -> 1.05 | K55: =J55 -> 1.05 | L55: =K55 -> 1.05 | M55: =L55 -> 1.05 | N55: =M55 -> 1.05 | O55: =N55 -> 1.05 | P55: =O55 -> 1.05 | Q55: =P55 -> 1.05 | R55: =MAX(TechData_R0!F68,1) -> 1 | T55: 5
A56: UC_GrowthOfCOAUP58 | B56: =TechData_R0!B70 -> MINCCABMU2 | E56: CAP, GROWTH | G56: UP | H56: =TechData_R0!G70 -> 1.05 | I56: =H56 -> 1.05 | J56: =I56 -> 1.05 | K56: =J56 -> 1.05 | L56: =K56 -> 1.05 | M56: =L56 -> 1.05 | N56: =M56 -> 1.05 | O56: =N56 -> 1.05 | P56: =O56 -> 1.05 | Q56: =P56 -> 1.05 | R56: =MAX(TechData_R0!F69,1) -> 1 | T56: 5
A57: UC_GrowthOfCOAUP59 | B57: =TechData_R0!B71 -> MINCCABMU3 | E57: CAP, GROWTH | G57: UP | H57: =TechData_R0!G71 -> 1.05 | I57: =H57 -> 1.05 | J57: =I57 -> 1.05 | K57: =J57 -> 1.05 | L57: =K57 -> 1.05 | M57: =L57 -> 1.05 | N57: =M57 -> 1.05 | O57: =N57 -> 1.05 | P57: =O57 -> 1.05 | Q57: =P57 -> 1.05 | R57: =MAX(TechData_R0!F70,1) -> 1 | T57: 5
A58: UC_GrowthOfCOAUP60 | B58: =TechData_R0!B72 -> MINCCABMU4 | E58: CAP, GROWTH | G58: UP | H58: =TechData_R0!G72 -> 1.05 | I58: =H58 -> 1.05 | J58: =I58 -> 1.05 | K58: =J58 -> 1.05 | L58: =K58 -> 1.05 | M58: =L58 -> 1.05 | N58: =M58 -> 1.05 | O58: =N58 -> 1.05 | P58: =O58 -> 1.05 | Q58: =P58 -> 1.05 | R58: =MAX(TechData_R0!F71,1) -> 1 | T58: 5
A59: UC_GrowthOfCOAUP61 | B59: =TechData_R0!B73 -> MINCCABMU5 | E59: CAP, GROWTH | G59: UP | H59: =TechData_R0!G73 -> 1.05 | I59: =H59 -> 1.05 | J59: =I59 -> 1.05 | K59: =J59 -> 1.05 | L59: =K59 -> 1.05 | M59: =L59 -> 1.05 | N59: =M59 -> 1.05 | O59: =N59 -> 1.05 | P59: =O59 -> 1.05 | Q59: =P59 -> 1.05 | R59: =MAX(TechData_R0!F72,1) -> 1 | T59: 5
A60: UC_GrowthOfCOAUP62 | B60: =TechData_R0!B74 -> MINCCABMU6 | E60: CAP, GROWTH | G60: UP | H60: =TechData_R0!G74 -> 1.05 | I60: =H60 -> 1.05 | J60: =I60 -> 1.05 | K60: =J60 -> 1.05 | L60: =K60 -> 1.05 | M60: =L60 -> 1.05 | N60: =M60 -> 1.05 | O60: =N60 -> 1.05 | P60: =O60 -> 1.05 | Q60: =P60 -> 1.05 | R60: =MAX(TechData_R0!F73,1) -> 7.2145057 | T60: 5
A61: UC_GrowthOfCOAUP64 | B61: =TechData_R0!B76 -> MINCCABMS1 | E61: CAP, GROWTH | G61: UP | H61: =TechData_R0!G76 -> 1.05 | I61: =H61 -> 1.05 | J61: =I61 -> 1.05 | K61: =J61 -> 1.05 | L61: =K61 -> 1.05 | M61: =L61 -> 1.05 | N61: =M61 -> 1.05 | O61: =N61 -> 1.05 | P61: =O61 -> 1.05 | Q61: =P61 -> 1.05 | R61: =MAX(TechData_R0!F75,1) -> 1 | T61: 5
A62: UC_GrowthOfCOAUP65 | B62: =TechData_R0!B77 -> MINCCABMS2 | E62: CAP, GROWTH | G62: UP | H62: =TechData_R0!G77 -> 1.05 | I62: =H62 -> 1.05 | J62: =I62 -> 1.05 | K62: =J62 -> 1.05 | L62: =K62 -> 1.05 | M62: =L62 -> 1.05 | N62: =M62 -> 1.05 | O62: =N62 -> 1.05 | P62: =O62 -> 1.05 | Q62: =P62 -> 1.05 | R62: =MAX(TechData_R0!F76,1) -> 1 | T62: 5
A63: UC_GrowthOfCOAUP66 | B63: =TechData_R0!B78 -> MINCCABMS3 | E63: CAP, GROWTH | G63: UP | H63: =TechData_R0!G78 -> 1.05 | I63: =H63 -> 1.05 | J63: =I63 -> 1.05 | K63: =J63 -> 1.05 | L63: =K63 -> 1.05 | M63: =L63 -> 1.05 | N63: =M63 -> 1.05 | O63: =N63 -> 1.05 | P63: =O63 -> 1.05 | Q63: =P63 -> 1.05 | R63: =MAX(TechData_R0!F77,1) -> 1 | T63: 5
A64: UC_GrowthOfCOAUP67 | B64: =TechData_R0!B79 -> MINCCABMS4 | E64: CAP, GROWTH | G64: UP | H64: =TechData_R0!G79 -> 1.05 | I64: =H64 -> 1.05 | J64: =I64 -> 1.05 | K64: =J64 -> 1.05 | L64: =K64 -> 1.05 | M64: =L64 -> 1.05 | N64: =M64 -> 1.05 | O64: =N64 -> 1.05 | P64: =O64 -> 1.05 | Q64: =P64 -> 1.05 | R64: =MAX(TechData_R0!F78,1) -> 1 | T64: 5
A65: UC_GrowthOfCOAUP68 | B65: =TechData_R0!B80 -> MINCCABMS5 | E65: CAP, GROWTH | G65: UP | H65: =TechData_R0!G80 -> 1.05 | I65: =H65 -> 1.05 | J65: =I65 -> 1.05 | K65: =J65 -> 1.05 | L65: =K65 -> 1.05 | M65: =L65 -> 1.05 | N65: =M65 -> 1.05 | O65: =N65 -> 1.05 | P65: =O65 -> 1.05 | Q65: =P65 -> 1.05 | R65: =MAX(TechData_R0!F79,1) -> 1 | T65: 5
A66: UC_GrowthOfCOAUP69 | B66: =TechData_R0!B81 -> MINCCABMS6 | E66: CAP, GROWTH | G66: UP | H66: =TechData_R0!G81 -> 1.05 | I66: =H66 -> 1.05 | J66: =I66 -> 1.05 | K66: =J66 -> 1.05 | L66: =K66 -> 1.05 | M66: =L66 -> 1.05 | N66: =M66 -> 1.05 | O66: =N66 -> 1.05 | P66: =O66 -> 1.05 | Q66: =P66 -> 1.05 | R66: =MAX(TechData_R0!F80,1) -> 20.940353 | T66: 5
A67: UC_GrowthOfCOAUP71 | B67: =TechData_R0!B83 -> MINCSAPLU1 | E67: CAP, GROWTH | G67: UP | H67: =TechData_R0!G83 -> 1.05 | I67: =H67 -> 1.05 | J67: =I67 -> 1.05 | K67: =J67 -> 1.05 | L67: =K67 -> 1.05 | M67: =L67 -> 1.05 | N67: =M67 -> 1.05 | O67: =N67 -> 1.05 | P67: =O67 -> 1.05 | Q67: =P67 -> 1.05 | R67: =MAX(TechData_R0!F82,1) -> 1 | T67: 5
A68: UC_GrowthOfCOAUP72 | B68: =TechData_R0!B84 -> MINCSAPLU2 | E68: CAP, GROWTH | G68: UP | H68: =TechData_R0!G84 -> 1.05 | I68: =H68 -> 1.05 | J68: =I68 -> 1.05 | K68: =J68 -> 1.05 | L68: =K68 -> 1.05 | M68: =L68 -> 1.05 | N68: =M68 -> 1.05 | O68: =N68 -> 1.05 | P68: =O68 -> 1.05 | Q68: =P68 -> 1.05 | R68: =MAX(TechData_R0!F83,1) -> 1 | T68: 5
A69: UC_GrowthOfCOAUP73 | B69: =TechData_R0!B85 -> MINCSAPLU3 | E69: CAP, GROWTH | G69: UP | H69: =TechData_R0!G85 -> 1.05 | I69: =H69 -> 1.05 | J69: =I69 -> 1.05 | K69: =J69 -> 1.05 | L69: =K69 -> 1.05 | M69: =L69 -> 1.05 | N69: =M69 -> 1.05 | O69: =N69 -> 1.05 | P69: =O69 -> 1.05 | Q69: =P69 -> 1.05 | R69: =MAX(TechData_R0!F84,1) -> 1 | T69: 5
A70: UC_GrowthOfCOAUP74 | B70: =TechData_R0!B86 -> MINCSAPLU4 | E70: CAP, GROWTH | G70: UP | H70: =TechData_R0!G86 -> 1.05 | I70: =H70 -> 1.05 | J70: =I70 -> 1.05 | K70: =J70 -> 1.05 | L70: =K70 -> 1.05 | M70: =L70 -> 1.05 | N70: =M70 -> 1.05 | O70: =N70 -> 1.05 | P70: =O70 -> 1.05 | Q70: =P70 -> 1.05 | R70: =MAX(TechData_R0!F85,1) -> 1 | T70: 5
A71: UC_GrowthOfCOAUP75 | B71: =TechData_R0!B87 -> MINCSAPLU5 | E71: CAP, GROWTH | G71: UP | H71: =TechData_R0!G87 -> 1.05 | I71: =H71 -> 1.05 | J71: =I71 -> 1.05 | K71: =J71 -> 1.05 | L71: =K71 -> 1.05 | M71: =L71 -> 1.05 | N71: =M71 -> 1.05 | O71: =N71 -> 1.05 | P71: =O71 -> 1.05 | Q71: =P71 -> 1.05 | R71: =MAX(TechData_R0!F86,1) -> 1 | T71: 5
A72: UC_GrowthOfCOAUP76 | B72: =TechData_R0!B88 -> MINCSAPLU6 | E72: CAP, GROWTH | G72: UP | H72: =TechData_R0!G88 -> 1.05 | I72: =H72 -> 1.05 | J72: =I72 -> 1.05 | K72: =J72 -> 1.05 | L72: =K72 -> 1.05 | M72: =L72 -> 1.05 | N72: =M72 -> 1.05 | O72: =N72 -> 1.05 | P72: =O72 -> 1.05 | Q72: =P72 -> 1.05 | R72: =MAX(TechData_R0!F87,1) -> 2.8064405 | T72: 5
A73: UC_GrowthOfCOAUP78 | B73: =TechData_R0!B90 -> MINCSABLU1 | E73: CAP, GROWTH | G73: UP | H73: =TechData_R0!G90 -> 1.05 | I73: =H73 -> 1.05 | J73: =I73 -> 1.05 | K73: =J73 -> 1.05 | L73: =K73 -> 1.05 | M73: =L73 -> 1.05 | N73: =M73 -> 1.05 | O73: =N73 -> 1.05 | P73: =O73 -> 1.05 | Q73: =P73 -> 1.05 | R73: =MAX(TechData_R0!F89,1) -> 1 | T73: 5
A74: UC_GrowthOfCOAUP79 | B74: =TechData_R0!B91 -> MINCSABLU2 | E74: CAP, GROWTH | G74: UP | H74: =TechData_R0!G91 -> 1.05 | I74: =H74 -> 1.05 | J74: =I74 -> 1.05 | K74: =J74 -> 1.05 | L74: =K74 -> 1.05 | M74: =L74 -> 1.05 | N74: =M74 -> 1.05 | O74: =N74 -> 1.05 | P74: =O74 -> 1.05 | Q74: =P74 -> 1.05 | R74: =MAX(TechData_R0!F90,1) -> 1 | T74: 5
A75: UC_GrowthOfCOAUP80 | B75: =TechData_R0!B92 -> MINCSABLU3 | E75: CAP, GROWTH | G75: UP | H75: =TechData_R0!G92 -> 1.05 | I75: =H75 -> 1.05 | J75: =I75 -> 1.05 | K75: =J75 -> 1.05 | L75: =K75 -> 1.05 | M75: =L75 -> 1.05 | N75: =M75 -> 1.05 | O75: =N75 -> 1.05 | P75: =O75 -> 1.05 | Q75: =P75 -> 1.05 | R75: =MAX(TechData_R0!F91,1) -> 1 | T75: 5
A76: UC_GrowthOfCOAUP81 | B76: =TechData_R0!B93 -> MINCSABLU4 | E76: CAP, GROWTH | G76: UP | H76: =TechData_R0!G93 -> 1.05 | I76: =H76 -> 1.05 | J76: =I76 -> 1.05 | K76: =J76 -> 1.05 | L76: =K76 -> 1.05 | M76: =L76 -> 1.05 | N76: =M76 -> 1.05 | O76: =N76 -> 1.05 | P76: =O76 -> 1.05 | Q76: =P76 -> 1.05 | R76: =MAX(TechData_R0!F92,1) -> 1 | T76: 5
A77: UC_GrowthOfCOAUP82 | B77: =TechData_R0!B94 -> MINCSABLU5 | E77: CAP, GROWTH | G77: UP | H77: =TechData_R0!G94 -> 1.05 | I77: =H77 -> 1.05 | J77: =I77 -> 1.05 | K77: =J77 -> 1.05 | L77: =K77 -> 1.05 | M77: =L77 -> 1.05 | N77: =M77 -> 1.05 | O77: =N77 -> 1.05 | P77: =O77 -> 1.05 | Q77: =P77 -> 1.05 | R77: =MAX(TechData_R0!F93,1) -> 1 | T77: 5
A78: UC_GrowthOfCOAUP83 | B78: =TechData_R0!B95 -> MINCSABLU6 | E78: CAP, GROWTH | G78: UP | H78: =TechData_R0!G95 -> 1.05 | I78: =H78 -> 1.05 | J78: =I78 -> 1.05 | K78: =J78 -> 1.05 | L78: =K78 -> 1.05 | M78: =L78 -> 1.05 | N78: =M78 -> 1.05 | O78: =N78 -> 1.05 | P78: =O78 -> 1.05 | Q78: =P78 -> 1.05 | R78: =MAX(TechData_R0!F94,1) -> 1 | T78: 5
A79: UC_GrowthOfCOAUP85 | B79: =TechData_R0!B97 -> MINCSABLS1 | E79: CAP, GROWTH | G79: UP | H79: =TechData_R0!G97 -> 1.05 | I79: =H79 -> 1.05 | J79: =I79 -> 1.05 | K79: =J79 -> 1.05 | L79: =K79 -> 1.05 | M79: =L79 -> 1.05 | N79: =M79 -> 1.05 | O79: =N79 -> 1.05 | P79: =O79 -> 1.05 | Q79: =P79 -> 1.05 | R79: =MAX(TechData_R0!F96,1) -> 1 | T79: 5
A80: UC_GrowthOfCOAUP86 | B80: =TechData_R0!B98 -> MINCSABLS2 | E80: CAP, GROWTH | G80: UP | H80: =TechData_R0!G98 -> 1.05 | I80: =H80 -> 1.05 | J80: =I80 -> 1.05 | K80: =J80 -> 1.05 | L80: =K80 -> 1.05 | M80: =L80 -> 1.05 | N80: =M80 -> 1.05 | O80: =N80 -> 1.05 | P80: =O80 -> 1.05 | Q80: =P80 -> 1.05 | R80: =MAX(TechData_R0!F97,1) -> 1 | T80: 5
A81: UC_GrowthOfCOAUP87 | B81: =TechData_R0!B99 -> MINCSABLS3 | E81: CAP, GROWTH | G81: UP | H81: =TechData_R0!G99 -> 1.05 | I81: =H81 -> 1.05 | J81: =I81 -> 1.05 | K81: =J81 -> 1.05 | L81: =K81 -> 1.05 | M81: =L81 -> 1.05 | N81: =M81 -> 1.05 | O81: =N81 -> 1.05 | P81: =O81 -> 1.05 | Q81: =P81 -> 1.05 | R81: =MAX(TechData_R0!F98,1) -> 1 | T81: 5
A82: UC_GrowthOfCOAUP88 | B82: =TechData_R0!B100 -> MINCSABLS4 | E82: CAP, GROWTH | G82: UP | H82: =TechData_R0!G100 -> 1.05 | I82: =H82 -> 1.05 | J82: =I82 -> 1.05 | K82: =J82 -> 1.05 | L82: =K82 -> 1.05 | M82: =L82 -> 1.05 | N82: =M82 -> 1.05 | O82: =N82 -> 1.05 | P82: =O82 -> 1.05 | Q82: =P82 -> 1.05 | R82: =MAX(TechData_R0!F99,1) -> 1 | T82: 5
A83: UC_GrowthOfCOAUP89 | B83: =TechData_R0!B101 -> MINCSABLS5 | E83: CAP, GROWTH | G83: UP | H83: =TechData_R0!G101 -> 1.05 | I83: =H83 -> 1.05 | J83: =I83 -> 1.05 | K83: =J83 -> 1.05 | L83: =K83 -> 1.05 | M83: =L83 -> 1.05 | N83: =M83 -> 1.05 | O83: =N83 -> 1.05 | P83: =O83 -> 1.05 | Q83: =P83 -> 1.05 | R83: =MAX(TechData_R0!F100,1) -> 1 | T83: 5
A84: UC_GrowthOfCOAUP90 | B84: =TechData_R0!B102 -> MINCSABLS6 | E84: CAP, GROWTH | G84: UP | H84: =TechData_R0!G102 -> 1.05 | I84: =H84 -> 1.05 | J84: =I84 -> 1.05 | K84: =J84 -> 1.05 | L84: =K84 -> 1.05 | M84: =L84 -> 1.05 | N84: =M84 -> 1.05 | O84: =N84 -> 1.05 | P84: =O84 -> 1.05 | Q84: =P84 -> 1.05 | R84: =MAX(TechData_R0!F101,1) -> 1 | T84: 5
A85: UC_GrowthOfCOAUP92 | B85: =TechData_R0!B104 -> MINCSABMU1 | E85: CAP, GROWTH | G85: UP | H85: =TechData_R0!G104 -> 1.05 | I85: =H85 -> 1.05 | J85: =I85 -> 1.05 | K85: =J85 -> 1.05 | L85: =K85 -> 1.05 | M85: =L85 -> 1.05 | N85: =M85 -> 1.05 | O85: =N85 -> 1.05 | P85: =O85 -> 1.05 | Q85: =P85 -> 1.05 | R85: =MAX(TechData_R0!F103,1) -> 1 | T85: 5
A86: UC_GrowthOfCOAUP93 | B86: =TechData_R0!B105 -> MINCSABMU2 | E86: CAP, GROWTH | G86: UP | H86: =TechData_R0!G105 -> 1.05 | I86: =H86 -> 1.05 | J86: =I86 -> 1.05 | K86: =J86 -> 1.05 | L86: =K86 -> 1.05 | M86: =L86 -> 1.05 | N86: =M86 -> 1.05 | O86: =N86 -> 1.05 | P86: =O86 -> 1.05 | Q86: =P86 -> 1.05 | R86: =MAX(TechData_R0!F104,1) -> 1 | T86: 5
A87: UC_GrowthOfCOAUP94 | B87: =TechData_R0!B106 -> MINCSABMU3 | E87: CAP, GROWTH | G87: UP | H87: =TechData_R0!G106 -> 1.05 | I87: =H87 -> 1.05 | J87: =I87 -> 1.05 | K87: =J87 -> 1.05 | L87: =K87 -> 1.05 | M87: =L87 -> 1.05 | N87: =M87 -> 1.05 | O87: =N87 -> 1.05 | P87: =O87 -> 1.05 | Q87: =P87 -> 1.05 | R87: =MAX(TechData_R0!F105,1) -> 1 | T87: 5
A88: UC_GrowthOfCOAUP95 | B88: =TechData_R0!B107 -> MINCSABMU4 | E88: CAP, GROWTH | G88: UP | H88: =TechData_R0!G107 -> 1.05 | I88: =H88 -> 1.05 | J88: =I88 -> 1.05 | K88: =J88 -> 1.05 | L88: =K88 -> 1.05 | M88: =L88 -> 1.05 | N88: =M88 -> 1.05 | O88: =N88 -> 1.05 | P88: =O88 -> 1.05 | Q88: =P88 -> 1.05 | R88: =MAX(TechData_R0!F106,1) -> 1 | T88: 5
A89: UC_GrowthOfCOAUP96 | B89: =TechData_R0!B108 -> MINCSABMU5 | E89: CAP, GROWTH | G89: UP | H89: =TechData_R0!G108 -> 1.05 | I89: =H89 -> 1.05 | J89: =I89 -> 1.05 | K89: =J89 -> 1.05 | L89: =K89 -> 1.05 | M89: =L89 -> 1.05 | N89: =M89 -> 1.05 | O89: =N89 -> 1.05 | P89: =O89 -> 1.05 | Q89: =P89 -> 1.05 | R89: =MAX(TechData_R0!F107,1) -> 1 | T89: 5
A90: UC_GrowthOfCOAUP97 | B90: =TechData_R0!B109 -> MINCSABMU6 | E90: CAP, GROWTH | G90: UP | H90: =TechData_R0!G109 -> 1.05 | I90: =H90 -> 1.05 | J90: =I90 -> 1.05 | K90: =J90 -> 1.05 | L90: =K90 -> 1.05 | M90: =L90 -> 1.05 | N90: =M90 -> 1.05 | O90: =N90 -> 1.05 | P90: =O90 -> 1.05 | Q90: =P90 -> 1.05 | R90: =MAX(TechData_R0!F108,1) -> 1 | T90: 5
A91: UC_GrowthOfCOAUP99 | B91: =TechData_R0!B111 -> MINCSABMS1 | E91: CAP, GROWTH | G91: UP | H91: =TechData_R0!G111 -> 1.05 | I91: =H91 -> 1.05 | J91: =I91 -> 1.05 | K91: =J91 -> 1.05 | L91: =K91 -> 1.05 | M91: =L91 -> 1.05 | N91: =M91 -> 1.05 | O91: =N91 -> 1.05 | P91: =O91 -> 1.05 | Q91: =P91 -> 1.05 | R91: =MAX(TechData_R0!F110,1) -> 1 | T91: 5
A92: UC_GrowthOfCOAUP100 | B92: =TechData_R0!B112 -> MINCSABMS2 | E92: CAP, GROWTH | G92: UP | H92: =TechData_R0!G112 -> 1.05 | I92: =H92 -> 1.05 | J92: =I92 -> 1.05 | K92: =J92 -> 1.05 | L92: =K92 -> 1.05 | M92: =L92 -> 1.05 | N92: =M92 -> 1.05 | O92: =N92 -> 1.05 | P92: =O92 -> 1.05 | Q92: =P92 -> 1.05 | R92: =MAX(TechData_R0!F111,1) -> 1 | T92: 5
A93: UC_GrowthOfCOAUP101 | B93: =TechData_R0!B113 -> MINCSABMS3 | E93: CAP, GROWTH | G93: UP | H93: =TechData_R0!G113 -> 1.05 | I93: =H93 -> 1.05 | J93: =I93 -> 1.05 | K93: =J93 -> 1.05 | L93: =K93 -> 1.05 | M93: =L93 -> 1.05 | N93: =M93 -> 1.05 | O93: =N93 -> 1.05 | P93: =O93 -> 1.05 | Q93: =P93 -> 1.05 | R93: =MAX(TechData_R0!F112,1) -> 1 | T93: 5
A94: UC_GrowthOfCOAUP102 | B94: =TechData_R0!B114 -> MINCSABMS4 | E94: CAP, GROWTH | G94: UP | H94: =TechData_R0!G114 -> 1.05 | I94: =H94 -> 1.05 | J94: =I94 -> 1.05 | K94: =J94 -> 1.05 | L94: =K94 -> 1.05 | M94: =L94 -> 1.05 | N94: =M94 -> 1.05 | O94: =N94 -> 1.05 | P94: =O94 -> 1.05 | Q94: =P94 -> 1.05 | R94: =MAX(TechData_R0!F113,1) -> 1 | T94: 5
A95: UC_GrowthOfCOAUP103 | B95: =TechData_R0!B115 -> MINCSABMS5 | E95: CAP, GROWTH | G95: UP | H95: =TechData_R0!G115 -> 1.05 | I95: =H95 -> 1.05 | J95: =I95 -> 1.05 | K95: =J95 -> 1.05 | L95: =K95 -> 1.05 | M95: =L95 -> 1.05 | N95: =M95 -> 1.05 | O95: =N95 -> 1.05 | P95: =O95 -> 1.05 | Q95: =P95 -> 1.05 | R95: =MAX(TechData_R0!F114,1) -> 1 | T95: 5
A96: UC_GrowthOfCOAUP104 | B96: =TechData_R0!B116 -> MINCSABMS6 | E96: CAP, GROWTH | G96: UP | H96: =TechData_R0!G116 -> 1.05 | I96: =H96 -> 1.05 | J96: =I96 -> 1.05 | K96: =J96 -> 1.05 | L96: =K96 -> 1.05 | M96: =L96 -> 1.05 | N96: =M96 -> 1.05 | O96: =N96 -> 1.05 | P96: =O96 -> 1.05 | Q96: =P96 -> 1.05 | R96: =MAX(TechData_R0!F115,1) -> 2.1171496 | T96: 5
A97: UC_GrowthOfCOAUP106 | B97: =TechData_R0!B118 -> MINCEIBMU1 | E97: CAP, GROWTH | G97: UP | H97: =TechData_R0!G118 -> 1.05 | I97: =H97 -> 1.05 | J97: =I97 -> 1.05 | K97: =J97 -> 1.05 | L97: =K97 -> 1.05 | M97: =L97 -> 1.05 | N97: =M97 -> 1.05 | O97: =N97 -> 1.05 | P97: =O97 -> 1.05 | Q97: =P97 -> 1.05 | R97: =MAX(TechData_R0!F117,1) -> 1 | T97: 5
A98: UC_GrowthOfCOAUP107 | B98: =TechData_R0!B119 -> MINCEIBMU2 | E98: CAP, GROWTH | G98: UP | H98: =TechData_R0!G119 -> 1.05 | I98: =H98 -> 1.05 | J98: =I98 -> 1.05 | K98: =J98 -> 1.05 | L98: =K98 -> 1.05 | M98: =L98 -> 1.05 | N98: =M98 -> 1.05 | O98: =N98 -> 1.05 | P98: =O98 -> 1.05 | Q98: =P98 -> 1.05 | R98: =MAX(TechData_R0!F118,1) -> 1 | T98: 5
A99: UC_GrowthOfCOAUP108 | B99: =TechData_R0!B120 -> MINCEIBMU3 | E99: CAP, GROWTH | G99: UP | H99: =TechData_R0!G120 -> 1.05 | I99: =H99 -> 1.05 | J99: =I99 -> 1.05 | K99: =J99 -> 1.05 | L99: =K99 -> 1.05 | M99: =L99 -> 1.05 | N99: =M99 -> 1.05 | O99: =N99 -> 1.05 | P99: =O99 -> 1.05 | Q99: =P99 -> 1.05 | R99: =MAX(TechData_R0!F119,1) -> 1 | T99: 5
A100: UC_GrowthOfCOAUP109 | B100: =TechData_R0!B121 -> MINCEIBMU4 | E100: CAP, GROWTH | G100: UP | H100: =TechData_R0!G121 -> 1.05 | I100: =H100 -> 1.05 | J100: =I100 -> 1.05 | K100: =J100 -> 1.05 | L100: =K100 -> 1.05 | M100: =L100 -> 1.05 | N100: =M100 -> 1.05 | O100: =N100 -> 1.05 | P100: =O100 -> 1.05 | Q100: =P100 -> 1.05 | R100: =MAX(TechData_R0!F120,1) -> 1 | T100: 5
A101: UC_GrowthOfCOAUP110 | B101: =TechData_R0!B122 -> MINCEIBMU5 | E101: CAP, GROWTH | G101: UP | H101: =TechData_R0!G122 -> 1.05 | I101: =H101 -> 1.05 | J101: =I101 -> 1.05 | K101: =J101 -> 1.05 | L101: =K101 -> 1.05 | M101: =L101 -> 1.05 | N101: =M101 -> 1.05 | O101: =N101 -> 1.05 | P101: =O101 -> 1.05 | Q101: =P101 -> 1.05 | R101: =MAX(TechData_R0!F121,1) -> 1 | T101: 5
...

Sheet TechData_R0
A1: TechData | B1: R0 | J1: * | W1: * | X1: *
N4: 0.9
E5: START | F5: GROWTH_TIDr = right hand side of the growth constraint | G5: GROWTHr = growth rate | H5: GROWTHr | I5: GROWTHr | J5: DECAYr = decay rate of the production | K5: DECAYr | L5: COST | M5: COST | N5: COST | O5: COST | P5: COST | Q5: COST | R5: COST | S5: COST | T5: COST | U5: COST | V5: CUM | W5: BOUND(LO)Or | X5: BOUND(UP)Or
A11: Region | B11: TechName | C11: *TechDesc | D11: CommOUT | E11: *TID | F11: *TID | G11: *2010 | H11: *2015-2020 | I11: *2025-2055 | J11: *2010 | K11: *2010-2055 | L11: COST~2010 | M11: COST~2015 | N11: COST~2020 | O11: COST~2025 | P11: COST~2030 | Q11: COST~2035 | R11: COST~2040 | S11: COST~2045 | T11: COST~2050 | U11: COST~2055 | V11: ACT_BND~LO~2010 | W11: ACT_BND~UP~2005 | X11: ACT_BND~UP~2010
A12: *Coal minning
A13: R0 | B13: MINCNAPMU1 | C13: MIN.COA.NA.PMU.1 | D13: =CONCATENATE(MID(B13,4,6),"1") -> CNAPMU1 | E13: 2010 | G13: 1.05 | H13: 1.05 | I13: 1.05 | J13: 1.05 | K13: 1.005 | L13: =L15*'Production Steps'!$O$10 -> 2.4213307 | M13: =M15*'Production Steps'!$O$10 -> 2.9001275 | N13: =N15*'Production Steps'!$O$10 -> 3.3234457 | O13: =O15*'Production Steps'!$O$10 -> 3.9037571 | P13: =P15*'Production Steps'!$O$10 -> 4.2530556 | Q13: =Q15*'Production Steps'!$O$10 -> 4.6228547 | R13: =R15*'Production Steps'!$O$10 -> 5.0148483 | S13: =S15*'Production Steps'!$O$10 -> 5.4400809 | ... U13: =U15*'Production Steps'!$O$10 -> 6.4017761 | V13: =X13*0.8 -> 222.70512 | W13: ='Production Steps'!H7*1.1 -> 53.414848 | X13: ='Production Steps'!I7*1.1 -> 278.3814
B14: MINCNAPMU2 | C14: MIN.COA.NA.PMU.2 | D14: =CONCATENATE(MID(B14,4,6),"1") -> CNAPMU1 | E14: 2010 | G14: 1.05 | H14: 1.05 | I14: 1.05 | J14: 1.05 | K14: 1.005 | L14: =L15*'Production Steps'!$O$11 -> 2.7460091 | M14: =M15*'Production Steps'!$O$11 -> 3.2890082 | N14: =N15*'Production Steps'!$O$11 -> 3.7690896 | O14: =O15*'Production Steps'!$O$11 -> 4.4272154 | P14: =P15*'Production Steps'!$O$11 -> 4.8233517 | Q14: =Q15*'Production Steps'!$O$11 -> 5.2427375 | R14: =R15*'Production Steps'!$O$11 -> 5.6872939 | S14: =S15*'Production Steps'!$O$11 -> 6.1695463 | ... U14: =U15*'Production Steps'!$O$11 -> 7.2601961 | V14: =X14*0.8 -> 218.25102 | W14: ='Production Steps'!H8*1.1 -> 52.346551 | X14: ='Production Steps'!I8*1.1 -> 272.81377
B15: MINCNAPMU3 | C15: MIN.COA.NA.PMU.3 | D15: =CONCATENATE(MID(B15,4,6),"1") -> CNAPMU1 | E15: 2010 | G15: 1.05 | H15: 1.05 | I15: 1.05 | J15: 1.05 | K15: 1.005 | L15: ='AEO Coal Prices'!M7*'Production Steps'!$Q$17*$N$4 -> 2.7515122 | M15: ='AEO Coal Prices'!N7*'Production Steps'!$Q$17*$N$4 -> 3.2955994 | N15: ='AEO Coal Prices'!O7*'Production Steps'!$Q$17*$N$4 -> 3.7766429 | O15: ='AEO Coal Prices'!P7*'Production Steps'!$Q$17*$N$4 -> 4.4360876 | P15: ='AEO Coal Prices'!Q7*'Production Steps'!$Q$17*$N$4 -> 4.8330177 | Q15: ='AEO Coal Prices'!R7*'Production Steps'!$Q$17*$N$4 -> 5.253244 | R15: ='AEO Coal Prices'!S7*'Production Steps'!$Q$17*$N$4 -> 5.6986913 | S15: =R15*(1+(R15-Q15)/Q15) -> 6.1819102 | T15: =S15*(1+(S15-R15)/R15) -> 6.7061035 | U15: =T15*(1+(T15-S15)/S15) -> 7.2747456 | V15: =X15*0.8 -> 4.4541024 | W15: ='Production Steps'!H9*1.1 -> 1.068297 | X15: ='Production Steps'!I9*1.1 -> 5.567628
B16: MINCNAPMU4 | C16: MIN.COA.NA.PMU.4 | D16: =CONCATENATE(MID(B16,4,6),"1") -> CNAPMU1 | E16: 2010 | G16: 1.05 | H16: 1.05 | I16: 1.05 | J16: 1.05 | K16: 1.005 | L16: =L15*'Production Steps'!$O$13 -> 2.7597667 | M16: =M15*'Production Steps'!$O$13 -> 3.3054862 | N16: =N15*'Production Steps'!$O$13 -> 3.7879728 | O16: =O15*'Production Steps'!$O$13 -> 4.4493958 | P16: =P15*'Production Steps'!$O$13 -> 4.8475168 | Q16: =Q15*'Production Steps'!$O$13 -> 5.2690037 | R16: =R15*'Production Steps'!$O$13 -> 5.7157873 | S16: =S15*'Production Steps'!$O$13 -> 6.2004559 | ... U16: =U15*'Production Steps'!$O$13 -> 7.2965698 | V16: =X16*0.8 -> 4.4541024 | W16: ='Production Steps'!H10*1.1 -> 1.068297 | X16: ='Production Steps'!I10*1.1 -> 5.567628
B17: MINCNAPMU5 | C17: MIN.COA.NA.PMU.5 | D17: =CONCATENATE(MID(B17,4,6),"1") -> CNAPMU1 | E17: 2010 | F17: =X17*0.1 -> 5.0108652 | G17: 1.05 | H17: 1.05 | I17: 1.05 | J17: 1.05 | K17: 1.005 | L17: =L15*'Production Steps'!$O$14 -> 3.0816936 | M17: =M15*'Production Steps'!$O$14 -> 3.6910714 | N17: =N15*'Production Steps'!$O$14 -> 4.22984 | O17: =O15*'Production Steps'!$O$14 -> 4.9684181 | P17: =P15*'Production Steps'!$O$14 -> 5.4129798 | Q17: =Q15*'Production Steps'!$O$14 -> 5.8836332 | R17: =R15*'Production Steps'!$O$14 -> 6.3825342 | S17: =S15*'Production Steps'!$O$14 -> 6.9237394 | ... U17: =U15*'Production Steps'!$O$14 -> 8.147715 | W17: ='Production Steps'!H11*1.1 -> 9.6146726 | X17: ='Production Steps'!I11*1.1 -> 50.108652
B18: MINCNAPMU6 | C18: MIN.COA.NA.PMU.6 | D18: =CONCATENATE(MID(B18,4,6),"1") -> CNAPMU1 | E18: 2010 | F18: =X18*0.1 -> 5.567628 | G18: 1.05 | H18: 1.05 | I18: 1.05 | J18: 1.05 | K18: 1.005 | L18: =L15*'Production Steps'!$O$15 -> 4.2098136 | M18: =M15*'Production Steps'!$O$15 -> 5.0422672 | N18: =N15*'Production Steps'!$O$15 -> 5.7782636 | O18: =O15*'Production Steps'!$O$15 -> 6.787214 | P18: =P15*'Production Steps'!$O$15 -> 7.3945171 | Q18: =Q15*'Production Steps'!$O$15 -> 8.0374633 | R18: =R15*'Production Steps'!$O$15 -> 8.7189976 | S18: =S15*'Production Steps'!$O$15 -> 9.4583225 | ... U18: =U15*'Production Steps'!$O$15 -> 11.130361 | W18: ='Production Steps'!H12*1.1 -> 10.68297 | X18: ='Production Steps'!I12*1.1 -> 55.67628
A19: *
A20: R0 | B20: MINCNABMU1 | C20: MIN.COA.NA.BMU.1 | D20: =CONCATENATE(MID(B20,4,6),"1") -> CNABMU1 | E20: 2010 | G20: 1.05 | H20: 1.05 | I20: 1.05 | J20: 1.05 | K20: 1.05 | L20: =L22*'Production Steps'!$O$10 -> 1.6252417 | M20: =M22*'Production Steps'!$O$10 -> 1.7986292 | N20: =N22*'Production Steps'!$O$10 -> 1.958612 | O20: =O22*'Production Steps'!$O$10 -> 2.0465499 | P20: =P22*'Production Steps'!$O$10 -> 2.1387409 | Q20: =Q22*'Production Steps'!$O$10 -> 2.2263202 | R20: =R22*'Production Steps'!$O$10 -> 2.3239259 | S20: =S22*'Production Steps'!$O$10 -> 2.4258109 | ... U20: =U22*'Production Steps'!$O$10 -> 2.6431771 | V20: =X20*0.8 -> 317.62849 | W20: ='Production Steps'!H14*1.1*'Production Steps'!K14 -> 812.58462 | X20: ='Production Steps'!I14*1.1*'Production Steps'!K14 -> 397.03561
B21: MINCNABMU2 | C21: MIN.COA.NA.BMU.2 | D21: =CONCATENATE(MID(B21,4,6),"1") -> CNABMU1 | E21: 2010 | G21: 1.05 | H21: 1.05 | I21: 1.05 | J21: 1.05 | K21: 1.05 | L21: =L22*'Production Steps'!$O$11 -> 1.8431719 | M21: =M22*'Production Steps'!$O$11 -> 2.0398091 | N21: =N22*'Production Steps'!$O$11 -> 2.221244 | O21: =O22*'Production Steps'!$O$11 -> 2.3209736 | P21: =P22*'Production Steps'!$O$11 -> 2.4255266 | Q21: =Q22*'Production Steps'!$O$11 -> 2.5248495 | R21: =R22*'Production Steps'!$O$11 -> 2.6355433 | S21: =S22*'Production Steps'!$O$11 -> 2.7510901 | ... U21: =U22*'Production Steps'!$O$11 -> 2.9976031 | V21: =X21*0.8 -> 311.27592 | W21: ='Production Steps'!H15*1.1*'Production Steps'!K15 -> 796.33292 | X21: ='Production Steps'!I15*1.1*'Production Steps'!K15 -> 389.0949
B22: MINCNABMU3 | C22: MIN.COA.NA.BMU.3 | D22: =CONCATENATE(MID(B22,4,6),"1") -> CNABMU1 | E22: 2010 | G22: 1.05 | H22: 1.05 | I22: 1.05 | J22: 1.05 | K22: 1.05 | L22: ='AEO Coal Prices'!M8*'Production Steps'!$Q$17*$N$4 -> 1.8468656 | M22: ='AEO Coal Prices'!N8*'Production Steps'!$Q$17*$N$4 -> 2.0438969 | N22: ='AEO Coal Prices'!O8*'Production Steps'!$Q$17*$N$4 -> 2.2256954 | O22: ='AEO Coal Prices'!P8*'Production Steps'!$Q$17*$N$4 -> 2.3256249 | P22: ='AEO Coal Prices'!Q8*'Production Steps'!$Q$17*$N$4 -> 2.4303874 | Q22: ='AEO Coal Prices'!R8*'Production Steps'!$Q$17*$N$4 -> 2.5299093 | R22: ='AEO Coal Prices'!S8*'Production Steps'!$Q$17*$N$4 -> 2.6408249 | S22: =R22*(1+(R22-Q22)/Q22) -> 2.7566033 | T22: =S22*(1+(S22-R22)/R22) -> 2.8774576 | U22: =T22*(1+(T22-S22)/S22) -> 3.0036103 | V22: =X22*0.8 -> 6.3525698 | W22: ='Production Steps'!H16*1.1*'Production Steps'!K16 -> 16.251692 | X22: ='Production Steps'!I16*1.1*'Production Steps'!K16 -> 7.9407123
B23: MINCNABMU4 | C23: MIN.COA.NA.BMU.4 | D23: =CONCATENATE(MID(B23,4,6),"1") -> CNABMU1 | E23: 2010 | G23: 1.05 | H23: 1.05 | I23: 1.05 | J23: 1.05 | K23: 1.05 | L23: =L22*'Production Steps'!$O$13 -> 1.8524062 | M23: =M22*'Production Steps'!$O$13 -> 2.0500286 | N23: =N22*'Production Steps'!$O$13 -> 2.2323725 | O23: =O22*'Production Steps'!$O$13 -> 2.3326018 | P23: =P22*'Production Steps'!$O$13 -> 2.4376786 | Q23: =Q22*'Production Steps'!$O$13 -> 2.537499 | R23: =R22*'Production Steps'!$O$13 -> 2.6487474 | S23: =S22*'Production Steps'!$O$13 -> 2.7648731 | ... U23: =U22*'Production Steps'!$O$13 -> 3.0126212 | V23: =X23*0.8 -> 6.3525698 | W23: ='Production Steps'!H17*1.1*'Production Steps'!K17 -> 16.251692 | X23: ='Production Steps'!I17*1.1*'Production Steps'!K17 -> 7.9407123
B24: MINCNABMU5 | C24: MIN.COA.NA.BMU.5 | D24: =CONCATENATE(MID(B24,4,6),"1") -> CNABMU1 | E24: 2010 | F24: =X24*0.1 -> 7.146641 | G24: 1.05 | H24: 1.05 | I24: 1.05 | J24: 1.05 | K24: 1.05 | L24: =L22*'Production Steps'!$O$14 -> 2.0684895 | M24: =M22*'Production Steps'!$O$14 -> 2.2891645 | N24: =N22*'Production Steps'!$O$14 -> 2.4927788 | O24: =O22*'Production Steps'!$O$14 -> 2.6046999 | P24: =P22*'Production Steps'!$O$14 -> 2.7220339 | Q24: =Q22*'Production Steps'!$O$14 -> 2.8334984 | R24: =R22*'Production Steps'!$O$14 -> 2.9577239 | S24: =S22*'Production Steps'!$O$14 -> 3.0873957 | ... U24: =U22*'Production Steps'!$O$14 -> 3.3640436 | W24: ='Production Steps'!H18*1.1*'Production Steps'!K18 -> 146.26523 | X24: ='Production Steps'!I18*1.1*'Production Steps'!K18 -> 71.46641
B25: MINCNABMU6 | C25: MIN.COA.NA.BMU.6 | D25: =CONCATENATE(MID(B25,4,6),"1") -> CNABMU1 | E25: 2010 | F25: =X25*0.1 -> 7.9407123 | G25: 1.05 | H25: 1.05 | I25: 1.05 | J25: 1.05 | K25: 1.05 | L25: =L22*'Production Steps'!$O$15 -> 2.8257044 | M25: =M22*'Production Steps'!$O$15 -> 3.1271622 | N25: =N22*'Production Steps'!$O$15 -> 3.405314 | O25: =O22*'Production Steps'!$O$15 -> 3.5582061 | P25: =P22*'Production Steps'!$O$15 -> 3.7184927 | Q25: =Q22*'Production Steps'!$O$15 -> 3.8707612 | R25: =R22*'Production Steps'!$O$15 -> 4.0404622 | S25: =S22*'Production Steps'!$O$15 -> 4.2176031 | ... U25: =U22*'Production Steps'!$O$15 -> 4.5955238 | W25: ='Production Steps'!H19*1.1*'Production Steps'!K19 -> 162.51692 | X25: ='Production Steps'!I19*1.1*'Production Steps'!K19 -> 79.407123
A26: *
A27: R0 | B27: MINCNABMS1 | C27: MIN.COA.NA.BMS.1 | D27: =CONCATENATE(MID(B27,4,6),"1") -> CNABMS1 | E27: 2010 | G27: 1.05 | H27: 1.05 | I27: 1.05 | J27: 1.05 | K27: 1.05 | L27: =L29*'Production Steps'!$O$10 -> 1.6252417 | M27: =M29*'Production Steps'!$O$10 -> 1.7986292 | N27: =N29*'Production Steps'!$O$10 -> 1.958612 | O27: =O29*'Production Steps'!$O$10 -> 2.0465499 | P27: =P29*'Production Steps'!$O$10 -> 2.1387409 | Q27: =Q29*'Production Steps'!$O$10 -> 2.2263202 | R27: =R29*'Production Steps'!$O$10 -> 2.3239259 | S27: =S29*'Production Steps'!$O$10 -> 2.4258109 | ... U27: =U29*'Production Steps'!$O$10 -> 2.6431771 | V27: =X27*0.8 -> 111.0131 | W27: ='Production Steps'!H14*1.1*'Production Steps'!L14 -> 284.00329 | X27: ='Production Steps'!I14*1.1*'Production Steps'!L14 -> 138.76637
B28: MINCNABMS2 | C28: MIN.COA.NA.BMS.2 | D28: =CONCATENATE(MID(B28,4,6),"1") -> CNABMS1 | E28: 2010 | G28: 1.05 | H28: 1.05 | I28: 1.05 | J28: 1.05 | K28: 1.05 | L28: =L29*'Production Steps'!$O$11 -> 1.8431719 | M28: =M29*'Production Steps'!$O$11 -> 2.0398091 | N28: =N29*'Production Steps'!$O$11 -> 2.221244 | O28: =O29*'Production Steps'!$O$11 -> 2.3209736 | P28: =P29*'Production Steps'!$O$11 -> 2.4255266 | Q28: =Q29*'Production Steps'!$O$11 -> 2.5248495 | R28: =R29*'Production Steps'!$O$11 -> 2.6355433 | S28: =S29*'Production Steps'!$O$11 -> 2.7510901 | ... U28: =U29*'Production Steps'!$O$11 -> 2.9976031 | V28: =X28*0.8 -> 108.79284 | W28: ='Production Steps'!H15*1.1*'Production Steps'!L15 -> 278.32323 | X28: ='Production Steps'!I15*1.1*'Production Steps'!L15 -> 135.99105
B29: MINCNABMS3 | C29: MIN.COA.NA.BMS.3 | D29: =CONCATENATE(MID(B29,4,6),"1") -> CNABMS1 | E29: 2010 | G29: 1.05 | H29: 1.05 | I29: 1.05 | J29: 1.05 | K29: 1.05 | L29: =L22 -> 1.8468656 | M29: =M22 -> 2.0438969 | N29: =N22 -> 2.2256954 | O29: =O22 -> 2.3256249 | P29: =P22 -> 2.4303874 | Q29: =Q22 -> 2.5299093 | R29: =R22 -> 2.6408249 | S29: =R29*(1+(R29-Q29)/Q29) -> 2.7566033 | T29: =S29*(1+(S29-R29)/R29) -> 2.8774576 | U29: =T29*(1+(T29-S29)/S29) -> 3.0036103 | V29: =X29*0.8 -> 2.220262 | W29: ='Production Steps'!H16*1.1*'Production Steps'!L16 -> 5.6800658 | X29: ='Production Steps'!I16*1.1*'Production Steps'!L16 -> 2.7753275
B30: MINCNABMS4 | C30: MIN.COA.NA.BMS.4 | D30: =CONCATENATE(MID(B30,4,6),"1") -> CNABMS1 | E30: 2010 | G30: 1.05 | H30: 1.05 | I30: 1.05 | J30: 1.05 | K30: 1.05 | L30: =L29*'Production Steps'!$O$13 -> 1.8524062 | M30: =M29*'Production Steps'!$O$13 -> 2.0500286 | N30: =N29*'Production Steps'!$O$13 -> 2.2323725 | O30: =O29*'Production Steps'!$O$13 -> 2.3326018 | P30: =P29*'Production Steps'!$O$13 -> 2.4376786 | Q30: =Q29*'Production Steps'!$O$13 -> 2.537499 | R30: =R29*'Production Steps'!$O$13 -> 2.6487474 | S30: =S29*'Production Steps'!$O$13 -> 2.7648731 | ... U30: =U29*'Production Steps'!$O$13 -> 3.0126212 | V30: =X30*0.8 -> 2.220262 | W30: ='Production Steps'!H17*1.1*'Production Steps'!L17 -> 5.6800658 | X30: ='Production Steps'!I17*1.1*'Production Steps'!L17 -> 2.7753275
B31: MINCNABMS5 | C31: MIN.COA.NA.BMS.5 | D31: =CONCATENATE(MID(B31,4,6),"1") -> CNABMS1 | E31: 2010 | F31: =X31*0.1 -> 2.4977947 | G31: 1.05 | H31: 1.05 | I31: 1.05 | J31: 1.05 | K31: 1.05 | L31: =L29*'Production Steps'!$O$14 -> 2.0684895 | M31: =M29*'Production Steps'!$O$14 -> 2.2891645 | N31: =N29*'Production Steps'!$O$14 -> 2.4927788 | O31: =O29*'Production Steps'!$O$14 -> 2.6046999 | P31: =P29*'Production Steps'!$O$14 -> 2.7220339 | Q31: =Q29*'Production Steps'!$O$14 -> 2.8334984 | R31: =R29*'Production Steps'!$O$14 -> 2.9577239 | S31: =S29*'Production Steps'!$O$14 -> 3.0873957 | ... U31: =U29*'Production Steps'!$O$14 -> 3.3640436 | W31: ='Production Steps'!H18*1.1*'Production Steps'!L18 -> 51.120593 | X31: ='Production Steps'!I18*1.1*'Production Steps'!L18 -> 24.977947
B32: MINCNABMS6 | C32: MIN.COA.NA.BMS.6 | D32: =CONCATENATE(MID(B32,4,6),"1") -> CNABMS1 | E32: 2010 | F32: =X32*0.1 -> 2.7753275 | G32: 1.05 | H32: 1.05 | I32: 1.05 | J32: 1.05 | K32: 1.05 | L32: =L29*'Production Steps'!$O$15 -> 2.8257044 | M32: =M29*'Production Steps'!$O$15 -> 3.1271622 | N32: =N29*'Production Steps'!$O$15 -> 3.405314 | O32: =O29*'Production Steps'!$O$15 -> 3.5582061 | P32: =P29*'Production Steps'!$O$15 -> 3.7184927 | Q32: =Q29*'Production Steps'!$O$15 -> 3.8707612 | R32: =R29*'Production Steps'!$O$15 -> 4.0404622 | S32: =S29*'Production Steps'!$O$15 -> 4.2176031 | ... U32: =U29*'Production Steps'!$O$15 -> 4.5955238 | W32: ='Production Steps'!H19*1.1*'Production Steps'!L19 -> 56.800658 | X32: ='Production Steps'!I19*1.1*'Production Steps'!L19 -> 27.753275
A33: *
A34: R0 | B34: MINCNABHU1 | C34: MIN.COA.NA.BHU.1 | D34: =CONCATENATE(MID(B34,4,6),"1") -> CNABHU1 | E34: 2010 | G34: 1.05 | H34: 1.05 | I34: 1.05 | J34: 1.05 | K34: 1.005 | L34: =L36*'Production Steps'!$O$10 -> 1.5963672 | M34: =M36*'Production Steps'!$O$10 -> 1.7470789 | N34: =N36*'Production Steps'!$O$10 -> 1.9351 | O34: =O36*'Production Steps'!$O$10 -> 2.0183163 | P34: =P36*'Production Steps'!$O$10 -> 2.112953 | Q34: =Q36*'Production Steps'!$O$10 -> 2.1904386 | R34: =R36*'Production Steps'!$O$10 -> 2.2828618 | S34: =S36*'Production Steps'!$O$10 -> 2.3791847 | ... U34: =U36*'Production Steps'!$O$10 -> 2.5841947 | V34: =X34*0.8 -> 717.92908 | W34: ='Production Steps'!H21*1.1*'Production Steps'!K21 -> 708.60173 | X34: ='Production Steps'!I21*1.1*'Production Steps'!K21 -> 897.41135
B35: MINCNABHU2 | C35: MIN.COA.NA.BHU.2 | D35: =CONCATENATE(MID(B35,4,6),"1") -> CNABHU1 | E35: 2010 | G35: 1.05 | H35: 1.05 | I35: 1.05 | J35: 1.05 | K35: 1.005 | L35: =L36*'Production Steps'!$O$11 -> 1.8104255 | M35: =M36*'Production Steps'!$O$11 -> 1.9813462 | N35: =N36*'Production Steps'!$O$11 -> 2.1945793 | O35: =O36*'Production Steps'!$O$11 -> 2.2889541 | P35: =P36*'Production Steps'!$O$11 -> 2.3962808 | Q35: =Q36*'Production Steps'!$O$11 -> 2.4841565 | R35: =R36*'Production Steps'!$O$11 -> 2.5889728 | S35: =S36*'Production Steps'!$O$11 -> 2.6982118 | ... U35: =U36*'Production Steps'!$O$11 -> 2.9307117 | V35: =X35*0.8 -> 703.5705 | W35: ='Production Steps'!H22*1.1*'Production Steps'!K22 -> 694.42969 | X35: ='Production Steps'!I22*1.1*'Production Steps'!K22 -> 879.46313
B36: MINCNABHU3 | C36: MIN.COA.NA.BHU.3 | D36: =CONCATENATE(MID(B36,4,6),"1") -> CNABHU1 | E36: 2010 | G36: 1.05 | H36: 1.05 | I36: 1.05 | J36: 1.05 | K36: 1.005 | L36: ='AEO Coal Prices'!M9*'Production Steps'!$Q$17*$N$4 -> 1.8140536 | M36: ='AEO Coal Prices'!N9*'Production Steps'!$Q$17*$N$4 -> 1.9853169 | N36: ='AEO Coal Prices'!O9*'Production Steps'!$Q$17*$N$4 -> 2.1989772 | O36: ='AEO Coal Prices'!P9*'Production Steps'!$Q$17*$N$4 -> 2.2935412 | P36: ='AEO Coal Prices'!Q9*'Production Steps'!$Q$17*$N$4 -> 2.4010829 | Q36: ='AEO Coal Prices'!R9*'Production Steps'!$Q$17*$N$4 -> 2.4891348 | R36: ='AEO Coal Prices'!S9*'Production Steps'!$Q$17*$N$4 -> 2.5941612 | S36: =R36*(1+(R36-Q36)/Q36) -> 2.703619 | T36: =S36*(1+(S36-R36)/R36) -> 2.8176953 | U36: =T36*(1+(T36-S36)/S36) -> 2.9365849 | V36: =X36*0.8 -> 14.358582 | W36: ='Production Steps'!H23*1.1*'Production Steps'!K23 -> 14.172035 | X36: ='Production Steps'!I23*1.1*'Production Steps'!K23 -> 17.948227
B37: MINCNABHU4 | C37: MIN.COA.NA.BHU.4 | D37: =CONCATENATE(MID(B37,4,6),"1") -> CNABHU1 | E37: 2010 | G37: 1.05 | H37: 1.05 | I37: 1.05 | J37: 1.05 | K37: 1.005 | L37: =L36*'Production Steps'!$O$13 -> 1.8194958 | M37: =M36*'Production Steps'!$O$13 -> 1.9912728 | N37: =N36*'Production Steps'!$O$13 -> 2.2055742 | O37: =O36*'Production Steps'!$O$13 -> 2.3004218 | P37: =P36*'Production Steps'!$O$13 -> 2.4082862 | Q37: =Q36*'Production Steps'!$O$13 -> 2.4966022 | R37: =R36*'Production Steps'!$O$13 -> 2.6019436 | S37: =S36*'Production Steps'!$O$13 -> 2.7117299 | ... U37: =U36*'Production Steps'!$O$13 -> 2.9453947 | V37: =X37*0.8 -> 14.358582 | W37: ='Production Steps'!H24*1.1*'Production Steps'!K24 -> 14.172035 | X37: ='Production Steps'!I24*1.1*'Production Steps'!K24 -> 17.948227
B38: MINCNABHU5 | C38: MIN.COA.NA.BHU.5 | D38: =CONCATENATE(MID(B38,4,6),"1") -> CNABHU1 | E38: 2010 | F38: =X38*0.1 -> 16.153404 | G38: 1.05 | H38: 1.05 | I38: 1.05 | J38: 1.05 | K38: 1.005 | L38: =L36*'Production Steps'!$O$14 -> 2.03174 | M38: =M36*'Production Steps'!$O$14 -> 2.2235549 | N38: =N36*'Production Steps'!$O$14 -> 2.4628545 | O38: =O36*'Production Steps'!$O$14 -> 2.5687662 | P38: =P36*'Production Steps'!$O$14 -> 2.6892129 | Q38: =Q36*'Production Steps'!$O$14 -> 2.787831 | R38: =R36*'Production Steps'!$O$14 -> 2.9054605 | S38: =S36*'Production Steps'!$O$14 -> 3.0280533 | ... U38: =U36*'Production Steps'!$O$14 -> 3.2889751 | W38: ='Production Steps'!H25*1.1*'Production Steps'!K25 -> 127.54831 | X38: ='Production Steps'!I25*1.1*'Production Steps'!K25 -> 161.53404
B39: MINCNABHU6 | C39: MIN.COA.NA.BHU.6 | D39: =CONCATENATE(MID(B39,4,6),"1") -> CNABHU1 | E39: 2010 | F39: =X39*0.1 -> 17.948227 | G39: 1.05 | H39: 1.05 | I39: 1.05 | J39: 1.05 | K39: 1.005 | L39: =L36*'Production Steps'!$O$15 -> 2.775502 | M39: =M36*'Production Steps'!$O$15 -> 3.0375348 | N39: =N36*'Production Steps'!$O$15 -> 3.3644352 | O39: =O36*'Production Steps'!$O$15 -> 3.5091181 | P39: =P36*'Production Steps'!$O$15 -> 3.6736569 | Q39: =Q36*'Production Steps'!$O$15 -> 3.8083762 | R39: =R36*'Production Steps'!$O$15 -> 3.9690666 | S39: =S36*'Production Steps'!$O$15 -> 4.1365371 | ... U39: =U36*'Production Steps'!$O$15 -> 4.4929749 | W39: ='Production Steps'!H26*1.1*'Production Steps'!K26 -> 141.72035 | X39: ='Production Steps'!I26*1.1*'Production Steps'!K26 -> 179.48227
A40: *
A41: R0 | B41: MINCNABHS1 | C41: MIN.COA.NA.BHS.1 | D41: =CONCATENATE(MID(B41,4,6),"1") -> CNABHS1 | E41: 2010 | G41: 1.05 | H41: 1.05 | I41: 1.05 | J41: 1.05 | K41: 1.005 | L41: =L43*'Production Steps'!$O$10 -> 1.5963672 | M41: =M43*'Production Steps'!$O$10 -> 1.7470789 | N41: =N43*'Production Steps'!$O$10 -> 1.9351 | O41: =O43*'Production Steps'!$O$10 -> 2.0183163 | P41: =P43*'Production Steps'!$O$10 -> 2.112953 | Q41: =Q43*'Production Steps'!$O$10 -> 2.1904386 | R41: =R43*'Production Steps'!$O$10 -> 2.2828618 | S41: =S43*'Production Steps'!$O$10 -> 2.3791847 | ... U41: =U43*'Production Steps'!$O$10 -> 2.5841947 | V41: =X41*0.8 -> 174.93491 | W41: ='Production Steps'!H21*1.1*'Production Steps'!L21 -> 172.66215 | X41: ='Production Steps'!I21*1.1*'Production Steps'!L21 -> 218.66864
B42: MINCNABHS2 | C42: MIN.COA.NA.BHS.2 | D42: =CONCATENATE(MID(B42,4,6),"1") -> CNABHS1 | E42: 2010 | G42: 1.05 | H42: 1.05 | I42: 1.05 | J42: 1.05 | K42: 1.005 | L42: =L43*'Production Steps'!$O$11 -> 1.8104255 | M42: =M43*'Production Steps'!$O$11 -> 1.9813462 | N42: =N43*'Production Steps'!$O$11 -> 2.1945793 | O42: =O43*'Production Steps'!$O$11 -> 2.2889541 | P42: =P43*'Production Steps'!$O$11 -> 2.3962808 | Q42: =Q43*'Production Steps'!$O$11 -> 2.4841565 | R42: =R43*'Production Steps'!$O$11 -> 2.5889728 | S42: =S43*'Production Steps'!$O$11 -> 2.6982118 | ... U42: =U43*'Production Steps'!$O$11 -> 2.9307117 | V42: =X42*0.8 -> 171.43622 | W42: ='Production Steps'!H22*1.1*'Production Steps'!L22 -> 169.20891 | X42: ='Production Steps'!I22*1.1*'Production Steps'!L22 -> 214.29527
B43: MINCNABHS3 | C43: MIN.COA.NA.BHS.3 | D43: =CONCATENATE(MID(B43,4,6),"1") -> CNABHS1 | E43: 2010 | G43: 1.05 | H43: 1.05 | I43: 1.05 | J43: 1.05 | K43: 1.005 | L43: =L36 -> 1.8140536 | M43: =M36 -> 1.9853169 | N43: =N36 -> 2.1989772 | O43: =O36 -> 2.2935412 | P43: =P36 -> 2.4010829 | Q43: =Q36 -> 2.4891348 | R43: =R36 -> 2.5941612 | S43: =R43*(1+(R43-Q43)/Q43) -> 2.703619 | T43: =S43*(1+(S43-R43)/R43) -> 2.8176953 | U43: =T43*(1+(T43-S43)/S43) -> 2.9365849 | V43: =X43*0.8 -> 3.4986983 | W43: ='Production Steps'!H23*1.1*'Production Steps'!L23 -> 3.4532431 | X43: ='Production Steps'!I23*1.1*'Production Steps'!L23 -> 4.3733729
B44: MINCNABHS4 | C44: MIN.COA.NA.BHS.4 | D44: =CONCATENATE(MID(B44,4,6),"1") -> CNABHS1 | E44: 2010 | G44: 1.05 | H44: 1.05 | I44: 1.05 | J44: 1.05 | K44: 1.005 | L44: =L43*'Production Steps'!$O$13 -> 1.8194958 | M44: =M43*'Production Steps'!$O$13 -> 1.9912728 | N44: =N43*'Production Steps'!$O$13 -> 2.2055742 | O44: =O43*'Production Steps'!$O$13 -> 2.3004218 | P44: =P43*'Production Steps'!$O$13 -> 2.4082862 | Q44: =Q43*'Production Steps'!$O$13 -> 2.4966022 | R44: =R43*'Production Steps'!$O$13 -> 2.6019436 | S44: =S43*'Production Steps'!$O$13 -> 2.7117299 | ... U44: =U43*'Production Steps'!$O$13 -> 2.9453947 | V44: =X44*0.8 -> 3.4986983 | W44: ='Production Steps'!H24*1.1*'Production Steps'!L24 -> 3.4532431 | X44: ='Production Steps'!I24*1.1*'Production Steps'!L24 -> 4.3733729
B45: MINCNABHS5 | C45: MIN.COA.NA.BHS.5 | D45: =CONCATENATE(MID(B45,4,6),"1") -> CNABHS1 | E45: 2010 | F45: =X45*0.1 -> 3.9360356 | G45: 1.05 | H45: 1.05 | I45: 1.05 | J45: 1.05 | K45: 1.005 | L45: =L43*'Production Steps'!$O$14 -> 2.03174 | M45: =M43*'Production Steps'!$O$14 -> 2.2235549 | N45: =N43*'Production Steps'!$O$14 -> 2.4628545 | O45: =O43*'Production Steps'!$O$14 -> 2.5687662 | P45: =P43*'Production Steps'!$O$14 -> 2.6892129 | Q45: =Q43*'Production Steps'!$O$14 -> 2.787831 | R45: =R43*'Production Steps'!$O$14 -> 2.9054605 | S45: =S43*'Production Steps'!$O$14 -> 3.0280533 | ... U45: =U43*'Production Steps'!$O$14 -> 3.2889751 | W45: ='Production Steps'!H25*1.1*'Production Steps'!L25 -> 31.079188 | X45: ='Production Steps'!I25*1.1*'Production Steps'!L25 -> 39.360356
B46: MINCNABHS6 | C46: MIN.COA.NA.BHS.6 | D46: =CONCATENATE(MID(B46,4,6),"1") -> CNABHS1 | E46: 2010 | F46: =X46*0.1 -> 4.3733729 | G46: 1.05 | H46: 1.05 | I46: 1.05 | J46: 1.05 | K46: 1.005 | L46: =L43*'Production Steps'!$O$15 -> 2.775502 | M46: =M43*'Production Steps'!$O$15 -> 3.0375348 | N46: =N43*'Production Steps'!$O$15 -> 3.3644352 | O46: =O43*'Production Steps'!$O$15 -> 3.5091181 | P46: =P43*'Production Steps'!$O$15 -> 3.6736569 | Q46: =Q43*'Production Steps'!$O$15 -> 3.8083762 | R46: =R43*'Production Steps'!$O$15 -> 3.9690666 | S46: =S43*'Production Steps'!$O$15 -> 4.1365371 | ... U46: =U43*'Production Steps'!$O$15 -> 4.4929749 | W46: ='Production Steps'!H26*1.1*'Production Steps'!L26 -> 34.532431 | X46: ='Production Steps'!I26*1.1*'Production Steps'!L26 -> 43.733729
A47: *
A48: R0 | B48: MINCCAPMU1 | C48: MIN.COA.CA.PMU.1 | D48: =CONCATENATE(MID(B48,4,6),"1") -> CCAPMU1 | E48: 2010 | G48: 1.05 | H48: 1.05 | I48: 1.05 | J48: 1.05 | K48: 1.001 | L48: =L50*'Production Steps'!$O$10 -> 3.1796895 | M48: =M50*'Production Steps'!$O$10 -> 3.7749621 | N48: =N50*'Production Steps'!$O$10 -> 4.3388193 | O48: =O50*'Production Steps'!$O$10 -> 4.7484838 | P48: =P50*'Production Steps'!$O$10 -> 5.192394 | Q48: =Q50*'Production Steps'!$O$10 -> 5.514707 | R48: =R50*'Production Steps'!$O$10 -> 5.701434 | S48: =S50*'Production Steps'!$O$10 -> 5.8944835 | ... U48: =U50*'Production Steps'!$O$10 -> 6.3004138 | V48: =X48*0.8 -> 752.91126 | W48: ='Production Steps'!H29*1.1 -> 598.55154 | X48: ='Production Steps'!I29*1.1 -> 941.13908
B49: MINCCAPMU2 | C49: MIN.COA.CA.PMU.2 | D49: =CONCATENATE(MID(B49,4,6),"1") -> CCAPMU1 | E49: 2010 | G49: 1.05 | H49: 1.05 | I49: 1.05 | J49: 1.05 | K49: 1.001 | L49: =L50*'Production Steps'!$O$11 -> 3.6060569 | M49: =M50*'Production Steps'!$O$11 -> 4.2811502 | N49: =N50*'Production Steps'!$O$11 -> 4.9206155 | O49: =O50*'Production Steps'!$O$11 -> 5.3852123 | P49: =P50*'Production Steps'!$O$11 -> 5.8886469 | Q49: =Q50*'Production Steps'!$O$11 -> 6.2541791 | R49: =R50*'Production Steps'!$O$11 -> 6.4659445 | S49: =S50*'Production Steps'!$O$11 -> 6.6848802 | ... U49: =U50*'Production Steps'!$O$11 -> 7.145242 | V49: =X49*0.8 -> 737.85304 | W49: ='Production Steps'!H30*1.1 -> 586.58051 | X49: ='Production Steps'!I30*1.1 -> 922.3163
B50: MINCCAPMU3 | C50: MIN.COA.CA.PMU.3 | D50: =CONCATENATE(MID(B50,4,6),"1") -> CCAPMU1 | E50: 2010 | G50: 1.05 | H50: 1.05 | I50: 1.05 | J50: 1.05 | K50: 1.001 | L50: ='AEO Coal Prices'!M12*'Production Steps'!$Q$17*$N$4 -> 3.6132835 | M50: ='AEO Coal Prices'!N12*'Production Steps'!$Q$17*$N$4 -> 4.2897296 | N50: ='AEO Coal Prices'!O12*'Production Steps'!$Q$17*$N$4 -> 4.9304765 | O50: ='AEO Coal Prices'!P12*'Production Steps'!$Q$17*$N$4 -> 5.3960043 | P50: ='AEO Coal Prices'!Q12*'Production Steps'!$Q$17*$N$4 -> 5.9004477 | Q50: ='AEO Coal Prices'!R12*'Production Steps'!$Q$17*$N$4 -> 6.2667125 | R50: ='AEO Coal Prices'!S12*'Production Steps'!$Q$17*$N$4 -> 6.4789023 | S50: =R50*(1+(R50-Q50)/Q50) -> 6.6982767 | T50: =S50*(1+(S50-R50)/R50) -> 6.9250792 | U50: =T50*(1+(T50-S50)/S50) -> 7.1595611 | V50: =X50*0.8 -> 15.058225 | W50: ='Production Steps'!H31*1.1 -> 11.971031 | X50: ='Production Steps'!I31*1.1 -> 18.822782
B51: MINCCAPMU4 | C51: MIN.COA.CA.PMU.4 | D51: =CONCATENATE(MID(B51,4,6),"1") -> CCAPMU1 | E51: 2010 | G51: 1.05 | H51: 1.05 | I51: 1.05 | J51: 1.05 | K51: 1.001 | L51: =L50*'Production Steps'!$O$13 -> 3.6241233 | M51: =M50*'Production Steps'!$O$13 -> 4.3025988 | N51: =N50*'Production Steps'!$O$13 -> 4.9452679 | O51: =O50*'Production Steps'!$O$13 -> 5.4121923 | P51: =P50*'Production Steps'!$O$13 -> 5.9181491 | Q51: =Q50*'Production Steps'!$O$13 -> 6.2855126 | R51: =R50*'Production Steps'!$O$13 -> 6.498339 | S51: =S50*'Production Steps'!$O$13 -> 6.7183716 | ... U51: =U50*'Production Steps'!$O$13 -> 7.1810398 | V51: =X51*0.8 -> 15.058225 | W51: ='Production Steps'!H32*1.1 -> 11.971031 | X51: ='Production Steps'!I32*1.1 -> 18.822782
B52: MINCCAPMU5 | C52: MIN.COA.CA.PMU.5 | D52: =CONCATENATE(MID(B52,4,6),"1") -> CCAPMU1 | E52: 2010 | F52: =X52*0.1 -> 16.940503 | G52: 1.05 | H52: 1.05 | I52: 1.05 | J52: 1.05 | K52: 1.001 | L52: =L50*'Production Steps'!$O$14 -> 4.0468775 | M52: =M50*'Production Steps'!$O$14 -> 4.8044972 | N52: =N50*'Production Steps'!$O$14 -> 5.5221337 | O52: =O50*'Production Steps'!$O$14 -> 6.0435248 | P52: =P50*'Production Steps'!$O$14 -> 6.6085015 | Q52: =Q50*'Production Steps'!$O$14 -> 7.018718 | R52: =R50*'Production Steps'!$O$14 -> 7.2563705 | S52: =S50*'Production Steps'!$O$14 -> 7.5020699 | ... U52: =U50*'Production Steps'!$O$14 -> 8.0187085 | W52: ='Production Steps'!H33*1.1 -> 107.73928 | X52: ='Production Steps'!I33*1.1 -> 169.40503
B53: MINCCAPMU6 | C53: MIN.COA.CA.PMU.6 | D53: =CONCATENATE(MID(B53,4,6),"1") -> CCAPMU1 | E53: 2010 | F53: =X53*0.1 -> 18.822782 | G53: 1.05 | H53: 1.05 | I53: 1.05 | J53: 1.05 | K53: 1.001 | L53: =L50*'Production Steps'!$O$15 -> 5.5283238 | M53: =M50*'Production Steps'!$O$15 -> 6.5632863 | N53: =N50*'Production Steps'!$O$15 -> 7.543629 | O53: =O50*'Production Steps'!$O$15 -> 8.2558866 | P53: =P50*'Production Steps'!$O$15 -> 9.0276851 | Q53: =Q50*'Production Steps'!$O$15 -> 9.5880701 | R53: =R50*'Production Steps'!$O$15 -> 9.9127205 | S53: =S50*'Production Steps'!$O$15 -> 10.248363 | ... U53: =U50*'Production Steps'!$O$15 -> 10.954129 | W53: ='Production Steps'!H34*1.1 -> 119.71031 | X53: ='Production Steps'!I34*1.1 -> 188.22782
A54: *
A55: R0 | B55: MINCCABLU1 | C55: MIN.COA.CA.BLU.1 | D55: =CONCATENATE(MID(B55,4,6),"1") -> CCABLU1 | E55: 2010 | G55: 1.05 | H55: 1.05 | I55: 1.05 | J55: 1.05 | K55: 1.01 | L55: =L57*'Production Steps'!$O$10 -> 2.1218195 | M55: =M57*'Production Steps'!$O$10 -> 2.1894376 | N55: =N57*'Production Steps'!$O$10 -> 2.3409723 | O55: =O57*'Production Steps'!$O$10 -> 2.4462917 | P55: =P57*'Production Steps'!$O$10 -> 2.7522874 | Q55: =Q57*'Production Steps'!$O$10 -> 2.9588559 | R55: =R57*'Production Steps'!$O$10 -> 3.2592869 | S55: =S57*'Production Steps'!$O$10 -> 3.5902225 | ... U55: =U57*'Production Steps'!$O$10 -> 4.3563115 | V55: =X55*0.8 -> 30.429245 | W55: ='Production Steps'!H36*1.1*'Production Steps'!K36 -> 127.90118 | X55: ='Production Steps'!I36*1.1*'Production Steps'!K36 -> 38.036556
B56: MINCCABLU2 | C56: MIN.COA.CA.BLU.2 | D56: =CONCATENATE(MID(B56,4,6),"1") -> CCABLU1 | E56: 2010 | G56: 1.05 | H56: 1.05 | I56: 1.05 | J56: 1.05 | K56: 1.01 | L56: =L57*'Production Steps'!$O$11 -> 2.4063363 | M56: =M57*'Production Steps'!$O$11 -> 2.4830212 | N56: =N57*'Production Steps'!$O$11 -> 2.6548754 | O56: =O57*'Production Steps'!$O$11 -> 2.7743172 | P56: =P57*'Production Steps'!$O$11 -> 3.1213441 | Q56: =Q57*'Production Steps'!$O$11 -> 3.3556115 | R56: =R57*'Production Steps'!$O$11 -> 3.6963276 | S56: =S57*'Production Steps'!$O$11 -> 4.0716387 | ... U56: =U57*'Production Steps'!$O$11 -> 4.9404533 | V56: =X56*0.8 -> 29.82066 | W56: ='Production Steps'!H37*1.1*'Production Steps'!K37 -> 125.34316 | X56: ='Production Steps'!I37*1.1*'Production Steps'!K37 -> 37.275825
B57: MINCCABLU3 | C57: MIN.COA.CA.BLU.3 | D57: =CONCATENATE(MID(B57,4,6),"1") -> CCABLU1 | E57: 2010 | G57: 1.05 | H57: 1.05 | I57: 1.05 | J57: 1.05 | K57: 1.01 | L57: ='AEO Coal Prices'!M13*'Production Steps'!$Q$17*$N$4 -> 2.4111586 | M57: ='AEO Coal Prices'!N13*'Production Steps'!$Q$17*$N$4 -> 2.4879972 | N57: ='AEO Coal Prices'!O13*'Production Steps'!$Q$17*$N$4 -> 2.6601958 | O57: ='AEO Coal Prices'!P13*'Production Steps'!$Q$17*$N$4 -> 2.779877 | P57: ='AEO Coal Prices'!Q13*'Production Steps'!$Q$17*$N$4 -> 3.1275993 | Q57: ='AEO Coal Prices'!R13*'Production Steps'!$Q$17*$N$4 -> 3.3623362 | R57: ='AEO Coal Prices'!S13*'Production Steps'!$Q$17*$N$4 -> 3.7037351 | S57: =R57*(1+(R57-Q57)/Q57) -> 4.0797983 | T57: =S57*(1+(S57-R57)/R57) -> 4.4940456 | U57: =T57*(1+(T57-S57)/S57) -> 4.950354 | V57: =X57*0.8 -> 0.6085849 | W57: ='Production Steps'!H38*1.1*'Production Steps'!K38 -> 2.5580236 | X57: ='Production Steps'!I38*1.1*'Production Steps'!K38 -> 0.76073112
B58: MINCCABLU4 | C58: MIN.COA.CA.BLU.4 | D58: =CONCATENATE(MID(B58,4,6),"1") -> CCABLU1 | E58: 2010 | G58: 1.05 | H58: 1.05 | I58: 1.05 | J58: 1.05 | K58: 1.01 | L58: =L57*'Production Steps'!$O$13 -> 2.4183921 | M58: =M57*'Production Steps'!$O$13 -> 2.4954612 | N58: =N57*'Production Steps'!$O$13 -> 2.6681764 | O58: =O57*'Production Steps'!$O$13 -> 2.7882166 | P58: =P57*'Production Steps'!$O$13 -> 3.1369821 | Q58: =Q57*'Production Steps'!$O$13 -> 3.3724232 | R58: =R57*'Production Steps'!$O$13 -> 3.7148463 | S58: =S57*'Production Steps'!$O$13 -> 4.0920377 | ... U58: =U57*'Production Steps'!$O$13 -> 4.9652051 | V58: =X58*0.8 -> 0.6085849 | W58: ='Production Steps'!H39*1.1*'Production Steps'!K39 -> 2.5580236 | X58: ='Production Steps'!I39*1.1*'Production Steps'!K39 -> 0.76073112
B59: MINCCABLU5 | C59: MIN.COA.CA.BLU.5 | D59: =CONCATENATE(MID(B59,4,6),"1") -> CCABLU1 | E59: 2010 | F59: =X59*0.1 -> 0.68465801 | G59: 1.05 | H59: 1.05 | I59: 1.05 | J59: 1.05 | K59: 1.01 | L59: =L57*'Production Steps'!$O$14 -> 2.7004976 | M59: =M57*'Production Steps'!$O$14 -> 2.7865569 | N59: =N57*'Production Steps'!$O$14 -> 2.9794193 | O59: =O57*'Production Steps'!$O$14 -> 3.1134622 | P59: =P57*'Production Steps'!$O$14 -> 3.5029112 | Q59: =Q57*'Production Steps'!$O$14 -> 3.7658166 | R59: =R57*'Production Steps'!$O$14 -> 4.1481833 | S59: =S57*'Production Steps'!$O$14 -> 4.5693741 | ... U59: =U57*'Production Steps'!$O$14 -> 5.5443965 | W59: ='Production Steps'!H40*1.1*'Production Steps'!K40 -> 23.022212 | X59: ='Production Steps'!I40*1.1*'Production Steps'!K40 -> 6.8465801
B60: MINCCABLU6 | C60: MIN.COA.CA.BLU.6 | D60: =CONCATENATE(MID(B60,4,6),"1") -> CCABLU1 | E60: 2010 | F60: =X60*0.1 -> 0.76073112 | G60: 1.05 | H60: 1.05 | I60: 1.05 | J60: 1.05 | K60: 1.01 | L60: =L57*'Production Steps'!$O$15 -> 3.6890726 | M60: =M57*'Production Steps'!$O$15 -> 3.8066358 | N60: =N57*'Production Steps'!$O$15 -> 4.0700995 | O60: =O57*'Production Steps'!$O$15 -> 4.2532118 | P60: =P57*'Production Steps'!$O$15 -> 4.7852269 | Q60: =Q57*'Production Steps'!$O$15 -> 5.1443744 | R60: =R57*'Production Steps'!$O$15 -> 5.6667147 | S60: =S57*'Production Steps'!$O$15 -> 6.2420915 | ... U60: =U57*'Production Steps'!$O$15 -> 7.5740416 | W60: ='Production Steps'!H41*1.1*'Production Steps'!K41 -> 25.580236 | X60: ='Production Steps'!I41*1.1*'Production Steps'!K41 -> 7.6073112
A61: *
A62: R0 | B62: MINCCABLS1 | C62: MIN.COA.CA.BLS.1 | D62: =CONCATENATE(MID(B62,4,6),"1") -> CCABLS1 | E62: 2010 | G62: 1.05 | H62: 1.05 | I62: 1.05 | J62: 1.05 | K62: 1.01 | L62: =L64*'Production Steps'!$O$10 -> 2.1218195 | M62: =M64*'Production Steps'!$O$10 -> 2.1894376 | N62: =N64*'Production Steps'!$O$10 -> 2.3409723 | O62: =O64*'Production Steps'!$O$10 -> 2.4462917 | P62: =P64*'Production Steps'!$O$10 -> 2.7522874 | Q62: =Q64*'Production Steps'!$O$10 -> 2.9588559 | R62: =R64*'Production Steps'!$O$10 -> 3.2592869 | S62: =S64*'Production Steps'!$O$10 -> 3.5902225 | ... U62: =U64*'Production Steps'!$O$10 -> 4.3563115 | V62: =X62*0.8 -> 130.41323 | W62: ='Production Steps'!H36*1.1*'Production Steps'!L36 -> 548.15707 | X62: ='Production Steps'!I36*1.1*'Production Steps'!L36 -> 163.01654
B63: MINCCABLS2 | C63: MIN.COA.CA.BLS.2 | D63: =CONCATENATE(MID(B63,4,6),"1") -> CCABLS1 | E63: 2010 | G63: 1.05 | H63: 1.05 | I63: 1.05 | J63: 1.05 | K63: 1.01 | L63: =L64*'Production Steps'!$O$11 -> 2.4063363 | M63: =M64*'Production Steps'!$O$11 -> 2.4830212 | N63: =N64*'Production Steps'!$O$11 -> 2.6548754 | O63: =O64*'Production Steps'!$O$11 -> 2.7743172 | P63: =P64*'Production Steps'!$O$11 -> 3.1213441 | Q63: =Q64*'Production Steps'!$O$11 -> 3.3556115 | R63: =R64*'Production Steps'!$O$11 -> 3.6963276 | S63: =S64*'Production Steps'!$O$11 -> 4.0716387 | ... U63: =U64*'Production Steps'!$O$11 -> 4.9404533 | V63: =X63*0.8 -> 127.80496 | W63: ='Production Steps'!H37*1.1*'Production Steps'!L37 -> 537.19393 | X63: ='Production Steps'!I37*1.1*'Production Steps'!L37 -> 159.75621
B64: MINCCABLS3 | C64: MIN.COA.CA.BLS.3 | D64: =CONCATENATE(MID(B64,4,6),"1") -> CCABLS1 | E64: 2010 | G64: 1.05 | H64: 1.05 | I64: 1.05 | J64: 1.05 | K64: 1.01 | L64: =L57 -> 2.4111586 | M64: =M57 -> 2.4879972 | N64: =N57 -> 2.6601958 | O64: =O57 -> 2.779877 | P64: =P57 -> 3.1275993 | Q64: =Q57 -> 3.3623362 | R64: =R57 -> 3.7037351 | S64: =R64*(1+(R64-Q64)/Q64) -> 4.0797983 | T64: =S64*(1+(S64-R64)/R64) -> 4.4940456 | U64: =T64*(1+(T64-S64)/S64) -> 4.950354 | V64: =X64*0.8 -> 2.6082646 | W64: ='Production Steps'!H38*1.1*'Production Steps'!L38 -> 10.963141 | X64: ='Production Steps'!I38*1.1*'Production Steps'!L38 -> 3.2603307
B65: MINCCABLS4 | C65: MIN.COA.CA.BLS.4 | D65: =CONCATENATE(MID(B65,4,6),"1") -> CCABLS1 | E65: 2010 | G65: 1.05 | H65: 1.05 | I65: 1.05 | J65: 1.05 | K65: 1.01 | L65: =L64*'Production Steps'!$O$13 -> 2.4183921 | M65: =M64*'Production Steps'!$O$13 -> 2.4954612 | N65: =N64*'Production Steps'!$O$13 -> 2.6681764 | O65: =O64*'Production Steps'!$O$13 -> 2.7882166 | P65: =P64*'Production Steps'!$O$13 -> 3.1369821 | Q65: =Q64*'Production Steps'!$O$13 -> 3.3724232 | R65: =R64*'Production Steps'!$O$13 -> 3.7148463 | S65: =S64*'Production Steps'!$O$13 -> 4.0920377 | ... U65: =U64*'Production Steps'!$O$13 -> 4.9652051 | V65: =X65*0.8 -> 2.6082646 | W65: ='Production Steps'!H39*1.1*'Production Steps'!L39 -> 10.963141 | X65: ='Production Steps'!I39*1.1*'Production Steps'!L39 -> 3.2603307
B66: MINCCABLS5 | C66: MIN.COA.CA.BLS.5 | D66: =CONCATENATE(MID(B66,4,6),"1") -> CCABLS1 | E66: 2010 | F66: =X66*0.1 -> 2.9342976 | G66: 1.05 | H66: 1.05 | I66: 1.05 | J66: 1.05 | K66: 1.01 | L66: =L64*'Production Steps'!$O$14 -> 2.7004976 | M66: =M64*'Production Steps'!$O$14 -> 2.7865569 | N66: =N64*'Production Steps'!$O$14 -> 2.9794193 | O66: =O64*'Production Steps'!$O$14 -> 3.1134622 | P66: =P64*'Production Steps'!$O$14 -> 3.5029112 | Q66: =Q64*'Production Steps'!$O$14 -> 3.7658166 | R66: =R64*'Production Steps'!$O$14 -> 4.1481833 | S66: =S64*'Production Steps'!$O$14 -> 4.5693741 | ... U66: =U64*'Production Steps'!$O$14 -> 5.5443965 | W66: ='Production Steps'!H40*1.1*'Production Steps'!L40 -> 98.668273 | X66: ='Production Steps'!I40*1.1*'Production Steps'!L40 -> 29.342976
B67: MINCCABLS6 | C67: MIN.COA.CA.BLS.6 | D67: =CONCATENATE(MID(B67,4,6),"1") -> CCABLS1 | E67: 2010 | F67: =X67*0.1 -> 3.2603307 | G67: 1.05 | H67: 1.05 | I67: 1.05 | J67: 1.05 | K67: 1.01 | L67: =L64*'Production Steps'!$O$15 -> 3.6890726 | M67: =M64*'Production Steps'!$O$15 -> 3.8066358 | N67: =N64*'Production Steps'!$O$15 -> 4.0700995 | O67: =O64*'Production Steps'!$O$15 -> 4.2532118 | P67: =P64*'Production Steps'!$O$15 -> 4.7852269 | Q67: =Q64*'Production Steps'!$O$15 -> 5.1443744 | R67: =R64*'Production Steps'!$O$15 -> 5.6667147 | S67: =S64*'Production Steps'!$O$15 -> 6.2420915 | ... U67: =U64*'Production Steps'!$O$15 -> 7.5740416 | W67: ='Production Steps'!H41*1.1*'Production Steps'!L41 -> 109.63141 | X67: ='Production Steps'!I41*1.1*'Production Steps'!L41 -> 32.603307
A68: *
A69: R0 | B69: MINCCABMU1 | C69: MIN.COA.CA.BMU.1 | D69: =CONCATENATE(MID(B69,4,6),"1") -> CCABMU1 | E69: 2010 | G69: 1.05 | H69: 1.05 | I69: 1.05 | J69: 1.05 | K69: 1.05 | L69: =L71*'Production Steps'!$O$10 -> 2.0095916 | M69: =M71*'Production Steps'!$O$10 -> 2.0514862 | N69: =N71*'Production Steps'!$O$10 -> 2.2018918 | O69: =O71*'Production Steps'!$O$10 -> 2.2850116 | P69: =P71*'Production Steps'!$O$10 -> 2.3699541 | Q69: =Q71*'Production Steps'!$O$10 -> 2.4611057 | R69: =R71*'Production Steps'!$O$10 -> 2.5553157 | S69: =S71*'Production Steps'!$O$10 -> 2.653132 | ... U69: =U71*'Production Steps'!$O$10 -> 2.8601411 | V69: =X69*0.8 -> 320.6447 | W69: ='Production Steps'!H43*1.1*'Production Steps'!K43 -> 547.96316 | X69: ='Production Steps'!I43*1.1*'Production Steps'!K43 -> 400.80587
B70: MINCCABMU2 | C70: MIN.COA.CA.BMU.2 | D70: =CONCATENATE(MID(B70,4,6),"1") -> CCABMU1 | E70: 2010 | G70: 1.05 | H70: 1.05 | I70: 1.05 | J70: 1.05 | K70: 1.05 | L70: =L71*'Production Steps'!$O$11 -> 2.2790595 | M70: =M71*'Production Steps'!$O$11 -> 2.3265718 | N70: =N71*'Production Steps'!$O$11 -> 2.4971455 | O70: =O71*'Production Steps'!$O$11 -> 2.5914109 | P70: =P71*'Production Steps'!$O$11 -> 2.6877434 | Q70: =Q71*'Production Steps'!$O$11 -> 2.7911176 | R70: =R71*'Production Steps'!$O$11 -> 2.8979603 | S70: =S71*'Production Steps'!$O$11 -> 3.0088929 | ... U70: =U71*'Production Steps'!$O$11 -> 3.24366 | V70: =X70*0.8 -> 314.23181 | W70: ='Production Steps'!H44*1.1*'Production Steps'!K44 -> 537.0039 | X70: ='Production Steps'!I44*1.1*'Production Steps'!K44 -> 392.78976
B71: MINCCABMU3 | C71: MIN.COA.CA.BMU.3 | D71: =CONCATENATE(MID(B71,4,6),"1") -> CCABMU1 | E71: 2010 | G71: 1.05 | H71: 1.05 | I71: 1.05 | J71: 1.05 | K71: 1.05 | L71: ='AEO Coal Prices'!M14*'Production Steps'!$Q$17*$N$4 -> 2.2836268 | M71: ='AEO Coal Prices'!N14*'Production Steps'!$Q$17*$N$4 -> 2.3312343 | N71: ='AEO Coal Prices'!O14*'Production Steps'!$Q$17*$N$4 -> 2.5021498 | O71: ='AEO Coal Prices'!P14*'Production Steps'!$Q$17*$N$4 -> 2.5966041 | P71: ='AEO Coal Prices'!Q14*'Production Steps'!$Q$17*$N$4 -> 2.6931297 | Q71: ='AEO Coal Prices'!R14*'Production Steps'!$Q$17*$N$4 -> 2.796711 | R71: ='AEO Coal Prices'!S14*'Production Steps'!$Q$17*$N$4 -> 2.9037678 | S71: =R71*(1+(R71-Q71)/Q71) -> 3.0149227 | T71: =S71*(1+(S71-R71)/R71) -> 3.1303326 | U71: =T71*(1+(T71-S71)/S71) -> 3.2501603 | V71: =X71*0.8 -> 6.412894 | W71: ='Production Steps'!H45*1.1*'Production Steps'!K45 -> 10.959263 | X71: ='Production Steps'!I45*1.1*'Production Steps'!K45 -> 8.0161175
B72: MINCCABMU4 | C72: MIN.COA.CA.BMU.4 | D72: =CONCATENATE(MID(B72,4,6),"1") -> CCABMU1 | E72: 2010 | G72: 1.05 | H72: 1.05 | I72: 1.05 | J72: 1.05 | K72: 1.05 | L72: =L71*'Production Steps'!$O$13 -> 2.2904776 | M72: =M71*'Production Steps'!$O$13 -> 2.338228 | N72: =N71*'Production Steps'!$O$13 -> 2.5096562 | O72: =O71*'Production Steps'!$O$13 -> 2.6043939 | P72: =P71*'Production Steps'!$O$13 -> 2.7012091 | Q72: =Q71*'Production Steps'!$O$13 -> 2.8051012 | R72: =R71*'Production Steps'!$O$13 -> 2.9124791 | S72: =S71*'Production Steps'!$O$13 -> 3.0239675 | ... U72: =U71*'Production Steps'!$O$13 -> 3.2599108 | V72: =X72*0.8 -> 6.412894 | W72: ='Production Steps'!H46*1.1*'Production Steps'!K46 -> 10.959263 | X72: ='Production Steps'!I46*1.1*'Production Steps'!K46 -> 8.0161175
B73: MINCCABMU5 | C73: MIN.COA.CA.BMU.5 | D73: =CONCATENATE(MID(B73,4,6),"1") -> CCABMU1 | E73: 2010 | F73: =X73*0.1 -> 7.2145057 | G73: 1.05 | H73: 1.05 | I73: 1.05 | J73: 1.05 | K73: 1.05 | L73: =L71*'Production Steps'!$O$14 -> 2.557662 | M73: =M71*'Production Steps'!$O$14 -> 2.6109824 | N73: =N71*'Production Steps'!$O$14 -> 2.8024077 | O73: =O71*'Production Steps'!$O$14 -> 2.9081966 | P73: =P71*'Production Steps'!$O$14 -> 3.0163053 | Q73: =Q71*'Production Steps'!$O$14 -> 3.1323164 | R73: =R71*'Production Steps'!$O$14 -> 3.25222 | S73: =S71*'Production Steps'!$O$14 -> 3.3767135 | ... U73: =U71*'Production Steps'!$O$14 -> 3.6401795 | W73: ='Production Steps'!H47*1.1*'Production Steps'!K47 -> 98.633369 | X73: ='Production Steps'!I47*1.1*'Production Steps'!K47 -> 72.145057
B74: MINCCABMU6 | C74: MIN.COA.CA.BMU.6 | D74: =CONCATENATE(MID(B74,4,6),"1") -> CCABMU1 | E74: 2010 | F74: =X74*0.1 -> 8.0161175 | G74: 1.05 | H74: 1.05 | I74: 1.05 | J74: 1.05 | K74: 1.05 | L74: =L71*'Production Steps'!$O$15 -> 3.4939489 | M74: =M71*'Production Steps'!$O$15 -> 3.5667884 | N74: =N71*'Production Steps'!$O$15 -> 3.8282891 | O74: =O71*'Production Steps'!$O$15 -> 3.9728042 | P74: =P71*'Production Steps'!$O$15 -> 4.1204884 | Q74: =Q71*'Production Steps'!$O$15 -> 4.2789679 | R74: =R71*'Production Steps'!$O$15 -> 4.4427648 | S74: =S71*'Production Steps'!$O$15 -> 4.6128318 | ... U74: =U71*'Production Steps'!$O$15 -> 4.9727453 | W74: ='Production Steps'!H48*1.1*'Production Steps'!K48 -> 109.59263 | X74: ='Production Steps'!I48*1.1*'Production Steps'!K48 -> 80.161175
A75: *
A76: R0 | B76: MINCCABMS1 | C76: MIN.COA.CA.BMS.1 | D76: =CONCATENATE(MID(B76,4,6),"1") -> CCABMS1 | E76: 2010 | G76: 1.05 | H76: 1.05 | I76: 1.05 | J76: 1.05 | K76: 1.05 | L76: =L78*'Production Steps'!$O$10 -> 2.0095916 | M76: =M78*'Production Steps'!$O$10 -> 2.0514862 | N76: =N78*'Production Steps'!$O$10 -> 2.2018918 | O76: =O78*'Production Steps'!$O$10 -> 2.2850116 | P76: =P78*'Production Steps'!$O$10 -> 2.3699541 | Q76: =Q78*'Production Steps'!$O$10 -> 2.4611057 | R76: =R78*'Production Steps'!$O$10 -> 2.5553157 | S76: =S78*'Production Steps'!$O$10 -> 2.653132 | ... U76: =U78*'Production Steps'!$O$10 -> 2.8601411 | V76: =X76*0.8 -> 930.68237 | W76: ='Production Steps'!H43*1.1*'Production Steps'!L43 -> 1590.4821 | X76: ='Production Steps'!I43*1.1*'Production Steps'!L43 -> 1163.353
B77: MINCCABMS2 | C77: MIN.COA.CA.BMS.2 | D77: =CONCATENATE(MID(B77,4,6),"1") -> CCABMS1 | E77: 2010 | G77: 1.05 | H77: 1.05 | I77: 1.05 | J77: 1.05 | K77: 1.05 | L77: =L78*'Production Steps'!$O$11 -> 2.2790595 | M77: =M78*'Production Steps'!$O$11 -> 2.3265718 | N77: =N78*'Production Steps'!$O$11 -> 2.4971455 | O77: =O78*'Production Steps'!$O$11 -> 2.5914109 | P77: =P78*'Production Steps'!$O$11 -> 2.6877434 | Q77: =Q78*'Production Steps'!$O$11 -> 2.7911176 | R77: =R78*'Production Steps'!$O$11 -> 2.8979603 | S77: =S78*'Production Steps'!$O$11 -> 3.0088929 | ... U77: =U78*'Production Steps'!$O$11 -> 3.24366 | V77: =X77*0.8 -> 912.06872 | W77: ='Production Steps'!H44*1.1*'Production Steps'!L44 -> 1558.6725 | X77: ='Production Steps'!I44*1.1*'Production Steps'!L44 -> 1140.0859
B78: MINCCABMS3 | C78: MIN.COA.CA.BMS.3 | D78: =CONCATENATE(MID(B78,4,6),"1") -> CCABMS1 | E78: 2010 | G78: 1.05 | H78: 1.05 | I78: 1.05 | J78: 1.05 | K78: 1.05 | L78: =L71 -> 2.2836268 | M78: =M71 -> 2.3312343 | N78: =N71 -> 2.5021498 | O78: =O71 -> 2.5966041 | P78: =P71 -> 2.6931297 | Q78: =Q71 -> 2.796711 | R78: =R71 -> 2.9037678 | S78: =R78*(1+(R78-Q78)/Q78) -> 3.0149227 | T78: =S78*(1+(S78-R78)/R78) -> 3.1303326 | U78: =T78*(1+(T78-S78)/S78) -> 3.2501603 | V78: =X78*0.8 -> 18.613647 | W78: ='Production Steps'!H45*1.1*'Production Steps'!L45 -> 31.809642 | X78: ='Production Steps'!I45*1.1*'Production Steps'!L45 -> 23.267059
B79: MINCCABMS4 | C79: MIN.COA.CA.BMS.4 | D79: =CONCATENATE(MID(B79,4,6),"1") -> CCABMS1 | E79: 2010 | G79: 1.05 | H79: 1.05 | I79: 1.05 | J79: 1.05 | K79: 1.05 | L79: =L78*'Production Steps'!$O$13 -> 2.2904776 | M79: =M78*'Production Steps'!$O$13 -> 2.338228 | N79: =N78*'Production Steps'!$O$13 -> 2.5096562 | O79: =O78*'Production Steps'!$O$13 -> 2.6043939 | P79: =P78*'Production Steps'!$O$13 -> 2.7012091 | Q79: =Q78*'Production Steps'!$O$13 -> 2.8051012 | R79: =R78*'Production Steps'!$O$13 -> 2.9124791 | S79: =S78*'Production Steps'!$O$13 -> 3.0239675 | ... U79: =U78*'Production Steps'!$O$13 -> 3.2599108 | V79: =X79*0.8 -> 18.613647 | W79: ='Production Steps'!H46*1.1*'Production Steps'!L46 -> 31.809642 | X79: ='Production Steps'!I46*1.1*'Production Steps'!L46 -> 23.267059
B80: MINCCABMS5 | C80: MIN.COA.CA.BMS.5 | D80: =CONCATENATE(MID(B80,4,6),"1") -> CCABMS1 | E80: 2010 | F80: =X80*0.1 -> 20.940353 | G80: 1.05 | H80: 1.05 | I80: 1.05 | J80: 1.05 | K80: 1.05 | L80: =L78*'Production Steps'!$O$14 -> 2.557662 | M80: =M78*'Production Steps'!$O$14 -> 2.6109824 | N80: =N78*'Production Steps'!$O$14 -> 2.8024077 | O80: =O78*'Production Steps'!$O$14 -> 2.9081966 | P80: =P78*'Production Steps'!$O$14 -> 3.0163053 | Q80: =Q78*'Production Steps'!$O$14 -> 3.1323164 | R80: =R78*'Production Steps'!$O$14 -> 3.25222 | S80: =S78*'Production Steps'!$O$14 -> 3.3767135 | ... U80: =U78*'Production Steps'!$O$14 -> 3.6401795 | W80: ='Production Steps'!H47*1.1*'Production Steps'!L47 -> 286.28678 | X80: ='Production Steps'!I47*1.1*'Production Steps'!L47 -> 209.40353
B81: MINCCABMS6 | C81: MIN.COA.CA.BMS.6 | D81: =CONCATENATE(MID(B81,4,6),"1") -> CCABMS1 | E81: 2010 | F81: =X81*0.1 -> 23.267059 | G81: 1.05 | H81: 1.05 | I81: 1.05 | J81: 1.05 | K81: 1.05 | L81: =L78*'Production Steps'!$O$15 -> 3.4939489 | M81: =M78*'Production Steps'!$O$15 -> 3.5667884 | N81: =N78*'Production Steps'!$O$15 -> 3.8282891 | O81: =O78*'Production Steps'!$O$15 -> 3.9728042 | P81: =P78*'Production Steps'!$O$15 -> 4.1204884 | Q81: =Q78*'Production Steps'!$O$15 -> 4.2789679 | R81: =R78*'Production Steps'!$O$15 -> 4.4427648 | S81: =S78*'Production Steps'!$O$15 -> 4.6128318 | ... U81: =U78*'Production Steps'!$O$15 -> 4.9727453 | W81: ='Production Steps'!H48*1.1*'Production Steps'!L48 -> 318.09642 | X81: ='Production Steps'!I48*1.1*'Production Steps'!L48 -> 232.67059
A82: *
A83: R0 | B83: MINCSAPLU1 | C83: MIN.COA.SA.PLU.1 | D83: =CONCATENATE(MID(B83,4,6),"1") -> CSAPLU1 | E83: 2010 | G83: 1.05 | H83: 1.05 | I83: 1.05 | J83: 1.05 | K83: 1.005 | L83: =L85*'Production Steps'!$O$10 -> 2.5408843 | M83: =M85*'Production Steps'!$O$10 -> 3.8093892 | N83: =N85*'Production Steps'!$O$10 -> 4.2658229 | O83: =O85*'Production Steps'!$O$10 -> 4.5878601 | P83: =P85*'Production Steps'!$O$10 -> 4.9421721 | Q83: =Q85*'Production Steps'!$O$10 -> 5.2171438 | R83: =R85*'Production Steps'!$O$10 -> 5.3155073 | S83: =S85*'Production Steps'!$O$10 -> 5.4157254 | ... U83: =U85*'Production Steps'!$O$10 -> 5.6218657 | V83: =X83*0.8 -> 124.73069 | W83: ='Production Steps'!H51*1.1 -> 123.31199 | X83: ='Production Steps'!I51*1.1 -> 155.91336
B84: MINCSAPLU2 | C84: MIN.COA.SA.PLU.2 | D84: =CONCATENATE(MID(B84,4,6),"1") -> CSAPLU1 | E84: 2010 | G84: 1.05 | H84: 1.05 | I84: 1.05 | J84: 1.05 | K84: 1.005 | L84: =L85*'Production Steps'!$O$11 -> 2.8815938 | M84: =M85*'Production Steps'!$O$11 -> 4.3201936 | N84: =N85*'Production Steps'!$O$11 -> 4.837831 | O84: =O85*'Production Steps'!$O$11 -> 5.2030504 | P84: =P85*'Production Steps'!$O$11 -> 5.6048725 | Q84: =Q85*'Production Steps'!$O$11 -> 5.9167153 | R84: =R85*'Production Steps'!$O$11 -> 6.0282686 | S84: =S85*'Production Steps'!$O$11 -> 6.141925 | ... U84: =U85*'Production Steps'!$O$11 -> 6.3757068 | V84: =X84*0.8 -> 122.23608 | W84: ='Production Steps'!H52*1.1 -> 120.84575 | X84: ='Production Steps'!I52*1.1 -> 152.79509
B85: MINCSAPLU3 | C85: MIN.COA.SA.PLU.3 | D85: =CONCATENATE(MID(B85,4,6),"1") -> CSAPLU1 | E85: 2010 | G85: 1.05 | H85: 1.05 | I85: 1.05 | J85: 1.05 | K85: 1.005 | L85: ='AEO Coal Prices'!M17*'Production Steps'!$Q$17*$N$4 -> 2.8873685 | M85: ='AEO Coal Prices'!N17*'Production Steps'!$Q$17*$N$4 -> 4.3288513 | N85: ='AEO Coal Prices'!O17*'Production Steps'!$Q$17*$N$4 -> 4.847526 | O85: ='AEO Coal Prices'!P17*'Production Steps'!$Q$17*$N$4 -> 5.2134774 | P85: ='AEO Coal Prices'!Q17*'Production Steps'!$Q$17*$N$4 -> 5.6161047 | Q85: ='AEO Coal Prices'!R17*'Production Steps'!$Q$17*$N$4 -> 5.9285725 | R85: ='AEO Coal Prices'!S17*'Production Steps'!$Q$17*$N$4 -> 6.0403493 | S85: =R85*(1+(R85-Q85)/Q85) -> 6.1542334 | T85: =S85*(1+(S85-R85)/R85) -> 6.2702648 | U85: =T85*(1+(T85-S85)/S85) -> 6.3884838 | V85: =X85*0.8 -> 2.4946138 | W85: ='Production Steps'!H53*1.1 -> 2.4662398 | X85: ='Production Steps'!I53*1.1 -> 3.1182672
B86: MINCSAPLU4 | C86: MIN.COA.SA.PLU.4 | D86: =CONCATENATE(MID(B86,4,6),"1") -> CSAPLU1 | E86: 2010 | G86: 1.05 | H86: 1.05 | I86: 1.05 | J86: 1.05 | K86: 1.005 | L86: =L85*'Production Steps'!$O$13 -> 2.8960306 | M86: =M85*'Production Steps'!$O$13 -> 4.3418379 | N86: =N85*'Production Steps'!$O$13 -> 4.8620686 | O86: =O85*'Production Steps'!$O$13 -> 5.2291178 | P86: =P85*'Production Steps'!$O$13 -> 5.632953 | Q86: =Q85*'Production Steps'!$O$13 -> 5.9463582 | R86: =R85*'Production Steps'!$O$13 -> 6.0584703 | S86: =S85*'Production Steps'!$O$13 -> 6.1726961 | ... U86: =U85*'Production Steps'!$O$13 -> 6.4076492 | V86: =X86*0.8 -> 2.4946138 | W86: ='Production Steps'!H54*1.1 -> 2.4662398 | X86: ='Production Steps'!I54*1.1 -> 3.1182672
B87: MINCSAPLU5 | C87: MIN.COA.SA.PLU.5 | D87: =CONCATENATE(MID(B87,4,6),"1") -> CSAPLU1 | E87: 2010 | F87: =X87*0.1 -> 2.8064405 | G87: 1.05 | H87: 1.05 | I87: 1.05 | J87: 1.05 | K87: 1.005 | L87: =L85*'Production Steps'!$O$14 -> 3.2338527 | M87: =M85*'Production Steps'!$O$14 -> 4.8483135 | N87: =N85*'Production Steps'!$O$14 -> 5.4292291 | O87: =O85*'Production Steps'!$O$14 -> 5.8390947 | P87: =P85*'Production Steps'!$O$14 -> 6.2900373 | Q87: =Q85*'Production Steps'!$O$14 -> 6.6400012 | R87: =R85*'Production Steps'!$O$14 -> 6.7651912 | S87: =S85*'Production Steps'!$O$14 -> 6.8927415 | ... U87: =U85*'Production Steps'!$O$14 -> 7.1551018 | W87: ='Production Steps'!H55*1.1 -> 22.196158 | X87: ='Production Steps'!I55*1.1 -> 28.064405
B88: MINCSAPLU6 | C88: MIN.COA.SA.PLU.6 | D88: =CONCATENATE(MID(B88,4,6),"1") -> CSAPLU1 | E88: 2010 | F88: =X88*0.1 -> 3.1182672 | G88: 1.05 | H88: 1.05 | I88: 1.05 | J88: 1.05 | K88: 1.005 | L88: =L85*'Production Steps'!$O$15 -> 4.4176738 | M88: =M85*'Production Steps'!$O$15 -> 6.6231425 | N88: =N85*'Production Steps'!$O$15 -> 7.4167148 | O88: =O85*'Production Steps'!$O$15 -> 7.9766204 | P88: =P85*'Production Steps'!$O$15 -> 8.5926402 | Q88: =Q85*'Production Steps'!$O$15 -> 9.0707159 | R88: =R85*'Production Steps'!$O$15 -> 9.2417344 | S88: =S85*'Production Steps'!$O$15 -> 9.4159772 | ... U88: =U85*'Production Steps'!$O$15 -> 9.7743802 | W88: ='Production Steps'!H56*1.1 -> 24.662398 | X88: ='Production Steps'!I56*1.1 -> 31.182672
A89: *
A90: R0 | B90: MINCSABLU1 | C90: MIN.COA.SA.BLU.1 | D90: =CONCATENATE(MID(B90,4,6),"1") -> CSABLU1 | E90: 2010 | G90: 1.05 | H90: 1.05 | I90: 1.05 | J90: 1.05 | K90: 1.05 | L90: =L92*'Production Steps'!$O$10 -> 2.2465618 | M90: =M92*'Production Steps'!$O$10 -> 2.3884614 | N90: =N92*'Production Steps'!$O$10 -> 2.5403816 | O90: =O92*'Production Steps'!$O$10 -> 2.6084902 | P90: =P92*'Production Steps'!$O$10 -> 2.7967603 | Q90: =Q92*'Production Steps'!$O$10 -> 2.9481807 | R90: =R92*'Production Steps'!$O$10 -> 3.1209514 | S90: =S92*'Production Steps'!$O$10 -> 3.3038469 | ... U90: =U92*'Production Steps'!$O$10 -> 3.7024203 | V90: =X90*0.8 -> 0 | W90: ='Production Steps'!H58*1.1*'Production Steps'!K58 -> 0 | X90: ='Production Steps'!I58*1.1*'Production Steps'!K58 -> 0
B91: MINCSABLU2 | C91: MIN.COA.SA.BLU.2 | D91: =CONCATENATE(MID(B91,4,6),"1") -> CSABLU1 | E91: 2010 | G91: 1.05 | H91: 1.05 | I91: 1.05 | J91: 1.05 | K91: 1.05 | L91: =L92*'Production Steps'!$O$11 -> 2.5478053 | M91: =M92*'Production Steps'!$O$11 -> 2.7087324 | N91: =N92*'Production Steps'!$O$11 -> 2.8810237 | O91: =O92*'Production Steps'!$O$11 -> 2.958265 | P91: =P92*'Production Steps'!$O$11 -> 3.1717804 | Q91: =Q92*'Production Steps'!$O$11 -> 3.343505 | R91: =R92*'Production Steps'!$O$11 -> 3.5394426 | S91: =S92*'Production Steps'!$O$11 -> 3.7468627 | ... U91: =U92*'Production Steps'!$O$11 -> 4.1988812 | V91: =X91*0.8 -> 0 | W91: ='Production Steps'!H59*1.1*'Production Steps'!K59 -> 0 | X91: ='Production Steps'!I59*1.1*'Production Steps'!K59 -> 0
B92: MINCSABLU3 | C92: MIN.COA.SA.BLU.3 | D92: =CONCATENATE(MID(B92,4,6),"1") -> CSABLU1 | E92: 2010 | G92: 1.05 | H92: 1.05 | I92: 1.05 | J92: 1.05 | K92: 1.05 | L92: ='AEO Coal Prices'!M18*'Production Steps'!$Q$17*$N$4 -> 2.5529111 | M92: ='AEO Coal Prices'!N18*'Production Steps'!$Q$17*$N$4 -> 2.7141607 | N92: ='AEO Coal Prices'!O18*'Production Steps'!$Q$17*$N$4 -> 2.8867972 | O92: ='AEO Coal Prices'!P18*'Production Steps'!$Q$17*$N$4 -> 2.9641934 | P92: ='AEO Coal Prices'!Q18*'Production Steps'!$Q$17*$N$4 -> 3.1781367 | Q92: ='AEO Coal Prices'!R18*'Production Steps'!$Q$17*$N$4 -> 3.3502054 | R92: ='AEO Coal Prices'!S18*'Production Steps'!$Q$17*$N$4 -> 3.5465357 | S92: =R92*(1+(R92-Q92)/Q92) -> 3.7543715 | T92: =S92*(1+(S92-R92)/R92) -> 3.9743869 | U92: =T92*(1+(T92-S92)/S92) -> 4.2072958 | V92: =X92*0.8 -> 0 | W92: ='Production Steps'!H60*1.1*'Production Steps'!K60 -> 0 | X92: ='Production Steps'!I60*1.1*'Production Steps'!K60 -> 0
B93: MINCSABLU4 | C93: MIN.COA.SA.BLU.4 | D93: =CONCATENATE(MID(B93,4,6),"1") -> CSABLU1 | E93: 2010 | G93: 1.05 | H93: 1.05 | I93: 1.05 | J93: 1.05 | K93: 1.05 | L93: =L92*'Production Steps'!$O$13 -> 2.5605699 | M93: =M92*'Production Steps'!$O$13 -> 2.7223032 | N93: =N92*'Production Steps'!$O$13 -> 2.8954576 | O93: =O92*'Production Steps'!$O$13 -> 2.973086 | P93: =P92*'Production Steps'!$O$13 -> 3.1876711 | Q93: =Q92*'Production Steps'!$O$13 -> 3.360256 | R93: =R92*'Production Steps'!$O$13 -> 3.5571753 | S93: =S92*'Production Steps'!$O$13 -> 3.7656346 | ... U93: =U92*'Production Steps'!$O$13 -> 4.2199177 | V93: =X93*0.8 -> 0 | W93: ='Production Steps'!H61*1.1*'Production Steps'!K61 -> 0 | X93: ='Production Steps'!I61*1.1*'Production Steps'!K61 -> 0
B94: MINCSABLU5 | C94: MIN.COA.SA.BLU.5 | D94: =CONCATENATE(MID(B94,4,6),"1") -> CSABLU1 | E94: 2010 | F94: =X94*0.1 -> 0 | G94: 1.05 | H94: 1.05 | I94: 1.05 | J94: 1.05 | K94: 1.05 | L94: =L92*'Production Steps'!$O$14 -> 2.8592605 | M94: =M92*'Production Steps'!$O$14 -> 3.03986 | N94: =N92*'Production Steps'!$O$14 -> 3.2332129 | O94: =O92*'Production Steps'!$O$14 -> 3.3198966 | P94: =P92*'Production Steps'!$O$14 -> 3.5595131 | Q94: =Q92*'Production Steps'!$O$14 -> 3.75223 | R94: =R92*'Production Steps'!$O$14 -> 3.97212 | S94: =S92*'Production Steps'!$O$14 -> 4.2048961 | ... U94: =U92*'Production Steps'!$O$14 -> 4.7121713 | W94: ='Production Steps'!H62*1.1*'Production Steps'!K62 -> 0 | X94: ='Production Steps'!I62*1.1*'Production Steps'!K62 -> 0
B95: MINCSABLU6 | C95: MIN.COA.SA.BLU.6 | D95: =CONCATENATE(MID(B95,4,6),"1") -> CSABLU1 | E95: 2010 | F95: =X95*0.1 -> 0 | G95: 1.05 | H95: 1.05 | I95: 1.05 | J95: 1.05 | K95: 1.05 | L95: =L92*'Production Steps'!$O$15 -> 3.905954 | M95: =M92*'Production Steps'!$O$15 -> 4.1526659 | N95: =N92*'Production Steps'!$O$15 -> 4.4167998 | O95: =O92*'Production Steps'!$O$15 -> 4.5352159 | P95: =P92*'Production Steps'!$O$15 -> 4.8625491 | Q95: =Q92*'Production Steps'!$O$15 -> 5.1258142 | R95: =R92*'Production Steps'!$O$15 -> 5.4261996 | S95: =S92*'Production Steps'!$O$15 -> 5.7441884 | ... U95: =U92*'Production Steps'!$O$15 -> 6.4371626 | W95: ='Production Steps'!H63*1.1*'Production Steps'!K63 -> 0 | X95: ='Production Steps'!I63*1.1*'Production Steps'!K63 -> 0
A96: *
A97: R0 | B97: MINCSABLS1 | C97: MIN.COA.SA.BLS.1 | D97: =CONCATENATE(MID(B97,4,6),"1") -> CSABLS1 | E97: 2010 | G97: 1.05 | H97: 1.05 | I97: 1.05 | J97: 1.05 | K97: 1.05 | L97: =L99*'Production Steps'!$O$10 -> 2.2465618 | M97: =M99*'Production Steps'!$O$10 -> 2.3884614 | N97: =N99*'Production Steps'!$O$10 -> 2.5403816 | O97: =O99*'Production Steps'!$O$10 -> 2.6084902 | P97: =P99*'Production Steps'!$O$10 -> 2.7967603 | Q97: =Q99*'Production Steps'!$O$10 -> 2.9481807 | R97: =R99*'Production Steps'!$O$10 -> 3.1209514 | S97: =S99*'Production Steps'!$O$10 -> 3.3038469 | ... U97: =U99*'Production Steps'!$O$10 -> 3.7024203 | V97: =X97*0.8 -> 5.470776 | W97: ='Production Steps'!H58*1.1*'Production Steps'!L58 -> 7.9057453 | X97: ='Production Steps'!I58*1.1*'Production Steps'!L58 -> 6.83847
B98: MINCSABLS2 | C98: MIN.COA.SA.BLS.2 | D98: =CONCATENATE(MID(B98,4,6),"1") -> CSABLS1 | E98: 2010 | G98: 1.05 | H98: 1.05 | I98: 1.05 | J98: 1.05 | K98: 1.05 | L98: =L99*'Production Steps'!$O$11 -> 2.5478053 | M98: =M99*'Production Steps'!$O$11 -> 2.7087324 | N98: =N99*'Production Steps'!$O$11 -> 2.8810237 | O98: =O99*'Production Steps'!$O$11 -> 2.958265 | P98: =P99*'Production Steps'!$O$11 -> 3.1717804 | Q98: =Q99*'Production Steps'!$O$11 -> 3.343505 | R98: =R99*'Production Steps'!$O$11 -> 3.5394426 | S98: =S99*'Production Steps'!$O$11 -> 3.7468627 | ... U98: =U99*'Production Steps'!$O$11 -> 4.1988812 | V98: =X98*0.8 -> 5.3613604 | W98: ='Production Steps'!H59*1.1*'Production Steps'!L59 -> 7.7476304 | X98: ='Production Steps'!I59*1.1*'Production Steps'!L59 -> 6.7017006
B99: MINCSABLS3 | C99: MIN.COA.SA.BLS.3 | D99: =CONCATENATE(MID(B99,4,6),"1") -> CSABLS1 | E99: 2010 | G99: 1.05 | H99: 1.05 | I99: 1.05 | J99: 1.05 | K99: 1.05 | L99: =L92 -> 2.5529111 | M99: =M92 -> 2.7141607 | N99: =N92 -> 2.8867972 | O99: =O92 -> 2.9641934 | P99: =P92 -> 3.1781367 | Q99: =Q92 -> 3.3502054 | R99: =R92 -> 3.5465357 | S99: =R99*(1+(R99-Q99)/Q99) -> 3.7543715 | T99: =S99*(1+(S99-R99)/R99) -> 3.9743869 | U99: =T99*(1+(T99-S99)/S99) -> 4.2072958 | V99: =X99*0.8 -> 0.10941552 | W99: ='Production Steps'!H60*1.1*'Production Steps'!L60 -> 0.15811491 | X99: ='Production Steps'!I60*1.1*'Production Steps'!L60 -> 0.1367694
B100: MINCSABLS4 | C100: MIN.COA.SA.BLS.4 | D100: =CONCATENATE(MID(B100,4,6),"1") -> CSABLS1 | E100: 2010 | G100: 1.05 | H100: 1.05 | I100: 1.05 | J100: 1.05 | K100: 1.05 | L100: =L99*'Production Steps'!$O$13 -> 2.5605699 | M100: =M99*'Production Steps'!$O$13 -> 2.7223032 | N100: =N99*'Production Steps'!$O$13 -> 2.8954576 | O100: =O99*'Production Steps'!$O$13 -> 2.973086 | P100: =P99*'Production Steps'!$O$13 -> 3.1876711 | Q100: =Q99*'Production Steps'!$O$13 -> 3.360256 | R100: =R99*'Production Steps'!$O$13 -> 3.5571753 | S100: =S99*'Production Steps'!$O$13 -> 3.7656346 | ... U100: =U99*'Production Steps'!$O$13 -> 4.2199177 | V100: =X100*0.8 -> 0.10941552 | W100: ='Production Steps'!H61*1.1*'Production Steps'!L61 -> 0.15811491 | X100: ='Production Steps'!I61*1.1*'Production Steps'!L61 -> 0.1367694
B101: MINCSABLS5 | C101: MIN.COA.SA.BLS.5 | D101: =CONCATENATE(MID(B101,4,6),"1") -> CSABLS1 | E101: 2010 | F101: =X101*0.1 -> 0.12309246 | G101: 1.05 | H101: 1.05 | I101: 1.05 | J101: 1.05 | K101: 1.05 | L101: =L99*'Production Steps'!$O$14 -> 2.8592605 | M101: =M99*'Production Steps'!$O$14 -> 3.03986 | N101: =N99*'Production Steps'!$O$14 -> 3.2332129 | O101: =O99*'Production Steps'!$O$14 -> 3.3198966 | P101: =P99*'Production Steps'!$O$14 -> 3.5595131 | Q101: =Q99*'Production Steps'!$O$14 -> 3.75223 | R101: =R99*'Production Steps'!$O$14 -> 3.97212 | S101: =S99*'Production Steps'!$O$14 -> 4.2048961 | ... U101: =U99*'Production Steps'!$O$14 -> 4.7121713 | W101: ='Production Steps'!H62*1.1*'Production Steps'!L62 -> 1.4230342 | X101: ='Production Steps'!I62*1.1*'Production Steps'!L62 -> 1.2309246
B102: MINCSABLS6 | C102: MIN.COA.SA.BLS.6 | D102: =CONCATENATE(MID(B102,4,6),"1") -> CSABLS1 | E102: 2010 | F102: =X102*0.1 -> 0.1367694 | G102: 1.05 | H102: 1.05 | I102: 1.05 | J102: 1.05 | K102: 1.05 | L102: =L99*'Production Steps'!$O$15 -> 3.905954 | M102: =M99*'Production Steps'!$O$15 -> 4.1526659 | N102: =N99*'Production Steps'!$O$15 -> 4.4167998 | O102: =O99*'Production Steps'!$O$15 -> 4.5352159 | P102: =P99*'Production Steps'!$O$15 -> 4.8625491 | Q102: =Q99*'Production Steps'!$O$15 -> 5.1258142 | R102: =R99*'Production Steps'!$O$15 -> 5.4261996 | S102: =S99*'Production Steps'!$O$15 -> 5.7441884 | ... U102: =U99*'Production Steps'!$O$15 -> 6.4371626 | W102: ='Production Steps'!H63*1.1*'Production Steps'!L63 -> 1.5811491 | X102: ='Production Steps'!I63*1.1*'Production Steps'!L63 -> 1.367694
A103: *
A104: R0 | B104: MINCSABMU1 | C104: MIN.COA.SA.BMU.1 | D104: =CONCATENATE(MID(B104,4,6),"1") -> CSABMU1 | E104: 2010 | G104: 1.05 | H104: 1.01 | I104: 1.005 | J104: 1.005 | K104: 1.05 | L104: =L106*'Production Steps'!$O$10 -> 1.9743779 | M104: =M106*'Production Steps'!$O$10 -> 2.3949639 | N104: =N106*'Production Steps'!$O$10 -> 2.0791335 | O104: =O106*'Production Steps'!$O$10 -> 2.1435524 | P104: =P106*'Production Steps'!$O$10 -> 2.2182236 | Q104: =Q106*'Production Steps'!$O$10 -> 2.2959556 | R104: =R106*'Production Steps'!$O$10 -> 2.3915625 | S104: =S106*'Production Steps'!$O$10 -> 2.4911505 | ... U104: =U106*'Production Steps'!$O$10 -> 2.7029404 | V104: =X104*0.8 -> 4.741346 | W104: ='Production Steps'!H65*1.1*'Production Steps'!K65 -> 8.7455124 | X104: ='Production Steps'!I65*1.1*'Production Steps'!K65 -> 5.9266825
B105: MINCSABMU2 | C105: MIN.COA.SA.BMU.2 | D105: =CONCATENATE(MID(B105,4,6),"1") -> CSABMU1 | E105: 2010 | G105: 1.05 | H105: 1.01 | I105: 1.005 | J105: 1.005 | K105: 1.05 | L105: =L106*'Production Steps'!$O$11 -> 2.239124 | M105: =M106*'Production Steps'!$O$11 -> 2.7161068 | N105: =N106*'Production Steps'!$O$11 -> 2.3579264 | O105: =O106*'Production Steps'!$O$11 -> 2.4309833 | P105: =P106*'Production Steps'!$O$11 -> 2.5156672 | Q105: =Q106*'Production Steps'!$O$11 -> 2.6038224 | R105: =R106*'Production Steps'!$O$11 -> 2.7122493 | S105: =S106*'Production Steps'!$O$11 -> 2.8251912 | ... U105: =U106*'Production Steps'!$O$11 -> 3.0653801 | V105: =X105*0.8 -> 4.6465191 | W105: ='Production Steps'!H66*1.1*'Production Steps'!K66 -> 8.5706021 | X105: ='Production Steps'!I66*1.1*'Production Steps'!K66 -> 5.8081488
B106: MINCSABMU3 | C106: MIN.COA.SA.BMU.3 | D106: =CONCATENATE(MID(B106,4,6),"1") -> CSABMU1 | E106: 2010 | G106: 1.05 | H106: 1.01 | I106: 1.005 | J106: 1.005 | K106: 1.05 | L106: ='AEO Coal Prices'!M19*'Production Steps'!$Q$17*$N$4 -> 2.2436112 | M106: ='AEO Coal Prices'!N19*'Production Steps'!$Q$17*$N$4 -> 2.7215499 | N106: ='AEO Coal Prices'!O19*'Production Steps'!$Q$17*$N$4 -> 2.3626517 | O106: ='AEO Coal Prices'!P19*'Production Steps'!$Q$17*$N$4 -> 2.435855 | P106: ='AEO Coal Prices'!Q19*'Production Steps'!$Q$17*$N$4 -> 2.5207086 | Q106: ='AEO Coal Prices'!R19*'Production Steps'!$Q$17*$N$4 -> 2.6090405 | R106: ='AEO Coal Prices'!S19*'Production Steps'!$Q$17*$N$4 -> 2.7176846 | S106: =R106*(1+(R106-Q106)/Q106) -> 2.8308529 | T106: =S106*(1+(S106-R106)/R106) -> 2.9487337 | U106: =T106*(1+(T106-S106)/S106) -> 3.0715231 | V106: =X106*0.8 -> 0.09482692 | W106: ='Production Steps'!H67*1.1*'Production Steps'!K67 -> 0.17491025 | X106: ='Production Steps'!I67*1.1*'Production Steps'!K67 -> 0.11853365
B107: MINCSABMU4 | C107: MIN.COA.SA.BMU.4 | D107: =CONCATENATE(MID(B107,4,6),"1") -> CSABMU1 | E107: 2010 | G107: 1.05 | H107: 1.01 | I107: 1.005 | J107: 1.005 | K107: 1.05 | L107: =L106*'Production Steps'!$O$13 -> 2.2503421 | M107: =M106*'Production Steps'!$O$13 -> 2.7297146 | N107: =N106*'Production Steps'!$O$13 -> 2.3697397 | O107: =O106*'Production Steps'!$O$13 -> 2.4431626 | P107: =P106*'Production Steps'!$O$13 -> 2.5282708 | Q107: =Q106*'Production Steps'!$O$13 -> 2.6168676 | R107: =R106*'Production Steps'!$O$13 -> 2.7258377 | S107: =S106*'Production Steps'!$O$13 -> 2.8393455 | ... U107: =U106*'Production Steps'!$O$13 -> 3.0807377 | V107: =X107*0.8 -> 0.09482692 | W107: ='Production Steps'!H68*1.1*'Production Steps'!K68 -> 0.17491025 | X107: ='Production Steps'!I68*1.1*'Production Steps'!K68 -> 0.11853365
...

Sheet ANSv6.1-Technologies
A1: ANSWER-Technologies
B7: TechName | C7: TechDesc | D7: TACTUnit | E7: TCAPUnit | F7: Set Memberships | G7: Comment

Sheet ANSv6.1-Constraints
A1: ANSWER-Constraints
B7: ConstrName | C7: ConstrDesc | D7: Units | E7: Set Memberships | F7: Comment

Sheet ANSv6.1-CommData
A1: ANSWER-CommData
B7: CommName | C7: CommDesc | D7: Units

Sheet ANSv6.1-TechData
A1: ANSWER-TechData
B7: TechName | C7: TechDesc | D7: Units | E7: CommIN | F7: CommOUT

Sheet AEO Coal Prices
A1: Coal Minemouth Prices by Region and Type, Reference case
A2: (2012 dollars per short ton) | L2: PJ per million btu | O2: 1.055056e-06
A4: Supply Regions and Coal Types | B4: 2005 | C4: 2010 | D4: 2015 | E4: 2020 | F4: 2025 | G4: 2030 | H4: 2035 | I4: 2040 | L4: 2005 | M4: 2010 | N4: 2015 | O4: 2020 | P4: 2025 | Q4: 2030 | R4: 2035 | S4: 2040 | X4: 2005 | Y4: 2010 | Z4: 2015 | AA4: 2020 | AB4: 2025 | AC4: 2030 | AD4: 2035 | AE4: 2040
A6: Northern Appalachia 1/ | B6: 35.065239 | C6: 54.224152 | D6: 67.093102 | E6: 75.796234 | F6: 84.36412 | G6: 89.95134 | H6: 96.711006 | I6: 103.28035
A7: Medium Sulfur (Premium) 2/ | B7: 70.030243 | C7: 83.834381 | D7: 105.43449 | E7: 120.82428 | F7: 141.92157 | G7: 154.62036 | H7: 168.06445 | I7: 182.31543 | L7: =B7*'Conversion Factors'!$C$38/Types!$R$9/$O$2/1000000 -> 2.4485497 | M7: =C7*'Conversion Factors'!$C$41/Types!$R$9/$O$2/1000000 -> 2.7793052 | N7: =D7*'Conversion Factors'!$C$44/Types!$R$9/$O$2/1000000 -> 3.3288883 | O7: =E7*'Conversion Factors'!$C$44/Types!$R$9/$O$2/1000000 -> 3.8147908 | P7: =F7*'Conversion Factors'!$C$44/Types!$R$9/$O$2/1000000 -> 4.4808965 | Q7: =G7*'Conversion Factors'!$C$44/Types!$R$9/$O$2/1000000 -> 4.8818361 | R7: =H7*'Conversion Factors'!$C$44/Types!$R$9/$O$2/1000000 -> 5.306307 | S7: =I7*'Conversion Factors'!$C$44/Types!$R$9/$O$2/1000000 -> 5.7562538 | U7: =L7/M7 -> 0.88099345 | X7: =L7*'AEO Coal Prod'!L7 -> 237.79802 | Y7: =M7*'AEO Coal Prod'!M7 -> 1406.7398 | Z7: =N7*'AEO Coal Prod'!N7 -> 1873.1986 | AA7: =O7*'AEO Coal Prod'!O7 -> 2590.0824 | AB7: =P7*'AEO Coal Prod'!P7 -> 3707.0742 | AC7: =Q7*'AEO Coal Prod'!Q7 -> 4138.155 | AD7: =R7*'AEO Coal Prod'!R7 -> 5012.3347 | AE7: =S7*'AEO Coal Prod'!S7 -> 5737.1816
A8: Medium Sulfur (Bituminous) | B8: 36.763557 | C8: 53.896236 | D8: 62.629608 | E8: 68.200325 | F8: 71.26239 | G8: 74.472549 | H8: 77.522125 | I8: 80.92083 | L8: =B8*'Conversion Factors'!$C$38/Types!$R$4/$O$2/1000000 -> 1.3420491 | M8: =C8*'Conversion Factors'!$C$41/Types!$R$4/$O$2/1000000 -> 1.8655208 | N8: =D8*'Conversion Factors'!$C$44/Types!$R$4/$O$2/1000000 -> 2.0645423 | O8: =E8*'Conversion Factors'!$C$44/Types!$R$4/$O$2/1000000 -> 2.2481772 | P8: =F8*'Conversion Factors'!$C$44/Types!$R$4/$O$2/1000000 -> 2.3491161 | Q8: =G8*'Conversion Factors'!$C$44/Types!$R$4/$O$2/1000000 -> 2.4549368 | R8: =H8*'Conversion Factors'!$C$44/Types!$R$4/$O$2/1000000 -> 2.5554639 | S8: =I8*'Conversion Factors'!$C$44/Types!$R$4/$O$2/1000000 -> 2.6674999 | U8: =L8/M8 -> 0.71939647 | X8: =L8*'AEO Coal Prod'!L8 -> 2675.7724 | Y8: =M8*'AEO Coal Prod'!M8 -> 1817.3632 | Z8: =N8*'AEO Coal Prod'!N8 -> 1112.6984 | AA8: =O8*'AEO Coal Prod'!O8 -> 1522.2824 | AB8: =P8*'AEO Coal Prod'!P8 -> 1502.9772 | AC8: =Q8*'AEO Coal Prod'!Q8 -> 1664.1689 | AD8: =R8*'AEO Coal Prod'!R8 -> 1650.1024 | AE8: =S8*'AEO Coal Prod'!S8 -> 1736.8888
A9: High Sulfur (Bituminous) | B9: 31.007643 | C9: 51.845879 | D9: 59.57877 | E9: 65.990654 | F9: 68.828491 | G9: 72.055786 | H9: 74.698196 | I9: 77.850006 | L9: =B9*'Conversion Factors'!$C$38/Types!$R$5/$O$2/1000000 -> 1.1557892 | M9: =C9*'Conversion Factors'!$C$41/Types!$R$5/$O$2/1000000 -> 1.8323774 | N9: =D9*'Conversion Factors'!$C$44/Types!$R$5/$O$2/1000000 -> 2.0053706 | O9: =E9*'Conversion Factors'!$C$44/Types!$R$5/$O$2/1000000 -> 2.2211891 | P9: =F9*'Conversion Factors'!$C$44/Types!$R$5/$O$2/1000000 -> 2.3167083 | Q9: =G9*'Conversion Factors'!$C$44/Types!$R$5/$O$2/1000000 -> 2.4253363 | R9: =H9*'Conversion Factors'!$C$44/Types!$R$5/$O$2/1000000 -> 2.5142776 | S9: =I9*'Conversion Factors'!$C$44/Types!$R$5/$O$2/1000000 -> 2.6203648 | U9: =L9/M9 -> 0.63075938 | X9: =L9*'AEO Coal Prod'!L9 -> 1851.9187 | Y9: =M9*'AEO Coal Prod'!M9 -> 3718.3268 | Z9: =N9*'AEO Coal Prod'!N9 -> 4772.208 | AA9: =O9*'AEO Coal Prod'!O9 -> 5355.0519 | AB9: =P9*'AEO Coal Prod'!P9 -> 5436.5377 | AC9: =Q9*'AEO Coal Prod'!Q9 -> 5576.119 | AD9: =R9*'AEO Coal Prod'!R9 -> 5835.2476 | AE9: =S9*'AEO Coal Prod'!S9 -> 6144.6021
A11: Central Appalachia | B11: 46.536526 | C11: 78.00705 | D11: 102.05424 | E11: 119.74264 | F11: 129.09392 | G11: 141.12996 | H11: 147.79279 | I11: 152.37442
A12: Medium Sulfur (Premium) 2/ | B12: 66.089821 | C12: 110.09124 | D12: 137.23921 | E12: 157.73831 | F12: 172.63171 | G12: 188.77013 | H12: 200.48785 | I12: 207.27634 | L12: =B12*'Conversion Factors'!$C$38/Types!$R$14/$O$2/1000000 -> 2.3107761 | M12: =C12*'Conversion Factors'!$C$41/Types!$R$14/$O$2/1000000 -> 3.6497813 | N12: =D12*'Conversion Factors'!$C$44/Types!$R$14/$O$2/1000000 -> 4.3330602 | O12: =E12*'Conversion Factors'!$C$44/Types!$R$14/$O$2/1000000 -> 4.9802793 | P12: =F12*'Conversion Factors'!$C$44/Types!$R$14/$O$2/1000000 -> 5.4505094 | Q12: =G12*'Conversion Factors'!$C$44/Types!$R$14/$O$2/1000000 -> 5.9600482 | R12: =H12*'Conversion Factors'!$C$44/Types!$R$14/$O$2/1000000 -> 6.3300126 | S12: =I12*'Conversion Factors'!$C$44/Types!$R$14/$O$2/1000000 -> 6.5443457 | U12: =L12/M12 -> 0.63312727 | X12: =L12*'AEO Coal Prod'!L12 -> 2514.7611 | Y12: =M12*'AEO Coal Prod'!M12 -> 6245.3669 | Z12: =N12*'AEO Coal Prod'!N12 -> 6469.3048 | AA12: =O12*'AEO Coal Prod'!O12 -> 7638.4753 | AB12: =P12*'AEO Coal Prod'!P12 -> 8010.4103 | AC12: =Q12*'AEO Coal Prod'!Q12 -> 8498.1819 | AD12: =R12*'AEO Coal Prod'!R12 -> 8531.6439 | AE12: =S12*'AEO Coal Prod'!S12 -> 7740.0688
A13: Low Sulfur (Bituminous) | B13: 44.572205 | C13: 69.05088 | D13: 74.815384 | E13: 79.993484 | F13: 83.592361 | G13: 94.048553 | H13: 101.10722 | I13: 111.37326 | L13: =B13*'Conversion Factors'!$C$38/Types!$R$10/$O$2/1000000 -> 1.6580388 | M13: =C13*'Conversion Factors'!$C$41/Types!$R$10/$O$2/1000000 -> 2.4355137 | N13: =D13*'Conversion Factors'!$C$44/Types!$R$10/$O$2/1000000 -> 2.5131285 | O13: =E13*'Conversion Factors'!$C$44/Types!$R$10/$O$2/1000000 -> 2.6870664 | P13: =F13*'Conversion Factors'!$C$44/Types!$R$10/$O$2/1000000 -> 2.8079565 | Q13: =G13*'Conversion Factors'!$C$44/Types!$R$10/$O$2/1000000 -> 3.1591912 | R13: =H13*'Conversion Factors'!$C$44/Types!$R$10/$O$2/1000000 -> 3.3962992 | S13: =I13*'Conversion Factors'!$C$44/Types!$R$10/$O$2/1000000 -> 3.7411466 | U13: =L13/M13 -> 0.6807758 | X13: =L13*'AEO Coal Prod'!L13 -> 2038.056 | Y13: =M13*'AEO Coal Prod'!M13 -> 890.30466 | Z13: =N13*'AEO Coal Prod'!N13 -> 368.58316 | AA13: =O13*'AEO Coal Prod'!O13 -> 385.28918 | AB13: =P13*'AEO Coal Prod'!P13 -> 341.03435 | AC13: =Q13*'AEO Coal Prod'!Q13 -> 430.72804 | AD13: =R13*'AEO Coal Prod'!R13 -> 450.95728 | AE13: =S13*'AEO Coal Prod'!S13 -> 517.01096
A14: Medium Sulfur (Bituminous) | B14: 42.024334 | C14: 65.239883 | D14: 69.93129 | E14: 75.058334 | F14: 77.891731 | G14: 80.787262 | H14: 83.894447 | I14: 87.105888 | L14: =B14*'Conversion Factors'!$C$38/Types!$R$11/$O$2/1000000 -> 1.5670643 | M14: =C14*'Conversion Factors'!$C$41/Types!$R$11/$O$2/1000000 -> 2.3066937 | N14: =D14*'Conversion Factors'!$C$44/Types!$R$11/$O$2/1000000 -> 2.3547821 | O14: =E14*'Conversion Factors'!$C$44/Types!$R$11/$O$2/1000000 -> 2.527424 | P14: =F14*'Conversion Factors'!$C$44/Types!$R$11/$O$2/1000000 -> 2.6228324 | Q14: =G14*'Conversion Factors'!$C$44/Types!$R$11/$O$2/1000000 -> 2.720333 | R14: =H14*'Conversion Factors'!$C$44/Types!$R$11/$O$2/1000000 -> 2.8249606 | S14: =I14*'Conversion Factors'!$C$44/Types!$R$11/$O$2/1000000 -> 2.9330988 | U14: =L14/M14 -> 0.67935515 | X14: =L14*'AEO Coal Prod'!L14 -> 6092.8748 | Y14: =M14*'AEO Coal Prod'!M14 -> 6560.0643 | Z14: =N14*'AEO Coal Prod'!N14 -> 3318.5751 | AA14: =O14*'AEO Coal Prod'!O14 -> 2769.0437 | AB14: =P14*'AEO Coal Prod'!P14 -> 2790.8921 | AC14: =Q14*'AEO Coal Prod'!Q14 -> 2582.6564 | AD14: =R14*'AEO Coal Prod'!R14 -> 2670.751 | AE14: =S14*'AEO Coal Prod'!S14 -> 2482.0496
A16: Southern Appalachia | B16: 55.298611 | C16: 78.789536 | D16: 125.83792 | E16: 140.53088 | F16: 144.94121 | G16: 154.81975 | H16: 162.00633 | I16: 168.1198
A17: Low Sulfur (Premium) 2/ | B17: 73.135132 | C17: 87.973717 | D17: 138.49081 | E17: 155.08452 | F17: 166.79222 | G17: 179.67328 | H17: 189.66991 | I17: 193.24593 | L17: =B17*'Conversion Factors'!$C$38/Types!$R$19/$O$2/1000000 -> 2.5571096 | M17: =C17*'Conversion Factors'!$C$41/Types!$R$19/$O$2/1000000 -> 2.9165339 | N17: =D17*'Conversion Factors'!$C$44/Types!$R$19/$O$2/1000000 -> 4.3725771 | O17: =E17*'Conversion Factors'!$C$44/Types!$R$19/$O$2/1000000 -> 4.8964909 | P17: =F17*'Conversion Factors'!$C$44/Types!$R$19/$O$2/1000000 -> 5.2661388 | Q17: =G17*'Conversion Factors'!$C$44/Types!$R$19/$O$2/1000000 -> 5.672833 | R17: =H17*'Conversion Factors'!$C$44/Types!$R$19/$O$2/1000000 -> 5.9884571 | S17: =I17*'Conversion Factors'!$C$44/Types!$R$19/$O$2/1000000 -> 6.1013629 | U17: =L17/M17 -> 0.87676321 | X17: =L17*'AEO Coal Prod'!L17 -> 573.31322 | Y17: =M17*'AEO Coal Prod'!M17 -> 826.77563 | Z17: =N17*'AEO Coal Prod'!N17 -> 1526.0323 | AA17: =O17*'AEO Coal Prod'!O17 -> 1776.0633 | AB17: =P17*'AEO Coal Prod'!P17 -> 1807.002 | AC17: =Q17*'AEO Coal Prod'!Q17 -> 1899.1006 | AD17: =R17*'AEO Coal Prod'!R17 -> 1905.3967 | AE17: =S17*'AEO Coal Prod'!S17 -> 2152.2281
A18: Low Sulfur (Bituminous) | B18: 49.286278 | C18: 77.487556 | D18: 86.502647 | E18: 92.004723 | F18: 94.471405 | G18: 101.28996 | H18: 106.77394 | I18: 113.03116 | L18: =B18*'Conversion Factors'!$C$38/Types!$R$15/$O$2/1000000 -> 1.7298314 | M18: =C18*'Conversion Factors'!$C$41/Types!$R$15/$O$2/1000000 -> 2.5786981 | N18: =D18*'Conversion Factors'!$C$44/Types!$R$15/$O$2/1000000 -> 2.7415765 | O18: =E18*'Conversion Factors'!$C$44/Types!$R$15/$O$2/1000000 -> 2.9159568 | P18: =F18*'Conversion Factors'!$C$44/Types!$R$15/$O$2/1000000 -> 2.9941347 | Q18: =G18*'Conversion Factors'!$C$44/Types!$R$15/$O$2/1000000 -> 3.2102391 | R18: =H18*'Conversion Factors'!$C$44/Types!$R$15/$O$2/1000000 -> 3.3840458 | S18: =I18*'Conversion Factors'!$C$44/Types!$R$15/$O$2/1000000 -> 3.5823593 | U18: =L18/M18 -> 0.67081577 | X18: =L18*'AEO Coal Prod'!L18 -> 24.864739 | Y18: =M18*'AEO Coal Prod'!M18 -> 32.062454 | Z18: =N18*'AEO Coal Prod'!N18 -> 49.756096 | AA18: =O18*'AEO Coal Prod'!O18 -> 39.901195 | AB18: =P18*'AEO Coal Prod'!P18 -> 38.447614 | AC18: =Q18*'AEO Coal Prod'!Q18 -> 40.995522 | AD18: =R18*'AEO Coal Prod'!R18 -> 42.510881 | AE18: =S18*'AEO Coal Prod'!S18 -> 41.182621
A19: Medium Sulfur (Bituminous) | B19: 44.334949 | C19: 63.498878 | D19: 80.878357 | E19: 70.212708 | F19: 72.388145 | G19: 74.909805 | H19: 77.534828 | I19: 80.763489 | L19: =B19*'Conversion Factors'!$C$38/Types!$R$16/$O$2/1000000 -> 1.6687904 | M19: =C19*'Conversion Factors'!$C$41/Types!$R$16/$O$2/1000000 -> 2.266274 | N19: =D19*'Conversion Factors'!$C$44/Types!$R$16/$O$2/1000000 -> 2.7490403 | O19: =E19*'Conversion Factors'!$C$44/Types!$R$16/$O$2/1000000 -> 2.3865169 | P19: =F19*'Conversion Factors'!$C$44/Types!$R$16/$O$2/1000000 -> 2.4604596 | Q19: =G19*'Conversion Factors'!$C$44/Types!$R$16/$O$2/1000000 -> 2.5461704 | R19: =H19*'Conversion Factors'!$C$44/Types!$R$16/$O$2/1000000 -> 2.6353944 | S19: =I19*'Conversion Factors'!$C$44/Types!$R$16/$O$2/1000000 -> 2.745136 | U19: =L19/M19 -> 0.73635862 | X19: =L19*'AEO Coal Prod'!L19 -> 553.14852 | Y19: =M19*'AEO Coal Prod'!M19 -> 509.0715 | Z19: =N19*'AEO Coal Prod'!N19 -> 210.10728 | AA19: =O19*'AEO Coal Prod'!O19 -> 145.40784 | AB19: =P19*'AEO Coal Prod'!P19 -> 215.69914 | AC19: =Q19*'AEO Coal Prod'!Q19 -> 225.94837 | AD19: =R19*'AEO Coal Prod'!R19 -> 234.89885 | AE19: =S19*'AEO Coal Prod'!S19 -> 240.15999
A21: Eastern Interior | B21: w | C21: 44.883808 | D21: 52.043491 | E21: 57.922966 | F21: 59.986744 | G21: 62.594608 | H21: 64.764236 | I21: 66.851547
A22: Medium Sulfur (Bituminous) | B22: 31.141741 | C22: 54.252983 | D22: 58.842049 | E22: 64.748085 | F22: 66.657181 | G22: 69.43602 | H22: 71.616425 | I22: 73.522926 | L22: =B22*'Conversion Factors'!$C$38/Types!$R$20/$O$2/1000000 -> 1.2721737 | M22: =C22*'Conversion Factors'!$C$41/Types!$R$20/$O$2/1000000 -> 2.1014446 | N22: =D22*'Conversion Factors'!$C$44/Types!$R$20/$O$2/1000000 -> 2.1706237 | O22: =E22*'Conversion Factors'!$C$44/Types!$R$20/$O$2/1000000 -> 2.3884914 | P22: =F22*'Conversion Factors'!$C$44/Types!$R$20/$O$2/1000000 -> 2.4589161 | Q22: =G22*'Conversion Factors'!$C$44/Types!$R$20/$O$2/1000000 -> 2.5614246 | R22: =H22*'Conversion Factors'!$C$44/Types!$R$20/$O$2/1000000 -> 2.6418576 | S22: =I22*'Conversion Factors'!$C$44/Types!$R$20/$O$2/1000000 -> 2.7121865 | U22: =L22/M22 -> 0.60538056 | X22: =L22*'AEO Coal Prod'!L22 -> 883.73754 | Y22: =M22*'AEO Coal Prod'!M22 -> 509.92359 | Z22: =N22*'AEO Coal Prod'!N22 -> 425.42013 | AA22: =O22*'AEO Coal Prod'!O22 -> 428.84363 | AB22: =P22*'AEO Coal Prod'!P22 -> 454.63815 | AC22: =Q22*'AEO Coal Prod'!Q22 -> 492.67564 | AD22: =R22*'AEO Coal Prod'!R22 -> 521.80672 | AE22: =S22*'AEO Coal Prod'!S22 -> 542.76888
A23: High Sulfur (Bituminous) | B23: 26.623665 | C23: 44.272259 | D23: 53.015858 | E23: 58.978973 | F23: 60.857269 | G23: 63.613976 | H23: 65.766449 | I23: 67.85173 | L23: =B23*'Conversion Factors'!$C$38/Types!$R$21/$O$2/1000000 -> 1.0761318 | M23: =C23*'Conversion Factors'!$C$41/Types!$R$21/$O$2/1000000 -> 1.6967588 | N23: =D23*'Conversion Factors'!$C$44/Types!$R$21/$O$2/1000000 -> 1.9350699 | O23: =E23*'Conversion Factors'!$C$44/Types!$R$21/$O$2/1000000 -> 2.1527226 | P23: =F23*'Conversion Factors'!$C$44/Types!$R$21/$O$2/1000000 -> 2.22128 | Q23: =G23*'Conversion Factors'!$C$44/Types!$R$21/$O$2/1000000 -> 2.3218994 | R23: =H23*'Conversion Factors'!$C$44/Types!$R$21/$O$2/1000000 -> 2.4004643 | S23: =I23*'Conversion Factors'!$C$44/Types!$R$21/$O$2/1000000 -> 2.4765767 | U23: =L23/M23 -> 0.63422793 | X23: =L23*'AEO Coal Prod'!L23 -> 1644.0719 | Y23: =M23*'AEO Coal Prod'!M23 -> 4327.2105 | Z23: =N23*'AEO Coal Prod'!N23 -> 6752.4218 | AA23: =O23*'AEO Coal Prod'!O23 -> 8377.1457 | AB23: =P23*'AEO Coal Prod'!P23 -> 9223.8597 | AC23: =Q23*'AEO Coal Prod'!Q23 -> 10594.216 | AD23: =R23*'AEO Coal Prod'!R23 -> 11665.128 | AE23: =S23*'AEO Coal Prod'!S23 -> 12609.018
A24: Medium Sulfur (Lignite) | B24: w | C24: 20.302601 | D24: 22.685019 | E24: 26.098757 | F24: 26.653751 | G24: 28.637218 | H24: 29.263145 | I24: 30.115891 | L24: =M24*$U$60 -> 1.1723251 | M24: =C24*'Conversion Factors'!$C$41/Types!$R$24/$O$2/1000000 -> 1.708684 | N24: =D24*'Conversion Factors'!$C$44/Types!$R$24/$O$2/1000000 -> 1.8182418 | O24: =E24*'Conversion Factors'!$C$44/Types!$R$24/$O$2/1000000 -> 2.0918586 | P24: =F24*'Conversion Factors'!$C$44/Types!$R$24/$O$2/1000000 -> 2.1363423 | Q24: =G24*'Conversion Factors'!$C$44/Types!$R$24/$O$2/1000000 -> 2.2953205 | R24: =H24*'Conversion Factors'!$C$44/Types!$R$24/$O$2/1000000 -> 2.3454895 | S24: =I24*'Conversion Factors'!$C$44/Types!$R$24/$O$2/1000000 -> 2.4138385
A26: Western Interior High Sulfur (Bituminous) | B26: 30.347471 | C26: 56.689579 | D26: 48.515842 | E26: 56.246765 | F26: 57.939674 | G26: 59.226864 | H26: 61.727329 | I26: 64.839836 | L26: =B26*'Conversion Factors'!$C$38/Types!$R$25/$O$2/1000000 -> 1.3132355 | M26: =C26*'Conversion Factors'!$C$41/Types!$R$25/$O$2/1000000 -> 2.3260236 | N26: =D26*'Conversion Factors'!$C$44/Types!$R$25/$O$2/1000000 -> 1.8958191 | O26: =E26*'Conversion Factors'!$C$44/Types!$R$25/$O$2/1000000 -> 2.1979149 | P26: =F26*'Conversion Factors'!$C$44/Types!$R$25/$O$2/1000000 -> 2.2640675 | Q26: =G26*'Conversion Factors'!$C$44/Types!$R$25/$O$2/1000000 -> 2.3143661 | R26: =H26*'Conversion Factors'!$C$44/Types!$R$25/$O$2/1000000 -> 2.412075 | S26: =I26*'Conversion Factors'!$C$44/Types!$R$25/$O$2/1000000 -> 2.5337002 | U26: =L26/M26 -> 0.5645839 | X26: =L26*'AEO Coal Prod'!L26 -> 77.434202 | Y26: =M26*'AEO Coal Prod'!M26 -> 92.825773 | Z26: =N26*'AEO Coal Prod'!N26 -> 48.195414 | AA26: =O26*'AEO Coal Prod'!O26 -> 34.121843 | AB26: =P26*'AEO Coal Prod'!P26 -> 42.511157 | AC26: =Q26*'AEO Coal Prod'!Q26 -> 32.680172 | AD26: =R26*'AEO Coal Prod'!R26 -> 30.101866 | AE26: =S26*'AEO Coal Prod'!S26 -> 31.192019
A28: Gulf | B28: w | C28: 18.071056 | D28: 21.312981 | E28: 23.479725 | F28: 25.807581 | G28: 27.817467 | H28: 28.947941 | I28: 29.977573
A29: Medium Sulfur (Lignite) | B29: w | C29: 19.59021 | D29: 21.080399 | E29: 23.227949 | F29: 26.073206 | G29: 28.448868 | H29: 29.704285 | I29: 30.773726 | L29: =M29*$U$60 -> 0.87066314 | M29: =C29*'Conversion Factors'!$C$41/Types!$R$26/$O$2/1000000 -> 1.2690065 | N29: =D29*'Conversion Factors'!$C$44/Types!$R$26/$O$2/1000000 -> 1.300487 | O29: =E29*'Conversion Factors'!$C$44/Types!$R$26/$O$2/1000000 -> 1.4329732 | P29: =F29*'Conversion Factors'!$C$44/Types!$R$26/$O$2/1000000 -> 1.6085021 | Q29: =G29*'Conversion Factors'!$C$44/Types!$R$26/$O$2/1000000 -> 1.7550609 | R29: =H29*'Conversion Factors'!$C$44/Types!$R$26/$O$2/1000000 -> 1.8325098 | S29: =I29*'Conversion Factors'!$C$44/Types!$R$26/$O$2/1000000 -> 1.8984855 | X29: =L29*'AEO Coal Prod'!L29 -> 288.33627 | Y29: =M29*'AEO Coal Prod'!M29 -> 701.68184 | Z29: =N29*'AEO Coal Prod'!N29 -> 551.96137 | AA29: =O29*'AEO Coal Prod'!O29 -> 696.37031 | AB29: =P29*'AEO Coal Prod'!P29 -> 914.03116 | AC29: =Q29*'AEO Coal Prod'!Q29 -> 1090.2552 | AD29: =R29*'AEO Coal Prod'!R29 -> 1137.6836 | AE29: =S29*'AEO Coal Prod'!S29 -> 1192.5656
A30: High Sulfur (Lignite) | B30: w | C30: 16.875051 | D30: 21.772913 | E30: 23.997196 | F30: 25.169128 | G30: 26.153002 | H30: 26.94739 | I30: 27.840399 | L30: =M30*$U$60 -> 0.84194174 | M30: =C30*'Conversion Factors'!$C$41/Types!$R$27/$O$2/1000000 -> 1.2271446 | N30: =D30*'Conversion Factors'!$C$44/Types!$R$27/$O$2/1000000 -> 1.5078898 | O30: =E30*'Conversion Factors'!$C$44/Types!$R$27/$O$2/1000000 -> 1.6619332 | P30: =F30*'Conversion Factors'!$C$44/Types!$R$27/$O$2/1000000 -> 1.7430957 | Q30: =G30*'Conversion Factors'!$C$44/Types!$R$27/$O$2/1000000 -> 1.8112342 | R30: =H30*'Conversion Factors'!$C$44/Types!$R$27/$O$2/1000000 -> 1.8662498 | S30: =I30*'Conversion Factors'!$C$44/Types!$R$27/$O$2/1000000 -> 1.9280954 | X30: =L30*'AEO Coal Prod'!L30 -> 285.22482 | Y30: =M30*'AEO Coal Prod'!M30 -> 168.1493 | Z30: =N30*'AEO Coal Prod'!N30 -> 288.28888 | AA30: =O30*'AEO Coal Prod'!O30 -> 350.03731 | AB30: =P30*'AEO Coal Prod'!P30 -> 367.09231 | AC30: =Q30*'AEO Coal Prod'!Q30 -> 380.20274 | AD30: =R30*'AEO Coal Prod'!R30 -> 390.20136 | AE30: =S30*'AEO Coal Prod'!S30 -> 401.91409
A32: Dakota Medium Sulfur (Lignite) | B32: w | C32: 14.62882 | D32: 17.979803 | E32: 21.409149 | F32: 22.995337 | G32: 24.480183 | H32: 25.694098 | I32: 27.030115 | L32: =M32*$U$60 -> 0.6624645 | M32: =C32*'Conversion Factors'!$C$41/Types!$R$28/$O$2/1000000 -> 0.96555342 | N32: =D32*'Conversion Factors'!$C$44/Types!$R$28/$O$2/1000000 -> 1.1301976 | O32: =E32*'Conversion Factors'!$C$44/Types!$R$28/$O$2/1000000 -> 1.3457638 | P32: =F32*'Conversion Factors'!$C$44/Types!$R$28/$O$2/1000000 -> 1.4454705 | Q32: =G32*'Conversion Factors'!$C$44/Types!$R$28/$O$2/1000000 -> 1.5388068 | R32: =H32*'Conversion Factors'!$C$44/Types!$R$28/$O$2/1000000 -> 1.6151126 | S32: =I32*'Conversion Factors'!$C$44/Types!$R$28/$O$2/1000000 -> 1.6990937 | X32: =L32*'AEO Coal Prod'!L32 -> 279.66636 | Y32: =M32*'AEO Coal Prod'!M32 -> 384.6888 | Z32: =N32*'AEO Coal Prod'!N32 -> 464.66476 | AA32: =O32*'AEO Coal Prod'!O32 -> 578.81875 | AB32: =P32*'AEO Coal Prod'!P32 -> 621.60499 | AC32: =Q32*'AEO Coal Prod'!Q32 -> 665.12456 | AD32: =R32*'AEO Coal Prod'!R32 -> 695.87673 | AE32: =S32*'AEO Coal Prod'!S32 -> 734.14123
A34: Western Montana | B34: w | C34: 16.278589 | D34: 20.247177 | E34: 24.778656 | F34: 26.633322 | G34: 28.590448 | H34: 30.840282 | I34: 33.202961
A35: Low Sulfur (Bituminous) | D35: 26.604315 | E35: 31.389259 | F35: 31.413757 | G35: 31.854862 | H35: 34.179668 | I35: 36.578922 | L35: =B35*'Conversion Factors'!$C$38/Types!$R$29/$O$2/1000000 -> 0 | M35: =C35*'Conversion Factors'!$C$41/Types!$R$29/$O$2/1000000 -> 0 | N35: =D35*'Conversion Factors'!$C$44/Types!$R$29/$O$2/1000000 -> 1.1151669 | O35: =E35*'Conversion Factors'!$C$44/Types!$R$29/$O$2/1000000 -> 1.3157363 | P35: =F35*'Conversion Factors'!$C$44/Types!$R$29/$O$2/1000000 -> 1.3167631 | Q35: =G35*'Conversion Factors'!$C$44/Types!$R$29/$O$2/1000000 -> 1.3352528 | R35: =H35*'Conversion Factors'!$C$44/Types!$R$29/$O$2/1000000 -> 1.4327012 | S35: =I35*'Conversion Factors'!$C$44/Types!$R$29/$O$2/1000000 -> 1.5332702 | X35: =L35*'AEO Coal Prod'!L35 -> 0 | Y35: =M35*'AEO Coal Prod'!M35 -> 0 | Z35: =N35*'AEO Coal Prod'!N35 -> 262.83126 | AA35: =O35*'AEO Coal Prod'!O35 -> 391.97945 | AB35: =P35*'AEO Coal Prod'!P35 -> 345.96942 | AC35: =Q35*'AEO Coal Prod'!Q35 -> 334.18081 | AD35: =R35*'AEO Coal Prod'!R35 -> 414.4516 | AE35: =S35*'AEO Coal Prod'!S35 -> 455.12471
A36: Low Sulfur (Sub-Bituminous) | B36: 9.9238176 | C36: 16.942034 | D36: 16.165998 | E36: 19.93099 | F36: 23.007982 | G36: 25.562902 | H36: 27.880976 | I36: 30.421452 | L36: =B36*'Conversion Factors'!$C$38/Types!$R$30/$O$2/1000000 -> 0.5041726 | M36: =C36*'Conversion Factors'!$C$41/Types!$R$30/$O$2/1000000 -> 0.81612523 | N36: =D36*'Conversion Factors'!$C$44/Types!$R$30/$O$2/1000000 -> 0.74164522 | O36: =E36*'Conversion Factors'!$C$44/Types!$R$30/$O$2/1000000 -> 0.91437123 | P36: =F36*'Conversion Factors'!$C$44/Types!$R$30/$O$2/1000000 -> 1.055534 | Q36: =G36*'Conversion Factors'!$C$44/Types!$R$30/$O$2/1000000 -> 1.1727457 | R36: =H36*'Conversion Factors'!$C$44/Types!$R$30/$O$2/1000000 -> 1.2790916 | S36: =I36*'Conversion Factors'!$C$44/Types!$R$30/$O$2/1000000 -> 1.3956407 | U36: =L36/M36 -> 0.61776377 | X36: =L36*'AEO Coal Prod'!L36 -> 198.23926 | Y36: =M36*'AEO Coal Prod'!M36 -> 299.85043 | Z36: =N36*'AEO Coal Prod'!N36 -> 298.95678 | AA36: =O36*'AEO Coal Prod'!O36 -> 404.06652 | AB36: =P36*'AEO Coal Prod'!P36 -> 541.25794 | AC36: =Q36*'AEO Coal Prod'!Q36 -> 622.37566 | AD36: =R36*'AEO Coal Prod'!R36 -> 712.91484 | AE36: =S36*'AEO Coal Prod'!S36 -> 817.87538
A37: Medium Sulfur (Sub-Bituminous) | B37: w | C37: 15.264915 | D37: 21.024343 | E37: 25.781261 | F37: 28.698696 | G37: 31.209028 | H37: 33.315269 | I37: 35.640102 | L37: =M37*$U$60 -> 0.52937255 | M37: =C37*'Conversion Factors'!$C$41/Types!$R$31/$O$2/1000000 -> 0.77156962 | N37: =D37*'Conversion Factors'!$C$44/Types!$R$31/$O$2/1000000 -> 1.0120584 | O37: =E37*'Conversion Factors'!$C$44/Types!$R$31/$O$2/1000000 -> 1.2410444 | P37: =F37*'Conversion Factors'!$C$44/Types!$R$31/$O$2/1000000 -> 1.3814823 | Q37: =G37*'Conversion Factors'!$C$44/Types!$R$31/$O$2/1000000 -> 1.5023233 | R37: =H37*'Conversion Factors'!$C$44/Types!$R$31/$O$2/1000000 -> 1.6037124 | S37: =I37*'Conversion Factors'!$C$44/Types!$R$31/$O$2/1000000 -> 1.7156239 | X37: =L37*'AEO Coal Prod'!L37 -> 187.19698 | Y37: =M37*'AEO Coal Prod'!M37 -> 242.63071 | Z37: =N37*'AEO Coal Prod'!N37 -> 342.73025 | AA37: =O37*'AEO Coal Prod'!O37 -> 404.40668 | AB37: =P37*'AEO Coal Prod'!P37 -> 453.49251 | AC37: =Q37*'AEO Coal Prod'!Q37 -> 470.3571 | AD37: =R37*'AEO Coal Prod'!R37 -> 473.51153 | AE37: =S37*'AEO Coal Prod'!S37 -> 479.30636
A39: Wyoming, Powder River Basin | B39: w | C39: 13.932995 | D39: 15.057492 | E39: 18.487614 | F39: 21.324152 | G39: 24.262512 | H39: 26.411327 | I39: 28.814512
A40: Low Sulfur (Sub-Bituminous) | B40: 7.7255955 | C40: 13.949697 | D40: 15.049236 | E40: 18.44298 | F40: 21.289709 | G40: 24.23736 | H40: 26.38921 | I40: 28.796261 | L40: =B40*'Conversion Factors'!$C$38/Types!$R$32/$O$2/1000000 -> 0.42186055 | M40: =C40*'Conversion Factors'!$C$41/Types!$R$32/$O$2/1000000 -> 0.72225826 | N40: =D40*'Conversion Factors'!$C$44/Types!$R$32/$O$2/1000000 -> 0.74206957 | O40: =E40*'Conversion Factors'!$C$44/Types!$R$32/$O$2/1000000 -> 0.90941322 | P40: =F40*'Conversion Factors'!$C$44/Types!$R$32/$O$2/1000000 -> 1.0497839 | Q40: =G40*'Conversion Factors'!$C$44/Types!$R$32/$O$2/1000000 -> 1.1951309 | R40: =H40*'Conversion Factors'!$C$44/Types!$R$32/$O$2/1000000 -> 1.3012375 | S40: =I40*'Conversion Factors'!$C$44/Types!$R$32/$O$2/1000000 -> 1.4199278 | U40: =L40/M40 -> 0.58408547 | X40: =L40*'AEO Coal Prod'!L40 -> 2897.2914 | Y40: =M40*'AEO Coal Prod'!M40 -> 5436.7615 | Z40: =N40*'AEO Coal Prod'!N40 -> 5600.5194 | AA40: =O40*'AEO Coal Prod'!O40 -> 6736.1469 | AB40: =P40*'AEO Coal Prod'!P40 -> 8161.6655 | AC40: =Q40*'AEO Coal Prod'!Q40 -> 9306.1154 | AD40: =R40*'AEO Coal Prod'!R40 -> 9956.8781 | AE40: =S40*'AEO Coal Prod'!S40 -> 10576.782
A41: Medium Sulfur (Sub-Bituminous) | B41: w | C41: 11.735514 | D41: 15.754457 | E41: 22.947866 | F41: 25.533693 | G41: 27.855654 | H41: 29.798782 | I41: 31.946428 | L41: =M41*$U$60 -> 0.43282007 | M41: =C41*'Conversion Factors'!$C$41/Types!$R$33/$O$2/1000000 -> 0.63084272 | N41: =D41*'Conversion Factors'!$C$44/Types!$R$33/$O$2/1000000 -> 0.80653802 | O41: =E41*'Conversion Factors'!$C$44/Types!$R$33/$O$2/1000000 -> 1.1747994 | P41: =F41*'Conversion Factors'!$C$44/Types!$R$33/$O$2/1000000 -> 1.3071789 | Q41: =G41*'Conversion Factors'!$C$44/Types!$R$33/$O$2/1000000 -> 1.42605 | R41: =H41*'Conversion Factors'!$C$44/Types!$R$33/$O$2/1000000 -> 1.5255271 | S41: =I41*'Conversion Factors'!$C$44/Types!$R$33/$O$2/1000000 -> 1.6354743 | X41: =L41*'AEO Coal Prod'!L41 -> 26.516535 | Y41: =M41*'AEO Coal Prod'!M41 -> 26.014198 | Z41: =N41*'AEO Coal Prod'!N41 -> 69.461138 | AA41: =O41*'AEO Coal Prod'!O41 -> 83.873506 | AB41: =P41*'AEO Coal Prod'!P41 -> 80.093844 | AC41: =Q41*'AEO Coal Prod'!Q41 -> 74.870808 | AD41: =R41*'AEO Coal Prod'!R41 -> 73.414837 | AE41: =S41*'AEO Coal Prod'!S41 -> 68.377565
A43: Western Wyoming | B43: w | C43: 27.758377 | D43: 37.935009 | E43: 49.246014 | F43: 53.219028 | G43: 49.001682 | H43: 46.372147 | I43: 48.943317
A44: Low Sulfur (Sub-Bituminous) | B44: w | C44: 26.11595 | D44: 39.355072 | E44: 52.353317 | F44: 56.766273 | G44: 52.717167 | H44: 45.991131 | I44: 48.592892 | L44: =M44*$U$60 -> 0.82792321 | M44: =C44*'Conversion Factors'!$C$41/Types!$R$35/$O$2/1000000 -> 1.2067123 | N44: =D44*'Conversion Factors'!$C$44/Types!$R$35/$O$2/1000000 -> 1.7318133 | O44: =E44*'Conversion Factors'!$C$44/Types!$R$35/$O$2/1000000 -> 2.3037989 | P44: =F44*'Conversion Factors'!$C$44/Types!$R$35/$O$2/1000000 -> 2.4979902 | Q44: =G44*'Conversion Factors'!$C$44/Types!$R$35/$O$2/1000000 -> 2.31981 | R44: =H44*'Conversion Factors'!$C$44/Types!$R$35/$O$2/1000000 -> 2.0238319 | S44: =I44*'Conversion Factors'!$C$44/Types!$R$35/$O$2/1000000 -> 2.138322 | X44: =L44*'AEO Coal Prod'!L44 -> 65.767354 | Y44: =M44*'AEO Coal Prod'!M44 -> 160.83564 | Z44: =N44*'AEO Coal Prod'!N44 -> 367.07259 | AA44: =O44*'AEO Coal Prod'!O44 -> 488.21697 | AB44: =P44*'AEO Coal Prod'!P44 -> 529.53448 | AC44: =Q44*'AEO Coal Prod'!Q44 -> 256.42211 | AD44: =R44*'AEO Coal Prod'!R44 -> 101.8742 | AE44: =S44*'AEO Coal Prod'!S44 -> 112.59687
A45: Medium Sulfur (Sub-Bituminous) | B45: 22.580086 | C45: 30.052296 | D45: 33.79686 | E45: 39.620701 | F45: 40.946262 | G45: 42.559505 | H45: 46.672523 | I45: 49.282093 | L45: =B45*'Conversion Factors'!$C$38/Types!$R$37/$O$2/1000000 -> 1.0626251 | M45: =C45*'Conversion Factors'!$C$41/Types!$R$37/$O$2/1000000 -> 1.3409819 | N45: =D45*'Conversion Factors'!$C$44/Types!$R$37/$O$2/1000000 -> 1.4362302 | O45: =E45*'Conversion Factors'!$C$44/Types!$R$37/$O$2/1000000 -> 1.6837199 | P45: =F45*'Conversion Factors'!$C$44/Types!$R$37/$O$2/1000000 -> 1.7400509 | Q45: =G45*'Conversion Factors'!$C$44/Types!$R$37/$O$2/1000000 -> 1.8086072 | R45: =H45*'Conversion Factors'!$C$44/Types!$R$37/$O$2/1000000 -> 1.9833939 | S45: =I45*'Conversion Factors'!$C$44/Types!$R$37/$O$2/1000000 -> 2.0942901 | U45: =L45/M45 -> 0.79242312 | X45: =L45*'AEO Coal Prod'!L45 -> 223.44997 | Y45: =M45*'AEO Coal Prod'!M45 -> 163.01115 | Z45: =N45*'AEO Coal Prod'!N45 -> 108.17557 | AA45: =O45*'AEO Coal Prod'!O45 -> 119.27776 | AB45: =P45*'AEO Coal Prod'!P45 -> 110.39944 | AC45: =Q45*'AEO Coal Prod'!Q45 -> 119.39414 | AD45: =R45*'AEO Coal Prod'!R45 -> 131.1394 | AE45: =S45*'AEO Coal Prod'!S45 -> 118.12157
A48: Rocky Mountain | B48: 21.942982 | C48: 35.970459 | D48: 37.924408 | E48: 43.396564 | F48: 46.605312 | G48: 48.551785 | H48: 52.55751 | I48: 55.617268
A49: Low Sulfur (Premium) 2/ | C49: 75.717163 | D49: 97.423523 | E49: 122.82065 | F49: 165.91988 | G49: 174.70548 | H49: 175.90497 | I49: 189.82895 | L49: =B49*'Conversion Factors'!$C$38/Types!$R$40/$O$2/1000000 -> 0 | M49: =C49*'Conversion Factors'!$C$41/Types!$R$40/$O$2/1000000 -> 2.5102005 | N49: =D49*'Conversion Factors'!$C$44/Types!$R$40/$O$2/1000000 -> 3.0759576 | O49: =E49*'Conversion Factors'!$C$44/Types!$R$40/$O$2/1000000 -> 3.8778222 | P49: =F49*'Conversion Factors'!$C$44/Types!$R$40/$O$2/1000000 -> 5.2385962 | Q49: =G49*'Conversion Factors'!$C$44/Types!$R$40/$O$2/1000000 -> 5.5159843 | R49: =H49*'Conversion Factors'!$C$44/Types!$R$40/$O$2/1000000 -> 5.553856 | S49: =I49*'Conversion Factors'!$C$44/Types!$R$40/$O$2/1000000 -> 5.9934785 | X49: =L49*'AEO Coal Prod'!L49 -> 0 | Y49: =M49*'AEO Coal Prod'!M49 -> 1.2328577 | Z49: =N49*'AEO Coal Prod'!N49 -> 16.307701 | AA49: =O49*'AEO Coal Prod'!O49 -> 70.164274 | AB49: =P49*'AEO Coal Prod'!P49 -> 28.958704 | AC49: =Q49*'AEO Coal Prod'!Q49 -> 2.6465152 | AD49: =R49*'AEO Coal Prod'!R49 -> 48.901628 | AE49: =S49*'AEO Coal Prod'!S49 -> 47.79377
A50: Low Sulfur (Bituminous) | B50: 21.91991 | C50: 35.836514 | D50: 37.856892 | E50: 42.015896 | F50: 46.183384 | G50: 48.822533 | H50: 51.557343 | I50: 54.687389 | L50: =B50*'Conversion Factors'!$C$38/Types!$R$38/$O$2/1000000 -> 0.88639511 | M50: =C50*'Conversion Factors'!$C$41/Types!$R$38/$O$2/1000000 -> 1.3740582 | N50: =D50*'Conversion Factors'!$C$44/Types!$R$38/$O$2/1000000 -> 1.3823778 | O50: =E50*'Conversion Factors'!$C$44/Types!$R$38/$O$2/1000000 -> 1.5342475 | P50: =F50*'Conversion Factors'!$C$44/Types!$R$38/$O$2/1000000 -> 1.686427 | Q50: =G50*'Conversion Factors'!$C$44/Types!$R$38/$O$2/1000000 -> 1.7827979 | R50: =H50*'Conversion Factors'!$C$44/Types!$R$38/$O$2/1000000 -> 1.8826619 | S50: =I50*'Conversion Factors'!$C$44/Types!$R$38/$O$2/1000000 -> 1.9969583 | U50: =L50/M50 -> 0.64509285 | X50: =L50*'AEO Coal Prod'!L50 -> 1126.2668 | Y50: =M50*'AEO Coal Prod'!M50 -> 1356.1672 | Z50: =N50*'AEO Coal Prod'!N50 -> 964.0146 | AA50: =O50*'AEO Coal Prod'!O50 -> 1012.613 | AB50: =P50*'AEO Coal Prod'!P50 -> 1116.505 | AC50: =Q50*'AEO Coal Prod'!Q50 -> 1162.2191 | AD50: =R50*'AEO Coal Prod'!R50 -> 1012.0794 | AE50: =S50*'AEO Coal Prod'!S50 -> 1046.2685
A51: Low Sulfur (Sub-Bituminous) | B51: 22.064323 | C51: 32.693531 | D51: 36.151985 | E51: 40.36515 | F51: 44.073627 | G51: 46.367561 | H51: 48.715916 | I51: 51.41518 | L51: =B51*'Conversion Factors'!$C$38/Types!$R$39/$O$2/1000000 -> 1.0180342 | M51: =C51*'Conversion Factors'!$C$41/Types!$R$39/$O$2/1000000 -> 1.4302908 | N51: =D51*'Conversion Factors'!$C$44/Types!$R$39/$O$2/1000000 -> 1.5062502 | O51: =E51*'Conversion Factors'!$C$44/Types!$R$39/$O$2/1000000 -> 1.6817891 | P51: =F51*'Conversion Factors'!$C$44/Types!$R$39/$O$2/1000000 -> 1.8363005 | Q51: =G51*'Conversion Factors'!$C$44/Types!$R$39/$O$2/1000000 -> 1.9318758 | R51: =H51*'Conversion Factors'!$C$44/Types!$R$39/$O$2/1000000 -> 2.0297186 | S51: =I51*'Conversion Factors'!$C$44/Types!$R$39/$O$2/1000000 -> 2.1421818 | U51: =L51/M51 -> 0.71176724 | X51: =L51*'AEO Coal Prod'!L51 -> 215.5632 | Y51: =M51*'AEO Coal Prod'!M51 -> 161.86422 | Z51: =N51*'AEO Coal Prod'!N51 -> 168.07419 | AA51: =O51*'AEO Coal Prod'!O51 -> 161.0907 | AB51: =P51*'AEO Coal Prod'!P51 -> 184.95187 | AC51: =Q51*'AEO Coal Prod'!Q51 -> 177.39068 | AD51: =R51*'AEO Coal Prod'!R51 -> 185.87171 | AE51: =S51*'AEO Coal Prod'!S51 -> 195.77698
A53: Arizona/New Mexico | B53: w | C53: 32.814438 | D53: 38.37347 | E53: 40.283176 | F53: 42.489239 | G53: 44.276184 | H53: 46.116894 | I53: 47.749584
A54: Low Sulfur (Bituminous) | B54: w | C54: 39.294292 | D54: 42.175289 | E54: 48.393826 | F54: 52.977467 | G54: 55.918732 | H54: 58.748604 | I54: 61.051937 | L54: =M54*$U$60 -> 1.0912893 | M54: =C54*'Conversion Factors'!$C$41/Types!$R$42/$O$2/1000000 -> 1.590573 | N54: =D54*'Conversion Factors'!$C$44/Types!$R$42/$O$2/1000000 -> 1.6258655 | O54: =E54*'Conversion Factors'!$C$44/Types!$R$42/$O$2/1000000 -> 1.8655913 | P54: =F54*'Conversion Factors'!$C$44/Types!$R$42/$O$2/1000000 -> 2.0422916 | Q54: =G54*'Conversion Factors'!$C$44/Types!$R$42/$O$2/1000000 -> 2.1556779 | R54: =H54*'Conversion Factors'!$C$44/Types!$R$42/$O$2/1000000 -> 2.26477 | S54: =I54*'Conversion Factors'!$C$44/Types!$R$42/$O$2/1000000 -> 2.353564 | X54: =L54*'AEO Coal Prod'!L54 -> 432.27339 | Y54: =M54*'AEO Coal Prod'!M54 -> 289.18493 | Z54: =N54*'AEO Coal Prod'!N54 -> 208.62159 | AA54: =O54*'AEO Coal Prod'!O54 -> 302.7791 | AB54: =P54*'AEO Coal Prod'!P54 -> 356.91587 | AC54: =Q54*'AEO Coal Prod'!Q54 -> 364.52585 | AD54: =R54*'AEO Coal Prod'!R54 -> 390.80756 | AE54: =S54*'AEO Coal Prod'!S54 -> 403.69111
A55: Medium Sulfur (Bituminous) | B55: w | C55: 42.986237 | D55: 55.839455 | E55: 58.041546 | F55: 47.801662 | G55: 46.027245 | H55: 50.411835 | I55: 53.742344 | L55: =M55*$U$60 -> 1.3484501 | M55: =C55*'Conversion Factors'!$C$41/Types!$R$41/$O$2/1000000 -> 1.9653892 | N55: =D55*'Conversion Factors'!$C$44/Types!$R$41/$O$2/1000000 -> 2.4314354 | O55: =E55*'Conversion Factors'!$C$44/Types!$R$41/$O$2/1000000 -> 2.5273218 | P55: =F55*'Conversion Factors'!$C$44/Types!$R$41/$O$2/1000000 -> 2.0814432 | Q55: =G55*'Conversion Factors'!$C$44/Types!$R$41/$O$2/1000000 -> 2.0041792 | R55: =H55*'Conversion Factors'!$C$44/Types!$R$41/$O$2/1000000 -> 2.1950988 | S55: =I55*'Conversion Factors'!$C$44/Types!$R$41/$O$2/1000000 -> 2.3401202 | X55: =L55*'AEO Coal Prod'!L55 -> 214.60387 | Y55: =M55*'AEO Coal Prod'!M55 -> 157.50164 | Z55: =N55*'AEO Coal Prod'!N55 -> 302.81571 | AA55: =O55*'AEO Coal Prod'!O55 -> 83.309339 | AB55: =P55*'AEO Coal Prod'!P55 -> 33.724059 | AC55: =Q55*'AEO Coal Prod'!Q55 -> 128.08494 | AD55: =R55*'AEO Coal Prod'!R55 -> 139.15856 | AE55: =S55*'AEO Coal Prod'!S55 -> 132.96736
A56: Medium Sulfur (Sub-Bituminous) | B56: w | C56: 26.946581 | D56: 32.326595 | E56: 36.391743 | F56: 38.940636 | G56: 40.37014 | H56: 41.442368 | I56: 42.900303 | L56: =M56*$U$60 -> 0.89654091 | M56: =C56*'Conversion Factors'!$C$41/Types!$R$43/$O$2/1000000 -> 1.3067238 | N56: =D56*'Conversion Factors'!$C$44/Types!$R$43/$O$2/1000000 -> 1.4929406 | O56: =E56*'Conversion Factors'!$C$44/Types!$R$43/$O$2/1000000 -> 1.6806815 | P56: =F56*'Conversion Factors'!$C$44/Types!$R$43/$O$2/1000000 -> 1.7983972 | Q56: =G56*'Conversion Factors'!$C$44/Types!$R$43/$O$2/1000000 -> 1.864416 | R56: =H56*'Conversion Factors'!$C$44/Types!$R$43/$O$2/1000000 -> 1.9139348 | S56: =I56*'Conversion Factors'!$C$44/Types!$R$43/$O$2/1000000 -> 1.9812666 | X56: =L56*'AEO Coal Prod'!L56 -> 259.36129 | Y56: =M56*'AEO Coal Prod'!M56 -> 447.43363 | Z56: =N56*'AEO Coal Prod'!N56 -> 606.89592 | AA56: =O56*'AEO Coal Prod'!O56 -> 712.92306 | AB56: =P56*'AEO Coal Prod'!P56 -> 816.52071 | AC56: =Q56*'AEO Coal Prod'!Q56 -> 834.77132 | AD56: =R56*'AEO Coal Prod'!R56 -> 850.07057 | AE56: =S56*'AEO Coal Prod'!S56 -> 909.31612
A58: Washington/Alaska
A59: Low Sulfur (Sub-Bituminous) | B59: w | C59: 64.718628 | D59: 37.046108 | E59: 40.310471 | F59: 42.997967 | G59: 45.532192 | H59: 48.721401 | I59: 52.863388 | L59: =M59*$U$60 -> 2.416701 | M59: =C59*'Conversion Factors'!$C$41/Types!$R$44/$O$2/1000000 -> 3.5223833 | N59: =D59*'Conversion Factors'!$C$44/Types!$R$44/$O$2/1000000 -> 1.9202259 | O59: =E59*'Conversion Factors'!$C$44/Types!$R$44/$O$2/1000000 -> 2.089429 | P59: =F59*'Conversion Factors'!$C$44/Types!$R$44/$O$2/1000000 -> 2.2287311 | Q59: =G59*'Conversion Factors'!$C$44/Types!$R$44/$O$2/1000000 -> 2.3600886 | R59: =H59*'Conversion Factors'!$C$44/Types!$R$44/$O$2/1000000 -> 2.5253961 | S59: =I59*'Conversion Factors'!$C$44/Types!$R$44/$O$2/1000000 -> 2.7400894 | X59: =L59*'AEO Coal Prod'!L59 -> 274.49232 | Y59: =M59*'AEO Coal Prod'!M59 -> 127.93543 | Z59: =N59*'AEO Coal Prod'!N59 -> 57.004104 | AA59: =O59*'AEO Coal Prod'!O59 -> 73.902076 | AB59: =P59*'AEO Coal Prod'!P59 -> 94.568968 | AC59: =Q59*'AEO Coal Prod'!Q59 -> 121.28599 | AD59: =R59*'AEO Coal Prod'!R59 -> 158.67422 | AE59: =S59*'AEO Coal Prod'!S59 -> 212.29228
U60: =AVERAGE(U7:U51) -> 0.68609823
A61: Average by Type: All Regions | X61: =SUM(X7:X60)/SUM('AEO Coal Prod'!L7:L59) -> 1.0763608 | Y61: =SUM(Y7:Y60)/SUM('AEO Coal Prod'!M7:M59) -> 1.5936061 | Z61: =SUM(Z7:Z60)/SUM('AEO Coal Prod'!N7:N59) -> 1.6949528 | AA61: =SUM(AA7:AA60)/SUM('AEO Coal Prod'!O7:O59) -> 1.9416966 | AB61: =SUM(AB7:AB60)/SUM('AEO Coal Prod'!P7:P59) -> 2.0817817 | AC61: =SUM(AC7:AC60)/SUM('AEO Coal Prod'!Q7:Q59) -> 2.227636 | AD61: =SUM(AD7:AD60)/SUM('AEO Coal Prod'!R7:R59) -> 2.3578254 | AE61: =SUM(AE7:AE60)/SUM('AEO Coal Prod'!S7:S59) -> 2.4720051
A63: Premium Metallurgical 2/ | B63: 67.481903 | C63: 103.28445 | D63: 129.90686 | E63: 147.45979 | F63: 162.25705 | G63: 176.50397 | H63: 187.3987 | I63: 195.47902
A64: Bituminous | B64: 35.044464 | C64: 53.39777 | D64: 56.154694 | E64: 61.096153 | F64: 63.454346 | G64: 66.098373 | H64: 68.569382 | I64: 71.070221
A65: Sub-Bituminous | B65: 9.2983809 | C65: 15.339892 | D65: 16.974638 | E65: 20.749598 | F65: 23.585878 | G65: 25.999084 | H65: 27.964045 | I65: 30.417837
A66: Lignite | B66: 13.647387 | C66: 16.771704 | D66: 20.216072 | E66: 22.96624 | F66: 24.9354 | G66: 26.829681 | H66: 27.949966 | I66: 29.064968
A68: Low Sulfur | B68: 14.306739 | C68: 20.745073 | D68: 21.349749 | E68: 25.700178 | F68: 28.220646 | G68: 30.917419 | H68: 33.024399 | I68: 36.126522
A69: Medium Sulfur | B69: 35.724915 | C69: 57.876949 | D69: 65.00338 | E69: 73.40789 | F69: 79.42527 | G69: 83.951164 | H69: 89.108299 | I69: 91.761528
A70: High Sulfur | B70: 26.277803 | C70: 44.792454 | D70: 53.500904 | E70: 59.218369 | F70: 61.292328 | G70: 64.024239 | H70: 66.260628 | I70: 68.602898
A72: Underground | C72: 62.23064 | D72: 72.899483 | E72: 81.523674 | F72: 87.071373 | G72: 91.481812 | H72: 95.618774 | I72: 98.107361
A73: Surface | C73: 24.054285 | D73: 26.174227 | E73: 29.704268 | F73: 31.542477 | G73: 34.024597 | H73: 36.137939 | I73: 38.556046
A75: United States Average | B75: 24.073635 | C75: 36.637375 | D75: 40.543594 | E75: 46.522297 | F75: 49.668926 | G75: 53.149624 | H75: 56.368309 | I75: 59.155964
A77: Waste Coal | B77: 11.862539 | C77: 14.813438 | D77: 18.938404 | E77: 21.027378 | F77: 21.783594 | G77: 22.631582 | H77: 24.162844 | I77: 25.577887
A79: 1/ Includes Pennsylvania anthracite.
A80: 2/ "Premium" coal is used to make metallurgical coke.
A81: Northern Appalachia: Pennsylvania, Maryland, Ohio, Northern West Virginia.
A82: Central Appalachia: Southern West Virginia, Virginia, Eastern Kentucky, Northern Tennessee.
A83: Southern Appalachia: Alabama, Southern Tennessee.
A84: Eastern Interior: Illinois, Indiana, Mississippi, Western Kentucky.
A85: Western Interior: Iowa, Missouri, Kansas, Oklahoma, Arkansas, Texas (bituminous).
A86: Gulf (lignite Only): Texas, Louisiana, Arkansas.
A87: Dakota: North Dakota, Montana (lignite).
A88: Western Montana: Montana (subbituminous).
A89: Wyoming, Powder River Basin: Wyoming portion of Powder River Basin.
A90: Western Wyoming: Wyoming other than Powder River Basin.
... A99: Source: U.S. Energy Information Administration, AEO2014 National Energy Modeling System.

Sheet Production Steps
A4: Supply Regions and Coal Types | B4: ='AEO Coal Prod'!L4 -> 2005 | C4: ='AEO Coal Prod'!M4 -> 2010 | E4: 2005 | F4: 2010 | H4: 2005 | I4: 2010 | K4: %U | L4: %S
A6: Northern Appalachia 1/
D7: 1 | E7: =B9*$P$10 -> 48.558952 | F7: =C9*$P$10 -> 253.074 | H7: =E7 -> 48.558952 | I7: =F7 -> 253.074
D8: 2 | E8: =B9*$P$11 -> 96.146726 | F8: =C9*$P$11 -> 501.08652 | H8: =E8-E7 -> 47.587773 | I8: =F8-F7 -> 248.01252 | O8: Supply Curve Steps
A9: Medium Sulfur (Premium) 2/ | B9: ='AEO Coal Prod'!L7 -> 97.117905 | C9: ='AEO Coal Prod'!M7 -> 506.148 | D9: 3 | E9: =B9*$P$12 -> 97.117905 | F9: =C9*$P$12 -> 506.148 | H9: =E9-E8 -> 0.97117905 | I9: =F9-F8 -> 5.06148 | O9: Prices | P9: Quantity
D10: 4 | E10: =B9*$P$13 -> 98.089084 | F10: =C9*$P$13 -> 511.20948 | H10: =E10-E9 -> 0.97117905 | I10: =F10-F9 -> 5.06148 | N10: 1 | O10: 0.88 | P10: 0.5
D11: 5 | E11: =B9*$P$14 -> 106.8297 | F11: =C9*$P$14 -> 556.7628 | H11: =E11-E10 -> 8.7406114 | I11: =F11-F10 -> 45.55332 | N11: 2 | O11: 0.998 | P11: 0.99
D12: 6 | E12: =B9*$P$15 -> 116.54149 | F12: =C9*$P$15 -> 607.3776 | H12: =E12-E11 -> 9.7117905 | I12: =F12-F11 -> 50.6148 | N12: 3 | O12: 1 | P12: 1 | AB12: 4
N13: 4 | O13: 1.003 | P13: 1.01
D14: 1 | E14: =B16*$P$10 -> 996.8981 | F14: =C16*$P$10 -> 487.09272 | H14: =E14 -> 996.8981 | I14: =F14 -> 487.09272 | K14: =Types!Z4/(Types!Z4+Types!Z6) -> 0.74101183 | L14: =1-K14 -> 0.25898817 | N14: 5 | O14: 1.12 | P14: 1.1
D15: 2 | E15: =B16*$P$11 -> 1973.8582 | F15: =C16*$P$11 -> 964.44358 | H15: =E15-E14 -> 976.96014 | I15: =F15-F14 -> 477.35086 | K15: =K14 -> 0.74101183 | L15: =L14 -> 0.25898817 | N15: 6 | O15: 1.53 | P15: 1.2
A16: Medium Sulfur (Bituminous) | B16: ='AEO Coal Prod'!L8 -> 1993.7962 | C16: ='AEO Coal Prod'!M8 -> 974.18543 | D16: 3 | E16: =B16*$P$12 -> 1993.7962 | F16: =C16*$P$12 -> 974.18543 | H16: =E16-E15 -> 19.937962 | I16: =F16-F15 -> 9.7418543 | K16: =K15 -> 0.74101183 | L16: =L15 -> 0.25898817
D17: 4 | E17: =B16*$P$13 -> 2013.7342 | F17: =C16*$P$13 -> 983.92729 | H17: =E17-E16 -> 19.937962 | I17: =F17-F16 -> 9.7418543 | K17: =K16 -> 0.74101183 | L17: =L16 -> 0.25898817 | N17: Step 3 Price Starting Point: | Q17: 1.1
D18: 5 | E18: =B16*$P$14 -> 2193.1758 | F18: =C16*$P$14 -> 1071.604 | H18: =E18-E17 -> 179.44166 | I18: =F18-F17 -> 87.676689 | K18: =K17 -> 0.74101183 | L18: =L17 -> 0.25898817 | Q18: *10% above average price
D19: 6 | E19: =B16*$P$15 -> 2392.5554 | F19: =C16*$P$15 -> 1169.0225 | H19: =E19-E18 -> 199.37962 | I19: =F19-F18 -> 97.418543 | K19: =K18 -> 0.74101183 | L19: =L18 -> 0.25898817
D21: 1 | E21: =B23*$P$10 -> 801.14898 | F21: =C23*$P$10 -> 1014.6182 | H21: =E21 -> 801.14898 | I21: =F21 -> 1014.6182 | K21: =Types!Z5/(Types!Z5+Types!Z7) -> 0.8040744 | L21: =1-K21 -> 0.1959256
D22: 2 | E22: =B23*$P$11 -> 1586.275 | F22: =C23*$P$11 -> 2008.944 | H22: =E22-E21 -> 785.126 | I22: =F22-F21 -> 994.32582 | K22: =K21 -> 0.8040744 | L22: =L21 -> 0.1959256
A23: High Sulfur (Bituminous) | B23: ='AEO Coal Prod'!L9 -> 1602.298 | C23: ='AEO Coal Prod'!M9 -> 2029.2364 | D23: 3 | E23: =B23*$P$12 -> 1602.298 | F23: =C23*$P$12 -> 2029.2364 | H23: =E23-E22 -> 16.02298 | I23: =F23-F22 -> 20.292364 | K23: =K22 -> 0.8040744 | L23: =L22 -> 0.1959256
D24: 4 | E24: =B23*$P$13 -> 1618.3209 | F24: =C23*$P$13 -> 2049.5287 | H24: =E24-E23 -> 16.02298 | I24: =F24-F23 -> 20.292364 | K24: =K23 -> 0.8040744 | L24: =L23 -> 0.1959256
D25: 5 | E25: =B23*$P$14 -> 1762.5278 | F25: =C23*$P$14 -> 2232.16 | H25: =E25-E24 -> 144.20682 | I25: =F25-F24 -> 182.63127 | K25: =K24 -> 0.8040744 | L25: =L24 -> 0.1959256
D26: 6 | E26: =B23*$P$15 -> 1922.7576 | F26: =C23*$P$15 -> 2435.0836 | H26: =E26-E25 -> 160.2298 | I26: =F26-F25 -> 202.92364 | K26: =K25 -> 0.8040744 | L26: =L25 -> 0.1959256
A28: Central Appalachia
D29: 1 | E29: =B31*$P$10 -> 544.13776 | F29: =C31*$P$10 -> 855.58098 | H29: =E29 -> 544.13776 | I29: =F29 -> 855.58098
D30: 2 | E30: =B31*$P$11 -> 1077.3928 | F30: =C31*$P$11 -> 1694.0503 | H30: =E30-E29 -> 533.25501 | I30: =F30-F29 -> 838.46936
A31: Medium Sulfur (Premium) 2/ | B31: ='AEO Coal Prod'!L12 -> 1088.2755 | C31: ='AEO Coal Prod'!M12 -> 1711.162 | D31: 3 | E31: =B31*$P$12 -> 1088.2755 | F31: =C31*$P$12 -> 1711.162 | H31: =E31-E30 -> 10.882755 | I31: =F31-F30 -> 17.11162
E32: =B31*$P$13 -> 1099.1583 | F32: =C31*$P$13 -> 1728.2736 | H32: =E32-E31 -> 10.882755 | I32: =F32-F31 -> 17.11162
D33: 5 | E33: =B31*$P$14 -> 1197.1031 | F33: =C31*$P$14 -> 1882.2782 | H33: =E33-E32 -> 97.944797 | I33: =F33-F32 -> 154.00458
D34: 6 | E34: =B31*$P$15 -> 1305.9306 | F34: =C31*$P$15 -> 2053.3944 | H34: =E34-E33 -> 108.82755 | I34: =F34-F33 -> 171.1162
D36: 1 | E36: =B38*$P$10 -> 614.59841 | F36: =C38*$P$10 -> 182.77554 | H36: =E36 -> 614.59841 | I36: =F36 -> 182.77554 | K36: =Types!Z10/(Types!Z10+Types!Z12) -> 0.18918663 | L36: =1-K36 -> 0.81081337
D37: 2 | E37: =B38*$P$11 -> 1216.9049 | F37: =C38*$P$11 -> 361.89557 | H37: =E37-E36 -> 602.30644 | I37: =F37-F36 -> 179.12003 | K37: =K36 -> 0.18918663 | L37: =L36 -> 0.81081337
A38: Low Sulfur (Bituminous) | B38: ='AEO Coal Prod'!L13 -> 1229.1968 | C38: ='AEO Coal Prod'!M13 -> 365.55108 | D38: 3 | E38: =B38*$P$12 -> 1229.1968 | F38: =C38*$P$12 -> 365.55108 | H38: =E38-E37 -> 12.291968 | I38: =F38-F37 -> 3.6555108 | K38: =K37 -> 0.18918663 | L38: =L37 -> 0.81081337
D39: 4 | E39: =B38*$P$13 -> 1241.4888 | F39: =C38*$P$13 -> 369.20659 | H39: =E39-E38 -> 12.291968 | I39: =F39-F38 -> 3.6555108 | K39: =K38 -> 0.18918663 | L39: =L38 -> 0.81081337
D40: 5 | E40: =B38*$P$14 -> 1352.1165 | F40: =C38*$P$14 -> 402.10618 | H40: =E40-E39 -> 110.62771 | I40: =F40-F39 -> 32.899597 | K40: =K39 -> 0.18918663 | L40: =L39 -> 0.81081337
D41: 6 | E41: =B38*$P$15 -> 1475.0362 | F41: =C38*$P$15 -> 438.66129 | H41: =E41-E40 -> 122.91968 | I41: =F41-F40 -> 36.555108 | K41: =K40 -> 0.18918663 | L41: =L40 -> 0.81081337
D43: 1 | E43: =B45*$P$10 -> 1944.0412 | F43: =C45*$P$10 -> 1421.9626 | H43: =E43 -> 1944.0412 | I43: =F43 -> 1421.9626 | K43: =Types!Z11/(Types!Z11+Types!Z13) -> 0.25624372 | L43: =1-K43 -> 0.74375628
D44: 2 | E44: =B45*$P$11 -> 3849.2015 | F44: =C45*$P$11 -> 2815.4859 | H44: =E44-E43 -> 1905.1603 | I44: =F44-F43 -> 1393.5233 | K44: =K43 -> 0.25624372 | L44: =L43 -> 0.74375628
A45: Medium Sulfur (Bituminous) | B45: ='AEO Coal Prod'!L14 -> 3888.0823 | C45: ='AEO Coal Prod'!M14 -> 2843.9252 | D45: 3 | E45: =B45*$P$12 -> 3888.0823 | F45: =C45*$P$12 -> 2843.9252 | H45: =E45-E44 -> 38.880823 | I45: =F45-F44 -> 28.439252 | K45: =K44 -> 0.25624372 | L45: =L44 -> 0.74375628
D46: 4 | E46: =B45*$P$13 -> 3926.9631 | F46: =C45*$P$13 -> 2872.3644 | H46: =E46-E45 -> 38.880823 | I46: =F46-F45 -> 28.439252 | K46: =K45 -> 0.25624372 | L46: =L45 -> 0.74375628
D47: 5 | E47: =B45*$P$14 -> 4276.8905 | F47: =C45*$P$14 -> 3128.3177 | H47: =E47-E46 -> 349.92741 | I47: =F47-F46 -> 255.95326 | K47: =K46 -> 0.25624372 | L47: =L46 -> 0.74375628
D48: 6 | E48: =B45*$P$15 -> 4665.6988 | F48: =C45*$P$15 -> 3412.7102 | H48: =E48-E47 -> 388.80823 | I48: =F48-F47 -> 284.39252 | K48: =K47 -> 0.25624372 | L48: =L47 -> 0.74375628
A50: Southern Appalachia
D51: 1 | E51: =B53*$P$10 -> 112.10181 | F51: =C53*$P$10 -> 141.73942 | H51: =E51 -> 112.10181 | I51: =F51 -> 141.73942
D52: 2 | E52: =B53*$P$11 -> 221.96158 | F52: =C53*$P$11 -> 280.64405 | H52: =E52-E51 -> 109.85977 | I52: =F52-F51 -> 138.90463
A53: Low Sulfur (Premium) 2/ | B53: ='AEO Coal Prod'!L17 -> 224.20362 | C53: ='AEO Coal Prod'!M17 -> 283.47884 | D53: 3 | E53: =B53*$P$12 -> 224.20362 | F53: =C53*$P$12 -> 283.47884 | H53: =E53-E52 -> 2.2420362 | I53: =F53-F52 -> 2.8347884
D54: 4 | E54: =B53*$P$13 -> 226.44565 | F54: =C53*$P$13 -> 286.31363 | H54: =E54-E53 -> 2.2420362 | I54: =F54-F53 -> 2.8347884
D55: 5 | E55: =B53*$P$14 -> 246.62398 | F55: =C53*$P$14 -> 311.82672 | H55: =E55-E54 -> 20.178326 | I55: =F55-F54 -> 25.513096
D56: 6 | E56: =B53*$P$15 -> 269.04434 | F56: =C53*$P$15 -> 340.17461 | H56: =E56-E55 -> 22.420362 | I56: =F56-F55 -> 28.347884
D58: 1 | E58: =B60*$P$10 -> 7.1870412 | F58: =C60*$P$10 -> 6.2167909 | H58: =E58 -> 7.1870412 | I58: =F58 -> 6.2167909 | K58: =Types!Z15/(Types!Z15+Types!Z17) -> 0 | L58: =1-K58 -> 1
D59: 2 | E59: =B60*$P$11 -> 14.230342 | F59: =C60*$P$11 -> 12.309246 | H59: =E59-E58 -> 7.0433004 | I59: =F59-F58 -> 6.0924551 | K59: =K58 -> 0 | L59: =L58 -> 1
A60: Low Sulfur (Bituminous) | B60: ='AEO Coal Prod'!L18 -> 14.374082 | C60: ='AEO Coal Prod'!M18 -> 12.433582 | D60: 3 | E60: =B60*$P$12 -> 14.374082 | F60: =C60*$P$12 -> 12.433582 | H60: =E60-E59 -> 0.14374082 | I60: =F60-F59 -> 0.12433582 | K60: =K59 -> 0 | L60: =L59 -> 1
D61: 4 | E61: =B60*$P$13 -> 14.517823 | F61: =C60*$P$13 -> 12.557918 | H61: =E61-E60 -> 0.14374082 | I61: =F61-F60 -> 0.12433582 | K61: =K60 -> 0 | L61: =L60 -> 1
D62: 5 | E62: =B60*$P$14 -> 15.811491 | F62: =C60*$P$14 -> 13.67694 | H62: =E62-E61 -> 1.2936674 | I62: =F62-F61 -> 1.1190224 | K62: =K61 -> 0 | L62: =L61 -> 1
D63: 6 | E63: =B60*$P$15 -> 17.248899 | F63: =C60*$P$15 -> 14.920298 | H63: =E63-E62 -> 1.4374082 | I63: =F63-F62 -> 1.2433582 | K63: =K62 -> 0 | L63: =L62 -> 1
D65: 1 | E65: =B67*$P$10 -> 165.73337 | F65: =C67*$P$10 -> 112.31464 | H65: =E65 -> 165.73337 | I65: =F65 -> 112.31464 | K65: =Types!Z16/(Types!Z16+Types!Z18) -> 0.047971423 | L65: =1-K65 -> 0.95202858
D66: 2 | E66: =B67*$P$11 -> 328.15208 | F66: =C67*$P$11 -> 222.38299 | H66: =E66-E65 -> 162.41871 | I66: =F66-F65 -> 110.06835 | K66: =K65 -> 0.047971423 | L66: =L65 -> 0.95202858
A67: Medium Sulfur (Bituminous) | B67: ='AEO Coal Prod'!L19 -> 331.46675 | C67: ='AEO Coal Prod'!M19 -> 224.62928 | D67: 3 | E67: =B67*$P$12 -> 331.46675 | F67: =C67*$P$12 -> 224.62928 | H67: =E67-E66 -> 3.3146675 | I67: =F67-F66 -> 2.2462928 | K67: =K66 -> 0.047971423 | L67: =L66 -> 0.95202858
D68: 4 | E68: =B67*$P$13 -> 334.78142 | F68: =C67*$P$13 -> 226.87558 | H68: =E68-E67 -> 3.3146675 | I68: =F68-F67 -> 2.2462928 | K68: =K67 -> 0.047971423 | L68: =L67 -> 0.95202858
D69: 5 | E69: =B67*$P$14 -> 364.61342 | F69: =C67*$P$14 -> 247.09221 | H69: =E69-E68 -> 29.832007 | I69: =F69-F68 -> 20.216635 | K69: =K68 -> 0.047971423 | L69: =L68 -> 0.95202858
D70: 6 | E70: =B67*$P$15 -> 397.7601 | F70: =C67*$P$15 -> 269.55514 | H70: =E70-E69 -> 33.146675 | I70: =F70-F69 -> 22.462928 | K70: =K69 -> 0.047971423 | L70: =L69 -> 0.95202858
A72: Eastern Interior
D73: 1 | E73: =B75*$P$10 -> 347.33367 | F73: =C75*$P$10 -> 121.32692 | H73: =E73 -> 347.33367 | I73: =F73 -> 121.32692 | K73: =Types!Z20/(Types!Z20+Types!Z22) -> 0.75157992 | L73: =1-K73 -> 0.24842008
D74: 2 | E74: =B75*$P$11 -> 687.72066 | F74: =C75*$P$11 -> 240.22729 | H74: =E74-E73 -> 340.38699 | I74: =F74-F73 -> 118.90038 | K74: =K73 -> 0.75157992 | L74: =L73 -> 0.24842008
A75: Medium Sulfur (Bituminous) | B75: ='AEO Coal Prod'!L22 -> 694.66733 | C75: ='AEO Coal Prod'!M22 -> 242.65383 | D75: 3 | E75: =B75*$P$12 -> 694.66733 | F75: =C75*$P$12 -> 242.65383 | H75: =E75-E74 -> 6.9466733 | I75: =F75-F74 -> 2.4265383 | K75: =K74 -> 0.75157992 | L75: =L74 -> 0.24842008
D76: 4 | E76: =B75*$P$13 -> 701.61401 | F76: =C75*$P$13 -> 245.08037 | H76: =E76-E75 -> 6.9466733 | I76: =F76-F75 -> 2.4265383 | K76: =K75 -> 0.75157992 | L76: =L75 -> 0.24842008
D77: 5 | E77: =B75*$P$14 -> 764.13407 | F77: =C75*$P$14 -> 266.91921 | H77: =E77-E76 -> 62.52006 | I77: =F77-F76 -> 21.838845 | K77: =K76 -> 0.75157992 | L77: =L76 -> 0.24842008
D78: 6 | E78: =B75*$P$15 -> 833.6008 | F78: =C75*$P$15 -> 291.1846 | H78: =E78-E77 -> 69.466733 | I78: =F78-F77 -> 24.265383 | K78: =K77 -> 0.75157992 | L78: =L77 -> 0.24842008
D80: 1 | E80: =B82*$P$10 -> 763.88034 | F80: =C82*$P$10 -> 1275.1401 | H80: =E80 -> 763.88034 | I80: =F80 -> 1275.1401 | K80: =Types!Z21/(Types!Z21+Types!Z23) -> 0.72356857 | L80: =1-K80 -> 0.27643143
D81: 2 | E81: =B82*$P$11 -> 1512.4831 | F81: =C82*$P$11 -> 2524.7775 | H81: =E81-E80 -> 748.60274 | I81: =F81-F80 -> 1249.6373 | K81: =K80 -> 0.72356857 | L81: =L80 -> 0.27643143
A82: High Sulfur (Bituminous) | B82: ='AEO Coal Prod'!L23 -> 1527.7607 | C82: ='AEO Coal Prod'!M23 -> 2550.2803 | D82: 3 | E82: =B82*$P$12 -> 1527.7607 | F82: =C82*$P$12 -> 2550.2803 | H82: =E82-E81 -> 15.277607 | I82: =F82-F81 -> 25.502803 | K82: =K81 -> 0.72356857 | L82: =L81 -> 0.27643143
D83: 4 | E83: =B82*$P$13 -> 1543.0383 | F83: =C82*$P$13 -> 2575.7831 | H83: =E83-E82 -> 15.277607 | I83: =F83-F82 -> 25.502803 | K83: =K82 -> 0.72356857 | L83: =L82 -> 0.27643143
D84: 5 | E84: =B82*$P$14 -> 1680.5368 | F84: =C82*$P$14 -> 2805.3083 | H84: =E84-E83 -> 137.49846 | I84: =F84-F83 -> 229.52522 | K84: =K83 -> 0.72356857 | L84: =L83 -> 0.27643143
D85: 6 | E85: =B82*$P$15 -> 1833.3128 | F85: =C82*$P$15 -> 3060.3363 | H85: =E85-E84 -> 152.77607 | I85: =F85-F84 -> 255.02803 | K85: =K84 -> 0.72356857 | L85: =L84 -> 0.27643143
D87: 1 | E87: =B89*$P$10 -> 19.456076 | F87: =C89*$P$10 -> 15.011238 | H87: =E87 -> 19.456076 | I87: =F87 -> 15.011238
D88: 2 | E88: =B89*$P$11 -> 38.523031 | F88: =C89*$P$11 -> 29.72225 | H88: =E88-E87 -> 19.066955 | I88: =F88-F87 -> 14.711013
A89: Medium Sulfur (Lignite) | B89: ='AEO Coal Prod'!L24 -> 38.912153 | C89: ='AEO Coal Prod'!M24 -> 30.022475 | D89: 3 | E89: =B89*$P$12 -> 38.912153 | F89: =C89*$P$12 -> 30.022475 | H89: =E89-E88 -> 0.38912153 | I89: =F89-F88 -> 0.30022475
D90: 4 | E90: =B89*$P$13 -> 39.301274 | F90: =C89*$P$13 -> 30.3227 | H90: =E90-E89 -> 0.38912153 | I90: =F90-F89 -> 0.30022475
D91: 5 | E91: =B89*$P$14 -> 42.803368 | F91: =C89*$P$14 -> 33.024723 | H91: =E91-E90 -> 3.5020937 | I91: =F91-F90 -> 2.7020228
D92: 6 | E92: =B89*$P$15 -> 46.694583 | F92: =C89*$P$15 -> 36.02697 | H92: =E92-E91 -> 3.8912153 | I92: =F92-F91 -> 3.0022475
D94: 1 | E94: =B96*$P$10 -> 29.482222 | F94: =C96*$P$10 -> 19.953747 | H94: =E94 -> 29.482222 | I94: =F94 -> 19.953747
D95: 2 | E95: =B96*$P$11 -> 58.3748 | F95: =C96*$P$11 -> 39.508418 | H95: =E95-E94 -> 28.892578 | I95: =F95-F94 -> 19.554672
A96: Western Interior High Sulfur (Bituminous) | B96: ='AEO Coal Prod'!L26 -> 58.964445 | C96: ='AEO Coal Prod'!M26 -> 39.907493 | D96: 3 | E96: =B96*$P$12 -> 58.964445 | F96: =C96*$P$12 -> 39.907493 | H96: =E96-E95 -> 0.58964445 | I96: =F96-F95 -> 0.39907493
D97: 4 | E97: =B96*$P$13 -> 59.554089 | F97: =C96*$P$13 -> 40.306568 | H97: =E97-E96 -> 0.58964445 | I97: =F97-F96 -> 0.39907493
D98: 5 | E98: =B96*$P$14 -> 64.860889 | F98: =C96*$P$14 -> 43.898243 | H98: =E98-E97 -> 5.3068 | I98: =F98-F97 -> 3.5916744
D99: 6 | E99: =B96*$P$15 -> 70.757334 | F99: =C96*$P$15 -> 47.888992 | H99: =E99-E98 -> 5.8964445 | I99: =F99-F98 -> 3.9907493
A101: Gulf
D102: 1 | E102: =B104*$P$10 -> 165.58428 | F102: =C104*$P$10 -> 276.46896 | H102: =E102 -> 165.58428 | I102: =F102 -> 276.46896
D103: 2 | E103: =B104*$P$11 -> 327.85688 | F103: =C104*$P$11 -> 547.40854 | H103: =E103-E102 -> 162.2726 | I103: =F103-F102 -> 270.93958
A104: Medium Sulfur (Lignite) | B104: ='AEO Coal Prod'!L29 -> 331.16857 | C104: ='AEO Coal Prod'!M29 -> 552.93792 | D104: 3 | E104: =B104*$P$12 -> 331.16857 | F104: =C104*$P$12 -> 552.93792 | H104: =E104-E103 -> 3.3116857 | I104: =F104-F103 -> 5.5293792
D105: 4 | E105: =B104*$P$13 -> 334.48026 | F105: =C104*$P$13 -> 558.4673 | H105: =E105-E104 -> 3.3116857 | I105: =F105-F104 -> 5.5293792
D106: 5 | E106: =B104*$P$14 -> 364.28543 | F106: =C104*$P$14 -> 608.23172 | H106: =E106-E105 -> 29.805171 | I106: =F106-F105 -> 49.764413
D107: 6 | E107: =B104*$P$15 -> 397.40228 | F107: =C104*$P$15 -> 663.52551 | H107: =E107-E106 -> 33.116857 | I107: =F107-F106 -> 55.293792
D109: 1 | E109: =B111*$P$10 -> 169.38513 | F109: =C111*$P$10 -> 68.512425 | H109: =E109 -> 169.38513 | I109: =F109 -> 68.512425
D110: 2 | E110: =B111*$P$11 -> 335.38256 | F110: =C111*$P$11 -> 135.6546 | H110: =E110-E109 -> 165.99743 | I110: =F110-F109 -> 67.142177
A111: High Sulfur (Lignite) | B111: ='AEO Coal Prod'!L30 -> 338.77026 | C111: ='AEO Coal Prod'!M30 -> 137.02485 | D111: 3 | E111: =B111*$P$12 -> 338.77026 | F111: =C111*$P$12 -> 137.02485 | H111: =E111-E110 -> 3.3877026 | I111: =F111-F110 -> 1.3702485
D112: 4 | E112: =B111*$P$13 -> 342.15796 | F112: =C111*$P$13 -> 138.3951 | H112: =E112-E111 -> 3.3877026 | I112: =F112-F111 -> 1.3702485
D113: 5 | E113: =B111*$P$14 -> 372.64729 | F113: =C111*$P$14 -> 150.72734 | H113: =E113-E112 -> 30.489323 | I113: =F113-F112 -> 12.332237
D114: 6 | E114: =B111*$P$15 -> 406.52431 | F114: =C111*$P$15 -> 164.42982 | H114: =E114-E113 -> 33.877026 | I114: =F114-F113 -> 13.702485
D116: 1 | E116: =B118*$P$10 -> 211.08026 | F116: =C118*$P$10 -> 199.20638 | H116: =E116 -> 211.08026 | I116: =F116 -> 199.20638
D117: 2 | E117: =B118*$P$11 -> 417.93891 | F117: =C118*$P$11 -> 394.42863 | H117: =E117-E116 -> 206.85865 | I117: =F117-F116 -> 195.22225
A118: Dakota Medium Sulfur (Lignite) | B118: ='AEO Coal Prod'!L32 -> 422.16052 | C118: ='AEO Coal Prod'!M32 -> 398.41276 | D118: 3 | E118: =B118*$P$12 -> 422.16052 | F118: =C118*$P$12 -> 398.41276 | H118: =E118-E117 -> 4.2216052 | I118: =F118-F117 -> 3.9841276
...

Sheet AEO Coal Prod
A1: Coal Production by Region and Type, Reference case
A2: (million short tons) | L2: PJ per million btu | O2: 1.055056e-06
A4: Supply Regions and Coal Types | B4: 2005 | C4: 2011 | D4: 2015 | E4: 2020 | F4: 2025 | G4: 2030 | H4: 2035 | I4: 2040 | L4: 2005 | M4: 2010 | N4: 2015 | O4: 2020 | P4: 2025 | Q4: 2030 | R4: 2035 | S4: 2040
A6: Northern Appalachia 1/ | B6: 140.08 | C6: 132.85919 | D6: 131.98666 | E6: 142.5726 | F6: 144.04724 | G6: 144.38678 | H6: 147.5047 | I6: 150.51137
A7: Medium Sulfur (Premium) 2/ | B7: 3.5 | C7: 18.2409 | D7: 20.279318 | E7: 24.468739 | F7: 29.81502 | G7: 30.54867 | H7: 34.042107 | I7: 35.919262 | L7: =B7*1000000*Types!$R$9*$O$2 -> 97.117905 | M7: =C7*1000000*Types!$R$9*$O$2 -> 506.148 | N7: =D7*1000000*Types!$R$9*$O$2 -> 562.70996 | O7: =E7*1000000*Types!$R$9*$O$2 -> 678.9579 | P7: =F7*1000000*Types!$R$9*$O$2 -> 827.30636 | Q7: =G7*1000000*Types!$R$9*$O$2 -> 847.66366 | R7: =H7*1000000*Types!$R$9*$O$2 -> 944.59946 | S7: =I7*1000000*Types!$R$9*$O$2 -> 996.6867
A8: Medium Sulfur (Bituminous) | B8: 75.020004 | C8: 36.655399 | D8: 20.279161 | E8: 25.477747 | F8: 24.073778 | G8: 25.506649 | H8: 24.29615 | I8: 24.499878 | L8: =B8*1000000*Types!$R$4*$O$2 -> 1993.7962 | M8: =C8*1000000*Types!$R$4*$O$2 -> 974.18543 | N8: =D8*1000000*Types!$R$4*$O$2 -> 538.95644 | O8: =E8*1000000*Types!$R$4*$O$2 -> 677.11853 | P8: =F8*1000000*Types!$R$4*$O$2 -> 639.80544 | Q8: =G8*1000000*Types!$R$4*$O$2 -> 677.88666 | R8: =H8*1000000*Types!$R$4*$O$2 -> 645.71539 | S8: =I8*1000000*Types!$R$4*$O$2 -> 651.12984
A9: High Sulfur (Bituminous) | B9: 61.560001 | C9: 77.962898 | D9: 91.428177 | E9: 92.626122 | F9: 90.15844 | G9: 88.331459 | H9: 89.166435 | I9: 90.092232 | L9: =B9*1000000*Types!$R$5*$O$2 -> 1602.298 | M9: =C9*1000000*Types!$R$5*$O$2 -> 2029.2364 | N9: =D9*1000000*Types!$R$5*$O$2 -> 2379.7138 | O9: =E9*1000000*Types!$R$5*$O$2 -> 2410.8941 | P9: =F9*1000000*Types!$R$5*$O$2 -> 2346.6647 | Q9: =G9*1000000*Types!$R$5*$O$2 -> 2299.1117 | R9: =H9*1000000*Types!$R$5*$O$2 -> 2320.8446 | S9: =I9*1000000*Types!$R$5*$O$2 -> 2344.9415
A11: Central Appalachia | B11: 235.79001 | C11: 184.99139 | D11: 113.59618 | E11: 102.88164 | F11: 98.519623 | G11: 93.103806 | H11: 90.001526 | I11: 80.446884
A12: Medium Sulfur (Premium) 2/ | B12: 39.220001 | C12: 61.667999 | D12: 53.806114 | E12: 55.274105 | F12: 52.964687 | G12: 51.386021 | H12: 48.573219 | I12: 42.623325 | L12: =B12*1000000*Types!$R$14*$O$2 -> 1088.2755 | M12: =C12*1000000*Types!$R$14*$O$2 -> 1711.162 | N12: =D12*1000000*Types!$R$14*$O$2 -> 1493.0106 | O12: =E12*1000000*Types!$R$14*$O$2 -> 1533.7444 | P12: =F12*1000000*Types!$R$14*$O$2 -> 1469.6627 | Q12: =G12*1000000*Types!$R$14*$O$2 -> 1425.8579 | R12: =H12*1000000*Types!$R$14*$O$2 -> 1347.8084 | S12: =I12*1000000*Types!$R$14*$O$2 -> 1182.7109
A13: Low Sulfur (Bituminous) | B13: 47.130001 | C13: 14.016 | D13: 5.623372 | E13: 5.497743 | F13: 4.656759 | G13: 5.227611 | H13: 5.091028 | I13: 5.298721 | L13: =B13*1000000*Types!$R$10*$O$2 -> 1229.1968 | M13: =C13*1000000*Types!$R$10*$O$2 -> 365.55108 | N13: =D13*1000000*Types!$R$10*$O$2 -> 146.66308 | O13: =E13*1000000*Types!$R$10*$O$2 -> 143.38655 | P13: =F13*1000000*Types!$R$10*$O$2 -> 121.45286 | Q13: =G13*1000000*Types!$R$10*$O$2 -> 136.34124 | R13: =H13*1000000*Types!$R$10*$O$2 -> 132.77902 | S13: =I13*1000000*Types!$R$10*$O$2 -> 138.19586
A14: Medium Sulfur (Bituminous) | B14: 149.44 | C14: 109.3074 | D14: 54.166695 | E14: 42.109795 | F14: 40.898174 | G14: 36.490177 | H14: 36.33728 | I14: 32.524841 | L14: =B14*1000000*Types!$R$11*$O$2 -> 3888.0823 | M14: =C14*1000000*Types!$R$11*$O$2 -> 2843.9252 | N14: =D14*1000000*Types!$R$11*$O$2 -> 1409.2918 | O14: =E14*1000000*Types!$R$11*$O$2 -> 1095.5992 | P14: =F14*1000000*Types!$R$11*$O$2 -> 1064.0756 | Q14: =G14*1000000*Types!$R$11*$O$2 -> 949.38978 | R14: =H14*1000000*Types!$R$11*$O$2 -> 945.41176 | S14: =I14*1000000*Types!$R$11*$O$2 -> 846.22094
A16: Southern Appalachia | B16: 21.460001 | C16: 19.381001 | D16: 16.19932 | E16: 15.930906 | F16: 16.231911 | G16: 15.969572 | H16: 15.37926 | I16: 16.52256
A17: Low Sulfur (Premium) 2/ | B17: 8.0799999 | C17: 10.2162 | D17: 12.577519 | E17: 13.072006 | F17: 12.366166 | G17: 12.064705 | H17: 11.46672 | I17: 12.712477 | L17: =B17*1000000*Types!$R$19*$O$2 -> 224.20362 | M17: =C17*1000000*Types!$R$19*$O$2 -> 283.47884 | N17: =D17*1000000*Types!$R$19*$O$2 -> 349.00066 | O17: =E17*1000000*Types!$R$19*$O$2 -> 362.72167 | P17: =F17*1000000*Types!$R$19*$O$2 -> 343.13604 | Q17: =G17*1000000*Types!$R$19*$O$2 -> 334.77111 | R17: =H17*1000000*Types!$R$19*$O$2 -> 318.17823 | S17: =I17*1000000*Types!$R$19*$O$2 -> 352.74547
A18: Low Sulfur (Bituminous) | B18: 0.51999998 | C18: 0.4498 | D18: 0.656552 | E18: 0.495026 | F18: 0.464538 | G18: 0.461979 | H18: 0.454451 | I18: 0.41588 | L18: =B18*1000000*Types!$R$15*$O$2 -> 14.374082 | M18: =C18*1000000*Types!$R$15*$O$2 -> 12.433582 | N18: =D18*1000000*Types!$R$15*$O$2 -> 18.148717 | O18: =E18*1000000*Types!$R$15*$O$2 -> 13.68374 | P18: =F18*1000000*Types!$R$15*$O$2 -> 12.840976 | Q18: =G18*1000000*Types!$R$15*$O$2 -> 12.770239 | R18: =H18*1000000*Types!$R$15*$O$2 -> 12.562147 | S18: =I18*1000000*Types!$R$15*$O$2 -> 11.495949
A19: Medium Sulfur (Bituminous) | B19: 12.860001 | C19: 8.715 | D19: 2.965248 | E19: 2.363874 | F19: 3.401208 | G19: 3.442887 | H19: 3.45809 | I19: 3.394203 | L19: =B19*1000000*Types!$R$16*$O$2 -> 331.46675 | M19: =C19*1000000*Types!$R$16*$O$2 -> 224.62928 | N19: =D19*1000000*Types!$R$16*$O$2 -> 76.429321 | O19: =E19*1000000*Types!$R$16*$O$2 -> 60.928895 | P19: =F19*1000000*Types!$R$16*$O$2 -> 87.666198 | Q19: =G19*1000000*Types!$R$16*$O$2 -> 88.740475 | R19: =H19*1000000*Types!$R$16*$O$2 -> 89.132332 | S19: =I19*1000000*Types!$R$16*$O$2 -> 87.485644
A21: Eastern Interior | B21: 96.460007 | C21: 119.21451 | D21: 160.35899 | E21: 176.68649 | F21: 186.86386 | G21: 205.53111 | H21: 218.0965 | I21: 227.84753
A22: Medium Sulfur (Bituminous) | B22: 29.25 | C22: 10.2173 | D22: 8.252442 | E22: 7.560043 | F22: 7.785225 | G22: 8.098946 | H22: 8.316666 | I22: 8.426445 | L22: =B22*1000000*Types!$R$20*$O$2 -> 694.66733 | M22: =C22*1000000*Types!$R$20*$O$2 -> 242.65383 | N22: =D22*1000000*Types!$R$20*$O$2 -> 195.98981 | O22: =E22*1000000*Types!$R$20*$O$2 -> 179.54581 | P22: =F22*1000000*Types!$R$20*$O$2 -> 184.89373 | Q22: =G22*1000000*Types!$R$20*$O$2 -> 192.34438 | R22: =H22*1000000*Types!$R$20*$O$2 -> 197.51508 | S22: =I22*1000000*Types!$R$20*$O$2 -> 200.12226
A23: High Sulfur (Bituminous) | B23: 63.650002 | C23: 106.2505 | D23: 145.38045 | E23: 162.12541 | F23: 173.00253 | G23: 190.09404 | H23: 202.45912 | I23: 212.11559 | L23: =B23*1000000*Types!$R$21*$O$2 -> 1527.7607 | M23: =C23*1000000*Types!$R$21*$O$2 -> 2550.2803 | N23: =D23*1000000*Types!$R$21*$O$2 -> 3489.4977 | O23: =E23*1000000*Types!$R$21*$O$2 -> 3891.4191 | P23: =F23*1000000*Types!$R$21*$O$2 -> 4152.4975 | Q23: =G23*1000000*Types!$R$21*$O$2 -> 4562.7368 | R23: =H23*1000000*Types!$R$21*$O$2 -> 4859.5299 | S23: =I23*1000000*Types!$R$21*$O$2 -> 5091.3094
A24: Medium Sulfur (Lignite) | B24: 3.5599999 | C24: 2.7467 | D24: 6.726106 | E24: 7.001031 | F24: 6.0761 | G24: 7.338125 | H24: 7.32071 | I24: 7.305501 | L24: =B24*1000000*Types!$R$24*$O$2 -> 38.912153 | M24: =C24*1000000*Types!$R$24*$O$2 -> 30.022475 | N24: =D24*1000000*Types!$R$24*$O$2 -> 73.518896 | O24: =E24*1000000*Types!$R$24*$O$2 -> 76.52393 | P24: =F24*1000000*Types!$R$24*$O$2 -> 66.414083 | Q24: =G24*1000000*Types!$R$24*$O$2 -> 80.208496 | R24: =H24*1000000*Types!$R$24*$O$2 -> 80.018143 | S24: =I24*1000000*Types!$R$24*$O$2 -> 79.851903
A26: Western Interior High Sulfur (Bituminous) | B26: 2.6300001 | C26: 1.78 | D26: 1.133899 | E26: 0.692448 | F26: 0.837489 | G26: 0.629822 | H26: 0.556632 | I26: 0.549103 | L26: =B26*1000000*Types!$R$25*$O$2 -> 58.964445 | M26: =C26*1000000*Types!$R$25*$O$2 -> 39.907493 | N26: =D26*1000000*Types!$R$25*$O$2 -> 25.421948 | O26: =E26*1000000*Types!$R$25*$O$2 -> 15.524643 | P26: =F26*1000000*Types!$R$25*$O$2 -> 18.776453 | Q26: =G26*1000000*Types!$R$25*$O$2 -> 14.120571 | R26: =H26*1000000*Types!$R$25*$O$2 -> 12.479656 | S26: =I26*1000000*Types!$R$25*$O$2 -> 12.310856
A28: Gulf | B28: 50.099998 | C28: 49.768303 | D28: 45.000435 | E28: 50.869812 | F28: 56.662525 | G28: 60.337494 | H28: 60.245583 | I28: 60.712029
A29: Medium Sulfur (Lignite) | B29: 23.32 | C29: 38.936401 | D29: 29.886984 | E29: 34.220127 | F29: 40.014629 | G29: 43.74369 | H29: 43.71743 | I29: 44.233818 | L29: =B29*1000000*Types!$R$26*$O$2 -> 331.16857 | M29: =C29*1000000*Types!$R$26*$O$2 -> 552.93792 | N29: =D29*1000000*Types!$R$26*$O$2 -> 424.42667 | O29: =E29*1000000*Types!$R$26*$O$2 -> 485.96186 | P29: =F29*1000000*Types!$R$26*$O$2 -> 568.2499 | Q29: =G29*1000000*Types!$R$26*$O$2 -> 621.20649 | R29: =H29*1000000*Types!$R$26*$O$2 -> 620.83357 | S29: =I29*1000000*Types!$R$26*$O$2 -> 628.16683
A30: High Sulfur (Lignite) | B30: 26.780001 | C30: 10.8319 | D30: 15.113449 | E30: 16.649687 | F30: 16.647896 | G30: 16.593803 | H30: 16.528152 | I30: 16.478209 | L30: =B30*1000000*Types!$R$27*$O$2 -> 338.77026 | M30: =C30*1000000*Types!$R$27*$O$2 -> 137.02485 | N30: =D30*1000000*Types!$R$27*$O$2 -> 191.18697 | O30: =E30*1000000*Types!$R$27*$O$2 -> 210.62056 | P30: =F30*1000000*Types!$R$27*$O$2 -> 210.59791 | Q30: =G30*1000000*Types!$R$27*$O$2 -> 209.91362 | R30: =H30*1000000*Types!$R$27*$O$2 -> 209.08313 | S30: =I30*1000000*Types!$R$27*$O$2 -> 208.45134
A32: Dakota Medium Sulfur (Lignite) | B32: 30.290001 | C32: 28.5861 | D32: 29.498983 | E32: 30.859964 | F32: 30.855099 | G32: 31.01277 | H32: 30.913713 | I32: 31.001589 | L32: =B32*1000000*Types!$R$28*$O$2 -> 422.16052 | M32: =C32*1000000*Types!$R$28*$O$2 -> 398.41276 | N32: =D32*1000000*Types!$R$28*$O$2 -> 411.13587 | O32: =E32*1000000*Types!$R$28*$O$2 -> 430.10426 | P32: =F32*1000000*Types!$R$28*$O$2 -> 430.03646 | Q32: =G32*1000000*Types!$R$28*$O$2 -> 432.23396 | R32: =H32*1000000*Types!$R$28*$O$2 -> 430.85338 | S32: =I32*1000000*Types!$R$28*$O$2 -> 432.07813
A34: Western Montana | B34: 40.02 | C34: 41.653599 | D34: 50.992363 | E34: 55.299286 | F34: 57.459915 | G34: 56.967728 | H34: 59.250511 | I34: 60.240067
A35: Low Sulfur (Bituminous) | B35: 0 | C35: 5.1356 | D35: 11.276574 | E35: 14.253925 | F35: 12.571007 | G35: 11.974517 | H35: 13.840705 | I35: 14.202073 | L35: =B35*1000000*Types!$R$29*$O$2 -> 0 | M35: =C35*1000000*Types!$R$29*$O$2 -> 107.33743 | N35: =D35*1000000*Types!$R$29*$O$2 -> 235.68783 | O35: =E35*1000000*Types!$R$29*$O$2 -> 297.91643 | P35: =F35*1000000*Types!$R$29*$O$2 -> 262.74234 | Q35: =G35*1000000*Types!$R$29*$O$2 -> 250.2753 | R35: =H35*1000000*Types!$R$29*$O$2 -> 289.27986 | S35: =I35*1000000*Types!$R$29*$O$2 -> 296.83269
A36: Low Sulfur (Sub-Bituminous) | B36: 20.59 | C36: 19.2395 | D36: 21.108536 | E36: 23.140686 | F36: 26.852083 | G36: 27.790392 | H36: 29.186493 | I36: 30.687353 | L36: =B36*1000000*Types!$R$30*$O$2 -> 393.19722 | M36: =C36*1000000*Types!$R$30*$O$2 -> 367.40737 | N36: =D36*1000000*Types!$R$30*$O$2 -> 403.09944 | O36: =E36*1000000*Types!$R$30*$O$2 -> 441.90642 | P36: =F36*1000000*Types!$R$30*$O$2 -> 512.78117 | Q36: =G36*1000000*Types!$R$30*$O$2 -> 530.6996 | R36: =H36*1000000*Types!$R$30*$O$2 -> 557.36026 | S36: =I36*1000000*Types!$R$30*$O$2 -> 586.02145
A37: Medium Sulfur (Sub-Bituminous) | B37: 19.43 | C37: 17.2785 | D37: 18.607252 | E37: 17.904673 | F37: 18.036829 | G37: 17.202822 | H37: 16.22331 | I37: 15.35064 | L37: =B37*1000000*Types!$R$31*$O$2 -> 353.62049 | M37: =C37*1000000*Types!$R$31*$O$2 -> 314.46379 | N37: =D37*1000000*Types!$R$31*$O$2 -> 338.6467 | O37: =E37*1000000*Types!$R$31*$O$2 -> 325.85996 | P37: =F37*1000000*Types!$R$31*$O$2 -> 328.26517 | Q37: =G37*1000000*Types!$R$31*$O$2 -> 313.08647 | R37: =H37*1000000*Types!$R$31*$O$2 -> 295.25963 | S37: =I37*1000000*Types!$R$31*$O$2 -> 279.37729
A39: Wyoming, Powder River Basin | B39: 390.12997 | C39: 426.08209 | D39: 429.81457 | E39: 421.07266 | F39: 441.16431 | G39: 441.33151 | H39: 433.48651 | I39: 421.68985
A40: Low Sulfur (Sub-Bituminous) | B40: 386.54999 | C40: 423.67239 | D40: 424.78198 | E40: 416.90076 | F40: 437.58386 | G40: 438.26355 | H40: 430.67438 | I40: 419.24674 | L40: =B40*1000000*Types!$R$32*$O$2 -> 6867.8889 | M40: =C40*1000000*Types!$R$32*$O$2 -> 7527.448 | N40: =D40*1000000*Types!$R$32*$O$2 -> 7547.1622 | O40: =E40*1000000*Types!$R$32*$O$2 -> 7407.1354 | P40: =F40*1000000*Types!$R$32*$O$2 -> 7774.6151 | Q40: =G40*1000000*Types!$R$32*$O$2 -> 7786.6912 | R40: =H40*1000000*Types!$R$32*$O$2 -> 7651.8533 | S40: =I40*1000000*Types!$R$32*$O$2 -> 7448.8167
A41: Medium Sulfur (Sub-Bituminous) | B41: 3.5799999 | C41: 2.4097 | D41: 5.03258 | E41: 4.171908 | F41: 3.580451 | G41: 3.067972 | H41: 2.812144 | I41: 2.443113 | L41: =B41*1000000*Types!$R$33*$O$2 -> 61.264568 | M41: =C41*1000000*Types!$R$33*$O$2 -> 41.237216 | N41: =D41*1000000*Types!$R$33*$O$2 -> 86.122583 | O41: =E41*1000000*Types!$R$33*$O$2 -> 71.393896 | P41: =F41*1000000*Types!$R$33*$O$2 -> 61.272288 | Q41: =G41*1000000*Types!$R$33*$O$2 -> 52.50223 | R41: =H41*1000000*Types!$R$33*$O$2 -> 48.124244 | S41: =I41*1000000*Types!$R$33*$O$2 -> 41.809013
A43: Western Wyoming | B43: 14.19 | C43: 12.5912 | D43: 14.299883 | E43: 14.080681 | F43: 13.725255 | G43: 8.754208 | H43: 5.735566 | I43: 5.380729
A44: Low Sulfur (Sub-Bituminous) | B44: 3.99 | C44: 6.6947 | D44: 10.646417 | E44: 10.644393 | F44: 10.647707 | G44: 5.552079 | H44: 2.52838 | I44: 2.644879 | L44: =B44*1000000*Types!$R$35*$O$2 -> 79.436538 | M44: =C44*1000000*Types!$R$35*$O$2 -> 133.28416 | N44: =D44*1000000*Types!$R$35*$O$2 -> 211.95852 | O44: =E44*1000000*Types!$R$35*$O$2 -> 211.91823 | P44: =F44*1000000*Types!$R$35*$O$2 -> 211.98421 | Q44: =G44*1000000*Types!$R$35*$O$2 -> 110.53582 | R44: =H44*1000000*Types!$R$35*$O$2 -> 50.337282 | S44: =I44*1000000*Types!$R$35*$O$2 -> 52.656649
A45: Medium Sulfur (Sub-Bituminous) | B45: 10.2 | C45: 5.8965 | D45: 3.653466 | E45: 3.436288 | F45: 3.077548 | G45: 3.202128 | H45: 3.207186 | I45: 2.73585 | L45: =B45*1000000*Types!$R$37*$O$2 -> 210.2811 | M45: =C45*1000000*Types!$R$37*$O$2 -> 121.56103 | N45: =D45*1000000*Types!$R$37*$O$2 -> 75.319103 | O45: =E45*1000000*Types!$R$37*$O$2 -> 70.841806 | P45: =F45*1000000*Types!$R$37*$O$2 -> 63.446096 | Q45: =G45*1000000*Types!$R$37*$O$2 -> 66.014412 | R45: =H45*1000000*Types!$R$37*$O$2 -> 66.118687 | S45: =I45*1000000*Types!$R$37*$O$2 -> 56.401721
A48: Rocky Mountain | B48: 63.029999 | C48: 46.537601 | D48: 34.564098 | E48: 32.716827 | F48: 32.583977 | G48: 31.556044 | H48: 27.079 | I48: 26.471478
A49: Low Sulfur (Premium) 2/ | B49: 0 | C49: 0.0177 | D49: 0.191065 | E49: 0.652074 | F49: 0.19922 | G49: 0.017291 | H49: 0.31732 | I49: 0.287383 | L49: =B49*1000000*Types!$R$40*$O$2 -> 0 | M49: =C49*1000000*Types!$R$40*$O$2 -> 0.49113912 | N49: =D49*1000000*Types!$R$40*$O$2 -> 5.3016664 | O49: =E49*1000000*Types!$R$40*$O$2 -> 18.093732 | P49: =F49*1000000*Types!$R$40*$O$2 -> 5.5279511 | Q49: =G49*1000000*Types!$R$40*$O$2 -> 0.4797902 | R49: =H49*1000000*Types!$R$40*$O$2 -> 8.8049867 | S49: =I49*1000000*Types!$R$40*$O$2 -> 7.9742957
A50: Low Sulfur (Bituminous) | B50: 52.959999 | C50: 41.137901 | D50: 29.066376 | E50: 27.509462 | F50: 27.594793 | G50: 27.171896 | H50: 22.406616 | I50: 21.837765 | L50: =B50*1000000*Types!$R$38*$O$2 -> 1270.6149 | M50: =C50*1000000*Types!$R$38*$O$2 -> 986.97943 | N50: =D50*1000000*Types!$R$38*$O$2 -> 697.35972 | O50: =E50*1000000*Types!$R$38*$O$2 -> 660.00628 | P50: =F50*1000000*Types!$R$38*$O$2 -> 662.05354 | Q50: =G50*1000000*Types!$R$38*$O$2 -> 651.90741 | R50: =H50*1000000*Types!$R$38*$O$2 -> 537.57894 | S50: =I50*1000000*Types!$R$38*$O$2 -> 523.93108
A51: Low Sulfur (Sub-Bituminous) | B51: 10.07 | C51: 5.382 | D51: 5.306658 | E51: 4.555291 | F51: 4.789963 | G51: 4.366855 | H51: 4.355065 | I51: 4.346328 | L51: =B51*1000000*Types!$R$39*$O$2 -> 211.74456 | M51: =C51*1000000*Types!$R$39*$O$2 -> 113.16875 | N51: =D51*1000000*Types!$R$39*$O$2 -> 111.58451 | O51: =E51*1000000*Types!$R$39*$O$2 -> 95.785316 | P51: =F51*1000000*Types!$R$39*$O$2 -> 100.71983 | Q51: =G51*1000000*Types!$R$39*$O$2 -> 91.823022 | R51: =H51*1000000*Types!$R$39*$O$2 -> 91.575111 | S51: =I51*1000000*Types!$R$39*$O$2 -> 91.391395
A53: Arizona/New Mexico | B53: 40.59 | C53: 30.0333 | D53: 33.265373 | E53: 31.140871 | F53: 32.429356 | G53: 34.219841 | H53: 34.157242 | I53: 34.565533
A54: Low Sulfur (Bituminous) | B54: 17.43 | C54: 8.0002 | D54: 5.646163 | E54: 7.141479 | F54: 7.69001 | G54: 7.440862 | H54: 7.593074 | I54: 7.54748 | L54: =B54*1000000*Types!$R$42*$O$2 -> 396.11255 | M54: =C54*1000000*Types!$R$42*$O$2 -> 181.8118 | N54: =D54*1000000*Types!$R$42*$O$2 -> 128.31417 | O54: =E54*1000000*Types!$R$42*$O$2 -> 162.29658 | P54: =F54*1000000*Types!$R$42*$O$2 -> 174.76245 | Q54: =G54*1000000*Types!$R$42*$O$2 -> 169.10033 | R54: =H54*1000000*Types!$R$42*$O$2 -> 172.55949 | S54: =I54*1000000*Types!$R$42*$O$2 -> 171.52332
A55: Medium Sulfur (Bituminous) | B55: 7.9099998 | C55: 3.983 | D55: 6.189983 | E55: 1.638351 | F55: 0.805284 | G55: 3.176401 | H55: 3.150864 | I55: 2.824104 | L55: =B55*1000000*Types!$R$41*$O$2 -> 159.14855 | M55: =C55*1000000*Types!$R$41*$O$2 -> 80.137633 | N55: =D55*1000000*Types!$R$41*$O$2 -> 124.54195 | O55: =E55*1000000*Types!$R$41*$O$2 -> 32.963488 | P55: =F55*1000000*Types!$R$41*$O$2 -> 16.202248 | Q55: =G55*1000000*Types!$R$41*$O$2 -> 63.908927 | R55: =H55*1000000*Types!$R$41*$O$2 -> 63.395125 | S55: =I55*1000000*Types!$R$41*$O$2 -> 56.820741
A56: Medium Sulfur (Sub-Bituminous) | B56: 15.25 | C56: 18.0501 | D56: 21.429226 | E56: 22.361042 | F56: 23.934061 | G56: 23.602581 | H56: 23.413301 | I56: 24.193949 | L56: =B56*1000000*Types!$R$43*$O$2 -> 289.29108 | M56: =C56*1000000*Types!$R$43*$O$2 -> 342.40872 | N56: =D56*1000000*Types!$R$43*$O$2 -> 406.51042 | O56: =E56*1000000*Types!$R$43*$O$2 -> 424.18688 | P56: =F56*1000000*Types!$R$43*$O$2 -> 454.02691 | Q56: =G56*1000000*Types!$R$43*$O$2 -> 447.73876 | R56: =H56*1000000*Types!$R$43*$O$2 -> 444.14814 | S56: =I56*1000000*Types!$R$43*$O$2 -> 458.95696
A58: Washington/Alaska
A59: Low Sulfur (Sub-Bituminous) | B59: 6.7199998 | C59: 2.1489 | D59: 1.756369 | E59: 2.092623 | F59: 2.510458 | G59: 3.040495 | H59: 3.717396 | I59: 4.583861 | L59: =B59*1000000*Types!$R$44*$O$2 -> 113.58142 | M59: =C59*1000000*Types!$R$44*$O$2 -> 36.320702 | N59: =D59*1000000*Types!$R$44*$O$2 -> 29.686144 | O59: =E59*1000000*Types!$R$44*$O$2 -> 35.369508 | P59: =F59*1000000*Types!$R$44*$O$2 -> 42.431754 | Q59: =G59*1000000*Types!$R$44*$O$2 -> 51.390438 | R59: =H59*1000000*Types!$R$44*$O$2 -> 62.831416 | S59: =I59*1000000*Types!$R$44*$O$2 -> 77.476405
A61: Subtotals: All Regions
A63: Premium Metallurgical 2/ | B63: 50.800003 | C63: 90.142799 | D63: 86.854019 | E63: 93.466927 | F63: 95.345093 | G63: 94.016685 | H63: 94.399368 | I63: 91.54245
A64: Bituminous | B64: 520.35999 | C64: 423.61102 | D64: 382.06509 | E64: 389.49142 | F64: 393.93924 | G64: 408.04724 | H64: 417.12714 | I64: 423.72833
A65: Sub-Bituminous | B65: 476.38 | C65: 500.77231 | D65: 512.32251 | E65: 505.20764 | F65: 531.013 | G65: 526.08887 | H65: 516.11762 | I65: 506.23267
A66: Lignite | B66: 83.949997 | C66: 81.101097 | D66: 81.225525 | E66: 88.730804 | F66: 93.593719 | G66: 98.688393 | H66: 98.480003 | I66: 99.019112
A68: Low Sulfur | B68: 547.32001 | C68: 536.1109 | D68: 528.63757 | E68: 525.95551 | F68: 547.92664 | G68: 543.37219 | H68: 531.63159 | I68: 523.81085
A69: Medium Sulfur | B69: 429.54999 | C69: 362.69098 | D69: 280.77356 | E69: 278.84769 | F69: 285.31808 | G69: 287.81986 | H69: 285.78217 | I69: 277.47653
A70: High Sulfur | B70: 154.62 | C70: 196.8253 | D70: 253.05597 | E70: 272.09366 | F70: 280.64636 | G70: 295.64914 | H70: 308.71033 | I70: 319.23514
A72: Underground | B72: 368.15002 | C72: 345.07047 | D72: 326.73929 | E72: 349.50772 | F72: 363.61057 | G72: 375.07669 | H72: 383.01263 | I72: 387.60965
A73: Surface | B73: 763.33997 | C73: 750.5567 | D73: 735.72778 | E73: 727.3891 | F73: 750.28052 | G73: 751.76453 | H73: 743.11145 | I73: 732.91302
A75: United States Total | B75: 1131.49 | C75: 1095.6272 | D75: 1062.4672 | E75: 1076.8969 | F75: 1113.891 | G75: 1126.8412 | H75: 1126.124 | I75: 1120.5226
A77: Waste Coal | C77: 13.209 | D77: 10.28835 | E77: 13.733294 | F77: 13.847169 | G77: 14.739177 | H77: 16.96714 | I77: 18.792078
A79: 1/ Includes Pennsylvania anthracite.
A80: 2/ "Premium" coal is used to make metallurgical coke.
A81: Northern Appalachia: Pennsylvania, Maryland, Ohio, Northern West Virginia.
A82: Central Appalachia: Southern West Virginia, Virginia, Eastern Kentucky, Northern Tennessee.
A83: Southern Appalachia: Alabama, Southern Tennessee.
A84: Eastern Interior: Illinois, Indiana, Mississippi, Western Kentucky.
A85: Western Interior: Iowa, Missouri, Kansas, Oklahoma, Arkansas, Texas (bituminous).
A86: Gulf (lignite Only): Texas, Louisiana, Arkansas.
A87: Dakota: North Dakota, Montana (lignite).
A88: Western Montana: Montana (subbituminous).
A89: Wyoming, Powder River Basin: Wyoming portion of Powder River Basin.
A90: Western Wyoming: Wyoming other than Powder River Basin.
... A97: Source: U.S. Energy Information Administration, AEO2014 National Energy Modeling System.

Sheet Types
A1: Data from EMMDB2010 Table CMM_BASE_YR_SUPPLY_CURVE
A2: Contact: Michael.Mellish@eia.doe.gov | B2: Received:02.24.2010
A3: SCENARIO_DATE | C3: CSCURVE | D3: CSRG | E3: CSRG Code | F3: CSRGCLT | G3: CPSCLT | H3: NBAS Coal Type | I3: CSUL | K3: CMINE | M3: CRANK | O3: Coal Type | P3: Types | Q3: Coal Name | R3: AVG_BTU_CONTENT (MMBtu/ton) | S3: AEO Cumulative Production (MMTons) | T3: AVG_SULFUR_CONTENT (Lbs/MMBtu) | U3: AVG_MERC_CONTENT (Lbs/MMBtu) | V3: Wtd S (lbs/MMBtu) | W3: Wtd Hg (lbs/MMBtu) | X3: Reserves | Y3: Reserves (PJ) | Z3: BASE_YR Prod | AA3: AVG_CO2_EMISS_FCTR (Lbs/MMBtu)
A4: =CONCATENATE("MIN.COAL.",C4,".",E4,".",RIGHT(Q4,3)) -> MIN.COAL.1.NA.BMU | B4: =CONCATENATE(D4,F4) -> 12 | C4: =BASE_YR_SUPPLY_CURVE!B6 -> 1 | D4: =BASE_YR_SUPPLY_CURVE!C6 -> 1 | E4: =BASE_YR_SUPPLY_CURVE!D6 -> NA | F4: =BASE_YR_SUPPLY_CURVE!G6 -> 2 | G4: 2 | H4: 1 | I4: =BASE_YR_SUPPLY_CURVE!K6 -> Medium | J4: {=IF(I4="Low","L",IF(I4="Medium","M",IF(I4="High","H","")))} -> M | K4: =BASE_YR_SUPPLY_CURVE!I6 -> Deep | L4: =IF(K4="Deep","U",IF(K4="Surface","S",IF(K4="Underground","U",""))) -> U | M4: =BASE_YR_SUPPLY_CURVE!J6 -> Bituminous | N4: =IF(M4="Bituminous","B",IF(M4="Lignite","L",IF(M4="Premium","P",IF(M4="GOB","L",IF(M4="Subbituminous","S",""))))) -> B | O4: =BASE_YR_SUPPLY_CURVE!H6 -> MDB | P4: =CONCATENATE(N4,J4) -> BM | Q4: =CONCATENATE("C",E4,P4,L4) -> CNABMU | R4: =BASE_YR_SUPPLY_CURVE!M6 -> 25.19 | S4: {=TRANSPOSE(#REF!)} -> #REF! | T4: =BASE_YR_SUPPLY_CURVE!N6 -> 1.39 | U4: =BASE_YR_SUPPLY_CURVE!P6 -> 11.17 | V4: =S4*T4 -> #REF! | W4: =S4*U4 -> #REF! | X4: =#REF! -> #REF! | Y4: =X4*R4*'Conversion Factors'!$B$4*10^6 -> #REF! | Z4: =BASE_YR_SUPPLY_CURVE!L6 -> 23.308397 | AA4: =BASE_YR_SUPPLY_CURVE!O6 -> 204.7 | AD4: Types | AE4: Types | AF4: Types | AG4: Types | AH4: Types | AI4: Types | AJ4: Types | AK4: Types | AL4: Types
A5: =CONCATENATE("MIN.COAL.",C5,".",E5,".",RIGHT(Q5,3)) -> MIN.COAL.2.NA.BHU | B5: =CONCATENATE(D5,F5) -> 13 | C5: =BASE_YR_SUPPLY_CURVE!B7 -> 2 | D5: =BASE_YR_SUPPLY_CURVE!C7 -> 1 | E5: =BASE_YR_SUPPLY_CURVE!D7 -> NA | F5: =BASE_YR_SUPPLY_CURVE!G7 -> 3 | G5: 3 | H5: 2 | I5: =BASE_YR_SUPPLY_CURVE!K7 -> High | J5: {=IF(I5="Low","L",IF(I5="Medium","M",IF(I5="High","H","")))} -> H | K5: =BASE_YR_SUPPLY_CURVE!I7 -> Deep | L5: =IF(K5="Deep","U",IF(K5="Surface","S",IF(K5="Underground","U",""))) -> U | M5: =BASE_YR_SUPPLY_CURVE!J7 -> Bituminous | N5: =IF(M5="Bituminous","B",IF(M5="Lignite","L",IF(M5="Premium","P",IF(M5="GOB","L",IF(M5="Subbituminous","S",""))))) -> B | O5: =BASE_YR_SUPPLY_CURVE!H7 -> HDB | P5: =CONCATENATE(N5,J5) -> BH | Q5: =CONCATENATE("C",E5,P5,L5) -> CNABHU | R5: =BASE_YR_SUPPLY_CURVE!M7 -> 24.67 | S5: #REF! | T5: =BASE_YR_SUPPLY_CURVE!N7 -> 2.76 | U5: =BASE_YR_SUPPLY_CURVE!P7 -> 11.67 | V5: =S5*T5 -> #REF! | W5: =S5*U5 -> #REF! | X5: =#REF! -> #REF! | Y5: =X5*R5*'Conversion Factors'!$B$4*10^6 -> #REF! | Z5: =BASE_YR_SUPPLY_CURVE!L7 -> 57.71358 | AA5: =BASE_YR_SUPPLY_CURVE!O7 -> 204.7 | AD5: BH | AE5: BL | AF5: BM | AG5: LH | AH5: LM | AI5: PL | AJ5: PM | AK5: SL | AL5: SM
A6: =CONCATENATE("MIN.COAL.",C6,".",E6,".",RIGHT(Q6,3)) -> MIN.COAL.4.NA.BMS | B6: =CONCATENATE(D6,F6) -> 15 | C6: =BASE_YR_SUPPLY_CURVE!B8 -> 4 | D6: =BASE_YR_SUPPLY_CURVE!C8 -> 1 | E6: =BASE_YR_SUPPLY_CURVE!D8 -> NA | F6: =BASE_YR_SUPPLY_CURVE!G8 -> 5 | G6: 14 | H6: 3 | I6: =BASE_YR_SUPPLY_CURVE!K8 -> Medium | J6: {=IF(I6="Low","L",IF(I6="Medium","M",IF(I6="High","H","")))} -> M | K6: =BASE_YR_SUPPLY_CURVE!I8 -> Surface | L6: =IF(K6="Deep","U",IF(K6="Surface","S",IF(K6="Underground","U",""))) -> S | M6: =BASE_YR_SUPPLY_CURVE!J8 -> Bituminous | N6: =IF(M6="Bituminous","B",IF(M6="Lignite","L",IF(M6="Premium","P",IF(M6="GOB","L",IF(M6="Subbituminous","S",""))))) -> B | O6: =BASE_YR_SUPPLY_CURVE!H8 -> MSB | P6: =CONCATENATE(N6,J6) -> BM | Q6: =CONCATENATE("C",E6,P6,L6) -> CNABMS | R6: =BASE_YR_SUPPLY_CURVE!M8 -> 25.19 | S6: #REF! | T6: =BASE_YR_SUPPLY_CURVE!N8 -> 1.39 | U6: =BASE_YR_SUPPLY_CURVE!P8 -> 11.17 | V6: =S6*T6 -> #REF! | W6: =S6*U6 -> #REF! | X6: =#REF! -> #REF! | Y6: =X6*R6*'Conversion Factors'!$B$4*10^6 -> #REF! | Z6: =BASE_YR_SUPPLY_CURVE!L8 -> 8.1464274 | AA6: =BASE_YR_SUPPLY_CURVE!O8 -> 204.7 | AC6: Hg avg | AD6: =DSUM($P$3:$W$44,$W$3,AD4:AD5)/DSUM($P$3:$W$44,$S$3,AD4:AD5) -> #REF! | AE6: =DSUM($P$3:$W$44,$W$3,AE4:AE5)/DSUM($P$3:$W$44,$S$3,AE4:AE5) -> #REF! | AF6: =DSUM($P$3:$W$44,$W$3,AF4:AF5)/DSUM($P$3:$W$44,$S$3,AF4:AF5) -> #REF! | AG6: =DSUM($P$3:$W$44,$W$3,AG4:AG5)/DSUM($P$3:$W$44,$S$3,AG4:AG5) -> #REF! | AH6: =DSUM($P$3:$W$44,$W$3,AH4:AH5)/DSUM($P$3:$W$44,$S$3,AH4:AH5) -> #REF! | AI6: =DSUM($P$3:$W$44,$W$3,AI4:AI5)/DSUM($P$3:$W$44,$S$3,AI4:AI5) -> #REF! | AJ6: =DSUM($P$3:$W$44,$W$3,AJ4:AJ5)/DSUM($P$3:$W$44,$S$3,AJ4:AJ5) -> #REF! | AK6: =DSUM($P$3:$W$44,$W$3,AK4:AK5)/DSUM($P$3:$W$44,$S$3,AK4:AK5) -> #REF! | AL6: =DSUM($P$3:$W$44,$W$3,AL4:AL5)/DSUM($P$3:$W$44,$S$3,AL4:AL5) -> #REF!
A7: =CONCATENATE("MIN.COAL.",C7,".",E7,".",RIGHT(Q7,3)) -> MIN.COAL.5.NA.BHS | B7: =CONCATENATE(D7,F7) -> 16 | C7: =BASE_YR_SUPPLY_CURVE!B9 -> 5 | D7: =BASE_YR_SUPPLY_CURVE!C9 -> 1 | E7: =BASE_YR_SUPPLY_CURVE!D9 -> NA | F7: =BASE_YR_SUPPLY_CURVE!G9 -> 6 | G7: 8 | H7: 1 | I7: =BASE_YR_SUPPLY_CURVE!K9 -> High | J7: {=IF(I7="Low","L",IF(I7="Medium","M",IF(I7="High","H","")))} -> H | K7: =BASE_YR_SUPPLY_CURVE!I9 -> Surface | L7: =IF(K7="Deep","U",IF(K7="Surface","S",IF(K7="Underground","U",""))) -> S | M7: =BASE_YR_SUPPLY_CURVE!J9 -> Bituminous | N7: =IF(M7="Bituminous","B",IF(M7="Lignite","L",IF(M7="Premium","P",IF(M7="GOB","L",IF(M7="Subbituminous","S",""))))) -> B | O7: =BASE_YR_SUPPLY_CURVE!H9 -> HSB | P7: =CONCATENATE(N7,J7) -> BH | Q7: =CONCATENATE("C",E7,P7,L7) -> CNABHS | R7: =BASE_YR_SUPPLY_CURVE!M9 -> 24.67 | S7: #REF! | T7: =BASE_YR_SUPPLY_CURVE!N9 -> 2.76 | U7: =BASE_YR_SUPPLY_CURVE!P9 -> 11.67 | V7: =S7*T7 -> #REF! | W7: =S7*U7 -> #REF! | X7: =#REF! -> #REF! | Y7: =X7*R7*'Conversion Factors'!$B$4*10^6 -> #REF! | Z7: =BASE_YR_SUPPLY_CURVE!L9 -> 14.062838 | AA7: =BASE_YR_SUPPLY_CURVE!O9 -> 204.7 | AC7: S avg | AD7: =DSUM($P$3:$W$44,$V$3,AD4:AD5)/DSUM($P$3:$W$44,$S$3,AD4:AD5) -> #REF! | AE7: =DSUM($P$3:$W$44,$V$3,AE4:AE5)/DSUM($P$3:$W$44,$S$3,AE4:AE5) -> #REF! | AF7: =DSUM($P$3:$W$44,$V$3,AF4:AF5)/DSUM($P$3:$W$44,$S$3,AF4:AF5) -> #REF! | AG7: =DSUM($P$3:$W$44,$V$3,AG4:AG5)/DSUM($P$3:$W$44,$S$3,AG4:AG5) -> #REF! | AH7: =DSUM($P$3:$W$44,$V$3,AH4:AH5)/DSUM($P$3:$W$44,$S$3,AH4:AH5) -> #REF! | AI7: =DSUM($P$3:$W$44,$V$3,AI4:AI5)/DSUM($P$3:$W$44,$S$3,AI4:AI5) -> #REF! | AJ7: =DSUM($P$3:$W$44,$V$3,AJ4:AJ5)/DSUM($P$3:$W$44,$S$3,AJ4:AJ5) -> #REF! | AK7: =DSUM($P$3:$W$44,$V$3,AK4:AK5)/DSUM($P$3:$W$44,$S$3,AK4:AK5) -> #REF! | AL7: =DSUM($P$3:$W$44,$V$3,AL4:AL5)/DSUM($P$3:$W$44,$S$3,AL4:AL5) -> #REF!
A8: =CONCATENATE("MIN.COAL.",C8,".",E8,".",RIGHT(Q8,3)) -> MIN.COAL.6.NA.LHS | B8: =CONCATENATE(D8,F8) -> 18 | C8: =BASE_YR_SUPPLY_CURVE!B10 -> 6 | D8: =BASE_YR_SUPPLY_CURVE!C10 -> 1 | E8: =BASE_YR_SUPPLY_CURVE!D10 -> NA | F8: =BASE_YR_SUPPLY_CURVE!G10 -> 8 | G8: 9 | H8: 2 | I8: =BASE_YR_SUPPLY_CURVE!K10 -> High | J8: {=IF(I8="Low","L",IF(I8="Medium","M",IF(I8="High","H","")))} -> H | K8: =BASE_YR_SUPPLY_CURVE!I10 -> Surface | L8: =IF(K8="Deep","U",IF(K8="Surface","S",IF(K8="Underground","U",""))) -> S | M8: =BASE_YR_SUPPLY_CURVE!J10 -> GOB | N8: =IF(M8="Bituminous","B",IF(M8="Lignite","L",IF(M8="Premium","P",IF(M8="GOB","L",IF(M8="Subbituminous","S",""))))) -> L | O8: =BASE_YR_SUPPLY_CURVE!H10 -> HAL | P8: =CONCATENATE(N8,J8) -> LH | Q8: =CONCATENATE("C",E8,P8,L8) -> CNALHS | R8: =BASE_YR_SUPPLY_CURVE!M10 -> 11.6 | S8: #REF! | T8: =BASE_YR_SUPPLY_CURVE!N10 -> 3.65 | U8: =BASE_YR_SUPPLY_CURVE!P10 -> 63.9 | V8: =S8*T8 -> #REF! | W8: =S8*U8 -> #REF! | X8: =#REF! -> #REF! | Y8: =X8*R8*'Conversion Factors'!$B$4*10^6 -> #REF! | Z8: =BASE_YR_SUPPLY_CURVE!L10 -> 11.040236 | AA8: =BASE_YR_SUPPLY_CURVE!O10 -> 204.7
A9: =CONCATENATE("MIN.COAL.",C9,".",E9,".",RIGHT(Q9,3)) -> MIN.COAL.3.NA.PMU | B9: =CONCATENATE(D9,F9) -> 17 | C9: =BASE_YR_SUPPLY_CURVE!B11 -> 3 | D9: =BASE_YR_SUPPLY_CURVE!C11 -> 1 | E9: =BASE_YR_SUPPLY_CURVE!D11 -> NA | F9: =BASE_YR_SUPPLY_CURVE!G11 -> 7 | G9: 15 | H9: 4 | I9: =BASE_YR_SUPPLY_CURVE!K11 -> Medium | J9: {=IF(I9="Low","L",IF(I9="Medium","M",IF(I9="High","H","")))} -> M | K9: =BASE_YR_SUPPLY_CURVE!I11 -> Underground | L9: =IF(K9="Deep","U",IF(K9="Surface","S",IF(K9="Underground","U",""))) -> U | M9: =BASE_YR_SUPPLY_CURVE!J11 -> Premium | N9: =IF(M9="Bituminous","B",IF(M9="Lignite","L",IF(M9="Premium","P",IF(M9="GOB","L",IF(M9="Subbituminous","S",""))))) -> P | O9: =BASE_YR_SUPPLY_CURVE!H11 -> MUP | P9: =CONCATENATE(N9,J9) -> PM | Q9: =CONCATENATE("C",E9,P9,L9) -> CNAPMU | R9: =BASE_YR_SUPPLY_CURVE!M11 -> 26.3 | S9: #REF! | T9: =BASE_YR_SUPPLY_CURVE!N11 -> 0.88 | U9: =BASE_YR_SUPPLY_CURVE!P11 -> 0 | V9: =S9*T9 -> #REF! | W9: =S9*U9 -> #REF! | X9: 1000 | Y9: =X9*R9*'Conversion Factors'!$B$4*10^6 -> 27747.973 | Z9: =BASE_YR_SUPPLY_CURVE!L11 -> 22.386608 | AA9: =BASE_YR_SUPPLY_CURVE!O11 -> 204.7
A10: =CONCATENATE("MIN.COAL.",C10,".",E10,".",RIGHT(Q10,3)) -> MIN.COAL.7.CA.BLU | B10: =CONCATENATE(D10,F10) -> 21 | C10: =BASE_YR_SUPPLY_CURVE!B12 -> 7 | D10: =BASE_YR_SUPPLY_CURVE!C12 -> 2 | E10: =BASE_YR_SUPPLY_CURVE!D12 -> CA | F10: =BASE_YR_SUPPLY_CURVE!G12 -> 1 | G10: 1 | H10: 1 | I10: =BASE_YR_SUPPLY_CURVE!K12 -> Low | J10: {=IF(I10="Low","L",IF(I10="Medium","M",IF(I10="High","H","")))} -> L | K10: =BASE_YR_SUPPLY_CURVE!I12 -> Deep | L10: =IF(K10="Deep","U",IF(K10="Surface","S",IF(K10="Underground","U",""))) -> U | M10: =BASE_YR_SUPPLY_CURVE!J12 -> Bituminous | N10: =IF(M10="Bituminous","B",IF(M10="Lignite","L",IF(M10="Premium","P",IF(M10="GOB","L",IF(M10="Subbituminous","S",""))))) -> B | O10: =BASE_YR_SUPPLY_CURVE!H12 -> CDB | P10: =CONCATENATE(N10,J10) -> BL | Q10: =CONCATENATE("C",E10,P10,L10) -> CCABLU | R10: =BASE_YR_SUPPLY_CURVE!M12 -> 24.72 | S10: #REF! | T10: =BASE_YR_SUPPLY_CURVE!N12 -> 0.54 | U10: =BASE_YR_SUPPLY_CURVE!P12 -> 5.61 | V10: =S10*T10 -> #REF! | W10: =S10*U10 -> #REF! | X10: =#REF! -> #REF! | Y10: =X10*R10*'Conversion Factors'!$B$4*10^6 -> #REF! | Z10: =BASE_YR_SUPPLY_CURVE!L12 -> 1.9266733 | AA10: =BASE_YR_SUPPLY_CURVE!O12 -> 206.4
A11: =CONCATENATE("MIN.COAL.",C11,".",E11,".",RIGHT(Q11,3)) -> MIN.COAL.8.CA.BMU | B11: =CONCATENATE(D11,F11) -> 22 | C11: =BASE_YR_SUPPLY_CURVE!B13 -> 8 | D11: =BASE_YR_SUPPLY_CURVE!C13 -> 2 | E11: =BASE_YR_SUPPLY_CURVE!D13 -> CA | F11: =BASE_YR_SUPPLY_CURVE!G13 -> 2 | G11: 2 | H11: 2 | I11: =BASE_YR_SUPPLY_CURVE!K13 -> Medium | J11: {=IF(I11="Low","L",IF(I11="Medium","M",IF(I11="High","H","")))} -> M | K11: =BASE_YR_SUPPLY_CURVE!I13 -> Deep | L11: =IF(K11="Deep","U",IF(K11="Surface","S",IF(K11="Underground","U",""))) -> U | M11: =BASE_YR_SUPPLY_CURVE!J13 -> Bituminous | N11: =IF(M11="Bituminous","B",IF(M11="Lignite","L",IF(M11="Premium","P",IF(M11="GOB","L",IF(M11="Subbituminous","S",""))))) -> B | O11: =BASE_YR_SUPPLY_CURVE!H13 -> MDB | P11: =CONCATENATE(N11,J11) -> BM | Q11: =CONCATENATE("C",E11,P11,L11) -> CCABMU | R11: =BASE_YR_SUPPLY_CURVE!M13 -> 24.66 | S11: #REF! | T11: =BASE_YR_SUPPLY_CURVE!N13 -> 0.95 | U11: =BASE_YR_SUPPLY_CURVE!P13 -> 7.58 | V11: =S11*T11 -> #REF! | W11: =S11*U11 -> #REF! | X11: =#REF! -> #REF! | Y11: =X11*R11*'Conversion Factors'!$B$4*10^6 -> #REF! | Z11: =BASE_YR_SUPPLY_CURVE!L13 -> 21.215743 | AA11: =BASE_YR_SUPPLY_CURVE!O13 -> 206.4
A12: =CONCATENATE("MIN.COAL.",C12,".",E12,".",RIGHT(Q12,3)) -> MIN.COAL.10.CA.BLS | B12: =CONCATENATE(D12,F12) -> 24 | C12: =BASE_YR_SUPPLY_CURVE!B14 -> 10 | D12: =BASE_YR_SUPPLY_CURVE!C14 -> 2 | E12: =BASE_YR_SUPPLY_CURVE!D14 -> CA | F12: =BASE_YR_SUPPLY_CURVE!G14 -> 4 | G12: 14 | H12: 3 | I12: =BASE_YR_SUPPLY_CURVE!K14 -> Low | J12: {=IF(I12="Low","L",IF(I12="Medium","M",IF(I12="High","H","")))} -> L | K12: =BASE_YR_SUPPLY_CURVE!I14 -> Surface | L12: =IF(K12="Deep","U",IF(K12="Surface","S",IF(K12="Underground","U",""))) -> S | M12: =BASE_YR_SUPPLY_CURVE!J14 -> Bituminous | N12: =IF(M12="Bituminous","B",IF(M12="Lignite","L",IF(M12="Premium","P",IF(M12="GOB","L",IF(M12="Subbituminous","S",""))))) -> B | O12: =BASE_YR_SUPPLY_CURVE!H14 -> CSB | P12: =CONCATENATE(N12,J12) -> BL | Q12: =CONCATENATE("C",E12,P12,L12) -> CCABLS | R12: =BASE_YR_SUPPLY_CURVE!M14 -> 24.72 | S12: #REF! | T12: =BASE_YR_SUPPLY_CURVE!N14 -> 0.54 | U12: =BASE_YR_SUPPLY_CURVE!P14 -> 5.61 | V12: =S12*T12 -> #REF! | W12: =S12*U12 -> #REF! | X12: =#REF! -> #REF! | Y12: =X12*R12*'Conversion Factors'!$B$4*10^6 -> #REF! | Z12: =BASE_YR_SUPPLY_CURVE!L14 -> 8.2573094 | AA12: =BASE_YR_SUPPLY_CURVE!O14 -> 206.4
A13: =CONCATENATE("MIN.COAL.",C13,".",E13,".",RIGHT(Q13,3)) -> MIN.COAL.11.CA.BMS | B13: =CONCATENATE(D13,F13) -> 25 | C13: =BASE_YR_SUPPLY_CURVE!B15 -> 11 | D13: =BASE_YR_SUPPLY_CURVE!C15 -> 2 | E13: =BASE_YR_SUPPLY_CURVE!D15 -> CA | F13: =BASE_YR_SUPPLY_CURVE!G15 -> 5 | G13: 7 | H13: 1 | I13: =BASE_YR_SUPPLY_CURVE!K15 -> Medium | J13: {=IF(I13="Low","L",IF(I13="Medium","M",IF(I13="High","H","")))} -> M | K13: =BASE_YR_SUPPLY_CURVE!I15 -> Surface | L13: =IF(K13="Deep","U",IF(K13="Surface","S",IF(K13="Underground","U",""))) -> S | M13: =BASE_YR_SUPPLY_CURVE!J15 -> Bituminous | N13: =IF(M13="Bituminous","B",IF(M13="Lignite","L",IF(M13="Premium","P",IF(M13="GOB","L",IF(M13="Subbituminous","S",""))))) -> B | O13: =BASE_YR_SUPPLY_CURVE!H15 -> MSB | P13: =CONCATENATE(N13,J13) -> BM | Q13: =CONCATENATE("C",E13,P13,L13) -> CCABMS | R13: =BASE_YR_SUPPLY_CURVE!M15 -> 24.66 | S13: #REF! | T13: =BASE_YR_SUPPLY_CURVE!N15 -> 0.95 | U13: =BASE_YR_SUPPLY_CURVE!P15 -> 7.58 | V13: =S13*T13 -> #REF! | W13: =S13*U13 -> #REF! | X13: =#REF! -> #REF! | Y13: =X13*R13*'Conversion Factors'!$B$4*10^6 -> #REF! | Z13: =BASE_YR_SUPPLY_CURVE!L15 -> 61.57943 | AA13: =BASE_YR_SUPPLY_CURVE!O15 -> 206.4
A14: =CONCATENATE("MIN.COAL.",C14,".",E14,".",RIGHT(Q14,3)) -> MIN.COAL.9.CA.PMU | B14: =CONCATENATE(D14,F14) -> 27 | C14: =BASE_YR_SUPPLY_CURVE!B16 -> 9 | D14: =BASE_YR_SUPPLY_CURVE!C16 -> 2 | E14: =BASE_YR_SUPPLY_CURVE!D16 -> CA | F14: =BASE_YR_SUPPLY_CURVE!G16 -> 7 | G14: 8 | H14: 2 | I14: =BASE_YR_SUPPLY_CURVE!K16 -> Medium | J14: {=IF(I14="Low","L",IF(I14="Medium","M",IF(I14="High","H","")))} -> M | K14: =BASE_YR_SUPPLY_CURVE!I16 -> Underground | L14: =IF(K14="Deep","U",IF(K14="Surface","S",IF(K14="Underground","U",""))) -> U | M14: =BASE_YR_SUPPLY_CURVE!J16 -> Premium | N14: =IF(M14="Bituminous","B",IF(M14="Lignite","L",IF(M14="Premium","P",IF(M14="GOB","L",IF(M14="Subbituminous","S",""))))) -> P | O14: =BASE_YR_SUPPLY_CURVE!H16 -> MUP | P14: =CONCATENATE(N14,J14) -> PM | Q14: =CONCATENATE("C",E14,P14,L14) -> CCAPMU | R14: =BASE_YR_SUPPLY_CURVE!M16 -> 26.3 | S14: #REF! | T14: =BASE_YR_SUPPLY_CURVE!N16 -> 0.62 | U14: =BASE_YR_SUPPLY_CURVE!P16 -> 0 | V14: =S14*T14 -> #REF! | W14: =S14*U14 -> #REF! | X14: =#REF! -> #REF! | Y14: =X14*R14*'Conversion Factors'!$B$4*10^6 -> #REF! | Z14: =BASE_YR_SUPPLY_CURVE!L16 -> 54.924838 | AA14: =BASE_YR_SUPPLY_CURVE!O16 -> 206.4
A15: =CONCATENATE("MIN.COAL.",C15,".",E15,".",RIGHT(Q15,3)) -> MIN.COAL.12.SA.BLU | B15: =CONCATENATE(D15,F15) -> 31 | C15: =BASE_YR_SUPPLY_CURVE!B17 -> 12 | D15: =BASE_YR_SUPPLY_CURVE!C17 -> 3 | E15: =BASE_YR_SUPPLY_CURVE!D17 -> SA | F15: =BASE_YR_SUPPLY_CURVE!G17 -> 1 | G15: 1 | H15: 1 | I15: =BASE_YR_SUPPLY_CURVE!K17 -> Low | J15: {=IF(I15="Low","L",IF(I15="Medium","M",IF(I15="High","H","")))} -> L | K15: =BASE_YR_SUPPLY_CURVE!I17 -> Deep | L15: =IF(K15="Deep","U",IF(K15="Surface","S",IF(K15="Underground","U",""))) -> U | M15: =BASE_YR_SUPPLY_CURVE!J17 -> Bituminous | N15: =IF(M15="Bituminous","B",IF(M15="Lignite","L",IF(M15="Premium","P",IF(M15="GOB","L",IF(M15="Subbituminous","S",""))))) -> B | O15: =BASE_YR_SUPPLY_CURVE!H17 -> CDB | P15: =CONCATENATE(N15,J15) -> BL | Q15: =CONCATENATE("C",E15,P15,L15) -> CSABLU | R15: =BASE_YR_SUPPLY_CURVE!M17 -> 26.2 | S15: #REF! | T15: =BASE_YR_SUPPLY_CURVE!N17 -> 0.5 | U15: =BASE_YR_SUPPLY_CURVE!P17 -> 3.87 | V15: =S15*T15 -> #REF! | W15: =S15*U15 -> #REF! | X15: =#REF! -> #REF! | Y15: =X15*R15*'Conversion Factors'!$B$4*10^6 -> #REF! | Z15: =BASE_YR_SUPPLY_CURVE!L17 -> 0 | AA15: =BASE_YR_SUPPLY_CURVE!O17 -> 204.7
A16: =CONCATENATE("MIN.COAL.",C16,".",E16,".",RIGHT(Q16,3)) -> MIN.COAL.13.SA.BMU | B16: =CONCATENATE(D16,F16) -> 32 | C16: =BASE_YR_SUPPLY_CURVE!B18 -> 13 | D16: =BASE_YR_SUPPLY_CURVE!C18 -> 3 | E16: =BASE_YR_SUPPLY_CURVE!D18 -> SA | F16: =BASE_YR_SUPPLY_CURVE!G18 -> 2 | G16: 2 | H16: 2 | I16: =BASE_YR_SUPPLY_CURVE!K18 -> Medium | J16: {=IF(I16="Low","L",IF(I16="Medium","M",IF(I16="High","H","")))} -> M | K16: =BASE_YR_SUPPLY_CURVE!I18 -> Deep | L16: =IF(K16="Deep","U",IF(K16="Surface","S",IF(K16="Underground","U",""))) -> U | M16: =BASE_YR_SUPPLY_CURVE!J18 -> Bituminous | N16: =IF(M16="Bituminous","B",IF(M16="Lignite","L",IF(M16="Premium","P",IF(M16="GOB","L",IF(M16="Subbituminous","S",""))))) -> B | O16: =BASE_YR_SUPPLY_CURVE!H18 -> MDB | P16: =CONCATENATE(N16,J16) -> BM | Q16: =CONCATENATE("C",E16,P16,L16) -> CSABMU | R16: =BASE_YR_SUPPLY_CURVE!M18 -> 24.43 | S16: #REF! | T16: =BASE_YR_SUPPLY_CURVE!N18 -> 1.37 | U16: =BASE_YR_SUPPLY_CURVE!P18 -> 10.15 | V16: =S16*T16 -> #REF! | W16: =S16*U16 -> #REF! | X16: =#REF! -> #REF! | Y16: =X16*R16*'Conversion Factors'!$B$4*10^6 -> #REF! | Z16: =BASE_YR_SUPPLY_CURVE!L18 -> 0.334467 | AA16: =BASE_YR_SUPPLY_CURVE!O18 -> 204.7
A17: =CONCATENATE("MIN.COAL.",C17,".",E17,".",RIGHT(Q17,3)) -> MIN.COAL.15.SA.BLS | B17: =CONCATENATE(D17,F17) -> 34 | C17: =BASE_YR_SUPPLY_CURVE!B19 -> 15 | D17: =BASE_YR_SUPPLY_CURVE!C19 -> 3 | E17: =BASE_YR_SUPPLY_CURVE!D19 -> SA | F17: =BASE_YR_SUPPLY_CURVE!G19 -> 4 | G17: 13 | H17: 3 | I17: =BASE_YR_SUPPLY_CURVE!K19 -> Low | J17: {=IF(I17="Low","L",IF(I17="Medium","M",IF(I17="High","H","")))} -> L | K17: =BASE_YR_SUPPLY_CURVE!I19 -> Surface | L17: =IF(K17="Deep","U",IF(K17="Surface","S",IF(K17="Underground","U",""))) -> S | M17: =BASE_YR_SUPPLY_CURVE!J19 -> Bituminous | N17: =IF(M17="Bituminous","B",IF(M17="Lignite","L",IF(M17="Premium","P",IF(M17="GOB","L",IF(M17="Subbituminous","S",""))))) -> B | O17: =BASE_YR_SUPPLY_CURVE!H19 -> CSB | P17: =CONCATENATE(N17,J17) -> BL | Q17: =CONCATENATE("C",E17,P17,L17) -> CSABLS | R17: =BASE_YR_SUPPLY_CURVE!M19 -> 26.2 | S17: #REF! | T17: =BASE_YR_SUPPLY_CURVE!N19 -> 0.5 | U17: =BASE_YR_SUPPLY_CURVE!P19 -> 3.87 | V17: =S17*T17 -> #REF! | W17: =S17*U17 -> #REF! | X17: =#REF! -> #REF! | Y17: =X17*R17*'Conversion Factors'!$B$4*10^6 -> #REF! | Z17: =BASE_YR_SUPPLY_CURVE!L19 -> 0.24724858 | AA17: =BASE_YR_SUPPLY_CURVE!O19 -> 204.7
A18: =CONCATENATE("MIN.COAL.",C18,".",E18,".",RIGHT(Q18,3)) -> MIN.COAL.16.SA.BMS | B18: =CONCATENATE(D18,F18) -> 35 | C18: =BASE_YR_SUPPLY_CURVE!B20 -> 16 | D18: =BASE_YR_SUPPLY_CURVE!C20 -> 3 | E18: =BASE_YR_SUPPLY_CURVE!D20 -> SA | F18: =BASE_YR_SUPPLY_CURVE!G20 -> 5 | G18: 7 | H18: 1 | I18: =BASE_YR_SUPPLY_CURVE!K20 -> Medium | J18: {=IF(I18="Low","L",IF(I18="Medium","M",IF(I18="High","H","")))} -> M | K18: =BASE_YR_SUPPLY_CURVE!I20 -> Surface | L18: =IF(K18="Deep","U",IF(K18="Surface","S",IF(K18="Underground","U",""))) -> S | M18: =BASE_YR_SUPPLY_CURVE!J20 -> Bituminous | N18: =IF(M18="Bituminous","B",IF(M18="Lignite","L",IF(M18="Premium","P",IF(M18="GOB","L",IF(M18="Subbituminous","S",""))))) -> B | O18: =BASE_YR_SUPPLY_CURVE!H20 -> MSB | P18: =CONCATENATE(N18,J18) -> BM | Q18: =CONCATENATE("C",E18,P18,L18) -> CSABMS | R18: =BASE_YR_SUPPLY_CURVE!M20 -> 24.43 | S18: #REF! | T18: =BASE_YR_SUPPLY_CURVE!N20 -> 1.37 | U18: =BASE_YR_SUPPLY_CURVE!P20 -> 10.15 | V18: =S18*T18 -> #REF! | W18: =S18*U18 -> #REF! | X18: =#REF! -> #REF! | Y18: =X18*R18*'Conversion Factors'!$B$4*10^6 -> #REF! | Z18: =BASE_YR_SUPPLY_CURVE!L20 -> 6.6377464 | AA18: =BASE_YR_SUPPLY_CURVE!O20 -> 204.7
A19: =CONCATENATE("MIN.COAL.",C19,".",E19,".",RIGHT(Q19,3)) -> MIN.COAL.14.SA.PLU | B19: =CONCATENATE(D19,F19) -> 37 | C19: =BASE_YR_SUPPLY_CURVE!B21 -> 14 | D19: =BASE_YR_SUPPLY_CURVE!C21 -> 3 | E19: =BASE_YR_SUPPLY_CURVE!D21 -> SA | F19: =BASE_YR_SUPPLY_CURVE!G21 -> 7 | G19: 8 | H19: 2 | I19: =BASE_YR_SUPPLY_CURVE!K21 -> Low | J19: {=IF(I19="Low","L",IF(I19="Medium","M",IF(I19="High","H","")))} -> L | K19: =BASE_YR_SUPPLY_CURVE!I21 -> Underground | L19: =IF(K19="Deep","U",IF(K19="Surface","S",IF(K19="Underground","U",""))) -> U | M19: =BASE_YR_SUPPLY_CURVE!J21 -> Premium | N19: =IF(M19="Bituminous","B",IF(M19="Lignite","L",IF(M19="Premium","P",IF(M19="GOB","L",IF(M19="Subbituminous","S",""))))) -> P | O19: =BASE_YR_SUPPLY_CURVE!H21 -> CUP | P19: =CONCATENATE(N19,J19) -> PL | Q19: =CONCATENATE("C",E19,P19,L19) -> CSAPLU | R19: =BASE_YR_SUPPLY_CURVE!M21 -> 26.3 | S19: #REF! | T19: =BASE_YR_SUPPLY_CURVE!N21 -> 0.46 | U19: =BASE_YR_SUPPLY_CURVE!P21 -> 0 | V19: =S19*T19 -> #REF! | W19: =S19*U19 -> #REF! | X19: =#REF! -> #REF! | Y19: =X19*R19*'Conversion Factors'!$B$4*10^6 -> #REF! | Z19: =BASE_YR_SUPPLY_CURVE!L21 -> 12.235132 | AA19: =BASE_YR_SUPPLY_CURVE!O21 -> 204.7
A20: =CONCATENATE("MIN.COAL.",C20,".",E20,".",RIGHT(Q20,3)) -> MIN.COAL.17.EI.BMU | B20: =CONCATENATE(D20,F20) -> 42 | C20: =BASE_YR_SUPPLY_CURVE!B22 -> 17 | D20: =BASE_YR_SUPPLY_CURVE!C22 -> 4 | E20: =BASE_YR_SUPPLY_CURVE!D22 -> EI | F20: =BASE_YR_SUPPLY_CURVE!G22 -> 2 | G20: 2 | H20: 1 | I20: =BASE_YR_SUPPLY_CURVE!K22 -> Medium | J20: {=IF(I20="Low","L",IF(I20="Medium","M",IF(I20="High","H","")))} -> M | K20: =BASE_YR_SUPPLY_CURVE!I22 -> Deep | L20: =IF(K20="Deep","U",IF(K20="Surface","S",IF(K20="Underground","U",""))) -> U | M20: =BASE_YR_SUPPLY_CURVE!J22 -> Bituminous | N20: =IF(M20="Bituminous","B",IF(M20="Lignite","L",IF(M20="Premium","P",IF(M20="GOB","L",IF(M20="Subbituminous","S",""))))) -> B | O20: =BASE_YR_SUPPLY_CURVE!H22 -> MDB | P20: =CONCATENATE(N20,J20) -> BM | Q20: =CONCATENATE("C",E20,P20,L20) -> CEIBMU | R20: =BASE_YR_SUPPLY_CURVE!M22 -> 22.51 | S20: #REF! | T20: =BASE_YR_SUPPLY_CURVE!N22 -> 1.21 | U20: =BASE_YR_SUPPLY_CURVE!P22 -> 5.6 | V20: =S20*T20 -> #REF! | W20: =S20*U20 -> #REF! | X20: =#REF! -> #REF! | Y20: =X20*R20*'Conversion Factors'!$B$4*10^6 -> #REF! | Z20: =BASE_YR_SUPPLY_CURVE!L22 -> 5.6488708 | AA20: =BASE_YR_SUPPLY_CURVE!O22 -> 203.1
