Workbook

Sheet GHG-SUP
C2: ~TFM_INS
C3: TimeSlice | D3: LimType | E3: Attribute | F3: Year | G3: Other_Indexes | H3: Pset_PN | I3: PSET_CI | J3: PSET_CO | K3: Pset_PD | L3: Cset_CN | M3: AllRegions | N3: R0 | O3: R1 | P3: R2 | Q3: R3 | R3: R4 | S3: R5 | T3: R6
E4: FLO_EMIS | F4: 2010 | G4: ACT | H4: ="SEC"&J4 -> SECC* | J4: C* | L4: CO2 | N4: =#REF! -> #REF!
E5: FLO_EMIS | F5: 2015 | G5: ACT | H5: ="SEC"&J5 -> SECC* | J5: C* | L5: CO2 | N5: =N4 -> #REF!
E6: FLO_EMIS | F6: 2020 | G6: ACT | H6: ="SEC"&J6 -> SECC* | J6: C* | L6: CO2 | N6: =N5 -> #REF!
E7: FLO_EMIS | F7: 2055 | G7: ACT | H7: ="SEC"&J7 -> SECC* | J7: C* | L7: CO2 | N7: =N6 -> #REF!
E8: FLO_EMIS | F8: 2010 | G8: ACT | H8: ="SEC"&J8 -> SECC* | J8: C* | L8: VOC | N8: =#REF! -> #REF!
E9: FLO_EMIS | F9: 2015 | G9: ACT | H9: ="SEC"&J9 -> SECC* | J9: C* | L9: VOC | N9: =N8 -> #REF!
E10: FLO_EMIS | F10: 2020 | G10: ACT | H10: ="SEC"&J10 -> SECC* | J10: C* | L10: VOC | N10: =N9 -> #REF!
E11: FLO_EMIS | F11: 2055 | G11: ACT | H11: ="SEC"&J11 -> SECC* | J11: C* | L11: VOC | N11: =N10 -> #REF!
E12: FLO_EMIS | F12: 2010 | G12: ACT | H12: ="SEC"&J12 -> SECC* | J12: C* | L12: CO | N12: =#REF! -> #REF!
E13: FLO_EMIS | F13: 2015 | G13: ACT | H13: ="SEC"&J13 -> SECC* | J13: C* | L13: CO | N13: =N12 -> #REF!
E14: FLO_EMIS | F14: 2020 | G14: ACT | H14: ="SEC"&J14 -> SECC* | J14: C* | L14: CO | N14: =N13 -> #REF!
E15: FLO_EMIS | F15: 2055 | G15: ACT | H15: ="SEC"&J15 -> SECC* | J15: C* | L15: CO | N15: =N14 -> #REF!
E16: FLO_EMIS | F16: 2010 | G16: ACT | H16: ="SEC"&J16 -> SECC* | J16: C* | L16: NOX | N16: =#REF! -> #REF!
E17: FLO_EMIS | F17: 2015 | G17: ACT | H17: ="SEC"&J17 -> SECC* | J17: C* | L17: NOX | N17: =N16 -> #REF!
E18: FLO_EMIS | F18: 2020 | G18: ACT | H18: ="SEC"&J18 -> SECC* | J18: C* | L18: NOX | N18: =N17 -> #REF!
E19: FLO_EMIS | F19: 2055 | G19: ACT | H19: ="SEC"&J19 -> SECC* | J19: C* | L19: NOX | N19: =N18 -> #REF!
E20: FLO_EMIS | F20: 2010 | G20: ACT | H20: ="SEC"&J20 -> SECC* | J20: C* | L20: PM10 | N20: =#REF! -> #REF!
E21: FLO_EMIS | F21: 2015 | G21: ACT | H21: ="SEC"&J21 -> SECC* | J21: C* | L21: PM10 | N21: =N20 -> #REF!
E22: FLO_EMIS | F22: 2020 | G22: ACT | H22: ="SEC"&J22 -> SECC* | J22: C* | L22: PM10 | N22: =N21 -> #REF!
E23: FLO_EMIS | F23: 2055 | G23: ACT | H23: ="SEC"&J23 -> SECC* | J23: C* | L23: PM10 | N23: =N22 -> #REF!
E24: FLO_EMIS | F24: 2010 | G24: ACT | H24: ="SEC"&J24 -> SECC* | J24: C* | L24: PM25 | N24: =#REF! -> #REF!
E25: FLO_EMIS | F25: 2015 | G25: ACT | H25: ="SEC"&J25 -> SECC* | J25: C* | L25: PM25 | N25: =N24 -> #REF!
E26: FLO_EMIS | F26: 2020 | G26: ACT | H26: ="SEC"&J26 -> SECC* | J26: C* | L26: PM25 | N26: =N25 -> #REF!
E27: FLO_EMIS | F27: 2055 | G27: ACT | H27: ="SEC"&J27 -> SECC* | J27: C* | L27: PM25 | N27: =N26 -> #REF!
E28: FLO_EMIS | F28: 2010 | G28: ACT | H28: ="SEC"&J28 -> SECC* | J28: C* | L28: SO2 | N28: =#REF! -> #REF!
E29: FLO_EMIS | F29: 2015 | G29: ACT | H29: ="SEC"&J29 -> SECC* | J29: C* | L29: SO2 | N29: =N28 -> #REF!
E30: FLO_EMIS | F30: 2020 | G30: ACT | H30: ="SEC"&J30 -> SECC* | J30: C* | L30: SO2 | N30: =N29 -> #REF!
E31: FLO_EMIS | F31: 2055 | G31: ACT | H31: ="SEC"&J31 -> SECC* | J31: C* | L31: SO2 | N31: =N30 -> #REF!
E32: FLO_EMIS | F32: 2010 | G32: ACT | H32: ="SEC"&J32 -> SECC* | J32: C* | L32: CH4 | N32: =#REF! -> #REF!
E33: FLO_EMIS | F33: 2015 | G33: ACT | H33: ="SEC"&J33 -> SECC* | J33: C* | L33: CH4 | N33: =N32 -> #REF!
E34: FLO_EMIS | F34: 2020 | G34: ACT | H34: ="SEC"&J34 -> SECC* | J34: C* | L34: CH4 | N34: =N33 -> #REF!
E35: FLO_EMIS | F35: 2055 | G35: ACT | H35: ="SEC"&J35 -> SECC* | J35: C* | L35: CH4 | N35: =N34 -> #REF!
E36: FLO_EMIS | F36: 2010 | G36: ACT | H36: ="SEC"&J36 -> SECC* | J36: C* | L36: N2O | N36: =#REF! -> #REF!
E37: FLO_EMIS | F37: 2015 | G37: ACT | H37: ="SEC"&J37 -> SECC* | J37: C* | L37: N2O | N37: =N36 -> #REF!
E38: FLO_EMIS | F38: 2020 | G38: ACT | H38: ="SEC"&J38 -> SECC* | J38: C* | L38: N2O | N38: =N37 -> #REF!
E39: FLO_EMIS | F39: 2055 | G39: ACT | H39: ="SEC"&J39 -> SECC* | J39: C* | L39: N2O | N39: =N38 -> #REF!
E40: FLO_EMIS | F40: 2010 | G40: ACT | H40: ="SEC"&J40 -> SECC* | J40: C* | L40: OC | N40: =#REF! -> #REF!
E41: FLO_EMIS | F41: 2015 | G41: ACT | H41: ="SEC"&J41 -> SECC* | J41: C* | L41: OC | N41: =N40 -> #REF!
E42: FLO_EMIS | F42: 2020 | G42: ACT | H42: ="SEC"&J42 -> SECC* | J42: C* | L42: OC | N42: =N41 -> #REF!
E43: FLO_EMIS | F43: 2055 | G43: ACT | H43: ="SEC"&J43 -> SECC* | J43: C* | L43: OC | N43: =N42 -> #REF!
E44: FLO_EMIS | F44: 2010 | G44: ACT | H44: ="SEC"&J44 -> SECC* | J44: C* | L44: BC | N44: =#REF! -> #REF!
E45: FLO_EMIS | F45: 2015 | G45: ACT | H45: ="SEC"&J45 -> SECC* | J45: C* | L45: BC | N45: =N44 -> #REF!
E46: FLO_EMIS | F46: 2020 | G46: ACT | H46: ="SEC"&J46 -> SECC* | J46: C* | L46: BC | N46: =N45 -> #REF!
E47: FLO_EMIS | F47: 2055 | G47: ACT | H47: ="SEC"&J47 -> SECC* | J47: C* | L47: BC | N47: =N46 -> #REF!
C48: *
E49: FLO_EMIS | F49: 2010 | G49: ACT | H49: SCMINNGAD | I49: NGAD0 | L49: CO2 | O49: =P49 -> #REF! | P49: =#REF!/1000 -> #REF! | Q49: =#REF!/1000 -> #REF! | R49: =#REF!/1000 -> #REF! | S49: =#REF!/1000 -> #REF! | T49: =#REF!/1000 -> #REF!
E50: FLO_EMIS | F50: 2015 | G50: ACT | H50: SCMINNGAD | I50: NGAD0 | L50: CO2 | O50: =P50 -> #REF! | P50: =#REF!/1000 -> #REF! | Q50: =#REF!/1000 -> #REF! | R50: =#REF!/1000 -> #REF! | S50: =#REF!/1000 -> #REF! | T50: =#REF!/1000 -> #REF!
E51: FLO_EMIS | F51: 2020 | G51: ACT | H51: SCMINNGAD | I51: NGAD0 | L51: CO2 | O51: =O50 -> #REF! | P51: =P50 -> #REF! | Q51: =Q50 -> #REF! | R51: =R50 -> #REF! | S51: =S50 -> #REF! | T51: =T50 -> #REF!
E52: FLO_EMIS | F52: 2055 | G52: ACT | H52: SCMINNGAD | I52: NGAD0 | L52: CO2 | O52: =O51 -> #REF! | P52: =P51 -> #REF! | Q52: =Q51 -> #REF! | R52: =R51 -> #REF! | S52: =S51 -> #REF! | T52: =T51 -> #REF!
E53: FLO_EMIS | F53: 2010 | G53: ACT | H53: SCMINNGAD | I53: NGAD0 | L53: VOC | O53: =P53 -> #REF! | P53: =#REF! -> #REF! | Q53: =P53 -> #REF! | R53: =Q53 -> #REF! | S53: =R53 -> #REF! | T53: =S53 -> #REF!
E54: FLO_EMIS | F54: 2015 | G54: ACT | H54: SCMINNGAD | I54: NGAD0 | L54: VOC | O54: =P54 -> #REF! | P54: =#REF! -> #REF! | Q54: =P54 -> #REF! | R54: =Q54 -> #REF! | S54: =R54 -> #REF! | T54: =S54 -> #REF!
E55: FLO_EMIS | F55: 2020 | G55: ACT | H55: SCMINNGAD | I55: NGAD0 | L55: VOC | O55: =P55 -> #REF! | P55: =#REF! -> #REF! | Q55: =P55 -> #REF! | R55: =Q55 -> #REF! | S55: =R55 -> #REF! | T55: =S55 -> #REF!
E56: FLO_EMIS | F56: 2055 | G56: ACT | H56: SCMINNGAD | I56: NGAD0 | L56: VOC | O56: =O55 -> #REF! | P56: =P55 -> #REF! | Q56: =Q55 -> #REF! | R56: =R55 -> #REF! | S56: =S55 -> #REF! | T56: =T55 -> #REF!
E57: FLO_EMIS | F57: 2010 | G57: ACT | H57: SCMINNGAD | I57: NGAD0 | L57: CO | O57: =P57 -> #REF! | P57: =#REF! -> #REF! | Q57: =P57 -> #REF! | R57: =Q57 -> #REF! | S57: =R57 -> #REF! | T57: =S57 -> #REF!
E58: FLO_EMIS | F58: 2015 | G58: ACT | H58: SCMINNGAD | I58: NGAD0 | L58: CO | O58: =P58 -> #REF! | P58: =#REF! -> #REF! | Q58: =P58 -> #REF! | R58: =Q58 -> #REF! | S58: =R58 -> #REF! | T58: =S58 -> #REF!
E59: FLO_EMIS | F59: 2020 | G59: ACT | H59: SCMINNGAD | I59: NGAD0 | L59: CO | O59: =P59 -> #REF! | P59: =#REF! -> #REF! | Q59: =P59 -> #REF! | R59: =Q59 -> #REF! | S59: =R59 -> #REF! | T59: =S59 -> #REF!
E60: FLO_EMIS | F60: 2055 | G60: ACT | H60: SCMINNGAD | I60: NGAD0 | L60: CO | O60: =O59 -> #REF! | P60: =P59 -> #REF! | Q60: =Q59 -> #REF! | R60: =R59 -> #REF! | S60: =S59 -> #REF! | T60: =T59 -> #REF!
E61: FLO_EMIS | F61: 2010 | G61: ACT | H61: SCMINNGAD | I61: NGAD0 | L61: NOX | O61: =P61 -> #REF! | P61: =#REF! -> #REF! | Q61: =P61 -> #REF! | R61: =Q61 -> #REF! | S61: =R61 -> #REF! | T61: =S61 -> #REF!
E62: FLO_EMIS | F62: 2015 | G62: ACT | H62: SCMINNGAD | I62: NGAD0 | L62: NOX | O62: =P62 -> #REF! | P62: =#REF! -> #REF! | Q62: =P62 -> #REF! | R62: =Q62 -> #REF! | S62: =R62 -> #REF! | T62: =S62 -> #REF!
E63: FLO_EMIS | F63: 2020 | G63: ACT | H63: SCMINNGAD | I63: NGAD0 | L63: NOX | O63: =P63 -> #REF! | P63: =#REF! -> #REF! | Q63: =P63 -> #REF! | R63: =Q63 -> #REF! | S63: =R63 -> #REF! | T63: =S63 -> #REF!
E64: FLO_EMIS | F64: 2055 | G64: ACT | H64: SCMINNGAD | I64: NGAD0 | L64: NOX | O64: =O63 -> #REF! | P64: =P63 -> #REF! | Q64: =Q63 -> #REF! | R64: =R63 -> #REF! | S64: =S63 -> #REF! | T64: =T63 -> #REF!
E65: FLO_EMIS | F65: 2010 | G65: ACT | H65: SCMINNGAD | I65: NGAD0 | L65: PM10 | O65: =P65 -> #REF! | P65: =#REF! -> #REF! | Q65: =P65 -> #REF! | R65: =Q65 -> #REF! | S65: =R65 -> #REF! | T65: =S65 -> #REF!
E66: FLO_EMIS | F66: 2015 | G66: ACT | H66: SCMINNGAD | I66: NGAD0 | L66: PM10 | O66: =P66 -> #REF! | P66: =#REF! -> #REF! | Q66: =P66 -> #REF! | R66: =Q66 -> #REF! | S66: =R66 -> #REF! | T66: =S66 -> #REF!
E67: FLO_EMIS | F67: 2020 | G67: ACT | H67: SCMINNGAD | I67: NGAD0 | L67: PM10 | O67: =P67 -> #REF! | P67: =#REF! -> #REF! | Q67: =P67 -> #REF! | R67: =Q67 -> #REF! | S67: =R67 -> #REF! | T67: =S67 -> #REF!
E68: FLO_EMIS | F68: 2055 | G68: ACT | H68: SCMINNGAD | I68: NGAD0 | L68: PM10 | O68: =O67 -> #REF! | P68: =P67 -> #REF! | Q68: =Q67 -> #REF! | R68: =R67 -> #REF! | S68: =S67 -> #REF! | T68: =T67 -> #REF!
E69: FLO_EMIS | F69: 2010 | G69: ACT | H69: SCMINNGAD | I69: NGAD0 | L69: PM25 | O69: =P69 -> #REF! | P69: =#REF! -> #REF! | Q69: =P69 -> #REF! | R69: =Q69 -> #REF! | S69: =R69 -> #REF! | T69: =S69 -> #REF!
E70: FLO_EMIS | F70: 2015 | G70: ACT | H70: SCMINNGAD | I70: NGAD0 | L70: PM25 | O70: =P70 -> #REF! | P70: =#REF! -> #REF! | Q70: =P70 -> #REF! | R70: =Q70 -> #REF! | S70: =R70 -> #REF! | T70: =S70 -> #REF!
E71: FLO_EMIS | F71: 2020 | G71: ACT | H71: SCMINNGAD | I71: NGAD0 | L71: PM25 | O71: =P71 -> #REF! | P71: =#REF! -> #REF! | Q71: =P71 -> #REF! | R71: =Q71 -> #REF! | S71: =R71 -> #REF! | T71: =S71 -> #REF!
E72: FLO_EMIS | F72: 2055 | G72: ACT | H72: SCMINNGAD | I72: NGAD0 | L72: PM25 | O72: =O71 -> #REF! | P72: =P71 -> #REF! | Q72: =Q71 -> #REF! | R72: =R71 -> #REF! | S72: =S71 -> #REF! | T72: =T71 -> #REF!
E73: FLO_EMIS | F73: 2010 | G73: ACT | H73: SCMINNGAD | I73: NGAD0 | L73: SO2 | O73: =P73 -> #REF! | P73: =#REF! -> #REF! | Q73: =P73 -> #REF! | R73: =Q73 -> #REF! | S73: =R73 -> #REF! | T73: =S73 -> #REF!
E74: FLO_EMIS | F74: 2015 | G74: ACT | H74: SCMINNGAD | I74: NGAD0 | L74: SO2 | O74: =P74 -> #REF! | P74: =#REF! -> #REF! | Q74: =P74 -> #REF! | R74: =Q74 -> #REF! | S74: =R74 -> #REF! | T74: =S74 -> #REF!
E75: FLO_EMIS | F75: 2020 | G75: ACT | H75: SCMINNGAD | I75: NGAD0 | L75: SO2 | O75: =P75 -> #REF! | P75: =#REF! -> #REF! | Q75: =P75 -> #REF! | R75: =Q75 -> #REF! | S75: =R75 -> #REF! | T75: =S75 -> #REF!
E76: FLO_EMIS | F76: 2055 | G76: ACT | H76: SCMINNGAD | I76: NGAD0 | L76: SO2 | O76: =O75 -> #REF! | P76: =P75 -> #REF! | Q76: =Q75 -> #REF! | R76: =R75 -> #REF! | S76: =S75 -> #REF! | T76: =T75 -> #REF!
E77: FLO_EMIS | F77: 2010 | G77: ACT | H77: SCMINNGAD | I77: NGAD0 | L77: CH4 | O77: =P77 -> #REF! | P77: =#REF! -> #REF! | Q77: =#REF!/1000 -> #REF! | R77: =#REF!/1000 -> #REF! | S77: =#REF!/1000 -> #REF! | T77: =#REF!/1000 -> #REF!
E78: FLO_EMIS | F78: 2015 | G78: ACT | H78: SCMINNGAD | I78: NGAD0 | L78: CH4 | O78: =P78 -> #REF! | P78: =#REF! -> #REF! | Q78: =#REF!/1000 -> #REF! | R78: =#REF!/1000 -> #REF! | S78: =#REF!/1000 -> #REF! | T78: =#REF!/1000 -> #REF!
E79: FLO_EMIS | F79: 2020 | G79: ACT | H79: SCMINNGAD | I79: NGAD0 | L79: CH4 | O79: =O78 -> #REF! | P79: =P78 -> #REF! | Q79: =Q78 -> #REF! | R79: =R78 -> #REF! | S79: =S78 -> #REF! | T79: =T78 -> #REF!
E80: FLO_EMIS | F80: 2055 | G80: ACT | H80: SCMINNGAD | I80: NGAD0 | L80: CH4 | O80: =O79 -> #REF! | P80: =P79 -> #REF! | Q80: =Q79 -> #REF! | R80: =R79 -> #REF! | S80: =S79 -> #REF! | T80: =T79 -> #REF!
E81: FLO_EMIS | F81: 2010 | G81: ACT | H81: SCMINNGAD | I81: NGAD0 | L81: N2O | O81: =P81 -> #REF! | P81: =#REF! -> #REF! | Q81: =P81 -> #REF! | R81: =Q81 -> #REF! | S81: =R81 -> #REF! | T81: =S81 -> #REF!
E82: FLO_EMIS | F82: 2015 | G82: ACT | H82: SCMINNGAD | I82: NGAD0 | L82: N2O | O82: =P82 -> #REF! | P82: =#REF! -> #REF! | Q82: =P82 -> #REF! | R82: =Q82 -> #REF! | S82: =R82 -> #REF! | T82: =S82 -> #REF!
E83: FLO_EMIS | F83: 2020 | G83: ACT | H83: SCMINNGAD | I83: NGAD0 | L83: N2O | O83: =P83 -> #REF! | P83: =#REF! -> #REF! | Q83: =P83 -> #REF! | R83: =Q83 -> #REF! | S83: =R83 -> #REF! | T83: =S83 -> #REF!
E84: FLO_EMIS | F84: 2055 | G84: ACT | H84: SCMINNGAD | I84: NGAD0 | L84: N2O | O84: =O83 -> #REF! | P84: =P83 -> #REF! | Q84: =Q83 -> #REF! | R84: =R83 -> #REF! | S84: =S83 -> #REF! | T84: =T83 -> #REF!
E85: FLO_EMIS | F85: 2010 | G85: ACT | H85: SCMINNGAD | I85: NGAD0 | L85: OC | O85: =P85 -> #REF! | P85: =#REF! -> #REF! | Q85: =P85 -> #REF! | R85: =Q85 -> #REF! | S85: =R85 -> #REF! | T85: =S85 -> #REF!
E86: FLO_EMIS | F86: 2015 | G86: ACT | H86: SCMINNGAD | I86: NGAD0 | L86: OC | O86: =P86 -> #REF! | P86: =P$85*P70/P$69 -> #REF! | Q86: =P86 -> #REF! | R86: =Q86 -> #REF! | S86: =R86 -> #REF! | T86: =S86 -> #REF!
E87: FLO_EMIS | F87: 2020 | G87: ACT | H87: SCMINNGAD | I87: NGAD0 | L87: OC | O87: =P87 -> #REF! | P87: =P$85*P71/P$69 -> #REF! | Q87: =P87 -> #REF! | R87: =Q87 -> #REF! | S87: =R87 -> #REF! | T87: =S87 -> #REF!
E88: FLO_EMIS | F88: 2055 | G88: ACT | H88: SCMINNGAD | I88: NGAD0 | L88: OC | O88: =O87 -> #REF! | P88: =P87 -> #REF! | Q88: =Q87 -> #REF! | R88: =R87 -> #REF! | S88: =S87 -> #REF! | T88: =T87 -> #REF!
E89: FLO_EMIS | F89: 2010 | G89: ACT | H89: SCMINNGAD | I89: NGAD0 | L89: BC | O89: =P89 -> #REF! | P89: =#REF! -> #REF! | Q89: =P89 -> #REF! | R89: =Q89 -> #REF! | S89: =R89 -> #REF! | T89: =S89 -> #REF!
E90: FLO_EMIS | F90: 2015 | G90: ACT | H90: SCMINNGAD | I90: NGAD0 | L90: BC | O90: =P90 -> #REF! | P90: =P$89*P70/P$69 -> #REF! | Q90: =P90 -> #REF! | R90: =Q90 -> #REF! | S90: =R90 -> #REF! | T90: =S90 -> #REF!
E91: FLO_EMIS | F91: 2020 | G91: ACT | H91: SCMINNGAD | I91: NGAD0 | L91: BC | O91: =P91 -> #REF! | P91: =P$89*P71/P$69 -> #REF! | Q91: =P91 -> #REF! | R91: =Q91 -> #REF! | S91: =R91 -> #REF! | T91: =S91 -> #REF!
E92: FLO_EMIS | F92: 2055 | G92: ACT | H92: SCMINNGAD | I92: NGAD0 | L92: BC | O92: =O91 -> #REF! | P92: =P91 -> #REF! | Q92: =Q91 -> #REF! | R92: =R91 -> #REF! | S92: =S91 -> #REF! | T92: =T91 -> #REF!
C93: *
E94: FLO_EMIS | F94: 2010 | G94: ACT | H94: XNGARES | I94: NGA | L94: CO2 | M94: =#REF!/1000 -> #REF!
E95: FLO_EMIS | F95: 2015 | G95: ACT | H95: XNGARES | I95: NGA | L95: CO2 | M95: =M94 -> #REF!
E96: FLO_EMIS | F96: 2020 | G96: ACT | H96: XNGARES | I96: NGA | L96: CO2 | M96: =M95 -> #REF!
E97: FLO_EMIS | F97: 2055 | G97: ACT | H97: XNGARES | I97: NGA | L97: CO2 | M97: =M96 -> #REF!
E98: FLO_EMIS | F98: 2010 | G98: ACT | H98: XNGARES | I98: NGA | L98: VOC | M98: =#REF! -> #REF!
E99: FLO_EMIS | F99: 2015 | G99: ACT | H99: XNGARES | I99: NGA | L99: VOC | M99: =M98 -> #REF!
E100: FLO_EMIS | F100: 2020 | G100: ACT | H100: XNGARES | I100: NGA | L100: VOC | M100: =M99 -> #REF!
E101: FLO_EMIS | F101: 2055 | G101: ACT | H101: XNGARES | I101: NGA | L101: VOC | M101: =M100 -> #REF!
...

Sheet GHG-ELC
C2: ~TFM_INS
C3: TimeSlice | D3: LimType | E3: Attribute | F3: Year | G3: Other_Indexes | H3: Pset_PN | I3: PSET_CI | J3: PSET_CO | K3: Pset_PD | L3: Cset_CN | M3: AllRegions | N3: R0 | O3: R1 | P3: R2 | Q3: R3 | R3: R4 | S3: R5 | T3: R6
E4: FLO_EMIS | G4: ACT | H4: SECSTBHFGO | L4: SO2 | O4: ='Retrofit - ELC'!C6-'Retrofit - ELC'!$D$6 -> -1.1268508
E5: FLO_EMIS | G5: ACT | H5: SECSTBMFGO | L5: SO2 | O5: ='Retrofit - ELC'!$E$6-'Retrofit - ELC'!$F$6 -> -0.50478579
E6: FLO_EMIS | G6: ACT | H6: SECSTBLFGO | L6: SO2 | O6: ='Retrofit - ELC'!$G$6-'Retrofit - ELC'!$H$6 -> -0.14010986
E7: FLO_EMIS | G7: ACT | H7: SECSTSMFGO | L7: SO2 | O7: ='Retrofit - ELC'!$E$12-'Retrofit - ELC'!$F$12 -> -0.34112163
E8: FLO_EMIS | G8: ACT | H8: SECSTSLFGO | L8: SO2 | O8: ='Retrofit - ELC'!$G$12-'Retrofit - ELC'!$H$12 -> -0.19686958
E9: FLO_EMIS | G9: ACT | H9: SECSTLHFGO | L9: SO2 | O9: ='Retrofit - ELC'!$C$18-'Retrofit - ELC'!$D$18 -> -0.91646048
E10: FLO_EMIS | G10: ACT | H10: SECSTLMFGO | L10: SO2 | O10: ='Retrofit - ELC'!$E$18-'Retrofit - ELC'!$F$18 -> -0.63448162
E11: FLO_EMIS | G11: ACT | H11: SECSTBHFGU | L11: SO2 | O11: ='Retrofit - ELC'!$C$6-'Retrofit - ELC'!$D$6 -> -1.1268508
E12: FLO_EMIS | G12: ACT | H12: SECSTBMFGU | L12: SO2 | O12: ='Retrofit - ELC'!$E$6-'Retrofit - ELC'!$F$6 -> -0.50478579
E13: FLO_EMIS | G13: ACT | H13: SECSTBLFGU | L13: SO2 | O13: ='Retrofit - ELC'!$G$6-'Retrofit - ELC'!$H$6 -> -0.14010986
E14: FLO_EMIS | G14: ACT | H14: SECSTSMFGU | L14: SO2 | O14: ='Retrofit - ELC'!$E$12-'Retrofit - ELC'!$F$12 -> -0.34112163
E15: FLO_EMIS | G15: ACT | H15: SECSTSLFGU | L15: SO2 | O15: ='Retrofit - ELC'!$G$12-'Retrofit - ELC'!$H$12 -> -0.19686958
E16: FLO_EMIS | G16: ACT | H16: SECSTLHFGU | L16: SO2 | O16: ='Retrofit - ELC'!$C$18-'Retrofit - ELC'!$D$18 -> -0.91646048
E17: FLO_EMIS | G17: ACT | H17: SECSTLMFGU | L17: SO2 | O17: ='Retrofit - ELC'!$E$18-'Retrofit - ELC'!$F$18 -> -0.63448162
E18: FLO_EMIS | G18: ACT | H18: SECSTBHFGO | L18: SO2E | O18: =O4 -> -1.1268508
E19: FLO_EMIS | G19: ACT | H19: SECSTBMFGO | L19: SO2E | O19: =O5 -> -0.50478579
E20: FLO_EMIS | G20: ACT | H20: SECSTBLFGO | L20: SO2E | O20: =O6 -> -0.14010986
E21: FLO_EMIS | G21: ACT | H21: SECSTSMFGO | L21: SO2E | O21: =O7 -> -0.34112163
E22: FLO_EMIS | G22: ACT | H22: SECSTSLFGO | L22: SO2E | O22: =O8 -> -0.19686958
E23: FLO_EMIS | G23: ACT | H23: SECSTLHFGO | L23: SO2E | O23: =O9 -> -0.91646048
E24: FLO_EMIS | G24: ACT | H24: SECSTLMFGO | L24: SO2E | O24: =O10 -> -0.63448162
E25: FLO_EMIS | G25: ACT | H25: SECSTBHFGU | L25: SO2E | O25: =O11 -> -1.1268508
E26: FLO_EMIS | G26: ACT | H26: SECSTBMFGU | L26: SO2E | O26: =O12 -> -0.50478579
E27: FLO_EMIS | G27: ACT | H27: SECSTBLFGU | L27: SO2E | O27: =O13 -> -0.14010986
E28: FLO_EMIS | G28: ACT | H28: SECSTSMFGU | L28: SO2E | O28: =O14 -> -0.34112163
E29: FLO_EMIS | G29: ACT | H29: SECSTSLFGU | L29: SO2E | O29: =O15 -> -0.19686958
... E31: FLO_EMIS | G31: ACT | H31: SECSTLMFGU | L31: SO2E | O31: =O17 -> -0.63448162
E32: FLO_EMIS | G32: ACT | H32: SECSTBLNBO | L32: NOX | O32: ='Retrofit - ELC'!$D$25-'Retrofit - ELC'!$C$25 -> -0.1164154
E33: FLO_EMIS | G33: ACT | H33: SECSTBSCRO | L33: NOX | O33: ='Retrofit - ELC'!$E$25-'Retrofit - ELC'!$D$25 -> -0.1822319
E34: FLO_EMIS | G34: ACT | H34: SECSTBSNCO | L34: NOX | O34: ='Retrofit - ELC'!$F$25-'Retrofit - ELC'!$D$25 -> -0.11061362
E35: FLO_EMIS | G35: ACT | H35: SECSTBSC2O | L35: NOX | O35: ='Retrofit - ELC'!$G$25-'Retrofit - ELC'!$C$25 -> -0.26973369
E36: FLO_EMIS | G36: ACT | H36: SECSTBSN2O | L36: NOX | O36: ='Retrofit - ELC'!$H$25-'Retrofit - ELC'!$C$25 -> -0.15474498
E37: FLO_EMIS | G37: ACT | H37: SECSTBLS2O | L37: NOX | O37: ='Retrofit - ELC'!$I$25-'Retrofit - ELC'!$C$25 -> -0.30039735
E38: FLO_EMIS | G38: ACT | H38: SECSTBLN2O | L38: NOX | O38: ='Retrofit - ELC'!$J$25-'Retrofit - ELC'!$C$25 -> -0.23140412
E39: FLO_EMIS | G39: ACT | H39: SECSTSLNBO | L39: NOX | O39: ='Retrofit - ELC'!$D$30-'Retrofit - ELC'!$C$30 -> -0.14308236
E40: FLO_EMIS | G40: ACT | H40: SECSTSSCRO | L40: NOX | O40: ='Retrofit - ELC'!$E$30-'Retrofit - ELC'!$D$30 -> -0.17732445
E41: FLO_EMIS | G41: ACT | H41: SECSTSSNCO | L41: NOX | O41: ='Retrofit - ELC'!$F$30-'Retrofit - ELC'!$D$30 -> -0.13134727
E42: FLO_EMIS | G42: ACT | H42: SECSTSSC2O | L42: NOX | O42: ='Retrofit - ELC'!$G$30-'Retrofit - ELC'!$C$30 -> -0.28173297
E43: FLO_EMIS | G43: ACT | H43: SECSTSSN2O | L43: NOX | O43: ='Retrofit - ELC'!$H$30-'Retrofit - ELC'!$C$30 -> -0.17774501
E44: FLO_EMIS | G44: ACT | H44: SECSTSLS2O | L44: NOX | O44: ='Retrofit - ELC'!$I$30-'Retrofit - ELC'!$C$30 -> -0.30946309
E45: FLO_EMIS | G45: ACT | H45: SECSTSLN2O | L45: NOX | O45: ='Retrofit - ELC'!$J$30-'Retrofit - ELC'!$C$30 -> -0.24707032
E46: FLO_EMIS | G46: ACT | H46: SECSTLLNBO | L46: NOX | O46: ='Retrofit - ELC'!$D$35-'Retrofit - ELC'!$C$35 -> -0.072188919
E47: FLO_EMIS | G47: ACT | H47: SECSTLSCRO | L47: NOX | O47: ='Retrofit - ELC'!$E$35-'Retrofit - ELC'!$D$35 -> -0.08916396
E48: FLO_EMIS | G48: ACT | H48: SECSTLSNCO | L48: NOX | O48: ='Retrofit - ELC'!$F$35-'Retrofit - ELC'!$D$35 -> -0.03032444
E49: FLO_EMIS | G49: ACT | H49: SECSTLSC2O | L49: NOX | O49: ='Retrofit - ELC'!$G$35-'Retrofit - ELC'!$C$35 -> -0.15778246
E50: FLO_EMIS | G50: ACT | H50: SECSTLSN2O | L50: NOX | O50: ='Retrofit - ELC'!$H$35-'Retrofit - ELC'!$C$35 -> -0.093587304
E51: FLO_EMIS | G51: ACT | H51: SECSTLLS2O | L51: NOX | O51: ='Retrofit - ELC'!$I$35-'Retrofit - ELC'!$C$35 -> -0.17490116
E52: FLO_EMIS | G52: ACT | H52: SECSTLLN2O | L52: NOX | O52: ='Retrofit - ELC'!$J$35-'Retrofit - ELC'!$C$35 -> -0.13638407
E53: FLO_EMIS | G53: ACT | H53: SECSTBLNBU | L53: NOX | O53: ='Retrofit - ELC'!$D$25-'Retrofit - ELC'!$C$25 -> -0.1164154
E54: FLO_EMIS | G54: ACT | H54: SECSTBSCRU | L54: NOX | O54: ='Retrofit - ELC'!$E$25-'Retrofit - ELC'!$D$25 -> -0.1822319
E55: FLO_EMIS | G55: ACT | H55: SECSTBSNCU | L55: NOX | O55: ='Retrofit - ELC'!$F$25-'Retrofit - ELC'!$D$25 -> -0.11061362
E56: FLO_EMIS | G56: ACT | H56: SECSTBSC2U | L56: NOX | O56: ='Retrofit - ELC'!$G$25-'Retrofit - ELC'!$C$25 -> -0.26973369
E57: FLO_EMIS | G57: ACT | H57: SECSTBSN2U | L57: NOX | O57: ='Retrofit - ELC'!$H$25-'Retrofit - ELC'!$C$25 -> -0.15474498
E58: FLO_EMIS | G58: ACT | H58: SECSTBLS2U | L58: NOX | O58: ='Retrofit - ELC'!$I$25-'Retrofit - ELC'!$C$25 -> -0.30039735
E59: FLO_EMIS | G59: ACT | H59: SECSTBLN2U | L59: NOX | O59: ='Retrofit - ELC'!$J$25-'Retrofit - ELC'!$C$25 -> -0.23140412
E60: FLO_EMIS | G60: ACT | H60: SECSTSLNBU | L60: NOX | O60: ='Retrofit - ELC'!$D$30-'Retrofit - ELC'!$C$30 -> -0.14308236
E61: FLO_EMIS | G61: ACT | H61: SECSTSSCRU | L61: NOX | O61: ='Retrofit - ELC'!$E$30-'Retrofit - ELC'!$D$30 -> -0.17732445
E62: FLO_EMIS | G62: ACT | H62: SECSTSSNCU | L62: NOX | O62: ='Retrofit - ELC'!$F$30-'Retrofit - ELC'!$D$30 -> -0.13134727
E63: FLO_EMIS | G63: ACT | H63: SECSTSSC2U | L63: NOX | O63: ='Retrofit - ELC'!$G$30-'Retrofit - ELC'!$C$30 -> -0.28173297
E64: FLO_EMIS | G64: ACT | H64: SECSTSSN2U | L64: NOX | O64: ='Retrofit - ELC'!$H$30-'Retrofit - ELC'!$C$30 -> -0.17774501
E65: FLO_EMIS | G65: ACT | H65: SECSTSLS2U | L65: NOX | O65: ='Retrofit - ELC'!$I$30-'Retrofit - ELC'!$C$30 -> -0.30946309
E66: FLO_EMIS | G66: ACT | H66: SECSTSLN2U | L66: NOX | O66: ='Retrofit - ELC'!$J$30-'Retrofit - ELC'!$C$30 -> -0.24707032
E67: FLO_EMIS | G67: ACT | H67: SECSTLLNBU | L67: NOX | O67: ='Retrofit - ELC'!$D$35-'Retrofit - ELC'!$C$35 -> -0.072188919
E68: FLO_EMIS | G68: ACT | H68: SECSTLSCRU | L68: NOX | O68: ='Retrofit - ELC'!$E$35-'Retrofit - ELC'!$D$35 -> -0.08916396
E69: FLO_EMIS | G69: ACT | H69: SECSTLSNCU | L69: NOX | O69: ='Retrofit - ELC'!$F$35-'Retrofit - ELC'!$D$35 -> -0.03032444
E70: FLO_EMIS | G70: ACT | H70: SECSTLSC2U | L70: NOX | O70: ='Retrofit - ELC'!$G$35-'Retrofit - ELC'!$C$35 -> -0.15778246
E71: FLO_EMIS | G71: ACT | H71: SECSTLSN2U | L71: NOX | O71: ='Retrofit - ELC'!$H$35-'Retrofit - ELC'!$C$35 -> -0.093587304
E72: FLO_EMIS | G72: ACT | H72: SECSTLLS2U | L72: NOX | O72: ='Retrofit - ELC'!$I$35-'Retrofit - ELC'!$C$35 -> -0.17490116
E73: FLO_EMIS | G73: ACT | H73: SECSTLLN2U | L73: NOX | O73: ='Retrofit - ELC'!$J$35-'Retrofit - ELC'!$C$35 -> -0.13638407
E74: FLO_EMIS | G74: ACT | H74: SECSTBLNBO | L74: NOXE | O74: =O32 -> -0.1164154
E75: FLO_EMIS | G75: ACT | H75: SECSTBSCRO | L75: NOXE | O75: =O33 -> -0.1822319
E76: FLO_EMIS | G76: ACT | H76: SECSTBSNCO | L76: NOXE | O76: =O34 -> -0.11061362
E77: FLO_EMIS | G77: ACT | H77: SECSTBSC2O | L77: NOXE | O77: =O35 -> -0.26973369
E78: FLO_EMIS | G78: ACT | H78: SECSTBSN2O | L78: NOXE | O78: =O36 -> -0.15474498
E79: FLO_EMIS | G79: ACT | H79: SECSTBLS2O | L79: NOXE | O79: =O37 -> -0.30039735
E80: FLO_EMIS | G80: ACT | H80: SECSTBLN2O | L80: NOXE | O80: =O38 -> -0.23140412
E81: FLO_EMIS | G81: ACT | H81: SECSTSLNBO | L81: NOXE | O81: =O39 -> -0.14308236
E82: FLO_EMIS | G82: ACT | H82: SECSTSSCRO | L82: NOXE | O82: =O40 -> -0.17732445
E83: FLO_EMIS | G83: ACT | H83: SECSTSSNCO | L83: NOXE | O83: =O41 -> -0.13134727
E84: FLO_EMIS | G84: ACT | H84: SECSTSSC2O | L84: NOXE | O84: =O42 -> -0.28173297
E85: FLO_EMIS | G85: ACT | H85: SECSTSSN2O | L85: NOXE | O85: =O43 -> -0.17774501
... E115: FLO_EMIS | G115: ACT | H115: SECSTLLN2U | L115: NOXE | O115: =O73 -> -0.13638407
E116: FLO_EMIS | G116: ACT | H116: SECSTBFFRO | L116: PM10 | O116: -0.008327475
E117: FLO_EMIS | G117: ACT | H117: SECSTBCYCO | L117: PM10 | O117: -0.00714
E118: FLO_EMIS | G118: ACT | H118: SECSTBESPO | L118: PM10 | O118: -0.008251241
E119: FLO_EMIS | G119: ACT | H119: SECSTBEPUO | L119: PM10 | O119: -6.4759032e-05
E120: FLO_EMIS | G120: ACT | H120: SECSTSFFRO | L120: PM10 | O120: -0.0077239933
E121: FLO_EMIS | G121: ACT | H121: SECSTSCYCO | L121: PM10 | O121: -0.0077064
E122: FLO_EMIS | G122: ACT | H122: SECSTSESPO | L122: PM10 | O122: -0.0076641452
E123: FLO_EMIS | G123: ACT | H123: SECSTSEPUO | L123: PM10 | O123: -5.7854815e-05
E124: FLO_EMIS | G124: ACT | H124: SECSTLFFRO | L124: PM10 | O124: -0.01188
E125: FLO_EMIS | G125: ACT | H125: SECSTLCYCO | L125: PM10 | O125: 0
E126: FLO_EMIS | G126: ACT | H126: SECSTLESPO | L126: PM10 | O126: -0.01179492
E127: FLO_EMIS | G127: ACT | H127: SECSTLEPUO | L127: PM10 | O127: -8.508e-05
... E139: FLO_EMIS | G139: ACT | H139: SECSTLEPUU | L139: PM10 | O139: -1.8e-05
E140: FLO_EMIS | G140: ACT | H140: SECSTBFFRO | L140: PM10E | O140: =O116 -> -0.008327475
E141: FLO_EMIS | G141: ACT | H141: SECSTBCYCO | L141: PM10E | O141: =O117 -> -0.00714
E142: FLO_EMIS | G142: ACT | H142: SECSTBESPO | L142: PM10E | O142: =O118 -> -0.008251241
...

Sheet Emissions - REF
A1: Updated emission factor from GREET(Beta), dated Dec 21st, 2012
A2: Refinery emissions per unit outputs
A4: Conventional gasoline, onsite emissions (kT/PJ)
B5: 2005 | C5: 2010 | D5: 2015 | E5: 2020
A6: VOC | B6: 0.002354489 | C6: 0.002323298 | D6: 0.002323298 | E6: 0.002323298
A7: CO | B7: 0.004303286 | C7: 0.003558378 | D7: 0.003558378 | E7: 0.003558378
A8: NOx | B8: 0.009465847 | C8: 0.008144765 | D8: 0.007228721 | E8: 0.00683861
A9: PM10 | B9: 0.00225246 | C9: 0.001952885 | D9: 0.001736782 | E9: 0.00166413
A10: PM2.5 | B10: 0.001243051 | C10: 0.001086119 | D10: 0.001013099 | E10: 0.000941026
A11: SOx | B11: 0.009231452 | C11: 0.007105053 | D11: 0.006111093 | E11: 0.00568511
A12: CH4 | B12: 0.000186316 | C12: 0.000186316 | D12: 0.000186316 | E12: 0.000186316
A13: N2O | B13: 9.9824e-05 | C13: 9.9824e-05 | D13: 9.9824e-05 | E13: 9.9824e-05
A14: CO2 | B14: 6.1227432 | C14: 6.124011 | D14: 6.124011 | E14: 6.124011
A15: CO2Biogenic | B15: =B42/1000000 -> 0 | C15: =C42/1000000 -> 0 | D15: =D42/1000000 -> 0 | E15: =E42/1000000 -> 0
A17: Reformulated gasoline, onsite Emissions (kT/PJ)
B18: 2005 | C18: 2010 | D18: 2015 | E18: 2020
A19: VOC | B19: 0.002354219 | C19: 0.002323027 | D19: 0.002323027 | E19: 0.002323027
A20: CO | B20: 0.004298525 | C20: 0.003553682 | D20: 0.003553682 | E20: 0.003553682
A21: NOx | B21: 0.009421162 | C21: 0.008107528 | D21: 0.007194463 | E21: 0.006805841
A22: PM10 | B22: 0.002237565 | C22: 0.001939658 | D22: 0.001726355 | E22: 0.001655193
A23: PM2.5 | B23: 0.00123337 | C23: 0.001077521 | D23: 0.001006322 | E23: 0.000935217
A24: SOx | B24: 0.009165232 | C24: 0.007044704 | D24: 0.006050744 | E24: 0.005624762
A25: CH4 | B25: 0.000185351 | C25: 0.000185351 | D25: 0.000185351 | E25: 0.000185351
A26: N2O | B26: 9.9717e-05 | C26: 9.9717e-05 | D26: 9.9717e-05 | E26: 9.9717e-05
A27: CO2 | B27: 6.0990561 | C27: 6.1003237 | D27: 6.1003237 | E27: 6.1003237
A28: CO2Biogenic | B28: 0 | C28: 0 | D28: 0 | E28: 0
A30: Jet fuel, onsite emissions (kT/PJ)
B31: 2005 | C31: 2010 | D31: 2015 | E31: 2020
A32: VOC | B32: 0.000159747 | C32: 0.000130362 | D32: 0.000130362 | E32: 0.000130362
A33: CO | B33: 0.003077782 | C33: 0.002375158 | D33: 0.002375158 | E33: 0.002375158
A34: NOx | B34: 0.008263487 | C34: 0.006917476 | D34: 0.00601345 | E34: 0.005625476
A35: PM10 | B35: 0.002038953 | C35: 0.00173366 | D35: 0.001491726 | E35: 0.001402946
A36: PM2.5 | B36: 0.001158822 | C36: 0.000996048 | D36: 0.000902429 | E36: 0.000821276
A37: SOx | B37: 0.005663935 | C37: 0.003577855 | D37: 0.002640019 | E37: 0.00223809
A38: CH4 | B38: 0.000187993 | C38: 0.000187993 | D38: 0.000187993 | E38: 0.000187993
A39: N2O | B39: 9.244e-05 | C39: 9.244e-05 | D39: 9.244e-05 | E39: 9.244e-05
A40: CO2 | B40: 5.0043131 | C40: 5.0055088 | D40: 5.0055088 | E40: 5.0055088
A41: CO2Biogenic | B41: 0 | C41: 0 | D41: 0 | E41: 0
A43: Conventional diesel, onsite emissions (kT/PJ)
B44: 2005 | C44: 2010 | D44: 2015 | E44: 2020
A45: VOC | B45: 0.002354488 | C45: 0.002323296 | D45: 0.002323296 | E45: 0.002323296
A46: CO | B46: 0.004303261 | C46: 0.003558354 | D46: 0.003558354 | E46: 0.003558354
A47: NOx | B47: 0.009465617 | C47: 0.008144574 | D47: 0.007228545 | E47: 0.006838442
A48: PM10 | B48: 0.002252384 | C48: 0.001952817 | D48: 0.001736728 | E48: 0.001664084
A49: PM2.5 | B49: 0.001243002 | C49: 0.001086075 | D49: 0.001013064 | E49: 0.000940997
A50: SOx | B50: 0.009231112 | C50: 0.007104743 | D50: 0.006110783 | E50: 0.0056848
A51: CH4 | B51: 0.000186311 | C51: 0.000186311 | D51: 0.000186311 | E51: 0.000186311
A52: N2O | B52: 9.9823e-05 | C52: 9.9823e-05 | D52: 9.9823e-05 | E52: 9.9823e-05
A53: CO2 | B53: 6.1226215 | C53: 6.1238893 | D53: 6.1238893 | E53: 6.1238893
A54: CO2Biogenic | B54: 0 | C54: 0 | D54: 0 | E54: 0
A56: Low sulfur diesel, onsite emissions (kT/PJ)
B57: 2005 | C57: 2010 | D57: 2015 | E57: 2020
A58: VOC | B58: 0.002350104 | C58: 0.002318931 | D58: 0.002318931 | E58: 0.002318931
A59: CO | B59: 0.004299594 | C59: 0.003555149 | D59: 0.003555149 | E59: 0.003555149
A60: NOx | B60: 0.009458921 | C60: 0.008138539 | D60: 0.007222818 | E60: 0.006832852
A61: PM10 | B61: 0.002251655 | C61: 0.001952094 | D61: 0.001735997 | E61: 0.001663348
A62: PM2.5 | B62: 0.001242554 | C62: 0.001085635 | D62: 0.001012619 | E62: 0.000940548
A63: SOx | B63: 0.009223109 | C63: 0.007096723 | D63: 0.006102763 | E63: 0.00567678
A64: CH4 | B64: 0.000186214 | C64: 0.000186214 | D64: 0.000186214 | E64: 0.000186214
A65: N2O | B65: 9.9753e-05 | C65: 9.9753e-05 | D65: 9.9753e-05 | E65: 9.9753e-05
A66: CO2 | B66: 6.1176291 | C66: 6.1188961 | D66: 6.1188961 | E66: 6.1188961
A67: CO2Biogenic | B67: 0 | C67: 0 | D67: 0 | E67: 0
A69: LPG, onsite Emissions (kT/PJ)
B70: 2005 | C70: 2010 | D70: 2015 | E70: 2020
A71: VOC | B71: 0.002354488 | C71: 0.002323296 | D71: 0.002323296 | E71: 0.002323296
A72: CO | B72: 0.004303261 | C72: 0.003558354 | D72: 0.003558354 | E72: 0.003558354
A73: NOx | B73: 0.009465617 | C73: 0.008144574 | D73: 0.007228545 | E73: 0.006838442
A74: PM10 | B74: 0.002252384 | C74: 0.001952817 | D74: 0.001736728 | E74: 0.001664084
A75: PM2.5 | B75: 0.001243002 | C75: 0.001086075 | D75: 0.001013064 | E75: 0.000940997
A76: SOx | B76: 0.009231112 | C76: 0.007104743 | D76: 0.006110783 | E76: 0.0056848
A77: CH4 | B77: 0.000186311 | C77: 0.000186311 | D77: 0.000186311 | E77: 0.000186311
A78: N2O | B78: 9.9823e-05 | C78: 9.9823e-05 | D78: 9.9823e-05 | E78: 9.9823e-05
A79: CO2 | B79: 6.1226215 | C79: 6.1238893 | D79: 6.1238893 | E79: 6.1238893
A80: CO2Biogenic | B80: 0 | C80: 0 | D80: 0 | E80: 0
A82: Residual fuel oil, onsite emissions (kT/PJ)
B83: 2005 | C83: 2010 | D83: 2015 | E83: 2020
A84: VOC | B84: 0.000873611 | C84: 0.000862038 | D84: 0.000862038 | E84: 0.000862038
A85: CO | B85: 0.001596686 | C85: 0.001320295 | D85: 0.001320295 | E85: 0.001320295
A86: NOx | B86: 0.003512131 | C86: 0.00302197 | D86: 0.002682086 | E86: 0.002537342
A87: PM10 | B87: 0.000835727 | C87: 0.000724575 | D87: 0.000644397 | E87: 0.000617443
A88: PM2.5 | B88: 0.000461204 | C88: 0.000402978 | D88: 0.000375888 | E88: 0.000349148
A89: SOx | B89: 0.00342512 | C89: 0.00263615 | D89: 0.00226735 | E89: 0.002109293
A90: CH4 | B90: 6.9129e-05 | C90: 6.9129e-05 | D90: 6.9129e-05 | E90: 6.9129e-05
A91: N2O | B91: 3.7039e-05 | C91: 3.7039e-05 | D91: 3.7039e-05 | E91: 3.7039e-05
A92: CO2 | B92: 2.2717432 | C92: 2.2722136 | D92: 2.2722136 | E92: 2.2722136
A93: CO2Biogenic | B93: 0 | C93: 0 | D93: 0 | E93: 0

Sheet Retrofit - ELC
B1: Data generated with the EPA/NRMRL/APPCD CUECost spreadsheet model
B3: SOX Control Summary
B4: Bituminous | C4: High Sulfur | E4: Medium Sulfur | G4: Low Sulfur
C5: FGD (SECSTMBHFG) | D5: Pass (SECSTMBHPT) | E5: FGD (SECSTMBMFG) | F5: Pass (SECSTMBMPT) | G5: FGD (SECSTMBLFG) | H5: Pass (SECSTMBLPT)
B6: Equilibrium Emissions Rate (kT/PJ) | C6: 0.059311582 | D6: 1.1861624 | E6: 0.022017182 | F6: 0.52680297 | G6: 0.007384394 | H6: 0.14749425
B7: Capital Cost (m$/PJ/yr) | C7: 2.6322316 | E7: 1.9397894 | G7: 3.1387047
B8: Variable O&M (m$/PJ) | C8: 0.3006257 | E8: 0.21797395 | G8: 0.34990926
B10: Sub-Bituminous | C10: High Sulfur | E10: Medium Sulfur | G10: Low Sulfur
C11: FGD (SECSTMSHFG) | D11: Pass (SECSTMSHPT) | E11: FGD (SECSTMSMFG) | F11: Pass (SECSTMSMPT) | G11: FGD (SECSTMSLFG) | H11: Pass (SECSTMSLPT)
B12: Equilibrium Emissions Rate (kT/PJ) | C12: N/A | D12: N/A | E12: 0.017954111 | F12: 0.35907574 | G12: 0.010354962 | H12: 0.20722455
B13: Capital Cost (m$/PJ/yr) | C13: N/A | E13: 1.8680997 | G13: 2.4832624
B14: Variable O&M (m$/PJ) | C14: N/A | E14: 0.22666376 | G14: 0.25235776
B16: Lignite | C16: High Sulfur | E16: Medium Sulfur | G16: Low Sulfur
C17: FGD (SECSTMLHFG) | D17: Pass (SECSTMLHPT) | E17: FGD (SECSTMLMFG) | F17: Pass (SECSTMLMPT) | G17: FGD | H17: Pass
B18: Equilibrium Emissions Rate (kT/PJ) | C18: 0.048256727 | D18: 0.9647172 | E18: 0.03334584 | F18: 0.66782746 | G18: N/A | H18: N/A
B19: Capital Cost (m$/PJ/yr) | C19: 1.9028621 | E19: 1.7693982 | G19: N/A
B20: Variable O&M (m$/PJ) | C20: 0.23452508 | E20: 0.229388 | G20: N/A
B23: NOX Control Summary | L23: Calculated $/tonne removed
B24: Bituminous | C24: Pass Through (SECSTMBPT/2) | D24: LNB (SECSTMBLNB) | E24: SCR (after LNB, SECSTMBSCR) | F24: SNCR (after LNB, SECSTMBSNC) | G24: SCR only (SECSTMBSC2) | H24: SNCR only (SECSTMBSN2) | I24: LNB-SCR (SECSTMBLS2) | J24: LNB-SNCR (SECSTMBLN2) | L24: LNB (SECSTMBLNB) | M24: SCR (after LNB, SECSTMBSCR) | N24: SNCR (after LNB, SECSTMBSNC) | O24: SCR only (SECSTMBSC2) | P24: SNCR only (SECSTMBSN2) | Q24: LNB-SCR (SECSTMBLS2) | R24: LNB-SNCR (SECSTMBLN2)
B25: Equilibrium Emissions Rate (kT/PJ) | C25: 0.34639283 | D25: 0.22997743 | E25: 0.047745523 | F25: 0.11936381 | G25: 0.076659143 | H25: 0.19164786 | I25: 0.045995486 | J25: 0.11498871 | L25: =(D26+D27)*1000000/((C25-D25)*1000) -> 1835.705 | M25: =(E26+E27)*1000000/((C25-E25)*1000) -> 2727.9428 | N25: =(F26+F27)*1000000/((C25-F25)*1000) -> 545.75321 | O25: =(G26+G27)*1000000/((C25-G25)*1000) -> 3258.9695 | P25: =(H26+H27)*1000000/((C25-H25)*1000) -> 1125.1149 | Q25: =(I26+I27)*1000000/((C25-I25)*1000) -> 3523.2852 | R25: =(J26+J27)*1000000/((C25-J25)*1000) -> 1523.0785
B26: Capital Cost (m$/PJ/yr) | D26: 0.20789446 | E26: 0.66512172 | F26: 0.078552329 | G26: 0.76318038 | H26: 0.10455476 | I26: 0.94847608 | J26: 0.30305871
B27: Variable O&M (m$/PJ) | D27: 0.0058098808 | E27: 0.14957106 | F27: 0.04534949 | G27: 0.11587348 | H27: 0.069551114 | I27: 0.10990944 | J27: 0.049387931
L28: Calculated $/tonne removed
B29: Sub-Bituminous | C29: Pass Through (SECSTMSPT/2) | D29: LNB (SECSTMSLNB) | E29: SCR (after LNB, SECSTMSSCR) | F29: SNCR (after LNB, SECSTMSSNC) | G29: SCR only (SECSTMSSC2) | H29: SNCR only (SECSTMSSN2) | I29: LNB-SCR (SECSTMSLS2) | J29: LNB-SNCR (SECSTMSLN2) | L29: LNB (SECSTMBLNB) | M29: SCR (after LNB, SECSTMBSCR) | N29: SNCR (after LNB, SECSTMBSNC) | O29: SCR only (SECSTMBSC2) | P29: SNCR only (SECSTMBSN2) | Q29: LNB-SCR (SECSTMBLS2) | R29: LNB-SNCR (SECSTMBLN2)
B30: Equilibrium Emissions Rate (kT/PJ) | C30: 0.35105827 | D30: 0.20797591 | E30: 0.030651455 | F30: 0.076628637 | G30: 0.069325303 | H30: 0.17331326 | I30: 0.041595182 | J30: 0.10398795 | L30: =(D31+D32)*1000000/((C30-D30)*1000) -> 1435.0803 | M30: =(E31+E32)*1000000/((C30-E30)*1000) -> 2325.7259 | N30: =(F31+F32)*1000000/((C30-F30)*1000) -> 357.32969 | O30: =(G31+G32)*1000000/((C30-G30)*1000) -> 3105.9962 | P30: =(H31+H32)*1000000/((C30-H30)*1000) -> 900.67535 | Q30: =(I31+I32)*1000000/((C30-I30)*1000) -> 3392.7459 | R30: =(J31+J32)*1000000/((C30-J30)*1000) -> 1351.3962
B31: Capital Cost (m$/PJ/yr) | D31: 0.19951384 | E31: 0.64700165 | F31: 0.069391685 | G31: 0.75678625 | H31: 0.096804473 | I31: 0.93650317 | J31: 0.28827588
B32: Variable O&M (m$/PJ) | D32: 0.0058208355 | E32: 0.098176768 | F32: 0.028670169 | G32: 0.11827527 | H32: 0.063286079 | I32: 0.11342646 | J32: 0.045614005
L33: Calculated $/tonne removed
B34: Lignite | C34: Pass Through (SECSTMLPT/2) | D34: LNB (SECSTMLLNB) | E34: SCR (after LNB, SECSTMLSCR) | F34: SNCR (after LNB, SECSTMLSNC) | G34: SCR only (SECSTMLSC2) | H34: SNCR only (SECSTMLSN2) | I34: LNB-SCR (SECSTMLLS2) | J34: LNB-SNCR (SECSTMLLN2) | L34: LNB (SECSTMBLNB) | M34: SCR (after LNB, SECSTMBSCR) | N34: SNCR (after LNB, SECSTMBSNC) | O34: SCR only (SECSTMBSC2) | P34: SNCR only (SECSTMBSN2) | Q34: LNB-SCR (SECSTMBLS2) | R34: LNB-SNCR (SECSTMBLN2)
B35: Equilibrium Emissions Rate (kT/PJ) | C35: 0.20057923 | D35: 0.12839031 | E35: 0.039226347 | F35: 0.098065867 | G35: 0.042796769 | H35: 0.10699192 | I35: 0.025678061 | J35: 0.064195154 | L35: =(D36+D37)*1000000/((C35-D35)*1000) -> 2296.1831 | M35: =(E36+E37)*1000000/((C35-E35)*1000) -> 4889.6577 | N35: =(F36+F37)*1000000/((C35-F35)*1000) -> 1083.109 | O35: =(G36+G37)*1000000/((C35-G35)*1000) -> 4743.0702 | P35: =(H36+H37)*1000000/((C35-H35)*1000) -> 1143.5103 | Q35: =(I36+I37)*1000000/((C35-I35)*1000) -> 5117.5766 | R35: =(J36+J37)*1000000/((C35-J35)*1000) -> 1856.4064
B36: Capital Cost (m$/PJ/yr) | D36: 0.16097879 | E36: 0.6805863 | F36: 0.075029313 | G36: 0.63922747 | H36: 0.068316629 | I36: 0.78772395 | J36: 0.2242033
B37: Variable O&M (m$/PJ) | D37: 0.0047801848 | E37: 0.10837405 | F37: 0.036003828 | G37: 0.10914581 | H37: 0.038701415 | I37: 0.10734615 | J37: 0.028980971
B41: RESID capacity for air pollution controls by Region. Based on EPA eGrid data (Original workbook "Coal Plant 9R RESIDS for 2000.xls")
B43: FGD Data
E44: Nameplate capacity in PJ/yr
B46: Sum of EffNPC(PJ) | E46: FGD
B47: EPA9Rregion | C47: Coal Type | D47: Coal S Content | E47: N | F47: Y | G47: Grand Total | H47: Data from:
B48: 1 | C48: BIT | D48: L | E48: 53.687876 | G48: 53.687876 | H48: EIA767 (yr. 2000)
D49: M | E49: 18.7488 | G49: 18.7488 | H49: eGRID2002 (yr. 2000)
C50: SUB | D50: L | E50: 12.58425 | G50: 12.58425
B51: 2 | C51: BIT | D51: H | E51: 66.6729 | F51: 196.59251 | G51: 263.26541
D52: L | E52: 24.145065 | G52: 24.145065
D53: M | E53: 429.87628 | F53: 38.341233 | G53: 468.21751
B54: 3 | C54: BIT | D54: H | E54: 229.30759 | F54: 398.52398 | G54: 627.83157
D55: L | E55: 476.86924 | G55: 476.86924
D56: M | E56: 864.52865 | F56: 5.04 | G56: 869.56865
C57: SUB | D57: L | E57: 559.84232 | G57: 559.84232
B58: 4 | C58: BIT | D58: H | E58: 5.235993 | G58: 5.235993
D59: L | E59: 225.80429 | F59: 16.307392 | G59: 242.11168
C60: LIG | D60: M | E60: 36.1305 | F60: 96.389874 | G60: 132.52037
C61: SUB | D61: L | E61: 458.62916 | F61: 172.87704 | G61: 631.5062
D62: M | E62: 27.160875 | F62: 59.15385 | G62: 86.314725
B63: 5 | C63: BIT | D63: H | E63: 19.719 | F63: 210.15855 | G63: 229.87755
D64: L | E64: 434.4773 | G64: 434.4773
D65: M | E65: 1364.0589 | F65: 209.57139 | G65: 1573.6303
B66: 6 | C66: BIT | D66: H | E66: 65.010834 | F66: 350.71769 | G66: 415.72853
D67: L | E67: 285.34873 | F67: 16.011135 | G67: 301.35987
D68: M | E68: 449.65003 | F68: 27.468 | G68: 477.11803
C69: SUB | D69: L | E69: 31.185 | G69: 31.185
D70: M | E70: 39.5388 | G70: 39.5388
B71: 7 | C71: BIT | D71: L | E71: 34.347285 | F71: 16.38 | G71: 50.727285
C72: LIG | D72: H | F72: 56.507535 | G72: 56.507535
D73: L | F73: 22.703625 | G73: 22.703625
D74: M | E74: 85.7682 | F74: 148.90995 | G74: 234.67815
C75: SUB | D75: L | E75: 601.69435 | F75: 88.486965 | G75: 690.18132
B76: 8 | C76: BIT | D76: L | E76: 153.54001 | F76: 213.9543 | G76: 367.49431
D77: M | E77: 3.591 | F77: 68.49549 | G77: 72.08649
C78: SUB | D78: L | E78: 42.973308 | F78: 209.25535 | G78: 252.22866
D79: M | F79: 221.75717 | G79: 221.75717
B80: 9 | C80: BIT | D80: L | E80: 18.73305 | G80: 18.73305
C81: SUB | D81: M | E81: 45.98937 | G81: 45.98937
B82: Grand Total | E82: 7164.849 | F82: 2843.603 | G82: 10008.452
B85: NOX Control Retrofits
F86: Nameplate capacity in PJ/yr
F87: Neither | G87: SNCR | H87: SCR
B88: Sum of EffNPC(PJ) | F88: SCR | G88: SNCR
F89: N | H89: Y | I89: Grand Total
B90: EPA9Rregion | C90: Coal Type | D90: LNB | E90: Coal S Content | F90: N | G90: Y | H90: N
B91: 1 | C91: BIT | D91: N | F91: 7.875 | G91: 2.583 | H91: 14.4648 | I91: 24.9228
D92: Y | F92: 39.711703 | G92: 7.802172 | I92: 47.513875
C93: SUB | D93: Y | F93: 12.58425 | I93: 12.58425
B94: 2 | C94: BIT | D94: N | F94: 54.256734 | G94: 34.9083 | I94: 89.165034
D95: Y | F95: 645.82714 | H95: 20.635808 | I95: 666.46295
B96: 3 | C96: BIT | D96: N | F96: 864.04396 | I96: 864.04396
D97: Y | F97: 1100.3534 | G97: 9.8721 | I97: 1110.2255
C98: SUB | D98: N | F98: 332.27051 | I98: 332.27051
D99: Y | F99: 227.57181 | I99: 227.57181
B100: 4 | C100: BIT | D100: N | F100: 90.518935 | I100: 90.518935
D101: Y | F101: 156.82873 | I101: 156.82873
C102: LIG | D102: N | F102: 98.311437 | I102: 98.311437
D103: Y | F103: 34.208937 | I103: 34.208937
C104: SUB | D104: N | F104: 372.69332 | I104: 372.69332
D105: Y | F105: 345.12761 | I105: 345.12761
B106: 5 | C106: BIT | D106: N | F106: 623.40062 | G106: 2.3625 | I106: 625.76312
D107: Y | F107: 1578.083 | G107: 19.5048 | H107: 14.63427 | I107: 1612.222
B108: 6 | C108: BIT | D108: N | F108: 339.81412 | I108: 339.81412
D109: Y | F109: 854.3923 | I109: 854.3923
C110: SUB | D110: N | F110: 31.185 | I110: 31.185
D111: Y | F111: 39.5388 | I111: 39.5388
B112: 7 | C112: BIT | D112: N | F112: 34.347285 | I112: 34.347285
...

Sheet Water Data
A1: Source: Madknick et al. (2011), A Review of Operational Water Consumption and Withdrawal Factors for Electricity Generating Technologies. NREL: Golden, CO
A2: Table 1. Water Consumption Factors for Renewable Technologies (gal/MWh)
A3: Table 2. Water Consumption Factors for Non-renewable Technologies (gal/MWh) | L3: N/a for "source" and "table" ==> withdrawals not reported and assumed to be equal to consumption.
A4: Table 3. Water Withdrawal Factors for Electricity Generating Technologies (gal/MWh) | Y4: nonrenewable = | Z4: NR
D6: Withdrawals (H20W) | O6: Consumption (H20C) | AB6: Percent water withdrawal consumed
D7: Million gallons H2O/PJ | H7: gallons H2O/MWh | O7: Million gallons H2O/PJ | S7: gallons H2O/MWh
A8: Fuel Type | B8: Cooling | C8: Technology | D8: Median | E8: Min | F8: Max | H8: Median | I8: Min | J8: Max | K8: n | L8: Source(s) | M8: Table | O8: Median | P8: Min | Q8: Max | S8: Median | T8: Min | U8: Max | V8: n | W8: Source(s) | X8: Table | Z8: R or NR
A9: Biopower | B9: Dry | C9: Biogas | D9: =H9*((1/Conversions!$K$5)*(1/1000000)) -> 9.7222249 | H9: 35 | L9: n/a | M9: n/a | O9: =S9*((1/Conversions!$K$5)*(1/1000000)) -> 9.7222249 | P9: =T9*((1/Conversions!$K$5)*(1/1000000)) -> 9.7222249 | Q9: =U9*((1/Conversions!$K$5)*(1/1000000)) -> 9.7222249 | S9: 35 | T9: 35 | U9: 35 | V9: 1 | W9: [51] | X9: 1 | Z9: R | AB9: =S9/H9 -> 1
A10: Biopower | B10: Once-through | C10: Steam | D10: =H10*((1/Conversions!$K$5)*(1/1000000)) -> 9722.2249 | E10: =I10*((1/Conversions!$K$5)*(1/1000000)) -> 5555.5571 | F10: =J10*((1/Conversions!$K$5)*(1/1000000)) -> 13888.893 | H10: 35000 | I10: 20000 | J10: 50000 | K10: 1 | L10: [50] | M10: 3 | O10: =S10*((1/Conversions!$K$5)*(1/1000000)) -> 83.333356 | P10: =T10*((1/Conversions!$K$5)*(1/1000000)) -> 83.333356 | Q10: =U10*((1/Conversions!$K$5)*(1/1000000)) -> 83.333356 | S10: 300 | T10: 300 | U10: 300 | V10: 1 | W10: [50] | X10: 1 | Z10: R | AB10: =S10/H10 -> 0.0085714286
A11: Biopower | B11: Pond | C11: Steam | D11: =H11*((1/Conversions!$K$5)*(1/1000000)) -> 125.00003 | E11: =I11*((1/Conversions!$K$5)*(1/1000000)) -> 83.333356 | F11: =J11*((1/Conversions!$K$5)*(1/1000000)) -> 166.66671 | H11: 450 | I11: 300 | J11: 600 | K11: 1 | L11: [50] | M11: 3 | O11: =S11*((1/Conversions!$K$5)*(1/1000000)) -> 108.33336 | P11: =T11*((1/Conversions!$K$5)*(1/1000000)) -> 83.333356 | Q11: =U11*((1/Conversions!$K$5)*(1/1000000)) -> 133.33337 | S11: 390 | T11: 300 | U11: 480 | V11: 1 | W11: [50] | X11: 1 | Z11: R | AB11: =S11/H11 -> 0.86666667
A12: Biopower | B12: Tower | C12: Biogas | D12: =H12*((1/Conversions!$K$5)*(1/1000000)) -> 65.277796 | H12: =S12 -> 235 | L12: n/a | M12: n/a | O12: =S12*((1/Conversions!$K$5)*(1/1000000)) -> 65.277796 | P12: =T12*((1/Conversions!$K$5)*(1/1000000)) -> 65.277796 | Q12: =U12*((1/Conversions!$K$5)*(1/1000000)) -> 65.277796 | S12: 235 | T12: 235 | U12: 235 | V12: 1 | W12: [52] | X12: 1 | Z12: R | AB12: =S12/H12 -> 1
A13: Biopower | B13: Tower | C13: Steam | D13: =H13*((1/Conversions!$K$5)*(1/1000000)) -> 243.88896 | E13: =I13*((1/Conversions!$K$5)*(1/1000000)) -> 138.88893 | F13: =J13*((1/Conversions!$K$5)*(1/1000000)) -> 405.55567 | H13: 878 | I13: 500 | J13: 1460 | K13: 2 | L13: [49] | M13: 3 | O13: =S13*((1/Conversions!$K$5)*(1/1000000)) -> 153.61115 | P13: =T13*((1/Conversions!$K$5)*(1/1000000)) -> 133.33337 | Q13: =U13*((1/Conversions!$K$5)*(1/1000000)) -> 268.05563 | S13: 553 | T13: 480 | U13: 965 | V13: 4 | W13: [49-51] | X13: 1 | Z13: R | AB13: =S13/H13 -> 0.62984055
A14: Coal | B14: Once-through | C14: Generic | D14: =H14*((1/Conversions!$K$5)*(1/1000000)) -> 10097.225 | E14: =I14*((1/Conversions!$K$5)*(1/1000000)) -> 5555.5571 | F14: =J14*((1/Conversions!$K$5)*(1/1000000)) -> 13888.893 | H14: 36350 | I14: 20000 | J14: 50000 | K14: 4 | L14: [11, 27, 50, 58] | M14: 3 | O14: =S14*((1/Conversions!$K$5)*(1/1000000)) -> 69.444464 | P14: =T14*((1/Conversions!$K$5)*(1/1000000)) -> 27.777785 | Q14: =U14*((1/Conversions!$K$5)*(1/1000000)) -> 88.05558 | S14: 250 | T14: 100 | U14: 317 | V14: 4 | W14: [10, 27, 50, 58] | X14: 2 | Z14: NR | AB14: =S14/H14 -> 0.0068775791
A15: Coal | B15: Once-through | C15: Subcritical | D15: =H15*((1/Conversions!$K$5)*(1/1000000)) -> 7524.4465 | E15: =I15*((1/Conversions!$K$5)*(1/1000000)) -> 7512.7799 | F15: =J15*((1/Conversions!$K$5)*(1/1000000)) -> 7531.391 | H15: 27088 | I15: 27046 | J15: 27113 | K15: 3 | L15: [57] | M15: 3 | O15: =S15*((1/Conversions!$K$5)*(1/1000000)) -> 31.388898 | P15: =T15*((1/Conversions!$K$5)*(1/1000000)) -> 19.722228 | Q15: =U15*((1/Conversions!$K$5)*(1/1000000)) -> 38.333344 | S15: 113 | T15: 71 | U15: 138 | V15: 3 | W15: [57] | X15: 2 | Z15: NR | AB15: =S15/H15 -> 0.0041715889
A16: Coal | B16: Once-through | C16: Supercritical | D16: =H16*((1/Conversions!$K$5)*(1/1000000)) -> 6275.0017 | E16: =I16*((1/Conversions!$K$5)*(1/1000000)) -> 6264.1684 | F16: =J16*((1/Conversions!$K$5)*(1/1000000)) -> 6280.8351 | H16: 22590 | I16: 22551 | J16: 22611 | K16: 3 | L16: [57] | M16: 3 | O16: =S16*((1/Conversions!$K$5)*(1/1000000)) -> 28.611119 | P16: =T16*((1/Conversions!$K$5)*(1/1000000)) -> 17.777783 | Q16: =U16*((1/Conversions!$K$5)*(1/1000000)) -> 34.444454 | S16: 103 | T16: 64 | U16: 124 | V16: 3 | W16: [57] | X16: 2 | Z16: NR | AB16: =S16/H16 -> 0.0045595396
A17: Coal | B17: Pond | C17: Generic | D17: =H17*((1/Conversions!$K$5)*(1/1000000)) -> 3395.8343 | E17: =I17*((1/Conversions!$K$5)*(1/1000000)) -> 83.333356 | F17: =J17*((1/Conversions!$K$5)*(1/1000000)) -> 6666.6685 | H17: 12225 | I17: 300 | J17: 24000 | K17: 2 | L17: [27, 50] | M17: 3 | O17: =S17*((1/Conversions!$K$5)*(1/1000000)) -> 151.38893 | P17: =T17*((1/Conversions!$K$5)*(1/1000000)) -> 83.333356 | Q17: =U17*((1/Conversions!$K$5)*(1/1000000)) -> 194.4445 | S17: 545 | T17: 300 | U17: 700 | V17: 2 | W17: [27, 50] | X17: 2 | Z17: NR | AB17: =S17/H17 -> 0.044580777
A18: Coal | B18: Pond | C18: Subcritical | D18: =H18*((1/Conversions!$K$5)*(1/1000000)) -> 4976.1125 | E18: =I18*((1/Conversions!$K$5)*(1/1000000)) -> 4960.8347 | F18: =J18*((1/Conversions!$K$5)*(1/1000000)) -> 4979.7236 | H18: 17914 | I18: 17859 | J18: 17927 | K18: 3 | L18: [57] | M18: 3 | O18: =S18*((1/Conversions!$K$5)*(1/1000000)) -> 216.38895 | P18: =T18*((1/Conversions!$K$5)*(1/1000000)) -> 204.72228 | Q18: =U18*((1/Conversions!$K$5)*(1/1000000)) -> 223.3334 | S18: 779 | T18: 737 | U18: 804 | V18: 3 | W18: [57] | X18: 2 | Z18: NR | AB18: =S18/H18 -> 0.043485542
A19: Coal | B19: Pond | C19: Supercritical | D19: =H19*((1/Conversions!$K$5)*(1/1000000)) -> 4179.4456 | E19: =I19*((1/Conversions!$K$5)*(1/1000000)) -> 4165.5567 | F19: =J19*((1/Conversions!$K$5)*(1/1000000)) -> 4182.5012 | H19: 15046 | I19: 14996 | J19: 15057 | K19: 3 | L19: [57] | M19: 3 | O19: =S19*((1/Conversions!$K$5)*(1/1000000)) -> 11.66667 | P19: =T19*((1/Conversions!$K$5)*(1/1000000)) -> 1.1111114 | Q19: =U19*((1/Conversions!$K$5)*(1/1000000)) -> 17.777783 | S19: 42 | T19: 4 | U19: 64 | V19: 3 | W19: [57] | X19: 2 | Z19: NR | AB19: =S19/H19 -> 0.0027914396
A20: Coal | B20: Tower | C20: Generic | D20: =H20*((1/Conversions!$K$5)*(1/1000000)) -> 279.16674 | E20: =I20*((1/Conversions!$K$5)*(1/1000000)) -> 138.88893 | F20: =J20*((1/Conversions!$K$5)*(1/1000000)) -> 333.33343 | H20: 1005 | I20: 500 | J20: 1200 | K20: 4 | L20: [27, 35, 50, 58] | M20: 3 | O20: =S20*((1/Conversions!$K$5)*(1/1000000)) -> 190.83339 | P20: =T20*((1/Conversions!$K$5)*(1/1000000)) -> 133.33337 | Q20: =U20*((1/Conversions!$K$5)*(1/1000000)) -> 305.55564 | S20: 687 | T20: 480 | U20: 1100 | V20: 5 | W20: [10, 14, 27, 50, 58] | X20: 2 | Z20: NR | AB20: =S20/H20 -> 0.68358209
A21: Coal | B21: Tower | C21: IGCC | D21: =H21*((1/Conversions!$K$5)*(1/1000000)) -> 108.33336 | E21: =I21*((1/Conversions!$K$5)*(1/1000000)) -> 99.444472 | F21: =J21*((1/Conversions!$K$5)*(1/1000000)) -> 168.0556 | H21: 390 | I21: 358 | J21: 605 | K21: 11 | L21: [12, 13, 35, 59] | M21: 3 | O21: =S21*((1/Conversions!$K$5)*(1/1000000)) -> 103.33336 | P21: =T21*((1/Conversions!$K$5)*(1/1000000)) -> 88.333358 | Q21: =U21*((1/Conversions!$K$5)*(1/1000000)) -> 121.94448 | S21: 372 | T21: 318 | U21: 439 | V21: 7 | W21: [13, 59] | X21: 2 | Z21: NR | AB21: =S21/H21 -> 0.95384615
A22: Coal | B22: Tower | C22: IGCC with CCS | D22: =H22*((1/Conversions!$K$5)*(1/1000000)) -> 162.77782 | E22: =I22*((1/Conversions!$K$5)*(1/1000000)) -> 133.05559 | F22: =J22*((1/Conversions!$K$5)*(1/1000000)) -> 188.33339 | H22: 586 | I22: 479 | J22: 678 | K22: 6 | L22: [12, 59] | M22: 3 | O22: =S22*((1/Conversions!$K$5)*(1/1000000)) -> 150.00004 | P22: =T22*((1/Conversions!$K$5)*(1/1000000)) -> 145.00004 | Q22: =U22*((1/Conversions!$K$5)*(1/1000000)) -> 155.00004 | S22: 540 | T22: 522 | U22: 558 | V22: 3 | W22: [59] | X22: 2 | Z22: NR | AB22: =S22/H22 -> 0.92150171
A23: Coal | B23: Tower | C23: Subcritical | D23: =H23*((1/Conversions!$K$5)*(1/1000000)) -> 147.50004 | E23: =I23*((1/Conversions!$K$5)*(1/1000000)) -> 128.61115 | F23: =J23*((1/Conversions!$K$5)*(1/1000000)) -> 188.33339 | H23: 531 | I23: 463 | J23: 678 | K23: 7 | L23: [12, 13, 57, 59, 61] | M23: 3 | O23: =S23*((1/Conversions!$K$5)*(1/1000000)) -> 130.83337 | P23: =T23*((1/Conversions!$K$5)*(1/1000000)) -> 109.44447 | Q23: =U23*((1/Conversions!$K$5)*(1/1000000)) -> 184.4445 | S23: 471 | T23: 394 | U23: 664 | V23: 6 | W23: [13, 57, 59, 61] | X23: 2 | Z23: NR | AB23: =S23/H23 -> 0.88700565
A24: Coal | B24: Tower | C24: Subcritical with CCS | D24: =H24*((1/Conversions!$K$5)*(1/1000000)) -> 354.72232 | E24: =I24*((1/Conversions!$K$5)*(1/1000000)) -> 340.00009 | F24: =J24*((1/Conversions!$K$5)*(1/1000000)) -> 369.16677 | H24: 1277 | I24: 1224 | J24: 1329 | K24: 2 | L24: [12, 59] | M24: 3 | O24: =S24*((1/Conversions!$K$5)*(1/1000000)) -> 261.66674 | P24: =T24*((1/Conversions!$K$5)*(1/1000000)) -> 261.66674 | Q24: =U24*((1/Conversions!$K$5)*(1/1000000)) -> 261.66674 | S24: 942 | T24: 942 | U24: 942 | V24: 1 | W24: [59] | X24: 2 | Z24: NR | AB24: =S24/H24 -> 0.73766641
... A26: Coal | B26: Tower | C26: Supercritical with CCS | D26: =H26*((1/Conversions!$K$5)*(1/1000000)) -> 311.94453 | E26: =I26*((1/Conversions!$K$5)*(1/1000000)) -> 305.00008 | F26: =J26*((1/Conversions!$K$5)*(1/1000000)) -> 318.88898 | H26: 1123 | I26: 1098 | J26: 1148 | K26: 2 | L26: [12, 59] | M26: 3 | O26: =S26*((1/Conversions!$K$5)*(1/1000000)) -> 235.00007 | P26: =T26*((1/Conversions!$K$5)*(1/1000000)) -> 235.00007 | Q26: =U26*((1/Conversions!$K$5)*(1/1000000)) -> 235.00007 | S26: 846 | T26: 846 | U26: 846 | V26: 1 | W26: [59] | X26: 2 | Z26: NR | AB26: =S26/H26 -> 0.75333927
A27: CSP | B27: Dry | C27: Power Tower | D27: =H27*((1/Conversions!$K$5)*(1/1000000)) -> 7.2222242 | H27: =S27 -> 26 | L27: n/a | M27: n/a | O27: =S27*((1/Conversions!$K$5)*(1/1000000)) -> 7.2222242 | P27: =T27*((1/Conversions!$K$5)*(1/1000000)) -> 7.2222242 | Q27: =U27*((1/Conversions!$K$5)*(1/1000000)) -> 7.2222242 | S27: 26 | T27: 26 | U27: 26 | V27: 1 | W27: [48] | X27: 1 | Z27: R | AB27: =S27/H27 -> 1
A28: CSP | B28: Dry | C28: Trough | D28: =H28*((1/Conversions!$K$5)*(1/1000000)) -> 21.666673 | H28: =S28 -> 78 | L28: n/a | M28: n/a | O28: =S28*((1/Conversions!$K$5)*(1/1000000)) -> 21.666673 | P28: =T28*((1/Conversions!$K$5)*(1/1000000)) -> 11.944448 | Q28: =U28*((1/Conversions!$K$5)*(1/1000000)) -> 21.944451 | S28: 78 | T28: 43 | U28: 79 | V28: 10 | W28: [38, 42-44] | X28: 1 | Z28: R | AB28: =S28/H28 -> 1
A29: CSP | B29: Hybrid | C29: Power Tower | D29: =H29*((1/Conversions!$K$5)*(1/1000000)) -> 47.222235 | H29: =S29 -> 170 | L29: n/a | M29: n/a | O29: =S29*((1/Conversions!$K$5)*(1/1000000)) -> 47.222235 | P29: =T29*((1/Conversions!$K$5)*(1/1000000)) -> 25.000007 | Q29: =U29*((1/Conversions!$K$5)*(1/1000000)) -> 69.444464 | S29: 170 | T29: 90 | U29: 250 | V29: 2 | W29: [47] | X29: 1 | Z29: R | AB29: =S29/H29 -> 1
A30: CSP | B30: Hybrid | C30: Trough | D30: =H30*((1/Conversions!$K$5)*(1/1000000)) -> 93.888915 | H30: =S30 -> 338 | L30: n/a | M30: n/a | O30: =S30*((1/Conversions!$K$5)*(1/1000000)) -> 93.888915 | P30: =T30*((1/Conversions!$K$5)*(1/1000000)) -> 29.166675 | Q30: =U30*((1/Conversions!$K$5)*(1/1000000)) -> 95.83336 | S30: 338 | T30: 105 | U30: 345 | V30: 3 | W30: [42, 47] | X30: 1 | Z30: R | AB30: =S30/H30 -> 1
A31: CSP | B31: N/A | C31: Stirling | D31: =H31*((1/Conversions!$K$5)*(1/1000000)) -> 1.3888893 | H31: =S31 -> 5 | L31: n/a | M31: n/a | O31: =S31*((1/Conversions!$K$5)*(1/1000000)) -> 1.3888893 | P31: =T31*((1/Conversions!$K$5)*(1/1000000)) -> 1.1111114 | Q31: =U31*((1/Conversions!$K$5)*(1/1000000)) -> 1.6666671 | S31: 5 | T31: 4 | U31: 6 | V31: 2 | W31: [34, 49] | X31: 1 | Z31: R | AB31: =S31/H31 -> 1
A32: CSP | B32: Tower | C32: Fresnel | D32: =H32*((1/Conversions!$K$5)*(1/1000000)) -> 277.77785 | H32: =S32 -> 1000 | L32: n/a | M32: n/a | O32: =S32*((1/Conversions!$K$5)*(1/1000000)) -> 277.77785 | P32: =T32*((1/Conversions!$K$5)*(1/1000000)) -> 277.77785 | Q32: =U32*((1/Conversions!$K$5)*(1/1000000)) -> 277.77785 | S32: 1000 | T32: 1000 | U32: 1000 | V32: 1 | W32: [47] | X32: 1 | Z32: R | AB32: =S32/H32 -> 1
A33: CSP | B33: Tower | C33: Power Tower | D33: =H33*((1/Conversions!$K$5)*(1/1000000)) -> 218.33339 | H33: =S33 -> 786 | L33: n/a | M33: n/a | O33: =S33*((1/Conversions!$K$5)*(1/1000000)) -> 218.33339 | P33: =T33*((1/Conversions!$K$5)*(1/1000000)) -> 205.55561 | Q33: =U33*((1/Conversions!$K$5)*(1/1000000)) -> 238.88896 | S33: 786 | T33: 740 | U33: 860 | V33: 4 | W33: [34, 39-41] | X33: 1 | Z33: R | AB33: =S33/H33 -> 1
A34: CSP | B34: Tower | C34: Trough | D34: =H34*((1/Conversions!$K$5)*(1/1000000)) -> 240.27784 | H34: =S34 -> 865 | L34: n/a | M34: n/a | O34: =S34*((1/Conversions!$K$5)*(1/1000000)) -> 240.27784 | P34: =T34*((1/Conversions!$K$5)*(1/1000000)) -> 201.38894 | Q34: =U34*((1/Conversions!$K$5)*(1/1000000)) -> 293.61119 | S34: 865 | T34: 725 | U34: 1057 | V34: 17 | W34: [10, 34, 37-46] | X34: 1 | Z34: R | AB34: =S34/H34 -> 1
A35: Geothermal | B35: Dry | C35: Binary | D35: =H35*((1/Conversions!$K$5)*(1/1000000)) -> 37.50001 | H35: =S35 -> 135 | L35: n/a | M35: n/a | O35: =S35*((1/Conversions!$K$5)*(1/1000000)) -> 37.50001 | P35: =T35*((1/Conversions!$K$5)*(1/1000000)) -> 0 | Q35: =U35*((1/Conversions!$K$5)*(1/1000000)) -> 75.000021 | S35: 135 | T35: 0 | U35: 270 | V35: 2 | W35: [19, 51] | X35: 1 | Z35: R | AB35: =S35/H35 -> 1
A36: Geothermal | B36: Dry | C36: EGS | D36: =H36*((1/Conversions!$K$5)*(1/1000000)) -> 236.11118 | H36: =S36 -> 850 | L36: n/a | M36: n/a | O36: =S36*((1/Conversions!$K$5)*(1/1000000)) -> 236.11118 | P36: =T36*((1/Conversions!$K$5)*(1/1000000)) -> 83.333356 | Q36: =U36*((1/Conversions!$K$5)*(1/1000000)) -> 493.88903 | S36: 850 | T36: 300 | U36: 1778 | V36: 2 | W36: [19, 51] | X36: 1 | Z36: R | AB36: =S36/H36 -> 1
A37: Geothermal | B37: Dry | C37: Flash | D37: =H37*((1/Conversions!$K$5)*(1/1000000)) -> 0 | H37: =S37 -> 0 | L37: n/a | M37: n/a | O37: =S37*((1/Conversions!$K$5)*(1/1000000)) -> 0 | P37: =T37*((1/Conversions!$K$5)*(1/1000000)) -> 0 | Q37: =U37*((1/Conversions!$K$5)*(1/1000000)) -> 0 | S37: 0 | T37: 0 | U37: 0 | V37: 1 | W37: [51] | X37: 1 | Z37: R | AB37: =S37/H37 -> #DIV/0!
A38: Geothermal | B38: Hybrid | C38: EGS | D38: =H38*((1/Conversions!$K$5)*(1/1000000)) -> 390.55566 | H38: =S38 -> 1406 | L38: n/a | M38: n/a | O38: =S38*((1/Conversions!$K$5)*(1/1000000)) -> 390.55566 | P38: =T38*((1/Conversions!$K$5)*(1/1000000)) -> 225.8334 | Q38: =U38*((1/Conversions!$K$5)*(1/1000000)) -> 555.27793 | S38: 1406 | T38: 813 | U38: 1999 | V38: 2 | W38: [51, 56] | X38: 1 | Z38: R | AB38: =S38/H38 -> 1
... A45: Hydropower | B45: N/A | C45: Aggregated in-stream & reservoir | D45: =H45*((1/Conversions!$K$5)*(1/1000000)) -> 1247.5003 | H45: =S45 -> 4491 | L45: n/a | M45: n/a | O45: =S45*((1/Conversions!$K$5)*(1/1000000)) -> 1247.5003 | P45: =T45*((1/Conversions!$K$5)*(1/1000000)) -> 395.83344 | Q45: =U45*((1/Conversions!$K$5)*(1/1000000)) -> 5000.0014 | S45: 4491 | T45: 1425 | U45: 18000 | V45: 3 | W45: [22, 23] | X45: 1 | Z45: R | AB45: =S45/H45 -> 1
A46: Natural Gas | B46: Dry | C46: Combined Cycle | D46: =H46*((1/Conversions!$K$5)*(1/1000000)) -> 0.55555571 | E46: =I46*((1/Conversions!$K$5)*(1/1000000)) -> 0 | F46: =J46*((1/Conversions!$K$5)*(1/1000000)) -> 1.1111114 | H46: 2 | I46: 0 | J46: 4 | K46: 2 | L46: [50, 57] | M46: 3 | O46: =S46*((1/Conversions!$K$5)*(1/1000000)) -> 0.55555571 | P46: =T46*((1/Conversions!$K$5)*(1/1000000)) -> 0 | Q46: =U46*((1/Conversions!$K$5)*(1/1000000)) -> 1.1111114 | S46: 2 | T46: 0 | U46: 4 | V46: 2 | W46: [50, 57] | X46: 2 | Z46: NR | AB46: =S46/H46 -> 1
A47: Natural Gas | B47: Inlet | C47: Steam | D47: =H47*((1/Conversions!$K$5)*(1/1000000)) -> 118.05559 | E47: =I47*((1/Conversions!$K$5)*(1/1000000)) -> 27.777785 | F47: =J47*((1/Conversions!$K$5)*(1/1000000)) -> 208.33339 | H47: 425 | I47: 100 | J47: 750 | K47: 1 | L47: [49] | M47: 3 | O47: =S47*((1/Conversions!$K$5)*(1/1000000)) -> 94.444471 | P47: =T47*((1/Conversions!$K$5)*(1/1000000)) -> 22.222228 | Q47: =U47*((1/Conversions!$K$5)*(1/1000000)) -> 166.66671 | S47: 340 | T47: 80 | U47: 600 | V47: 1 | W47: [49] | X47: 2 | Z47: NR | AB47: =S47/H47 -> 0.8
A48: Natural Gas | B48: Once-through | C48: Combined Cycle | D48: =H48*((1/Conversions!$K$5)*(1/1000000)) -> 3161.112 | E48: =I48*((1/Conversions!$K$5)*(1/1000000)) -> 2083.3339 | F48: =J48*((1/Conversions!$K$5)*(1/1000000)) -> 5555.5571 | H48: 11380 | I48: 7500 | J48: 20000 | K48: 2 | L48: [50, 57] | M48: 3 | O48: =S48*((1/Conversions!$K$5)*(1/1000000)) -> 27.777785 | P48: =T48*((1/Conversions!$K$5)*(1/1000000)) -> 5.5555571 | Q48: =U48*((1/Conversions!$K$5)*(1/1000000)) -> 27.777785 | S48: 100 | T48: 20 | U48: 100 | V48: 3 | W48: [50, 57, 60] | X48: 2 | Z48: NR | AB48: =S48/H48 -> 0.0087873462
A49: Natural Gas | B49: Once-through | C49: Steam | D49: =H49*((1/Conversions!$K$5)*(1/1000000)) -> 9722.2249 | E49: =I49*((1/Conversions!$K$5)*(1/1000000)) -> 2777.7785 | F49: =J49*((1/Conversions!$K$5)*(1/1000000)) -> 16666.671 | H49: 35000 | I49: 10000 | J49: 60000 | K49: 1 | L49: [49] | M49: 3 | O49: =S49*((1/Conversions!$K$5)*(1/1000000)) -> 66.666685 | P49: =T49*((1/Conversions!$K$5)*(1/1000000)) -> 26.388896 | Q49: =U49*((1/Conversions!$K$5)*(1/1000000)) -> 80.833356 | S49: 240 | T49: 95 | U49: 291 | V49: 2 | W49: [10, 49] | X49: 2 | Z49: NR | AB49: =S49/H49 -> 0.0068571429
A50: Natural Gas | B50: Pond | C50: Combined Cycle | D50: =H50*((1/Conversions!$K$5)*(1/1000000)) -> 1652.7782 | E50: =I50*((1/Conversions!$K$5)*(1/1000000)) -> 1652.7782 | F50: =J50*((1/Conversions!$K$5)*(1/1000000)) -> 1652.7782 | H50: 5950 | I50: 5950 | J50: 5950 | K50: 1 | L50: [57] | M50: 3 | O50: =S50*((1/Conversions!$K$5)*(1/1000000)) -> 66.666685 | P50: =T50*((1/Conversions!$K$5)*(1/1000000)) -> 66.666685 | Q50: =U50*((1/Conversions!$K$5)*(1/1000000)) -> 66.666685 | S50: 240 | T50: 240 | U50: 240 | V50: 1 | W50: [57] | X50: 2 | Z50: NR | AB50: =S50/H50 -> 0.040336134
A51: Natural Gas | B51: Tower | C51: Combined Cycle | D51: =H51*((1/Conversions!$K$5)*(1/1000000)) -> 70.277797 | E51: =I51*((1/Conversions!$K$5)*(1/1000000)) -> 41.666678 | F51: =J51*((1/Conversions!$K$5)*(1/1000000)) -> 78.611133 | H51: 253 | I51: 150 | J51: 283 | K51: 6 | L51: [12, 13, 50, 57, 59] | M51: 3 | O51: =S51*((1/Conversions!$K$5)*(1/1000000)) -> 55.000015 | P51: =T51*((1/Conversions!$K$5)*(1/1000000)) -> 36.111121 | Q51: =U51*((1/Conversions!$K$5)*(1/1000000)) -> 83.333356 | S51: 198 | T51: 130 | U51: 300 | V51: 5 | W51: [13, 34, 50, 57, 59] | X51: 2 | Z51: NR | AB51: =S51/H51 -> 0.7826087
A52: Natural Gas | B52: Tower | C52: Combined Cycle with CCS | D52: =H52*((1/Conversions!$K$5)*(1/1000000)) -> 137.77782 | E52: =I52*((1/Conversions!$K$5)*(1/1000000)) -> 135.27782 | F52: =J52*((1/Conversions!$K$5)*(1/1000000)) -> 140.55559 | H52: 496 | I52: 487 | J52: 506 | K52: 2 | L52: [12, 59] | M52: 3 | O52: =S52*((1/Conversions!$K$5)*(1/1000000)) -> 105.00003 | P52: =T52*((1/Conversions!$K$5)*(1/1000000)) -> 105.00003 | Q52: =U52*((1/Conversions!$K$5)*(1/1000000)) -> 105.00003 | S52: 378 | T52: 378 | U52: 378 | V52: 1 | W52: [59] | X52: 2 | Z52: NR | AB52: =S52/H52 -> 0.76209677
A53: Natural Gas | B53: Tower | C53: Steam | D53: =H53*((1/Conversions!$K$5)*(1/1000000)) -> 334.16676 | E53: =I53*((1/Conversions!$K$5)*(1/1000000)) -> 263.88896 | F53: =J53*((1/Conversions!$K$5)*(1/1000000)) -> 405.55567 | H53: 1203 | I53: 950 | J53: 1460 | K53: 2 | L53: [49, 60] | M53: 3 | O53: =S53*((1/Conversions!$K$5)*(1/1000000)) -> 229.44451 | P53: =T53*((1/Conversions!$K$5)*(1/1000000)) -> 183.88894 | Q53: =U53*((1/Conversions!$K$5)*(1/1000000)) -> 325.00009 | S53: 826 | T53: 662 | U53: 1170 | V53: 4 | W53: [10, 14, 49, 60] | X53: 2 | Z53: NR | AB53: =S53/H53 -> 0.68661679
A54: Nuclear | B54: Once-through | C54: Generic | D54: =H54*((1/Conversions!$K$5)*(1/1000000)) -> 12319.448 | E54: =I54*((1/Conversions!$K$5)*(1/1000000)) -> 6944.4464 | F54: =J54*((1/Conversions!$K$5)*(1/1000000)) -> 16666.671 | H54: 44350 | I54: 25000 | J54: 60000 | K54: 4 | L54: [27, 50, 57, 58] | M54: 3 | O54: =S54*((1/Conversions!$K$5)*(1/1000000)) -> 74.722243 | P54: =T54*((1/Conversions!$K$5)*(1/1000000)) -> 27.777785 | Q54: =U54*((1/Conversions!$K$5)*(1/1000000)) -> 111.11114 | S54: 269 | T54: 100 | U54: 400 | V54: 4 | W54: [27, 50, 57, 58] | X54: 2 | Z54: NR | AB54: =S54/H54 -> 0.006065389
A55: Nuclear | B55: Pond | C55: Generic | D55: =H55*((1/Conversions!$K$5)*(1/1000000)) -> 1958.3339 | E55: =I55*((1/Conversions!$K$5)*(1/1000000)) -> 138.88893 | F55: =J55*((1/Conversions!$K$5)*(1/1000000)) -> 3611.1121 | H55: 7050 | I55: 500 | J55: 13000 | K55: 2 | L55: [27, 50] | M55: 3 | O55: =S55*((1/Conversions!$K$5)*(1/1000000)) -> 169.44449 | P55: =T55*((1/Conversions!$K$5)*(1/1000000)) -> 155.5556 | Q55: =U55*((1/Conversions!$K$5)*(1/1000000)) -> 200.00006 | S55: 610 | T55: 560 | U55: 720 | V55: 2 | W55: [27, 50] | X55: 2 | Z55: NR | AB55: =S55/H55 -> 0.086524823
A56: Nuclear | B56: Tower | C56: Generic | D56: =H56*((1/Conversions!$K$5)*(1/1000000)) -> 305.83342 | E56: =I56*((1/Conversions!$K$5)*(1/1000000)) -> 222.22228 | F56: =J56*((1/Conversions!$K$5)*(1/1000000)) -> 722.22242 | H56: 1101 | I56: 800 | J56: 2600 | K56: 3 | L56: [27, 50, 57] | M56: 3 | O56: =S56*((1/Conversions!$K$5)*(1/1000000)) -> 186.66672 | P56: =T56*((1/Conversions!$K$5)*(1/1000000)) -> 161.38893 | Q56: =U56*((1/Conversions!$K$5)*(1/1000000)) -> 234.72229 | S56: 672 | T56: 581 | U56: 845 | V56: 6 | W56: [10, 14, 27, 50, 57] | X56: 2 | Z56: NR | AB56: =S56/H56 -> 0.61035422
A57: PV | B57: N/A | C57: Utility Scale PV | D57: =H57*((1/Conversions!$K$5)*(1/1000000)) -> 7.2222242 | H57: =S57 -> 26 | L57: n/a | M57: n/a | O57: =S57*((1/Conversions!$K$5)*(1/1000000)) -> 7.2222242 | P57: =T57*((1/Conversions!$K$5)*(1/1000000)) -> 0 | Q57: =U57*((1/Conversions!$K$5)*(1/1000000)) -> 9.1666692 | S57: 26 | T57: 0 | U57: 33 | V57: 3 | W57: [10, 34, 35] | X57: 1 | Z57: R | AB57: =S57/H57 -> 1
A58: Wind | B58: N/A | C58: Wind Turbine | D58: =H58*((1/Conversions!$K$5)*(1/1000000)) -> 0 | H58: =S58 -> 0 | L58: n/a | M58: n/a | O58: =S58*((1/Conversions!$K$5)*(1/1000000)) -> 0 | P58: =T58*((1/Conversions!$K$5)*(1/1000000)) -> 0 | Q58: =U58*((1/Conversions!$K$5)*(1/1000000)) -> 0.27777785 | S58: 0 | T58: 0 | U58: 1 | V58: 2 | W58: [11, 36] | X58: 1 | Z58: R | AB58: =S58/H58 -> #DIV/0!
A62: Source: DOE (2006), Energy Demands on Water Resources: Report to Congress on the Interdependency of Energy and Water. DOE, Washington DC.
A63: p. 56 (primarily mined in WY, TX, NE but older mines in NM an UT are considering reopening)
A64: p. 53; lower range for Western coals, higher range for underground Eastern underground coals
D65: Withdrawal/Consumption Values
D66: Million gallons H2O/PJ | H66: gallons H2O/MMBtu
A67: Fuel Type | B67: Cooling | C67: Technology | D67: Low Range | E67: Average or Reported Value | F67: High Range | H67: Low Range | I67: Average or Reported Value | J67: High Range
A68: Nuclear | C68: Uranium Mining | D68: =H68*(1/Conversions!$K$7)*Conversions!$K$6*(1/1000000) -> 0.94728366 | E68: =I68*(1/Conversions!$K$7)*Conversions!$K$6*(1/1000000) -> 3.3154928 | F68: =J68*(1/Conversions!$K$7)*Conversions!$K$6*(1/1000000) -> 5.683702 | H68: 1 | I68: =AVERAGE(H68,J68) -> 3.5 | J68: 6
A69: Nuclear | C69: Uranium Processing | D69: =H69*(1/Conversions!$K$7)*Conversions!$K$6*(1/1000000) -> 6.6309856 | E69: =I69*(1/Conversions!$K$7)*Conversions!$K$6*(1/1000000) -> 7.1046275 | F69: =J69*(1/Conversions!$K$7)*Conversions!$K$6*(1/1000000) -> 7.5782693 | H69: 7 | I69: =AVERAGE(H69,J69) -> 7.5 | J69: 8
A70: Coal | C70: Coal mining (extraction) | D70: =H70*(1/Conversions!$K$7)*Conversions!$K$6*(1/1000000) -> 0.94728366 | E70: =I70*(1/Conversions!$K$7)*Conversions!$K$6*(1/1000000) -> 3.3154928 | F70: =J70*(1/Conversions!$K$7)*Conversions!$K$6*(1/1000000) -> 5.683702 | H70: 1 | I70: =AVERAGE(H70,J70) -> 3.5 | J70: 6 | K70: USDOE 2006 - water use per unit of thermal energy shown here and units of water use per electric energy shown in USDOE Appendix B; water use varies from 10 to 100 gal per ton of coal mined; 1 MMBTU = approximately 8 gal of gasoline

Sheet CompositeGREETEFs
B1: Using factors labeled *-EPA where available
B2: Methodology for 2005 and 2010 appears to be different than for 2015 and 2020. If 2005&10 are less than 2015, 2015 factor is used.
B3: Correction for GREET factors being based upon LHVs | E3: =1/1.1 -> 0.90909091
B4: Note: for 2015 values, the 2013 values from the GREET2014 update are used. | U4: 2020 value from GREET12. 2010 is 10% greater, 2020 is 10% greater.
B5: Assuming biomass-to-steam and biomass-to-IGCC require 1/10th of energy input from lignite and bit. coal, respectively. This factors into the CO2 EF. This assumptions should be revisited in the future.
B6: Using typical bit. coal CO2 EF for IGCC
B8: kT/PJ | C8: VOC | D8: VOC | E8: VOC | F8: VOC | G8: VOC | H8: VOC | I8: CO | J8: CO | K8: CO | L8: CO | M8: CO | N8: CO | O8: NOX | P8: NOX | Q8: NOX | R8: NOX | S8: NOX | T8: NOX | U8: PM10 | V8: PM10 | W8: PM10 | X8: PM10 | Y8: PM10 | Z8: PM10 | AA8: PM25 | AB8: PM25 | AC8: PM25 | AD8: PM25 | AE8: PM25 | AF8: PM25 | AG8: SO2 | AH8: SO2 | AI8: SO2 | AJ8: SO2 | AK8: SO2 | AL8: SO2 | AM8: CH4 | AN8: CH4 | AO8: CH4 | AP8: CH4 | AQ8: CH4 | AR8: CH4 | AS8: N2O | AT8: N2O | AU8: N2O | AV8: N2O | AW8: N2O | AX8: N2O | AY8: BC | AZ8: BC | BA8: BC | BB8: BC | BC8: BC | BD8: BC | BE8: CO2 | BF8: CO2 | BG8: CO2 | BH8: CO2 | BI8: CO2 | BJ8: CO2 | BK8: OC | BL8: OC | BM8: OC | BN8: OC | BO8: OC | BP8: OC
C9: 2005 | D9: 2010 | E9: 2015 | F9: 2020 | G9: 2025 | H9: 2030-2055 | I9: 2005 | J9: 2010 | K9: 2015 | L9: 2020 | M9: 2025 | N9: 2030-2055 | O9: 2005 | P9: 2010 | Q9: 2015 | R9: 2020 | S9: 2025 | T9: 2030-2055 | U9: 2005 | V9: 2010 | W9: 2015 | X9: 2020 | Y9: 2025 | Z9: 2030-2055 | AA9: 2005 | AB9: 2010 | AC9: 2015 | AD9: 2020 | AE9: 2025 | AF9: 2030-2055 | AG9: 2005 | AH9: 2010 | AI9: 2015 | AJ9: 2020 | AK9: 2025 | AL9: 2030-2055 | AM9: 2005 | AN9: 2010 | AO9: 2015 | AP9: 2020 | AQ9: 2025 | AR9: 2030-2055 | AS9: 2005 | AT9: 2010 | AU9: 2015 | AV9: 2020 | AW9: 2025 | AX9: 2030-2055 | AY9: 2005 | AZ9: 2010 | BA9: 2015 | BB9: 2020 | BC9: 2025 | BD9: 2030-2055 | BE9: 2005 | BF9: 2010 | BG9: 2015 | BH9: 2020 | BI9: 2025 | BJ9: 2030-2055 | BK9: 2005 | BL9: 2010 | BM9: 2015 | BN9: 2020 | BO9: 2025 | BP9: 2030-2055
B10: IGCC turbine | C10: =IF($E$3*$C28*0.000947817>D10,$E$3*$C28*0.000947817,D10) -> 0.0012157907 | D10: =IF($E$3*$D28*0.000947817>E10,$E$3*$D28*0.000947817,E10) -> 0.00061893915 | E10: =$E$3*$H$28*0.453592*947817/1000000 -> 0.00036865137 | F10: =$E$3*$I$28*0.453592*947817/1000000 -> 0.0003857812 | G10: =(F10+H10)/2 -> 0.00039518087 | H10: =$E$3*$J$28*0.453592*947817/1000000 -> 0.00040458053 | I10: =IF($E$3*$C29*0.000947817>J10,$E$3*$C29*0.000947817,J10) -> 0.010901619 | J10: =IF($E$3*$D29*0.000947817>K10,$E$3*$D29*0.000947817,K10) -> 0.010901619 | K10: =$E$3*$H$29*0.453592*947817/1000000 -> 0.0064556856 | L10: =$E$3*$I$29*0.453592*947817/1000000 -> 0.0067556569 | M10: =(L10+N10)/2 -> 0.0069202603 | N10: =$E$3*$J$29*0.453592*947817/1000000 -> 0.0070848638 | O10: =IF($E$3*$C30*0.000947817>P10,$E$3*$C30*0.000947817,P10) -> 0.036278127 | P10: =IF($E$3*$D30*0.000947817>Q10,$E$3*$D30*0.000947817,Q10) -> 0.018840017 | Q10: =$E$3*$H$30*0.453592*947817/1000000 -> 0.01115599 | R10: =$E$3*$I$30*0.453592*947817/1000000 -> 0.011674367 | S10: =(R10+T10)/2 -> 0.011958816 | T10: =$E$3*$J$30*0.453592*947817/1000000 -> 0.012243266 | U10: =IF($E$3*$C31*0.000947817>V10,$E$3*$C31*0.000947817,V10) -> 0.005374984 | V10: =IF($E$3*$D31*0.000947817>W10,$E$3*$D31*0.000947817,W10) -> 0.0026168366 | W10: =$E$3*$H$31*0.453592*947817/1000000 -> 0.0015512292 | X10: =$E$3*$I$31*0.453592*947817/1000000 -> 0.001623309 | Y10: =(X10+Z10)/2 -> 0.0016628614 | Z10: =$E$3*$J$31*0.453592*947817/1000000 -> 0.0017024137 | AA10: =IF($E$3*$C32*0.000947817>AB10,$E$3*$C32*0.000947817,AB10) -> 0.002687492 | AB10: =IF($E$3*$D32*0.000947817>AC10,$E$3*$D32*0.000947817,AC10) -> 0.001314019 | AC10: =$E$3*$H$32*0.453592*947817/1000000 -> 0 | AD10: =$E$3*$I$32*0.453592*947817/1000000 -> 0 | AE10: =(AD10+AF10)/2 -> 0 | AF10: =$E$3*$J$32*0.453592*947817/1000000 -> 0 | AG10: =IF($E$3*$C33*0.000947817>AH10,$E$3*$C33*0.000947817,AH10) -> 0.036278127 | AH10: =IF($E$3*$D33*0.000947817>AI10,$E$3*$D33*0.000947817,AI10) -> 0.0068923529 | AI10: =$E$3*$H$33*0.453592*947817/1000000 -> 0.0040814207 | AJ10: =$E$3*$I$33*0.453592*947817/1000000 -> 0.0042710689 | AK10: =(AJ10+AL10)/2 -> 0.0043751347 | AL10: =$E$3*$J$33*0.453592*947817/1000000 -> 0.0044792005 | AM10: =IF($E$3*$C34*0.000947817>AN10,$E$3*$C34*0.000947817,AN10) -> 0.004392701 | AN10: =IF($E$3*$D34*0.000947817>AO10,$E$3*$D34*0.000947817,AO10) -> 0.0041066326 | AO10: =$E$3*$H$34*0.453592*947817/1000000 -> 0.00066516887 | AP10: =$E$3*$I$34*0.453592*947817/1000000 -> 0.00069607675 | AQ10: =(AP10+AR10)/2 -> 0.00071303685 | AR10: =$E$3*$J$34*0.453592*947817/1000000 -> 0.00072999695 | AS10: =IF($E$3*$C35*0.000947817>AT10,$E$3*$C35*0.000947817,AT10) -> 0.004392701 | AT10: =IF($E$3*$D35*0.000947817>AU10,$E$3*$D35*0.000947817,AU10) -> 0.0041066326 | AU10: =$E$3*$H$35*0.453592*947817/1000000 -> 0.0009977533 | AV10: =$E$3*$I$35*0.453592*947817/1000000 -> 0.0010441151 | AW10: =(AV10+AX10)/2 -> 0.0010695553 | AX10: =$E$3*$J$35*0.453592*947817/1000000 -> 0.0010949954 | AY10: =$E$3*AA10*#REF! -> #REF! | AZ10: =$E$3*AB10*#REF! -> #REF! | BA10: =$E$3*$H$36*0.453592*947817/1000000 -> 0 | BB10: =$E$3*$I$36*0.453592*947817/1000000 -> 0 | BC10: =(BB10+BD10)/2 -> 0 | BD10: =$E$3*$J$36*0.453592*947817/1000000 -> 0 | BE10: =BE11 -> 83.357128 | BF10: =BF11 -> 83.357128 | BG10: =BG11 -> 83.357128 | BH10: =BH11 -> 83.357128 | BI10: =BI11 -> 83.357128 | BJ10: =BJ11 -> 83.357128 | BK10: =$E$3*AA10*#REF! -> #REF! | BL10: =$E$3*AB10*#REF! -> #REF! | BM10: =$E$3*AC10*#REF! -> #REF! | BO10: =(BN10+BP10)/2 -> #REF! | BP10: =$E$3*AF10*#REF! -> #REF!
B11: utility coal boiler - bituminous | C11: =IF($E$3*$C41*0.000947817>D11,$E$3*$C41*0.000947817,D11) -> 0.0011589217 | D11: =IF($E$3*$D41*0.000947817>E11,$E$3*$D41*0.000947817,E11) -> 0.0011589217 | E11: =$E$3*$H$41*0.453592*947817/1000000 -> 0.0010343132 | F11: =$E$3*$I$41*0.453592*947817/1000000 -> 0.0010343132 | G11: =(F11+H11)/2 -> 0.0010343132 | H11: =$E$3*$J$41*0.453592*947817/1000000 -> 0.0010343132 | I11: =IF($E$3*$C42*0.000947817>J11,$E$3*$C42*0.000947817,J11) -> 0.013067811 | J11: =IF($E$3*$D42*0.000947817>K11,$E$3*$D42*0.000947817,K11) -> 0.0095134977 | K11: =$E$3*$H$42*0.453592*947817/1000000 -> 0.008716262 | L11: =$E$3*$I$42*0.453592*947817/1000000 -> 0.008716262 | M11: =(L11+N11)/2 -> 0.008716262 | N11: =$E$3*$J$42*0.453592*947817/1000000 -> 0.008716262 | O11: =IF($E$3*$C43*0.000947817>P11,$E$3*$C43*0.000947817,P11) -> 0.13787808 | P11: =IF($E$3*$D43*0.000947817>Q11,$E$3*$D43*0.000947817,Q11) -> 0.12988703 | Q11: =$E$3*$H$43*0.453592*947817/1000000 -> 0.12988703 | R11: =$E$3*$I$43*0.453592*947817/1000000 -> 0.11226549 | S11: =(R11+T11)/2 -> 0.097580881 | T11: =$E$3*$J$43*0.453592*947817/1000000 -> 0.082896269 | U11: =IF($E$3*$C44*0.000947817>V11,$E$3*$C44*0.000947817,V11) -> 0.013103139 | V11: =IF($E$3*$D44*0.000947817>W11,$E$3*$D44*0.000947817,W11) -> 0.013103139 | W11: =$E$3*E44*0.000947817 -> 0.013103139 | X11: =$E$3*F44*0.000947817 -> 0.013103139 | Y11: =X11 -> 0.013103139 | Z11: =Y11 -> 0.013103139 | AA11: =IF($E$3*$C45*0.000947817>AB11,$E$3*$C45*0.000947817,AB11) -> 0.010297601 | AB11: =IF($E$3*$D45*0.000947817>AC11,$E$3*$D45*0.000947817,AC11) -> 0.010297601 | AC11: =AD11 -> 0.010297601 | AD11: =$E$3*F45*0.000947817 -> 0.010297601 | AE11: =AD11 -> 0.010297601 | AF11: =AE11 -> 0.010297601 | AG11: =IF($E$3*$C46*0.000947817>AH11,$E$3*$C46*0.000947817,AH11) -> 0.42017954 | AH11: =IF($E$3*$D46*0.000947817>AI11,$E$3*$D46*0.000947817,AI11) -> 0.42017954 | AI11: =$E$3*$H$46*0.453592*947817/1000000 -> 0.42017954 | AJ11: =$E$3*$I$46*0.453592*947817/1000000 -> 0.064315956 | AK11: =(AJ11+AL11)/2 -> 0.06179046 | AL11: =$E$3*$J$46*0.453592*947817/1000000 -> 0.059264964 | AM11: =IF($E$3*$C47*0.000947817>AN11,$E$3*$C47*0.000947817,AN11) -> 0.0010494919 | AN11: =IF($E$3*$D47*0.000947817>AO11,$E$3*$D47*0.000947817,AO11) -> 0.00096677334 | AO11: =$E$3*$H$47*0.453592*947817/1000000 -> 0.00095625183 | AP11: =$E$3*$I$47*0.453592*947817/1000000 -> 0.00095625183 | AQ11: =(AP11+AR11)/2 -> 0.00095625183 | AR11: =$E$3*$J$47*0.453592*947817/1000000 -> 0.00095625183 | AS11: =IF($E$3*$C48*0.000947817>AT11,$E$3*$C48*0.000947817,AT11) -> 0.0014286187 | AT11: =IF($E$3*$D48*0.000947817>AU11,$E$3*$D48*0.000947817,AU11) -> 0.0014286187 | AU11: =$E$3*$H$48*0.453592*947817/1000000 -> 0.0014042177 | AV11: =$E$3*$I$48*0.453592*947817/1000000 -> 0.0014042177 | AW11: =(AV11+AX11)/2 -> 0.0014042177 | AX11: =$E$3*$J$48*0.453592*947817/1000000 -> 0.0014042177 | AY11: =$E$3*AA11*#REF! -> #REF! | AZ11: =$E$3*AB11*#REF! -> #REF! | BA11: =$E$3*$H$49*0.453592*947817/1000000 -> 0.00031691144 | BB11: =$E$3*$I$49*0.453592*947817/1000000 -> 0.00029172458 | BC11: =(BB11+BD11)/2 -> 0.0002761309 | BD11: =$E$3*$J$49*0.453592*947817/1000000 -> 0.00026053723 | BE11: =IF($E$3*$C50*0.000947817>BF11,$E$3*$C50*0.000947817,BF11) -> 83.357128 | BF11: =IF($E$3*$D50*0.000947817>BG11,$E$3*$D50*0.000947817,BG11) -> 83.357128 | BG11: =$E$3*$H$50*0.453592*947817/1000000 -> 83.357128 | BH11: =$E$3*$I$50*0.453592*947817/1000000 -> 83.357128 | BI11: =(BH11+BJ11)/2 -> 83.357128 | BJ11: =$E$3*$J$50*0.453592*947817/1000000 -> 83.357128 | BK11: =$E$3*AA11*#REF! -> #REF! | BL11: =$E$3*AB11*#REF! -> #REF! | BM11: =$E$3*AC11*#REF! -> #REF! | BO11: =(BN11+BP11)/2 -> #REF! | BP11: =$E$3*AF11*#REF! -> #REF!
B12: Utility coal boiler - subbituminous | C12: =IF(C11>D12,C11,D12) -> 0.0012286199 | D12: =IF(D11>E12,D11,E12) -> 0.0012286199 | E12: =$E$3*$H$54*0.453592*947817/1000000 -> 0.0012286199 | F12: =$E$3*$I$54*0.453592*947817/1000000 -> 0.0012286199 | G12: =(F12+H12)/2 -> 0.0012286199 | H12: =$E$3*$J$54*0.453592*947817/1000000 -> 0.0012286199 | I12: =IF(I11>J12,I11,J12) -> 0.013067811 | J12: =IF(J11>K12,J11,K12) -> 0.01034293 | K12: =$E$3*$H$55*0.453592*947817/1000000 -> 0.01034293 | L12: =$E$3*$I$55*0.453592*947817/1000000 -> 0.01034293 | M12: =(L12+N12)/2 -> 0.01034293 | N12: =$E$3*$J$55*0.453592*947817/1000000 -> 0.01034293 | O12: =IF(O11>P12,O11,P12) -> 0.13787808 | P12: =IF(P11>Q12,P11,Q12) -> 0.12988703 | Q12: =$E$3*$H$56*0.453592*947817/1000000 -> 0.11262998 | R12: =$E$3*$I$56*0.453592*947817/1000000 -> 0.098068201 | S12: =(R12+T12)/2 -> 0.085933384 | T12: =$E$3*$J$56*0.453592*947817/1000000 -> 0.073798566 | U12: =IF(U11>V12,U11,V12) -> 0.013103139 | V12: =IF(V11>W12,V11,W12) -> 0.013103139 | W12: =$E$3*E44*0.000947817 -> 0.013103139 | X12: =$E$3*F44*0.000947817 -> 0.013103139 | Y12: =X12 -> 0.013103139 | Z12: =Y12 -> 0.013103139 | AA12: =IF(AA11>AB12,AA11,AB12) -> 0.010297601 | AB12: =IF(AB11>AC12,AB11,AC12) -> 0.010297601 | AC12: =AD12 -> 0.010297601 | AD12: =$E$3*F45*0.000947817 -> 0.010297601 | AE12: =AD12 -> 0.010297601 | AF12: =AE12 -> 0.010297601 | AG12: =IF(AG11>AH12,AG11,AH12) -> 0.42017954 | AH12: =IF(AH11>AI12,AH11,AI12) -> 0.42017954 | AI12: =$E$3*$H$59*0.453592*947817/1000000 -> 0.23963253 | AJ12: =$E$3*$I$59*0.453592*947817/1000000 -> 0.063796411 | AK12: =(AJ12+AL12)/2 -> 0.061291317 | AL12: =$E$3*$J$59*0.453592*947817/1000000 -> 0.058786222 | AM12: =IF(AM11>AN12,AM11,AN12) -> 0.0010494919 | AN12: =IF(AN11>AO12,AN11,AO12) -> 0.00097205764 | AO12: =$E$3*$H$60*0.453592*947817/1000000 -> 0.00097205764 | AP12: =$E$3*$I$60*0.453592*947817/1000000 -> 0.00097205764 | AQ12: =(AP12+AR12)/2 -> 0.00097205764 | AR12: =$E$3*$J$60*0.453592*947817/1000000 -> 0.00097205764 | AS12: =IF(AS11>AT12,AS11,AT12) -> 0.0014487723 | AT12: =IF(AT11>AU12,AT11,AU12) -> 0.0014487723 | AU12: =$E$3*$H$61*0.453592*947817/1000000 -> 0.0014487723 | AV12: =$E$3*$I$61*0.453592*947817/1000000 -> 0.0014487723 | AW12: =(AV12+AX12)/2 -> 0.0014487723 | AX12: =$E$3*$J$61*0.453592*947817/1000000 -> 0.0014487723 | AY12: =AY11 -> #REF! | AZ12: =AZ11 -> #REF! | BA12: =$E$3*$H$62*0.453592*947817/1000000 -> 8.7925493e-05 | BB12: =$E$3*$I$62*0.453592*947817/1000000 -> 0.00060555899 | BC12: =(BB12+BD12)/2 -> 0.00057253719 | BD12: =$E$3*$J$62*0.453592*947817/1000000 -> 0.00053951539 | BE12: =IF(BE11>BF12,BE11,BF12) -> 85.512283 | BF12: =IF(BF11>BG12,BF11,BG12) -> 85.512283 | BG12: =$E$3*$H$63*0.453592*947817/1000000 -> 85.512283 | BH12: =$E$3*$I$63*0.453592*947817/1000000 -> 85.512283 | BI12: =(BH12+BJ12)/2 -> 85.512283 | BJ12: =$E$3*$J$63*0.453592*947817/1000000 -> 85.512283
B13: Utility coal boiler - lignite | C13: =IF(C12>D13,C12,D13) -> 0.0012581068 | D13: =IF(D12>E13,D12,E13) -> 0.0012581068 | E13: =$E$3*$H$67*0.453592*947817/1000000 -> 0.0012581068 | F13: =$E$3*$I$67*0.453592*947817/1000000 -> 0.0012581068 | G13: =(F13+H13)/2 -> 0.0012581068 | H13: =$E$3*$J$67*0.453592*947817/1000000 -> 0.0012581068 | I13: =IF(I12>J13,I12,J13) -> 0.013067811 | J13: =IF(J12>K13,J12,K13) -> 0.010591161 | K13: =$E$3*$H$68*0.453592*947817/1000000 -> 0.010591161 | L13: =$E$3*$I$68*0.453592*947817/1000000 -> 0.010591161 | M13: =(L13+N13)/2 -> 0.010591161 | N13: =$E$3*$J$68*0.453592*947817/1000000 -> 0.010591161 | O13: =IF(O12>P13,O12,P13) -> 0.13787808 | P13: =IF(P12>Q13,P12,Q13) -> 0.12988703 | Q13: =$E$3*$H$69*0.453592*947817/1000000 -> 0.1153331 | R13: =$E$3*$I$69*0.453592*947817/1000000 -> 0.10042184 | S13: =(R13+T13)/2 -> 0.087995785 | T13: =$E$3*$J$69*0.453592*947817/1000000 -> 0.075569732 | U13: =IF(U12>V13,U12,V13) -> 0.013103139 | V13: =IF(V12>W13,V12,W13) -> 0.013103139 | W13: =$E$3*E44*0.000947817 -> 0.013103139 | X13: =$E$3*F44*0.000947817 -> 0.013103139 | Y13: =X13 -> 0.013103139 | Z13: =Y13 -> 0.013103139 | AA13: =IF(AA12>AB13,AA12,AB13) -> 0.010297601 | AB13: =IF(AB12>AC13,AB12,AC13) -> 0.010297601 | AC13: =AD13 -> 0.010297601 | AD13: =$E$3*F45*0.000947817 -> 0.010297601 | AE13: =AD13 -> 0.010297601 | AF13: =AE13 -> 0.010297601 | AG13: =IF(AG12>AH13,AG12,AH13) -> 0.42017954 | AH13: =IF(AH12>AI13,AH12,AI13) -> 0.42017954 | AI13: =$E$3*$H$72*0.453592*947817/1000000 -> 0.24538371 | AJ13: =$E$3*$I$72*0.453592*947817/1000000 -> 0.065327525 | AK13: =(AJ13+AL13)/2 -> 0.062762308 | AL13: =$E$3*$J$72*0.453592*947817/1000000 -> 0.060197091 | AM13: =IF(AM12>AN13,AM12,AN13) -> 0.0010494919 | AN13: =IF(AN12>AO13,AN12,AO13) -> 0.00099538703 | AO13: =$E$3*$H$73*0.453592*947817/1000000 -> 0.00099538703 | AP13: =$E$3*$I$73*0.453592*947817/1000000 -> 0.00099538703 | AQ13: =(AP13+AR13)/2 -> 0.00099538703 | AR13: =$E$3*$J$73*0.453592*947817/1000000 -> 0.00099538703 | AS13: =IF(AS12>AT13,AS12,AT13) -> 0.0014835429 | AT13: =IF(AT12>AU13,AT12,AU13) -> 0.0014835429 | AU13: =$E$3*$H$74*0.453592*947817/1000000 -> 0.0014835429 | AV13: =$E$3*$I$74*0.453592*947817/1000000 -> 0.0014835429 | AW13: =(AV13+AX13)/2 -> 0.0014835429 | AX13: =$E$3*$J$74*0.453592*947817/1000000 -> 0.0014835429 | AY13: =AY12 -> #REF! | AZ13: =AZ12 -> #REF! | BA13: =$E$3*$H$75*0.453592*947817/1000000 -> 9.0035704e-05 | BB13: =$E$3*$I$75*0.453592*947817/1000000 -> 0.0006200924 | BC13: =(BB13+BD13)/2 -> 0.00058627808 | BD13: =$E$3*$J$75*0.453592*947817/1000000 -> 0.00055246376 | BE13: =IF(BE12>BF13,BE12,BF13) -> 87.564578 | BF13: =IF(BF12>BG13,BF12,BG13) -> 87.564578 | BG13: =$E$3*$H$76*0.453592*947817/1000000 -> 87.564578 | BH13: =$E$3*$I$76*0.453592*947817/1000000 -> 87.564578 | BI13: =(BH13+BJ13)/2 -> 87.564578 | BJ13: =$E$3*$J$76*0.453592*947817/1000000 -> 87.564578
B14: Natural gas boiler | C14: =IF($E$3*$C79*0.000947817>D14,$E$3*$C79*0.000947817,D14) -> 0.0022471879 | D14: =IF($E$3*$D79*0.000947817>E14,$E$3*$D79*0.000947817,E14) -> 0.0022471879 | E14: =$E$3*$H$79*0.453592*947817/1000000 -> 0.0022107225 | F14: =$E$3*$I$79*0.453592*947817/1000000 -> 0.0022107225 | G14: =(F14+H14)/2 -> 0.0022107225 | H14: =$E$3*$J$79*0.453592*947817/1000000 -> 0.0022107225 | I14: =IF($E$3*$C80*0.000947817>J14,$E$3*$C80*0.000947817,J14) -> 0.033841375 | J14: =IF($E$3*$D80*0.000947817>K14,$E$3*$D80*0.000947817,K14) -> 0.033841375 | K14: =$E$3*$H$80*0.453592*947817/1000000 -> 0.032766927 | L14: =$E$3*$I$80*0.453592*947817/1000000 -> 0.032766927 | M14: =(L14+N14)/2 -> 0.032766927 | N14: =$E$3*$J$80*0.453592*947817/1000000 -> 0.032766927 | O14: =IF($E$3*$C81*0.000947817>P14,$E$3*$C81*0.000947817,P14) -> 0.069342292 | P14: =IF($E$3*$D81*0.000947817>Q14,$E$3*$D81*0.000947817,Q14) -> 0.069342292 | Q14: =$E$3*$H$81*0.453592*947817/1000000 -> 0.067305647 | R14: =$E$3*$I$81*0.453592*947817/1000000 -> 0.060143818 | S14: =(R14+T14)/2 -> 0.053694517 | T14: =$E$3*$J$81*0.453592*947817/1000000 -> 0.047245217 | U14: =IF($E$3*$C82*0.000947817>V14,$E$3*$C82*0.000947817,V14) -> 0.0029322011 | V14: =IF($E$3*$D82*0.000947817>W14,$E$3*$D82*0.000947817,W14) -> 0.0029322011 | W14: =$E$3*$H$82*0.453592*947817/1000000 -> 0.002836156 | X14: =$E$3*$I$82*0.453592*947817/1000000 -> 0.002836156 | Y14: =(X14+Z14)/2 -> 0.002836156 | Z14: =$E$3*$J$82*0.453592*947817/1000000 -> 0.002836156 | AA14: =IF($E$3*$C83*0.000947817>AB14,$E$3*$C83*0.000947817,AB14) -> 0.0029322011 | AB14: =IF($E$3*$D83*0.000947817>AC14,$E$3*$D83*0.000947817,AC14) -> 0.0029322011 | AC14: =$E$3*$H$83*0.453592*947817/1000000 -> 0.002836156 | AD14: =$E$3*$I$83*0.453592*947817/1000000 -> 0.002836156 | AE14: =(AD14+AF14)/2 -> 0.002836156 | AF14: =$E$3*$J$83*0.453592*947817/1000000 -> 0.002836156 | AG14: =IF($E$3*$C84*0.000947817>AH14,$E$3*$C84*0.000947817,AH14) -> 0.00038666625 | AH14: =IF($E$3*$D84*0.000947817>AI14,$E$3*$D84*0.000947817,AI14) -> 0.00038666625 | AI14: =$E$3*$H$84*0.453592*947817/1000000 -> 0.00036095069 | AJ14: =$E$3*$I$84*0.453592*947817/1000000 -> 0.00036095069 | AK14: =(AJ14+AL14)/2 -> 0.00036095069 | AL14: =$E$3*$J$84*0.453592*947817/1000000 -> 0.00036095069 | AM14: =IF($E$3*$C85*0.000947817>AN14,$E$3*$C85*0.000947817,AN14) -> 0.0010072856 | AN14: =IF($E$3*$D85*0.000947817>AO14,$E$3*$D85*0.000947817,AO14) -> 0.0010072856 | AO14: =$E$3*$H$85*0.453592*947817/1000000 -> 0.0010072856 | AP14: =$E$3*$I$85*0.453592*947817/1000000 -> 0.0010072856 | AQ14: =(AP14+AR14)/2 -> 0.0010072856 | AR14: =$E$3*$J$85*0.453592*947817/1000000 -> 0.0010072856 | AS14: =IF($E$3*$C86*0.000947817>AT14,$E$3*$C86*0.000947817,AT14) -> 0.00095040196 | AT14: =IF($E$3*$D86*0.000947817>AU14,$E$3*$D86*0.000947817,AU14) -> 0.00011495757 | AU14: =$E$3*$H$86*0.453592*947817/1000000 -> 0.00011495757 | AV14: =$E$3*$I$86*0.453592*947817/1000000 -> 0.00011495757 | AW14: =(AV14+AX14)/2 -> 0.00011495757 | AX14: =$E$3*$J$86*0.453592*947817/1000000 -> 0.00011495757 | AY14: =$E$3*AA14*#REF! -> #REF! | AZ14: =$E$3*AB14*#REF! -> #REF! | BA14: =$E$3*$H$87*0.453592*947817/1000000 -> 0.0010777393 | BB14: =$E$3*$I$87*0.453592*947817/1000000 -> 0.0010777393 | BC14: =(BB14+BD14)/2 -> 0.0010777393 | BD14: =$E$3*$J$87*0.453592*947817/1000000 -> 0.0010777393 | BE14: =IF($E$3*$C88*0.000947817>BF14,$E$3*$C88*0.000947817,BF14) -> 50.74211 | BF14: =IF($E$3*$D88*0.000947817>BG14,$E$3*$D88*0.000947817,BG14) -> 50.74211 | BG14: =$E$3*$H$88*0.453592*947817/1000000 -> 50.74211 | BH14: =$E$3*$I$88*0.453592*947817/1000000 -> 50.74211 | BI14: =(BH14+BJ14)/2 -> 50.74211 | BJ14: =$E$3*$J$88*0.453592*947817/1000000 -> 50.74211 | BK14: =$E$3*AA14*#REF! -> #REF! | BL14: =$E$3*AB14*#REF! -> #REF! | BM14: =$E$3*AC14*#REF! -> #REF! | BO14: =(BN14+BP14)/2 -> #REF! | BP14: =$E$3*AF14*#REF! -> #REF!
B15: Natural gas turbine (large) | C15: =IF($E$3*$C91*0.000947817>D15,$E$3*$C91*0.000947817,D15) -> 0.0035896415 | D15: =IF($E$3*$D91*0.000947817>E15,$E$3*$D91*0.000947817,E15) -> 0.0011356571 | E15: =$E$3*$H$91*0.453592*947817/1000000 -> 0.00096598296 | F15: =$E$3*$I$91*0.453592*947817/1000000 -> 0.00096598296 | G15: =(F15+H15)/2 -> 0.00096598296 | H15: =$E$3*$J$91*0.453592*947817/1000000 -> 0.00096598296 | I15: =IF($E$3*$C92*0.000947817>J15,$E$3*$C92*0.000947817,J15) -> 0.043063635 | J15: =IF($E$3*$D92*0.000947817>K15,$E$3*$D92*0.000947817,K15) -> 0.043063635 | K15: =$E$3*$H$92*0.453592*947817/1000000 -> 0.018329644 | L15: =$E$3*$I$92*0.453592*947817/1000000 -> 0.018329644 | M15: =(L15+N15)/2 -> 0.018329644 | N15: =$E$3*$J$92*0.453592*947817/1000000 -> 0.018329644 | O15: =IF($E$3*$C93*0.000947817>P15,$E$3*$C93*0.000947817,P15) -> 0.039193956 | P15: =IF($E$3*$D93*0.000947817>Q15,$E$3*$D93*0.000947817,Q15) -> 0.031011323 | Q15: =$E$3*$H$93*0.453592*947817/1000000 -> 0.031011323 | R15: =$E$3*$I$93*0.453592*947817/1000000 -> 0.031011323 | S15: =(R15+T15)/2 -> 0.031011323 | T15: =$E$3*$J$93*0.453592*947817/1000000 -> 0.031011323 | U15: =IF($E$3*$C94*0.000947817>V15,$E$3*$C94*0.000947817,V15) -> 0.0032432574 | V15: =IF($E$3*$D94*0.000947817>W15,$E$3*$D94*0.000947817,W15) -> 0.0032432574 | W15: =$E$3*$H$94*0.453592*947817/1000000 -> 0.0030358202 | X15: =$E$3*$I$94*0.453592*947817/1000000 -> 0.0030358202 | Y15: =(X15+Z15)/2 -> 0.0030358202 | Z15: =$E$3*$J$94*0.453592*947817/1000000 -> 0.0030358202 | AA15: =IF($E$3*$C95*0.000947817>AB15,$E$3*$C95*0.000947817,AB15) -> 0.0032432574 | AB15: =IF($E$3*$D95*0.000947817>AC15,$E$3*$D95*0.000947817,AC15) -> 0.0032432574 | AC15: =$E$3*$H$95*0.453592*947817/1000000 -> 0.0030358202 | AD15: =$E$3*$I$95*0.453592*947817/1000000 -> 0.0030358202 | AE15: =(AD15+AF15)/2 -> 0.0030358202 | AF15: =$E$3*$J$95*0.453592*947817/1000000 -> 0.0030358202 | AG15: =IF($E$3*$C96*0.000947817>AH15,$E$3*$C96*0.000947817,AH15) -> 0.00057269621 | AH15: =IF($E$3*$D96*0.000947817>AI15,$E$3*$D96*0.000947817,AI15) -> 0.00057269621 | AI15: =$E$3*$H$96*0.453592*947817/1000000 -> 0.00057269621 | AJ15: =$E$3*$I$96*0.453592*947817/1000000 -> 0.00057269621 | AK15: =(AJ15+AL15)/2 -> 0.00057269621 | AL15: =$E$3*$J$96*0.453592*947817/1000000 -> 0.00057269621 | AM15: =IF($E$3*$C97*0.000947817>AN15,$E$3*$C97*0.000947817,AN15) -> 0.0036706367 | AN15: =IF($E$3*$D97*0.000947817>AO15,$E$3*$D97*0.000947817,AO15) -> 0.0036706367 | AO15: =$E$3*$H$97*0.453592*947817/1000000 -> 0.0010932488 | AP15: =$E$3*$I$97*0.453592*947817/1000000 -> 0.0010932488 | AQ15: =(AP15+AR15)/2 -> 0.0010932488 | AR15: =$E$3*$J$97*0.453592*947817/1000000 -> 0.0010932488 | AS15: =IF($E$3*$C98*0.000947817>AT15,$E$3*$C98*0.000947817,AT15) -> 0.0012924777 | AT15: =IF($E$3*$D98*0.000947817>AU15,$E$3*$D98*0.000947817,AU15) -> 0.0012924777 | AU15: =$E$3*$H$98*0.453592*947817/1000000 -> 0.00011842792 | AV15: =$E$3*$I$98*0.453592*947817/1000000 -> 0.00011842792 | AW15: =(AV15+AX15)/2 -> 0.00011842792 | AX15: =$E$3*$J$98*0.453592*947817/1000000 -> 0.00011842792 | AY15: =$E$3*AA15*#REF! -> #REF! | AZ15: =$E$3*AB15*#REF! -> #REF! | BA15: =$E$3*$H$99*0.453592*947817/1000000 -> 0.0019269206 | BB15: =$E$3*$I$99*0.453592*947817/1000000 -> 0.0019269206 | BC15: =(BB15+BD15)/2 -> 0.0019269206 | BD15: =$E$3*$J$99*0.453592*947817/1000000 -> 0.0019269206 | BE15: =IF($E$3*$C100*0.000947817>BF15,$E$3*$C100*0.000947817,BF15) -> 55.024794 | BF15: =IF($E$3*$D100*0.000947817>BG15,$E$3*$D100*0.000947817,BG15) -> 55.024794 | BG15: =$E$3*$H$100*0.453592*947817/1000000 -> 55.024794 | BH15: =$E$3*$I$100*0.453592*947817/1000000 -> 55.024794 | BI15: =(BH15+BJ15)/2 -> 55.024794 | BJ15: =$E$3*$J$100*0.453592*947817/1000000 -> 55.024794 | BK15: =$E$3*AA15*#REF! -> #REF! | BL15: =$E$3*AB15*#REF! -> #REF! | BM15: =$E$3*AC15*#REF! -> #REF! | BO15: =(BN15+BP15)/2 -> #REF! | BP15: =$E$3*AF15*#REF! -> #REF!
B16: Natural gas combined cycle | C16: =IF($E$3*$C103*0.000947817>D16,$E$3*$C103*0.000947817,D16) -> 0.003848137 | D16: =IF($E$3*$D103*0.000947817>E16,$E$3*$D103*0.000947817,E16) -> 0.00024058119 | E16: =$E$3*$H$103*0.453592*947817/1000000 -> 0.00024058119 | F16: =$E$3*$I$103*0.453592*947817/1000000 -> 0.00024058119 | G16: =(F16+H16)/2 -> 0.00024058119 | H16: =$E$3*$J$103*0.453592*947817/1000000 -> 0.00024058119 | I16: =IF($E$3*$C104*0.000947817>J16,$E$3*$C104*0.000947817,J16) -> 0.026774107 | J16: =IF($E$3*$D104*0.000947817>K16,$E$3*$D104*0.000947817,K16) -> 0.018329644 | K16: =$E$3*$H$104*0.453592*947817/1000000 -> 0.018329644 | L16: =$E$3*$I$104*0.453592*947817/1000000 -> 0.018329644 | M16: =(L16+N16)/2 -> 0.018329644 | N16: =$E$3*$J$104*0.453592*947817/1000000 -> 0.018329644 | O16: =IF($E$3*$C105*0.000947817>P16,$E$3*$C105*0.000947817,P16) -> 0.014261199 | P16: =IF($E$3*$D105*0.000947817>Q16,$E$3*$D105*0.000947817,Q16) -> 0.0089085798 | Q16: =$E$3*$H$105*0.453592*947817/1000000 -> 0.0089085798 | R16: =$E$3*$I$105*0.453592*947817/1000000 -> 0.0089085798 | S16: =(R16+T16)/2 -> 0.0089085798 | T16: =$E$3*$J$105*0.453592*947817/1000000 -> 0.0089085798 | U16: =IF($E$3*$C106*0.000947817>V16,$E$3*$C106*0.000947817,V16) -> 0.0019740443 | V16: =IF($E$3*$D106*0.000947817>W16,$E$3*$D106*0.000947817,W16) -> 0.00011746023 | W16: =$E$3*$H$106*0.453592*947817/1000000 -> 0.00011746023 | X16: =$E$3*$I$106*0.453592*947817/1000000 -> 0.00011746023 | Y16: =(X16+Z16)/2 -> 0.00011746023 | Z16: =$E$3*$J$106*0.453592*947817/1000000 -> 0.00011746023 | AA16: =IF($E$3*$C107*0.000947817>AB16,$E$3*$C107*0.000947817,AB16) -> 0.0019740443 | AB16: =IF($E$3*$D107*0.000947817>AC16,$E$3*$D107*0.000947817,AC16) -> 0.00011746023 | AC16: =$E$3*$H$107*0.453592*947817/1000000 -> 0.00011746023 | AD16: =$E$3*$I$107*0.453592*947817/1000000 -> 0.00011746023 | AE16: =(AD16+AF16)/2 -> 0.00011746023 | AF16: =$E$3*$J$107*0.453592*947817/1000000 -> 0.00011746023 | AG16: =IF($E$3*$C108*0.000947817>AH16,$E$3*$C108*0.000947817,AH16) -> 0.00028728224 | AH16: =IF($E$3*$D108*0.000947817>AI16,$E$3*$D108*0.000947817,AI16) -> 0.00028728224 | AI16: =$E$3*$H$108*0.453592*947817/1000000 -> 0.00028728224 | AJ16: =$E$3*$I$108*0.453592*947817/1000000 -> 0.00028728224 | AK16: =(AJ16+AL16)/2 -> 0.00028728224 | AL16: =$E$3*$J$108*0.453592*947817/1000000 -> 0.00028728224 | AM16: =IF($E$3*$C109*0.000947817>AN16,$E$3*$C109*0.000947817,AN16) -> 0.0036706367 | AN16: =IF($E$3*$D109*0.000947817>AO16,$E$3*$D109*0.000947817,AO16) -> 0.0011222405 | AO16: =$E$3*$H$109*0.453592*947817/1000000 -> 0.0011222405 | AP16: =$E$3*$I$109*0.453592*947817/1000000 -> 0.0011222405 | AQ16: =(AP16+AR16)/2 -> 0.0011222405 | AR16: =$E$3*$J$109*0.453592*947817/1000000 -> 0.0011222405 | AS16: =IF($E$3*$C110*0.000947817>AT16,$E$3*$C110*0.000947817,AT16) -> 0.0012924777 | AT16: =IF($E$3*$D110*0.000947817>AU16,$E$3*$D110*0.000947817,AU16) -> 0.0011321468 | AU16: =$E$3*$H$110*0.453592*947817/1000000 -> 0.0011321468 | AV16: =$E$3*$I$110*0.453592*947817/1000000 -> 0.0011321468 | AW16: =(AV16+AX16)/2 -> 0.0011321468 | AX16: =$E$3*$J$110*0.453592*947817/1000000 -> 0.0011321468 | AY16: =$E$3*AA16*#REF! -> #REF! | AZ16: =$E$3*AB16*#REF! -> #REF! | BA16: =$E$3*$H$111*0.453592*947817/1000000 -> 0.00081794379 | BB16: =$E$3*$I$111*0.453592*947817/1000000 -> 0.00081794379 | BC16: =(BB16+BD16)/2 -> 0.00081794379 | BD16: =$E$3*$J$111*0.453592*947817/1000000 -> 0.00081794379 | BE16: =IF($E$3*$C112*0.000947817>BF16,$E$3*$C112*0.000947817,BF16) -> 57.838547 | BF16: =IF($E$3*$D112*0.000947817>BG16,$E$3*$D112*0.000947817,BG16) -> 57.838547 | BG16: =$E$3*$H$112*0.453592*947817/1000000 -> 57.838547 | BH16: =$E$3*$I$112*0.453592*947817/1000000 -> 57.838547 | BI16: =(BH16+BJ16)/2 -> 57.838547 | BJ16: =$E$3*$J$112*0.453592*947817/1000000 -> 57.838547 | BK16: =$E$3*AA16*#REF! -> #REF! | BL16: =$E$3*AB16*#REF! -> #REF! | BM16: =$E$3*AC16*#REF! -> #REF! | BO16: =(BN16+BP16)/2 -> #REF! | BP16: =$E$3*AF16*#REF! -> #REF!
B17: Residual fuel oil boiler | C17: =IF($E$3*$C115*0.000947817>D17,$E$3*$C115*0.000947817,D17) -> 0.0021368965 | D17: =IF($E$3*$D115*0.000947817>E17,$E$3*$D115*0.000947817,E17) -> 0.0021205251 | E17: =$E$3*$H$115*0.453592*947817/1000000 -> 0.0021119109 | F17: =$E$3*$I$115*0.453592*947817/1000000 -> 0.0021119109 | G17: =(F17+H17)/2 -> 0.0021119109 | H17: =$E$3*$J$115*0.453592*947817/1000000 -> 0.0021119109 | I17: =IF($E$3*$C116*0.000947817>J17,$E$3*$C116*0.000947817,J17) -> 0.021135641 | J17: =IF($E$3*$D116*0.000947817>K17,$E$3*$D116*0.000947817,K17) -> 0.021135641 | K17: =$E$3*$H$116*0.453592*947817/1000000 -> 0.021135641 | L17: =$E$3*$I$116*0.453592*947817/1000000 -> 0.021135641 | M17: =(L17+N17)/2 -> 0.021135641 | N17: =$E$3*$J$116*0.453592*947817/1000000 -> 0.021135641 | O17: =IF($E$3*$C117*0.000947817>P17,$E$3*$C117*0.000947817,P17) -> 0.14211654 | P17: =IF($E$3*$D117*0.000947817>Q17,$E$3*$D117*0.000947817,Q17) -> 0.11206644 | Q17: =$E$3*$H$117*0.453592*947817/1000000 -> 0.11183705 | R17: =$E$3*$I$117*0.453592*947817/1000000 -> 0.097201305 | S17: =(R17+T17)/2 -> 0.087037593 | T17: =$E$3*$J$117*0.453592*947817/1000000 -> 0.076873882 | U17: =IF($E$3*$C118*0.000947817>V17,$E$3*$C118*0.000947817,V17) -> 0.011579739 | V17: =IF($E$3*$D118*0.000947817>W17,$E$3*$D118*0.000947817,W17) -> 0.011579739 | W17: =$E$3*$H$118*0.453592*947817/1000000 -> 0.011554757 | X17: =$E$3*$I$118*0.453592*947817/1000000 -> 0.010176226 | Y17: =(X17+Z17)/2 -> 0.0092189135 | Z17: =$E$3*$J$118*0.453592*947817/1000000 -> 0.0082616008 | AA17: =IF($E$3*$C119*0.000947817>AB17,$E$3*$C119*0.000947817,AB17) -> 0.0095808845 | AB17: =IF($E$3*$D119*0.000947817>AC17,$E$3*$D119*0.000947817,AC17) -> 0.0095808845 | AC17: =$E$3*$H$119*0.453592*947817/1000000 -> 0.0095808845 | AD17: =$E$3*$I$119*0.453592*947817/1000000 -> 0.00850704 | AE17: =(AD17+AF17)/2 -> 0.0077613146 | AF17: =$E$3*$J$119*0.453592*947817/1000000 -> 0.0070155893 | AG17: =IF($E$3*$C120*0.000947817>AH17,$E$3*$C120*0.000947817,AH17) -> 0.46882475 | AH17: =IF($E$3*$D120*0.000947817>AI17,$E$3*$D120*0.000947817,AI17) -> 0.27325909 | AI17: =$E$3*$H$120*0.453592*947817/1000000 -> 0.27269688 | AJ17: =$E$3*$I$120*0.453592*947817/1000000 -> 0.23228764 | AK17: =(AJ17+AL17)/2 -> 0.20422567 | AL17: =$E$3*$J$120*0.453592*947817/1000000 -> 0.17616369 | AM17: =IF($E$3*$C121*0.000947817>AN17,$E$3*$C121*0.000947817,AN17) -> 0.002534118 | AN17: =IF($E$3*$D121*0.000947817>AO17,$E$3*$D121*0.000947817,AO17) -> 0.002534118 | AO17: =$E$3*$H$121*0.453592*947817/1000000 -> 0.0025276805 | AP17: =$E$3*$I$121*0.453592*947817/1000000 -> 0.0025276805 | AQ17: =(AP17+AR17)/2 -> 0.0025276805 | AR17: =$E$3*$J$121*0.453592*947817/1000000 -> 0.0025276805 | AS17: =IF($E$3*$C122*0.000947817>AT17,$E$3*$C122*0.000947817,AT17) -> 0.00048868669 | AT17: =IF($E$3*$D122*0.000947817>AU17,$E$3*$D122*0.000947817,AU17) -> 0.00048868669 | AU17: =$E$3*$H$122*0.453592*947817/1000000 -> 0.00048768198 | AV17: =$E$3*$I$122*0.453592*947817/1000000 -> 0.00048768198 | AW17: =(AV17+AX17)/2 -> 0.00048768198 | AX17: =$E$3*$J$122*0.453592*947817/1000000 -> 0.00048768198 | AY17: =$E$3*AA17*#REF! -> #REF! | AZ17: =$E$3*AB17*#REF! -> #REF! | BA17: =$E$3*$H$123*0.453592*947817/1000000 -> 0.00095808845 | BB17: =$E$3*$I$123*0.453592*947817/1000000 -> 0.00095808845 | BC17: =(BB17+BD17)/2 -> 0.00095808845 | BD17: =$E$3*$J$123*0.453592*947817/1000000 -> 0.00095808845 | BE17: =IF($E$3*$C124*0.000947817>BF17,$E$3*$C124*0.000947817,BF17) -> 65.390714 | BF17: =IF($E$3*$D124*0.000947817>BG17,$E$3*$D124*0.000947817,BG17) -> 65.390714 | BG17: =$E$3*$H$124*0.453592*947817/1000000 -> 65.390714 | BH17: =$E$3*$I$124*0.453592*947817/1000000 -> 65.390714 | BI17: =(BH17+BJ17)/2 -> 65.390714 | BJ17: =$E$3*$J$124*0.453592*947817/1000000 -> 65.390714 | BK17: =$E$3*AA17*#REF! -> #REF! | BL17: =$E$3*AB17*#REF! -> #REF! | BM17: =$E$3*AC17*#REF! -> #REF! | BO17: =(BN17+BP17)/2 -> #REF! | BP17: =$E$3*AF17*#REF! -> #REF!
B18: Diesel turbines | C18: =IF($E$3*$C139*0.000947817>D18,$E$3*$C139*0.000947817,D18) -> 0.0011503052 | D18: =IF($E$3*$D139*0.000947817>E18,$E$3*$D139*0.000947817,E18) -> 0.0011503052 | E18: =$E$3*$H$139*0.453592*947817/1000000 -> 0.00020956971 | F18: =$E$3*$I$139*0.453592*947817/1000000 -> 0.00020956971 | G18: =(F18+H18)/2 -> 0.00020956971 | H18: =$E$3*$J$139*0.453592*947817/1000000 -> 0.00020956971 | I18: =IF($E$3*$C140*0.000947817>J18,$E$3*$C140*0.000947817,J18) -> 0.0075084339 | J18: =IF($E$3*$D140*0.000947817>K18,$E$3*$D140*0.000947817,K18) -> 0.0075084339 | K18: =$E$3*$H$140*0.453592*947817/1000000 -> 0.0016852898 | L18: =$E$3*$I$140*0.453592*947817/1000000 -> 0.0016852898 | M18: =(L18+N18)/2 -> 0.0016852898 | N18: =$E$3*$J$140*0.453592*947817/1000000 -> 0.0016852898 | O18: =IF($E$3*$C141*0.000947817>P18,$E$3*$C141*0.000947817,P18) -> 0.21819224 | P18: =IF($E$3*$D141*0.000947817>Q18,$E$3*$D141*0.000947817,Q18) -> 0.21819224 | Q18: =$E$3*$H$141*0.453592*947817/1000000 -> 0.21819224 | R18: =$E$3*$I$141*0.453592*947817/1000000 -> 0.21819224 | S18: =(R18+T18)/2 -> 0.21819224 | T18: =$E$3*$J$141*0.453592*947817/1000000 -> 0.21819224 | U18: =IF($E$3*$C142*0.000947817>V18,$E$3*$C142*0.000947817,V18) -> 0.015380988 | V18: =IF($E$3*$D142*0.000947817>W18,$E$3*$D142*0.000947817,W18) -> 0.015380988 | W18: =$E$3*$H$142*0.453592*947817/1000000 -> 0.015380988 | X18: =$E$3*$I$142*0.453592*947817/1000000 -> 0.015380988 | Y18: =(X18+Z18)/2 -> 0.015380988 | Z18: =$E$3*$J$142*0.453592*947817/1000000 -> 0.015380988 | AA18: =IF($E$3*$C143*0.000947817>AB18,$E$3*$C143*0.000947817,AB18) -> 0.011201474 | AB18: =IF($E$3*$D143*0.000947817>AC18,$E$3*$D143*0.000947817,AC18) -> 0.011201474 | AC18: =$E$3*$H$143*0.453592*947817/1000000 -> 0.0054616962 | AD18: =$E$3*$I$143*0.453592*947817/1000000 -> 0.0054616962 | AE18: =(AD18+AF18)/2 -> 0.0054616962 | AF18: =$E$3*$J$143*0.453592*947817/1000000 -> 0.0054616962 | AG18: =IF($E$3*$C144*0.000947817>AH18,$E$3*$C144*0.000947817,AH18) -> 0.047492365 | AH18: =IF($E$3*$D144*0.000947817>AI18,$E$3*$D144*0.000947817,AI18) -> 0.047492365 | AI18: =$E$3*$H$144*0.453592*947817/1000000 -> 0.047492365 | AJ18: =$E$3*$I$144*0.453592*947817/1000000 -> 0.03787554 | AK18: =(AJ18+AL18)/2 -> 0.033067128 | AL18: =$E$3*$J$144*0.453592*947817/1000000 -> 0.028258715 | AM18: =IF($E$3*$C145*0.000947817>AN18,$E$3*$C145*0.000947817,AN18) -> 0.0029236563 | AN18: =IF($E$3*$D145*0.000947817>AO18,$E$3*$D145*0.000947817,AO18) -> 0.0029236563 | AO18: =$E$3*$H$145*0.453592*947817/1000000 -> 0.0029236563 | AP18: =$E$3*$I$145*0.453592*947817/1000000 -> 0.0029236563 | AQ18: =(AP18+AR18)/2 -> 0.0029236563 | AR18: =$E$3*$J$145*0.453592*947817/1000000 -> 0.0029236563 | AS18: =IF($E$3*$C146*0.000947817>AT18,$E$3*$C146*0.000947817,AT18) -> 0.00058663644 | AT18: =IF($E$3*$D146*0.000947817>AU18,$E$3*$D146*0.000947817,AU18) -> 0.00058663644 | AU18: =$E$3*$H$146*0.453592*947817/1000000 -> 0.00058663644 | AV18: =$E$3*$I$146*0.453592*947817/1000000 -> 0.00058663644 | AW18: =(AV18+AX18)/2 -> 0.00058663644 | AX18: =$E$3*$J$146*0.453592*947817/1000000 -> 0.00058663644 | AY18: =$E$3*AA18*#REF! -> #REF! | AZ18: =$E$3*AB18*#REF! -> #REF! | BA18: =$E$3*$H$147*0.453592*947817/1000000 -> 0.00084630075 | BB18: =$E$3*$I$147*0.453592*947817/1000000 -> 0.00084630075 | BC18: =(BB18+BD18)/2 -> 0.00084630075 | BD18: =$E$3*$J$147*0.453592*947817/1000000 -> 0.00084630075 | BE18: =IF($E$3*$C148*0.000947817>BF18,$E$3*$C148*0.000947817,BF18) -> 69.007179 | BF18: =IF($E$3*$D148*0.000947817>BG18,$E$3*$D148*0.000947817,BG18) -> 69.007179 | BG18: =$E$3*$H$148*0.453592*947817/1000000 -> 69.007179 | BH18: =$E$3*$I$148*0.453592*947817/1000000 -> 69.007179 | BI18: =(BH18+BJ18)/2 -> 69.007179 | BJ18: =$E$3*$J$148*0.453592*947817/1000000 -> 69.007179 | BK18: =$E$3*AA18*#REF! -> #REF! | BL18: =$E$3*AB18*#REF! -> #REF! | BM18: =$E$3*AC18*#REF! -> #REF! | BO18: =(BN18+BP18)/2 -> #REF! | BP18: =$E$3*AF18*#REF! -> #REF!
B19: Diesel engines | C19: =IF($E$3*$C127*0.000947817>D19,$E$3*$C127*0.000947817,D19) -> 0.08493302 | D19: =IF($E$3*$D127*0.000947817>E19,$E$3*$D127*0.000947817,E19) -> 0.060694754 | E19: =$E$3*$H$127*0.453592*947817/1000000 -> 0.0017469751 | F19: =$E$3*$I$127*0.453592*947817/1000000 -> 0.0017469751 | G19: =(F19+H19)/2 -> 0.0017469751 | H19: =$E$3*$J$127*0.453592*947817/1000000 -> 0.0017469751 | I19: =IF($E$3*$C128*0.000947817>J19,$E$3*$C128*0.000947817,J19) -> 0.56611184 | J19: =IF($E$3*$D128*0.000947817>K19,$E$3*$D128*0.000947817,K19) -> 0.56611184 | K19: =$E$3*$H$128*0.453592*947817/1000000 -> 0.56611184 | L19: =$E$3*$I$128*0.453592*947817/1000000 -> 0.45339608 | M19: =(L19+N19)/2 -> 0.4203359 | N19: =$E$3*$J$128*0.453592*947817/1000000 -> 0.38727572 | O19: =IF($E$3*$C129*0.000947817>P19,$E$3*$C129*0.000947817,P19) -> 1.7896483 | P19: =IF($E$3*$D129*0.000947817>Q19,$E$3*$D129*0.000947817,Q19) -> 1.7896483 | Q19: =$E$3*$H$129*0.453592*947817/1000000 -> 1.7896483 | R19: =$E$3*$I$129*0.453592*947817/1000000 -> 0.23082847 | S19: =(R19+T19)/2 -> 0.1436959 | T19: =$E$3*$J$129*0.453592*947817/1000000 -> 0.056563329 | U19: =IF($E$3*$C130*0.000947817>V19,$E$3*$C130*0.000947817,V19) -> 0.077178153 | V19: =IF($E$3*$D130*0.000947817>W19,$E$3*$D130*0.000947817,W19) -> 0.053303505 | W19: =$E$3*$H$130*0.453592*947817/1000000 -> 0.043842878 | X19: =$E$3*$I$130*0.453592*947817/1000000 -> 0.016210552 | Y19: =(X19+Z19)/2 -> 0.0089379952 | Z19: =$E$3*$J$130*0.453592*947817/1000000 -> 0.0016654385 | AA19: =IF($E$3*$C131*0.000947817>AB19,$E$3*$C131*0.000947817,AB19) -> 0.069460338 | AB19: =IF($E$3*$D131*0.000947817>AC19,$E$3*$D131*0.000947817,AC19) -> 0.047973327 | AC19: =$E$3*$H$131*0.453592*947817/1000000 -> 0.043355719 | AD19: =$E$3*$I$131*0.453592*947817/1000000 -> 0.016004569 | AE19: =(AD19+AF19)/2 -> 0.008806463 | AF19: =$E$3*$J$131*0.453592*947817/1000000 -> 0.0016083569 | AG19: =IF($E$3*$C132*0.000947817>AH19,$E$3*$C132*0.000947817,AH19) -> 0.092496387 | AH19: =IF($E$3*$D132*0.000947817>AI19,$E$3*$D132*0.000947817,AI19) -> 0.092496387 | AI19: =$E$3*$H$132*0.453592*947817/1000000 -> 0.092496387 | AJ19: =$E$3*$I$132*0.453592*947817/1000000 -> 0.00063167164 | AK19: =(AJ19+AL19)/2 -> 0.00063167164 | AL19: =$E$3*$J$132*0.453592*947817/1000000 -> 0.00063167164 | AM19: =IF($E$3*$C133*0.000947817>AN19,$E$3*$C133*0.000947817,AN19) -> 0.0036370484 | AN19: =IF($E$3*$D133*0.000947817>AO19,$E$3*$D133*0.000947817,AO19) -> 0.0036370484 | AO19: =$E$3*$H$133*0.453592*947817/1000000 -> 0.0036370484 | AP19: =$E$3*$I$133*0.453592*947817/1000000 -> 0.0036370484 | AQ19: =(AP19+AR19)/2 -> 0.0036370484 | AR19: =$E$3*$J$133*0.453592*947817/1000000 -> 0.0036370484 | AS19: =IF($E$3*$C135*0.000947817>AT19,$E$3*$C135*0.000947817,AT19) -> 0.05348446 | AT19: =IF($E$3*$D135*0.000947817>AU19,$E$3*$D135*0.000947817,AU19) -> 0.036939462 | AU19: =$E$3*$H$134*0.453592*947817/1000000 -> 0.00051707917 | AV19: =$E$3*$I$134*0.453592*947817/1000000 -> 0.00051707917 | AW19: =(AV19+AX19)/2 -> 0.00051707917 | AX19: =$E$3*$J$134*0.453592*947817/1000000 -> 0.00051707917 | AY19: =$E$3*AA19*#REF! -> #REF! | AZ19: =$E$3*AB19*#REF! -> #REF! | BA19: =$E$3*$H$135*0.453592*947817/1000000 -> 0.035855971 | BB19: =$E$3*$I$135*0.453592*947817/1000000 -> 0.012323518 | BC19: =(BB19+BD19)/2 -> 0.0067809765 | BD19: =$E$3*$J$135*0.453592*947817/1000000 -> 0.0012384348 | BE19: =IF($E$3*$C137*0.000947817>BF19,$E$3*$C137*0.000947817,BF19) -> 68.419537 | BF19: =IF($E$3*$D137*0.000947817>BG19,$E$3*$D137*0.000947817,BG19) -> 68.419537 | BG19: =$E$3*$H$136*0.453592*947817/1000000 -> 68.419537 | BH19: =$E$3*$I$136*0.453592*947817/1000000 -> 68.419537 | BI19: =(BH19+BJ19)/2 -> 68.419537 | BJ19: =$E$3*$J$136*0.453592*947817/1000000 -> 68.419537 | BK19: =$E$3*AA19*#REF! -> #REF! | BL19: =$E$3*AB19*#REF! -> #REF! | BM19: =$E$3*AC19*#REF! -> #REF! | BO19: =(BN19+BP19)/2 -> #REF! | BP19: =$E$3*AF19*#REF! -> #REF!
B20: Biomass IGCC | C20: =IF($E$3*$C151*0.000947817>D20,$E$3*$C151*0.000947817,D20) -> 0.0070707148 | D20: =IF($E$3*$D151*0.000947817>E20,$E$3*$D151*0.000947817,E20) -> 0.0070707148 | E20: =$E$3*$H$151*0.453592*947817/1000000 -> 0.0036738807 | F20: =$E$3*$I$151*0.453592*947817/1000000 -> 0.0036738807 | G20: =(F20+H20)/2 -> 0.0036738807 | H20: =$E$3*$J$151*0.453592*947817/1000000 -> 0.0036738807 | I20: =IF($E$3*$C152*0.000947817>J20,$E$3*$C152*0.000947817,J20) -> 0.089306568 | J20: =IF($E$3*$D152*0.000947817>K20,$E$3*$D152*0.000947817,K20) -> 0.089306568 | K20: =$E$3*$H$152*0.453592*947817/1000000 -> 0.089306568 | L20: =$E$3*$I$152*0.453592*947817/1000000 -> 0.089306568 | M20: =(L20+N20)/2 -> 0.089306568 | N20: =$E$3*$J$152*0.453592*947817/1000000 -> 0.089306568 | O20: =IF($E$3*$C153*0.000947817>P20,$E$3*$C153*0.000947817,P20) -> 0.058625756 | P20: =IF($E$3*$D153*0.000947817>Q20,$E$3*$D153*0.000947817,Q20) -> 0.058625756 | Q20: =$E$3*$H$153*0.453592*947817/1000000 -> 0.058625756 | R20: =$E$3*$I$153*0.453592*947817/1000000 -> 0.058625756 | S20: =(R20+T20)/2 -> 0.058625756 | T20: =$E$3*$J$153*0.453592*947817/1000000 -> 0.058625756 | U20: =IF($E$3*$C154*0.000947817>V20,$E$3*$C154*0.000947817,V20) -> 0.0077405539 | V20: =IF($E$3*$D154*0.000947817>W20,$E$3*$D154*0.000947817,W20) -> 0.0077405539 | W20: =$E$3*$H$154*0.453592*947817/1000000 -> 0.0077405539 | X20: =$E$3*$I$154*0.453592*947817/1000000 -> 0.0077405539 | Y20: =(X20+Z20)/2 -> 0.0077405539 | Z20: =$E$3*$J$154*0.453592*947817/1000000 -> 0.0077405539 | AA20: =IF($E$3*$C155*0.000947817>AB20,$E$3*$C155*0.000947817,AB20) -> 0.0077405539 | AB20: =IF($E$3*$D155*0.000947817>AC20,$E$3*$D155*0.000947817,AC20) -> 0.0077405539 | AC20: =$E$3*$H$155*0.453592*947817/1000000 -> 0.0077405539 | AD20: =$E$3*$I$155*0.453592*947817/1000000 -> 0.0077405539 | AE20: =(AD20+AF20)/2 -> 0.0077405539 | AF20: =$E$3*$J$155*0.453592*947817/1000000 -> 0.0077405539 | AG20: =IF($E$3*$C156*0.000947817>AH20,$E$3*$C156*0.000947817,AH20) -> 0.032525633 | AH20: =IF($E$3*$D156*0.000947817>AI20,$E$3*$D156*0.000947817,AI20) -> 0.032525633 | AI20: =$E$3*$H$156*0.453592*947817/1000000 -> 0.010064088 | AJ20: =$E$3*$I$156*0.453592*947817/1000000 -> 0.010064088 | AK20: =(AJ20+AL20)/2 -> 0.010064088 | AL20: =$E$3*$J$156*0.453592*947817/1000000 -> 0.010064088 | AM20: =IF($E$3*$C157*0.000947817>AN20,$E$3*$C157*0.000947817,AN20) -> 0.0045463105 | AN20: =IF($E$3*$D157*0.000947817>AO20,$E$3*$D157*0.000947817,AO20) -> 0.0045463105 | AO20: =$E$3*$H$157*0.453592*947817/1000000 -> 0.0045463105 | AP20: =$E$3*$I$157*0.453592*947817/1000000 -> 0.0045463105 | AQ20: =(AP20+AR20)/2 -> 0.0045463105 | AR20: =$E$3*$J$157*0.453592*947817/1000000 -> 0.0045463105 | AS20: =IF($E$3*$C158*0.000947817>AT20,$E$3*$C158*0.000947817,AT20) -> 0.00947817 | AT20: =IF($E$3*$D158*0.000947817>AU20,$E$3*$D158*0.000947817,AU20) -> 0.00947817 | AU20: =$E$3*$H$158*0.453592*947817/1000000 -> 9.0926209e-05 | AV20: =$E$3*$I$158*0.453592*947817/1000000 -> 9.0926209e-05 | AW20: =(AV20+AX20)/2 -> 9.0926209e-05 | AX20: =$E$3*$J$158*0.453592*947817/1000000 -> 9.0926209e-05 | AY20: =$E$3*AA20*#REF! -> #REF! | AZ20: =$E$3*AB20*#REF! -> #REF! | BA20: =$E$3*$H$159*0.453592*947817/1000000 -> 0.0032835973 | BB20: =$E$3*$I$159*0.453592*947817/1000000 -> 0.0032835973 | BC20: =(BB20+BD20)/2 -> 0.0032835973 | BD20: =$E$3*$J$159*0.453592*947817/1000000 -> 0.0032835973 | BE20: =0.15*BE11 -> 12.503569 | BF20: =0.15*BF11 -> 12.503569 | BG20: =0.15*BG11 -> 12.503569 | BH20: =0.15*BH11 -> 12.503569 | BI20: =0.15*BI11 -> 12.503569 | BJ20: =0.15*BJ11 -> 12.503569 | BK20: =$E$3*AA20*#REF! -> #REF! | BL20: =$E$3*AB20*#REF! -> #REF! | BM20: =$E$3*AC20*#REF! -> #REF! | BO20: =(BN20+BP20)/2 -> #REF! | BP20: =$E$3*AF20*#REF! -> #REF!
B21: Biomass STM | C21: =IF($E$3*$C163*0.000947817>D21,$E$3*$C163*0.000947817,D21) -> 0.0071017343 | D21: =IF($E$3*$D163*0.000947817>E21,$E$3*$D163*0.000947817,E21) -> 0.0071017343 | E21: =$E$3*$H$163*0.453592*947817/1000000 -> 0.0066442523 | F21: =$E$3*$I$163*0.453592*947817/1000000 -> 0.0066442523 | G21: =(F21+H21)/2 -> 0.0066442523 | H21: =$E$3*$J$163*0.453592*947817/1000000 -> 0.0066442523 | I21: =IF($E$3*$C164*0.000947817>J21,$E$3*$C164*0.000947817,J21) -> 0.24882781 | J21: =IF($E$3*$D164*0.000947817>K21,$E$3*$D164*0.000947817,K21) -> 0.24882781 | K21: =$E$3*$H$164*0.453592*947817/1000000 -> 0.23450302 | L21: =$E$3*$I$164*0.453592*947817/1000000 -> 0.22477196 | M21: =(L21+N21)/2 -> 0.21877361 | N21: =$E$3*$J$164*0.453592*947817/1000000 -> 0.21277527 | O21: =IF($E$3*$C165*0.000947817>P21,$E$3*$C165*0.000947817,P21) -> 0.26283827 | P21: =IF($E$3*$D165*0.000947817>Q21,$E$3*$D165*0.000947817,Q21) -> 0.26283827 | Q21: =$E$3*$H$165*0.453592*947817/1000000 -> 0.085984442 | R21: =$E$3*$I$165*0.453592*947817/1000000 -> 0.085984442 | S21: =(R21+T21)/2 -> 0.085984442 | T21: =$E$3*$J$165*0.453592*947817/1000000 -> 0.085984442 | U21: =IF($E$3*$C166*0.000947817>V21,$E$3*$C166*0.000947817,V21) -> 0.15103895 | V21: =IF($E$3*$D166*0.000947817>W21,$E$3*$D166*0.000947817,W21) -> 0.15103895 | W21: =$E$3*$H$166*0.453592*947817/1000000 -> 0.023821599 | X21: =$E$3*$I$166*0.453592*947817/1000000 -> 0.010273178 | Y21: =(X21+Z21)/2 -> 0.0099237938 | Z21: =$E$3*$J$166*0.453592*947817/1000000 -> 0.0095744098 | AA21: =IF($E$3*$C167*0.000947817>AB21,$E$3*$C167*0.000947817,AB21) -> 0.11680552 | AB21: =IF($E$3*$D167*0.000947817>AC21,$E$3*$D167*0.000947817,AC21) -> 0.11680552 | AC21: =$E$3*$H$167*0.453592*947817/1000000 -> 0.02067535 | AD21: =$E$3*$I$167*0.453592*947817/1000000 -> 0.0090746179 | AE21: =(AD21+AF21)/2 -> 0.0087565921 | AF21: =$E$3*$J$167*0.453592*947817/1000000 -> 0.0084385663 | AG21: =IF($E$3*$C168*0.000947817>AH21,$E$3*$C168*0.000947817,AH21) -> 0.016891822 | AH21: =IF($E$3*$D168*0.000947817>AI21,$E$3*$D168*0.000947817,AI21) -> 0.0097709593 | AI21: =$E$3*$H$168*0.453592*947817/1000000 -> 0.0097709593 | AJ21: =$E$3*$I$168*0.453592*947817/1000000 -> 0.0097709593 | AK21: =(AJ21+AL21)/2 -> 0.0097709593 | AL21: =$E$3*$J$168*0.453592*947817/1000000 -> 0.0097709593 | AM21: =IF($E$3*$C169*0.000947817>AN21,$E$3*$C169*0.000947817,AN21) -> 0.028935991 | AN21: =IF($E$3*$D169*0.000947817>AO21,$E$3*$D169*0.000947817,AO21) -> 0.028935991 | AO21: =$E$3*$H$169*0.453592*947817/1000000 -> 0.0082076058 | AP21: =$E$3*$I$169*0.453592*947817/1000000 -> 0.0082076058 | AQ21: =(AP21+AR21)/2 -> 0.0082076058 | AR21: =$E$3*$J$169*0.453592*947817/1000000 -> 0.0082076058 | AS21: =IF($E$3*$C170*0.000947817>AT21,$E$3*$C170*0.000947817,AT21) -> 0.00947817 | AT21: =IF($E$3*$D170*0.000947817>AU21,$E$3*$D170*0.000947817,AU21) -> 0.0050808988 | AU21: =$E$3*$H$170*0.453592*947817/1000000 -> 0.0050808988 | AV21: =$E$3*$I$170*0.453592*947817/1000000 -> 0.0050808988 | AW21: =(AV21+AX21)/2 -> 0.0050808988 | AX21: =$E$3*$J$170*0.453592*947817/1000000 -> 0.0050808988 | AY21: =$E$3*AA21*#REF! -> #REF! | AZ21: =$E$3*AB21*#REF! -> #REF! | BA21: =$E$3*$H$171*0.453592*947817/1000000 -> 0.0010927841 | BB21: =$E$3*$I$171*0.453592*947817/1000000 -> 0.00077391183 | BC21: =(BB21+BD21)/2 -> 0.00074721544 | BD21: =$E$3*$J$171*0.453592*947817/1000000 -> 0.00072051904 | BE21: =0.15*BE13 -> 13.134687 | BF21: =0.15*BF13 -> 13.134687 | BG21: =0.15*BG13 -> 13.134687 | BH21: =0.15*BH13 -> 13.134687 | BI21: =0.15*BI13 -> 13.134687 | BJ21: =0.15*BJ13 -> 13.134687 | BK21: =$E$3*AA21*#REF! -> #REF! | BL21: =$E$3*AB21*#REF! -> #REF! | BM21: =$E$3*AC21*#REF! -> #REF! | BO21: =(BN21+BP21)/2 -> #REF! | BP21: =$E$3*AF21*#REF! -> #REF!
B22: Aggregate diesel | C22: =IF($E$3*$N$45*C18+(1-$N$45)*C19>D22,$E$3*$N$45*C18+(1-$N$45),D22) -> 0.021024817 | D22: =IF($E$3*$N$45*D18+(1-$N$45)*D19>E22,$E$3*$N$45*D18+(1-$N$45),E22) -> 0.021024817 | E22: =$E$3*$N$45*E18+(1-$N$45)*E19 -> 0.00022164706 | F22: =$E$3*$N$45*F18+(1-$N$45)*F19 -> 0.00022164706 | G22: =$N$45*G18+(1-$N$45)*G19 -> 0.00024031782 | H22: =$E$3*$N$45*H18+(1-$N$45)*H19 -> 0.00022164706 | I22: =IF($E$3*$N$45*I18+(1-$N$45)*I19>J22,$E$3*$N$45*I18+(1-$N$45),J22) -> 0.026689332 | J22: =IF($E$3*$N$45*J18+(1-$N$45)*J19>K22,$E$3*$N$45*J18+(1-$N$45),K22) -> 0.026689332 | K22: =$E$3*$N$45*K18+(1-$N$45)*K19 -> 0.012823677 | L22: =$E$3*$N$45*L18+(1-$N$45)*L19 -> 0.010569362 | M22: =$N$45*M18+(1-$N$45)*M19 -> 0.010058302 | N22: =$E$3*$N$45*N18+(1-$N$45)*N19 -> 0.0092469545 | O22: =IF($E$3*$N$45*O18+(1-$N$45)*O19>P22,$E$3*$N$45*O18+(1-$N$45),P22) -> 0.23018242 | P22: =IF($E$3*$N$45*P18+(1-$N$45)*P19>Q22,$E$3*$N$45*P18+(1-$N$45),Q22) -> 0.23018242 | Q22: =$E$3*$N$45*Q18+(1-$N$45)*Q19 -> 0.23018242 | R22: =$E$3*$N$45*R18+(1-$N$45)*R19 -> 0.19900602 | S22: =$N$45*S18+(1-$N$45)*S19 -> 0.21670231 | T22: =$E$3*$N$45*T18+(1-$N$45)*T19 -> 0.19552072 | U22: =IF($E$3*$N$45*U18+(1-$N$45)*U19>V22,$E$3*$N$45*U18+(1-$N$45),V22) -> 0.033703062 | V22: =IF($E$3*$N$45*V18+(1-$N$45)*V19>W22,$E$3*$N$45*V18+(1-$N$45),W22) -> 0.033703062 | W22: =$E$3*$N$45*W18+(1-$N$45)*W19 -> 0.01457992 | X22: =$E$3*$N$45*X18+(1-$N$45)*X19 -> 0.014027273 | Y22: =$N$45*Y18+(1-$N$45)*Y19 -> 0.015252129 | Z22: =$E$3*$N$45*Z18+(1-$N$45)*Z19 -> 0.013736371 | AA22: =$E$3*$N$45*AA18+(1-$N$45)*AA19 -> 0.011368701 | AB22: =$E$3*$N$45*AB18+(1-$N$45)*AB19 -> 0.010938961 | AC22: =$E$3*$N$45*AC18+(1-$N$45)*AC19 -> 0.0057329892 | AD22: =$E$3*$N$45*AD18+(1-$N$45)*AD19 -> 0.0051859662 | AE22: =$N$45*AE18+(1-$N$45)*AE19 -> 0.0055285915 | AF22: =$E$3*$N$45*AF18+(1-$N$45)*AF19 -> 0.0048980419 | AG22: =$E$3*$N$45*AG18+(1-$N$45)*AG19 -> 0.044161308 | AH22: =$E$3*$N$45*AH18+(1-$N$45)*AH19 -> 0.044161308 | AI22: =$E$3*$N$45*AI18+(1-$N$45)*AI19 -> 0.044161308 | AJ22: =$E$3*$N$45*AJ18+(1-$N$45)*AJ19 -> 0.033756296 | AK22: =$N$45*AK18+(1-$N$45)*AK19 -> 0.032418418 | AL22: =$E$3*$N$45*AL18+(1-$N$45)*AL19 -> 0.025188579 | AM22: =$E$3*$N$45*AM18+(1-$N$45)*AM19 -> 0.0026774529 | AN22: =$E$3*$N$45*AN18+(1-$N$45)*AN19 -> 0.0026774529 | AO22: =$E$3*$N$45*AO18+(1-$N$45)*AO19 -> 0.0026774529 | AP22: =$E$3*$N$45*AP18+(1-$N$45)*AP19 -> 0.0026774529 | AQ22: =$N$45*AQ18+(1-$N$45)*AQ19 -> 0.0029379241 | AR22: =$E$3*$N$45*AR18+(1-$N$45)*AR19 -> 0.0026774529 | AS22: =$E$3*$N$45*AS18+(1-$N$45)*AS19 -> 0.0015923289 | AT22: =$E$3*$N$45*AT18+(1-$N$45)*AT19 -> 0.001261429 | AU22: =$E$3*$N$45*AU18+(1-$N$45)*AU19 -> 0.00053298132 | AV22: =$E$3*$N$45*AV18+(1-$N$45)*AV19 -> 0.00053298132 | AW22: =$N$45*AW18+(1-$N$45)*AW19 -> 0.00058524529 | AX22: =$E$3*$N$45*AX18+(1-$N$45)*AX19 -> 0.00053298132 | AY22: =$E$3*$N$45*AY18+(1-$N$45)*AY19 -> #REF! | AZ22: =$E$3*$N$45*AZ18+(1-$N$45)*AZ19 -> #REF! | BA22: =$E$3*$N$45*BA18+(1-$N$45)*BA19 -> 0.0014710964 | BB22: =$E$3*$N$45*BB18+(1-$N$45)*BB19 -> 0.0010004474 | BC22: =$N$45*BC18+(1-$N$45)*BC19 -> 0.00096499426 | BD22: =$E$3*$N$45*BD18+(1-$N$45)*BD19 -> 0.00077874573 | BE22: =$E$3*$N$45*BE18+(1-$N$45)*BE19 -> 62.847514 | BF22: =$E$3*$N$45*BF18+(1-$N$45)*BF19 -> 62.847514 | BG22: =$E$3*$N$45*BG18+(1-$N$45)*BG19 -> 62.847514 | BH22: =$E$3*$N$45*BH18+(1-$N$45)*BH19 -> 62.847514 | BI22: =$N$45*BI18+(1-$N$45)*BI19 -> 68.995426 | BJ22: =$E$3*$N$45*BJ18+(1-$N$45)*BJ19 -> 62.847514 | BK22: =$E$3*$N$45*BK18+(1-$N$45)*BK19 -> #REF! | BL22: =$E$3*$N$45*BL18+(1-$N$45)*BL19 -> #REF! | BM22: =$E$3*$N$45*BM18+(1-$N$45)*BM19 -> #REF! | BN22: =$E$3*$N$45*BN18+(1-$N$45)*BN19 -> 0 | BO22: =$N$45*BO18+(1-$N$45)*BO19 -> #REF! | BP22: =$E$3*$N$45*BP18+(1-$N$45)*BP19 -> #REF!
B25: Emission factors from GREET 2012 | H25: Factors from GREET 2014
H26: Converted to lbs/MMBTUin | M26: Original units | R26: =D45/D44 -> 0.78588808 | S26: engine voc
B27: IGCC turbine | C27: 2005 | D27: 2010 | E27: 2015 | F27: 2020 | H27: 2013_14 | I27: 2020_14 | J27: 2030_14 | M27: 2013_14 | N27: 2020_14 | O27: 2030_14
B28: VOC | C28: 1.411 | D28: 0.718317 | E28: 0.718317 | F28: 0.680511 | G28: g/mmbtu | H28: =M28/0.003412142/1000*2.204623/M$41 -> 0.00094323228 | I28: =N28/0.003412142/1000*2.204623/N$41 -> 0.00098706072 | J28: =O28/0.003412142/1000*2.204623/O$41 -> 0.0010351607 | K28: lbs/MMBTU | M28: ='GREET2014-EFUpdate'!M61 -> 0.0057333333 | N28: ='GREET2014-EFUpdate'!N61 -> 0.0057333333 | O28: ='GREET2014-EFUpdate'!O61 -> 0.0057333333 | P28: g/kWh
B29: CO | C29: 11.758 | D29: 12.652 | E29: 12.652 | F29: 11.884 | G29: g/mmbtu | H29: =M29/0.003412142/1000*2.204623/M$41 -> 0.016517533 | I29: =N29/0.003412142/1000*2.204623/N$41 -> 0.01728504 | J29: =O29/0.003412142/1000*2.204623/O$41 -> 0.01812735 | K29: lbs/MMBTU | M29: ='GREET2014-EFUpdate'!M60 -> 0.1004 | N29: ='GREET2014-EFUpdate'!N60 -> 0.1004 | O29: ='GREET2014-EFUpdate'!O60 -> 0.1004 | P29: g/kWh | R29: turbine voc | S29: 82
B30: NOX | C30: 42.103 | D30: 21.865 | E30: 21.865 | F30: 20.554 | G30: g/mmbtu | H30: =M30/0.003412142/1000*2.204623/M$41 -> 0.028543744 | I30: =N30/0.003412142/1000*2.204623/N$41 -> 0.029870064 | J30: =O30/0.003412142/1000*2.204623/O$41 -> 0.031325649 | K30: lbs/MMBTU | M30: ='GREET2014-EFUpdate'!M62 -> 0.1735 | N30: ='GREET2014-EFUpdate'!N62 -> 0.1735 | O30: ='GREET2014-EFUpdate'!O62 -> 0.1735 | P30: g/kWh | S30: 93
B31: PM10 | C31: 6.238 | D31: 3.037 | E31: 3.037 | F31: 2.848 | G31: g/mmbtu | H31: =M31/0.003412142/1000*2.204623/M$41 -> 0.0039689788 | I31: =N31/0.003412142/1000*2.204623/N$41 -> 0.0041534023 | J31: =O31/0.003412142/1000*2.204623/O$41 -> 0.0043557999 | K31: lbs/MMBTU | M31: ='GREET2014-EFUpdate'!M64 -> 0.024125 | N31: ='GREET2014-EFUpdate'!N64 -> 0.024125 | O31: ='GREET2014-EFUpdate'!O64 -> 0.024125 | P31: g/kWh
B32: PM25 | C32: 3.119 | D32: 1.525 | E32: 1.525 | F32: 1.424 | G32: g/mmbtu | H32: =M32/0.003412142/1000*2.204623/M$41 -> 0 | I32: =N32/0.003412142/1000*2.204623/N$41 -> 0 | J32: =O32/0.003412142/1000*2.204623/O$41 -> 0 | K32: lbs/MMBTU | P32: g/kWh
B33: SO2 | C33: 42.103 | D33: 7.999 | E33: 7.999 | F33: 7.519 | G33: g/mmbtu | H33: =M33/0.003412142/1000*2.204623/M$41 -> 0.010442733 | I33: =N33/0.003412142/1000*2.204623/N$41 -> 0.010927967 | J33: =O33/0.003412142/1000*2.204623/O$41 -> 0.011460493 | K33: lbs/MMBTU | M33: ='GREET2014-EFUpdate'!M63 -> 0.063475 | N33: ='GREET2014-EFUpdate'!N63 -> 0.063475 | O33: ='GREET2014-EFUpdate'!O63 -> 0.063475 | P33: g/kWh
B34: CH4 | C34: 5.098 | D34: 4.766 | E34: 4.664 | F34: 4.384 | G34: g/mmbtu | H34: =M34/0.003412142/1000*2.204623/M$41 -> 0.0017019027 | I34: =N34/0.003412142/1000*2.204623/N$41 -> 0.0017809837 | J34: =O34/0.003412142/1000*2.204623/O$41 -> 0.001867772 | K34: lbs/MMBTU | M34: ='GREET2014-EFUpdate'!M57 -> 0.010344828 | N34: ='GREET2014-EFUpdate'!N57 -> 0.010344828 | O34: ='GREET2014-EFUpdate'!O57 -> 0.010344828 | P34: g/kWh
B35: N2O | C35: 5.098 | D35: 4.766 | E35: 4.664 | F35: 4.384 | G35: g/mmbtu | H35: =M35/0.003412142/1000*2.204623/M$41 -> 0.002552854 | I35: =N35/0.003412142/1000*2.204623/N$41 -> 0.0026714755 | J35: =O35/0.003412142/1000*2.204623/O$41 -> 0.0028016579 | K35: lbs/MMBTU | M35: ='GREET2014-EFUpdate'!M58 -> 0.015517241 | N35: ='GREET2014-EFUpdate'!N58 -> 0.015517241 | O35: ='GREET2014-EFUpdate'!O58 -> 0.015517241 | P35: g/kWh
B36: BC | G36: g/mmbtu | H36: =M36/0.003412142/1000*2.204623/M$41 -> 0 | I36: =N36/0.003412142/1000*2.204623/N$41 -> 0 | J36: =O36/0.003412142/1000*2.204623/O$41 -> 0 | K36: lbs/MMBTU | P36: g/kWh
B37: CO2 | C37: 94.252 | D37: 94.254 | E37: 94.254 | F37: 94.256 | G37: kg/mmbtu | H37: =M37/0.003412142/1000*2.204623/M$41 -> 114.65619 | I37: =N37/0.003412142/1000*2.204623/N$41 -> 119.98383 | J37: =O37/0.003412142/1000*2.204623/O$41 -> 125.83071 | K37: lbs/MMBTU | M37: ='GREET2014-EFUpdate'!M56 -> 696.925 | N37: ='GREET2014-EFUpdate'!N56 -> 696.925 | O37: ='GREET2014-EFUpdate'!O56 -> 696.925 | P37: g/kWh
H39: bituminous | M39: IGCC Coal efficiency
B40: utility coal boiler | C40: 2005 | D40: 2010 | E40: 2015 | F40: 2020 | H40: 2013_14 | I40: 2020_14 | J40: 2030_14 | M40: 2013_14 | N40: 2020_14 | O40: 2030_14
B41: VOC | C41: 1.153 | D41: 1.345 | E41: 1.173 | F41: 1.173 | G41: g/mmbtu | H41: ='GREET2014-EFUpdate'!B30 -> 0.0026463962 | I41: ='GREET2014-EFUpdate'!C30 -> 0.0026463962 | J41: ='GREET2014-EFUpdate'!D30 -> 0.0026463962 | K41: lbs/MMBTU | M41: 3.9273154 | N41: 3.7529308 | O41: 3.5785463
B42: CO | C42: 15.166 | D42: 11.041 | E42: 11.041 | F42: 11.041 | G42: g/mmbtu | H42: ='GREET2014-EFUpdate'!B29 -> 0.022301449 | I42: ='GREET2014-EFUpdate'!C29 -> 0.022301449 | J42: ='GREET2014-EFUpdate'!D29 -> 0.022301449 | K42: lbs/MMBTU
B43: NOX | C43: 160.016 | D43: 139.966 | E43: 19.201 | F43: 19.201 | G43: g/mmbtu | H43: ='GREET2014-EFUpdate'!B31 -> 0.33232927 | I43: ='GREET2014-EFUpdate'!C31 -> 0.28724276 | J43: ='GREET2014-EFUpdate'!D31 -> 0.21209859 | K43: lbs/MMBTU
B44: PM10 | C44: 9.626 | D44: 15.207 | E44: 15.207 | F44: 15.207 | G44: g/mmbtu | H44: ='GREET2014-EFUpdate'!B34 -> 0.04833645 | I44: ='GREET2014-EFUpdate'!C34 -> 0.049419256 | J44: ='GREET2014-EFUpdate'!D34 -> 0.042493564 | K44: lbs/MMBTU | M44: Calibration parameter: Fraction of diesel emissions
B45: PM25 | C45: 4.813 | D45: 11.951 | E45: 11.951 | F45: 11.951 | G45: g/mmbtu | H45: ='GREET2014-EFUpdate'!B35 -> 0.040542518 | I45: ='GREET2014-EFUpdate'!C35 -> 0.03732036 | J45: ='GREET2014-EFUpdate'!D35 -> 0.033330559 | K45: lbs/MMBTU | M45: turbine | N45: 0.98
B46: SO2 | C46: 420.514 | D46: 398.139 | E46: 319.557 | F46: 319.557 | G46: g/mmbtu | H46: ='GREET2014-EFUpdate'!B32 -> 1.0750724 | I46: ='GREET2014-EFUpdate'!C32 -> 0.16455896 | J46: ='GREET2014-EFUpdate'!D32 -> 0.15163548 | K46: lbs/MMBTU | M46: engine | N46: =1-N45 -> 0.02
B47: CH4 | C47: 1.218 | D47: 1.122 | E47: 1.122 | F47: 1.113 | G47: g/mmbtu | H47: ='GREET2014-EFUpdate'!B26 -> 0.0024466682 | I47: ='GREET2014-EFUpdate'!C26 -> 0.0024466682 | J47: ='GREET2014-EFUpdate'!D26 -> 0.0024466682 | K47: lbs/MMBTU
B48: N2O | C48: 1.076 | D48: 1.658 | E48: 1.658 | F48: 1.644 | G48: g/mmbtu | H48: ='GREET2014-EFUpdate'!B27 -> 0.0035928347 | I48: ='GREET2014-EFUpdate'!C27 -> 0.0035928347 | J48: ='GREET2014-EFUpdate'!D27 -> 0.0035928347 | K48: lbs/MMBTU
B49: BC | C49: =J62/J58*C45 -> 0.19252 | D49: =J62/J58*D45 -> 0.47804 | E49: =J62/J58*E45 -> 0.47804 | F49: =J62/J58*F45 -> 0.47804 | G49: g/mmbtu | H49: ='GREET2014-EFUpdate'!B28 -> 0.00081085036 | I49: ='GREET2014-EFUpdate'!C28 -> 0.00074640721 | J49: ='GREET2014-EFUpdate'!D28 -> 0.00066661119 | K49: lbs/MMBTU
B50: CO2 | C50: 94.258 | D50: 94.264 | E50: 94.265 | F50: 94.265 | G50: kg/mmbtu | H50: ='GREET2014-EFUpdate'!B25 -> 213.27775 | I50: ='GREET2014-EFUpdate'!C25 -> 213.27775 | J50: ='GREET2014-EFUpdate'!D25 -> 213.27775 | K50: lbs/MMBTU
H52: subbituminous
H53: 2013_14 | I53: 2020_14 | J53: 2030_14
G54: VOC | H54: ='GREET2014-EFUpdate'!B48 -> 0.0031435498 | I54: ='GREET2014-EFUpdate'!C48 -> 0.0031435498 | J54: ='GREET2014-EFUpdate'!D48 -> 0.0031435498 | K54: lbs/MMBTU
G55: CO | H55: ='GREET2014-EFUpdate'!B47 -> 0.026463447 | I55: ='GREET2014-EFUpdate'!C47 -> 0.026463447 | J55: ='GREET2014-EFUpdate'!D47 -> 0.026463447 | K55: lbs/MMBTU
G56: NOX | H56: ='GREET2014-EFUpdate'!B49 -> 0.28817534 | I56: ='GREET2014-EFUpdate'!C49 -> 0.25091754 | J56: ='GREET2014-EFUpdate'!D49 -> 0.18882119 | K56: lbs/MMBTU
G57: PM10 | H57: ='GREET2014-EFUpdate'!B52 -> 0.010370898 | I57: ='GREET2014-EFUpdate'!C52 -> 0.051272623 | J57: ='GREET2014-EFUpdate'!D52 -> 0.043939558 | K57: lbs/MMBTU
G58: PM25 | H58: ='GREET2014-EFUpdate'!B53 -> 0.0056241594 | I58: ='GREET2014-EFUpdate'!C53 -> 0.038734617 | J58: ='GREET2014-EFUpdate'!D53 -> 0.034510134 | K58: lbs/MMBTU
G59: SO2 | H59: ='GREET2014-EFUpdate'!B50 -> 0.61312437 | I59: ='GREET2014-EFUpdate'!C50 -> 0.16322965 | J59: ='GREET2014-EFUpdate'!D50 -> 0.15041057 | K59: lbs/MMBTU
G60: CH4 | H60: ='GREET2014-EFUpdate'!B44 -> 0.002487109 | I60: ='GREET2014-EFUpdate'!C44 -> 0.002487109 | J60: ='GREET2014-EFUpdate'!D44 -> 0.002487109 | K60: lbs/MMBTU
G61: N2O | H61: ='GREET2014-EFUpdate'!B45 -> 0.0037068324 | I61: ='GREET2014-EFUpdate'!C45 -> 0.0037068324 | J61: ='GREET2014-EFUpdate'!D45 -> 0.0037068324 | K61: lbs/MMBTU
G62: BC | H62: ='GREET2014-EFUpdate'!B46 -> 0.00022496638 | I62: ='GREET2014-EFUpdate'!C46 -> 0.0015493847 | J62: ='GREET2014-EFUpdate'!D46 -> 0.0013804054 | K62: lbs/MMBTU
G63: CO2 | H63: ='GREET2014-EFUpdate'!B43 -> 218.79193 | I63: ='GREET2014-EFUpdate'!C43 -> 218.79193 | J63: ='GREET2014-EFUpdate'!D43 -> 218.79193 | K63: lbs/MMBTU
C64: Multiplier
B65: Calculated using multiplier | C65: 1.024 | H65: lignite
H66: 2013_14 | I66: 2020_14 | J66: 2030_14
B67: Multiplier derived from comparing energy content of lignite and subb, | G67: VOC | H67: =H54*$C$65 -> 0.003218995 | I67: =I54*$C$65 -> 0.003218995 | J67: =J54*$C$65 -> 0.003218995 | K67: lbs/MMBTU
B68: based upon EIA fuel heat content estimates | G68: CO | H68: =H55*$C$65 -> 0.027098569 | I68: =I55*$C$65 -> 0.027098569 | J68: =J55*$C$65 -> 0.027098569 | K68: lbs/MMBTU
G69: NOX | H69: =H56*$C$65 -> 0.29509155 | I69: =I56*$C$65 -> 0.25693956 | J69: =J56*$C$65 -> 0.1933529 | K69: lbs/MMBTU
G70: PM10 | H70: =H57*$C$65 -> 0.0106198 | I70: =I57*$C$65 -> 0.052503166 | J70: =J57*$C$65 -> 0.044994108 | K70: lbs/MMBTU
G71: PM25 | H71: =H58*$C$65 -> 0.0057591393 | I71: =I58*$C$65 -> 0.039664248 | J71: =J58*$C$65 -> 0.035338378 | K71: lbs/MMBTU
G72: SO2 | H72: =H59*$C$65 -> 0.62783936 | I72: =I59*$C$65 -> 0.16714716 | J72: =J59*$C$65 -> 0.15402042 | K72: lbs/MMBTU
G73: CH4 | H73: =H60*$C$65 -> 0.0025467996 | I73: =I60*$C$65 -> 0.0025467996 | J73: =J60*$C$65 -> 0.0025467996 | K73: lbs/MMBTU
G74: N2O | H74: =H61*$C$65 -> 0.0037957963 | I74: =I61*$C$65 -> 0.0037957963 | J74: =J61*$C$65 -> 0.0037957963 | K74: lbs/MMBTU
G75: BC | H75: =H62*$C$65 -> 0.00023036557 | I75: =I62*$C$65 -> 0.0015865699 | J75: =J62*$C$65 -> 0.0014135351 | K75: lbs/MMBTU
G76: CO2 | H76: =H63*$C$65 -> 224.04294 | I76: =I63*$C$65 -> 224.04294 | J76: =J63*$C$65 -> 224.04294 | K76: lbs/MMBTU
B78: Natural gas boiler | C78: 2005 | D78: 2010 | E78: 2015 | F78: 2020 | H78: 2013_14 | I78: 2020_14 | J78: 2030_14
B79: VOC | C79: 2.001 | D79: 2.608 | E79: 1.945 | F79: 1.945 | G79: g/mmbtu | H79: ='GREET2014-EFUpdate'!B13 -> 0.0056563599 | I79: ='GREET2014-EFUpdate'!C13 -> 0.0056563599 | J79: ='GREET2014-EFUpdate'!D13 -> 0.0056563599 | K79: lbs/MMBTU
B80: CO | C80: 17.071 | D80: 39.275 | E80: 39.275 | F80: 39.275 | G80: g/mmbtu | H80: ='GREET2014-EFUpdate'!B12 -> 0.083837538 | I80: ='GREET2014-EFUpdate'!C12 -> 0.083837538 | J80: ='GREET2014-EFUpdate'!D12 -> 0.083837538 | K80: lbs/MMBTU
B81: NOX | C81: 48.418 | D81: 80.476 | E81: 80.476 | F81: 80.476 | G81: g/mmbtu | H81: ='GREET2014-EFUpdate'!B14 -> 0.17220839 | I81: ='GREET2014-EFUpdate'!C14 -> 0.15388412 | J81: ='GREET2014-EFUpdate'!D14 -> 0.12088173 | K81: lbs/MMBTU
B82: PM10 | C82: 1.43 | D82: 3.403 | E82: 3.403 | F82: 3.403 | G82: g/mmbtu | H82: ='GREET2014-EFUpdate'!B17 -> 0.0072565955 | I82: ='GREET2014-EFUpdate'!C17 -> 0.0072565955 | J82: ='GREET2014-EFUpdate'!D17 -> 0.0072565955 | K82: lbs/MMBTU
B83: PM25 | C83: 1.43 | D83: 3.403 | E83: 3.403 | F83: 3.403 | G83: g/mmbtu | H83: ='GREET2014-EFUpdate'!B18 -> 0.0072565955 | I83: ='GREET2014-EFUpdate'!C18 -> 0.0072565955 | J83: ='GREET2014-EFUpdate'!D18 -> 0.0072565955 | K83: lbs/MMBTU
B84: SO2 | C84: =0.44875 -> 0.44875 | D84: =0.44875 -> 0.44875 | E84: =0.44875 -> 0.44875 | F84: =0.44875 -> 0.44875 | G84: g/mmbtu | H84: ='GREET2014-EFUpdate'!B15 -> 0.00092352931 | I84: ='GREET2014-EFUpdate'!C15 -> 0.00092352931 | J84: ='GREET2014-EFUpdate'!D15 -> 0.00092352931 | K84: lbs/MMBTU
B85: CH4 | C85: 1.103 | D85: 1.159 | E85: 1.159 | F85: 1.159 | G85: g/mmbtu | H85: ='GREET2014-EFUpdate'!B9 -> 0.0025772433 | I85: ='GREET2014-EFUpdate'!C9 -> 0.0025772433 | J85: ='GREET2014-EFUpdate'!D9 -> 0.0025772433 | K85: lbs/MMBTU
B86: N2O | C86: 1.103 | D86: 0.130886 | E86: 0.130886 | F86: 0.130886 | G86: g/mmbtu | H86: ='GREET2014-EFUpdate'!B10 -> 0.00029413072 | I86: ='GREET2014-EFUpdate'!C10 -> 0.00029413072 | J86: ='GREET2014-EFUpdate'!D10 -> 0.00029413072 | K86: lbs/MMBTU
B87: BC | C87: =J87/J83*C83 -> 0.5434 | D87: =J87/J83*D83 -> 1.29314 | E87: =J87/J83*E83 -> 1.29314 | F87: =J87/J83*F83 -> 1.29314 | G87: g/mmbtu | H87: ='GREET2014-EFUpdate'!B11 -> 0.0027575063 | I87: ='GREET2014-EFUpdate'!C11 -> 0.0027575063 | J87: ='GREET2014-EFUpdate'!D11 -> 0.0027575063 | K87: lbs/MMBTU
B88: CO2 | C88: 53.594 | D88: 53.557 | E88: 53.559 | F88: 53.559 | G88: kg/mmbtu | H88: ='GREET2014-EFUpdate'!B8 -> 129.82889 | I88: ='GREET2014-EFUpdate'!C8 -> 129.82889 | J88: ='GREET2014-EFUpdate'!D8 -> 129.82889 | K88: lbs/MMBTU
B90: Natural gas turbine | C90: 2005 | D90: 2010 | E90: 2015 | F90: 2020 | H90: 2013_14 | I90: 2020_14 | J90: 2030_14
B91: VOC | C91: 4.166 | D91: 1.318 | E91: 0.94858 | F91: 0.94858 | G91: g/mmbtu | H91: ='GREET2014-EFUpdate'!M13 -> 0.0024715663 | I91: ='GREET2014-EFUpdate'!N13 -> 0.0024715663 | J91: ='GREET2014-EFUpdate'!O13 -> 0.0024715663 | K91: lbs/MMBTU
B92: CO | C92: 20.341 | D92: 49.978 | E92: 49.978 | F92: 49.978 | G92: g/mmbtu | H92: ='GREET2014-EFUpdate'!M12 -> 0.046898271 | I92: ='GREET2014-EFUpdate'!N12 -> 0.046898271 | J92: ='GREET2014-EFUpdate'!O12 -> 0.046898271 | K92: lbs/MMBTU
B93: NOX | C93: 45.487 | D93: 34.548 | E93: 34.548 | F93: 34.548 | G93: g/mmbtu | H93: ='GREET2014-EFUpdate'!M14 -> 0.079345646 | I93: ='GREET2014-EFUpdate'!N14 -> 0.079345646 | J93: ='GREET2014-EFUpdate'!O14 -> 0.079345646 | K93: lbs/MMBTU
B94: PM10 | C94: 1.5 | D94: 3.764 | E94: 3.764 | F94: 3.764 | G94: g/mmbtu | H94: ='GREET2014-EFUpdate'!M16 -> 0.0077674569 | I94: ='GREET2014-EFUpdate'!N16 -> 0.0077674569 | J94: ='GREET2014-EFUpdate'!O16 -> 0.0077674569 | K94: lbs/MMBTU
B95: PM25 | C95: 1.5 | D95: 3.764 | E95: 3.764 | F95: 3.764 | G95: g/mmbtu | H95: ='GREET2014-EFUpdate'!M17 -> 0.0077674569 | I95: ='GREET2014-EFUpdate'!N17 -> 0.0077674569 | J95: ='GREET2014-EFUpdate'!O17 -> 0.0077674569 | K95: lbs/MMBTU
B96: SO2 | C96: 0.592355 | D96: 0.592355 | E96: 0.592355 | F96: 0.592355 | G96: g/mmbtu | H96: ='GREET2014-EFUpdate'!M15 -> 0.0014653019 | I96: ='GREET2014-EFUpdate'!N15 -> 0.0014653019 | J96: ='GREET2014-EFUpdate'!O15 -> 0.0014653019 | K96: lbs/MMBTU
B97: CH4 | C97: 4.26 | D97: 4.26 | E97: 4.26 | F97: 4.26 | G97: g/mmbtu | H97: ='GREET2014-EFUpdate'!M9 -> 0.002797189 | I97: ='GREET2014-EFUpdate'!N9 -> 0.002797189 | J97: ='GREET2014-EFUpdate'!O9 -> 0.002797189 | K97: lbs/MMBTU
B98: N2O | C98: 1.5 | D98: 1.5 | E98: 1.5 | F98: 1.5 | G98: g/mmbtu | H98: ='GREET2014-EFUpdate'!M10 -> 0.00030300996 | I98: ='GREET2014-EFUpdate'!N10 -> 0.00030300996 | J98: ='GREET2014-EFUpdate'!O10 -> 0.00030300996 | K98: lbs/MMBTU
B99: BC | C99: =J99/J95*C95 -> 0.95209225 | D99: =J99/J95*D95 -> 2.3891168 | E99: =J99/J95*E95 -> 2.3891168 | F99: =J99/J95*F95 -> 2.3891168 | G99: g/mmbtu | H99: ='GREET2014-EFUpdate'!M11 -> 0.0049302237 | I99: ='GREET2014-EFUpdate'!N11 -> 0.0049302237 | J99: ='GREET2014-EFUpdate'!O11 -> 0.0049302237 | K99: lbs/MMBTU
B100: CO2 | C100: 53.573 | D100: 53.535 | E100: 53.536 | F100: 53.536 | G100: kg/mmbtu | H100: ='GREET2014-EFUpdate'!M8 -> 140.78657 | I100: ='GREET2014-EFUpdate'!N8 -> 140.78657 | J100: ='GREET2014-EFUpdate'!O8 -> 140.78657 | K100: lbs/MMBTU
B102: Natural gas combined cycle | C102: 2005 | D102: 2010 | E102: 2015 | F102: 2020 | H102: 2013_14 | I102: 2020_14 | J102: 2030_14
B103: VOC | C103: 4.466 | D103: 0.248114 | E103: 0.248114 | F103: 0.248114 | G103: g/mmbtu | H103: ='GREET2014-EFUpdate'!M45 -> 0.0006155516 | I103: ='GREET2014-EFUpdate'!N45 -> 0.0006155516 | J103: ='GREET2014-EFUpdate'!O45 -> 0.0006155516 | K103: lbs/MMBTU
B104: CO | C104: 31.073 | D104: 4.101 | E104: 4.101 | F104: 4.101 | G104: g/mmbtu | H104: ='GREET2014-EFUpdate'!M44 -> 0.046898271 | I104: ='GREET2014-EFUpdate'!N44 -> 0.046898271 | J104: ='GREET2014-EFUpdate'!O44 -> 0.046898271 | K104: lbs/MMBTU
B105: NOX | C105: 16.551 | D105: 9.18 | E105: 9.18 | F105: 9.18 | G105: g/mmbtu | H105: ='GREET2014-EFUpdate'!M46 -> 0.022793514 | I105: ='GREET2014-EFUpdate'!N46 -> 0.022793514 | J105: ='GREET2014-EFUpdate'!O46 -> 0.022793514 | K105: lbs/MMBTU
B106: PM10 | C106: 2.291 | D106: 0.11676 | E106: 0.11676 | F106: 0.11676 | G106: g/mmbtu | H106: ='GREET2014-EFUpdate'!M48 -> 0.00030053402 | I106: ='GREET2014-EFUpdate'!N48 -> 0.00030053402 | J106: ='GREET2014-EFUpdate'!O48 -> 0.00030053402 | K106: lbs/MMBTU
B107: PM25 | C107: 2.291 | D107: 0.11676 | E107: 0.11676 | F107: 0.11676 | G107: g/mmbtu | H107: ='GREET2014-EFUpdate'!M49 -> 0.00030053402 | I107: ='GREET2014-EFUpdate'!N49 -> 0.00030053402 | J107: ='GREET2014-EFUpdate'!O49 -> 0.00030053402 | K107: lbs/MMBTU
B108: SO2 | C108: 0.291899 | D108: 0.291899 | E108: 0.291899 | F108: 0.291899 | G108: g/mmbtu | H108: ='GREET2014-EFUpdate'!M47 -> 0.00073504103 | I108: ='GREET2014-EFUpdate'!N47 -> 0.00073504103 | J108: ='GREET2014-EFUpdate'!O47 -> 0.00073504103 | K108: lbs/MMBTU
...

Sheet GREET2014-EFUpdate
A1: Summary of 2013, 2020 and 2030 Emission Factors for Gaseous and Liquid Fuel Boilers, by boiler size.
A3: Boilers | G3: Engines | L3: Turbines
A5: Natural Gas: EGU >250 mmBtu/hr | G5: Diesel: | L5: Natural Gas (>1 MW) Single-cycle
A6: Pollutant | B6: Emission Factor (lb/MMBtu Lower Heating Value (LHV) Basis) | H6: Emission Factor (lb/MMBtu Lower Heating Value (LHV) Basis) | M6: Emission Factor (lb/MMBtu Lower Heating Value (LHV) Basis)
B7: 2013 | C7: 2020 | D7: 2030 | G7: Pollutant | H7: 2013 | I7: 2020 | J7: 2030 | L7: Pollutant | M7: 2013 | N7: 2020 | O7: 2030
A8: CO2 | B8: 129.82889 | C8: 129.82889 | D8: 129.82889 | G8: CO2 | H8: 175.05839 | I8: 175.05839 | J8: 175.05839 | L8: CO2 | M8: 140.78657 | N8: 140.78657 | O8: 140.78657
A9: CH4 | B9: 0.0025772433 | C9: 0.0025772433 | D9: 0.0025772433 | G9: CH4 | H9: 0.0093057607 | I9: 0.0093057607 | J9: 0.0093057607 | L9: CH4 | M9: 0.002797189 | N9: 0.002797189 | O9: 0.002797189
A10: N2O | B10: 0.00029413072 | C10: 0.00029413072 | D10: 0.00029413072 | G10: N2O | H10: 0.001323 | I10: 0.001323 | J10: 0.001323 | L10: N2O | M10: 0.00030300996 | N10: 0.00030300996 | O10: 0.00030300996
A11: Black Carbon | B11: 0.0027575063 | C11: 0.0027575063 | D11: 0.0027575063 | G11: Black Carbon | H11: 0.091741173 | I11: 0.031530983 | J11: 0.0031686623 | L11: Black Carbon | M11: 0.0049302237 | N11: 0.0049302237 | O11: 0.0049302237
A12: CO | B12: 0.083837538 | C12: 0.083837538 | D12: 0.083837538 | G12: CO | H12: 1.4484551 | I12: 1.1600603 | J12: 0.9908846 | L12: CO | M12: 0.046898271 | N12: 0.046898271 | O12: 0.046898271
A13: VOC | B13: 0.0056563599 | C13: 0.0056563599 | D13: 0.0056563599 | G13: VOC | H13: 0.0044698146 | I13: 0.0044698146 | J13: 0.0044698146 | L13: VOC | M13: 0.0024715663 | N13: 0.0024715663 | O13: 0.0024715663
A14: NOx | B14: 0.17220839 | C14: 0.15388412 | D14: 0.12088173 | G14: NOx | H14: 4.5789986 | I14: 0.59059827 | J14: 0.14472307 | L14: NOx | M14: 0.079345646 | N14: 0.079345646 | O14: 0.079345646
A15: SOx | B15: 0.00092352931 | C15: 0.00092352931 | D15: 0.00092352931 | G15: SOx | H15: 0.23666148 | I15: 0.0016161966 | J15: 0.0016161966 | L15: SOx | M15: 0.0014653019 | N15: 0.0014653019 | O15: 0.0014653019
A16: PM-con | B16: Included in PM10/PM2.5 factors | G16: PM10-fil | H16: 0.11217649 | I16: 0.041476357 | J16: 0.0042611949 | L16: PM10-fil | M16: 0.0077674569 | N16: 0.0077674569 | O16: 0.0077674569
A17: PM10-pri | B17: 0.0072565955 | C17: 0.0072565955 | D17: 0.0072565955 | G17: PM2.5-fil | H17: 0.11093005 | I17: 0.040949329 | J17: 0.0041151459 | L17: PM2.5-fil | M17: 0.0077674569 | N17: 0.0077674569 | O17: 0.0077674569
A18: PM2.5-pri | B18: 0.0072565955 | C18: 0.0072565955 | D18: 0.0072565955 | G18: Condensable PM | H18: 0.0082143324 | I18: 0.0082143324 | J18: 0.0082143324 | L18: Condensable PM | M18: 0.0052068159 | N18: 0.0052068159 | O18: 0.0052068159
G21: Gasoline: | L21: Diesel:
A22: Coal: >250 mmBtu/hr (EGU-Bituminous) | H22: Emission Factor (lb/MMBtu Lower Heating Value (LHV) Basis) | M22: Emission Factor (lb/MMBtu Lower Heating Value (LHV) Basis)
A23: Pollutant | B23: Emission Factor (lb/MMBtu Lower Heating Value (LHV) Basis) | E23: Coal Type Applicability | G23: Pollutant | H23: 2013 | I23: 2020 | J23: 2030 | L23: Pollutant | M23: 2013 | N23: 2020 | O23: 2030
B24: 2013 | C24: 2020 | D24: 2030 | G24: CO2 | H24: 178.44091 | I24: 178.44091 | J24: 178.44091 | L24: CO2 | M24: 176.56193 | N24: 176.56193 | O24: 176.56193
A25: CO2 | B25: 213.27775 | C25: 213.27775 | D25: 213.27775 | E25: Bit | G25: CH4 | H25: 0.006615 | I25: 0.006615 | J25: 0.006615 | L25: CH4 | M25: 0.007480474 | N25: 0.007480474 | O25: 0.007480474
A26: CH4 | B26: 0.0024466682 | C26: 0.0024466682 | D26: 0.0024466682 | E26: Bit | G26: N2O | H26: 0.001323 | I26: 0.001323 | J26: 0.001323 | L26: N2O | M26: 0.0015009694 | N26: 0.0015009694 | O26: 0.0015009694
A27: N2O | B27: 0.0035928347 | C27: 0.0035928347 | D27: 0.0035928347 | E27: Bit | G27: Black Carbon | H27: 0.011587072 | I27: 0.011587072 | J27: 0.011587072 | L27: Black Carbon | M27: 0.0021653471 | N27: 0.0021653471 | O27: 0.0021653471
A28: Black Carbon | B28: 0.00081085036 | C28: 0.00074640721 | D28: 0.00066661119 | E28: Bit | G28: CO | H28: 3.3520102 | I28: 2.8747387 | J28: 2.3974673 | L28: CO | M28: 0.0043119865 | N28: 0.0043119865 | O28: 0.0043119865
A29: CO | B29: 0.022301449 | C29: 0.022301449 | D29: 0.022301449 | E29: Bit | G29: VOC | H29: 1.3191436 | I29: 1.3191436 | J29: 1.3191436 | L29: VOC | M29: 0.00053620558 | N29: 0.00053620558 | O29: 0.00053620558
A30: VOC | B30: 0.0026463962 | C30: 0.0026463962 | D30: 0.0026463962 | E30: Bit | G30: NOx | H30: 0.21735 | I30: 0.21735 | J30: 0.21735 | L30: NOx | M30: 0.55826719 | N30: 0.55826719 | O30: 0.55826719
A31: NOx | B31: 0.33232927 | C31: 0.28724276 | D31: 0.21209859 | E31: Bit | G31: SOx | H31: 0.097331408 | I31: 0.097331408 | J31: 0.097331408 | L31: SOx | M31: 0.12151408 | N31: 0.096908448 | O31: 0.072302816
A32: SOx | B32: 1.0750724 | C32: 0.16455896 | D32: 0.15163548 | E32: Bit | G32: PM10-fil | H32: 0.11587072 | I32: 0.11587072 | J32: 0.11587072 | L32: PM10-fil | M32: 0.039353834 | N32: 0.039353834 | O32: 0.039353834
A33: PM-con | B33: Included in PRI values | C33: 0.020878271 | D33: 0.020878271 | E33: Bit | G33: PM2.5-fil | H33: 0.11587072 | I33: 0.11587072 | J33: 0.11587072 | L33: PM2.5-fil | M33: 0.013974309 | N33: 0.013974309 | O33: 0.013974309
A34: PM10-pri | B34: 0.04833645 | C34: 0.049419256 | D34: 0.042493564 | E34: Bit | G34: Condensable PM | H34: Not available | I34: Not available | J34: Not available | L34: Condensable PM | M34: 0.0076791623 | N34: 0.0076791623 | O34: 0.0076791623
A35: PM2.5-pri | B35: 0.040542518 | C35: 0.03732036 | D35: 0.033330559 | E35: Bit
A36: PM10-fil | B36: Not available | C36: 0.028540985 | D36: 0.021615293 | E36: Bit
A37: PM2.5-fil | C37: 0.016442089 | D37: 0.012452288 | E37: Bit | G37: Natural Gas: | L37: Natural Gas (>1 MW) Combined-cycle
H38: Emission Factor (lb/MMBtu Lower Heating Value (LHV) Basis) | M38: Emission Factor (lb/MMBtu Lower Heating Value (LHV) Basis)
G39: Pollutant | H39: 2013 | I39: 2020 | J39: 2030 | L39: Pollutant | M39: 2013 | N39: 2020 | O39: 2030
A40: Coal: >250 mmBtu/hr (EGU-Sub-bituminous) | G40: CO2 | H40: 121.86165 | I40: 122.01783 | J40: 122.28153 | L40: CO2 | M40: 147.98585 | N40: 147.98585 | O40: 147.98585
A41: Pollutant | B41: Emission Factor (lb/MMBtu Lower Heating Value (LHV) Basis) | E41: Coal Type Applicability | G41: CH4 | H41: 0.86499613 | I41: 0.86499613 | J41: 0.86499613 | L41: CH4 | M41: 0.0028713672 | N41: 0.0028713672 | O41: 0.0028713672
B42: 2013 | C42: 2020 | D42: 2030 | G42: N2O | H42: 0.0002442313 | I42: 0.0002442313 | J42: 0.0002442313 | L42: N2O | M42: 0.0028967134 | N42: 0.0028967134 | O42: 0.0028967134
A43: CO2 | B43: 218.79193 | C43: 218.79193 | D43: 218.79193 | E43: Sub-bit | G43: Black Carbon | H43: 0.0063463924 | I43: 0.0063463924 | J43: 0.0063463924 | L43: Black Carbon | M43: 0.002092793 | N43: 0.002092793 | O43: 0.002092793
A44: CH4 | B44: 0.002487109 | C44: 0.002487109 | D44: 0.002487109 | E44: Sub-bit | G44: CO | H44: 1.5564553 | I44: 1.4570651 | J44: 1.2892546 | L44: CO | M44: 0.046898271 | N44: 0.046898271 | O44: 0.046898271
A45: N2O | B45: 0.0037068324 | C45: 0.0037068324 | D45: 0.0037068324 | E45: Sub-bit | G45: VOC | H45: 0.2939128 | I45: 0.28673113 | J45: 0.27314984 | L45: VOC | M45: 0.0006155516 | N45: 0.0006155516 | O45: 0.0006155516
A46: Black Carbon | B46: 0.00022496638 | C46: 0.0015493847 | D46: 0.0013804054 | E46: Sub-bit | G46: NOx | H46: 1.8363533 | I46: 1.6596832 | J46: 1.3853153 | L46: NOx | M46: 0.022793514 | N46: 0.022793514 | O46: 0.022793514
A47: CO | B47: 0.026463447 | C47: 0.026463447 | D47: 0.026463447 | E47: Sub-bit | G47: SOx | H47: 0.0006514059 | I47: 0.0006514059 | J47: 0.0006514059 | L47: SOx | M47: 0.00073504103 | N47: 0.00073504103 | O47: 0.00073504103
A48: VOC | B48: 0.0031435498 | C48: 0.0031435498 | D48: 0.0031435498 | E48: Sub-bit | G48: PM10-fil | H48: 0.0048873545 | I48: 0.0048873545 | J48: 0.0048873545 | L48: PM10-fil | M48: 0.00030053402 | N48: 0.00030053402 | O48: 0.00030053402
A49: NOx | B49: 0.28817534 | C49: 0.25091754 | D49: 0.18882119 | E49: Sub-bit | G49: PM2.5-fil | H49: 0.0048873545 | I49: 0.0048873545 | J49: 0.0048873545 | L49: PM2.5-fil | M49: 0.00030053402 | N49: 0.00030053402 | O49: 0.00030053402
A50: SOx | B50: 0.61312437 | C50: 0.16322965 | D50: 0.15041057 | E50: Sub-bit | G50: Condensable PM | H50: 0.010978627 | I50: 0.010978627 | J50: 0.010978627 | L50: Condensable PM | M50: 0.0052068159 | N50: 0.0052068159 | O50: 0.0052068159
A51: PM-con | B51: Included in PRI values | C51: 0.021695789 | D51: 0.021695789 | E51: Sub-bit
A52: PM10-pri | B52: 0.010370898 | C52: 0.051272623 | D52: 0.043939558 | E52: Sub-bit
A53: PM2.5-pri | B53: 0.0056241594 | C53: 0.038734617 | D53: 0.034510134 | E53: Sub-bit | G53: Biogas: | L53: IGCC:
A54: PM10-fil | B54: Not available | C54: 0.029576834 | D54: 0.02224377 | E54: Sub-bit | H54: Emission Factor (lb/MMBtu Lower Heating Value (LHV) Basis) | M54: Emission Factor (g/kWh Net Output Basis)
A55: PM2.5-fil | C55: 0.017038829 | D55: 0.012814346 | E55: Sub-bit | G55: Pollutant | H55: 2013 | I55: 2020 | J55: 2030 | L55: Pollutant | M55: 2013 | N55: 2020 | O55: 2030
G56: CO2 | H56: 127.02363 | I56: 127.02363 | J56: 127.02363 | L56: CO2 | M56: 696.925 | N56: 696.925 | O56: 696.925
G57: CH4 | H57: 0.0023264402 | I57: 0.0023264402 | J57: 0.0023264402 | L57: CH4 | M57: 0.010344828 | N57: 0.010344828 | O57: 0.010344828
A58: Small LPG | G58: N2O | H58: 0.00023264402 | I58: 0.00023264402 | J58: 0.00023264402 | L58: N2O | M58: 0.015517241 | N58: 0.015517241 | O58: 0.015517241
A59: Pollutant | B59: Emission Factor (lb/MMBtu Lower Heating Value (LHV) Basis) | G59: Black Carbon | H59: 0.0061216 | I59: 0.0061216 | J59: 0.0061216 | L59: Black Carbon | M59: NA | N59: NA | O59: NA
B60: 2013 | C60: 2020 | D60: 2030 | G60: CO | H60: 0.5 | I60: 0.5 | J60: 0.5 | L60: CO | M60: 0.1004 | N60: 0.1004 | O60: 0.1004
A61: CO2 | B61: 147.14538 | C61: 147.14538 | D61: 147.14538 | G61: VOC | H61: 0.041 | I61: 0.041 | J61: 0.041 | L61: VOC | M61: 0.0057333333 | N61: 0.0057333333 | O61: 0.0057333333
A62: CH4 | B62: 0.0023543261 | C62: 0.0023543261 | D62: 0.0023543261 | G62: NOx | H62: 0.7 | I62: 0.7 | J62: 0.7 | L62: NOx | M62: 0.1735 | N62: 0.1735 | O62: 0.1735
A63: N2O | B63: 0.010594467 | C63: 0.010594467 | D63: 0.010594467 | G63: SOx | H63: 0.011546508 | I63: 0.011546508 | J63: 0.011546508 | L63: SOx | M63: 0.063475 | N63: 0.063475 | O63: 0.063475
A64: Black Carbon | B64: 0.0035785756 | C64: 0.0035785756 | D64: 0.0035785756 | G64: PM10-fil | H64: 0.013 | I64: 0.013 | J64: 0.013 | L64: PM10-fil | M64: 0.024125 | N64: 0.024125 | O64: 0.024125
A65: CO | B65: 0.007784552 | C65: 0.007784552 | D65: 0.007784552 | G65: PM2.5-fil | H65: 0.013 | I65: 0.013 | J65: 0.013 | L65: PM2.5-fil | M65: NA | N65: NA | O65: NA
A66: VOC | B66: 0.0094173043 | C66: 0.0094173043 | D66: 0.0094173043 | G66: Condensable PM | H66: 0.002304 | I66: 0.002304 | J66: 0.002304 | L66: Condensable PM | M66: NA | N66: NA | O66: NA
A67: NOx | B67: 0.15303119 | C67: 0.15303119 | D67: 0.15303119
A68: SOx | B68: 0.018021077 | C68: 0.018021077 | D68: 0.018021077
A69: PM-con | B69: 0.0070629782 | C69: 0.0070629782 | D69: 0.0070629782 | L69: Biogas (<1 MW)
A70: PM10-fil | B70: 0.0023543261 | C70: 0.0023543261 | D70: 0.0023543261 | M70: Emission Factor (lb/MMBtu Lower Heating Value (LHV) Basis)
A71: PM2.5-fil | B71: 0.0023543261 | C71: 0.0023543261 | D71: 0.0023543261 | L71: Pollutant | M71: 2013 | N71: 2020 | O71: 2030
A72: (Projections same as baseline) | L72: CO2 | M72: 38.5 | N72: 38.5 | O72: 38.5
L73: CH4 | M73: 0.011632201 | N73: 0.011632201 | O73: 0.011632201
L74: N2O | M74: 0.00023264402 | N74: 0.00023264402 | O74: 0.00023264402
A75: Wet Biomass (Forest Residue): >250 mmBtu/hr | L75: Black Carbon | M75: 0.00840142 | N75: 0.00840142 | O75: 0.00840142
A76: Pollutant | B76: Emission Factor (lb/MMBtu Higher Heating Value (HHV) Basis) | L76: CO | M76: 0.2285 | N76: 0.2285 | O76: 0.2285
B77: 2013 | C77: 2020 | D77: 2030 | L77: VOC | M77: 0.0094 | N77: 0.0094 | O77: 0.0094
A78: CO2 | B78: 195 | C78: 195 | D78: 195 | L78: NOx | M78: 0.15 | N78: 0.15 | O78: 0.15
A79: CH4 | B79: 0.021 | C79: 0.021 | D79: 0.021 | L79: SOx | M79: 0.02575 | N79: 0.02575 | O79: 0.02575
A80: N2O | B80: 0.013 | C80: 0.013 | D80: 0.013 | L80: PM10-fil | M80: 0.019805 | N80: 0.019805 | O80: 0.019805
A81: Black Carbon | B81: 0.002796 | C81: 0.0019801327 | D81: 0.0018435218 | L81: PM2.5-fil | M81: 0.019805 | N81: 0.019805 | O81: 0.019805
A82: CO | B82: 0.6 | C82: 0.57510208 | D82: 0.54440731 | L82: Condensable PM | M82: 0.002304 | N82: 0.002304 | O82: 0.002304
A83: VOC | B83: 0.017 | C83: 0.017 | D83: 0.017
A84: NOx | B84: 0.22 | C84: 0.22 | D84: 0.22
A85: SOx | B85: 0.025 | C85: 0.025 | D85: 0.025
A86: PM-con | B86: 0.017 | C86: 0.017 | D86: 0.017
A87: PM10-fil | B87: 0.06095 | C87: 0.026284978 | D87: 0.024497108
A88: PM2.5-fil | B88: 0.0529 | C88: 0.023218339 | D88: 0.021590936
A91: Distillate Liquid: EGU >250 mmBtu/hr
A92: Pollutant | B92: Emission Factor (lb/MMBtu Lower Heating Value (LHV) Basis)
B93: 2013 | C93: 2020 | D93: 2030
A94: CO2 | B94: 173.36954 | C94: 173.36954 | D94: 173.36954
A95: CH4 | B95: 0.0074607855 | C95: 0.0074607855 | D95: 0.0074607855
A96: N2O | B96: 0.0014965674 | C96: 0.0014965674 | D96: 0.0014965674
A97: Black Carbon | B97: 0.0011684399 | C97: 0.0011684399 | D97: 0.0011684399
A98: CO | B98: 0.037690565 | C98: 0.037690565 | D98: 0.037690565
A99: VOC | B99: 0.0057290012 | C99: 0.0057290012 | D99: 0.0057290012
A100: NOx | B100: 0.26337087 | C100: 0.1985639 | D100: 0.16093405
A101: SOx | B101: 0.70800281 | C101: 0.51510826 | D101: 0.40310497
A102: PM-con | B102: Included in PM10/PM2.5 factors | C102: 0.0094628039 | D102: 0.0094628039
A103: PM10-pri | B103: 0.017338424 | C103: 0.016375606 | D103: 0.013912175
A104: PM2.5-pri | B104: 0.011684399 | C104: 0.015884338 | D104: 0.01349481
A107: Residual Oil: EGU >250 mmBtu/hr
A108: Pollutant | B108: Emission Factor (lb/MMBtu Lower Heating Value (LHV) Basis)
...

Sheet Conversions
A1: State to Census Region Conversion | E1: GDP Deflators (Conversion to US$2005) | I1: Standard Conversions
A2: Alabama | B2: AL | C2: 6 | E2: Year | F2: Deflator | G2: Multiply By (for $2005) | I2: from | J2: to | K2: multiply by
A3: Alaska | B3: AK | C3: 9 | E3: 1983 | F3: 57.652 | G3: =$F$25/F3 -> 1.7345452 | I3: Btu | J3: J | K3: 1055
A4: Arizona | B4: AZ | C4: 8 | E4: 1984 | F4: 59.817 | G4: =$F$25/F4 -> 1.6717656 | I4: kWh | J4: MJ | K4: 3.6
A5: Arkansas | B5: AR | C5: 7 | E5: 1985 | F5: 61.628 | G5: =$F$25/F5 -> 1.6226391 | I5: MWh | J5: PJ | K5: 3.599999e-06
A6: California | B6: CA | C6: 9 | E6: 1986 | F6: 62.991 | G6: =$F$25/F6 -> 1.5875284 | I6: PJ | J6: J | K6: 1e+15
A7: Colorado | B7: CO | C7: 8 | E7: 1987 | F7: 64.819 | G7: =$F$25/F7 -> 1.5427575 | I7: MMBtu | J7: J | K7: 1055650000
A8: Connecticut | B8: CT | C8: 1 | E8: 1988 | F8: 67.046 | G8: =$F$25/F8 -> 1.4915133 | I8: yr | J8: hr | K8: 8766
A9: Delaware | B9: DE | C9: 5 | E9: 1989 | F9: 69.577 | G9: =$F$25/F9 -> 1.4372566 | I9: GW | J9: Pja | K9: 31.536
A10: District of Columbia | B10: DC | C10: 5 | E10: 1990 | F10: 72.262 | G10: =$F$25/F10 -> 1.3838532 | I10: $mills/kWh | J10: $Million/PJ | K10: =1/K4 -> 0.27777778
A11: Florida | B11: FL | C11: 5 | E11: 1991 | F11: 74.824 | G11: =$F$25/F11 -> 1.3364696
A12: Georgia | B12: GA | C12: 5 | E12: 1992 | F12: 76.598 | G12: =$F$25/F12 -> 1.3055171
A13: Hawaii | B13: HI | C13: 9 | E13: 1993 | F13: 78.29 | G13: =$F$25/F13 -> 1.2773023
A14: Idaho | B14: ID | C14: 8 | E14: 1994 | F14: 79.94 | G14: =$F$25/F14 -> 1.2509382
A15: Illinois | B15: IL | C15: 3 | E15: 1995 | F15: 81.606 | G15: =$F$25/F15 -> 1.2254001
A16: Indiana | B16: IN | C16: 3 | E16: 1996 | F16: 83.159 | G16: =$F$25/F16 -> 1.2025157
A17: Iowa | B17: IA | C17: 4 | E17: 1997 | F17: 84.628 | G17: =$F$25/F17 -> 1.181642
A18: Kansas | B18: KS | C18: 4 | E18: 1998 | F18: 85.584 | G18: =$F$25/F18 -> 1.1684427
A19: Kentucky | B19: KY | C19: 6 | E19: 1999 | F19: 86.842 | G19: =$F$25/F19 -> 1.1515165
A20: Louisiana | B20: LA | C20: 7 | E20: 2000 | F20: 88.723 | G20: =$F$25/F20 -> 1.1271035
A21: Maine | B21: ME | C21: 1 | E21: 2001 | F21: 90.727 | G21: =$F$25/F21 -> 1.1022077
A22: Maryland | B22: MD | C22: 5 | E22: 2002 | F22: 92.196 | G22: =$F$25/F22 -> 1.0846458
... A30: Nevada | B30: NV | C30: 8 | E30: 2010 | F30: 110.99 | G30: =$F$25/F30 -> 0.90098207
A31: New Hampshire | B31: NH | C31: 1 | E31: 2011 | F31: =103.311*100/91.88 -> 112.44123 | G31: =$F$25/F31 -> 0.88935351
A32: New Jersey | B32: NJ | C32: 2 | E32: 2012 | F32: =105.214*100/91.988 -> 114.37796 | G32: =$F$25/F32 -> 0.8742943
A33: New Mexico | B33: NM | C33: 8 | E33: 2013 | F33: =106.929*100/91.98 -> 116.25245 | G33: =$F$25/F33 -> 0.86019695
A34: New York | B34: NY | C34: 2
A35: North Carolina | B35: NC | C35: 5 | E35: NIPA Table 1.1.9. Implicit Price Deflators for Gross Domestic Product
A36: North Dakota | B36: ND | C36: 4 | E36: [Index numbers, 2005=100]
A37: Ohio | B37: OH | C37: 3 | E37: US Department of Commerce: Bureau of Economic Analysis
A38: Oklahoma | B38: OK | C38: 7 | E38: http://www.bea.gov/national/nipaweb/SelectTable.asp?Selected=Y
A39: Oregon | B39: OR | C39: 9 | E39: Downloaded on 4/20/2012 Last Revised March 29,2012
A40: Pennsylvania | B40: PA | C40: 2
A41: Rhode Island | B41: RI | C41: 1
A42: South Carolina | B42: SC | C42: 5
A43: South Dakota | B43: SD | C43: 4
A44: Tennessee | B44: TN | C44: 6
A45: Texas | B45: TX | C45: 7
A46: Utah | B46: UT | C46: 8
A47: Vermont | B47: VT | C47: 1
A48: Virginia | B48: VA | C48: 5
A49: Washington | B49: WA | C49: 9
A50: West Virginia | B50: WV | C50: 5
A51: Wisconsin | B51: WI | C51: 3
A52: Wyoming | B52: WY | C52: 8
