Workbook
Name AnswerData: #REF!
Name AnswerData: #REF!
Name bprint: #REF!
Name btu_per_watthr: '[1]Conversion Factors'!$B$5
Name CMM_SUPPLY_CRV_TABLE: [2]cum2025curves!#REF!
Name cprint: #REF!
Name days_per_year: '[1]Conversion Factors'!$B$3
Name dollar____per__m: '[1]Conversion Factors'!$B$7
Name exch_rate: #REF!
Name exch_rate: #REF!
Name fitfile: [3]MODEL!$D$38
Name hours_per_day: '[1]Conversion Factors'!$B$2
Name INF: [3]MODEL!$H$14
Name j_per_btu: '[1]Conversion Factors'!$B$4
Name j_per_pj: '[1]Conversion Factors'!$B$6
Name lumens_per_billion_lumens: '[1]Conversion Factors'!$B$9
Name MAXREC: #REF!
Name million_short_tons_to_short_ton: [4]Steps!$Y$5
Name MMBTU_to_PJ: [4]Steps!$Y$6
Name PPP: [3]MODEL!$D$12
Name PPPEX: [3]MODEL!$D$13
Name rail_coal: #REF!
Name rail_coal: #REF!
Name region1: [5]Regions!$B$3:$C$61
Name TECHNAME: #REF!
Name TRNDTYPE: #REF!

Sheet ANSv6.1-Commodities
A1: ANSWER-Commodities
B7: CommName | C7: CommDesc | D7: CommUnit | E7: Set Memberships | F7: Comment

Sheet UC_NGAa
A2: Maximum capacity technology growth:
A3: ~UC_Sets: R_E: R1
A4: ~UC_Sets: T_SUC:
G5: ~UC_T
A6: UC_N | B6: Pset_PN | C6: Pset_CI | D6: Pset_CO | E6: UC_ATTR | F6: Year | G6: LimType | H6: UC_CAP~2010 | I6: UC_CAP~2015 | J6: UC_CAP~2020 | K6: UC_CAP~2025 | L6: UC_CAP~2030 | M6: UC_CAP~2035 | N6: UC_CAP~2040 | O6: UC_CAP~2045 | P6: UC_CAP~2050 | Q6: UC_CAP~2055 | R6: UC_CAP~RHS | S6: UC_RHSRTS | T6: UC_RHSRTS~0 | U6: UC_Desc
A7: UC_GrowthOfNGAR1UP1 | B7: =TechData_R0!B9 -> MINNGAD1 | E7: CAP, GROWTH | G7: UP | H7: =TechData_R0!G9 -> 1.25 | I7: =TechData_R0!H9 -> 1.1 | J7: =I7 -> 1.1 | K7: =TechData_R0!I9 -> 1.1 | L7: =K7 -> 1.1 | M7: =L7 -> 1.1 | N7: =M7 -> 1.1 | O7: =N7 -> 1.1 | P7: =O7 -> 1.1 | Q7: =P7 -> 1.1 | R7: =MAX(1,TechData_R0!F9) -> 1 | T7: 5
A8: UC_GrowthOfNGAR1UP2 | B8: =TechData_R0!B10 -> MINNGAD2 | E8: CAP, GROWTH | G8: UP | H8: =TechData_R0!G10 -> 1.25 | I8: =TechData_R0!H10 -> 1.1 | J8: =I8 -> 1.1 | K8: =TechData_R0!I10 -> 1.1 | L8: =K8 -> 1.1 | M8: =L8 -> 1.1 | N8: =M8 -> 1.1 | O8: =N8 -> 1.1 | P8: =O8 -> 1.1 | Q8: =P8 -> 1.1 | R8: =MAX(1,TechData_R0!F10) -> 1 | T8: 5
A9: UC_GrowthOfNGAR1UP3 | B9: =TechData_R0!B11 -> MINNGAD3 | E9: CAP, GROWTH | G9: UP | H9: =TechData_R0!G11 -> 1.25 | I9: =TechData_R0!H11 -> 1.1 | J9: =I9 -> 1.1 | K9: =TechData_R0!I11 -> 1.1 | L9: =K9 -> 1.1 | M9: =L9 -> 1.1 | N9: =M9 -> 1.1 | O9: =N9 -> 1.1 | P9: =O9 -> 1.1 | Q9: =P9 -> 1.1 | R9: =MAX(1,TechData_R0!F11) -> 1 | T9: 5
A10: UC_GrowthOfNGAR1UP4 | B10: =TechData_R0!B12 -> MINNGAD4 | E10: CAP, GROWTH | G10: UP | H10: =TechData_R0!G12 -> 1.25 | I10: =TechData_R0!H12 -> 1.1 | J10: =I10 -> 1.1 | K10: =TechData_R0!I12 -> 1.1 | L10: =K10 -> 1.1 | M10: =L10 -> 1.1 | N10: =M10 -> 1.1 | O10: =N10 -> 1.1 | P10: =O10 -> 1.1 | Q10: =P10 -> 1.1 | R10: =MAX(1,TechData_R0!F12) -> 1 | T10: 5
A11: UC_GrowthOfNGAR1UP5 | B11: =TechData_R0!B13 -> MINNGAD5 | E11: CAP, GROWTH | G11: UP | H11: =TechData_R0!G13 -> 1.25 | I11: =TechData_R0!H13 -> 1.1 | J11: =I11 -> 1.1 | K11: =TechData_R0!I13 -> 1.1 | L11: =K11 -> 1.1 | M11: =L11 -> 1.1 | N11: =M11 -> 1.1 | O11: =N11 -> 1.1 | P11: =O11 -> 1.1 | Q11: =P11 -> 1.1 | R11: =MAX(1,TechData_R0!F13) -> #REF! | T11: 5
A12: UC_GrowthOfNGAR1UP6 | B12: =TechData_R0!B14 -> MINNGAD6 | E12: CAP, GROWTH | G12: UP | H12: =TechData_R0!G14 -> 1.25 | I12: =TechData_R0!H14 -> 1.1 | J12: =I12 -> 1.1 | K12: =TechData_R0!I14 -> 1.1 | L12: =K12 -> 1.1 | M12: =L12 -> 1.1 | N12: =M12 -> 1.1 | O12: =N12 -> 1.1 | P12: =O12 -> 1.1 | Q12: =P12 -> 1.1 | R12: =MAX(1,TechData_R0!F14) -> #REF! | T12: 5
G14: ~UC_T
A15: UC_N | B15: Pset_PN | C15: Pset_CI | D15: Pset_CO | E15: UC_ATTR | F15: Year | G15: LimType | H15: UC_CAP~2010 | I15: UC_CAP~2015 | J15: UC_CAP~2020 | K15: UC_CAP~2025 | L15: UC_CAP~2030 | M15: UC_CAP~2035 | N15: UC_CAP~2040 | O15: UC_CAP~2045 | P15: UC_CAP~2050 | Q15: UC_CAP~2055 | R15: UC_CAP~RHS | S15: UC_RHSRTS | T15: UC_RHSRTS~0 | U15: UC_Desc
A16: UC_GrowthOfNGAR1LO1 | B16: =TechData_R0!B9 -> MINNGAD1 | E16: CAP, GROWTH | G16: LO | H16: =1-TechData_R0!J9+1 -> 0.9 | I16: =1-TechData_R0!K9+1 -> 0.99 | J16: =I16 -> 0.99 | K16: =J16 -> 0.99 | L16: =K16 -> 0.99 | M16: =L16 -> 0.99 | N16: =M16 -> 0.99 | O16: =N16 -> 0.99 | P16: =O16 -> 0.99 | Q16: =P16 -> 0.99 | R16: 1 | T16: 5
A17: UC_GrowthOfNGAR1LO2 | B17: =TechData_R0!B10 -> MINNGAD2 | E17: CAP, GROWTH | G17: LO | H17: =1-TechData_R0!J10+1 -> 0.9 | I17: =1-TechData_R0!K10+1 -> 0.99 | J17: =I17 -> 0.99 | K17: =J17 -> 0.99 | L17: =K17 -> 0.99 | M17: =L17 -> 0.99 | N17: =M17 -> 0.99 | O17: =N17 -> 0.99 | P17: =O17 -> 0.99 | Q17: =P17 -> 0.99 | R17: 1 | T17: 5
A18: UC_GrowthOfNGAR1LO3 | B18: =TechData_R0!B11 -> MINNGAD3 | E18: CAP, GROWTH | G18: LO | H18: =1-TechData_R0!J11+1 -> 0.9 | I18: =1-TechData_R0!K11+1 -> 0.99 | J18: =I18 -> 0.99 | K18: =J18 -> 0.99 | L18: =K18 -> 0.99 | M18: =L18 -> 0.99 | N18: =M18 -> 0.99 | O18: =N18 -> 0.99 | P18: =O18 -> 0.99 | Q18: =P18 -> 0.99 | R18: 1 | T18: 5
A19: UC_GrowthOfNGAR1LO4 | B19: =TechData_R0!B12 -> MINNGAD4 | E19: CAP, GROWTH | G19: LO | H19: =1-TechData_R0!J12+1 -> 0.9 | I19: =1-TechData_R0!K12+1 -> 0.99 | J19: =I19 -> 0.99 | K19: =J19 -> 0.99 | L19: =K19 -> 0.99 | M19: =L19 -> 0.99 | N19: =M19 -> 0.99 | O19: =N19 -> 0.99 | P19: =O19 -> 0.99 | Q19: =P19 -> 0.99 | R19: 1 | T19: 5
A20: UC_GrowthOfNGAR1LO5 | B20: =TechData_R0!B13 -> MINNGAD5 | E20: CAP, GROWTH | G20: LO | H20: =1-TechData_R0!J13+1 -> 0.9 | I20: =1-TechData_R0!K13+1 -> 0.99 | J20: =I20 -> 0.99 | K20: =J20 -> 0.99 | L20: =K20 -> 0.99 | M20: =L20 -> 0.99 | N20: =M20 -> 0.99 | O20: =N20 -> 0.99 | P20: =O20 -> 0.99 | Q20: =P20 -> 0.99 | R20: 1 | T20: 5
A21: UC_GrowthOfNGAR1LO6 | B21: =TechData_R0!B14 -> MINNGAD6 | E21: CAP, GROWTH | G21: LO | H21: =1-TechData_R0!J14+1 -> 0.9 | I21: =1-TechData_R0!K14+1 -> 0.99 | J21: =I21 -> 0.99 | K21: =J21 -> 0.99 | L21: =K21 -> 0.99 | M21: =L21 -> 0.99 | N21: =M21 -> 0.99 | O21: =N21 -> 0.99 | P21: =O21 -> 0.99 | Q21: =P21 -> 0.99 | R21: 1 | T21: 5
A24: Maximum capacity technology growth:
A25: ~UC_Sets: R_E: R2
A26: ~UC_Sets: T_SUC:
G27: ~UC_T
A28: UC_N | B28: Pset_PN | C28: Pset_CI | D28: Pset_CO | E28: UC_ATTR | F28: Year | G28: LimType | H28: UC_CAP~2010 | I28: UC_CAP~2015 | J28: UC_CAP~2020 | K28: UC_CAP~2025 | L28: UC_CAP~2030 | M28: UC_CAP~2035 | N28: UC_CAP~2040 | O28: UC_CAP~2045 | P28: UC_CAP~2050 | Q28: UC_CAP~2055 | R28: UC_CAP~RHS | S28: UC_RHSRTS | T28: UC_RHSRTS~0 | U28: UC_Desc
A29: UC_GrowthOfNGAR2UP1 | B29: =TechData_R0!B16 -> MINNGAD1 | E29: CAP, GROWTH | G29: UP | H29: =TechData_R0!G16 -> 1.25 | I29: =TechData_R0!H16 -> 1.1 | J29: =I29 -> 1.1 | K29: =TechData_R0!I16 -> 1.1 | L29: =K29 -> 1.1 | M29: =L29 -> 1.1 | N29: =M29 -> 1.1 | O29: =N29 -> 1.1 | P29: =O29 -> 1.1 | Q29: =P29 -> 1.1 | R29: =MAX(1,TechData_R0!F16) -> 1 | T29: 5
A30: UC_GrowthOfNGAR2UP2 | B30: =TechData_R0!B17 -> MINNGAD2 | E30: CAP, GROWTH | G30: UP | H30: =TechData_R0!G17 -> 1.25 | I30: =TechData_R0!H17 -> 1.1 | J30: =I30 -> 1.1 | K30: =TechData_R0!I17 -> 1.1 | L30: =K30 -> 1.1 | M30: =L30 -> 1.1 | N30: =M30 -> 1.1 | O30: =N30 -> 1.1 | P30: =O30 -> 1.1 | Q30: =P30 -> 1.1 | R30: =MAX(1,TechData_R0!F17) -> 1 | T30: 5
A31: UC_GrowthOfNGAR2UP3 | B31: =TechData_R0!B18 -> MINNGAD3 | E31: CAP, GROWTH | G31: UP | H31: =TechData_R0!G18 -> 1.25 | I31: =TechData_R0!H18 -> 1.1 | J31: =I31 -> 1.1 | K31: =TechData_R0!I18 -> 1.1 | L31: =K31 -> 1.1 | M31: =L31 -> 1.1 | N31: =M31 -> 1.1 | O31: =N31 -> 1.1 | P31: =O31 -> 1.1 | Q31: =P31 -> 1.1 | R31: =MAX(1,TechData_R0!F18) -> 1 | T31: 5
A32: UC_GrowthOfNGAR2UP4 | B32: =TechData_R0!B19 -> MINNGAD4 | E32: CAP, GROWTH | G32: UP | H32: =TechData_R0!G19 -> 1.25 | I32: =TechData_R0!H19 -> 1.1 | J32: =I32 -> 1.1 | K32: =TechData_R0!I19 -> 1.1 | L32: =K32 -> 1.1 | M32: =L32 -> 1.1 | N32: =M32 -> 1.1 | O32: =N32 -> 1.1 | P32: =O32 -> 1.1 | Q32: =P32 -> 1.1 | R32: =MAX(1,TechData_R0!F19) -> 1 | T32: 5
A33: UC_GrowthOfNGAR2UP5 | B33: =TechData_R0!B20 -> MINNGAD5 | E33: CAP, GROWTH | G33: UP | H33: =TechData_R0!G20 -> 1.25 | I33: =TechData_R0!H20 -> 1.1 | J33: =I33 -> 1.1 | K33: =TechData_R0!I20 -> 1.1 | L33: =K33 -> 1.1 | M33: =L33 -> 1.1 | N33: =M33 -> 1.1 | O33: =N33 -> 1.1 | P33: =O33 -> 1.1 | Q33: =P33 -> 1.1 | R33: =MAX(1,TechData_R0!F20) -> 1 | T33: 5
A34: UC_GrowthOfNGAR2UP6 | B34: =TechData_R0!B21 -> MINNGAD6 | E34: CAP, GROWTH | G34: UP | H34: =TechData_R0!G21 -> 1.25 | I34: =TechData_R0!H21 -> 1.1 | J34: =I34 -> 1.1 | K34: =TechData_R0!I21 -> 1.1 | L34: =K34 -> 1.1 | M34: =L34 -> 1.1 | N34: =M34 -> 1.1 | O34: =N34 -> 1.1 | P34: =O34 -> 1.1 | Q34: =P34 -> 1.1 | R34: =MAX(1,TechData_R0!F21) -> 1 | T34: 5
G36: ~UC_T
A37: UC_N | B37: Pset_PN | C37: Pset_CI | D37: Pset_CO | E37: UC_ATTR | F37: Year | G37: LimType | H37: UC_CAP~2010 | I37: UC_CAP~2015 | J37: UC_CAP~2020 | K37: UC_CAP~2025 | L37: UC_CAP~2030 | M37: UC_CAP~2035 | N37: UC_CAP~2040 | O37: UC_CAP~2045 | P37: UC_CAP~2050 | Q37: UC_CAP~2055 | R37: UC_CAP~RHS | S37: UC_RHSRTS | T37: UC_RHSRTS~0 | U37: UC_Desc
A38: UC_GrowthOfNGAR2LO1 | B38: =TechData_R0!B16 -> MINNGAD1 | E38: CAP, GROWTH | G38: LO | H38: =1-TechData_R0!J16+1 -> 0.9 | I38: =1-TechData_R0!K16+1 -> 0.99 | J38: =I38 -> 0.99 | K38: =J38 -> 0.99 | L38: =K38 -> 0.99 | M38: =L38 -> 0.99 | N38: =M38 -> 0.99 | O38: =N38 -> 0.99 | P38: =O38 -> 0.99 | Q38: =P38 -> 0.99 | R38: 1 | T38: 5
A39: UC_GrowthOfNGAR2LO2 | B39: =TechData_R0!B17 -> MINNGAD2 | E39: CAP, GROWTH | G39: LO | H39: =1-TechData_R0!J17+1 -> 0.9 | I39: =1-TechData_R0!K17+1 -> 0.99 | J39: =I39 -> 0.99 | K39: =J39 -> 0.99 | L39: =K39 -> 0.99 | M39: =L39 -> 0.99 | N39: =M39 -> 0.99 | O39: =N39 -> 0.99 | P39: =O39 -> 0.99 | Q39: =P39 -> 0.99 | R39: 1 | T39: 5
A40: UC_GrowthOfNGAR2LO3 | B40: =TechData_R0!B18 -> MINNGAD3 | E40: CAP, GROWTH | G40: LO | H40: =1-TechData_R0!J18+1 -> 0.9 | I40: =1-TechData_R0!K18+1 -> 0.99 | J40: =I40 -> 0.99 | K40: =J40 -> 0.99 | L40: =K40 -> 0.99 | M40: =L40 -> 0.99 | N40: =M40 -> 0.99 | O40: =N40 -> 0.99 | P40: =O40 -> 0.99 | Q40: =P40 -> 0.99 | R40: 1 | T40: 5
A41: UC_GrowthOfNGAR2LO4 | B41: =TechData_R0!B19 -> MINNGAD4 | E41: CAP, GROWTH | G41: LO | H41: =1-TechData_R0!J19+1 -> 0.9 | I41: =1-TechData_R0!K19+1 -> 0.99 | J41: =I41 -> 0.99 | K41: =J41 -> 0.99 | L41: =K41 -> 0.99 | M41: =L41 -> 0.99 | N41: =M41 -> 0.99 | O41: =N41 -> 0.99 | P41: =O41 -> 0.99 | Q41: =P41 -> 0.99 | R41: 1 | T41: 5
A42: UC_GrowthOfNGAR2LO5 | B42: =TechData_R0!B20 -> MINNGAD5 | E42: CAP, GROWTH | G42: LO | H42: =1-TechData_R0!J20+1 -> 0.9 | I42: =1-TechData_R0!K20+1 -> 0.99 | J42: =I42 -> 0.99 | K42: =J42 -> 0.99 | L42: =K42 -> 0.99 | M42: =L42 -> 0.99 | N42: =M42 -> 0.99 | O42: =N42 -> 0.99 | P42: =O42 -> 0.99 | Q42: =P42 -> 0.99 | R42: 1 | T42: 5
A43: UC_GrowthOfNGAR2LO6 | B43: =TechData_R0!B21 -> MINNGAD6 | E43: CAP, GROWTH | G43: LO | H43: =1-TechData_R0!J21+1 -> 0.9 | I43: =1-TechData_R0!K21+1 -> 0.99 | J43: =I43 -> 0.99 | K43: =J43 -> 0.99 | L43: =K43 -> 0.99 | M43: =L43 -> 0.99 | N43: =M43 -> 0.99 | O43: =N43 -> 0.99 | P43: =O43 -> 0.99 | Q43: =P43 -> 0.99 | R43: 1 | T43: 5
A46: Maximum capacity technology growth:
A47: ~UC_Sets: R_E: R3
A48: ~UC_Sets: T_SUC:
G49: ~UC_T
A50: UC_N | B50: Pset_PN | C50: Pset_CI | D50: Pset_CO | E50: UC_ATTR | F50: Year | G50: LimType | H50: UC_CAP~2010 | I50: UC_CAP~2015 | J50: UC_CAP~2020 | K50: UC_CAP~2025 | L50: UC_CAP~2030 | M50: UC_CAP~2035 | N50: UC_CAP~2040 | O50: UC_CAP~2045 | P50: UC_CAP~2050 | Q50: UC_CAP~2055 | R50: UC_CAP~RHS | S50: UC_RHSRTS | T50: UC_RHSRTS~0 | U50: UC_Desc
A51: UC_GrowthOfNGAR3UP1 | B51: =TechData_R0!B23 -> MINNGAD1 | E51: CAP, GROWTH | G51: UP | H51: =TechData_R0!G23 -> 1.25 | I51: =TechData_R0!H23 -> 1.1 | J51: =I51 -> 1.1 | K51: =TechData_R0!I23 -> 1.1 | L51: =K51 -> 1.1 | M51: =L51 -> 1.1 | N51: =M51 -> 1.1 | O51: =N51 -> 1.1 | P51: =O51 -> 1.1 | Q51: =P51 -> 1.1 | R51: =MAX(1,TechData_R0!F23) -> 1 | T51: 5
A52: UC_GrowthOfNGAR3UP2 | B52: =TechData_R0!B24 -> MINNGAD2 | E52: CAP, GROWTH | G52: UP | H52: =TechData_R0!G24 -> 1.25 | I52: =TechData_R0!H24 -> 1.1 | J52: =I52 -> 1.1 | K52: =TechData_R0!I24 -> 1.1 | L52: =K52 -> 1.1 | M52: =L52 -> 1.1 | N52: =M52 -> 1.1 | O52: =N52 -> 1.1 | P52: =O52 -> 1.1 | Q52: =P52 -> 1.1 | R52: =MAX(1,TechData_R0!F24) -> 1 | T52: 5
A53: UC_GrowthOfNGAR3UP3 | B53: =TechData_R0!B25 -> MINNGAD3 | E53: CAP, GROWTH | G53: UP | H53: =TechData_R0!G25 -> 1.25 | I53: =TechData_R0!H25 -> 1.1 | J53: =I53 -> 1.1 | K53: =TechData_R0!I25 -> 1.1 | L53: =K53 -> 1.1 | M53: =L53 -> 1.1 | N53: =M53 -> 1.1 | O53: =N53 -> 1.1 | P53: =O53 -> 1.1 | Q53: =P53 -> 1.1 | R53: =MAX(1,TechData_R0!F25) -> 1 | T53: 5
A54: UC_GrowthOfNGAR3UP4 | B54: =TechData_R0!B26 -> MINNGAD4 | E54: CAP, GROWTH | G54: UP | H54: =TechData_R0!G26 -> 1.1 | I54: =TechData_R0!H26 -> 1.1 | J54: =I54 -> 1.1 | K54: =TechData_R0!I26 -> 1.1 | L54: =K54 -> 1.1 | M54: =L54 -> 1.1 | N54: =M54 -> 1.1 | O54: =N54 -> 1.1 | P54: =O54 -> 1.1 | Q54: =P54 -> 1.1 | R54: =MAX(1,TechData_R0!F26) -> 1 | T54: 5
A55: UC_GrowthOfNGAR3UP5 | B55: =TechData_R0!B27 -> MINNGAD5 | E55: CAP, GROWTH | G55: UP | H55: =TechData_R0!G27 -> 1.01 | I55: =TechData_R0!H27 -> 1.01 | J55: =I55 -> 1.01 | K55: =TechData_R0!I27 -> 1.01 | L55: =K55 -> 1.01 | M55: =L55 -> 1.01 | N55: =M55 -> 1.01 | O55: =N55 -> 1.01 | P55: =O55 -> 1.01 | Q55: =P55 -> 1.01 | R55: =MAX(1,TechData_R0!F27) -> 1 | T55: 5
A56: UC_GrowthOfNGAR3UP6 | B56: =TechData_R0!B28 -> MINNGAD6 | E56: CAP, GROWTH | G56: UP | H56: =TechData_R0!G28 -> 1.01 | I56: =TechData_R0!H28 -> 1.01 | J56: =I56 -> 1.01 | K56: =TechData_R0!I28 -> 1.01 | L56: =K56 -> 1.01 | M56: =L56 -> 1.01 | N56: =M56 -> 1.01 | O56: =N56 -> 1.01 | P56: =O56 -> 1.01 | Q56: =P56 -> 1.01 | R56: =MAX(1,TechData_R0!F28) -> 1 | T56: 5
G58: ~UC_T
A59: UC_N | B59: Pset_PN | C59: Pset_CI | D59: Pset_CO | E59: UC_ATTR | F59: Year | G59: LimType | H59: UC_CAP~2010 | I59: UC_CAP~2015 | J59: UC_CAP~2020 | K59: UC_CAP~2025 | L59: UC_CAP~2030 | M59: UC_CAP~2035 | N59: UC_CAP~2040 | O59: UC_CAP~2045 | P59: UC_CAP~2050 | Q59: UC_CAP~2055 | R59: UC_CAP~RHS | S59: UC_RHSRTS | T59: UC_RHSRTS~0 | U59: UC_Desc
A60: UC_GrowthOfNGAR3LO1 | B60: =TechData_R0!B23 -> MINNGAD1 | E60: CAP, GROWTH | G60: LO | H60: =1-TechData_R0!J23+1 -> 0.9 | I60: =1-TechData_R0!K23+1 -> 0.99 | J60: =I60 -> 0.99 | K60: =J60 -> 0.99 | L60: =K60 -> 0.99 | M60: =L60 -> 0.99 | N60: =M60 -> 0.99 | O60: =N60 -> 0.99 | P60: =O60 -> 0.99 | Q60: =P60 -> 0.99 | R60: 1 | T60: 5
A61: UC_GrowthOfNGAR3LO2 | B61: =TechData_R0!B24 -> MINNGAD2 | E61: CAP, GROWTH | G61: LO | H61: =1-TechData_R0!J24+1 -> 0.9 | I61: =1-TechData_R0!K24+1 -> 0.99 | J61: =I61 -> 0.99 | K61: =J61 -> 0.99 | L61: =K61 -> 0.99 | M61: =L61 -> 0.99 | N61: =M61 -> 0.99 | O61: =N61 -> 0.99 | P61: =O61 -> 0.99 | Q61: =P61 -> 0.99 | R61: 1 | T61: 5
A62: UC_GrowthOfNGAR3LO3 | B62: =TechData_R0!B25 -> MINNGAD3 | E62: CAP, GROWTH | G62: LO | H62: =1-TechData_R0!J25+1 -> 0.9 | I62: =1-TechData_R0!K25+1 -> 0.99 | J62: =I62 -> 0.99 | K62: =J62 -> 0.99 | L62: =K62 -> 0.99 | M62: =L62 -> 0.99 | N62: =M62 -> 0.99 | O62: =N62 -> 0.99 | P62: =O62 -> 0.99 | Q62: =P62 -> 0.99 | R62: 1 | T62: 5
A63: UC_GrowthOfNGAR3LO4 | B63: =TechData_R0!B26 -> MINNGAD4 | E63: CAP, GROWTH | G63: LO | H63: =1-TechData_R0!J26+1 -> 0.9 | I63: =1-TechData_R0!K26+1 -> 0.99 | J63: =I63 -> 0.99 | K63: =J63 -> 0.99 | L63: =K63 -> 0.99 | M63: =L63 -> 0.99 | N63: =M63 -> 0.99 | O63: =N63 -> 0.99 | P63: =O63 -> 0.99 | Q63: =P63 -> 0.99 | R63: 1 | T63: 5
A64: UC_GrowthOfNGAR3LO5 | B64: =TechData_R0!B27 -> MINNGAD5 | E64: CAP, GROWTH | G64: LO | H64: =1-TechData_R0!J27+1 -> 0.9 | I64: =1-TechData_R0!K27+1 -> 0.99 | J64: =I64 -> 0.99 | K64: =J64 -> 0.99 | L64: =K64 -> 0.99 | M64: =L64 -> 0.99 | N64: =M64 -> 0.99 | O64: =N64 -> 0.99 | P64: =O64 -> 0.99 | Q64: =P64 -> 0.99 | R64: 1 | T64: 5
A65: UC_GrowthOfNGAR3LO6 | B65: =TechData_R0!B28 -> MINNGAD6 | E65: CAP, GROWTH | G65: LO | H65: =1-TechData_R0!J28+1 -> 0.9 | I65: =1-TechData_R0!K28+1 -> 0.99 | J65: =I65 -> 0.99 | K65: =J65 -> 0.99 | L65: =K65 -> 0.99 | M65: =L65 -> 0.99 | N65: =M65 -> 0.99 | O65: =N65 -> 0.99 | P65: =O65 -> 0.99 | Q65: =P65 -> 0.99 | R65: 1 | T65: 5
A67: Maximum capacity technology growth:
A68: ~UC_Sets: R_E: R4
A69: ~UC_Sets: T_SUC:
G70: ~UC_T
A71: UC_N | B71: Pset_PN | C71: Pset_CI | D71: Pset_CO | E71: UC_ATTR | F71: Year | G71: LimType | H71: UC_CAP~2010 | I71: UC_CAP~2015 | J71: UC_CAP~2020 | K71: UC_CAP~2025 | L71: UC_CAP~2030 | M71: UC_CAP~2035 | N71: UC_CAP~2040 | O71: UC_CAP~2045 | P71: UC_CAP~2050 | Q71: UC_CAP~2055 | R71: UC_CAP~RHS | S71: UC_RHSRTS | T71: UC_RHSRTS~0 | U71: UC_Desc
A72: UC_GrowthOfNGAR4UP1 | B72: =TechData_R0!B30 -> MINNGAD1 | E72: CAP, GROWTH | G72: UP | H72: =TechData_R0!G30 -> 1.1 | I72: =TechData_R0!H30 -> 1.05 | J72: =I72 -> 1.05 | K72: =TechData_R0!I30 -> 1.01 | L72: =K72 -> 1.01 | M72: =L72 -> 1.01 | N72: =M72 -> 1.01 | O72: =N72 -> 1.01 | P72: =O72 -> 1.01 | Q72: =P72 -> 1.01 | R72: =MAX(1,TechData_R0!F30) -> 1 | T72: 5
A73: UC_GrowthOfNGAR4UP2 | B73: =TechData_R0!B31 -> MINNGAD2 | E73: CAP, GROWTH | G73: UP | H73: =TechData_R0!G31 -> 1.2 | I73: =TechData_R0!H31 -> 1.1 | J73: =I73 -> 1.1 | K73: =TechData_R0!I31 -> 1.05 | L73: =K73 -> 1.05 | M73: =L73 -> 1.05 | N73: =M73 -> 1.05 | O73: =N73 -> 1.05 | P73: =O73 -> 1.05 | Q73: =P73 -> 1.05 | R73: =MAX(1,TechData_R0!F31) -> 1 | T73: 5
A74: UC_GrowthOfNGAR4UP3 | B74: =TechData_R0!B32 -> MINNGAD3 | E74: CAP, GROWTH | G74: UP | H74: =TechData_R0!G32 -> 1.1 | I74: =TechData_R0!H32 -> 1.1 | J74: =I74 -> 1.1 | K74: =TechData_R0!I32 -> 1.05 | L74: =K74 -> 1.05 | M74: =L74 -> 1.05 | N74: =M74 -> 1.05 | O74: =N74 -> 1.05 | P74: =O74 -> 1.05 | Q74: =P74 -> 1.05 | R74: =MAX(1,TechData_R0!F32) -> 1 | T74: 5
A75: UC_GrowthOfNGAR4UP4 | B75: =TechData_R0!B33 -> MINNGAD4 | E75: CAP, GROWTH | G75: UP | H75: =TechData_R0!G33 -> 1.1 | I75: =TechData_R0!H33 -> 1.1 | J75: =I75 -> 1.1 | K75: =TechData_R0!I33 -> 1.1 | L75: =K75 -> 1.1 | M75: =L75 -> 1.1 | N75: =M75 -> 1.1 | O75: =N75 -> 1.1 | P75: =O75 -> 1.1 | Q75: =P75 -> 1.1 | R75: =MAX(1,TechData_R0!F33) -> 1 | T75: 5
A76: UC_GrowthOfNGAR4UP5 | B76: =TechData_R0!B34 -> MINNGAD5 | E76: CAP, GROWTH | G76: UP | H76: =TechData_R0!G34 -> 1.01 | I76: =TechData_R0!H34 -> 1.01 | J76: =I76 -> 1.01 | K76: =TechData_R0!I34 -> 1.01 | L76: =K76 -> 1.01 | M76: =L76 -> 1.01 | N76: =M76 -> 1.01 | O76: =N76 -> 1.01 | P76: =O76 -> 1.01 | Q76: =P76 -> 1.01 | R76: =MAX(1,TechData_R0!F34) -> 1 | T76: 5
A77: UC_GrowthOfNGAR4UP6 | B77: =TechData_R0!B35 -> MINNGAD6 | E77: CAP, GROWTH | G77: UP | H77: =TechData_R0!G35 -> 1.01 | I77: =TechData_R0!H35 -> 1.01 | J77: =I77 -> 1.01 | K77: =TechData_R0!I35 -> 1.01 | L77: =K77 -> 1.01 | M77: =L77 -> 1.01 | N77: =M77 -> 1.01 | O77: =N77 -> 1.01 | P77: =O77 -> 1.01 | Q77: =P77 -> 1.01 | R77: =MAX(1,TechData_R0!F35) -> 1 | T77: 5
G79: ~UC_T
A80: UC_N | B80: Pset_PN | C80: Pset_CI | D80: Pset_CO | E80: UC_ATTR | F80: Year | G80: LimType | H80: UC_CAP~2010 | I80: UC_CAP~2015 | J80: UC_CAP~2020 | K80: UC_CAP~2025 | L80: UC_CAP~2030 | M80: UC_CAP~2035 | N80: UC_CAP~2040 | O80: UC_CAP~2045 | P80: UC_CAP~2050 | Q80: UC_CAP~2055 | R80: UC_CAP~RHS | S80: UC_RHSRTS | T80: UC_RHSRTS~0 | U80: UC_Desc
A81: UC_GrowthOfNGAR4LO1 | B81: =TechData_R0!B30 -> MINNGAD1 | E81: CAP, GROWTH | G81: LO | H81: =1-TechData_R0!J30+1 -> 0.9 | I81: =1-TechData_R0!K30+1 -> 0.99 | J81: =I81 -> 0.99 | K81: =J81 -> 0.99 | L81: =K81 -> 0.99 | M81: =L81 -> 0.99 | N81: =M81 -> 0.99 | O81: =N81 -> 0.99 | P81: =O81 -> 0.99 | Q81: =P81 -> 0.99 | R81: 1 | T81: 5
A82: UC_GrowthOfNGAR4LO2 | B82: =TechData_R0!B31 -> MINNGAD2 | E82: CAP, GROWTH | G82: LO | H82: =1-TechData_R0!J31+1 -> 0.9 | I82: =1-TechData_R0!K31+1 -> 0.99 | J82: =I82 -> 0.99 | K82: =J82 -> 0.99 | L82: =K82 -> 0.99 | M82: =L82 -> 0.99 | N82: =M82 -> 0.99 | O82: =N82 -> 0.99 | P82: =O82 -> 0.99 | Q82: =P82 -> 0.99 | R82: 1 | T82: 5
A83: UC_GrowthOfNGAR4LO3 | B83: =TechData_R0!B32 -> MINNGAD3 | E83: CAP, GROWTH | G83: LO | H83: =1-TechData_R0!J32+1 -> 0.9 | I83: =1-TechData_R0!K32+1 -> 0.99 | J83: =I83 -> 0.99 | K83: =J83 -> 0.99 | L83: =K83 -> 0.99 | M83: =L83 -> 0.99 | N83: =M83 -> 0.99 | O83: =N83 -> 0.99 | P83: =O83 -> 0.99 | Q83: =P83 -> 0.99 | R83: 1 | T83: 5
A84: UC_GrowthOfNGAR4LO4 | B84: =TechData_R0!B33 -> MINNGAD4 | E84: CAP, GROWTH | G84: LO | H84: =1-TechData_R0!J33+1 -> 0.9 | I84: =1-TechData_R0!K33+1 -> 0.99 | J84: =I84 -> 0.99 | K84: =J84 -> 0.99 | L84: =K84 -> 0.99 | M84: =L84 -> 0.99 | N84: =M84 -> 0.99 | O84: =N84 -> 0.99 | P84: =O84 -> 0.99 | Q84: =P84 -> 0.99 | R84: 1 | T84: 5
A85: UC_GrowthOfNGAR4LO5 | B85: =TechData_R0!B34 -> MINNGAD5 | E85: CAP, GROWTH | G85: LO | H85: =1-TechData_R0!J34+1 -> 0.9 | I85: =1-TechData_R0!K34+1 -> 0.99 | J85: =I85 -> 0.99 | K85: =J85 -> 0.99 | L85: =K85 -> 0.99 | M85: =L85 -> 0.99 | N85: =M85 -> 0.99 | O85: =N85 -> 0.99 | P85: =O85 -> 0.99 | Q85: =P85 -> 0.99 | R85: 1 | T85: 5
A86: UC_GrowthOfNGAR4LO6 | B86: =TechData_R0!B35 -> MINNGAD6 | E86: CAP, GROWTH | G86: LO | H86: =1-TechData_R0!J35+1 -> 0.9 | I86: =1-TechData_R0!K35+1 -> 0.99 | J86: =I86 -> 0.99 | K86: =J86 -> 0.99 | L86: =K86 -> 0.99 | M86: =L86 -> 0.99 | N86: =M86 -> 0.99 | O86: =N86 -> 0.99 | P86: =O86 -> 0.99 | Q86: =P86 -> 0.99 | R86: 1 | T86: 5
A88: Maximum capacity technology growth:
A89: ~UC_Sets: R_E: R5
A90: ~UC_Sets: T_SUC:
G91: ~UC_T
A92: UC_N | B92: Pset_PN | C92: Pset_CI | D92: Pset_CO | E92: UC_ATTR | F92: Year | G92: LimType | H92: UC_CAP~2010 | I92: UC_CAP~2015 | J92: UC_CAP~2020 | K92: UC_CAP~2025 | L92: UC_CAP~2030 | M92: UC_CAP~2035 | N92: UC_CAP~2040 | O92: UC_CAP~2045 | P92: UC_CAP~2050 | Q92: UC_CAP~2055 | R92: UC_CAP~RHS | S92: UC_RHSRTS | T92: UC_RHSRTS~0 | U92: UC_Desc
A93: UC_GrowthOfNGAR5UP1 | B93: =TechData_R0!B37 -> MINNGAD1 | E93: CAP, GROWTH | G93: UP | H93: =TechData_R0!G37 -> 1.1 | I93: =TechData_R0!H37 -> 1.05 | J93: =I93 -> 1.05 | K93: =TechData_R0!I37 -> 1.01 | L93: =K93 -> 1.01 | M93: =L93 -> 1.01 | N93: =M93 -> 1.01 | O93: =N93 -> 1.01 | P93: =O93 -> 1.01 | Q93: =P93 -> 1.01 | R93: =MAX(1,TechData_R0!F37) -> 1 | T93: 5
A94: UC_GrowthOfNGAR5UP2 | B94: =TechData_R0!B38 -> MINNGAD2 | E94: CAP, GROWTH | G94: UP | H94: =TechData_R0!G38 -> 1.2 | I94: =TechData_R0!H38 -> 1.1 | J94: =I94 -> 1.1 | K94: =TechData_R0!I38 -> 1.05 | L94: =K94 -> 1.05 | M94: =L94 -> 1.05 | N94: =M94 -> 1.05 | O94: =N94 -> 1.05 | P94: =O94 -> 1.05 | Q94: =P94 -> 1.05 | R94: =MAX(1,TechData_R0!F38) -> 1 | T94: 5
A95: UC_GrowthOfNGAR5UP3 | B95: =TechData_R0!B39 -> MINNGAD3 | E95: CAP, GROWTH | G95: UP | H95: =TechData_R0!G39 -> 1.1 | I95: =TechData_R0!H39 -> 1.1 | J95: =I95 -> 1.1 | K95: =TechData_R0!I39 -> 1.05 | L95: =K95 -> 1.05 | M95: =L95 -> 1.05 | N95: =M95 -> 1.05 | O95: =N95 -> 1.05 | P95: =O95 -> 1.05 | Q95: =P95 -> 1.05 | R95: =MAX(1,TechData_R0!F39) -> 1 | T95: 5
A96: UC_GrowthOfNGAR5UP4 | B96: =TechData_R0!B40 -> MINNGAD4 | E96: CAP, GROWTH | G96: UP | H96: =TechData_R0!G40 -> 1.1 | I96: =TechData_R0!H40 -> 1.1 | J96: =I96 -> 1.1 | K96: =TechData_R0!I40 -> 1.1 | L96: =K96 -> 1.1 | M96: =L96 -> 1.1 | N96: =M96 -> 1.1 | O96: =N96 -> 1.1 | P96: =O96 -> 1.1 | Q96: =P96 -> 1.1 | R96: =MAX(1,TechData_R0!F40) -> 1 | T96: 5
A97: UC_GrowthOfNGAR5UP5 | B97: =TechData_R0!B41 -> MINNGAD5 | E97: CAP, GROWTH | G97: UP | H97: =TechData_R0!G41 -> 1.01 | I97: =TechData_R0!H41 -> 1.01 | J97: =I97 -> 1.01 | K97: =TechData_R0!I41 -> 1.01 | L97: =K97 -> 1.01 | M97: =L97 -> 1.01 | N97: =M97 -> 1.01 | O97: =N97 -> 1.01 | P97: =O97 -> 1.01 | Q97: =P97 -> 1.01 | R97: =MAX(1,TechData_R0!F41) -> 1 | T97: 5
A98: UC_GrowthOfNGAR5UP6 | B98: =TechData_R0!B42 -> MINNGAD6 | E98: CAP, GROWTH | G98: UP | H98: =TechData_R0!G42 -> 1.01 | I98: =TechData_R0!H42 -> 1.01 | J98: =I98 -> 1.01 | K98: =TechData_R0!I42 -> 1.01 | L98: =K98 -> 1.01 | M98: =L98 -> 1.01 | N98: =M98 -> 1.01 | O98: =N98 -> 1.01 | P98: =O98 -> 1.01 | Q98: =P98 -> 1.01 | R98: =MAX(1,TechData_R0!F42) -> 1 | T98: 5
G100: ~UC_T
A101: UC_N | B101: Pset_PN | C101: Pset_CI | D101: Pset_CO | E101: UC_ATTR | F101: Year | G101: LimType | H101: UC_CAP~2010 | I101: UC_CAP~2015 | J101: UC_CAP~2020 | K101: UC_CAP~2025 | L101: UC_CAP~2030 | M101: UC_CAP~2035 | N101: UC_CAP~2040 | O101: UC_CAP~2045 | P101: UC_CAP~2050 | Q101: UC_CAP~2055 | R101: UC_CAP~RHS | S101: UC_RHSRTS | T101: UC_RHSRTS~0 | U101: UC_Desc
A102: UC_GrowthOfNGAR5LO1 | B102: =TechData_R0!B37 -> MINNGAD1 | E102: CAP, GROWTH | G102: LO | H102: =1-TechData_R0!J37+1 -> 0.9 | I102: =1-TechData_R0!K37+1 -> 0.99 | J102: =I102 -> 0.99 | K102: =J102 -> 0.99 | L102: =K102 -> 0.99 | M102: =L102 -> 0.99 | N102: =M102 -> 0.99 | O102: =N102 -> 0.99 | P102: =O102 -> 0.99 | Q102: =P102 -> 0.99 | R102: 1 | T102: 5
A103: UC_GrowthOfNGAR5LO2 | B103: =TechData_R0!B38 -> MINNGAD2 | E103: CAP, GROWTH | G103: LO | H103: =1-TechData_R0!J38+1 -> 0.9 | I103: =1-TechData_R0!K38+1 -> 0.99 | J103: =I103 -> 0.99 | K103: =J103 -> 0.99 | L103: =K103 -> 0.99 | M103: =L103 -> 0.99 | N103: =M103 -> 0.99 | O103: =N103 -> 0.99 | P103: =O103 -> 0.99 | Q103: =P103 -> 0.99 | R103: 1 | T103: 5
A104: UC_GrowthOfNGAR5LO3 | B104: =TechData_R0!B39 -> MINNGAD3 | E104: CAP, GROWTH | G104: LO | H104: =1-TechData_R0!J39+1 -> 0.9 | I104: =1-TechData_R0!K39+1 -> 0.99 | J104: =I104 -> 0.99 | K104: =J104 -> 0.99 | L104: =K104 -> 0.99 | M104: =L104 -> 0.99 | N104: =M104 -> 0.99 | O104: =N104 -> 0.99 | P104: =O104 -> 0.99 | Q104: =P104 -> 0.99 | R104: 1 | T104: 5
A105: UC_GrowthOfNGAR5LO4 | B105: =TechData_R0!B40 -> MINNGAD4 | E105: CAP, GROWTH | G105: LO | H105: =1-TechData_R0!J40+1 -> 0.9 | I105: =1-TechData_R0!K40+1 -> 0.99 | J105: =I105 -> 0.99 | K105: =J105 -> 0.99 | L105: =K105 -> 0.99 | M105: =L105 -> 0.99 | N105: =M105 -> 0.99 | O105: =N105 -> 0.99 | P105: =O105 -> 0.99 | Q105: =P105 -> 0.99 | R105: 1 | T105: 5
A106: UC_GrowthOfNGAR5LO5 | B106: =TechData_R0!B41 -> MINNGAD5 | E106: CAP, GROWTH | G106: LO | H106: =1-TechData_R0!J41+1 -> 0.9 | I106: =1-TechData_R0!K41+1 -> 0.99 | J106: =I106 -> 0.99 | K106: =J106 -> 0.99 | L106: =K106 -> 0.99 | M106: =L106 -> 0.99 | N106: =M106 -> 0.99 | O106: =N106 -> 0.99 | P106: =O106 -> 0.99 | Q106: =P106 -> 0.99 | R106: 1 | T106: 5
A107: UC_GrowthOfNGAR5LO6 | B107: =TechData_R0!B42 -> MINNGAD6 | E107: CAP, GROWTH | G107: LO | H107: =1-TechData_R0!J42+1 -> 0.9 | I107: =1-TechData_R0!K42+1 -> 0.99 | J107: =I107 -> 0.99 | K107: =J107 -> 0.99 | L107: =K107 -> 0.99 | M107: =L107 -> 0.99 | N107: =M107 -> 0.99 | O107: =N107 -> 0.99 | P107: =O107 -> 0.99 | Q107: =P107 -> 0.99 | R107: 1 | T107: 5
A110: Maximum capacity technology growth:
A111: ~UC_Sets: R_E: R0
A112: ~UC_Sets: T_SUC:
G113: ~UC_T
A114: UC_N | B114: Pset_PN | C114: Pset_CI | D114: Pset_CO | E114: UC_ATTR | F114: Year | G114: LimType | H114: UC_CAP~2010 | I114: UC_CAP~2015 | J114: UC_CAP~2020 | K114: UC_CAP~2025 | L114: UC_CAP~2030 | M114: UC_CAP~2035 | N114: UC_CAP~2040 | O114: UC_CAP~2045 | P114: UC_CAP~2050 | Q114: UC_CAP~2055 | R114: UC_CAP~RHS | S114: UC_RHSRTS | T114: UC_RHSRTS~0 | U114: UC_Desc
...

Sheet UC_NGAb
A4: ~UC_Sets: R_E: R0 | J4: 0.8
G6: ~UC_T:
A7: UC_N | B7: Pset_PN | C7: Pset_PD | D7: Pset_CI | E7: Pset_CO | F7: Cset_CN | G7: Year | H7: LimType | I7: UC_FLO~2010 | J7: UC_FLO~2055 | K7: UC_RHSRTS | L7: UC_RHSRTS~0
A8: UC_NGA_CAN | B8: SCNGAC* | F8: NGAC1 | G8: 2020 | H8: LO | I8: 1 | J8: 1 | K8: 0 | L8: 15
B9: SCIMPNGA* | D9: NGAC | F9: NGACX | G9: 2025 | I9: =-Exports!$G$55 -> -0.083594039 | J9: =I9*J4 -> -0.066875231

Sheet TechData_R0
A1: TechData | B1: _GLOBAL,R0,R1,R2,R3,R4,R5,R6 | BO1: *
A6: Region | B6: TechName | C6: TechDesc | D6: CommOUT | E6: *TID | F6: *GROWTH_TIDr | G6: *GROWTHr~2010 | H6: *GROWTHr~2015-2020 | I6: *GROWTHr~2025-2055 | J6: *DECAYr~2010 | K6: *DECAYr~2015-2055 | L6: COST~2010 | M6: COST~2015 | N6: COST~2020 | O6: COST~2025 | P6: COST~2030 | Q6: COST~2035 | R6: COST~2040 | S6: COST~2045 | T6: COST~2050 | U6: COST~2055 | V6: CUM | W6: ACT_BND~LO~2010 | X6: ACT_BND~UP~2010 | Y6: ACT_BND~UP~2015 | Z6: ACT_BND~UP~2020 | AA6: ACT_BND~UP~2055
A7: *Minning Natural gas
A8: * Price Shocks | M8: 1 | N8: 1 | O8: 1 | P8: 1 | Q8: 1 | R8: 1 | S8: 1 | T8: 1 | U8: 1
A9: R1 | B9: MINNGAD1 | C9: Domestic natural gas - step 1 | D9: =Commodities!C$11 -> NGAD0 | E9: 2010 | G9: 1.25 | H9: 1.1 | I9: 1.1 | J9: 1.1 | K9: 1.01 | L9: =L11*'Domestic NG Prices'!$N$19 -> #REF! | M9: =M11*'Domestic NG Prices'!$N$19 -> #REF! | N9: =N11*'Domestic NG Prices'!$N$19 -> #REF! | O9: =O11*'Domestic NG Prices'!$N$19 -> #REF! | P9: =P11*'Domestic NG Prices'!$N$19 -> #REF! | Q9: =Q11*'Domestic NG Prices'!$N$19 -> #REF! | R9: =R11*'Domestic NG Prices'!$N$19 -> #REF! | S9: =S11*'Domestic NG Prices'!$N$19 -> 6.6176 | ... U9: =U11*'Domestic NG Prices'!$N$19 -> 8.0872 | V9: =X9/SUM($X$9:$X$14)*#REF! -> #REF! | W9: =#REF! -> #REF! | X9: =#REF! -> #REF!
A10: R1 | B10: MINNGAD2 | C10: Domestic natural gas - step 2 | D10: =Commodities!C$11 -> NGAD0 | E10: 2010 | G10: 1.25 | H10: 1.1 | I10: 1.1 | J10: 1.1 | K10: 1.01 | L10: =L11*'Domestic NG Prices'!$N$20 -> #REF! | M10: =M11*'Domestic NG Prices'!$N$20 -> #REF! | N10: =N11*'Domestic NG Prices'!$N$20 -> #REF! | O10: =O11*'Domestic NG Prices'!$N$20 -> #REF! | P10: =P11*'Domestic NG Prices'!$N$20 -> #REF! | Q10: =Q11*'Domestic NG Prices'!$N$20 -> #REF! | R10: =R11*'Domestic NG Prices'!$N$20 -> #REF! | S10: =S11*'Domestic NG Prices'!$N$20 -> 7.144 | ... U10: =U11*'Domestic NG Prices'!$N$20 -> 8.7305 | V10: =X10/SUM($X$9:$X$14)*#REF! -> #REF! | W10: =#REF! -> #REF! | X10: =#REF! -> #REF!
A11: R1 | B11: MINNGAD3 | C11: Domestic natural gas - step 3 | D11: =Commodities!C$11 -> NGAD0 | E11: 2010 | G11: 1.25 | H11: 1.1 | I11: 1.1 | J11: 1.1 | K11: 1.01 | L11: ='Domestic NG Prices'!N42*'Domestic NG Prices'!$P$27*#REF! -> #REF! | M11: ='Domestic NG Prices'!O42*'Domestic NG Prices'!$P$27*#REF!*M8 -> #REF! | N11: ='Domestic NG Prices'!P42*'Domestic NG Prices'!$P$27*#REF!*N8 -> #REF! | O11: ='Domestic NG Prices'!Q42*'Domestic NG Prices'!$P$27*#REF!*O8 -> #REF! | P11: ='Domestic NG Prices'!R42*'Domestic NG Prices'!$P$27*#REF!*P8 -> #REF! | Q11: ='Domestic NG Prices'!S42*'Domestic NG Prices'!$P$27*#REF!*Q8 -> #REF! | R11: ='Domestic NG Prices'!T42*'Domestic NG Prices'!$P$27*#REF!*R8 -> #REF! | S11: =7.52*S8 -> 7.52 | T11: =8.32*T8 -> 8.32 | U11: =9.19*U8 -> 9.19 | V11: =X11/SUM($X$9:$X$14)*#REF! -> #REF! | W11: =#REF! -> #REF! | X11: =#REF! -> #REF!
A12: R1 | B12: MINNGAD4 | C12: Domestic natural gas - step 4 | D12: =Commodities!C$11 -> NGAD0 | E12: 2010 | G12: 1.25 | H12: 1.1 | I12: 1.1 | J12: 1.1 | K12: 1.01 | L12: =L11*'Domestic NG Prices'!$N$22 -> #REF! | M12: =M11*'Domestic NG Prices'!$N$22 -> #REF! | N12: =N11*'Domestic NG Prices'!$N$22 -> #REF! | O12: =O11*'Domestic NG Prices'!$N$22 -> #REF! | P12: =P11*'Domestic NG Prices'!$N$22 -> #REF! | Q12: =Q11*'Domestic NG Prices'!$N$22 -> #REF! | R12: =R11*'Domestic NG Prices'!$N$22 -> #REF! | S12: =S11*'Domestic NG Prices'!$N$22 -> 8.1216 | ... U12: =U11*'Domestic NG Prices'!$N$22 -> 9.9252 | V12: =X12/SUM($X$9:$X$14)*#REF! -> #REF! | W12: =#REF! -> #REF! | X12: =#REF! -> #REF!
A13: R1 | B13: MINNGAD5 | C13: Domestic natural gas - step 5 | D13: =Commodities!C$11 -> NGAD0 | E13: 2010 | F13: =X13 -> #REF! | G13: 1.25 | H13: 1.1 | I13: 1.1 | J13: 1.1 | K13: 1.01 | L13: =L11*'Domestic NG Prices'!$N$23 -> #REF! | M13: =M11*'Domestic NG Prices'!$N$23 -> #REF! | N13: =N11*'Domestic NG Prices'!$N$23 -> #REF! | O13: =O11*'Domestic NG Prices'!$N$23 -> #REF! | P13: =P11*'Domestic NG Prices'!$N$23 -> #REF! | Q13: =Q11*'Domestic NG Prices'!$N$23 -> #REF! | R13: =R11*'Domestic NG Prices'!$N$23 -> #REF! | S13: =S11*'Domestic NG Prices'!$N$23 -> 8.4224 | ... U13: =U11*'Domestic NG Prices'!$N$23 -> 10.2928 | V13: =X13/SUM($X$9:$X$14)*#REF! -> #REF! | X13: =#REF! -> #REF!
A14: R1 | B14: MINNGAD6 | C14: Domestic natural gas - step 6 | D14: =Commodities!C$11 -> NGAD0 | E14: 2010 | F14: =X14 -> #REF! | G14: 1.25 | H14: 1.1 | I14: 1.1 | J14: 1.1 | K14: 1.01 | L14: =L11*'Domestic NG Prices'!$N$24 -> #REF! | M14: =M11*'Domestic NG Prices'!$N$24 -> #REF! | N14: =N11*'Domestic NG Prices'!$N$24 -> #REF! | O14: =O11*'Domestic NG Prices'!$N$24 -> #REF! | P14: =P11*'Domestic NG Prices'!$N$24 -> #REF! | Q14: =Q11*'Domestic NG Prices'!$N$24 -> #REF! | R14: =R11*'Domestic NG Prices'!$N$24 -> #REF! | S14: =S11*'Domestic NG Prices'!$N$24 -> 11.5056 | ... U14: =U11*'Domestic NG Prices'!$N$24 -> 14.0607 | V14: =X14/SUM($X$9:$X$14)*#REF! -> #REF! | X14: =#REF! -> #REF!
A15: *
A16: R2 | B16: MINNGAD1 | C16: Domestic natural gas - step 1 | D16: =Commodities!C$11 -> NGAD0 | E16: 2010 | G16: 1.25 | H16: 1.1 | I16: 1.1 | J16: 1.1 | K16: 1.01 | L16: =L18*'Domestic NG Prices'!$N$19 -> #REF! | M16: =M18*'Domestic NG Prices'!$N$19 -> #REF! | N16: =N18*'Domestic NG Prices'!$N$19 -> #REF! | O16: =O18*'Domestic NG Prices'!$N$19 -> #REF! | P16: =P18*'Domestic NG Prices'!$N$19 -> #REF! | Q16: =Q18*'Domestic NG Prices'!$N$19 -> #REF! | R16: =R18*'Domestic NG Prices'!$N$19 -> #REF! | S16: =S18*'Domestic NG Prices'!$N$19 -> 6.5694775 | ... U16: =U18*'Domestic NG Prices'!$N$19 -> 8.0217982 | V16: 0 | W16: =X16*0.9 -> 0 | X16: 0 | Y16: 0 | Z16: 0 | AA16: =Z16 -> 0
A17: R2 | B17: MINNGAD2 | C17: Domestic natural gas - step 2 | D17: =Commodities!C$11 -> NGAD0 | E17: 2010 | G17: 1.25 | H17: 1.1 | I17: 1.1 | J17: 1.1 | K17: 1.01 | L17: =L18*'Domestic NG Prices'!$N$20 -> #REF! | M17: =M18*'Domestic NG Prices'!$N$20 -> #REF! | N17: =N18*'Domestic NG Prices'!$N$20 -> #REF! | O17: =O18*'Domestic NG Prices'!$N$20 -> #REF! | P17: =P18*'Domestic NG Prices'!$N$20 -> #REF! | Q17: =Q18*'Domestic NG Prices'!$N$20 -> #REF! | R17: =R18*'Domestic NG Prices'!$N$20 -> #REF! | S17: =S18*'Domestic NG Prices'!$N$20 -> 7.0920495 | ... U17: =U18*'Domestic NG Prices'!$N$20 -> 8.6598958 | V17: 0 | W17: =X17*0.9 -> 0 | X17: 0 | Y17: 0 | Z17: 0 | AA17: =Z17 -> 0
A18: R2 | B18: MINNGAD3 | C18: Domestic natural gas - step 3 | D18: =Commodities!C$11 -> NGAD0 | E18: 2010 | G18: 1.25 | H18: 1.1 | I18: 1.1 | J18: 1.1 | K18: 1.01 | L18: ='Domestic NG Prices'!N42*'Domestic NG Prices'!$P$27*#REF! -> #REF! | M18: ='Domestic NG Prices'!O42*'Domestic NG Prices'!$P$27*#REF!*M8 -> #REF! | N18: ='Domestic NG Prices'!P42*'Domestic NG Prices'!$P$27*#REF!*N8 -> #REF! | O18: ='Domestic NG Prices'!Q42*'Domestic NG Prices'!$P$27*#REF!*O8 -> #REF! | P18: ='Domestic NG Prices'!R42*'Domestic NG Prices'!$P$27*#REF!*P8 -> #REF! | Q18: ='Domestic NG Prices'!S42*'Domestic NG Prices'!$P$27*#REF!*Q8 -> #REF! | R18: ='Domestic NG Prices'!T42*'Domestic NG Prices'!$P$27*#REF!*R8 -> #REF! | S18: =7.46531529457816*S8 -> 7.4653153 | T18: =8.2493286895923*T8 -> 8.2493287 | U18: =9.11567979966692*U8 -> 9.1156798 | V18: 0 | W18: =X18*0.9 -> 0 | X18: 0 | Y18: 0 | Z18: 0 | AA18: =Z18 -> 0
A19: R2 | B19: MINNGAD4 | C19: Domestic natural gas - step 4 | D19: =Commodities!C$11 -> NGAD0 | E19: 2010 | G19: 1.25 | H19: 1.1 | I19: 1.1 | J19: 1.1 | K19: 1.01 | L19: =L18*'Domestic NG Prices'!$N$22 -> #REF! | M19: =M18*'Domestic NG Prices'!$N$22 -> #REF! | N19: =N18*'Domestic NG Prices'!$N$22 -> #REF! | O19: =O18*'Domestic NG Prices'!$N$22 -> #REF! | P19: =P18*'Domestic NG Prices'!$N$22 -> #REF! | Q19: =Q18*'Domestic NG Prices'!$N$22 -> #REF! | R19: =R18*'Domestic NG Prices'!$N$22 -> #REF! | S19: =S18*'Domestic NG Prices'!$N$22 -> 8.0625405 | ... U19: =U18*'Domestic NG Prices'!$N$22 -> 9.8449342 | V19: 0 | W19: =X19*0.9 -> 0 | X19: 0 | Y19: 0 | Z19: 0 | AA19: =Z19 -> 0
A20: R2 | B20: MINNGAD5 | C20: Domestic natural gas - step 5 | D20: =Commodities!C$11 -> NGAD0 | E20: 2010 | F20: =X20 -> 0 | G20: 1.25 | H20: 1.1 | I20: 1.1 | J20: 1.1 | K20: 1.01 | L20: =L18*'Domestic NG Prices'!$N$23 -> #REF! | M20: =M18*'Domestic NG Prices'!$N$23 -> #REF! | N20: =N18*'Domestic NG Prices'!$N$23 -> #REF! | O20: =O18*'Domestic NG Prices'!$N$23 -> #REF! | P20: =P18*'Domestic NG Prices'!$N$23 -> #REF! | Q20: =Q18*'Domestic NG Prices'!$N$23 -> #REF! | R20: =R18*'Domestic NG Prices'!$N$23 -> #REF! | S20: =S18*'Domestic NG Prices'!$N$23 -> 8.3611531 | ... U20: =U18*'Domestic NG Prices'!$N$23 -> 10.209561 | V20: 0 | W20: =X20*0.9 -> 0 | X20: 0 | Y20: 0 | Z20: 0 | AA20: =Z20 -> 0
A21: R2 | B21: MINNGAD6 | C21: Domestic natural gas - step 6 | D21: =Commodities!C$11 -> NGAD0 | E21: 2010 | F21: =X21 -> 0 | G21: 1.25 | H21: 1.1 | I21: 1.1 | J21: 1.1 | K21: 1.01 | L21: =L18*'Domestic NG Prices'!$N$24 -> #REF! | M21: =M18*'Domestic NG Prices'!$N$24 -> #REF! | N21: =N18*'Domestic NG Prices'!$N$24 -> #REF! | O21: =O18*'Domestic NG Prices'!$N$24 -> #REF! | P21: =P18*'Domestic NG Prices'!$N$24 -> #REF! | Q21: =Q18*'Domestic NG Prices'!$N$24 -> #REF! | R21: =R18*'Domestic NG Prices'!$N$24 -> #REF! | S21: =S18*'Domestic NG Prices'!$N$24 -> 11.421932 | ... U21: =U18*'Domestic NG Prices'!$N$24 -> 13.94699 | V21: 0 | W21: =X21*0.9 -> 0 | X21: 0 | Y21: 0 | Z21: 0 | AA21: =Z21 -> 0
A22: *
A23: R3 | B23: MINNGAD1 | C23: Domestic natural gas - step 1 | D23: =Commodities!C$11 -> NGAD0 | E23: 2010 | G23: 1.25 | H23: 1.1 | I23: 1.1 | J23: 1.1 | K23: 1.01 | L23: =L25*'Domestic NG Prices'!$N$19 -> #REF! | M23: =M25*'Domestic NG Prices'!$N$19 -> #REF! | N23: =N25*'Domestic NG Prices'!$N$19 -> #REF! | O23: =O25*'Domestic NG Prices'!$N$19 -> #REF! | P23: =P25*'Domestic NG Prices'!$N$19 -> #REF! | Q23: =Q25*'Domestic NG Prices'!$N$19 -> #REF! | R23: =R25*'Domestic NG Prices'!$N$19 -> #REF! | S23: =S25*'Domestic NG Prices'!$N$19 -> 6.0617197 | ... U23: =U25*'Domestic NG Prices'!$N$19 -> 7.40179 | V23: 0 | W23: =X23*0.9 -> 0 | X23: 0 | Y23: 0 | Z23: 0 | AA23: =Z23 -> 0
A24: R3 | B24: MINNGAD2 | C24: Domestic natural gas - step 2 | D24: =Commodities!C$11 -> NGAD0 | E24: 2010 | G24: 1.25 | H24: 1.1 | I24: 1.1 | J24: 1.1 | K24: 1.01 | L24: =L25*'Domestic NG Prices'!$N$20 -> #REF! | M24: =M25*'Domestic NG Prices'!$N$20 -> #REF! | N24: =N25*'Domestic NG Prices'!$N$20 -> #REF! | O24: =O25*'Domestic NG Prices'!$N$20 -> #REF! | P24: =P25*'Domestic NG Prices'!$N$20 -> #REF! | Q24: =Q25*'Domestic NG Prices'!$N$20 -> #REF! | R24: =R25*'Domestic NG Prices'!$N$20 -> #REF! | S24: =S25*'Domestic NG Prices'!$N$20 -> 6.543902 | ... U24: =U25*'Domestic NG Prices'!$N$20 -> 7.9905688 | V24: 0 | W24: =X24*0.9 -> 0 | X24: 0 | Y24: 0 | Z24: 0 | AA24: =Z24 -> 0
A25: R3 | B25: MINNGAD3 | C25: Domestic natural gas - step 3 | D25: =Commodities!C$11 -> NGAD0 | E25: 2010 | G25: 1.25 | H25: 1.1 | I25: 1.1 | J25: 1.1 | K25: 1.01 | L25: ='Domestic NG Prices'!N42*'Domestic NG Prices'!$P$27*#REF! -> #REF! | M25: ='Domestic NG Prices'!O42*'Domestic NG Prices'!$P$27*#REF!*M8 -> #REF! | N25: ='Domestic NG Prices'!P42*'Domestic NG Prices'!$P$27*#REF!*N8 -> #REF! | O25: ='Domestic NG Prices'!Q42*'Domestic NG Prices'!$P$27*#REF!*O8 -> #REF! | P25: ='Domestic NG Prices'!R42*'Domestic NG Prices'!$P$27*#REF!*P8 -> #REF! | Q25: ='Domestic NG Prices'!S42*'Domestic NG Prices'!$P$27*#REF!*Q8 -> #REF! | R25: ='Domestic NG Prices'!T42*'Domestic NG Prices'!$P$27*#REF!*R8 -> #REF! | S25: =6.88831787744587*S8 -> 6.8883179 | T25: =7.61173454130134*T8 -> 7.6117345 | U25: =8.41112500294819*U8 -> 8.411125 | V25: 0 | W25: =X25*0.9 -> 0 | X25: 0 | Y25: 0 | Z25: 0 | AA25: =Z25 -> 0
A26: R3 | B26: MINNGAD4 | C26: Domestic natural gas - step 4 | D26: =Commodities!C$11 -> NGAD0 | E26: 2010 | G26: 1.1 | H26: 1.1 | I26: 1.1 | J26: 1.1 | K26: 1.01 | L26: =L25*'Domestic NG Prices'!$N$22 -> #REF! | M26: =M25*'Domestic NG Prices'!$N$22 -> #REF! | N26: =N25*'Domestic NG Prices'!$N$22 -> #REF! | O26: =O25*'Domestic NG Prices'!$N$22 -> #REF! | P26: =P25*'Domestic NG Prices'!$N$22 -> #REF! | Q26: =Q25*'Domestic NG Prices'!$N$22 -> #REF! | R26: =R25*'Domestic NG Prices'!$N$22 -> #REF! | S26: =S25*'Domestic NG Prices'!$N$22 -> 7.4393833 | ... U26: =U25*'Domestic NG Prices'!$N$22 -> 9.084015 | V26: 0 | W26: =X26*0.9 -> 0 | X26: 0 | Y26: 0 | Z26: 0 | AA26: =Z26 -> 0
A27: R3 | B27: MINNGAD5 | C27: Domestic natural gas - step 5 | D27: =Commodities!C$11 -> NGAD0 | E27: 2010 | F27: =X27 -> 0 | G27: 1.01 | H27: 1.01 | I27: 1.01 | J27: 1.1 | K27: 1.01 | L27: =L25*'Domestic NG Prices'!$N$23 -> #REF! | M27: =M25*'Domestic NG Prices'!$N$23 -> #REF! | N27: =N25*'Domestic NG Prices'!$N$23 -> #REF! | O27: =O25*'Domestic NG Prices'!$N$23 -> #REF! | P27: =P25*'Domestic NG Prices'!$N$23 -> #REF! | Q27: =Q25*'Domestic NG Prices'!$N$23 -> #REF! | R27: =R25*'Domestic NG Prices'!$N$23 -> #REF! | S27: =S25*'Domestic NG Prices'!$N$23 -> 7.714916 | ... U27: =U25*'Domestic NG Prices'!$N$23 -> 9.42046 | V27: 0 | W27: =X27*0.9 -> 0 | X27: 0 | Y27: 0 | Z27: 0 | AA27: =Z27 -> 0
A28: R3 | B28: MINNGAD6 | C28: Domestic natural gas - step 6 | D28: =Commodities!C$11 -> NGAD0 | E28: 2010 | F28: =X28 -> 0 | G28: 1.01 | H28: 1.01 | I28: 1.01 | J28: 1.1 | K28: 1.01 | L28: =L25*'Domestic NG Prices'!$N$24 -> #REF! | M28: =M25*'Domestic NG Prices'!$N$24 -> #REF! | N28: =N25*'Domestic NG Prices'!$N$24 -> #REF! | O28: =O25*'Domestic NG Prices'!$N$24 -> #REF! | P28: =P25*'Domestic NG Prices'!$N$24 -> #REF! | Q28: =Q25*'Domestic NG Prices'!$N$24 -> #REF! | R28: =R25*'Domestic NG Prices'!$N$24 -> #REF! | S28: =S25*'Domestic NG Prices'!$N$24 -> 10.539126 | ... U28: =U25*'Domestic NG Prices'!$N$24 -> 12.869021 | V28: 0 | W28: =X28*0.9 -> 0 | X28: 0 | Y28: 0 | Z28: 0 | AA28: =Z28 -> 0
A29: *
A30: R4 | B30: MINNGAD1 | C30: Domestic natural gas - step 1 | D30: =Commodities!C$11 -> NGAD0 | E30: 2010 | G30: 1.1 | H30: 1.05 | I30: 1.01 | J30: 1.1 | K30: 1.01 | L30: =L32*'Domestic NG Prices'!$N$19 -> #REF! | M30: =M32*'Domestic NG Prices'!$N$19 -> #REF! | N30: =N32*'Domestic NG Prices'!$N$19 -> #REF! | O30: =O32*'Domestic NG Prices'!$N$19 -> #REF! | P30: =P32*'Domestic NG Prices'!$N$19 -> #REF! | Q30: =Q32*'Domestic NG Prices'!$N$19 -> #REF! | R30: =R32*'Domestic NG Prices'!$N$19 -> #REF! | S30: =S32*'Domestic NG Prices'!$N$19 -> 6.4965138 | ... U30: =U32*'Domestic NG Prices'!$N$19 -> 7.9327045 | V30: 0 | W30: =X30*0.9 -> 0 | X30: 0 | Y30: 0 | Z30: 0 | AA30: =Z30 -> 0
A31: R4 | B31: MINNGAD2 | C31: Domestic natural gas - step 2 | D31: =Commodities!C$11 -> NGAD0 | E31: 2010 | G31: 1.2 | H31: 1.1 | I31: 1.05 | J31: 1.1 | K31: 1.01 | L31: =L32*'Domestic NG Prices'!$N$20 -> #REF! | M31: =M32*'Domestic NG Prices'!$N$20 -> #REF! | N31: =N32*'Domestic NG Prices'!$N$20 -> #REF! | O31: =O32*'Domestic NG Prices'!$N$20 -> #REF! | P31: =P32*'Domestic NG Prices'!$N$20 -> #REF! | Q31: =Q32*'Domestic NG Prices'!$N$20 -> #REF! | R31: =R32*'Domestic NG Prices'!$N$20 -> #REF! | S31: =S32*'Domestic NG Prices'!$N$20 -> 7.013282 | ... U31: =U32*'Domestic NG Prices'!$N$20 -> 8.5637151 | V31: 0 | W31: =X31*0.9 -> 0 | X31: 0 | Y31: 0 | Z31: 0 | AA31: =Z31 -> 0
A32: R4 | B32: MINNGAD3 | C32: Domestic natural gas - step 3 | D32: =Commodities!C$11 -> NGAD0 | E32: 2010 | G32: 1.1 | H32: 1.1 | I32: 1.05 | J32: 1.1 | K32: 1.01 | L32: ='Domestic NG Prices'!N42*'Domestic NG Prices'!$P$27*#REF! -> #REF! | M32: ='Domestic NG Prices'!O42*'Domestic NG Prices'!$P$27*#REF!*M8 -> #REF! | N32: ='Domestic NG Prices'!P42*'Domestic NG Prices'!$P$27*#REF!*N8 -> #REF! | O32: ='Domestic NG Prices'!Q42*'Domestic NG Prices'!$P$27*#REF!*O8 -> #REF! | P32: ='Domestic NG Prices'!R42*'Domestic NG Prices'!$P$27*#REF!*P8 -> #REF! | Q32: ='Domestic NG Prices'!S42*'Domestic NG Prices'!$P$27*#REF!*Q8 -> #REF! | R32: ='Domestic NG Prices'!T42*'Domestic NG Prices'!$P$27*#REF!*R8 -> #REF! | S32: =7.38240209732537*S8 -> 7.3824021 | T32: =8.15770788191657*T8 -> 8.1577079 | U32: =9.01443690134327*U8 -> 9.0144369 | V32: 0 | W32: =X32*0.9 -> 0 | X32: 0 | Y32: 0 | Z32: 0 | AA32: =Z32 -> 0
A33: R4 | B33: MINNGAD4 | C33: Domestic natural gas - step 4 | D33: =Commodities!C$11 -> NGAD0 | E33: 2010 | G33: 1.1 | H33: 1.1 | I33: 1.1 | J33: 1.1 | K33: 1.01 | L33: =L32*'Domestic NG Prices'!$N$22 -> #REF! | M33: =M32*'Domestic NG Prices'!$N$22 -> #REF! | N33: =N32*'Domestic NG Prices'!$N$22 -> #REF! | O33: =O32*'Domestic NG Prices'!$N$22 -> #REF! | P33: =P32*'Domestic NG Prices'!$N$22 -> #REF! | Q33: =Q32*'Domestic NG Prices'!$N$22 -> #REF! | R33: =R32*'Domestic NG Prices'!$N$22 -> #REF! | S33: =S32*'Domestic NG Prices'!$N$22 -> 7.9729943 | ... U33: =U32*'Domestic NG Prices'!$N$22 -> 9.7355919 | V33: 0 | W33: =X33*0.9 -> 0 | X33: 0 | Y33: 0 | Z33: 0 | AA33: =Z33 -> 0
A34: R4 | B34: MINNGAD5 | C34: Domestic natural gas - step 5 | D34: =Commodities!C$11 -> NGAD0 | E34: 2010 | F34: =X34 -> 0 | G34: 1.01 | H34: 1.01 | I34: 1.01 | J34: 1.1 | K34: 1.01 | L34: =L32*'Domestic NG Prices'!$N$23 -> #REF! | M34: =M32*'Domestic NG Prices'!$N$23 -> #REF! | N34: =N32*'Domestic NG Prices'!$N$23 -> #REF! | O34: =O32*'Domestic NG Prices'!$N$23 -> #REF! | P34: =P32*'Domestic NG Prices'!$N$23 -> #REF! | Q34: =Q32*'Domestic NG Prices'!$N$23 -> #REF! | R34: =R32*'Domestic NG Prices'!$N$23 -> #REF! | S34: =S32*'Domestic NG Prices'!$N$23 -> 8.2682903 | ... U34: =U32*'Domestic NG Prices'!$N$23 -> 10.096169 | V34: 0 | W34: =X34*0.9 -> 0 | X34: 0 | Y34: 0 | Z34: 0 | AA34: =Z34 -> 0
A35: R4 | B35: MINNGAD6 | C35: Domestic natural gas - step 6 | D35: =Commodities!C$11 -> NGAD0 | E35: 2010 | F35: =X35 -> 0 | G35: 1.01 | H35: 1.01 | I35: 1.01 | J35: 1.1 | K35: 1.01 | L35: =L32*'Domestic NG Prices'!$N$24 -> #REF! | M35: =M32*'Domestic NG Prices'!$N$24 -> #REF! | N35: =N32*'Domestic NG Prices'!$N$24 -> #REF! | O35: =O32*'Domestic NG Prices'!$N$24 -> #REF! | P35: =P32*'Domestic NG Prices'!$N$24 -> #REF! | Q35: =Q32*'Domestic NG Prices'!$N$24 -> #REF! | R35: =R32*'Domestic NG Prices'!$N$24 -> #REF! | S35: =S32*'Domestic NG Prices'!$N$24 -> 11.295075 | ... U35: =U32*'Domestic NG Prices'!$N$24 -> 13.792088 | V35: 0 | W35: =X35*0.9 -> 0 | X35: 0 | Y35: 0 | Z35: 0 | AA35: =Z35 -> 0
A36: *
A37: R5 | B37: MINNGAD1 | C37: Domestic natural gas - step 1 | D37: =Commodities!C$11 -> NGAD0 | E37: 2010 | G37: 1.1 | H37: 1.05 | I37: 1.01 | J37: 1.1 | K37: 1.01 | L37: =L39*'Domestic NG Prices'!$N$19 -> #REF! | M37: =M39*'Domestic NG Prices'!$N$19 -> #REF! | N37: =N39*'Domestic NG Prices'!$N$19 -> #REF! | O37: =O39*'Domestic NG Prices'!$N$19 -> #REF! | P37: =P39*'Domestic NG Prices'!$N$19 -> #REF! | Q37: =Q39*'Domestic NG Prices'!$N$19 -> #REF! | R37: =R39*'Domestic NG Prices'!$N$19 -> #REF! | S37: =S39*'Domestic NG Prices'!$N$19 -> 6.286944 | ... U37: =U39*'Domestic NG Prices'!$N$19 -> 7.6768048 | V37: 0 | W37: =X37*0.9 -> 0 | X37: 0 | Y37: 0 | Z37: 0 | AA37: =Z37 -> 0
A38: R5 | B38: MINNGAD2 | C38: Domestic natural gas - step 2 | D38: =Commodities!C$11 -> NGAD0 | E38: 2010 | G38: 1.2 | H38: 1.1 | I38: 1.05 | J38: 1.1 | K38: 1.01 | L38: =L39*'Domestic NG Prices'!$N$20 -> #REF! | M38: =M39*'Domestic NG Prices'!$N$20 -> #REF! | N38: =N39*'Domestic NG Prices'!$N$20 -> #REF! | O38: =O39*'Domestic NG Prices'!$N$20 -> #REF! | P38: =P39*'Domestic NG Prices'!$N$20 -> #REF! | Q38: =Q39*'Domestic NG Prices'!$N$20 -> #REF! | R38: =R39*'Domestic NG Prices'!$N$20 -> #REF! | S38: =S39*'Domestic NG Prices'!$N$20 -> 6.7870418 | ... U38: =U39*'Domestic NG Prices'!$N$20 -> 8.2874597 | V38: 0 | W38: =X38*0.9 -> 0 | X38: 0 | Y38: 0 | Z38: 0 | AA38: =Z38 -> 0
A39: R5 | B39: MINNGAD3 | C39: Domestic natural gas - step 3 | D39: =Commodities!C$11 -> NGAD0 | E39: 2010 | G39: 1.1 | H39: 1.1 | I39: 1.05 | J39: 1.1 | K39: 1.01 | L39: ='Domestic NG Prices'!N42*'Domestic NG Prices'!$P$27*#REF! -> #REF! | M39: ='Domestic NG Prices'!O42*'Domestic NG Prices'!$P$27*#REF!*M8 -> #REF! | N39: ='Domestic NG Prices'!P42*'Domestic NG Prices'!$P$27*#REF!*N8 -> #REF! | O39: ='Domestic NG Prices'!Q42*'Domestic NG Prices'!$P$27*#REF!*O8 -> #REF! | P39: ='Domestic NG Prices'!R42*'Domestic NG Prices'!$P$27*#REF!*P8 -> #REF! | Q39: ='Domestic NG Prices'!S42*'Domestic NG Prices'!$P$27*#REF!*Q8 -> #REF! | R39: ='Domestic NG Prices'!T42*'Domestic NG Prices'!$P$27*#REF!*R8 -> #REF! | S39: =7.14425453277032*S8 -> 7.1442545 | T39: =7.89454986927814*T8 -> 7.8945499 | U39: =8.72364182332011*U8 -> 8.7236418 | V39: 0 | W39: =X39*0.9 -> 0 | X39: 0 | Y39: 0 | Z39: 0 | AA39: =Z39 -> 0
A40: R5 | B40: MINNGAD4 | C40: Domestic natural gas - step 4 | D40: =Commodities!C$11 -> NGAD0 | E40: 2010 | G40: 1.1 | H40: 1.1 | I40: 1.1 | J40: 1.1 | K40: 1.01 | L40: =L39*'Domestic NG Prices'!$N$22 -> #REF! | M40: =M39*'Domestic NG Prices'!$N$22 -> #REF! | N40: =N39*'Domestic NG Prices'!$N$22 -> #REF! | O40: =O39*'Domestic NG Prices'!$N$22 -> #REF! | P40: =P39*'Domestic NG Prices'!$N$22 -> #REF! | Q40: =Q39*'Domestic NG Prices'!$N$22 -> #REF! | R40: =R39*'Domestic NG Prices'!$N$22 -> #REF! | S40: =S39*'Domestic NG Prices'!$N$22 -> 7.7157949 | ... U40: =U39*'Domestic NG Prices'!$N$22 -> 9.4215332 | V40: 0 | W40: =X40*0.9 -> 0 | X40: 0 | Y40: 0 | Z40: 0 | AA40: =Z40 -> 0
A41: R5 | B41: MINNGAD5 | C41: Domestic natural gas - step 5 | D41: =Commodities!C$11 -> NGAD0 | E41: 2010 | F41: =X41 -> 0 | G41: 1.01 | H41: 1.01 | I41: 1.01 | J41: 1.1 | K41: 1.01 | L41: =L39*'Domestic NG Prices'!$N$23 -> #REF! | M41: =M39*'Domestic NG Prices'!$N$23 -> #REF! | N41: =N39*'Domestic NG Prices'!$N$23 -> #REF! | O41: =O39*'Domestic NG Prices'!$N$23 -> #REF! | P41: =P39*'Domestic NG Prices'!$N$23 -> #REF! | Q41: =Q39*'Domestic NG Prices'!$N$23 -> #REF! | R41: =R39*'Domestic NG Prices'!$N$23 -> #REF! | S41: =S39*'Domestic NG Prices'!$N$23 -> 8.0015651 | ... U41: =U39*'Domestic NG Prices'!$N$23 -> 9.7704788 | V41: 0 | W41: =X41*0.9 -> 0 | X41: 0 | Y41: 0 | Z41: 0 | AA41: =Z41 -> 0
A42: R5 | B42: MINNGAD6 | C42: Domestic natural gas - step 6 | D42: =Commodities!C$11 -> NGAD0 | E42: 2010 | F42: =X42 -> 0 | G42: 1.01 | H42: 1.01 | I42: 1.01 | J42: 1.1 | K42: 1.01 | L42: =L39*'Domestic NG Prices'!$N$24 -> #REF! | M42: =M39*'Domestic NG Prices'!$N$24 -> #REF! | N42: =N39*'Domestic NG Prices'!$N$24 -> #REF! | O42: =O39*'Domestic NG Prices'!$N$24 -> #REF! | P42: =P39*'Domestic NG Prices'!$N$24 -> #REF! | Q42: =Q39*'Domestic NG Prices'!$N$24 -> #REF! | R42: =R39*'Domestic NG Prices'!$N$24 -> #REF! | S42: =S39*'Domestic NG Prices'!$N$24 -> 10.930709 | ... U42: =U39*'Domestic NG Prices'!$N$24 -> 13.347172 | V42: 0 | W42: =X42*0.9 -> 0 | X42: 0 | Y42: 0 | Z42: 0 | AA42: =Z42 -> 0
A43: *
A44: *
A48: Region | B48: TechName | C48: TechDesc | D48: CommIN | E48: CommOUT | F48: *TID | G48: EFF | H48: NCAP_COST | I48: NCAP_FOM | J48: ACT_COST | K48: AFA | N48: ENV_ACT~CO2~2010 | O48: ENV_ACT~CO2~2015-2055 | P48: ENV_ACT~VOC~2010 | Q48: ENV_ACT~VOC~2015 | R48: ENV_ACT~VOC~2020-2055 | S48: ENV_ACT~CO~2010 | T48: ENV_ACT~CO~2015 | U48: ENV_ACT~CO~2020-2055 | V48: ENV_ACT~NOX~2010 | W48: ENV_ACT~NOX~2015 | X48: ENV_ACT~NOX~2020-2055 | Y48: ENV_ACT~PM10~2010 | Z48: ENV_ACT~PM10~2015 | AA48: ENV_ACT~PM10~2020-2055 | AB48: ENV_ACT~PM25~2010 | AC48: ENV_ACT~PM25~2015 | AD48: ENV_ACT~PM25~2020-2055 | AE48: ENV_ACT~SO2~2010 | AF48: ENV_ACT~SO2~2015 | AG48: ENV_ACT~SO2~2020-2055 | AH48: ENV_ACT~CH4~2010-2015 | AI48: ENV_ACT~CH4~2015 | AJ48: ENV_ACT~CH4~2020-2055 | AK48: ENV_ACT~N2O~2010 | AL48: ENV_ACT~N2O~2015 | AM48: ENV_ACT~N2O~2020-2055 | AN48: ENV_ACT~OC~2010 | AO48: ENV_ACT~OC~2015 | AP48: ENV_ACT~OC~2020-2055 | AQ48: ENV_ACT~BC~2010 | AR48: ENV_ACT~BC~2015 | AS48: ENV_ACT~BC~2020-2055
A49: *Extraction Natural gas
A50: R1 | B50: SCMINNGAD | C50: Collector: MINNGAD | D50: NGAD0 | E50: =Commodities!C12 -> NGAD1 | F50: 2010 | G50: 1 | N50: =N51 -> 0.0056288631 | O50: =O51 -> 0.0056288631 | P50: =P51 -> 0.00073165 | Q50: =Q51 -> 0.00069187 | R50: =R51 -> 0.00066926 | S50: =S51 -> 0.00482293 | T50: =T51 -> 0.00459133 | U50: =U51 -> 0.00442755 | ... AN50: =AN51 -> 1.8008454e-05 | AO50: =AN51 -> 1.8008454e-05 | AP50: =AP51 -> 1.4447292e-05 | AQ50: =AQ51 -> 4.739067e-06 | AR50: =AR51 -> 4.2047746e-06 | AS50: =AS51 -> 3.8019189e-06
A51: R2 | B51: SCMINNGAD | C51: Collector: MINNGAD | D51: NGAD0 | E51: =Commodities!C13 -> NGAD2 | F51: 2010 | G51: 1 | N51: =Emissions!G109/1000 -> 0.0056288631 | O51: =Emissions!H109/1000 -> 0.0056288631 | P51: =Emissions!D71 -> 0.00073165 | Q51: =Emissions!E71 -> 0.00069187 | R51: =Emissions!F71 -> 0.00066926 | S51: =Emissions!D72 -> 0.00482293 | T51: =Emissions!E72 -> 0.00459133 | U51: =Emissions!F72 -> 0.00442755 | V51: =Emissions!D73 -> 0.01509156 | W51: =Emissions!E73 -> 0.01298537 | X51: =Emissions!F73 -> 0.01214993 | Y51: =Emissions!D74 -> 0.00035759 | Z51: =Emissions!E74 -> 0.00032223 | AA51: =Emissions!F74 -> 0.00029514 | AB51: =Emissions!D75 -> 0.00027727 | AC51: =Emissions!E75 -> 0.00024601 | AD51: =Emissions!F75 -> 0.00022244 | AE51: =Emissions!D76 -> 0.00054063 | AF51: =Emissions!E76 -> 0.00048401 | AG51: =Emissions!F76 -> 0.00048117 | AH51: =Emissions!J109 -> 0.28887951 | AI51: =Emissions!K109 -> 0.2251827 | AJ51: =AI51 -> 0.2251827 | AK51: =Emissions!D78 -> 4.3059e-05 | AL51: =Emissions!E78 -> 4.3051e-05 | AM51: =Emissions!F78 -> 4.3033e-05 | AN51: =Emissions!M11 -> 1.8008454e-05 | AO51: =$AN51/$AB51*AC51 -> 1.5978144e-05 | AP51: =$AN51/$AB51*AD51 -> 1.4447292e-05 | AQ51: =Emissions!N11 -> 4.739067e-06 | AR51: =$AQ51/$AB51*AC51 -> 4.2047746e-06 | AS51: =$AQ51/$AB51*AD51 -> 3.8019189e-06
A52: R3 | B52: SCMINNGAD | C52: Collector: MINNGAD | D52: NGAD0 | E52: =Commodities!C14 -> NGAD3 | F52: 2010 | G52: 1 | N52: =Emissions!G110/1000 -> 0.0055391483 | O52: =Emissions!H110/1000 -> 0.0055391483 | P52: =P51 -> 0.00073165 | Q52: =Q51 -> 0.00069187 | R52: =R51 -> 0.00066926 | S52: =S51 -> 0.00482293 | T52: =T51 -> 0.00459133 | U52: =U51 -> 0.00442755 | V52: =V51 -> 0.01509156 | W52: =W51 -> 0.01298537 | ... AG52: =AG51 -> 0.00048117 | AH52: =Emissions!J110 -> 0.30777943 | AI52: =Emissions!K110 -> 0.26800655 | AJ52: =AI52 -> 0.26800655 | AK52: =AK51 -> 4.3059e-05 | AL52: =AL51 -> 4.3051e-05 | AM52: =AM51 -> 4.3033e-05 | AN52: =AN51 -> 1.8008454e-05 | AO52: =AO51 -> 1.5978144e-05 | AP52: =AP51 -> 1.4447292e-05 | AQ52: =AQ51 -> 4.739067e-06 | AR52: =AR51 -> 4.2047746e-06 | AS52: =AS51 -> 3.8019189e-06
A53: R4 | B53: SCMINNGAD | C53: Collector: MINNGAD | D53: NGAD0 | E53: =Commodities!C15 -> NGAD4 | F53: 2010 | G53: 1 | N53: =Emissions!G111/1000 -> 0.0054616638 | O53: =Emissions!H111/1000 -> 0.0054616638 | P53: =P52 -> 0.00073165 | Q53: =Q52 -> 0.00069187 | R53: =R52 -> 0.00066926 | S53: =S52 -> 0.00482293 | T53: =T52 -> 0.00459133 | U53: =U52 -> 0.00442755 | V53: =V52 -> 0.01509156 | W53: =W52 -> 0.01298537 | ... AG53: =AG52 -> 0.00048117 | AH53: =Emissions!J111 -> 0.32410282 | AI53: =Emissions!K111 -> 0.30499246 | AJ53: =AI53 -> 0.30499246 | AK53: =AK52 -> 4.3059e-05 | AL53: =AL52 -> 4.3051e-05 | AM53: =AM52 -> 4.3033e-05 | AN53: =AN52 -> 1.8008454e-05 | AO53: =AO52 -> 1.5978144e-05 | AP53: =AP52 -> 1.4447292e-05 | AQ53: =AQ52 -> 4.739067e-06 | AR53: =AR52 -> 4.2047746e-06 | AS53: =AS52 -> 3.8019189e-06
A54: R5 | B54: SCMINNGAD | C54: Collector: MINNGAD | D54: NGAD0 | E54: =Commodities!C16 -> NGAD5 | F54: 2010 | G54: 1 | N54: =Emissions!G112/1000 -> 0.0055209677 | O54: =Emissions!H112/1000 -> 0.0055209677 | P54: =P53 -> 0.00073165 | Q54: =Q53 -> 0.00069187 | R54: =R53 -> 0.00066926 | S54: =S53 -> 0.00482293 | T54: =T53 -> 0.00459133 | U54: =U53 -> 0.00442755 | V54: =V53 -> 0.01509156 | W54: =W53 -> 0.01298537 | ... AG54: =AG53 -> 0.00048117 | AH54: =Emissions!J112 -> 0.31160946 | AI54: =Emissions!K112 -> 0.27668473 | AJ54: =AI54 -> 0.27668473 | AK54: =AK53 -> 4.3059e-05 | AL54: =AL53 -> 4.3051e-05 | AM54: =AM53 -> 4.3033e-05 | AN54: =AN53 -> 1.8008454e-05 | AO54: =AO53 -> 1.5978144e-05 | AP54: =AP53 -> 1.4447292e-05 | AQ54: =AQ53 -> 4.739067e-06 | AR54: =AR53 -> 4.2047746e-06 | AS54: =AS53 -> 3.8019189e-06
A55: R6 | B55: SCMINNGAD | C55: Collector: MINNGAD | D55: NGAD0 | E55: =Commodities!C17 -> NGAD6 | F55: 2010 | G55: 1 | N55: =Emissions!G113/1000 -> 0.00539 | O55: =Emissions!H113/1000 -> 0.00539 | P55: =P54 -> 0.00073165 | Q55: =Q54 -> 0.00069187 | R55: =R54 -> 0.00066926 | S55: =S54 -> 0.00482293 | T55: =T54 -> 0.00459133 | U55: =U54 -> 0.00442755 | V55: =V54 -> 0.01509156 | W55: =W54 -> 0.01298537 | ... AG55: =AG54 -> 0.00048117 | AH55: =Emissions!J113 -> 0.3392 | AI55: =Emissions!K113 -> 0.3392 | AJ55: =AI55 -> 0.3392 | AK55: =AK54 -> 4.3059e-05 | AL55: =AL54 -> 4.3051e-05 | AM55: =AM54 -> 4.3033e-05 | AN55: =AN54 -> 1.8008454e-05 | AO55: =AO54 -> 1.5978144e-05 | AP55: =AP54 -> 1.4447292e-05 | AQ55: =AQ54 -> 4.739067e-06 | AR55: =AR54 -> 4.2047746e-06 | AS55: =AS54 -> 3.8019189e-06
A56: *
A57: *
A61: Region | B61: TechName | C61: TechDesc | D61: CommOUT | E61: *TID | F61: *GROWTH_TIDr | G61: *GROWTHr~2010 | H61: *GROWTHr~2015-2020 | I61: *GROWTHr~2025-2055 | J61: *DECAYr~2010 | K61: *DECAYr~2015-2055 | L61: COST~2010 | M61: COST~2015 | N61: COST~2020 | O61: COST~2025 | P61: COST~2030 | Q61: COST~2035 | R61: COST~2040 | S61: COST~2045 | T61: COST~2050 | U61: COST~2055 | V61: ACT_BND~LO~2010 | W61: ACT_BND~UP~2010 | X61: ACT_BND~UP~2015 | Y61: ACT_BND~UP~2020 | Z61: ACT_BND~UP~2055
A62: *Imported Natural Gas supply
A63: R0 | B63: =Technologies!C30 -> IMPNGALA | C63: =Technologies!D30 -> Imported LNG - Step A | D63: =Commodities!$C$27 -> NGAL | E63: 2010 | L63: =L65*'Domestic NG Prices'!$N$19 -> 4.0308211 | M63: =M65*'Domestic NG Prices'!$N$19 -> 3.8312125 | N63: =N65*'Domestic NG Prices'!$N$19 -> 4.4927205 | O63: =O65*'Domestic NG Prices'!$N$19 -> 4.930375 | P63: =P65*'Domestic NG Prices'!$N$19 -> 5.4268446 | Q63: =Q65*'Domestic NG Prices'!$N$19 -> 6.1015641 | R63: =R65*'Domestic NG Prices'!$N$19 -> 6.7357129 | S63: =S65*'Domestic NG Prices'!$N$19 -> 7.4743024 | ... U63: =U65*'Domestic NG Prices'!$N$19 -> 9.2033271 | V63: =W63*0.9 -> 143.6252 | W63: ='AEO NG Imports'!AB16 -> 159.58355 | X63: ='AEO NG Imports'!AC16 -> 16.799403 | Y63: 0 | Z63: =Y63 -> 0
A64: R0 | B64: =Technologies!C31 -> IMPNGALB | C64: =Technologies!D31 -> Imported LNG - Step B | D64: =Commodities!$C$27 -> NGAL | E64: 2010 | L64: =L65*'Domestic NG Prices'!$N$20 -> 4.3514546 | M64: =M65*'Domestic NG Prices'!$N$20 -> 4.1359681 | N64: =N65*'Domestic NG Prices'!$N$20 -> 4.850096 | O64: =O65*'Domestic NG Prices'!$N$20 -> 5.322564 | P64: =P65*'Domestic NG Prices'!$N$20 -> 5.8585254 | Q64: =Q65*'Domestic NG Prices'!$N$20 -> 6.5869158 | R64: =R65*'Domestic NG Prices'!$N$20 -> 7.2715083 | S64: =S65*'Domestic NG Prices'!$N$20 -> 8.0688492 | ... U64: =U65*'Domestic NG Prices'!$N$20 -> 9.9354099 | V64: =W64*0.9 -> 107.7189 | W64: ='AEO NG Imports'!AB17 -> 119.68766 | X64: ='AEO NG Imports'!AC17 -> 12.599553 | Y64: 0 | Z64: =Y64 -> 0
A65: R0 | B65: =Technologies!C32 -> IMPNGALC | C65: =Technologies!D32 -> Imported LNG - Step C | D65: =Commodities!$C$27 -> NGAL | E65: 2010 | L65: ='AEO NG Imports'!L29*'Domestic NG Prices'!$P$27 -> 4.5804785 | M65: ='AEO NG Imports'!M29*'Domestic NG Prices'!$P$27 -> 4.3536506 | N65: ='AEO NG Imports'!N29*'Domestic NG Prices'!$P$27 -> 5.1053642 | O65: ='AEO NG Imports'!O29*'Domestic NG Prices'!$P$27 -> 5.6026989 | P65: ='AEO NG Imports'!P29*'Domestic NG Prices'!$P$27 -> 6.1668688 | Q65: ='AEO NG Imports'!Q29*'Domestic NG Prices'!$P$27 -> 6.9335955 | R65: ='AEO NG Imports'!R29*'Domestic NG Prices'!$P$27 -> 7.6542192 | S65: =R65*'AEO NG Imports'!$S$29 -> 8.4935255 | T65: =S65*'AEO NG Imports'!$S$29 -> 9.424864 | U65: =T65*'AEO NG Imports'!$S$29 -> 10.458326 | V65: =W65*0.9 -> 107.7189 | W65: ='AEO NG Imports'!AB18 -> 119.68766 | X65: ='AEO NG Imports'!AC18 -> 12.599553 | Y65: 0 | Z65: =Y65 -> 0
A66: R0 | B66: =Technologies!$C$34 -> IMPNGAC1 | C66: =Technologies!$D$34 -> Imported natural gas from Canada - Step 1 | D66: =Commodities!$C$25 -> NGAC | E66: 2010 | G66: 1.005 | H66: 1.005 | I66: 1.005 | J66: 1.25 | K66: 1.25 | L66: =L68*'Domestic NG Prices'!$N$19 -> 3.6554815 | M66: =M68*'Domestic NG Prices'!$N$19 -> 3.1311435 | N66: =N68*'Domestic NG Prices'!$N$19 -> 4.2346097 | O66: =O68*'Domestic NG Prices'!$N$19 -> 4.6125943 | P66: =P68*'Domestic NG Prices'!$N$19 -> 5.1934754 | Q66: =Q68*'Domestic NG Prices'!$N$19 -> 5.7363474 | R66: =R68*'Domestic NG Prices'!$N$19 -> 6.2166128 | S66: =S68*'Domestic NG Prices'!$N$19 -> 6.8676714 | ... U66: =U68*'Domestic NG Prices'!$N$19 -> 8.3814834 | V66: =W66*0.9 -> 974.32227 | W66: ='AEO NG Imports'!AB9 -> 1082.5803
A67: R0 | B67: =Technologies!$C$35 -> IMPNGAC2 | C67: =Technologies!$D$35 -> Imported natural gas from Canada - Step 2 | D67: =Commodities!$C$25 -> NGAC | E67: 2010 | G67: 1.005 | H67: 1.005 | I67: 1.005 | J67: 1.25 | K67: 1.25 | L67: =L68*'Domestic NG Prices'!$N$20 -> 3.9462584 | M67: =M68*'Domestic NG Prices'!$N$20 -> 3.3802117 | N67: =N68*'Domestic NG Prices'!$N$20 -> 4.5714536 | O67: =O68*'Domestic NG Prices'!$N$20 -> 4.9795052 | P67: =P68*'Domestic NG Prices'!$N$20 -> 5.6065927 | Q67: =Q68*'Domestic NG Prices'!$N$20 -> 6.1926478 | R67: =R68*'Domestic NG Prices'!$N$20 -> 6.711116 | S67: =S68*'Domestic NG Prices'!$N$20 -> 7.4139634 | ... U67: =U68*'Domestic NG Prices'!$N$20 -> 9.0481923 | V67: =W67*0.9 -> 730.7417 | W67: ='AEO NG Imports'!AB10 -> 811.93523
A68: R0 | B68: =Technologies!$C$36 -> IMPNGAC3 | C68: =Technologies!$D$36 -> Imported natural gas from Canada - Step 3 | D68: =Commodities!$C$25 -> NGAC | E68: 2010 | G68: 1.005 | H68: 1.005 | I68: 1.005 | J68: 1.25 | K68: 1.25 | L68: ='AEO NG Imports'!L26*'Domestic NG Prices'!$P$27 -> 4.1539562 | M68: ='AEO NG Imports'!M26*'Domestic NG Prices'!$P$27 -> 3.5581176 | N68: ='AEO NG Imports'!N26*'Domestic NG Prices'!$P$27 -> 4.8120564 | O68: ='AEO NG Imports'!O26*'Domestic NG Prices'!$P$27 -> 5.2415845 | P68: ='AEO NG Imports'!P26*'Domestic NG Prices'!$P$27 -> 5.9016766 | Q68: ='AEO NG Imports'!Q26*'Domestic NG Prices'!$P$27 -> 6.5185766 | R68: ='AEO NG Imports'!R26*'Domestic NG Prices'!$P$27 -> 7.0643327 | S68: =R68*'AEO NG Imports'!$S$26 -> 7.804172 | T68: =S68*'AEO NG Imports'!$S$26 -> 8.6214939 | U68: =T68*'AEO NG Imports'!$S$26 -> 9.524413 | V68: =W68*0.9 -> 730.7417 | W68: ='AEO NG Imports'!AB11 -> 811.93523
A69: R0 | B69: =Technologies!$C$37 -> IMPNGAC4 | C69: =Technologies!$D$37 -> Imported natural gas from Canada - Step 4 | D69: =Commodities!$C$25 -> NGAC | E69: 2010 | G69: 1.005 | H69: 1.005 | I69: 1.005 | J69: 1.25 | K69: 1.25 | L69: =L68*'Domestic NG Prices'!$N$22 -> 4.4862727 | M69: =M68*'Domestic NG Prices'!$N$22 -> 3.842767 | N69: =N68*'Domestic NG Prices'!$N$22 -> 5.197021 | O69: =O68*'Domestic NG Prices'!$N$22 -> 5.6609112 | P69: =P68*'Domestic NG Prices'!$N$22 -> 6.3738107 | Q69: =Q68*'Domestic NG Prices'!$N$22 -> 7.0400627 | R69: =R68*'Domestic NG Prices'!$N$22 -> 7.6294793 | S69: =S68*'Domestic NG Prices'!$N$22 -> 8.4285058 | ... U69: =U68*'Domestic NG Prices'!$N$22 -> 10.286366 | W69: ='AEO NG Imports'!AB12 -> 135.32254
A70: R0 | B70: =Technologies!$C$38 -> IMPNGAC5 | C70: =Technologies!$D$38 -> Imported natural gas from Canada - Step 5 | D70: =Commodities!$C$25 -> NGAC | E70: 2010 | G70: 1.005 | H70: 1.005 | I70: 1.005 | J70: 1.25 | K70: 1.25 | L70: =L68*'Domestic NG Prices'!$N$23 -> 4.652431 | M70: =M68*'Domestic NG Prices'!$N$23 -> 3.9850917 | N70: =N68*'Domestic NG Prices'!$N$23 -> 5.3895032 | O70: =O68*'Domestic NG Prices'!$N$23 -> 5.8705746 | P70: =P68*'Domestic NG Prices'!$N$23 -> 6.6098777 | Q70: =Q68*'Domestic NG Prices'!$N$23 -> 7.3008058 | R70: =R68*'Domestic NG Prices'!$N$23 -> 7.9120526 | S70: =S68*'Domestic NG Prices'!$N$23 -> 8.7406727 | ... U70: =U68*'Domestic NG Prices'!$N$23 -> 10.667343 | W70: ='AEO NG Imports'!AB13 -> 135.32254
A71: R0 | B71: =Technologies!$C$39 -> IMPNGAC6 | C71: =Technologies!$D$39 -> Imported natural gas from Canada - Step 6 | D71: =Commodities!$C$25 -> NGAC | E71: 2010 | G71: 1.005 | H71: 1.005 | I71: 1.005 | J71: 1.25 | K71: 1.25 | L71: =L68*'Domestic NG Prices'!$N$24 -> 6.355553 | M71: =M68*'Domestic NG Prices'!$N$24 -> 5.4439199 | N71: =N68*'Domestic NG Prices'!$N$24 -> 7.3624464 | O71: =O68*'Domestic NG Prices'!$N$24 -> 8.0196242 | P71: =P68*'Domestic NG Prices'!$N$24 -> 9.0295651 | Q71: =Q68*'Domestic NG Prices'!$N$24 -> 9.9734222 | R71: =R68*'Domestic NG Prices'!$N$24 -> 10.808429 | S71: =S68*'Domestic NG Prices'!$N$24 -> 11.940383 | ... U71: =U68*'Domestic NG Prices'!$N$24 -> 14.572352 | W71: ='AEO NG Imports'!AB14 -> 270.64508
A76: Region | B76: TechName | C76: TechDesc | D76: CommIN | E76: CommOUT | F76: *TID | G76: EFF | H76: Share~UP
A77: R0 | B77: SCIMPNGAL | C77: Share of Imported LNG to Existing Terminals | D77: NGAL | F77: 2010 | G77: 1
A78: =A77 -> R0 | E78: NGALE1 | H78: 0.266993
A79: =A78 -> R0 | E79: NGALE4 | H79: 0.5604
A80: =A79 -> R0 | E80: NGALE5 | H80: 0.17261824
A81: R0 | B81: SCIMPNGAC | C81: Canadian imported natural gas shares | D81: NGAC | E81: NGACX | F81: 2010 | G81: 1
A82: =Technologies!B41 -> R0 | B82: =Technologies!C41 -> SCNGAC1 | C82: =Technologies!D41 -> Canadian imported natural gas in R1 | D82: NGACX | E82: =Commodities!C29 -> NGAC1 | F82: 2010 | G82: 1
A83: =Technologies!B42 -> *R0 | B83: =Technologies!C42 -> SCNGAC2 | C83: =Technologies!D42 -> Canadian imported natural gas in R2 | D83: NGACX | E83: =Commodities!C30 -> NGAC2 | F83: 2010 | G83: 1
A84: =Technologies!B43 -> *R0 | B84: =Technologies!C43 -> SCNGAC3 | C84: =Technologies!D43 -> Canadian imported natural gas in R3 | D84: NGACX | E84: =Commodities!C31 -> NGAC3 | F84: 2010 | G84: 1
A85: =Technologies!B44 -> *R0 | B85: =Technologies!C44 -> SCNGAC4 | C85: =Technologies!D44 -> Canadian imported natural gas in R4 | D85: NGACX | E85: =Commodities!C32 -> NGAC4 | F85: 2010 | G85: 1
A86: =Technologies!B45 -> *R0 | B86: =Technologies!C45 -> SCNGAC5 | C86: =Technologies!D45 -> Canadian imported natural gas in R5 | D86: NGACX | E86: =Commodities!C33 -> NGAC5 | F86: 2010 | G86: 1
A87: =Technologies!B46 -> *R0 | B87: =Technologies!C46 -> SCNGAC6 | C87: =Technologies!D46 -> Canadian imported natural gas in R6 | D87: NGACX | E87: =Commodities!C34 -> NGAC6 | F87: 2010 | G87: 1
A94: Region | B94: TechName | C94: TechDesc | D94: CommIN | E94: ACT_BND~FX~2010 | F94: ACT_BND~FX~2015 | G94: ACT_BND~FX~2020 | H94: ACT_BND~FX~2025 | I94: ACT_BND~FX~2030 | J94: ACT_BND~FX~2035 | K94: ACT_BND~FX~2040 | L94: ACT_BND~FX~2045 | M94: ACT_BND~FX~2050 | N94: ACT_BND~FX~2055
A95: * Exports of NG Liguids
A96: R1 | B96: =Technologies!C$49 -> EXPNGAL | C96: =Technologies!D$49 -> Exported natural gas liquids | D96: =Commodities!C18 -> NGAR1 | G96: 0 | H96: =-'AEO NG Imports'!O$20*#REF! -> #REF! | I96: =-'AEO NG Imports'!P$20*#REF! -> #REF! | J96: =-'AEO NG Imports'!Q$20*#REF! -> #REF! | K96: =-'AEO NG Imports'!R$20*#REF! -> #REF! | L96: =K96 -> #REF! | M96: =L96 -> #REF! | N96: =M96 -> #REF!
A97: R2 | B97: =Technologies!C$49 -> EXPNGAL | C97: =Technologies!D$49 -> Exported natural gas liquids | D97: =Commodities!C19 -> NGAR2 | E97: 0 | F97: 0 | G97: 0 | H97: 0 | I97: 0 | J97: 0 | K97: 0 | L97: 0 | M97: 0 | N97: 0
A98: R3 | B98: =Technologies!C$49 -> EXPNGAL | C98: =Technologies!D$49 -> Exported natural gas liquids | D98: =Commodities!C20 -> NGAR3 | E98: 0 | F98: 0 | G98: 0 | H98: 0 | I98: 0 | J98: 0 | K98: 0 | L98: 0 | M98: 0 | N98: 0
A99: R4 | B99: =Technologies!C$49 -> EXPNGAL | C99: =Technologies!D$49 -> Exported natural gas liquids | D99: =Commodities!C21 -> NGAR4 | E99: 0 | F99: 0 | G99: 0 | H99: 0 | I99: 0 | J99: 0 | K99: 0 | L99: 0 | M99: 0 | N99: 0
A100: R5 | B100: =Technologies!C$49 -> EXPNGAL | C100: =Technologies!D$49 -> Exported natural gas liquids | D100: =Commodities!C22 -> NGAR5 | E100: 0 | F100: 0 | G100: 0 | H100: 0 | I100: 0 | J100: 0 | K100: 0 | L100: 0 | M100: 0 | N100: 0
A101: R6 | B101: =Technologies!C$49 -> EXPNGAL | C101: =Technologies!D$49 -> Exported natural gas liquids | D101: =Commodities!C23 -> NGAR6 | E101: 0 | F101: 0 | G101: 0 | H101: 0 | I101: 0 | J101: 0 | K101: 0 | L101: 0 | M101: 0 | N101: 0
A109: Region | B109: TechName | C109: TechDesc | D109: CommOUT | E109: *TID | F109: COST~2010 | G109: COST~2015 | H109: COST~2020 | I109: COST~2025 | J109: COST~2030 | K109: COST~2035 | L109: COST~2040 | M109: COST~2045 | N109: COST~2050 | O109: COST~2055
A110: * Dummy NGA Supply Technologies (COST is 1.25 x the highest price step)
A111: =Technologies!B15 -> R1 | B111: =Technologies!C15 -> MINNGLDMY | C111: =Technologies!D15 -> Dummy NGL Resource Supply | D111: =Commodities!C24 -> NGL | E111: 2010 | F111: =L65*1.25 -> 5.7255981 | G111: =M65*1.25 -> 5.4420633 | H111: =N65*1.25 -> 6.3817052 | I111: =O65*1.25 -> 7.0033736 | J111: =P65*1.25 -> 7.708586 | K111: =Q65*1.25 -> 8.6669944 | L111: =R65*1.25 -> 9.5677741 | M111: =S65*1.25 -> 10.616907 | ... O111: =U65*1.25 -> 13.072908

Sheet >> Not used

Sheet Commodities
B1: Commodities | C1: _GLOBAL,R0,R1,R2,R3,R4,R5,R6
B7: Region | C7: CommName | D7: CommDesc | E7: Unit | F7: Csets | G7: LimType | H7: CTSLvl | I7: PeakTS | J7: Ctype | O7: Comment
B8: * Natural Gas Supply Commodities - Domestic and Imported
B9: R1,R2,R3,R4,R5,R6 | C9: NGA | D9: Natural Gas | E9: PJ | F9: NRG
B10: R1,R2,R3,R4,R5,R6 | C10: NGAD | D10: Domestic Natural Gas | E10: PJ
B11: R1,R2,R3,R4,R5,R6 | C11: NGAD0 | D11: Domestic Natural Gas - D0 | E11: PJ
B12: R1 | C12: NGAD1 | D12: Domestic Natural Gas - R1 | E12: PJ
B13: R2 | C13: NGAD2 | D13: Domestic Natural Gas - R2 | E13: PJ
B14: R3 | C14: NGAD3 | D14: Domestic Natural Gas - R3 | E14: PJ
B15: R4 | C15: NGAD4 | D15: Domestic Natural Gas - R4 | E15: PJ
B16: R5 | C16: NGAD5 | D16: Domestic Natural Gas - R5 | E16: PJ
B17: R6 | C17: NGAD6 | D17: Domestic Natural Gas - R6 | E17: PJ
B18: R1,R2,R3,R4,R5,R6 | C18: NGAR1 | D18: Natural Gas - R1 | E18: PJ
B19: R1,R2,R3,R4,R5,R6 | C19: NGAR2 | D19: Natural Gas - R2 | E19: PJ
B20: R1,R2,R3,R4,R5,R6 | C20: NGAR3 | D20: Natural Gas - R3 | E20: PJ
B21: R1,R2,R3,R4,R5,R6 | C21: NGAR4 | D21: Natural Gas - R4 | E21: PJ
... B43: R1,R2,R3,R4,R5,R6 | C43: NGLR6 | D43: Traded natural gas plant liquids from R6 | E43: PJ
B44: * Natural Gas End-Use Commodities
B45: R1,R2,R3,R4,R5,R6 | C45: RESNGA | D45: Natural gas to Residential sector | E45: PJ | F45: NRG
B46: R1,R2,R3,R4,R5,R6 | C46: COMNGA | D46: Natural gas to Commercial sector | E46: PJ
B47: R1,R2,R3,R4,R5,R6 | C47: INDNGA | D47: Natural gas to Industrial sector | E47: PJ
B48: R1,R2,R3,R4,R5,R6 | C48: ELCNGA | D48: Natural gas to Electricity generation | E48: PJ
B49: R1,R2,R3,R4,R5,R6 | C49: TRNNGA | D49: Natural gas to Transportation sector | E49: PJ
B50: *R1,R2,R3,R4,R5,R6 | C50: LPG | D50: LPG from NGL | E50: PJ
B51: *R1,R2,R3,R4,R5,R7 | C51: PFS | D51: PFS from NGL | E51: PJ
B52: *R1,R2,R3,R4,R5,R8 | C52: PENTS | D52: Pentanes from NGL | E52: PJ
B53: *R1,R2,R3,R4,R5,R9 | C53: GSR | D53: NGL Pentanes to gasoline | E53: PJ
B54: *R1,R2,R3,R4,R5,R10 | C54: DENAT | D54: NGL Pentanes to ethanol denaturant | E54: PJ
B55: *R1,R2,R3,R4,R5,R11 | C55: PFS_NGL | D55: Natural gas liquids to PFS (C2 & C4) | E55: PJ
B56: *R1,R2,R3,R4,R5,R12 | C56: LPG_NGL | D56: Natural gas liquids to LPG (C3) | E56: PJ
B57: *R1,R2,R3,R4,R5,R13 | C57: NGLPENT | D57: Natural gas liquids to pentanes (C5+) | E57: PJ
B74: * Emissions Commodities
B75: R1,R2,R3,R4,R5,R6 | C75: CO2 | D75: Carbon dioxide | E75: Mt | F75: ENV
B76: R1,R2,R3,R4,R5,R6 | C76: NOX | D76: Nitrogen oxide | E76: kt | F76: ENV
B77: R1,R2,R3,R4,R5,R6 | C77: PM10 | D77: Particulate matter | E77: kt | F77: ENV
B78: R1,R2,R3,R4,R5,R6 | C78: PM25 | D78: Fine particulate matter | E78: kt | F78: ENV
B79: R1,R2,R3,R4,R5,R6 | C79: VOC | D79: Volatile organic compounds | E79: kt | F79: ENV
B80: R1,R2,R3,R4,R5,R6 | C80: CO | D80: Carbon monoxide | E80: kt | F80: ENV
B81: R1,R2,R3,R4,R5,R6 | C81: CH4 | D81: Methane | E81: kt | F81: ENV
B82: R1,R2,R3,R4,R5,R6 | C82: N2O | D82: N2O | E82: kt | F82: ENV
B83: R1,R2,R3,R4,R5,R6 | C83: BC | D83: Black carbon | E83: kt | F83: ENV
B84: R1,R2,R3,R4,R5,R6 | C84: OC | D84: Organic carbon | E84: kt | F84: ENV
B85: R1,R2,R3,R4,R5,R6 | C85: SO2 | D85: Sulfur dioxide | E85: kt | F85: ENV

Sheet ANSv6.1-Technologies
A1: ANSWER-Technologies
B7: TechName | C7: TechDesc | D7: TACTUnit | E7: TCAPUnit | F7: Set Memberships | G7: Comment

Sheet Technologies
B1: Technologies | C1: _GLOBAL,R0,R1,R2,R3,R4,R5,R6
B7: Region | C7: TechName | D7: TechDesc | E7: Tact | F7: Tcap | G7: Sets | H7: PrimaryCG | I7: Vintage | O7: Comment
B8: R1,R2,R3,R4,R5,R6 | C8: MINNGAD1 | D8: Domestic natural gas - step 1 | E8: PJ | F8: PJ/a | G8: MIN
B9: R1,R2,R3,R4,R5,R6 | C9: MINNGAD2 | D9: Domestic natural gas - step 2 | E9: PJ | F9: PJ/a
B10: R1,R2,R3,R4,R5,R6 | C10: MINNGAD3 | D10: Domestic natural gas - step 3 | E10: PJ | F10: PJ/a
B11: R1,R2,R3,R4,R5,R6 | C11: MINNGAD4 | D11: Domestic natural gas - step 4 | E11: PJ | F11: PJ/a
B12: R1,R2,R3,R4,R5,R6 | C12: MINNGAD5 | D12: Domestic natural gas - step 5 | E12: PJ | F12: PJ/a
B13: R1,R2,R3,R4,R5,R6 | C13: MINNGAD6 | D13: Domestic natural gas - step 6 | E13: PJ | F13: PJ/a
B14: R1,R2,R3,R4,R5,R6 | C14: SCMINNGAD | D14: Collector: MINNGAD | E14: PJ | F14: PJ/a | G14: PRE
B15: R1 | C15: MINNGLDMY | D15: Dummy NGL Resource Supply | E15: PJ | F15: PJ/a | G15: MIN
B16: R1 | C16: SCNGAR1 | D16: Collector: Natural Gas R1 | E16: PJ | F16: PJ/a | G16: PRE
B17: R2 | C17: SCNGAR2 | D17: Collector: Natural Gas R2 | E17: PJ | F17: PJ/a
B18: R3 | C18: SCNGAR3 | D18: Collector: Natural Gas R3 | E18: PJ | F18: PJ/a
B19: R4 | C19: SCNGAR4 | D19: Collector: Natural Gas R4 | E19: PJ | F19: PJ/a
B20: R5 | C20: SCNGAR5 | D20: Collector: Natural Gas R5 | E20: PJ | F20: PJ/a
B21: R6 | C21: SCNGAR6 | D21: Collector: Natural Gas R6 | E21: PJ | F21: PJ/a
B22: *
B23: R1 | C23: SCNGAD1 | D23: Domestic natural gas Existing infrastructure in R1 | E23: PJ | F23: PJ/a
B24: R2 | C24: SCNGAD2 | D24: Domestic natural gas Existing infrastructure in R2 | E24: PJ | F24: PJ/a
B25: R3 | C25: SCNGAD3 | D25: Domestic natural gas Existing infrastructure in R3 | E25: PJ | F25: PJ/a
B26: R4 | C26: SCNGAD4 | D26: Domestic natural gas Existing infrastructure in R4 | E26: PJ | F26: PJ/a
B27: R5 | C27: SCNGAD5 | D27: Domestic natural gas Existing infrastructure in R5 | E27: PJ | F27: PJ/a
B28: R6 | C28: SCNGAD6 | D28: Domestic natural gas Existing infrastructure in R6 | E28: PJ | F28: PJ/a
B29: *Imported natural gas supply and transport
B30: R0 | C30: IMPNGALA | D30: Imported LNG - Step A | E30: PJ | F30: PJ/a | G30: IMP
B31: R0 | C31: IMPNGALB | D31: Imported LNG - Step B | E31: PJ | F31: PJ/a
B32: R0 | C32: IMPNGALC | D32: Imported LNG - Step C | E32: PJ | F32: PJ/a
B33: R0 | C33: SCIMPNGAL | D33: Share of Imported LNG to Existing Terminals | E33: PJ | F33: PJ/a | G33: PRE
B34: R0 | C34: IMPNGAC1 | D34: Imported natural gas from Canada - Step 1 | E34: PJ | F34: PJ/a | G34: IMP
B35: R0 | C35: IMPNGAC2 | D35: Imported natural gas from Canada - Step 2 | E35: PJ | F35: PJ/a
B36: R0 | C36: IMPNGAC3 | D36: Imported natural gas from Canada - Step 3 | E36: PJ | F36: PJ/a
B37: R0 | C37: IMPNGAC4 | D37: Imported natural gas from Canada - Step 4 | E37: PJ | F37: PJ/a
B38: R0 | C38: IMPNGAC5 | D38: Imported natural gas from Canada - Step 5 | E38: PJ | F38: PJ/a
B39: R0 | C39: IMPNGAC6 | D39: Imported natural gas from Canada - Step 6 | E39: PJ | F39: PJ/a
B40: R0 | C40: SCIMPNGAC | D40: Canadian imported natural gas shares | E40: PJ | F40: PJ/a | G40: PRE
B41: R0 | C41: SCNGAC1 | D41: Canadian imported natural gas in R1 | E41: PJ | F41: PJ/a
B42: *R0 | C42: SCNGAC2 | D42: Canadian imported natural gas in R2 | E42: PJ | F42: PJ/a
B43: *R0 | C43: SCNGAC3 | D43: Canadian imported natural gas in R3 | E43: PJ | F43: PJ/a
B44: *R0 | C44: SCNGAC4 | D44: Canadian imported natural gas in R4 | E44: PJ | F44: PJ/a
B45: *R0 | C45: SCNGAC5 | D45: Canadian imported natural gas in R5 | E45: PJ | F45: PJ/a
B46: *R0 | C46: SCNGAC6 | D46: Canadian imported natural gas in R6 | E46: PJ | F46: PJ/a
B47: *Export natural gas supply and transport
B48: *R7,R8,R9 | C48: EXPNGAM | D48: Exported natural gas to Mexico | G48: TCH,SRCENCP,SEP_EXP
B49: R1,R2,R3,R4,R5,R6 | C49: EXPNGAL | D49: Exported natural gas liquids | E49: PJ | F49: PJ/a | G49: EXP
B50: R1 | C50: XNGAC1E | D50: Existing Pipeline for Import Canadian natural gas to R1 | E50: PJ | F50: PJ/a | G50: PRE
B51: *R2 | C51: XNGAC2E | D51: Existing Pipeline for Import Canadian natural gas to R2 | E51: PJ | F51: PJ/a
B52: *R3 | C52: XNGAC3E | D52: Existing Pipeline for Import Canadian natural gas to R3 | E52: PJ | F52: PJ/a
B53: *R4 | C53: XNGAC4E | D53: Existing Pipeline for Import Canadian natural gas to R4 | E53: PJ | F53: PJ/a
B54: *R5 | C54: XNGAC5E | D54: Existing Pipeline for Import Canadian natural gas to R5 | E54: PJ | F54: PJ/a
B55: *R6 | C55: XNGAC6E | D55: Existing Pipeline for Import Canadian natural gas to R6 | E55: PJ | F55: PJ/a
B56: *
B57: R1 | C57: XNGALE1E | D57: Infrastructure for Import LNG to Existing terminal in R1 | E57: PJ | F57: PJ/a
B58: R4 | C58: XNGALE4E | D58: Infrastructure for Import LNG to Existing terminal in R4 - Manhattan | E58: PJ | F58: PJ/a
B59: R5 | C59: XNGALE5E | D59: Infrastructure for Import LNG to Existing terminal in R5 - Staten Island | E59: PJ | F59: PJ/a
B60: * Domestic natural gas delivery costs to end-use demands
B61: R1,R2,R3,R4,R5,R6 | C61: XNGARES | D61: Domestic natural gas to residential end-use | E61: PJ | F61: PJ/a | G61: PRE
B62: R1,R2,R3,R4,R5,R6 | C62: XNGACOM | D62: Domestic natural gas to commercial end-use | E62: PJ | F62: PJ/a
B63: R1,R2,R3,R4,R5,R6 | C63: XNGAIND | D63: Domestic natural gas to industrial end-use | E63: PJ | F63: PJ/a
B64: R1,R2,R3,R4,R5,R6 | C64: XNGAELC | D64: Domestic natural gas to electricity generation | E64: PJ | F64: PJ/a
B65: R1,R2,R3,R4,R5,R6 | C65: XNGATRN | D65: Domestic natural gas to transportation end-use | E65: PJ | F65: PJ/a
B66: * | C66: XNGLFRAC | D66: Domestic natural gas liquids to end-products
B67: * Collectors for NGL products
B68: *R1,R2,R3,R4,R5,R6 | C68: SCGSRPENT | D68: Collector: GSR from NGL Pentanes
B69: *R1,R2,R3,R4,R5,R6 | C69: SCDENPENT | D69: Collector: Ethanol denaturant from NGL Pentanes
B70: *R1,R2,R3,R4,R5,R6 | C70: SCPFSNGL | D70: Collector: PFS from NGL
B71: *R1,R2,R3,R4,R5,R6 | C71: SCLPGNGL | D71: Collector: LPG from NGL
B72: *R1,R2,R3,R4,R5,R6 | C72: SCPENTNGL | D72: Collector: Pentanes from NGL
B73: *
B74: * Imported natural gas Pipeline technologies
B75: R2 | C75: XNGA12E | D75: Existing natural gas pipeline from R1 to R2 | E75: PJ | F75: PJ/a | G75: PRE
B76: R3 | C76: XNGA13E | D76: Existing natural gas pipeline from R1 to R3 | E76: PJ | F76: PJ/a
B77: R4 | C77: XNGA14E | D77: Existing natural gas pipeline from R1 to R4 | E77: PJ | F77: PJ/a
B78: R5 | C78: XNGA15E | D78: Existing natural gas pipeline from R1 to R5 | E78: PJ | F78: PJ/a
B79: R6 | C79: XNGA16E | D79: Existing natural gas pipeline from R1 to R6 | E79: PJ | F79: PJ/a
B80: R3 | C80: XNGA23E | D80: Existing natural gas pipeline from R2 to R3 | E80: PJ | F80: PJ/a
B81: R4 | C81: XNGA24E | D81: Existing natural gas pipeline from R2 to R4 | E81: PJ | F81: PJ/a
B82: R5 | C82: XNGA25E | D82: Existing natural gas pipeline from R2 to R5 | E82: PJ | F82: PJ/a
B83: R2 | C83: XNGA32E | D83: Existing natural gas pipeline from R3 to R2 | E83: PJ | F83: PJ/a
B84: R4 | C84: XNGA34E | D84: Existing natural gas pipeline from R3 to R4 | E84: PJ | F84: PJ/a
B85: R6 | C85: XNGA36E | D85: Existing natural gas pipeline from R3 to R6 | E85: PJ | F85: PJ/a
B86: R2 | C86: XNGA42E | D86: Existing natural gas pipeline from R4 to R2 | E86: PJ | F86: PJ/a
B87: R3 | C87: XNGA43E | D87: Existing natural gas pipeline from R4 to R3 | E87: PJ | F87: PJ/a
... B93: R4 | C93: XNGA64E | D93: Existing natural gas pipeline from R6 to R4 | E93: PJ | F93: PJ/a
B94: *
B103: =B75 -> R2 | C103: XNGA12N | D103: New natural gas pipeline from R1 to R2 | E103: PJ | F103: PJ/a | G103: PRE
B104: =B76 -> R3 | C104: XNGA13N | D104: New natural gas pipeline from R1 to R3 | E104: PJ | F104: PJ/a
B105: =B77 -> R4 | C105: XNGA14N | D105: New natural gas pipeline from R1 to R4 | E105: PJ | F105: PJ/a
B106: =B78 -> R5 | C106: XNGA15N | D106: New natural gas pipeline from R1 to R5 | E106: PJ | F106: PJ/a
B107: =B79 -> R6 | C107: XNGA16N | D107: New natural gas pipeline from R1 to R6 | E107: PJ | F107: PJ/a
B108: =B80 -> R3 | C108: XNGA23N | D108: New natural gas pipeline from R2 to R3 | E108: PJ | F108: PJ/a
B109: =B81 -> R4 | C109: XNGA24N | D109: New natural gas pipeline from R2 to R4 | E109: PJ | F109: PJ/a
B110: =B82 -> R5 | C110: XNGA25N | D110: New natural gas pipeline from R2 to R5 | E110: PJ | F110: PJ/a
B111: =B83 -> R2 | C111: XNGA32N | D111: New natural gas pipeline from R3 to R3 | E111: PJ | F111: PJ/a
B112: =B84 -> R4 | C112: XNGA34N | D112: New natural gas pipeline from R3 to R4 | E112: PJ | F112: PJ/a
B113: =B85 -> R6 | C113: XNGA36N | D113: New natural gas pipeline from R3 to R6 | E113: PJ | F113: PJ/a
B114: =B86 -> R2 | C114: XNGA42N | D114: New natural gas pipeline from R4 to R2 | E114: PJ | F114: PJ/a
B115: =B87 -> R3 | C115: XNGA43N | D115: New natural gas pipeline from R4 to R3 | E115: PJ | F115: PJ/a
... B121: =B93 -> R4 | C121: XNGA64N | D121: New natural gas pipeline from R6 to R4 | E121: PJ | F121: PJ/a
B122: *
B123: R1 | C123: XNGAC1N | D123: New Pipeline for Import Canadian natural gas to R1 | E123: PJ | F123: PJ/a
...

Sheet ANSv6.1-Constraints
A1: ANSWER-Constraints
B7: ConstrName | C7: ConstrDesc | D7: Units | E7: Set Memberships | F7: Comment

Sheet ANSv6.1-CommData
A1: ANSWER-CommData
B7: CommName | C7: CommDesc | D7: Units

Sheet ANSv6.1-TechData
A1: ANSWER-TechData
B7: TechName | C7: TechDesc | D7: Units | E7: CommIN | F7: CommOUT

Sheet ANSv6.1-ConstrData
A1: ANSWER-ConstrData
B7: ConstrName | C7: ConstrDesc | D7: Units | E7: TechName

Sheet Domestic NG Prices
A1: Lower 48 Natural Gas Production and Wellhead Prices by Supply Region, Reference case
A3: Region | B3: 2005 in 2005$ | C3: 2010 in 2010$ | D3: 2015 | E3: 2020 | F3: 2025 | G3: 2030 | H3: 2035 | I3: 2040
A5: Dry Production (trillion cubic feet) 1/
A6: Lower 48 Total | B6: 17.772602 | C6: 21.22 | D6: 24.329756 | E6: 28.812149 | F6: 31.609116 | G6: 33.242813 | H6: 34.918686 | I6: 36.377583
A8: Lower 48 Onshore | C8: 18.66 | D8: 22.213337 | E8: 26.654739 | F8: 29.519766 | G8: 30.82295 | H8: 32.458858 | I8: 33.428997
A9: Northeast | B9: 1.0956695 | C9: 1.52 | D9: 4.255119 | E9: 5.287964 | F9: 6.526698 | G9: 6.571349 | H9: 7.722331 | I9: 8.083803
A10: Gulf Coast | B10: 4.651669 | C10: 4.85 | D10: 6.021707 | E10: 8.327435 | F10: 9.761693 | G10: 10.173032 | H10: 10.303289 | I10: 10.544703
A11: Midcontinent | B11: 2.4793184 | C11: 3.43 | D11: 3.387572 | E11: 3.736248 | F11: 3.707607 | G11: 3.486203 | H11: 3.278044 | I11: 2.976638
A12: Southwest | B12: 1.8143151 | C12: 3.59 | D12: 3.454635 | E12: 3.461408 | F12: 3.271382 | G12: 3.288815 | H12: 3.325309 | I12: 4.202095
A13: Rocky Mountain | B13: 4.0738535 | C13: 5.06 | D13: 4.943402 | E13: 5.698319 | F13: 6.122963 | G13: 7.191331 | H13: 7.722852 | I13: 7.498688
A14: West Coast | B14: 0.25004801 | C14: 0.21 | D14: 0.150902 | E14: 0.143363 | F14: 0.129423 | G14: 0.112223 | H14: 0.107034 | I14: 0.123074
A16: Lower 48 Offshore | C16: 2.56 | D16: 2.11642 | E16: 2.157413 | F16: 2.089348 | G16: 2.419865 | H16: 2.459829 | I16: 2.948587
A17: Gulf | B17: 3.3515694 | C17: 2.52 | D17: 2.08797 | E17: 2.136284 | F17: 2.072056 | G17: 2.313114 | H17: 2.297252 | I17: 2.485032 | N17: Supply Curve Steps
A18: Shallow | B18: 1.9836395 | C18: 0.94 | D18: 0.609703 | E18: 0.420437 | F18: 0.490367 | G18: 0.567648 | H18: 0.577533 | I18: 0.526555 | N18: Prices | O18: Quantity
A19: Deep | B19: 1.3679301 | C19: 1.58 | D19: 1.478266 | E19: 1.715847 | F19: 1.581689 | G19: 1.745466 | H19: 1.719719 | I19: 1.958477 | M19: 1 | N19: 0.88 | O19: 0.4
A20: Pacific | B20: 0.056159936 | C20: 0.04 | D20: 0.02845 | E20: 0.02113 | F20: 0.017292 | G20: 0.044993 | H20: 0.119662 | I20: 0.154505 | M20: 2 | N20: 0.95 | O20: 0.7
A21: Atlantic | B21: 0 | C21: 0 | D21: 0 | E21: 0 | F21: 0 | G21: 0.061758 | H21: 0.042915 | I21: 0.30905 | M21: 3 | N21: 1 | O21: 1
M22: 4 | N22: 1.08 | O22: 1.05
A23: Supply Prices | M23: 5 | N23: 1.12 | O23: 1.1 | R23: * Based on estimated state production in the U.S. Crude Oil, NG, and NGL Reserves report found on
A24: (2012 dollars per million Btu) | M24: 6 | N24: 1.53 | O24: 1.2 | R24: Domestic NG CUM worksheet, the following assumptions were made:
A25: Henry Hub Spot Price | B25: 8.6000004 | C25: 4.39 | D25: 3.743775 | E25: 4.376477 | F25: 5.233528 | G25: 6.034758 | H25: 6.924771 | I25: 7.652016 | S25: R4 prices allotted as 33% of Rocky Mountain and 67% of Midcontinent
A26: Lower 48 Average Price | B26: 7.2912626 | C26: 4.06 | D26: 3.451457 | E26: 4.244283 | F26: 4.905202 | G26: 5.631371 | H26: 6.350606 | I26: 7.263971 | J26: =1+(I26-H26)/H26 -> 1.1438233 | S26: R6 prices allotted as 26% of Northeast and 74% of Gulf Coast
B27: =B26/Conv!$J$5/1000000*Conv!$D$38 -> 6.9107826 | C27: =C26/Conv!$J$5/1000000*Conv!$D$43 -> 3.4975839 | D27: =D26/Conv!$J$5/1000000*Conv!$D$45 -> 2.8659904 | E27: =E26/Conv!$J$5/1000000*Conv!$D$45 -> 3.5243302 | F27: =F26/Conv!$J$5/1000000*Conv!$D$45 -> 4.0731383 | G27: =G26/Conv!$J$5/1000000*Conv!$D$45 -> 4.6761281 | H27: =H26/Conv!$J$5/1000000*Conv!$D$45 -> 5.2733601 | I27: =I26/Conv!$J$5/1000000*Conv!$D$45 -> 6.031792 | M27: Step 3 Price Starting Point: | P27: 1.1 | S27: R7 prices allotted as 25% of Southwest, 40% of Gulf Coast, 24% of Midcontinent, and 11% offshore
A28: (2012 dollars per thousand cubic feet) | P28: *10% above average price
A29: Lower 48 Average Price | B29: 7.5100002 | C29: 4.16 | D29: 3.527389 | E29: 4.337657 | F29: 5.013116 | G29: 5.755261 | H29: 6.490319 | I29: 7.423778
B30: =B29/Conv!$D$6/1000/Conv!$J$5/1000000*Conv!$D$38 -> 6.9648785 | C30: =C29/Conv!$D$6/1000/Conv!$J$5/1000000*Conv!$D$43 -> 3.5065864 | D30: =D29/Conv!$D$6/1000/Conv!$J$5/1000000*Conv!$D$45 -> 2.8659903 | E30: =E29/Conv!$D$6/1000/Conv!$J$5/1000000*Conv!$D$45 -> 3.52433 | F30: =F29/Conv!$D$6/1000/Conv!$J$5/1000000*Conv!$D$45 -> 4.0731379 | G30: =G29/Conv!$D$6/1000/Conv!$J$5/1000000*Conv!$D$45 -> 4.6761279 | H30: =H29/Conv!$D$6/1000/Conv!$J$5/1000000*Conv!$D$45 -> 5.2733598 | I30: =I29/Conv!$D$6/1000/Conv!$J$5/1000000*Conv!$D$45 -> 6.0317917
A31: Lower 48 Onshore Price | J31: Growth Rate: 2012-2040 | M31: 2005 | N31: 2010 | O31: 2015 | P31: 2020 | Q31: 2025 | R31: 2030 | S31: 2035 | T31: 2040 | U31: Growth 2040+
A32: Northeast | B32: 7.6983781 | C32: 4.59 | D32: 3.462149 | E32: 4.10648 | F32: 5.444122 | G32: 6.612253 | H32: 6.571887 | I32: 8.110544 | J32: 1.4 | L32: R1 | M32: =B32/Conv!$D$6/1000/Conv!$J$5/1000000*Conv!$D$38 -> 7.1395827 | N32: =C32/Conv!$D$6/1000/Conv!$J$5/1000000*Conv!$D$43 -> 3.8690461 | O32: =D32/Conv!$D$6/1000/Conv!$J$5/1000000*Conv!$D$45 -> 2.8129831 | P32: =E32/Conv!$D$6/1000/Conv!$J$5/1000000*Conv!$D$45 -> 3.3364996 | Q32: =F32/Conv!$D$6/1000/Conv!$J$5/1000000*Conv!$D$45 -> 4.4233287 | R32: =G32/Conv!$D$6/1000/Conv!$J$5/1000000*Conv!$D$45 -> 5.3724307 | S32: =H32/Conv!$D$6/1000/Conv!$J$5/1000000*Conv!$D$45 -> 5.3396335 | T32: =I32/Conv!$D$6/1000/Conv!$J$5/1000000*Conv!$D$45 -> 6.5897865 | U32: =1+(T32-S32)/S32 -> 1.2341271
A33: Gulf Coast | B33: 7.881938 | C33: 4.18 | D33: 3.516361 | E33: 4.144482 | F33: 4.981838 | G33: 5.780926 | H33: 6.654837 | I33: 7.406928 | J33: 1.4 | L33: R2 | M33: =B32/Conv!$D$6/1000/Conv!$J$5/1000000*Conv!$D$38 -> 7.1395827 | N33: =C32/Conv!$D$6/1000/Conv!$J$5/1000000*Conv!$D$43 -> 3.8690461 | O33: =D32/Conv!$D$6/1000/Conv!$J$5/1000000*Conv!$D$45 -> 2.8129831 | P33: =E32/Conv!$D$6/1000/Conv!$J$5/1000000*Conv!$D$45 -> 3.3364996 | Q33: =F32/Conv!$D$6/1000/Conv!$J$5/1000000*Conv!$D$45 -> 4.4233287 | R33: =G32/Conv!$D$6/1000/Conv!$J$5/1000000*Conv!$D$45 -> 5.3724307 | S33: =H32/Conv!$D$6/1000/Conv!$J$5/1000000*Conv!$D$45 -> 5.3396335 | T33: =I32/Conv!$D$6/1000/Conv!$J$5/1000000*Conv!$D$45 -> 6.5897865 | U33: =1+(T33-S33)/S33 -> 1.2341271
A34: Midcontinent | B34: 7.3497467 | C34: 3.85 | D34: 3.693374 | E34: 4.74555 | F34: 5.072756 | G34: 5.835664 | H34: 6.776257 | I34: 7.591363 | J34: 1.5 | L34: R3 | M34: =B32/Conv!$D$6/1000/Conv!$J$5/1000000*Conv!$D$38 -> 7.1395827 | N34: =C32/Conv!$D$6/1000/Conv!$J$5/1000000*Conv!$D$43 -> 3.8690461 | O34: =D32/Conv!$D$6/1000/Conv!$J$5/1000000*Conv!$D$45 -> 2.8129831 | P34: =E32/Conv!$D$6/1000/Conv!$J$5/1000000*Conv!$D$45 -> 3.3364996 | Q34: =F32/Conv!$D$6/1000/Conv!$J$5/1000000*Conv!$D$45 -> 4.4233287 | R34: =G32/Conv!$D$6/1000/Conv!$J$5/1000000*Conv!$D$45 -> 5.3724307 | S34: =H32/Conv!$D$6/1000/Conv!$J$5/1000000*Conv!$D$45 -> 5.3396335 | T34: =I32/Conv!$D$6/1000/Conv!$J$5/1000000*Conv!$D$45 -> 6.5897865 | U34: =1+(T34-S34)/S34 -> 1.2341271
A35: Southwest | B35: 7.4758234 | C35: 4.21 | D35: 3.797485 | E35: 4.900776 | F35: 5.25594 | G35: 5.816219 | H35: 6.761253 | I35: 7.014832 | J35: 1.5 | L35: R4 | M35: =(B34*0.67+B36*0.33)/Conv!$D$6/1000/Conv!$J$5/1000000*Conv!$D$38 -> 6.6324621 | N35: =(C34*0.67+C36*0.33)/Conv!$D$6/1000/Conv!$J$5/1000000*Conv!$D$43 -> 3.2285883 | O35: =(D34*0.67+D36*0.33)/Conv!$D$6/1000/Conv!$J$5/1000000*Conv!$D$45 -> 2.8317147 | P35: =(E34*0.67+E36*0.33)/Conv!$D$6/1000/Conv!$J$5/1000000*Conv!$D$45 -> 3.6307605 | Q35: =(F34*0.67+F36*0.33)/Conv!$D$6/1000/Conv!$J$5/1000000*Conv!$D$45 -> 3.9224538 | R35: =(G34*0.67+G36*0.33)/Conv!$D$6/1000/Conv!$J$5/1000000*Conv!$D$45 -> 4.4561491 | S35: =(H34*0.67+H36*0.33)/Conv!$D$6/1000/Conv!$J$5/1000000*Conv!$D$45 -> 5.2438224 | T35: =(I34*0.67+I36*0.33)/Conv!$D$6/1000/Conv!$J$5/1000000*Conv!$D$45 -> 5.9401603 | U35: =1+(T35-S35)/S35 -> 1.132792
A36: Rocky Mountain | B36: 6.7492008 | C36: 3.79 | D36: 3.062554 | E36: 3.906456 | F36: 4.330034 | G36: 4.771581 | H36: 5.799615 | I36: 6.741779 | J36: 1.6 | L36: R5 | M36: =B32/Conv!$D$6/1000/Conv!$J$5/1000000*Conv!$D$38 -> 7.1395827 | N36: =C32/Conv!$D$6/1000/Conv!$J$5/1000000*Conv!$D$43 -> 3.8690461 | O36: =D32/Conv!$D$6/1000/Conv!$J$5/1000000*Conv!$D$45 -> 2.8129831 | P36: =E32/Conv!$D$6/1000/Conv!$J$5/1000000*Conv!$D$45 -> 3.3364996 | Q36: =F32/Conv!$D$6/1000/Conv!$J$5/1000000*Conv!$D$45 -> 4.4233287 | R36: =G32/Conv!$D$6/1000/Conv!$J$5/1000000*Conv!$D$45 -> 5.3724307 | S36: =H32/Conv!$D$6/1000/Conv!$J$5/1000000*Conv!$D$45 -> 5.3396335 | T36: =I32/Conv!$D$6/1000/Conv!$J$5/1000000*Conv!$D$45 -> 6.5897865 | U36: =1+(T36-S36)/S36 -> 1.2341271
A37: West Coast | B37: 7.5527425 | C37: 4.33 | D37: 4.386786 | E37: 4.760738 | F37: 5.281815 | G37: 5.659292 | H37: 6.794529 | I37: 7.623652 | J37: 1 | L37: R6 | M37: =(B32*0.26+B33*0.74)/Conv!$D$6/1000/Conv!$J$5/1000000*Conv!$D$38 -> 7.2655573 | N37: =(C32*0.26+C33*0.74)/Conv!$D$6/1000/Conv!$J$5/1000000*Conv!$D$43 -> 3.6133013 | O37: =(D32*0.26+D33*0.74)/Conv!$D$6/1000/Conv!$J$5/1000000*Conv!$D$45 -> 2.8455779 | P37: =(E32*0.26+E33*0.74)/Conv!$D$6/1000/Conv!$J$5/1000000*Conv!$D$45 -> 3.3593482 | Q37: =(F32*0.26+F33*0.74)/Conv!$D$6/1000/Conv!$J$5/1000000*Conv!$D$45 -> 4.1453817 | R37: =(G32*0.26+G33*0.74)/Conv!$D$6/1000/Conv!$J$5/1000000*Conv!$D$45 -> 4.8725977 | S37: =(H32*0.26+H33*0.74)/Conv!$D$6/1000/Conv!$J$5/1000000*Conv!$D$45 -> 5.389507 | T37: =(I32*0.26+I33*0.74)/Conv!$D$6/1000/Conv!$J$5/1000000*Conv!$D$45 -> 6.1667394 | U37: =1+(T37-S37)/S37 -> 1.1442122
L38: R7 | M38: =(B33*0.4+B34*0.24+B35*0.25+B40*0.11)/Conv!$D$6/1000/Conv!$J$5/1000000*Conv!$D$38 -> 7.1082317 | N38: =(C33*0.4+C34*0.24+C35*0.25+C40*0.11)/Conv!$D$6/1000/Conv!$J$5/1000000*Conv!$D$43 -> 3.5325487 | O38: =(D33*0.4+D34*0.24+D35*0.25+D40*0.11)/Conv!$D$6/1000/Conv!$J$5/1000000*Conv!$D$45 -> 2.9916272 | P38: =(E33*0.4+E34*0.24+E35*0.25+E40*0.11)/Conv!$D$6/1000/Conv!$J$5/1000000*Conv!$D$45 -> 3.7279214 | Q38: =(F33*0.4+F34*0.24+F35*0.25+F40*0.11)/Conv!$D$6/1000/Conv!$J$5/1000000*Conv!$D$45 -> 4.1502662 | R38: =(G33*0.4+G34*0.24+G35*0.25+G40*0.11)/Conv!$D$6/1000/Conv!$J$5/1000000*Conv!$D$45 -> 4.733051 | S38: =(H33*0.4+H34*0.24+H35*0.25+H40*0.11)/Conv!$D$6/1000/Conv!$J$5/1000000*Conv!$D$45 -> 5.4771501 | T38: =(I33*0.4+I34*0.24+I35*0.25+I40*0.11)/Conv!$D$6/1000/Conv!$J$5/1000000*Conv!$D$45 -> 5.9943983 | U38: =1+(T38-S38)/S38 -> 1.0944375
A39: Lower 48 Offshore Price | L39: R8 | M39: =B36/Conv!$D$6/1000/Conv!$J$5/1000000*Conv!$D$38 -> 6.2593025 | N39: =C36/Conv!$D$6/1000/Conv!$J$5/1000000*Conv!$D$43 -> 3.1947025 | O39: =D36/Conv!$D$6/1000/Conv!$J$5/1000000*Conv!$D$45 -> 2.4883136 | P39: =E36/Conv!$D$6/1000/Conv!$J$5/1000000*Conv!$D$45 -> 3.1739808 | Q39: =F36/Conv!$D$6/1000/Conv!$J$5/1000000*Conv!$D$45 -> 3.5181364 | R39: =G36/Conv!$D$6/1000/Conv!$J$5/1000000*Conv!$D$45 -> 3.8768916 | S39: =H36/Conv!$D$6/1000/Conv!$J$5/1000000*Conv!$D$45 -> 4.7121654 | T39: =I36/Conv!$D$6/1000/Conv!$J$5/1000000*Conv!$D$45 -> 5.4776701 | U39: =1+(T39-S39)/S39 -> 1.1624529
A40: Gulf | B40: 7.9900274 | C40: 4.93 | D40: 3.997221 | E40: 5.148303 | F40: 5.307836 | G40: 5.984872 | H40: 6.93263 | I40: 7.630444 | L40: R9 | M40: =B37/Conv!$D$6/1000/Conv!$J$5/1000000*Conv!$D$38 -> 7.0045182 | N40: =C37/Conv!$D$6/1000/Conv!$J$5/1000000*Conv!$D$43 -> 3.6498844 | O40: =D37/Conv!$D$6/1000/Conv!$J$5/1000000*Conv!$D$45 -> 3.5642471 | P40: =E37/Conv!$D$6/1000/Conv!$J$5/1000000*Conv!$D$45 -> 3.8680817 | Q40: =F37/Conv!$D$6/1000/Conv!$J$5/1000000*Conv!$D$45 -> 4.2914548 | R40: =G37/Conv!$D$6/1000/Conv!$J$5/1000000*Conv!$D$45 -> 4.5981535 | S40: =H37/Conv!$D$6/1000/Conv!$J$5/1000000*Conv!$D$45 -> 5.5205293 | T40: =I37/Conv!$D$6/1000/Conv!$J$5/1000000*Conv!$D$45 -> 6.1941886 | U40: =1+(T40-S40)/S40 -> 1.122028
A41: Pacific | B41: 7.5570188 | C41: 4.52 | D41: 4.76031 | E41: 5.304164 | F41: 5.757464 | G41: 7.071461 | H41: 6.676446 | I41: 7.566227
A42: Atlantic | B42: 0 | C42: 4.25 | D42: 4.103883 | E42: 5.020764 | F42: 5.201926 | G42: 7.711931 | H42: 8.816 | I42: 8.718942 | L42: Henry Hub | M42: =B25/Conv!$D$6/1000/Conv!$J$5/1000000*Conv!$D$38 -> 7.9757597 | N42: =C25/Conv!$D$6/1000/Conv!$J$5/1000000*Conv!$D$43 -> 3.7004602 | O42: =D25/Conv!$D$6/1000/Conv!$J$5/1000000*Conv!$D$45 -> 3.0418031 | P42: =E25/Conv!$D$6/1000/Conv!$J$5/1000000*Conv!$D$45 -> 3.5558711 | Q42: =F25/Conv!$D$6/1000/Conv!$J$5/1000000*Conv!$D$45 -> 4.2522218 | R42: =G25/Conv!$D$6/1000/Conv!$J$5/1000000*Conv!$D$45 -> 4.9032182 | S42: =H25/Conv!$D$6/1000/Conv!$J$5/1000000*Conv!$D$45 -> 5.6263504 | T42: =I25/Conv!$D$6/1000/Conv!$J$5/1000000*Conv!$D$45 -> 6.2172342 | U42: =1+(T42-S42)/S42 -> 1.1050208
A44: 1/ Marketed production (wet) minus extraction losses.
A45: - - = Not applicable.
A46: Note: Oil and Gas Supply Model regions are defined in Appendix F of the Annual Energy Outlook. Totals may not equal sum of
A47: components due to independent rounding.
A48: Sources: 2011 production: U.S. Department of the Interior, Office of Natural Resources Revenue; U.S. Energy
A49: Information Administration (EIA), Natural Gas Annual 2011, DOE/EIA-0131(2011) (Washington, DC, January 2013); EIA, U.S. Crude Oil,
A50: Natural Gas, and Natural Gas Liquids Reserves, DOE/EIA-0216(2011) (Washington, DC, August 2013); and EIA, Office of Energy Analysis
A51: (OEA). 2012 production: EIA, Natural Gas Monthly, DOE/EIA-0130(2013/06) (Washington, DC, June 2013)
A52: and EIA, Office of Energy Analysis. 2011 and 2012 natural gas spot prices at Henry Hub: Thomson Reuters.
A53: 2011 and 2012 offshore prices based on revenue data from the U.S. Department of the
A54: Interior, Office of Natural Resources Revenue; and EIA, OEA. 2011 and 2012 onshore prices based on
A55: daily data from Natural Gas Intelligence and assumed gathering charges. Projections: EIA, AEO2014 National Energy Modeling System.
A59: Oil and Gas Supply, Reference case
A61: Production and Supply | B61: 2005 in 2005$ | C61: 2010 in 2010$ | D61: 2015 | E61: 2020 | F61: 2025 | G61: 2030 | H61: 2035 | I61: 2040
A63: Dry Production (trillion cubic feet) 4/
A64: Alaska | B64: 0.45 | C64: 0.36 | D64: 0.299816 | E64: 0.277361 | F64: 0.255625 | G64: 1.1858 | H64: 1.174398 | I64: 1.167153

Sheet AEO NG Imports
A1: Natural Gas Imports and Exports, Reference case
A3: Volumes and Prices | B3: 2005 | C3: 2010 | D3: 2015 | E3: 2020 | F3: 2025 | G3: 2030 | H3: 2035 | I3: 2040
A5: Volumes (trillion cubic feet)
A6: Net Imports | B6: 3.5729237 | C6: 2.58 | D6: 1.084329 | E6: -1.926104 | F6: -3.410152 | G6: -4.937026 | H6: -5.531103 | I6: -5.798003
A7: Imports | B7: 4.3210435 | C7: 3.71 | D7: 3.108017 | E7: 2.335441 | F7: 1.988579 | G7: 1.964056 | H7: 2.004963 | I7: 2.22168
A8: Pipeline Imports from Canada | B8: 3.6804636 | C8: 3.25 | D8: 2.958251 | E8: 2.187141 | F8: 1.840279 | G8: 1.815756 | H8: 1.856663 | I8: 2.07338 | W8: 2005 | X8: 2010 | Y8: 2015 | AA8: 2005 | AB8: 2010 | AC8: 2015
A9: Pipeline Imports from Mexico | B9: 0.0093200002 | C9: 0.03 | D9: 0.002816 | E9: 0.0003 | F9: 0.0003 | G9: 0.0003 | H9: 0.0003 | I9: 0.0003 | U9: Canada | V9: Step 1 | W9: =W11*'Domestic NG Prices'!$O$19 -> 1424.2786 | X9: =X11*'Domestic NG Prices'!$O$19 -> 1082.5803 | AA9: =W9 -> 1424.2786 | AB9: =X9 -> 1082.5803
A10: Pipeline Imports from Bahamas | B10: 0 | C10: 0 | D10: 0 | E10: 0 | F10: 0 | G10: 0 | H10: 0 | I10: 0 | V10: Step 2 | W10: =W11*'Domestic NG Prices'!$O$20 -> 2492.4876 | X10: =X11*'Domestic NG Prices'!$O$20 -> 1894.5155 | AA10: =W10-W9 -> 1068.209 | AB10: =X10-X9 -> 811.93523
A11: Liquefied Natural Gas Imports 1/ | B11: 0.63126004 | C11: 0.43 | D11: 0.14695 | E11: 0.148 | F11: 0.148 | G11: 0.148 | H11: 0.148 | I11: 0.148 | V11: Step 3 | W11: =K17 -> 3560.6966 | X11: =L17 -> 2706.4508 | AA11: =W11-W10 -> 1068.209 | AB11: =X11-X10 -> 811.93523
A12: Exports | B12: 0.74812007 | C12: 1.14 | D12: 2.023689 | E12: 4.261545 | F12: 5.398732 | G12: 6.901082 | H12: 7.536067 | I12: 8.019683 | V12: Step 4 | W12: =W11*'Domestic NG Prices'!$O$22 -> 3738.7315 | X12: =X11*'Domestic NG Prices'!$O$22 -> 2841.7733 | AA12: =W12-W11 -> 178.03483 | AB12: =X12-X11 -> 135.32254
A13: Pipeline Exports to Canada | B13: 0.37822407 | C13: 0.74 | D13: 1.014307 | E13: 1.080964 | F13: 1.18302 | G13: 1.372742 | H13: 1.449109 | I13: 1.368091 | V13: Step 5 | W13: =W11*'Domestic NG Prices'!$O$23 -> 3916.7663 | X13: =X11*'Domestic NG Prices'!$O$23 -> 2977.0958 | AA13: =W13-W12 -> 178.03483 | AB13: =X13-X12 -> 135.32254
A14: Pipeline Exports to Mexico | B14: 0.30519602 | C14: 0.33 | D14: 0.901382 | E14: 1.102581 | F14: 1.497712 | G14: 2.01034 | H14: 2.568958 | I14: 3.133591 | V14: Step 6 | W14: =W11*'Domestic NG Prices'!$O$24 -> 4272.8359 | X14: =X11*'Domestic NG Prices'!$O$24 -> 3247.7409 | AA14: =W14-W13 -> 356.06966 | AB14: =X14-X13 -> 270.64508
A15: Liquefied Natural Gas Exports 2/ | B15: 0.0647 | C15: 0.06 | D15: 0.108 | E15: 2.078 | F15: 2.718 | G15: 3.518 | H15: 3.518 | I15: 3.518
A16: Net Imports | B16: =B7-B12 -> 3.5729234 | C16: 2.58 | D16: 1.084329 | E16: -1.926104 | F16: -3.410153 | G16: -4.937026 | H16: -5.531103 | I16: -5.798003 | K16: 2005 | L16: 2010 | M16: 2015 | N16: 2020 | O16: 2025 | P16: 2030 | Q16: 2035 | R16: 2040 | U16: LNG | V16: Step 1 | W16: =W18*'Domestic NG Prices'!$O$19 -> 244.36125 | X16: =X18*'Domestic NG Prices'!$O$19 -> 159.58355 | Y16: =Y18*'Domestic NG Prices'!$O$19 -> 16.799403 | AA16: =W16 -> 244.36125 | AB16: =X16 -> 159.58355 | AC16: =Y16 -> 16.799403
A17: Canada | B17: =B8-B13 -> 3.3022395 | C17: 2.51 | D17: 1.943944 | E17: 1.106177 | F17: 0.657259 | G17: 0.443014 | H17: 0.407555 | I17: 0.705289 | K17: =B17*1000000*Conv!$D$6*Conv!$J$5*1000000 -> 3560.6966 | L17: =C17*1000000*Conv!$D$6*Conv!$J$5*1000000 -> 2706.4508 | M17: =D17*1000000*Conv!$D$6*Conv!$J$5*1000000 -> 2096.0911 | N17: =E17*1000000*Conv!$D$6*Conv!$J$5*1000000 -> 1192.7544 | O17: =F17*1000000*Conv!$D$6*Conv!$J$5*1000000 -> 708.70084 | P17: =G17*1000000*Conv!$D$6*Conv!$J$5*1000000 -> 477.68748 | Q17: =H17*1000000*Conv!$D$6*Conv!$J$5*1000000 -> 439.4532 | R17: =I17*1000000*Conv!$D$6*Conv!$J$5*1000000 -> 760.49002 | V17: Step 2 | W17: =W18*'Domestic NG Prices'!$O$20 -> 427.63219 | X17: =X18*'Domestic NG Prices'!$O$20 -> 279.27121 | Y17: =Y18*'Domestic NG Prices'!$O$20 -> 29.398956 | AA17: =W17-W16 -> 183.27094 | AB17: =X17-X16 -> 119.68766 | AC17: =Y17-Y16 -> 12.599553
A18: Mexico | B18: =B9-B14 -> -0.29587602 | C18: -0.3 | D18: -0.898566 | E18: -1.102281 | F18: -1.497411 | G18: -2.01004 | H18: -2.568658 | I18: -3.133291 | K18: =B18*1000000*Conv!$D$6*Conv!$J$5*1000000 -> -319.03341 | L18: =C18*1000000*Conv!$D$6*Conv!$J$5*1000000 -> -323.48017 | M18: =D18*1000000*Conv!$D$6*Conv!$J$5*1000000 -> -968.89427 | N18: =E18*1000000*Conv!$D$6*Conv!$J$5*1000000 -> -1188.5535 | O18: =F18*1000000*Conv!$D$6*Conv!$J$5*1000000 -> -1614.6092 | P18: =G18*1000000*Conv!$D$6*Conv!$J$5*1000000 -> -2167.3603 | Q18: =H18*1000000*Conv!$D$6*Conv!$J$5*1000000 -> -2769.6998 | R18: =I18*1000000*Conv!$D$6*Conv!$J$5*1000000 -> -3378.525 | S18: =1+T18 -> 1.2198163 | T18: =AVERAGE((R18-Q18)/Q18) -> 0.21981634 | V18: Step 3 | W18: =K20 -> 610.90312 | X18: =L20 -> 398.95888 | Y18: =M20 -> 41.998509 | AA18: =W18-W17 -> 183.27094 | AB18: =X18-X17 -> 119.68766 | AC18: =Y18-Y17 -> 12.599553
A19: Bahamas | B19: 0 | C19: 0 | D19: 0 | E19: 0 | F19: 0 | G19: 0 | H19: 0 | I19: 0
A20: Liquefied Natural Gas | B20: =B11-B15 -> 0.56656004 | C20: 0.37 | D20: 0.03895 | E20: -1.93 | F20: -2.57 | G20: -3.37 | H20: -3.37 | I20: -3.37 | K20: =B20*1000000*Conv!$D$6*Conv!$J$5*1000000 -> 610.90312 | L20: =C20*1000000*Conv!$D$6*Conv!$J$5*1000000 -> 398.95888 | M20: =D20*1000000*Conv!$D$6*Conv!$J$5*1000000 -> 41.998509 | N20: =E20*1000000*Conv!$D$6*Conv!$J$5*1000000 -> -2081.0558 | O20: =F20*1000000*Conv!$D$6*Conv!$J$5*1000000 -> -2771.1468 | P20: =G20*1000000*Conv!$D$6*Conv!$J$5*1000000 -> -3633.7606 | Q20: =H20*1000000*Conv!$D$6*Conv!$J$5*1000000 -> -3633.7606 | R20: =I20*1000000*Conv!$D$6*Conv!$J$5*1000000 -> -3633.7606 | S20: =1+T20 -> 1 | T20: =AVERAGE((R20-Q20)/Q20) -> 0
A22: Border Prices
A23: (2012 dollars per thousand cubic feet)
A24: Average Import Price | B24: 7.7595983 | C24: 4.53 | D24: 4.023057 | E24: 5.404779 | F24: 5.894635 | G24: 6.625491 | H24: 7.327688 | I24: 7.948038
A25: Pipeline Import Prices | K25: 2005 | L25: 2010 | M25: 2015 | N25: 2020 | O25: 2025 | P25: 2030 | Q25: 2035 | R25: 2040 | S25: Growth 2040+
A26: From Canada | B26: 7.7216897 | C26: 4.48 | D26: 3.981129 | E26: 5.384144 | F26: 5.864737 | G26: 6.603305 | H26: 7.293546 | I26: 7.904185 | K26: =B26/Conv!$D$6/1000/Conv!$J$5/1000000*Conv!$D$38 -> 7.1612022 | L26: =C26/Conv!$D$6/1000/Conv!$J$5/1000000*Conv!$D$43 -> 3.7763238 | M26: =D26/Conv!$D$6/1000/Conv!$J$5/1000000*Conv!$D$45 -> 3.2346524 | N26: =E26/Conv!$D$6/1000/Conv!$J$5/1000000*Conv!$D$45 -> 4.3745968 | O26: =F26/Conv!$D$6/1000/Conv!$J$5/1000000*Conv!$D$45 -> 4.7650768 | P26: =G26/Conv!$D$6/1000/Conv!$J$5/1000000*Conv!$D$45 -> 5.3651605 | Q26: =H26/Conv!$D$6/1000/Conv!$J$5/1000000*Conv!$D$45 -> 5.9259787 | R26: =I26/Conv!$D$6/1000/Conv!$J$5/1000000*Conv!$D$45 -> 6.4221206 | S26: =1+T26 -> 1.1047288 | T26: =AVERAGE((R26-Q26)/Q26,(Q26-P26)/P26,(P26-O26)/O26) -> 0.10472884
A27: From Mexico | B27: 8.2281752 | C27: 4.63 | D27: 3.808583 | E27: 4.125798 | F27: 4.71418 | G27: 5.474166 | H27: 6.385399 | I27: 7.05028
A28: From Bahamas | B28: 2.3101912 | C28: 0 | D28: 0 | E28: 0 | F28: 0 | G28: 0 | H28: 0 | I28: 0
A29: LNG Price (including regasification) | B29: 7.9806232 | C29: 4.94 | D29: 4.87124 | E29: 5.712322 | F29: 6.268783 | G29: 6.900025 | H29: 7.757905 | I29: 8.564201 | K29: =B29/Conv!$D$6/1000/Conv!$J$5/1000000*Conv!$D$38 -> 7.4013408 | L29: =C29/Conv!$D$6/1000/Conv!$J$5/1000000*Conv!$D$43 -> 4.1640714 | M29: =D29/Conv!$D$6/1000/Conv!$J$5/1000000*Conv!$D$45 -> 3.9578642 | N29: =E29/Conv!$D$6/1000/Conv!$J$5/1000000*Conv!$D$45 -> 4.6412402 | O29: =F29/Conv!$D$6/1000/Conv!$J$5/1000000*Conv!$D$45 -> 5.0933626 | P29: =G29/Conv!$D$6/1000/Conv!$J$5/1000000*Conv!$D$45 -> 5.6062444 | Q29: =H29/Conv!$D$6/1000/Conv!$J$5/1000000*Conv!$D$45 -> 6.3032687 | R29: =I29/Conv!$D$6/1000/Conv!$J$5/1000000*Conv!$D$45 -> 6.9583811 | S29: =1+T29 -> 1.1096528 | T29: =AVERAGE((R29-Q29)/Q29,(Q29-P29)/P29,(P29-O29)/O29) -> 0.10965276
A31: 1/ Includes imports of liquefied natural gas that are later re-exported.
A32: 2/ Includes re-exported liquefied natural gas.
A33: LNG = Liquefied natural gas.
A34: - - = Not applicable.
A35: Note: Totals may not equal sum of components due to independent rounding. Data for 2011 and 2012
A36: may differ from official EIA data reports due to internal conversion factors within the AEO2014 National Energy Modeling System.
A37: Sources: 2011 and 2012: U.S. Energy Information Administration (EIA), Natural Gas Monthly, DOE/EIA-
A38: 0130(2013/06) (Washington, DC, June 2013) and EIA, Office of Energy Analysis. Projections: EIA, AEO2014 National Energy Modeling System.
A40: Office of Energy Analysis. Projections: EIA, AEO2012 National Energy Modeling System.

Sheet Exports
A1: Back to Contents | B1: Data 1: Natural Gas Exports (Summary)
A2: Sourcekey | B2: N9130US2 | C2: NA1284_SAK_2 | D2: NA1284_SAZ_2 | E2: NA1284_SCA_2 | F2: NA1284_SID-Z00_2 | G2: NGA_EPG0_EEX_SLA-Z00_MMCF | H2: NGA_EPG0_EEX_SME-Z00_MMCF | I2: NA1284_SMI_2 | J2: NA1284_SMN-Z00_2 | K2: NA1284_SMT_2 | L2: NGA_EPG0_EEX_SNH-Z00_MMCF | M2: NA1284_SNY_2 | N2: NA1284_SND-Z00_2 | O2: NA1284_STX_2 | P2: NA1284_SWA_2
A3: Date | B3: U.S. Natural Gas Exports (MMcf) | C3: Alaska Natural Gas Exports (No Intransit Deliveries) (MMcf) | D3: Arizona Natural Gas Exports (No Intransit Deliveries) (MMcf) | E3: California Natural Gas Exports (No Intransit Deliveries) (MMcf) | F3: Idaho Natural Gas Exports to All Countries (Million Cubic Feet) | G3: Louisiana Natural Gas Exports From All Countries (Million Cubic Feet) | H3: Maine Natural Gas Exports (No Intransit Deliveries) (Million Cubic Feet) | I3: Michigan Natural Gas Exports (No Intransit Deliveries) (MMcf) | J3: Minnesota Natural Gas Exports to All Countries (Million Cubic Feet) | K3: Montana Natural Gas Exports (No Intransit Deliveries) (MMcf) | L3: New Hampshire Natural Gas Exports (Million Cubic Feet) | M3: New York Natural Gas Exports (No Intransit Deliveries) (MMcf) | N3: North Dakota Natural Gas Exports to All Countries (Million Cubic Feet) | O3: Texas Natural Gas Exports (No Intransit Deliveries) (MMcf) | P3: Washington Natural Gas Exports (No Intransit Deliveries) (MMcf)
A4: 37802 | B4: 679922 | C4: 65698 | D4: 10840 | E4: 53720 | F4: 15 | I4: 259597 | J4: 172 | K4: 8889 | M4: 2215 | N4: 66 | O4: 278676 | P4: 33
A5: 38168 | B5: 854138 | C5: 62099 | D5: 7544 | E5: 80019 | F5: 48 | I5: 368947 | J5: 2193 | K5: 23379 | M5: 3 | N5: 0 | O5: 309891 | P5: 15
A6: 38533 | B6: 728601 | C6: 65124 | D6: 7376 | E6: 89987 | F6: 0 | I6: 337818 | J6: 0 | K6: 19159 | M6: 0 | N6: 0 | O6: 207833 | P6: 1304
A7: 38898 | B7: 723958 | C7: 60765 | D7: 15720 | E7: 101101 | F7: 0 | I7: 317291 | J7: 0 | K7: 21245 | M7: 0 | N7: 0 | O7: 205307 | P7: 2529
A8: 39263 | B8: 822454 | C8: 48396 | D8: 16207 | E8: 96757 | F8: 0 | G8: 0 | H8: 0 | I8: 455216 | J8: 0 | K8: 20420 | L8: 0 | M8: 2 | N8: 0 | O8: 178897 | P8: 6560
A9: 39629 | B9: 963263 | C9: 39164 | D9: 46581 | E9: 109127 | F9: 252 | G9: 0 | H9: 0 | I9: 531333 | J9: 0 | K9: 16399 | L9: 64 | M9: 0 | N9: 0 | O9: 209741 | P9: 10603
A10: 39994 | B10: 1072357 | C10: 30536 | D10: 44152 | E10: 101422 | F10: 113 | G10: 0 | H10: 2131 | I10: 673318 | J10: 0 | K10: 12504 | L10: 0 | M10: 0 | N10: 0 | O10: 195651 | P10: 12530
A11: 40359 | B11: 1136789 | C11: 30100 | D11: 44693 | E11: 43278 | F11: 12 | G11: 22814 | H11: 452 | I11: 721075 | J11: 0 | K11: 9437 | L11: 0 | M11: 0 | N11: 0 | O11: 257158 | P11: 7769
A12: 40724 | B12: 1505650 | C12: 16398 | D12: 45086 | E12: 94433 | F12: 10 | G12: 38552 | H12: 1028 | I12: 876267 | J12: 3975 | K12: 6826 | L12: 336 | M12: 38783 | N12: 0 | O12: 374188 | P12: 9768
A13: 41090 | B13: 1618828 | C13: 9342 | D13: 46385 | E13: 110656 | F13: 0 | G13: 7655 | H13: 6952 | I13: 872620 | J13: 11768 | K13: 4332 | L13: 199 | M13: 68843 | N13: 0 | O13: 474060 | P13: 6016
A14: 41455 | B14: 1572413
C16: R9 | D16: R8 | E16: R9 | F16: R8 | G16: R7 | H16: R1 | I16: R3 | J16: R4 | K16: R8 | L16: R1 | M16: R2 | N16: R4 | O16: R7 | P16: R9
C17: LNG | D17: Mexico | E17: Mexico | F17: Canada | G17: LNG | H17: LNG | I17: Canada | J17: Canada | K17: Canada | L17: Canada | M17: Canada | N17: Canada | O17: Mexico (.965) | P17: Canada
O18: LNG (.035)
C20: Canada | D20: Mexico | E20: LNG | O20: 2011 | P20: 2012
B21: 2011 | C21: =F12+I12+J12+K12+L12+M12+N12+P12 -> 935965 | D21: =D12+E12+O12*0.965 -> 500610.42 | E21: =C12+G12+H12+O12*0.035 -> 69074.58 | F21: =SUM(C21:E21) -> 1505650 | N21: R7 | O21: =O12*0.965 -> 361091.42 | P21: =O13*0.965 -> 457467.9
B22: 2012 | C22: =F13+I13+J13+K13+L13+M13+N13+P13 -> 963778 | D22: =D13+E13+O13*0.965 -> 614508.9 | E22: =C13+G13+H13+O12*0.035 -> 37045.58 | F22: =SUM(C22:E22) -> 1615332.5 | N22: R8 | O22: =D12 -> 45086 | P22: =D13 -> 46385
N23: R9 | O23: =E12 -> 94433 | P23: =E13 -> 110656
O24: =SUM(O21:O23) -> 500610.42 | P24: =SUM(P21:P23) -> 614508.9
N26: R7 | O26: =O21/O24 -> 0.72130225 | P26: =P21/P24 -> 0.74444471 | Q26: =AVERAGE(O26:P26) -> 0.73287348
N27: R8 | O27: =O22/O24 -> 0.090062049 | P27: =P22/P24 -> 0.07548304 | Q27: =AVERAGE(O27:P27) -> 0.082772544
N28: R9 | O28: =O23/O24 -> 0.18863571 | P28: =P23/P24 -> 0.18007225 | Q28: =AVERAGE(O28:P28) -> 0.18435398
A31: Back to Contents | B31: Data 1: Natural Gas Imports (Summary)
A32: Sourcekey | B32: N9100US2 | C32: NGA_EPG0_IM0_SCA-Z00_MMCF | D32: NA1274_SGA-Z00_2 | E32: NA1274_SID_2 | F32: NA1274_SLA_2 | G32: NA1274_SME_2 | H32: NA1274_SMD-Z00_2 | I32: NA1274_SMA_2 | J32: NA1274_SMI_2 | K32: NA1274_SMN_2 | L32: NGM_EPG0_IM0_SMS-Z00_MMCF | M32: NA1274_SMT_2 | N32: NA1274_SNH_2 | O32: NA1274_SNY_2 | P32: NA1274_SND_2 | Q32: NA1274_STX_2 | R32: NA1274_SVT_2 | S32: NA1274_SWA_2
A33: Date | B33: U.S. Natural Gas Imports (MMcf) | C33: California Natural Gas Imports (No intransit Receipts) (MMcf) | D33: Georgia Natural Gas Imports from All Countries (Million Cubic Feet) | E33: Idaho Natural Gas Imports (No intransit Receipts) (MMcf) | F33: Louisiana Natural Gas Imports (No intransit Receipts) (MMcf) | G33: Maine Natural Gas Imports (No intransit Receipts) (MMcf) | H33: Maryland Natural Gas Imports from All Countries (Million Cubic Feet) | I33: Massachusetts Natural Gas Imports (No intransit Receipts) (MMcf) | J33: Michigan Natural Gas Imports (No intransit Receipts) (MMcf) | K33: Minnesota Natural Gas Imports (No intransit Receipts) (MMcf) | L33: Mississippi Natural Gas Imports (No intransit Receipts) (MMcf) | M33: Montana Natural Gas Imports (No intransit Receipts) (MMcf) | N33: New Hampshire Natural Gas Imports (No intransit Receipts) (MMcf) | O33: New York Natural Gas Imports (No intransit Receipts) (MMcf) | P33: North Dakota Natural Gas Imports (No intransit Receipts) (MMcf) | Q33: Texas Natural Gas Imports (No intransit Receipts) (MMcf) | R33: Vermont Natural Gas Imports (No intransit Receipts) (MMcf) | S33: Washington Natural Gas Imports (No intransit Receipts) (MMcf)
A34: 37802 | B34: 3943749 | D34: 43927 | E34: 623652 | F34: 238237 | G34: 115301 | H34: 66078 | I34: 158277 | J34: 7716 | K34: 364725 | M34: 719011 | N34: 34983 | O34: 761859 | P34: 435453 | R34: 8272 | S34: 366257
A35: 38168 | B35: 4258558 | D35: 105203 | E35: 707885 | F35: 163738 | G35: 102292 | H35: 209294 | I35: 173780 | J35: 24272 | K35: 404091 | M35: 757642 | N35: 17257 | O35: 785055 | P35: 460237 | Q35: 0 | R35: 8761 | S35: 339051
A36: 38533 | B36: 4341034 | D36: 132062 | E36: 624468 | F36: 108967 | G36: 135162 | H36: 221689 | I36: 168542 | J36: 18281 | K36: 472600 | M36: 728851 | N36: 28041 | O36: 856107 | P36: 491867 | Q36: 9320 | R36: 8392 | S36: 336684
A37: 38898 | B37: 4186281 | D37: 146766 | E37: 690781 | F37: 144060 | G37: 105650 | H37: 116613 | I37: 176097 | J37: 10434 | K37: 422847 | M37: 684278 | N37: 31853 | O37: 865952 | P37: 514052 | Q37: 12749 | R37: 8404 | S37: 255743
A38: 39263 | B38: 4607582 | C38: 0 | D38: 170243 | E38: 704429 | F38: 268714 | G38: 106643 | H38: 148231 | I38: 183624 | J38: 10590 | K38: 504676 | L38: 0 | M38: 779129 | N38: 56879 | O38: 892283 | P38: 465973 | Q38: 54062 | R38: 8021 | S38: 254086
A39: 39629 | B39: 3984101 | C39: 1345 | D39: 135711 | E39: 688782 | F39: 18110 | G39: 121295 | H39: 25894 | I39: 166247 | J39: 12109 | K39: 481748 | L39: 0 | M39: 666251 | N39: 39438 | O39: 780862 | P39: 490045 | Q39: 47704 | R39: 8106 | S39: 300453
A40: 39994 | B40: 3751360 | C40: 1953 | D40: 142244 | E40: 693892 | F40: 70099 | G40: 114081 | H40: 72339 | I40: 161486 | J40: 12216 | K40: 482749 | L40: 0 | M40: 502435 | N40: 26767 | O40: 640119 | P40: 480013 | Q40: 32131 | R40: 9319 | S40: 309516
A41: 40359 | B41: 3740757 | C41: 22503 | D41: 106454 | E41: 708806 | F41: 90867 | G41: 131035 | H41: 43431 | I41: 164984 | J41: 11365 | K41: 451405 | L41: 0 | M41: 706201 | N41: 18297 | O41: 434526 | P41: 476864 | Q41: 32765 | R41: 8895 | S41: 332358
A42: 40724 | B42: 3468693 | C42: 2171 | D42: 75641 | E42: 606099 | F42: 60554 | G42: 149736 | H42: 13981 | I42: 135278 | J42: 15193 | K42: 548686 | L42: 5774 | M42: 679848 | N42: 19826 | O42: 324474 | P42: 448977 | Q42: 58212 | R42: 10319 | S42: 313922
A43: 41090 | B43: 3137789 | C43: 0 | D43: 59266 | E43: 634194 | F43: 20132 | G43: 76540 | H43: 2790 | I43: 86609 | J43: 11630 | K43: 406327 | L43: 0 | M43: 754058 | N43: 47451 | O43: 278422 | P43: 433721 | Q43: 6165 | R43: 8247 | S43: 312236
C45: R9 | D45: R5 | E45: R8 | F45: R7 | G45: R1 | H45: R5 | I45: R1 | J45: R3 | K45: R4 | L45: R6 | M45: R8 | N45: R1 | O45: R2 | P45: R4 | Q45: R7 | R45: R1 | S45: R9
C46: LNG | D46: LNG | E46: Canada | F46: LNG | G46: Canada | H46: LNG | I46: LNG | J46: Canada | K46: Canada | L46: LNG | M46: Canada | N46: Canada | O46: Canada | P46: Canada | Q46: Mexico | R46: Canada | S46: Canada
Q47: LNG
C49: Canada | D49: Mexico | E49: LNG
B50: 2011 | C50: =E42+G42+J42+K42+M42+N42+O42+P42+R42+S42 -> 3117080 | D50: =0 -> 0 | E50: =D42+F42+H42+I42+L42+Q42 -> 349440 | F50: =SUM(C50:E50) -> 3466520
B51: 2012 | C51: =C43+E43+G43+J43+K43+M43+N43+O43+P43+R43+S43 -> 2962826 | D51: =0 -> 0 | E51: =D43+F43+H43+I43+L43+Q43 -> 174962 | F51: =SUM(C51:E51) -> 3137788
A53: Net Imports from Canada | C53: 2011 | D53: 2011 | E53: 2011 | F53: 2012 | G53: AVG
B54: R1 | C54: =(G42+N42+R42-L12)/1000000 -> 0.179545 | D54: =(G43+N43+R43-L13)/1000000 -> 0.132039 | E54: =C54/C$65 -> 0.059018358 | F54: =D54/D$65 -> 0.046166869 | G54: =AVERAGE(E54:F54) -> 0.052592614
B55: R2 | C55: =(O42-M12)/1000000 -> 0.285691 | D55: =(O43-M13)/1000000 -> 0.209579 | E55: =C55/C$65 -> 0.093909681 | F55: =D55/D$65 -> 0.073278397 | G55: =AVERAGE(E55:F55) -> 0.083594039
B56: R3 | C56: =(J42-I12)/1000000 -> -0.861074 | D56: =(J43-I13)/1000000 -> -0.86099
B57: R4 | C57: =(K42+P42-N12-J12)/1000000 -> 0.993688 | D57: =(K43+P43-N13-J13)/1000000 -> 0.82828 | E57: =C57/C$65 -> 0.32663585 | F57: =D57/D$65 -> 0.28960454 | G57: =AVERAGE(E57:F57) -> 0.3081202
B58: R5 | C58: 0 | D58: =0 -> 0 | E58: =C58/C$65 -> 0 | F58: =D58/D$65 -> 0 | G58: =AVERAGE(E58:F58) -> 0
B59: R6 | C59: =0 -> 0 | D59: =0 -> 0 | E59: =C59/C$65 -> 0 | F59: =D59/D$65 -> 0 | G59: =AVERAGE(E59:F59) -> 0
B60: R7 | C60: =0 -> 0 | D60: =0 -> 0 | E60: =C60/C$65 -> 0 | F60: =D60/D$65 -> 0 | G60: =AVERAGE(E60:F60) -> 0
B61: R8 | C61: =(E42+M42-F12-K12)/1000000 -> 1.279111 | D61: =(E43+M43-F13-K13)/1000000 -> 1.38392 | E61: =C61/C$65 -> 0.42045744 | F61: =D61/D$65 -> 0.48388168 | G61: =AVERAGE(E61:F61) -> 0.45216956
B62: R9 | C62: =(S42-P12)/1000000 -> 0.304154 | D62: =(S43-P13)/1000000 -> 0.30622 | E62: =C62/C$65 -> 0.099978667 | F62: =D62/D$65 -> 0.10706851 | G62: =AVERAGE(E62:F62) -> 0.10352359
C63: =SUM(C54:C62) -> 2.181115 | D63: =SUM(D54:D62) -> 1.999048 | E63: =C63/C$63 -> 1 | F63: =D63/D$63 -> 1
C64: =(C50-C21)/1000000 -> 2.181115 | D64: =(C51-C22)/1000000 -> 1.999048 | E64: =C64/C$63 -> 1 | F64: =D64/D$63 -> 1
C65: =SUM(C54:C55,C57:C62) -> 3.042189 | D65: =SUM(D54:D55,D57:D62) -> 2.860038

Sheet ANSv6.0-ConstrData
A1: ANSWER-ConstrData
B7: ConstrName | C7: ConstrDesc | D7: Units | E7: TechName

Sheet ANSv6.0-TechData
A1: ANSWER-TechData
B7: TechName | C7: TechDesc | D7: Units | E7: CommIN | F7: CommOUT

Sheet ANSv6.0-CommData
A1: ANSWER-CommData
B7: CommName | C7: CommDesc | D7: Units

Sheet ANSv6.0-Constraints
A1: ANSWER-Constraints
B7: ConstrName | C7: ConstrDesc | D7: Units | E7: Set Memberships | F7: Comment

Sheet ANSv6.0-Technologies
A1: ANSWER-Technologies
B7: TechName | C7: TechDesc | D7: TACTUnit | E7: TCAPUnit | F7: Set Memberships | G7: Comment

Sheet ANSv6.0-Commodities
A1: ANSWER-Commodities
B7: CommName | C7: CommDesc | D7: CommUnit | E7: Set Memberships | F7: Comment

Sheet Emissions
A1: Emissions Calculations Raw Data
A3: Table 1B. GREET Production Emissions Factors with Nonroad Sources Excluded, ktonnes/Petajoule
A4: * Table used for OC and BC factors
A5: Resource | B5: Extraction Description | C5: Units | D5: VOC | E5: CO | F5: NOx | G5: PM10 | H5: PM2.5 | I5: SOx | J5: CH4 | K5: N2O | L5: CO2 | M5: OC | N5: BC1 | O5: Hg2
A6: Oil | B6: Crude for Use in U.S. Refineries (no oil sands) | C6: ktonnes/Petajoule | D6: 0.0010994635 | E6: 0.0029382215 | F6: 0.0092506587 | G6: 0.0011184198 | H6: 0.00038860349 | I6: 0.0019524956 | J6: 0.018861487 | K6: 4.3599416e-05 | L6: 2.4880102 | M6: 3.1277842e-05 | N6: 1.2321574e-05 | O6: 0
A7: Coal | B7: Mining and Cleaning | C7: ktonnes/Petajoule | D7: 0.0065019999 | E7: 0.00015165014 | F7: 0.00054973177 | G7: 0.16024681 | H7: 0.039609122 | I7: 0.0062650465 | J7: 0.1117472 | K7: 4.739067e-06 | L7: 0.43978542 | M7: 0.0020595985 | N7: 0.00055447084 | O7: 0
A8: Natural Gas | B8: Recovery | C8: ktonnes/Petajoule | D8: 0.00056868804 | E8: 0.0040471632 | F8: 0.013364169 | G8: 0.00018008454 | H8: 0.00012321574 | I8: 0.00040755976 | J8: 0.074592914 | K8: 2.9382215e-05 | L8: 1.3980248 | M8: na3 | N8: na | O8: 0
B9: Processing: Combustion | C9: ktonnes/Petajoule | D9: 0.00018008454 | E9: 0.00070138191 | F9: 0.002758137 | G9: 0.00030330029 | H9: 0.00014217201 | I9: 0.00064451311 | J9: 0.031941311 | K9: 3.6016909e-05 | L9: 1.7544026 | M9: na | N9: na | O9: 0
B10: Processing: Non-Combustion | C10: ktonnes/Petajoule | D10: 0.0041893352 | E10: 0.0011373761 | F10: 0.0014691108 | G10: 1.8956268e-05 | H10: 9.4781339e-06 | I10: 0.0096013497 | J10: 0 | K10: 0 | L10: 1.1771842 | M10: na | N10: na | O10: 0
B11: Natural Gas Total | C11: ktonnes/Petajoule | D11: 0.0049381078 | E11: 0.0058859212 | F11: 0.017591417 | G11: 0.0005023411 | H11: 0.00027486588 | I11: 0.010653423 | J11: 0.10653423 | K11: 6.5399124e-05 | L11: 4.3296116 | M11: 1.8008454e-05 | N11: 4.739067e-06 | O11: 0
A12: Uranium | B12: Mining | C12: ktonnes/Petajoule | D12: 2.8434402e-05 | E12: 0.00018008454 | F12: 0.00062555684 | G12: 0.00014217201 | H12: 3.7912536e-05 | I12: 0.00024643148 | J12: 0.0004739067 | K12: 2.8434402e-06 | L12: 0.15638921 | M12: na | N12: na | O12: 0
B13: Ore Transportation | C13: ktonnes/Petajoule | D13: 0 | E13: 0 | F13: 0 | G13: 0 | H13: 0 | I13: 0 | J13: 0 | K13: 0 | L13: 0.00094781339 | M13: na | N13: na | O13: 0
B14: Enrichment | C14: ktonnes/Petajoule | D14: 7.5825072e-05 | E14: 0.00021799708 | F14: 0.00085303206 | G14: 0.0010899854 | H14: 0.00028434402 | I14: 0.0018861487 | J14: 0.0011373761 | K14: 1.0425947e-05 | L14: 0.83407579 | M14: na | N14: na | O14: 0
B15: Conversion, Fabrication, & Waste Storage | C15: ktonnes/Petajoule | D15: 1.8956268e-05 | E15: 0.00010425947 | F15: 0.00036016909 | G15: 6.6346938e-05 | H15: 1.8956268e-05 | I15: 0.00012321574 | J15: 0.00028434402 | K15: 9.4781339e-07 | L15: 0.083407579 | M15: na | N15: na | O15: 0
B16: Uranium Total | C16: ktonnes/Petajoule | D16: 0.00012321574 | E16: 0.00051181923 | F16: 0.0018482361 | G16: 0.0013079825 | H16: 0.00035069096 | I16: 0.0022557959 | J16: 0.0018956268 | K16: 1.4217201e-05 | L16: 1.0738726 | M16: na | N16: na | O16: 0
A17: 1Using elemental carbon as a surrogate for black carbon.
A18: 2Hg emissions from resource extraction are insignificant.
A19: 3Not available.
A22: Emissions from natural gas distribution to end-use sectors
A23: From GREET 1.8
B25: Natural Gas as a Processing Fuel (produced in North America)
B26: NG Recovery | C26: NG Processing | D26: NG Processing: Non-Combustion Emissions | E26: NG Transmission and Distribution
A27: Energy efficiency | B27: 0.972 | C27: 0.972
A28: Urban emission share | B28: 0.01 | C28: 0.01
A29: Loss factor | C29: 1.0014791 | E29: 1.0036721
A30: Total emissions: grams/mmBtu of fuel throughput | F30: kT/PJ
A31: VOC | B31: 0.75722497 | C31: 0.19822358 | D31: 4.4 | E31: 0.45055161 | F31: =E31*0.00094778 -> 0.0004270238
A32: CO | B32: 4.9469324 | C32: 0.79524214 | D32: 1.2 | E32: 1.0349977 | F32: =E32*0.00094778 -> 0.00098095011
A33: NOx | B33: 15.387618 | C33: 3.0383871 | D33: 1.546 | E33: 2.7566019 | F33: =E33*0.00094778 -> 0.0026126522
A34: PM10 | B34: 0.35918495 | C34: 0.35059469 | D34: 0.02 | E34: 0.14467216 | F34: =E34*0.00094778 -> 0.00013711738
A35: PM2.5 | B35: 0.26284648 | C35: 0.16672718 | D35: 0.01 | E35: 0.079537846 | F35: =E35*0.00094778 -> 7.538438e-05
A36: SOx | B36: 0.52121423 | C36: 0.71670428 | D36: 10.089 | E36: 0.20353486 | F36: =E36*0.00094778 -> 0.00019290627
A37: CH4: combustion | B37: 4.5946923 | C37: 0.4672887 | E37: 1.7443944 | F37: =E37*0.00094778 -> 0.0016533021
A38: N2O | B38: 0.036854129 | C38: 0.038858 | E38: 0.010635234 | F38: =E38*0.00094778 -> 1.0079863e-05
A39: CO2 | B39: 1752.5699 | C39: 1885.2003 | D39: 1237 | E39: 362.45502 | F39: =E39*0.00094778 -> 0.34352762
A40: CH4: leakage | B40: 73.736946 | C40: 33.103413 | E40: 82.18236 | F40: =E40*0.00094778 -> 0.077890798
A41: VOC evaporation
A42: Misc. Items
A44: Distribution emissions (from column F, transposed)
A45: VOC | B45: CO | C45: NOx | D45: PM10 | E45: PM2.5 | F45: SOx | G45: CH4: combustion | H45: N2O | I45: CO2
A46: 0.0004270238 | B46: 0.00098095011 | C46: 0.0026126522 | D46: 0.00013711738 | E46: 7.538438e-05 | F46: 0.00019290627 | G46: =F40+F37 -> 0.0795441 | H46: 1.0079863e-05 | I46: 0.34352762
A50: From the 2012 US EPA greenhouse gas inventory: http://epa.gov/climatechange/emissions/downloads12/3.%20Energy.pdf
A52: CH4 emissions by source for Natural Gas Systems (Gg=Ktonne)
C53: 2006 | D53: EF
A54: Field production | C54: 5624 | D54: =C54/C62 -> 0.27956455
A55: Processing | C55: 704 | D55: =C55/C62 -> 0.034995278
A56: Transmission and storage | C56: 1949
A57: Distribution | C57: 1346
A58: Total | C58: 9499
A60: 2006 estimate of natural gas production from EIA: http://www.eia.gov/dnav/ng/ng_sum_lsum_dcu_nus_a.htm
A61: Dry production | C61: 18503605 | D61: million cubic feet
A62: Equivalent in PJ | C62: 20117 | D62: PJ
A65: Emissions from Domestic Natural Gas Production
B66: Gas extraction emission factors from GREET, developed 2/13/13
B68: Units: kT/PJ
C70: 2005 | D70: 2010 | E70: 2015 | F70: 2020-2055
B71: VOC | C71: 0.00084612 | D71: 0.00073165 | E71: 0.00069187 | F71: 0.00066926
B72: CO | C72: 0.00871699 | D72: 0.00482293 | E72: 0.00459133 | F72: 0.00442755
B73: Nox | C73: 0.0188133 | D73: 0.01509156 | E73: 0.01298537 | F73: 0.01214993
B74: PM10 | C74: 0.000418 | D74: 0.00035759 | E74: 0.00032223 | F74: 0.00029514
B75: PM25 | C75: 0.0003284 | D75: 0.00027727 | E75: 0.00024601 | F75: 0.00022244
B76: SO2 | C76: 0.00082742 | D76: 0.00054063 | E76: 0.00048401 | F76: 0.00048117
B77: CH4 | C77: 0.39119804 | D77: 0.39120454 | E77: 0.3911935 | F77: 0.39118678 | G77: * Values not used, updated values calculated below for weighting shale
B78: N2O | C78: 4.3049e-05 | D78: 4.3059e-05 | E78: 4.3051e-05 | F78: 4.3033e-05
B79: CO2 | C79: 1.9351723 | D79: 1.9422011 | E79: 1.9412332 | F79: 1.9404609 | G79: * Values not used, updated values calculated below for weighting shale
A82: Natural gas domestic production CO2 and CH4 update, these numbers will replace the GREET factors above. 4/11/13 pok.
A83: Carbon footprint from well to plant gate Table SI-5 of Weber and Clavin (2012) Environmental Science and Technology 46, 5688-5695.
A84: IPCC, 2007: GWP for CH4=25 | C84: Conventional | F84: Shale | I84: Shale with green completions
A85: g/MJ = kT/PJ | C85: CO2e | D85: CO2 | E85: CH4 | F85: CO2e | G85: CO2 | H85: CH4 | I85: CO2e | J85: CO2 | K85: CH4
A86: Preproduction | B86: well pad construction | C86: 0.16 | D86: =C86 -> 0.16 | F86: 0.16 | G86: =F86 -> 0.16 | I86: 0.16 | J86: =I86 -> 0.16
B87: well drilling | C87: 0.23 | D87: =C87 -> 0.23 | F87: 0.2 | G87: =F87 -> 0.2 | I87: 0.2 | J87: =I87 -> 0.2
B88: fracking water | F88: 0.26 | G88: =F88 -> 0.26 | I88: 0.26 | J88: =I88 -> 0.26
B89: fracking chemicals | F89: 0.07 | G89: =F89 -> 0.07 | I89: 0.07 | J89: =I89 -> 0.07
B90: well completion | C90: 0.18 | E90: =C90/25 -> 0.0072 | F90: 1.2 | H90: =F90/25 -> 0.048 | I90: 0.2 | K90: =I90/25 -> 0.008
B91: subtotal | C91: =SUM(C86:C90) -> 0.57 | D91: =SUM(D86:D90) -> 0.39 | E91: =SUM(E86:E90) -> 0.0072 | F91: =SUM(F86:F90) -> 1.89 | G91: =SUM(G86:G90) -> 0.69 | H91: =SUM(H86:H90) -> 0.048 | I91: =SUM(I86:I90) -> 0.89 | J91: =SUM(J86:J90) -> 0.69 | K91: =SUM(K86:K90) -> 0.008
A92: Production/processing | B92: flaring | C92: 0.6 | D92: =C92 -> 0.6 | F92: 0.6 | G92: =F92 -> 0.6 | I92: 0.6 | J92: =I92 -> 0.6
B93: lease/plant energy | C93: 3.2 | D93: =C93 -> 3.2 | F93: 3.2 | G93: =F93 -> 3.2 | I93: 3.2 | J93: =I93 -> 3.2
B94: vented CO2 at plant | C94: 1.2 | D94: =C94 -> 1.2 | F94: 1.2 | G94: =F94 -> 1.2 | I94: 1.2 | J94: =I94 -> 1.2
B95: fugitive at well | C95: 2.7 | E95: =C95/25 -> 0.108 | F95: 2.7 | H95: =F95/25 -> 0.108 | I95: 2.7 | K95: =I95/25 -> 0.108
B96: fugitive at plant | C96: 1.8 | E96: =C96/25 -> 0.072 | F96: 1.8 | H96: =F96/25 -> 0.072 | I96: 1.8 | K96: =I96/25 -> 0.072
B97: workovers | C97: 0 | F97: 1.2 | H97: =F97/25 -> 0.048 | I97: 0.2 | K97: =I97/25 -> 0.008
B98: liquids unloading | C98: 3.8 | E98: =C98/25 -> 0.152 | H98: =F98/25 -> 0 | K98: =I98/25 -> 0
B99: subtotal | C99: =SUM(C92:C98) -> 13.3 | D99: =SUM(D92:D98) -> 5 | E99: =SUM(E92:E98) -> 0.332 | F99: =SUM(F92:F98) -> 10.7 | G99: =SUM(G92:G98) -> 5 | H99: =SUM(H92:H98) -> 0.228 | I99: =SUM(I92:I98) -> 9.7 | J99: =SUM(J92:J98) -> 5 | K99: =SUM(K92:K98) -> 0.188
A100: Transmission | B100: compression fuel | C100: 0.4 | D100: =C100 -> 0.4 | F100: 0.4 | G100: =F100 -> 0.4 | I100: 0.4 | J100: =I100 -> 0.4
B101: fugitive transmission | C101: 1.9 | E101: =C101/25 -> 0.076 | F101: 1.9 | H101: =F101/25 -> 0.076 | I101: 1.9 | K101: =I101/25 -> 0.076
B102: subtotal | C102: =SUM(C100:C101) -> 2.3 | D102: =SUM(D100:D101) -> 0.4 | E102: =SUM(E100:E101) -> 0.076 | F102: =SUM(F100:F101) -> 2.3 | G102: =SUM(G100:G101) -> 0.4 | H102: =SUM(H100:H101) -> 0.076 | I102: =SUM(I100:I101) -> 2.3 | J102: =SUM(J100:J101) -> 0.4 | K102: =SUM(K100:K101) -> 0.076
B103: upstream subtotal | C103: =C91+C99+C102 -> 16.17 | D103: =D91+D99+D102 -> 5.79 | E103: =E91+E99+E102 -> 0.4152 | F103: =F91+F99+F102 -> 14.89 | G103: =G91+G99+G102 -> 6.09 | H103: =H91+H99+H102 -> 0.352 | I103: =I91+I99+I102 -> 12.89 | J103: =J91+J99+J102 -> 6.09 | K103: =K91+K99+K102 -> 0.272
B104: total except transmission | C104: =C91+C99 -> 13.87 | D104: =D91+D99 -> 5.39 | E104: =E91+E99 -> 0.3392 | F104: =F91+F99 -> 12.59 | G104: =G91+G99 -> 5.69 | H104: =H91+H99 -> 0.276 | I104: =I91+I99 -> 10.59 | J104: =J91+J99 -> 5.69 | K104: =K91+K99 -> 0.196 | L104: =K104/H104 -> 0.71014493 | M104: Effectiveness of greencompletions
B105: total transmission | C105: =C102 -> 2.3 | D105: =D102 -> 0.4 | E105: =E102 -> 0.076 | F105: =F102 -> 2.3 | G105: =G102 -> 0.4 | H105: =H102 -> 0.076 | I105: =I102 -> 2.3 | J105: =J102 -> 0.4 | K105: =K102 -> 0.076 | L105: =1+P126 -> 0.9388922 | M105: Assumed national average reduction in emissions due to green completions
F107: CO2, kT/PJ | I107: CH4, kT/PJ | L107: Bottom-up vs. top-down emission factors:
C108: 2005 | D108: 2010-2015 | E108: 2020-2055 | F108: 2005 | G108: 2010-2015 | H108: 2020-2055 | I108: 2005 | J108: 2010-2015 | K108: 2020-2055 | L108: TRUE | M108: Option "true" will use Weber and Clavin (2012) estimates with regional variation
B109: R2 | C109: 0 | D109: ='Conv vs Shale'!D3 -> 0.79621023 | E109: =D109 -> 0.79621023 | F109: =D$104*(1-$C109)+G$104*$C109 -> 5.39 | G109: =D$104*(1-$D109)+G$104*$D109 -> 5.6288631 | H109: =D$104*(1-$E109)+J$104*$E109 -> 5.6288631 | I109: =E$104*(1-$C109)+H$104*$C109 -> 0.3392 | J109: =IF($L$108=TRUE, E$104*(1-$D109)+H$104*$D109, IF($L$111="High", $D$133, IF($L$111="Avg", $E$133,$C$133))) -> 0.28887951 | K109: =IF($L$108=TRUE, $E$104*(1-$E109)+$K$104*$E109, IF($L$111="High", $D$133*$L$104, IF($L$111="Avg", $E$133*$L$104,$C$133*$L$104))) -> 0.2251827 | M109: Option "false" will use Caulton et al. (2014) estimates, same values for whole nation.
B110: R3 | C110: 0 | D110: ='Conv vs Shale'!D4 -> 0.49716094 | E110: =D110 -> 0.49716094 | F110: =D$104*(1-$C110)+G$104*$C110 -> 5.39 | G110: =D$104*(1-$D110)+G$104*$D110 -> 5.5391483 | H110: =D$104*(1-$E110)+J$104*$E110 -> 5.5391483 | I110: =E$104*(1-$C110)+H$104*$C110 -> 0.3392 | J110: =IF($L$108=TRUE, E$104*(1-$D110)+H$104*$D110, IF($L$111="High", $D$133, IF($L$111="Avg", $E$133,$C$133))) -> 0.30777943 | K110: =IF($L$108=TRUE, $E$104*(1-$E110)+$K$104*$E110, IF($L$111="High", $D$133*$L$104, IF($L$111="Avg", $E$133*$L$104,$C$133*$L$104))) -> 0.26800655 | L110: if top-down estimates selected, which value in the range? (High, Avg)
B111: R4 | C111: 0 | D111: ='Conv vs Shale'!D5 -> 0.23887945 | E111: =D111 -> 0.23887945 | F111: =D$104*(1-$C111)+G$104*$C111 -> 5.39 | G111: =D$104*(1-$D111)+G$104*$D111 -> 5.4616638 | H111: =D$104*(1-$E111)+J$104*$E111 -> 5.4616638 | I111: =E$104*(1-$C111)+H$104*$C111 -> 0.3392 | J111: =IF($L$108=TRUE, E$104*(1-$D111)+H$104*$D111, IF($L$111="High", $D$133, IF($L$111="Avg", $E$133,$C$133))) -> 0.32410282 | K111: =IF($L$108=TRUE, $E$104*(1-$E111)+$K$104*$E111, IF($L$111="High", $D$133*$L$104, IF($L$111="Avg", $E$133*$L$104,$C$133*$L$104))) -> 0.30499246 | L111: avg
B112: R5 | C112: 0 | D112: ='Conv vs Shale'!D6 -> 0.43655914 | E112: =D112 -> 0.43655914 | F112: =D$104*(1-$C112)+G$104*$C112 -> 5.39 | G112: =D$104*(1-$D112)+G$104*$D112 -> 5.5209677 | H112: =D$104*(1-$E112)+J$104*$E112 -> 5.5209677 | I112: =E$104*(1-$C112)+H$104*$C112 -> 0.3392 | J112: =IF($L$108=TRUE, E$104*(1-$D112)+H$104*$D112, IF($L$111="High", $D$133, IF($L$111="Avg", $E$133,$C$133))) -> 0.31160946 | K112: =IF($L$108=TRUE, $E$104*(1-$E112)+$K$104*$E112, IF($L$111="High", $D$133*$L$104, IF($L$111="Avg", $E$133*$L$104,$C$133*$L$104))) -> 0.27668473
B113: R6 | C113: 0 | D113: ='Conv vs Shale'!D7 -> 0 | E113: =D113 -> 0 | F113: =D$104*(1-$C113)+G$104*$C113 -> 5.39 | G113: =D$104*(1-$D113)+G$104*$D113 -> 5.39 | H113: =D$104*(1-$E113)+J$104*$E113 -> 5.39 | I113: =E$104*(1-$C113)+H$104*$C113 -> 0.3392 | J113: =IF($L$108=TRUE, E$104*(1-$D113)+H$104*$D113, IF($L$111="High", $D$133, IF($L$111="Avg", $E$133,$C$133))) -> 0.3392 | K113: =IF($L$108=TRUE, $E$104*(1-$E113)+$K$104*$E113, IF($L$111="High", $D$133*$L$104, IF($L$111="Avg", $E$133*$L$104,$C$133*$L$104))) -> 0.3392
B114: R7 | C114: 0 | D114: ='Conv vs Shale'!D8 -> 0.40893952 | E114: =D114 -> 0.40893952 | F114: =D$104*(1-$C114)+G$104*$C114 -> 5.39 | G114: =D$104*(1-$D114)+G$104*$D114 -> 5.5126819 | H114: =D$104*(1-$E114)+J$104*$E114 -> 5.5126819 | I114: =E$104*(1-$C114)+H$104*$C114 -> 0.3392 | J114: =IF($L$108=TRUE, E$104*(1-$D114)+H$104*$D114, IF($L$111="High", $D$133, IF($L$111="Avg", $E$133,$C$133))) -> 0.31335502 | K114: =IF($L$108=TRUE, $E$104*(1-$E114)+$K$104*$E114, IF($L$111="High", $D$133*$L$104, IF($L$111="Avg", $E$133*$L$104,$C$133*$L$104))) -> 0.28063986
B115: R8 | C115: 0 | D115: ='Conv vs Shale'!D9 -> 0.055082556 | E115: =D115 -> 0.055082556 | F115: =D$104*(1-$C115)+G$104*$C115 -> 5.39 | G115: =D$104*(1-$D115)+G$104*$D115 -> 5.4065248 | H115: =D$104*(1-$E115)+J$104*$E115 -> 5.4065248 | I115: =E$104*(1-$C115)+H$104*$C115 -> 0.3392 | J115: =IF($L$108=TRUE, E$104*(1-$D115)+H$104*$D115, IF($L$111="High", $D$133, IF($L$111="Avg", $E$133,$C$133))) -> 0.33571878 | K115: =IF($L$108=TRUE, $E$104*(1-$E115)+$K$104*$E115, IF($L$111="High", $D$133*$L$104, IF($L$111="Avg", $E$133*$L$104,$C$133*$L$104))) -> 0.33131218
B116: R9 | C116: 0 | D116: ='Conv vs Shale'!D10 -> 0.027399985 | E116: =D116 -> 0.027399985 | F116: =D$104*(1-$C116)+G$104*$C116 -> 5.39 | G116: =D$104*(1-$D116)+G$104*$D116 -> 5.39822 | H116: =D$104*(1-$E116)+J$104*$E116 -> 5.39822 | I116: =E$104*(1-$C116)+H$104*$C116 -> 0.3392 | J116: =IF($L$108=TRUE, E$104*(1-$D116)+H$104*$D116, IF($L$111="High", $D$133, IF($L$111="Avg", $E$133,$C$133))) -> 0.33746832 | K116: =IF($L$108=TRUE, $E$104*(1-$E116)+$K$104*$E116, IF($L$111="High", $D$133*$L$104, IF($L$111="Avg", $E$133*$L$104,$C$133*$L$104))) -> 0.33527632
A117: Assumptions: | N117: % change in emissions based on regional shale (based on calculation using Weber data) | O117: average % of regional NG production from reference run (2025-2050) | P117: emissions reduction in later years due to green completions
...

Sheet Conv vs Shale
A1: Regions | B1: Gross Withdrawals | C1: Shale Gas | D1: % Shale Gas in the Region in 2011
A2: 1 | B2: =SUMIFS($F$40:$F$93,$H$40:$H$93,$A$2:$A$10) -> 0 | C2: =SUMIFS($G$40:$G$93,$H$40:$H$93,$A$2:$A$10) -> 0 | D2: 0
A3: 2 | B3: =SUMIFS($F$40:$F$93,$H$40:$H$93,$A$2:$A$10) -> 1341716 | C3: =SUMIFS($G$40:$G$93,$H$40:$H$93,$A$2:$A$10) -> 1068288 | D3: =C3/B3 -> 0.79621023
A4: 3 | B4: =SUMIFS($F$40:$F$93,$H$40:$H$93,$A$2:$A$10) -> 233880 | C4: =SUMIFS($G$40:$G$93,$H$40:$H$93,$A$2:$A$10) -> 116276 | D4: =C4/B4 -> 0.49716094
A5: 4 | B5: =SUMIFS($F$40:$F$93,$H$40:$H$93,$A$2:$A$10) -> 481406 | C5: =SUMIFS($G$40:$G$93,$H$40:$H$93,$A$2:$A$10) -> 114998 | D5: =C5/B5 -> 0.23887945
A6: 5 | B6: =SUMIFS($F$40:$F$93,$H$40:$H$93,$A$2:$A$10) -> 562382 | C6: =SUMIFS($G$40:$G$93,$H$40:$H$93,$A$2:$A$10) -> 245513 | D6: =C6/B6 -> 0.43655914
A7: 6 | B7: =SUMIFS($F$40:$F$93,$H$40:$H$93,$A$2:$A$10) -> 572445 | C7: =SUMIFS($G$40:$G$93,$H$40:$H$93,$A$2:$A$10) -> 0 | D7: =C7/B7 -> 0
A8: 7 | B8: =SUMIFS($F$40:$F$93,$H$40:$H$93,$A$2:$A$10) -> 15990494 | C8: =SUMIFS($G$40:$G$93,$H$40:$H$93,$A$2:$A$10) -> 6539145 | D8: =C8/B8 -> 0.40893952
A9: 8 | B9: =SUMIFS($F$40:$F$93,$H$40:$H$93,$A$2:$A$10) -> 5853305 | C9: =SUMIFS($G$40:$G$93,$H$40:$H$93,$A$2:$A$10) -> 322415 | D9: =C9/B9 -> 0.055082556
A10: 9 | B10: =SUMIFS($F$40:$F$93,$H$40:$H$93,$A$2:$A$10) -> 3443396 | C10: =SUMIFS($G$40:$G$93,$H$40:$H$93,$A$2:$A$10) -> 94349 | D10: =C10/B10 -> 0.027399985
A12: References
A13: Natural Gas Gross Withdrawals
A15: Release Date: | B15: 1/7/2013
A16: Next Release Date: | B16: 1/31/2013
A18: Excel File Name: | B18: ng_prod_sum_a_epg0_fgw_mmcf_a.xls
A19: Available from Web Page: | B19: http://www.eia.gov/dnav/ng/ng_prod_sum_a_epg0_fgw_mmcf_a.htm
A20: Source: | B20: Energy Information Administration
A21: For Help, Contact: | B21: infoctr@eia.gov
B22: (202) 586-8800 | F22: 1/10/2013 5:08:26 PM
A24: Natural Gas Gross Withdrawals from Gas Wells
A26: Release Date: | B26: 1/7/2013
A27: Next Release Date: | B27: 1/31/2013
A29: Excel File Name: | B29: ng_prod_sum_a_epg0_fgg_mmcf_a.xls
A30: Available from Web Page: | B30: http://www.eia.gov/dnav/ng/ng_prod_sum_a_epg0_fgg_mmcf_a.htm
A31: Source: | B31: Energy Information Administration
A32: For Help, Contact: | B32: infoctr@eia.gov
B33: (202) 586-8800 | F33: 1/10/2013 5:08:22 PM
A35: Date | B35: 40724 | D35: =B35 -> 40724 | E35: State | F35: Gross Withdrawals | G35: Shale Gas | H35: Markal Region
A36: U.S. Natural Gas Gross Withdrawals (MMcf) | B36: 28479026 | C36: U.S. Natural Gas Gross Withdrawals from Shale Gas (Million Cubic Feet) | D36: 8500983
A37: U.S. Natural Gas Gross Withdrawals Offshore (MMcf) | B37: 2416644
A38: US--State Offshore Natural Gas Gross Withdrawals (MMcf) | B38: 549151
A39: US--Federal Offshore Natural Gas Gross Withdrawals (MMcf) | B39: 1867492 | C39: Federal Offshore--Gulf of Mexico Natural Gas Gross Withdrawals from Shale Gas (Million Cubic Feet) | D39: 0
A40: Alaska Natural Gas Gross Withdrawals (MMcf) | B40: 3162922 | E40: AK | F40: =B40 -> 3162922 | G40: 0 | H40: 9
A41: Alaska--onshore Natural Gas Gross Withdrawals (MMcf) | B41: 2798220
A42: Alaska Natural Gas Gross Withdrawals Total Offshore (MMcf) | B42: 364702
A43: Alaska--State Offshore Natural Gas Gross Withdrawals (MMcf) | B43: 364702
A44: Federal Offshore--Gulf of Mexico Natural Gas Gross Withdrawals (MMcf) | B44: 1830913 | E44: TX | F44: =B44 -> 1830913 | G44: 0 | H44: 7
A45: Federal Offshore--Alabama Natural Gas Gross Withdrawals (MMcf)
A46: Federal Offshore--Louisiana Natural Gas Gross Withdrawals (MMcf)
A47: Federal Offshore--Texas Natural Gas Gross Withdrawals (MMcf)
A48: Louisiana Natural Gas Gross Withdrawals (MMcf) | B48: 3040523 | C48: Louisiana Natural Gas Gross Withdrawals from Shale Gas (Million Cubic Feet) | D48: 2088306 | E48: LA | F48: =B48 -> 3040523 | G48: =D48 -> 2088306 | H48: 7
A49: Louisiana--onshore Natural Gas Gross Withdrawals (MMcf) | B49: 2969297 | C49: Louisiana--onshore Natural Gas Gross Withdrawals from Shale Gas (Million Cubic Feet) | D49: 2088306
A50: Louisiana Natural Gas Gross Withdrawals Total Offshore (MMcf) | B50: 71226
A51: Louisiana--State Offshore Natural Gas Gross Withdrawals (MMcf) | B51: 71226
A52: New Mexico Natural Gas Gross Withdrawals (MMcf) | B52: 1287682 | C52: New Mexico Natural Gas Gross Withdrawals from Shale Gas (Million Cubic Feet) | D52: 93071 | E52: NM | F52: =B52 -> 1287682 | G52: =D52 -> 93071 | H52: 8
A53: Oklahoma Natural Gas Gross Withdrawals (MMcf) | B53: 1888870 | C53: Oklahoma Natural Gas Gross Withdrawals from Shale Gas (Million Cubic Feet) | D53: 449167 | E53: OK | F53: =B53 -> 1888870 | G53: =D53 -> 449167 | H53: 7
A54: Texas Natural Gas Gross Withdrawals (MMcf) | B54: 7934689 | C54: Texas Natural Gas Gross Withdrawals from Shale Gas (Million Cubic Feet) | D54: 3066435 | E54: TX | F54: =B54 -> 7934689 | G54: =D54 -> 3066435 | H54: 7
A55: Texas--onshore Natural Gas Gross Withdrawals (MMcf) | B55: 7910898 | C55: Texas--onshore Natural Gas Gross Withdrawals from Shale Gas (Million Cubic Feet) | D55: 3066435
A56: Texas Natural Gas Gross Withdrawals Total Offshore (MMcf) | B56: 23791 | C56: Texas--State Offshore Natural Gas Withdrawals from Shale Gas (Million Cubic Feet) | D56: 0
A57: Texas--State Offshore Natural Gas Gross Withdrawals (MMcf) | B57: 23791
A58: Wyoming Natural Gas Gross Withdrawals (MMcf) | B58: 2375301 | C58: Wyoming Natural Gas Gross Withdrawals from Shale Gas (Million Cubic Feet) | D58: 4755 | E58: WY | F58: =B58 -> 2375301 | G58: =D58 -> 4755 | H58: 8
A59: Other States Natural Gas Gross Withdrawals (MMcf) | B59: 6958125 | C59: Other States Natural Gas Gross Withdrawals from Shale Gas (Million Cubic Feet) | D59: 2799249
A60: Alabama Natural Gas Gross Withdrawals (MMcf) | B60: 218574 | C60: Alabama Natural Gas Gross Withdrawals from Shale Gas (Million Cubic Feet) | D60: 0 | E60: AL | F60: =B60 -> 218574 | G60: =D60 -> 0 | H60: 7
A61: Alabama--onshore Natural Gas Gross Withdrawals (MMcf) | B61: 134305 | C61: Alabama--onshore Natural Gas Gross Withdrawals from Shale Gas (Million Cubic Feet) | D61: 0
A62: Alabama Natural Gas Gross Withdrawals Total Offshore (MMcf) | B62: 84270 | C62: Alabama--State Offshore Natural Gas Withdrawals from Shale Gas (Million Cubic Feet) | D62: 0
A63: Alabama--State Offshore Natural Gas Gross Withdrawals (MMcf) | B63: 84270
A64: Arizona Natural Gas Gross Withdrawals (MMcf) | B64: 168 | C64: Arizona Natural Gas Gross Withdrawals from Shale Gas (Million Cubic Feet) | D64: 0 | E64: AZ | F64: =B64 -> 168 | G64: =D64 -> 0 | H64: 7
A65: Arkansas Natural Gas Gross Withdrawals (MMcf) | B65: 1076757 | C65: Arkansas Natural Gas Gross Withdrawals from Shale Gas (Million Cubic Feet) | D65: 935237 | E65: AR | F65: =B65 -> 1076757 | G65: =D65 -> 935237 | H65: 7
A66: California Natural Gas Gross Withdrawals (MMcf) | B66: 279130 | C66: California Natural Gas Gross Withdrawals from Shale Gas (Million Cubic Feet) | D66: 94349 | E66: CA | F66: =B66 -> 279130 | G66: =D66 -> 94349 | H66: 9
A67: Calif--onshore Natural Gas Gross Withdrawals (MMcf) | B67: 237388 | C67: California--onshore Natural Gas Gross Withdrawals from Shale Gas (Million Cubic Feet) | D67: 94349
A68: California Natural Gas Gross Withdrawals Total Offshore (MMcf) | B68: 41742
A69: California--State Offshore Natural Gas Gross Withdrawals (MMcf) | B69: 5163
A70: Federal Offshore California Natural Gas Gross Withdrawals (MMcf) | B70: 36579
A71: Colorado Natural Gas Gross Withdrawals (MMcf) | B71: 1649306 | C71: Colorado Natural Gas Gross Withdrawals from Shale Gas (Million Cubic Feet) | D71: 211488 | E71: CO | F71: =B71 -> 1649306 | G71: =D71 -> 211488 | H71: 8
A72: Florida Natural Gas Gross Withdrawals (MMcf) | B72: 17129 | C72: Florida Natural Gas Gross Withdrawals from Shale Gas (Million Cubic Feet) | D72: 0 | E72: FL | F72: =B72 -> 17129 | G72: =D72 -> 0 | H72: 5
A73: Illinois Natural Gas Gross Withdrawals (MMcf) | B73: 2121 | C73: Illinois Natural Gas Gross Withdrawals from Shale Gas (Million Cubic Feet) | D73: 0 | E73: IL | F73: =B73 -> 2121 | G73: =D73 -> 0 | H73: 3
A74: Indiana Natural Gas Gross Withdrawals (MMcf) | B74: 9075 | C74: Indiana Natural Gas Gross Withdrawals from Shale Gas (Million Cubic Feet) | D74: 0 | E74: IN | F74: =B74 -> 9075 | G74: =D74 -> 0 | H74: 3
A75: Kansas Natural Gas Gross Withdrawals (MMcf) | B75: 309952 | C75: Kansas Natural Gas Gross Withdrawals from Shale Gas (Million Cubic Feet) | D75: 0 | E75: KS | F75: =B75 -> 309952 | G75: =D75 -> 0 | H75: 4
A76: Kentucky Natural Gas Gross Withdrawals (MMcf) | B76: 124243 | C76: Kentucky Natural Gas Gross Withdrawals from Shale Gas (Million Cubic Feet) | D76: 0 | E76: KY | F76: =B76 -> 124243 | G76: =D76 -> 0 | H76: 6
A77: Maryland Natural Gas Gross Withdrawals (MMcf) | B77: 34 | C77: Maryland Natural Gas Gross Withdrawals from Shale Gas (Million Cubic Feet) | D77: 0 | E77: MD | F77: =B77 -> 34 | G77: =D77 -> 0 | H77: 5
A78: Michigan Natural Gas Gross Withdrawals (MMcf) | B78: 143826 | C78: Michigan Natural Gas Gross Withdrawals from Shale Gas (Million Cubic Feet) | D78: 113736 | E78: MI | F78: =B78 -> 143826 | G78: =D78 -> 113736 | H78: 3
A79: Mississippi Natural Gas Gross Withdrawals (MMcf) | B79: 443351 | C79: Mississippi Natural Gas Gross Withdrawals from Shale Gas (Million Cubic Feet) | D79: 0 | E79: MS | F79: =B79 -> 443351 | G79: =D79 -> 0 | H79: 6
A80: Missouri Natural Gas Gross Withdrawals (MMcf) | B80: 0 | C80: Missouri Natural Gas Gross Withdrawals from Shale Gas (Million Cubic Feet) | D80: 0 | E80: MO | F80: =B80 -> 0 | G80: =D80 -> 0 | H80: 4
A81: Montana Natural Gas Gross Withdrawals (MMcf) | B81: 79506 | C81: Montana Natural Gas Gross Withdrawals from Shale Gas (Million Cubic Feet) | D81: 13101 | E81: MT | F81: =B81 -> 79506 | G81: =D81 -> 13101 | H81: 8
A82: Nebraska Natural Gas Gross Withdrawals (MMcf) | B82: 1980 | C82: Nebraska Natural Gas Gross Withdrawals from Shale Gas (Million Cubic Feet) | D82: 0 | E82: NE | F82: =B82 -> 1980 | G82: =D82 -> 0 | H82: 4
... A93: West Virginia Natural Gas Gross Withdrawals (MMcf) | B93: 394125 | C93: West Virginia Natural Gas Gross Withdrawals from Shale Gas (Million Cubic Feet) | D93: 227012 | E93: WV | F93: =B93 -> 394125 | G93: =D93 -> 227012 | H93: 5

Sheet Conv
B1: Conversion Factors
B4: From AEO2014 Appendix Table G
D5: MMBtu per cf | I5: MMBTU | J5: 1.055056e-06 | K5: PJ
B6: Natural gas | C6: Production | D6: 0.001022 | I6: Quad= | J6: 1055 | K6: PJ
C7: Imports | D7: 0.001025 | I7: kwh= | J7: 3412 | K7: BTU
B10: NIPA Table 1.1.9. Implicit Price Deflators for Gross Domestic Product
B11: [Index numbers, 2009=100]
B12: US Department of Commerce: Bureau of Economic Analysis
B13: http://www.bea.gov/national/nipaweb/SelectTable.asp?Selected=Y
B14: Downloaded on 1/09/2014 Last Revised 12/23/2013
B15: Year | C15: Deflator | D15: To bring to $2005
B16: 1983 | C16: 53.623 | D16: =$C$38/C16 -> 1.7155139
B17: 1984 | C17: 55.525 | D17: =$C$38/C17 -> 1.6567492
B18: 1985 | C18: 57.302 | D18: =$C$38/C18 -> 1.6053715
B19: 1986 | C19: 58.458 | D19: =$C$38/C19 -> 1.5736255
B20: 1987 | C20: 59.949 | D20: =$C$38/C20 -> 1.5344876
B21: 1988 | C21: 62.048 | D21: =$C$38/C21 -> 1.482578
B22: 1989 | C22: 64.46 | D22: =$C$38/C22 -> 1.4271021
B23: 1990 | C23: 66.845 | D23: =$C$38/C23 -> 1.3761837
B24: 1991 | C24: 69.069 | D24: =$C$38/C24 -> 1.331871
B25: 1992 | C25: 70.644 | D25: =$C$38/C25 -> 1.3021771
B26: 1993 | C26: 72.325 | D26: =$C$38/C26 -> 1.2719115
B27: 1994 | C27: 73.865 | D27: =$C$38/C27 -> 1.2453936
... B45: 2012 | C45: 105.002 | D45: =$C$38/C45 -> 0.87608807
