Workbook
Name AnswerData: #REF!
Name AnswerData: #REF!
Name AnswerData: #REF!
Name AnswerData: #REF!
Name AnswerData: #REF!
Name BDSEFF: [1]TechInfo!$J$33
Name BFBEFF: [1]TechInfo!$J$32
Name BFCEFF: [1]TechInfo!$J$34
Name blah: #REF!
Name bprint: #REF!
Name bprint: #REF!
Name bprint: #REF!
Name bprint: #REF!
Name BSGEFF: [1]TechInfo!$J$35
Name BSOEFF: [1]TechInfo!$J$31
Name BST_AF: [1]CHPData!$B$40
Name BST2_INV: [1]CHPData!$C$66
Name BST3_INV: [1]CHPData!$D$66
Name CCT_AF: [1]CHPData!$B$81
Name CCT2_INV: [1]CHPData!$C$91
Name CCT3_INV: [1]CHPData!$D$91
Name CCT4_INV: [1]CHPData!$E$91
Name CCT5_INV: [1]CHPData!$F$91
Name CFBEFF: [1]TechInfo!$J$29
Name CMM_SUPPLY_CRV_TABLE: [2]cum2025curves!#REF!
Name CMM_SUPPLY_CRV_TABLE: [2]cum2025curves!#REF!
Name CMM_SUPPLY_CRV_TABLE: [2]cum2025curves!#REF!
Name CMM_SUPPLY_CRV_TABLE: [2]cum2025curves!#REF!
Name cprint: #REF!
Name cprint: #REF!
Name cprint: #REF!
Name cprint: #REF!
Name CPVEFF: [1]TechInfo!$J$27
Name CSOEFF: [1]TechInfo!$J$28
Name DSTEFF: [1]TechInfo!$J$37
Name exch_rate: #REF!
Name exch_rate: #REF!
Name exch_rate: #REF!
Name exch_rate: #REF!
Name exch_rate: #REF!
Name FCL_AF: [1]CHPData!$B$154
Name FCL2_INV: [1]CHPData!$C$163
Name FCL3_INV: [1]CHPData!$D$163
Name fitfile: [3]MODEL!$D$38
Name INF: [3]MODEL!$H$14
Name million_short_tons_to_short_ton: [4]Steps!$Y$5
Name MMBTU_to_PJ: [4]Steps!$Y$6
Name MT2_INV: [1]CHPData!$C$141
Name MT3_INV: [1]CHPData!$D$141
Name neb: #REF!
Name PPP: [3]MODEL!$D$12
Name PPPEX: [3]MODEL!$D$13
Name rail_coal: #REF!
Name rail_coal: #REF!
Name rail_coal: #REF!
Name rail_coal: #REF!
Name rail_coal: #REF!
Name REG1_AF: [1]CHPData!$B$107
Name REG1_INV: [1]CHPData!$B$117
Name REG2_AF: [1]CHPData!$C$107

Sheet Fractions10
C1: Back to home page | J1: 29 | K1: 30 | L1: 31 | M1: 32 | N1: 33 | O1: 34 | P1: 35 | Q1: 36 | R1: 37 | S1: 40 | T1: 41 | U1: 42 | V1: 43 | W1: 44 | X1: 45 | Y1: 46 | Z1: 47 | AA1: 48 | BO1: R1 | BP1: R2 | BQ1: R3 | BR1: R4 | BS1: R5 | BT1: R6 | BU1: R7 | BV1: R8 | BW1: R9 | DG1: R1 | DH1: R2 | DI1: R3 | DJ1: R4 | DK1: R5 | DL1: R6 | DM1: R7 | DN1: R8 | DO1: R9
A3: This sheet contains the calculations and analysis needed for determining key fractions that will be used in order to help steer projections in the right direction. Fractions include end use shares for each sub-sector and region, output shares for each sub-sector, fuel, end-use and region, and regional breakdowns of demand.
A5: Table 90. 2010 Output for each technology | AW5: Table P65. 2010 Regional Output for each sub-sector and end use combination | BJ5: Table 91. 2010 End use fractions for each sub-sector | CH5: Table P66. Table 91 in pivot form | CS5: Table P67. 2010 Regional output for each sub-sector, fuel, and end-use combination | DE5: Table 92. 2010 Output shares relative to each sub-sector and end-use combination | DZ5: Table P68. Table 93 in pivot form | EK5: Table 93. Fuel Relaxation Percentages | EO5: Table 94. 2010 Regional breakdown of demand for each sub-sector | ET5: Table P69. Table 94 in pivot form | EW5: Table 95. 2010 demand adjustments | FI5: Table P70. Table 95 in pivot form
J6: Capacity (CHP - GW, Other - PJ/a) | S6: Availability Factor | AB6: Output | AL6: CHP Electricity Output | AX6: Values | BO6: Output (PJ/a) | BX6: Fraction | CI6: Values | CT6: Values | DG6: Output (PJ/a) | DP6: Output fraction relative to end-use | EA6: Values | FI6: Sum of Demand Adjustment | FJ6: Column Labels
A7: Sub-Sector | B7: End-Use | C7: AEO Fuel Type | D7: MARKAL Fuel Type | E7: Technology | F7: Constraint Identifier | G7: Sheet | H7: % Steam Output (CHP) | I7: % Electricity Output (CHP) | J7: R1 (Cap) | K7: R2 (Cap) | L7: R3 (Cap) | M7: R4 (Cap) | N7: R5 (Cap) | O7: R6 (Cap) | P7: R7 (Cap) | Q7: R8 (Cap) | R7: R9 (Cap) | S7: R1 (AF) | T7: R2 (AF) | U7: R3 (AF) | V7: R4 (AF) | W7: R5 (AF) | X7: R6 (AF) | Y7: R7 (AF) | Z7: R8 (AF) | AA7: R9 (AF) | AB7: R1 (Out) | AC7: R2 (Out) | AD7: R3 (Out) | AE7: R4 (Out) | AF7: R5 (Out) | AG7: R6 (Out) | AH7: R7 (Out) | AI7: R8 (Out) | AJ7: R9 (Out) | AK7: U.S. (Out) | AL7: R1 (ELC) | AM7: R2 (ELC) | AN7: R3 (ELC) | AO7: R4 (ELC) | AP7: R5 (ELC) | AQ7: R6 (ELC) | AR7: R7 (ELC) | AS7: R8 (ELC) | AT7: R9 (ELC) | AU7: U.S. (ELC) | AW7: Row Labels | AX7: Sum of R1 (Out) | AY7: Sum of R2 (Out) | AZ7: Sum of R3 (Out) | BA7: Sum of R4 (Out) | BB7: Sum of R5 (Out) | BC7: Sum of R6 (Out) | BD7: Sum of R7 (Out) | BE7: Sum of R8 (Out) | BF7: Sum of R9 (Out) | BG7: Sum of U.S. (Out) | BH7: Sum of U.S. (ELC) | BJ7: Sub-Sector | BK7: MARKAL Sub-Sector Identifier | BL7: End-Use | BM7: MARKAL End-Use Identifier | BN7: End-Use Commodity | BO7: R1 (Out) | BP7: R2 (Out) | BQ7: R3 (Out) | BR7: R4 (Out) | BS7: R5 (Out) | BT7: R6 (Out) | BU7: R7 (Out) | BV7: R8 (Out) | BW7: R9 (Out) | BX7: R1 (%) | BY7: R2 (%) | BZ7: R3 (%) | CA7: R4 (%) | CB7: R5 (%) | CC7: R6 (%) | CD7: R7 (%) | CE7: R8 (%) | CF7: R9 (%) | CH7: Row Labels | CI7: Sum of R1 (%) | CJ7: Sum of R2 (%) | CK7: Sum of R3 (%) | CL7: Sum of R4 (%) | CM7: Sum of R5 (%) | CN7: Sum of R6 (%) | CO7: Sum of R7 (%) | CP7: Sum of R8 (%) | CQ7: Sum of R9 (%) | CS7: Row Labels | CT7: Sum of R1 (Out) | CU7: Sum of R2 (Out) | CV7: Sum of R3 (Out) | CW7: Sum of R4 (Out) | CX7: Sum of R5 (Out) | CY7: Sum of R6 (Out) | CZ7: Sum of R7 (Out) | DA7: Sum of R8 (Out) | DB7: Sum of R9 (Out) | DC7: Sum of U.S. (Out) | DE7: Constraint identifier | DF7: Sub-sector and End Use Identifier | DG7: =DG1&" (Fuel)" -> R1 (Fuel) | DH7: =DH1&" (Fuel)" -> R2 (Fuel) | DI7: =DI1&" (Fuel)" -> R3 (Fuel) | DJ7: =DJ1&" (Fuel)" -> R4 (Fuel) | DK7: =DK1&" (Fuel)" -> R5 (Fuel) | DL7: =DL1&" (Fuel)" -> R6 (Fuel) | DM7: =DM1&" (Fuel)" -> R7 (Fuel) | DN7: =DN1&" (Fuel)" -> R8 (Fuel) | DO7: =DO1&" (Fuel)" -> R9 (Fuel) | DP7: =DG1&" (Frac)" -> R1 (Frac) | DQ7: =DH1&" (Frac)" -> R2 (Frac) | DR7: =DI1&" (Frac)" -> R3 (Frac) | DS7: =DJ1&" (Frac)" -> R4 (Frac) | DT7: =DK1&" (Frac)" -> R5 (Frac) | DU7: =DL1&" (Frac)" -> R6 (Frac) | DV7: =DM1&" (Frac)" -> R7 (Frac) | DW7: =DN1&" (Frac)" -> R8 (Frac) | DX7: =DO1&" (Frac)" -> R9 (Frac) | DZ7: Row Labels | EA7: Sum of R1 (Frac) | EB7: Sum of R2 (Frac) | EC7: Sum of R3 (Frac) | ED7: Sum of R4 (Frac) | EE7: Sum of R5 (Frac) | EF7: Sum of R6 (Frac) | EG7: Sum of R7 (Frac) | EH7: Sum of R8 (Frac) | EI7: Sum of R9 (Frac) | EK7: General Industry Category | EL7: Natural Gas | EM7: Coal | EO7: Sub-sector | EP7: Region | EQ7: Output (PJ/a) | ER7: Output (%) | ET7: Row Labels | EU7: Sum of Output (%) | EW7: Sub-sector | EX7: MARKAL Sub-Sector Identifier | EY7: Minimum End Use | EZ7: MARKAL End Use Identifier | FA7: End Use | FB7: Region | FC7: Original Demand | FD7: End Use Demand | FE7: End Use Fraction | FF7: End Use Adjustment | FG7: Demand Adjustment | FI7: Row Labels | FJ7: R1 | FK7: R2 | FL7: R3 | FM7: R4 | FN7: R5 | FO7: R6 | FP7: R7 | FQ7: R8 | FR7: R9 | FS7: Grand Total
A8: Agricultural Chemicals | B8: Facilities | C8: Distillate Oil | D8: Distillate Oil | E8: ICAEFACDST | F8: =EndUse(A8,B8,C8,G8) -> #NAME? | G8: TechData_OTR | H8: 1 | I8: 0 | J8: 0 | K8: 2.6967092 | S8: 1 | T8: 1 | U8: 1 | V8: 1 | W8: 1 | X8: 1 | Y8: 1 | Z8: 1 | AA8: 1 | AB8: =J8*$H8*S8 -> 0 | AC8: =K8*$H8*T8 -> 2.6967092 | AD8: =L8*$H8*U8 -> 0 | AE8: =M8*$H8*V8 -> 0 | AF8: =N8*$H8*W8 -> 0 | AG8: =O8*$H8*X8 -> 0 | AH8: =P8*$H8*Y8 -> 0 | AI8: =Q8*$H8*Z8 -> 0 | AJ8: =R8*$H8*AA8 -> 0 | AK8: =SUM(AB8:AJ8) -> 2.6967092 | AL8: 0 | AM8: 0 | AN8: 0 | AO8: 0 | AP8: 0 | AQ8: 0 | AR8: 0 | AS8: 0 | AT8: 0 | AU8: 0 | AW8: Agricultural Chemicals | AX8: 0 | AY8: 0 | AZ8: 45.432757 | BA8: 39.801248 | BB8: 61.795009 | BC8: 59.992423 | BD8: 194.70981 | BE8: 4.2262309 | BF8: 1.8615012 | BG8: 407.81898 | BH8: 1.823728 | BJ8: Agricultural Chemicals | BK8: ICA | BL8: Electrochemical | BM8: ETC | BN8: =BK8&BM8 -> ICAETC | BO8: =IF(ISERROR(GETPIVOTDATA("Sum of "&BO$1&" (Out)",$AW$6,"Sub-Sector",$BJ8,"End-Use",$BL8)),0,GETPIVOTDATA("Sum of "&BO$1&" (Out)",$AW$6,"Sub-Sector",$BJ8,"End-Use",$BL8)) -> 0 | BP8: =IF(ISERROR(GETPIVOTDATA("Sum of "&BP$1&" (Out)",$AW$6,"Sub-Sector",$BJ8,"End-Use",$BL8)),0,GETPIVOTDATA("Sum of "&BP$1&" (Out)",$AW$6,"Sub-Sector",$BJ8,"End-Use",$BL8)) -> 0 | BQ8: =IF(ISERROR(GETPIVOTDATA("Sum of "&BQ$1&" (Out)",$AW$6,"Sub-Sector",$BJ8,"End-Use",$BL8)),0,GETPIVOTDATA("Sum of "&BQ$1&" (Out)",$AW$6,"Sub-Sector",$BJ8,"End-Use",$BL8)) -> 0 | BR8: =IF(ISERROR(GETPIVOTDATA("Sum of "&BR$1&" (Out)",$AW$6,"Sub-Sector",$BJ8,"End-Use",$BL8)),0,GETPIVOTDATA("Sum of "&BR$1&" (Out)",$AW$6,"Sub-Sector",$BJ8,"End-Use",$BL8)) -> 0 | BS8: =IF(ISERROR(GETPIVOTDATA("Sum of "&BS$1&" (Out)",$AW$6,"Sub-Sector",$BJ8,"End-Use",$BL8)),0,GETPIVOTDATA("Sum of "&BS$1&" (Out)",$AW$6,"Sub-Sector",$BJ8,"End-Use",$BL8)) -> 0 | BT8: =IF(ISERROR(GETPIVOTDATA("Sum of "&BT$1&" (Out)",$AW$6,"Sub-Sector",$BJ8,"End-Use",$BL8)),0,GETPIVOTDATA("Sum of "&BT$1&" (Out)",$AW$6,"Sub-Sector",$BJ8,"End-Use",$BL8)) -> 0 | BU8: =IF(ISERROR(GETPIVOTDATA("Sum of "&BU$1&" (Out)",$AW$6,"Sub-Sector",$BJ8,"End-Use",$BL8)),0,GETPIVOTDATA("Sum of "&BU$1&" (Out)",$AW$6,"Sub-Sector",$BJ8,"End-Use",$BL8)) -> 0 | BV8: =IF(ISERROR(GETPIVOTDATA("Sum of "&BV$1&" (Out)",$AW$6,"Sub-Sector",$BJ8,"End-Use",$BL8)),0,GETPIVOTDATA("Sum of "&BV$1&" (Out)",$AW$6,"Sub-Sector",$BJ8,"End-Use",$BL8)) -> 0 | BW8: =IF(ISERROR(GETPIVOTDATA("Sum of "&BW$1&" (Out)",$AW$6,"Sub-Sector",$BJ8,"End-Use",$BL8)),0,GETPIVOTDATA("Sum of "&BW$1&" (Out)",$AW$6,"Sub-Sector",$BJ8,"End-Use",$BL8)) -> 0 | BX8: 0 | BY8: 0 | BZ8: =BQ8/BQ15 -> 0 | CA8: =BR8/BR15 -> 0 | CB8: =BS8/BS15 -> 0 | CC8: =BT8/BT15 -> 0 | CD8: =BU8/BU15 -> 0 | CE8: =BV8/BV15 -> 0 | CF8: =BW8/BW15 -> 0 | CH8: ICAETC | CI8: 0 | CJ8: 0 | CK8: 0 | CL8: 0 | CM8: 0 | CN8: 0 | CO8: 0 | CP8: 0 | CQ8: 0 | CS8: ICAFA_DST | CT8: 0 | CU8: 0 | CV8: 0 | CW8: 0 | CX8: 2.6967092 | CY8: 2.3505749 | CZ8: 8.1659027 | DA8: 0 | DB8: 0 | DC8: 13.213187 | DE8: ICAOH_OTP | DF8: =LEFT(DE8,5) -> ICAOH | DG8: =GETPIVOTDATA("Sum of "&DG$1&" (Out)",$CS$6,"Constraint Identifier",$DE8) -> 0 | DH8: =GETPIVOTDATA("Sum of "&DH$1&" (Out)",$CS$6,"Constraint Identifier",$DE8) -> 0 | DI8: =GETPIVOTDATA("Sum of "&DI$1&" (Out)",$CS$6,"Constraint Identifier",$DE8) -> 0.36588093 | DJ8: =GETPIVOTDATA("Sum of "&DJ$1&" (Out)",$CS$6,"Constraint Identifier",$DE8) -> 0.24781986 | DK8: =GETPIVOTDATA("Sum of "&DK$1&" (Out)",$CS$6,"Constraint Identifier",$DE8) -> 0 | DL8: =GETPIVOTDATA("Sum of "&DL$1&" (Out)",$CS$6,"Constraint Identifier",$DE8) -> 0 | DM8: =GETPIVOTDATA("Sum of "&DM$1&" (Out)",$CS$6,"Constraint Identifier",$DE8) -> 0 | DN8: =GETPIVOTDATA("Sum of "&DN$1&" (Out)",$CS$6,"Constraint Identifier",$DE8) -> 0 | DO8: =GETPIVOTDATA("Sum of "&DO$1&" (Out)",$CS$6,"Constraint Identifier",$DE8) -> 0 | DP8: =IF(SUMIF($DF$8:$DF$380,"="&$DF8,DG$8:DG$380)=0,0,DG8/SUMIF($DF$8:$DF$380,"="&$DF8,DG$8:DG$380)) -> 0 | DQ8: =IF(SUMIF($DF$8:$DF$380,"="&$DF8,DH$8:DH$380)=0,0,DH8/SUMIF($DF$8:$DF$380,"="&$DF8,DH$8:DH$380)) -> 0 | DR8: =IF(SUMIF($DF$8:$DF$380,"="&$DF8,DI$8:DI$380)=0,0,DI8/SUMIF($DF$8:$DF$380,"="&$DF8,DI$8:DI$380)) -> 1 | DS8: =IF(SUMIF($DF$8:$DF$380,"="&$DF8,DJ$8:DJ$380)=0,0,DJ8/SUMIF($DF$8:$DF$380,"="&$DF8,DJ$8:DJ$380)) -> 1 | DT8: =IF(SUMIF($DF$8:$DF$380,"="&$DF8,DK$8:DK$380)=0,0,DK8/SUMIF($DF$8:$DF$380,"="&$DF8,DK$8:DK$380)) -> 0 | DU8: =IF(SUMIF($DF$8:$DF$380,"="&$DF8,DL$8:DL$380)=0,0,DL8/SUMIF($DF$8:$DF$380,"="&$DF8,DL$8:DL$380)) -> 0 | DV8: =IF(SUMIF($DF$8:$DF$380,"="&$DF8,DM$8:DM$380)=0,0,DM8/SUMIF($DF$8:$DF$380,"="&$DF8,DM$8:DM$380)) -> 0 | DW8: =IF(SUMIF($DF$8:$DF$380,"="&$DF8,DN$8:DN$380)=0,0,DN8/SUMIF($DF$8:$DF$380,"="&$DF8,DN$8:DN$380)) -> 0 | DX8: =IF(SUMIF($DF$8:$DF$380,"="&$DF8,DO$8:DO$380)=0,0,DO8/SUMIF($DF$8:$DF$380,"="&$DF8,DO$8:DO$380)) -> 0 | DZ8: ICAFA_DST | EA8: 0 | EB8: 0 | EC8: 0 | ED8: 0 | EE8: 0.90292324 | EF8: 0.90292324 | EG8: 0.90292324 | EH8: 0 | EI8: 0 | EK8: Feedstocks | EL8: 0.9 | EO8: Agricultural Chemicals | EP8: R1 | EQ8: =GETPIVOTDATA("Sum of "&EP8&" (Out)",$AW$6,"Sub-Sector",EO8) -> 0 | ER8: =EQ8/SUM(EQ8:EQ16) -> 0 | ET8: Agricultural Chemicals | EU8: 1 | EW8: Agricultural Chemicals | EX8: ICA | EY8: Facilities | EZ8: FAC | FA8: =EX8&EZ8 -> ICAFAC | FB8: R3 | FC8: =GETPIVOTDATA("Sum of "&FB8&" (Out)",$AW$6,"Sub-Sector",EW8) -> 45.432757 | FD8: =GETPIVOTDATA("Sum of "&FB8&" (Out)",$AW$6,"Sub-Sector",EW8,"End-Use",EY8) -> 0.28316891 | FE8: =GETPIVOTDATA("Sum of "&FB8&" (%)",$CH$6,"End-Use Commodity",FA8) -> 0.0062327035 | FF8: 0 | FG8: =FC8-((FD8-FF8)/FE8) -> 0 | FI8: ICA | FL8: 0 | FM8: 0 | FN8: 0 | FO8: 0 | FP8: 0.43059052 | FQ8: 0 | FR8: 0 | FS8: 0.43059052
A9: Agricultural Chemicals | B9: Facilities | C9: Electricity | D9: Electricity | E9: ICAEFACELC | F9: =EndUse(A9,B9,C9,G9) -> #NAME? | G9: TechData_OTR | H9: 1 | I9: 0 | J9: 0.12902151 | K9: 0.16302314 | S9: 1 | T9: 1 | U9: 1 | V9: 1 | W9: 1 | X9: 1 | Y9: 1 | Z9: 1 | AA9: 1 | AB9: =J9*$H9*S9 -> 0.12902151 | AC9: =K9*$H9*T9 -> 0.16302314 | AD9: =L9*$H9*U9 -> 0 | AE9: =M9*$H9*V9 -> 0 | AF9: =N9*$H9*W9 -> 0 | AG9: =O9*$H9*X9 -> 0 | AH9: =P9*$H9*Y9 -> 0 | AI9: =Q9*$H9*Z9 -> 0 | AJ9: =R9*$H9*AA9 -> 0 | AK9: =SUM(AB9:AJ9) -> 0.29204465 | AL9: 0 | AM9: 0 | AN9: 0 | AO9: 0 | AP9: 0 | AQ9: 0 | AR9: 0 | AS9: 0 | AT9: 0 | AU9: 0 | AW9: Facilities | AX9: 0 | AY9: 0 | AZ9: 0.28316891 | BA9: 0.19179703 | BB9: 2.9866428 | BC9: 2.6032943 | BD9: 9.0438504 | BE9: 0.10910629 | BF9: 0.06841461 | BG9: 15.286274 | BH9: 0 | BJ9: Agricultural Chemicals | BK9: ICA | BL9: Facilities | BM9: FAC | BN9: =BK9&BM9 -> ICAFAC | BO9: =IF(ISERROR(GETPIVOTDATA("Sum of "&BO$1&" (Out)",$AW$6,"Sub-Sector",$BJ9,"End-Use",$BL9)),0,GETPIVOTDATA("Sum of "&BO$1&" (Out)",$AW$6,"Sub-Sector",$BJ9,"End-Use",$BL9)) -> 0 | BP9: =IF(ISERROR(GETPIVOTDATA("Sum of "&BP$1&" (Out)",$AW$6,"Sub-Sector",$BJ9,"End-Use",$BL9)),0,GETPIVOTDATA("Sum of "&BP$1&" (Out)",$AW$6,"Sub-Sector",$BJ9,"End-Use",$BL9)) -> 0 | BQ9: =IF(ISERROR(GETPIVOTDATA("Sum of "&BQ$1&" (Out)",$AW$6,"Sub-Sector",$BJ9,"End-Use",$BL9)),0,GETPIVOTDATA("Sum of "&BQ$1&" (Out)",$AW$6,"Sub-Sector",$BJ9,"End-Use",$BL9)) -> 0.28316891 | BR9: =IF(ISERROR(GETPIVOTDATA("Sum of "&BR$1&" (Out)",$AW$6,"Sub-Sector",$BJ9,"End-Use",$BL9)),0,GETPIVOTDATA("Sum of "&BR$1&" (Out)",$AW$6,"Sub-Sector",$BJ9,"End-Use",$BL9)) -> 0.19179703 | BS9: =IF(ISERROR(GETPIVOTDATA("Sum of "&BS$1&" (Out)",$AW$6,"Sub-Sector",$BJ9,"End-Use",$BL9)),0,GETPIVOTDATA("Sum of "&BS$1&" (Out)",$AW$6,"Sub-Sector",$BJ9,"End-Use",$BL9)) -> 2.9866428 | BT9: =IF(ISERROR(GETPIVOTDATA("Sum of "&BT$1&" (Out)",$AW$6,"Sub-Sector",$BJ9,"End-Use",$BL9)),0,GETPIVOTDATA("Sum of "&BT$1&" (Out)",$AW$6,"Sub-Sector",$BJ9,"End-Use",$BL9)) -> 2.6032943 | BU9: =IF(ISERROR(GETPIVOTDATA("Sum of "&BU$1&" (Out)",$AW$6,"Sub-Sector",$BJ9,"End-Use",$BL9)),0,GETPIVOTDATA("Sum of "&BU$1&" (Out)",$AW$6,"Sub-Sector",$BJ9,"End-Use",$BL9)) -> 9.0438504 | BV9: =IF(ISERROR(GETPIVOTDATA("Sum of "&BV$1&" (Out)",$AW$6,"Sub-Sector",$BJ9,"End-Use",$BL9)),0,GETPIVOTDATA("Sum of "&BV$1&" (Out)",$AW$6,"Sub-Sector",$BJ9,"End-Use",$BL9)) -> 0.10910629 | BW9: =IF(ISERROR(GETPIVOTDATA("Sum of "&BW$1&" (Out)",$AW$6,"Sub-Sector",$BJ9,"End-Use",$BL9)),0,GETPIVOTDATA("Sum of "&BW$1&" (Out)",$AW$6,"Sub-Sector",$BJ9,"End-Use",$BL9)) -> 0.06841461 | BX9: 0 | BY9: 0 | BZ9: =BQ9/BQ15 -> 0.0062327035 | CA9: =BR9/BR15 -> 0.0048188698 | CB9: =BS9/BS15 -> 0.048331457 | CC9: =BT9/BT15 -> 0.043393717 | CD9: =BU9/BU15 -> 0.046447841 | CE9: =BV9/BV15 -> 0.025816452 | CF9: =BW9/BW15 -> 0.036752386 | CH9: ICAFAC | CI9: 0 | CJ9: 0 | CK9: 0.0062327035 | CL9: 0.0048188698 | CM9: 0.048331457 | CN9: 0.043393717 | CO9: 0.046447841 | CP9: 0.025816452 | CQ9: 0.036752386 | CS9: ICAFA_ELC | CT9: 0 | CU9: 0 | CV9: 0.1904872 | CW9: 0.12902151 | CX9: 0.16302314 | CY9: 0.14209841 | CZ9: 0.49365022 | DA9: 0.098186775 | DB9: 0.06156758 | DC9: 1.2780348 | DE9: INCOH_OTP | DF9: =LEFT(DE9,5) -> INCOH | DG9: =GETPIVOTDATA("Sum of "&DG$1&" (Out)",$CS$6,"Constraint Identifier",$DE9) -> 0.16085723 | DH9: =GETPIVOTDATA("Sum of "&DH$1&" (Out)",$CS$6,"Constraint Identifier",$DE9) -> 0.44278584 | DI9: =GETPIVOTDATA("Sum of "&DI$1&" (Out)",$CS$6,"Constraint Identifier",$DE9) -> 2.1593079 | DJ9: =GETPIVOTDATA("Sum of "&DJ$1&" (Out)",$CS$6,"Constraint Identifier",$DE9) -> 1.4625506 | DK9: =GETPIVOTDATA("Sum of "&DK$1&" (Out)",$CS$6,"Constraint Identifier",$DE9) -> 0.44351597 | DL9: =GETPIVOTDATA("Sum of "&DL$1&" (Out)",$CS$6,"Constraint Identifier",$DE9) -> 0.38658877 | DM9: =GETPIVOTDATA("Sum of "&DM$1&" (Out)",$CS$6,"Constraint Identifier",$DE9) -> 1.3430103 | DN9: =GETPIVOTDATA("Sum of "&DN$1&" (Out)",$CS$6,"Constraint Identifier",$DE9) -> 0.44520677 | DO9: =GETPIVOTDATA("Sum of "&DO$1&" (Out)",$CS$6,"Constraint Identifier",$DE9) -> 0.27916492 | DP9: =IF(SUMIF($DF$8:$DF$380,"="&$DF9,DG$8:DG$380)=0,0,DG9/SUMIF($DF$8:$DF$380,"="&$DF9,DG$8:DG$380)) -> 1 | DQ9: =IF(SUMIF($DF$8:$DF$380,"="&$DF9,DH$8:DH$380)=0,0,DH9/SUMIF($DF$8:$DF$380,"="&$DF9,DH$8:DH$380)) -> 0.077581754 | DR9: =IF(SUMIF($DF$8:$DF$380,"="&$DF9,DI$8:DI$380)=0,0,DI9/SUMIF($DF$8:$DF$380,"="&$DF9,DI$8:DI$380)) -> 0.10286678 | DS9: =IF(SUMIF($DF$8:$DF$380,"="&$DF9,DJ$8:DJ$380)=0,0,DJ9/SUMIF($DF$8:$DF$380,"="&$DF9,DJ$8:DJ$380)) -> 0.10286678 | DT9: =IF(SUMIF($DF$8:$DF$380,"="&$DF9,DK$8:DK$380)=0,0,DK9/SUMIF($DF$8:$DF$380,"="&$DF9,DK$8:DK$380)) -> 0.10286678 | DU9: =IF(SUMIF($DF$8:$DF$380,"="&$DF9,DL$8:DL$380)=0,0,DL9/SUMIF($DF$8:$DF$380,"="&$DF9,DL$8:DL$380)) -> 0.10286678 | DV9: =IF(SUMIF($DF$8:$DF$380,"="&$DF9,DM$8:DM$380)=0,0,DM9/SUMIF($DF$8:$DF$380,"="&$DF9,DM$8:DM$380)) -> 0.10286678 | DW9: =IF(SUMIF($DF$8:$DF$380,"="&$DF9,DN$8:DN$380)=0,0,DN9/SUMIF($DF$8:$DF$380,"="&$DF9,DN$8:DN$380)) -> 0.10286678 | DX9: =IF(SUMIF($DF$8:$DF$380,"="&$DF9,DO$8:DO$380)=0,0,DO9/SUMIF($DF$8:$DF$380,"="&$DF9,DO$8:DO$380)) -> 0.10286678 | DZ9: ICAFA_ELC | EA9: 0 | EB9: 0 | EC9: 0.67269815 | ED9: 0.67269815 | EE9: 0.054584076 | EF9: 0.054584076 | EG9: 0.054584076 | EH9: 0.89991859 | EI9: 0.89991859 | EK9: Food | EL9: 28 | EM9: 20 | EO9: Agricultural Chemicals | EP9: R2 | EQ9: =GETPIVOTDATA("Sum of "&EP9&" (Out)",$AW$6,"Sub-Sector",EO9) -> 0 | ER9: =EQ9/SUM(EQ8:EQ16) -> 0 | ET9: R1 | EU9: 0 | EW9: Agricultural Chemicals | EX9: ICA | EY9: Facilities | EZ9: FAC | FA9: =EX9&EZ9 -> ICAFAC | FB9: R4 | FC9: =GETPIVOTDATA("Sum of "&FB9&" (Out)",$AW$6,"Sub-Sector",EW9) -> 39.801248 | FD9: =GETPIVOTDATA("Sum of "&FB9&" (Out)",$AW$6,"Sub-Sector",EW9,"End-Use",EY9) -> 0.19179703 | FE9: =GETPIVOTDATA("Sum of "&FB9&" (%)",$CH$6,"End-Use Commodity",FA9) -> 0.0048188698 | FF9: 0 | FG9: =FC9-((FD9-FF9)/FE9) -> 0 | FI9: ICI | FJ9: 0 | FK9: 0 | FL9: 0 | FM9: 0 | FN9: 0.064592122 | FO9: 0.6505523 | FP9: 0.062730209 | FQ9: 0.079818174 | FR9: 0.077045684 | FS9: 0.93473849
A10: Agricultural Chemicals | B10: Facilities | C10: Natural Gas | D10: Natural Gas | E10: ICAEFACNGA | F10: =EndUse(A10,B10,C10,G10) -> #NAME? | G10: TechData_OTR | H10: 1 | I10: 0 | J10: 0.062775525 | K10: 0.12691048 | S10: 1 | T10: 1 | U10: 1 | V10: 1 | W10: 1 | X10: 1 | Y10: 1 | Z10: 1 | AA10: 1 | AB10: =J10*$H10*S10 -> 0.062775525 | AC10: =K10*$H10*T10 -> 0.12691048 | AD10: =L10*$H10*U10 -> 0 | AE10: =M10*$H10*V10 -> 0 | AF10: =N10*$H10*W10 -> 0 | AG10: =O10*$H10*X10 -> 0 | AH10: =P10*$H10*Y10 -> 0 | AI10: =Q10*$H10*Z10 -> 0 | AJ10: =R10*$H10*AA10 -> 0 | AK10: =SUM(AB10:AJ10) -> 0.189686 | AL10: 0 | AM10: 0 | AN10: 0 | AO10: 0 | AP10: 0 | AQ10: 0 | AR10: 0 | AS10: 0 | AT10: 0 | AU10: 0 | AW10: Feedstock | AX10: 0 | AY10: 0 | AZ10: 29.234538 | BA10: 19.801248 | BB10: 39.003975 | BC10: 33.997645 | BD10: 118.1079 | BE10: 0 | BF10: 0 | BG10: 240.14531 | BH10: 0 | BJ10: Agricultural Chemicals | BK10: ICA | BL10: Feedstock | BM10: FEED | BN10: =BK10&BM10 -> ICAFEED | BO10: =IF(ISERROR(GETPIVOTDATA("Sum of "&BO$1&" (Out)",$AW$6,"Sub-Sector",$BJ10,"End-Use",$BL10)),0,GETPIVOTDATA("Sum of "&BO$1&" (Out)",$AW$6,"Sub-Sector",$BJ10,"End-Use",$BL10)) -> 0 | BP10: =IF(ISERROR(GETPIVOTDATA("Sum of "&BP$1&" (Out)",$AW$6,"Sub-Sector",$BJ10,"End-Use",$BL10)),0,GETPIVOTDATA("Sum of "&BP$1&" (Out)",$AW$6,"Sub-Sector",$BJ10,"End-Use",$BL10)) -> 0 | BQ10: =IF(ISERROR(GETPIVOTDATA("Sum of "&BQ$1&" (Out)",$AW$6,"Sub-Sector",$BJ10,"End-Use",$BL10)),0,GETPIVOTDATA("Sum of "&BQ$1&" (Out)",$AW$6,"Sub-Sector",$BJ10,"End-Use",$BL10)) -> 29.234538 | BR10: =IF(ISERROR(GETPIVOTDATA("Sum of "&BR$1&" (Out)",$AW$6,"Sub-Sector",$BJ10,"End-Use",$BL10)),0,GETPIVOTDATA("Sum of "&BR$1&" (Out)",$AW$6,"Sub-Sector",$BJ10,"End-Use",$BL10)) -> 19.801248 | BS10: =IF(ISERROR(GETPIVOTDATA("Sum of "&BS$1&" (Out)",$AW$6,"Sub-Sector",$BJ10,"End-Use",$BL10)),0,GETPIVOTDATA("Sum of "&BS$1&" (Out)",$AW$6,"Sub-Sector",$BJ10,"End-Use",$BL10)) -> 39.003975 | BT10: =IF(ISERROR(GETPIVOTDATA("Sum of "&BT$1&" (Out)",$AW$6,"Sub-Sector",$BJ10,"End-Use",$BL10)),0,GETPIVOTDATA("Sum of "&BT$1&" (Out)",$AW$6,"Sub-Sector",$BJ10,"End-Use",$BL10)) -> 33.997645 | BU10: =IF(ISERROR(GETPIVOTDATA("Sum of "&BU$1&" (Out)",$AW$6,"Sub-Sector",$BJ10,"End-Use",$BL10)),0,GETPIVOTDATA("Sum of "&BU$1&" (Out)",$AW$6,"Sub-Sector",$BJ10,"End-Use",$BL10)) -> 118.1079 | BV10: =IF(ISERROR(GETPIVOTDATA("Sum of "&BV$1&" (Out)",$AW$6,"Sub-Sector",$BJ10,"End-Use",$BL10)),0,GETPIVOTDATA("Sum of "&BV$1&" (Out)",$AW$6,"Sub-Sector",$BJ10,"End-Use",$BL10)) -> 0 | BW10: =IF(ISERROR(GETPIVOTDATA("Sum of "&BW$1&" (Out)",$AW$6,"Sub-Sector",$BJ10,"End-Use",$BL10)),0,GETPIVOTDATA("Sum of "&BW$1&" (Out)",$AW$6,"Sub-Sector",$BJ10,"End-Use",$BL10)) -> 0 | BX10: 0 | BY10: 0 | BZ10: =BQ10/BQ15 -> 0.64346828 | CA10: =BR10/BR15 -> 0.49750319 | CB10: =BS10/BS15 -> 0.63118325 | CC10: =BT10/BT15 -> 0.56669899 | CD10: =BU10/BU15 -> 0.60658422 | CE10: =BV10/BV15 -> 0 | CF10: =BW10/BW15 -> 0 | CH10: ICAFEED | CI10: 0 | CJ10: 0 | CK10: 0.64346828 | CL10: 0.49750319 | CM10: 0.63118325 | CN10: 0.56669899 | CO10: 0.60658422 | CP10: 0 | CQ10: 0 | CS10: ICAFA_NGA | CT10: 0 | CU10: 0 | CV10: 0.092681708 | CW10: 0.062775525 | CX10: 0.12691048 | CY10: 0.11062096 | CZ10: 0.38429749 | DA10: 0.010919511 | DB10: 0.0068470304 | DC10: 0.79505271 | DE10: INCOH_PTC | DF10: =LEFT(DE10,5) -> INCOH | DG10: =GETPIVOTDATA("Sum of "&DG$1&" (Out)",$CS$6,"Constraint Identifier",$DE10) -> 0 | DH10: =GETPIVOTDATA("Sum of "&DH$1&" (Out)",$CS$6,"Constraint Identifier",$DE10) -> 5.2645593 | DI10: =GETPIVOTDATA("Sum of "&DI$1&" (Out)",$CS$6,"Constraint Identifier",$DE10) -> 18.831997 | DJ10: =GETPIVOTDATA("Sum of "&DJ$1&" (Out)",$CS$6,"Constraint Identifier",$DE10) -> 12.755359 | DK10: =GETPIVOTDATA("Sum of "&DK$1&" (Out)",$CS$6,"Constraint Identifier",$DE10) -> 3.868041 | DL10: =GETPIVOTDATA("Sum of "&DL$1&" (Out)",$CS$6,"Constraint Identifier",$DE10) -> 3.3715611 | DM10: =GETPIVOTDATA("Sum of "&DM$1&" (Out)",$CS$6,"Constraint Identifier",$DE10) -> 11.712811 | DN10: =GETPIVOTDATA("Sum of "&DN$1&" (Out)",$CS$6,"Constraint Identifier",$DE10) -> 3.8827869 | DO10: =GETPIVOTDATA("Sum of "&DO$1&" (Out)",$CS$6,"Constraint Identifier",$DE10) -> 2.4346842 | DP10: =IF(SUMIF($DF$8:$DF$380,"="&$DF10,DG$8:DG$380)=0,0,DG10/SUMIF($DF$8:$DF$380,"="&$DF10,DG$8:DG$380)) -> 0 | DQ10: =IF(SUMIF($DF$8:$DF$380,"="&$DF10,DH$8:DH$380)=0,0,DH10/SUMIF($DF$8:$DF$380,"="&$DF10,DH$8:DH$380)) -> 0.92241825 | DR10: =IF(SUMIF($DF$8:$DF$380,"="&$DF10,DI$8:DI$380)=0,0,DI10/SUMIF($DF$8:$DF$380,"="&$DF10,DI$8:DI$380)) -> 0.89713322 | DS10: =IF(SUMIF($DF$8:$DF$380,"="&$DF10,DJ$8:DJ$380)=0,0,DJ10/SUMIF($DF$8:$DF$380,"="&$DF10,DJ$8:DJ$380)) -> 0.89713322 | DT10: =IF(SUMIF($DF$8:$DF$380,"="&$DF10,DK$8:DK$380)=0,0,DK10/SUMIF($DF$8:$DF$380,"="&$DF10,DK$8:DK$380)) -> 0.89713322 | DU10: =IF(SUMIF($DF$8:$DF$380,"="&$DF10,DL$8:DL$380)=0,0,DL10/SUMIF($DF$8:$DF$380,"="&$DF10,DL$8:DL$380)) -> 0.89713322 | DV10: =IF(SUMIF($DF$8:$DF$380,"="&$DF10,DM$8:DM$380)=0,0,DM10/SUMIF($DF$8:$DF$380,"="&$DF10,DM$8:DM$380)) -> 0.89713322 | DW10: =IF(SUMIF($DF$8:$DF$380,"="&$DF10,DN$8:DN$380)=0,0,DN10/SUMIF($DF$8:$DF$380,"="&$DF10,DN$8:DN$380)) -> 0.89713322 | DX10: =IF(SUMIF($DF$8:$DF$380,"="&$DF10,DO$8:DO$380)=0,0,DO10/SUMIF($DF$8:$DF$380,"="&$DF10,DO$8:DO$380)) -> 0.89713322 | DZ10: ICAFA_NGA | EA10: 0 | EB10: 0 | EC10: 0.32730185 | ED10: 0.32730185 | EE10: 0.042492686 | EF10: 0.042492686 | EG10: 0.042492686 | EH10: 0.10008141 | EI10: 0.10008141 | EK10: Paper | EL10: 32 | EM10: 23 | EO10: Agricultural Chemicals | EP10: R3 | EQ10: =GETPIVOTDATA("Sum of "&EP10&" (Out)",$AW$6,"Sub-Sector",EO10) -> 45.432757 | ER10: =EQ10/SUM(EQ8:EQ16) -> 0.11140422 | ET10: R2 | EU10: 0 | EW10: Agricultural Chemicals | EX10: ICA | EY10: Steam | EZ10: STM | FA10: =EX10&EZ10 -> ICASTM | FB10: R5 | FC10: =GETPIVOTDATA("Sum of "&FB10&" (Out)",$AW$6,"Sub-Sector",EW10) -> 61.795009 | FD10: =GETPIVOTDATA("Sum of "&FB10&" (Out)",$AW$6,"Sub-Sector",EW10,"End-Use",EY10) -> 0.91713298 | FE10: =GETPIVOTDATA("Sum of "&FB10&" (%)",$CH$6,"End-Use Commodity",FA10) -> 0.014841538 | FF10: 0 | FG10: =FC10-((FD10-FF10)/FE10) -> 0 | FI10: ICO | FJ10: 0 | FK10: 0 | FL10: 0.55714857 | FM10: 0 | FN10: 0.80380033 | FO10: 0.80056719 | FP10: 4.8401814 | FQ10: 0 | FR10: 0 | FS10: 7.0016975
A11: Agricultural Chemicals | B11: Feedstock | C11: Natural Gas | D11: Natural Gas | E11: ICAEFEDNGA | F11: =EndUse(A11,B11,C11,G11) -> #NAME? | G11: TechData_OTR | H11: 1 | I11: 0 | J11: 18.722287 | K11: 39.003975 | S11: 1 | T11: 1 | U11: 1 | V11: 1 | W11: 1 | X11: 1 | Y11: 1 | Z11: 1 | AA11: 1 | AB11: =J11*$H11*S11 -> 18.722287 | AC11: =K11*$H11*T11 -> 39.003975 | AD11: =L11*$H11*U11 -> 0 | AE11: =M11*$H11*V11 -> 0 | AF11: =N11*$H11*W11 -> 0 | AG11: =O11*$H11*X11 -> 0 | AH11: =P11*$H11*Y11 -> 0 | AI11: =Q11*$H11*Z11 -> 0 | AJ11: =R11*$H11*AA11 -> 0 | AK11: =SUM(AB11:AJ11) -> 57.726262 | AL11: 0 | AM11: 0 | AN11: 0 | AO11: 0 | AP11: 0 | AQ11: 0 | AR11: 0 | AS11: 0 | AT11: 0 | AU11: 0 | AW11: Machine Drive | AX11: 0 | AY11: 0 | AZ11: 2.9448659 | BA11: 1.9946277 | BB11: 2.6630554 | BC11: 2.3212407 | BD11: 8.0639956 | BE11: 1.4073734 | BF11: 0.88248721 | BG11: 20.277646 | BH11: 0 | BJ11: Agricultural Chemicals | BK11: ICA | BL11: Machine Drive | BM11: MDR | BN11: =BK11&BM11 -> ICAMDR | BO11: =IF(ISERROR(GETPIVOTDATA("Sum of "&BO$1&" (Out)",$AW$6,"Sub-Sector",$BJ11,"End-Use",$BL11)),0,GETPIVOTDATA("Sum of "&BO$1&" (Out)",$AW$6,"Sub-Sector",$BJ11,"End-Use",$BL11)) -> 0 | BP11: =IF(ISERROR(GETPIVOTDATA("Sum of "&BP$1&" (Out)",$AW$6,"Sub-Sector",$BJ11,"End-Use",$BL11)),0,GETPIVOTDATA("Sum of "&BP$1&" (Out)",$AW$6,"Sub-Sector",$BJ11,"End-Use",$BL11)) -> 0 | BQ11: =IF(ISERROR(GETPIVOTDATA("Sum of "&BQ$1&" (Out)",$AW$6,"Sub-Sector",$BJ11,"End-Use",$BL11)),0,GETPIVOTDATA("Sum of "&BQ$1&" (Out)",$AW$6,"Sub-Sector",$BJ11,"End-Use",$BL11)) -> 2.9448659 | BR11: =IF(ISERROR(GETPIVOTDATA("Sum of "&BR$1&" (Out)",$AW$6,"Sub-Sector",$BJ11,"End-Use",$BL11)),0,GETPIVOTDATA("Sum of "&BR$1&" (Out)",$AW$6,"Sub-Sector",$BJ11,"End-Use",$BL11)) -> 1.9946277 | BS11: =IF(ISERROR(GETPIVOTDATA("Sum of "&BS$1&" (Out)",$AW$6,"Sub-Sector",$BJ11,"End-Use",$BL11)),0,GETPIVOTDATA("Sum of "&BS$1&" (Out)",$AW$6,"Sub-Sector",$BJ11,"End-Use",$BL11)) -> 2.6630554 | BT11: =IF(ISERROR(GETPIVOTDATA("Sum of "&BT$1&" (Out)",$AW$6,"Sub-Sector",$BJ11,"End-Use",$BL11)),0,GETPIVOTDATA("Sum of "&BT$1&" (Out)",$AW$6,"Sub-Sector",$BJ11,"End-Use",$BL11)) -> 2.3212407 | BU11: =IF(ISERROR(GETPIVOTDATA("Sum of "&BU$1&" (Out)",$AW$6,"Sub-Sector",$BJ11,"End-Use",$BL11)),0,GETPIVOTDATA("Sum of "&BU$1&" (Out)",$AW$6,"Sub-Sector",$BJ11,"End-Use",$BL11)) -> 8.0639956 | BV11: =IF(ISERROR(GETPIVOTDATA("Sum of "&BV$1&" (Out)",$AW$6,"Sub-Sector",$BJ11,"End-Use",$BL11)),0,GETPIVOTDATA("Sum of "&BV$1&" (Out)",$AW$6,"Sub-Sector",$BJ11,"End-Use",$BL11)) -> 1.4073734 | BW11: =IF(ISERROR(GETPIVOTDATA("Sum of "&BW$1&" (Out)",$AW$6,"Sub-Sector",$BJ11,"End-Use",$BL11)),0,GETPIVOTDATA("Sum of "&BW$1&" (Out)",$AW$6,"Sub-Sector",$BJ11,"End-Use",$BL11)) -> 0.88248721 | BX11: 0 | BY11: 0 | BZ11: =BQ11/BQ15 -> 0.06481812 | CA11: =BR11/BR15 -> 0.050114702 | CB11: =BS11/BS15 -> 0.043094991 | CC11: =BT11/BT15 -> 0.03869223 | CD11: =BU11/BU15 -> 0.041415455 | CE11: =BV11/BV15 -> 0.33300911 | CF11: =BW11/BW15 -> 0.47407287 | CH11: ICAMDR | CI11: 0 | CJ11: 0 | CK11: 0.06481812 | CL11: 0.050114702 | CM11: 0.043094991 | CN11: 0.03869223 | CO11: 0.041415455 | CP11: 0.33300911 | CQ11: 0.47407287 | CS11: ICAFS_NGA | CT11: 0 | CU11: 0 | CV11: 27.641561 | CW11: 18.722287 | CX11: 39.003975 | CY11: 33.997645 | CZ11: 118.1079 | DA11: 0 | DB11: 0 | DC11: 237.47337 | DE11: IFDOH_DST | DF11: =LEFT(DE11,5) -> IFDOH | DG11: =GETPIVOTDATA("Sum of "&DG$1&" (Out)",$CS$6,"Constraint Identifier",$DE11) -> 0.069456426 | DH11: =GETPIVOTDATA("Sum of "&DH$1&" (Out)",$CS$6,"Constraint Identifier",$DE11) -> 0.19119017 | DI11: =GETPIVOTDATA("Sum of "&DI$1&" (Out)",$CS$6,"Constraint Identifier",$DE11) -> 0.15539433 | DJ11: =GETPIVOTDATA("Sum of "&DJ$1&" (Out)",$CS$6,"Constraint Identifier",$DE11) -> 0.10525227 | DK11: =GETPIVOTDATA("Sum of "&DK$1&" (Out)",$CS$6,"Constraint Identifier",$DE11) -> 0.10639191 | DL11: =GETPIVOTDATA("Sum of "&DL$1&" (Out)",$CS$6,"Constraint Identifier",$DE11) -> 0.092736046 | DM11: =GETPIVOTDATA("Sum of "&DM$1&" (Out)",$CS$6,"Constraint Identifier",$DE11) -> 0.32216524 | DN11: =GETPIVOTDATA("Sum of "&DN$1&" (Out)",$CS$6,"Constraint Identifier",$DE11) -> 0.58738626 | DO11: =GETPIVOTDATA("Sum of "&DO$1&" (Out)",$CS$6,"Constraint Identifier",$DE11) -> 0.36831794 | DP11: =IF(SUMIF($DF$8:$DF$380,"="&$DF11,DG$8:DG$380)=0,0,DG11/SUMIF($DF$8:$DF$380,"="&$DF11,DG$8:DG$380)) -> 0.11882275 | DQ11: =IF(SUMIF($DF$8:$DF$380,"="&$DF11,DH$8:DH$380)=0,0,DH11/SUMIF($DF$8:$DF$380,"="&$DF11,DH$8:DH$380)) -> 0.13148637 | DR11: =IF(SUMIF($DF$8:$DF$380,"="&$DF11,DI$8:DI$380)=0,0,DI11/SUMIF($DF$8:$DF$380,"="&$DF11,DI$8:DI$380)) -> 0.012023188 | DS11: =IF(SUMIF($DF$8:$DF$380,"="&$DF11,DJ$8:DJ$380)=0,0,DJ11/SUMIF($DF$8:$DF$380,"="&$DF11,DJ$8:DJ$380)) -> 0.013751338 | DT11: =IF(SUMIF($DF$8:$DF$380,"="&$DF11,DK$8:DK$380)=0,0,DK11/SUMIF($DF$8:$DF$380,"="&$DF11,DK$8:DK$380)) -> 0.0307272 | DU11: =IF(SUMIF($DF$8:$DF$380,"="&$DF11,DL$8:DL$380)=0,0,DL11/SUMIF($DF$8:$DF$380,"="&$DF11,DL$8:DL$380)) -> 0.037954893 | DV11: =IF(SUMIF($DF$8:$DF$380,"="&$DF11,DM$8:DM$380)=0,0,DM11/SUMIF($DF$8:$DF$380,"="&$DF11,DM$8:DM$380)) -> 0.031419424 | DW11: =IF(SUMIF($DF$8:$DF$380,"="&$DF11,DN$8:DN$380)=0,0,DN11/SUMIF($DF$8:$DF$380,"="&$DF11,DN$8:DN$380)) -> 0.11307213 | DX11: =IF(SUMIF($DF$8:$DF$380,"="&$DF11,DO$8:DO$380)=0,0,DO11/SUMIF($DF$8:$DF$380,"="&$DF11,DO$8:DO$380)) -> 0.14882417 | DZ11: ICAFS_NGA | EA11: 0 | EB11: 0 | EC11: 0.94551045 | ED11: 0.94551045 | EE11: 1 | EF11: 1 | EG11: 1 | EH11: 0 | EI11: 0 | EK11: Chemicals | EL11: 10 | EM11: 36 | EO11: Agricultural Chemicals | EP11: R4 | EQ11: =GETPIVOTDATA("Sum of "&EP11&" (Out)",$AW$6,"Sub-Sector",EO11) -> 39.801248 | ER11: =EQ11/SUM(EQ8:EQ16) -> 0.097595379 | ET11: R3 | EU11: 0.11140422 | EW11: Agricultural Chemicals | EX11: ICA | EY11: Machine Drive | EZ11: MDR | FA11: =EX11&EZ11 -> ICAMDR | FB11: R6 | FC11: =GETPIVOTDATA("Sum of "&FB11&" (Out)",$AW$6,"Sub-Sector",EW11) -> 59.992423 | FD11: =GETPIVOTDATA("Sum of "&FB11&" (Out)",$AW$6,"Sub-Sector",EW11,"End-Use",EY11) -> 2.3212407 | FE11: =GETPIVOTDATA("Sum of "&FB11&" (%)",$CH$6,"End-Use Commodity",FA11) -> 0.03869223 | FF11: 0 | FG11: =FC11-((FD11-FF11)/FE11) -> 0 | FI11: ICP | FJ11: 0 | FK11: 0 | FL11: 0 | FM11: 0 | FN11: 0.025857733 | FO11: 0.026692934 | FP11: 0.025785168 | FQ11: 0 | FR11: 0 | FS11: 0.078335835
A12: Agricultural Chemicals | B12: Feedstock | C12: Petrochemical Feedstock | D12: Petrochemical Feedstock | E12: ICAEFEDPFS | F12: =EndUse(A12,B12,C12,G12) -> #NAME? | G12: TechData_OTR | H12: 1 | I12: 0 | J12: 1.0789611 | K12: 0 | S12: 1 | T12: 1 | U12: 1 | V12: 1 | W12: 1 | X12: 1 | Y12: 1 | Z12: 1 | AA12: 1 | AB12: =J12*$H12*S12 -> 1.0789611 | AC12: =K12*$H12*T12 -> 0 | AD12: =L12*$H12*U12 -> 0 | AE12: =M12*$H12*V12 -> 0 | AF12: =N12*$H12*W12 -> 0 | AG12: =O12*$H12*X12 -> 0 | AH12: =P12*$H12*Y12 -> 0 | AI12: =Q12*$H12*Z12 -> 0 | AJ12: =R12*$H12*AA12 -> 0 | AK12: =SUM(AB12:AJ12) -> 1.0789611 | AL12: 0 | AM12: 0 | AN12: 0 | AO12: 0 | AP12: 0 | AQ12: 0 | AR12: 0 | AS12: 0 | AT12: 0 | AU12: 0 | AW12: Other Heat | AX12: 0 | AY12: 0 | AZ12: 0.36588093 | BA12: 0.24781986 | BB12: 0 | BC12: 0 | BD12: 0 | BE12: 0 | BF12: 0 | BG12: 0.61370079 | BH12: 0 | BJ12: Agricultural Chemicals | BK12: ICA | BL12: Other Heat | BM12: OHT | BN12: =BK12&BM12 -> ICAOHT | BO12: =IF(ISERROR(GETPIVOTDATA("Sum of "&BO$1&" (Out)",$AW$6,"Sub-Sector",$BJ12,"End-Use",$BL12)),0,GETPIVOTDATA("Sum of "&BO$1&" (Out)",$AW$6,"Sub-Sector",$BJ12,"End-Use",$BL12)) -> 0 | BP12: =IF(ISERROR(GETPIVOTDATA("Sum of "&BP$1&" (Out)",$AW$6,"Sub-Sector",$BJ12,"End-Use",$BL12)),0,GETPIVOTDATA("Sum of "&BP$1&" (Out)",$AW$6,"Sub-Sector",$BJ12,"End-Use",$BL12)) -> 0 | BQ12: =IF(ISERROR(GETPIVOTDATA("Sum of "&BQ$1&" (Out)",$AW$6,"Sub-Sector",$BJ12,"End-Use",$BL12)),0,GETPIVOTDATA("Sum of "&BQ$1&" (Out)",$AW$6,"Sub-Sector",$BJ12,"End-Use",$BL12)) -> 0.36588093 | BR12: =IF(ISERROR(GETPIVOTDATA("Sum of "&BR$1&" (Out)",$AW$6,"Sub-Sector",$BJ12,"End-Use",$BL12)),0,GETPIVOTDATA("Sum of "&BR$1&" (Out)",$AW$6,"Sub-Sector",$BJ12,"End-Use",$BL12)) -> 0.24781986 | BS12: =IF(ISERROR(GETPIVOTDATA("Sum of "&BS$1&" (Out)",$AW$6,"Sub-Sector",$BJ12,"End-Use",$BL12)),0,GETPIVOTDATA("Sum of "&BS$1&" (Out)",$AW$6,"Sub-Sector",$BJ12,"End-Use",$BL12)) -> 0 | BT12: =IF(ISERROR(GETPIVOTDATA("Sum of "&BT$1&" (Out)",$AW$6,"Sub-Sector",$BJ12,"End-Use",$BL12)),0,GETPIVOTDATA("Sum of "&BT$1&" (Out)",$AW$6,"Sub-Sector",$BJ12,"End-Use",$BL12)) -> 0 | BU12: =IF(ISERROR(GETPIVOTDATA("Sum of "&BU$1&" (Out)",$AW$6,"Sub-Sector",$BJ12,"End-Use",$BL12)),0,GETPIVOTDATA("Sum of "&BU$1&" (Out)",$AW$6,"Sub-Sector",$BJ12,"End-Use",$BL12)) -> 0 | BV12: =IF(ISERROR(GETPIVOTDATA("Sum of "&BV$1&" (Out)",$AW$6,"Sub-Sector",$BJ12,"End-Use",$BL12)),0,GETPIVOTDATA("Sum of "&BV$1&" (Out)",$AW$6,"Sub-Sector",$BJ12,"End-Use",$BL12)) -> 0 | BW12: =IF(ISERROR(GETPIVOTDATA("Sum of "&BW$1&" (Out)",$AW$6,"Sub-Sector",$BJ12,"End-Use",$BL12)),0,GETPIVOTDATA("Sum of "&BW$1&" (Out)",$AW$6,"Sub-Sector",$BJ12,"End-Use",$BL12)) -> 0 | BX12: 0 | BY12: 0 | BZ12: =BQ12/BQ15 -> 0.0080532408 | CA12: =BR12/BR15 -> 0.0062264343 | CB12: =BS12/BS15 -> 0 | CC12: =BT12/BT15 -> 0 | CD12: =BU12/BU15 -> 0 | CE12: =BV12/BV15 -> 0 | CF12: =BW12/BW15 -> 0 | CH12: ICAOHT | CI12: 0 | CJ12: 0 | CK12: 0.0080532408 | CL12: 0.0062264343 | CM12: 0 | CN12: 0 | CO12: 0 | CP12: 0 | CQ12: 0 | CS12: ICAFS_PFS | CT12: 0 | CU12: 0 | CV12: 1.5929769 | CW12: 1.0789611 | CX12: 0 | CY12: 0 | CZ12: 0 | DA12: 0 | DB12: 0 | DC12: 2.671938 | DE12: IFDOH_ELC | DF12: =LEFT(DE12,5) -> IFDOH | DG12: =GETPIVOTDATA("Sum of "&DG$1&" (Out)",$CS$6,"Constraint Identifier",$DE12) -> 0.13106152 | DH12: =GETPIVOTDATA("Sum of "&DH$1&" (Out)",$CS$6,"Constraint Identifier",$DE12) -> 0.36076827 | DI12: =GETPIVOTDATA("Sum of "&DI$1&" (Out)",$CS$6,"Constraint Identifier",$DE12) -> 1.3805913 | DJ12: =GETPIVOTDATA("Sum of "&DJ$1&" (Out)",$CS$6,"Constraint Identifier",$DE12) -> 0.93510732 | DK12: =GETPIVOTDATA("Sum of "&DK$1&" (Out)",$CS$6,"Constraint Identifier",$DE12) -> 0.33041308 | DL12: =GETPIVOTDATA("Sum of "&DL$1&" (Out)",$CS$6,"Constraint Identifier",$DE12) -> 0.28800313 | DM12: =GETPIVOTDATA("Sum of "&DM$1&" (Out)",$CS$6,"Constraint Identifier",$DE12) -> 1.0005235 | DN12: =GETPIVOTDATA("Sum of "&DN$1&" (Out)",$CS$6,"Constraint Identifier",$DE12) -> 0.51640179 | DO12: =GETPIVOTDATA("Sum of "&DO$1&" (Out)",$CS$6,"Constraint Identifier",$DE12) -> 0.32380744 | DP12: =IF(SUMIF($DF$8:$DF$380,"="&$DF12,DG$8:DG$380)=0,0,DG12/SUMIF($DF$8:$DF$380,"="&$DF12,DG$8:DG$380)) -> 0.22421382 | DQ12: =IF(SUMIF($DF$8:$DF$380,"="&$DF12,DH$8:DH$380)=0,0,DH12/SUMIF($DF$8:$DF$380,"="&$DF12,DH$8:DH$380)) -> 0.24810957 | DR12: =IF(SUMIF($DF$8:$DF$380,"="&$DF12,DI$8:DI$380)=0,0,DI12/SUMIF($DF$8:$DF$380,"="&$DF12,DI$8:DI$380)) -> 0.10681927 | DS12: =IF(SUMIF($DF$8:$DF$380,"="&$DF12,DJ$8:DJ$380)=0,0,DJ12/SUMIF($DF$8:$DF$380,"="&$DF12,DJ$8:DJ$380)) -> 0.12217292 | DT12: =IF(SUMIF($DF$8:$DF$380,"="&$DF12,DK$8:DK$380)=0,0,DK12/SUMIF($DF$8:$DF$380,"="&$DF12,DK$8:DK$380)) -> 0.095427076 | DU12: =IF(SUMIF($DF$8:$DF$380,"="&$DF12,DL$8:DL$380)=0,0,DL12/SUMIF($DF$8:$DF$380,"="&$DF12,DL$8:DL$380)) -> 0.11787356 | DV12: =IF(SUMIF($DF$8:$DF$380,"="&$DF12,DM$8:DM$380)=0,0,DM12/SUMIF($DF$8:$DF$380,"="&$DF12,DM$8:DM$380)) -> 0.097576861 | DW12: =IF(SUMIF($DF$8:$DF$380,"="&$DF12,DN$8:DN$380)=0,0,DN12/SUMIF($DF$8:$DF$380,"="&$DF12,DN$8:DN$380)) -> 0.099407587 | DX12: =IF(SUMIF($DF$8:$DF$380,"="&$DF12,DO$8:DO$380)=0,0,DO12/SUMIF($DF$8:$DF$380,"="&$DF12,DO$8:DO$380)) -> 0.13083906 | DZ12: ICAFS_PFS | EA12: 0 | EB12: 0 | EC12: 0.054489552 | ED12: 0.054489552 | EE12: 0 | EF12: 0 | EG12: 0 | EH12: 0 | EI12: 0 | EK12: Nonmetallic Mineral Products | EL12: 29 | EM12: 51 | EO12: Agricultural Chemicals | EP12: R5 | EQ12: =GETPIVOTDATA("Sum of "&EP12&" (Out)",$AW$6,"Sub-Sector",EO12) -> 61.795009 | ER12: =EQ12/SUM(EQ8:EQ16) -> 0.15152558 | ET12: R4 | EU12: 0.097595379 | EW12: Agricultural Chemicals | EX12: ICA | EY12: Facilities | EZ12: FAC | FA12: =EX12&EZ12 -> ICAFAC | FB12: R7 | FC12: =GETPIVOTDATA("Sum of "&FB12&" (Out)",$AW$6,"Sub-Sector",EW12) -> 194.70981 | FD12: =GETPIVOTDATA("Sum of "&FB12&" (Out)",$AW$6,"Sub-Sector",EW12,"End-Use",EY12) -> 9.0438504 | FE12: =GETPIVOTDATA("Sum of "&FB12&" (%)",$CH$6,"End-Use Commodity",FA12) -> 0.046447841 | FF12: 0.02 | FG12: =FC12-((FD12-FF12)/FE12) -> 0.43059052 | FI12: ICT | FJ12: 0 | FK12: 0.062709394 | FL12: 0 | FM12: 0 | FN12: 0.10979158 | FO12: 0.06234656 | FP12: 0.059490288 | FQ12: 0 | FR12: 0 | FS12: 0.29433782
A13: Agricultural Chemicals | B13: Machine Drive | C13: Electricity | D13: Electricity | E13: ICAEMDRELC | F13: =EndUse(A13,B13,C13,G13) -> #NAME? | G13: TechData_OTR | H13: 1 | I13: 0 | J13: 1.8063011 | K13: 2.282324 | S13: 1 | T13: 1 | U13: 1 | V13: 1 | W13: 1 | X13: 1 | Y13: 1 | Z13: 1 | AA13: 1 | AB13: =J13*$H13*S13 -> 1.8063011 | AC13: =K13*$H13*T13 -> 2.282324 | AD13: =L13*$H13*U13 -> 0 | AE13: =M13*$H13*V13 -> 0 | AF13: =N13*$H13*W13 -> 0 | AG13: =O13*$H13*X13 -> 0 | AH13: =P13*$H13*Y13 -> 0 | AI13: =Q13*$H13*Z13 -> 0 | AJ13: =R13*$H13*AA13 -> 0 | AK13: =SUM(AB13:AJ13) -> 4.0886251 | AL13: 0 | AM13: 0 | AN13: 0 | AO13: 0 | AP13: 0 | AQ13: 0 | AR13: 0 | AS13: 0 | AT13: 0 | AU13: 0 | AW13: Process Heat | AX13: 0 | AY13: 0 | AZ13: 11.683019 | BA13: 7.9131866 | BB13: 16.224203 | BC13: 14.141756 | BD13: 49.128495 | BE13: 1.4522061 | BF13: 0.91059935 | BG13: 101.45347 | BH13: 0 | BJ13: Agricultural Chemicals | BK13: ICA | BL13: Process Heat | BM13: PRH | BN13: =BK13&BM13 -> ICAPRH | BO13: =IF(ISERROR(GETPIVOTDATA("Sum of "&BO$1&" (Out)",$AW$6,"Sub-Sector",$BJ13,"End-Use",$BL13)),0,GETPIVOTDATA("Sum of "&BO$1&" (Out)",$AW$6,"Sub-Sector",$BJ13,"End-Use",$BL13)) -> 0 | BP13: =IF(ISERROR(GETPIVOTDATA("Sum of "&BP$1&" (Out)",$AW$6,"Sub-Sector",$BJ13,"End-Use",$BL13)),0,GETPIVOTDATA("Sum of "&BP$1&" (Out)",$AW$6,"Sub-Sector",$BJ13,"End-Use",$BL13)) -> 0 | BQ13: =IF(ISERROR(GETPIVOTDATA("Sum of "&BQ$1&" (Out)",$AW$6,"Sub-Sector",$BJ13,"End-Use",$BL13)),0,GETPIVOTDATA("Sum of "&BQ$1&" (Out)",$AW$6,"Sub-Sector",$BJ13,"End-Use",$BL13)) -> 11.683019 | BR13: =IF(ISERROR(GETPIVOTDATA("Sum of "&BR$1&" (Out)",$AW$6,"Sub-Sector",$BJ13,"End-Use",$BL13)),0,GETPIVOTDATA("Sum of "&BR$1&" (Out)",$AW$6,"Sub-Sector",$BJ13,"End-Use",$BL13)) -> 7.9131866 | BS13: =IF(ISERROR(GETPIVOTDATA("Sum of "&BS$1&" (Out)",$AW$6,"Sub-Sector",$BJ13,"End-Use",$BL13)),0,GETPIVOTDATA("Sum of "&BS$1&" (Out)",$AW$6,"Sub-Sector",$BJ13,"End-Use",$BL13)) -> 16.224203 | BT13: =IF(ISERROR(GETPIVOTDATA("Sum of "&BT$1&" (Out)",$AW$6,"Sub-Sector",$BJ13,"End-Use",$BL13)),0,GETPIVOTDATA("Sum of "&BT$1&" (Out)",$AW$6,"Sub-Sector",$BJ13,"End-Use",$BL13)) -> 14.141756 | BU13: =IF(ISERROR(GETPIVOTDATA("Sum of "&BU$1&" (Out)",$AW$6,"Sub-Sector",$BJ13,"End-Use",$BL13)),0,GETPIVOTDATA("Sum of "&BU$1&" (Out)",$AW$6,"Sub-Sector",$BJ13,"End-Use",$BL13)) -> 49.128495 | BV13: =IF(ISERROR(GETPIVOTDATA("Sum of "&BV$1&" (Out)",$AW$6,"Sub-Sector",$BJ13,"End-Use",$BL13)),0,GETPIVOTDATA("Sum of "&BV$1&" (Out)",$AW$6,"Sub-Sector",$BJ13,"End-Use",$BL13)) -> 1.4522061 | BW13: =IF(ISERROR(GETPIVOTDATA("Sum of "&BW$1&" (Out)",$AW$6,"Sub-Sector",$BJ13,"End-Use",$BL13)),0,GETPIVOTDATA("Sum of "&BW$1&" (Out)",$AW$6,"Sub-Sector",$BJ13,"End-Use",$BL13)) -> 0.91059935 | BX13: 0 | BY13: 0 | BZ13: =BQ13/BQ15 -> 0.25714968 | CA13: =BR13/BR15 -> 0.19881755 | CB13: =BS13/BS15 -> 0.26254876 | CC13: =BT13/BT15 -> 0.23572571 | CD13: =BU13/BU15 -> 0.25231648 | CE13: =BV13/BV15 -> 0.34361731 | CF13: =BW13/BW15 -> 0.48917474 | CH13: ICAPRH | CI13: 0 | CJ13: 0 | CK13: 0.25714968 | CL13: 0.19881755 | CM13: 0.26254876 | CN13: 0.23572571 | CO13: 0.25231648 | CP13: 0.34361731 | CQ13: 0.48917474 | CS13: ICAMD_ELC | CT13: 0 | CU13: 0 | CV13: 2.6668208 | CW13: 1.8063011 | CX13: 2.282324 | CY13: 1.9893778 | CZ13: 6.9111031 | DA13: 1.3746148 | DB13: 0.86194612 | DC13: 17.892488 | DE13: IFDOH_NGA | DF13: =LEFT(DE13,5) -> IFDOH | DG13: =GETPIVOTDATA("Sum of "&DG$1&" (Out)",$CS$6,"Constraint Identifier",$DE13) -> 0.22391973 | DH13: =GETPIVOTDATA("Sum of "&DH$1&" (Out)",$CS$6,"Constraint Identifier",$DE13) -> 0.61637567 | DI13: =GETPIVOTDATA("Sum of "&DI$1&" (Out)",$CS$6,"Constraint Identifier",$DE13) -> 2.2454365 | DJ13: =GETPIVOTDATA("Sum of "&DJ$1&" (Out)",$CS$6,"Constraint Identifier",$DE13) -> 1.5208875 | DK13: =GETPIVOTDATA("Sum of "&DK$1&" (Out)",$CS$6,"Constraint Identifier",$DE13) -> 0.4501817 | DL13: =GETPIVOTDATA("Sum of "&DL$1&" (Out)",$CS$6,"Constraint Identifier",$DE13) -> 0.39239893 | DM13: =GETPIVOTDATA("Sum of "&DM$1&" (Out)",$CS$6,"Constraint Identifier",$DE13) -> 1.3631948 | DN13: =GETPIVOTDATA("Sum of "&DN$1&" (Out)",$CS$6,"Constraint Identifier",$DE13) -> 1.1620232 | DO13: =GETPIVOTDATA("Sum of "&DO$1&" (Out)",$CS$6,"Constraint Identifier",$DE13) -> 0.72864146 | DP13: =IF(SUMIF($DF$8:$DF$380,"="&$DF13,DG$8:DG$380)=0,0,DG13/SUMIF($DF$8:$DF$380,"="&$DF13,DG$8:DG$380)) -> 0.38307123 | DQ13: =IF(SUMIF($DF$8:$DF$380,"="&$DF13,DH$8:DH$380)=0,0,DH13/SUMIF($DF$8:$DF$380,"="&$DF13,DH$8:DH$380)) -> 0.42389731 | DR13: =IF(SUMIF($DF$8:$DF$380,"="&$DF13,DI$8:DI$380)=0,0,DI13/SUMIF($DF$8:$DF$380,"="&$DF13,DI$8:DI$380)) -> 0.17373417 | DS13: =IF(SUMIF($DF$8:$DF$380,"="&$DF13,DJ$8:DJ$380)=0,0,DJ13/SUMIF($DF$8:$DF$380,"="&$DF13,DJ$8:DJ$380)) -> 0.19870582 | DT13: =IF(SUMIF($DF$8:$DF$380,"="&$DF13,DK$8:DK$380)=0,0,DK13/SUMIF($DF$8:$DF$380,"="&$DF13,DK$8:DK$380)) -> 0.13001762 | DU13: =IF(SUMIF($DF$8:$DF$380,"="&$DF13,DL$8:DL$380)=0,0,DL13/SUMIF($DF$8:$DF$380,"="&$DF13,DL$8:DL$380)) -> 0.16060054 | DV13: =IF(SUMIF($DF$8:$DF$380,"="&$DF13,DM$8:DM$380)=0,0,DM13/SUMIF($DF$8:$DF$380,"="&$DF13,DM$8:DM$380)) -> 0.13294667 | DW13: =IF(SUMIF($DF$8:$DF$380,"="&$DF13,DN$8:DN$380)=0,0,DN13/SUMIF($DF$8:$DF$380,"="&$DF13,DN$8:DN$380)) -> 0.22369001 | DX13: =IF(SUMIF($DF$8:$DF$380,"="&$DF13,DO$8:DO$380)=0,0,DO13/SUMIF($DF$8:$DF$380,"="&$DF13,DO$8:DO$380)) -> 0.29441808 | DZ13: ICAMD_ELC | EA13: 0 | EB13: 0 | EC13: 0.9055831 | ED13: 0.9055831 | EE13: 0.8570321 | EF13: 0.8570321 | EG13: 0.8570321 | EH13: 0.97672364 | EI13: 0.97672364 | EK13: Primary Metals | EL13: 12 | EM13: 3 | EO13: Agricultural Chemicals | EP13: R6 | EQ13: =GETPIVOTDATA("Sum of "&EP13&" (Out)",$AW$6,"Sub-Sector",EO13) -> 59.992423 | ER13: =EQ13/SUM(EQ8:EQ16) -> 0.14710552 | ET13: R5 | EU13: 0.15152558 | EW13: Agricultural Chemicals | EX13: ICA | EY13: Facilities | EZ13: FAC | FA13: =EX13&EZ13 -> ICAFAC | FB13: R8 | FC13: =GETPIVOTDATA("Sum of "&FB13&" (Out)",$AW$6,"Sub-Sector",EW13) -> 4.2262309 | FD13: =GETPIVOTDATA("Sum of "&FB13&" (Out)",$AW$6,"Sub-Sector",EW13,"End-Use",EY13) -> 0.10910629 | FE13: =GETPIVOTDATA("Sum of "&FB13&" (%)",$CH$6,"End-Use Commodity",FA13) -> 0.025816452 | FF13: 0 | FG13: =FC13-((FD13-FF13)/FE13) -> 0 | FI13: IFD | FJ13: 0 | FK13: 0 | FL13: 0.40226525 | FM13: 0.65868011 | FN13: 0 | FO13: 0 | FP13: 0 | FQ13: 0 | FR13: 0 | FS13: 1.0609454
A14: Agricultural Chemicals | B14: Machine Drive | C14: Natural Gas | D14: Natural Gas | E14: ICAEMDRNGA | F14: =EndUse(A14,B14,C14,G14) -> #NAME? | G14: TechData_OTR | H14: 1 | I14: 0 | J14: 0.18832657 | K14: 0.38073143 | S14: 1 | T14: 1 | U14: 1 | V14: 1 | W14: 1 | X14: 1 | Y14: 1 | Z14: 1 | AA14: 1 | AB14: =J14*$H14*S14 -> 0.18832657 | AC14: =K14*$H14*T14 -> 0.38073143 | AD14: =L14*$H14*U14 -> 0 | AE14: =M14*$H14*V14 -> 0 | AF14: =N14*$H14*W14 -> 0 | AG14: =O14*$H14*X14 -> 0 | AH14: =P14*$H14*Y14 -> 0 | AI14: =Q14*$H14*Z14 -> 0 | AJ14: =R14*$H14*AA14 -> 0 | AK14: =SUM(AB14:AJ14) -> 0.569058 | AL14: 0 | AM14: 0 | AN14: 0 | AO14: 0 | AP14: 0 | AQ14: 0 | AR14: 0 | AS14: 0 | AT14: 0 | AU14: 0 | AW14: Steam | AX14: 0 | AY14: 0 | AZ14: 0.92128435 | BA14: 9.6525691 | BB14: 0.91713298 | BC14: 6.9284866 | BD14: 10.365573 | BE14: 1.2575452 | BF14: 0 | BG14: 30.042591 | BH14: 1.823728 | BJ14: Agricultural Chemicals | BK14: ICA | BL14: Steam | BM14: STM | BN14: =BK14&BM14 -> ICASTM | BO14: =IF(ISERROR(GETPIVOTDATA("Sum of "&BO$1&" (Out)",$AW$6,"Sub-Sector",$BJ14,"End-Use",$BL14)),0,GETPIVOTDATA("Sum of "&BO$1&" (Out)",$AW$6,"Sub-Sector",$BJ14,"End-Use",$BL14)) -> 0 | BP14: =IF(ISERROR(GETPIVOTDATA("Sum of "&BP$1&" (Out)",$AW$6,"Sub-Sector",$BJ14,"End-Use",$BL14)),0,GETPIVOTDATA("Sum of "&BP$1&" (Out)",$AW$6,"Sub-Sector",$BJ14,"End-Use",$BL14)) -> 0 | BQ14: =IF(ISERROR(GETPIVOTDATA("Sum of "&BQ$1&" (Out)",$AW$6,"Sub-Sector",$BJ14,"End-Use",$BL14)),0,GETPIVOTDATA("Sum of "&BQ$1&" (Out)",$AW$6,"Sub-Sector",$BJ14,"End-Use",$BL14)) -> 0.92128435 | BR14: =IF(ISERROR(GETPIVOTDATA("Sum of "&BR$1&" (Out)",$AW$6,"Sub-Sector",$BJ14,"End-Use",$BL14)),0,GETPIVOTDATA("Sum of "&BR$1&" (Out)",$AW$6,"Sub-Sector",$BJ14,"End-Use",$BL14)) -> 9.6525691 | BS14: =IF(ISERROR(GETPIVOTDATA("Sum of "&BS$1&" (Out)",$AW$6,"Sub-Sector",$BJ14,"End-Use",$BL14)),0,GETPIVOTDATA("Sum of "&BS$1&" (Out)",$AW$6,"Sub-Sector",$BJ14,"End-Use",$BL14)) -> 0.91713298 | BT14: =IF(ISERROR(GETPIVOTDATA("Sum of "&BT$1&" (Out)",$AW$6,"Sub-Sector",$BJ14,"End-Use",$BL14)),0,GETPIVOTDATA("Sum of "&BT$1&" (Out)",$AW$6,"Sub-Sector",$BJ14,"End-Use",$BL14)) -> 6.9284866 | BU14: =IF(ISERROR(GETPIVOTDATA("Sum of "&BU$1&" (Out)",$AW$6,"Sub-Sector",$BJ14,"End-Use",$BL14)),0,GETPIVOTDATA("Sum of "&BU$1&" (Out)",$AW$6,"Sub-Sector",$BJ14,"End-Use",$BL14)) -> 10.365573 | BV14: =IF(ISERROR(GETPIVOTDATA("Sum of "&BV$1&" (Out)",$AW$6,"Sub-Sector",$BJ14,"End-Use",$BL14)),0,GETPIVOTDATA("Sum of "&BV$1&" (Out)",$AW$6,"Sub-Sector",$BJ14,"End-Use",$BL14)) -> 1.2575452 | BW14: =IF(ISERROR(GETPIVOTDATA("Sum of "&BW$1&" (Out)",$AW$6,"Sub-Sector",$BJ14,"End-Use",$BL14)),0,GETPIVOTDATA("Sum of "&BW$1&" (Out)",$AW$6,"Sub-Sector",$BJ14,"End-Use",$BL14)) -> 0 | BX14: 0 | BY14: 0 | BZ14: =BQ14/BQ15 -> 0.020277976 | CA14: =BR14/BR15 -> 0.24251926 | CB14: =BS14/BS15 -> 0.014841538 | CC14: =BT14/BT15 -> 0.11548936 | CD14: =BU14/BU15 -> 0.053236008 | CE14: =BV14/BV15 -> 0.29755713 | CF14: =BW14/BW15 -> 0 | CH14: ICASTM | CI14: 0 | CJ14: 0 | CK14: 0.020277976 | CL14: 0.24251926 | CM14: 0.014841538 | CN14: 0.11548936 | CO14: 0.053236008 | CP14: 0.29755713 | CQ14: 0 | CS14: ICAMD_NGA | CT14: 0 | CU14: 0 | CV14: 0.27804513 | CW14: 0.18832657 | CX14: 0.38073143 | CY14: 0.33186289 | CZ14: 1.1528925 | DA14: 0.032758532 | DB14: 0.020541091 | DC14: 2.3851581 | DE14: IFDOH_CHP | DF14: =LEFT(DE14,5) -> IFDOH | DG14: =GETPIVOTDATA("Sum of "&DG$1&" (Out)",$CS$6,"Constraint Identifier",$DE14) -> 0.0020921173 | DH14: =GETPIVOTDATA("Sum of "&DH$1&" (Out)",$CS$6,"Constraint Identifier",$DE14) -> 0.20752189 | DI14: =GETPIVOTDATA("Sum of "&DI$1&" (Out)",$CS$6,"Constraint Identifier",$DE14) -> 4.3775166 | DJ14: =GETPIVOTDATA("Sum of "&DJ$1&" (Out)",$CS$6,"Constraint Identifier",$DE14) -> 4.552543 | DK14: =GETPIVOTDATA("Sum of "&DK$1&" (Out)",$CS$6,"Constraint Identifier",$DE14) -> 0.88852272 | DL14: =GETPIVOTDATA("Sum of "&DL$1&" (Out)",$CS$6,"Constraint Identifier",$DE14) -> 1.5967659 | DM14: =GETPIVOTDATA("Sum of "&DM$1&" (Out)",$CS$6,"Constraint Identifier",$DE14) -> 7.3899107 | DN14: =GETPIVOTDATA("Sum of "&DN$1&" (Out)",$CS$6,"Constraint Identifier",$DE14) -> 0.13993091 | DO14: =GETPIVOTDATA("Sum of "&DO$1&" (Out)",$CS$6,"Constraint Identifier",$DE14) -> 1.0130085 | DP14: =IF(SUMIF($DF$8:$DF$380,"="&$DF14,DG$8:DG$380)=0,0,DG14/SUMIF($DF$8:$DF$380,"="&$DF14,DG$8:DG$380)) -> 0.0035790948 | DQ14: =IF(SUMIF($DF$8:$DF$380,"="&$DF14,DH$8:DH$380)=0,0,DH14/SUMIF($DF$8:$DF$380,"="&$DF14,DH$8:DH$380)) -> 0.14271811 | DR14: =IF(SUMIF($DF$8:$DF$380,"="&$DF14,DI$8:DI$380)=0,0,DI14/SUMIF($DF$8:$DF$380,"="&$DF14,DI$8:DI$380)) -> 0.33869772 | DS14: =IF(SUMIF($DF$8:$DF$380,"="&$DF14,DJ$8:DJ$380)=0,0,DJ14/SUMIF($DF$8:$DF$380,"="&$DF14,DJ$8:DJ$380)) -> 0.59479532 | DT14: =IF(SUMIF($DF$8:$DF$380,"="&$DF14,DK$8:DK$380)=0,0,DK14/SUMIF($DF$8:$DF$380,"="&$DF14,DK$8:DK$380)) -> 0.25661552 | DU14: =IF(SUMIF($DF$8:$DF$380,"="&$DF14,DL$8:DL$380)=0,0,DL14/SUMIF($DF$8:$DF$380,"="&$DF14,DL$8:DL$380)) -> 0.65352235 | DV14: =IF(SUMIF($DF$8:$DF$380,"="&$DF14,DM$8:DM$380)=0,0,DM14/SUMIF($DF$8:$DF$380,"="&$DF14,DM$8:DM$380)) -> 0.72070697 | DW14: =IF(SUMIF($DF$8:$DF$380,"="&$DF14,DN$8:DN$380)=0,0,DN14/SUMIF($DF$8:$DF$380,"="&$DF14,DN$8:DN$380)) -> 0.026936767 | DX14: =IF(SUMIF($DF$8:$DF$380,"="&$DF14,DO$8:DO$380)=0,0,DO14/SUMIF($DF$8:$DF$380,"="&$DF14,DO$8:DO$380)) -> 0.40932067 | DZ14: ICAMD_NGA | EA14: 0 | EB14: 0 | EC14: 0.094416905 | ED14: 0.094416905 | EE14: 0.1429679 | EF14: 0.1429679 | EG14: 0.1429679 | EH14: 0.023276362 | EI14: 0.023276362 | EK14: Other | EL14: 20 | EM14: 20 | EO14: Agricultural Chemicals | EP14: R7 | EQ14: =GETPIVOTDATA("Sum of "&EP14&" (Out)",$AW$6,"Sub-Sector",EO14) -> 194.70981 | ER14: =EQ14/SUM(EQ8:EQ16) -> 0.47744176 | ET14: R6 | EU14: 0.14710552 | EW14: Agricultural Chemicals | EX14: ICA | EY14: Facilities | EZ14: FAC | FA14: =EX14&EZ14 -> ICAFAC | FB14: R9 | FC14: =GETPIVOTDATA("Sum of "&FB14&" (Out)",$AW$6,"Sub-Sector",EW14) -> 1.8615012 | FD14: =GETPIVOTDATA("Sum of "&FB14&" (Out)",$AW$6,"Sub-Sector",EW14,"End-Use",EY14) -> 0.06841461 | FE14: =GETPIVOTDATA("Sum of "&FB14&" (%)",$CH$6,"End-Use Commodity",FA14) -> 0.036752386 | FF14: 0 | FG14: =FC14-((FD14-FF14)/FE14) -> 0 | FI14: IMA | FJ14: 0 | FK14: 0 | FL14: 0 | FM14: 0 | FN14: 0 | FO14: 0 | FP14: 0.44107409 | FQ14: 0 | FR14: 0 | FS14: 0.44107409
A15: Agricultural Chemicals | B15: Other Heat | C15: Other Petroleum | D15: Other Petroleum | E15: ICAEOHTOTP | F15: =EndUse(A15,B15,C15,G15) -> #NAME? | G15: TechData_OTR | H15: 1 | I15: 0 | J15: 0.24781986 | K15: 0 | S15: 1 | T15: 1 | U15: 1 | V15: 1 | W15: 1 | X15: 1 | Y15: 1 | Z15: 1 | AA15: 1 | AB15: =J15*$H15*S15 -> 0.24781986 | AC15: =K15*$H15*T15 -> 0 | AD15: =L15*$H15*U15 -> 0 | AE15: =M15*$H15*V15 -> 0 | AF15: =N15*$H15*W15 -> 0 | AG15: =O15*$H15*X15 -> 0 | AH15: =P15*$H15*Y15 -> 0 | AI15: =Q15*$H15*Z15 -> 0 | AJ15: =R15*$H15*AA15 -> 0 | AK15: =SUM(AB15:AJ15) -> 0.24781986 | AL15: 0 | AM15: 0 | AN15: 0 | AO15: 0 | AP15: 0 | AQ15: 0 | AR15: 0 | AS15: 0 | AT15: 0 | AU15: 0 | AW15: Cement | AX15: 5.1174965 | AY15: 19.351306 | AZ15: 43.505092 | BA15: 29.467033 | BB15: 18.144209 | BC15: 15.815321 | BD15: 54.942462 | BE15: 25.763156 | BF15: 16.154672 | BG15: 228.26075 | BH15: 2.2933893e-17 | BJ15: Agricultural Chemicals | BK15: ICA | BL15: Total | BO15: =GETPIVOTDATA("Sum of "&BO$1&" (Out)",$AW$6,"Sub-Sector",$BJ15) -> 0 | BP15: =GETPIVOTDATA("Sum of "&BP$1&" (Out)",$AW$6,"Sub-Sector",$BJ15) -> 0 | BQ15: =GETPIVOTDATA("Sum of "&BQ$1&" (Out)",$AW$6,"Sub-Sector",$BJ15) -> 45.432757 | BR15: =GETPIVOTDATA("Sum of "&BR$1&" (Out)",$AW$6,"Sub-Sector",$BJ15) -> 39.801248 | BS15: =GETPIVOTDATA("Sum of "&BS$1&" (Out)",$AW$6,"Sub-Sector",$BJ15) -> 61.795009 | BT15: =GETPIVOTDATA("Sum of "&BT$1&" (Out)",$AW$6,"Sub-Sector",$BJ15) -> 59.992423 | BU15: =GETPIVOTDATA("Sum of "&BU$1&" (Out)",$AW$6,"Sub-Sector",$BJ15) -> 194.70981 | BV15: =GETPIVOTDATA("Sum of "&BV$1&" (Out)",$AW$6,"Sub-Sector",$BJ15) -> 4.2262309 | BW15: =GETPIVOTDATA("Sum of "&BW$1&" (Out)",$AW$6,"Sub-Sector",$BJ15) -> 1.8615012 | CH15: ICIETC | CI15: 0.20343255 | CJ15: 0.21920853 | CK15: 0.2031139 | CL15: 0.2014114 | CM15: 0.11501976 | CN15: 0.13420263 | CO15: 0.11843369 | CP15: 0.1502062 | CQ15: 0.15561138 | CS15: ICAOH_OTP | CT15: 0 | CU15: 0 | CV15: 0.36588093 | CW15: 0.24781986 | CX15: 0 | CY15: 0 | CZ15: 0 | DA15: 0 | DB15: 0 | DC15: 0.61370079 | DE15: IFDOH_BIO | DF15: =LEFT(DE15,5) -> IFDOH | DG15: =GETPIVOTDATA("Sum of "&DG$1&" (Out)",$CS$6,"Constraint Identifier",$DE15) -> 0.12959496 | DH15: =GETPIVOTDATA("Sum of "&DH$1&" (Out)",$CS$6,"Constraint Identifier",$DE15) -> 0 | DI15: =GETPIVOTDATA("Sum of "&DI$1&" (Out)",$CS$6,"Constraint Identifier",$DE15) -> 4.244513 | DJ15: =GETPIVOTDATA("Sum of "&DJ$1&" (Out)",$CS$6,"Constraint Identifier",$DE15) -> 0.1872213 | DK15: =GETPIVOTDATA("Sum of "&DK$1&" (Out)",$CS$6,"Constraint Identifier",$DE15) -> 1.6282068 | DL15: =GETPIVOTDATA("Sum of "&DL$1&" (Out)",$CS$6,"Constraint Identifier",$DE15) -> 0.022208913 | DM15: =GETPIVOTDATA("Sum of "&DM$1&" (Out)",$CS$6,"Constraint Identifier",$DE15) -> 0 | DN15: =GETPIVOTDATA("Sum of "&DN$1&" (Out)",$CS$6,"Constraint Identifier",$DE15) -> 2.7235405 | DO15: =GETPIVOTDATA("Sum of "&DO$1&" (Out)",$CS$6,"Constraint Identifier",$DE15) -> 0 | DP15: =IF(SUMIF($DF$8:$DF$380,"="&$DF15,DG$8:DG$380)=0,0,DG15/SUMIF($DF$8:$DF$380,"="&$DF15,DG$8:DG$380)) -> 0.2217049 | DQ15: =IF(SUMIF($DF$8:$DF$380,"="&$DF15,DH$8:DH$380)=0,0,DH15/SUMIF($DF$8:$DF$380,"="&$DF15,DH$8:DH$380)) -> 0 | DR15: =IF(SUMIF($DF$8:$DF$380,"="&$DF15,DI$8:DI$380)=0,0,DI15/SUMIF($DF$8:$DF$380,"="&$DF15,DI$8:DI$380)) -> 0.32840695 | DS15: =IF(SUMIF($DF$8:$DF$380,"="&$DF15,DJ$8:DJ$380)=0,0,DJ15/SUMIF($DF$8:$DF$380,"="&$DF15,DJ$8:DJ$380)) -> 0.024460693 | DT15: =IF(SUMIF($DF$8:$DF$380,"="&$DF15,DK$8:DK$380)=0,0,DK15/SUMIF($DF$8:$DF$380,"="&$DF15,DK$8:DK$380)) -> 0.47024475 | DU15: =IF(SUMIF($DF$8:$DF$380,"="&$DF15,DL$8:DL$380)=0,0,DL15/SUMIF($DF$8:$DF$380,"="&$DF15,DL$8:DL$380)) -> 0.0090896361 | DV15: =IF(SUMIF($DF$8:$DF$380,"="&$DF15,DM$8:DM$380)=0,0,DM15/SUMIF($DF$8:$DF$380,"="&$DF15,DM$8:DM$380)) -> 0 | DW15: =IF(SUMIF($DF$8:$DF$380,"="&$DF15,DN$8:DN$380)=0,0,DN15/SUMIF($DF$8:$DF$380,"="&$DF15,DN$8:DN$380)) -> 0.52428283 | DX15: =IF(SUMIF($DF$8:$DF$380,"="&$DF15,DO$8:DO$380)=0,0,DO15/SUMIF($DF$8:$DF$380,"="&$DF15,DO$8:DO$380)) -> 0 | DZ15: ICAOH_OTP | EA15: 0 | EB15: 0 | EC15: 1 | ED15: 1 | EE15: 0 | EF15: 0 | EG15: 0 | EH15: 0 | EI15: 0 | EK15: Source: 2007 OPEI Report | EO15: Agricultural Chemicals | EP15: R8 | EQ15: =GETPIVOTDATA("Sum of "&EP15&" (Out)",$AW$6,"Sub-Sector",EO15) -> 4.2262309 | ER15: =EQ15/SUM(EQ8:EQ16) -> 0.010363007 | ET15: R7 | EU15: 0.47744176 | EW15: Cement | EX15: INC | EY15: Other Heat | EZ15: OHT | FA15: =EX15&EZ15 -> INCOHT | FB15: R1 | FC15: =GETPIVOTDATA("Sum of "&FB15&" (Out)",$AW$6,"Sub-Sector",EW15) -> 5.1174965 | FD15: =GETPIVOTDATA("Sum of "&FB15&" (Out)",$AW$6,"Sub-Sector",EW15,"End-Use",EY15) -> 0.16085723 | FE15: =GETPIVOTDATA("Sum of "&FB15&" (%)",$CH$6,"End-Use Commodity",FA15) -> 0.031432797 | FF15: 0 | FG15: =FC15-((FD15-FF15)/FE15) -> 0 | FI15: IML | FJ15: 0 | FK15: 0 | FL15: 0 | FM15: 0 | FN15: 0 | FO15: 0 | FP15: 0 | FQ15: 0 | FR15: 0 | FS15: 0
A16: Agricultural Chemicals | B16: Process Heat | C16: Electricity | D16: Electricity | E16: ICAEPRHELC | F16: =EndUse(A16,B16,C16,G16) -> #NAME? | G16: TechData_OTR | H16: 1 | I16: 0 | J16: 0.12902151 | K16: 0.16302314 | S16: 1 | T16: 1 | U16: 1 | V16: 1 | W16: 1 | X16: 1 | Y16: 1 | Z16: 1 | AA16: 1 | AB16: =J16*$H16*S16 -> 0.12902151 | AC16: =K16*$H16*T16 -> 0.16302314 | AD16: =L16*$H16*U16 -> 0 | AE16: =M16*$H16*V16 -> 0 | AF16: =N16*$H16*W16 -> 0 | AG16: =O16*$H16*X16 -> 0 | AH16: =P16*$H16*Y16 -> 0 | AI16: =Q16*$H16*Z16 -> 0 | AJ16: =R16*$H16*AA16 -> 0 | AK16: =SUM(AB16:AJ16) -> 0.29204465 | AL16: 0 | AM16: 0 | AN16: 0 | AO16: 0 | AP16: 0 | AQ16: 0 | AR16: 0 | AS16: 0 | AT16: 0 | AU16: 0 | AW16: Facilities | AX16: 0.28196852 | AY16: 0.77616447 | AZ16: 0.86095524 | BA16: 0.58314545 | BB16: 0.34724513 | BC16: 0.30267471 | BD16: 1.0514927 | BE16: 0.23721998 | BF16: 0.14874773 | BG16: 4.5896139 | BH16: 0 | BJ16: Cement | BK16: INC | BL16: Electrochemical | BM16: ETC | BN16: =BK16&BM16 -> INCETC | BO16: =IF(ISERROR(GETPIVOTDATA("Sum of "&BO$1&" (Out)",$AW$6,"Sub-Sector",$BJ16,"End-Use",$BL16)),0,GETPIVOTDATA("Sum of "&BO$1&" (Out)",$AW$6,"Sub-Sector",$BJ16,"End-Use",$BL16)) -> 0 | BP16: =IF(ISERROR(GETPIVOTDATA("Sum of "&BP$1&" (Out)",$AW$6,"Sub-Sector",$BJ16,"End-Use",$BL16)),0,GETPIVOTDATA("Sum of "&BP$1&" (Out)",$AW$6,"Sub-Sector",$BJ16,"End-Use",$BL16)) -> 0 | BQ16: =IF(ISERROR(GETPIVOTDATA("Sum of "&BQ$1&" (Out)",$AW$6,"Sub-Sector",$BJ16,"End-Use",$BL16)),0,GETPIVOTDATA("Sum of "&BQ$1&" (Out)",$AW$6,"Sub-Sector",$BJ16,"End-Use",$BL16)) -> 0 | BR16: =IF(ISERROR(GETPIVOTDATA("Sum of "&BR$1&" (Out)",$AW$6,"Sub-Sector",$BJ16,"End-Use",$BL16)),0,GETPIVOTDATA("Sum of "&BR$1&" (Out)",$AW$6,"Sub-Sector",$BJ16,"End-Use",$BL16)) -> 0 | BS16: =IF(ISERROR(GETPIVOTDATA("Sum of "&BS$1&" (Out)",$AW$6,"Sub-Sector",$BJ16,"End-Use",$BL16)),0,GETPIVOTDATA("Sum of "&BS$1&" (Out)",$AW$6,"Sub-Sector",$BJ16,"End-Use",$BL16)) -> 0 | BT16: =IF(ISERROR(GETPIVOTDATA("Sum of "&BT$1&" (Out)",$AW$6,"Sub-Sector",$BJ16,"End-Use",$BL16)),0,GETPIVOTDATA("Sum of "&BT$1&" (Out)",$AW$6,"Sub-Sector",$BJ16,"End-Use",$BL16)) -> 0 | BU16: =IF(ISERROR(GETPIVOTDATA("Sum of "&BU$1&" (Out)",$AW$6,"Sub-Sector",$BJ16,"End-Use",$BL16)),0,GETPIVOTDATA("Sum of "&BU$1&" (Out)",$AW$6,"Sub-Sector",$BJ16,"End-Use",$BL16)) -> 0 | BV16: =IF(ISERROR(GETPIVOTDATA("Sum of "&BV$1&" (Out)",$AW$6,"Sub-Sector",$BJ16,"End-Use",$BL16)),0,GETPIVOTDATA("Sum of "&BV$1&" (Out)",$AW$6,"Sub-Sector",$BJ16,"End-Use",$BL16)) -> 0 | BW16: =IF(ISERROR(GETPIVOTDATA("Sum of "&BW$1&" (Out)",$AW$6,"Sub-Sector",$BJ16,"End-Use",$BL16)),0,GETPIVOTDATA("Sum of "&BW$1&" (Out)",$AW$6,"Sub-Sector",$BJ16,"End-Use",$BL16)) -> 0 | BX16: =BO16/BO23 -> 0 | BY16: =BP16/BP23 -> 0 | BZ16: =BQ16/BQ23 -> 0 | CA16: =BR16/BR23 -> 0 | CB16: =BS16/BS23 -> 0 | CC16: =BT16/BT23 -> 0 | CD16: =BU16/BU23 -> 0 | CE16: =BV16/BV23 -> 0 | CF16: =BW16/BW23 -> 0 | CH16: ICIFAC | CI16: 0.021221409 | CJ16: 0.022867107 | CK16: 0.021721345 | CL16: 0.021539277 | CM16: 0.01442956 | CN16: 0.016836106 | CO16: 0.014857848 | CP16: 0.018327423 | CQ16: 0.018986936 | CS16: ICAPH_ELC | CT16: 0 | CU16: 0 | CV16: 0.1904872 | CW16: 0.12902151 | CX16: 0.16302314 | CY16: 0.14209841 | CZ16: 0.49365022 | DA16: 0.098186775 | DB16: 0.06156758 | DC16: 1.2780348 | DE16: IFDOH_RFL | DF16: =LEFT(DE16,5) -> IFDOH | DG16: =GETPIVOTDATA("Sum of "&DG$1&" (Out)",$CS$6,"Constraint Identifier",$DE16) -> 0.026993181 | DH16: =GETPIVOTDATA("Sum of "&DH$1&" (Out)",$CS$6,"Constraint Identifier",$DE16) -> 0.074303146 | DI16: =GETPIVOTDATA("Sum of "&DI$1&" (Out)",$CS$6,"Constraint Identifier",$DE16) -> 0.060391636 | DJ16: =GETPIVOTDATA("Sum of "&DJ$1&" (Out)",$CS$6,"Constraint Identifier",$DE16) -> 0.040904691 | DK16: =GETPIVOTDATA("Sum of "&DK$1&" (Out)",$CS$6,"Constraint Identifier",$DE16) -> 0.041347594 | DL16: =GETPIVOTDATA("Sum of "&DL$1&" (Out)",$CS$6,"Constraint Identifier",$DE16) -> 0.03604045 | DM16: =GETPIVOTDATA("Sum of "&DM$1&" (Out)",$CS$6,"Constraint Identifier",$DE16) -> 0.12520461 | DN16: =GETPIVOTDATA("Sum of "&DN$1&" (Out)",$CS$6,"Constraint Identifier",$DE16) -> 0 | DO16: =GETPIVOTDATA("Sum of "&DO$1&" (Out)",$CS$6,"Constraint Identifier",$DE16) -> 0 | DP16: =IF(SUMIF($DF$8:$DF$380,"="&$DF16,DG$8:DG$380)=0,0,DG16/SUMIF($DF$8:$DF$380,"="&$DF16,DG$8:DG$380)) -> 0.046178652 | DQ16: =IF(SUMIF($DF$8:$DF$380,"="&$DF16,DH$8:DH$380)=0,0,DH16/SUMIF($DF$8:$DF$380,"="&$DF16,DH$8:DH$380)) -> 0.051100174 | DR16: =IF(SUMIF($DF$8:$DF$380,"="&$DF16,DI$8:DI$380)=0,0,DI16/SUMIF($DF$8:$DF$380,"="&$DF16,DI$8:DI$380)) -> 0.0046726286 | DS16: =IF(SUMIF($DF$8:$DF$380,"="&$DF16,DJ$8:DJ$380)=0,0,DJ16/SUMIF($DF$8:$DF$380,"="&$DF16,DJ$8:DJ$380)) -> 0.005344248 | DT16: =IF(SUMIF($DF$8:$DF$380,"="&$DF16,DK$8:DK$380)=0,0,DK16/SUMIF($DF$8:$DF$380,"="&$DF16,DK$8:DK$380)) -> 0.011941658 | DU16: =IF(SUMIF($DF$8:$DF$380,"="&$DF16,DL$8:DL$380)=0,0,DL16/SUMIF($DF$8:$DF$380,"="&$DF16,DL$8:DL$380)) -> 0.014750591 | DV16: =IF(SUMIF($DF$8:$DF$380,"="&$DF16,DM$8:DM$380)=0,0,DM16/SUMIF($DF$8:$DF$380,"="&$DF16,DM$8:DM$380)) -> 0.01221068 | DW16: =IF(SUMIF($DF$8:$DF$380,"="&$DF16,DN$8:DN$380)=0,0,DN16/SUMIF($DF$8:$DF$380,"="&$DF16,DN$8:DN$380)) -> 0 | DX16: =IF(SUMIF($DF$8:$DF$380,"="&$DF16,DO$8:DO$380)=0,0,DO16/SUMIF($DF$8:$DF$380,"="&$DF16,DO$8:DO$380)) -> 0 | DZ16: ICAPH_COA | EA16: 0 | EB16: 0 | EC16: 0 | ED16: 0 | EE16: 0.019987498 | EF16: 0.019987498 | EG16: 0.019987498 | EH16: 0 | EI16: 0 | EK16: epa.gov/sectors/pdf/energy/report.pdf | EO16: Agricultural Chemicals | EP16: R9 | EQ16: =GETPIVOTDATA("Sum of "&EP16&" (Out)",$AW$6,"Sub-Sector",EO16) -> 1.8615012 | ER16: =EQ16/SUM(EQ8:EQ16) -> 0.004564528 | ET16: R8 | EU16: 0.010363007 | EW16: Cement | EX16: INC | EY16: Facilities | EZ16: FAC | FA16: =EX16&EZ16 -> INCFAC | FB16: R2 | FC16: =GETPIVOTDATA("Sum of "&FB16&" (Out)",$AW$6,"Sub-Sector",EW16) -> 19.351306 | FD16: =GETPIVOTDATA("Sum of "&FB16&" (Out)",$AW$6,"Sub-Sector",EW16,"End-Use",EY16) -> 0.77616447 | FE16: =GETPIVOTDATA("Sum of "&FB16&" (%)",$CH$6,"End-Use Commodity",FA16) -> 0.040109153 | FF16: 0 | FG16: =FC16-((FD16-FF16)/FE16) -> 0 | FI16: IMO | FJ16: 0.35116661 | FK16: 0 | FL16: 0.41929072 | FM16: 0 | FN16: 0 | FO16: 0 | FP16: 0 | FQ16: 0 | FR16: 0 | FS16: 0.77045732
A17: Agricultural Chemicals | B17: Process Heat | C17: Natural Gas | D17: Natural Gas | E17: ICAEPRHNGA | F17: =EndUse(A17,B17,C17,G17) -> #NAME? | G17: TechData_OTR | H17: 1 | I17: 0 | J17: 7.7841651 | K17: 15.736899 | S17: 1 | T17: 1 | U17: 1 | V17: 1 | W17: 1 | X17: 1 | Y17: 1 | Z17: 1 | AA17: 1 | AB17: =J17*$H17*S17 -> 7.7841651 | AC17: =K17*$H17*T17 -> 15.736899 | AD17: =L17*$H17*U17 -> 0 | AE17: =M17*$H17*V17 -> 0 | AF17: =N17*$H17*W17 -> 0 | AG17: =O17*$H17*X17 -> 0 | AH17: =P17*$H17*Y17 -> 0 | AI17: =Q17*$H17*Z17 -> 0 | AJ17: =R17*$H17*AA17 -> 0 | AK17: =SUM(AB17:AJ17) -> 23.521064 | AL17: 0 | AM17: 0 | AN17: 0 | AO17: 0 | AP17: 0 | AQ17: 0 | AR17: 0 | AS17: 0 | AT17: 0 | AU17: 0 | AW17: Feedstock | AX17: 0 | AY17: 0 | AZ17: 0 | BA17: 0 | BB17: 0.23953094 | BC17: 0.2087861 | BD17: 0.72532342 | BE17: 0 | BF17: 0 | BG17: 1.1736405 | BH17: 0 | BJ17: Cement | BK17: INC | BL17: Facilities | BM17: FAC | BN17: =BK17&BM17 -> INCFAC | BO17: =IF(ISERROR(GETPIVOTDATA("Sum of "&BO$1&" (Out)",$AW$6,"Sub-Sector",$BJ17,"End-Use",$BL17)),0,GETPIVOTDATA("Sum of "&BO$1&" (Out)",$AW$6,"Sub-Sector",$BJ17,"End-Use",$BL17)) -> 0.28196852 | BP17: =IF(ISERROR(GETPIVOTDATA("Sum of "&BP$1&" (Out)",$AW$6,"Sub-Sector",$BJ17,"End-Use",$BL17)),0,GETPIVOTDATA("Sum of "&BP$1&" (Out)",$AW$6,"Sub-Sector",$BJ17,"End-Use",$BL17)) -> 0.77616447 | BQ17: =IF(ISERROR(GETPIVOTDATA("Sum of "&BQ$1&" (Out)",$AW$6,"Sub-Sector",$BJ17,"End-Use",$BL17)),0,GETPIVOTDATA("Sum of "&BQ$1&" (Out)",$AW$6,"Sub-Sector",$BJ17,"End-Use",$BL17)) -> 0.86095524 | BR17: =IF(ISERROR(GETPIVOTDATA("Sum of "&BR$1&" (Out)",$AW$6,"Sub-Sector",$BJ17,"End-Use",$BL17)),0,GETPIVOTDATA("Sum of "&BR$1&" (Out)",$AW$6,"Sub-Sector",$BJ17,"End-Use",$BL17)) -> 0.58314545 | BS17: =IF(ISERROR(GETPIVOTDATA("Sum of "&BS$1&" (Out)",$AW$6,"Sub-Sector",$BJ17,"End-Use",$BL17)),0,GETPIVOTDATA("Sum of "&BS$1&" (Out)",$AW$6,"Sub-Sector",$BJ17,"End-Use",$BL17)) -> 0.34724513 | BT17: =IF(ISERROR(GETPIVOTDATA("Sum of "&BT$1&" (Out)",$AW$6,"Sub-Sector",$BJ17,"End-Use",$BL17)),0,GETPIVOTDATA("Sum of "&BT$1&" (Out)",$AW$6,"Sub-Sector",$BJ17,"End-Use",$BL17)) -> 0.30267471 | BU17: =IF(ISERROR(GETPIVOTDATA("Sum of "&BU$1&" (Out)",$AW$6,"Sub-Sector",$BJ17,"End-Use",$BL17)),0,GETPIVOTDATA("Sum of "&BU$1&" (Out)",$AW$6,"Sub-Sector",$BJ17,"End-Use",$BL17)) -> 1.0514927 | BV17: =IF(ISERROR(GETPIVOTDATA("Sum of "&BV$1&" (Out)",$AW$6,"Sub-Sector",$BJ17,"End-Use",$BL17)),0,GETPIVOTDATA("Sum of "&BV$1&" (Out)",$AW$6,"Sub-Sector",$BJ17,"End-Use",$BL17)) -> 0.23721998 | BW17: =IF(ISERROR(GETPIVOTDATA("Sum of "&BW$1&" (Out)",$AW$6,"Sub-Sector",$BJ17,"End-Use",$BL17)),0,GETPIVOTDATA("Sum of "&BW$1&" (Out)",$AW$6,"Sub-Sector",$BJ17,"End-Use",$BL17)) -> 0.14874773 | BX17: =BO17/BO23 -> 0.055098917 | BY17: =BP17/BP23 -> 0.040109153 | BZ17: =BQ17/BQ23 -> 0.019789758 | CA17: =BR17/BR23 -> 0.019789758 | CB17: =BS17/BS23 -> 0.019138069 | CC17: =BT17/BT23 -> 0.019138069 | CD17: =BU17/BU23 -> 0.019138069 | CE17: =BV17/BV23 -> 0.0092077218 | CF17: =BW17/BW23 -> 0.0092077218 | CH17: ICIFEED | CI17: 0 | CJ17: 0 | CK17: 0.091575283 | CL17: 0.090807698 | CM17: 0.30963528 | CN17: 0.36127592 | CO17: 0.31882566 | CP17: 0.2505695 | CQ17: 0.25958625 | CS17: ICAPH_NGA | CT17: 0 | CU17: 0 | CV17: 11.492532 | CW17: 7.7841651 | CX17: 15.736899 | CY17: 13.717 | CZ17: 47.652889 | DA17: 1.3540193 | DB17: 0.84903177 | DC17: 98.586536 | DE17: IFDOH_COA | DF17: =LEFT(DE17,5) -> IFDOH | DG17: =GETPIVOTDATA("Sum of "&DG$1&" (Out)",$CS$6,"Constraint Identifier",$DE17) -> 0.0014201579 | DH17: =GETPIVOTDATA("Sum of "&DH$1&" (Out)",$CS$6,"Constraint Identifier",$DE17) -> 0.0039092168 | DI17: =GETPIVOTDATA("Sum of "&DI$1&" (Out)",$CS$6,"Constraint Identifier",$DE17) -> 0.4607097 | DJ17: =GETPIVOTDATA("Sum of "&DJ$1&" (Out)",$CS$6,"Constraint Identifier",$DE17) -> 0.31204963 | DK17: =GETPIVOTDATA("Sum of "&DK$1&" (Out)",$CS$6,"Constraint Identifier",$DE17) -> 0.017402946 | DL17: =GETPIVOTDATA("Sum of "&DL$1&" (Out)",$CS$6,"Constraint Identifier",$DE17) -> 0.015169203 | DM17: =GETPIVOTDATA("Sum of "&DM$1&" (Out)",$CS$6,"Constraint Identifier",$DE17) -> 0.052697846 | DN17: =GETPIVOTDATA("Sum of "&DN$1&" (Out)",$CS$6,"Constraint Identifier",$DE17) -> 0.06550984 | DO17: =GETPIVOTDATA("Sum of "&DO$1&" (Out)",$CS$6,"Constraint Identifier",$DE17) -> 0.041077653 | DP17: =IF(SUMIF($DF$8:$DF$380,"="&$DF17,DG$8:DG$380)=0,0,DG17/SUMIF($DF$8:$DF$380,"="&$DF17,DG$8:DG$380)) -> 0.0024295386 | DQ17: =IF(SUMIF($DF$8:$DF$380,"="&$DF17,DH$8:DH$380)=0,0,DH17/SUMIF($DF$8:$DF$380,"="&$DF17,DH$8:DH$380)) -> 0.0026884684 | DR17: =IF(SUMIF($DF$8:$DF$380,"="&$DF17,DI$8:DI$380)=0,0,DI17/SUMIF($DF$8:$DF$380,"="&$DF17,DI$8:DI$380)) -> 0.035646084 | DS17: =IF(SUMIF($DF$8:$DF$380,"="&$DF17,DJ$8:DJ$380)=0,0,DJ17/SUMIF($DF$8:$DF$380,"="&$DF17,DJ$8:DJ$380)) -> 0.040769667 | DT17: =IF(SUMIF($DF$8:$DF$380,"="&$DF17,DK$8:DK$380)=0,0,DK17/SUMIF($DF$8:$DF$380,"="&$DF17,DK$8:DK$380)) -> 0.0050261699 | DU17: =IF(SUMIF($DF$8:$DF$380,"="&$DF17,DL$8:DL$380)=0,0,DL17/SUMIF($DF$8:$DF$380,"="&$DF17,DL$8:DL$380)) -> 0.0062084323 | DV17: =IF(SUMIF($DF$8:$DF$380,"="&$DF17,DM$8:DM$380)=0,0,DM17/SUMIF($DF$8:$DF$380,"="&$DF17,DM$8:DM$380)) -> 0.0051393997 | DW17: =IF(SUMIF($DF$8:$DF$380,"="&$DF17,DN$8:DN$380)=0,0,DN17/SUMIF($DF$8:$DF$380,"="&$DF17,DN$8:DN$380)) -> 0.012610675 | DX17: =IF(SUMIF($DF$8:$DF$380,"="&$DF17,DO$8:DO$380)=0,0,DO17/SUMIF($DF$8:$DF$380,"="&$DF17,DO$8:DO$380)) -> 0.016598018 | DZ17: ICAPH_ELC | EA17: 0 | EB17: 0 | EC17: 0.016304621 | ED17: 0.016304621 | EE17: 0.010048145 | EF17: 0.010048145 | EG17: 0.010048145 | EH17: 0.06761215 | EI17: 0.06761215 | EO17: Cement | EP17: R1 | EQ17: =GETPIVOTDATA("Sum of "&EP17&" (Out)",$AW$6,"Sub-Sector",EO17) -> 5.1174965 | ER17: =EQ17/SUM(EQ17:EQ25) -> 0.022419521 | ET17: R9 | EU17: 0.004564528 | EW17: Cement | EX17: INC | EY17: Facilities | EZ17: FAC | FA17: =EX17&EZ17 -> INCFAC | FB17: R3 | FC17: =GETPIVOTDATA("Sum of "&FB17&" (Out)",$AW$6,"Sub-Sector",EW17) -> 43.505092 | FD17: =GETPIVOTDATA("Sum of "&FB17&" (Out)",$AW$6,"Sub-Sector",EW17,"End-Use",EY17) -> 0.86095524 | FE17: =GETPIVOTDATA("Sum of "&FB17&" (%)",$CH$6,"End-Use Commodity",FA17) -> 0.019789758 | FF17: 0 | FG17: =FC17-((FD17-FF17)/FE17) -> 0 | FI17: IMS | FJ17: 0 | FK17: 1.2620859 | FL17: 0.56694565 | FM17: 0.54892285 | FN17: 0 | FO17: 0 | FP17: 0.80530889 | FQ17: 0 | FR17: 0 | FS17: 3.1832633
A18: Agricultural Chemicals | B18: Process Heat | C18: Steam Coal | D18: Steam Coal | E18: ICAEPRHCOA | F18: =EndUse(A18,B18,C18,G18) -> #NAME? | G18: TechData_OTR | H18: 1 | I18: 0 | J18: 0 | K18: 0.32428122 | S18: 1 | T18: 1 | U18: 1 | V18: 1 | W18: 1 | X18: 1 | Y18: 1 | Z18: 1 | AA18: 1 | AB18: =J18*$H18*S18 -> 0 | AC18: =K18*$H18*T18 -> 0.32428122 | AD18: =L18*$H18*U18 -> 0 | AE18: =M18*$H18*V18 -> 0 | AF18: =N18*$H18*W18 -> 0 | AG18: =O18*$H18*X18 -> 0 | AH18: =P18*$H18*Y18 -> 0 | AI18: =Q18*$H18*Z18 -> 0 | AJ18: =R18*$H18*AA18 -> 0 | AK18: =SUM(AB18:AJ18) -> 0.32428122 | AL18: 0 | AM18: 0 | AN18: 0 | AO18: 0 | AP18: 0 | AQ18: 0 | AR18: 0 | AS18: 0 | AT18: 0 | AU18: 0 | AW18: Machine Drive | AX18: 0.56568417 | AY18: 1.5571382 | AZ18: 3.7968025 | BA18: 2.5716646 | BB18: 1.8774237 | BC18: 1.6364482 | BD18: 5.685025 | BE18: 2.6094197 | BF18: 1.636225 | BG18: 21.935831 | BH18: 0 | BJ18: Cement | BK18: INC | BL18: Feedstock | BM18: FEED | BN18: =BK18&BM18 -> INCFEED | BO18: =IF(ISERROR(GETPIVOTDATA("Sum of "&BO$1&" (Out)",$AW$6,"Sub-Sector",$BJ18,"End-Use",$BL18)),0,GETPIVOTDATA("Sum of "&BO$1&" (Out)",$AW$6,"Sub-Sector",$BJ18,"End-Use",$BL18)) -> 0 | BP18: =IF(ISERROR(GETPIVOTDATA("Sum of "&BP$1&" (Out)",$AW$6,"Sub-Sector",$BJ18,"End-Use",$BL18)),0,GETPIVOTDATA("Sum of "&BP$1&" (Out)",$AW$6,"Sub-Sector",$BJ18,"End-Use",$BL18)) -> 0 | BQ18: =IF(ISERROR(GETPIVOTDATA("Sum of "&BQ$1&" (Out)",$AW$6,"Sub-Sector",$BJ18,"End-Use",$BL18)),0,GETPIVOTDATA("Sum of "&BQ$1&" (Out)",$AW$6,"Sub-Sector",$BJ18,"End-Use",$BL18)) -> 0 | BR18: =IF(ISERROR(GETPIVOTDATA("Sum of "&BR$1&" (Out)",$AW$6,"Sub-Sector",$BJ18,"End-Use",$BL18)),0,GETPIVOTDATA("Sum of "&BR$1&" (Out)",$AW$6,"Sub-Sector",$BJ18,"End-Use",$BL18)) -> 0 | BS18: =IF(ISERROR(GETPIVOTDATA("Sum of "&BS$1&" (Out)",$AW$6,"Sub-Sector",$BJ18,"End-Use",$BL18)),0,GETPIVOTDATA("Sum of "&BS$1&" (Out)",$AW$6,"Sub-Sector",$BJ18,"End-Use",$BL18)) -> 0.23953094 | BT18: =IF(ISERROR(GETPIVOTDATA("Sum of "&BT$1&" (Out)",$AW$6,"Sub-Sector",$BJ18,"End-Use",$BL18)),0,GETPIVOTDATA("Sum of "&BT$1&" (Out)",$AW$6,"Sub-Sector",$BJ18,"End-Use",$BL18)) -> 0.2087861 | BU18: =IF(ISERROR(GETPIVOTDATA("Sum of "&BU$1&" (Out)",$AW$6,"Sub-Sector",$BJ18,"End-Use",$BL18)),0,GETPIVOTDATA("Sum of "&BU$1&" (Out)",$AW$6,"Sub-Sector",$BJ18,"End-Use",$BL18)) -> 0.72532342 | BV18: =IF(ISERROR(GETPIVOTDATA("Sum of "&BV$1&" (Out)",$AW$6,"Sub-Sector",$BJ18,"End-Use",$BL18)),0,GETPIVOTDATA("Sum of "&BV$1&" (Out)",$AW$6,"Sub-Sector",$BJ18,"End-Use",$BL18)) -> 0 | BW18: =IF(ISERROR(GETPIVOTDATA("Sum of "&BW$1&" (Out)",$AW$6,"Sub-Sector",$BJ18,"End-Use",$BL18)),0,GETPIVOTDATA("Sum of "&BW$1&" (Out)",$AW$6,"Sub-Sector",$BJ18,"End-Use",$BL18)) -> 0 | BX18: =BO18/BO23 -> 0 | BY18: =BP18/BP23 -> 0 | BZ18: =BQ18/BQ23 -> 0 | CA18: =BR18/BR23 -> 0 | CB18: =BS18/BS23 -> 0.013201509 | CC18: =BT18/BT23 -> 0.013201509 | CD18: =BU18/BU23 -> 0.013201509 | CE18: =BV18/BV23 -> 0 | CF18: =BW18/BW23 -> 0 | CH18: ICIMDR | CI18: 0.38493682 | CJ18: 0.41478828 | CK18: 0.39366447 | CL18: 0.39036477 | CM18: 0.26018529 | CN18: 0.30357871 | CO18: 0.26790792 | CP18: 0.33074365 | CQ18: 0.34264547 | CS18: ICAPH_COA | CT18: 0 | CU18: 0 | CV18: 0 | CW18: 0 | CX18: 0.32428122 | CY18: 0.28265832 | CZ18: 0.98195568 | DA18: 0 | DB18: 0 | DC18: 1.5888952 | DE18: INGOH_DST | DF18: =LEFT(DE18,5) -> INGOH | DG18: =GETPIVOTDATA("Sum of "&DG$1&" (Out)",$CS$6,"Constraint Identifier",$DE18) -> 1.3868583 | DH18: =GETPIVOTDATA("Sum of "&DH$1&" (Out)",$CS$6,"Constraint Identifier",$DE18) -> 3.8175544 | DI18: =GETPIVOTDATA("Sum of "&DI$1&" (Out)",$CS$6,"Constraint Identifier",$DE18) -> 5.5474437 | DJ18: =GETPIVOTDATA("Sum of "&DJ$1&" (Out)",$CS$6,"Constraint Identifier",$DE18) -> 3.7574155 | DK18: =GETPIVOTDATA("Sum of "&DK$1&" (Out)",$CS$6,"Constraint Identifier",$DE18) -> 2.3496718 | DL18: =GETPIVOTDATA("Sum of "&DL$1&" (Out)",$CS$6,"Constraint Identifier",$DE18) -> 2.0480812 | DM18: =GETPIVOTDATA("Sum of "&DM$1&" (Out)",$CS$6,"Constraint Identifier",$DE18) -> 7.1150389 | DN18: =GETPIVOTDATA("Sum of "&DN$1&" (Out)",$CS$6,"Constraint Identifier",$DE18) -> 2.6171092 | DO18: =GETPIVOTDATA("Sum of "&DO$1&" (Out)",$CS$6,"Constraint Identifier",$DE18) -> 1.6410467 | DP18: =IF(SUMIF($DF$8:$DF$380,"="&$DF18,DG$8:DG$380)=0,0,DG18/SUMIF($DF$8:$DF$380,"="&$DF18,DG$8:DG$380)) -> 0.43829122 | DQ18: =IF(SUMIF($DF$8:$DF$380,"="&$DF18,DH$8:DH$380)=0,0,DH18/SUMIF($DF$8:$DF$380,"="&$DF18,DH$8:DH$380)) -> 0.43829122 | DR18: =IF(SUMIF($DF$8:$DF$380,"="&$DF18,DI$8:DI$380)=0,0,DI18/SUMIF($DF$8:$DF$380,"="&$DF18,DI$8:DI$380)) -> 0.43881857 | DS18: =IF(SUMIF($DF$8:$DF$380,"="&$DF18,DJ$8:DJ$380)=0,0,DJ18/SUMIF($DF$8:$DF$380,"="&$DF18,DJ$8:DJ$380)) -> 0.43881857 | DT18: =IF(SUMIF($DF$8:$DF$380,"="&$DF18,DK$8:DK$380)=0,0,DK18/SUMIF($DF$8:$DF$380,"="&$DF18,DK$8:DK$380)) -> 0.43872254 | DU18: =IF(SUMIF($DF$8:$DF$380,"="&$DF18,DL$8:DL$380)=0,0,DL18/SUMIF($DF$8:$DF$380,"="&$DF18,DL$8:DL$380)) -> 0.43872254 | DV18: =IF(SUMIF($DF$8:$DF$380,"="&$DF18,DM$8:DM$380)=0,0,DM18/SUMIF($DF$8:$DF$380,"="&$DF18,DM$8:DM$380)) -> 0.43872254 | DW18: =IF(SUMIF($DF$8:$DF$380,"="&$DF18,DN$8:DN$380)=0,0,DN18/SUMIF($DF$8:$DF$380,"="&$DF18,DN$8:DN$380)) -> 0.43888153 | DX18: =IF(SUMIF($DF$8:$DF$380,"="&$DF18,DO$8:DO$380)=0,0,DO18/SUMIF($DF$8:$DF$380,"="&$DF18,DO$8:DO$380)) -> 0.43888153 | DZ18: ICAPH_NGA | EA18: 0 | EB18: 0 | EC18: 0.98369538 | ED18: 0.98369538 | EE18: 0.96996436 | EF18: 0.96996436 | EG18: 0.96996436 | EH18: 0.93238785 | EI18: 0.93238785 | EO18: Cement | EP18: R2 | EQ18: =GETPIVOTDATA("Sum of "&EP18&" (Out)",$AW$6,"Sub-Sector",EO18) -> 19.351306 | ER18: =EQ18/SUM(EQ17:EQ25) -> 0.084777194 | ET18: Cement | EU18: 1 | EW18: Cement | EX18: INC | EY18: Facilities | EZ18: FAC | FA18: =EX18&EZ18 -> INCFAC | FB18: R4 | FC18: =GETPIVOTDATA("Sum of "&FB18&" (Out)",$AW$6,"Sub-Sector",EW18) -> 29.467033 | FD18: =GETPIVOTDATA("Sum of "&FB18&" (Out)",$AW$6,"Sub-Sector",EW18,"End-Use",EY18) -> 0.58314545 | FE18: =GETPIVOTDATA("Sum of "&FB18&" (%)",$CH$6,"End-Use Commodity",FA18) -> 0.019789758 | FF18: 0 | FG18: =FC18-((FD18-FF18)/FE18) -> 0 | FI18: IMT | FJ18: 0 | FK18: 0 | FL18: 0 | FM18: 0 | FN18: 0 | FO18: 0 | FP18: 0 | FQ18: 0 | FR18: 0 | FS18: 0
A19: Agricultural Chemicals | B19: Steam | C19: Natural Gas | D19: Natural Gas | E19: ICAEBOLNGA | F19: =EndUse(A19,B19,C19,G19) -> #NAME? | G19: TechData_Boiler | H19: 1 | I19: 0 | J19: 2.654245 | K19: 2.9019252 | S19: #REF! | T19: =S19 -> #REF! | U19: =T19 -> #REF! | V19: =U19 -> #REF! | W19: =V19 -> #REF! | X19: =W19 -> #REF! | Y19: =X19 -> #REF! | Z19: =Y19 -> #REF! | AA19: =Z19 -> #REF! | AB19: =J19*$H19*S19 -> #REF! | AC19: =K19*$H19*T19 -> #REF! | AD19: =L19*$H19*U19 -> #REF! | AE19: =M19*$H19*V19 -> #REF! | AF19: =N19*$H19*W19 -> #REF! | AG19: =O19*$H19*X19 -> #REF! | AH19: =P19*$H19*Y19 -> #REF! | AI19: =Q19*$H19*Z19 -> #REF! | AJ19: =R19*$H19*AA19 -> #REF! | AK19: =SUM(AB19:AJ19) -> #REF! | AL19: 0 | AM19: 0 | AN19: 0 | AO19: 0 | AP19: 0 | AQ19: 0 | AR19: 0 | AS19: 0 | AT19: 0 | AU19: 0 | AW19: Other Heat | AX19: 0.16085723 | AY19: 5.7073451 | AZ19: 20.991304 | BA19: 14.21791 | BB19: 4.3115569 | BC19: 3.7581499 | BD19: 13.055822 | BE19: 4.3279936 | BF19: 2.7138491 | BG19: 69.244787 | BH19: 0 | BJ19: Cement | BK19: INC | BL19: Machine Drive | BM19: MDR | BN19: =BK19&BM19 -> INCMDR | BO19: =IF(ISERROR(GETPIVOTDATA("Sum of "&BO$1&" (Out)",$AW$6,"Sub-Sector",$BJ19,"End-Use",$BL19)),0,GETPIVOTDATA("Sum of "&BO$1&" (Out)",$AW$6,"Sub-Sector",$BJ19,"End-Use",$BL19)) -> 0.56568417 | BP19: =IF(ISERROR(GETPIVOTDATA("Sum of "&BP$1&" (Out)",$AW$6,"Sub-Sector",$BJ19,"End-Use",$BL19)),0,GETPIVOTDATA("Sum of "&BP$1&" (Out)",$AW$6,"Sub-Sector",$BJ19,"End-Use",$BL19)) -> 1.5571382 | BQ19: =IF(ISERROR(GETPIVOTDATA("Sum of "&BQ$1&" (Out)",$AW$6,"Sub-Sector",$BJ19,"End-Use",$BL19)),0,GETPIVOTDATA("Sum of "&BQ$1&" (Out)",$AW$6,"Sub-Sector",$BJ19,"End-Use",$BL19)) -> 3.7968025 | BR19: =IF(ISERROR(GETPIVOTDATA("Sum of "&BR$1&" (Out)",$AW$6,"Sub-Sector",$BJ19,"End-Use",$BL19)),0,GETPIVOTDATA("Sum of "&BR$1&" (Out)",$AW$6,"Sub-Sector",$BJ19,"End-Use",$BL19)) -> 2.5716646 | BS19: =IF(ISERROR(GETPIVOTDATA("Sum of "&BS$1&" (Out)",$AW$6,"Sub-Sector",$BJ19,"End-Use",$BL19)),0,GETPIVOTDATA("Sum of "&BS$1&" (Out)",$AW$6,"Sub-Sector",$BJ19,"End-Use",$BL19)) -> 1.8774237 | BT19: =IF(ISERROR(GETPIVOTDATA("Sum of "&BT$1&" (Out)",$AW$6,"Sub-Sector",$BJ19,"End-Use",$BL19)),0,GETPIVOTDATA("Sum of "&BT$1&" (Out)",$AW$6,"Sub-Sector",$BJ19,"End-Use",$BL19)) -> 1.6364482 | BU19: =IF(ISERROR(GETPIVOTDATA("Sum of "&BU$1&" (Out)",$AW$6,"Sub-Sector",$BJ19,"End-Use",$BL19)),0,GETPIVOTDATA("Sum of "&BU$1&" (Out)",$AW$6,"Sub-Sector",$BJ19,"End-Use",$BL19)) -> 5.685025 | BV19: =IF(ISERROR(GETPIVOTDATA("Sum of "&BV$1&" (Out)",$AW$6,"Sub-Sector",$BJ19,"End-Use",$BL19)),0,GETPIVOTDATA("Sum of "&BV$1&" (Out)",$AW$6,"Sub-Sector",$BJ19,"End-Use",$BL19)) -> 2.6094197 | BW19: =IF(ISERROR(GETPIVOTDATA("Sum of "&BW$1&" (Out)",$AW$6,"Sub-Sector",$BJ19,"End-Use",$BL19)),0,GETPIVOTDATA("Sum of "&BW$1&" (Out)",$AW$6,"Sub-Sector",$BJ19,"End-Use",$BL19)) -> 1.636225 | BX19: =BO19/BO23 -> 0.11053924 | BY19: =BP19/BP23 -> 0.08046683 | BZ19: =BQ19/BQ23 -> 0.087272601 | CA19: =BR19/BR23 -> 0.087272601 | CB19: =BS19/BS23 -> 0.10347234 | CC19: =BT19/BT23 -> 0.10347234 | CD19: =BU19/BU23 -> 0.10347234 | CE19: =BV19/BV23 -> 0.10128494 | CF19: =BW19/BW23 -> 0.10128494 | CH19: ICIOHT | CI19: 0.038442747 | CJ19: 0.041423943 | CK19: 0.18428345 | CL19: 0.18273878 | CM19: 0.02468131 | CN19: 0.028797632 | CO19: 0.025413883 | CP19: 0.024502374 | CQ19: 0.025384092 | CS19: ICAST_NGA | CT19: 0 | CU19: 0 | CV19: 0.92128435 | CW19: 9.6525691 | CX19: 0.91713298 | CY19: 1.002715 | CZ19: 5.7116436 | DA19: 1.2575452 | DB19: 0 | DC19: 19.46289 | DE19: INGOH_LPG | DF19: =LEFT(DE19,5) -> INGOH | DG19: =GETPIVOTDATA("Sum of "&DG$1&" (Out)",$CS$6,"Constraint Identifier",$DE19) -> 1.6596022 | DH19: =GETPIVOTDATA("Sum of "&DH$1&" (Out)",$CS$6,"Constraint Identifier",$DE19) -> 4.5683265 | DI19: =GETPIVOTDATA("Sum of "&DI$1&" (Out)",$CS$6,"Constraint Identifier",$DE19) -> 6.6384211 | DJ19: =GETPIVOTDATA("Sum of "&DJ$1&" (Out)",$CS$6,"Constraint Identifier",$DE19) -> 4.4963604 | DK19: =GETPIVOTDATA("Sum of "&DK$1&" (Out)",$CS$6,"Constraint Identifier",$DE19) -> 2.8117655 | DL19: =GETPIVOTDATA("Sum of "&DL$1&" (Out)",$CS$6,"Constraint Identifier",$DE19) -> 2.4508632 | DM19: =GETPIVOTDATA("Sum of "&DM$1&" (Out)",$CS$6,"Constraint Identifier",$DE19) -> 8.5143044 | DN19: =GETPIVOTDATA("Sum of "&DN$1&" (Out)",$CS$6,"Constraint Identifier",$DE19) -> 3.131798 | DO19: =GETPIVOTDATA("Sum of "&DO$1&" (Out)",$CS$6,"Constraint Identifier",$DE19) -> 1.96378 | DP19: =IF(SUMIF($DF$8:$DF$380,"="&$DF19,DG$8:DG$380)=0,0,DG19/SUMIF($DF$8:$DF$380,"="&$DF19,DG$8:DG$380)) -> 0.52448693 | DQ19: =IF(SUMIF($DF$8:$DF$380,"="&$DF19,DH$8:DH$380)=0,0,DH19/SUMIF($DF$8:$DF$380,"="&$DF19,DH$8:DH$380)) -> 0.52448693 | DR19: =IF(SUMIF($DF$8:$DF$380,"="&$DF19,DI$8:DI$380)=0,0,DI19/SUMIF($DF$8:$DF$380,"="&$DF19,DI$8:DI$380)) -> 0.52511798 | DS19: =IF(SUMIF($DF$8:$DF$380,"="&$DF19,DJ$8:DJ$380)=0,0,DJ19/SUMIF($DF$8:$DF$380,"="&$DF19,DJ$8:DJ$380)) -> 0.52511798 | DT19: =IF(SUMIF($DF$8:$DF$380,"="&$DF19,DK$8:DK$380)=0,0,DK19/SUMIF($DF$8:$DF$380,"="&$DF19,DK$8:DK$380)) -> 0.52500306 | DU19: =IF(SUMIF($DF$8:$DF$380,"="&$DF19,DL$8:DL$380)=0,0,DL19/SUMIF($DF$8:$DF$380,"="&$DF19,DL$8:DL$380)) -> 0.52500306 | DV19: =IF(SUMIF($DF$8:$DF$380,"="&$DF19,DM$8:DM$380)=0,0,DM19/SUMIF($DF$8:$DF$380,"="&$DF19,DM$8:DM$380)) -> 0.52500306 | DW19: =IF(SUMIF($DF$8:$DF$380,"="&$DF19,DN$8:DN$380)=0,0,DN19/SUMIF($DF$8:$DF$380,"="&$DF19,DN$8:DN$380)) -> 0.52519333 | DX19: =IF(SUMIF($DF$8:$DF$380,"="&$DF19,DO$8:DO$380)=0,0,DO19/SUMIF($DF$8:$DF$380,"="&$DF19,DO$8:DO$380)) -> 0.52519333 | DZ19: ICAST_CHP | EA19: 0 | EB19: 0 | EC19: 0 | ED19: 0 | EE19: 0 | EF19: 0.85527647 | EG19: 0.44897947 | EH19: 0 | EI19: 0 | EO19: Cement | EP19: R3 | EQ19: =GETPIVOTDATA("Sum of "&EP19&" (Out)",$AW$6,"Sub-Sector",EO19) -> 43.505092 | ER19: =EQ19/SUM(EQ17:EQ25) -> 0.19059384 | ET19: R1 | EU19: 0.022419521 | EW19: Cement | EX19: INC | EY19: Feedstock | EZ19: FEED | FA19: =EX19&EZ19 -> INCFEED | FB19: R5 | FC19: =GETPIVOTDATA("Sum of "&FB19&" (Out)",$AW$6,"Sub-Sector",EW19) -> 18.144209 | FD19: =GETPIVOTDATA("Sum of "&FB19&" (Out)",$AW$6,"Sub-Sector",EW19,"End-Use",EY19) -> 0.23953094 | FE19: =GETPIVOTDATA("Sum of "&FB19&" (%)",$CH$6,"End-Use Commodity",FA19) -> 0.013201509 | FF19: 0 | FG19: =FC19-((FD19-FF19)/FE19) -> 0 | FI19: INC | FJ19: 0 | FK19: 0 | FL19: 0 | FM19: 0 | FN19: 0 | FO19: 0 | FP19: 0 | FQ19: 0 | FR19: 0 | FS19: 0
A20: Agricultural Chemicals | B20: Steam | C20: Natural Gas | D20: Natural Gas | E20: ICAEBSANGA | F20: =EndUse(A20,B20,C20,G20) -> #NAME? | G20: TechData_CHP | H20: =1-I20 -> 0.91317837 | I20: 0.086821627 | J20: #REF! | K20: #REF! | S20: #REF! | T20: =S20 -> #REF! | U20: =T20 -> #REF! | V20: =U20 -> #REF! | W20: =V20 -> #REF! | X20: =W20 -> #REF! | Y20: =X20 -> #REF! | Z20: =Y20 -> #REF! | AA20: =Z20 -> #REF! | AB20: =J20*31.536*$H20*S20 -> #REF! | AC20: =K20*31.536*$H20*T20 -> #REF! | AD20: =L20*31.536*$H20*U20 -> #REF! | AE20: =M20*31.536*$H20*V20 -> #REF! | AF20: =N20*31.536*$H20*W20 -> #REF! | AG20: =O20*31.536*$H20*X20 -> #REF! | AH20: =P20*31.536*$H20*Y20 -> #REF! | AI20: =Q20*31.536*$H20*Z20 -> #REF! | AJ20: =R20*31.536*$H20*AA20 -> #REF! | AK20: =SUM(AB20:AJ20) -> #REF! | AL20: =J20*31.536*$I20*S20 -> #REF! | AM20: =K20*31.536*$I20*T20 -> #REF! | AN20: =L20*31.536*$I20*U20 -> #REF! | AO20: =M20*31.536*$I20*V20 -> #REF! | AP20: =N20*31.536*$I20*W20 -> #REF! | AQ20: =O20*31.536*$I20*X20 -> #REF! | AR20: =P20*31.536*$I20*Y20 -> #REF! | AS20: =Q20*31.536*$I20*Z20 -> #REF! | AT20: =R20*31.536*$I20*AA20 -> #REF! | AU20: =SUM(AL20:AT20) -> #REF! | AW20: Process Heat | AX20: 4.1089866 | AY20: 11.310658 | AZ20: 17.856029 | BA20: 12.094313 | BB20: 11.368452 | BC20: 9.9092619 | BD20: 34.424799 | BE20: 18.588523 | BF20: 11.65585 | BG20: 131.31687 | BH20: 0 | BJ20: Cement | BK20: INC | BL20: Other Heat | BM20: OHT | BN20: =BK20&BM20 -> INCOHT | BO20: =IF(ISERROR(GETPIVOTDATA("Sum of "&BO$1&" (Out)",$AW$6,"Sub-Sector",$BJ20,"End-Use",$BL20)),0,GETPIVOTDATA("Sum of "&BO$1&" (Out)",$AW$6,"Sub-Sector",$BJ20,"End-Use",$BL20)) -> 0.16085723 | BP20: =IF(ISERROR(GETPIVOTDATA("Sum of "&BP$1&" (Out)",$AW$6,"Sub-Sector",$BJ20,"End-Use",$BL20)),0,GETPIVOTDATA("Sum of "&BP$1&" (Out)",$AW$6,"Sub-Sector",$BJ20,"End-Use",$BL20)) -> 5.7073451 | BQ20: =IF(ISERROR(GETPIVOTDATA("Sum of "&BQ$1&" (Out)",$AW$6,"Sub-Sector",$BJ20,"End-Use",$BL20)),0,GETPIVOTDATA("Sum of "&BQ$1&" (Out)",$AW$6,"Sub-Sector",$BJ20,"End-Use",$BL20)) -> 20.991304 | BR20: =IF(ISERROR(GETPIVOTDATA("Sum of "&BR$1&" (Out)",$AW$6,"Sub-Sector",$BJ20,"End-Use",$BL20)),0,GETPIVOTDATA("Sum of "&BR$1&" (Out)",$AW$6,"Sub-Sector",$BJ20,"End-Use",$BL20)) -> 14.21791 | BS20: =IF(ISERROR(GETPIVOTDATA("Sum of "&BS$1&" (Out)",$AW$6,"Sub-Sector",$BJ20,"End-Use",$BL20)),0,GETPIVOTDATA("Sum of "&BS$1&" (Out)",$AW$6,"Sub-Sector",$BJ20,"End-Use",$BL20)) -> 4.3115569 | BT20: =IF(ISERROR(GETPIVOTDATA("Sum of "&BT$1&" (Out)",$AW$6,"Sub-Sector",$BJ20,"End-Use",$BL20)),0,GETPIVOTDATA("Sum of "&BT$1&" (Out)",$AW$6,"Sub-Sector",$BJ20,"End-Use",$BL20)) -> 3.7581499 | BU20: =IF(ISERROR(GETPIVOTDATA("Sum of "&BU$1&" (Out)",$AW$6,"Sub-Sector",$BJ20,"End-Use",$BL20)),0,GETPIVOTDATA("Sum of "&BU$1&" (Out)",$AW$6,"Sub-Sector",$BJ20,"End-Use",$BL20)) -> 13.055822 | BV20: =IF(ISERROR(GETPIVOTDATA("Sum of "&BV$1&" (Out)",$AW$6,"Sub-Sector",$BJ20,"End-Use",$BL20)),0,GETPIVOTDATA("Sum of "&BV$1&" (Out)",$AW$6,"Sub-Sector",$BJ20,"End-Use",$BL20)) -> 4.3279936 | BW20: =IF(ISERROR(GETPIVOTDATA("Sum of "&BW$1&" (Out)",$AW$6,"Sub-Sector",$BJ20,"End-Use",$BL20)),0,GETPIVOTDATA("Sum of "&BW$1&" (Out)",$AW$6,"Sub-Sector",$BJ20,"End-Use",$BL20)) -> 2.7138491 | BX20: =BO20/BO23 -> 0.031432797 | BY20: =BP20/BP23 -> 0.29493334 | BZ20: =BQ20/BQ23 -> 0.48250225 | CA20: =BR20/BR23 -> 0.48250225 | CB20: =BS20/BS23 -> 0.23762717 | CC20: =BT20/BT23 -> 0.23762717 | CD20: =BU20/BU23 -> 0.23762717 | CE20: =BV20/BV23 -> 0.16799159 | CF20: =BW20/BW23 -> 0.16799159 | CH20: ICIPRH | CI20: 0.23271582 | CJ20: 0.25076269 | CK20: 0.068110196 | CL20: 0.067539295 | CM20: 0.1067605 | CN20: 0.1245659 | CO20: 0.10992929 | CP20: 0.17050787 | CQ20: 0.1766436 | CS20: ICAST_CHP | CT20: 0 | CU20: 0 | CV20: 0 | CW20: 0 | CX20: 0 | CY20: 5.9257716 | CZ20: 4.6539296 | DA20: 0 | DB20: 0 | DC20: 10.579701 | DE20: INGOH_NGA | DF20: =LEFT(DE20,5) -> INGOH | DG20: =GETPIVOTDATA("Sum of "&DG$1&" (Out)",$CS$6,"Constraint Identifier",$DE20) -> 0.071136145 | DH20: =GETPIVOTDATA("Sum of "&DH$1&" (Out)",$CS$6,"Constraint Identifier",$DE20) -> 0.19581387 | DI20: =GETPIVOTDATA("Sum of "&DI$1&" (Out)",$CS$6,"Constraint Identifier",$DE20) -> 0.26933474 | DJ20: =GETPIVOTDATA("Sum of "&DJ$1&" (Out)",$CS$6,"Constraint Identifier",$DE20) -> 0.18242683 | DK20: =GETPIVOTDATA("Sum of "&DK$1&" (Out)",$CS$6,"Constraint Identifier",$DE20) -> 0.1152513 | DL20: =GETPIVOTDATA("Sum of "&DL$1&" (Out)",$CS$6,"Constraint Identifier",$DE20) -> 0.1004583 | DM20: =GETPIVOTDATA("Sum of "&DM$1&" (Out)",$CS$6,"Constraint Identifier",$DE20) -> 0.34899236 | DN20: =GETPIVOTDATA("Sum of "&DN$1&" (Out)",$CS$6,"Constraint Identifier",$DE20) -> 0.126208 | DO20: =GETPIVOTDATA("Sum of "&DO$1&" (Out)",$CS$6,"Constraint Identifier",$DE20) -> 0.079138166 | DP20: =IF(SUMIF($DF$8:$DF$380,"="&$DF20,DG$8:DG$380)=0,0,DG20/SUMIF($DF$8:$DF$380,"="&$DF20,DG$8:DG$380)) -> 0.022481278 | DQ20: =IF(SUMIF($DF$8:$DF$380,"="&$DF20,DH$8:DH$380)=0,0,DH20/SUMIF($DF$8:$DF$380,"="&$DF20,DH$8:DH$380)) -> 0.022481278 | DR20: =IF(SUMIF($DF$8:$DF$380,"="&$DF20,DI$8:DI$380)=0,0,DI20/SUMIF($DF$8:$DF$380,"="&$DF20,DI$8:DI$380)) -> 0.021305144 | DS20: =IF(SUMIF($DF$8:$DF$380,"="&$DF20,DJ$8:DJ$380)=0,0,DJ20/SUMIF($DF$8:$DF$380,"="&$DF20,DJ$8:DJ$380)) -> 0.021305144 | DT20: =IF(SUMIF($DF$8:$DF$380,"="&$DF20,DK$8:DK$380)=0,0,DK20/SUMIF($DF$8:$DF$380,"="&$DF20,DK$8:DK$380)) -> 0.021519322 | DU20: =IF(SUMIF($DF$8:$DF$380,"="&$DF20,DL$8:DL$380)=0,0,DL20/SUMIF($DF$8:$DF$380,"="&$DF20,DL$8:DL$380)) -> 0.021519322 | DV20: =IF(SUMIF($DF$8:$DF$380,"="&$DF20,DM$8:DM$380)=0,0,DM20/SUMIF($DF$8:$DF$380,"="&$DF20,DM$8:DM$380)) -> 0.021519322 | DW20: =IF(SUMIF($DF$8:$DF$380,"="&$DF20,DN$8:DN$380)=0,0,DN20/SUMIF($DF$8:$DF$380,"="&$DF20,DN$8:DN$380)) -> 0.021164711 | DX20: =IF(SUMIF($DF$8:$DF$380,"="&$DF20,DO$8:DO$380)=0,0,DO20/SUMIF($DF$8:$DF$380,"="&$DF20,DO$8:DO$380)) -> 0.021164711 | DZ20: ICAST_NGA | EA20: 0 | EB20: 0 | EC20: 1 | ED20: 1 | EE20: 1 | EF20: 0.14472353 | EG20: 0.55102053 | EH20: 1 | EI20: 0 | EO20: Cement | EP20: R4 | EQ20: =GETPIVOTDATA("Sum of "&EP20&" (Out)",$AW$6,"Sub-Sector",EO20) -> 29.467033 | ER20: =EQ20/SUM(EQ17:EQ25) -> 0.12909374 | ET20: R2 | EU20: 0.084777194 | EW20: Cement | EX20: INC | EY20: Feedstock | EZ20: FEED | FA20: =EX20&EZ20 -> INCFEED | FB20: R6 | FC20: =GETPIVOTDATA("Sum of "&FB20&" (Out)",$AW$6,"Sub-Sector",EW20) -> 15.815321 | FD20: =GETPIVOTDATA("Sum of "&FB20&" (Out)",$AW$6,"Sub-Sector",EW20,"End-Use",EY20) -> 0.2087861 | FE20: =GETPIVOTDATA("Sum of "&FB20&" (%)",$CH$6,"End-Use Commodity",FA20) -> 0.013201509 | FF20: 0 | FG20: =FC20-((FD20-FF20)/FE20) -> 0 | FI20: ING | FJ20: 0 | FK20: 0 | FL20: 0 | FM20: 0 | FN20: 0 | FO20: 0 | FP20: 0 | FQ20: 0 | FR20: 0 | FS20: 0
A21: Agricultural Chemicals | B21: Steam | C21: Natural Gas | D21: Natural Gas | E21: ICAEBSTNGA | F21: =EndUse(A21,B21,C21,G21) -> #NAME? | G21: TechData_CHP | H21: =1-I21 -> 0.91317837 | I21: 0.086821627 | J21: #REF! | K21: #REF! | S21: #REF! | T21: =S21 -> #REF! | U21: =T21 -> #REF! | V21: =U21 -> #REF! | W21: =V21 -> #REF! | X21: =W21 -> #REF! | Y21: =X21 -> #REF! | Z21: =Y21 -> #REF! | AA21: =Z21 -> #REF! | AB21: =J21*31.536*$H21*S21 -> #REF! | AC21: =K21*31.536*$H21*T21 -> #REF! | AD21: =L21*31.536*$H21*U21 -> #REF! | AE21: =M21*31.536*$H21*V21 -> #REF! | AF21: =N21*31.536*$H21*W21 -> #REF! | AG21: =O21*31.536*$H21*X21 -> #REF! | AH21: =P21*31.536*$H21*Y21 -> #REF! | AI21: =Q21*31.536*$H21*Z21 -> #REF! | AJ21: =R21*31.536*$H21*AA21 -> #REF! | AK21: =SUM(AB21:AJ21) -> #REF! | AL21: =J21*31.536*$I21*S21 -> #REF! | AM21: =K21*31.536*$I21*T21 -> #REF! | AN21: =L21*31.536*$I21*U21 -> #REF! | AO21: =M21*31.536*$I21*V21 -> #REF! | AP21: =N21*31.536*$I21*W21 -> #REF! | AQ21: =O21*31.536*$I21*X21 -> #REF! | AR21: =P21*31.536*$I21*Y21 -> #REF! | AS21: =Q21*31.536*$I21*Z21 -> #REF! | AT21: =R21*31.536*$I21*AA21 -> #REF! | AU21: =SUM(AL21:AT21) -> #REF! | AW21: Steam | AX21: 0 | AY21: 5.926564e-19 | AZ21: 2.0363211e-17 | BA21: 0 | BB21: 0 | BC21: 0 | BD21: 0 | BE21: 0 | BF21: 0 | BG21: 2.0955867e-17 | BH21: 2.2933893e-17 | BJ21: Cement | BK21: INC | BL21: Process Heat | BM21: PRH | BN21: =BK21&BM21 -> INCPRH | BO21: =IF(ISERROR(GETPIVOTDATA("Sum of "&BO$1&" (Out)",$AW$6,"Sub-Sector",$BJ21,"End-Use",$BL21)),0,GETPIVOTDATA("Sum of "&BO$1&" (Out)",$AW$6,"Sub-Sector",$BJ21,"End-Use",$BL21)) -> 4.1089866 | BP21: =IF(ISERROR(GETPIVOTDATA("Sum of "&BP$1&" (Out)",$AW$6,"Sub-Sector",$BJ21,"End-Use",$BL21)),0,GETPIVOTDATA("Sum of "&BP$1&" (Out)",$AW$6,"Sub-Sector",$BJ21,"End-Use",$BL21)) -> 11.310658 | BQ21: =IF(ISERROR(GETPIVOTDATA("Sum of "&BQ$1&" (Out)",$AW$6,"Sub-Sector",$BJ21,"End-Use",$BL21)),0,GETPIVOTDATA("Sum of "&BQ$1&" (Out)",$AW$6,"Sub-Sector",$BJ21,"End-Use",$BL21)) -> 17.856029 | BR21: =IF(ISERROR(GETPIVOTDATA("Sum of "&BR$1&" (Out)",$AW$6,"Sub-Sector",$BJ21,"End-Use",$BL21)),0,GETPIVOTDATA("Sum of "&BR$1&" (Out)",$AW$6,"Sub-Sector",$BJ21,"End-Use",$BL21)) -> 12.094313 | BS21: =IF(ISERROR(GETPIVOTDATA("Sum of "&BS$1&" (Out)",$AW$6,"Sub-Sector",$BJ21,"End-Use",$BL21)),0,GETPIVOTDATA("Sum of "&BS$1&" (Out)",$AW$6,"Sub-Sector",$BJ21,"End-Use",$BL21)) -> 11.368452 | BT21: =IF(ISERROR(GETPIVOTDATA("Sum of "&BT$1&" (Out)",$AW$6,"Sub-Sector",$BJ21,"End-Use",$BL21)),0,GETPIVOTDATA("Sum of "&BT$1&" (Out)",$AW$6,"Sub-Sector",$BJ21,"End-Use",$BL21)) -> 9.9092619 | BU21: =IF(ISERROR(GETPIVOTDATA("Sum of "&BU$1&" (Out)",$AW$6,"Sub-Sector",$BJ21,"End-Use",$BL21)),0,GETPIVOTDATA("Sum of "&BU$1&" (Out)",$AW$6,"Sub-Sector",$BJ21,"End-Use",$BL21)) -> 34.424799 | BV21: =IF(ISERROR(GETPIVOTDATA("Sum of "&BV$1&" (Out)",$AW$6,"Sub-Sector",$BJ21,"End-Use",$BL21)),0,GETPIVOTDATA("Sum of "&BV$1&" (Out)",$AW$6,"Sub-Sector",$BJ21,"End-Use",$BL21)) -> 18.588523 | BW21: =IF(ISERROR(GETPIVOTDATA("Sum of "&BW$1&" (Out)",$AW$6,"Sub-Sector",$BJ21,"End-Use",$BL21)),0,GETPIVOTDATA("Sum of "&BW$1&" (Out)",$AW$6,"Sub-Sector",$BJ21,"End-Use",$BL21)) -> 11.65585 | BX21: =BO21/BO23 -> 0.80292905 | BY21: =BP21/BP23 -> 0.58449068 | BZ21: =BQ21/BQ23 -> 0.4104354 | CA21: =BR21/BR23 -> 0.4104354 | CB21: =BS21/BS23 -> 0.62656092 | CC21: =BT21/BT23 -> 0.62656092 | CD21: =BU21/BU23 -> 0.62656092 | CE21: =BV21/BV23 -> 0.72151574 | CF21: =BW21/BW23 -> 0.72151574 | CH21: ICISTM | CI21: 0.11925065 | CJ21: 0.050949446 | CK21: 0.037531359 | CL21: 0.045598785 | CM21: 0.1692883 | CN21: 0.030743108 | CO21: 0.14463172 | CP21: 0.055142984 | CQ21: 0.021142281 | CS21: INCFA_DST | CT21: 0.23054269 | CU21: 0.63460645 | CV21: 0.51579137 | CW21: 0.34935776 | CX21: 0.17657025 | CY21: 0.15390669 | CZ21: 0.5346722 | DA21: 0 | DB21: 0 | DC21: 2.5954474 | DE21: INGOH_RFL | DF21: =LEFT(DE21,5) -> INGOH | DG21: =GETPIVOTDATA("Sum of "&DG$1&" (Out)",$CS$6,"Constraint Identifier",$DE21) -> 0.034664592 | DH21: =GETPIVOTDATA("Sum of "&DH$1&" (Out)",$CS$6,"Constraint Identifier",$DE21) -> 0.09541996 | DI21: =GETPIVOTDATA("Sum of "&DI$1&" (Out)",$CS$6,"Constraint Identifier",$DE21) -> 0.13865863 | DJ21: =GETPIVOTDATA("Sum of "&DJ$1&" (Out)",$CS$6,"Constraint Identifier",$DE21) -> 0.093916785 | DK21: =GETPIVOTDATA("Sum of "&DK$1&" (Out)",$CS$6,"Constraint Identifier",$DE21) -> 0.058730161 | DL21: =GETPIVOTDATA("Sum of "&DL$1&" (Out)",$CS$6,"Constraint Identifier",$DE21) -> 0.05119189 | DM21: =GETPIVOTDATA("Sum of "&DM$1&" (Out)",$CS$6,"Constraint Identifier",$DE21) -> 0.17784075 | DN21: =GETPIVOTDATA("Sum of "&DN$1&" (Out)",$CS$6,"Constraint Identifier",$DE21) -> 0.065414773 | DO21: =GETPIVOTDATA("Sum of "&DO$1&" (Out)",$CS$6,"Constraint Identifier",$DE21) -> 0.041018042 | DP21: =IF(SUMIF($DF$8:$DF$380,"="&$DF21,DG$8:DG$380)=0,0,DG21/SUMIF($DF$8:$DF$380,"="&$DF21,DG$8:DG$380)) -> 0.010955111 | DQ21: =IF(SUMIF($DF$8:$DF$380,"="&$DF21,DH$8:DH$380)=0,0,DH21/SUMIF($DF$8:$DF$380,"="&$DF21,DH$8:DH$380)) -> 0.010955111 | DR21: =IF(SUMIF($DF$8:$DF$380,"="&$DF21,DI$8:DI$380)=0,0,DI21/SUMIF($DF$8:$DF$380,"="&$DF21,DI$8:DI$380)) -> 0.010968292 | DS21: =IF(SUMIF($DF$8:$DF$380,"="&$DF21,DJ$8:DJ$380)=0,0,DJ21/SUMIF($DF$8:$DF$380,"="&$DF21,DJ$8:DJ$380)) -> 0.010968292 | DT21: =IF(SUMIF($DF$8:$DF$380,"="&$DF21,DK$8:DK$380)=0,0,DK21/SUMIF($DF$8:$DF$380,"="&$DF21,DK$8:DK$380)) -> 0.010965891 | DU21: =IF(SUMIF($DF$8:$DF$380,"="&$DF21,DL$8:DL$380)=0,0,DL21/SUMIF($DF$8:$DF$380,"="&$DF21,DL$8:DL$380)) -> 0.010965891 | DV21: =IF(SUMIF($DF$8:$DF$380,"="&$DF21,DM$8:DM$380)=0,0,DM21/SUMIF($DF$8:$DF$380,"="&$DF21,DM$8:DM$380)) -> 0.010965891 | DW21: =IF(SUMIF($DF$8:$DF$380,"="&$DF21,DN$8:DN$380)=0,0,DN21/SUMIF($DF$8:$DF$380,"="&$DF21,DN$8:DN$380)) -> 0.010969865 | DX21: =IF(SUMIF($DF$8:$DF$380,"="&$DF21,DO$8:DO$380)=0,0,DO21/SUMIF($DF$8:$DF$380,"="&$DF21,DO$8:DO$380)) -> 0.010969865 | DZ21: ICIFA_ELC | EA21: 0.95861943 | EB21: 0.95861943 | EC21: 0.93508898 | ED21: 0.93508898 | EE21: 0.79711203 | EF21: 0.79711203 | EG21: 0.79711203 | EH21: 0.81957077 | EI21: 0.81957077 | EO21: Cement | EP21: R5 | EQ21: =GETPIVOTDATA("Sum of "&EP21&" (Out)",$AW$6,"Sub-Sector",EO21) -> 18.144209 | ER21: =EQ21/SUM(EQ17:EQ25) -> 0.079488958 | ET21: R3 | EU21: 0.19059384 | EW21: Cement | EX21: INC | EY21: Feedstock | EZ21: FEED | FA21: =EX21&EZ21 -> INCFEED | FB21: R7 | FC21: =GETPIVOTDATA("Sum of "&FB21&" (Out)",$AW$6,"Sub-Sector",EW21) -> 54.942462 | FD21: =GETPIVOTDATA("Sum of "&FB21&" (Out)",$AW$6,"Sub-Sector",EW21,"End-Use",EY21) -> 0.72532342 | FE21: =GETPIVOTDATA("Sum of "&FB21&" (%)",$CH$6,"End-Use Commodity",FA21) -> 0.013201509 | FF21: 0 | FG21: =FC21-((FD21-FF21)/FE21) -> 0 | FI21: INO | FJ21: 0 | FK21: 0 | FL21: 0 | FM21: 0 | FN21: 0 | FO21: 0 | FP21: 0 | FQ21: 0 | FR21: 0 | FS21: 0
A22: Agricultural Chemicals | B22: Steam | C22: Natural Gas | D22: Natural Gas | E22: ICAECCTNGA | F22: =EndUse(A22,B22,C22,G22) -> #NAME? | G22: TechData_CHP | H22: =1-I22 -> 0.51728586 | I22: 0.48271414 | J22: 0 | K22: 0 | S22: #REF! | T22: =S22 -> #REF! | U22: =T22 -> #REF! | V22: =U22 -> #REF! | W22: =V22 -> #REF! | X22: =W22 -> #REF! | Y22: =X22 -> #REF! | Z22: =Y22 -> #REF! | AA22: =Z22 -> #REF! | AB22: =J22*31.536*$H22*S22 -> #REF! | AC22: =K22*31.536*$H22*T22 -> #REF! | AD22: =L22*31.536*$H22*U22 -> #REF! | AE22: =M22*31.536*$H22*V22 -> #REF! | AF22: =N22*31.536*$H22*W22 -> #REF! | AG22: =O22*31.536*$H22*X22 -> #REF! | AH22: =P22*31.536*$H22*Y22 -> #REF! | AI22: =Q22*31.536*$H22*Z22 -> #REF! | AJ22: =R22*31.536*$H22*AA22 -> #REF! | AK22: =SUM(AB22:AJ22) -> #REF! | AL22: =J22*31.536*$I22*S22 -> #REF! | AM22: =K22*31.536*$I22*T22 -> #REF! | AN22: =L22*31.536*$I22*U22 -> #REF! | AO22: =M22*31.536*$I22*V22 -> #REF! | AP22: =N22*31.536*$I22*W22 -> #REF! | AQ22: =O22*31.536*$I22*X22 -> #REF! | AR22: =P22*31.536*$I22*Y22 -> #REF! | AS22: =Q22*31.536*$I22*Z22 -> #REF! | AT22: =R22*31.536*$I22*AA22 -> #REF! | AU22: =SUM(AL22:AT22) -> #REF! | AW22: Food | AX22: 18.944491 | AY22: 50.907889 | AZ22: 259.95493 | BA22: 252.07575 | BB22: 89.953184 | BC22: 48.287695 | BD22: 115.92343 | BE22: 87.17097 | BF22: 97.77029 | BG22: 1020.9886 | BH22: 83.627933 | BJ22: Cement | BK22: INC | BL22: Steam | BM22: STM | BN22: =BK22&BM22 -> INCSTM | BO22: =IF(ISERROR(GETPIVOTDATA("Sum of "&BO$1&" (Out)",$AW$6,"Sub-Sector",$BJ22,"End-Use",$BL22)),0,GETPIVOTDATA("Sum of "&BO$1&" (Out)",$AW$6,"Sub-Sector",$BJ22,"End-Use",$BL22)) -> 0 | BP22: =IF(ISERROR(GETPIVOTDATA("Sum of "&BP$1&" (Out)",$AW$6,"Sub-Sector",$BJ22,"End-Use",$BL22)),0,GETPIVOTDATA("Sum of "&BP$1&" (Out)",$AW$6,"Sub-Sector",$BJ22,"End-Use",$BL22)) -> 5.926564e-19 | BQ22: =IF(ISERROR(GETPIVOTDATA("Sum of "&BQ$1&" (Out)",$AW$6,"Sub-Sector",$BJ22,"End-Use",$BL22)),0,GETPIVOTDATA("Sum of "&BQ$1&" (Out)",$AW$6,"Sub-Sector",$BJ22,"End-Use",$BL22)) -> 2.0363211e-17 | BR22: =IF(ISERROR(GETPIVOTDATA("Sum of "&BR$1&" (Out)",$AW$6,"Sub-Sector",$BJ22,"End-Use",$BL22)),0,GETPIVOTDATA("Sum of "&BR$1&" (Out)",$AW$6,"Sub-Sector",$BJ22,"End-Use",$BL22)) -> 0 | BS22: =IF(ISERROR(GETPIVOTDATA("Sum of "&BS$1&" (Out)",$AW$6,"Sub-Sector",$BJ22,"End-Use",$BL22)),0,GETPIVOTDATA("Sum of "&BS$1&" (Out)",$AW$6,"Sub-Sector",$BJ22,"End-Use",$BL22)) -> 0 | BT22: =IF(ISERROR(GETPIVOTDATA("Sum of "&BT$1&" (Out)",$AW$6,"Sub-Sector",$BJ22,"End-Use",$BL22)),0,GETPIVOTDATA("Sum of "&BT$1&" (Out)",$AW$6,"Sub-Sector",$BJ22,"End-Use",$BL22)) -> 0 | BU22: =IF(ISERROR(GETPIVOTDATA("Sum of "&BU$1&" (Out)",$AW$6,"Sub-Sector",$BJ22,"End-Use",$BL22)),0,GETPIVOTDATA("Sum of "&BU$1&" (Out)",$AW$6,"Sub-Sector",$BJ22,"End-Use",$BL22)) -> 0 | BV22: =IF(ISERROR(GETPIVOTDATA("Sum of "&BV$1&" (Out)",$AW$6,"Sub-Sector",$BJ22,"End-Use",$BL22)),0,GETPIVOTDATA("Sum of "&BV$1&" (Out)",$AW$6,"Sub-Sector",$BJ22,"End-Use",$BL22)) -> 0 | BW22: =IF(ISERROR(GETPIVOTDATA("Sum of "&BW$1&" (Out)",$AW$6,"Sub-Sector",$BJ22,"End-Use",$BL22)),0,GETPIVOTDATA("Sum of "&BW$1&" (Out)",$AW$6,"Sub-Sector",$BJ22,"End-Use",$BL22)) -> 0 | BX22: =BO22/BO23 -> 0 | BY22: =BP22/BP23 -> 3.0626171e-20 | BZ22: =BQ22/BQ23 -> 4.6806501e-19 | CA22: =BR22/BR23 -> 0 | CB22: =BS22/BS23 -> 0 | CC22: =BT22/BT23 -> 0 | CD22: =BU22/BU23 -> 0 | CE22: =BV22/BV23 -> 0 | CF22: =BW22/BW23 -> 0 | CH22: ICOETC | CI22: 0 | CJ22: 0 | CK22: 0 | CL22: 0 | CM22: 0 | CN22: 0 | CO22: 0 | CP22: 0 | CQ22: 0 | CS22: INCFA_ELC | CT22: 0.051425834 | CU22: 0.14155802 | CV22: 0.34516386 | CW22: 0.23378769 | CX22: 0.17067488 | CY22: 0.14876802 | CZ22: 0.51682046 | DA22: 0.23721998 | DB22: 0.14874773 | DC22: 1.9941665 | DE22: INGOH_COA | DF22: =LEFT(DE22,5) -> INGOH | DG22: =GETPIVOTDATA("Sum of "&DG$1&" (Out)",$CS$6,"Constraint Identifier",$DE22) -> 0.011978111 | DH22: =GETPIVOTDATA("Sum of "&DH$1&" (Out)",$CS$6,"Constraint Identifier",$DE22) -> 0.03297171 | DI22: =GETPIVOTDATA("Sum of "&DI$1&" (Out)",$CS$6,"Constraint Identifier",$DE22) -> 0.047912534 | DJ22: =GETPIVOTDATA("Sum of "&DJ$1&" (Out)",$CS$6,"Constraint Identifier",$DE22) -> 0.032452298 | DK22: =GETPIVOTDATA("Sum of "&DK$1&" (Out)",$CS$6,"Constraint Identifier",$DE22) -> 0.020293803 | DL22: =GETPIVOTDATA("Sum of "&DL$1&" (Out)",$CS$6,"Constraint Identifier",$DE22) -> 0.017689005 | DM22: =GETPIVOTDATA("Sum of "&DM$1&" (Out)",$CS$6,"Constraint Identifier",$DE22) -> 0.061451645 | DN22: =GETPIVOTDATA("Sum of "&DN$1&" (Out)",$CS$6,"Constraint Identifier",$DE22) -> 0.022603624 | DO22: =GETPIVOTDATA("Sum of "&DO$1&" (Out)",$CS$6,"Constraint Identifier",$DE22) -> 0.014173502 | DP22: =IF(SUMIF($DF$8:$DF$380,"="&$DF22,DG$8:DG$380)=0,0,DG22/SUMIF($DF$8:$DF$380,"="&$DF22,DG$8:DG$380)) -> 0.003785463 | DQ22: =IF(SUMIF($DF$8:$DF$380,"="&$DF22,DH$8:DH$380)=0,0,DH22/SUMIF($DF$8:$DF$380,"="&$DF22,DH$8:DH$380)) -> 0.003785463 | DR22: =IF(SUMIF($DF$8:$DF$380,"="&$DF22,DI$8:DI$380)=0,0,DI22/SUMIF($DF$8:$DF$380,"="&$DF22,DI$8:DI$380)) -> 0.0037900176 | DS22: =IF(SUMIF($DF$8:$DF$380,"="&$DF22,DJ$8:DJ$380)=0,0,DJ22/SUMIF($DF$8:$DF$380,"="&$DF22,DJ$8:DJ$380)) -> 0.0037900176 | DT22: =IF(SUMIF($DF$8:$DF$380,"="&$DF22,DK$8:DK$380)=0,0,DK22/SUMIF($DF$8:$DF$380,"="&$DF22,DK$8:DK$380)) -> 0.0037891882 | DU22: =IF(SUMIF($DF$8:$DF$380,"="&$DF22,DL$8:DL$380)=0,0,DL22/SUMIF($DF$8:$DF$380,"="&$DF22,DL$8:DL$380)) -> 0.0037891882 | DV22: =IF(SUMIF($DF$8:$DF$380,"="&$DF22,DM$8:DM$380)=0,0,DM22/SUMIF($DF$8:$DF$380,"="&$DF22,DM$8:DM$380)) -> 0.0037891882 | DW22: =IF(SUMIF($DF$8:$DF$380,"="&$DF22,DN$8:DN$380)=0,0,DN22/SUMIF($DF$8:$DF$380,"="&$DF22,DN$8:DN$380)) -> 0.0037905614 | DX22: =IF(SUMIF($DF$8:$DF$380,"="&$DF22,DO$8:DO$380)=0,0,DO22/SUMIF($DF$8:$DF$380,"="&$DF22,DO$8:DO$380)) -> 0.0037905614 | DZ22: ICIFA_NGA | EA22: 0.041380573 | EB22: 0.041380573 | EC22: 0.064911023 | ED22: 0.064911023 | EE22: 0.20288797 | EF22: 0.20288797 | EG22: 0.20288797 | EH22: 0.18042923 | EI22: 0.18042923 | EO22: Cement | EP22: R6 | EQ22: =GETPIVOTDATA("Sum of "&EP22&" (Out)",$AW$6,"Sub-Sector",EO22) -> 15.815321 | ER22: =EQ22/SUM(EQ17:EQ25) -> 0.069286205 | ET22: R4 | EU22: 0.12909374 | EW22: Cement | EX22: INC | EY22: Facilities | EZ22: FAC | FA22: =EX22&EZ22 -> INCFAC | FB22: R8 | FC22: =GETPIVOTDATA("Sum of "&FB22&" (Out)",$AW$6,"Sub-Sector",EW22) -> 25.763156 | FD22: =GETPIVOTDATA("Sum of "&FB22&" (Out)",$AW$6,"Sub-Sector",EW22,"End-Use",EY22) -> 0.23721998 | FE22: =GETPIVOTDATA("Sum of "&FB22&" (%)",$CH$6,"End-Use Commodity",FA22) -> 0.0092077218 | FF22: 0 | FG22: =FC22-((FD22-FF22)/FE22) -> 0 | FI22: IOT | FJ22: 4.1522669 | FK22: 0 | FL22: 0 | FM22: 1.86547 | FN22: 0.10425446 | FO22: 0 | FP22: 0 | FQ22: 0 | FR22: 0 | FS22: 6.1219913
A23: Agricultural Chemicals | B23: Steam | C23: Steam Coal | D23: Steam Coal | E23: ICAEBSTCOA | F23: =EndUse(A23,B23,C23,G23) -> #NAME? | G23: TechData_CHP | H23: =1-I23 -> 0.88332653 | I23: 0.11667347 | J23: #REF! | K23: #REF! | S23: #REF! | T23: =S23 -> #REF! | U23: =T23 -> #REF! | V23: =U23 -> #REF! | W23: =V23 -> #REF! | X23: =W23 -> #REF! | Y23: =X23 -> #REF! | Z23: =Y23 -> #REF! | AA23: =Z23 -> #REF! | AB23: =J23*31.536*$H23*S23 -> #REF! | AC23: =K23*31.536*$H23*T23 -> #REF! | AD23: =L23*31.536*$H23*U23 -> #REF! | AE23: =M23*31.536*$H23*V23 -> #REF! | AF23: =N23*31.536*$H23*W23 -> #REF! | AG23: =O23*31.536*$H23*X23 -> #REF! | AH23: =P23*31.536*$H23*Y23 -> #REF! | AI23: =Q23*31.536*$H23*Z23 -> #REF! | AJ23: =R23*31.536*$H23*AA23 -> #REF! | AK23: =SUM(AB23:AJ23) -> #REF! | AL23: =J23*31.536*$I23*S23 -> #REF! | AM23: =K23*31.536*$I23*T23 -> #REF! | AN23: =L23*31.536*$I23*U23 -> #REF! | AO23: =M23*31.536*$I23*V23 -> #REF! | AP23: =N23*31.536*$I23*W23 -> #REF! | AQ23: =O23*31.536*$I23*X23 -> #REF! | AR23: =P23*31.536*$I23*Y23 -> #REF! | AS23: =Q23*31.536*$I23*Z23 -> #REF! | AT23: =R23*31.536*$I23*AA23 -> #REF! | AU23: =SUM(AL23:AT23) -> #REF! | AW23: Electrochemical | AX23: 0.026212304 | AY23: 0.072153655 | AZ23: 0.27611826 | BA23: 0.18702146 | BB23: 0.066082616 | BC23: 0.057600625 | BD23: 0.20010471 | BE23: 0.10328036 | BF23: 0.064761489 | BG23: 1.0533355 | BH23: 0 | BJ23: Cement | BK23: INC | BL23: Total | BO23: =GETPIVOTDATA("Sum of "&BO$1&" (Out)",$AW$6,"Sub-Sector",$BJ23) -> 5.1174965 | BP23: =GETPIVOTDATA("Sum of "&BP$1&" (Out)",$AW$6,"Sub-Sector",$BJ23) -> 19.351306 | BQ23: =GETPIVOTDATA("Sum of "&BQ$1&" (Out)",$AW$6,"Sub-Sector",$BJ23) -> 43.505092 | BR23: =GETPIVOTDATA("Sum of "&BR$1&" (Out)",$AW$6,"Sub-Sector",$BJ23) -> 29.467033 | BS23: =GETPIVOTDATA("Sum of "&BS$1&" (Out)",$AW$6,"Sub-Sector",$BJ23) -> 18.144209 | BT23: =GETPIVOTDATA("Sum of "&BT$1&" (Out)",$AW$6,"Sub-Sector",$BJ23) -> 15.815321 | BU23: =GETPIVOTDATA("Sum of "&BU$1&" (Out)",$AW$6,"Sub-Sector",$BJ23) -> 54.942462 | BV23: =GETPIVOTDATA("Sum of "&BV$1&" (Out)",$AW$6,"Sub-Sector",$BJ23) -> 25.763156 | BW23: =GETPIVOTDATA("Sum of "&BW$1&" (Out)",$AW$6,"Sub-Sector",$BJ23) -> 16.154672 | CH23: ICOFAC | CI23: 0.04274319 | CJ23: 0.010264274 | CK23: 0.029566257 | CL23: 0.038615809 | CM23: 0.0043853511 | CN23: 0.0044571689 | CO23: 0.0041320765 | CP23: 0.033710171 | CQ23: 0.033865003 | CS23: INCFS_OTP | CT23: 0 | CU23: 0 | CV23: 0 | CW23: 0 | CX23: 0.024639776 | CY23: 0.021477154 | CZ23: 0.074611684 | DA23: 0 | DB23: 0 | DC23: 0.12072861 | DE23: ICIOH_ELC | DF23: =LEFT(DE23,5) -> ICIOH | DG23: =GETPIVOTDATA("Sum of "&DG$1&" (Out)",$CS$6,"Constraint Identifier",$DE23) -> 0.031637408 | DH23: =GETPIVOTDATA("Sum of "&DH$1&" (Out)",$CS$6,"Constraint Identifier",$DE23) -> 0.08708714 | DI23: =GETPIVOTDATA("Sum of "&DI$1&" (Out)",$CS$6,"Constraint Identifier",$DE23) -> 0.15405522 | DJ23: =GETPIVOTDATA("Sum of "&DJ$1&" (Out)",$CS$6,"Constraint Identifier",$DE23) -> 0.10434526 | DK23: =GETPIVOTDATA("Sum of "&DK$1&" (Out)",$CS$6,"Constraint Identifier",$DE23) -> 0.15821262 | DL23: =GETPIVOTDATA("Sum of "&DL$1&" (Out)",$CS$6,"Constraint Identifier",$DE23) -> 0.13790534 | DM23: =GETPIVOTDATA("Sum of "&DM$1&" (Out)",$CS$6,"Constraint Identifier",$DE23) -> 0.47908349 | DN23: =GETPIVOTDATA("Sum of "&DN$1&" (Out)",$CS$6,"Constraint Identifier",$DE23) -> 0.08584636 | DO23: =GETPIVOTDATA("Sum of "&DO$1&" (Out)",$CS$6,"Constraint Identifier",$DE23) -> 0.053829578 | DP23: =IF(SUMIF($DF$8:$DF$380,"="&$DF23,DG$8:DG$380)=0,0,DG23/SUMIF($DF$8:$DF$380,"="&$DF23,DG$8:DG$380)) -> 0.088197194 | DQ23: =IF(SUMIF($DF$8:$DF$380,"="&$DF23,DH$8:DH$380)=0,0,DH23/SUMIF($DF$8:$DF$380,"="&$DF23,DH$8:DH$380)) -> 0.088197194 | DR23: =IF(SUMIF($DF$8:$DF$380,"="&$DF23,DI$8:DI$380)=0,0,DI23/SUMIF($DF$8:$DF$380,"="&$DF23,DI$8:DI$380)) -> 0.018369701 | DS23: =IF(SUMIF($DF$8:$DF$380,"="&$DF23,DJ$8:DJ$380)=0,0,DJ23/SUMIF($DF$8:$DF$380,"="&$DF23,DJ$8:DJ$380)) -> 0.018369701 | DT23: =IF(SUMIF($DF$8:$DF$380,"="&$DF23,DK$8:DK$380)=0,0,DK23/SUMIF($DF$8:$DF$380,"="&$DF23,DK$8:DK$380)) -> 0.077669945 | DU23: =IF(SUMIF($DF$8:$DF$380,"="&$DF23,DL$8:DL$380)=0,0,DL23/SUMIF($DF$8:$DF$380,"="&$DF23,DL$8:DL$380)) -> 0.077669945 | DV23: =IF(SUMIF($DF$8:$DF$380,"="&$DF23,DM$8:DM$380)=0,0,DM23/SUMIF($DF$8:$DF$380,"="&$DF23,DM$8:DM$380)) -> 0.077669945 | DW23: =IF(SUMIF($DF$8:$DF$380,"="&$DF23,DN$8:DN$380)=0,0,DN23/SUMIF($DF$8:$DF$380,"="&$DF23,DN$8:DN$380)) -> 0.10217119 | DX23: =IF(SUMIF($DF$8:$DF$380,"="&$DF23,DO$8:DO$380)=0,0,DO23/SUMIF($DF$8:$DF$380,"="&$DF23,DO$8:DO$380)) -> 0.10217119 | DZ23: ICIFS_NGA | EA23: 0 | EB23: 0 | EC23: 0.80887689 | ED23: 0.80887689 | EE23: 0.95732117 | EF23: 0.95732117 | EG23: 0.95732117 | EH23: 0.80887689 | EI23: 0.80887689 | EO23: Cement | EP23: R7 | EQ23: =GETPIVOTDATA("Sum of "&EP23&" (Out)",$AW$6,"Sub-Sector",EO23) -> 54.942462 | ER23: =EQ23/SUM(EQ17:EQ25) -> 0.24070044 | ET23: R5 | EU23: 0.079488958 | EW23: Cement | EX23: INC | EY23: Facilities | EZ23: FAC | FA23: =EX23&EZ23 -> INCFAC | FB23: R9 | FC23: =GETPIVOTDATA("Sum of "&FB23&" (Out)",$AW$6,"Sub-Sector",EW23) -> 16.154672 | FD23: =GETPIVOTDATA("Sum of "&FB23&" (Out)",$AW$6,"Sub-Sector",EW23,"End-Use",EY23) -> 0.14874773 | FE23: =GETPIVOTDATA("Sum of "&FB23&" (%)",$CH$6,"End-Use Commodity",FA23) -> 0.0092077218 | FF23: 0 | FG23: =FC23-((FD23-FF23)/FE23) -> 0 | FI23: IPA | FJ23: 0 | FK23: 0 | FL23: 0 | FM23: 0 | FN23: 1.5173765 | FO23: 0 | FP23: 0 | FQ23: 0 | FR23: 0 | FS23: 1.5173765
A24: Cement | B24: Facilities | C24: Distillate Oil | D24: Distillate Oil | E24: INCEFACDST | F24: =EndUse(A24,B24,C24,G24) -> #NAME? | G24: TechData_OTR | H24: 1 | I24: 0 | J24: 0.34935776 | K24: 0.17657025 | S24: 1 | T24: 1 | U24: 1 | V24: 1 | W24: 1 | X24: 1 | Y24: 1 | Z24: 1 | AA24: 1 | AB24: =J24*$H24*S24 -> 0.34935776 | AC24: =K24*$H24*T24 -> 0.17657025 | AD24: =L24*$H24*U24 -> 0 | AE24: =M24*$H24*V24 -> 0 | AF24: =N24*$H24*W24 -> 0 | AG24: =O24*$H24*X24 -> 0 | AH24: =P24*$H24*Y24 -> 0 | AI24: =Q24*$H24*Z24 -> 0 | AJ24: =R24*$H24*AA24 -> 0 | AK24: =SUM(AB24:AJ24) -> 0.52592801 | AL24: 0 | AM24: 0 | AN24: 0 | AO24: 0 | AP24: 0 | AQ24: 0 | AR24: 0 | AS24: 0 | AT24: 0 | AU24: 0 | AW24: Facilities | AX24: 3.3063578 | AY24: 9.1012906 | AZ24: 30.53019 | BA24: 20.678824 | BB24: 7.0901482 | BC24: 6.1800969 | BD24: 21.469671 | BE24: 16.490795 | BF24: 10.34048 | BG24: 125.18785 | BH24: 0 | BJ24: Food | BK24: IFD | BL24: Electrochemical | BM24: ETC | BN24: =BK24&BM24 -> IFDETC | BO24: =IF(ISERROR(GETPIVOTDATA("Sum of "&BO$1&" (Out)",$AW$6,"Sub-Sector",$BJ24,"End-Use",$BL24)),0,GETPIVOTDATA("Sum of "&BO$1&" (Out)",$AW$6,"Sub-Sector",$BJ24,"End-Use",$BL24)) -> 0.026212304 | BP24: =IF(ISERROR(GETPIVOTDATA("Sum of "&BP$1&" (Out)",$AW$6,"Sub-Sector",$BJ24,"End-Use",$BL24)),0,GETPIVOTDATA("Sum of "&BP$1&" (Out)",$AW$6,"Sub-Sector",$BJ24,"End-Use",$BL24)) -> 0.072153655 | BQ24: =IF(ISERROR(GETPIVOTDATA("Sum of "&BQ$1&" (Out)",$AW$6,"Sub-Sector",$BJ24,"End-Use",$BL24)),0,GETPIVOTDATA("Sum of "&BQ$1&" (Out)",$AW$6,"Sub-Sector",$BJ24,"End-Use",$BL24)) -> 0.27611826 | BR24: =IF(ISERROR(GETPIVOTDATA("Sum of "&BR$1&" (Out)",$AW$6,"Sub-Sector",$BJ24,"End-Use",$BL24)),0,GETPIVOTDATA("Sum of "&BR$1&" (Out)",$AW$6,"Sub-Sector",$BJ24,"End-Use",$BL24)) -> 0.18702146 | BS24: =IF(ISERROR(GETPIVOTDATA("Sum of "&BS$1&" (Out)",$AW$6,"Sub-Sector",$BJ24,"End-Use",$BL24)),0,GETPIVOTDATA("Sum of "&BS$1&" (Out)",$AW$6,"Sub-Sector",$BJ24,"End-Use",$BL24)) -> 0.066082616 | BT24: =IF(ISERROR(GETPIVOTDATA("Sum of "&BT$1&" (Out)",$AW$6,"Sub-Sector",$BJ24,"End-Use",$BL24)),0,GETPIVOTDATA("Sum of "&BT$1&" (Out)",$AW$6,"Sub-Sector",$BJ24,"End-Use",$BL24)) -> 0.057600625 | BU24: =IF(ISERROR(GETPIVOTDATA("Sum of "&BU$1&" (Out)",$AW$6,"Sub-Sector",$BJ24,"End-Use",$BL24)),0,GETPIVOTDATA("Sum of "&BU$1&" (Out)",$AW$6,"Sub-Sector",$BJ24,"End-Use",$BL24)) -> 0.20010471 | BV24: =IF(ISERROR(GETPIVOTDATA("Sum of "&BV$1&" (Out)",$AW$6,"Sub-Sector",$BJ24,"End-Use",$BL24)),0,GETPIVOTDATA("Sum of "&BV$1&" (Out)",$AW$6,"Sub-Sector",$BJ24,"End-Use",$BL24)) -> 0.10328036 | BW24: =IF(ISERROR(GETPIVOTDATA("Sum of "&BW$1&" (Out)",$AW$6,"Sub-Sector",$BJ24,"End-Use",$BL24)),0,GETPIVOTDATA("Sum of "&BW$1&" (Out)",$AW$6,"Sub-Sector",$BJ24,"End-Use",$BL24)) -> 0.064761489 | BX24: =BO24/BO31 -> 0.0013836373 | BY24: =BP24/BP31 -> 0.0014173374 | BZ24: =BQ24/BQ31 -> 0.0010621774 | CA24: =BR24/BR31 -> 0.00074192565 | CB24: =BS24/BS31 -> 0.00073463343 | CC24: =BT24/BT31 -> 0.0011928634 | CD24: =BU24/BU31 -> 0.00172618 | CE24: =BV24/BV31 -> 0.0011848022 | CF24: =BW24/BW31 -> 0.00066238413 | CH24: ICOFEED | CI24: 0 | CJ24: 0 | CK24: 0.0062688844 | CL24: 0.0081876459 | CM24: 0.7902655 | CN24: 0.80320749 | CO24: 0.74462397 | CP24: 0.25939612 | CQ24: 0.26058754 | CS24: INCFS_PTC | CT24: 0 | CU24: 0 | CV24: 0 | CW24: 0 | CX24: 0.21489116 | CY24: 0.18730895 | CZ24: 0.65071174 | DA24: 0 | DB24: 0 | DC24: 1.0529119 | DE24: ICIOH_OTP | DF24: =LEFT(DE24,5) -> ICIOH | DG24: =GETPIVOTDATA("Sum of "&DG$1&" (Out)",$CS$6,"Constraint Identifier",$DE24) -> 0.32707477 | DH24: =GETPIVOTDATA("Sum of "&DH$1&" (Out)",$CS$6,"Constraint Identifier",$DE24) -> 0.90032681 | DI24: =GETPIVOTDATA("Sum of "&DI$1&" (Out)",$CS$6,"Constraint Identifier",$DE24) -> 8.232321 | DJ24: =GETPIVOTDATA("Sum of "&DJ$1&" (Out)",$CS$6,"Constraint Identifier",$DE24) -> 5.5759468 | DK24: =GETPIVOTDATA("Sum of "&DK$1&" (Out)",$CS$6,"Constraint Identifier",$DE24) -> 1.8787738 | DL24: =GETPIVOTDATA("Sum of "&DL$1&" (Out)",$CS$6,"Constraint Identifier",$DE24) -> 1.637625 | DM24: =GETPIVOTDATA("Sum of "&DM$1&" (Out)",$CS$6,"Constraint Identifier",$DE24) -> 5.6891131 | DN24: =GETPIVOTDATA("Sum of "&DN$1&" (Out)",$CS$6,"Constraint Identifier",$DE24) -> 0.75437445 | DO24: =GETPIVOTDATA("Sum of "&DO$1&" (Out)",$CS$6,"Constraint Identifier",$DE24) -> 0.47302714 | DP24: =IF(SUMIF($DF$8:$DF$380,"="&$DF24,DG$8:DG$380)=0,0,DG24/SUMIF($DF$8:$DF$380,"="&$DF24,DG$8:DG$380)) -> 0.91180281 | DQ24: =IF(SUMIF($DF$8:$DF$380,"="&$DF24,DH$8:DH$380)=0,0,DH24/SUMIF($DF$8:$DF$380,"="&$DF24,DH$8:DH$380)) -> 0.91180281 | DR24: =IF(SUMIF($DF$8:$DF$380,"="&$DF24,DI$8:DI$380)=0,0,DI24/SUMIF($DF$8:$DF$380,"="&$DF24,DI$8:DI$380)) -> 0.9816303 | DS24: =IF(SUMIF($DF$8:$DF$380,"="&$DF24,DJ$8:DJ$380)=0,0,DJ24/SUMIF($DF$8:$DF$380,"="&$DF24,DJ$8:DJ$380)) -> 0.9816303 | DT24: =IF(SUMIF($DF$8:$DF$380,"="&$DF24,DK$8:DK$380)=0,0,DK24/SUMIF($DF$8:$DF$380,"="&$DF24,DK$8:DK$380)) -> 0.92233005 | DU24: =IF(SUMIF($DF$8:$DF$380,"="&$DF24,DL$8:DL$380)=0,0,DL24/SUMIF($DF$8:$DF$380,"="&$DF24,DL$8:DL$380)) -> 0.92233005 | DV24: =IF(SUMIF($DF$8:$DF$380,"="&$DF24,DM$8:DM$380)=0,0,DM24/SUMIF($DF$8:$DF$380,"="&$DF24,DM$8:DM$380)) -> 0.92233005 | DW24: =IF(SUMIF($DF$8:$DF$380,"="&$DF24,DN$8:DN$380)=0,0,DN24/SUMIF($DF$8:$DF$380,"="&$DF24,DN$8:DN$380)) -> 0.89782881 | DX24: =IF(SUMIF($DF$8:$DF$380,"="&$DF24,DO$8:DO$380)=0,0,DO24/SUMIF($DF$8:$DF$380,"="&$DF24,DO$8:DO$380)) -> 0.89782881 | DZ24: ICIFS_PFS | EA24: 0 | EB24: 0 | EC24: 0.19112311 | ED24: 0.19112311 | EE24: 0.042678835 | EF24: 0.042678835 | EG24: 0.042678835 | EH24: 0.19112311 | EI24: 0.19112311 | EO24: Cement | EP24: R8 | EQ24: =GETPIVOTDATA("Sum of "&EP24&" (Out)",$AW$6,"Sub-Sector",EO24) -> 25.763156 | ER24: =EQ24/SUM(EQ17:EQ25) -> 0.11286722 | ET24: R6 | EU24: 0.069286205 | EW24: Food | EX24: IFD | EY24: Electrochemical | EZ24: ETC | FA24: =EX24&EZ24 -> IFDETC | FB24: R1 | FC24: =GETPIVOTDATA("Sum of "&FB24&" (Out)",$AW$6,"Sub-Sector",EW24) -> 18.944491 | FD24: =GETPIVOTDATA("Sum of "&FB24&" (Out)",$AW$6,"Sub-Sector",EW24,"End-Use",EY24) -> 0.026212304 | FE24: =GETPIVOTDATA("Sum of "&FB24&" (%)",$CH$6,"End-Use Commodity",FA24) -> 0.0013836373 | FF24: 0 | FG24: =FC24-((FD24-FF24)/FE24) -> 0 | FI24: IPB | FJ24: 0 | FK24: 0 | FL24: 0 | FM24: 0 | FN24: 0.45095911 | FO24: 2.013865 | FP24: 0 | FQ24: 0 | FR24: 0 | FS24: 2.4648241
A25: Cement | B25: Facilities | C25: Electricity | D25: Electricity | E25: INCEFACELC | F25: =EndUse(A25,B25,C25,G25) -> #NAME? | G25: TechData_OTR | H25: 1 | I25: 0 | J25: 0.23378769 | K25: 0.17067488 | S25: 1 | T25: 1 | U25: 1 | V25: 1 | W25: 1 | X25: 1 | Y25: 1 | Z25: 1 | AA25: 1 | AB25: =J25*$H25*S25 -> 0.23378769 | AC25: =K25*$H25*T25 -> 0.17067488 | AD25: =L25*$H25*U25 -> 0 | AE25: =M25*$H25*V25 -> 0 | AF25: =N25*$H25*W25 -> 0 | AG25: =O25*$H25*X25 -> 0 | AH25: =P25*$H25*Y25 -> 0 | AI25: =Q25*$H25*Z25 -> 0 | AJ25: =R25*$H25*AA25 -> 0 | AK25: =SUM(AB25:AJ25) -> 0.40446257 | AL25: 0 | AM25: 0 | AN25: 0 | AO25: 0 | AP25: 0 | AQ25: 0 | AR25: 0 | AS25: 0 | AT25: 0 | AU25: 0 | AW25: Feedstock | AX25: 0 | AY25: 0 | AZ25: 2.5311191 | BA25: 1.7143872 | BB25: 0 | BC25: 0 | BD25: 0 | BE25: 0.76282474 | BF25: 0.47832586 | BG25: 5.4866569 | BH25: 0 | BJ25: Food | BK25: IFD | BL25: Facilities | BM25: FAC | BN25: =BK25&BM25 -> IFDFAC | BO25: =IF(ISERROR(GETPIVOTDATA("Sum of "&BO$1&" (Out)",$AW$6,"Sub-Sector",$BJ25,"End-Use",$BL25)),0,GETPIVOTDATA("Sum of "&BO$1&" (Out)",$AW$6,"Sub-Sector",$BJ25,"End-Use",$BL25)) -> 3.3063578 | BP25: =IF(ISERROR(GETPIVOTDATA("Sum of "&BP$1&" (Out)",$AW$6,"Sub-Sector",$BJ25,"End-Use",$BL25)),0,GETPIVOTDATA("Sum of "&BP$1&" (Out)",$AW$6,"Sub-Sector",$BJ25,"End-Use",$BL25)) -> 9.1012906 | BQ25: =IF(ISERROR(GETPIVOTDATA("Sum of "&BQ$1&" (Out)",$AW$6,"Sub-Sector",$BJ25,"End-Use",$BL25)),0,GETPIVOTDATA("Sum of "&BQ$1&" (Out)",$AW$6,"Sub-Sector",$BJ25,"End-Use",$BL25)) -> 30.53019 | BR25: =IF(ISERROR(GETPIVOTDATA("Sum of "&BR$1&" (Out)",$AW$6,"Sub-Sector",$BJ25,"End-Use",$BL25)),0,GETPIVOTDATA("Sum of "&BR$1&" (Out)",$AW$6,"Sub-Sector",$BJ25,"End-Use",$BL25)) -> 20.678824 | BS25: =IF(ISERROR(GETPIVOTDATA("Sum of "&BS$1&" (Out)",$AW$6,"Sub-Sector",$BJ25,"End-Use",$BL25)),0,GETPIVOTDATA("Sum of "&BS$1&" (Out)",$AW$6,"Sub-Sector",$BJ25,"End-Use",$BL25)) -> 7.0901482 | BT25: =IF(ISERROR(GETPIVOTDATA("Sum of "&BT$1&" (Out)",$AW$6,"Sub-Sector",$BJ25,"End-Use",$BL25)),0,GETPIVOTDATA("Sum of "&BT$1&" (Out)",$AW$6,"Sub-Sector",$BJ25,"End-Use",$BL25)) -> 6.1800969 | BU25: =IF(ISERROR(GETPIVOTDATA("Sum of "&BU$1&" (Out)",$AW$6,"Sub-Sector",$BJ25,"End-Use",$BL25)),0,GETPIVOTDATA("Sum of "&BU$1&" (Out)",$AW$6,"Sub-Sector",$BJ25,"End-Use",$BL25)) -> 21.469671 | BV25: =IF(ISERROR(GETPIVOTDATA("Sum of "&BV$1&" (Out)",$AW$6,"Sub-Sector",$BJ25,"End-Use",$BL25)),0,GETPIVOTDATA("Sum of "&BV$1&" (Out)",$AW$6,"Sub-Sector",$BJ25,"End-Use",$BL25)) -> 16.490795 | BW25: =IF(ISERROR(GETPIVOTDATA("Sum of "&BW$1&" (Out)",$AW$6,"Sub-Sector",$BJ25,"End-Use",$BL25)),0,GETPIVOTDATA("Sum of "&BW$1&" (Out)",$AW$6,"Sub-Sector",$BJ25,"End-Use",$BL25)) -> 10.34048 | BX25: =BO25/BO31 -> 0.17452872 | BY25: =BP25/BP31 -> 0.17877957 | BZ25: =BQ25/BQ31 -> 0.11744417 | CA25: =BR25/BR31 -> 0.082034165 | CB25: =BS25/BS31 -> 0.078820425 | CC25: =BT25/BT31 -> 0.12798492 | CD25: =BU25/BU31 -> 0.18520562 | CE25: =BV25/BV31 -> 0.1891776 | CF25: =BW25/BW31 -> 0.105763 | CH25: ICOMDR | CI25: 0.26964966 | CJ25: 0.064753195 | CK25: 0.1870351 | CL25: 0.24428225 | CM25: 0.024579751 | CN25: 0.024982288 | CO25: 0.023160155 | CP25: 0.22682508 | CQ25: 0.22786689 | CS25: INCMD_ELC | CT25: 0.56568417 | CU25: 1.5571382 | CV25: 3.7968025 | CW25: 2.5716646 | CX25: 1.8774237 | CY25: 1.6364482 | CZ25: 5.685025 | DA25: 2.6094197 | DB25: 1.636225 | DC25: 21.935831 | DE25: ICOOH_DST | DF25: =LEFT(DE25,5) -> ICOOH | DG25: =GETPIVOTDATA("Sum of "&DG$1&" (Out)",$CS$6,"Constraint Identifier",$DE25) -> 0 | DH25: =GETPIVOTDATA("Sum of "&DH$1&" (Out)",$CS$6,"Constraint Identifier",$DE25) -> 0 | DI25: =GETPIVOTDATA("Sum of "&DI$1&" (Out)",$CS$6,"Constraint Identifier",$DE25) -> 0 | DJ25: =GETPIVOTDATA("Sum of "&DJ$1&" (Out)",$CS$6,"Constraint Identifier",$DE25) -> 0 | DK25: =GETPIVOTDATA("Sum of "&DK$1&" (Out)",$CS$6,"Constraint Identifier",$DE25) -> 2.6967092 | DL25: =GETPIVOTDATA("Sum of "&DL$1&" (Out)",$CS$6,"Constraint Identifier",$DE25) -> 2.3505749 | DM25: =GETPIVOTDATA("Sum of "&DM$1&" (Out)",$CS$6,"Constraint Identifier",$DE25) -> 8.1659027 | DN25: =GETPIVOTDATA("Sum of "&DN$1&" (Out)",$CS$6,"Constraint Identifier",$DE25) -> 0 | DO25: =GETPIVOTDATA("Sum of "&DO$1&" (Out)",$CS$6,"Constraint Identifier",$DE25) -> 0 | DP25: =IF(SUMIF($DF$8:$DF$380,"="&$DF25,DG$8:DG$380)=0,0,DG25/SUMIF($DF$8:$DF$380,"="&$DF25,DG$8:DG$380)) -> 0 | DQ25: =IF(SUMIF($DF$8:$DF$380,"="&$DF25,DH$8:DH$380)=0,0,DH25/SUMIF($DF$8:$DF$380,"="&$DF25,DH$8:DH$380)) -> 0 | DR25: =IF(SUMIF($DF$8:$DF$380,"="&$DF25,DI$8:DI$380)=0,0,DI25/SUMIF($DF$8:$DF$380,"="&$DF25,DI$8:DI$380)) -> 0 | DS25: =IF(SUMIF($DF$8:$DF$380,"="&$DF25,DJ$8:DJ$380)=0,0,DJ25/SUMIF($DF$8:$DF$380,"="&$DF25,DJ$8:DJ$380)) -> 0 | DT25: =IF(SUMIF($DF$8:$DF$380,"="&$DF25,DK$8:DK$380)=0,0,DK25/SUMIF($DF$8:$DF$380,"="&$DF25,DK$8:DK$380)) -> 0.078073693 | DU25: =IF(SUMIF($DF$8:$DF$380,"="&$DF25,DL$8:DL$380)=0,0,DL25/SUMIF($DF$8:$DF$380,"="&$DF25,DL$8:DL$380)) -> 0.078073693 | DV25: =IF(SUMIF($DF$8:$DF$380,"="&$DF25,DM$8:DM$380)=0,0,DM25/SUMIF($DF$8:$DF$380,"="&$DF25,DM$8:DM$380)) -> 0.078073693 | DW25: =IF(SUMIF($DF$8:$DF$380,"="&$DF25,DN$8:DN$380)=0,0,DN25/SUMIF($DF$8:$DF$380,"="&$DF25,DN$8:DN$380)) -> 0 | DX25: =IF(SUMIF($DF$8:$DF$380,"="&$DF25,DO$8:DO$380)=0,0,DO25/SUMIF($DF$8:$DF$380,"="&$DF25,DO$8:DO$380)) -> 0 | DZ25: ICIMD_ELC | EA25: 0.96007736 | EB25: 0.96007736 | EC25: 0.93732173 | ED25: 0.93732173 | EE25: 0.80309139 | EF25: 0.80309139 | EG25: 0.80309139 | EH25: 0.82503352 | EI25: 0.82503352 | EO25: Cement | EP25: R9 | EQ25: =GETPIVOTDATA("Sum of "&EP25&" (Out)",$AW$6,"Sub-Sector",EO25) -> 16.154672 | ER25: =EQ25/SUM(EQ17:EQ25) -> 0.070772888 | ET25: R7 | EU25: 0.24070044 | EW25: Food | EX25: IFD | EY25: Electrochemical | EZ25: ETC | FA25: =EX25&EZ25 -> IFDETC | FB25: R2 | FC25: =GETPIVOTDATA("Sum of "&FB25&" (Out)",$AW$6,"Sub-Sector",EW25) -> 50.907889 | FD25: =GETPIVOTDATA("Sum of "&FB25&" (Out)",$AW$6,"Sub-Sector",EW25,"End-Use",EY25) -> 0.072153655 | FE25: =GETPIVOTDATA("Sum of "&FB25&" (%)",$CH$6,"End-Use Commodity",FA25) -> 0.0014173374 | FF25: 0 | FG25: =FC25-((FD25-FF25)/FE25) -> 0 | FI25: IPL | FJ25: 0 | FK25: 0 | FL25: 0 | FM25: 0 | FN25: 0 | FO25: 0 | FP25: 0 | FQ25: 0 | FR25: 0 | FS25: 0
A26: Cement | B26: Feedstock | C26: Other Petroleum | D26: Other Petroleum | E26: INCEFEDOTP | F26: =EndUse(A26,B26,C26,G26) -> #NAME? | G26: TechData_OTR | H26: 1 | I26: 0 | J26: 0 | K26: 0.024639776 | S26: 1 | T26: 1 | U26: 1 | V26: 1 | W26: 1 | X26: 1 | Y26: 1 | Z26: 1 | AA26: 1 | AB26: =J26*$H26*S26 -> 0 | AC26: =K26*$H26*T26 -> 0.024639776 | AD26: =L26*$H26*U26 -> 0 | AE26: =M26*$H26*V26 -> 0 | AF26: =N26*$H26*W26 -> 0 | AG26: =O26*$H26*X26 -> 0 | AH26: =P26*$H26*Y26 -> 0 | AI26: =Q26*$H26*Z26 -> 0 | AJ26: =R26*$H26*AA26 -> 0 | AK26: =SUM(AB26:AJ26) -> 0.024639776 | AL26: 0 | AM26: 0 | AN26: 0 | AO26: 0 | AP26: 0 | AQ26: 0 | AR26: 0 | AS26: 0 | AT26: 0 | AU26: 0 | AW26: Machine Drive | AX26: 4.7716846 | AY26: 13.134842 | AZ26: 49.92415 | BA26: 33.814814 | BB26: 11.9067 | BC26: 10.378423 | BD26: 36.054667 | BE26: 19.164635 | BF26: 12.017099 | BG26: 191.16701 | BH26: 0 | BJ26: Food | BK26: IFD | BL26: Feedstock | BM26: FEED | BN26: =BK26&BM26 -> IFDFEED | BO26: =IF(ISERROR(GETPIVOTDATA("Sum of "&BO$1&" (Out)",$AW$6,"Sub-Sector",$BJ26,"End-Use",$BL26)),0,GETPIVOTDATA("Sum of "&BO$1&" (Out)",$AW$6,"Sub-Sector",$BJ26,"End-Use",$BL26)) -> 0 | BP26: =IF(ISERROR(GETPIVOTDATA("Sum of "&BP$1&" (Out)",$AW$6,"Sub-Sector",$BJ26,"End-Use",$BL26)),0,GETPIVOTDATA("Sum of "&BP$1&" (Out)",$AW$6,"Sub-Sector",$BJ26,"End-Use",$BL26)) -> 0 | BQ26: =IF(ISERROR(GETPIVOTDATA("Sum of "&BQ$1&" (Out)",$AW$6,"Sub-Sector",$BJ26,"End-Use",$BL26)),0,GETPIVOTDATA("Sum of "&BQ$1&" (Out)",$AW$6,"Sub-Sector",$BJ26,"End-Use",$BL26)) -> 2.5311191 | BR26: =IF(ISERROR(GETPIVOTDATA("Sum of "&BR$1&" (Out)",$AW$6,"Sub-Sector",$BJ26,"End-Use",$BL26)),0,GETPIVOTDATA("Sum of "&BR$1&" (Out)",$AW$6,"Sub-Sector",$BJ26,"End-Use",$BL26)) -> 1.7143872 | BS26: =IF(ISERROR(GETPIVOTDATA("Sum of "&BS$1&" (Out)",$AW$6,"Sub-Sector",$BJ26,"End-Use",$BL26)),0,GETPIVOTDATA("Sum of "&BS$1&" (Out)",$AW$6,"Sub-Sector",$BJ26,"End-Use",$BL26)) -> 0 | BT26: =IF(ISERROR(GETPIVOTDATA("Sum of "&BT$1&" (Out)",$AW$6,"Sub-Sector",$BJ26,"End-Use",$BL26)),0,GETPIVOTDATA("Sum of "&BT$1&" (Out)",$AW$6,"Sub-Sector",$BJ26,"End-Use",$BL26)) -> 0 | BU26: =IF(ISERROR(GETPIVOTDATA("Sum of "&BU$1&" (Out)",$AW$6,"Sub-Sector",$BJ26,"End-Use",$BL26)),0,GETPIVOTDATA("Sum of "&BU$1&" (Out)",$AW$6,"Sub-Sector",$BJ26,"End-Use",$BL26)) -> 0 | BV26: =IF(ISERROR(GETPIVOTDATA("Sum of "&BV$1&" (Out)",$AW$6,"Sub-Sector",$BJ26,"End-Use",$BL26)),0,GETPIVOTDATA("Sum of "&BV$1&" (Out)",$AW$6,"Sub-Sector",$BJ26,"End-Use",$BL26)) -> 0.76282474 | BW26: =IF(ISERROR(GETPIVOTDATA("Sum of "&BW$1&" (Out)",$AW$6,"Sub-Sector",$BJ26,"End-Use",$BL26)),0,GETPIVOTDATA("Sum of "&BW$1&" (Out)",$AW$6,"Sub-Sector",$BJ26,"End-Use",$BL26)) -> 0.47832586 | BX26: =BO26/BO31 -> 0 | BY26: =BP26/BP31 -> 0 | BZ26: =BQ26/BQ31 -> 0.0097367615 | CA26: =BR26/BR31 -> 0.0068010794 | CB26: =BS26/BS31 -> 0 | CC26: =BT26/BT31 -> 0 | CD26: =BU26/BU31 -> 0 | CE26: =BV26/BV31 -> 0.0087509035 | CF26: =BW26/BW31 -> 0.0048923436 | CH26: ICOOHT | CI26: 0.10069783 | CJ26: 0.0241814 | CK26: 0.035897068 | CL26: 0.046884336 | CM26: 0.065586529 | CN26: 0.066660624 | CO26: 0.0617986 | CP26: 0.09897728 | CQ26: 0.099431886 | CS26: INCOH_OTP | CT26: 0.16085723 | CU26: 0.44278584 | CV26: 2.1593079 | CW26: 1.4625506 | CX26: 0.44351597 | CY26: 0.38658877 | CZ26: 1.3430103 | DA26: 0.44520677 | DB26: 0.27916492 | DC26: 7.1229883 | DE26: ICOOH_LPG | DF26: =LEFT(DE26,5) -> ICOOH | DG26: =GETPIVOTDATA("Sum of "&DG$1&" (Out)",$CS$6,"Constraint Identifier",$DE26) -> 0 | DH26: =GETPIVOTDATA("Sum of "&DH$1&" (Out)",$CS$6,"Constraint Identifier",$DE26) -> 0 | DI26: =GETPIVOTDATA("Sum of "&DI$1&" (Out)",$CS$6,"Constraint Identifier",$DE26) -> 0 | DJ26: =GETPIVOTDATA("Sum of "&DJ$1&" (Out)",$CS$6,"Constraint Identifier",$DE26) -> 0 | DK26: =GETPIVOTDATA("Sum of "&DK$1&" (Out)",$CS$6,"Constraint Identifier",$DE26) -> 3.1979798 | DL26: =GETPIVOTDATA("Sum of "&DL$1&" (Out)",$CS$6,"Constraint Identifier",$DE26) -> 2.7875052 | DM26: =GETPIVOTDATA("Sum of "&DM$1&" (Out)",$CS$6,"Constraint Identifier",$DE26) -> 9.6837998 | DN26: =GETPIVOTDATA("Sum of "&DN$1&" (Out)",$CS$6,"Constraint Identifier",$DE26) -> 0 | DO26: =GETPIVOTDATA("Sum of "&DO$1&" (Out)",$CS$6,"Constraint Identifier",$DE26) -> 0 | DP26: =IF(SUMIF($DF$8:$DF$380,"="&$DF26,DG$8:DG$380)=0,0,DG26/SUMIF($DF$8:$DF$380,"="&$DF26,DG$8:DG$380)) -> 0 | DQ26: =IF(SUMIF($DF$8:$DF$380,"="&$DF26,DH$8:DH$380)=0,0,DH26/SUMIF($DF$8:$DF$380,"="&$DF26,DH$8:DH$380)) -> 0 | DR26: =IF(SUMIF($DF$8:$DF$380,"="&$DF26,DI$8:DI$380)=0,0,DI26/SUMIF($DF$8:$DF$380,"="&$DF26,DI$8:DI$380)) -> 0 | DS26: =IF(SUMIF($DF$8:$DF$380,"="&$DF26,DJ$8:DJ$380)=0,0,DJ26/SUMIF($DF$8:$DF$380,"="&$DF26,DJ$8:DJ$380)) -> 0 | DT26: =IF(SUMIF($DF$8:$DF$380,"="&$DF26,DK$8:DK$380)=0,0,DK26/SUMIF($DF$8:$DF$380,"="&$DF26,DK$8:DK$380)) -> 0.092586213 | DU26: =IF(SUMIF($DF$8:$DF$380,"="&$DF26,DL$8:DL$380)=0,0,DL26/SUMIF($DF$8:$DF$380,"="&$DF26,DL$8:DL$380)) -> 0.092586213 | DV26: =IF(SUMIF($DF$8:$DF$380,"="&$DF26,DM$8:DM$380)=0,0,DM26/SUMIF($DF$8:$DF$380,"="&$DF26,DM$8:DM$380)) -> 0.092586213 | DW26: =IF(SUMIF($DF$8:$DF$380,"="&$DF26,DN$8:DN$380)=0,0,DN26/SUMIF($DF$8:$DF$380,"="&$DF26,DN$8:DN$380)) -> 0 | DX26: =IF(SUMIF($DF$8:$DF$380,"="&$DF26,DO$8:DO$380)=0,0,DO26/SUMIF($DF$8:$DF$380,"="&$DF26,DO$8:DO$380)) -> 0 | DZ26: ICIMD_NGA | EA26: 0.039922644 | EB26: 0.039922644 | EC26: 0.06267827 | ED26: 0.06267827 | EE26: 0.19690861 | EF26: 0.19690861 | EG26: 0.19690861 | EH26: 0.17496648 | EI26: 0.17496648 | EO26: Food | EP26: R1 | EQ26: =GETPIVOTDATA("Sum of "&EP26&" (Out)",$AW$6,"Sub-Sector",EO26) -> 18.944491 | ER26: =EQ26/SUM(EQ26:EQ34) -> 0.018555046 | ET26: R8 | EU26: 0.11286722 | EW26: Food | EX26: IFD | EY26: Other Heat | EZ26: OHT | FA26: =EX26&EZ26 -> IFDOHT | FB26: R3 | FC26: =GETPIVOTDATA("Sum of "&FB26&" (Out)",$AW$6,"Sub-Sector",EW26) -> 259.95493 | FD26: =GETPIVOTDATA("Sum of "&FB26&" (Out)",$AW$6,"Sub-Sector",EW26,"End-Use",EY26) -> 12.924553 | FE26: =GETPIVOTDATA("Sum of "&FB26&" (%)",$CH$6,"End-Use Commodity",FA26) -> 0.049718438 | FF26: 0.02 | FG26: =FC26-((FD26-FF26)/FE26) -> 0.40226525 | FI26: IPO | FJ26: 0 | FK26: 0 | FL26: 0 | FM26: 0 | FN26: 0 | FO26: 0 | FP26: 0 | FQ26: 0 | FR26: 0 | FS26: 0
A27: Cement | B27: Feedstock | C27: Petroleum Coke | D27: Petroleum Coke | E27: INCEFEDPTC | F27: =EndUse(A27,B27,C27,G27) -> #NAME? | G27: TechData_OTR | H27: 1 | I27: 0 | J27: 0 | K27: 0.21489116 | S27: 1 | T27: 1 | U27: 1 | V27: 1 | W27: 1 | X27: 1 | Y27: 1 | Z27: 1 | AA27: 1 | AB27: =J27*$H27*S27 -> 0 | AC27: =K27*$H27*T27 -> 0.21489116 | AD27: =L27*$H27*U27 -> 0 | AE27: =M27*$H27*V27 -> 0 | AF27: =N27*$H27*W27 -> 0 | AG27: =O27*$H27*X27 -> 0 | AH27: =P27*$H27*Y27 -> 0 | AI27: =Q27*$H27*Z27 -> 0 | AJ27: =R27*$H27*AA27 -> 0 | AK27: =SUM(AB27:AJ27) -> 0.21489116 | AL27: 0 | AM27: 0 | AN27: 0 | AO27: 0 | AP27: 0 | AQ27: 0 | AR27: 0 | AS27: 0 | AT27: 0 | AU27: 0 | AW27: Other Heat | AX27: 0.58453809 | AY27: 1.4540684 | AZ27: 12.924553 | BA27: 7.6539657 | BB27: 3.4624668 | BC27: 2.4433225 | BD27: 10.253697 | BE27: 5.1947925 | BF27: 2.474853 | BG27: 46.446257 | BH27: 2.6468776 | BJ27: Food | BK27: IFD | BL27: Machine Drive | BM27: MDR | BN27: =BK27&BM27 -> IFDMDR | BO27: =IF(ISERROR(GETPIVOTDATA("Sum of "&BO$1&" (Out)",$AW$6,"Sub-Sector",$BJ27,"End-Use",$BL27)),0,GETPIVOTDATA("Sum of "&BO$1&" (Out)",$AW$6,"Sub-Sector",$BJ27,"End-Use",$BL27)) -> 4.7716846 | BP27: =IF(ISERROR(GETPIVOTDATA("Sum of "&BP$1&" (Out)",$AW$6,"Sub-Sector",$BJ27,"End-Use",$BL27)),0,GETPIVOTDATA("Sum of "&BP$1&" (Out)",$AW$6,"Sub-Sector",$BJ27,"End-Use",$BL27)) -> 13.134842 | BQ27: =IF(ISERROR(GETPIVOTDATA("Sum of "&BQ$1&" (Out)",$AW$6,"Sub-Sector",$BJ27,"End-Use",$BL27)),0,GETPIVOTDATA("Sum of "&BQ$1&" (Out)",$AW$6,"Sub-Sector",$BJ27,"End-Use",$BL27)) -> 49.92415 | BR27: =IF(ISERROR(GETPIVOTDATA("Sum of "&BR$1&" (Out)",$AW$6,"Sub-Sector",$BJ27,"End-Use",$BL27)),0,GETPIVOTDATA("Sum of "&BR$1&" (Out)",$AW$6,"Sub-Sector",$BJ27,"End-Use",$BL27)) -> 33.814814 | BS27: =IF(ISERROR(GETPIVOTDATA("Sum of "&BS$1&" (Out)",$AW$6,"Sub-Sector",$BJ27,"End-Use",$BL27)),0,GETPIVOTDATA("Sum of "&BS$1&" (Out)",$AW$6,"Sub-Sector",$BJ27,"End-Use",$BL27)) -> 11.9067 | BT27: =IF(ISERROR(GETPIVOTDATA("Sum of "&BT$1&" (Out)",$AW$6,"Sub-Sector",$BJ27,"End-Use",$BL27)),0,GETPIVOTDATA("Sum of "&BT$1&" (Out)",$AW$6,"Sub-Sector",$BJ27,"End-Use",$BL27)) -> 10.378423 | BU27: =IF(ISERROR(GETPIVOTDATA("Sum of "&BU$1&" (Out)",$AW$6,"Sub-Sector",$BJ27,"End-Use",$BL27)),0,GETPIVOTDATA("Sum of "&BU$1&" (Out)",$AW$6,"Sub-Sector",$BJ27,"End-Use",$BL27)) -> 36.054667 | BV27: =IF(ISERROR(GETPIVOTDATA("Sum of "&BV$1&" (Out)",$AW$6,"Sub-Sector",$BJ27,"End-Use",$BL27)),0,GETPIVOTDATA("Sum of "&BV$1&" (Out)",$AW$6,"Sub-Sector",$BJ27,"End-Use",$BL27)) -> 19.164635 | BW27: =IF(ISERROR(GETPIVOTDATA("Sum of "&BW$1&" (Out)",$AW$6,"Sub-Sector",$BJ27,"End-Use",$BL27)),0,GETPIVOTDATA("Sum of "&BW$1&" (Out)",$AW$6,"Sub-Sector",$BJ27,"End-Use",$BL27)) -> 12.017099 | BX27: =BO27/BO31 -> 0.25187717 | BY27: =BP27/BP31 -> 0.25801193 | BZ27: =BQ27/BQ31 -> 0.19204925 | CA27: =BR27/BR31 -> 0.13414545 | CB27: =BS27/BS31 -> 0.13236552 | CC27: =BT27/BT31 -> 0.21492894 | CD27: =BU27/BU31 -> 0.31102139 | CE27: =BV27/BV31 -> 0.21985112 | CF27: =BW27/BW31 -> 0.12291156 | CH27: ICOPRH | CI27: 0.58012661 | CJ27: 0.13931058 | CK27: 0.4084659 | CL27: 0.53348792 | CM27: 0.090301068 | CN27: 0.091779908 | CO27: 0.085085759 | CP27: 0.32144228 | CQ27: 0.32291868 | CS27: INCOH_PTC | CT27: 0 | CU27: 5.2645593 | CV27: 18.831997 | CW27: 12.755359 | CX27: 3.868041 | CY27: 3.3715611 | CZ27: 11.712811 | DA27: 3.8827869 | DB27: 2.4346842 | DC27: 62.121799 | DE27: ICOOH_NGA | DF27: =LEFT(DE27,5) -> ICOOH | DG27: =GETPIVOTDATA("Sum of "&DG$1&" (Out)",$CS$6,"Constraint Identifier",$DE27) -> 0.013789461 | DH27: =GETPIVOTDATA("Sum of "&DH$1&" (Out)",$CS$6,"Constraint Identifier",$DE27) -> 0.037957746 | DI27: =GETPIVOTDATA("Sum of "&DI$1&" (Out)",$CS$6,"Constraint Identifier",$DE27) -> 0.35324457 | DJ27: =GETPIVOTDATA("Sum of "&DJ$1&" (Out)",$CS$6,"Constraint Identifier",$DE27) -> 0.23926095 | DK27: =GETPIVOTDATA("Sum of "&DK$1&" (Out)",$CS$6,"Constraint Identifier",$DE27) -> 0.33901467 | DL27: =GETPIVOTDATA("Sum of "&DL$1&" (Out)",$CS$6,"Constraint Identifier",$DE27) -> 0.29550066 | DM27: =GETPIVOTDATA("Sum of "&DM$1&" (Out)",$CS$6,"Constraint Identifier",$DE27) -> 1.02657 | DN27: =GETPIVOTDATA("Sum of "&DN$1&" (Out)",$CS$6,"Constraint Identifier",$DE27) -> 0.01272176 | DO27: =GETPIVOTDATA("Sum of "&DO$1&" (Out)",$CS$6,"Constraint Identifier",$DE27) -> 0.0079771228 | DP27: =IF(SUMIF($DF$8:$DF$380,"="&$DF27,DG$8:DG$380)=0,0,DG27/SUMIF($DF$8:$DF$380,"="&$DF27,DG$8:DG$380)) -> 0.040454408 | DQ27: =IF(SUMIF($DF$8:$DF$380,"="&$DF27,DH$8:DH$380)=0,0,DH27/SUMIF($DF$8:$DF$380,"="&$DF27,DH$8:DH$380)) -> 0.040454408 | DR27: =IF(SUMIF($DF$8:$DF$380,"="&$DF27,DI$8:DI$380)=0,0,DI27/SUMIF($DF$8:$DF$380,"="&$DF27,DI$8:DI$380)) -> 0.077451047 | DS27: =IF(SUMIF($DF$8:$DF$380,"="&$DF27,DJ$8:DJ$380)=0,0,DJ27/SUMIF($DF$8:$DF$380,"="&$DF27,DJ$8:DJ$380)) -> 0.077451047 | DT27: =IF(SUMIF($DF$8:$DF$380,"="&$DF27,DK$8:DK$380)=0,0,DK27/SUMIF($DF$8:$DF$380,"="&$DF27,DK$8:DK$380)) -> 0.0098149726 | DU27: =IF(SUMIF($DF$8:$DF$380,"="&$DF27,DL$8:DL$380)=0,0,DL27/SUMIF($DF$8:$DF$380,"="&$DF27,DL$8:DL$380)) -> 0.0098149726 | DV27: =IF(SUMIF($DF$8:$DF$380,"="&$DF27,DM$8:DM$380)=0,0,DM27/SUMIF($DF$8:$DF$380,"="&$DF27,DM$8:DM$380)) -> 0.0098149726 | DW27: =IF(SUMIF($DF$8:$DF$380,"="&$DF27,DN$8:DN$380)=0,0,DN27/SUMIF($DF$8:$DF$380,"="&$DF27,DN$8:DN$380)) -> 0.021990843 | DX27: =IF(SUMIF($DF$8:$DF$380,"="&$DF27,DO$8:DO$380)=0,0,DO27/SUMIF($DF$8:$DF$380,"="&$DF27,DO$8:DO$380)) -> 0.021990843 | DZ27: ICIOH_ELC | EA27: 0.088197194 | EB27: 0.088197194 | EC27: 0.018369701 | ED27: 0.018369701 | EE27: 0.077669945 | EF27: 0.077669945 | EG27: 0.077669945 | EH27: 0.10217119 | EI27: 0.10217119 | EO27: Food | EP27: R2 | EQ27: =GETPIVOTDATA("Sum of "&EP27&" (Out)",$AW$6,"Sub-Sector",EO27) -> 50.907889 | ER27: =EQ27/SUM(EQ26:EQ34) -> 0.049861367 | ET27: R9 | EU27: 0.070772888 | EW27: Food | EX27: IFD | EY27: Other Heat | EZ27: OHT | FA27: =EX27&EZ27 -> IFDOHT | FB27: R4 | FC27: =GETPIVOTDATA("Sum of "&FB27&" (Out)",$AW$6,"Sub-Sector",EW27) -> 252.07575 | FD27: =GETPIVOTDATA("Sum of "&FB27&" (Out)",$AW$6,"Sub-Sector",EW27,"End-Use",EY27) -> 7.6539657 | FE27: =GETPIVOTDATA("Sum of "&FB27&" (%)",$CH$6,"End-Use Commodity",FA27) -> 0.030363753 | FF27: 0.02 | FG27: =FC27-((FD27-FF27)/FE27) -> 0.65868011 | FI27: Grand Total | FJ27: 4.5034335 | FK27: 1.3247953 | FL27: 1.9456502 | FM27: 3.073073 | FN27: 3.0766318 | FO27: 3.5540239 | FP27: 6.6651606 | FQ27: 0.079818174 | FR27: 0.077045684 | FS27: 24.299632
A28: Cement | B28: Machine Drive | C28: Electricity | D28: Electricity | E28: INCEMDRELC | F28: =EndUse(A28,B28,C28,G28) -> #NAME? | G28: TechData_OTR | H28: 1 | I28: 0 | J28: 2.5716646 | K28: 1.8774237 | S28: 1 | T28: 1 | U28: 1 | V28: 1 | W28: 1 | X28: 1 | Y28: 1 | Z28: 1 | AA28: 1 | AB28: =J28*$H28*S28 -> 2.5716646 | AC28: =K28*$H28*T28 -> 1.8774237 | AD28: =L28*$H28*U28 -> 0 | AE28: =M28*$H28*V28 -> 0 | AF28: =N28*$H28*W28 -> 0 | AG28: =O28*$H28*X28 -> 0 | AH28: =P28*$H28*Y28 -> 0 | AI28: =Q28*$H28*Z28 -> 0 | AJ28: =R28*$H28*AA28 -> 0 | AK28: =SUM(AB28:AJ28) -> 4.4490883 | AL28: 0 | AM28: 0 | AN28: 0 | AO28: 0 | AP28: 0 | AQ28: 0 | AR28: 0 | AS28: 0 | AT28: 0 | AU28: 0 | AW28: Process Heat | AX28: 6.6127432 | AY28: 18.202657 | AZ28: 73.363414 | BA28: 49.690785 | BB28: 13.792976 | BC28: 12.022588 | BD28: 41.766499 | BE28: 34.56584 | BF28: 21.674356 | BG28: 271.69186 | BH28: 0 | BJ28: Food | BK28: IFD | BL28: Other Heat | BM28: OHT | BN28: =BK28&BM28 -> IFDOHT | BO28: =IF(ISERROR(GETPIVOTDATA("Sum of "&BO$1&" (Out)",$AW$6,"Sub-Sector",$BJ28,"End-Use",$BL28)),0,GETPIVOTDATA("Sum of "&BO$1&" (Out)",$AW$6,"Sub-Sector",$BJ28,"End-Use",$BL28)) -> 0.58453809 | BP28: =IF(ISERROR(GETPIVOTDATA("Sum of "&BP$1&" (Out)",$AW$6,"Sub-Sector",$BJ28,"End-Use",$BL28)),0,GETPIVOTDATA("Sum of "&BP$1&" (Out)",$AW$6,"Sub-Sector",$BJ28,"End-Use",$BL28)) -> 1.4540684 | BQ28: =IF(ISERROR(GETPIVOTDATA("Sum of "&BQ$1&" (Out)",$AW$6,"Sub-Sector",$BJ28,"End-Use",$BL28)),0,GETPIVOTDATA("Sum of "&BQ$1&" (Out)",$AW$6,"Sub-Sector",$BJ28,"End-Use",$BL28)) -> 12.924553 | BR28: =IF(ISERROR(GETPIVOTDATA("Sum of "&BR$1&" (Out)",$AW$6,"Sub-Sector",$BJ28,"End-Use",$BL28)),0,GETPIVOTDATA("Sum of "&BR$1&" (Out)",$AW$6,"Sub-Sector",$BJ28,"End-Use",$BL28)) -> 7.6539657 | BS28: =IF(ISERROR(GETPIVOTDATA("Sum of "&BS$1&" (Out)",$AW$6,"Sub-Sector",$BJ28,"End-Use",$BL28)),0,GETPIVOTDATA("Sum of "&BS$1&" (Out)",$AW$6,"Sub-Sector",$BJ28,"End-Use",$BL28)) -> 3.4624668 | BT28: =IF(ISERROR(GETPIVOTDATA("Sum of "&BT$1&" (Out)",$AW$6,"Sub-Sector",$BJ28,"End-Use",$BL28)),0,GETPIVOTDATA("Sum of "&BT$1&" (Out)",$AW$6,"Sub-Sector",$BJ28,"End-Use",$BL28)) -> 2.4433225 | BU28: =IF(ISERROR(GETPIVOTDATA("Sum of "&BU$1&" (Out)",$AW$6,"Sub-Sector",$BJ28,"End-Use",$BL28)),0,GETPIVOTDATA("Sum of "&BU$1&" (Out)",$AW$6,"Sub-Sector",$BJ28,"End-Use",$BL28)) -> 10.253697 | BV28: =IF(ISERROR(GETPIVOTDATA("Sum of "&BV$1&" (Out)",$AW$6,"Sub-Sector",$BJ28,"End-Use",$BL28)),0,GETPIVOTDATA("Sum of "&BV$1&" (Out)",$AW$6,"Sub-Sector",$BJ28,"End-Use",$BL28)) -> 5.1947925 | BW28: =IF(ISERROR(GETPIVOTDATA("Sum of "&BW$1&" (Out)",$AW$6,"Sub-Sector",$BJ28,"End-Use",$BL28)),0,GETPIVOTDATA("Sum of "&BW$1&" (Out)",$AW$6,"Sub-Sector",$BJ28,"End-Use",$BL28)) -> 2.474853 | BX28: =BO28/BO31 -> 0.030855308 | BY28: =BP28/BP31 -> 0.028562732 | BZ28: =BQ28/BQ31 -> 0.049718438 | CA28: =BR28/BR31 -> 0.030363753 | CB28: =BS28/BS31 -> 0.038491876 | CC28: =BT28/BT31 -> 0.050599279 | CD28: =BU28/BU31 -> 0.088452322 | CE28: =BV28/BV31 -> 0.059593148 | CF28: =BW28/BW31 -> 0.025312935 | CH28: ICOSTM | CI28: 0.0067827059 | CJ28: 0.76149055 | CK28: 0.33276679 | CL28: 0.12854203 | CM28: 0.024881801 | CN28: 0.0089125202 | CO28: 0.081199442 | CP28: 0.059649068 | CQ28: 0.055330001 | CS28: INCPH_ELC | CT28: 0.1542775 | CU28: 0.42467406 | CV28: 1.0354916 | CW28: 0.70136308 | CX28: 0.51202465 | CY28: 0.44630406 | CZ28: 1.5504614 | DA28: 0.71165993 | DB28: 0.44624319 | DC28: 5.9824994 | DE28: ICOOH_OTP | DF28: =LEFT(DE28,5) -> ICOOH | DG28: =GETPIVOTDATA("Sum of "&DG$1&" (Out)",$CS$6,"Constraint Identifier",$DE28) -> 0.32707477 | DH28: =GETPIVOTDATA("Sum of "&DH$1&" (Out)",$CS$6,"Constraint Identifier",$DE28) -> 0.90032681 | DI28: =GETPIVOTDATA("Sum of "&DI$1&" (Out)",$CS$6,"Constraint Identifier",$DE28) -> 4.2076307 | DJ28: =GETPIVOTDATA("Sum of "&DJ$1&" (Out)",$CS$6,"Constraint Identifier",$DE28) -> 2.8499284 | DK28: =GETPIVOTDATA("Sum of "&DK$1&" (Out)",$CS$6,"Constraint Identifier",$DE28) -> 28.306858 | DL28: =GETPIVOTDATA("Sum of "&DL$1&" (Out)",$CS$6,"Constraint Identifier",$DE28) -> 24.67355 | DM28: =GETPIVOTDATA("Sum of "&DM$1&" (Out)",$CS$6,"Constraint Identifier",$DE28) -> 85.715971 | DN28: =GETPIVOTDATA("Sum of "&DN$1&" (Out)",$CS$6,"Constraint Identifier",$DE28) -> 0.56578083 | DO28: =GETPIVOTDATA("Sum of "&DO$1&" (Out)",$CS$6,"Constraint Identifier",$DE28) -> 0.35477035 | DP28: =IF(SUMIF($DF$8:$DF$380,"="&$DF28,DG$8:DG$380)=0,0,DG28/SUMIF($DF$8:$DF$380,"="&$DF28,DG$8:DG$380)) -> 0.95954559 | DQ28: =IF(SUMIF($DF$8:$DF$380,"="&$DF28,DH$8:DH$380)=0,0,DH28/SUMIF($DF$8:$DF$380,"="&$DF28,DH$8:DH$380)) -> 0.95954559 | DR28: =IF(SUMIF($DF$8:$DF$380,"="&$DF28,DI$8:DI$380)=0,0,DI28/SUMIF($DF$8:$DF$380,"="&$DF28,DI$8:DI$380)) -> 0.92254895 | DS28: =IF(SUMIF($DF$8:$DF$380,"="&$DF28,DJ$8:DJ$380)=0,0,DJ28/SUMIF($DF$8:$DF$380,"="&$DF28,DJ$8:DJ$380)) -> 0.92254895 | DT28: =IF(SUMIF($DF$8:$DF$380,"="&$DF28,DK$8:DK$380)=0,0,DK28/SUMIF($DF$8:$DF$380,"="&$DF28,DK$8:DK$380)) -> 0.81952512 | DU28: =IF(SUMIF($DF$8:$DF$380,"="&$DF28,DL$8:DL$380)=0,0,DL28/SUMIF($DF$8:$DF$380,"="&$DF28,DL$8:DL$380)) -> 0.81952512 | DV28: =IF(SUMIF($DF$8:$DF$380,"="&$DF28,DM$8:DM$380)=0,0,DM28/SUMIF($DF$8:$DF$380,"="&$DF28,DM$8:DM$380)) -> 0.81952512 | DW28: =IF(SUMIF($DF$8:$DF$380,"="&$DF28,DN$8:DN$380)=0,0,DN28/SUMIF($DF$8:$DF$380,"="&$DF28,DN$8:DN$380)) -> 0.97800916 | DX28: =IF(SUMIF($DF$8:$DF$380,"="&$DF28,DO$8:DO$380)=0,0,DO28/SUMIF($DF$8:$DF$380,"="&$DF28,DO$8:DO$380)) -> 0.97800916 | DZ28: ICIOH_OTP | EA28: 0.91180281 | EB28: 0.91180281 | EC28: 0.9816303 | ED28: 0.9816303 | EE28: 0.92233005 | EF28: 0.92233005 | EG28: 0.92233005 | EH28: 0.89782881 | EI28: 0.89782881 | EO28: Food | EP28: R3 | EQ28: =GETPIVOTDATA("Sum of "&EP28&" (Out)",$AW$6,"Sub-Sector",EO28) -> 259.95493 | ER28: =EQ28/SUM(EQ26:EQ34) -> 0.25461099 | ET28: Food | EU28: 1 | EW28: Food | EX28: IFD | EY28: Electrochemical | EZ28: ETC | FA28: =EX28&EZ28 -> IFDETC | FB28: R5 | FC28: =GETPIVOTDATA("Sum of "&FB28&" (Out)",$AW$6,"Sub-Sector",EW28) -> 89.953184 | FD28: =GETPIVOTDATA("Sum of "&FB28&" (Out)",$AW$6,"Sub-Sector",EW28,"End-Use",EY28) -> 0.066082616 | FE28: =GETPIVOTDATA("Sum of "&FB28&" (%)",$CH$6,"End-Use Commodity",FA28) -> 0.00073463343 | FF28: 0 | FG28: =FC28-((FD28-FF28)/FE28) -> 0
A29: Cement | B29: Other Heat | C29: Other Petroleum | D29: Other Petroleum | E29: INCEOHTOTP | F29: =EndUse(A29,B29,C29,G29) -> #NAME? | G29: TechData_OTR | H29: 1 | I29: 0 | J29: 1.4625506 | K29: 0.44351597 | S29: 1 | T29: 1 | U29: 1 | V29: 1 | W29: 1 | X29: 1 | Y29: 1 | Z29: 1 | AA29: 1 | AB29: =J29*$H29*S29 -> 1.4625506 | AC29: =K29*$H29*T29 -> 0.44351597 | AD29: =L29*$H29*U29 -> 0 | AE29: =M29*$H29*V29 -> 0 | AF29: =N29*$H29*W29 -> 0 | AG29: =O29*$H29*X29 -> 0 | AH29: =P29*$H29*Y29 -> 0 | AI29: =Q29*$H29*Z29 -> 0 | AJ29: =R29*$H29*AA29 -> 0 | AK29: =SUM(AB29:AJ29) -> 1.9060665 | AL29: 0 | AM29: 0 | AN29: 0 | AO29: 0 | AP29: 0 | AQ29: 0 | AR29: 0 | AS29: 0 | AT29: 0 | AU29: 0 | AW29: Steam | AX29: 3.6429546 | AY29: 8.9428763 | AZ29: 90.405383 | BA29: 138.33595 | BB29: 53.63481 | BC29: 17.205663 | BD29: 6.1787923 | BE29: 10.888802 | BF29: 50.720415 | BG29: 379.95565 | BH29: 80.981055 | BJ29: Food | BK29: IFD | BL29: Process Heat | BM29: PRH | BN29: =BK29&BM29 -> IFDPRH | BO29: =IF(ISERROR(GETPIVOTDATA("Sum of "&BO$1&" (Out)",$AW$6,"Sub-Sector",$BJ29,"End-Use",$BL29)),0,GETPIVOTDATA("Sum of "&BO$1&" (Out)",$AW$6,"Sub-Sector",$BJ29,"End-Use",$BL29)) -> 6.6127432 | BP29: =IF(ISERROR(GETPIVOTDATA("Sum of "&BP$1&" (Out)",$AW$6,"Sub-Sector",$BJ29,"End-Use",$BL29)),0,GETPIVOTDATA("Sum of "&BP$1&" (Out)",$AW$6,"Sub-Sector",$BJ29,"End-Use",$BL29)) -> 18.202657 | BQ29: =IF(ISERROR(GETPIVOTDATA("Sum of "&BQ$1&" (Out)",$AW$6,"Sub-Sector",$BJ29,"End-Use",$BL29)),0,GETPIVOTDATA("Sum of "&BQ$1&" (Out)",$AW$6,"Sub-Sector",$BJ29,"End-Use",$BL29)) -> 73.363414 | BR29: =IF(ISERROR(GETPIVOTDATA("Sum of "&BR$1&" (Out)",$AW$6,"Sub-Sector",$BJ29,"End-Use",$BL29)),0,GETPIVOTDATA("Sum of "&BR$1&" (Out)",$AW$6,"Sub-Sector",$BJ29,"End-Use",$BL29)) -> 49.690785 | BS29: =IF(ISERROR(GETPIVOTDATA("Sum of "&BS$1&" (Out)",$AW$6,"Sub-Sector",$BJ29,"End-Use",$BL29)),0,GETPIVOTDATA("Sum of "&BS$1&" (Out)",$AW$6,"Sub-Sector",$BJ29,"End-Use",$BL29)) -> 13.792976 | BT29: =IF(ISERROR(GETPIVOTDATA("Sum of "&BT$1&" (Out)",$AW$6,"Sub-Sector",$BJ29,"End-Use",$BL29)),0,GETPIVOTDATA("Sum of "&BT$1&" (Out)",$AW$6,"Sub-Sector",$BJ29,"End-Use",$BL29)) -> 12.022588 | BU29: =IF(ISERROR(GETPIVOTDATA("Sum of "&BU$1&" (Out)",$AW$6,"Sub-Sector",$BJ29,"End-Use",$BL29)),0,GETPIVOTDATA("Sum of "&BU$1&" (Out)",$AW$6,"Sub-Sector",$BJ29,"End-Use",$BL29)) -> 41.766499 | BV29: =IF(ISERROR(GETPIVOTDATA("Sum of "&BV$1&" (Out)",$AW$6,"Sub-Sector",$BJ29,"End-Use",$BL29)),0,GETPIVOTDATA("Sum of "&BV$1&" (Out)",$AW$6,"Sub-Sector",$BJ29,"End-Use",$BL29)) -> 34.56584 | BW29: =IF(ISERROR(GETPIVOTDATA("Sum of "&BW$1&" (Out)",$AW$6,"Sub-Sector",$BJ29,"End-Use",$BL29)),0,GETPIVOTDATA("Sum of "&BW$1&" (Out)",$AW$6,"Sub-Sector",$BJ29,"End-Use",$BL29)) -> 21.674356 | BX29: =BO29/BO31 -> 0.34905891 | BY29: =BP29/BP31 -> 0.35756064 | BZ29: =BQ29/BQ31 -> 0.2822159 | CA29: =BR29/BR31 -> 0.1971264 | CB29: =BS29/BS31 -> 0.15333506 | CC29: =BT29/BT31 -> 0.2489783 | CD29: =BU29/BU31 -> 0.36029385 | CE29: =BV29/BV31 -> 0.39652926 | CF29: =BW29/BW31 -> 0.22168653 | CH29: ICPETC | CI29: 0.013905101 | CJ29: 0.016380944 | CK29: 0.0086328619 | CL29: 0.0097812136 | CM29: 0.007457136 | CN29: 0.0072238079 | CO29: 0.0074781218 | CP29: 0.094618423 | CQ29: 0.061015935 | CS29: INCPH_NGA | CT29: 0 | CU29: 0 | CV29: 0.68624096 | CW29: 0.46480732 | CX29: 1.0571402 | CY29: 0.92145168 | CZ29: 3.2011253 | DA29: 0.70744687 | DB29: 0.44360141 | DC29: 7.4818138 | DE29: IOTOH_DST | DF29: =LEFT(DE29,5) -> IOTOH | DG29: =GETPIVOTDATA("Sum of "&DG$1&" (Out)",$CS$6,"Constraint Identifier",$DE29) -> 0.06936195 | DH29: =GETPIVOTDATA("Sum of "&DH$1&" (Out)",$CS$6,"Constraint Identifier",$DE29) -> 0.19093011 | DI29: =GETPIVOTDATA("Sum of "&DI$1&" (Out)",$CS$6,"Constraint Identifier",$DE29) -> 0.13301396 | DJ29: =GETPIVOTDATA("Sum of "&DJ$1&" (Out)",$CS$6,"Constraint Identifier",$DE29) -> 0.090093519 | DK29: =GETPIVOTDATA("Sum of "&DK$1&" (Out)",$CS$6,"Constraint Identifier",$DE29) -> 0.075890851 | DL29: =GETPIVOTDATA("Sum of "&DL$1&" (Out)",$CS$6,"Constraint Identifier",$DE29) -> 0.066149931 | DM29: =GETPIVOTDATA("Sum of "&DM$1&" (Out)",$CS$6,"Constraint Identifier",$DE29) -> 0.22980502 | DN29: =GETPIVOTDATA("Sum of "&DN$1&" (Out)",$CS$6,"Constraint Identifier",$DE29) -> 0.29710265 | DO29: =GETPIVOTDATA("Sum of "&DO$1&" (Out)",$CS$6,"Constraint Identifier",$DE29) -> 0.18629689 | DP29: =IF(SUMIF($DF$8:$DF$380,"="&$DF29,DG$8:DG$380)=0,0,DG29/SUMIF($DF$8:$DF$380,"="&$DF29,DG$8:DG$380)) -> 0.010232556 | DQ29: =IF(SUMIF($DF$8:$DF$380,"="&$DF29,DH$8:DH$380)=0,0,DH29/SUMIF($DF$8:$DF$380,"="&$DF29,DH$8:DH$380)) -> 0.0073627044 | DR29: =IF(SUMIF($DF$8:$DF$380,"="&$DF29,DI$8:DI$380)=0,0,DI29/SUMIF($DF$8:$DF$380,"="&$DF29,DI$8:DI$380)) -> 0.006353503 | DS29: =IF(SUMIF($DF$8:$DF$380,"="&$DF29,DJ$8:DJ$380)=0,0,DJ29/SUMIF($DF$8:$DF$380,"="&$DF29,DJ$8:DJ$380)) -> 0.0063300368 | DT29: =IF(SUMIF($DF$8:$DF$380,"="&$DF29,DK$8:DK$380)=0,0,DK29/SUMIF($DF$8:$DF$380,"="&$DF29,DK$8:DK$380)) -> 0.0042551646 | DU29: =IF(SUMIF($DF$8:$DF$380,"="&$DF29,DL$8:DL$380)=0,0,DL29/SUMIF($DF$8:$DF$380,"="&$DF29,DL$8:DL$380)) -> 0.0043587874 | DV29: =IF(SUMIF($DF$8:$DF$380,"="&$DF29,DM$8:DM$380)=0,0,DM29/SUMIF($DF$8:$DF$380,"="&$DF29,DM$8:DM$380)) -> 0.0041208869 | DW29: =IF(SUMIF($DF$8:$DF$380,"="&$DF29,DN$8:DN$380)=0,0,DN29/SUMIF($DF$8:$DF$380,"="&$DF29,DN$8:DN$380)) -> 0.020990198 | DX29: =IF(SUMIF($DF$8:$DF$380,"="&$DF29,DO$8:DO$380)=0,0,DO29/SUMIF($DF$8:$DF$380,"="&$DF29,DO$8:DO$380)) -> 0.020644602 | DZ29: ICIPH_COA | EA29: 0 | EB29: 0 | EC29: 0 | ED29: 0 | EE29: 0.010515338 | EF29: 0.010515338 | EG29: 0.010515338 | EH29: 0.28631827 | EI29: 0.28631827 | EO29: Food | EP29: R4 | EQ29: =GETPIVOTDATA("Sum of "&EP29&" (Out)",$AW$6,"Sub-Sector",EO29) -> 252.07575 | ER29: =EQ29/SUM(EQ26:EQ34) -> 0.24689379 | ET29: R1 | EU29: 0.018555046 | EW29: Food | EX29: IFD | EY29: Electrochemical | EZ29: ETC | FA29: =EX29&EZ29 -> IFDETC | FB29: R6 | FC29: =GETPIVOTDATA("Sum of "&FB29&" (Out)",$AW$6,"Sub-Sector",EW29) -> 48.287695 | FD29: =GETPIVOTDATA("Sum of "&FB29&" (Out)",$AW$6,"Sub-Sector",EW29,"End-Use",EY29) -> 0.057600625 | FE29: =GETPIVOTDATA("Sum of "&FB29&" (%)",$CH$6,"End-Use Commodity",FA29) -> 0.0011928634 | FF29: 0 | FG29: =FC29-((FD29-FF29)/FE29) -> 0
A30: Cement | B30: Other Heat | C30: Petroleum Coke | D30: Petroleum Coke | E30: INCEOHTPTC | F30: =EndUse(A30,B30,C30,G30) -> #NAME? | G30: TechData_OTR | H30: 1 | I30: 0 | J30: 12.755359 | K30: 3.868041 | S30: 1 | T30: 1 | U30: 1 | V30: 1 | W30: 1 | X30: 1 | Y30: 1 | Z30: 1 | AA30: 1 | AB30: =J30*$H30*S30 -> 12.755359 | AC30: =K30*$H30*T30 -> 3.868041 | AD30: =L30*$H30*U30 -> 0 | AE30: =M30*$H30*V30 -> 0 | AF30: =N30*$H30*W30 -> 0 | AG30: =O30*$H30*X30 -> 0 | AH30: =P30*$H30*Y30 -> 0 | AI30: =Q30*$H30*Z30 -> 0 | AJ30: =R30*$H30*AA30 -> 0 | AK30: =SUM(AB30:AJ30) -> 16.6234 | AL30: 0 | AM30: 0 | AN30: 0 | AO30: 0 | AP30: 0 | AQ30: 0 | AR30: 0 | AS30: 0 | AT30: 0 | AU30: 0 | AW30: Glass | AX30: 15.46751 | AY30: 42.576852 | AZ30: 61.587244 | BA30: 41.714505 | BB30: 26.107654 | BC30: 22.756624 | BD30: 80.113221 | BE30: 29.039007 | BF30: 18.20878 | BG30: 337.5714 | BH30: 1.0912917 | BJ30: Food | BK30: IFD | BL30: Steam | BM30: STM | BN30: =BK30&BM30 -> IFDSTM | BO30: =IF(ISERROR(GETPIVOTDATA("Sum of "&BO$1&" (Out)",$AW$6,"Sub-Sector",$BJ30,"End-Use",$BL30)),0,GETPIVOTDATA("Sum of "&BO$1&" (Out)",$AW$6,"Sub-Sector",$BJ30,"End-Use",$BL30)) -> 3.6429546 | BP30: =IF(ISERROR(GETPIVOTDATA("Sum of "&BP$1&" (Out)",$AW$6,"Sub-Sector",$BJ30,"End-Use",$BL30)),0,GETPIVOTDATA("Sum of "&BP$1&" (Out)",$AW$6,"Sub-Sector",$BJ30,"End-Use",$BL30)) -> 8.9428763 | BQ30: =IF(ISERROR(GETPIVOTDATA("Sum of "&BQ$1&" (Out)",$AW$6,"Sub-Sector",$BJ30,"End-Use",$BL30)),0,GETPIVOTDATA("Sum of "&BQ$1&" (Out)",$AW$6,"Sub-Sector",$BJ30,"End-Use",$BL30)) -> 90.405383 | BR30: =IF(ISERROR(GETPIVOTDATA("Sum of "&BR$1&" (Out)",$AW$6,"Sub-Sector",$BJ30,"End-Use",$BL30)),0,GETPIVOTDATA("Sum of "&BR$1&" (Out)",$AW$6,"Sub-Sector",$BJ30,"End-Use",$BL30)) -> 138.33595 | BS30: =IF(ISERROR(GETPIVOTDATA("Sum of "&BS$1&" (Out)",$AW$6,"Sub-Sector",$BJ30,"End-Use",$BL30)),0,GETPIVOTDATA("Sum of "&BS$1&" (Out)",$AW$6,"Sub-Sector",$BJ30,"End-Use",$BL30)) -> 53.63481 | BT30: =IF(ISERROR(GETPIVOTDATA("Sum of "&BT$1&" (Out)",$AW$6,"Sub-Sector",$BJ30,"End-Use",$BL30)),0,GETPIVOTDATA("Sum of "&BT$1&" (Out)",$AW$6,"Sub-Sector",$BJ30,"End-Use",$BL30)) -> 17.205663 | BU30: =IF(ISERROR(GETPIVOTDATA("Sum of "&BU$1&" (Out)",$AW$6,"Sub-Sector",$BJ30,"End-Use",$BL30)),0,GETPIVOTDATA("Sum of "&BU$1&" (Out)",$AW$6,"Sub-Sector",$BJ30,"End-Use",$BL30)) -> 6.1787923 | BV30: =IF(ISERROR(GETPIVOTDATA("Sum of "&BV$1&" (Out)",$AW$6,"Sub-Sector",$BJ30,"End-Use",$BL30)),0,GETPIVOTDATA("Sum of "&BV$1&" (Out)",$AW$6,"Sub-Sector",$BJ30,"End-Use",$BL30)) -> 10.888802 | BW30: =IF(ISERROR(GETPIVOTDATA("Sum of "&BW$1&" (Out)",$AW$6,"Sub-Sector",$BJ30,"End-Use",$BL30)),0,GETPIVOTDATA("Sum of "&BW$1&" (Out)",$AW$6,"Sub-Sector",$BJ30,"End-Use",$BL30)) -> 50.720415 | BX30: =BO30/BO31 -> 0.19229626 | BY30: =BP30/BP31 -> 0.17566779 | BZ30: =BQ30/BQ31 -> 0.3477733 | CA30: =BR30/BR31 -> 0.54878723 | CB30: =BS30/BS31 -> 0.59625249 | CC30: =BT30/BT31 -> 0.35631569 | CD30: =BU30/BU31 -> 0.053300634 | CE30: =BV30/BV31 -> 0.12491317 | CF30: =BW30/BW31 -> 0.51877125 | CH30: ICPFAC | CI30: 0.016968377 | CJ30: 0.019989645 | CK30: 0.01039328 | CL30: 0.011775805 | CM30: 0.010638197 | CN30: 0.010305336 | CO30: 0.010668135 | CP30: 0.11133028 | CQ30: 0.071792796 | CS30: INCPH_COA | CT30: 3.9547091 | CU30: 10.885984 | CV30: 16.134297 | CW30: 10.928143 | CX30: 9.7992872 | CY30: 8.5415062 | CZ30: 29.673213 | DA30: 17.169416 | DB30: 10.766006 | DC30: 117.85256 | DE30: IOTOH_ELC | DF30: =LEFT(DE30,5) -> IOTOH | DG30: =GETPIVOTDATA("Sum of "&DG$1&" (Out)",$CS$6,"Constraint Identifier",$DE30) -> 1.0842306 | DH30: =GETPIVOTDATA("Sum of "&DH$1&" (Out)",$CS$6,"Constraint Identifier",$DE30) -> 2.9845222 | DI30: =GETPIVOTDATA("Sum of "&DI$1&" (Out)",$CS$6,"Constraint Identifier",$DE30) -> 6.7871739 | DJ30: =GETPIVOTDATA("Sum of "&DJ$1&" (Out)",$CS$6,"Constraint Identifier",$DE30) -> 4.5971143 | DK30: =GETPIVOTDATA("Sum of "&DK$1&" (Out)",$CS$6,"Constraint Identifier",$DE30) -> 2.9105974 | DL30: =GETPIVOTDATA("Sum of "&DL$1&" (Out)",$CS$6,"Constraint Identifier",$DE30) -> 2.5370096 | DM30: =GETPIVOTDATA("Sum of "&DM$1&" (Out)",$CS$6,"Constraint Identifier",$DE30) -> 8.8135772 | DN30: =GETPIVOTDATA("Sum of "&DN$1&" (Out)",$CS$6,"Constraint Identifier",$DE30) -> 3.2837475 | DO30: =GETPIVOTDATA("Sum of "&DO$1&" (Out)",$CS$6,"Constraint Identifier",$DE30) -> 2.0590592 | DP30: =IF(SUMIF($DF$8:$DF$380,"="&$DF30,DG$8:DG$380)=0,0,DG30/SUMIF($DF$8:$DF$380,"="&$DF30,DG$8:DG$380)) -> 0.1599501 | DQ30: =IF(SUMIF($DF$8:$DF$380,"="&$DF30,DH$8:DH$380)=0,0,DH30/SUMIF($DF$8:$DF$380,"="&$DF30,DH$8:DH$380)) -> 0.11509004 | DR30: =IF(SUMIF($DF$8:$DF$380,"="&$DF30,DI$8:DI$380)=0,0,DI30/SUMIF($DF$8:$DF$380,"="&$DF30,DI$8:DI$380)) -> 0.32419401 | DS30: =IF(SUMIF($DF$8:$DF$380,"="&$DF30,DJ$8:DJ$380)=0,0,DJ30/SUMIF($DF$8:$DF$380,"="&$DF30,DJ$8:DJ$380)) -> 0.32299662 | DT30: =IF(SUMIF($DF$8:$DF$380,"="&$DF30,DK$8:DK$380)=0,0,DK30/SUMIF($DF$8:$DF$380,"="&$DF30,DK$8:DK$380)) -> 0.16319583 | DU30: =IF(SUMIF($DF$8:$DF$380,"="&$DF30,DL$8:DL$380)=0,0,DL30/SUMIF($DF$8:$DF$380,"="&$DF30,DL$8:DL$380)) -> 0.16717002 | DV30: =IF(SUMIF($DF$8:$DF$380,"="&$DF30,DM$8:DM$380)=0,0,DM30/SUMIF($DF$8:$DF$380,"="&$DF30,DM$8:DM$380)) -> 0.15804596 | DW30: =IF(SUMIF($DF$8:$DF$380,"="&$DF30,DN$8:DN$380)=0,0,DN30/SUMIF($DF$8:$DF$380,"="&$DF30,DN$8:DN$380)) -> 0.23199561 | DX30: =IF(SUMIF($DF$8:$DF$380,"="&$DF30,DO$8:DO$380)=0,0,DO30/SUMIF($DF$8:$DF$380,"="&$DF30,DO$8:DO$380)) -> 0.22817589 | DZ30: ICIPH_ELC | EA30: 0.10198618 | EB30: 0.10198618 | EC30: 0.34791593 | ED30: 0.34791593 | EE30: 0.12569229 | EF30: 0.12569229 | EG30: 0.12569229 | EH30: 0.10277565 | EI30: 0.10277565 | EO30: Food | EP30: R5 | EQ30: =GETPIVOTDATA("Sum of "&EP30&" (Out)",$AW$6,"Sub-Sector",EO30) -> 89.953184 | ER30: =EQ30/SUM(EQ26:EQ34) -> 0.088104002 | ET30: R2 | EU30: 0.049861367 | EW30: Food | EX30: IFD | EY30: Electrochemical | EZ30: ETC | FA30: =EX30&EZ30 -> IFDETC | FB30: R7 | FC30: =GETPIVOTDATA("Sum of "&FB30&" (Out)",$AW$6,"Sub-Sector",EW30) -> 115.92343 | FD30: =GETPIVOTDATA("Sum of "&FB30&" (Out)",$AW$6,"Sub-Sector",EW30,"End-Use",EY30) -> 0.20010471 | FE30: =GETPIVOTDATA("Sum of "&FB30&" (%)",$CH$6,"End-Use Commodity",FA30) -> 0.00172618 | FF30: 0 | FG30: =FC30-((FD30-FF30)/FE30) -> 0
A31: Cement | B31: Process Heat | C31: Electricity | D31: Electricity | E31: INCEPRHELC | F31: =EndUse(A31,B31,C31,G31) -> #NAME? | G31: TechData_OTR | H31: 1 | I31: 0 | J31: 0.70136308 | K31: 0.51202465 | S31: 1 | T31: 1 | U31: 1 | V31: 1 | W31: 1 | X31: 1 | Y31: 1 | Z31: 1 | AA31: 1 | AB31: =J31*$H31*S31 -> 0.70136308 | AC31: =K31*$H31*T31 -> 0.51202465 | AD31: =L31*$H31*U31 -> 0 | AE31: =M31*$H31*V31 -> 0 | AF31: =N31*$H31*W31 -> 0 | AG31: =O31*$H31*X31 -> 0 | AH31: =P31*$H31*Y31 -> 0 | AI31: =Q31*$H31*Z31 -> 0 | AJ31: =R31*$H31*AA31 -> 0 | AK31: =SUM(AB31:AJ31) -> 1.2133877 | AL31: 0 | AM31: 0 | AN31: 0 | AO31: 0 | AP31: 0 | AQ31: 0 | AR31: 0 | AS31: 0 | AT31: 0 | AU31: 0 | AW31: Facilities | AX31: 0.87089561 | AY31: 2.3972826 | AZ31: 3.6733037 | BA31: 2.488016 | BB31: 1.5412436 | BC31: 1.3434183 | BD31: 4.6670383 | BE31: 1.7436213 | BF31: 1.09333 | BG31: 19.818149 | BH31: 0 | BJ31: Food | BK31: IFD | BL31: Total | BO31: =GETPIVOTDATA("Sum of "&BO$1&" (Out)",$AW$6,"Sub-Sector",$BJ31) -> 18.944491 | BP31: =GETPIVOTDATA("Sum of "&BP$1&" (Out)",$AW$6,"Sub-Sector",$BJ31) -> 50.907889 | BQ31: =GETPIVOTDATA("Sum of "&BQ$1&" (Out)",$AW$6,"Sub-Sector",$BJ31) -> 259.95493 | BR31: =GETPIVOTDATA("Sum of "&BR$1&" (Out)",$AW$6,"Sub-Sector",$BJ31) -> 252.07575 | BS31: =GETPIVOTDATA("Sum of "&BS$1&" (Out)",$AW$6,"Sub-Sector",$BJ31) -> 89.953184 | BT31: =GETPIVOTDATA("Sum of "&BT$1&" (Out)",$AW$6,"Sub-Sector",$BJ31) -> 48.287695 | BU31: =GETPIVOTDATA("Sum of "&BU$1&" (Out)",$AW$6,"Sub-Sector",$BJ31) -> 115.92343 | BV31: =GETPIVOTDATA("Sum of "&BV$1&" (Out)",$AW$6,"Sub-Sector",$BJ31) -> 87.17097 | BW31: =GETPIVOTDATA("Sum of "&BW$1&" (Out)",$AW$6,"Sub-Sector",$BJ31) -> 97.77029 | CH31: ICPFEED | CI31: 0.38849407 | CJ31: 0.45766654 | CK31: 0.7688033 | CL31: 0.87107026 | CM31: 0.77346302 | CN31: 0.74926195 | CO31: 0.77563969 | CP31: 0 | CQ31: 0 | CS31: INCST_DST | CT31: 0 | CU31: 0 | CV31: 0 | CW31: 0 | CX31: 0 | CY31: 0 | CZ31: 0 | DA31: 0 | DB31: 0 | DC31: 0 | DE31: IOTOH_LPG | DF31: =LEFT(DE31,5) -> IOTOH | DG31: =GETPIVOTDATA("Sum of "&DG$1&" (Out)",$CS$6,"Constraint Identifier",$DE31) -> 0.039145408 | DH31: =GETPIVOTDATA("Sum of "&DH$1&" (Out)",$CS$6,"Constraint Identifier",$DE31) -> 0.10775414 | DI31: =GETPIVOTDATA("Sum of "&DI$1&" (Out)",$CS$6,"Constraint Identifier",$DE31) -> 1.0509566 | DJ31: =GETPIVOTDATA("Sum of "&DJ$1&" (Out)",$CS$6,"Constraint Identifier",$DE31) -> 0.71183791 | DK31: =GETPIVOTDATA("Sum of "&DK$1&" (Out)",$CS$6,"Constraint Identifier",$DE31) -> 0.32979167 | DL31: =GETPIVOTDATA("Sum of "&DL$1&" (Out)",$CS$6,"Constraint Identifier",$DE31) -> 0.28746148 | DM31: =GETPIVOTDATA("Sum of "&DM$1&" (Out)",$CS$6,"Constraint Identifier",$DE31) -> 0.99864185 | DN31: =GETPIVOTDATA("Sum of "&DN$1&" (Out)",$CS$6,"Constraint Identifier",$DE31) -> 0.2708582 | DO31: =GETPIVOTDATA("Sum of "&DO$1&" (Out)",$CS$6,"Constraint Identifier",$DE31) -> 0.16984043 | DP31: =IF(SUMIF($DF$8:$DF$380,"="&$DF31,DG$8:DG$380)=0,0,DG31/SUMIF($DF$8:$DF$380,"="&$DF31,DG$8:DG$380)) -> 0.0057748894 | DQ31: =IF(SUMIF($DF$8:$DF$380,"="&$DF31,DH$8:DH$380)=0,0,DH31/SUMIF($DF$8:$DF$380,"="&$DF31,DH$8:DH$380)) -> 0.0041552475 | DR31: =IF(SUMIF($DF$8:$DF$380,"="&$DF31,DI$8:DI$380)=0,0,DI31/SUMIF($DF$8:$DF$380,"="&$DF31,DI$8:DI$380)) -> 0.050199663 | DS31: =IF(SUMIF($DF$8:$DF$380,"="&$DF31,DJ$8:DJ$380)=0,0,DJ31/SUMIF($DF$8:$DF$380,"="&$DF31,DJ$8:DJ$380)) -> 0.050014254 | DT31: =IF(SUMIF($DF$8:$DF$380,"="&$DF31,DK$8:DK$380)=0,0,DK31/SUMIF($DF$8:$DF$380,"="&$DF31,DK$8:DK$380)) -> 0.018491265 | DU31: =IF(SUMIF($DF$8:$DF$380,"="&$DF31,DL$8:DL$380)=0,0,DL31/SUMIF($DF$8:$DF$380,"="&$DF31,DL$8:DL$380)) -> 0.018941569 | DV31: =IF(SUMIF($DF$8:$DF$380,"="&$DF31,DM$8:DM$380)=0,0,DM31/SUMIF($DF$8:$DF$380,"="&$DF31,DM$8:DM$380)) -> 0.017907747 | DW31: =IF(SUMIF($DF$8:$DF$380,"="&$DF31,DN$8:DN$380)=0,0,DN31/SUMIF($DF$8:$DF$380,"="&$DF31,DN$8:DN$380)) -> 0.019136037 | DX31: =IF(SUMIF($DF$8:$DF$380,"="&$DF31,DO$8:DO$380)=0,0,DO31/SUMIF($DF$8:$DF$380,"="&$DF31,DO$8:DO$380)) -> 0.018820969 | DZ31: ICIPH_NGA | EA31: 0.11886537 | EB31: 0.11886537 | EC31: 0.65208407 | ED31: 0.65208407 | EE31: 0.86379237 | EF31: 0.86379237 | EG31: 0.86379237 | EH31: 0.61090608 | EI31: 0.61090608 | EO31: Food | EP31: R6 | EQ31: =GETPIVOTDATA("Sum of "&EP31&" (Out)",$AW$6,"Sub-Sector",EO31) -> 48.287695 | ER31: =EQ31/SUM(EQ26:EQ34) -> 0.047295037 | ET31: R3 | EU31: 0.25461099 | EW31: Food | EX31: IFD | EY31: Electrochemical | EZ31: ETC | FA31: =EX31&EZ31 -> IFDETC | FB31: R8 | FC31: =GETPIVOTDATA("Sum of "&FB31&" (Out)",$AW$6,"Sub-Sector",EW31) -> 87.17097 | FD31: =GETPIVOTDATA("Sum of "&FB31&" (Out)",$AW$6,"Sub-Sector",EW31,"End-Use",EY31) -> 0.10328036 | FE31: =GETPIVOTDATA("Sum of "&FB31&" (%)",$CH$6,"End-Use Commodity",FA31) -> 0.0011848022 | FF31: 0 | FG31: =FC31-((FD31-FF31)/FE31) -> 0
A32: Cement | B32: Process Heat | C32: Natural Gas | D32: Natural Gas | E32: INCEPRHNGA | F32: =EndUse(A32,B32,C32,G32) -> #NAME? | G32: TechData_OTR | H32: 1 | I32: 0 | J32: 0.46480732 | K32: 1.0571402 | S32: 1 | T32: 1 | U32: 1 | V32: 1 | W32: 1 | X32: 1 | Y32: 1 | Z32: 1 | AA32: 1 | AB32: =J32*$H32*S32 -> 0.46480732 | AC32: =K32*$H32*T32 -> 1.0571402 | AD32: =L32*$H32*U32 -> 0 | AE32: =M32*$H32*V32 -> 0 | AF32: =N32*$H32*W32 -> 0 | AG32: =O32*$H32*X32 -> 0 | AH32: =P32*$H32*Y32 -> 0 | AI32: =Q32*$H32*Z32 -> 0 | AJ32: =R32*$H32*AA32 -> 0 | AK32: =SUM(AB32:AJ32) -> 1.5219475 | AL32: 0 | AM32: 0 | AN32: 0 | AO32: 0 | AP32: 0 | AQ32: 0 | AR32: 0 | AS32: 0 | AT32: 0 | AU32: 0 | AW32: Machine Drive | AX32: 0.95899524 | AY32: 2.6397912 | AZ32: 4.5976128 | BA32: 3.1140725 | BB32: 1.8886744 | BC32: 1.6462548 | BD32: 5.7190932 | BE32: 2.2118536 | BF32: 1.3869329 | BG32: 24.163281 | BH32: 0 | BJ32: Glass | BK32: ING | BL32: Electrochemical | BM32: ETC | BN32: =BK32&BM32 -> INGETC | BO32: =IF(ISERROR(GETPIVOTDATA("Sum of "&BO$1&" (Out)",$AW$6,"Sub-Sector",$BJ32,"End-Use",$BL32)),0,GETPIVOTDATA("Sum of "&BO$1&" (Out)",$AW$6,"Sub-Sector",$BJ32,"End-Use",$BL32)) -> 0 | BP32: =IF(ISERROR(GETPIVOTDATA("Sum of "&BP$1&" (Out)",$AW$6,"Sub-Sector",$BJ32,"End-Use",$BL32)),0,GETPIVOTDATA("Sum of "&BP$1&" (Out)",$AW$6,"Sub-Sector",$BJ32,"End-Use",$BL32)) -> 0 | BQ32: =IF(ISERROR(GETPIVOTDATA("Sum of "&BQ$1&" (Out)",$AW$6,"Sub-Sector",$BJ32,"End-Use",$BL32)),0,GETPIVOTDATA("Sum of "&BQ$1&" (Out)",$AW$6,"Sub-Sector",$BJ32,"End-Use",$BL32)) -> 0 | BR32: =IF(ISERROR(GETPIVOTDATA("Sum of "&BR$1&" (Out)",$AW$6,"Sub-Sector",$BJ32,"End-Use",$BL32)),0,GETPIVOTDATA("Sum of "&BR$1&" (Out)",$AW$6,"Sub-Sector",$BJ32,"End-Use",$BL32)) -> 0 | BS32: =IF(ISERROR(GETPIVOTDATA("Sum of "&BS$1&" (Out)",$AW$6,"Sub-Sector",$BJ32,"End-Use",$BL32)),0,GETPIVOTDATA("Sum of "&BS$1&" (Out)",$AW$6,"Sub-Sector",$BJ32,"End-Use",$BL32)) -> 0 | BT32: =IF(ISERROR(GETPIVOTDATA("Sum of "&BT$1&" (Out)",$AW$6,"Sub-Sector",$BJ32,"End-Use",$BL32)),0,GETPIVOTDATA("Sum of "&BT$1&" (Out)",$AW$6,"Sub-Sector",$BJ32,"End-Use",$BL32)) -> 0 | BU32: =IF(ISERROR(GETPIVOTDATA("Sum of "&BU$1&" (Out)",$AW$6,"Sub-Sector",$BJ32,"End-Use",$BL32)),0,GETPIVOTDATA("Sum of "&BU$1&" (Out)",$AW$6,"Sub-Sector",$BJ32,"End-Use",$BL32)) -> 0 | BV32: =IF(ISERROR(GETPIVOTDATA("Sum of "&BV$1&" (Out)",$AW$6,"Sub-Sector",$BJ32,"End-Use",$BL32)),0,GETPIVOTDATA("Sum of "&BV$1&" (Out)",$AW$6,"Sub-Sector",$BJ32,"End-Use",$BL32)) -> 0 | BW32: =IF(ISERROR(GETPIVOTDATA("Sum of "&BW$1&" (Out)",$AW$6,"Sub-Sector",$BJ32,"End-Use",$BL32)),0,GETPIVOTDATA("Sum of "&BW$1&" (Out)",$AW$6,"Sub-Sector",$BJ32,"End-Use",$BL32)) -> 0 | BX32: =BO32/BO39 -> 0 | BY32: =BP32/BP39 -> 0 | BZ32: =BQ32/BQ39 -> 0 | CA32: =BR32/BR39 -> 0 | CB32: =BS32/BS39 -> 0 | CC32: =BT32/BT39 -> 0 | CD32: =BU32/BU39 -> 0 | CE32: =BV32/BV39 -> 0 | CF32: =BW32/BW39 -> 0 | CH32: ICPMDR | CI32: 0.085125281 | CJ32: 0.10028208 | CK32: 0.052619537 | CL32: 0.059619039 | CM32: 0.048151327 | CN32: 0.046644709 | CO32: 0.048286834 | CP32: 0.57252684 | CQ32: 0.36920147 | CS32: INCST_CHP | CT32: 0 | CU32: 5.926564e-19 | CV32: 2.0363211e-17 | CW32: 0 | CX32: 0 | CY32: 0 | CZ32: 0 | DA32: 0 | DB32: 0 | DC32: 2.0955867e-17 | DE32: IOTOH_NGA | DF32: =LEFT(DE32,5) -> IOTOH | DG32: =GETPIVOTDATA("Sum of "&DG$1&" (Out)",$CS$6,"Constraint Identifier",$DE32) -> 1.1880489 | DH32: =GETPIVOTDATA("Sum of "&DH$1&" (Out)",$CS$6,"Constraint Identifier",$DE32) -> 3.2702989 | DI32: =GETPIVOTDATA("Sum of "&DI$1&" (Out)",$CS$6,"Constraint Identifier",$DE32) -> 7.8918313 | DJ32: =GETPIVOTDATA("Sum of "&DJ$1&" (Out)",$CS$6,"Constraint Identifier",$DE32) -> 5.345325 | DK32: =GETPIVOTDATA("Sum of "&DK$1&" (Out)",$CS$6,"Constraint Identifier",$DE32) -> 2.3545205 | DL32: =GETPIVOTDATA("Sum of "&DL$1&" (Out)",$CS$6,"Constraint Identifier",$DE32) -> 2.0523076 | DM32: =GETPIVOTDATA("Sum of "&DM$1&" (Out)",$CS$6,"Constraint Identifier",$DE32) -> 7.1297213 | DN32: =GETPIVOTDATA("Sum of "&DN$1&" (Out)",$CS$6,"Constraint Identifier",$DE32) -> 2.4011618 | DO32: =GETPIVOTDATA("Sum of "&DO$1&" (Out)",$CS$6,"Constraint Identifier",$DE32) -> 1.5056378 | DP32: =IF(SUMIF($DF$8:$DF$380,"="&$DF32,DG$8:DG$380)=0,0,DG32/SUMIF($DF$8:$DF$380,"="&$DF32,DG$8:DG$380)) -> 0.17526579 | DQ32: =IF(SUMIF($DF$8:$DF$380,"="&$DF32,DH$8:DH$380)=0,0,DH32/SUMIF($DF$8:$DF$380,"="&$DF32,DH$8:DH$380)) -> 0.12611025 | DR32: =IF(SUMIF($DF$8:$DF$380,"="&$DF32,DI$8:DI$380)=0,0,DI32/SUMIF($DF$8:$DF$380,"="&$DF32,DI$8:DI$380)) -> 0.37695873 | DS32: =IF(SUMIF($DF$8:$DF$380,"="&$DF32,DJ$8:DJ$380)=0,0,DJ32/SUMIF($DF$8:$DF$380,"="&$DF32,DJ$8:DJ$380)) -> 0.37556646 | DT32: =IF(SUMIF($DF$8:$DF$380,"="&$DF32,DK$8:DK$380)=0,0,DK32/SUMIF($DF$8:$DF$380,"="&$DF32,DK$8:DK$380)) -> 0.13201686 | DU32: =IF(SUMIF($DF$8:$DF$380,"="&$DF32,DL$8:DL$380)=0,0,DL32/SUMIF($DF$8:$DF$380,"="&$DF32,DL$8:DL$380)) -> 0.13523177 | DV32: =IF(SUMIF($DF$8:$DF$380,"="&$DF32,DM$8:DM$380)=0,0,DM32/SUMIF($DF$8:$DF$380,"="&$DF32,DM$8:DM$380)) -> 0.12785089 | DW32: =IF(SUMIF($DF$8:$DF$380,"="&$DF32,DN$8:DN$380)=0,0,DN32/SUMIF($DF$8:$DF$380,"="&$DF32,DN$8:DN$380)) -> 0.16964124 | DX32: =IF(SUMIF($DF$8:$DF$380,"="&$DF32,DO$8:DO$380)=0,0,DO32/SUMIF($DF$8:$DF$380,"="&$DF32,DO$8:DO$380)) -> 0.16684816 | DZ32: ICIPH_RFL | EA32: 0.77914845 | EB32: 0.77914845 | EC32: 0 | ED32: 0 | EE32: 0 | EF32: 0 | EG32: 0 | EH32: 0 | EI32: 0 | EO32: Food | EP32: R7 | EQ32: =GETPIVOTDATA("Sum of "&EP32&" (Out)",$AW$6,"Sub-Sector",EO32) -> 115.92343 | ER32: =EQ32/SUM(EQ26:EQ34) -> 0.11354037 | ET32: R4 | EU32: 0.24689379 | EW32: Food | EX32: IFD | EY32: Electrochemical | EZ32: ETC | FA32: =EX32&EZ32 -> IFDETC | FB32: R9 | FC32: =GETPIVOTDATA("Sum of "&FB32&" (Out)",$AW$6,"Sub-Sector",EW32) -> 97.77029 | FD32: =GETPIVOTDATA("Sum of "&FB32&" (Out)",$AW$6,"Sub-Sector",EW32,"End-Use",EY32) -> 0.064761489 | FE32: =GETPIVOTDATA("Sum of "&FB32&" (%)",$CH$6,"End-Use Commodity",FA32) -> 0.00066238413 | FF32: 0 | FG32: =FC32-((FD32-FF32)/FE32) -> 0
A33: Cement | B33: Process Heat | C33: Steam Coal | D33: Steam Coal | E33: INCEPRHCOA | F33: =EndUse(A33,B33,C33,G33) -> #NAME? | G33: TechData_OTR | H33: 1 | I33: 0 | J33: 10.928143 | K33: 9.7992872 | S33: 1 | T33: 1 | U33: 1 | V33: 1 | W33: 1 | X33: 1 | Y33: 1 | Z33: 1 | AA33: 1 | AB33: =J33*$H33*S33 -> 10.928143 | AC33: =K33*$H33*T33 -> 9.7992872 | AD33: =L33*$H33*U33 -> 0 | AE33: =M33*$H33*V33 -> 0 | AF33: =N33*$H33*W33 -> 0 | AG33: =O33*$H33*X33 -> 0 | AH33: =P33*$H33*Y33 -> 0 | AI33: =Q33*$H33*Z33 -> 0 | AJ33: =R33*$H33*AA33 -> 0 | AK33: =SUM(AB33:AJ33) -> 20.72743 | AL33: 0 | AM33: 0 | AN33: 0 | AO33: 0 | AP33: 0 | AQ33: 0 | AR33: 0 | AS33: 0 | AT33: 0 | AU33: 0 | AW33: Other Heat | AX33: 3.1642394 | AY33: 8.7100864 | AZ33: 12.641771 | BA33: 8.5625719 | BB33: 5.3557125 | BC33: 4.6682836 | BD33: 16.217628 | BE33: 5.9631336 | BF33: 3.7391564 | BG33: 69.022582 | BH33: 0 | BJ33: Glass | BK33: ING | BL33: Facilities | BM33: FAC | BN33: =BK33&BM33 -> INGFAC | BO33: =IF(ISERROR(GETPIVOTDATA("Sum of "&BO$1&" (Out)",$AW$6,"Sub-Sector",$BJ33,"End-Use",$BL33)),0,GETPIVOTDATA("Sum of "&BO$1&" (Out)",$AW$6,"Sub-Sector",$BJ33,"End-Use",$BL33)) -> 0.87089561 | BP33: =IF(ISERROR(GETPIVOTDATA("Sum of "&BP$1&" (Out)",$AW$6,"Sub-Sector",$BJ33,"End-Use",$BL33)),0,GETPIVOTDATA("Sum of "&BP$1&" (Out)",$AW$6,"Sub-Sector",$BJ33,"End-Use",$BL33)) -> 2.3972826 | BQ33: =IF(ISERROR(GETPIVOTDATA("Sum of "&BQ$1&" (Out)",$AW$6,"Sub-Sector",$BJ33,"End-Use",$BL33)),0,GETPIVOTDATA("Sum of "&BQ$1&" (Out)",$AW$6,"Sub-Sector",$BJ33,"End-Use",$BL33)) -> 3.6733037 | BR33: =IF(ISERROR(GETPIVOTDATA("Sum of "&BR$1&" (Out)",$AW$6,"Sub-Sector",$BJ33,"End-Use",$BL33)),0,GETPIVOTDATA("Sum of "&BR$1&" (Out)",$AW$6,"Sub-Sector",$BJ33,"End-Use",$BL33)) -> 2.488016 | BS33: =IF(ISERROR(GETPIVOTDATA("Sum of "&BS$1&" (Out)",$AW$6,"Sub-Sector",$BJ33,"End-Use",$BL33)),0,GETPIVOTDATA("Sum of "&BS$1&" (Out)",$AW$6,"Sub-Sector",$BJ33,"End-Use",$BL33)) -> 1.5412436 | BT33: =IF(ISERROR(GETPIVOTDATA("Sum of "&BT$1&" (Out)",$AW$6,"Sub-Sector",$BJ33,"End-Use",$BL33)),0,GETPIVOTDATA("Sum of "&BT$1&" (Out)",$AW$6,"Sub-Sector",$BJ33,"End-Use",$BL33)) -> 1.3434183 | BU33: =IF(ISERROR(GETPIVOTDATA("Sum of "&BU$1&" (Out)",$AW$6,"Sub-Sector",$BJ33,"End-Use",$BL33)),0,GETPIVOTDATA("Sum of "&BU$1&" (Out)",$AW$6,"Sub-Sector",$BJ33,"End-Use",$BL33)) -> 4.6670383 | BV33: =IF(ISERROR(GETPIVOTDATA("Sum of "&BV$1&" (Out)",$AW$6,"Sub-Sector",$BJ33,"End-Use",$BL33)),0,GETPIVOTDATA("Sum of "&BV$1&" (Out)",$AW$6,"Sub-Sector",$BJ33,"End-Use",$BL33)) -> 1.7436213 | BW33: =IF(ISERROR(GETPIVOTDATA("Sum of "&BW$1&" (Out)",$AW$6,"Sub-Sector",$BJ33,"End-Use",$BL33)),0,GETPIVOTDATA("Sum of "&BW$1&" (Out)",$AW$6,"Sub-Sector",$BJ33,"End-Use",$BL33)) -> 1.09333 | BX33: =BO33/BO39 -> 0.056304835 | BY33: =BP33/BP39 -> 0.056304835 | BZ33: =BQ33/BQ39 -> 0.059643905 | CA33: =BR33/BR39 -> 0.059643905 | CB33: =BS33/BS39 -> 0.059034166 | CC33: =BT33/BT39 -> 0.059034166 | CD33: =BU33/BU39 -> 0.058255532 | CE33: =BV33/BV39 -> 0.060044108 | CF33: =BW33/BW39 -> 0.060044108 | CH33: ICPOHT | CI33: 0.042102235 | CJ33: 0.049598658 | CK33: 0.018270184 | CL33: 0.020700501 | CM33: 0.036403465 | CN33: 0.035264428 | CO33: 0.036505911 | CP33: 0.010513158 | CQ33: 0.0067795484 | CS33: IFDEC_ELC | CT33: 0.026212304 | CU33: 0.072153655 | CV33: 0.27611826 | CW33: 0.18702146 | CX33: 0.066082616 | CY33: 0.057600625 | CZ33: 0.20010471 | DA33: 0.10328036 | DB33: 0.064761489 | DC33: 1.0533355 | DE33: IOTOH_OTP | DF33: =LEFT(DE33,5) -> IOTOH | DG33: =GETPIVOTDATA("Sum of "&DG$1&" (Out)",$CS$6,"Constraint Identifier",$DE33) -> 0 | DH33: =GETPIVOTDATA("Sum of "&DH$1&" (Out)",$CS$6,"Constraint Identifier",$DE33) -> 0 | DI33: =GETPIVOTDATA("Sum of "&DI$1&" (Out)",$CS$6,"Constraint Identifier",$DE33) -> 0.0040194004 | DJ33: =GETPIVOTDATA("Sum of "&DJ$1&" (Out)",$CS$6,"Constraint Identifier",$DE33) -> 0.0027224355 | DK33: =GETPIVOTDATA("Sum of "&DK$1&" (Out)",$CS$6,"Constraint Identifier",$DE33) -> 0 | DL33: =GETPIVOTDATA("Sum of "&DL$1&" (Out)",$CS$6,"Constraint Identifier",$DE33) -> 0 | DM33: =GETPIVOTDATA("Sum of "&DM$1&" (Out)",$CS$6,"Constraint Identifier",$DE33) -> 0 | DN33: =GETPIVOTDATA("Sum of "&DN$1&" (Out)",$CS$6,"Constraint Identifier",$DE33) -> 0 | DO33: =GETPIVOTDATA("Sum of "&DO$1&" (Out)",$CS$6,"Constraint Identifier",$DE33) -> 0 | DP33: =IF(SUMIF($DF$8:$DF$380,"="&$DF33,DG$8:DG$380)=0,0,DG33/SUMIF($DF$8:$DF$380,"="&$DF33,DG$8:DG$380)) -> 0 | DQ33: =IF(SUMIF($DF$8:$DF$380,"="&$DF33,DH$8:DH$380)=0,0,DH33/SUMIF($DF$8:$DF$380,"="&$DF33,DH$8:DH$380)) -> 0 | DR33: =IF(SUMIF($DF$8:$DF$380,"="&$DF33,DI$8:DI$380)=0,0,DI33/SUMIF($DF$8:$DF$380,"="&$DF33,DI$8:DI$380)) -> 0.00019198942 | DS33: =IF(SUMIF($DF$8:$DF$380,"="&$DF33,DJ$8:DJ$380)=0,0,DJ33/SUMIF($DF$8:$DF$380,"="&$DF33,DJ$8:DJ$380)) -> 0.00019128032 | DT33: =IF(SUMIF($DF$8:$DF$380,"="&$DF33,DK$8:DK$380)=0,0,DK33/SUMIF($DF$8:$DF$380,"="&$DF33,DK$8:DK$380)) -> 0 | DU33: =IF(SUMIF($DF$8:$DF$380,"="&$DF33,DL$8:DL$380)=0,0,DL33/SUMIF($DF$8:$DF$380,"="&$DF33,DL$8:DL$380)) -> 0 | DV33: =IF(SUMIF($DF$8:$DF$380,"="&$DF33,DM$8:DM$380)=0,0,DM33/SUMIF($DF$8:$DF$380,"="&$DF33,DM$8:DM$380)) -> 0 | DW33: =IF(SUMIF($DF$8:$DF$380,"="&$DF33,DN$8:DN$380)=0,0,DN33/SUMIF($DF$8:$DF$380,"="&$DF33,DN$8:DN$380)) -> 0 | DX33: =IF(SUMIF($DF$8:$DF$380,"="&$DF33,DO$8:DO$380)=0,0,DO33/SUMIF($DF$8:$DF$380,"="&$DF33,DO$8:DO$380)) -> 0 | DZ33: ICIST_CHP | EA33: 1 | EB33: 0.91551647 | EC33: 0.16162848 | ED33: 0.084723596 | EE33: 0.92272058 | EF33: 0.30886746 | EG33: 0.87190635 | EH33: 1 | EI33: 0.6304103 | EO33: Food | EP33: R8 | EQ33: =GETPIVOTDATA("Sum of "&EP33&" (Out)",$AW$6,"Sub-Sector",EO33) -> 87.17097 | ER33: =EQ33/SUM(EQ26:EQ34) -> 0.085378982 | ET33: R5 | EU33: 0.088104002 | EW33: Glass | EX33: ING | EY33: Facilities | EZ33: FAC | FA33: =EX33&EZ33 -> INGFAC | FB33: R1 | FC33: =GETPIVOTDATA("Sum of "&FB33&" (Out)",$AW$6,"Sub-Sector",EW33) -> 15.46751 | FD33: =GETPIVOTDATA("Sum of "&FB33&" (Out)",$AW$6,"Sub-Sector",EW33,"End-Use",EY33) -> 0.87089561 | FE33: =GETPIVOTDATA("Sum of "&FB33&" (%)",$CH$6,"End-Use Commodity",FA33) -> 0.056304835 | FF33: 0 | FG33: =FC33-((FD33-FF33)/FE33) -> 0
A34: Cement | B34: Steam | C34: Distillate Oil | D34: Distillate Oil | E34: INCEBOLDST | F34: =EndUse(A34,B34,C34,G34) -> #NAME? | G34: TechData_Boiler | H34: 1 | I34: 0 | J34: 0 | K34: 0 | S34: #REF! | T34: =S34 -> #REF! | U34: =T34 -> #REF! | V34: =U34 -> #REF! | W34: =V34 -> #REF! | X34: =W34 -> #REF! | Y34: =X34 -> #REF! | Z34: =Y34 -> #REF! | AA34: =Z34 -> #REF! | AB34: =J34*$H34*S34 -> #REF! | AC34: =K34*$H34*T34 -> #REF! | AD34: =L34*$H34*U34 -> #REF! | AE34: =M34*$H34*V34 -> #REF! | AF34: =N34*$H34*W34 -> #REF! | AG34: =O34*$H34*X34 -> #REF! | AH34: =P34*$H34*Y34 -> #REF! | AI34: =Q34*$H34*Z34 -> #REF! | AJ34: =R34*$H34*AA34 -> #REF! | AK34: =SUM(AB34:AJ34) -> #REF! | AL34: 0 | AM34: 0 | AN34: 0 | AO34: 0 | AP34: 0 | AQ34: 0 | AR34: 0 | AS34: 0 | AT34: 0 | AU34: 0 | AW34: Process Heat | AX34: 10.47338 | AY34: 28.829691 | AZ34: 40.674557 | BA34: 27.549844 | BB34: 17.322024 | BC34: 15.098667 | BD34: 52.452805 | BE34: 19.120399 | BF34: 11.989361 | BG34: 223.51073 | BH34: 0 | BJ34: Glass | BK34: ING | BL34: Feedstock | BM34: FEED | BN34: =BK34&BM34 -> INGFEED | BO34: =IF(ISERROR(GETPIVOTDATA("Sum of "&BO$1&" (Out)",$AW$6,"Sub-Sector",$BJ34,"End-Use",$BL34)),0,GETPIVOTDATA("Sum of "&BO$1&" (Out)",$AW$6,"Sub-Sector",$BJ34,"End-Use",$BL34)) -> 0 | BP34: =IF(ISERROR(GETPIVOTDATA("Sum of "&BP$1&" (Out)",$AW$6,"Sub-Sector",$BJ34,"End-Use",$BL34)),0,GETPIVOTDATA("Sum of "&BP$1&" (Out)",$AW$6,"Sub-Sector",$BJ34,"End-Use",$BL34)) -> 0 | BQ34: =IF(ISERROR(GETPIVOTDATA("Sum of "&BQ$1&" (Out)",$AW$6,"Sub-Sector",$BJ34,"End-Use",$BL34)),0,GETPIVOTDATA("Sum of "&BQ$1&" (Out)",$AW$6,"Sub-Sector",$BJ34,"End-Use",$BL34)) -> 0 | BR34: =IF(ISERROR(GETPIVOTDATA("Sum of "&BR$1&" (Out)",$AW$6,"Sub-Sector",$BJ34,"End-Use",$BL34)),0,GETPIVOTDATA("Sum of "&BR$1&" (Out)",$AW$6,"Sub-Sector",$BJ34,"End-Use",$BL34)) -> 0 | BS34: =IF(ISERROR(GETPIVOTDATA("Sum of "&BS$1&" (Out)",$AW$6,"Sub-Sector",$BJ34,"End-Use",$BL34)),0,GETPIVOTDATA("Sum of "&BS$1&" (Out)",$AW$6,"Sub-Sector",$BJ34,"End-Use",$BL34)) -> 0 | BT34: =IF(ISERROR(GETPIVOTDATA("Sum of "&BT$1&" (Out)",$AW$6,"Sub-Sector",$BJ34,"End-Use",$BL34)),0,GETPIVOTDATA("Sum of "&BT$1&" (Out)",$AW$6,"Sub-Sector",$BJ34,"End-Use",$BL34)) -> 0 | BU34: =IF(ISERROR(GETPIVOTDATA("Sum of "&BU$1&" (Out)",$AW$6,"Sub-Sector",$BJ34,"End-Use",$BL34)),0,GETPIVOTDATA("Sum of "&BU$1&" (Out)",$AW$6,"Sub-Sector",$BJ34,"End-Use",$BL34)) -> 0 | BV34: =IF(ISERROR(GETPIVOTDATA("Sum of "&BV$1&" (Out)",$AW$6,"Sub-Sector",$BJ34,"End-Use",$BL34)),0,GETPIVOTDATA("Sum of "&BV$1&" (Out)",$AW$6,"Sub-Sector",$BJ34,"End-Use",$BL34)) -> 0 | BW34: =IF(ISERROR(GETPIVOTDATA("Sum of "&BW$1&" (Out)",$AW$6,"Sub-Sector",$BJ34,"End-Use",$BL34)),0,GETPIVOTDATA("Sum of "&BW$1&" (Out)",$AW$6,"Sub-Sector",$BJ34,"End-Use",$BL34)) -> 0 | BX34: =BO34/BO39 -> 0 | BY34: =BP34/BP39 -> 0 | BZ34: =BQ34/BQ39 -> 0 | CA34: =BR34/BR39 -> 0 | CB34: =BS34/BS39 -> 0 | CC34: =BT34/BT39 -> 0 | CD34: =BU34/BU39 -> 0 | CE34: =BV34/BV39 -> 0 | CF34: =BW34/BW39 -> 0 | CH34: ICPPRH | CI34: 0.041383542 | CJ34: 0.048751999 | CK34: 0.022917831 | CL34: 0.025966383 | CM34: 0.052381902 | CN34: 0.050742912 | CO34: 0.052529314 | CP34: 0.20049814 | CQ34: 0.12929386 | CS34: IFDFA_DST | CT34: 0.34728213 | CU34: 0.95595087 | CV34: 0.77697164 | CW34: 0.52626136 | CX34: 0.53195955 | CY34: 0.46368023 | CZ34: 1.6108262 | DA34: 2.9369313 | DB34: 1.8415897 | DC34: 9.991453 | DE34: IOTOH_CHP | DF34: =LEFT(DE34,5) -> IOTOH | DG34: =GETPIVOTDATA("Sum of "&DG$1&" (Out)",$CS$6,"Constraint Identifier",$DE34) -> 4.1955879 | DH34: =GETPIVOTDATA("Sum of "&DH$1&" (Out)",$CS$6,"Constraint Identifier",$DE34) -> 4.3909128 | DI34: =GETPIVOTDATA("Sum of "&DI$1&" (Out)",$CS$6,"Constraint Identifier",$DE34) -> 4.4236881 | DJ34: =GETPIVOTDATA("Sum of "&DJ$1&" (Out)",$CS$6,"Constraint Identifier",$DE34) -> 1.3623333 | DK34: =GETPIVOTDATA("Sum of "&DK$1&" (Out)",$CS$6,"Constraint Identifier",$DE34) -> 1.8323299 | DL34: =GETPIVOTDATA("Sum of "&DL$1&" (Out)",$CS$6,"Constraint Identifier",$DE34) -> 2.0150254 | DM34: =GETPIVOTDATA("Sum of "&DM$1&" (Out)",$CS$6,"Constraint Identifier",$DE34) -> 8.4324642 | DN34: =GETPIVOTDATA("Sum of "&DN$1&" (Out)",$CS$6,"Constraint Identifier",$DE34) -> 4.7903109 | DO34: =GETPIVOTDATA("Sum of "&DO$1&" (Out)",$CS$6,"Constraint Identifier",$DE34) -> 3.8369529 | DP34: =IF(SUMIF($DF$8:$DF$380,"="&$DF34,DG$8:DG$380)=0,0,DG34/SUMIF($DF$8:$DF$380,"="&$DF34,DG$8:DG$380)) -> 0.61895014 | DQ34: =IF(SUMIF($DF$8:$DF$380,"="&$DF34,DH$8:DH$380)=0,0,DH34/SUMIF($DF$8:$DF$380,"="&$DF34,DH$8:DH$380)) -> 0.1693237 | DR34: =IF(SUMIF($DF$8:$DF$380,"="&$DF34,DI$8:DI$380)=0,0,DI34/SUMIF($DF$8:$DF$380,"="&$DF34,DI$8:DI$380)) -> 0.21130049 | DS34: =IF(SUMIF($DF$8:$DF$380,"="&$DF34,DJ$8:DJ$380)=0,0,DJ34/SUMIF($DF$8:$DF$380,"="&$DF34,DJ$8:DJ$380)) -> 0.095718536 | DT34: =IF(SUMIF($DF$8:$DF$380,"="&$DF34,DK$8:DK$380)=0,0,DK34/SUMIF($DF$8:$DF$380,"="&$DF34,DK$8:DK$380)) -> 0.10273788 | DU34: =IF(SUMIF($DF$8:$DF$380,"="&$DF34,DL$8:DL$380)=0,0,DL34/SUMIF($DF$8:$DF$380,"="&$DF34,DL$8:DL$380)) -> 0.13277516 | DV34: =IF(SUMIF($DF$8:$DF$380,"="&$DF34,DM$8:DM$380)=0,0,DM34/SUMIF($DF$8:$DF$380,"="&$DF34,DM$8:DM$380)) -> 0.1512118 | DW34: =IF(SUMIF($DF$8:$DF$380,"="&$DF34,DN$8:DN$380)=0,0,DN34/SUMIF($DF$8:$DF$380,"="&$DF34,DN$8:DN$380)) -> 0.33843378 | DX34: =IF(SUMIF($DF$8:$DF$380,"="&$DF34,DO$8:DO$380)=0,0,DO34/SUMIF($DF$8:$DF$380,"="&$DF34,DO$8:DO$380)) -> 0.42519424 | DZ34: ICIST_COA | EA34: 0 | EB34: 0 | EC34: 0.048571268 | ED34: 0 | EE34: 0.035238685 | EF34: 0.044189449 | EG34: 0 | EH34: 0 | EI34: 0 | EO34: Food | EP34: R9 | EQ34: =GETPIVOTDATA("Sum of "&EP34&" (Out)",$AW$6,"Sub-Sector",EO34) -> 97.77029 | ER34: =EQ34/SUM(EQ26:EQ34) -> 0.095760411 | ET34: R6 | EU34: 0.047295037 | EW34: Glass | EX34: ING | EY34: Facilities | EZ34: FAC | FA34: =EX34&EZ34 -> INGFAC | FB34: R2 | FC34: =GETPIVOTDATA("Sum of "&FB34&" (Out)",$AW$6,"Sub-Sector",EW34) -> 42.576852 | FD34: =GETPIVOTDATA("Sum of "&FB34&" (Out)",$AW$6,"Sub-Sector",EW34,"End-Use",EY34) -> 2.3972826 | FE34: =GETPIVOTDATA("Sum of "&FB34&" (%)",$CH$6,"End-Use Commodity",FA34) -> 0.056304835 | FF34: 0 | FG34: =FC34-((FD34-FF34)/FE34) -> 0
A35: Cement | B35: Steam | C35: Natural Gas | D35: Natural Gas | E35: INCEREGNGA | F35: =EndUse(A35,B35,C35,G35) -> #NAME? | G35: TechData_CHP | H35: =1-I35 -> 0.47746598 | I35: 0.52253402 | J35: 0 | K35: 0 | S35: #REF! | T35: =S35 -> #REF! | U35: =T35 -> #REF! | V35: =U35 -> #REF! | W35: =V35 -> #REF! | X35: =W35 -> #REF! | Y35: =X35 -> #REF! | Z35: =Y35 -> #REF! | AA35: =Z35 -> #REF! | AB35: =J35*31.536*$H35*S35 -> #REF! | AC35: =K35*31.536*$H35*T35 -> #REF! | AD35: =L35*31.536*$H35*U35 -> #REF! | AE35: =M35*31.536*$H35*V35 -> #REF! | AF35: =N35*31.536*$H35*W35 -> #REF! | AG35: =O35*31.536*$H35*X35 -> #REF! | AH35: =P35*31.536*$H35*Y35 -> #REF! | AI35: =Q35*31.536*$H35*Z35 -> #REF! | AJ35: =R35*31.536*$H35*AA35 -> #REF! | AK35: =SUM(AB35:AJ35) -> #REF! | AL35: =J35*31.536*$I35*S35 -> #REF! | AM35: =K35*31.536*$I35*T35 -> #REF! | AN35: =L35*31.536*$I35*U35 -> #REF! | AO35: =M35*31.536*$I35*V35 -> #REF! | AP35: =N35*31.536*$I35*W35 -> #REF! | AQ35: =O35*31.536*$I35*X35 -> #REF! | AR35: =P35*31.536*$I35*Y35 -> #REF! | AS35: =Q35*31.536*$I35*Z35 -> #REF! | AT35: =R35*31.536*$I35*AA35 -> #REF! | AU35: =SUM(AL35:AT35) -> #REF! | AW35: Steam | AX35: 0 | AY35: 0 | AZ35: 0 | BA35: 0 | BB35: 0 | BC35: 0 | BD35: 1.0566565 | BE35: 0 | BF35: 0 | BG35: 1.0566565 | BH35: 1.0912917 | BJ35: Glass | BK35: ING | BL35: Machine Drive | BM35: MDR | BN35: =BK35&BM35 -> INGMDR | BO35: =IF(ISERROR(GETPIVOTDATA("Sum of "&BO$1&" (Out)",$AW$6,"Sub-Sector",$BJ35,"End-Use",$BL35)),0,GETPIVOTDATA("Sum of "&BO$1&" (Out)",$AW$6,"Sub-Sector",$BJ35,"End-Use",$BL35)) -> 0.95899524 | BP35: =IF(ISERROR(GETPIVOTDATA("Sum of "&BP$1&" (Out)",$AW$6,"Sub-Sector",$BJ35,"End-Use",$BL35)),0,GETPIVOTDATA("Sum of "&BP$1&" (Out)",$AW$6,"Sub-Sector",$BJ35,"End-Use",$BL35)) -> 2.6397912 | BQ35: =IF(ISERROR(GETPIVOTDATA("Sum of "&BQ$1&" (Out)",$AW$6,"Sub-Sector",$BJ35,"End-Use",$BL35)),0,GETPIVOTDATA("Sum of "&BQ$1&" (Out)",$AW$6,"Sub-Sector",$BJ35,"End-Use",$BL35)) -> 4.5976128 | BR35: =IF(ISERROR(GETPIVOTDATA("Sum of "&BR$1&" (Out)",$AW$6,"Sub-Sector",$BJ35,"End-Use",$BL35)),0,GETPIVOTDATA("Sum of "&BR$1&" (Out)",$AW$6,"Sub-Sector",$BJ35,"End-Use",$BL35)) -> 3.1140725 | BS35: =IF(ISERROR(GETPIVOTDATA("Sum of "&BS$1&" (Out)",$AW$6,"Sub-Sector",$BJ35,"End-Use",$BL35)),0,GETPIVOTDATA("Sum of "&BS$1&" (Out)",$AW$6,"Sub-Sector",$BJ35,"End-Use",$BL35)) -> 1.8886744 | BT35: =IF(ISERROR(GETPIVOTDATA("Sum of "&BT$1&" (Out)",$AW$6,"Sub-Sector",$BJ35,"End-Use",$BL35)),0,GETPIVOTDATA("Sum of "&BT$1&" (Out)",$AW$6,"Sub-Sector",$BJ35,"End-Use",$BL35)) -> 1.6462548 | BU35: =IF(ISERROR(GETPIVOTDATA("Sum of "&BU$1&" (Out)",$AW$6,"Sub-Sector",$BJ35,"End-Use",$BL35)),0,GETPIVOTDATA("Sum of "&BU$1&" (Out)",$AW$6,"Sub-Sector",$BJ35,"End-Use",$BL35)) -> 5.7190932 | BV35: =IF(ISERROR(GETPIVOTDATA("Sum of "&BV$1&" (Out)",$AW$6,"Sub-Sector",$BJ35,"End-Use",$BL35)),0,GETPIVOTDATA("Sum of "&BV$1&" (Out)",$AW$6,"Sub-Sector",$BJ35,"End-Use",$BL35)) -> 2.2118536 | BW35: =IF(ISERROR(GETPIVOTDATA("Sum of "&BW$1&" (Out)",$AW$6,"Sub-Sector",$BJ35,"End-Use",$BL35)),0,GETPIVOTDATA("Sum of "&BW$1&" (Out)",$AW$6,"Sub-Sector",$BJ35,"End-Use",$BL35)) -> 1.3869329 | BX35: =BO35/BO39 -> 0.062000621 | BY35: =BP35/BP39 -> 0.062000621 | BZ35: =BQ35/BQ39 -> 0.074652031 | CA35: =BR35/BR39 -> 0.074652031 | CB35: =BS35/BS39 -> 0.072341787 | CC35: =BT35/BT39 -> 0.072341787 | CD35: =BU35/BU39 -> 0.071387632 | CE35: =BV35/BV39 -> 0.07616836 | CF35: =BW35/BW39 -> 0.07616836 | CH35: ICPSTM | CI35: 0.4120214 | CJ35: 0.30733013 | CK35: 0.11836301 | CL35: 0.0010868015 | CM35: 0.071504952 | CN35: 0.10055685 | CO35: 0.068891996 | CP35: 0.010513158 | CQ35: 0.36191639 | CS35: IFDFA_ELC | CT35: 1.2581906 | CU35: 3.4633754 | CV35: 13.253677 | CW35: 8.9770303 | CX35: 3.1719656 | CY35: 2.76483 | CZ35: 9.605026 | DA35: 4.9574572 | DB35: 3.1085515 | DC35: 50.560103 | DE35: IOTOH_PTC | DF35: =LEFT(DE35,5) -> IOTOH | DG35: =GETPIVOTDATA("Sum of "&DG$1&" (Out)",$CS$6,"Constraint Identifier",$DE35) -> 0 | DH35: =GETPIVOTDATA("Sum of "&DH$1&" (Out)",$CS$6,"Constraint Identifier",$DE35) -> 0.78727737 | DI35: =GETPIVOTDATA("Sum of "&DI$1&" (Out)",$CS$6,"Constraint Identifier",$DE35) -> 0.33977161 | DJ35: =GETPIVOTDATA("Sum of "&DJ$1&" (Out)",$CS$6,"Constraint Identifier",$DE35) -> 0.23013539 | DK35: =GETPIVOTDATA("Sum of "&DK$1&" (Out)",$CS$6,"Constraint Identifier",$DE35) -> 0.40691551 | DL35: =GETPIVOTDATA("Sum of "&DL$1&" (Out)",$CS$6,"Constraint Identifier",$DE35) -> 0.35468613 | DM35: =GETPIVOTDATA("Sum of "&DM$1&" (Out)",$CS$6,"Constraint Identifier",$DE35) -> 1.2321805 | DN35: =GETPIVOTDATA("Sum of "&DN$1&" (Out)",$CS$6,"Constraint Identifier",$DE35) -> 0.40293221 | DO35: =GETPIVOTDATA("Sum of "&DO$1&" (Out)",$CS$6,"Constraint Identifier",$DE35) -> 0.25265685 | DP35: =IF(SUMIF($DF$8:$DF$380,"="&$DF35,DG$8:DG$380)=0,0,DG35/SUMIF($DF$8:$DF$380,"="&$DF35,DG$8:DG$380)) -> 0 | DQ35: =IF(SUMIF($DF$8:$DF$380,"="&$DF35,DH$8:DH$380)=0,0,DH35/SUMIF($DF$8:$DF$380,"="&$DF35,DH$8:DH$380)) -> 0.030359227 | DR35: =IF(SUMIF($DF$8:$DF$380,"="&$DF35,DI$8:DI$380)=0,0,DI35/SUMIF($DF$8:$DF$380,"="&$DF35,DI$8:DI$380)) -> 0.016229424 | DS35: =IF(SUMIF($DF$8:$DF$380,"="&$DF35,DJ$8:DJ$380)=0,0,DJ35/SUMIF($DF$8:$DF$380,"="&$DF35,DJ$8:DJ$380)) -> 0.016169481 | DT35: =IF(SUMIF($DF$8:$DF$380,"="&$DF35,DK$8:DK$380)=0,0,DK35/SUMIF($DF$8:$DF$380,"="&$DF35,DK$8:DK$380)) -> 0.022815562 | DU35: =IF(SUMIF($DF$8:$DF$380,"="&$DF35,DL$8:DL$380)=0,0,DL35/SUMIF($DF$8:$DF$380,"="&$DF35,DL$8:DL$380)) -> 0.023371172 | DV35: =IF(SUMIF($DF$8:$DF$380,"="&$DF35,DM$8:DM$380)=0,0,DM35/SUMIF($DF$8:$DF$380,"="&$DF35,DM$8:DM$380)) -> 0.022095585 | DW35: =IF(SUMIF($DF$8:$DF$380,"="&$DF35,DN$8:DN$380)=0,0,DN35/SUMIF($DF$8:$DF$380,"="&$DF35,DN$8:DN$380)) -> 0.028467019 | DX35: =IF(SUMIF($DF$8:$DF$380,"="&$DF35,DO$8:DO$380)=0,0,DO35/SUMIF($DF$8:$DF$380,"="&$DF35,DO$8:DO$380)) -> 0.02799832 | DZ35: ICIST_DST | EA35: 0 | EB35: 0 | EC35: 0 | ED35: 0 | EE35: 0 | EF35: 0 | EG35: 0 | EH35: 0 | EI35: 0 | EO35: Glass | EP35: R1 | EQ35: =GETPIVOTDATA("Sum of "&EP35&" (Out)",$AW$6,"Sub-Sector",EO35) -> 15.46751 | ER35: =EQ35/SUM(EQ35:EQ43) -> 0.045819967 | ET35: R7 | EU35: 0.11354037 | EW35: Glass | EX35: ING | EY35: Facilities | EZ35: FAC | FA35: =EX35&EZ35 -> INGFAC | FB35: R3 | FC35: =GETPIVOTDATA("Sum of "&FB35&" (Out)",$AW$6,"Sub-Sector",EW35) -> 61.587244 | FD35: =GETPIVOTDATA("Sum of "&FB35&" (Out)",$AW$6,"Sub-Sector",EW35,"End-Use",EY35) -> 3.6733037 | FE35: =GETPIVOTDATA("Sum of "&FB35&" (%)",$CH$6,"End-Use Commodity",FA35) -> 0.059643905 | FF35: 0 | FG35: =FC35-((FD35-FF35)/FE35) -> 0
A36: Food | B36: Electrochemical | C36: Electricity | D36: Electricity | E36: IFDEETCELC | F36: =EndUse(A36,B36,C36,G36) -> #NAME? | G36: TechData_OTR | H36: 1 | I36: 0 | J36: 0.18702146 | K36: 0.066082616 | S36: 1 | T36: 1 | U36: 1 | V36: 1 | W36: 1 | X36: 1 | Y36: 1 | Z36: 1 | AA36: 1 | AB36: =J36*$H36*S36 -> 0.18702146 | AC36: =K36*$H36*T36 -> 0.066082616 | AD36: =L36*$H36*U36 -> 0 | AE36: =M36*$H36*V36 -> 0 | AF36: =N36*$H36*W36 -> 0 | AG36: =O36*$H36*X36 -> 0 | AH36: =P36*$H36*Y36 -> 0 | AI36: =Q36*$H36*Z36 -> 0 | AJ36: =R36*$H36*AA36 -> 0 | AK36: =SUM(AB36:AJ36) -> 0.25310408 | AL36: 0 | AM36: 0 | AN36: 0 | AO36: 0 | AP36: 0 | AQ36: 0 | AR36: 0 | AS36: 0 | AT36: 0 | AU36: 0 | AW36: Inorganic Chemicals | AX36: 9.3310756 | AY36: 23.836793 | AZ36: 45.508028 | BA36: 31.084218 | BB36: 82.531535 | BC36: 61.655429 | BD36: 242.70973 | BE36: 34.291404 | BF36: 20.755389 | BG36: 551.7036 | BH36: 26.136564 | BJ36: Glass | BK36: ING | BL36: Other Heat | BM36: OHT | BN36: =BK36&BM36 -> INGOHT | BO36: =IF(ISERROR(GETPIVOTDATA("Sum of "&BO$1&" (Out)",$AW$6,"Sub-Sector",$BJ36,"End-Use",$BL36)),0,GETPIVOTDATA("Sum of "&BO$1&" (Out)",$AW$6,"Sub-Sector",$BJ36,"End-Use",$BL36)) -> 3.1642394 | BP36: =IF(ISERROR(GETPIVOTDATA("Sum of "&BP$1&" (Out)",$AW$6,"Sub-Sector",$BJ36,"End-Use",$BL36)),0,GETPIVOTDATA("Sum of "&BP$1&" (Out)",$AW$6,"Sub-Sector",$BJ36,"End-Use",$BL36)) -> 8.7100864 | BQ36: =IF(ISERROR(GETPIVOTDATA("Sum of "&BQ$1&" (Out)",$AW$6,"Sub-Sector",$BJ36,"End-Use",$BL36)),0,GETPIVOTDATA("Sum of "&BQ$1&" (Out)",$AW$6,"Sub-Sector",$BJ36,"End-Use",$BL36)) -> 12.641771 | BR36: =IF(ISERROR(GETPIVOTDATA("Sum of "&BR$1&" (Out)",$AW$6,"Sub-Sector",$BJ36,"End-Use",$BL36)),0,GETPIVOTDATA("Sum of "&BR$1&" (Out)",$AW$6,"Sub-Sector",$BJ36,"End-Use",$BL36)) -> 8.5625719 | BS36: =IF(ISERROR(GETPIVOTDATA("Sum of "&BS$1&" (Out)",$AW$6,"Sub-Sector",$BJ36,"End-Use",$BL36)),0,GETPIVOTDATA("Sum of "&BS$1&" (Out)",$AW$6,"Sub-Sector",$BJ36,"End-Use",$BL36)) -> 5.3557125 | BT36: =IF(ISERROR(GETPIVOTDATA("Sum of "&BT$1&" (Out)",$AW$6,"Sub-Sector",$BJ36,"End-Use",$BL36)),0,GETPIVOTDATA("Sum of "&BT$1&" (Out)",$AW$6,"Sub-Sector",$BJ36,"End-Use",$BL36)) -> 4.6682836 | BU36: =IF(ISERROR(GETPIVOTDATA("Sum of "&BU$1&" (Out)",$AW$6,"Sub-Sector",$BJ36,"End-Use",$BL36)),0,GETPIVOTDATA("Sum of "&BU$1&" (Out)",$AW$6,"Sub-Sector",$BJ36,"End-Use",$BL36)) -> 16.217628 | BV36: =IF(ISERROR(GETPIVOTDATA("Sum of "&BV$1&" (Out)",$AW$6,"Sub-Sector",$BJ36,"End-Use",$BL36)),0,GETPIVOTDATA("Sum of "&BV$1&" (Out)",$AW$6,"Sub-Sector",$BJ36,"End-Use",$BL36)) -> 5.9631336 | BW36: =IF(ISERROR(GETPIVOTDATA("Sum of "&BW$1&" (Out)",$AW$6,"Sub-Sector",$BJ36,"End-Use",$BL36)),0,GETPIVOTDATA("Sum of "&BW$1&" (Out)",$AW$6,"Sub-Sector",$BJ36,"End-Use",$BL36)) -> 3.7391564 | BX36: =BO36/BO39 -> 0.20457328 | BY36: =BP36/BP39 -> 0.20457328 | BZ36: =BQ36/BQ39 -> 0.20526606 | CA36: =BR36/BR39 -> 0.20526606 | CB36: =BS36/BS39 -> 0.20513955 | CC36: =BT36/BT39 -> 0.20513955 | CD36: =BU36/BU39 -> 0.20243385 | CE36: =BV36/BV39 -> 0.20534909 | CF36: =BW36/BW39 -> 0.20534909 | CH36: ICTETC | CI36: 0 | CJ36: 0 | CK36: 0 | CL36: 0 | CM36: 0 | CN36: 0 | CO36: 0 | CP36: 0 | CQ36: 0 | CS36: IFDFA_LPG | CT36: 0.10003826 | CU36: 0.27537168 | CV36: 0 | CW36: 0 | CX36: 0.15323653 | CY36: 0.13356796 | CZ36: 0.46401541 | DA36: 0.23073106 | DB36: 0.14467889 | DC36: 1.5016398 | DE36: IOTOH_BIO | DF36: =LEFT(DE36,5) -> IOTOH | DG36: =GETPIVOTDATA("Sum of "&DG$1&" (Out)",$CS$6,"Constraint Identifier",$DE36) -> 0.033764134 | DH36: =GETPIVOTDATA("Sum of "&DH$1&" (Out)",$CS$6,"Constraint Identifier",$DE36) -> 13.736773 | DI36: =GETPIVOTDATA("Sum of "&DI$1&" (Out)",$CS$6,"Constraint Identifier",$DE36) -> 0.30507653 | DJ36: =GETPIVOTDATA("Sum of "&DJ$1&" (Out)",$CS$6,"Constraint Identifier",$DE36) -> 1.8931389 | DK36: =GETPIVOTDATA("Sum of "&DK$1&" (Out)",$CS$6,"Constraint Identifier",$DE36) -> 9.8282107 | DL36: =GETPIVOTDATA("Sum of "&DL$1&" (Out)",$CS$6,"Constraint Identifier",$DE36) -> 7.7792591 | DM36: =GETPIVOTDATA("Sum of "&DM$1&" (Out)",$CS$6,"Constraint Identifier",$DE36) -> 28.63658 | DN36: =GETPIVOTDATA("Sum of "&DN$1&" (Out)",$CS$6,"Constraint Identifier",$DE36) -> 2.7082387 | DO36: =GETPIVOTDATA("Sum of "&DO$1&" (Out)",$CS$6,"Constraint Identifier",$DE36) -> 1.0135561 | DP36: =IF(SUMIF($DF$8:$DF$380,"="&$DF36,DG$8:DG$380)=0,0,DG36/SUMIF($DF$8:$DF$380,"="&$DF36,DG$8:DG$380)) -> 0.004981022 | DQ36: =IF(SUMIF($DF$8:$DF$380,"="&$DF36,DH$8:DH$380)=0,0,DH36/SUMIF($DF$8:$DF$380,"="&$DF36,DH$8:DH$380)) -> 0.52972157 | DR36: =IF(SUMIF($DF$8:$DF$380,"="&$DF36,DI$8:DI$380)=0,0,DI36/SUMIF($DF$8:$DF$380,"="&$DF36,DI$8:DI$380)) -> 0.014572189 | DS36: =IF(SUMIF($DF$8:$DF$380,"="&$DF36,DJ$8:DJ$380)=0,0,DJ36/SUMIF($DF$8:$DF$380,"="&$DF36,DJ$8:DJ$380)) -> 0.13301333 | DT36: =IF(SUMIF($DF$8:$DF$380,"="&$DF36,DK$8:DK$380)=0,0,DK36/SUMIF($DF$8:$DF$380,"="&$DF36,DK$8:DK$380)) -> 0.55106318 | DU36: =IF(SUMIF($DF$8:$DF$380,"="&$DF36,DL$8:DL$380)=0,0,DL36/SUMIF($DF$8:$DF$380,"="&$DF36,DL$8:DL$380)) -> 0.51259519 | DV36: =IF(SUMIF($DF$8:$DF$380,"="&$DF36,DM$8:DM$380)=0,0,DM36/SUMIF($DF$8:$DF$380,"="&$DF36,DM$8:DM$380)) -> 0.51351405 | DW36: =IF(SUMIF($DF$8:$DF$380,"="&$DF36,DN$8:DN$380)=0,0,DN36/SUMIF($DF$8:$DF$380,"="&$DF36,DN$8:DN$380)) -> 0.19133611 | DX36: =IF(SUMIF($DF$8:$DF$380,"="&$DF36,DO$8:DO$380)=0,0,DO36/SUMIF($DF$8:$DF$380,"="&$DF36,DO$8:DO$380)) -> 0.11231782 | DZ36: ICIST_NGA | EA36: 0 | EB36: 0.084483533 | EC36: 0.78980026 | ED36: 0.9152764 | EE36: 0.042040735 | EF36: 0.64694309 | EG36: 0.12809365 | EH36: 0 | EI36: 0.3695897 | EO36: Glass | EP36: R2 | EQ36: =GETPIVOTDATA("Sum of "&EP36&" (Out)",$AW$6,"Sub-Sector",EO36) -> 42.576852 | ER36: =EQ36/SUM(EQ35:EQ43) -> 0.12612695 | ET36: R8 | EU36: 0.085378982 | EW36: Glass | EX36: ING | EY36: Facilities | EZ36: FAC | FA36: =EX36&EZ36 -> INGFAC | FB36: R4 | FC36: =GETPIVOTDATA("Sum of "&FB36&" (Out)",$AW$6,"Sub-Sector",EW36) -> 41.714505 | FD36: =GETPIVOTDATA("Sum of "&FB36&" (Out)",$AW$6,"Sub-Sector",EW36,"End-Use",EY36) -> 2.488016 | FE36: =GETPIVOTDATA("Sum of "&FB36&" (%)",$CH$6,"End-Use Commodity",FA36) -> 0.059643905 | FF36: 0 | FG36: =FC36-((FD36-FF36)/FE36) -> 0
A37: Food | B37: Facilities | C37: Distillate Oil | D37: Distillate Oil | E37: IFDEFACDST | F37: =EndUse(A37,B37,C37,G37) -> #NAME? | G37: TechData_OTR | H37: 1 | I37: 0 | J37: 0.52626136 | K37: 0.53195955 | S37: 1 | T37: 1 | U37: 1 | V37: 1 | W37: 1 | X37: 1 | Y37: 1 | Z37: 1 | AA37: 1 | AB37: =J37*$H37*S37 -> 0.52626136 | AC37: =K37*$H37*T37 -> 0.53195955 | AD37: =L37*$H37*U37 -> 0 | AE37: =M37*$H37*V37 -> 0 | AF37: =N37*$H37*W37 -> 0 | AG37: =O37*$H37*X37 -> 0 | AH37: =P37*$H37*Y37 -> 0 | AI37: =Q37*$H37*Z37 -> 0 | AJ37: =R37*$H37*AA37 -> 0 | AK37: =SUM(AB37:AJ37) -> 1.0582209 | AL37: 0 | AM37: 0 | AN37: 0 | AO37: 0 | AP37: 0 | AQ37: 0 | AR37: 0 | AS37: 0 | AT37: 0 | AU37: 0 | AW37: Electrochemical | AX37: 1.8982445 | AY37: 5.2252284 | AZ37: 9.2433133 | BA37: 6.2607159 | BB37: 9.4927573 | BC37: 8.2743207 | BD37: 28.74501 | BE37: 5.1507816 | BF37: 3.2297747 | BG37: 77.520146 | BH37: 0 | BJ37: Glass | BK37: ING | BL37: Process Heat | BM37: PRH | BN37: =BK37&BM37 -> INGPRH | BO37: =IF(ISERROR(GETPIVOTDATA("Sum of "&BO$1&" (Out)",$AW$6,"Sub-Sector",$BJ37,"End-Use",$BL37)),0,GETPIVOTDATA("Sum of "&BO$1&" (Out)",$AW$6,"Sub-Sector",$BJ37,"End-Use",$BL37)) -> 10.47338 | BP37: =IF(ISERROR(GETPIVOTDATA("Sum of "&BP$1&" (Out)",$AW$6,"Sub-Sector",$BJ37,"End-Use",$BL37)),0,GETPIVOTDATA("Sum of "&BP$1&" (Out)",$AW$6,"Sub-Sector",$BJ37,"End-Use",$BL37)) -> 28.829691 | BQ37: =IF(ISERROR(GETPIVOTDATA("Sum of "&BQ$1&" (Out)",$AW$6,"Sub-Sector",$BJ37,"End-Use",$BL37)),0,GETPIVOTDATA("Sum of "&BQ$1&" (Out)",$AW$6,"Sub-Sector",$BJ37,"End-Use",$BL37)) -> 40.674557 | BR37: =IF(ISERROR(GETPIVOTDATA("Sum of "&BR$1&" (Out)",$AW$6,"Sub-Sector",$BJ37,"End-Use",$BL37)),0,GETPIVOTDATA("Sum of "&BR$1&" (Out)",$AW$6,"Sub-Sector",$BJ37,"End-Use",$BL37)) -> 27.549844 | BS37: =IF(ISERROR(GETPIVOTDATA("Sum of "&BS$1&" (Out)",$AW$6,"Sub-Sector",$BJ37,"End-Use",$BL37)),0,GETPIVOTDATA("Sum of "&BS$1&" (Out)",$AW$6,"Sub-Sector",$BJ37,"End-Use",$BL37)) -> 17.322024 | BT37: =IF(ISERROR(GETPIVOTDATA("Sum of "&BT$1&" (Out)",$AW$6,"Sub-Sector",$BJ37,"End-Use",$BL37)),0,GETPIVOTDATA("Sum of "&BT$1&" (Out)",$AW$6,"Sub-Sector",$BJ37,"End-Use",$BL37)) -> 15.098667 | BU37: =IF(ISERROR(GETPIVOTDATA("Sum of "&BU$1&" (Out)",$AW$6,"Sub-Sector",$BJ37,"End-Use",$BL37)),0,GETPIVOTDATA("Sum of "&BU$1&" (Out)",$AW$6,"Sub-Sector",$BJ37,"End-Use",$BL37)) -> 52.452805 | BV37: =IF(ISERROR(GETPIVOTDATA("Sum of "&BV$1&" (Out)",$AW$6,"Sub-Sector",$BJ37,"End-Use",$BL37)),0,GETPIVOTDATA("Sum of "&BV$1&" (Out)",$AW$6,"Sub-Sector",$BJ37,"End-Use",$BL37)) -> 19.120399 | BW37: =IF(ISERROR(GETPIVOTDATA("Sum of "&BW$1&" (Out)",$AW$6,"Sub-Sector",$BJ37,"End-Use",$BL37)),0,GETPIVOTDATA("Sum of "&BW$1&" (Out)",$AW$6,"Sub-Sector",$BJ37,"End-Use",$BL37)) -> 11.989361 | BX37: =BO37/BO39 -> 0.67712126 | BY37: =BP37/BP39 -> 0.67712126 | BZ37: =BQ37/BQ39 -> 0.66043801 | CA37: =BR37/BR39 -> 0.66043801 | CB37: =BS37/BS39 -> 0.6634845 | CC37: =BT37/BT39 -> 0.6634845 | CD37: =BU37/BU39 -> 0.65473344 | CE37: =BV37/BV39 -> 0.65843844 | CF37: =BW37/BW39 -> 0.65843844 | CH37: ICTFAC | CI37: 0.23256672 | CJ37: 0.16520452 | CK37: 0.16546682 | CL37: 0.20529666 | CM37: 0.071104935 | CN37: 0.12521498 | CO37: 0.13122685 | CP37: 0.24690048 | CQ37: 0.18188236 | CS37: IFDFA_NGA | CT37: 1.5994266 | CU37: 4.4026834 | CV37: 16.038832 | CW37: 10.863482 | CX37: 3.2155836 | CY37: 2.8028495 | CZ37: 9.7371057 | DA37: 8.3001656 | DB37: 5.2045819 | DC37: 62.164711 | DE37: IOTOH_RFL | DF37: =LEFT(DE37,5) -> IOTOH | DG37: =GETPIVOTDATA("Sum of "&DG$1&" (Out)",$CS$6,"Constraint Identifier",$DE37) -> 0.16841657 | DH37: =GETPIVOTDATA("Sum of "&DH$1&" (Out)",$CS$6,"Constraint Identifier",$DE37) -> 0.46359417 | DI37: =GETPIVOTDATA("Sum of "&DI$1&" (Out)",$CS$6,"Constraint Identifier",$DE37) -> 0 | DJ37: =GETPIVOTDATA("Sum of "&DJ$1&" (Out)",$CS$6,"Constraint Identifier",$DE37) -> 0 | DK37: =GETPIVOTDATA("Sum of "&DK$1&" (Out)",$CS$6,"Constraint Identifier",$DE37) -> 0.096741378 | DL37: =GETPIVOTDATA("Sum of "&DL$1&" (Out)",$CS$6,"Constraint Identifier",$DE37) -> 0.084324202 | DM37: =GETPIVOTDATA("Sum of "&DM$1&" (Out)",$CS$6,"Constraint Identifier",$DE37) -> 0.29294248 | DN37: =GETPIVOTDATA("Sum of "&DN$1&" (Out)",$CS$6,"Constraint Identifier",$DE37) -> 0 | DO37: =GETPIVOTDATA("Sum of "&DO$1&" (Out)",$CS$6,"Constraint Identifier",$DE37) -> 0 | DP37: =IF(SUMIF($DF$8:$DF$380,"="&$DF37,DG$8:DG$380)=0,0,DG37/SUMIF($DF$8:$DF$380,"="&$DF37,DG$8:DG$380)) -> 0.024845496 | DQ37: =IF(SUMIF($DF$8:$DF$380,"="&$DF37,DH$8:DH$380)=0,0,DH37/SUMIF($DF$8:$DF$380,"="&$DF37,DH$8:DH$380)) -> 0.017877258 | DR37: =IF(SUMIF($DF$8:$DF$380,"="&$DF37,DI$8:DI$380)=0,0,DI37/SUMIF($DF$8:$DF$380,"="&$DF37,DI$8:DI$380)) -> 0 | DS37: =IF(SUMIF($DF$8:$DF$380,"="&$DF37,DJ$8:DJ$380)=0,0,DJ37/SUMIF($DF$8:$DF$380,"="&$DF37,DJ$8:DJ$380)) -> 0 | DT37: =IF(SUMIF($DF$8:$DF$380,"="&$DF37,DK$8:DK$380)=0,0,DK37/SUMIF($DF$8:$DF$380,"="&$DF37,DK$8:DK$380)) -> 0.0054242439 | DU37: =IF(SUMIF($DF$8:$DF$380,"="&$DF37,DL$8:DL$380)=0,0,DL37/SUMIF($DF$8:$DF$380,"="&$DF37,DL$8:DL$380)) -> 0.0055563364 | DV37: =IF(SUMIF($DF$8:$DF$380,"="&$DF37,DM$8:DM$380)=0,0,DM37/SUMIF($DF$8:$DF$380,"="&$DF37,DM$8:DM$380)) -> 0.0052530743 | DW37: =IF(SUMIF($DF$8:$DF$380,"="&$DF37,DN$8:DN$380)=0,0,DN37/SUMIF($DF$8:$DF$380,"="&$DF37,DN$8:DN$380)) -> 0 | DX37: =IF(SUMIF($DF$8:$DF$380,"="&$DF37,DO$8:DO$380)=0,0,DO37/SUMIF($DF$8:$DF$380,"="&$DF37,DO$8:DO$380)) -> 0 | DZ37: ICOFA_ELC | EA37: 0.7140828 | EB37: 0.7140828 | EC37: 0.71789474 | ED37: 0.71789474 | EE37: 0.55962706 | EF37: 0.55962706 | EG37: 0.55962706 | EH37: 0.8062964 | EI37: 0.8062964 | EO37: Glass | EP37: R3 | EQ37: =GETPIVOTDATA("Sum of "&EP37&" (Out)",$AW$6,"Sub-Sector",EO37) -> 61.587244 | ER37: =EQ37/SUM(EQ35:EQ43) -> 0.18244213 | ET37: R9 | EU37: 0.095760411 | EW37: Glass | EX37: ING | EY37: Facilities | EZ37: FAC | FA37: =EX37&EZ37 -> INGFAC | FB37: R5 | FC37: =GETPIVOTDATA("Sum of "&FB37&" (Out)",$AW$6,"Sub-Sector",EW37) -> 26.107654 | FD37: =GETPIVOTDATA("Sum of "&FB37&" (Out)",$AW$6,"Sub-Sector",EW37,"End-Use",EY37) -> 1.5412436 | FE37: =GETPIVOTDATA("Sum of "&FB37&" (%)",$CH$6,"End-Use Commodity",FA37) -> 0.059034166 | FF37: 0 | FG37: =FC37-((FD37-FF37)/FE37) -> 0
A38: Food | B38: Facilities | C38: Electricity | D38: Electricity | E38: IFDEFACELC | F38: =EndUse(A38,B38,C38,G38) -> #NAME? | G38: TechData_OTR | H38: 1 | I38: 0 | J38: 8.9770303 | K38: 3.1719656 | S38: 1 | T38: 1 | U38: 1 | V38: 1 | W38: 1 | X38: 1 | Y38: 1 | Z38: 1 | AA38: 1 | AB38: =J38*$H38*S38 -> 8.9770303 | AC38: =K38*$H38*T38 -> 3.1719656 | AD38: =L38*$H38*U38 -> 0 | AE38: =M38*$H38*V38 -> 0 | AF38: =N38*$H38*W38 -> 0 | AG38: =O38*$H38*X38 -> 0 | AH38: =P38*$H38*Y38 -> 0 | AI38: =Q38*$H38*Z38 -> 0 | AJ38: =R38*$H38*AA38 -> 0 | AK38: =SUM(AB38:AJ38) -> 12.148996 | AL38: 0 | AM38: 0 | AN38: 0 | AO38: 0 | AP38: 0 | AQ38: 0 | AR38: 0 | AS38: 0 | AT38: 0 | AU38: 0 | AW38: Facilities | AX38: 0.19801857 | AY38: 0.5450785 | AZ38: 0.98849559 | BA38: 0.66953157 | BB38: 1.1908937 | BC38: 1.0380374 | BD38: 3.6061443 | BE38: 0.62847308 | BF38: 0.39408125 | BG38: 9.2587539 | BH38: 0 | BJ38: Glass | BK38: ING | BL38: Steam | BM38: STM | BN38: =BK38&BM38 -> INGSTM | BO38: =IF(ISERROR(GETPIVOTDATA("Sum of "&BO$1&" (Out)",$AW$6,"Sub-Sector",$BJ38,"End-Use",$BL38)),0,GETPIVOTDATA("Sum of "&BO$1&" (Out)",$AW$6,"Sub-Sector",$BJ38,"End-Use",$BL38)) -> 0 | BP38: =IF(ISERROR(GETPIVOTDATA("Sum of "&BP$1&" (Out)",$AW$6,"Sub-Sector",$BJ38,"End-Use",$BL38)),0,GETPIVOTDATA("Sum of "&BP$1&" (Out)",$AW$6,"Sub-Sector",$BJ38,"End-Use",$BL38)) -> 0 | BQ38: =IF(ISERROR(GETPIVOTDATA("Sum of "&BQ$1&" (Out)",$AW$6,"Sub-Sector",$BJ38,"End-Use",$BL38)),0,GETPIVOTDATA("Sum of "&BQ$1&" (Out)",$AW$6,"Sub-Sector",$BJ38,"End-Use",$BL38)) -> 0 | BR38: =IF(ISERROR(GETPIVOTDATA("Sum of "&BR$1&" (Out)",$AW$6,"Sub-Sector",$BJ38,"End-Use",$BL38)),0,GETPIVOTDATA("Sum of "&BR$1&" (Out)",$AW$6,"Sub-Sector",$BJ38,"End-Use",$BL38)) -> 0 | BS38: =IF(ISERROR(GETPIVOTDATA("Sum of "&BS$1&" (Out)",$AW$6,"Sub-Sector",$BJ38,"End-Use",$BL38)),0,GETPIVOTDATA("Sum of "&BS$1&" (Out)",$AW$6,"Sub-Sector",$BJ38,"End-Use",$BL38)) -> 0 | BT38: =IF(ISERROR(GETPIVOTDATA("Sum of "&BT$1&" (Out)",$AW$6,"Sub-Sector",$BJ38,"End-Use",$BL38)),0,GETPIVOTDATA("Sum of "&BT$1&" (Out)",$AW$6,"Sub-Sector",$BJ38,"End-Use",$BL38)) -> 0 | BU38: =IF(ISERROR(GETPIVOTDATA("Sum of "&BU$1&" (Out)",$AW$6,"Sub-Sector",$BJ38,"End-Use",$BL38)),0,GETPIVOTDATA("Sum of "&BU$1&" (Out)",$AW$6,"Sub-Sector",$BJ38,"End-Use",$BL38)) -> 1.0566565 | BV38: =IF(ISERROR(GETPIVOTDATA("Sum of "&BV$1&" (Out)",$AW$6,"Sub-Sector",$BJ38,"End-Use",$BL38)),0,GETPIVOTDATA("Sum of "&BV$1&" (Out)",$AW$6,"Sub-Sector",$BJ38,"End-Use",$BL38)) -> 0 | BW38: =IF(ISERROR(GETPIVOTDATA("Sum of "&BW$1&" (Out)",$AW$6,"Sub-Sector",$BJ38,"End-Use",$BL38)),0,GETPIVOTDATA("Sum of "&BW$1&" (Out)",$AW$6,"Sub-Sector",$BJ38,"End-Use",$BL38)) -> 0 | BX38: =BO38/BO39 -> 0 | BY38: =BP38/BP39 -> 0 | BZ38: =BQ38/BQ39 -> 0 | CA38: =BR38/BR39 -> 0 | CB38: =BS38/BS39 -> 0 | CC38: =BT38/BT39 -> 0 | CD38: =BU38/BU39 -> 0.013189539 | CE38: =BV38/BV39 -> 0 | CF38: =BW38/BW39 -> 0 | CH38: ICTFEED | CI38: 0 | CJ38: 0 | CK38: 0.068424118 | CL38: 0.084894625 | CM38: 0.18216333 | CN38: 0.32078755 | CO38: 0.33618933 | CP38: 0 | CQ38: 0 | CS38: IFDFA_COA | CT38: 0.0014201579 | CU38: 0.0039092168 | CV38: 0.4607097 | CW38: 0.31204963 | CX38: 0.017402946 | CY38: 0.015169203 | CZ38: 0.052697846 | DA38: 0.06550984 | DB38: 0.041077653 | DC38: 0.96994619 | DE38: ICTOH_ELC | DF38: =LEFT(DE38,5) -> ICTOH | DG38: =GETPIVOTDATA("Sum of "&DG$1&" (Out)",$CS$6,"Constraint Identifier",$DE38) -> 0.078034534 | DH38: =GETPIVOTDATA("Sum of "&DH$1&" (Out)",$CS$6,"Constraint Identifier",$DE38) -> 0.21480282 | DI38: =GETPIVOTDATA("Sum of "&DI$1&" (Out)",$CS$6,"Constraint Identifier",$DE38) -> 0.28127754 | DJ38: =GETPIVOTDATA("Sum of "&DJ$1&" (Out)",$CS$6,"Constraint Identifier",$DE38) -> 0.19051597 | DK38: =GETPIVOTDATA("Sum of "&DK$1&" (Out)",$CS$6,"Constraint Identifier",$DE38) -> 0.086328433 | DL38: =GETPIVOTDATA("Sum of "&DL$1&" (Out)",$CS$6,"Constraint Identifier",$DE38) -> 0.075247804 | DM38: =GETPIVOTDATA("Sum of "&DM$1&" (Out)",$CS$6,"Constraint Identifier",$DE38) -> 0.26141105 | DN38: =GETPIVOTDATA("Sum of "&DN$1&" (Out)",$CS$6,"Constraint Identifier",$DE38) -> 0.05999368 | DO38: =GETPIVOTDATA("Sum of "&DO$1&" (Out)",$CS$6,"Constraint Identifier",$DE38) -> 0.03761877 | DP38: =IF(SUMIF($DF$8:$DF$380,"="&$DF38,DG$8:DG$380)=0,0,DG38/SUMIF($DF$8:$DF$380,"="&$DF38,DG$8:DG$380)) -> 0.2032817 | DQ38: =IF(SUMIF($DF$8:$DF$380,"="&$DF38,DH$8:DH$380)=0,0,DH38/SUMIF($DF$8:$DF$380,"="&$DF38,DH$8:DH$380)) -> 0.1332993 | DR38: =IF(SUMIF($DF$8:$DF$380,"="&$DF38,DI$8:DI$380)=0,0,DI38/SUMIF($DF$8:$DF$380,"="&$DF38,DI$8:DI$380)) -> 0.063473208 | DS38: =IF(SUMIF($DF$8:$DF$380,"="&$DF38,DJ$8:DJ$380)=0,0,DJ38/SUMIF($DF$8:$DF$380,"="&$DF38,DJ$8:DJ$380)) -> 0.064378153 | DT38: =IF(SUMIF($DF$8:$DF$380,"="&$DF38,DK$8:DK$380)=0,0,DK38/SUMIF($DF$8:$DF$380,"="&$DF38,DK$8:DK$380)) -> 0.058481307 | DU38: =IF(SUMIF($DF$8:$DF$380,"="&$DF38,DL$8:DL$380)=0,0,DL38/SUMIF($DF$8:$DF$380,"="&$DF38,DL$8:DL$380)) -> 0.058481307 | DV38: =IF(SUMIF($DF$8:$DF$380,"="&$DF38,DM$8:DM$380)=0,0,DM38/SUMIF($DF$8:$DF$380,"="&$DF38,DM$8:DM$380)) -> 0.058481307 | DW38: =IF(SUMIF($DF$8:$DF$380,"="&$DF38,DN$8:DN$380)=0,0,DN38/SUMIF($DF$8:$DF$380,"="&$DF38,DN$8:DN$380)) -> 0.25596064 | DX38: =IF(SUMIF($DF$8:$DF$380,"="&$DF38,DO$8:DO$380)=0,0,DO38/SUMIF($DF$8:$DF$380,"="&$DF38,DO$8:DO$380)) -> 0.25596064 | DZ38: ICOFA_NGA | EA38: 0.2859172 | EB38: 0.2859172 | EC38: 0.28210526 | ED38: 0.28210526 | EE38: 0.44037294 | EF38: 0.44037294 | EG38: 0.44037294 | EH38: 0.1937036 | EI38: 0.1937036 | EO38: Glass | EP38: R4 | EQ38: =GETPIVOTDATA("Sum of "&EP38&" (Out)",$AW$6,"Sub-Sector",EO38) -> 41.714505 | ER38: =EQ38/SUM(EQ35:EQ43) -> 0.12357239 | ET38: Glass | EU38: 1 | EW38: Glass | EX38: ING | EY38: Facilities | EZ38: FAC | FA38: =EX38&EZ38 -> INGFAC | FB38: R6 | FC38: =GETPIVOTDATA("Sum of "&FB38&" (Out)",$AW$6,"Sub-Sector",EW38) -> 22.756624 | FD38: =GETPIVOTDATA("Sum of "&FB38&" (Out)",$AW$6,"Sub-Sector",EW38,"End-Use",EY38) -> 1.3434183 | FE38: =GETPIVOTDATA("Sum of "&FB38&" (%)",$CH$6,"End-Use Commodity",FA38) -> 0.059034166 | FF38: 0 | FG38: =FC38-((FD38-FF38)/FE38) -> 0
