Workbook
Name _1995_Implicit_GDP_Deflator: Lighting!#REF!
Name _2001_Implicit_GDP_Deflator: Lighting!#REF!
Name act_foundp: #REF!
Name act_foundp: '[1]WithReg-Coke'!$N$120
Name act_furnp: #REF!
Name act_furnp: '[1]WithReg-Coke'!$M$120
Name AnswerData: #REF!
Name AnswerData: #REF!
Name avg_water_heater_PJ: #REF!
Name avg_water_heater_PJ: #REF!
Name avg_water_heater_PJ: #REF!
Name avg_water_heater_PJ: #REF!
Name avg_water_heater_PJ: #REF!
Name avg_water_heater_PJ: #REF!
Name base_foundp: #REF!
Name base_foundp: #REF!
Name base_furnp: #REF!
Name base_furnp: #REF!
Name base_steelp: #REF!
Name base_steelp: '[1]Baseline-Steel Mill Products'!$K$39
Name bprint: #REF!
Name bprint: #REF!
Name btu_per_mmbtu: 'Conv Factors'!$C$13
Name btu_per_watthr: #REF!
Name btu_per_watthr: 'Conv Factors'!$C$6
Name BTUtoPJ: 'conversion factors'!$B$7
Name cfm_hrs_per_trillion_cfm_hrs: 'Conv Factors'!$C$9
Name CMM_SUPPLY_CRV_TABLE: #REF!
Name CMM_SUPPLY_CRV_TABLE: [2]cum2025curves!#REF!
Name cprint: #REF!
Name cprint: #REF!
Name days_per_year: #REF!
Name Days_per_year: 'Conv Factors'!$C$4
Name DCF: #REF!
Name DCF: [3]ReadMe!$D$49
Name DenatEthPJperGal: 'conversion factors'!$B$17
Name dollar____per__m: #REF!
Name dollar____per__m: 'Conv Factors'!$C$8
Name dolomite_conv: #REF!
Name dolomite_conv: #REF!
Name dolomite_conv_13: #REF!
Name dolomite_conv_13: #REF!
Name Domestic: #REF!
Name Domestic: '[4]Dom Calcs'!$P$22
Name Domestic_12: #REF!
Name Domestic_12: '[5]Dom Calcs'!$P$22
Name Domestic_13: #REF!
Name Domestic_13: '[6]Dom Calcs'!$P$22
Name EthanolPJperGal: 'conversion factors'!$B$16
Name Excel_BuiltIn__FilterDatabase_2: #REF!
Name Excel_BuiltIn__FilterDatabase_2: '[7]CRF Reporter'!$A$1:$AA$55
Name exch_rate: #REF!
Name exch_rate: #REF!
Name FID_1: #REF!
Name FID_1: [8]AGR_Fuels!$A$2
Name fitfile: #REF!
Name fitfile: [9]MODEL!$D$38
Name FO2_l_to_gj: 'Conv Factors'!$C$23
Name FO4_l_to_gj: 'Conv Factors'!$C$24
Name FO6_l_to_gj: 'Conv Factors'!$C$25

Sheet ANSv6.1-Commodities
A1: ANSWER-Commodities
B7: CommName | C7: CommDesc | D7: CommUnit | E7: Set Memberships | F7: Comment

Sheet ANSv6.1-Technologies
A1: ANSWER-Technologies
B7: TechName | C7: TechDesc | D7: TACTUnit | E7: TCAPUnit | F7: Set Memberships | G7: Comment

Sheet Commodities
B1: Commodities | D1: _GLOBAL,R0,R1,R2,R3,R4,R5,R6
B6: ~FI_Comm
B7: Region | C7: Csets | D7: CommName | E7: CommDesc | F7: Unit | G7: LimType | H7: CTSLvl | I7: PeakTS | J7: Ctype
B8: *Demands
B9: R2,R3,R4,R5,R6 | C9: DEM | D9: RSC | E9: Residential Cooling | F9: PJ
B10: * | C10: DEM | D10: RFZ | E10: Residential Freezing | F10: PJ
B11: R2,R3,R4,R5,R6 | C11: DEM | D11: RSH | E11: Residential Heating | F11: PJ
B12: R2,R3,R4,R5,R6 | C12: DEM | D12: RLT | E12: Residential Lighting | F12: bn-lum-yr
B13: R2,R3,R4,R5,R6 | C13: DEM | D13: ROE | E13: Residential Other Appliances - ELC | F13: PJ
B14: R2,R3,R4,R5,R6 | C14: DEM | D14: ROG | E14: Residential Other Appliances - NGA | F14: PJ
B15: * | C15: DEM | D15: ROL | E15: Residential Other Appliances - LPG | F15: PJ
B16: * | C16: DEM | D16: RRF | E16: Residential Refrigeration | F16: PJ
B17: R2,R3,R4,R5,R6 | C17: DEM | D17: RWH | E17: Residential Water Heating | F17: PJ
B18: *Energy Carriers
B19: R2,R3,R4,R5,R6 | C19: NRG | D19: RESELC | E19: Electricity to Residential Sector | F19: PJ | H19: DAYNITE | I19: ANNUAL | J19: ELC
B20: R2,R3,R4,R5,R6 | C20: NRG | D20: RESNGAEA | E20: Natural Gas to Residential Sector | F20: PJ
B21: R2,R3,R4,R5,R6 | C21: NRG | D21: RESCOAEA | E21: Coal to Residential Sector | F21: PJ
B22: R2,R3,R4,R5,R6 | C22: NRG | D22: RESDSLEA | E22: Diesel to Residential Sector | F22: PJ
B23: *R2,R3,R4,R5,R6 | C23: NRG | D23: RESKEREA | E23: Kerosene to Residential Sector | F23: PJ
B24: *R2,R3,R4,R5,R6 | C24: NRG | D24: RESLPGEA | E24: LPG to Residential Sector | F24: PJ
B25: *R2,R3,R4,R5,R6 | C25: NRG | D25: RESBIOEA | E25: Biomass-wood to Residential Sector after emissions | F25: PJ
B26: *CHP Energy Carriers
B27: R1,R2,R3,R4,R5,R6 | C27: NRG | D27: RESSTNUC | E27: STM from Residential NGA Utility-scale CHP | F27: PJ
B28: R1,R2,R3,R4,R5,R6 | C28: NRG | D28: RESSTBUC | E28: STM from Residential DST Utility-scale CHP | F28: PJ
B29: R2,R3,R4,R5,R6 | C29: NRG | D29: RESSTNB | E29: STM from Commercial NGA Boilers | F29: PJ
B30: R2,R3,R4,R5,R6 | C30: NRG | D30: RESSTDB | E30: STM from Commercial DST Boilers | F30: PJ
B31: *Residential End Use Water Commodities for Demand Pass Through Technologies
B32: R2,R3,R4,R5,R6 | C32: MAT | D32: RBLDLEDMY | E32: Dummy water commodity for low eff buildings | F32: Mt
B33: *R2,R3,R4,R5,R6 | C33: MAT | D33: RBLDMEDMY | E33: Dummy water commodity for medium eff buildings | F33: Mt
B34: R2,R3,R4,R5,R6 | C34: MAT | D34: RBLDHEDMY | E34: Dummy water commodity for high eff buildings | F34: Mt
B35: R2,R3,R4,R5,R6 | C35: MAT | D35: RBROOFDMY | E35: Dummy water commodity for black roofs | F35: Mt
B36: R2,R3,R4,R5,R6 | C36: MAT | D36: RWTROOFDMY | E36: Dummy water commodity for white roofs | F36: Mt
B37: R2,R3,R4,R5,R6 | C37: MAT | D37: RGRF6DMY | E37: Dummy water commodity for green roofs | F37: Mt
B38: R2,R3,R4,R5,R6 | C38: MAT | D38: RGRF12DMY | E38: Dummy water commodity for green roofs | F38: Mt
B39: *Roof/GI Heating & Cooling Commodities
B40: *R2,R3,R4,R5,R6 | C40: NRG | D40: RHCRFBLK | E40: Heating/cooling from black roofs | F40: PJ
B41: *R2,R3,R4,R5,R6 | C41: NRG | D41: RHCRFWT | E41: Heating/cooling from white roofs | F41: PJ
B42: *R2,R3,R4,R5,R6 | C42: NRG | D42: RHCRFG6 | E42: Heating/cooling from 6 inch green roof | F42: PJ
B43: *R2,R3,R4,R5,R6 | C43: NRG | D43: RHCRFG12 | E43: Heating/cooling from 12 inch green roof | F43: PJ
B44: *Demand Commodities for NYC Population
B45: *
B46: R2,R3,R4,R5,R6 | C46: DEM | D46: POPDMRES | E46: Water Energy Demand per Capita | F46: Mt
B47: *R2,R3,R4,R5,R6 | C47: DEM | D47: POPBKRES | E47: Population Brooklyn | F47: Mt
B48: *R2,R3,R4,R5,R6 | C48: DEM | D48: POPBXRES | E48: Population Bronx | F48: Mt
B49: *R2,R3,R4,R5,R6 | C49: DEM | D49: POPMHRES | E49: Population Manhattan | F49: Mt
B50: *R2,R3,R4,R5,R6 | C50: DEM | D50: POPSIRES | E50: Population Staten Island | F50: Mt
B51: *R2,R3,R4,R5,R6 | C51: DEM | D51: POPQNRES | E51: Population Queens | F51: Mt
B52: *
B53: *Emissions
B54: R2,R3,R4,R5,R6 | C54: ENV | D54: CO2R | E54: CO2 from the residential sector | F54: kt
B55: R2,R3,R4,R5,R6 | C55: ENV | D55: NOXR | E55: NOx from the residential sector | F55: kt
B56: R2,R3,R4,R5,R6 | C56: ENV | D56: PM10R | E56: PM10 from the residential sector | F56: kt
B57: R2,R3,R4,R5,R6 | C57: ENV | D57: SO2R | E57: SO2 from the residential sector | F57: kt
B58: R2,R3,R4,R5,R6 | C58: ENV | D58: NOX2CR | E58: Nox species for emission tracking | F58: kt
B59: R2,R3,R4,R5,R6 | C59: NRG | D59: RESNGA | E59: Natural Gas to Residential Sector | F59: PJ
B60: R2,R3,R4,R5,R6 | C60: NRG | D60: RESDSL | E60: Distillate-Heating Oil No. 2 to the Residential Sector | F60: PJ
B61: *R2,R3,R4,R5,R6 | C61: NRG | D61: RESCOA | E61: Coal to Residential Sector | F61: PJ
B62: *R2,R3,R4,R5,R6 | C62: NRG | D62: RESBIO | E62: Biomass to Residential | F62: PJ
B63: *R2,R3,R4,R5,R6 | C63: NRG | D63: RESKER | E63: Kerosene and Other Refined Products to the Residential Sector | F63: PJ
B64: *R2,R3,R4,R5,R6 | C64: NRG | D64: RESLPG | E64: LPG to the Residential Sector | F64: PJ
B65: R2,R3,R4,R5,R6 | C65: NRG | D65: SOLRES | E65: Solar Energy for Residential Sector | F65: PJ
B66: *Energy Carriers
B67: R2,R3,R4,R5,R6 | C67: NRG | D67: ELC | E67: Electricity | F67: PJ
B68: R2,R3,R4,R5,R6 | C68: NRG | D68: SOL | E68: Solar Energy | F68: PJ
B69: *INFES Backstop
B70: R2,R3,R4,R5,R6 | C70: NRG | D70: ZZDMY | E70: Dummy commodity for the ZZ-backstop no-INFES processes | F70: PJ
B71: *Emissions
B72: R2,R3,R4,R5,R6 | C72: ENV | D72: CO2 | E72: Carbon dioxide | F72: Mt
B73: R2,R3,R4,R5,R6 | C73: ENV | D73: NOX | E73: Nitrogen oxide | F73: kt
B74: R2,R3,R4,R5,R6 | C74: ENV | D74: PM10 | E74: Particulate matter | F74: kt
B75: R2,R3,R4,R5,R6 | C75: ENV | D75: PM25 | E75: Fine particulate matter | F75: kt
B76: R2,R3,R4,R5,R6 | C76: ENV | D76: VOC | E76: Volatile organic compounds | F76: kt
B77: R2,R3,R4,R5,R6 | C77: ENV | D77: CO | E77: Carbon monoxide | F77: kt
B78: R2,R3,R4,R5,R6 | C78: ENV | D78: CH4 | E78: Methane | F78: kt
B79: R2,R3,R4,R5,R6 | C79: ENV | D79: N2O | E79: N2O | F79: kt
B80: R2,R3,R4,R5,R6 | C80: ENV | D80: BC | E80: Black carbon | F80: kt
B81: R2,R3,R4,R5,R6 | C81: ENV | D81: OC | E81: Organic carbon | F81: kt
B82: R2,R3,R4,R5,R6 | C82: ENV | D82: SO2 | E82: Sulfur dioxide | F82: kt
B83: *
B84: *R2,R3,R4,R5,R6 | C84: MAT | D84: WCRT | E84: Water supply from the Croton System | F84: Mt
B85: *R2,R3,R4,R5,R6 | C85: MAT | D85: WCTDE | E85: Water supply from the Catskill-Delaware System | F85: Mt
B86: *R2,R3,R4,R5,R6 | C86: MAT | D86: WFLT | E86: Water filtered for end use purposes | F86: Mt
B87: *R2,R3,R4,R5,R6 | C87: MAT | D87: WSLT | E87: Saline or greywater supply from NYC Harbor and Rivers | F87: Mt
B88: R2,R3,R4,R5,R6 | C88: MAT | D88: WRAIN | E88: Annual rainfall as an initial supply material | F88: Mt
B89: *R2,R3,R4,R5,R6 | C89: MAT | D89: WROOF | E89: Rain falling on NYC rooftops | F89: Mt
B90: R2,R3,R4,R5,R6 | C90: MAT | D90: WDRK | E90: Treated water used by end use customers | F90: Mt
B91: *R2,R3,R4,R5,R6 | C91: MAT | D91: WSWR | E91: Stormwater flowing to pump stations | F91: Mt
B92: *R2,R3,R4,R5,R6 | C92: MAT | D92: WWWTPX | E92: Building wasterwater pumped to WWTPs | F92: Mt
B93: *R2,R3,R4,R5,R6 | C93: MAT | D93: WWWTPY | E93: Stormwater pumped to WWTPs | F93: Mt
B94: *R2,R3,R4,R5,R6 | C94: MAT | D94: WDSGSLT | E94: Discharged saline water from end use customers and ELC sector | F94: Mt
B95: *R2,R3,R4,R5,R6 | C95: MAT | D95: WDSGTRT | E95: Discharged water that has been treated by WWTP | F95: Mt
... B97: R2,R3,R4,R5,R6 | C97: MAT | D97: ZZDMYH2O | E97: Dummy water commodity to meet INFES demand | F97: Mt
B98: *
B99: *Industrial End Use Water Demand
B100: *
B101: *R2,R3,R4,R5,R6 | C101: DEM | D101: IWROOFDM | E101: Demand for rainfall on roofs | F101: Mt
B102: *R2,R3,R4,R5,R6 | C102: MAT | D102: IWROOF | E102: Rain on industrial roofs | F102: Mt
B103: *R2,R3,R4,R5,R6 | C103: MAT | D103: IWDRK | E103: Drinking water | F103: Mt
B104: *R2,R3,R4,R5,R6 | C104: MAT | D104: IWDSGTRT | E104: Discharged wastewater | F104: Mt
B105: *R2,R3,R4,R5,R6 | C105: MAT | D105: IWCW | E105: Industrial clothes washing demand | F105: Mt
...

Sheet Technologies
B1: Technologies | D1: _GLOBAL,R0,R1,R2,R3,R4,R5,R6
B6: ~FI_Process
B7: Region | C7: Sets | D7: TechName | E7: TechDesc | F7: Tact | G7: Tcap | H7: PrimaryCG | I7: Vintage | J7: Tslvl
B8: *Space Heating
B9: *Electric Radiant
B10: =TechData_DMD!A10 -> R2,R3,R4,R5,R6 | C10: DMD | D10: =TechData_DMD!B10 -> RSHERDV110 | E10: =TechData_DMD!C10 -> Electric Radiant Ver1.RSH.ELC.10 | F10: PJ | G10: PJ/a
B11: *Electric Resistance Furnaces
B12: *Electric Heat Pump
B13: =TechData_DMD!A13 -> R2,R3,R4,R5,R6 | C13: DMD | D13: =TechData_DMD!B13 -> RSHEHPV110 | E13: =TechData_DMD!C13 -> Electric Heat Pump Ver1.RSH.ELC.10 | F13: PJ | G13: PJ/a
B14: *Natural Gas Furnace
B15: =TechData_DMD!A15 -> R2,R3,R4,R5,R6 | C15: DMD | D15: =TechData_DMD!B15 -> RSHNFRV110 | E15: =TechData_DMD!C15 -> Natural Gas Furnace Ver1.RSH.NGA.10 | F15: PJ | G15: PJ/a
B16: *Natural Gas Radiant
B17: =TechData_DMD!A17 -> R2,R3,R4,R5,R6 | C17: DMD | D17: =TechData_DMD!B17 -> RSHNRDV110 | E17: =TechData_DMD!C17 -> Natural Gas Radiant Ver1.RSH.NGA.10 | F17: PJ | G17: PJ/a
B18: *Kerosene Furnace
B19: *Liquid Gas Furnace
B20: *Distillate Furnace
B21: =TechData_DMD!A21 -> R2,R3,R4,R5,R6 | C21: DMD | D21: =TechData_DMD!B21 -> RSHDFRV110 | E21: =TechData_DMD!C21 -> Distillate Furnace Ver1.RSH.DST.10 | F21: PJ | G21: PJ/a
B22: *Distillate Radiant
B23: =TechData_DMD!A23 -> R2,R3,R4,R5,R6 | C23: DMD | D23: =TechData_DMD!B23 -> RSHDRDV110 | E23: =TechData_DMD!C23 -> Distillate Radiant Ver1.RSH.DST.10 | F23: PJ | G23: PJ/a
B24: *Boiler district energy
B25: R4 | C25: DMD | D25: =TechData_CHP!B7 -> RESBLDBS05 | E25: =TechData_CHP!C7 -> RES.DSL.BOILER.DISTRICTHEAT.BS | F25: PJ | G25: PJ/a
B26: R4 | C26: DMD | D26: =TechData_CHP!B8 -> RESBLNG10 | E26: =TechData_CHP!C8 -> RES.NG.BOILER.DISTRICTHEAT.10 | F26: PJ | G26: PJ/a
B27: *UTILITY SCALE CHP - SH
B28: R4 | C28: DMD | D28: =TechData_DMD!B25 -> RSHNUTIBOI | E28: =TechData_DMD!C25 -> RSH.NG.UTILITY.BOILER | F28: PJ | G28: PJa
B29: R4 | C29: DMD | D29: =TechData_DMD!B26 -> RSHNUTICHP | E29: =TechData_DMD!C26 -> RSH.NG.UTILITY.CHP | F29: PJ | G29: PJa
B30: R4 | C30: DMD | D30: =TechData_DMD!B27 -> RSHBUTICHP | E30: =TechData_DMD!C27 -> RSH.DSL.UTILITY.CHP | F30: PJ | G30: PJa
B31: *Wood
B32: *Geothermal Heat Pump
B33: *Natural Gas Heat Pump
B34: *Space Cooling
B35: *Room AC
B36: =TechData_DMD!A33 -> R2,R3,R4,R5,R6 | C36: DMD | D36: =TechData_DMD!B33 -> RSCRACV110 | E36: =TechData_DMD!C33 -> Room AC Ver1.RSC.ELC.10 | F36: PJ | G36: PJ/a
B37: *Central AC
B38: =TechData_DMD!A35 -> R2,R3,R4,R5,R6 | C38: DMD | D38: =TechData_DMD!B35 -> RSCCACV110 | E38: =TechData_DMD!C35 -> Central AC Ver1.RSC.ELC.10 | F38: PJ | G38: PJ/a
B39: *Portable AC
B40: *Electric Heat Pump
B41: =TechData_DMD!A38 -> R2,R3,R4,R5,R6 | C41: DMD | D41: =TechData_DMD!B38 -> RSCEHPV110 | E41: =TechData_DMD!C38 -> Electric Heat Pump Ver1.RSC.ELC.10 | F41: PJ | G41: PJ/a
B42: *Geothermal Heat Pump
B43: *Natural Gas Heat Pump
B44: *Water Heating
B45: *Natural Gas
B46: =TechData_DMD!A43 -> R2,R3,R4,R5,R6 | C46: DMD | D46: =TechData_DMD!B43 -> RWHNWHV110 | E46: =TechData_DMD!C43 -> Natural Gas Ver1.RWH.NGA.10 | F46: PJ | G46: PJ/a
B47: *Electric
B48: =TechData_DMD!A45 -> R2,R3,R4,R5,R6 | C48: DMD | D48: =TechData_DMD!B45 -> RWHEWHV110 | E48: =TechData_DMD!C45 -> Electric Ver1.RWH.ELC.10 | F48: PJ | G48: PJ/a
B49: *Distillate
B50: =TechData_DMD!A47 -> R2,R3,R4,R5,R6 | C50: DMD | D50: =TechData_DMD!B47 -> RWHDWHV110 | E50: =TechData_DMD!C47 -> Distillate Ver1.RWH.DSL.10 | F50: PJ | G50: PJ/a
B51: *UTILITY SCALE CHP - SH
B52: R4 | C52: DMD | D52: =TechData_DMD!B49 -> RWHNUTIBOI | E52: =TechData_DMD!C49 -> RWH.NG.UTILITY.BOILER | F52: PJ | G52: PJa
B53: R4 | C53: DMD | D53: =TechData_DMD!B50 -> RWHNUTICHP | E53: =TechData_DMD!C50 -> RWH.NG.UTILITY.CHP | F53: PJ | G53: PJa
B54: R4 | C54: DMD | D54: =TechData_DMD!B51 -> RWHBUTICHP | E54: =TechData_DMD!C51 -> RWH.DSL.UTILITY.CHP | F54: PJ | G54: PJa
B55: *Gas
B56: *Solar
B57: *Refrigeration
B58: *Freezer
B59: =Lighting!B21 -> * General Services Lamps
B60: =TechData_DMD!A57 -> R2,R3,R4,R5,R6 | C60: DMD | D60: =TechData_DMD!B57 -> RLTGINC10 | E60: =TechData_DMD!C57 -> RLT.GSL.INC.10 | F60: bn-lum-yr | G60: bn-lum
B61: =TechData_DMD!A58 -> R2,R3,R4,R5,R6 | C61: DMD | D61: =TechData_DMD!B58 -> RLTGCFL10 | E61: =TechData_DMD!C58 -> RLT.GSL.CFL.10 | F61: bn-lum-yr | G61: bn-lum
B62: =TechData_DMD!A59 -> R2,R3,R4,R5,R6 | C62: DMD | D62: =TechData_DMD!B59 -> RLTRINC10 | E62: =TechData_DMD!C59 -> RLT.REF.INC.10 | F62: bn-lum-yr | G62: bn-lum
B63: =TechData_DMD!A60 -> R2,R3,R4,R5,R6 | C63: DMD | D63: =TechData_DMD!B60 -> RLTLFL10 | E63: =TechData_DMD!C60 -> RLT.LFL.10 | F63: bn-lum-yr | G63: bn-lum
B64: =TechData_DMD!A61 -> R2,R3,R4,R5,R6 | C64: DMD | D64: =TechData_DMD!B61 -> RLTEXTBS | E64: =TechData_DMD!C61 -> RLT.EXT.BS | F64: bn-lum-yr | G64: bn-lum
B65: * Other
B66: =TechData_DMD!A63 -> R2,R3,R4,R5,R6 | C66: DMD | D66: =TechData_DMD!B63 -> ROTHCELC | E66: =TechData_DMD!C63 -> Residential Other - Electric | F66: PJ | G66: PJ/a
B67: =TechData_DMD!A64 -> R2,R3,R4,R5,R6 | C67: DMD | D67: =TechData_DMD!B64 -> ROTHNGA | E67: =TechData_DMD!C64 -> Residential Other - NGA | F67: PJ | G67: PJ/a
B68: =TechData_DMD!A65 -> * Dummy/Pass Through Technologies for NYC LITE Model to Meet Populaiton Demand | F68: PJ | G68: PJ/a
B69: =TechData_DMD!A66 -> R2,R3,R4,R5,R6 | C69: DMD | D69: =TechData_DMD!B66 -> RBLDHEDM | E69: =TechData_DMD!C66 -> Residential Building High Eff | F69: PJ | G69: PJ/a
B70: =TechData_DMD!A67 -> R2,R3,R4,R5,R6 | C70: DMD | D70: =TechData_DMD!B67 -> RBLDLEDM | E70: =TechData_DMD!C67 -> Residential Building Low Eff | F70: PJ | G70: PJ/a
B71: =TechData_DMD!A68 -> R2,R3,R4,R5,R6 | C71: DMD | D71: =TechData_DMD!B68 -> RBROOFDM | E71: =TechData_DMD!C68 -> Residential Sector Black Roof | F71: PJ | G71: PJ/a
B72: =TechData_DMD!A69 -> R2,R3,R4,R5,R6 | C72: DMD | D72: =TechData_DMD!B69 -> RWTROOFDM | E72: =TechData_DMD!C69 -> Residential Sector White Roof | F72: PJ | G72: PJ/a
B73: =TechData_DMD!A70 -> R2,R3,R4,R5,R6 | C73: DMD | D73: =TechData_DMD!B70 -> RGROOF6DM | E73: =TechData_DMD!C70 -> Residential Sector Green Roof 6 Inch Depth | F73: PJ | G73: PJ/a
B74: =TechData_DMD!A71 -> R2,R3,R4,R5,R6 | C74: DMD | D74: =TechData_DMD!B71 -> RGROOF12DM | E74: =TechData_DMD!C71 -> Residential Sector Green Roof 12 Inch Depth | F74: PJ | G74: PJ/a
B75: =TechData_DMD!A72 -> * Green Infrastructure Heating & Cooling Technologies | F75: PJ | G75: PJ/a
B76: * Collectors
B77: =TechData_SESC!A7 -> R2,R3,R4,R5,R6 | C77: PRE | D77: =TechData_SESC!B7 -> SCRESELC | E77: =TechData_SESC!C7 -> Collector: ELC to RES | F77: PJ | G77: PJ/a | J77: DAYNITE
B78: * Solar and Wind energy conversion technologies
B79: R2,R3,R4,R5,R6 | C79: ELE | D79: =TechData_SolarPV!B7 -> ESOLPVRES | E79: =TechData_SolarPV!C7 -> Solar PV Distributed Residential Generation | F79: PJ | G79: GW | J79: DAYNITE
B80: * Emissions Accounting
B81: ='TechData-Emis'!A8 -> R2,R3,R4,R5,R6 | C81: PRE | D81: ='TechData-Emis'!B8 -> SERESNGA | E81: ='TechData-Emis'!C8 -> Emissions: NGA to RES | F81: PJ | G81: PJ/a
B82: ='TechData-Emis'!A10 -> R2,R3,R4,R5,R6 | C82: PRE | D82: ='TechData-Emis'!B10 -> SERESDSL | E82: ='TechData-Emis'!C10 -> Emissions: DSL to RES | F82: PJ | G82: PJ/a
B83: * DMY Backstop Technologies
B84: R2,R3,R4,R5,R6 | C84: DMD | D84: ZZRLT | E84: Residential Lighting - ZZINFES backstop | F84: PJ | G84: PJ/a
B85: R2,R3,R4,R5,R6 | C85: DMD | D85: ZZRFZ | E85: Residential Freezing - ZZINFES backstop | F85: PJ | G85: PJ/a
B86: R2,R3,R4,R5,R6 | C86: DMD | D86: ZZRRF | E86: Residential Refrigeration - ZZINFES backstop | F86: PJ | G86: PJ/a
B87: R2,R3,R4,R5,R6 | C87: DMD | D87: ZZRSC | E87: Residential Cooling - ZZINFES backstop | F87: PJ | G87: PJ/a
B88: R2,R3,R4,R5,R6 | C88: DMD | D88: ZZRSH | E88: Residential Heating - ZZINFES backstop | F88: PJ | G88: PJ/a
B89: R2,R3,R4,R5,R6 | C89: DMD | D89: ZZRWH | E89: Residential Water Heating - ZZINFES backstop | F89: PJ | G89: PJ/a

Sheet CommData_DMD
A1: CommData | B1: _GLOBAL,R0,R1,R2,R3,R4,R5,R6
E4: ~FI_T
A5: Region | B5: CommName | C5: *CommDesc | D5: *Units | E5: COM_PROJ~2010 | F5: COM_PROJ~2015 | G5: COM_PROJ~2020 | H5: COM_PROJ~2025 | I5: COM_PROJ~2030 | J5: COM_PROJ~2035 | K5: COM_PROJ~2040 | L5: COM_PROJ~2045 | M5: COM_PROJ~2050 | N5: COM_PROJ~2055 | O5: COM_FR~IDAM | P5: COM_FR~IDPM | Q5: COM_FR~IN | R5: COM_FR~IP | S5: COM_FR~SDAM | T5: COM_FR~SDPM | U5: COM_FR~SN | V5: COM_FR~SP | W5: COM_FR~WDAM | X5: COM_FR~WDPM | Y5: COM_FR~WN | Z5: COM_FR~WP
A6: *Brooklyn
A7: R2 | B7: =Commodities!$D$9 -> RSC | C7: Residential Cooling | D7: PJ | E7: =(1-DmdCalc!R$6)*Pop!D103*Pop!D$49*Pop!D24*Pop!D113/PJ_to_BTU -> 9.427232 | F7: =(1-DmdCalc!S$6)*Pop!E103*Pop!E$49*Pop!E24*Pop!E113/PJ_to_BTU -> 9.2041854 | G7: =(1-DmdCalc!T$6)*Pop!F103*Pop!F$49*Pop!F24*Pop!F113/PJ_to_BTU -> 9.6137311 | H7: =(1-DmdCalc!U$6)*Pop!G103*Pop!G$49*Pop!G24*Pop!G113/PJ_to_BTU -> 9.3917216 | I7: =(1-DmdCalc!V$6)*Pop!H103*Pop!H$49*Pop!H24*Pop!H113/PJ_to_BTU -> 9.2792535 | J7: =(1-DmdCalc!W$6)*Pop!I103*Pop!I$49*Pop!I24*Pop!I113/PJ_to_BTU -> 9.3555513 | K7: =(1-DmdCalc!X$6)*Pop!J103*Pop!J$49*Pop!J24*Pop!J113/PJ_to_BTU -> 10.173151 | L7: =(1-DmdCalc!Y$6)*Pop!K103*Pop!K$49*Pop!K24*Pop!K113/PJ_to_BTU -> 10.180276 | ... N7: =(1-DmdCalc!AA$6)*Pop!M103*Pop!M$49*Pop!M24*Pop!M113/PJ_to_BTU -> 10.837579 | O7: 0.0166 | P7: 0.0577 | Q7: 0.0254 | R7: 0.0022 | S7: 0.1552 | T7: 0.5033 | U7: 0.2118 | V7: 0.0192 | W7: 0.0026 | X7: 0.0026 | Y7: 0.0033 | Z7: 0.0001
A8: *R2 | B8: =Commodities!$D$10 -> RFZ | C8: Residential Freezing | D8: PJ | O8: 0.0795 | P8: 0.1018 | Q8: 0.1482 | R8: 0.0034 | S8: 0.1033 | T8: 0.1284 | U8: 0.1341 | V8: 0.0034 | W8: 0.0715 | X8: 0.1017 | Y8: 0.1217 | Z8: 0.003
A9: R2 | B9: =Commodities!$D$11 -> RSH | C9: Residential Heating | D9: PJ | E9: =Pop!D95*Pop!D$49*Pop!D24*Pop!D121/PJ_to_BTU -> 44.265367 | F9: =Pop!E95*Pop!E$49*Pop!E24*Pop!E121/PJ_to_BTU -> 44.376666 | G9: =Pop!F95*Pop!F$49*Pop!F24*Pop!F121/PJ_to_BTU -> 37.391626 | H9: =Pop!G95*Pop!G$49*Pop!G24*Pop!G121/PJ_to_BTU -> 43.801347 | I9: =Pop!H95*Pop!H$49*Pop!H24*Pop!H121/PJ_to_BTU -> 42.122428 | J9: =Pop!I95*Pop!I$49*Pop!I24*Pop!I121/PJ_to_BTU -> 39.97184 | K9: =Pop!J95*Pop!J$49*Pop!J24*Pop!J121/PJ_to_BTU -> 36.665712 | L9: =Pop!K95*Pop!K$49*Pop!K24*Pop!K121/PJ_to_BTU -> 35.166738 | ... N9: =Pop!M95*Pop!M$49*Pop!M24*Pop!M121/PJ_to_BTU -> 31.255487 | O9: 0.0824 | P9: 0.0706 | Q9: 0.1213 | R9: 0.004 | S9: 0.0103 | T9: 0.0059 | U9: 0.0074 | V9: 0.0002 | W9: 0.1947 | X9: 0.1751 | Y9: 0.3194 | Z9: 0.0087
A10: R2 | B10: =Commodities!$D$12 -> RLT | C10: Residential Lighting | D10: =Commodities!$F$12 -> bn-lum-yr | E10: =DmdCalc!E$7*Pop!D24/Pop!D$28 -> 2.841194 | F10: =DmdCalc!F$7*Pop!E24/Pop!E$28 -> 2.7230091 | G10: =DmdCalc!G$7*Pop!F24/Pop!F$28 -> 2.5743822 | H10: =DmdCalc!H$7*Pop!G24/Pop!G$28 -> 0.89649269 | I10: =DmdCalc!I$7*Pop!H24/Pop!H$28 -> 0.91090786 | J10: =DmdCalc!J$7*Pop!I24/Pop!I$28 -> 0.912049 | K10: =DmdCalc!K$7*Pop!J24/Pop!J$28 -> 0.9103326 | L10: =DmdCalc!L$7*Pop!K24/Pop!K$28 -> 0.87873969 | ... N10: =DmdCalc!N$7*Pop!M24/Pop!M$28 -> 0.89278797 | O10: 0.0627 | P10: 0.09 | Q10: 0.1773 | R10: 0.0033 | S10: 0.0591 | T10: 0.0914 | U10: 0.1315 | V10: 0.0014 | W10: 0.0742 | X10: 0.1447 | Y10: 0.1595 | Z10: 0.0049
A11: R2 | B11: =Commodities!$D$13 -> ROE | C11: Residential Other Appliances - ELC | D11: PJ | E11: =DmdCalc!E$8*Pop!D24/Pop!D$28 -> 8.9321044 | F11: =DmdCalc!F$8*Pop!E24/Pop!E$28 -> 8.5605564 | G11: =DmdCalc!G$8*Pop!F24/Pop!F$28 -> 8.0933054 | H11: =DmdCalc!H$8*Pop!G24/Pop!G$28 -> 10.02788 | I11: =DmdCalc!I$8*Pop!H24/Pop!H$28 -> 10.558734 | J11: =DmdCalc!J$8*Pop!I24/Pop!I$28 -> 11.109995 | K11: =DmdCalc!K$8*Pop!J24/Pop!J$28 -> 11.816972 | L11: =DmdCalc!L$8*Pop!K24/Pop!K$28 -> 12.652415 | ... N11: =DmdCalc!N$8*Pop!M24/Pop!M$28 -> 14.89615 | O11: 0.0892 | P11: 0.1211 | Q11: 0.1084 | R11: 0.0044 | S11: 0.0865 | T11: 0.1257 | U11: 0.0674 | V11: 0.0031 | W11: 0.1079 | X11: 0.1718 | Y11: 0.1091 | Z11: 0.0054
A12: R2 | B12: =Commodities!$D$14 -> ROG | C12: Residential Other Appliances - NGA | D12: PJ | E12: =DmdCalc!E$10*Pop!D24/Pop!D$28 -> 0.80672192 | F12: =DmdCalc!F$10*Pop!E24/Pop!E$28 -> 0.90430384 | G12: =DmdCalc!G$10*Pop!F24/Pop!F$28 -> 0.93116314 | H12: =DmdCalc!H$10*Pop!G24/Pop!G$28 -> 1.1069888 | I12: =DmdCalc!I$10*Pop!H24/Pop!H$28 -> 1.1309661 | J12: =DmdCalc!J$10*Pop!I24/Pop!I$28 -> 1.1469159 | K12: =DmdCalc!K$10*Pop!J24/Pop!J$28 -> 1.1681423 | L12: =DmdCalc!L$10*Pop!K24/Pop!K$28 -> 1.1886465 | ... N12: =DmdCalc!N$10*Pop!M24/Pop!M$28 -> 1.2282187
A13: *R2 | B13: =Commodities!$D$15 -> ROL | C13: Residential Other Appliances - LPG | D13: PJ
A14: *R2 | B14: =Commodities!$D$16 -> RRF | C14: Residential Refrigeration | D14: PJ | O14: 0.0788 | P14: 0.1045 | Q14: 0.1505 | R14: 0.0035 | S14: 0.1018 | T14: 0.1286 | U14: 0.1329 | V14: 0.0034 | W14: 0.0696 | X14: 0.1051 | Y14: 0.1181 | Z14: 0.0032
A15: R2 | B15: =Commodities!$D$17 -> RWH | C15: Residential Water Heating | D15: PJ | E15: =DmdCalc!E$5*Pop!D24/Pop!D$28 -> 11.919112 | F15: =DmdCalc!F$5*Pop!E24/Pop!E$28 -> 12.146867 | G15: =DmdCalc!G$5*Pop!F24/Pop!F$28 -> 11.708389 | H15: =DmdCalc!H$5*Pop!G24/Pop!G$28 -> 12.736536 | I15: =DmdCalc!I$5*Pop!H24/Pop!H$28 -> 11.953859 | J15: =DmdCalc!J$5*Pop!I24/Pop!I$28 -> 11.840225 | K15: =DmdCalc!K$5*Pop!J24/Pop!J$28 -> 11.793674 | L15: =DmdCalc!L$5*Pop!K24/Pop!K$28 -> 11.604949 | ... N15: =DmdCalc!N$5*Pop!M24/Pop!M$28 -> 11.115908 | O15: 0.1215 | P15: 0.1114 | Q15: 0.1279 | R15: 0.0053 | S15: 0.0868 | T15: 0.0892 | U15: 0.0653 | V15: 0.002 | W15: 0.1324 | X15: 0.1486 | Y15: 0.1042 | Z15: 0.0054
A16: *Bronx
A17: R3 | B17: =Commodities!$D$9 -> RSC | C17: Residential Cooling | D17: PJ | E17: =(1-DmdCalc!R$6)*Pop!D102*Pop!D$49*Pop!D23*Pop!D112/PJ_to_BTU -> 4.7126374 | F17: =(1-DmdCalc!S$6)*Pop!E102*Pop!E$49*Pop!E23*Pop!E112/PJ_to_BTU -> 4.6812323 | G17: =(1-DmdCalc!T$6)*Pop!F102*Pop!F$49*Pop!F23*Pop!F112/PJ_to_BTU -> 4.9571109 | H17: =(1-DmdCalc!U$6)*Pop!G102*Pop!G$49*Pop!G23*Pop!G112/PJ_to_BTU -> 4.9322943 | I17: =(1-DmdCalc!V$6)*Pop!H102*Pop!H$49*Pop!H23*Pop!H112/PJ_to_BTU -> 4.8372334 | J17: =(1-DmdCalc!W$6)*Pop!I102*Pop!I$49*Pop!I23*Pop!I112/PJ_to_BTU -> 4.8988356 | K17: =(1-DmdCalc!X$6)*Pop!J102*Pop!J$49*Pop!J23*Pop!J112/PJ_to_BTU -> 5.3499581 | L17: =(1-DmdCalc!Y$6)*Pop!K102*Pop!K$49*Pop!K23*Pop!K112/PJ_to_BTU -> 5.3024708 | ... N17: =(1-DmdCalc!AA$6)*Pop!M102*Pop!M$49*Pop!M23*Pop!M112/PJ_to_BTU -> 5.6205815 | O17: 0.0194 | P17: 0.0671 | Q17: 0.0298 | R17: 0.0026 | S17: 0.152 | T17: 0.493 | U17: 0.2074 | V17: 0.0188 | W17: 0.003 | X17: 0.003 | Y17: 0.0037 | Z17: 0.0002
A18: *R3 | B18: =Commodities!$D$10 -> RFZ | C18: Residential Freezing | D18: PJ | O18: 0.0795 | P18: 0.1018 | Q18: 0.1482 | R18: 0.0034 | S18: 0.1033 | T18: 0.1284 | U18: 0.1341 | V18: 0.0034 | W18: 0.0715 | X18: 0.1017 | Y18: 0.1217 | Z18: 0.003
A19: R3 | B19: =Commodities!$D$11 -> RSH | C19: Residential Heating | D19: PJ | E19: =Pop!D94*Pop!D$49*Pop!D23*Pop!D120/PJ_to_BTU -> 21.043435 | F19: =Pop!E94*Pop!E$49*Pop!E23*Pop!E120/PJ_to_BTU -> 21.513374 | G19: =Pop!F94*Pop!F$49*Pop!F23*Pop!F120/PJ_to_BTU -> 18.251944 | H19: =Pop!G94*Pop!G$49*Pop!G23*Pop!G120/PJ_to_BTU -> 21.213828 | I19: =Pop!H94*Pop!H$49*Pop!H23*Pop!H120/PJ_to_BTU -> 20.250009 | J19: =Pop!I94*Pop!I$49*Pop!I23*Pop!I120/PJ_to_BTU -> 19.302139 | K19: =Pop!J94*Pop!J$49*Pop!J23*Pop!J120/PJ_to_BTU -> 17.782092 | L19: =Pop!K94*Pop!K$49*Pop!K23*Pop!K120/PJ_to_BTU -> 16.891905 | ... N19: =Pop!M94*Pop!M$49*Pop!M23*Pop!M120/PJ_to_BTU -> 14.948687 | O19: 0.0779 | P19: 0.0668 | Q19: 0.1147 | R19: 0.0038 | S19: 0.0105 | T19: 0.006 | U19: 0.0075 | V19: 0.0002 | W19: 0.1989 | X19: 0.1787 | Y19: 0.3262 | Z19: 0.0088
A20: R3 | B20: =Commodities!$D$12 -> RLT | C20: Residential Lighting | D20: =Commodities!$F$12 -> bn-lum-yr | E20: =DmdCalc!E$7*Pop!D23/Pop!D$28 -> 1.4807422 | F20: =DmdCalc!F$7*Pop!E23/Pop!E$28 -> 1.4314466 | G20: =DmdCalc!G$7*Pop!F23/Pop!F$28 -> 1.3626364 | H20: =DmdCalc!H$7*Pop!G23/Pop!G$28 -> 0.47081526 | I20: =DmdCalc!I$7*Pop!H23/Pop!H$28 -> 0.4748522 | J20: =DmdCalc!J$7*Pop!I23/Pop!I$28 -> 0.47757508 | K20: =DmdCalc!K$7*Pop!J23/Pop!J$28 -> 0.47873481 | L20: =DmdCalc!L$7*Pop!K23/Pop!K$28 -> 0.45769797 | ... N20: =DmdCalc!N$7*Pop!M23/Pop!M$28 -> 0.46301739 | O20: 0.0627 | P20: 0.09 | Q20: 0.1773 | R20: 0.0033 | S20: 0.0591 | T20: 0.0914 | U20: 0.1315 | V20: 0.0014 | W20: 0.0742 | X20: 0.1447 | Y20: 0.1595 | Z20: 0.0049
A21: R3 | B21: =Commodities!$D$13 -> ROE | C21: Residential Other Appliances - ELC | D21: PJ | E21: =DmdCalc!E$8*Pop!D23/Pop!D$28 -> 4.6551357 | F21: =DmdCalc!F$8*Pop!E23/Pop!E$28 -> 4.5001609 | G21: =DmdCalc!G$8*Pop!F23/Pop!F$28 -> 4.2838366 | H21: =DmdCalc!H$8*Pop!G23/Pop!G$28 -> 5.2663888 | I21: =DmdCalc!I$8*Pop!H23/Pop!H$28 -> 5.5042207 | J21: =DmdCalc!J$8*Pop!I23/Pop!I$28 -> 5.8175126 | K21: =DmdCalc!K$8*Pop!J23/Pop!J$28 -> 6.2144276 | L21: =DmdCalc!L$8*Pop!K23/Pop!K$28 -> 6.5901023 | ... N21: =DmdCalc!N$8*Pop!M23/Pop!M$28 -> 7.7254362 | O21: 0.0892 | P21: 0.1211 | Q21: 0.1084 | R21: 0.0044 | S21: 0.0865 | T21: 0.1257 | U21: 0.0674 | V21: 0.0031 | W21: 0.1079 | X21: 0.1718 | Y21: 0.1091 | Z21: 0.0054
A22: R3 | B22: =Commodities!$D$14 -> ROG | C22: Residential Other Appliances - NGA | D22: PJ | E22: =DmdCalc!E$10*Pop!D23/Pop!D$28 -> 0.42043844 | F22: =DmdCalc!F$10*Pop!E23/Pop!E$28 -> 0.47537947 | G22: =DmdCalc!G$10*Pop!F23/Pop!F$28 -> 0.49287041 | H22: =DmdCalc!H$10*Pop!G23/Pop!G$28 -> 0.58136247 | I22: =DmdCalc!I$10*Pop!H23/Pop!H$28 -> 0.58956755 | J22: =DmdCalc!J$10*Pop!I23/Pop!I$28 -> 0.60055815 | K22: =DmdCalc!K$10*Pop!J23/Pop!J$28 -> 0.61431435 | L22: =DmdCalc!L$10*Pop!K23/Pop!K$28 -> 0.61911517 | ... N22: =DmdCalc!N$10*Pop!M23/Pop!M$28 -> 0.63697834
A23: *R3 | B23: =Commodities!$D$15 -> ROL | C23: Residential Other Appliances - LPG | D23: PJ
A24: *R3 | B24: =Commodities!$D$16 -> RRF | C24: Residential Refrigeration | D24: PJ | O24: 0.0788 | P24: 0.1045 | Q24: 0.1505 | R24: 0.0035 | S24: 0.1018 | T24: 0.1286 | U24: 0.1329 | V24: 0.0034 | W24: 0.0696 | X24: 0.1051 | Y24: 0.1181 | Z24: 0.0032
A25: R3 | B25: =Commodities!$D$17 -> RWH | C25: Residential Water Heating | D25: PJ | E25: =DmdCalc!E$5*Pop!D23/Pop!D$28 -> 6.2118713 | F25: =DmdCalc!F$5*Pop!E23/Pop!E$28 -> 6.3854327 | G25: =DmdCalc!G$5*Pop!F23/Pop!F$28 -> 6.1973228 | H25: =DmdCalc!H$5*Pop!G23/Pop!G$28 -> 6.6889062 | I25: =DmdCalc!I$5*Pop!H23/Pop!H$28 -> 6.2314932 | J25: =DmdCalc!J$5*Pop!I23/Pop!I$28 -> 6.1998822 | K25: =DmdCalc!K$5*Pop!J23/Pop!J$28 -> 6.2021754 | L25: =DmdCalc!L$5*Pop!K23/Pop!K$28 -> 6.0445222 | ... N25: =DmdCalc!N$5*Pop!M23/Pop!M$28 -> 5.7649281 | O25: 0.1215 | P25: 0.1114 | Q25: 0.1279 | R25: 0.0053 | S25: 0.0868 | T25: 0.0892 | U25: 0.0653 | V25: 0.002 | W25: 0.1324 | X25: 0.1486 | Y25: 0.1042 | Z25: 0.0054
A26: *Manhattan
A27: R4 | B27: =Commodities!$D$9 -> RSC | C27: Residential Cooling | D27: PJ | E27: =(1-DmdCalc!R$6)*Pop!D104*Pop!D$49*Pop!D25*Pop!D114/PJ_to_BTU -> 7.2268707 | F27: =(1-DmdCalc!S$6)*Pop!E104*Pop!E$49*Pop!E25*Pop!E114/PJ_to_BTU -> 7.6093011 | G27: =(1-DmdCalc!T$6)*Pop!F104*Pop!F$49*Pop!F25*Pop!F114/PJ_to_BTU -> 7.336496 | H27: =(1-DmdCalc!U$6)*Pop!G104*Pop!G$49*Pop!G25*Pop!G114/PJ_to_BTU -> 7.6402481 | I27: =(1-DmdCalc!V$6)*Pop!H104*Pop!H$49*Pop!H25*Pop!H114/PJ_to_BTU -> 7.7120931 | J27: =(1-DmdCalc!W$6)*Pop!I104*Pop!I$49*Pop!I25*Pop!I114/PJ_to_BTU -> 7.6891359 | K27: =(1-DmdCalc!X$6)*Pop!J104*Pop!J$49*Pop!J25*Pop!J114/PJ_to_BTU -> 8.2700836 | L27: =(1-DmdCalc!Y$6)*Pop!K104*Pop!K$49*Pop!K25*Pop!K114/PJ_to_BTU -> 8.3333903 | ... N27: =(1-DmdCalc!AA$6)*Pop!M104*Pop!M$49*Pop!M25*Pop!M114/PJ_to_BTU -> 8.8828218 | O27: 0.0311 | P27: 0.102 | Q27: 0.0493 | R27: 0.004 | S27: 0.133 | T27: 0.4322 | U27: 0.1813 | V27: 0.0165 | W27: 0.0151 | X27: 0.0155 | Y27: 0.0192 | Z27: 0.0008
A28: *R4 | B28: =Commodities!$D$10 -> RFZ | C28: Residential Freezing | D28: PJ | O28: 0.0795 | P28: 0.1018 | Q28: 0.1482 | R28: 0.0034 | S28: 0.1033 | T28: 0.1284 | U28: 0.1341 | V28: 0.0034 | W28: 0.0715 | X28: 0.1017 | Y28: 0.1217 | Z28: 0.003
A29: R4 | B29: =Commodities!$D$11 -> RSH | C29: Residential Heating | D29: PJ | E29: =Pop!D96*Pop!D$49*Pop!D25*Pop!D122/PJ_to_BTU -> 37.294841 | F29: =Pop!E96*Pop!E$49*Pop!E25*Pop!E122/PJ_to_BTU -> 39.427265 | G29: =Pop!F96*Pop!F$49*Pop!F25*Pop!F122/PJ_to_BTU -> 31.917949 | H29: =Pop!G96*Pop!G$49*Pop!G25*Pop!G122/PJ_to_BTU -> 38.271352 | I29: =Pop!H96*Pop!H$49*Pop!H25*Pop!H122/PJ_to_BTU -> 37.600767 | J29: =Pop!I96*Pop!I$49*Pop!I25*Pop!I122/PJ_to_BTU -> 35.284696 | K29: =Pop!J96*Pop!J$49*Pop!J25*Pop!J122/PJ_to_BTU -> 32.013904 | L29: =Pop!K96*Pop!K$49*Pop!K25*Pop!K122/PJ_to_BTU -> 30.918495 | ... N29: =Pop!M96*Pop!M$49*Pop!M25*Pop!M122/PJ_to_BTU -> 27.514968 | O29: 0.0732 | P29: 0.0627 | Q29: 0.1077 | R29: 0.0036 | S29: 0.0043 | T29: 0.0025 | U29: 0.0031 | V29: 0.0001 | W29: 0.2073 | X29: 0.1863 | Y29: 0.34 | Z29: 0.0092
A30: R4 | B30: =Commodities!$D$12 -> RLT | C30: Residential Lighting | D30: =Commodities!$F$12 -> bn-lum-yr | E30: =DmdCalc!E$7*Pop!D25/Pop!D$28 -> 2.2631958 | F30: =DmdCalc!F$7*Pop!E25/Pop!E$28 -> 2.2525114 | G30: =DmdCalc!G$7*Pop!F25/Pop!F$28 -> 2.0460186 | H30: =DmdCalc!H$7*Pop!G25/Pop!G$28 -> 0.72930468 | I30: =DmdCalc!I$7*Pop!H25/Pop!H$28 -> 0.75706588 | J30: =DmdCalc!J$7*Pop!I25/Pop!I$28 -> 0.74959439 | K30: =DmdCalc!K$7*Pop!J25/Pop!J$28 -> 0.74003886 | L30: =DmdCalc!L$7*Pop!K25/Pop!K$28 -> 0.71932047 | ... N30: =DmdCalc!N$7*Pop!M25/Pop!M$28 -> 0.73175719 | O30: 0.0627 | P30: 0.09 | Q30: 0.1773 | R30: 0.0033 | S30: 0.0591 | T30: 0.0914 | U30: 0.1315 | V30: 0.0014 | W30: 0.0742 | X30: 0.1447 | Y30: 0.1595 | Z30: 0.0049
A31: R4 | B31: =Commodities!$D$13 -> ROE | C31: Residential Other Appliances - ELC | D31: PJ | E31: =DmdCalc!E$8*Pop!D25/Pop!D$28 -> 7.1150021 | F31: =DmdCalc!F$8*Pop!E25/Pop!E$28 -> 7.0814124 | G31: =DmdCalc!G$8*Pop!F25/Pop!F$28 -> 6.4322435 | H31: =DmdCalc!H$8*Pop!G25/Pop!G$28 -> 8.1577688 | I31: =DmdCalc!I$8*Pop!H25/Pop!H$28 -> 8.7754836 | J31: =DmdCalc!J$8*Pop!I25/Pop!I$28 -> 9.131077 | K31: =DmdCalc!K$8*Pop!J25/Pop!J$28 -> 9.6063997 | L31: =DmdCalc!L$8*Pop!K25/Pop!K$28 -> 10.357039 | ... N31: =DmdCalc!N$8*Pop!M25/Pop!M$28 -> 12.209355 | O31: 0.0892 | P31: 0.1211 | Q31: 0.1084 | R31: 0.0044 | S31: 0.0865 | T31: 0.1257 | U31: 0.0674 | V31: 0.0031 | W31: 0.1079 | X31: 0.1718 | Y31: 0.1091 | Z31: 0.0054
A32: R4 | B32: =Commodities!$D$14 -> ROG | C32: Residential Other Appliances - NGA | D32: PJ | E32: =DmdCalc!E$10*Pop!D25/Pop!D$28 -> 0.64260648 | F32: =DmdCalc!F$10*Pop!E25/Pop!E$28 -> 0.74805283 | G32: =DmdCalc!G$10*Pop!F25/Pop!F$28 -> 0.74005215 | H32: =DmdCalc!H$10*Pop!G25/Pop!G$28 -> 0.9005451 | I32: =DmdCalc!I$10*Pop!H25/Pop!H$28 -> 0.93995875 | J32: =DmdCalc!J$10*Pop!I25/Pop!I$28 -> 0.9426267 | K32: =DmdCalc!K$10*Pop!J25/Pop!J$28 -> 0.94962071 | L32: =DmdCalc!L$10*Pop!K25/Pop!K$28 -> 0.97300458 | ... N32: =DmdCalc!N$10*Pop!M25/Pop!M$28 -> 1.0066868
A33: *R4 | B33: =Commodities!$D$15 -> ROL | C33: Residential Other Appliances - LPG | D33: PJ
A34: *R4 | B34: =Commodities!$D$16 -> RRF | C34: Residential Refrigeration | D34: PJ | O34: 0.0788 | P34: 0.1045 | Q34: 0.1505 | R34: 0.0035 | S34: 0.1018 | T34: 0.1286 | U34: 0.1329 | V34: 0.0034 | W34: 0.0696 | X34: 0.1051 | Y34: 0.1181 | Z34: 0.0032
A35: R4 | B35: =Commodities!$D$17 -> RWH | C35: Residential Water Heating | D35: PJ | E35: =DmdCalc!E$5*Pop!D25/Pop!D$28 -> 9.4943477 | F35: =DmdCalc!F$5*Pop!E25/Pop!E$28 -> 10.048059 | G35: =DmdCalc!G$5*Pop!F25/Pop!F$28 -> 9.3053712 | H35: =DmdCalc!H$5*Pop!G25/Pop!G$28 -> 10.361284 | I35: =DmdCalc!I$5*Pop!H25/Pop!H$28 -> 9.934988 | J35: =DmdCalc!J$5*Pop!I25/Pop!I$28 -> 9.7312384 | K35: =DmdCalc!K$5*Pop!J25/Pop!J$28 -> 9.5874599 | L35: =DmdCalc!L$5*Pop!K25/Pop!K$28 -> 9.4996021 | ... N35: =DmdCalc!N$5*Pop!M25/Pop!M$28 -> 9.1109486 | O35: 0.1215 | P35: 0.1114 | Q35: 0.1279 | R35: 0.0053 | S35: 0.0868 | T35: 0.0892 | U35: 0.0653 | V35: 0.002 | W35: 0.1324 | X35: 0.1486 | Y35: 0.1042 | Z35: 0.0054
A36: *Staten Island
A37: R5 | B37: =Commodities!$D$9 -> RSC | C37: Residential Cooling | D37: PJ | E37: =(1-DmdCalc!R$6)*Pop!D106*Pop!D$49*Pop!D27*Pop!D116/PJ_to_BTU -> 1.7162587 | F37: =(1-DmdCalc!S$6)*Pop!E106*Pop!E$49*Pop!E27*Pop!E116/PJ_to_BTU -> 1.6990831 | G37: =(1-DmdCalc!T$6)*Pop!F106*Pop!F$49*Pop!F27*Pop!F116/PJ_to_BTU -> 1.5939977 | H37: =(1-DmdCalc!U$6)*Pop!G106*Pop!G$49*Pop!G27*Pop!G116/PJ_to_BTU -> 1.6158227 | I37: =(1-DmdCalc!V$6)*Pop!H106*Pop!H$49*Pop!H27*Pop!H116/PJ_to_BTU -> 1.6130755 | J37: =(1-DmdCalc!W$6)*Pop!I106*Pop!I$49*Pop!I27*Pop!I116/PJ_to_BTU -> 1.6063549 | K37: =(1-DmdCalc!X$6)*Pop!J106*Pop!J$49*Pop!J27*Pop!J116/PJ_to_BTU -> 1.7256772 | L37: =(1-DmdCalc!Y$6)*Pop!K106*Pop!K$49*Pop!K27*Pop!K116/PJ_to_BTU -> 1.7267736 | ... N37: =(1-DmdCalc!AA$6)*Pop!M106*Pop!M$49*Pop!M27*Pop!M116/PJ_to_BTU -> 1.8221133 | O37: 0.0292 | P37: 0.0972 | Q37: 0.0462 | R37: 0.0038 | S37: 0.1364 | T37: 0.4432 | U37: 0.186 | V37: 0.017 | W37: 0.0122 | X37: 0.0125 | Y37: 0.0156 | Z37: 0.0007
A38: *R5 | B38: =Commodities!$D$10 -> RFZ | C38: Residential Freezing | D38: PJ | O38: 0.0795 | P38: 0.1018 | Q38: 0.1482 | R38: 0.0034 | S38: 0.1033 | T38: 0.1284 | U38: 0.1341 | V38: 0.0034 | W38: 0.0715 | X38: 0.1017 | Y38: 0.1217 | Z38: 0.003
A39: R5 | B39: =Commodities!$D$11 -> RSH | C39: Residential Heating | D39: PJ | E39: =Pop!D98*Pop!D$49*Pop!D27*Pop!D124/PJ_to_BTU -> 10.042388 | F39: =Pop!E98*Pop!E$49*Pop!E27*Pop!E124/PJ_to_BTU -> 9.4413972 | G39: =Pop!F98*Pop!F$49*Pop!F27*Pop!F124/PJ_to_BTU -> 7.5394413 | H39: =Pop!G98*Pop!G$49*Pop!G27*Pop!G124/PJ_to_BTU -> 8.9307806 | I39: =Pop!H98*Pop!H$49*Pop!H27*Pop!H124/PJ_to_BTU -> 8.6777771 | J39: =Pop!I98*Pop!I$49*Pop!I27*Pop!I124/PJ_to_BTU -> 8.133542 | K39: =Pop!J98*Pop!J$49*Pop!J27*Pop!J124/PJ_to_BTU -> 7.3708516 | L39: =Pop!K98*Pop!K$49*Pop!K27*Pop!K124/PJ_to_BTU -> 7.0690553 | ... N39: =Pop!M98*Pop!M$49*Pop!M27*Pop!M124/PJ_to_BTU -> 6.22763 | O39: 0.0728 | P39: 0.0625 | Q39: 0.1074 | R39: 0.0036 | S39: 0.0047 | T39: 0.0027 | U39: 0.0033 | V39: 0.0001 | W39: 0.2074 | X39: 0.1863 | Y39: 0.34 | Z39: 0.0092
A40: R5 | B40: =Commodities!$D$12 -> RLT | C40: Residential Lighting | D40: =Commodities!$F$12 -> bn-lum-yr | E40: =DmdCalc!E$7*Pop!D27/Pop!D$28 -> 0.50653993 | F40: =DmdCalc!F$7*Pop!E27/Pop!E$28 -> 0.48885183 | G40: =DmdCalc!G$7*Pop!F27/Pop!F$28 -> 0.43801038 | H40: =DmdCalc!H$7*Pop!G27/Pop!G$28 -> 0.15423938 | I40: =DmdCalc!I$7*Pop!H27/Pop!H$28 -> 0.15834928 | J40: =DmdCalc!J$7*Pop!I27/Pop!I$28 -> 0.15659947 | K40: =DmdCalc!K$7*Pop!J27/Pop!J$28 -> 0.15442023 | L40: =DmdCalc!L$7*Pop!K27/Pop!K$28 -> 0.14905141 | ... N40: =DmdCalc!N$7*Pop!M27/Pop!M$28 -> 0.15010371 | O40: 0.0627 | P40: 0.09 | Q40: 0.1773 | R40: 0.0033 | S40: 0.0591 | T40: 0.0914 | U40: 0.1315 | V40: 0.0014 | W40: 0.0742 | X40: 0.1447 | Y40: 0.1595 | Z40: 0.0049
A41: R5 | B41: =Commodities!$D$13 -> ROE | C41: Residential Other Appliances - ELC | D41: PJ | E41: =DmdCalc!E$8*Pop!D27/Pop!D$28 -> 1.5924528 | F41: =DmdCalc!F$8*Pop!E27/Pop!E$28 -> 1.5368453 | G41: =DmdCalc!G$8*Pop!F27/Pop!F$28 -> 1.3770106 | H41: =DmdCalc!H$8*Pop!G27/Pop!G$28 -> 1.7252723 | I41: =DmdCalc!I$8*Pop!H27/Pop!H$28 -> 1.8354961 | J41: =DmdCalc!J$8*Pop!I27/Pop!I$28 -> 1.9075941 | K41: =DmdCalc!K$8*Pop!J27/Pop!J$28 -> 2.0045197 | L41: =DmdCalc!L$8*Pop!K27/Pop!K$28 -> 2.1460966 | ... N41: =DmdCalc!N$8*Pop!M27/Pop!M$28 -> 2.5044775 | O41: 0.0892 | P41: 0.1211 | Q41: 0.1084 | R41: 0.0044 | S41: 0.0865 | T41: 0.1257 | U41: 0.0674 | V41: 0.0031 | W41: 0.1079 | X41: 0.1718 | Y41: 0.1091 | Z41: 0.0054
A42: R5 | B42: =Commodities!$D$14 -> ROG | C42: Residential Other Appliances - NGA | D42: PJ | E42: =DmdCalc!E$10*Pop!D27/Pop!D$28 -> 0.14382575 | F42: =DmdCalc!F$10*Pop!E27/Pop!E$28 -> 0.16234635 | G42: =DmdCalc!G$10*Pop!F27/Pop!F$28 -> 0.1584299 | H42: =DmdCalc!H$10*Pop!G27/Pop!G$28 -> 0.19045471 | I42: =DmdCalc!I$10*Pop!H27/Pop!H$28 -> 0.19660349 | J42: =DmdCalc!J$10*Pop!I27/Pop!I$28 -> 0.19692629 | K42: =DmdCalc!K$10*Pop!J27/Pop!J$28 -> 0.19815263 | L42: =DmdCalc!L$10*Pop!K27/Pop!K$28 -> 0.20161765 | ... N42: =DmdCalc!N$10*Pop!M27/Pop!M$28 -> 0.2064994
A43: *R5 | B43: =Commodities!$D$15 -> ROL | C43: Residential Other Appliances - LPG | D43: PJ
A44: *R5 | B44: =Commodities!$D$16 -> RRF | C44: Residential Refrigeration | D44: PJ | O44: 0.0788 | P44: 0.1045 | Q44: 0.1505 | R44: 0.0035 | S44: 0.1018 | T44: 0.1286 | U44: 0.1329 | V44: 0.0034 | W44: 0.0696 | X44: 0.1051 | Y44: 0.1181 | Z44: 0.0032
A45: R5 | B45: =Commodities!$D$17 -> RWH | C45: Residential Water Heating | D45: PJ | E45: =DmdCalc!E$5*Pop!D27/Pop!D$28 -> 2.124989 | F45: =DmdCalc!F$5*Pop!E27/Pop!E$28 -> 2.1806825 | G45: =DmdCalc!G$5*Pop!F27/Pop!F$28 -> 1.992088 | H45: =DmdCalc!H$5*Pop!G27/Pop!G$28 -> 2.1912899 | I45: =DmdCalc!I$5*Pop!H27/Pop!H$28 -> 2.0780202 | J45: =DmdCalc!J$5*Pop!I27/Pop!I$28 -> 2.0329752 | K45: =DmdCalc!K$5*Pop!J27/Pop!J$28 -> 2.0005676 | L45: =DmdCalc!L$5*Pop!K27/Pop!K$28 -> 1.9684259 | ... N45: =DmdCalc!N$5*Pop!M27/Pop!M$28 -> 1.8689084 | O45: 0.1215 | P45: 0.1114 | Q45: 0.1279 | R45: 0.0053 | S45: 0.0868 | T45: 0.0892 | U45: 0.0653 | V45: 0.002 | W45: 0.1324 | X45: 0.1486 | Y45: 0.1042 | Z45: 0.0054
A46: *Queens
A47: R6 | B47: =Commodities!$D$9 -> RSC | C47: Residential Cooling | D47: PJ | E47: =(1-DmdCalc!R$6)*Pop!D105*Pop!D$49*Pop!D26*Pop!D115/PJ_to_BTU -> 8.2274756 | F47: =(1-DmdCalc!S$6)*Pop!E105*Pop!E$49*Pop!E26*Pop!E115/PJ_to_BTU -> 7.8913427 | G47: =(1-DmdCalc!T$6)*Pop!F105*Pop!F$49*Pop!F26*Pop!F115/PJ_to_BTU -> 7.7895635 | H47: =(1-DmdCalc!U$6)*Pop!G105*Pop!G$49*Pop!G26*Pop!G115/PJ_to_BTU -> 7.6551898 | I47: =(1-DmdCalc!V$6)*Pop!H105*Pop!H$49*Pop!H26*Pop!H115/PJ_to_BTU -> 7.6085974 | J47: =(1-DmdCalc!W$6)*Pop!I105*Pop!I$49*Pop!I26*Pop!I115/PJ_to_BTU -> 7.6139346 | K47: =(1-DmdCalc!X$6)*Pop!J105*Pop!J$49*Pop!J26*Pop!J115/PJ_to_BTU -> 8.2190253 | L47: =(1-DmdCalc!Y$6)*Pop!K105*Pop!K$49*Pop!K26*Pop!K115/PJ_to_BTU -> 8.2430802 | ... N47: =(1-DmdCalc!AA$6)*Pop!M105*Pop!M$49*Pop!M26*Pop!M115/PJ_to_BTU -> 8.7398243 | O47: 0.0317 | P47: 0.1069 | Q47: 0.0502 | R47: 0.0042 | S47: 0.135 | T47: 0.4386 | U47: 0.184 | V47: 0.0169 | W47: 0.0097 | X47: 0.0099 | Y47: 0.0124 | Z47: 0.0005
A48: *R6 | B48: =Commodities!$D$10 -> RFZ | C48: Residential Freezing | D48: PJ | O48: 0.0795 | P48: 0.1018 | Q48: 0.1482 | R48: 0.0034 | S48: 0.1033 | T48: 0.1284 | U48: 0.1341 | V48: 0.0034 | W48: 0.0715 | X48: 0.1017 | Y48: 0.1217 | Z48: 0.003
A49: R6 | B49: =Commodities!$D$11 -> RSH | C49: Residential Heating | D49: PJ | E49: =Pop!D97*Pop!D$49*Pop!D26*Pop!D123/PJ_to_BTU -> 38.55416 | F49: =Pop!E97*Pop!E$49*Pop!E26*Pop!E123/PJ_to_BTU -> 37.497212 | G49: =Pop!F97*Pop!F$49*Pop!F26*Pop!F123/PJ_to_BTU -> 30.714713 | H49: =Pop!G97*Pop!G$49*Pop!G26*Pop!G123/PJ_to_BTU -> 36.209728 | I49: =Pop!H97*Pop!H$49*Pop!H26*Pop!H123/PJ_to_BTU -> 35.029343 | J49: =Pop!I97*Pop!I$49*Pop!I26*Pop!I123/PJ_to_BTU -> 32.992934 | K49: =Pop!J97*Pop!J$49*Pop!J26*Pop!J123/PJ_to_BTU -> 30.043602 | L49: =Pop!K97*Pop!K$49*Pop!K26*Pop!K123/PJ_to_BTU -> 28.879462 | ... N49: =Pop!M97*Pop!M$49*Pop!M26*Pop!M123/PJ_to_BTU -> 25.5637 | O49: 0.0641 | P49: 0.055 | Q49: 0.0944 | R49: 0.0031 | S49: 0.0037 | T49: 0.0021 | U49: 0.0026 | V49: 0.0001 | W49: 0.2163 | X49: 0.1943 | Y49: 0.3547 | Z49: 0.0096
A50: R6 | B50: =Commodities!$D$12 -> RLT | C50: Residential Lighting | D50: =Commodities!$F$12 -> bn-lum-yr | E50: =DmdCalc!E$7*Pop!D26/Pop!D$28 -> 2.3882325 | F50: =DmdCalc!F$7*Pop!E26/Pop!E$28 -> 2.2686441 | G50: =DmdCalc!G$7*Pop!F26/Pop!F$28 -> 2.0850578 | H50: =DmdCalc!H$7*Pop!G26/Pop!G$28 -> 0.73073096 | I50: =DmdCalc!I$7*Pop!H26/Pop!H$28 -> 0.74690611 | J50: =DmdCalc!J$7*Pop!I26/Pop!I$28 -> 0.7422632 | K50: =DmdCalc!K$7*Pop!J26/Pop!J$28 -> 0.73546997 | L50: =DmdCalc!L$7*Pop!K26/Pop!K$28 -> 0.71152509 | ... N50: =DmdCalc!N$7*Pop!M26/Pop!M$28 -> 0.71997721 | O50: 0.0627 | P50: 0.09 | Q50: 0.1773 | R50: 0.0033 | S50: 0.0591 | T50: 0.0914 | U50: 0.1315 | V50: 0.0014 | W50: 0.0742 | X50: 0.1447 | Y50: 0.1595 | Z50: 0.0049
A51: R6 | B51: =Commodities!$D$13 -> ROE | C51: Residential Other Appliances - ELC | D51: PJ | E51: =DmdCalc!E$8*Pop!D26/Pop!D$28 -> 7.5080905 | F51: =DmdCalc!F$8*Pop!E26/Pop!E$28 -> 7.1321302 | G51: =DmdCalc!G$8*Pop!F26/Pop!F$28 -> 6.5549744 | H51: =DmdCalc!H$8*Pop!G26/Pop!G$28 -> 8.1737227 | I51: =DmdCalc!I$8*Pop!H26/Pop!H$28 -> 8.6577172 | J51: =DmdCalc!J$8*Pop!I26/Pop!I$28 -> 9.0417732 | K51: =DmdCalc!K$8*Pop!J26/Pop!J$28 -> 9.5470912 | L51: =DmdCalc!L$8*Pop!K26/Pop!K$28 -> 10.244798 | ... N51: =DmdCalc!N$8*Pop!M26/Pop!M$28 -> 12.012806 | O51: 0.0892 | P51: 0.1211 | Q51: 0.1084 | R51: 0.0044 | S51: 0.0865 | T51: 0.1257 | U51: 0.0674 | V51: 0.0031 | W51: 0.1079 | X51: 0.1718 | Y51: 0.1091 | Z51: 0.0054
A52: R6 | B52: =Commodities!$D$14 -> ROG | C52: Residential Other Appliances - NGA | D52: PJ | E52: =DmdCalc!E$10*Pop!D26/Pop!D$28 -> 0.67810909 | F52: =DmdCalc!F$10*Pop!E26/Pop!E$28 -> 0.75341046 | G52: =DmdCalc!G$10*Pop!F26/Pop!F$28 -> 0.75417277 | H52: =DmdCalc!H$10*Pop!G26/Pop!G$28 -> 0.90230627 | I52: =DmdCalc!I$10*Pop!H26/Pop!H$28 -> 0.92734457 | J52: =DmdCalc!J$10*Pop!I26/Pop!I$28 -> 0.93340762 | K52: =DmdCalc!K$10*Pop!J26/Pop!J$28 -> 0.94375789 | L52: =DmdCalc!L$10*Pop!K26/Pop!K$28 -> 0.96245999 | ... N52: =DmdCalc!N$10*Pop!M26/Pop!M$28 -> 0.99048092
A53: *R6 | B53: =Commodities!$D$15 -> ROL | C53: Residential Other Appliances - LPG | D53: PJ
A54: *R6 | B54: =Commodities!$D$16 -> RRF | C54: Residential Refrigeration | D54: PJ | O54: 0.0788 | P54: 0.1045 | Q54: 0.1505 | R54: 0.0035 | S54: 0.1018 | T54: 0.1286 | U54: 0.1329 | V54: 0.0034 | W54: 0.0696 | X54: 0.1051 | Y54: 0.1181 | Z54: 0.0032
A55: R6 | B55: =Commodities!$D$17 -> RWH | C55: Residential Water Heating | D55: PJ | E55: =DmdCalc!E$5*Pop!D26/Pop!D$28 -> 10.01889 | F55: =DmdCalc!F$5*Pop!E26/Pop!E$28 -> 10.120024 | G55: =DmdCalc!G$5*Pop!F26/Pop!F$28 -> 9.482923 | H55: =DmdCalc!H$5*Pop!G26/Pop!G$28 -> 10.381547 | I55: =DmdCalc!I$5*Pop!H26/Pop!H$28 -> 9.8016611 | J55: =DmdCalc!J$5*Pop!I26/Pop!I$28 -> 9.6360649 | K55: =DmdCalc!K$5*Pop!J26/Pop!J$28 -> 9.5282683 | L55: =DmdCalc!L$5*Pop!K26/Pop!K$28 -> 9.3966536 | ... N55: =DmdCalc!N$5*Pop!M26/Pop!M$28 -> 8.9642786 | O55: 0.1215 | P55: 0.1114 | Q55: 0.1279 | R55: 0.0053 | S55: 0.0868 | T55: 0.0892 | U55: 0.0653 | V55: 0.002 | W55: 0.1324 | X55: 0.1486 | Y55: 0.1042 | Z55: 0.0054
A56: *NYC
A57: *R1 | B57: =Commodities!$D$9 -> RSC | C57: Residential Cooling | D57: PJ | E57: =SUM(E7,E17,E27,E37,E47) -> 31.310474 | F57: =SUM(F7,F17,F27,F37,F47) -> 31.085145 | G57: =SUM(G7,G17,G27,G37,G47) -> 31.290899 | H57: =SUM(H7,H17,H27,H37,H47) -> 31.235277 | I57: =SUM(I7,I17,I27,I37,I47) -> 31.050253 | J57: =SUM(J7,J17,J27,J37,J47) -> 31.163812 | K57: =SUM(K7,K17,K27,K37,K47) -> 33.737895 | L57: =SUM(L7,L17,L27,L37,L47) -> 33.785991 | ... N57: =SUM(N7,N17,N27,N37,N47) -> 35.90292 | O57: 0.0317 | P57: 0.1069 | Q57: 0.0502 | R57: 0.0042 | S57: 0.135 | T57: 0.4386 | U57: 0.184 | V57: 0.0169 | W57: 0.0097 | X57: 0.0099 | Y57: 0.0124 | Z57: 0.0005
A58: *R1 | B58: =Commodities!$D$10 -> RFZ | C58: Residential Freezing | D58: PJ | O58: 0.0795 | P58: 0.1018 | Q58: 0.1482 | R58: 0.0034 | S58: 0.1033 | T58: 0.1284 | U58: 0.1341 | V58: 0.0034 | W58: 0.0715 | X58: 0.1017 | Y58: 0.1217 | Z58: 0.003
A59: *R1 | B59: =Commodities!$D$11 -> RSH | C59: Residential Heating | D59: PJ | E59: =SUM(E9,E19,E29,E39,E49) -> 151.20019 | F59: =SUM(F9,F19,F29,F39,F49) -> 152.25591 | G59: =SUM(G9,G19,G29,G39,G49) -> 125.81567 | H59: =SUM(H9,H19,H29,H39,H49) -> 148.42704 | I59: =SUM(I9,I19,I29,I39,I49) -> 143.68032 | J59: =SUM(J9,J19,J29,J39,J49) -> 135.68515 | K59: =SUM(K9,K19,K29,K39,K49) -> 123.87616 | L59: =SUM(L9,L19,L29,L39,L49) -> 118.92566 | ... N59: =SUM(N9,N19,N29,N39,N49) -> 105.51047 | O59: 0.0641 | P59: 0.055 | Q59: 0.0944 | R59: 0.0031 | S59: 0.0037 | T59: 0.0021 | U59: 0.0026 | V59: 0.0001 | W59: 0.2163 | X59: 0.1943 | Y59: 0.3547 | Z59: 0.0096
A60: *R1 | B60: =Commodities!$D$12 -> RLT | C60: Residential Lighting | D60: =Commodities!$F$12 -> bn-lum-yr | E60: =SUM(E10,E20,E30,E40,E50) -> 9.4799044 | F60: =SUM(F10,F20,F30,F40,F50) -> 9.164463 | G60: =SUM(G10,G20,G30,G40,G50) -> 8.5061055 | H60: =SUM(H10,H20,H30,H40,H50) -> 2.981583 | I60: =SUM(I10,I20,I30,I40,I50) -> 3.0480813 | J60: =SUM(J10,J20,J30,J40,J50) -> 3.0380811 | K60: =SUM(K10,K20,K30,K40,K50) -> 3.0189965 | L60: =SUM(L10,L20,L30,L40,L50) -> 2.9163346 | ... N60: =SUM(N10,N20,N30,N40,N50) -> 2.9576435 | O60: 0.0627 | P60: 0.09 | Q60: 0.1773 | R60: 0.0033 | S60: 0.0591 | T60: 0.0914 | U60: 0.1315 | V60: 0.0014 | W60: 0.0742 | X60: 0.1447 | Y60: 0.1595 | Z60: 0.0049
A61: *R1 | B61: =Commodities!$D$13 -> ROE | C61: Residential Other Appliances - ELC | D61: PJ | E61: =SUM(E11,E21,E31,E41,E51) -> 29.802786 | F61: =SUM(F11,F21,F31,F41,F51) -> 28.811105 | G61: =SUM(G11,G21,G31,G41,G51) -> 26.741371 | H61: =SUM(H11,H21,H31,H41,H51) -> 33.351033 | I61: =SUM(I11,I21,I31,I41,I51) -> 35.331651 | J61: =SUM(J11,J21,J31,J41,J51) -> 37.007952 | K61: =SUM(K11,K21,K31,K41,K51) -> 39.189411 | L61: =SUM(L11,L21,L31,L41,L51) -> 41.99045 | ... N61: =SUM(N11,N21,N31,N41,N51) -> 49.348224 | O61: 0.0892 | P61: 0.1211 | Q61: 0.1084 | R61: 0.0044 | S61: 0.0865 | T61: 0.1257 | U61: 0.0674 | V61: 0.0031 | W61: 0.1079 | X61: 0.1718 | Y61: 0.1091 | Z61: 0.0054
A62: *R1 | B62: =Commodities!$D$14 -> ROG | C62: Residential Other Appliances - NGA | D62: PJ | E62: =SUM(E12,E22,E32,E42,E52) -> 2.6917017 | F62: =SUM(F12,F22,F32,F42,F52) -> 3.043493 | G62: =SUM(G12,G22,G32,G42,G52) -> 3.0766884 | H62: =SUM(H12,H22,H32,H42,H52) -> 3.6816573 | I62: =SUM(I12,I22,I32,I42,I52) -> 3.7844404 | J62: =SUM(J12,J22,J32,J42,J52) -> 3.8204347 | K62: =SUM(K12,K22,K32,K42,K52) -> 3.8739879 | L62: =SUM(L12,L22,L32,L42,L52) -> 3.9448439 | ... N62: =SUM(N12,N22,N32,N42,N52) -> 4.0688641
A63: *R1 | B63: =Commodities!$D$15 -> ROL | C63: Residential Other Appliances - LPG | D63: PJ
A64: *R1 | B64: =Commodities!$D$16 -> RRF | C64: Residential Refrigeration | D64: PJ | O64: 0.0788 | P64: 0.1045 | Q64: 0.1505 | R64: 0.0035 | S64: 0.1018 | T64: 0.1286 | U64: 0.1329 | V64: 0.0034 | W64: 0.0696 | X64: 0.1051 | Y64: 0.1181 | Z64: 0.0032
A65: *R1 | B65: =Commodities!$D$17 -> RWH | C65: Residential Water Heating | D65: PJ | E65: =SUM(E15,E25,E35,E45,E55) -> 39.76921 | F65: =SUM(F15,F25,F35,F45,F55) -> 40.881066 | G65: =SUM(G15,G25,G35,G45,G55) -> 38.686094 | H65: =SUM(H15,H25,H35,H45,H55) -> 42.359564 | I65: =SUM(I15,I25,I35,I45,I55) -> 40.000021 | J65: =SUM(J15,J25,J35,J45,J55) -> 39.440386 | K65: =SUM(K15,K25,K35,K45,K55) -> 39.112146 | L65: =SUM(L15,L25,L35,L45,L55) -> 38.514153 | ... N65: =SUM(N15,N25,N35,N45,N55) -> 36.824971 | O65: 0.1215 | P65: 0.1114 | Q65: 0.1279 | R65: 0.0053 | S65: 0.0868 | T65: 0.0892 | U65: 0.0653 | V65: 0.002 | W65: 0.1324 | X65: 0.1486 | Y65: 0.1042 | Z65: 0.0054

Sheet TechData_DMD
A1: TechData | B1: _GLOBAL,R0,R1,R2,R3,R4,R5,R6 | L1: R2 | M1: R3 | N1: R4 | O1: R5 | P1: R6 | S1: R2 | T1: R3 | U1: R4 | V1: R5 | W1: R6 | X1: R2 | Y1: R3 | Z1: R4 | AA1: R5 | AB1: R6 | AC1: R2 | AD1: R3 | AE1: R4 | AF1: R5 | AG1: R6
F6: ~FI_T
A7: Region | B7: TechName | C7: *TechDesc | D7: *Units | E7: CommIN | F7: CommOUT | G7: NCAP_START | H7: NCAP_TLIFE | I7: NCAP_COST | J7: EFF | K7: Share~UP | L7: NCAP_AF~R2 | M7: NCAP_AF~R3 | N7: NCAP_AF~R4 | O7: NCAP_AF~R5 | P7: NCAP_AF~R6 | Q7: NCAP_FOM | R7: NCAP_DRATE | S7: PRC_RESID~R2~2010 | T7: PRC_RESID~R3~2010 | U7: PRC_RESID~R4~2010 | V7: PRC_RESID~R5~2010 | W7: PRC_RESID~R6~2010 | X7: PRC_RESID~R2~2015 | Y7: PRC_RESID~R3~2015 | Z7: PRC_RESID~R4~2015 | AA7: PRC_RESID~R5~2015 | AB7: PRC_RESID~R6~2015 | AC7: PRC_RESID~R2~2020 | AD7: PRC_RESID~R3~2020 | AE7: PRC_RESID~R4~2020 | AF7: PRC_RESID~R5~2020 | AG7: PRC_RESID~R6~2020 | AH7: PRC_RESID~R4~2055 | AI7: NCAP_BND~2010 | AJ7: NCAP_BND~2015 | AK7: NCAP_BND~2020 | AL7: NCAP_BND~2025 | AM7: NCAP_BND~2030 | AN7: NCAP_BND~2035 | AO7: NCAP_BND~2040 | AP7: NCAP_BND~2045 | AQ7: NCAP_BND~2050 | AR7: NCAP_BND~2055
A8: *Space Heating
A9: *Electric Radiant Heating
A10: R2,R3,R4,R5,R6 | B10: RSHERDV110 | C10: Electric Radiant Ver1.RSH.ELC.10 | D10: PJ | E10: RESELC | F10: =Commodities!$D$11 -> RSH | G10: 2010 | H10: 20 | I10: 3.7369871 | J10: 1 | K10: 1 | L10: 0.16 | M10: 0.16 | N10: 0.16 | O10: 0.16 | P10: 0.16 | R10: 0.18 | S10: =Resid!U9 -> 4.6902592 | T10: =Resid!V9 -> 2.2297152 | U10: =Resid!W9 -> 3.9516778 | V10: =Resid!X9 -> 1.064069 | W10: =Resid!Y9 -> 4.0851125 | X10: =Resid!AJ9 -> 3.4695111 | Y10: =Resid!AK9 -> 1.6819851 | Z10: =Resid!AL9 -> 3.0825509 | AA10: =Resid!AM9 -> 0.73815893 | AB10: =Resid!AN9 -> 2.9316531 | AC10: =Resid!AY9 -> 2.4158177 | AD10: =Resid!AZ9 -> 1.1792311 | AE10: =Resid!BA9 -> 2.0621716 | AF10: =Resid!BB9 -> 0.48711217 | AG10: =Resid!BC9 -> 1.9844322 | AI10: 0 | AJ10: 0 | AK10: 0 | AL10: 0 | AM10: 0 | AN10: 0 | AO10: 0 | AP10: 0 | AQ10: 0 | AR10: 0
A11: *Electric Resistance Furnaces
A12: *Electric Heat Pumps
A13: R2,R3,R4,R5,R6 | B13: RSHEHPV110 | C13: Electric Heat Pump Ver1.RSH.ELC.10 | D13: PJ | E13: RESELC | F13: =Commodities!$D$11 -> RSH | G13: 2010 | H13: 15 | I13: 4.0729892 | J13: 2.26 | K13: 1 | L13: 0.16 | M13: 0.16 | N13: 0.16 | O13: 0.16 | P13: 0.16 | R13: 0.18 | S13: =Resid!U12 -> 2.3993521 | T13: =Resid!V12 -> 1.1406346 | U13: =Resid!W12 -> 2.0215229 | V13: =Resid!X12 -> 0.54433582 | W13: =Resid!Y12 -> 2.0897828 | X13: =Resid!AJ12 -> 4.7975571 | Y13: =Resid!AK12 -> 2.3258088 | Z13: =Resid!AL12 -> 4.2624779 | AA13: =Resid!AM12 -> 1.0207086 | AB13: =Resid!AN12 -> 4.05382 | AC13: =Resid!AY12 -> 5.2807679 | AD13: =Resid!AZ12 -> 2.5776969 | AE13: =Resid!BA12 -> 4.5077281 | AF13: =Resid!BB12 -> 1.0647849 | AG13: =Resid!BC12 -> 4.3377966 | AI13: 0 | AJ13: 0 | AK13: 0 | AL13: 0 | AM13: 0 | AN13: 0 | AO13: 0 | AP13: 0 | AQ13: 0 | AR13: 0
A14: *Natural Gas Furnaces
A15: R2,R3,R4,R5,R6 | B15: RSHNFRV110 | C15: Natural Gas Furnace Ver1.RSH.NGA.10 | D15: PJ | E15: RESNGAEA | F15: =Commodities!$D$11 -> RSH | G15: 2010 | H15: 15 | I15: 3.5376821 | J15: 0.78 | K15: 1 | L15: 0.16 | M15: 0.16 | N15: 0.16 | O15: 0.16 | P15: 0.16 | R15: 0.15 | S15: =Resid!U27 -> 105.29643 | T15: =Resid!V27 -> 50.057159 | U15: =Resid!W27 -> 88.715259 | V15: =Resid!X27 -> 23.888373 | W15: =Resid!Y27 -> 91.710871 | X15: =Resid!AJ27 -> 121.48624 | Y15: =Resid!AK27 -> 58.895341 | Z15: =Resid!AL27 -> 107.93668 | AA15: =Resid!AM27 -> 25.846913 | AB15: =Resid!AN27 -> 102.65294 | AC15: =Resid!AY27 -> 114.02275 | AD15: =Resid!AZ27 -> 55.657834 | AE15: =Resid!BA27 -> 97.331217 | AF15: =Resid!BB27 -> 22.990919 | AG15: =Resid!BC27 -> 93.662044 | AI15: 0 | AJ15: 0 | AK15: 0
A16: *Natural Gas Radiant Heating
A17: R2,R3,R4,R5,R6 | B17: RSHNRDV110 | C17: Natural Gas Radiant Ver1.RSH.NGA.10 | D17: PJ | E17: RESNGAEA | F17: =Commodities!$D$11 -> RSH | G17: 2010 | H17: 20 | I17: 8.2856238 | J17: 0.8 | K17: 1 | L17: 0.16 | M17: 0.16 | N17: 0.16 | O17: 0.16 | P17: 0.16 | R17: 0.15 | S17: =Resid!U34 -> 64.152367 | T17: =Resid!V34 -> 30.49757 | U17: =Resid!W34 -> 54.050208 | V17: =Resid!X34 -> 14.554109 | W17: =Resid!Y34 -> 55.875298 | X17: =Resid!AJ34 -> 71.204274 | Y17: =Resid!AK34 -> 34.519137 | Z17: =Resid!AL34 -> 63.262747 | AA17: =Resid!AM34 -> 15.149129 | AB17: =Resid!AN34 -> 60.165894 | AC17: =Resid!AY34 -> 64.326862 | AD17: =Resid!AZ34 -> 31.399819 | AE17: =Resid!BA34 -> 54.910197 | AF17: =Resid!BB34 -> 12.970514 | AG17: =Resid!BC34 -> 52.840203 | AI17: 0 | AJ17: 0 | AK17: 0 | AL17: 0 | AM17: 0 | AN17: 0 | AO17: 0 | AP17: 0 | AQ17: 0 | AR17: 0
A18: *Kerosene Furnaces
A19: *LPG Furnaces
A20: *Fuel Oil (DSL) Furnaces
A21: R2,R3,R4,R5,R6 | B21: RSHDFRV110 | C21: Distillate Furnace Ver1.RSH.DST.10 | D21: PJ | E21: RESDSLEA | F21: =Commodities!$D$11 -> RSH | G21: 2010 | H21: 20 | I21: 6.3922148 | J21: 0.8 | K21: 1 | L21: 0.16 | M21: 0.16 | N21: 0.16 | O21: 0.16 | P21: 0.16 | R21: 0.18 | S21: =Resid!U45 -> 20.966428 | T21: =Resid!V45 -> 9.9672877 | U21: =Resid!W45 -> 17.664816 | V21: =Resid!X45 -> 4.7566081 | W21: =Resid!Y45 -> 18.261297 | X21: =Resid!AJ45 -> 19.39449 | Y21: =Resid!AK45 -> 9.4022592 | Z21: =Resid!AL45 -> 17.231391 | AA21: =Resid!AM45 -> 4.126292 | AB21: =Resid!AN45 -> 16.387876 | AC21: =Resid!AY45 -> 13.868938 | AD21: =Resid!AZ45 -> 6.7698336 | AE21: =Resid!BA45 -> 11.838696 | AF21: =Resid!BB45 -> 2.7964563 | AG21: =Resid!BC45 -> 11.392403 | AI21: 0 | AJ21: 0 | AK21: 0 | AL21: 0 | AM21: 0 | AN21: 0 | AO21: 0 | AP21: 0 | AQ21: 0 | AR21: 0
A22: *Dfuel Oil (DSL) Radiant Space Heating
A23: R2,R3,R4,R5,R6 | B23: RSHDRDV110 | C23: Distillate Radiant Ver1.RSH.DST.10 | D23: PJ | E23: RESDSLEA | F23: =Commodities!$D$11 -> RSH | G23: 2010 | H23: 20 | I23: 11.507811 | J23: 0.85 | K23: 1 | L23: 0.16 | M23: 0.16 | N23: 0.16 | O23: 0.16 | P23: 0.16 | R23: 0.18 | S23: =Resid!U51 -> 48.65557 | T23: =Resid!V51 -> 23.130505 | U23: =Resid!W51 -> 40.993712 | V23: =Resid!X51 -> 11.038384 | W23: =Resid!Y51 -> 42.377929 | X23: =Resid!AJ51 -> 26.475951 | Y23: =Resid!AK51 -> 12.835282 | Z23: =Resid!AL51 -> 23.523046 | AA23: =Resid!AM51 -> 5.6329146 | AB23: =Resid!AN51 -> 22.37154 | AC23: =Resid!AY51 -> 8.6205856 | AD23: =Resid!AZ51 -> 4.2079594 | AE23: =Resid!BA51 -> 7.3586374 | AF23: =Resid!BB51 -> 1.7382074 | AG23: =Resid!BC51 -> 7.0812329 | AI23: 0 | AJ23: 0 | AK23: 0 | AL23: 0 | AM23: 0 | AN23: 0 | AO23: 0 | AP23: 0 | AQ23: 0 | AR23: 0
A24: *UTILITY SCALE CHP - SH | L24: =IF(K24="","",K24)
A25: R4 | B25: RSHNUTIBOI | C25: RSH.NG.UTILITY.BOILER | D25: PJ | E25: RESSTNB | F25: =Commodities!$D$11 -> RSH | G25: 2010 | H25: 30 | I25: 2.5215838 | J25: 0.78 | L25: 0.16 | M25: 0.16 | N25: 0.16 | O25: 0.16 | P25: 0.16 | Q25: 0.070919543 | R25: 0.18 | S25: =Resid!U56 -> 0 | T25: =Resid!V56 -> 0 | U25: =Resid!W56 -> 18.013416 | V25: =Resid!X56 -> 0 | W25: =Resid!Y56 -> 0 | X25: =Resid!AJ56 -> 0 | Y25: =Resid!AK56 -> 0 | Z25: =Resid!AL56 -> 17.927436 | AA25: =Resid!AM56 -> 0 | AB25: =Resid!AN56 -> 0 | AC25: =Resid!AY56 -> 0 | AD25: =Resid!AZ56 -> 0 | AE25: =Resid!BA56 -> 16.139476 | AF25: =Resid!BB56 -> 0 | AG25: =Resid!BC56 -> 0 | AH25: =AE25 -> 16.139476 | AI25: 0 | AJ25: 0 | AK25: 0 | AL25: 0 | AM25: 0 | AN25: 0 | AO25: 0 | AP25: 0 | AQ25: 0 | AR25: 0
A26: R4 | B26: RSHNUTICHP | C26: RSH.NG.UTILITY.CHP | D26: PJ | E26: RESSTNUC | F26: =Commodities!$D$11 -> RSH | G26: 2010 | H26: 30 | I26: 2.5215838 | J26: 0.78 | L26: 0.16 | M26: 0.16 | N26: 0.16 | O26: 0.16 | P26: 0.16 | Q26: 0.070919543 | R26: 0.18 | S26: =Resid!U57 -> 0 | T26: =Resid!V57 -> 0 | U26: =Resid!W57 -> 23.899633 | V26: =Resid!X57 -> 0 | W26: =Resid!Y57 -> 0 | X26: =Resid!AJ57 -> 0 | Y26: =Resid!AK57 -> 0 | Z26: =Resid!AL57 -> 23.785557 | AA26: =Resid!AM57 -> 0 | AB26: =Resid!AN57 -> 0 | AC26: =Resid!AY57 -> 0 | AD26: =Resid!AZ57 -> 0 | AE26: =Resid!BA57 -> 21.413349 | AF26: =Resid!BB57 -> 0 | AG26: =Resid!BC57 -> 0 | AH26: =AE26 -> 21.413349 | AI26: 0 | AJ26: 0 | AK26: 0 | AL26: 0 | AM26: 0 | AN26: 0 | AO26: 0 | AP26: 0 | AQ26: 0 | AR26: 0
A27: R4 | B27: RSHBUTICHP | C27: RSH.DSL.UTILITY.CHP | D27: PJ | E27: RESSTBUC | F27: =Commodities!$D$11 -> RSH | G27: 2010 | H27: 30 | I27: 2.5215838 | J27: 0.78 | L27: 0.16 | M27: 0.16 | N27: 0.16 | O27: 0.16 | P27: 0.16 | Q27: 0.070919543 | R27: 0.18 | S27: =Resid!U58 -> 0 | T27: =Resid!V58 -> 0 | U27: =Resid!W58 -> 0.021080538 | V27: =Resid!X58 -> 0 | W27: =Resid!Y58 -> 0 | X27: =Resid!AJ58 -> 0 | Y27: =Resid!AK58 -> 0 | Z27: =Resid!AL58 -> 0.020979917 | AA27: =Resid!AM58 -> 0 | AB27: =Resid!AN58 -> 0 | AC27: =Resid!AY58 -> 0 | AD27: =Resid!AZ58 -> 0 | AE27: =Resid!BA58 -> 0.031044583 | AF27: =Resid!BB58 -> 0 | AG27: =Resid!BC58 -> 0 | AH27: =AE27 -> 0.031044583 | AI27: 0 | AJ27: 0 | AK27: 0 | AL27: 0 | AM27: 0 | AN27: 0 | AO27: 0 | AP27: 0 | AQ27: 0 | AR27: 0
A28: *Wood Fired Furnaces
A29: *Geothermal Heat Pumps
A30: *Natural Gas Heat Pumps
A31: *Space Cooling
A32: *Room/Window AC
A33: R2,R3,R4,R5,R6 | B33: RSCRACV110 | C33: Room AC Ver1.RSC.ELC.10 | D33: PJ | E33: RESELC | F33: RSC | G33: 2010 | H33: 10 | I33: 3.5842305 | J33: 2.74 | K33: 1 | L33: 0.15 | M33: 0.15 | N33: 0.15 | O33: 0.15 | P33: 0.15 | R33: 0.6 | S33: =Resid!U63 -> 20.209281 | T33: =Resid!V63 -> 10.102543 | U33: =Resid!W63 -> 15.492338 | V33: =Resid!X63 -> 3.6791663 | W33: =Resid!Y63 -> 17.637348 | X33: =Resid!AJ63 -> 24.096392 | Y33: =Resid!AK63 -> 12.255382 | Z33: =Resid!AL63 -> 19.921013 | AA33: =Resid!AM63 -> 4.448169 | AB33: =Resid!AN63 -> 20.659393 | AC33: =Resid!AY63 -> 28.26642 | AD33: =Resid!AZ63 -> 14.574963 | AE33: =Resid!BA63 -> 21.570863 | AF33: =Resid!BB63 -> 4.686693 | AG33: =Resid!BC63 -> 22.902978 | AI33: 0 | AJ33: 0 | AK33: 0 | AL33: 0 | AM33: 0 | AN33: 0 | AO33: 0 | AP33: 0 | AQ33: 0 | AR33: 0
A34: *Central AC Units
A35: R2,R3,R4,R5,R6 | B35: RSCCACV110 | C35: Central AC Ver1.RSC.ELC.10 | D35: PJ | E35: RESELC | F35: RSC | G35: 2010 | H35: 11 | I35: 5.4306523 | J35: 2.92 | K35: 1 | L35: 0.15 | M35: 0.15 | N35: 0.15 | O35: 0.15 | P35: 0.15 | R35: 0.18 | S35: =Resid!U71 -> 40.770302 | T35: =Resid!V71 -> 20.380919 | U35: =Resid!W71 -> 31.254318 | V35: =Resid!X71 -> 7.4223679 | W35: =Resid!Y71 -> 35.581671 | X35: =Resid!AJ71 -> 32.810172 | Y35: =Resid!AK71 -> 16.687195 | Z35: =Resid!AL71 -> 27.124885 | AA35: =Resid!AM71 -> 6.0567238 | AB35: =Resid!AN71 -> 28.130279 | AC35: =Resid!AY71 -> 29.305651 | AD35: =Resid!AZ71 -> 15.11082 | AE35: =Resid!BA71 -> 22.363928 | AF35: =Resid!BB71 -> 4.859002 | AG35: =Resid!BC71 -> 23.745019 | AI35: 0 | AJ35: 0 | AK35: 0 | AL35: 0 | AM35: 0 | AN35: 0 | AO35: 0 | AP35: 0 | AQ35: 0 | AR35: 0
A36: *Portable AC Units
A37: *Electric Heat Pumps
A38: R2,R3,R4,R5,R6 | B38: RSCEHPV110 | C38: Electric Heat Pump Ver1.RSC.ELC.10 | D38: PJ | E38: RESELC | F38: RSC | G38: 2010 | H38: 15 | I38: 4.0729892 | J38: 3 | K38: 1 | L38: 0.15 | M38: 0.15 | N38: 0.15 | O38: 0.15 | P38: 0.15 | R38: 0.45 | S38: =Resid!U81 -> 1.8686296 | T38: =Resid!V81 -> 0.93412086 | U38: =Resid!W81 -> 1.4324825 | V38: =Resid!X81 -> 0.34019019 | W38: =Resid!Y81 -> 1.6308186 | X38: =Resid!AJ81 -> 4.4546727 | Y38: =Resid!AK81 -> 2.2656386 | Z38: =Resid!AL81 -> 3.6827752 | AA38: =Resid!AM81 -> 0.82232799 | AB38: =Resid!AN81 -> 3.8192787 | AC38: =Resid!AY81 -> 6.5194698 | AD38: =Resid!AZ81 -> 3.3616225 | AE38: =Resid!BA81 -> 4.9751823 | AF38: =Resid!BB81 -> 1.0809559 | AG38: =Resid!BC81 -> 5.2824261 | AI38: 0 | AJ38: 0 | AK38: 0 | AL38: 0 | AM38: 0 | AN38: 0 | AO38: 0 | AP38: 0 | AQ38: 0 | AR38: 0
A39: *Geothermal Heat Pumps
A40: *Natural Gas Heat Pumps
A41: *Water Heating
A42: *Natural Gas
A43: R2,R3,R4,R5,R6 | B43: RWHNWHV110 | C43: Natural Gas Ver1.RWH.NGA.10 | D43: PJ | E43: RESNGAEA | F43: RWH | G43: 2010 | H43: 8 | I43: 7.9209267 | J43: 0.59 | K43: 1 | L43: 0.1 | M43: 0.1 | N43: 0.1 | O43: 0.1 | P43: 0.1 | R43: 0.18 | S43: =Resid!U101 -> 90.94865 | T43: =Resid!V101 -> 47.399615 | U43: =Resid!W101 -> 72.446515 | V43: =Resid!X101 -> 16.214705 | W43: =Resid!Y101 -> 76.449027 | X43: =Resid!AJ101 -> 101.94989 | Y43: =Resid!AK101 -> 53.593587 | Z43: =Resid!AL101 -> 84.334383 | AA43: =Resid!AM101 -> 18.30269 | AB43: =Resid!AN101 -> 84.938394 | AC43: =Resid!AY101 -> 104.97797 | AD43: =Resid!AZ101 -> 55.565489 | AE43: =Resid!BA101 -> 83.432397 | AF43: =Resid!BB101 -> 17.861155 | AG43: =Resid!BC101 -> 85.024335 | AI43: 0 | AJ43: 0 | AK43: 0 | AL43: 0 | AM43: 0 | AN43: 0 | AO43: 0 | AP43: 0 | AQ43: 0 | AR43: 0
A44: *Electric Water Heaters
A45: R2,R3,R4,R5,R6 | B45: RWHEWHV110 | C45: Electric Ver1.RWH.ELC.10 | D45: PJ | E45: RESELC | F45: RWH | G45: 2010 | H45: 6 | I45: 4.8471342 | J45: 0.9 | K45: 1 | L45: 0.1 | M45: 0.1 | N45: 0.1 | O45: 0.1 | P45: 0.1 | R45: 0.18 | S45: =Resid!U109 -> 3.8075853 | T45: =Resid!V109 -> 1.9843953 | U45: =Resid!W109 -> 3.0329893 | V45: =Resid!X109 -> 0.67883219 | W45: =Resid!Y109 -> 3.2005553 | X45: =Resid!AJ109 -> 3.6492014 | Y45: =Resid!AK109 -> 1.9183325 | Z45: =Resid!AL109 -> 3.0186707 | AA45: =Resid!AM109 -> 0.65512773 | AB45: =Resid!AN109 -> 3.0402907 | AC45: =Resid!AY109 -> 3.4500213 | AD45: =Resid!AZ109 -> 1.8261176 | AE45: =Resid!BA109 -> 2.7419424 | AF45: =Resid!BB109 -> 0.5869933 | AG45: =Resid!BC109 -> 2.7942602 | AI45: 0 | AJ45: 0 | AK45: 0 | AL45: 0 | AM45: 0 | AN45: 0 | AO45: 0 | AP45: 0 | AQ45: 0 | AR45: 0
A46: *Fuel Oil (DSL) Water Heaters
A47: R2,R3,R4,R5,R6 | B47: RWHDWHV110 | C47: Distillate Ver1.RWH.DSL.10 | D47: PJ | E47: RESDSLEA | F47: RWH | G47: 2010 | H47: 10 | I47: 16.089338 | J47: 0.53 | K47: 1 | L47: 0.1 | M47: 0.1 | N47: 0.1 | O47: 0.1 | P47: 0.1 | R47: 0.18 | S47: =Resid!U118 -> 24.434882 | T47: =Resid!V118 -> 12.734703 | U47: =Resid!W118 -> 19.463973 | V47: =Resid!X118 -> 4.3563528 | W47: =Resid!Y118 -> 20.539315 | X47: =Resid!AJ118 -> 15.869577 | Y47: =Resid!AK118 -> 8.3424077 | Z47: =Resid!AL118 -> 13.127537 | AA47: =Resid!AM118 -> 2.849007 | AB47: =Resid!AN118 -> 13.221558 | AC47: =Resid!AY118 -> 8.6559007 | AD47: =Resid!AZ118 -> 4.5816218 | AE47: =Resid!BA118 -> 6.8793723 | AF47: =Resid!BB118 -> 1.4727317 | AG47: =Resid!BC118 -> 7.0106347 | AI47: 0 | AJ47: 0 | AK47: 0 | AL47: 0 | AM47: 0 | AN47: 0 | AO47: 0 | AP47: 0 | AQ47: 0 | AR47: 0
A48: *UTILITY SCALE CHP - WH | L48: =IF(K48="","",K48)
A49: R4 | B49: RWHNUTIBOI | C49: RWH.NG.UTILITY.BOILER | D49: PJ | E49: RESSTNB | F49: RWH | G49: 2010 | H49: 30 | I49: 2.5215838 | J49: 0.78 | L49: 0.1 | M49: 0.1 | N49: 0.1 | O49: 0.1 | P49: 0.1 | Q49: 0.070919543 | R49: 0.18 | S49: =Resid!U122 -> 0 | T49: =Resid!V122 -> 0 | U49: =Resid!W122 -> 4.6460994 | V49: =Resid!X122 -> 0 | W49: =Resid!Y122 -> 0 | X49: =Resid!AJ122 -> 0 | Y49: =Resid!AK122 -> 0 | Z49: =Resid!AL122 -> 4.6239228 | AA49: =Resid!AM122 -> 0 | AB49: =Resid!AN122 -> 0 | AC49: =Resid!AY122 -> 0 | AD49: =Resid!AZ122 -> 0 | AE49: =Resid!BA122 -> 4.1627646 | AF49: =Resid!BB122 -> 0 | AG49: =Resid!BC122 -> 0 | AH49: =AE49 -> 4.1627646 | AI49: 0 | AJ49: 0 | AK49: 0 | AL49: 0 | AM49: 0 | AN49: 0 | AO49: 0 | AP49: 0 | AQ49: 0 | AR49: 0
A50: R4 | B50: RWHNUTICHP | C50: RWH.NG.UTILITY.CHP | D50: PJ | E50: RESSTNUC | F50: RWH | G50: 2010 | H50: 30 | I50: 2.5215838 | J50: 0.78 | L50: 0.1 | M50: 0.1 | N50: 0.1 | O50: 0.1 | P50: 0.1 | Q50: 0.070919543 | R50: 0.18 | S50: =Resid!U123 -> 0 | T50: =Resid!V123 -> 0 | U50: =Resid!W123 -> 6.1642983 | V50: =Resid!X123 -> 0 | W50: =Resid!Y123 -> 0 | X50: =Resid!AJ123 -> 0 | Y50: =Resid!AK123 -> 0 | Z50: =Resid!AL123 -> 6.1348751 | AA50: =Resid!AM123 -> 0 | AB50: =Resid!AN123 -> 0 | AC50: =Resid!AY123 -> 0 | AD50: =Resid!AZ123 -> 0 | AE50: =Resid!BA123 -> 5.5230249 | AF50: =Resid!BB123 -> 0 | AG50: =Resid!BC123 -> 0 | AH50: =AE50 -> 5.5230249 | AJ50: 0 | AK50: 0 | AL50: 0 | AM50: 0 | AN50: 0 | AO50: 0 | AP50: 0 | AQ50: 0 | AR50: 0
A51: R4 | B51: RWHBUTICHP | C51: RWH.DSL.UTILITY.CHP | D51: PJ | E51: RESSTBUC | F51: RWH | G51: 2010 | H51: 30 | I51: 2.5215838 | J51: 0.78 | L51: 0.1 | M51: 0.1 | N51: 0.1 | O51: 0.1 | P51: 0.1 | Q51: 0.070919543 | R51: 0.18 | S51: =Resid!U124 -> 0 | T51: =Resid!V124 -> 0 | U51: =Resid!W124 -> 0.0089368587 | V51: =Resid!X124 -> 0 | W51: =Resid!Y124 -> 0 | X51: =Resid!AJ124 -> 0 | Y51: =Resid!AK124 -> 0 | Z51: =Resid!AL124 -> 0.0088942016 | AA51: =Resid!AM124 -> 0 | AB51: =Resid!AN124 -> 0 | AC51: =Resid!AY124 -> 0 | AD51: =Resid!AZ124 -> 0 | AE51: =Resid!BA124 -> 0.0080071552 | AF51: =Resid!BB124 -> 0 | AG51: =Resid!BC124 -> 0 | AH51: =AE51 -> 0.0080071552 | AJ51: 0 | AK51: 0 | AL51: 0 | AM51: 0 | AN51: 0 | AO51: 0 | AP51: 0 | AQ51: 0 | AR51: 0
A52: *Gas Water Heaters
A53: *Solar
A54: *Refrigeration
A55: *Freezer
A56: *Lighting
A57: R2,R3,R4,R5,R6 | B57: RLTGINC10 | C57: RLT.GSL.INC.10 | D57: bn-lum-yr | E57: =Commodities!$D$19 -> RESELC | F57: =Commodities!$D$12 -> RLT | G57: =IF(RIGHT(B57,2)="TI",2010,CONCATENATE(20,RIGHT(B57,2))) -> 2010 | H57: =Lighting!P24 -> 1.1643836 | I57: =Lighting!N24 -> 0.29993805 | J57: =Lighting!M24 -> 0.45981101 | K57: 1 | L57: 1 | M57: 1 | N57: 1 | O57: 1 | P57: 1 | R57: 0.18 | S57: =Resid!U127 -> 1.7134105 | T57: =Resid!V127 -> 0.89297638 | U57: =Resid!W127 -> 1.3648429 | V57: =Resid!X127 -> 0.30547397 | W57: =Resid!Y127 -> 1.4402475 | X57: =Resid!AJ127 -> 0.84413282 | Y57: =Resid!AK127 -> 0.44374844 | Z57: =Resid!AL127 -> 0.69827853 | AA57: =Resid!AM127 -> 0.15154407 | AB57: =Resid!AN127 -> 0.70327966 | AC57: =Resid!AY127 -> 0.38615734 | AD57: =Resid!AZ127 -> 0.20439547 | AE57: =Resid!BA127 -> 0.30690279 | AF57: =Resid!BB127 -> 0.065701557 | AG57: =Resid!BC127 -> 0.31275867 | AI57: 0 | AJ57: 0 | AK57: 0 | AL57: 0 | AM57: 0 | AN57: 0 | AO57: 0 | AP57: 0 | AQ57: 0 | AR57: 0
A58: R2,R3,R4,R5,R6 | B58: RLTGCFL10 | C58: RLT.GSL.CFL.10 | D58: bn-lum-yr | E58: =Commodities!$D$19 -> RESELC | F58: =Commodities!$D$12 -> RLT | G58: =IF(RIGHT(B58,2)="TI",2010,CONCATENATE(20,RIGHT(B58,2))) -> 2010 | H58: =Lighting!P30 -> 13.69863 | I58: =Lighting!N30 -> 2.7903328 | J58: =Lighting!M30 -> 2.1309862 | K58: 1 | L58: 1 | M58: 1 | N58: 1 | O58: 1 | P58: 1 | R58: 0.28 | S58: =Resid!U128 -> 0.3324197 | T58: =Resid!V128 -> 0.17324684 | U58: =Resid!W128 -> 0.26479391 | V58: =Resid!X128 -> 0.059265171 | W58: =Resid!Y128 -> 0.2794232 | X58: =Resid!AJ128 -> 0.87136291 | Y58: =Resid!AK128 -> 0.45806291 | Z58: =Resid!AL128 -> 0.72080364 | AA58: =Resid!AM128 -> 0.15643258 | AB58: =Resid!AN128 -> 0.7259661 | AC58: =Resid!AY128 -> 0.30892587 | AD58: =Resid!AZ128 -> 0.16351637 | AE58: =Resid!BA128 -> 0.24552223 | AF58: =Resid!BB128 -> 0.052561245 | AG58: =Resid!BC128 -> 0.25020694 | AI58: 0 | AJ58: 0 | AK58: 0 | AL58: 0 | AM58: 0 | AN58: 0 | AO58: 0 | AP58: 0 | AQ58: 0 | AR58: 0
A59: R2,R3,R4,R5,R6 | B59: RLTRINC10 | C59: RLT.REF.INC.10 | D59: bn-lum-yr | E59: =Commodities!$D$19 -> RESELC | F59: =Commodities!$D$12 -> RLT | G59: 2010 | H59: =Lighting!M51 -> 0.76793723 | I59: =Lighting!N51 -> 0 | J59: =Lighting!M51 -> 0.76793723 | K59: 1 | L59: 1 | M59: 1 | N59: 1 | O59: 1 | P59: 1 | R59: 0.18 | S59: =Resid!U129 -> 0.1420597 | T59: =Resid!V129 -> 0.074037109 | U59: =Resid!W129 -> 0.11315979 | V59: =Resid!X129 -> 0.025326996 | W59: =Resid!Y129 -> 0.11941162 | X59: =Resid!AJ129 -> 0.10892036 | Y59: =Resid!AK129 -> 0.057257863 | Z59: =Resid!AL129 -> 0.090100455 | AA59: =Resid!AM129 -> 0.019554073 | AB59: =Resid!AN129 -> 0.090745763 | AC59: =Resid!AY129 -> 1.2099597 | AD59: =Resid!AZ129 -> 0.64043913 | AE59: =Resid!BA129 -> 0.96162875 | AF59: =Resid!BB129 -> 0.20586488 | AG59: =Resid!BC129 -> 0.97997718 | AI59: 0 | AJ59: 0 | AK59: 0 | AL59: 0 | AM59: 0 | AN59: 0 | AO59: 0 | AP59: 0 | AQ59: 0 | AR59: 0
A60: R2,R3,R4,R5,R6 | B60: RLTLFL10 | C60: RLT.LFL.10 | D60: bn-lum-yr | E60: =Commodities!$D$19 -> RESELC | F60: =Commodities!$D$12 -> RLT | G60: =IF(RIGHT(B60,2)="TI",2010,CONCATENATE(20,RIGHT(B60,2))) -> 2010 | H60: =Lighting!P84 -> 32.876712 | I60: =Lighting!N84 -> 5.2625494 | J60: =Lighting!M84 -> 2.0009707 | K60: 1 | L60: 1 | M60: 1 | N60: 1 | O60: 1 | P60: 1 | R60: 0.18 | S60: =Resid!U130 -> 0.51141493 | T60: =Resid!V130 -> 0.26653359 | U60: =Resid!W130 -> 0.40737525 | V60: =Resid!X130 -> 0.091177187 | W60: =Resid!Y130 -> 0.42988184 | X60: =Resid!AJ130 -> 0.4492965 | Y60: =Resid!AK130 -> 0.23618869 | Z60: =Resid!AL130 -> 0.37166438 | AA60: =Resid!AM130 -> 0.080660552 | AB60: =Resid!AN130 -> 0.37432627 | AC60: =Resid!AY130 -> 0.33466969 | AD60: =Resid!AZ130 -> 0.17714274 | AE60: =Resid!BA130 -> 0.26598242 | AF60: =Resid!BB130 -> 0.056941349 | AG60: =Resid!BC130 -> 0.27105752 | AI60: 0 | AJ60: 0 | AK60: 0 | AL60: 0 | AM60: 0 | AN60: 0 | AO60: 0 | AP60: 0 | AQ60: 0 | AR60: 0
A61: R2,R3,R4,R5,R6 | B61: RLTEXTBS | C61: RLT.EXT.BS | D61: bn-lum-yr | E61: =Commodities!$D$19 -> RESELC | F61: =Commodities!$D$12 -> RLT | G61: 2010 | H61: =Lighting!M96 -> 1.3102452 | I61: =Lighting!N96 -> 0 | J61: =Lighting!M96 -> 1.3102452 | K61: 1 | L61: 1 | M61: 1 | N61: 1 | O61: 1 | P61: 1 | R61: 0.18 | S61: =Resid!U131 -> 0.14188923 | T61: =Resid!V131 -> 0.073948265 | U61: =Resid!W131 -> 0.113024 | V61: =Resid!X131 -> 0.025296604 | W61: =Resid!Y131 -> 0.11926833 | X61: =Resid!AJ131 -> 0.4492965 | Y61: =Resid!AK131 -> 0.23618869 | Z61: =Resid!AL131 -> 0.37166438 | AA61: =Resid!AM131 -> 0.080660552 | AB61: =Resid!AN131 -> 0.37432627 | AC61: =Resid!AY131 -> 0.33466969 | AD61: =Resid!AZ131 -> 0.17714274 | AE61: =Resid!BA131 -> 0.26598242 | AF61: =Resid!BB131 -> 0.056941349 | AG61: =Resid!BC131 -> 0.27105752 | AI61: 0 | AJ61: 0 | AK61: 0 | AL61: 0 | AM61: 0 | AN61: 0 | AO61: 0 | AP61: 0 | AQ61: 0 | AR61: 0
A62: * Residential Other
A63: R2,R3,R4,R5,R6 | B63: ROTHCELC | C63: Residential Other - Electric | D63: PJ | E63: =Commodities!$D$19 -> RESELC | F63: ROE | G63: 2010 | H63: 45 | J63: 1 | K63: 1 | L63: 1 | M63: 1 | N63: 1 | O63: 1 | P63: 1 | R63: 0.18 | S63: =Resid!U133 -> 8.9321044 | T63: =Resid!V133 -> 4.6551357 | U63: =Resid!W133 -> 7.1150021 | V63: =Resid!X133 -> 1.5924528 | W63: =Resid!Y133 -> 7.5080905 | X63: =Resid!AJ133 -> 8.5605564 | Y63: =Resid!AK133 -> 4.5001609 | Z63: =Resid!AL133 -> 7.0814124 | AA63: =Resid!AM133 -> 1.5368453 | AB63: =Resid!AN133 -> 7.1321302 | AC63: =Resid!AY133 -> 8.0933054 | AD63: =Resid!AZ133 -> 4.2838366 | AE63: =Resid!BA133 -> 6.4322435 | AF63: =Resid!BB133 -> 1.3770106 | AG63: =Resid!BC133 -> 6.5549744 | AI63: 0 | AJ63: 0 | AK63: 0 | AL63: 0 | AM63: 0 | AN63: 0 | AO63: 0 | AP63: 0 | AQ63: 0 | AR63: 0
A64: R2,R3,R4,R5,R6 | B64: ROTHNGA | C64: Residential Other - NGA | D64: PJ | E64: =Commodities!$D$20 -> RESNGAEA | F64: ROG | G64: 2010 | H64: 45 | J64: 1 | K64: 1 | L64: 1 | M64: 1 | N64: 1 | O64: 1 | P64: 1 | R64: 0.18 | S64: =Resid!U134 -> 0.80672192 | T64: =Resid!V134 -> 0.42043844 | U64: =Resid!W134 -> 0.64260648 | V64: =Resid!X134 -> 0.14382575 | W64: =Resid!Y134 -> 0.67810909 | X64: =Resid!AJ134 -> 0.90430384 | Y64: =Resid!AK134 -> 0.47537947 | Z64: =Resid!AL134 -> 0.74805283 | AA64: =Resid!AM134 -> 0.16234635 | AB64: =Resid!AN134 -> 0.75341046 | AC64: =Resid!AY134 -> 0.93116314 | AD64: =Resid!AZ134 -> 0.49287041 | AE64: =Resid!BA134 -> 0.74005215 | AF64: =Resid!BB134 -> 0.1584299 | AG64: =Resid!BC134 -> 0.75417277 | AI64: 0 | AJ64: 0 | AK64: 0 | AL64: 0 | AM64: 0 | AN64: 0 | AO64: 0 | AP64: 0 | AQ64: 0 | AR64: 0
A65: * Dummy/Pass Through Technologies for NYC LITE Model to Meet Populaiton Demand
A66: R2,R3,R4,R5,R6 | B66: RBLDHEDM | C66: Residential Building High Eff | D66: Mt, Mt/a | E66: RBLDHEDMY | F66: POPDMRES | G66: 2010 | H66: 55 | I66: 0 | J66: 1 | L66: 1 | M66: 1 | N66: 1 | O66: 1 | P66: 1 | Q66: 0 | R66: 0.01
A67: R2,R3,R4,R5,R6 | B67: RBLDLEDM | C67: Residential Building Low Eff | D67: Mt, Mt/a | E67: RBLDLEDMY | F67: POPDMRES | G67: 2010 | H67: 55 | I67: 0 | J67: 1 | L67: 1 | M67: 1 | N67: 1 | O67: 1 | P67: 1 | Q67: 0 | R67: 0.01
A68: R2,R3,R4,R5,R6 | B68: RBROOFDM | C68: Residential Sector Black Roof | D68: Mt, Mt/a | E68: RBROOFDMY | F68: RWROOFDM | G68: 2010 | H68: 55 | I68: 0 | J68: 1 | L68: 1 | M68: 1 | N68: 1 | O68: 1 | P68: 1 | Q68: 0.1 | R68: 0.01
A69: R2,R3,R4,R5,R6 | B69: RWTROOFDM | C69: Residential Sector White Roof | D69: Mt, Mt/a | E69: RWTROOFDMY | F69: RWROOFDM | G69: 2010 | H69: 55 | I69: 0 | J69: 1 | L69: 1 | M69: 1 | N69: 1 | O69: 1 | P69: 1 | Q69: 0.1 | R69: 0.01
A70: R2,R3,R4,R5,R6 | B70: RGROOF6DM | C70: Residential Sector Green Roof 6 Inch Depth | D70: Mt, Mt/a | E70: RGRF6DMY | F70: RWROOFDM | G70: 2010 | H70: 55 | I70: 0 | J70: 1 | L70: 1 | M70: 1 | N70: 1 | O70: 1 | P70: 1 | Q70: 0.15 | R70: 0.01
A71: R2,R3,R4,R5,R6 | B71: RGROOF12DM | C71: Residential Sector Green Roof 12 Inch Depth | D71: Mt, Mt/a | E71: RGRF12DMY | F71: RWROOFDM | G71: 2010 | H71: 55 | I71: 0 | J71: 1 | L71: 1 | M71: 1 | N71: 1 | O71: 1 | P71: 1 | Q71: 0.2 | R71: 0.01
A72: * Green Infrastructure Heating & Cooling Technologies
A79: *Space Heating
A80: *Electric Radiant Heating
A81: * | B81: RSHERDBS05 | C81: Electric Radiant Base.RSH.ELC.05 | D81: PJ | E81: RESELC | F81: =Commodities!$D$11 -> RSH | G81: 2010 | H81: 20 | J81: 1 | K81: 1 | L81: 0.16 | M81: 0.16 | N81: 0.16 | O81: 0.16 | P81: 0.16 | R81: 0.18 | AI81: 0 | AJ81: 0 | AK81: 0 | AL81: 0 | AM81: 0 | AN81: 0 | AO81: 0 | AP81: 0 | AQ81: 0 | AR81: 0
A82: *Electric Resistance Furnaces
A83: * | B83: RSHEFRV120 | C83: Electric Resistance Furnace Ver1.RSH.ELC.20 | D83: PJ | E83: RESELC | F83: =Commodities!$D$11 -> RSH | G83: 2020 | H83: 15 | I83: 2.775407 | J83: 0.98 | K83: 1 | L83: 0.16 | M83: 0.16 | N83: 0.16 | O83: 0.16 | P83: 0.16 | R83: 0.18
A84: * | B84: RSHEFRV130 | C84: Electric Resistance Furnace Ver1.RSH.ELC.30 | D84: PJ | E84: RESELC | F84: =Commodities!$D$11 -> RSH | G84: 2030 | H84: 15 | I84: 2.775407 | J84: 0.98 | K84: 1 | L84: 0.16 | M84: 0.16 | N84: 0.16 | O84: 0.16 | P84: 0.16 | R84: 0.18
A85: * | B85: RSHEFRV230 | C85: Electric Resistance Furnace Ver2.RSH.ELC.30 | D85: PJ | E85: RESELC | F85: =Commodities!$D$11 -> RSH | G85: 2030 | H85: 30 | I85: 3.2831034 | J85: 0.98 | K85: 1 | L85: 0.16 | M85: 0.16 | N85: 0.16 | O85: 0.16 | P85: 0.16 | R85: 0.18
A86: * | B86: RSHEFRV140 | C86: Electric Resistance Furnace Ver1.RSH.ELC.40 | D86: PJ | E86: RESELC | F86: =Commodities!$D$11 -> RSH | G86: 2040 | H86: 15 | I86: 2.775407 | J86: 0.98 | K86: 1 | L86: 0.16 | M86: 0.16 | N86: 0.16 | O86: 0.16 | P86: 0.16 | R86: 0.18
A87: * | B87: RSHEFRV240 | C87: Electric Resistance Furnace Ver2.RSH.ELC.40 | D87: PJ | E87: RESELC | F87: =Commodities!$D$11 -> RSH | G87: 2040 | H87: 30 | I87: 3.2831034 | J87: 0.98 | K87: 1 | L87: 0.16 | M87: 0.16 | N87: 0.16 | O87: 0.16 | P87: 0.16 | R87: 0.18
A88: * | B88: RSHEFRV250 | C88: Electric Resistance Furnace Ver2.RSH.ELC.50 | D88: PJ | E88: RESELC | F88: =Commodities!$D$11 -> RSH | G88: 2050 | H88: 30 | I88: 3.2831034 | J88: 0.98 | K88: 1 | L88: 0.16 | M88: 0.16 | N88: 0.16 | O88: 0.16 | P88: 0.16 | R88: 0.18
A89: * | B89: RSHEFRV220 | C89: Electric Resistance Furnace Ver2.RSH.ELC.20 | D89: PJ | E89: RESELC | F89: =Commodities!$D$11 -> RSH | G89: 2020 | H89: 30 | I89: 2.2343255 | J89: 0.98 | K89: 1 | L89: 0.16 | M89: 0.16 | N89: 0.16 | O89: 0.16 | P89: 0.16 | R89: 0.18
A90: * | B90: RSHEFRV130 | C90: Electric Resistance Furnace Ver1.RSH.ELC.30 | D90: PJ | E90: RESELC | F90: =Commodities!$D$11 -> RSH | G90: 2030 | H90: 15 | I90: 1.8619379 | J90: 0.98 | K90: 1 | L90: 0.16 | M90: 0.16 | N90: 0.16 | O90: 0.16 | P90: 0.16 | R90: 0.18
A91: * | B91: RSHEFRV230 | C91: Electric Resistance Furnace Ver2.RSH.ELC.30 | D91: PJ | E91: RESELC | F91: =Commodities!$D$11 -> RSH | G91: 2030 | H91: 30 | I91: 2.2343255 | J91: 0.98 | K91: 1 | L91: 0.16 | M91: 0.16 | N91: 0.16 | O91: 0.16 | P91: 0.16 | R91: 0.18
A92: * | B92: RSHEFRV140 | C92: Electric Resistance Furnace Ver1.RSH.ELC.40 | D92: PJ | E92: RESELC | F92: =Commodities!$D$11 -> RSH | G92: 2040 | H92: 15 | I92: 1.8619379 | J92: 0.98 | K92: 1 | L92: 0.16 | M92: 0.16 | N92: 0.16 | O92: 0.16 | P92: 0.16 | R92: 0.18
A93: * | B93: RSHEFRV240 | C93: Electric Resistance Furnace Ver2.RSH.ELC.40 | D93: PJ | E93: RESELC | F93: =Commodities!$D$11 -> RSH | G93: 2040 | H93: 30 | I93: 2.2343255 | J93: 0.98 | K93: 1 | L93: 0.16 | M93: 0.16 | N93: 0.16 | O93: 0.16 | P93: 0.16 | R93: 0.18
A94: * | B94: RSHEFRV150 | C94: Electric Resistance Furnace Ver1.RSH.ELC.50 | D94: PJ | E94: RESELC | F94: =Commodities!$D$11 -> RSH | G94: 2050 | H94: 15 | I94: 1.8619379 | J94: 0.98 | K94: 1 | L94: 0.16 | M94: 0.16 | N94: 0.16 | O94: 0.16 | P94: 0.16 | R94: 0.18
A95: * | B95: RSHEFRV250 | C95: Electric Resistance Furnace Ver2.RSH.ELC.50 | D95: PJ | E95: RESELC | F95: =Commodities!$D$11 -> RSH | G95: 2050 | H95: 30 | I95: 2.2343255 | J95: 0.98 | K95: 1 | L95: 0.16 | M95: 0.16 | N95: 0.16 | O95: 0.16 | P95: 0.16 | R95: 0.18
A96: *Electric Heat Pumps
A97: * | B97: RSHEHPBS05 | C97: Electric Heat Pump Base.RSH.ELC.05 | D97: PJ | E97: RESELC | F97: =Commodities!$D$11 -> RSH | G97: 2010 | H97: 15 | I97: 4.0729892 | J97: 2.2657 | K97: 1 | L97: 0.16 | M97: 0.16 | N97: 0.16 | O97: 0.16 | P97: 0.16 | R97: 0.18 | AK97: 0 | AL97: 0 | AM97: 0 | AN97: 0 | AO97: 0 | AP97: 0 | AQ97: 0 | AR97: 0
A98: * | B98: RSHEHPV115 | C98: Electric Heat Pump Ver1.RSH.ELC.15 | D98: PJ | E98: RESELC | F98: =Commodities!$D$11 -> RSH | G98: 2015 | H98: 15 | I98: 4.0729892 | J98: 2.26 | K98: 1 | L98: 0.16 | M98: 0.16 | N98: 0.16 | O98: 0.16 | P98: 0.16 | R98: 0.18 | AI98: 0
A99: * | B99: RSHEHPV215 | C99: Electric Heat Pump Ver2.RSH.ELC.15 | D99: PJ | E99: RESELC | F99: =Commodities!$D$11 -> RSH | G99: 2015 | H99: 15 | I99: 6.1935761 | J99: 2.7442857 | K99: 1 | L99: 0.16 | M99: 0.16 | N99: 0.16 | O99: 0.16 | P99: 0.16 | R99: 0.18
A100: * | B100: RSHEHPV320 | C100: Electric Heat Pump Ver3.RSH.ELC.20 | D100: PJ | E100: RESELC | F100: =Commodities!$D$11 -> RSH | G100: 2020 | H100: 9 | I100: 6.3763853 | J100: 2.7765714 | K100: 1 | L100: 0.16 | M100: 0.16 | N100: 0.16 | O100: 0.16 | P100: 0.16 | R100: 0.18
A101: * | B101: RSHEHPV520 | C101: Electric Heat Pump Ver5.RSH.ELC.20 | D101: PJ | E101: RESELC | F101: =Commodities!$D$11 -> RSH | G101: 2020 | H101: 9 | I101: 7.8022972 | J101: 2.9057143 | K101: 1 | L101: 0.16 | M101: 0.16 | N101: 0.16 | O101: 0.16 | P101: 0.16 | R101: 0.18
A102: * | B102: RSHEHPV430 | C102: Electric Heat Pump Ver4.RSH.ELC.30 | D102: PJ | E102: RESELC | F102: =Commodities!$D$11 -> RSH | G102: 2030 | H102: 22 | I102: 6.5628507 | J102: 2.8411429 | K102: 1 | L102: 0.16 | M102: 0.16 | N102: 0.16 | O102: 0.16 | P102: 0.16 | R102: 0.18
A103: * | B103: RSHEHPV630 | C103: Electric Heat Pump Ver6.RSH.ELC.30 | D103: PJ | E103: RESELC | F103: =Commodities!$D$11 -> RSH | G103: 2030 | H103: 22 | I103: 7.879077 | J103: 2.9057143 | K103: 1 | L103: 0.16 | M103: 0.16 | N103: 0.16 | O103: 0.16 | P103: 0.16 | R103: 0.18
A104: * | B104: RSHEHPV440 | C104: Electric Heat Pump Ver4.RSH.ELC.40 | D104: PJ | E104: RESELC | F104: =Commodities!$D$11 -> RSH | G104: 2040 | H104: 22 | I104: 6.5628507 | J104: 2.8411429 | K104: 1 | L104: 0.16 | M104: 0.16 | N104: 0.16 | O104: 0.16 | P104: 0.16 | R104: 0.18
A105: * | B105: RSHEHPV640 | C105: Electric Heat Pump Ver6.RSH.ELC.40 | D105: PJ | E105: RESELC | F105: =Commodities!$D$11 -> RSH | G105: 2040 | H105: 22 | I105: 7.8022972 | J105: 2.9057143 | K105: 1 | L105: 0.16 | M105: 0.16 | N105: 0.16 | O105: 0.16 | P105: 0.16 | R105: 0.18
A106: * | B106: RSHEHPV210 | C106: Electric Heat Pump Ver2.RSH.ELC.10 | D106: PJ | E106: RESELC | F106: =Commodities!$D$11 -> RSH | G106: 2010 | H106: 15 | I106: 8.8097833 | J106: 2.4 | K106: 1 | L106: 0.16 | M106: 0.16 | N106: 0.16 | O106: 0.16 | P106: 0.16 | R106: 0.18 | AI106: 0 | AJ106: 0 | AK106: 0 | AL106: 0 | AM106: 0 | AN106: 0 | AO106: 0 | AP106: 0 | AQ106: 0 | AR106: 0
A107: * | B107: RSHEHPV215 | C107: Electric Heat Pump Ver2.RSH.ELC.15 | D107: PJ | E107: RESELC | F107: =Commodities!$D$11 -> RSH | G107: 2015 | H107: 15 | I107: 9.3561264 | J107: 2.58 | K107: 1 | L107: 0.16 | M107: 0.16 | N107: 0.16 | O107: 0.16 | P107: 0.16 | R107: 0.18 | AI107: 0
A108: * | B108: RSHEHPV310 | C108: Electric Heat Pump Ver3.RSH.ELC.10 | D108: PJ | E108: RESELC | F108: =Commodities!$D$11 -> RSH | G108: 2010 | H108: 15 | I108: 9.7658838 | J108: 2.49 | K108: 1 | L108: 0.16 | M108: 0.16 | N108: 0.16 | O108: 0.16 | P108: 0.16 | R108: 0.18 | AI108: 0 | AJ108: 0 | AK108: 0 | AL108: 0 | AM108: 0 | AN108: 0 | AO108: 0 | AP108: 0 | AQ108: 0 | AR108: 0
A109: * | B109: RSHEHPV315 | C109: Electric Heat Pump Ver3.RSH.ELC.15 | D109: PJ | E109: RESELC | F109: =Commodities!$D$11 -> RSH | G109: 2015 | H109: 15 | I109: 9.7658838 | J109: 2.49 | K109: 1 | L109: 0.16 | M109: 0.16 | N109: 0.16 | O109: 0.16 | P109: 0.16 | R109: 0.18 | AI109: 0 | AL109: 0 | AM109: 0 | AN109: 0 | AO109: 0 | AP109: 0 | AQ109: 0 | AR109: 0
A110: * | B110: RSHEHPV320 | C110: Electric Heat Pump Ver3.RSH.ELC.20 | D110: PJ | E110: RESELC | F110: =Commodities!$D$11 -> RSH | G110: 2020 | H110: 15 | I110: 10.243934 | J110: 2.78 | K110: 1 | L110: 0.16 | M110: 0.16 | N110: 0.16 | O110: 0.16 | P110: 0.16 | R110: 0.18 | AI110: 0 | AM110: 0 | AN110: 0 | AO110: 0 | AP110: 0 | AQ110: 0 | AR110: 0
...

Sheet TechData_SolarPV
A1: TechData | B1: _GLOBAL,R0,R1,R2,R3,R4,R5,R6
F4: ~FI_T
A5: Region | B5: TechName | C5: *TechDesc | D5: *Units | E5: CommIN | F5: CommOUT | G5: NCAP_START | H5: NCAP_TLIFE | I5: PRC_CAPACT | J5: EFF | K5: Peak | L5: PRC_RESID~2010 | M5: NCAP_COST~2010 | N5: NCAP_COST~2015 | O5: NCAP_COST~2020 | P5: NCAP_COST~2025 | Q5: NCAP_COST~2030 | R5: NCAP_COST~2035 | S5: NCAP_COST~2040 | T5: NCAP_COST~2045 | U5: NCAP_COST~2050 | V5: NCAP_COST~2055 | W5: NCAP_FOM | X5: NCAP_AF~IDAM | Y5: NCAP_AF~IDPM | Z5: *NCAP_AF~IP | AA5: NCAP_AF~IP | AB5: NCAP_AF~IN | AC5: NCAP_AF~SDAM | AD5: NCAP_AF~SDPM | AE5: *NCAP_AF~SP | AF5: NCAP_AF~SP | AG5: NCAP_AF~SN | AH5: NCAP_AF~WDAM | AI5: NCAP_AF~WDPM | AJ5: *NCAP_AF~WP | AK5: NCAP_AF~WP | AL5: NCAP_AF~WN | AM5: NCAP_DRATE | AO5: Input | AP5: Output | AR5: ACT_BND~FX~2010 | AS5: ACT_BND~FX~2015 | AT5: ACT_BND~LO~2020 | AU5: ACT_BND~LO~2025 | AV5: ACT_BND~LO~2030 | AW5: ACT_BND~LO~2035 | AX5: ACT_BND~LO~2040 | AY5: ACT_BND~LO~2045 | AZ5: ACT_BND~LO~2050 | BA5: ACT_BND~LO~2055 | BB5: ACT_BND~UP~2020 | BC5: ACT_BND~UP~2025 | BD5: ACT_BND~UP~2030 | BE5: ACT_BND~UP~2035 | BF5: ACT_BND~UP~2040 | BG5: ACT_BND~UP~2045 | BH5: ACT_BND~UP~2050 | BI5: ACT_BND~UP~2055
A6: * Solar PV Technologies
A7: *R1 | B7: ESOLPVRES | C7: Solar PV Distributed Residential Generation | E7: SOLRES | F7: RESELC | G7: 2010 | H7: 30 | I7: 31.536 | J7: =AP7/AO7 -> 0.34965035 | K7: 0.1 | L7: 0 | M7: 6546.9995 | N7: 3903.1781 | O7: 3453.8021 | P7: 3004.4261 | Q7: 2839.3022 | R7: 2674.1784 | S7: 2596.418 | T7: 2558.6683 | U7: 2540.0679 | V7: 2530.8353 | W7: 10 | X7: 0 | Y7: 0.31357247 | Z7: 0.31357247 | AA7: =Z7*0.2 -> 0.062714494 | AB7: 0 | AC7: 0.3060734 | AD7: 0.3060734 | AE7: 0.3060734 | AF7: =AE7*0.2 -> 0.061214679 | AG7: 0 | AH7: 0.3020009 | AI7: 0.3020009 | AJ7: 0.3020009 | AK7: =AJ7*0.2 -> 0.06040018 | AL7: 0 | AM7: 0.15 | AO7: 2.86 | AP7: 1
A8: R2 | B8: ESOLPVRES | C8: Solar PV Distributed Residential Generation | E8: SOLRES | F8: RESELC | G8: 2010 | H8: 30 | I8: 31.536 | J8: =AP8/AO8 -> 0.34965035 | K8: 0.1 | L8: 0.002 | M8: 6546.9995 | N8: 3903.1781 | O8: 3453.8021 | P8: 3004.4261 | Q8: 2839.3022 | R8: 2674.1784 | S8: 2596.418 | T8: 2558.6683 | U8: 2540.0679 | V8: 2530.8353 | W8: 10 | X8: 0 | Y8: 0.317351 | Z8: 0.317351 | AA8: =Z8*0.2 -> 0.0634702 | AB8: 0 | AC8: 0.30541737 | AD8: 0.30541737 | AE8: 0.30541737 | AF8: =AE8*0.2 -> 0.061083474 | AG8: 0 | AH8: 0.29271621 | AI8: 0.29271621 | AJ8: 0.29271621 | AK8: =AJ8*0.2 -> 0.058543242 | AL8: 0 | AM8: 0.15 | AO8: 2.86 | AP8: 1 | AR8: ='Rooftop Calc'!M70 -> 0.0071942858 | AS8: ='Rooftop Calc'!M76 -> 0.10932348 | AT8: ='Rooftop Calc'!M82 -> 0.2449548 | AU8: ='Rooftop Calc'!M89 -> 0.43038221 | AV8: ='Rooftop Calc'!M96 -> 0.61580962 | AW8: ='Rooftop Calc'!M103 -> 0.80123703 | AX8: ='Rooftop Calc'!M110 -> 0.98666444 | AY8: ='Rooftop Calc'!M117 -> 1.1648976 | AZ8: ='Rooftop Calc'!M124 -> 1.2410015 | BA8: ='Rooftop Calc'!M131 -> 1.3072234 | BB8: ='Rooftop Calc'!U82 -> 0.37638511 | BC8: ='Rooftop Calc'!U89 -> 0.64266587 | BD8: ='Rooftop Calc'!U96 -> 0.90972751 | BE8: ='Rooftop Calc'!U103 -> 1.1760083 | BF8: ='Rooftop Calc'!U110 -> 1.4430699 | BG8: ='Rooftop Calc'!U117 -> 1.7093507 | BH8: ='Rooftop Calc'!U124 -> 1.9764123 | BI8: ='Rooftop Calc'!U131 -> 2.242693
A9: R3 | B9: ESOLPVRES | C9: Solar PV Distributed Residential Generation | E9: SOLRES | F9: RESELC | G9: 2010 | H9: 30 | I9: 31.536 | J9: =AP9/AO9 -> 0.34965035 | K9: 0.1 | L9: 0.002 | M9: 6546.9995 | N9: 3903.1781 | O9: 3453.8021 | P9: 3004.4261 | Q9: 2839.3022 | R9: 2674.1784 | S9: 2596.418 | T9: 2558.6683 | U9: 2540.0679 | V9: 2530.8353 | W9: 10 | X9: 0 | Y9: 0.29713464 | Z9: 0.29713464 | AA9: =Z9*0.2 -> 0.059426928 | AB9: 0 | AC9: 0.30672516 | AD9: 0.30672516 | AE9: 0.30672516 | AF9: =AE9*0.2 -> 0.061345033 | AG9: 0 | AH9: 0.26137287 | AI9: 0.26137287 | AJ9: 0.26137287 | AK9: =AJ9*0.2 -> 0.052274574 | AL9: 0 | AM9: 0.15 | AO9: 2.86 | AP9: 1 | AR9: ='Rooftop Calc'!N70 -> 0.0037521802 | AS9: ='Rooftop Calc'!N76 -> 0.073445454 | AT9: ='Rooftop Calc'!N82 -> 0.13819492 | AU9: ='Rooftop Calc'!N89 -> 0.20768262 | AV9: ='Rooftop Calc'!N96 -> 0.27717031 | AW9: ='Rooftop Calc'!N103 -> 0.34665801 | AX9: ='Rooftop Calc'!N110 -> 0.4161457 | AY9: ='Rooftop Calc'!N117 -> 0.48188122 | AZ9: ='Rooftop Calc'!N124 -> 0.47792346 | BA9: ='Rooftop Calc'!N131 -> 0.46631308 | BB9: ='Rooftop Calc'!V82 -> 0.25286221 | BC9: ='Rooftop Calc'!V89 -> 0.43175435 | BD9: ='Rooftop Calc'!V96 -> 0.6111711 | BE9: ='Rooftop Calc'!V103 -> 0.79006324 | BF9: ='Rooftop Calc'!V110 -> 0.96947999 | BG9: ='Rooftop Calc'!V117 -> 1.1483721 | BH9: ='Rooftop Calc'!V124 -> 1.3277889 | BI9: ='Rooftop Calc'!V131 -> 1.506681
A10: R4 | B10: ESOLPVRES | C10: Solar PV Distributed Residential Generation | E10: SOLRES | F10: RESELC | G10: 2010 | H10: 30 | I10: 31.536 | J10: =AP10/AO10 -> 0.34965035 | K10: 0.1 | L10: 0.0004 | M10: 6546.9995 | N10: 3903.1781 | O10: 3453.8021 | P10: 3004.4261 | Q10: 2839.3022 | R10: 2674.1784 | S10: 2596.418 | T10: 2558.6683 | U10: 2540.0679 | V10: 2530.8353 | W10: 10 | X10: 0 | Y10: 0.33039362 | Z10: 0.33039362 | AA10: =Z10*0.2 -> 0.066078724 | AB10: 0 | AC10: 0.32440092 | AD10: 0.32440092 | AE10: 0.32440092 | AF10: =AE10*0.2 -> 0.064880183 | AG10: 0 | AH10: 0.34679382 | AI10: 0.34679382 | AJ10: 0.34679382 | AK10: =AJ10*0.2 -> 0.069358764 | AL10: 0 | AM10: 0.15 | AO10: 2.86 | AP10: 1 | AR10: ='Rooftop Calc'!O70 -> 0.0011971758 | AS10: ='Rooftop Calc'!O76 -> 0.0093113675 | AT10: ='Rooftop Calc'!O82 -> 0.017876875 | AU10: ='Rooftop Calc'!O89 -> 0.024528127 | AV10: ='Rooftop Calc'!O96 -> 0.03117938 | AW10: ='Rooftop Calc'!O103 -> 0.037830632 | AX10: ='Rooftop Calc'!O110 -> 0.044481884 | AY10: ='Rooftop Calc'!O117 -> 0.04993596 | AZ10: ='Rooftop Calc'!O124 -> 0.047275844 | BA10: ='Rooftop Calc'!O131 -> 0.042167344 | BB10: ='Rooftop Calc'!W82 -> 0.032057708 | BC10: ='Rooftop Calc'!W89 -> 0.054737539 | BD10: ='Rooftop Calc'!W96 -> 0.07748388 | BE10: ='Rooftop Calc'!W103 -> 0.10016371 | BF10: ='Rooftop Calc'!W110 -> 0.12291005 | BG10: ='Rooftop Calc'!W117 -> 0.14558988 | BH10: ='Rooftop Calc'!W124 -> 0.16833622 | BI10: ='Rooftop Calc'!W131 -> 0.19101605
A11: R5 | B11: ESOLPVRES | C11: Solar PV Distributed Residential Generation | E11: SOLRES | F11: RESELC | G11: 2010 | H11: 30 | I11: 31.536 | J11: =AP11/AO11 -> 0.34965035 | K11: 0.1 | L11: 0.0006 | M11: 6546.9995 | N11: 3903.1781 | O11: 3453.8021 | P11: 3004.4261 | Q11: 2839.3022 | R11: 2674.1784 | S11: 2596.418 | T11: 2558.6683 | U11: 2540.0679 | V11: 2530.8353 | W11: 10 | X11: 0 | Y11: 0.34379748 | Z11: 0.34379748 | AA11: =Z11*0.2 -> 0.068759495 | AB11: 0 | AC11: 0.29466039 | AD11: 0.29466039 | AE11: 0.29466039 | AF11: =AE11*0.2 -> 0.058932078 | AG11: 0 | AH11: 0.36077416 | AI11: 0.36077416 | AJ11: 0.36077416 | AK11: =AJ11*0.2 -> 0.072154833 | AL11: 0 | AM11: 0.15 | AO11: 2.86 | AP11: 1 | AR11: ='Rooftop Calc'!P70 -> 0.0017437235 | AS11: ='Rooftop Calc'!P76 -> 0.32033226 | AT11: ='Rooftop Calc'!P82 -> 0.57040473 | AU11: ='Rooftop Calc'!P89 -> 1.0832858 | AV11: ='Rooftop Calc'!P96 -> 1.5961669 | AW11: ='Rooftop Calc'!P103 -> 2.1090479 | AX11: ='Rooftop Calc'!P110 -> 2.621929 | AY11: ='Rooftop Calc'!P117 -> 3.1330663 | AZ11: ='Rooftop Calc'!P124 -> 3.3256151 | BA11: ='Rooftop Calc'!P131 -> 3.7957364 | BB11: ='Rooftop Calc'!X82 -> 1.1028582 | BC11: ='Rooftop Calc'!X89 -> 1.8830961 | BD11: ='Rooftop Calc'!X96 -> 2.665622 | BE11: ='Rooftop Calc'!X103 -> 3.4458599 | BF11: ='Rooftop Calc'!X110 -> 4.2283858 | BG11: ='Rooftop Calc'!X117 -> 5.0086237 | BH11: ='Rooftop Calc'!X124 -> 5.7911496 | BI11: ='Rooftop Calc'!X131 -> 6.5713875
A12: R6 | B12: ESOLPVRES | C12: Solar PV Distributed Residential Generation | E12: SOLRES | F12: RESELC | G12: 2010 | H12: 30 | I12: 31.536 | J12: =AP12/AO12 -> 0.34965035 | K12: 0.1 | L12: 0.004 | M12: 6546.9995 | N12: 3903.1781 | O12: 3453.8021 | P12: 3004.4261 | Q12: 2839.3022 | R12: 2674.1784 | S12: 2596.418 | T12: 2558.6683 | U12: 2540.0679 | V12: 2530.8353 | W12: 10 | X12: 0 | Y12: 0.34054374 | Z12: 0.34054374 | AA12: =Z12*0.2 -> 0.068108748 | AB12: 0 | AC12: 0.30737101 | AD12: 0.30737101 | AE12: 0.30737101 | AF12: =AE12*0.2 -> 0.061474202 | AG12: 0 | AH12: 0.32128124 | AI12: 0.32128124 | AJ12: 0.32128124 | AK12: =AJ12*0.2 -> 0.064256247 | AL12: 0 | AM12: 0.15 | AO12: 2.86 | AP12: 1 | AR12: ='Rooftop Calc'!Q70 -> 0.012992495 | AS12: ='Rooftop Calc'!Q76 -> 0.17522773 | AT12: ='Rooftop Calc'!Q82 -> 0.47192793 | AU12: ='Rooftop Calc'!Q89 -> 0.89933033 | AV12: ='Rooftop Calc'!Q96 -> 1.3267327 | AW12: ='Rooftop Calc'!Q103 -> 1.7541351 | AX12: ='Rooftop Calc'!Q110 -> 2.1815375 | AY12: ='Rooftop Calc'!Q117 -> 2.5959474 | AZ12: ='Rooftop Calc'!Q124 -> 2.8481221 | BA12: ='Rooftop Calc'!Q131 -> 3.1386879 | BB12: ='Rooftop Calc'!Y82 -> 0.60328405 | BC12: ='Rooftop Calc'!Y89 -> 1.0300887 | BD12: ='Rooftop Calc'!Y96 -> 1.4581451 | BE12: ='Rooftop Calc'!Y103 -> 1.8849497 | BF12: ='Rooftop Calc'!Y110 -> 2.3130061 | BG12: ='Rooftop Calc'!Y117 -> 2.7398108 | BH12: ='Rooftop Calc'!Y124 -> 3.1678671 | BI12: ='Rooftop Calc'!Y131 -> 3.5946718
A13: * | AR13: =SUM(AR8:AR12) -> 0.026879861 | AS13: =SUM(AS8:AS12) -> 0.68764029 | AT13: =SUM(AT8:AT12) -> 1.4433592 | AU13: =SUM(AU8:AU12) -> 2.6452091 | AV13: =SUM(AV8:AV12) -> 3.8470589 | AW13: =SUM(AW8:AW12) -> 5.0489087 | AX13: =SUM(AX8:AX12) -> 6.2507585 | AY13: =SUM(AY8:AY12) -> 7.4257285 | ... BI13: =SUM(BI8:BI12) -> 14.106449
A14: *
G22: S

Sheet TechData_SESC
A1: TechData | B1: _GLOBAL,R0,R1,R2,R3,R4,R5,R6
F4: ~FI_T
A5: Region | B5: TechName | C5: *TechDesc | D5: *Units | E5: CommIN | F5: CommOUT | G5: NCAP_START | H5: NCAP_TLIFE | I5: EFF | J5: ACT_COST | K5: Share~UP | L5: Share~UP | M5: Peak | N5: NCAP_AF | O5: PRC_CAPACT | P5: NCAP_COST | V5: Input | W5: Output | X5: Input | Y5: Output
A6: * Collectors
A7: R2,R3,R4,R5,R6 | B7: SCRESELC | C7: Collector: ELC to RES | D7: PJ | E7: ELC | F7: RESELC | G7: 2010 | I7: =Y7/X7 -> 1 | J7: 48.826391 | M7: 1 | N7: 1 | O7: 1 | X7: 1 | Y7: 1
A15: * Building Retrofit Collectors
A16: R2,R3,R4,R5,R6 | B16: XELCRBLD | C16: Collects ELC for use in buildings | D16: PJ | E16: RESELC | F16: RESELCBLD | G16: 2010 | I16: =Y16/X16 -> 1 | M16: 1 | N16: 1 | O16: 1 | P16: 0 | X16: 1 | Y16: 1
A17: R2,R3,R4,R5,R6 | B17: XNGARBLD | C17: Collects NGA for use in buildings | D17: PJ | E17: RESNGAEA | F17: RESNGABLD | G17: 2010 | N17: 1 | O17: 1 | P17: 0 | V17: 1 | W17: 1
A18: *R2,R3,R4,R5,R6 | B18: XRFLRBLD | C18: Collects RFL for use in buildings | D18: PJ | E18: RESRFLEA | F18: RESRFLBLD | G18: 2010 | N18: 1 | O18: 1 | P18: 0 | V18: 1 | W18: 1
A19: R2,R3,R4,R5,R6 | B19: XDSLRBLD | C19: Collects DSL for use in buildings | D19: PJ | E19: RESDSLEA | F19: RESDSLBLD | G19: 2010 | N19: 1 | O19: 1 | P19: 0 | V19: 1 | W19: 1
A20: R2,R3,R4,R5,R6 | B20: RELCHE | C20: High efficiency building ELC without retrofits | D20: PJ | E20: RESELCBLD | F20: RESELCRB | G20: 2010 | I20: =Y20/X20 -> 1 | M20: 1 | N20: 1 | O20: 1 | P20: 0 | X20: 1 | Y20: 1
A21: R2,R3,R4,R5,R6 | B21: RBLDBAUHE | C21: High efficiency building energy without retrofits | D21: PJ | E21: RESNGABLD | G21: 2010 | I21: =SUM(W24,W25,W26)/SUM(V21,V22,V23) -> 1 | K21: =V21/SUM(V21,V22,V23) -> 0.33333333 | N21: 1 | O21: 1 | P21: 0 | V21: 1
E22: RESDSLBLD | K22: =V22/SUM(V21,V22,V23) -> 0.33333333 | V22: 1
A23: * | E23: RESRFLBLD | K23: =V23/SUM(V21,V22,V23) -> 0.33333333 | V23: 1
F24: RESNGARB | L24: =W24/SUM(W24,W25,W26) -> 0.33333333 | W24: 1
F25: RESDSLRB | L25: =W25/SUM(W24,W25,W26) -> 0.33333333 | W25: 1
A26: * | F26: RESRFLRB | L26: =W26/SUM(W24,W25,W26) -> 0.33333333 | W26: 1
A27: R2,R3,R4,R5,R6 | B27: RELCBAU | C27: Building ELC without retrofits | D27: PJ | E27: RESELCBLD | F27: RESELCRM | G27: 2010 | I27: =Y27/X27 -> 1 | M27: 1 | N27: 1 | O27: 1 | P27: 0 | X27: 1 | Y27: 1
A28: R2,R3,R4,R5,R6 | B28: RBLDBAU | C28: Building energy without retrofits | D28: PJ | E28: RESNGABLD | G28: 2010 | I28: =SUM(W31,W32,W33)/SUM(V28,V29,V30) -> 1 | K28: =V28/SUM(V28,V29,V30) -> 0.33333333 | N28: 1 | O28: 1 | P28: 0 | V28: 1
E29: RESDSLBLD | K29: =V29/SUM(V28,V29,V30) -> 0.33333333 | V29: 1
A30: * | E30: RESRFLBLD | K30: =V30/SUM(V28,V29,V30) -> 0.33333333 | V30: 1
F31: RESNGARM | L31: =W31/SUM(W31,W32,W33) -> 0.33333333 | W31: 1
F32: RESDSLRM | L32: =W32/SUM(W31,W32,W33) -> 0.33333333 | W32: 1
A33: * | F33: RESRFLRM | L33: =W33/SUM(W31,W32,W33) -> 0.33333333 | W33: 1
A34: R2,R3,R4,R5,R6 | B34: RELCR10 | C34: Building ELC retrofit for 10% energy reduction | D34: PJ | E34: RESELCBLD | F34: RESELCRB | G34: 2015 | I34: =Y34/X34 -> 1 | M34: 1 | N34: 1 | O34: 1 | P34: 0.25 | X34: 1 | Y34: 1
A35: R2,R3,R4,R5,R6 | B35: RBLDR10 | C35: Building retrofit for 10% energy reduction | D35: PJ | E35: RESNGABLD | G35: 2015 | I35: =SUM(W38,W39,W40)/SUM(V35,V36,V37) -> 1.1 | K35: =V35/SUM(V35,V36,V37) -> 0.33333333 | N35: 1 | O35: 1 | P35: 0.25 | V35: 1
E36: RESDSLBLD | K36: =V36/SUM(V35,V36,V37) -> 0.33333333 | V36: 1
A37: * | E37: RESRFLBLD | K37: =V37/SUM(V35,V36,V37) -> 0.33333333 | V37: 1
F38: RESNGARB | L38: =W38/SUM(W38,W39,W40) -> 0.33333333 | W38: 1.1
F39: RESDSLRB | L39: =W39/SUM(W38,W39,W40) -> 0.33333333 | W39: 1.1
A40: * | F40: RESRFLRB | L40: =W40/SUM(W38,W39,W40) -> 0.33333333 | W40: 1.1
A41: R2,R3,R4,R5,R6 | B41: RELCR25 | C41: Building ELC retrofit for 25% energy reduction | D41: PJ | E41: RESELCBLD | F41: RESELCRM | G41: 2020 | I41: =Y41/X41 -> 1 | M41: 1 | N41: 1 | O41: 1 | P41: 0.5 | X41: 1 | Y41: 1
A42: R2,R3,R4,R5,R6 | B42: RBLDR25 | C42: Building retrofit for 25% energy reduction | D42: PJ | E42: RESNGABLD | G42: 2020 | I42: =SUM(W45,W46,W47)/SUM(V42,V43,V44) -> 1.25 | K42: =V42/SUM(V42,V43,V44) -> 0.33333333 | N42: 1 | O42: 1 | P42: 0.5 | V42: 1
E43: RESDSLBLD | K43: =V43/SUM(V42,V43,V44) -> 0.33333333 | V43: 1
A44: * | E44: RESRFLBLD | K44: =V44/SUM(V42,V43,V44) -> 0.33333333 | V44: 1
F45: RESNGARM | L45: =W45/SUM(W45,W46,W47) -> 0.33333333 | W45: 1.25
F46: RESDSLRM | L46: =W46/SUM(W45,W46,W47) -> 0.33333333 | W46: 1.25
A47: * | F47: RESRFLRM | L47: =W47/SUM(W45,W46,W47) -> 0.33333333 | W47: 1.25
A48: R2,R3,R4,R5,R6 | B48: RELCR50 | C48: Building ELC retrofit for 50% energy reduction | D48: PJ | E48: RESELCBLD | F48: RESELCRM | G48: 2025 | I48: =Y48/X48 -> 1 | M48: 1 | N48: 1 | O48: 1 | P48: 1 | X48: 1 | Y48: 1
A49: R2,R3,R4,R5,R6 | B49: RBLDR50 | C49: Building retrofit for 50% energy reduction | D49: PJ | E49: RESNGABLD | G49: 2025 | I49: =SUM(W52,W53,W54)/SUM(V49,V50,V51) -> 1.5 | K49: =V49/SUM(V49,V50,V51) -> 0.33333333 | N49: 1 | O49: 1 | P49: 1 | V49: 1
E50: RESDSLBLD | K50: =V50/SUM(V49,V50,V51) -> 0.33333333 | V50: 1
A51: * | E51: RESRFLBLD | K51: =V51/SUM(V49,V50,V51) -> 0.33333333 | V51: 1
F52: RESNGARM | L52: =W52/SUM(W52,W53,W54) -> 0.33333333 | W52: 1.5
F53: RESDSLRM | L53: =W53/SUM(W52,W53,W54) -> 0.33333333 | W53: 1.5
A54: * | F54: RESRFLRM | L54: =W54/SUM(W52,W53,W54) -> 0.33333333 | W54: 1.5

Sheet TechData-Emis
A1: TechData | B1: _GLOBAL,R0,R1,R2,R3,R4,R5,R6
F4: ~FI_T
A5: Region | B5: TechName | C5: *TechDesc | D5: *Units | E5: CommIN | F5: CommOUT | G5: NCAP_START | H5: NCAP_TLIFE | I5: EFF | J5: ENV_ACT~CO2~2010 | K5: ENV_ACT~CO2~2055 | L5: ENV_ACT~NOX~2010 | M5: ENV_ACT~NOX~2055 | N5: ENV_ACT~PM10~2010 | O5: ENV_ACT~PM10~2055 | P5: ENV_ACT~PM25~2010 | Q5: ENV_ACT~PM25~2055 | R5: ENV_ACT~VOC~2010 | S5: ENV_ACT~VOC~2055 | T5: ENV_ACT~CO~2010 | U5: ENV_ACT~CO~2055 | V5: ENV_ACT~CH4~2010 | W5: ENV_ACT~CH4~2055 | X5: ENV_ACT~N2O~2010 | Y5: ENV_ACT~N2O~2055 | Z5: ENV_ACT~BC~2010 | AA5: ENV_ACT~BC~2055 | AB5: ENV_ACT~OC~2010 | AC5: ENV_ACT~OC~2055 | AD5: ENV_ACT~SO2~2010 | AE5: ENV_ACT~SO2~2055 | AF5: ENV_ACT~CO2R | AG5: ENV_ACT~NOXR | AH5: ENV_ACT~PM10R | AI5: ENV_ACT~SO2R | AJ5: ENV_ACT~NOX2CR
A6: * Residential
A7: * | B7: SERESCOA | C7: Emissions: COA to RES | D7: PJ | E7: RESCOA | F7: RESCOAEA | G7: 2010 | H7: 55 | I7: 1 | J7: =EmisRes!D18 -> 0.10059959 | K7: =J7 -> 0.10059959
A8: R2,R3,R4,R5,R6 | B8: SERESNGA | C8: Emissions: NGA to RES | D8: PJ | E8: RESNGA | F8: RESNGAEA | G8: 2010 | H8: 55 | I8: 1 | J8: =EmisRes!D9 -> 0.077177346 | K8: =J8 -> 0.077177346 | L8: =EmisRes!I28 -> 0.039275865 | M8: =L8 -> 0.039275865 | N8: =EmisRes!J28 -> 0.00021727074 | O8: =N8 -> 0.00021727074 | P8: =EmisRes!K28 -> 0.00017966619 | Q8: =P8 -> 0.00017966619 | R8: =EmisRes!L28 -> 0.0022980559 | S8: =R8 -> 0.0022980559 | T8: =EmisRes!M28 -> 0.016713134 | U8: =T8 -> 0.016713134 | V8: =EmisRes!N28 -> 0.0047390856 | W8: =V8 -> 0.0047390856 | X8: =EmisRes!O28 -> 9.4781712e-05 | Y8: =X8 -> 9.4781712e-05 | Z8: =P8*EmisRes!K177 -> 1.0779971e-05 | AA8: =Z8 -> 1.0779971e-05 | AB8: =R8*EmisRes!K101 -> 0.001149028 | AC8: =AB8 -> 0.001149028 | AD8: =EmisRes!H28 -> 0.00025069701 | AE8: =AD8 -> 0.00025069701 | AF8: =J8*1000 -> 77.177346 | AG8: =L8 -> 0.039275865 | AH8: =N8 -> 0.00021727074 | AI8: =AD8 -> 0.00025069701 | AJ8: =AG8 -> 0.039275865
A9: * | B9: SERESBIO | C9: Emissions: BIO to RES | D9: PJ | E9: RESBIO | F9: RESBIOEA | G9: 2010 | H9: 55 | I9: 1 | L9: =EmisRes!I27 -> 0.12680826 | M9: =L9 -> 0.12680826 | N9: =EmisRes!J27 -> 0.70373709 | O9: =N9 -> 0.70373709 | P9: =EmisRes!K27 -> 0.6052139 | Q9: =P9 -> 0.6052139 | R9: =EmisRes!L27 -> 1.1519338 | S9: =R9 -> 1.1519338 | T9: =EmisRes!M27 -> 5.1881544 | U9: =T9 -> 5.1881544 | V9: =EmisRes!N27 -> 0.1872974 | W9: =V9 -> 0.1872974 | X9: =EmisRes!O27 -> 0.0039808319 | Y9: =X9 -> 0.0039808319 | Z9: =P9*EmisRes!N243 -> 0.045693649 | AA9: =Z9 -> 0.045693649 | AB9: =R9*EmisRes!K65 -> 0.23038676 | AC9: =AB9 -> 0.23038676 | AD9: =EmisRes!H27 -> 0.010748065 | AE9: =AD9 -> 0.010748065 | AF9: =J9*1000 -> 0 | AG9: =L9 -> 0.12680826 | AH9: =N9 -> 0.70373709 | AI9: =AD9 -> 0.010748065 | AJ9: =AG9 -> 0.12680826
A10: R2,R3,R4,R5,R6 | B10: SERESDSL | C10: Emissions: DSL to RES | D10: PJ | E10: RESDSL | F10: RESDSLEA | G10: 2010 | H10: 55 | I10: 1 | J10: =EmisRes!D9 -> 0.077177346 | K10: =J10 -> 0.077177346 | L10: =EmisRes!I29 -> 0.055800636 | M10: =L10 -> 0.055800636 | N10: =EmisRes!J29 -> 0.0073780841 | O10: =N10 -> 0.0073780841 | P10: =EmisRes!K29 -> 0.0066030752 | Q10: =P10 -> 0.0066030752 | R10: =EmisRes!L29 -> 0.0021700247 | S10: =R10 -> 0.0021700247 | T10: =EmisRes!M29 -> 0.015500177 | U10: =T10 -> 0.015500177 | V10: =EmisRes!N29 -> 0.0055180629 | W10: =V10 -> 0.0055180629 | X10: =EmisRes!O29 -> 0.00056869027 | Y10: =X10 -> 0.00056869027 | Z10: =P10*EmisRes!K133 -> 0.0019809226 | AA10: =Z10 -> 0.0019809226 | AB10: =R10*EmisRes!K57 -> 0.00019530223 | AC10: =AB10 -> 0.00019530223 | AD10: =EmisRes!H29 -> 0.1320615 | AE10: =AD10 -> 0.1320615 | AF10: =J10*1000 -> 77.177346 | AG10: =L10 -> 0.055800636 | AH10: =N10 -> 0.0073780841 | AI10: =AD10 -> 0.1320615 | AJ10: =AG10 -> 0.055800636
A11: * | B11: SERESKER | C11: Emissions: KER to RES | D11: PJ | E11: RESKER | F11: RESKEREA | G11: 2010 | H11: 55 | I11: 1 | J11: =EmisRes!D11 -> 0.076291099 | K11: =J11 -> 0.076291099 | L11: =EmisRes!I31 -> 0.05732605 | M11: =L11 -> 0.05732605 | N11: =EmisRes!J45 -> 0.0072612997 | O11: =N11 -> 0.0072612997 | P11: =EmisRes!K45 -> 0.0065288001 | Q11: =P11 -> 0.0065288001 | R11: =EmisRes!L45 -> 0.0021401725 | S11: =R11 -> 0.0021401725 | T11: =EmisRes!M45 -> 0.015923903 | U11: =T11 -> 0.015923903 | V11: =EmisRes!N45 -> 0.0056689094 | W11: =V11 -> 0.0056689094 | X11: =EmisRes!O45 -> 0.00056869027 | Y11: =X11 -> 0.00056869027 | Z11: =P11*EmisRes!K178 -> 0.00052230401 | AA11: =Z11 -> 0.00052230401 | AB11: =R11*EmisRes!K99 -> 0.00021401725 | AC11: =AB11 -> 0.00021401725 | AD11: =EmisRes!H45 -> 0.13567165 | AE11: =AD11 -> 0.13567165 | AF11: =J11*1000 -> 76.291099 | AG11: =L11 -> 0.05732605 | AH11: =N11 -> 0.0072612997 | AI11: =AD11 -> 0.13567165 | AJ11: =AG11 -> 0.05732605
A12: * | B12: SERESLPG | C12: Emissions: LPG to RES | D12: PJ | E12: RESLPG | F12: RESLPGEA | G12: 2010 | H12: 55 | I12: 1 | J12: =EmisRes!D12 -> 0.065708888 | K12: =J12 -> 0.065708888 | L12: =EmisRes!I30 -> 0.062863259 | M12: =L12 -> 0.062863259 | N12: =EmisRes!J44 -> 0.0002345644 | O12: =N12 -> 0.0002345644 | P12: =EmisRes!K44 -> 0.00018765152 | Q12: =P12 -> 0.00018765152 | R12: =EmisRes!L44 -> 0.0024394698 | S12: =R12 -> 0.0024394698 | T12: =EmisRes!M44 -> 0.017826894 | U12: =T12 -> 0.017826894 | V12: =EmisRes!N44 -> 0.010425988 | W12: =V12 -> 0.010425988 | X12: =EmisRes!O44 -> 0.00056869027 | Y12: =X12 -> 0.00056869027 | Z12: =P12*EmisRes!K176 -> 2.4394698e-05 | AA12: =Z12 -> 2.4394698e-05 | AB12: =R12*EmisRes!K100 -> 0.00024394698 | AC12: =AB12 -> 0.00024394698 | AD12: =EmisRes!H44 -> 0.00028147728 | AE12: =AD12 -> 0.00028147728 | AF12: =J12*1000 -> 65.708888 | AG12: =L12 -> 0.062863259 | AH12: =N12 -> 0.0002345644 | AI12: =AD12 -> 0.00028147728 | AJ12: =AG12 -> 0.062863259

Sheet TechData_CHP
A1: TechData | B1: R2,R3,R4,R5,R6 | R1: R2 | S1: R3 | T1: R4 | U1: R5 | V1: R6 | W1: R2 | X1: R3 | Y1: R4 | Z1: R5 | AA1: R6 | AB1: R2 | AC1: R3 | AD1: R4 | AE1: R5 | AF1: R6 | AG1: R2 | AH1: R3 | AI1: R4 | AJ1: R5 | AK1: R6 | AL1: R2 | AM1: R3 | AN1: R4 | AO1: R5 | AP1: R6 | AQ1: R2 | AR1: R3 | AS1: R4 | AT1: R5 | AU1: R6 | AV1: R2 | AW1: R3 | AX1: R4 | AY1: R5 | AZ1: R6 | BA1: R2 | BB1: R3 | BC1: R4 | BD1: R5 | BE1: R6 | BL1: R2 | BM1: R3 | BN1: R4 | BO1: R5 | BP1: R6
F4: ~FI_T
A5: Region | B5: TechName | C5: *TechDesc | D5: *Units | E5: CommIN | F5: CommOUT | G5: NCAP_START | H5: NCAP_TLIFE | I5: PRC_CAPACT | J5: NCAP_DRATE | K5: EFF | L5: Share~UP | M5: NCAP_COST~2010 | N5: NCAP_COST~2055 | O5: NCAP_FOM | P5: ACT_COST | Q5: NCAP_AF | R5: PRC_RESID~R2~2010 | S5: PRC_RESID~R3~2010 | T5: PRC_RESID~R4~2010 | U5: PRC_RESID~R5~2010 | V5: PRC_RESID~R6~2010 | W5: PRC_RESID~R2~2015 | X5: PRC_RESID~R3~2015 | Y5: PRC_RESID~R4~2015 | Z5: PRC_RESID~R5~2015 | AA5: PRC_RESID~R6~2015 | AB5: PRC_RESID~R2~2020 | AC5: PRC_RESID~R3~2020 | AD5: PRC_RESID~R4~2020 | AE5: PRC_RESID~R5~2020 | AF5: PRC_RESID~R6~2020 | AG5: PRC_RESID~R2~2025 | AH5: PRC_RESID~R3~2025 | AI5: PRC_RESID~R4~2025 | AJ5: PRC_RESID~R5~2025 | AK5: PRC_RESID~R6~2025 | AL5: PRC_RESID~R2~2030 | AM5: PRC_RESID~R3~2030 | AN5: PRC_RESID~R4~2030 | AO5: PRC_RESID~R5~2030 | AP5: PRC_RESID~R6~2030 | AQ5: PRC_RESID~R2~2035 | AR5: PRC_RESID~R3~2035 | AS5: PRC_RESID~R4~2035 | AT5: PRC_RESID~R5~2035 | AU5: PRC_RESID~R6~2035 | AV5: PRC_RESID~R2~2040 | AW5: PRC_RESID~R3~2040 | AX5: PRC_RESID~R4~2040 | AY5: PRC_RESID~R5~2040 | AZ5: PRC_RESID~R6~2040 | BA5: PRC_RESID~R2~2055 | BB5: PRC_RESID~R3~2055 | BC5: PRC_RESID~R4~2055 | BD5: PRC_RESID~R5~2055 | BE5: PRC_RESID~R6~2055 | BG5: NCAP_BND~FX~2010 | BH5: NCAP_BND~FX~2020 | BI5: NCAP_BND~FX~2025 | BJ5: NCAP_BND~FX~2030 | BK5: NCAP_BND~FX~2055 | BL5: NCAP_BND~UP~R2~2015 | BM5: NCAP_BND~UP~R3~2015 | BN5: NCAP_BND~UP~R4~2015 | BO5: NCAP_BND~UP~R5~2015 | BP5: NCAP_BND~UP~R6~2015 | BQ5: NCAP_BND~UP~2020 | BR5: NCAP_BND~UP~2025 | BS5: NCAP_BND~UP~2030 | BT5: NCAP_BND~UP~2035 | BU5: NCAP_BND~UP~2040 | BV5: NCAP_BND~UP~2045 | BW5: NCAP_BND~UP~2050 | BX5: NCAP_BND~UP~2055 | BZ5: *GROWTH~2010 | CA5: *GROWTH~2055 | CB5: Input | CC5: Output
A6: * Existing Boilers | N6: =IF(M6="","",M6) | BA6: =IF(AV6="","",AV6) | BB6: =IF(AW6="","",AW6) | BC6: =IF(AX6="","",AX6) | BD6: =IF(AY6="","",AY6) | BE6: =IF(AZ6="","",AZ6) | BI6: =IF(BH6="","",BH6) | BK6: =IF(BJ6="","",BJ6) | CA6: =IF(BZ6="","",BZ6)
A7: R4 | B7: RESBLDBS05 | C7: RES.DSL.BOILER.DISTRICTHEAT.BS | D7: PJ, PJ/a | E7: =Commodities!D22 -> RESDSLEA | F7: =Commodities!D30 -> RESSTDB | G7: 2010 | H7: 25 | I7: 1 | J7: 0.18 | K7: =CC7/CB7 -> 0.77 | M7: 1.7907914 | N7: 1.7907914 | O7: 0.016496725 | Q7: 0.28 | BA7: =IF(AV7="","",AV7) | BB7: =IF(AW7="","",AW7) | BC7: =IF(AX7="","",AX7) | BD7: =IF(AY7="","",AY7) | BE7: =IF(AZ7="","",AZ7) | BG7: 0 | BH7: 0 | BI7: =IF(BH7="","",BH7) -> 0 | BJ7: 0 | BK7: =IF(BJ7="","",BJ7) -> 0 | BL7: 0 | BM7: 0 | BN7: 0 | BO7: 0 | BP7: 0 | BQ7: 0 | BR7: 0 | BS7: 0 | BT7: 0 | BU7: 0 | BV7: 0 | BW7: 0 | BX7: 0 | CA7: =IF(BZ7="","",BZ7) | CB7: 1.2987013 | CC7: 1
A8: R4 | B8: RESBLNG10 | C8: RES.NG.BOILER.DISTRICTHEAT.10 | D8: PJ, PJ/a | E8: =Commodities!D20 -> RESNGAEA | F8: =Commodities!D29 -> RESSTNB | G8: 2010 | H8: 25 | I8: 1 | J8: 0.18 | K8: =CC8/CB8 -> 0.73 | M8: 2.5215838 | N8: 2.5215838 | O8: 0.075777046 | Q8: 0.28 | BA8: =IF(AV8="","",AV8) | BB8: =IF(AW8="","",AW8) | BC8: =IF(AX8="","",AX8) | BD8: =IF(AY8="","",AY8) | BE8: =IF(AZ8="","",AZ8) | BH8: 0 | BI8: =IF(BH8="","",BH8) -> 0 | BJ8: 0 | BK8: =IF(BJ8="","",BJ8) -> 0 | BL8: 0 | BM8: 0 | BN8: 0 | BO8: 0 | BP8: 0 | CA8: =IF(BZ8="","",BZ8) | CB8: 1.369863 | CC8: 1

Sheet TechData_ZZ
A1: TechData | B1: _GLOBAL,R0,R1,R2,R3,R4,R5,R6
E4: ~FI_T
A5: Region | B5: TechName | C5: *TechDesc | D5: *Units | E5: CommIN | F5: CommOUT | G5: EFF | H5: ACT_COST
A6: * ZZ<dm>INFES Backstop Technologies
A7: =Technologies!B84 -> R2,R3,R4,R5,R6 | B7: =Technologies!D84 -> ZZRLT | C7: Residential Lighting - ZZINFES backstop | D7: PJ | E7: ZZDMY | F7: RLT | G7: 1 | H7: 9999
A8: *R2,R3,R4,R5,R6 | B8: ZZRFZ | C8: Residential Freezing - ZZINFES backstop | D8: PJ | E8: ZZDMY | F8: RFZ | G8: 1 | H8: 9999
A9: *R2,R3,R4,R5,R6 | B9: ZZRRF | C9: Residential Refrigeration - ZZINFES backstop | D9: PJ | E9: ZZDMY | F9: RRF | G9: 1 | H9: 9999
A10: =Technologies!B87 -> R2,R3,R4,R5,R6 | B10: =Technologies!D87 -> ZZRSC | C10: Residential Cooling - ZZINFES backstop | D10: PJ | E10: ZZDMY | F10: RSC | G10: 1 | H10: 9999
A11: =Technologies!B88 -> R2,R3,R4,R5,R6 | B11: =Technologies!D88 -> ZZRSH | C11: Residential Heating - ZZINFES backstop | D11: PJ | E11: ZZDMY | F11: RSH | G11: 1 | H11: 9999
A12: =Technologies!B89 -> R2,R3,R4,R5,R6 | B12: =Technologies!D89 -> ZZRWH | C12: Residential Water Heating - ZZINFES backstop | D12: PJ | E12: ZZDMY | F12: RWH | G12: 1 | H12: 9999
A13: *
A14: * Dummy and Backstop Water Technologies
A15: *
A16: R2,R3,R4,R5,R6 | B16: ZZDMYRBLD | C16: Dummy RES Building to meet POPDM | D16: Mt, Mt/a | E16: ZZDMYH2O | F16: POPDMRES | G16: 1 | H16: 999999
A17: R2,R3,R4,R5,R6 | B17: ZZDMYRRFDM | C17: Dummy technology to meet RWROOFDM | D17: Mt, Mt/a | E17: ZZDMYH2O | F17: RWROOFDM | G17: 1 | H17: 999999
A18: *

Sheet DmdCalc
B2: Residential Sector - AEO National Demands | D2: * (1) 2010 data is changed to the value provided by NYC gov. and increased by AEO projection | P2: Air-Conditioning Usage Indicators by Northeast Census Region, Middle Atlantic
B3: Demand, PJ/a or mu/a | D3: 2005 | E3: 2010 | F3: 2015 | G3: 2020 | H3: 2025 | I3: 2030 | J3: 2035 | K3: 2040 | L3: 2045 | M3: 2050 | N3: 2055 | Q3: 2005 | R3: 2010 | S3: 2015 | T3: 2020 | U3: 2025 | V3: 2030 | W3: 2035 | X3: 2040 | Y3: 2045 | Z3: 2050 | AA3: 2055
B4: Residential space heating | C4: RH | D4: =E4*D80/E80 -> 158.69174 | E4: =Resid!T5 -> 151.08046 | F4: =Resid!AI5 -> 150.59912 | G4: =Resid!AX5 -> 138.59306 | H4: =$E$4*H80/$E$80 -> 164.6166 | I4: =$E$4*I80/$E$80 -> 159.27352 | J4: =$E$4*J80/$E$80 -> 152.17908 | K4: =$E$4*K80/$E$80 -> 146.51968 | L4: =$E$4*L80/$E$80 -> 142.19176 | M4: =$E$4*M80/$E$80 -> 138.15959 | N4: =$E$4*N80/$E$80 -> 134.24177 | P4: Total | Q4: 15.1 | R4: 15.3 | S4: 15.4 | T4: 16.04 | U4: 16.04 | V4: 16.04 | W4: 16.04 | X4: 16.04 | Y4: 16.04 | Z4: 16.04 | AA4: 16.04
B5: Residential water heating | C5: RW | D5: =E5*1/((E82*E202)/(D82*D202)) -> 32.659724 | E5: =Resid!T98 -> 39.76921 | F5: =Resid!AI98 -> 40.881066 | G5: =Resid!AX98 -> 38.686094 | H5: =$E$5*1/((H82*H202)/($E$82*$E$202)) -> 42.359564 | I5: =$E$5*1/((I82*I202)/($E$82*$E$202)) -> 40.000021 | J5: =$E$5*1/((J82*J202)/($E$82*$E$202)) -> 39.440386 | K5: =$E$5*1/((K82*K202)/($E$82*$E$202)) -> 39.112146 | L5: =$E$5*1/((L82*L202)/($E$82*$E$202)) -> 38.514153 | M5: =$E$5*1/((M82*M202)/($E$82*$E$202)) -> 37.659291 | N5: =$E$5*1/((N82*N202)/($E$82*$E$202)) -> 36.824971 | P5: Do Not Have Cooling Equipment | Q5: 2.4 | R5: 1.7 | S5: 1.8 | T5: 1.51 | U5: 1.51 | V5: 1.51 | W5: 1.51 | X5: 1.51 | Y5: 1.51 | Z5: 1.51 | AA5: 1.51
B6: Residential refrigeration | C6: RR | D6: 3.8583481 | E6: 3.9036012 | F6: 4.1229886 | G6: 4.2954984 | H6: 4.5279075 | I6: 4.772867 | J6: 5.0060663 | K6: 5.2209979 | L6: 5.5544442 | M6: 5.8458402 | N6: 6.1640162 | P6: Proj % of Households with no AC | Q6: 0.1589404 | R6: 0.11111111 | S6: 0.11688312 | T6: 0.094139651 | U6: 0.094139651 | V6: 0.094139651 | W6: 0.094139651 | X6: 0.094139651 | Y6: 0.094139651 | Z6: 0.094139651 | AA6: 0.094139651
B7: Residential lighting | C7: RL | D7: =E7 -> 9.4799044 | E7: =Lighting!AA22 -> 9.4799044 | F7: =Lighting!AB22 -> 9.164463 | G7: =Lighting!AC22 -> 8.5061055 | H7: =$E$7*H45/$E$45 -> 2.981583 | I7: =$E$7*I45/$E$45 -> 3.0480813 | J7: =$E$7*J45/$E$45 -> 3.0380811 | K7: =$E$7*K45/$E$45 -> 3.0189965 | L7: =$E$7*L45/$E$45 -> 2.9163346 | M7: =$E$7*M45/$E$45 -> 2.9369164 | N7: =$E$7*N45/$E$45 -> 2.9576435
B8: Residential miscellaneous electric | C8: RME | D8: =E8*D53/E53 -> 27.240098 | E8: ='Fuel Share'!H45 -> 29.802786 | F8: ='Fuel Share'!R45 -> 28.811105 | G8: ='Fuel Share'!AB45 -> 26.741371 | H8: =$E$8*H53/$E$53 -> 33.351033 | I8: =$E$8*I53/$E$53 -> 35.331651 | J8: =$E$8*J53/$E$53 -> 37.007952 | K8: =$E$8*K53/$E$53 -> 39.189411 | L8: =$E$8*L53/$E$53 -> 41.99045 | M8: =$E$8*M53/$E$53 -> 45.497443 | N8: =$E$8*N53/$E$53 -> 49.348224 | P8: Source:
B9: Residential freezers | C9: RF | D9: =D172 -> 38.425449 | E9: =E172 -> 39.755409 | F9: =F172 -> 38.494755 | G9: =G172 -> 44.426056 | H9: =H172 -> 46.606503 | I9: =I172 -> 48.656849 | J9: =J172 -> 50.555218 | K9: =K172 -> 52.339035 | ... N9: =N172 -> 57.454142 | P9: https://usepa.sharepoint.com/sites/COMETSupport-EPAUNCAbt/Shared%20Documents/COMET-NYC/EGU/2021%20ConEd%20Steam%20Electric%20Production_a.xlsx
B10: Residential miscellaneous gas | C10: RMG | D10: =E10 -> 2.6917017 | E10: ='Fuel Share'!J45 -> 2.6917017 | F10: ='Fuel Share'!T45 -> 3.043493 | G10: ='Fuel Share'!AD45 -> 3.0766884 | H10: =$E$10*H62/$E$62 -> 3.6816573 | I10: =$E$10*I62/$E$62 -> 3.7844404 | J10: =$E$10*J62/$E$62 -> 3.8204347 | K10: =$E$10*K62/$E$62 -> 3.8739879 | L10: =$E$10*L62/$E$62 -> 3.9448439 | M10: =$E$10*M62/$E$62 -> 4.0044634 | N10: =$E$10*N62/$E$62 -> 4.0688641 | P10: Edison steam system | Q10: Mlb | R10: Share %
B11: Residential miscellaneous LPG | C11: RML | D11: =D73*quad_to_PJ -> 42.20224 | E11: =E73*quad_to_PJ -> 153.48005 | F11: =F73*quad_to_PJ -> 45.865394 | G11: =G73*quad_to_PJ -> 75.902839 | H11: =H73*quad_to_PJ -> 81.204495 | I11: =I73*quad_to_PJ -> 92.956764 | J11: =J73*quad_to_PJ -> 102.58415 | K11: =K73*quad_to_PJ -> 112.56181 | ... N11: =N73*quad_to_PJ -> 146.77695 | P11: Steam from Boiler | Q11: 17416000 | R11: =Q11/SUM($Q$11:$Q$13) -> 0.42942562
B12: Residential space cooling | C12: RC | D12: =E12*D81/E81 -> 23.99489 | E12: =Resid!T59 -> 26.737813 | F12: =Resid!AI59 -> 25.758992 | G12: =Resid!AX59 -> 23.852635 | H12: =$E$12*H81/$E$81 -> 28.363073 | I12: =$E$12*I81/$E$81 -> 31.100275 | J12: =$E$12*J81/$E$81 -> 33.521032 | K12: =$E$12*K81/$E$81 -> 36.714614 | L12: =$E$12*L81/$E$81 -> 40.249094 | M12: =$E$12*M81/$E$81 -> 44.559175 | N12: =$E$12*N81/$E$81 -> 49.330803 | P12: Steam from NG CHP | Q12: =23107000 -> 23107000 | R12: =Q12/SUM($Q$11:$Q$13) -> 0.56974838
B13: Total | D13: =SUM(D4,D5,D7,D8,D10,D12) -> 254.75806 | E13: =SUM(E4,E5,E7,E8,E10,E12) -> 259.56188 | F13: =SUM(F4,F5,F7,F8,F10,F12) -> 258.25824 | G13: =SUM(G4,G5,G7,G8,G10,G12) -> 239.45595 | H13: =SUM(H4,H5,H7,H8,H10,H12) -> 275.35351 | I13: =SUM(I4,I5,I7,I8,I10,I12) -> 272.53799 | J13: =SUM(J4,J5,J7,J8,J10,J12) -> 269.00697 | K13: =SUM(K4,K5,K7,K8,K10,K12) -> 268.42884 | ... N13: =SUM(N4,N5,N7,N8,N10,N12) -> 276.77227 | P13: Steam from OIL CHP | Q13: =33500 -> 33500 | R13: =Q13/SUM($Q$11:$Q$13) -> 0.00082600816
B16: Table 4. Residential Sector Key Indicators and Consumption, Reference case
B17: (quadrillion Btu, unless otherwise noted)
C18: units | D18: 2005 | E18: 2010 | F18: 2015 | G18: 2020 | H18: 2025 | I18: 2030 | J18: 2035 | K18: 2040 | L18: 2045 | M18: 2050 | N18: 2055
B19: Key Indicators
B20: Households (millions)
B21: Single-Family | C21: millions | D21: 79.653931 | E21: 82.848206 | F21: 80.548882 | G21: 84.750443 | H21: 89.519981 | I21: 93.970619 | J21: 98.154381 | K21: 102.12499 | L21: 106.01605 | M21: 109.74868 | N21: =M21*M21/L21 -> 113.61273
B22: Multifamily | C22: millions | D22: 24.493498 | E22: 25.778419 | F22: 28.870884 | G22: 31.968704 | H22: 33.85815 | I22: 35.46513 | J22: 36.930111 | K22: 38.36647 | L22: 39.776779 | M22: 41.144089 | N22: =M22*M22/L22 -> 42.5584
B23: Mobile Homes | C23: millions | D23: 6.9431958 | E23: 6.600786 | F23: 5.965145 | G23: 6.663464 | H23: 6.660283 | I23: 6.717811 | J23: 6.744905 | K23: 6.750861 | L23: 6.763837 | M23: 6.767235 | N23: =M23*M23/L23 -> 6.7706347
B24: Total | C24: millions | D24: =SUM(D21:D23) -> 111.09062 | E24: =SUM(E21:E23) -> 115.22741 | F24: =SUM(F21:F23) -> 115.38491 | G24: =SUM(G21:G23) -> 123.38261 | H24: =SUM(H21:H23) -> 130.03841 | I24: =SUM(I21:I23) -> 136.15356 | J24: =SUM(J21:J23) -> 141.8294 | K24: =SUM(K21:K23) -> 147.24232 | ... N24: =SUM(N21:N23) -> 162.94176
B26: Average House Square Footage | C26: sq ft | D26: 1801.6599 | E26: 1652.6066 | F26: 1695.0878 | G26: 1789.3104 | H26: 1813.3185 | I26: 1836.3394 | J26: 1858.4113 | K26: 1878.9578 | L26: 1898.1798 | M26: 1916.3303 | N26: =M26*M26/L26 -> 1934.6544
B28: Energy Intensity
B29: (million Btu per household)
B30: Gross End-use Consumption | C30: MMBtu/household | E30: 99.153183 | F30: 95.092171 | G30: 92.738022 | H30: 89.052956 | I30: 86.372932 | J30: 83.229088 | K30: 81.360573 | L30: 80.389549 | M30: 80.285049 | N30: =M30*M30/L30 -> 80.180685
B31: Delivered Energy Consumption | C31: MMBtu/household | G31: 92.104782 | H31: 87.901169 | I31: 84.758438 | J31: 81.117577 | K31: 78.743118 | L31: 77.127983 | M31: 76.260414 | N31: =M31*M31/L31 -> 75.402604
B32: (thousand Btu per square foot)
B33: Gross End-use Consumption | C33: thousand Btu/sq ft | E33: 59.998058 | F33: 56.098671 | G33: 51.828918 | H33: 49.110489 | I33: 47.035389 | J33: 44.785076 | K33: 43.300903 | L33: 42.350861 | M33: 41.895203 | N33: =M33*M33/L33 -> 41.444447
B34: Delivered Energy Consumption | C34: thousand Btu/sq ft | G34: 51.475014 | H34: 48.475307 | I34: 46.156193 | J34: 43.648884 | K34: 41.907867 | L34: 40.632603 | M34: 39.795025 | N34: =M34*M34/L34 -> 38.974712
B36: Delivered Energy Consumption by Fuel
B37: Electricity
B38: Space Heating | D38: 0.31044063 | E38: 0.296832 | F38: 0.331095 | G38: 0.648975 | H38: 0.656949 | I38: 0.637851 | J38: 0.599838 | K38: 0.565611 | L38: 0.536676 | M38: 0.512384 | N38: =M38*M38/L38 -> 0.48919155
B39: Space Cooling | D39: 0.82135016 | E39: 0.915239 | F39: 0.794241 | G39: 0.805393 | H39: 0.91105 | I39: 1.004471 | J39: 1.088333 | K39: 1.196908 | L39: 1.3168 | M39: 1.463148 | N39: =M39*M39/L39 -> 1.625761
B40: Water Heating | D40: 0.38218424 | E40: 0.446141 | F40: 0.450959 | G40: 0.607549 | H40: 0.599582 | I40: 0.593223 | J40: 0.588552 | K40: 0.601795 | L40: 0.616835 | M40: 0.63608 | N40: =M40*M40/L40 -> 0.65592544
B41: Refrigeration | D41: 0.39436102 | E41: 0.376004 | F41: 0.355201 | G41: 0.297571 | H41: 0.29163 | I41: 0.289659 | J41: 0.294343 | K41: 0.306848 | L41: 0.324507 | M41: 0.340702 | N41: =M41*M41/L41 -> 0.35770524
B42: Cooking | D42: 0.10201725 | E42: 0.107607 | F42: 0.107912 | G42: 0.055007 | H42: 0.056875 | I42: 0.058391 | J42: 0.059404 | K42: 0.060895 | L42: 0.062203 | M42: 0.063319 | N42: =M42*M42/L42 -> 0.064455022
B43: Clothes Dryers | D43: 0.25261107 | E43: 0.195791 | F43: 0.204635 | G43: 0.216421 | H43: 0.237295 | I43: 0.259671 | J43: 0.275723 | K43: 0.292206 | L43: 0.309109 | M43: 0.328278 | N43: =M43*M43/L43 -> 0.34863574
B44: Freezers | D44: 0.083529256 | E44: 0.082217 | F44: 0.07543 | G44: 0.069181 | H44: 0.068516 | I44: 0.067615 | J44: 0.067169 | K44: 0.067431 | L44: 0.068666 | M44: 0.070729 | N44: =M44*M44/L44 -> 0.072853981
B45: Lighting | D45: 0.72674227 | E45: 0.652205 | F45: 0.448123 | G45: 0.211247 | H45: 0.205129 | I45: 0.209704 | J45: 0.209016 | K45: 0.207703 | L45: 0.20064 | M45: 0.202056 | N45: =M45*M45/L45 -> 0.20348199
B46: Clothes Washers¹ | D46: 0.034679808 | E46: 0.032793 | F46: 0.026497 | G46: 0.036779 | H46: 0.038486 | I46: 0.040246 | J46: 0.042099 | K46: 0.043898 | L46: 0.045619 | M46: 0.047258 | N46: =M46*M46/L46 -> 0.048955886
B47: Dishwashers¹ | D47: 0.095851414 | E47: 0.103049 | F47: 0.094424 | G47: 0.026617 | H47: 0.028945 | I47: 0.031242 | J47: 0.034373 | K47: 0.037698 | L47: 0.040962 | M47: 0.044143 | N47: =M47*M47/L47 -> 0.047571028
B48: Televisions and Related Equipment | D48: 0.29940426 | E48: 0.31756 | F48: 0.288212 | G48: 0.209133 | H48: 0.175692 | I48: 0.160987 | J48: 0.146585 | K48: 0.13791 | L48: 0.135552 | M48: 0.138527 | N48: =M48*M48/L48 -> 0.14156729
B49: Computers and Related Equipment | D49: 0.065222315 | E49: 0.158562 | F49: 0.111117 | G49: 0.086664 | H49: 0.115363 | I49: 0.103168 | J49: 0.087647 | K49: 0.074726 | L49: 0.066753 | M49: 0.065107 | N49: =M49*M49/L49 -> 0.063501587
... B51: Other Uses | D51: 1.0101715 | E51: 1.114385 | F51: 1.373761 | G51: 1.782218 | H51: 1.841668 | I51: 2.015298 | J51: 2.169604 | K51: 2.353622 | L51: 2.573554 | M51: 2.840269 | N51: =M51*M51/L51 -> 3.1346255
B52: Delivered Energy | D52: =SUM(D38:D51) -> 4.6375789 | E52: =SUM(E38:E51) -> 4.93277 | F52: =SUM(F38:F51) -> 4.776404 | G52: =SUM(G38:G51) -> 5.130944 | H52: =SUM(H38:H51) -> 5.307274 | I52: =SUM(I38:I51) -> 5.554088 | J52: =SUM(J38:J51) -> 5.742076 | K52: =SUM(K38:K51) -> 6.020301 | ... N52: =SUM(N38:N51) -> 7.31652
B53: Miscellaneous Electric | D53: =SUM(D41:D44,D46:D51) -> 2.3968617 | E53: =SUM(E41:E44,E46:E51) -> 2.622353 | F53: =SUM(F41:F44,F46:F51) -> 2.751986 | G53: =SUM(G41:G44,G46:G51) -> 2.85778 | H53: =SUM(H41:H44,H46:H51) -> 2.934564 | I53: =SUM(I41:I44,I46:I51) -> 3.108839 | J53: =SUM(J41:J44,J46:J51) -> 3.256337 | K53: =SUM(K41:K44,K46:K51) -> 3.448284 | ... N53: =SUM(N41:N44,N46:N51) -> 4.34216
B54: Natural Gas
B55: Space Heating | D55: 3.33 | E55: 3.323368 | F55: 3.018605 | G55: 3.527199 | H55: 3.534772 | I55: 3.487897 | J55: 3.379413 | K55: 3.301509 | L55: 3.247816 | M55: 3.191122 | N55: =M55*M55/L55 -> 3.1354177
B56: Space Cooling | D56: 1.1e-08 | E56: 2e-06 | F56: 0.023169 | G56: 0.058618 | H56: 0.059824 | I56: 0.060099 | J56: 0.059099 | K56: 0.059841 | L56: 0.060936 | M56: 0.062122 | N56: =M56*M56/L56 -> 0.063331083
B57: Water Heating | D57: 1.088775 | E57: 1.295824 | F57: 1.207743 | G57: 1.007278 | H57: 1.005515 | I57: 1.078192 | J57: 1.121259 | K57: 1.158029 | L57: 1.194551 | M57: 1.228967 | N57: =M57*M57/L57 -> 1.2643746
B58: Cooking | D58: 0.21647027 | E58: 0.217054 | F58: 0.208441 | G58: 0.103456 | H58: 0.104173 | I58: 0.105678 | J58: 0.109004 | K58: 0.113552 | L58: 0.118736 | M58: 0.12409 | N58: =M58*M58/L58 -> 0.12968542
B59: Clothes Dryers | D59: 0.0719992 | E59: 0.056272 | F59: 0.051087 | G59: 0.039427 | H59: 0.041872 | I59: 0.046698 | J59: 0.05008 | K59: 0.053475 | L59: 0.057282 | M59: 0.06075 | N59: =M59*M59/L59 -> 0.064427962
B60: Other Uses | D60: 0.26 | E60: 0 | F60: 0.248127 | G60: 0.233372 | H60: 0.227805 | I60: 0.231911 | J60: 0.228858 | K60: 0.226353 | L60: 0.224557 | M60: 0.221789 | N60: =M60*M60/L60 -> 0.21905512
B61: Delivered Energy | D61: =SUM(D55:D60) -> 4.9672445 | E61: =SUM(E55:E60) -> 4.89252 | F61: =SUM(F55:F60) -> 4.757172 | G61: =SUM(G55:G60) -> 4.96935 | H61: =SUM(H55:H60) -> 4.973961 | I61: =SUM(I55:I60) -> 5.010475 | J61: =SUM(J55:J60) -> 4.947713 | K61: =SUM(K55:K60) -> 4.912759 | ... N61: =SUM(N55:N60) -> 4.8762918
B62: Miscellaneous Gas | D62: =SUM(D58:D60) -> 0.54846947 | E62: =SUM(E58:E60) -> 0.273326 | F62: =SUM(F58:F60) -> 0.507655 | G62: =SUM(G58:G60) -> 0.376255 | H62: =SUM(H58:H60) -> 0.37385 | I62: =SUM(I58:I60) -> 0.384287 | J62: =SUM(J58:J60) -> 0.387942 | K62: =SUM(K58:K60) -> 0.39338 | ... N62: =SUM(N58:N60) -> 0.4131685
B63: Distillate Fuel Oil
B64: Space Heating | D64: 0.65 | E64: 0.485259 | F64: 0.463082 | G64: 0.372665 | H64: 0.323264 | I64: 0.29494 | J64: 0.267846 | K64: 0.244715 | L64: 0.223829 | M64: 0.203485 | N64: =M64*M64/L64 -> 0.18499008
B65: Water Heating | D65: 0.10857271 | E65: 0.09739 | F65: 0.044641 | G65: 0.048758 | H65: 0.037466 | I65: 0.033803 | J65: 0.031182 | K65: 0.028531 | L65: 0.026321 | M65: 0.024542 | N65: =M65*M65/L65 -> 0.02288324
B66: Other Uses | F66: 0.00705 | G66: 0.007851 | H66: 0.007369 | I66: 0.00737 | J66: 0.007275 | K66: 0.007189 | L66: 0.007111 | M66: 0.007033 | N66: =M66*M66/L66 -> 0.0069558556
B67: Delivered Energy | D67: =SUM(D64:D66) -> 0.75857271 | E67: =SUM(E64:E66) -> 0.582649 | F67: =SUM(F64:F66) -> 0.514773 | G67: =SUM(G64:G66) -> 0.429274 | H67: =SUM(H64:H66) -> 0.368099 | I67: =SUM(I64:I66) -> 0.336113 | J67: =SUM(J64:J66) -> 0.306303 | K67: =SUM(K64:K66) -> 0.280435 | ... N67: =SUM(N64:N66) -> 0.21482918
B69: Propane
B70: Space Heating | D70: 0.37 | E70: 0.281909 | F70: 0.341401 | G70: 0.300826 | H70: 0.294508 | I70: 0.280645 | J70: 0.264355 | K70: 0.251703 | L70: 0.241594 | M70: 0.232634 | N70: =M70*M70/L70 -> 0.2240063
B71: Water Heating | D71: 0.057690114 | E71: 0.072251 | F71: 0.060069 | G71: 0.065345 | H71: 0.053262 | I71: 0.049293 | J71: 0.044928 | K71: 0.040704 | L71: 0.037623 | M71: 0.035496 | N71: =M71*M71/L71 -> 0.033489249
B72: Cooking | D72: 0.031476043 | E72: 0.030519 | F72: 0.02822 | G72: 0.017067 | H72: 0.016368 | I72: 0.015245 | J72: 0.01421 | K72: 0.01389 | L72: 0.013502 | M72: 0.013175 | N72: =M72*M72/L72 -> 0.012855919
B73: Other Uses | D73: 0.04 | E73: 0.145471 | F73: 0.043472 | G73: 0.071942 | H73: 0.076967 | I73: 0.088106 | J73: 0.097231 | K73: 0.106688 | L73: 0.116869 | M73: 0.127509 | N73: =M73*M73/L73 -> 0.13911769
B74: Delivered Energy | D74: =SUM(D70:D73) -> 0.49916616 | E74: =SUM(E70:E73) -> 0.53015 | F74: =SUM(F70:F73) -> 0.473162 | G74: =SUM(G70:G73) -> 0.45518 | H74: =SUM(H70:H73) -> 0.441105 | I74: =SUM(I70:I73) -> 0.433289 | J74: =SUM(J70:J73) -> 0.420724 | K74: =SUM(K70:K73) -> 0.412985 | ... N74: =SUM(N70:N73) -> 0.40946916
B76: Marketed Renewables (wood) | D76: 0.44818163 | E76: 0.43944 | F76: 0.440932 | G76: 0.457512 | H76: 0.489864 | I76: 0.426017 | J76: 0.387514 | K76: 0.353241 | L76: 0.327538 | M76: 0.308024 | N76: =M76*M76/L76 -> 0.2896726
B77: Other Fuels | D77: 0.10066375 | E77: 0.01853 | F77: 0.008559 | G77: 0 | H77: 0 | I77: 0 | J77: 0 | K77: 0 | L77: 0 | M77: 0
B79: Energy Consumption by End Use
B80: Space Heating | D80: =D38+D55+D64+D70+D76 -> 5.1086223 | E80: 4.863599 | F80: 4.604874 | G80: 5.307178 | H80: 5.299356 | I80: 5.127351 | J80: 4.898966 | K80: 4.716778 | L80: 4.577453 | M80: 4.447649 | N80: =M80*M80/L80 -> 4.3215259
B81: Space Cooling | D81: 0.82135016 | E81: 0.915241 | F81: 0.81741 | G81: 0.86401 | H81: 0.970874 | I81: 1.064569 | J81: 1.147432 | K81: 1.256749 | L81: 1.377735 | M81: 1.52527 | N81: =M81*M81/L81 -> 1.6886038
B82: Water Heating | D82: 1.6372221 | E82: 1.911607 | F82: 1.763412 | G82: 1.72893 | H82: 1.695826 | I82: 1.75451 | J82: 1.785921 | K82: 1.829057 | L82: 1.87533 | M82: 1.925086 | N82: =M82*M82/L82 -> 1.9761621
B83: Refrigeration | D83: 0.39436102 | E83: 0.376004 | F83: 0.355201 | G83: 0.297571 | H83: 0.29163 | I83: 0.289659 | J83: 0.294343 | K83: 0.306848 | L83: 0.324507 | M83: 0.340702 | N83: =M83*M83/L83 -> 0.35770524
B84: Cooking | D84: 0.34996358 | E84: 0.35518 | F84: 0.344572 | G84: 0.17553 | H84: 0.177417 | I84: 0.179315 | J84: 0.182619 | K84: 0.188336 | L84: 0.194441 | M84: 0.200584 | N84: =M84*M84/L84 -> 0.20692108
B85: Clothes Dryers | D85: 0.32461026 | E85: 0.252063 | F85: 0.255722 | G85: 0.255847 | H85: 0.279166 | I85: 0.306369 | J85: 0.325803 | K85: 0.345681 | L85: 0.366391 | M85: 0.389028 | N85: =M85*M85/L85 -> 0.4130636
B86: Freezers | D86: 0.083529256 | E86: 0.082217 | F86: 0.07543 | G86: 0.069181 | H86: 0.068516 | I86: 0.067615 | J86: 0.067169 | K86: 0.067431 | L86: 0.068666 | M86: 0.070729 | N86: =M86*M86/L86 -> 0.072853981
B87: Lighting | D87: 0.72674227 | E87: 0.652205 | F87: 0.448123 | G87: 0.211247 | H87: 0.205129 | I87: 0.209704 | J87: 0.209016 | K87: 0.207703 | L87: 0.20064 | M87: 0.202056 | N87: =M87*M87/L87 -> 0.20348199
B88: Clothes Washers | D88: 0.034679808 | E88: 0.032793 | F88: 0.026497 | G88: 0.036779 | H88: 0.038486 | I88: 0.040246 | J88: 0.042099 | K88: 0.043898 | L88: 0.045619 | M88: 0.047258 | N88: =M88*M88/L88 -> 0.048955886
B89: Dishwashers | D89: 0.095851414 | E89: 0.103049 | F89: 0.094424 | G89: 0.026617 | H89: 0.028945 | I89: 0.031242 | J89: 0.034373 | K89: 0.037698 | L89: 0.040962 | M89: 0.044143 | N89: =M89*M89/L89 -> 0.047571028
B90: Televisions and Related Equipment | D90: 0.29940426 | E90: 0.31756 | F90: 0.288212 | G90: 0.209133 | H90: 0.175692 | I90: 0.160987 | J90: 0.146585 | K90: 0.13791 | L90: 0.135552 | M90: 0.138527 | N90: =M90*M90/L90 -> 0.14156729
B91: Computers and Related Equipment | D91: 0.065222315 | E91: 0.158562 | F91: 0.111117 | G91: 0.086664 | H91: 0.115363 | I91: 0.103168 | J91: 0.087647 | K91: 0.074726 | L91: 0.066753 | M91: 0.065107 | N91: =M91*M91/L91 -> 0.063501587
B92: Furnace Fans and Boiler Circulation Pumps | D92: 0.059013724 | E92: 0.134385 | F92: 0.114797 | G92: 0.078189 | H92: 0.080094 | I92: 0.082562 | J92: 0.07939 | K92: 0.07305 | L92: 0.067823 | M92: 0.064997 | N92: =M92*M92/L92 -> 0.062288752
B93: Other Uses | D93: 1.160265 | E93: 1.259856 | F93: 1.672411 | G93: 2.095383 | H93: 2.15381 | I93: 2.342685 | J93: 2.502968 | K93: 2.693851 | L93: 2.92209 | M93: 3.196599 | N93: =M93*M93/L93 -> 3.4968961
B94: Gross End-use Consumption | G94: 11.442256 | H94: 11.580305 | I94: 11.759981 | J94: 11.804331 | K94: 11.979717 | L94: 12.263962 | M94: 12.657738 | N94: =M94*M94/L94 -> 13.064158
B95: Onsite Generation for Own Use | G95: 0.078131 | H95: 0.149777 | I95: 0.21982 | J95: 0.299474 | K95: 0.3854 | L95: 0.497574 | M95: 0.634524 | N95: =M95*M95/L95 -> 0.80916749
B96: Delivered Energy | D96: =SUM(D80:D93,D95) -> 11.160837 | E96: =SUM(E80:E93,E95) -> 11.414321 | F96: =SUM(F80:F93,F95) -> 10.972202 | G96: =SUM(G80:G93,G95) -> 11.52039 | H96: =SUM(H80:H93,H95) -> 11.730081 | I96: =SUM(I80:I93,I95) -> 11.979802 | J96: =SUM(J80:J93,J95) -> 12.103805 | K96: =SUM(K80:K93,K95) -> 12.365116 | ... N96: =SUM(N80:N93,N95) -> 13.910266
B98: Electricity Related Losses | D98: 10.124526 | E98: 10.347565 | F98: 9.569791 | G98: 9.417956 | H98: 9.27758 | I98: 9.133 | J98: 9.377416 | K98: 9.514772 | L98: 9.906764 | M98: 10.336385 | N98: =M98*M98/L98 -> 10.784637
B100: Total Energy Consumption by End Use
B101: Space Heating | D101: 6.1418977 | E101: 5.486269 | F101: 5.268241 | G101: 6.516824 | H101: 6.481146 | I101: 6.219484 | J101: 5.932523 | K101: 5.671903 | L101: 5.483564 | M101: 5.304385 | N101: =M101*M101/L101 -> 5.1310608
B102: Space Cooling | D102: 2.6144798 | E102: 2.835155 | F102: 2.408715 | G102: 2.365208 | H102: 2.609767 | I102: 2.784432 | J102: 3.022695 | K102: 3.277918 | L102: 3.600989 | M102: 3.971736 | N102: =M102*M102/L102 -> 4.380654
B103: Water Heating | D103: 2.4715872 | E103: 2.847484 | F103: 2.666933 | G103: 2.86136 | H103: 2.774418 | I103: 2.770231 | J103: 2.800031 | K103: 2.845284 | L103: 2.91678 | M103: 2.988648 | N103: =M103*M103/L103 -> 3.0622868
B104: Refrigeration | D104: 1.2553098 | E104: 1.164754 | F104: 1.066866 | G104: 0.852222 | H104: 0.816244 | I104: 0.785615 | J104: 0.801514 | K104: 0.825009 | L104: 0.872397 | M104: 0.910376 | N104: =M104*M104/L104 -> 0.95000838
B105: Cooking | D105: 0.57268238 | E105: 0.580909 | F105: 0.560779 | G105: 0.278059 | H105: 0.279729 | I105: 0.279292 | J105: 0.284976 | K105: 0.291167 | L105: 0.299464 | M105: 0.306457 | N105: =M105*M105/L105 -> 0.3136133
B106: Clothes Dryers | D106: 0.8760978 | E106: 0.662777 | F106: 0.665719 | G106: 0.659241 | H106: 0.706037 | I106: 0.75098 | J106: 0.80089 | K106: 0.839117 | L106: 0.888283 | M106: 0.937927 | N106: =M106*M106/L106 -> 0.99034548
B107: Freezers | D107: 0.26588607 | E107: 0.254684 | F107: 0.226559 | G107: 0.198131 | H107: 0.191769 | I107: 0.183387 | J107: 0.182904 | K107: 0.181299 | L107: 0.184599 | M107: 0.188993 | N107: =M107*M107/L107 -> 0.19349159
B108: Lighting | D108: 2.3133287 | E108: 2.020348 | F108: 1.345962 | G108: 0.604997 | H108: 0.574137 | I108: 0.56876 | J108: 0.569162 | K108: 0.558443 | L108: 0.539396 | M108: 0.539906 | N108: =M108*M108/L108 -> 0.54041648
B109: Clothes Washers | D109: 0.11039099 | E109: 0.101584 | F109: 0.079586 | G109: 0.105334 | H109: 0.107719 | I109: 0.109156 | J109: 0.114638 | K109: 0.118026 | L109: 0.12264 | M109: 0.126277 | N109: =M109*M109/L109 -> 0.13002186
B110: Dishwashers | D110: 0.30510932 | E110: 0.319218 | F110: 0.283609 | G110: 0.076228 | H110: 0.081015 | I110: 0.084734 | J110: 0.0936 | K110: 0.101357 | L110: 0.110121 | M110: 0.117952 | N110: =M110*M110/L110 -> 0.12633988
B111: Televisions and Related Equipment | D111: 0.95304835 | E111: 0.983711 | F111: 0.86566 | G111: 0.598942 | H111: 0.491745 | I111: 0.43663 | J111: 0.39916 | K111: 0.370793 | L111: 0.364416 | M111: 0.370152 | N111: =M111*M111/L111 -> 0.37597829
B112: Computers and Related Equipment | D112: 0.20761234 | E112: 0.49118 | F112: 0.333746 | G112: 0.2482 | H112: 0.322891 | I112: 0.279812 | J112: 0.238668 | K112: 0.200912 | L112: 0.179457 | M112: 0.17397 | N112: =M112*M112/L112 -> 0.16865077
...

Sheet Fuel Share
C2: 2010 Fuel Consumption by Type (PJ) | M2: 2015 Fuel Consumption by Type (PJ) | W2: 2020 Fuel Consumption by Type (PJ)
C3: Total | D3: Residential | E3: Commercial | F3: Industrial | M3: Total | N3: Residential | O3: Commercial | P3: Industrial | W3: Total | X3: Residential | Y3: Commercial | Z3: Industrial
B4: ELC | C4: =GHG_INV!I69 -> 181.06908 | D4: =GHG_INV!D69 -> 58.483486 | E4: =GHG_INV!F69 -> 90.642122 | F4: =GHG_INV!H69 -> 31.943468 | L4: ELC | M4: =GHG_INV!I79 -> 176.53776 | N4: =GHG_INV!D79 -> 56.537463 | O4: =GHG_INV!F79 -> 87.510498 | P4: =GHG_INV!H79 -> 32.489795 | V4: ELC | W4: =GHG_INV!I89 -> 151.91239 | X4: =GHG_INV!D89 -> 52.47592 | Y4: =GHG_INV!F89 -> 72.948497 | Z4: =GHG_INV!H89 -> 26.487976
B5: NGA | C5: =GHG_INV!I70 -> 288.72889 | D5: =GHG_INV!D70 -> 169.79321 | E5: =GHG_INV!F70 -> 96.13988 | F5: =GHG_INV!H70 -> 22.795794 | L5: NGA | M5: =GHG_INV!I80 -> 331.77185 | N5: =GHG_INV!D80 -> 191.98429 | O5: =GHG_INV!F80 -> 112.84987 | P5: =GHG_INV!H80 -> 26.93769 | V5: NGA | W5: =GHG_INV!I90 -> 341.56323 | X5: =GHG_INV!D90 -> 194.07827 | Y5: =GHG_INV!F90 -> 119.6856 | Z5: =GHG_INV!H90 -> 27.799357
B6: DSL | C6: =SUM(GHG_INV!I65:I68) -> 83.869941 | D6: =SUM(GHG_INV!D65:D68) -> 62.907741 | E6: =SUM(GHG_INV!F65:F68) -> 17.527795 | F6: =SUM(GHG_INV!H65:H68) -> 3.4344049 | L6: DSL | M6: =SUM(GHG_INV!I75:I77) -> 59.548416 | N6: =SUM(GHG_INV!D75:D78) -> 41.211086 | O6: =SUM(GHG_INV!F75:F78) -> 16.406123 | P6: =SUM(GHG_INV!H75:H78) -> 3.6873745 | V6: DSL | W6: =SUM(GHG_INV!I85:I87) -> 30.920698 | X6: =SUM(GHG_INV!D85:D88) -> 22.067888 | Y6: =SUM(GHG_INV!F85:F88) -> 9.5856427 | Z6: =SUM(GHG_INV!H85:H88) -> 2.1646891
B7: STM | C7: =GHG_INV!I71 -> 29.351245 | D7: =GHG_INV!D71 -> 7.4544235 | E7: =GHG_INV!F71 -> 16.843709 | F7: =GHG_INV!H71 -> 5.0531127 | L7: STM | M7: =GHG_INV!I81 -> 26.618414 | N7: =GHG_INV!D81 -> 7.4188424 | O7: =GHG_INV!F81 -> 14.768901 | P7: =GHG_INV!H81 -> 4.4306703 | V7: STM | W7: =GHG_INV!I91 -> 20.889407 | X7: =GHG_INV!D91 -> 6.6789381 | Y7: =GHG_INV!F91 -> 10.93113 | Z7: =GHG_INV!H91 -> 3.2793389
B9: 2010 Fuel Consumption by Borough (PJ) | L9: 2015 Fuel Consumption by Borough (PJ) | V9: 2020 Fuel Consumption by Borough (PJ)
C10: Bronx | D10: Space Heating | E10: DHW | F10: Space Cooling | G10: Lighting | H10: Other ELC | I10: Other DSL | J10: Other NGA | M10: Bronx | N10: Space Heating | O10: DHW | P10: Space Cooling | Q10: Lighting | R10: Other ELC | S10: Other DSL | T10: Other NGA | W10: Bronx | X10: Space Heating | Y10: DHW | Z10: Space Cooling | AA10: Lighting | AB10: Other ELC | AC10: Other DSL | AD10: Other NGA
B11: ELC | C11: =D4*BldgArea!$C$45 -> 8.4885673 | D11: =$C11*Original!C54 -> 0.45590898 | E11: =$C11*Original!D54 -> 0.20488555 | F11: =$C11*Original!E54 -> 1.3560803 | G11: =$C11*Original!F54 -> 2.1459765 | H11: =$C11*Original!G54 -> 4.325716 | I11: =$C11*Original!H54 -> 0 | J11: =$C11*Original!I54 -> 0 | L11: ELC | M11: =N4*BldgArea!$K$45 -> 8.1643636 | N11: =$M11*Original!C54 -> 0.43849646 | O11: =$M11*Original!D54 -> 0.19706036 | P11: =$M11*Original!E54 -> 1.3042875 | Q11: =$M11*Original!F54 -> 2.0640153 | R11: =$M11*Original!G54 -> 4.160504 | S11: =$M11*Original!H54 -> 0 | T11: =$M11*Original!I54 -> 0 | V11: ELC | W11: =X4*BldgArea!$S$45 -> 7.6927628 | X11: =$W11*Original!C54 -> 0.41316744 | Y11: =$W11*Original!D54 -> 0.1856775 | Z11: =$W11*Original!E54 -> 1.2289475 | AA11: =$W11*Original!F54 -> 1.9447909 | AB11: =$W11*Original!G54 -> 3.9201794 | AC11: =$W11*Original!H54 -> 0 | AD11: =$W11*Original!I54 -> 0
B12: NGA | C12: =D5*BldgArea!$C$45 -> 24.644582 | D12: =$C12*Original!C55 -> 16.788576 | E12: =$C12*Original!D55 -> 7.4653205 | F12: =$C12*Original!E55 -> 0 | G12: =$C12*Original!F55 -> 0 | H12: =$C12*Original!G55 -> 0 | I12: =$C12*Original!H55 -> 0 | J12: =$C12*Original!I55 -> 0.3906862 | L12: NGA | M12: =N5*BldgArea!$K$45 -> 27.723734 | N12: =$M12*Original!C55 -> 18.886179 | O12: =$M12*Original!D55 -> 8.398055 | P12: =$M12*Original!E55 -> 0 | Q12: =$M12*Original!F55 -> 0 | R12: =$M12*Original!G55 -> 0 | S12: =$M12*Original!H55 -> 0 | T12: =$M12*Original!I55 -> 0.43949944 | V12: NGA | W12: =X5*BldgArea!$S$45 -> 28.451108 | X12: =$W12*Original!C55 -> 19.381687 | Y12: =$W12*Original!D55 -> 8.6183906 | Z12: =$W12*Original!E55 -> 0 | AA12: =$W12*Original!F55 -> 0 | AB12: =$W12*Original!G55 -> 0 | AC12: =$W12*Original!H55 -> 0 | AD12: =$W12*Original!I55 -> 0.45103037
B13: DSL | C13: =D6*BldgArea!$C$45 -> 9.1307245 | D13: =$C13*Original!C56 -> 6.8979786 | E13: =$C13*Original!D56 -> 2.2327423 | F13: =$C13*Original!E56 -> 0 | G13: =$C13*Original!F56 -> 0 | H13: =$C13*Original!G56 -> 0 | I13: =$C13*Original!H56 -> 3.5425196e-06 | J13: =$C13*Original!I56 -> 0 | L13: DSL | M13: =N6*BldgArea!$K$45 -> 5.9511389 | N13: =$M13*Original!C56 -> 4.4959005 | O13: =$M13*Original!D56 -> 1.455236 | P13: =$M13*Original!E56 -> 0 | Q13: =$M13*Original!F56 -> 0 | R13: =$M13*Original!G56 -> 0 | S13: =$M13*Original!H56 -> 2.3089106e-06 | T13: =$M13*Original!I56 -> 0 | V13: DSL | W13: =X6*BldgArea!$S$45 -> 3.2350653 | X13: =$W13*Original!C56 -> 2.4439913 | Y13: =$W13*Original!D56 -> 0.79107272 | Z13: =$W13*Original!E56 -> 0 | AA13: =$W13*Original!F56 -> 0 | AB13: =$W13*Original!G56 -> 0 | AC13: =$W13*Original!H56 -> 1.255134e-06 | AD13: =$W13*Original!I56 -> 0
B14: STM | C14: =D7*BldgArea!$C$45 -> 1.08197 | D14: =$C14*Original!C57 -> 0.75984301 | E14: =$C14*Original!D57 -> 0.32212696 | F14: =$C14*Original!E57 -> 0 | G14: =$C14*Original!F57 -> 0 | H14: =$C14*Original!G57 -> 0 | I14: =$C14*Original!H57 -> 0 | J14: =$C14*Original!I57 -> 0 | L14: STM | M14: =N7*BldgArea!$K$45 -> 1.0713273 | N14: =$M14*Original!C57 -> 0.7523689 | O14: =$M14*Original!D57 -> 0.31895839 | P14: =$M14*Original!E57 -> 0 | Q14: =$M14*Original!F57 -> 0 | R14: =$M14*Original!G57 -> 0 | S14: =$M14*Original!H57 -> 0 | T14: =$M14*Original!I57 -> 0 | V14: STM | W14: =X7*BldgArea!$S$45 -> 0.97910597 | X14: =$W14*Original!C57 -> 0.68760395 | Y14: =$W14*Original!D57 -> 0.29150202 | Z14: =$W14*Original!E57 -> 0 | AA14: =$W14*Original!F57 -> 0 | AB14: =$W14*Original!G57 -> 0 | AC14: =$W14*Original!H57 -> 0 | AD14: =$W14*Original!I57 -> 0
D15: =SUM(D11:D14) -> 24.902306 | E15: =SUM(E11:E14) -> 10.225075 | F15: =SUM(F11:F14) -> 1.3560803 | G15: =SUM(G11:G14) -> 2.1459765 | H15: =SUM(H11:H14) -> 4.325716 | I15: =SUM(I11:I14) -> 3.5425196e-06 | J15: =SUM(J11:J14) -> 0.3906862 | N15: =SUM(N11:N14) -> 24.572945 | O15: =SUM(O11:O14) -> 10.36931 | P15: =SUM(P11:P14) -> 1.3042875 | Q15: =SUM(Q11:Q14) -> 2.0640153 | R15: =SUM(R11:R14) -> 4.160504 | S15: =SUM(S11:S14) -> 2.3089106e-06 | T15: =SUM(T11:T14) -> 0.43949944 | X15: =SUM(X11:X14) -> 22.92645 | Y15: =SUM(Y11:Y14) -> 9.8866429 | Z15: =SUM(Z11:Z14) -> 1.2289475 | AA15: =SUM(AA11:AA14) -> 1.9447909 | AB15: =SUM(AB11:AB14) -> 3.9201794 | AC15: =SUM(AC11:AC14) -> 1.255134e-06 | AD15: =SUM(AD11:AD14) -> 0.45103037
C16: Brooklyn | D16: Space Heating | E16: DHW | F16: Space Cooling | G16: Lighting | H16: Other ELC | I16: Other DSL | J16: Other NGA | M16: Brooklyn | N16: Space Heating | O16: DHW | P16: Space Cooling | Q16: Lighting | R16: Other ELC | S16: Other DSL | T16: Other NGA | W16: Brooklyn | X16: Space Heating | Y16: DHW | Z16: Space Cooling | AA16: Lighting | AB16: Other ELC | AC16: Other DSL | AD16: Other NGA
B17: ELC | C17: =D4*BldgArea!$C$46 -> 17.039249 | D17: =$C17*Original!C54 -> 0.91515403 | E17: =$C17*Original!D54 -> 0.41127033 | F17: =$C17*Original!E54 -> 2.7220835 | G17: =$C17*Original!F54 -> 4.307656 | H17: =$C17*Original!G54 -> 8.6830849 | I17: =$C17*Original!H54 -> 0 | J17: =$C17*Original!I54 -> 0 | L17: ELC | M17: =N4*BldgArea!$K$46 -> 16.472938 | N17: =$M17*Original!C54 -> 0.88473828 | O17: =$M17*Original!D54 -> 0.39760149 | P17: =$M17*Original!E54 -> 2.6316132 | Q17: =$M17*Original!F54 -> 4.1644882 | R17: =$M17*Original!G54 -> 8.3944968 | S17: =$M17*Original!H54 -> 0 | T17: =$M17*Original!I54 -> 0 | V17: ELC | W17: =X4*BldgArea!$S$46 -> 15.352435 | X17: =$W17*Original!C54 -> 0.82455762 | Y17: =$W17*Original!D54 -> 0.3705563 | Z17: =$W17*Original!E54 -> 2.4526086 | AA17: =$W17*Original!F54 -> 3.8812162 | AB17: =$W17*Original!G54 -> 7.8234959 | AC17: =$W17*Original!H54 -> 0 | AD17: =$W17*Original!I54 -> 0
B18: NGA | C18: =D5*BldgArea!$C$46 -> 49.469499 | D18: =$C18*Original!C55 -> 33.7 | E18: =$C18*Original!D55 -> 14.985268 | F18: =$C18*Original!E55 -> 0 | G18: =$C18*Original!F55 -> 0 | H18: =$C18*Original!G55 -> 0 | I18: =$C18*Original!H55 -> 0 | J18: =$C18*Original!I55 -> 0.7842312 | L18: NGA | M18: =N5*BldgArea!$K$46 -> 55.937165 | N18: =$M18*Original!C55 -> 38.105954 | O18: =$M18*Original!D55 -> 16.944449 | P18: =$M18*Original!E55 -> 0 | Q18: =$M18*Original!F55 -> 0 | R18: =$M18*Original!G55 -> 0 | S18: =$M18*Original!H55 -> 0 | T18: =$M18*Original!I55 -> 0.88676196 | V18: NGA | W18: =X5*BldgArea!$S$46 -> 56.779832 | X18: =$W18*Original!C55 -> 38.680002 | Y18: =$W18*Original!D55 -> 17.199709 | Z18: =$W18*Original!E55 -> 0 | AA18: =$W18*Original!F55 -> 0 | AB18: =$W18*Original!G55 -> 0 | AC18: =$W18*Original!H55 -> 0 | AD18: =$W18*Original!I55 -> 0.90012061
B19: DSL | C19: =D6*BldgArea!$C$46 -> 18.328262 | D19: =$C19*Original!C56 -> 13.846432 | E19: =$C19*Original!D56 -> 4.4818224 | F19: =$C19*Original!E56 -> 0 | G19: =$C19*Original!F56 -> 0 | H19: =$C19*Original!G56 -> 0 | I19: =$C19*Original!H56 -> 7.1109613e-06 | J19: =$C19*Original!I56 -> 0 | L19: DSL | M19: =N6*BldgArea!$K$46 -> 12.007395 | N19: =$M19*Original!C56 -> 9.0712142 | O19: =$M19*Original!D56 -> 2.9361766 | P19: =$M19*Original!E56 -> 0 | Q19: =$M19*Original!F56 -> 0 | R19: =$M19*Original!G56 -> 0 | S19: =$M19*Original!H56 -> 4.6586045e-06 | T19: =$M19*Original!I56 -> 0 | V19: DSL | W19: =X6*BldgArea!$S$46 -> 6.4562148 | X19: =$W19*Original!C56 -> 4.8774697 | Y19: =$W19*Original!D56 -> 1.5787426 | Z19: =$W19*Original!E56 -> 0 | AA19: =$W19*Original!F56 -> 0 | AB19: =$W19*Original!G56 -> 0 | AC19: =$W19*Original!H56 -> 2.5048689e-06 | AD19: =$W19*Original!I56 -> 0
B20: STM | C20: =D7*BldgArea!$C$46 -> 2.1718571 | D20: =$C20*Original!C57 -> 1.5252461 | E20: =$C20*Original!D57 -> 0.64661105 | F20: =$C20*Original!E57 -> 0 | G20: =$C20*Original!F57 -> 0 | H20: =$C20*Original!G57 -> 0 | I20: =$C20*Original!H57 -> 0 | J20: =$C20*Original!I57 -> 0 | L20: STM | M20: =N7*BldgArea!$K$46 -> 2.1615779 | N20: =$M20*Original!C57 -> 1.5180272 | O20: =$M20*Original!D57 -> 0.64355069 | P20: =$M20*Original!E57 -> 0 | Q20: =$M20*Original!F57 -> 0 | R20: =$M20*Original!G57 -> 0 | S20: =$M20*Original!H57 -> 0 | T20: =$M20*Original!I57 -> 0 | V20: STM | W20: =X7*BldgArea!$S$46 -> 1.9540002 | X20: =$W20*Original!C57 -> 1.3722501 | Y20: =$W20*Original!D57 -> 0.58175012 | Z20: =$W20*Original!E57 -> 0 | AA20: =$W20*Original!F57 -> 0 | AB20: =$W20*Original!G57 -> 0 | AC20: =$W20*Original!H57 -> 0 | AD20: =$W20*Original!I57 -> 0
D21: =SUM(D17:D20) -> 49.986833 | E21: =SUM(E17:E20) -> 20.524971 | F21: =SUM(F17:F20) -> 2.7220835 | G21: =SUM(G17:G20) -> 4.307656 | H21: =SUM(H17:H20) -> 8.6830849 | I21: =SUM(I17:I20) -> 7.1109613e-06 | J21: =SUM(J17:J20) -> 0.7842312 | N21: =SUM(N17:N20) -> 49.579934 | O21: =SUM(O17:O20) -> 20.921777 | P21: =SUM(P17:P20) -> 2.6316132 | Q21: =SUM(Q17:Q20) -> 4.1644882 | R21: =SUM(R17:R20) -> 8.3944968 | S21: =SUM(S17:S20) -> 4.6586045e-06 | T21: =SUM(T17:T20) -> 0.88676196 | X21: =SUM(X17:X20) -> 45.75428 | Y21: =SUM(Y17:Y20) -> 19.730758 | Z21: =SUM(Z17:Z20) -> 2.4526086 | AA21: =SUM(AA17:AA20) -> 3.8812162 | AB21: =SUM(AB17:AB20) -> 7.8234959 | AC21: =SUM(AC17:AC20) -> 2.5048689e-06 | AD21: =SUM(AD17:AD20) -> 0.90012061
C22: Manhattan | D22: Space Heating | E22: DHW | F22: Space Cooling | G22: Lighting | H22: Other ELC | I22: Other DSL | J22: Other NGA | M22: Manhattan | N22: Space Heating | O22: DHW | P22: Space Cooling | Q22: Lighting | R22: Other ELC | S22: Other DSL | T22: Other NGA | W22: Manhattan | X22: Space Heating | Y22: DHW | Z22: Space Cooling | AA22: Lighting | AB22: Other ELC | AC22: Other DSL | AD22: Other NGA
B23: ELC | C23: =D4*BldgArea!$C$47 -> 14.920722 | D23: =$C23*Original!C54 -> 0.80137093 | E23: =$C23*Original!D54 -> 0.36013619 | F23: =$C23*Original!E54 -> 2.3836409 | G23: =$C23*Original!F54 -> 3.7720757 | H23: =$C23*Original!G54 -> 7.603498 | I23: =$C23*Original!H54 -> 0 | J23: =$C23*Original!I54 -> 0 | L23: ELC | M23: =N4*BldgArea!$K$47 -> 14.421515 | N23: =$M23*Original!C54 -> 0.77455925 | O23: =$M23*Original!D54 -> 0.34808702 | P23: =$M23*Original!E54 -> 2.3038908 | Q23: =$M23*Original!F54 -> 3.6458724 | R23: =$M23*Original!G54 -> 7.3491058 | S23: =$M23*Original!H54 -> 0 | T23: =$M23*Original!I54 -> 0 | V23: ELC | W23: =X4*BldgArea!$S$47 -> 13.648274 | X23: =$W23*Original!C54 -> 0.73302955 | Y23: =$W23*Original!D54 -> 0.32942357 | Z23: =$W23*Original!E54 -> 2.1803626 | AA23: =$W23*Original!F54 -> 3.4503909 | AB23: =$W23*Original!G54 -> 6.9550672 | AC23: =$W23*Original!H54 -> 0 | AD23: =$W23*Original!I54 -> 0
B24: NGA | C24: =D5*BldgArea!$C$47 -> 43.318848 | D24: =$C24*Original!C55 -> 29.510005 | E24: =$C24*Original!D55 -> 13.122117 | F24: =$C24*Original!E55 -> 0 | G24: =$C24*Original!F55 -> 0 | H24: =$C24*Original!G55 -> 0 | I24: =$C24*Original!H55 -> 0 | J24: =$C24*Original!I55 -> 0.68672602 | L24: NGA | M24: =N5*BldgArea!$K$47 -> 48.971147 | N24: =$M24*Original!C55 -> 33.360509 | O24: =$M24*Original!D55 -> 14.834307 | P24: =$M24*Original!E55 -> 0 | Q24: =$M24*Original!F55 -> 0 | R24: =$M24*Original!G55 -> 0 | S24: =$M24*Original!H55 -> 0 | T24: =$M24*Original!I55 -> 0.77633092 | V24: NGA | W24: =X5*BldgArea!$S$47 -> 50.477121 | X24: =$W24*Original!C55 -> 34.38642 | Y24: =$W24*Original!D55 -> 15.290496 | Z24: =$W24*Original!E55 -> 0 | AA24: =$W24*Original!F55 -> 0 | AB24: =$W24*Original!G55 -> 0 | AC24: =$W24*Original!H55 -> 0 | AD24: =$W24*Original!I55 -> 0.80020485
B25: DSL | C25: =D6*BldgArea!$C$47 -> 16.049469 | D25: =$C25*Original!C56 -> 12.124875 | E25: =$C25*Original!D56 -> 3.9245876 | F25: =$C25*Original!E56 -> 0 | G25: =$C25*Original!F56 -> 0 | H25: =$C25*Original!G56 -> 0 | I25: =$C25*Original!H56 -> 6.2268399e-06 | J25: =$C25*Original!I56 -> 0 | L25: DSL | M25: =N6*BldgArea!$K$47 -> 10.51208 | N25: =$M25*Original!C56 -> 7.9415496 | O25: =$M25*Original!D56 -> 2.570526 | P25: =$M25*Original!E56 -> 0 | Q25: =$M25*Original!F56 -> 0 | R25: =$M25*Original!G56 -> 0 | S25: =$M25*Original!H56 -> 4.078455e-06 | T25: =$M25*Original!I56 -> 0 | V25: DSL | W25: =X6*BldgArea!$S$47 -> 5.7395579 | X25: =$W25*Original!C56 -> 4.3360577 | Y25: =$W25*Original!D56 -> 1.403498 | Z25: =$W25*Original!E56 -> 0 | AA25: =$W25*Original!F56 -> 0 | AB25: =$W25*Original!G56 -> 0 | AC25: =$W25*Original!H56 -> 2.2268218e-06 | AD25: =$W25*Original!I56 -> 0
B26: STM | C26: =D7*BldgArea!$C$47 -> 1.9018254 | D26: =$C26*Original!C57 -> 1.3356089 | E26: =$C26*Original!D57 -> 0.56621649 | F26: =$C26*Original!E57 -> 0 | G26: =$C26*Original!F57 -> 0 | H26: =$C26*Original!G57 -> 0 | I26: =$C26*Original!H57 -> 0 | J26: =$C26*Original!I57 -> 0 | L26: STM | M26: =N7*BldgArea!$K$47 -> 1.8923903 | N26: =$M26*Original!C57 -> 1.3289829 | O26: =$M26*Original!D57 -> 0.56340746 | P26: =$M26*Original!E57 -> 0 | Q26: =$M26*Original!F57 -> 0 | R26: =$M26*Original!G57 -> 0 | S26: =$M26*Original!H57 -> 0 | T26: =$M26*Original!I57 -> 0 | V26: STM | W26: =X7*BldgArea!$S$47 -> 1.7371011 | X26: =$W26*Original!C57 -> 1.2199267 | Y26: =$W26*Original!D57 -> 0.51717432 | Z26: =$W26*Original!E57 -> 0 | AA26: =$W26*Original!F57 -> 0 | AB26: =$W26*Original!G57 -> 0 | AC26: =$W26*Original!H57 -> 0 | AD26: =$W26*Original!I57 -> 0
D27: =SUM(D23:D26) -> 43.771861 | E27: =SUM(E23:E26) -> 17.973057 | F27: =SUM(F23:F26) -> 2.3836409 | G27: =SUM(G23:G26) -> 3.7720757 | H27: =SUM(H23:H26) -> 7.603498 | I27: =SUM(I23:I26) -> 6.2268399e-06 | J27: =SUM(J23:J26) -> 0.68672602 | N27: =SUM(N23:N26) -> 43.405601 | O27: =SUM(O23:O26) -> 18.316328 | P27: =SUM(P23:P26) -> 2.3038908 | Q27: =SUM(Q23:Q26) -> 3.6458724 | R27: =SUM(R23:R26) -> 7.3491058 | S27: =SUM(S23:S26) -> 4.078455e-06 | T27: =SUM(T23:T26) -> 0.77633092 | X27: =SUM(X23:X26) -> 40.675434 | Y27: =SUM(Y23:Y26) -> 17.540592 | Z27: =SUM(Z23:Z26) -> 2.1803626 | AA27: =SUM(AA23:AA26) -> 3.4503909 | AB27: =SUM(AB23:AB26) -> 6.9550672 | AC27: =SUM(AC23:AC26) -> 2.2268218e-06 | AD27: =SUM(AD23:AD26) -> 0.80020485
C28: Queens | D28: Space Heating | E28: DHW | F28: Space Cooling | G28: Lighting | H28: Other ELC | I28: Other DSL | J28: Other NGA | M28: Queens | N28: Space Heating | O28: DHW | P28: Space Cooling | Q28: Lighting | R28: Other ELC | S28: Other DSL | T28: Other NGA | W28: Queens | X28: Space Heating | Y28: DHW | Z28: Space Cooling | AA28: Lighting | AB28: Other ELC | AC28: Other DSL | AD28: Other NGA
B29: ELC | C29: =D4*BldgArea!$C$48 -> 14.252015 | D29: =$C29*Original!C54 -> 0.76545563 | E29: =$C29*Original!D54 -> 0.34399585 | F29: =$C29*Original!E54 -> 2.2768125 | G29: =$C29*Original!F54 -> 3.6030214 | H29: =$C29*Original!G54 -> 7.2627296 | I29: =$C29*Original!H54 -> 0 | J29: =$C29*Original!I54 -> 0 | L29: ELC | M29: =N4*BldgArea!$K$48 -> 13.818838 | N29: =$M29*Original!C54 -> 0.74219031 | O29: =$M29*Original!D54 -> 0.33354042 | P29: =$M29*Original!E54 -> 2.2076109 | Q29: =$M29*Original!F54 -> 3.4935109 | R29: =$M29*Original!G54 -> 7.0419856 | S29: =$M29*Original!H54 -> 0 | T29: =$M29*Original!I54 -> 0 | V29: ELC | W29: =X4*BldgArea!$S$48 -> 12.605884 | X29: =$W29*Original!C54 -> 0.67704423 | Y29: =$W29*Original!D54 -> 0.30426376 | Z29: =$W29*Original!E54 -> 2.0138369 | AA29: =$W29*Original!F54 -> 3.1868665 | AB29: =$W29*Original!G54 -> 6.4238723 | AC29: =$W29*Original!H54 -> 0 | AD29: =$W29*Original!I54 -> 0
B30: NGA | C30: =D5*BldgArea!$C$48 -> 41.377413 | D30: =$C30*Original!C55 -> 28.187446 | E30: =$C30*Original!D55 -> 12.534018 | F30: =$C30*Original!E55 -> 0 | G30: =$C30*Original!F55 -> 0 | H30: =$C30*Original!G55 -> 0 | I30: =$C30*Original!H55 -> 0 | J30: =$C30*Original!I55 -> 0.6559488 | L30: NGA | M30: =N5*BldgArea!$K$48 -> 46.924636 | N30: =$M30*Original!C55 -> 31.966369 | O30: =$M30*Original!D55 -> 14.214379 | P30: =$M30*Original!E55 -> 0 | Q30: =$M30*Original!F55 -> 0 | R30: =$M30*Original!G55 -> 0 | S30: =$M30*Original!H55 -> 0 | T30: =$M30*Original!I55 -> 0.74388794 | V30: NGA | W30: =X5*BldgArea!$S$48 -> 46.621918 | X30: =$W30*Original!C55 -> 31.760149 | Y30: =$W30*Original!D55 -> 14.12268 | Z30: =$W30*Original!E55 -> 0 | AA30: =$W30*Original!F55 -> 0 | AB30: =$W30*Original!G55 -> 0 | AC30: =$W30*Original!H55 -> 0 | AD30: =$W30*Original!I55 -> 0.739089
B31: DSL | C31: =D6*BldgArea!$C$48 -> 15.330175 | D31: =$C31*Original!C56 -> 11.581471 | E31: =$C31*Original!D56 -> 3.7486981 | F31: =$C31*Original!E56 -> 0 | G31: =$C31*Original!F56 -> 0 | H31: =$C31*Original!G56 -> 0 | I31: =$C31*Original!H56 -> 5.9477696e-06 | J31: =$C31*Original!I56 -> 0 | L31: DSL | M31: =N6*BldgArea!$K$48 -> 10.072778 | N31: =$M31*Original!C56 -> 7.6096711 | O31: =$M31*Original!D56 -> 2.4631033 | P31: =$M31*Original!E56 -> 0 | Q31: =$M31*Original!F56 -> 0 | R31: =$M31*Original!G56 -> 0 | S31: =$M31*Original!H56 -> 3.9080158e-06 | T31: =$M31*Original!I56 -> 0 | V31: DSL | W31: =X6*BldgArea!$S$48 -> 5.3011978 | X31: =$W31*Original!C56 -> 4.0048902 | Y31: =$W31*Original!D56 -> 1.2963055 | Z31: =$W31*Original!E56 -> 0 | AA31: =$W31*Original!F56 -> 0 | AB31: =$W31*Original!G56 -> 0 | AC31: =$W31*Original!H56 -> 2.0567478e-06 | AD31: =$W31*Original!I56 -> 0
B32: STM | C32: =D7*BldgArea!$C$48 -> 1.8165907 | D32: =$C32*Original!C57 -> 1.2757505 | E32: =$C32*Original!D57 -> 0.54084018 | F32: =$C32*Original!E57 -> 0 | G32: =$C32*Original!F57 -> 0 | H32: =$C32*Original!G57 -> 0 | I32: =$C32*Original!H57 -> 0 | J32: =$C32*Original!I57 -> 0 | L32: STM | M32: =N7*BldgArea!$K$48 -> 1.8133071 | N32: =$M32*Original!C57 -> 1.2734445 | O32: =$M32*Original!D57 -> 0.53986258 | P32: =$M32*Original!E57 -> 0 | Q32: =$M32*Original!F57 -> 0 | R32: =$M32*Original!G57 -> 0 | S32: =$M32*Original!H57 -> 0 | T32: =$M32*Original!I57 -> 0 | V32: STM | W32: =X7*BldgArea!$S$48 -> 1.6044295 | X32: =$W32*Original!C57 -> 1.1267545 | Y32: =$W32*Original!D57 -> 0.47767501 | Z32: =$W32*Original!E57 -> 0 | AA32: =$W32*Original!F57 -> 0 | AB32: =$W32*Original!G57 -> 0 | AC32: =$W32*Original!H57 -> 0 | AD32: =$W32*Original!I57 -> 0
D33: =SUM(D29:D32) -> 41.810123 | E33: =SUM(E29:E32) -> 17.167553 | F33: =SUM(F29:F32) -> 2.2768125 | G33: =SUM(G29:G32) -> 3.6030214 | H33: =SUM(H29:H32) -> 7.2627296 | I33: =SUM(I29:I32) -> 5.9477696e-06 | J33: =SUM(J29:J32) -> 0.6559488 | N33: =SUM(N29:N32) -> 41.591675 | O33: =SUM(O29:O32) -> 17.550886 | P33: =SUM(P29:P32) -> 2.2076109 | Q33: =SUM(Q29:Q32) -> 3.4935109 | R33: =SUM(R29:R32) -> 7.0419856 | S33: =SUM(S29:S32) -> 3.9080158e-06 | T33: =SUM(T29:T32) -> 0.74388794 | X33: =SUM(X29:X32) -> 37.568838 | Y33: =SUM(Y29:Y32) -> 16.200925 | Z33: =SUM(Z29:Z32) -> 2.0138369 | AA33: =SUM(AA29:AA32) -> 3.1868665 | AB33: =SUM(AB29:AB32) -> 6.4238723 | AC33: =SUM(AC29:AC32) -> 2.0567478e-06 | AD33: =SUM(AD29:AD32) -> 0.739089
C34: Staten island | D34: Space Heating | E34: DHW | F34: Space Cooling | G34: Lighting | H34: Other ELC | I34: Other DSL | J34: Other NGA | M34: Staten island | N34: Space Heating | O34: DHW | P34: Space Cooling | Q34: Lighting | R34: Other ELC | S34: Other DSL | T34: Other NGA | W34: Staten island | X34: Space Heating | Y34: DHW | Z34: Space Cooling | AA34: Lighting | AB34: Other ELC | AC34: Other DSL | AD34: Other NGA
B35: ELC | C35: =D4*BldgArea!$C$49 -> 3.7829334 | D35: =$C35*Original!C54 -> 0.20317602 | E35: =$C35*Original!D54 -> 0.091307329 | F35: =$C35*Original!E54 -> 0.60433771 | G35: =$C35*Original!F54 -> 0.95635531 | H35: =$C35*Original!G54 -> 1.9277571 | I35: =$C35*Original!H54 -> 0 | J35: =$C35*Original!I54 -> 0 | L35: ELC | M35: =N4*BldgArea!$K$49 -> 3.6598075 | N35: =$M35*Original!C54 -> 0.1965631 | O35: =$M35*Original!D54 -> 0.088335481 | P35: =$M35*Original!E54 -> 0.58466788 | Q35: =$M35*Original!F54 -> 0.92522809 | R35: =$M35*Original!G54 -> 1.8650129 | S35: =$M35*Original!H54 -> 0 | T35: =$M35*Original!I54 -> 0 | V35: ELC | W35: =X4*BldgArea!$S$49 -> 3.1765649 | X35: =$W35*Original!C54 -> 0.17060882 | Y35: =$W35*Original!D54 -> 0.076671627 | Z35: =$W35*Original!E54 -> 0.50746808 | AA35: =$W35*Original!F54 -> 0.80306058 | AB35: =$W35*Original!G54 -> 1.6187558 | AC35: =$W35*Original!H54 -> 0 | AD35: =$W35*Original!I54 -> 0
B36: NGA | C36: =D5*BldgArea!$C$49 -> 10.982868 | D36: =$C36*Original!C55 -> 7.4818356 | E36: =$C36*Original!D55 -> 3.3269231 | F36: =$C36*Original!E55 -> 0 | G36: =$C36*Original!F55 -> 0 | H36: =$C36*Original!G55 -> 0 | I36: =$C36*Original!H55 -> 0 | J36: =$C36*Original!I55 -> 0.17410946 | L36: NGA | M36: =N5*BldgArea!$K$49 -> 12.42761 | N36: =$M36*Original!C55 -> 8.4660341 | O36: =$M36*Original!D55 -> 3.7645634 | P36: =$M36*Original!E55 -> 0 | Q36: =$M36*Original!F55 -> 0 | R36: =$M36*Original!G55 -> 0 | S36: =$M36*Original!H55 -> 0 | T36: =$M36*Original!I55 -> 0.1970127 | V36: NGA | W36: =X5*BldgArea!$S$49 -> 11.748288 | X36: =$W36*Original!C55 -> 8.0032609 | Y36: =$W36*Original!D55 -> 3.5587835 | Z36: =$W36*Original!E55 -> 0 | AA36: =$W36*Original!F55 -> 0 | AB36: =$W36*Original!G55 -> 0 | AC36: =$W36*Original!H55 -> 0 | AD36: =$W36*Original!I55 -> 0.18624353
B37: DSL | C37: =D6*BldgArea!$C$49 -> 4.069111 | D37: =$C37*Original!C56 -> 3.074087 | E37: =$C37*Original!D56 -> 0.99502249 | F37: =$C37*Original!E56 -> 0 | G37: =$C37*Original!F56 -> 0 | H37: =$C37*Original!G56 -> 0 | I37: =$C37*Original!H56 -> 1.5787253e-06 | J37: =$C37*Original!I56 -> 0 | L37: DSL | M37: =N6*BldgArea!$K$49 -> 2.6676938 | N37: =$M37*Original!C56 -> 2.0153598 | O37: =$M37*Original!D56 -> 0.65233299 | P37: =$M37*Original!E56 -> 0 | Q37: =$M37*Original!F56 -> 0 | R37: =$M37*Original!G56 -> 0 | S37: =$M37*Original!H56 -> 1.0350063e-06 | T37: =$M37*Original!I56 -> 0 | V37: DSL | W37: =X6*BldgArea!$S$49 -> 1.3358523 | X37: =$W37*Original!C56 -> 1.0091949 | Y37: =$W37*Original!D56 -> 0.32665688 | Z37: =$W37*Original!E56 -> 0 | AA37: =$W37*Original!F56 -> 0 | AB37: =$W37*Original!G56 -> 0 | AC37: =$W37*Original!H56 -> 5.1828123e-07 | AD37: =$W37*Original!I56 -> 0
B38: STM | C38: =D7*BldgArea!$C$49 -> 0.48218035 | D38: =$C38*Original!C57 -> 0.33862434 | E38: =$C38*Original!D57 -> 0.14355601 | F38: =$C38*Original!E57 -> 0 | G38: =$C38*Original!F57 -> 0 | H38: =$C38*Original!G57 -> 0 | I38: =$C38*Original!H57 -> 0 | J38: =$C38*Original!I57 -> 0 | L38: STM | M38: =N7*BldgArea!$K$49 -> 0.48023971 | N38: =$M38*Original!C57 -> 0.33726147 | O38: =$M38*Original!D57 -> 0.14297824 | P38: =$M38*Original!E57 -> 0 | Q38: =$M38*Original!F57 -> 0 | R38: =$M38*Original!G57 -> 0 | S38: =$M38*Original!H57 -> 0 | T38: =$M38*Original!I57 -> 0 | V38: STM | W38: =X7*BldgArea!$S$49 -> 0.40430126 | X38: =$W38*Original!C57 -> 0.28393162 | Y38: =$W38*Original!D57 -> 0.12036964 | Z38: =$W38*Original!E57 -> 0 | AA38: =$W38*Original!F57 -> 0 | AB38: =$W38*Original!G57 -> 0 | AC38: =$W38*Original!H57 -> 0 | AD38: =$W38*Original!I57 -> 0
D39: =SUM(D35:D38) -> 11.097723 | E39: =SUM(E35:E38) -> 4.5568089 | F39: =SUM(F35:F38) -> 0.60433771 | G39: =SUM(G35:G38) -> 0.95635531 | H39: =SUM(H35:H38) -> 1.9277571 | I39: =SUM(I35:I38) -> 1.5787253e-06 | J39: =SUM(J35:J38) -> 0.17410946 | N39: =SUM(N35:N38) -> 11.015218 | O39: =SUM(O35:O38) -> 4.6482101 | P39: =SUM(P35:P38) -> 0.58466788 | Q39: =SUM(Q35:Q38) -> 0.92522809 | R39: =SUM(R35:R38) -> 1.8650129 | S39: =SUM(S35:S38) -> 1.0350063e-06 | T39: =SUM(T35:T38) -> 0.1970127 | X39: =SUM(X35:X38) -> 9.4669962 | Y39: =SUM(Y35:Y38) -> 4.0824817 | Z39: =SUM(Z35:Z38) -> 0.50746808 | AA39: =SUM(AA35:AA38) -> 0.80306058 | AB39: =SUM(AB35:AB38) -> 1.6187558 | AC39: =SUM(AC35:AC38) -> 5.1828123e-07 | AD39: =SUM(AD35:AD38) -> 0.18624353
C40: NYC | D40: Space Heating | E40: DHW | F40: Space Cooling | G40: Lighting | H40: Other ELC | I40: Other DSL | J40: Other NGA | M40: NYC | N40: Space Heating | O40: DHW | P40: Space Cooling | Q40: Lighting | R40: Other ELC | S40: Other DSL | T40: Other NGA | W40: NYC | X40: Space Heating | Y40: DHW | Z40: Space Cooling | AA40: Lighting | AB40: Other ELC | AC40: Other DSL | AD40: Other NGA
B41: ELC | C41: =C17+C11+C23+C29+C35 -> 58.483486 | D41: =D17+D11+D23+D29+D35 -> 3.1410656 | E41: =E17+E11+E23+E29+E35 -> 1.4115953 | F41: =F17+F11+F23+F29+F35 -> 9.3429548 | G41: =G17+G11+G23+G29+G35 -> 14.785085 | H41: =H17+H11+H23+H29+H35 -> 29.802786 | I41: =I17+I11+I23+I29+I35 -> 0 | J41: =J17+J11+J23+J29+J35 -> 0 | L41: ELC | M41: =M17+M11+M23+M29+M35 -> 56.537463 | N41: =N17+N11+N23+N29+N35 -> 3.0365474 | O41: =O17+O11+O23+O29+O35 -> 1.3646248 | P41: =P17+P11+P23+P29+P35 -> 9.0320703 | Q41: =Q17+Q11+Q23+Q29+Q35 -> 14.293115 | R41: =R17+R11+R23+R29+R35 -> 28.811105 | S41: =S17+S11+S23+S29+S35 -> 0 | T41: =T17+T11+T23+T29+T35 -> 0 | V41: ELC | W41: =W17+W11+W23+W29+W35 -> 52.47592 | X41: =X17+X11+X23+X29+X35 -> 2.8184077 | Y41: =Y17+Y11+Y23+Y29+Y35 -> 1.2665928 | Z41: =Z17+Z11+Z23+Z29+Z35 -> 8.3832237 | AA41: =AA17+AA11+AA23+AA29+AA35 -> 13.266325 | AB41: =AB17+AB11+AB23+AB29+AB35 -> 26.741371 | AC41: =AC17+AC11+AC23+AC29+AC35 -> 0 | AD41: =AD17+AD11+AD23+AD29+AD35 -> 0
B42: NGA | C42: =C18+C12+C24+C30+C36 -> 169.79321 | D42: =D18+D12+D24+D30+D36 -> 115.66786 | E42: =E18+E12+E24+E30+E36 -> 51.433646 | F42: =F18+F12+F24+F30+F36 -> 0 | G42: =G18+G12+G24+G30+G36 -> 0 | H42: =H18+H12+H24+H30+H36 -> 0 | I42: =I18+I12+I24+I30+I36 -> 0 | J42: =J18+J12+J24+J30+J36 -> 2.6917017 | L42: NGA | M42: =M18+M12+M24+M30+M36 -> 191.98429 | N42: =N18+N12+N24+N30+N36 -> 130.78505 | O42: =O18+O12+O24+O30+O36 -> 58.155754 | P42: =P18+P12+P24+P30+P36 -> 0 | Q42: =Q18+Q12+Q24+Q30+Q36 -> 0 | R42: =R18+R12+R24+R30+R36 -> 0 | S42: =S18+S12+S24+S30+S36 -> 0 | T42: =T18+T12+T24+T30+T36 -> 3.043493 | V42: NGA | W42: =W18+W12+W24+W30+W36 -> 194.07827 | X42: =X18+X12+X24+X30+X36 -> 132.21152 | Y42: =Y18+Y12+Y24+Y30+Y36 -> 58.790059 | Z42: =Z18+Z12+Z24+Z30+Z36 -> 0 | AA42: =AA18+AA12+AA24+AA30+AA36 -> 0 | AB42: =AB18+AB12+AB24+AB30+AB36 -> 0 | AC42: =AC18+AC12+AC24+AC30+AC36 -> 0 | AD42: =AD18+AD12+AD24+AD30+AD36 -> 3.0766884
B43: DSL | C43: =C19+C13+C25+C31+C37 -> 62.907741 | D43: =D19+D13+D25+D31+D37 -> 47.524844 | E43: =E19+E13+E25+E31+E37 -> 15.382873 | F43: =F19+F13+F25+F31+F37 -> 0 | G43: =G19+G13+G25+G31+G37 -> 0 | H43: =H19+H13+H25+H31+H37 -> 0 | I43: =I19+I13+I25+I31+I37 -> 2.4406816e-05 | J43: =J19+J13+J25+J31+J37 -> 0 | L43: DSL | M43: =M19+M13+M25+M31+M37 -> 41.211086 | N43: =N19+N13+N25+N31+N37 -> 31.133695 | O43: =O19+O13+O25+O31+O37 -> 10.077375 | P43: =P19+P13+P25+P31+P37 -> 0 | Q43: =Q19+Q13+Q25+Q31+Q37 -> 0 | R43: =R19+R13+R25+R31+R37 -> 0 | S43: =S19+S13+S25+S31+S37 -> 1.5988992e-05 | T43: =T19+T13+T25+T31+T37 -> 0 | V43: DSL | W43: =W19+W13+W25+W31+W37 -> 22.067888 | X43: =X19+X13+X25+X31+X37 -> 16.671604 | Y43: =Y19+Y13+Y25+Y31+Y37 -> 5.3962757 | Z43: =Z19+Z13+Z25+Z31+Z37 -> 0 | AA43: =AA19+AA13+AA25+AA31+AA37 -> 0 | AB43: =AB19+AB13+AB25+AB31+AB37 -> 0 | AC43: =AC19+AC13+AC25+AC31+AC37 -> 8.5618537e-06 | AD43: =AD19+AD13+AD25+AD31+AD37 -> 0
B44: STM | C44: =C20+C14+C26+C32+C38 -> 7.4544235 | D44: =D20+D14+D26+D32+D38 -> 5.2350728 | E44: =E20+E14+E26+E32+E38 -> 2.2193507 | F44: =F20+F14+F26+F32+F38 -> 0 | G44: =G20+G14+G26+G32+G38 -> 0 | H44: =H20+H14+H26+H32+H38 -> 0 | I44: =I20+I14+I26+I32+I38 -> 0 | J44: =J20+J14+J26+J32+J38 -> 0 | L44: STM | M44: =M20+M14+M26+M32+M38 -> 7.4188424 | N44: =N20+N14+N26+N32+N38 -> 5.210085 | O44: =O20+O14+O26+O32+O38 -> 2.2087574 | P44: =P20+P14+P26+P32+P38 -> 0 | Q44: =Q20+Q14+Q26+Q32+Q38 -> 0 | R44: =R20+R14+R26+R32+R38 -> 0 | S44: =S20+S14+S26+S32+S38 -> 0 | T44: =T20+T14+T26+T32+T38 -> 0 | V44: STM | W44: =W20+W14+W26+W32+W38 -> 6.6789381 | X44: =X20+X14+X26+X32+X38 -> 4.690467 | Y44: =Y20+Y14+Y26+Y32+Y38 -> 1.9884711 | Z44: =Z20+Z14+Z26+Z32+Z38 -> 0 | AA44: =AA20+AA14+AA26+AA32+AA38 -> 0 | AB44: =AB20+AB14+AB26+AB32+AB38 -> 0 | AC44: =AC20+AC14+AC26+AC32+AC38 -> 0 | AD44: =AD20+AD14+AD26+AD32+AD38 -> 0
D45: =SUM(D41:D44) -> 171.56885 | E45: =SUM(E41:E44) -> 70.447465 | F45: =SUM(F41:F44) -> 9.3429548 | G45: =SUM(G41:G44) -> 14.785085 | H45: =SUM(H41:H44) -> 29.802786 | I45: =SUM(I41:I44) -> 2.4406816e-05 | J45: =SUM(J41:J44) -> 2.6917017 | N45: =SUM(N41:N44) -> 170.16537 | O45: =SUM(O41:O44) -> 71.806511 | P45: =SUM(P41:P44) -> 9.0320703 | Q45: =SUM(Q41:Q44) -> 14.293115 | R45: =SUM(R41:R44) -> 28.811105 | S45: =SUM(S41:S44) -> 1.5988992e-05 | T45: =SUM(T41:T44) -> 3.043493 | X45: =SUM(X41:X44) -> 156.392 | Y45: =SUM(Y41:Y44) -> 67.441398 | Z45: =SUM(Z41:Z44) -> 8.3832237 | AA45: =SUM(AA41:AA44) -> 13.266325 | AB45: =SUM(AB41:AB44) -> 26.741371 | AC45: =SUM(AC41:AC44) -> 8.5618537e-06 | AD45: =SUM(AD41:AD44) -> 3.0766884
F47: =F44/kgs_to_pj -> 0

Sheet Resid
A1: Residential Technology Equipment Type Description File | Q1: 2010 | AF1: 2015 | AU1: 2020
A2: *Technology descriptions are from R1 off the RTEKTY14 worksheet, except for those technologies not available in R1. Those technology descriptions come from R5 | S2: Resid Total | T2: Demand Total | U2: RESID | Z2: DEMAND | AH2: Resid Total | AI2: Demand Total | AJ2: RESID | AO2: DEMAND | AW2: Resid Total | AX2: Demand Total | AY2: RESID | BD2: DEMAND
A3: *Where R5 is listed, those technologies apply to regions 5,6,7,9
B4: TechName | C4: TechDesc | D4: Units | E4: CommIN | F4: CommOUT | G4: START | H4: LIFE | I4: INVCOST | J4: EFF | K4: MA(ENT) | L4: OUT(DM) | M4: CF | N4: FIXOM | O4: DISCRATE | Q4: RESID EPAUS9r 2010 | R4: RESID EPAUS9r (%) | U4: BR | V4: BX | W4: MN | X4: SI | Y4: QN | Z4: BR | AA4: BX | AB4: MN | AC4: SI | AD4: QN | AF4: RESID EPAUS9r 2015 | AG4: RESID EPAUS9r (%) | AJ4: BR | AK4: BX | AL4: MN | AM4: SI | AN4: QN | AO4: BR | AP4: BX | AQ4: MN | AR4: SI | AS4: QN | AU4: RESID EPAUS9r 2020 | AV4: RESID EPAUS9r (%) | AY4: BR | AZ4: BX | BA4: MN | BB4: SI | BC4: QN | BD4: BR | BE4: BX | BF4: MN | BG4: SI | BH4: QN
A5: *Space Heating | T5: =SUM(T7:T58) -> 151.08046 | Z5: =CommData_DMD!E9 -> 44.265367 | AA5: =CommData_DMD!E19 -> 21.043435 | AB5: =CommData_DMD!E29 -> 37.294841 | AC5: =CommData_DMD!E39 -> 10.042388 | AD5: =CommData_DMD!E49 -> 38.55416 | AI5: =SUM(AI7:AI58) -> 150.59912 | AO5: =CommData_DMD!F9 -> 44.376666 | AP5: =CommData_DMD!F19 -> 21.513374 | AQ5: =CommData_DMD!F29 -> 39.427265 | AR5: =CommData_DMD!F39 -> 9.4413972 | AS5: =CommData_DMD!F49 -> 37.497212 | AX5: =SUM(AX7:AX58) -> 138.59306 | BD5: =CommData_DMD!G9 -> 37.391626 | BE5: =CommData_DMD!G19 -> 18.251944 | BF5: =CommData_DMD!G29 -> 31.917949 | BG5: =CommData_DMD!G39 -> 7.5394413 | BH5: =CommData_DMD!G49 -> 30.714713
A6: ELC | M6: =M8 -> 0.16 | Q6: =SUM(Q7:Q23) -> 165.61918 | R6: =A6 -> ELC | S6: ='Fuel Share'!D41 -> 3.1410656 | Z6: =SUM(Z8:Z54) -> 39.385665 | AA6: =SUM(AA8:AA54) -> 18.72366 | AB6: =SUM(AB8:AB54) -> 33.183551 | AC6: =SUM(AC8:AC54) -> 8.9353406 | AD6: =SUM(AD8:AD54) -> 34.304046 | AF6: =SUM(AF7:AF23) -> 226.90598 | AG6: ELC | AH6: ='Fuel Share'!N41 -> 3.0365474 | AO6: =SUM(AO8:AO54) -> 39.492483 | AP6: =SUM(AP8:AP54) -> 19.14557 | AQ6: =SUM(AQ8:AQ54) -> 35.087823 | AR6: =SUM(AR8:AR54) -> 8.4022586 | AS6: =SUM(AS8:AS54) -> 33.370196 | AU6: =SUM(AU7:AU23) -> 288.19279 | AV6: ELC | AW6: ='Fuel Share'!X41 -> 2.8184077 | BD6: =SUM(BD7:BD58) -> 33.365716 | BE6: =SUM(BE7:BE58) -> 16.28678 | BF6: =SUM(BF7:BF58) -> 43.403525 | BG6: =SUM(BG7:BG58) -> 6.727679 | BH6: =SUM(BH7:BH58) -> 27.407698
A7: *Electric Radiant
A8: R1,R2,R3,R4,R5,R6 | B8: RSHERDBS05 | C8: Electric Radiant Base.RSH.ELC.05 | D8: PJ | E8: RESELC | F8: RSH | G8: 2005 | H8: 20 | J8: 1 | K8: 1 | L8: 1 | M8: 0.16 | O8: 0.18
A9: R1,R2,R3,R4,R5,R6 | B9: RSHERDV110 | C9: Electric Radiant Ver1.RSH.ELC.10 | D9: PJ | E9: RESELC | F9: RSH | G9: 2010 | H9: 20 | I9: 3.7369871 | J9: 1 | K9: 1 | L9: 1 | M9: 0.16 | O9: 0.18 | Q9: =RECS!T5 -> 135.05002 | R9: =Q9/$Q$6 -> 0.81542505 | S9: =S6*$R$9*$J$9/$M$9 -> 16.008147 | T9: =S9*$M$9 -> 2.5613036 | U9: =$S9*Z$5/$T$5 -> 4.6902592 | V9: =$S9*AA$5/$T$5 -> 2.2297152 | W9: =$S9*AB$5/$T$5 -> 3.9516778 | X9: =$S9*AC$5/$T$5 -> 1.064069 | Y9: =$S9*AD$5/$T$5 -> 4.0851125 | Z9: =$T9*Z5/$T$5 -> 0.75044147 | AA9: =$T9*AA5/$T$5 -> 0.35675444 | AB9: =$T9*AB5/$T$5 -> 0.63226845 | AC9: =$T9*AC5/$T$5 -> 0.17025103 | AD9: =$T9*AD5/$T$5 -> 0.65361799 | AF9: =RECS!U5 -> 140.77382 | AG9: =AF9/$AF$6 -> 0.62040595 | AH9: =AH6*$AG$9*$J$9/$M$9 -> 11.774326 | AI9: =AH9*$M$9 -> 1.8838921 | AJ9: =$AH9*AO$5/$AI$5 -> 3.4695111 | AK9: =$AH9*AP$5/$AI$5 -> 1.6819851 | AL9: =$AH9*AQ$5/$AI$5 -> 3.0825509 | AM9: =$AH9*AR$5/$AI$5 -> 0.73815893 | AN9: =$AH9*AS$5/$AI$5 -> 2.9316531 | AO9: =$AI9*AO5/$AI$5 -> 0.55512177 | AP9: =$AI9*AP5/$AI$5 -> 0.26911761 | AQ9: =$AI9*AQ5/$AI$5 -> 0.49320815 | AR9: =$AI9*AR5/$AI$5 -> 0.11810543 | AS9: =$AI9*AS5/$AI$5 -> 0.4690645 | AU9: =RECS!V5 -> 146.49762 | AV9: =AU9/$AU$6 -> 0.50833201 | AW9: =AW6*$AV$9*$J$9/$M$9 -> 8.9542927 | AX9: =AW9*$M$9 -> 1.4326868 | AY9: =$AW9*BD$5/$AX$5 -> 2.4158177 | AZ9: =$AW9*BE$5/$AX$5 -> 1.1792311 | BA9: =$AW9*BF$5/$AX$5 -> 2.0621716 | BB9: =$AW9*BG$5/$AX$5 -> 0.48711217 | BC9: =$AW9*BH$5/$AX$5 -> 1.9844322 | BD9: =$AX9*BD5/$AX$5 -> 0.38653083 | BE9: =$AX9*BE5/$AX$5 -> 0.18867698 | BF9: =$AX9*BF5/$AX$5 -> 0.32994745 | BG9: =$AX9*BG5/$AX$5 -> 0.077937947 | BH9: =$AX9*BH5/$AX$5 -> 0.31750916
A10: *Electric Heat Pump
A11: R1,R2,R3,R4,R5,R6 | B11: RSHEHPBS05 | C11: Electric Heat Pump Base.RSH.ELC.05 | D11: PJ | E11: RESELC | F11: RSH | G11: 2005 | H11: 15 | J11: 2.2657 | K11: 1 | L11: 1 | M11: 0.16 | O11: 0.18
A12: R1,R2,R3,R4,R5,R6 | B12: RSHEHPV110 | C12: Electric Heat Pump Ver1.RSH.ELC.10 | D12: PJ | E12: RESELC | F12: RSH | G12: 2010 | H12: 15 | I12: 6.5561178 | J12: 2.26 | K12: 1 | L12: 1 | M12: 0.16 | O12: 0.18 | Q12: =RECS!T6 -> 30.56915 | R12: =Q12/$Q$6 -> 0.18457495 | S12: =S6*$R$12*$J$12/$M$12 -> 8.1891384 | T12: =S12*$M$12 -> 1.3102621 | U12: =$S12*Z$5/$T$5 -> 2.3993521 | V12: =$S12*AA$5/$T$5 -> 1.1406346 | W12: =$S12*AB$5/$T$5 -> 2.0215229 | X12: =$S12*AC$5/$T$5 -> 0.54433582 | Y12: =$S12*AD$5/$T$5 -> 2.0897828 | Z12: =$T12*Z$5/$T$5 -> 0.38389634 | AA12: =$T12*AA5/$T$5 -> 0.18250154 | AB12: =$T12*AB5/$T$5 -> 0.32344367 | AC12: =$T12*AC5/$T$5 -> 0.087093731 | AD12: =$T12*AD5/$T$5 -> 0.33436525 | AF12: =RECS!U6 -> 86.13216 | AG12: =AF12/$AF$6 -> 0.37959405 | AH12: =AH6*$AG$12*$J$12/$M$12 -> 16.281256 | AI12: =AH12*$M$12 -> 2.605001 | AJ12: =$AH12*AO$5/$AI$5 -> 4.7975571 | AK12: =$AH12*AP$5/$AI$5 -> 2.3258088 | AL12: =$AH12*AQ$5/$AI$5 -> 4.2624779 | AM12: =$AH12*AR$5/$AI$5 -> 1.0207086 | AN12: =$AH12*AS$5/$AI$5 -> 4.05382 | AO12: =$AI12*AO$5/$AI$5 -> 0.76760914 | AP12: =$AI12*AP$5/$AI$5 -> 0.37212941 | AQ12: =$AI12*AQ$5/$AI$5 -> 0.68199646 | AR12: =$AI12*AR$5/$AI$5 -> 0.16331337 | AS12: =$AI12*AS$5/$AI$5 -> 0.6486112 | AU12: =RECS!V6 -> 141.69517 | AV12: =AU12/$AU$6 -> 0.49166799 | AW12: =AW6*$AV$12*$J$12/$M$12 -> 19.573307 | AX12: =AW12*$M$12 -> 3.1317291 | AY12: =$AW12*BD$5/$AX$5 -> 5.2807679 | AZ12: =$AW12*BE$5/$AX$5 -> 2.5776969 | BA12: =$AW12*BF$5/$AX$5 -> 4.5077281 | BB12: =$AW12*BG$5/$AX$5 -> 1.0647849 | BC12: =$AW12*BH$5/$AX$5 -> 4.3377966 | BD12: =$AX12*BD$5/$AX$5 -> 0.84492286 | BE12: =$AX12*BE$5/$AX$5 -> 0.41243151 | BF12: =$AX12*BF$5/$AX$5 -> 0.7212365 | BG12: =$AX12*BG$5/$AX$5 -> 0.17036559 | BH12: =$AX12*BH$5/$AX$5 -> 0.69404746
A13: R1,R2,R3,R4,R5,R6 | B13: RSHEHPV115 | C13: Electric Heat Pump Ver1.RSH.ELC.15 | D13: PJ | E13: RESELC | F13: RSH | G13: 2015 | H13: 15 | I13: 6.7609965 | J13: 2.4 | K13: 1 | L13: 1 | M13: 0.16 | O13: 0.18
A14: R1,R2,R3,R4,R5,R6 | B14: RSHEHPV210 | C14: Electric Heat Pump Ver2.RSH.ELC.10 | D14: PJ | E14: RESELC | F14: RSH | G14: 2010 | H14: 15 | I14: 8.8097833 | J14: 2.4 | K14: 1 | L14: 1 | M14: 0.16 | O14: 0.18
A15: R1,R2,R3,R4,R5,R6 | B15: RSHEHPV215 | C15: Electric Heat Pump Ver2.RSH.ELC.15 | D15: PJ | E15: RESELC | F15: RSH | G15: 2015 | H15: 15 | I15: 9.3561264 | J15: 2.58 | K15: 1 | L15: 1 | M15: 0.16 | O15: 0.18
A16: R1,R2,R3,R4,R5,R6 | B16: RSHEHPV310 | C16: Electric Heat Pump Ver3.RSH.ELC.10 | D16: PJ | E16: RESELC | F16: RSH | G16: 2010 | H16: 15 | I16: 9.7658838 | J16: 2.49 | K16: 1 | L16: 1 | M16: 0.16 | O16: 0.18
A17: R1,R2,R3,R4,R5,R6 | B17: RSHEHPV315 | C17: Electric Heat Pump Ver3.RSH.ELC.15 | D17: PJ | E17: RESELC | F17: RSH | G17: 2015 | H17: 15 | I17: 9.7658838 | J17: 2.49 | K17: 1 | L17: 1 | M17: 0.16 | O17: 0.18
A18: R1,R2,R3,R4,R5,R6 | B18: RSHEHPV320 | C18: Electric Heat Pump Ver3.RSH.ELC.20 | D18: PJ | E18: RESELC | F18: RSH | G18: 2020 | H18: 15 | I18: 10.243934 | J18: 2.78 | K18: 1 | L18: 1 | M18: 0.16 | O18: 0.18
A19: R1,R2,R3,R4,R5,R6 | B19: RSHEHPV330 | C19: Electric Heat Pump Ver3.RSH.ELC.30 | D19: PJ | E19: RESELC | F19: RSH | G19: 2030 | H19: 15 | I19: 10.243934 | J19: 2.8 | K19: 1 | L19: 1 | M19: 0.16 | O19: 0.18
A20: R1,R2,R3,R4,R5,R6 | B20: RSHEHPV410 | C20: Electric Heat Pump Ver4.RSH.ELC.10 | D20: PJ | E20: RESELC | F20: RSH | G20: 2010 | H20: 15 | I20: 10.926863 | J20: 3.14 | K20: 1 | L20: 1 | M20: 0.16 | O20: 0.18
A21: R1,R2,R3,R4,R5,R6 | B21: RSHEHPV420 | C21: Electric Heat Pump Ver4.RSH.ELC.20 | D21: PJ | E21: RESELC | F21: RSH | G21: 2020 | H21: 15 | I21: 11.200035 | J21: 3.17 | K21: 1 | L21: 1 | M21: 0.16 | O21: 0.18
A22: R1,R2,R3,R4,R5,R6 | B22: RSHEHPV430 | C22: Electric Heat Pump Ver4.RSH.ELC.30 | D22: PJ | E22: RESELC | F22: RSH | G22: 2030 | H22: 15 | I22: 11.268327 | J22: 3.22 | K22: 1 | L22: 1 | M22: 0.16 | O22: 0.18
A23: R1,R2,R3,R4,R5,R6 | B23: RSHEHPV435 | C23: Electric Heat Pump Ver4.RSH.ELC.35 | D23: PJ | E23: RESELC | F23: RSH | G23: 2035 | H23: 15 | I23: 11.268327 | J23: 3.22 | K23: 1 | L23: 1 | M23: 0.16 | O23: 0.18
A24: NGA | M24: =M26 -> 0.16 | Q24: =SUM(Q25:Q37) -> 2687.6765 | R24: NGA | S24: ='Fuel Share'!D42 -> 115.66786 | AF24: =SUM(AF25:AF37) -> 2721.0301 | AH24: ='Fuel Share'!N42 -> 130.78505 | AU24: =SUM(AU25:AU37) -> 2754.3836 | AW24: ='Fuel Share'!X42 -> 132.21152
A25: *Natural Gas Furnace
A26: R1,R2,R3,R4,R5,R6 | B26: RSHNFRBS05 | C26: Natural Gas Furnace Base.RSH.NGA.05 | D26: PJ | E26: RESNGAEA | F26: RSH | G26: 2005 | H26: 15 | J26: 0.81440002 | K26: 1 | L26: 1 | M26: 0.16 | O26: 0.18
A27: R1,R2,R3,R4,R5,R6 | B27: RSHNFRV110 | C27: Natural Gas Furnace Ver1.RSH.NGA.10 | D27: PJ | E27: RESNGAEA | F27: RSH | G27: 2010 | H27: 15 | I27: 4.9170883 | J27: 0.8 | K27: 1 | L27: 1 | M27: 0.16 | O27: 0.18 | Q27: =RECS!T7 -> 1670.1372 | R27: =Q27/$Q$24 -> 0.62140559 | S27: =S24*$R$27*$J$27/$M$27 -> 359.38328 | T27: =S24*$R$27*$J$27 -> 57.501325 | U27: =$S27*Z$5/$T$5 -> 105.29643 | V27: =$S27*AA$5/$T$5 -> 50.057159 | W27: =$S27*AB$5/$T$5 -> 88.715259 | X27: =$S27*AC$5/$T$5 -> 23.888373 | Y27: =$S27*AD$5/$T$5 -> 91.710871 | Z27: =$T27*Z$5/$T$5 -> 16.847429 | AA27: =$T27*AA$5/$T$5 -> 8.0091455 | AB27: =$T27*AB$5/$T$5 -> 14.194442 | AC27: =$T27*AC$5/$T$5 -> 3.8221397 | AD27: =$T27*AD$5/$T$5 -> 14.673739 | AF27: =RECS!U7 -> 1715.537 | AG27: =AF27/$AF$24 -> 0.63047338 | AH27: =AH24*$AG$27*$J$27/$M$27 -> 412.28245 | AI27: =AH24*$AG$27*$J$27 -> 65.965191 | AJ27: =$AH27*AO$5/$AI$5 -> 121.48624 | AK27: =$AH27*AP$5/$AI$5 -> 58.895341 | AL27: =$AH27*AQ$5/$AI$5 -> 107.93668 | AM27: =$AH27*AR$5/$AI$5 -> 25.846913 | AN27: =$AH27*AS$5/$AI$5 -> 102.65294 | AO27: =$AI27*AO$5/$AI$5 -> 19.437798 | AP27: =$AI27*AP$5/$AI$5 -> 9.4232546 | AQ27: =$AI27*AQ$5/$AI$5 -> 17.269869 | AR27: =$AI27*AR$5/$AI$5 -> 4.1355061 | AS27: =$AI27*AS$5/$AI$5 -> 16.42447 | AU27: =RECS!V7 -> 1760.9368 | AV27: =AU27/$AU$24 -> 0.63932155 | AW27: =AW24*$AV$27*$J$27/$M$27 -> 422.62837 | AX27: =AW24*$AV$27*$J$27 -> 67.620539 | AY27: =$AW27*BD$5/$AX$5 -> 114.02275 | AZ27: =$AW27*BE$5/$AX$5 -> 55.657834 | BA27: =$AW27*BF$5/$AX$5 -> 97.331217 | BB27: =$AW27*BG$5/$AX$5 -> 22.990919 | BC27: =$AW27*BH$5/$AX$5 -> 93.662044 | BD27: =$AX27*BD$5/$AX$5 -> 18.24364 | BE27: =$AX27*BE$5/$AX$5 -> 8.9052534 | BF27: =$AX27*BF$5/$AX$5 -> 15.572995 | BG27: =$AX27*BG$5/$AX$5 -> 3.6785471 | BH27: =$AX27*BH$5/$AX$5 -> 14.985927
A28: R1,R2,R3,R4,R5,R6 | B28: RSHNFRV210 | C28: Natural Gas Furnace Ver2.RSH.NGA.10 | D28: PJ | E28: RESNGAEA | F28: RSH | G28: 2010 | H28: 15 | I28: 4.9170883 | J28: 0.8 | K28: 1 | L28: 1 | M28: 0.16 | O28: 0.18
A29: R1,R2,R3,R4,R5,R6 | B29: RSHNFRV310 | C29: Natural Gas Furnace Ver3.RSH.NGA.10 | D29: PJ | E29: RESNGAEA | F29: RSH | G29: 2010 | H29: 20 | I29: 5.4087972 | J29: 0.9 | K29: 1 | L29: 1 | M29: 0.16 | O29: 0.18
A30: R1,R2,R3,R4,R5,R6 | B30: RSHNFRV410 | C30: Natural Gas Furnace Ver4.RSH.NGA.10 | D30: PJ | E30: RESNGAEA | F30: RSH | G30: 2010 | H30: 20 | I30: 6.2938731 | J30: 0.95 | K30: 1 | L30: 1 | M30: 0.16 | O30: 0.18
A31: R1,R2,R3,R4,R5,R6 | B31: RSHNFRV510 | C31: Natural Gas Furnace Ver5.RSH.NGA.10 | D31: PJ | E31: RESNGAEA | F31: RSH | G31: 2010 | H31: 20 | I31: 7.3756325 | J31: 0.98 | K31: 1 | L31: 1 | M31: 0.16 | O31: 0.18
A32: *Natural Gas Radiant
A33: R1,R2,R3,R4,R5,R6 | B33: RSHNRDBS05 | C33: Natural Gas Radiant Base.RSH.NGA.05 | D33: PJ | E33: RESNGAEA | F33: RSH | G33: 2005 | H33: 20 | J33: 0.8 | K33: 1 | L33: 1 | M33: 0.16 | O33: 0.18
A34: R1,R2,R3,R4,R5,R6 | B34: RSHNRDV110 | C34: Natural Gas Radiant Ver1.RSH.NGA.10 | D34: PJ | E34: RESNGAEA | F34: RSH | G34: 2010 | H34: 20 | I34: 6.4905566 | J34: 0.8 | K34: 1 | L34: 1 | M34: 0.16 | O34: 0.18 | Q34: =RECS!T8 -> 1017.5393 | R34: =Q34/$Q$24 -> 0.37859441 | S34: =S24*$R$34*$J$34/$M$34 -> 218.95603 | T34: =S24*$R$34*$J$34 -> 35.032965 | U34: =$S34*Z$5/$T$5 -> 64.152367 | V34: =$S34*AA$5/$T$5 -> 30.49757 | W34: =$S34*AB$5/$T$5 -> 54.050208 | X34: =$S34*AC$5/$T$5 -> 14.554109 | Y34: =$S34*AD$5/$T$5 -> 55.875298 | Z34: =$T34*Z$5/$T$5 -> 10.264379 | AA34: =$T34*AA$5/$T$5 -> 4.8796112 | AB34: =$T34*AB$5/$T$5 -> 8.6480332 | AC34: =$T34*AC$5/$T$5 -> 2.3286574 | AD34: =$T34*AD$5/$T$5 -> 8.9400477 | AF34: =RECS!U8 -> 1005.4931 | AG34: =AF34/$AF$24 -> 0.36952662 | AH34: =AH24*$AG$34*$J$34/$M$34 -> 241.64278 | AI34: =AH24*$AG$34*$J$34 -> 38.662845 | AJ34: =$AH34*AO$5/$AI$5 -> 71.204274 | AK34: =$AH34*AP$5/$AI$5 -> 34.519137 | AL34: =$AH34*AQ$5/$AI$5 -> 63.262747 | AM34: =$AH34*AR$5/$AI$5 -> 15.149129 | AN34: =$AH34*AS$5/$AI$5 -> 60.165894 | AO34: =$AI34*AO$5/$AI$5 -> 11.392684 | AP34: =$AI34*AP$5/$AI$5 -> 5.5230619 | AQ34: =$AI34*AQ$5/$AI$5 -> 10.12204 | AR34: =$AI34*AR$5/$AI$5 -> 2.4238606 | AS34: =$AI34*AS$5/$AI$5 -> 9.626543 | AU34: =RECS!V8 -> 993.44682 | AV34: =AU34/$AU$24 -> 0.36067845 | AW34: =AW24*$AV$34*$J$34/$M$34 -> 238.42923 | AX34: =AW24*$AV$34*$J$34 -> 38.148676 | AY34: =$AW34*BD$5/$AX$5 -> 64.326862 | AZ34: =$AW34*BE$5/$AX$5 -> 31.399819 | BA34: =$AW34*BF$5/$AX$5 -> 54.910197 | BB34: =$AW34*BG$5/$AX$5 -> 12.970514 | BC34: =$AW34*BH$5/$AX$5 -> 52.840203 | BD34: =$AX34*BD$5/$AX$5 -> 10.292298 | BE34: =$AX34*BE$5/$AX$5 -> 5.023971 | BF34: =$AX34*BF$5/$AX$5 -> 8.7856315 | BG34: =$AX34*BG$5/$AX$5 -> 2.0752822 | BH34: =$AX34*BH$5/$AX$5 -> 8.4544325
A35: R1,R2,R3,R4,R5,R6 | B35: RSHNRDV115 | C35: Natural Gas Radiant Ver1.RSH.NGA.15 | D35: PJ | E35: RESNGAEA | F35: RSH | G35: 2015 | H35: 20 | I35: 6.8839237 | J35: 0.82 | K35: 1 | L35: 1 | M35: 0.16 | O35: 0.18
A36: R1,R2,R3,R4,R5,R6 | B36: RSHNRDV210 | C36: Natural Gas Radiant Ver2.RSH.NGA.10 | D36: PJ | E36: RESNGAEA | F36: RSH | G36: 2010 | H36: 20 | I36: 8.3590502 | J36: 0.85 | K36: 1 | L36: 1 | M36: 0.16 | O36: 0.18
A37: R1,R2,R3,R4,R5,R6 | B37: RSHNRDV310 | C37: Natural Gas Radiant Ver3.RSH.NGA.10 | D37: PJ | E37: RESNGAEA | F37: RSH | G37: 2010 | H37: 20 | I37: 7.8673413 | J37: 0.98 | K37: 1 | L37: 1 | M37: 0.16 | O37: 0.18
A38: *Natural Gas Heat Pump
A39: R1,R2,R3,R4,R5,R6 | B39: RSHNHPBS05 | C39: Natural Gas Heat Pump Base.RSH.NGA.05 | D39: PJ | E39: RESNGAEA | F39: RSH | G39: 2005 | H39: 15 | J39: 1.3 | K39: 1 | L39: 1 | M39: 0.16 | O39: 0.18
A40: R1,R2,R3,R4,R5,R6 | B40: RSHNHPV110 | C40: Natural Gas Heat Pump Ver1.RSH.NGA.10 | D40: PJ | E40: RESNGAEA | F40: RSH | G40: 2010 | H40: 15 | I40: 12.292721 | J40: 1.3 | K40: 1 | L40: 1 | M40: 0.16 | O40: 0.18
A41: R1,R2,R3,R4,R5,R6 | B41: RSHNHPV120 | C41: Natural Gas Heat Pump Ver1.RSH.NGA.20 | D41: PJ | E41: RESNGAEA | F41: RSH | G41: 2020 | H41: 15 | I41: 12.292721 | J41: 1.4 | K41: 1 | L41: 1 | M41: 0.16 | O41: 0.18
A42: DSL | M42: =M44 -> 0.16 | Q42: =SUM(Q43:Q54) -> 1266.031 | R42: DSL | S42: ='Fuel Share'!D43 -> 47.524844 | AF42: =SUM(AF43:AF54) -> 1030.2573 | AG42: DSL | AH42: ='Fuel Share'!N43 -> 31.133695 | AU42: =SUM(AU43:AU54) -> 794.48364 | AV42: DSL | AW42: ='Fuel Share'!X43 -> 16.671604
A43: *Distillate Furnace
A44: R1,R2,R3,R4,R5,R6 | B44: RSHDFRBS05 | C44: Distillate Furnace Base.RSH.DST.05 | D44: PJ | E44: RESDSLEA | F44: RSH | G44: 2005 | H44: 20 | J44: 0.81739998 | K44: 1 | L44: 1 | M44: 0.16 | O44: 0.45
A45: R1,R2,R3,R4,R5,R6 | B45: RSHDFRV110 | C45: Distillate Furnace Ver1.RSH.DST.10 | D45: PJ | E45: RESDSLEA | F45: RSH | G45: 2010 | H45: 20 | I45: 6.3922148 | J45: =TechData_DMD!J21 -> 0.8 | K45: 1 | L45: 1 | M45: 0.16 | O45: 0.45 | Q45: =RECS!T9 -> 381.26092 | R45: =Q45/$Q$42 -> 0.3011466 | S45: =S42*$R$45*$J$45/$M$45 -> 71.559726 | T45: =S42*$R$45*$J$45 -> 11.449556 | U45: =$S45*Z$5/$T$5 -> 20.966428 | V45: =$S45*AA$5/$T$5 -> 9.9672877 | W45: =$S45*AB$5/$T$5 -> 17.664816 | X45: =$S45*AC$5/$T$5 -> 4.7566081 | Y45: =$S45*AD$5/$T$5 -> 18.261297 | Z45: =$T45*Z$5/$T$5 -> 3.3546284 | AA45: =$T45*AA$5/$T$5 -> 1.594766 | AB45: =$T45*AB$5/$T$5 -> 2.8263706 | AC45: =$T45*AC$5/$T$5 -> 0.76105729 | AD45: =$T45*AD$5/$T$5 -> 2.9218075 | AF45: =RECS!U9 -> 435.60329 | AG45: =AF45/$AF$42 -> 0.42281019 | AH45: =AH42*$AG$45*$J$45/$M$45 -> 65.818218 | AI45: =AH42*$AG$45*$J$45 -> 10.530915 | AJ45: =$AH45*AO$5/$AI$5 -> 19.39449 | AK45: =$AH45*AP$5/$AI$5 -> 9.4022592 | AL45: =$AH45*AQ$5/$AI$5 -> 17.231391 | AM45: =$AH45*AR$5/$AI$5 -> 4.126292 | AN45: =$AH45*AS$5/$AI$5 -> 16.387876 | AO45: =$AI45*AO$5/$AI$5 -> 3.1031184 | AP45: =$AI45*AP$5/$AI$5 -> 1.5043615 | AQ45: =$AI45*AQ$5/$AI$5 -> 2.7570226 | AR45: =$AI45*AR$5/$AI$5 -> 0.66020672 | AS45: =$AI45*AS$5/$AI$5 -> 2.6220601 | AU45: =RECS!V9 -> 489.94566 | AV45: =AU45/$AU$42 -> 0.61668439 | AW45: =AW42*$AV$45*$J$45/$M$45 -> 51.405589 | AX45: =AW42*$AV$45*$J$45 -> 8.2248942 | AY45: =$AW45*BD$5/$AX$5 -> 13.868938 | AZ45: =$AW45*BE$5/$AX$5 -> 6.7698336 | BA45: =$AW45*BF$5/$AX$5 -> 11.838696 | BB45: =$AW45*BG$5/$AX$5 -> 2.7964563 | BC45: =$AW45*BH$5/$AX$5 -> 11.392403 | BD45: =$AX45*BD$5/$AX$5 -> 2.2190301 | BE45: =$AX45*BE$5/$AX$5 -> 1.0831734 | BF45: =$AX45*BF$5/$AX$5 -> 1.8941913 | BG45: =$AX45*BG$5/$AX$5 -> 0.447433 | BH45: =$AX45*BH$5/$AX$5 -> 1.8227844
A46: R1,R2,R3,R4,R5,R6 | B46: RSHDFRV115 | C46: Distillate Furnace Ver1.RSH.DST.15 | D46: PJ | E46: RESDSLEA | F46: RSH | G46: 2015 | H46: 20 | I46: 6.8839237 | J46: 0.83 | K46: 1 | L46: 1 | M46: 0.16 | O46: 0.45
A47: R1,R2,R3,R4,R5,R6 | B47: RSHDFRV210 | C47: Distillate Furnace Ver2.RSH.DST.10 | D47: PJ | E47: RESDSLEA | F47: RSH | G47: 2010 | H47: 20 | I47: 9.3424678 | J47: 0.85 | K47: 1 | L47: 1 | M47: 0.16 | O47: 0.45
A48: R1,R2,R3,R4,R5,R6 | B48: RSHDFRV310 | C48: Distillate Furnace Ver3.RSH.DST.10 | D48: PJ | E48: RESDSLEA | F48: RSH | G48: 2010 | H48: 20 | I48: 9.3424678 | J48: 0.98 | K48: 1 | L48: 1 | M48: 0.16 | O48: 0.45
A49: *Distillate Radiant
A50: R1,R2,R3,R4,R5,R6 | B50: RSHDRDBS05 | C50: Distillate Radiant Base.RSH.DST.05 | D50: PJ | E50: RESDSLEA | F50: RSH | G50: 2005 | H50: 20 | J50: 0.8 | K50: 1 | L50: 1 | M50: 0.16 | O50: 0.45
A51: R1,R2,R3,R4,R5,R6 | B51: RSHDRDV110 | C51: Distillate Radiant Ver1.RSH.DST.10 | D51: PJ | E51: RESDSLEA | F51: RSH | G51: 2010 | H51: 20 | I51: 9.014662 | J51: 0.8 | K51: 1 | L51: 1 | M51: 0.16 | O51: 0.45 | Q51: =RECS!T10 -> 884.77007 | R51: =Q51/$Q$42 -> 0.6988534 | S51: =S42*$R$51*$J$51/$M$51 -> 166.0645 | T51: =S42*$R$51*$J$51 -> 26.570319 | U51: =$S51*Z$5/$T$5 -> 48.65557 | V51: =$S51*AA$5/$T$5 -> 23.130505 | W51: =$S51*AB$5/$T$5 -> 40.993712 | X51: =$S51*AC$5/$T$5 -> 11.038384 | Y51: =$S51*AD$5/$T$5 -> 42.377929 | Z51: =$T51*Z$5/$T$5 -> 7.7848912 | AA51: =$T51*AA$5/$T$5 -> 3.7008808 | AB51: =$T51*AB$5/$T$5 -> 6.5589939 | AC51: =$T51*AC$5/$T$5 -> 1.7661414 | AD51: =$T51*AD$5/$T$5 -> 6.7804687 | AF51: =RECS!U10 -> 594.65402 | AG51: =AF51/$AF$42 -> 0.57718981 | AH51: =AH42*$AG$51*$J$51/$M$51 -> 89.850258 | AI51: =AH42*$AG$51*$J$51 -> 14.376041 | AJ51: =$AH51*AO$5/$AI$5 -> 26.475951 | AK51: =$AH51*AP$5/$AI$5 -> 12.835282 | AL51: =$AH51*AQ$5/$AI$5 -> 23.523046 | AM51: =$AH51*AR$5/$AI$5 -> 5.6329146 | AN51: =$AH51*AS$5/$AI$5 -> 22.37154 | AO51: =$AI51*AO$5/$AI$5 -> 4.2361522 | AP51: =$AI51*AP$5/$AI$5 -> 2.0536452 | AQ51: =$AI51*AQ$5/$AI$5 -> 3.7636873 | AR51: =$AI51*AR$5/$AI$5 -> 0.90126634 | AS51: =$AI51*AS$5/$AI$5 -> 3.5794464 | AU51: =RECS!V10 -> 304.53798 | AV51: =AU51/$AU$42 -> 0.38331561 | AW51: =AW42*$AV$51*$J$51/$M$51 -> 31.95243 | AX51: =AW42*$AV$51*$J$51 -> 5.1123888 | AY51: =$AW51*BD$5/$AX$5 -> 8.6205856 | AZ51: =$AW51*BE$5/$AX$5 -> 4.2079594 | BA51: =$AW51*BF$5/$AX$5 -> 7.3586374 | BB51: =$AW51*BG$5/$AX$5 -> 1.7382074 | BC51: =$AW51*BH$5/$AX$5 -> 7.0812329 | BD51: =$AX51*BD$5/$AX$5 -> 1.3792937 | BE51: =$AX51*BE$5/$AX$5 -> 0.67327351 | BF51: =$AX51*BF$5/$AX$5 -> 1.177382 | BG51: =$AX51*BG$5/$AX$5 -> 0.27811318 | BH51: =$AX51*BH$5/$AX$5 -> 1.1329973
A52: R1,R2,R3,R4,R5,R6 | B52: RSHDRDV115 | C52: Distillate Radiant Ver1.RSH.DST.15 | D52: PJ | E52: RESDSLEA | F52: RSH | G52: 2015 | H52: 20 | I52: 9.5610051 | J52: 0.85 | K52: 1 | L52: 1 | M52: 0.16 | O52: 0.45
A53: R1,R2,R3,R4,R5,R6 | B53: RSHDRDV210 | C53: Distillate Radiant Ver2.RSH.DST.10 | D53: PJ | E53: RESDSLEA | F53: RSH | G53: 2010 | H53: 20 | I53: 11.609792 | J53: 0.85 | K53: 1 | L53: 1 | M53: 0.16 | O53: 0.45
A54: R1,R2,R3,R4,R5,R6 | B54: RSHDRDV310 | C54: Distillate Radiant Ver3.RSH.DST.10 | D54: PJ | E54: RESDSLEA | F54: RSH | G54: 2010 | H54: 20 | I54: 10.926863 | J54: 0.98 | K54: 1 | L54: 1 | M54: 0.16 | O54: 0.45
A55: STM | M55: =M60 -> 0.15 | Q55: ='Fuel Share'!D44 -> 5.2350728 | R55: STM | S55: ='Fuel Share'!D44 -> 5.2350728 | AF55: ='Fuel Share'!N44 -> 5.210085 | AG55: STM | AH55: ='Fuel Share'!N44 -> 5.210085 | AU55: ='Fuel Share'!X44 -> 4.690467 | AV55: STM | AW55: ='Fuel Share'!X44 -> 4.690467
A56: =TechData_DMD!A25 -> R4 | B56: =TechData_DMD!B25 -> RSHNUTIBOI | C56: =TechData_DMD!C25 -> RSH.NG.UTILITY.BOILER | D56: =TechData_DMD!D25 -> PJ | E56: =TechData_DMD!E25 -> RESSTNB | F56: =TechData_DMD!F25 -> RSH | G56: =TechData_DMD!G25 -> 2010 | H56: =TechData_DMD!H25 -> 30 | ... J56: =TechData_DMD!J25 -> 0.78 | K56: 1 | L56: 1 | M56: 0.16 | O56: 0.18 | Q56: =Q55*R56 -> 2.2480744 | R56: =DmdCalc!R11 -> 0.42942562 | S56: =$S$55*R56/J56/M56 -> 18.013416 | T56: =S56*R56*J56 -> 6.0336295 | U56: 0 | V56: 0 | W56: =S56 -> 18.013416 | X56: 0 | Y56: 0 | Z56: 0 | AA56: 0 | AB56: =T56 -> 6.0336295 | AC56: 0 | AD56: 0 | AF56: =AF55*AG56 -> 2.237344 | AG56: =DmdCalc!R11 -> 0.42942562 | AH56: =$AH$55*$AG$56/J56/M56 -> 17.927436 | AI56: =AH56*R56*J56 -> 6.00483 | AJ56: 0 | AK56: 0 | AL56: =AH56 -> 17.927436 | AM56: 0 | AN56: 0 | AO56: 0 | AP56: 0 | AQ56: =AI56 -> 6.00483 | AR56: 0 | AS56: 0 | AU56: =AU55*AV56 -> 2.0142067 | AV56: =DmdCalc!R11 -> 0.42942562 | AW56: =$AW$55*AV56/J56/M56 -> 16.139476 | AX56: =AW56*AV56*J56 -> 5.4059496 | AY56: 0 | AZ56: 0 | BA56: =AW56 -> 16.139476 | BB56: 0 | BC56: 0 | BD56: 0 | BE56: 0 | BF56: =AX56 -> 5.4059496 | BG56: 0 | BH56: 0
A57: =TechData_DMD!A26 -> R4 | B57: =TechData_DMD!B26 -> RSHNUTICHP | C57: =TechData_DMD!C26 -> RSH.NG.UTILITY.CHP | D57: =TechData_DMD!D26 -> PJ | E57: =TechData_DMD!E26 -> RESSTNUC | F57: =TechData_DMD!F26 -> RSH | G57: =TechData_DMD!G26 -> 2010 | H57: =TechData_DMD!H26 -> 30 | ... J57: =TechData_DMD!J26 -> 0.78 | K57: 1 | L57: 1 | M57: 0.16 | O57: 0.18 | Q57: =Q55*R57 -> 2.9826742 | R57: =DmdCalc!R12 -> 0.56974838 | S57: =$S$55*R57/J57/M57 -> 23.899633 | T57: =S57*R57*J57 -> 10.621086 | U57: 0 | V57: 0 | W57: =S57 -> 23.899633 | X57: 0 | Y57: 0 | Z57: 0 | AA57: 0 | AB57: =T57 -> 10.621086 | AC57: 0 | AD57: 0 | AF57: =AF55*AG57 -> 2.9684375 | AG57: =DmdCalc!R12 -> 0.56974838 | AH57: =$AH$55*$AG$57/J57/M57 -> 23.785557 | AI57: =AH57*R57*J57 -> 10.57039 | AJ57: 0 | AK57: 0 | AL57: =AH57 -> 23.785557 | AM57: 0 | AN57: 0 | AO57: 0 | AP57: 0 | AQ57: =AI57 -> 10.57039 | AR57: 0 | AS57: 0 | AU57: =AU55*AV57 -> 2.6723859 | AV57: =DmdCalc!R12 -> 0.56974838 | AW57: =$AW$55*AV57/J57/M57 -> 21.413349 | AX57: =AW57*AV57*J57 -> 9.5161722 | AY57: 0 | AZ57: 0 | BA57: =AW57 -> 21.413349 | BB57: 0 | BC57: 0 | BD57: 0 | BE57: 0 | BF57: =AX57 -> 9.5161722 | BG57: 0 | BH57: 0
A58: =TechData_DMD!A27 -> R4 | B58: =TechData_DMD!B27 -> RSHBUTICHP | C58: =TechData_DMD!C27 -> RSH.DSL.UTILITY.CHP | D58: =TechData_DMD!D27 -> PJ | E58: =TechData_DMD!E27 -> RESSTBUC | F58: =TechData_DMD!F27 -> RSH | G58: =TechData_DMD!G27 -> 2010 | H58: =TechData_DMD!H27 -> 30 | ... J58: =TechData_DMD!J27 -> 0.78 | K58: 1 | L58: 1 | M58: 0.16 | O58: 0.18 | Q58: =Q55*R58 -> 0.0043242129 | R58: =DmdCalc!R13 -> 0.00082600816 | S58: =$S$55*R58*J58/M58 -> 0.021080538 | T58: =S58*R58*J58 -> 1.3581903e-05 | U58: 0 | V58: 0 | W58: =S58 -> 0.021080538 | X58: 0 | Y58: 0 | Z58: 0 | AA58: 0 | AB58: =T58 -> 1.3581903e-05 | AC58: 0 | AD58: 0 | AF58: =AF55*AG58 -> 0.0043035727 | AG58: =DmdCalc!R13 -> 0.00082600816 | AH58: =$AH$55*$AG$58*J58/M58 -> 0.020979917 | AI58: =AH58*R58*J58 -> 1.3517074e-05 | AJ58: 0 | AK58: 0 | AL58: =AH58 -> 0.020979917 | AM58: 0 | AN58: 0 | AO58: 0 | AP58: 0 | AQ58: =AI58 -> 1.3517074e-05 | AR58: 0 | AS58: 0 | AU58: =AU55*AV58 -> 0.003874364 | AV58: =DmdCalc!R13 -> 0.00082600816 | AW58: =$AW$55*AV58/J58/M58 -> 0.031044583 | AX58: =AW58*AV58*J58 -> 2.0001602e-05 | AY58: 0 | AZ58: 0 | BA58: =AW58 -> 0.031044583 | BB58: 0 | BC58: 0 | BD58: 0 | BE58: 0 | BF58: =AX58 -> 2.0001602e-05 | BG58: 0 | BH58: 0
A59: *Space Cooling | T59: =SUM(T61:T97) -> 26.737813 | Z59: =CommData_DMD!E7 -> 9.427232 | AA59: =CommData_DMD!E17 -> 4.7126374 | AB59: =CommData_DMD!E27 -> 7.2268707 | AC59: =CommData_DMD!E37 -> 1.7162587 | AD59: =CommData_DMD!E47 -> 8.2274756 | AI59: =SUM(AI61:AI97) -> 25.758992 | AO59: =CommData_DMD!F7 -> 9.2041854 | AP59: =CommData_DMD!F17 -> 4.6812323 | AQ59: =CommData_DMD!F27 -> 7.6093011 | AR59: =CommData_DMD!F37 -> 1.6990831 | AS59: =CommData_DMD!F47 -> 7.8913427 | AX59: =SUM(AX61:AX97) -> 23.852635 | BD59: =CommData_DMD!G7 -> 9.6137311 | BE59: =CommData_DMD!G17 -> 4.9571109 | BF59: =CommData_DMD!G27 -> 7.336496 | BG59: =CommData_DMD!G37 -> 1.5939977 | BH59: =CommData_DMD!G47 -> 7.7895635
A60: ELC | M60: =M62 -> 0.15 | Q60: =SUM(Q61:Q92) -> 675.8565 | R60: ELC | S60: ='Fuel Share'!F41 -> 9.3429548 | Z60: =SUM(Z61:Z97) -> 9.427232 | AA60: =SUM(AA61:AA97) -> 4.7126374 | AB60: =SUM(AB61:AB97) -> 7.2268707 | AC60: =SUM(AC61:AC97) -> 1.7162587 | AD60: =SUM(AD61:AD97) -> 8.2274756 | AF60: =SUM(AF61:AF92) -> 838.1905 | AG60: ELC | AH60: ='Fuel Share'!P41 -> 9.0320703 | AO60: =SUM(AO61:AO97) -> 9.2041854 | AP60: =SUM(AP61:AP97) -> 4.6812323 | AQ60: =SUM(AQ61:AQ97) -> 7.6093011 | AR60: =SUM(AR61:AR97) -> 1.6990831 | AS60: =SUM(AS61:AS97) -> 7.8913427 | AU60: =SUM(AU61:AU92) -> 1000.5245 | AV60: ELC | AW60: ='Fuel Share'!Z41 -> 8.3832237 | BD60: =SUM(BD61:BD97) -> 9.6137311 | BE60: =SUM(BE61:BE97) -> 4.9571109 | BF60: =SUM(BF61:BF97) -> 7.336496 | BG60: =SUM(BG61:BG97) -> 1.5939977 | BH60: =SUM(BH61:BH97) -> 7.7895635
A61: *Room AC
A62: R1,R2,R3,R4,R5,R6 | B62: RSCRACBS05 | C62: Room AC Base.RSC.ELC.05 | D62: PJ | E62: RESELC | F62: RSC | G62: 2005 | H62: 10 | J62: 2.7435958 | K62: 1 | L62: 1 | M62: 0.15 | O62: 0.6
A63: R1,R2,R3,R4,R5,R6 | B63: RSCRACV110 | C63: Room AC Ver1.RSC.ELC.10 | D63: PJ | E63: RESELC | F63: RSC | G63: 2010 | H63: 10 | I63: 2.7043986 | J63: 2.74 | K63: 1 | L63: 1 | M63: 0.15 | O63: 0.6 | Q63: =RECS!T12 -> 226.98832 | R63: =Q63/$Q$60 -> 0.33585283 | S63: =S60*$R$63*$J$63/$M$63 -> 57.318202 | T63: =S60*$R$63*$J$63 -> 8.5977303 | U63: =$S63*Z$59/$T$59 -> 20.209281 | V63: =$S63*AA$59/$T$59 -> 10.102543 | W63: =$S63*AB$59/$T$59 -> 15.492338 | X63: =$S63*AC$59/$T$59 -> 3.6791663 | Y63: =$S63*AD$59/$T$59 -> 17.637348 | Z63: =$T63*Z59/$T$59 -> 3.0313922 | AA63: =$T63*AA59/$T$59 -> 1.5153814 | AB63: =$T63*AB59/$T$59 -> 2.3238507 | AC63: =$T63*AC59/$T$59 -> 0.55187494 | AD63: =$T63*AD59/$T$59 -> 2.6456022 | AF63: =RECS!U12 -> 342.60338 | AG63: =AF63/$AF$60 -> 0.40874166 | AH63: =AH60*$AG$63*$J$63/$M$63 -> 67.436577 | AI63: =AH60*$AG$63*$J$63 -> 10.115487 | AJ63: =$AH63*AO$59/$AI$59 -> 24.096392 | AK63: =$AH63*AP$59/$AI$59 -> 12.255382 | AL63: =$AH63*AQ$59/$AI$59 -> 19.921013 | AM63: =$AH63*AR$59/$AI$59 -> 4.448169 | AN63: =$AH63*AS$59/$AI$59 -> 20.659393 | AO63: =$AI63*AO59/$AI$59 -> 3.6144588 | AP63: =$AI63*AP59/$AI$59 -> 1.8383073 | AQ63: =$AI63*AQ59/$AI$59 -> 2.988152 | AR63: =$AI63*AR59/$AI$59 -> 0.66722536 | AS63: =$AI63*AS59/$AI$59 -> 3.098909 | AU63: =RECS!V12 -> 458.21844 | AV63: =AU63/$AU$60 -> 0.45797823 | AW63: =AW60*$AV$63*$J$63/$M$63 -> 70.131834 | AX63: =AW60*$AV$63*$J$63 -> 10.519775 | AY63: =$AW63*BD$59/$AX$59 -> 28.26642 | AZ63: =$AW63*BE$59/$AX$59 -> 14.574963 | BA63: =$AW63*BF$59/$AX$59 -> 21.570863 | BB63: =$AW63*BG$59/$AX$59 -> 4.686693 | BC63: =$AW63*BH$59/$AX$59 -> 22.902978 | BD63: =$AX63*BD59/$AX$59 -> 4.239963 | BE63: =$AX63*BE59/$AX$59 -> 2.1862445 | BF63: =$AX63*BF59/$AX$59 -> 3.2356294 | BG63: =$AX63*BG59/$AX$59 -> 0.70300396 | BH63: =$AX63*BH59/$AX$59 -> 3.4354467
A64: R1,R2,R3,R4,R5,R6 | B64: RSCRACV210 | C64: Room AC Ver2.RSC.ELC.10 | D64: PJ | E64: RESELC | F64: RSC | G64: 2010 | H64: 10 | I64: 2.8519112 | J64: 3.17 | K64: 1 | L64: 1 | M64: 0.15 | O64: 0.6
A65: R1,R2,R3,R4,R5,R6 | B65: RSCRACV215 | C65: Room AC Ver2.RSC.ELC.15 | D65: PJ | E65: RESELC | F65: RSC | G65: 2015 | H65: 10 | I65: 2.9010821 | J65: 3.22 | K65: 1 | L65: 1 | M65: 0.15 | O65: 0.6
A66: R1,R2,R3,R4,R5,R6 | B66: RSCRACV230 | C66: Room AC Ver2.RSC.ELC.30 | D66: PJ | E66: RESELC | F66: RSC | G66: 2030 | H66: 10 | I66: 2.9010821 | J66: 3.28 | K66: 1 | L66: 1 | M66: 0.15 | O66: 0.6
A67: R1,R2,R3,R4,R5,R6 | B67: RSCRACV310 | C67: Room AC Ver3.RSC.ELC.10 | D67: PJ | E67: RESELC | F67: RSC | G67: 2010 | H67: 10 | I67: 4.4745504 | J67: 3.52 | K67: 1 | L67: 1 | M67: 0.15 | O67: 0.6
A68: R1,R2,R3,R4,R5,R6 | B68: RSCRACV320 | C68: Room AC Ver3.RSC.ELC.20 | D68: PJ | E68: RESELC | F68: RSC | G68: 2020 | H68: 10 | I68: 5.064601 | J68: 3.81 | K68: 1 | L68: 1 | M68: 0.15 | O68: 0.6
A69: *Central AC
A70: R1,R2,R3,R4,R5,R6 | B70: RSCCACBS05 | C70: Central AC Base.RSC.ELC.05 | D70: PJ | E70: RESELC | F70: RSC | G70: 2005 | H70: 15 | J70: 2.9175659 | K70: 1 | L70: 1 | M70: 0.15 | O70: 0.18
A71: R1,R2,R3,R4,R5,R6 | B71: RSCCACV110 | C71: Central AC Ver1.RSC.ELC.10 | D71: PJ | E71: RESELC | F71: RSC | G71: 2010 | H71: 15 | I71: 8.7414904 | J71: 2.92 | K71: 1 | L71: 1 | M71: 0.15 | O71: 0.18 | Q71: =RECS!T13 -> 429.69893 | R71: =Q71/$Q$60 -> 0.63578427 | S71: =S60*$R$71*$J$71/$M$71 -> 115.63402 | T71: =S60*$R$71*$J$71 -> 17.345103 | U71: =$S71*Z$59/$T$59 -> 40.770302 | V71: =$S71*AA$59/$T$59 -> 20.380919 | W71: =$S71*AB$59/$T$59 -> 31.254318 | X71: =$S71*AC$59/$T$59 -> 7.4223679 | Y71: =$S71*AD$59/$T$59 -> 35.581671 | Z71: =$T71*Z59/$T$59 -> 6.1155453 | AA71: =$T71*AA59/$T$59 -> 3.0571379 | AB71: =$T71*AB59/$T$59 -> 4.6881476 | AC71: =$T71*AC59/$T$59 -> 1.1133552 | AD71: =$T71*AD59/$T$59 -> 5.3372506 | AF71: =RECS!U13 -> 437.7396 | AG71: =AF71/$AF$60 -> 0.52224357 | AH71: =AH60*$AG$71*$J$71/$M$71 -> 91.823112 | AI71: =AH60*$AG$71*$J$71 -> 13.773467 | AJ71: =$AH71*AO$59/$AI$59 -> 32.810172 | AK71: =$AH71*AP$59/$AI$59 -> 16.687195 | AL71: =$AH71*AQ$59/$AI$59 -> 27.124885 | AM71: =$AH71*AR$59/$AI$59 -> 6.0567238 | AN71: =$AH71*AS$59/$AI$59 -> 28.130279 | AO71: =$AI71*AO59/$AI$59 -> 4.9215258 | AP71: =$AI71*AP59/$AI$59 -> 2.5030792 | AQ71: =$AI71*AQ59/$AI$59 -> 4.0687328 | AR71: =$AI71*AR59/$AI$59 -> 0.90850857 | AS71: =$AI71*AS59/$AI$59 -> 4.2195419 | AU71: =RECS!V13 -> 445.78027 | AV71: =AU71/$AU$60 -> 0.44554658 | AW71: =AW60*$AV$71*$J$71/$M$71 -> 72.710271 | AX71: =AW60*$AV$71*$J$71 -> 10.906541 | AY71: =$AW71*BD$59/$AX$59 -> 29.305651 | AZ71: =$AW71*BE$59/$AX$59 -> 15.11082 | BA71: =$AW71*BF$59/$AX$59 -> 22.363928 | BB71: =$AW71*BG$59/$AX$59 -> 4.859002 | BC71: =$AW71*BH$59/$AX$59 -> 23.745019 | BD71: =$AX71*BD59/$AX$59 -> 4.3958477 | BE71: =$AX71*BE59/$AX$59 -> 2.266623 | BF71: =$AX71*BF59/$AX$59 -> 3.3545892 | BG71: =$AX71*BG59/$AX$59 -> 0.72885031 | BH71: =$AX71*BH59/$AX$59 -> 3.5617529
A72: R5,R6,R7,R9 | B72: RSCCACV115 | C72: Central AC Ver1.RSC.ELC.15 | D72: PJ | E72: RESELC | F72: RSC | G72: 2015 | H72: 15 | I72: 9.6975909 | J72: 4.1 | K72: 1 | L72: 1 | M72: 0.15 | O72: 0.18
A73: R1,R2,R3,R4,R5,R6 | B73: RSCCACV220 | C73: Central AC Ver2.RSC.ELC.20 | D73: PJ | E73: RESELC | F73: RSC | G73: 2020 | H73: 15 | I73: 9.6975909 | J73: 4.1 | K73: 1 | L73: 1 | M73: 0.15 | O73: 0.18
A74: R1,R2,R3,R4,R5,R6 | B74: RSCCACV310 | C74: Central AC Ver3.RSC.ELC.10 | D74: PJ | E74: RESELC | F74: RSC | G74: 2010 | H74: 15 | I74: 10.517106 | J74: 4.69 | K74: 1 | L74: 1 | M74: 0.15 | O74: 0.18
A75: R1,R2,R3,R4,R5,R6 | B75: RSCCACV320 | C75: Central AC Ver3.RSC.ELC.20 | D75: PJ | E75: RESELC | F75: RSC | G75: 2020 | H75: 15 | I75: 10.107348 | J75: 4.69 | K75: 1 | L75: 1 | M75: 0.15 | O75: 0.18
A76: R1,R2,R3,R4,R5,R6 | B76: RSCCACV410 | C76: Central AC Ver4.RSC.ELC.10 | D76: PJ | E76: RESELC | F76: RSC | G76: 2010 | H76: 15 | I76: 12.292721 | J76: 6.15 | K76: 1 | L76: 1 | M76: 0.15 | O76: 0.18
A77: R1,R2,R3,R4,R5,R6 | B77: RSCCACV415 | C77: Central AC Ver4.RSC.ELC.15 | D77: PJ | E77: RESELC | F77: RSC | G77: 2015 | H77: 15 | I77: 16.390294 | J77: 7.03 | K77: 1 | L77: 1 | M77: 0.15 | O77: 0.18
A78: R1,R2,R3,R4,R5,R6 | B78: RSCCACV420 | C78: Central AC Ver4.RSC.ELC.20 | D78: PJ | E78: RESELC | F78: RSC | G78: 2020 | H78: 15 | I78: 15.707366 | J78: 7.03 | K78: 1 | L78: 1 | M78: 0.15 | O78: 0.18
A79: *Electric Heat Pump
A80: R1,R2,R3,R4,R5,R6 | B80: RSCEHPBS05 | C80: Electric Heat Pump Base.RSC.ELC.05 | D80: PJ | E80: RESELC | F80: RSC | G80: 2005 | H80: 15 | J80: 2.998007 | K80: 1 | L80: 1 | M80: 0.15 | O80: 0.45
A81: R1,R2,R3,R4,R5,R6 | B81: RSCEHPV110 | C81: Electric Heat Pump Ver1.RSC.ELC.10 | D81: PJ | E81: RESELC | F81: RSC | G81: 2010 | H81: 15 | I81: 6.5561178 | J81: 3 | K81: 1 | L81: 1 | M81: 0.15 | O81: 0.45 | Q81: =RECS!T14 -> 19.169252 | R81: =Q81/$Q$60 -> 0.028362903 | S81: =S60*$R$81*$J$81/$M$81 -> 5.2998664 | T81: =S60*$R$81*$J$81 -> 0.79497997 | U81: =$S81*Z$59/$T$59 -> 1.8686296 | V81: =$S81*AA$59/$T$59 -> 0.93412086 | W81: =$S81*AB$59/$T$59 -> 1.4324825 | X81: =$S81*AC$59/$T$59 -> 0.34019019 | Y81: =$S81*AD$59/$T$59 -> 1.6308186 | Z81: =$T81*Z59/$T$59 -> 0.28029445 | AA81: =$T81*AA59/$T$59 -> 0.14011813 | AB81: =$T81*AB59/$T$59 -> 0.21487238 | AC81: =$T81*AC59/$T$59 -> 0.051028528 | AD81: =$T81*AD59/$T$59 -> 0.24462278 | AF81: =RECS!U14 -> 57.847519 | AG81: =AF81/$AF$60 -> 0.069014763 | AH81: =AH60*$AG$81*$J$81/$M$81 -> 12.466924 | AI81: =AH60*$AG$81*$J$81 -> 1.8700386 | AJ81: =$AH81*AO$59/$AI$59 -> 4.4546727 | AK81: =$AH81*AP$59/$AI$59 -> 2.2656386 | AL81: =$AH81*AQ$59/$AI$59 -> 3.6827752 | AM81: =$AH81*AR$59/$AI$59 -> 0.82232799 | AN81: =$AH81*AS$59/$AI$59 -> 3.8192787 | AO81: =$AI81*AO59/$AI$59 -> 0.66820091 | AP81: =$AI81*AP59/$AI$59 -> 0.33984579 | AQ81: =$AI81*AQ59/$AI$59 -> 0.55241629 | AR81: =$AI81*AR59/$AI$59 -> 0.1233492 | AS81: =$AI81*AS59/$AI$59 -> 0.5728918 | AU81: =RECS!V14 -> 96.525785 | AV81: =AU81/$AU$60 -> 0.096475185 | AW81: =AW60*$AV$81*$J$81/$M$81 -> 16.175461 | AX81: =AW60*$AV$81*$J$81 -> 2.4263192 | AY81: =$AW81*BD$59/$AX$59 -> 6.5194698 | AZ81: =$AW81*BE$59/$AX$59 -> 3.3616225 | BA81: =$AW81*BF$59/$AX$59 -> 4.9751823 | BB81: =$AW81*BG$59/$AX$59 -> 1.0809559 | BC81: =$AW81*BH$59/$AX$59 -> 5.2824261 | BD81: =$AX81*BD59/$AX$59 -> 0.97792048 | BE81: =$AX81*BE59/$AX$59 -> 0.50424338 | BF81: =$AX81*BF59/$AX$59 -> 0.74627734 | BG81: =$AX81*BG59/$AX$59 -> 0.16214339 | BH81: =$AX81*BH59/$AX$59 -> 0.79236391
A82: R1,R2,R3,R4,R5,R6 | B82: RSCEHPV115 | C82: Electric Heat Pump Ver1.RSC.ELC.15 | D82: PJ | E82: RESELC | F82: RSC | G82: 2015 | H82: 15 | I82: 6.7609965 | J82: 4.1 | K82: 1 | L82: 1 | M82: 0.15 | O82: 0.45
A83: R1,R2,R3,R4,R5,R6 | B83: RSCEHPV210 | C83: Electric Heat Pump Ver2.RSC.ELC.10 | D83: PJ | E83: RESELC | F83: RSC | G83: 2010 | H83: 15 | I83: 9.4927122 | J83: 4.4 | K83: 1 | L83: 1 | M83: 0.15 | O83: 0.45
A84: R1,R2,R3,R4,R5,R6 | B84: RSCEHPV215 | C84: Electric Heat Pump Ver2.RSC.ELC.15 | D84: PJ | E84: RESELC | F84: RSC | G84: 2015 | H84: 15 | I84: 9.4927122 | J84: 4.4 | K84: 1 | L84: 1 | M84: 0.15 | O84: 0.45
A85: R1,R2,R3,R4,R5,R6 | B85: RSCEHPV310 | C85: Electric Heat Pump Ver3.RSC.ELC.10 | D85: PJ | E85: RESELC | F85: RSC | G85: 2010 | H85: 15 | I85: 9.8341767 | J85: 4.69 | K85: 1 | L85: 1 | M85: 0.15 | O85: 0.45
A86: R1,R2,R3,R4,R5,R6 | B86: RSCEHPV315 | C86: Electric Heat Pump Ver3.RSC.ELC.15 | D86: PJ | E86: RESELC | F86: RSC | G86: 2015 | H86: 15 | I86: 8.6049046 | J86: 4.84 | K86: 1 | L86: 1 | M86: 0.15 | O86: 0.45
A87: R1,R2,R3,R4,R5,R6 | B87: RSCEHPV320 | C87: Electric Heat Pump Ver3.RSC.ELC.20 | D87: PJ | E87: RESELC | F87: RSC | G87: 2020 | H87: 15 | I87: 8.6049046 | J87: 4.84 | K87: 1 | L87: 1 | M87: 0.15 | O87: 0.45
A88: R1,R2,R3,R4,R5,R6 | B88: RSCEHPV330 | C88: Electric Heat Pump Ver3.RSC.ELC.30 | D88: PJ | E88: RESELC | F88: RSC | G88: 2030 | H88: 15 | I88: 8.6049046 | J88: 4.84 | K88: 1 | L88: 1 | M88: 0.15 | O88: 0.45
A89: R1,R2,R3,R4,R5,R6 | B89: RSCEHPV410 | C89: Electric Heat Pump Ver4.RSC.ELC.10 | D89: PJ | E89: RESELC | F89: RSC | G89: 2010 | H89: 15 | I89: 10.85857 | J89: 6.45 | K89: 1 | L89: 1 | M89: 0.15 | O89: 0.45
A90: R1,R2,R3,R4,R5,R6 | B90: RSCEHPV420 | C90: Electric Heat Pump Ver4.RSC.ELC.20 | D90: PJ | E90: RESELC | F90: RSC | G90: 2020 | H90: 15 | I90: 10.995156 | J90: 6.74 | K90: 1 | L90: 1 | M90: 0.15 | O90: 0.45
A91: R1,R2,R3,R4,R5,R6 | B91: RSCEHPV430 | C91: Electric Heat Pump Ver4.RSC.ELC.30 | D91: PJ | E91: RESELC | F91: RSC | G91: 2030 | H91: 15 | I91: 11.268327 | J91: 7.03 | K91: 1 | L91: 1 | M91: 0.15 | O91: 0.45
A92: R1,R2,R3,R4,R5,R6 | B92: RSCEHPV435 | C92: Electric Heat Pump Ver4.RSC.ELC.35 | D92: PJ | E92: RESELC | F92: RSC | G92: 2035 | H92: 15 | I92: 11.268327 | J92: 7.33 | K92: 1 | L92: 1 | M92: 0.15 | O92: 0.45
A93: NGA | M93: =M95 -> 0.15 | Q93: =SUM(Q94:Q97) -> 1.7695813 | R93: NGA | S93: ='Fuel Share'!F42 -> 0 | AF93: =SUM(AF94:AF97) -> 4.6744018 | AG93: NGA | AH93: ='Fuel Share'!P42 -> 0 | AU93: =SUM(AU94:AU97) -> 7.5792224 | AV93: NGA | AW93: ='Fuel Share'!Z42 -> 0
A94: *Natural Gas Heat Pump
A95: R1,R2,R3,R4,R5,R6 | B95: RSCNHPBS05 | C95: Natural Gas Heat Pump Base.RSC.NGA.05 | D95: PJ | E95: RESNGAEA | F95: RSC | G95: 2005 | H95: 15 | I95: 0 | J95: 0.67000002 | K95: 1 | L95: 1 | M95: 0.15 | O95: 0.18
