Workbook
Name FO2_l_to_gj: Conversions!$C$23
Name FO4_l_to_gj: Conversions!$C$24
Name FO6_l_to_gj: Conversions!$C$25
Name gal_to_liter: Conversions!$C$20
Name GJ_to_PJ: Conversions!$C$18
Name kgs_to_gj: Conversions!$C$26
Name kwh_to_gj: Conversions!$C$21
Name MMBtu_to_PJ: Conversions!$C$14
Name scf_to_gj: Conversions!$C$22
Name trilBtu_to_PJ: Conversions!$C$28
Name var_derate: Tech_Data!$D$3
Name var_derate2: Tech_Data!$E$3
Name var_inflate: Tech_Data!$D$4
Name var_inflate2: Tech_Data!$E$4

Sheet Commodities
B3: ~FI_Comm
B4: Region | C4: Csets | D4: CommName | E4: CommDesc | F4: Unit | G4: LimType | H4: CTSLvl | I4: PeakTS | J4: Ctype
B5: *End Use demand
B6: R2,R3,R4,R5,R6 | C6: DEM | D6: ISH | E6: Industrial Heating | F6: PJ
B7: R2,R3,R4,R5,R6 | C7: DEM | D7: ISC | E7: Industrial Cooling | F7: PJ
B8: R2,R3,R4,R5,R6 | C8: DEM | D8: IWH | E8: Industrial Water Heating | F8: PJ
B9: R2,R3,R4,R5,R6 | C9: DEM | D9: ILT | E9: Industrial Lighting | F9: PJ
B10: R2,R3,R4,R5,R6 | C10: DEM | D10: IOTE | E10: Industrial Process Loads + Other, Electric | F10: PJ
B11: R2,R3,R4,R5,R6 | C11: DEM | D11: IOTF | E11: Industrial Process Loads + Other, Fossil | F11: PJ
B12: * Energy Carriers
B13: R2,R3,R4,R5,R6 | C13: NRG | D13: INDELC | E13: Electricity to Industrial Sector | F13: PJ | H13: DAYNITE | I13: ANNUAL | J13: ELC
B14: R2,R3,R4,R5,R6 | C14: NRG | D14: INDNGA | E14: Natural Gas to Industrial Sector | F14: PJ
B15: R2,R3,R4,R5,R6 | C15: NRG | D15: INDDSL | E15: Diesel to Industrial Sector | F15: PJ
B16: *CHP Energy Carriers
B17: R1,R2,R3,R4,R5,R6 | C17: NRG | D17: INDSTNUC | E17: STM from Industrial NGA Utility-scale CHP | F17: PJ
B18: R1,R2,R3,R4,R5,R6 | C18: NRG | D18: INDSTBUC | E18: STM from Industrial DST Utility-scale CHP | F18: PJ
B19: R2,R3,R4,R5,R6 | C19: NRG | D19: INDSTNB | E19: STM from Industrial NGA Boilers | F19: PJ
B20: R2,R3,R4,R5,R6 | C20: NRG | D20: INDSTNOC | E20: STM from Industrial NGA other CHP | F20: PJ
B21: *Industrial sector energy carriers after emissions accounting
B22: R2,R3,R4,R5,R6 | C22: NRG | D22: INDNGAEA | E22: Natural Gas to Industrial Sector after Emissions Accounting | F22: PJ
B23: R2,R3,R4,R5,R6 | C23: NRG | D23: INDDSLEA | E23: Diesel to Industrial Sector after Emissions Accounting | F23: PJ
B24: *Emissions Commodities
B25: R1,R2,R3,R4,R5,R6 | C25: ENV | D25: CO2 | E25: Carbon dioxide | F25: Mt
B26: R1,R2,R3,R4,R5,R6 | C26: ENV | D26: NOX | E26: Nitrogen oxide | F26: kt
B27: R1,R2,R3,R4,R5,R6 | C27: ENV | D27: PM10 | E27: Particulate matter | F27: kt
B28: R1,R2,R3,R4,R5,R6 | C28: ENV | D28: PM25 | E28: Fine particulate matter | F28: kt
B29: R1,R2,R3,R4,R5,R6 | C29: ENV | D29: VOC | E29: Volatile organic compounds | F29: kt
B30: R1,R2,R3,R4,R5,R6 | C30: ENV | D30: CO | E30: Carbon monoxide | F30: kt
B31: R1,R2,R3,R4,R5,R6 | C31: ENV | D31: CH4 | E31: Methane | F31: kt
B32: R1,R2,R3,R4,R5,R6 | C32: ENV | D32: N2O | E32: N2O | F32: kt
B33: R1,R2,R3,R4,R5,R6 | C33: ENV | D33: BC | E33: Black carbon | F33: kt
B34: R1,R2,R3,R4,R5,R6 | C34: ENV | D34: OC | E34: Organic carbon | F34: kt
B35: R1,R2,R3,R4,R5,R6 | C35: ENV | D35: SO2 | E35: Sulfur dioxide | F35: kt
B36: *IND_DEM_FI_Comm

Sheet Technologies
B2: *IND_DEM_FI_Process
B3: ~FI_Process
B4: Region | C4: Sets | D4: TechName | E4: *TechDesc | F4: Tact | G4: Tcap | H4: PrimaryCG | I4: Vintage | J4: Tslvl
B5: *Emissions Accounting Collectors
B6: R2,R3,R4,R5,R6 | C6: PRE | D6: SEINDNGA | E6: Emissions: NGA to IND | F6: PJ | G6: Pja
B7: R2,R3,R4,R5,R6 | C7: PRE | D7: SEINDDSL | E7: Emissions: DSL to IND | F7: PJ | G7: Pja
B8: R2,R3,R4,R5,R6 | C8: PRE | D8: SCINDELC | E8: Collector: ELC to IND | F8: PJ | G8: Pja
B9: *Energy Transfer
B10: R2,R3,R4,R5,R6 | C10: DMD | D10: ETINDNGA | E10: Energy Transfer: NGA to INDNGA | F10: PJ | G10: Pja
B11: R2,R3,R4,R5,R6 | C11: DMD | D11: ETINDDSL | E11: Energy Transfer: DSL to INDDSL | F11: PJ | G11: Pja
B12: R2,R3,R4,R5,R6 | C12: DMD | D12: ETINDELC | E12: Energy Transfer: ELC to INDELC | F12: PJ | G12: Pja
B13: *Dummy Backstops
B14: R2,R3,R4,R5,R6 | C14: DMD | D14: ZZDMYISH | E14: Industrial Heating - ZZ dummy backstop | F14: PJ | G14: Pja
B15: R2,R3,R4,R5,R6 | C15: DMD | D15: ZZDMYISC | E15: Industrial Cooling - ZZ dummy backstop | F15: PJ | G15: Pja
B16: R2,R3,R4,R5,R6 | C16: DMD | D16: ZZDMYIWH | E16: Industrial Water Heating - ZZ dummy backstop | F16: PJ | G16: Pja
B17: R2,R3,R4,R5,R6 | C17: DMD | D17: ZZDMYILT | E17: Industrial Lighting - ZZ dummy backstop | F17: PJ | G17: Pja
B18: R2,R3,R4,R5,R6 | C18: DMD | D18: ZZDMYIOT | E18: Industrial Process Loads + Other - ZZ dummy backstop | F18: PJ | G18: Pja
B19: *SPACE HEATING
B20: *Commercial Rooftop Air-source Heat Pumps
B21: R2,R3,R4,R5,R6 | C21: DMD | D21: ISHAHPST10 | E21: ISH.ELC.AHP.Ver1.10 | F21: PJ | G21: Pja
B22: *Commercial Ground Source Heat Pumps
B23: R2,R3,R4,R5,R6 | C23: DMD | D23: ISHGHPST10 | E23: ISH.ELC.GHP.Ver1.10 | F23: PJ | G23: Pja
B24: * Natural Gas Heat Pump
B25: R2,R3,R4,R5,R6 | C25: DMD | D25: ISHNHPST10 | E25: ISH.NG.HEATPUMP.ST.10 | F25: PJ | G25: Pja
B26: * Space Heating Commercial Electric Resistance Unit Heaters
B27: R2,R3,R4,R5,R6 | C27: DMD | D27: ISHERUST10 | E27: ISH.ELC.RSU.STANDARD.SMALL.12 | F27: PJ | G27: Pja
B28: R2,R3,R4,R5,R6 | C28: DMD | D28: ISHERUSTL10 | E28: ISH.ELC.RSU.STANDARD.LARGE.12 | F28: PJ | G28: Pja
B29: *Commercial Gas-Fired Furnaces
B30: R2,R3,R4,R5,R6 | C30: DMD | D30: ISHNGFST10 | E30: ISH.NG.FURNACE.Ver1.10 | F30: PJ | G30: Pja
B31: *Commercial Gas-fired Boilers
B32: R2,R3,R4,R5,R6 | C32: DMD | D32: ISHNGBST10 | E32: ISH.NG.BOILER | F32: PJ | G32: Pja
B33: *Commercial Oil-fired Furnaces
B34: R2,R3,R4,R5,R6 | C34: DMD | D34: ISHDSFST10 | E34: ISH.DSL.FURNACE.ST.10 | F34: PJ | G34: Pja
B35: *Commercial Oil-fired Boilers
B36: R2,R3,R4,R5,R6 | C36: DMD | D36: ISHDSBST10 | E36: ISH.DSL.BOILER.BS.10 | F36: PJ | G36: Pja
B37: *UTILITY SCALE CHP - SH
B38: R4 | C38: DMD | D38: ISHNUTIBOI10 | E38: ISH.NG.UTILITY.BOILER | F38: PJ | G38: Pja
B39: R4 | C39: DMD | D39: ISHNUTICHP10 | E39: ISH.NG.UTILITY.CHP | F39: PJ | G39: Pja
B40: R4 | C40: DMD | D40: ISHBUTICHP10 | E40: ISH.DSL.UTILITY.CHP | F40: PJ | G40: Pja
B41: * Space Cooling
B42: *Electric
B43: R2,R3,R4,R5,R6 | C43: DMD | D43: ISCAHPST10 | E43: ISC.ELC.AHP.ST.10 | F43: PJ | G43: Pja
B44: R2,R3,R4,R5,R6 | C44: DMD | D44: ISCGHPST10 | E44: ISC.ELC.GHP.ST.10 | F44: PJ | G44: Pja
B45: R2,R3,R4,R5,R6 | C45: DMD | D45: ISCCRCST10 | E45: ISC.ELC.CRC.ST.10 | F45: PJ | G45: Pja
B46: *R2,R3,R4,R5,R6 | C46: DMD | D46: ISCCCCST10 | E46: ISC.ELC.CCC.ST.10 | F46: PJ | G46: Pja
B47: R2,R3,R4,R5,R6 | C47: DMD | D47: ISCRACST10 | E47: ISC.ELC.RAC.ST.10 | F47: PJ | G47: Pja
B48: R2,R3,R4,R5,R6 | C48: DMD | D48: ISCWACST10 | E48: ISC.ELC.WAC.ST.10 | F48: PJ | G48: Pja
B49: R2,R3,R4,R5,R6 | C49: DMD | D49: ISCCACST10 | E49: ISC.ELC.CAC.ST.10 | F49: PJ | G49: Pja
B50: *NG
B51: *R2,R3,R4,R5,R6 | C51: DMD | D51: ISCNHPST10 | E51: ISC.NG.HEATPUMP.ST.10 | F51: PJ | G51: Pja
B52: *R2,R3,R4,R5,R6 | C52: DMD | D52: ISCCHAST10 | E52: ISC.NG.CHA.ST.10 | F52: PJ | G52: Pja
B53: * Water Heating
B54: *heatpump
B55: R2,R3,R4,R5,R6 | C55: DMD | D55: IWHEHPST10 | E55: IWH.ELC.HEATPUMP.ST.10 | F55: PJ | G55: Pja
B56: *ewh
B57: R2,R3,R4,R5,R6 | C57: DMD | D57: IWHEWHBS10 | E57: IWH.ELC.EWH.BS.10 | F57: PJ | G57: Pja
B58: *nwh
B59: R2,R3,R4,R5,R6 | C59: DMD | D59: IWHNGIBS10 | E59: IWH.NG.INSTANT.BS.10 | F59: PJ | G59: Pja
B60: *dwh
B61: R2,R3,R4,R5,R6 | C61: DMD | D61: IWHDWHBS10 | E61: IWH.DSL.DWH.BS.10 | F61: PJ | G61: Pja
B62: *chp-wh
B63: *R2,R3,R4,R5,R6 | C63: DMD | D63: IWHNOTRCHP | E63: IWH.NG.OTHERCHP | F63: PJ | G63: Pja
B64: *UTILITY SCALE CHP - WH
B65: R4 | C65: DMD | D65: IWHNUTIBOI10 | E65: IWH.NG.UTILITY.BOILER | F65: PJ | G65: Pja
B66: R4 | C66: DMD | D66: IWHNUTICHP10 | E66: IWH.NG.UTILITY.CHP | F66: PJ | G66: Pja
B67: R4 | C67: DMD | D67: IWHBUTICHP10 | E67: IWH.DSL.UTILITY.CHP | F67: PJ | G67: Pja
B68: * Lighting
B69: R2,R3,R4,R5,R6 | C69: DMD | D69: ILTINCBS | E69: ILT_INC_100W_BS | F69: PJ | G69: Pja
B70: R2,R3,R4,R5,R6 | C70: DMD | D70: ILTCFLBS | E70: ILT_CFL_26W_BS | F70: PJ | G70: Pja
B71: R2,R3,R4,R5,R6 | C71: DMD | D71: ILTHAL9010 | E71: ILT_HAL_90W_10 | F71: PJ | G71: Pja
B72: R2,R3,R4,R5,R6 | C72: DMD | D72: ILTT8MAGBS | E72: ILT_LFL_T8_F32_MAG_BS | F72: PJ | G72: Pja
B73: R2,R3,R4,R5,R6 | C73: DMD | D73: ILTT810 | E73: ILT_LFL_T8_F32_10 | F73: PJ | G73: Pja
B74: R2,R3,R4,R5,R6 | C74: DMD | D74: ILTT8HE10 | E74: ILT_LFL_T8_F32_HE_10 | F74: PJ | G74: Pja
B75: R2,R3,R4,R5,R6 | C75: DMD | D75: ILTT8LBS | E75: ILT_LFL_T8_F96_BS | F75: PJ | G75: Pja
B76: R2,R3,R4,R5,R6 | C76: DMD | D76: ILTT8LHEBS | E76: ILT_LFL_T8_F96_HE_BS | F76: PJ | G76: Pja
B77: R2,R3,R4,R5,R6 | C77: DMD | D77: ILTT5BS | E77: ILT_LFL_T5_BS | F77: PJ | G77: Pja
B78: R2,R3,R4,R5,R6 | C78: DMD | D78: ILTHIDLBBS | E78: ILT_HID_LB_BS | F78: PJ | G78: Pja
B79: R2,R3,R4,R5,R6 | C79: DMD | D79: ILTHIDHBBS | E79: ILT_HID_HB_BS | F79: PJ | G79: Pja
B80: * Other
B81: R2,R3,R4,R5,R6 | C81: DMD | D81: IOTELC10 | E81: Miscellaneous.ELC.BS.00 | F81: PJ | G81: Pja
B82: R2,R3,R4,R5,R6 | C82: DMD | D82: IOTELC110 | E82: Miscellaneous.ELC.BS1.00 | F82: PJ | G82: Pja
B83: R2,R3,R4,R5,R6 | C83: DMD | D83: IOTNGA10 | E83: Miscellaneous.NG.BS.00 | F83: PJ | G83: Pja
B84: R2,R3,R4,R5,R6 | C84: DMD | D84: IOTDSL10 | E84: Miscellaneous.DSL.BS.00 | F84: PJ | G84: Pja

Sheet CommDemand
B2: *IND_DEM_COM | F2: *Year Match | G2: =_xlfn.NUMBERVALUE(RIGHT(G5,4)) -> 2010 | H2: =_xlfn.NUMBERVALUE(RIGHT(H5,4)) -> 2015 | I2: =_xlfn.NUMBERVALUE(RIGHT(I5,4)) -> 2020 | J2: =_xlfn.NUMBERVALUE(RIGHT(J5,4)) -> 2023 | K2: =_xlfn.NUMBERVALUE(RIGHT(K5,4)) -> 2025 | L2: =_xlfn.NUMBERVALUE(RIGHT(L5,4)) -> 2030 | M2: =_xlfn.NUMBERVALUE(RIGHT(M5,4)) -> 2035 | N2: =_xlfn.NUMBERVALUE(RIGHT(N5,4)) -> 2040 | ... Q2: =_xlfn.NUMBERVALUE(RIGHT(Q5,4)) -> 2055
B3: *Source: DemandCalc | S3: Source: Time Slice File from EPA
G4: ~FI_T
B5: Region | C5: CommName | D5: *Comm Match | E5: *CommDesc | F5: *Units | G5: COM_PROJ~2010 | H5: COM_PROJ~2015 | I5: COM_PROJ~2020 | J5: COM_PROJ~2023 | K5: COM_PROJ~2025 | L5: COM_PROJ~2030 | M5: COM_PROJ~2035 | N5: COM_PROJ~2040 | O5: COM_PROJ~2045 | P5: COM_PROJ~2050 | Q5: COM_PROJ~2055 | R5: *TIME SLICES | S5: COM_FR~IDAM | T5: COM_FR~IDPM | U5: COM_FR~IN | V5: COM_FR~IP | W5: COM_FR~SDAM | X5: COM_FR~SDPM | Y5: COM_FR~SN | Z5: COM_FR~SP | AA5: COM_FR~WDAM | AB5: COM_FR~WDPM | AC5: COM_FR~WN | AD5: COM_FR~WP
B6: R2,R3,R4,R5,R6 | C6: ISH | D6: Space Heating | E6: Industrial Heating | F6: PJ | G6: =IF(G$2<YEAR(TODAY()),SUMIF(DemandPJ_historic[Year],CommDemand!G$2,_xlfn.XLOOKUP(CommDemand!$D6,DemandPJ_historic[#Headers],DemandPJ_historic[])), SUMIF(DemandPJ_projection[Year],CommDemand!G$2,_xlfn.XLOOKUP(CommDemand!$D6,DemandPJ_projection[#Headers],DemandPJ_projection[])))/5 -> 6.0169066 | H6: =IF(H$2<YEAR(TODAY()),SUMIF(DemandPJ_historic[Year],CommDemand!H$2,_xlfn.XLOOKUP(CommDemand!$D6,DemandPJ_historic[#Headers],DemandPJ_historic[])), SUMIF(DemandPJ_projection[Year],CommDemand!H$2,_xlfn.XLOOKUP(CommDemand!$D6,DemandPJ_projection[#Headers],DemandPJ_projection[])))/5 -> 6.761468 | I6: =IF(I$2<YEAR(TODAY()),SUMIF(DemandPJ_historic[Year],CommDemand!I$2,_xlfn.XLOOKUP(CommDemand!$D6,DemandPJ_historic[#Headers],DemandPJ_historic[])), SUMIF(DemandPJ_projection[Year],CommDemand!I$2,_xlfn.XLOOKUP(CommDemand!$D6,DemandPJ_projection[#Headers],DemandPJ_projection[])))/5 -> 6.4221479 | J6: =IF(J$2<YEAR(TODAY()),SUMIF(DemandPJ_historic[Year],CommDemand!J$2,_xlfn.XLOOKUP(CommDemand!$D6,DemandPJ_historic[#Headers],DemandPJ_historic[])), SUMIF(DemandPJ_projection[Year],CommDemand!J$2,_xlfn.XLOOKUP(CommDemand!$D6,DemandPJ_projection[#Headers],DemandPJ_projection[])))/5 -> 4.0412745 | K6: =IF(K$2<YEAR(TODAY()),SUMIF(DemandPJ_historic[Year],CommDemand!K$2,_xlfn.XLOOKUP(CommDemand!$D6,DemandPJ_historic[#Headers],DemandPJ_historic[])), SUMIF(DemandPJ_projection[Year],CommDemand!K$2,_xlfn.XLOOKUP(CommDemand!$D6,DemandPJ_projection[#Headers],DemandPJ_projection[])))/5 -> 3.885552 | L6: =IF(L$2<YEAR(TODAY()),SUMIF(DemandPJ_historic[Year],CommDemand!L$2,_xlfn.XLOOKUP(CommDemand!$D6,DemandPJ_historic[#Headers],DemandPJ_historic[])), SUMIF(DemandPJ_projection[Year],CommDemand!L$2,_xlfn.XLOOKUP(CommDemand!$D6,DemandPJ_projection[#Headers],DemandPJ_projection[])))/5 -> 3.7208848 | M6: =IF(M$2<YEAR(TODAY()),SUMIF(DemandPJ_historic[Year],CommDemand!M$2,_xlfn.XLOOKUP(CommDemand!$D6,DemandPJ_historic[#Headers],DemandPJ_historic[])), SUMIF(DemandPJ_projection[Year],CommDemand!M$2,_xlfn.XLOOKUP(CommDemand!$D6,DemandPJ_projection[#Headers],DemandPJ_projection[])))/5 -> 3.5446772 | N6: =IF(N$2<YEAR(TODAY()),SUMIF(DemandPJ_historic[Year],CommDemand!N$2,_xlfn.XLOOKUP(CommDemand!$D6,DemandPJ_historic[#Headers],DemandPJ_historic[])), SUMIF(DemandPJ_projection[Year],CommDemand!N$2,_xlfn.XLOOKUP(CommDemand!$D6,DemandPJ_projection[#Headers],DemandPJ_projection[])))/5 -> 3.4468983 | ... Q6: =IF(Q$2<YEAR(TODAY()),SUMIF(DemandPJ_historic[Year],CommDemand!Q$2,_xlfn.XLOOKUP(CommDemand!$D6,DemandPJ_historic[#Headers],DemandPJ_historic[])), SUMIF(DemandPJ_projection[Year],CommDemand!Q$2,_xlfn.XLOOKUP(CommDemand!$D6,DemandPJ_projection[#Headers],DemandPJ_projection[])))/5 -> 3.7208848 | R6: INDSHXXX | S6: 0.09583747 | T6: 0.10546803 | U6: 0.12880173 | V6: 0.00422628 | W6: 0.10930424 | X6: 0.11723673 | Y6: 0.10392567 | Z6: 0.0038677 | AA6: 0.09489002 | AB6: 0.11774265 | AC6: 0.11453188 | AD6: 0.0041676
B7: R2,R3,R4,R5,R6 | C7: ISC | D7: Space Cooling | E7: Industrial Cooling | F7: PJ | G7: =IF(G$2<YEAR(TODAY()),SUMIF(DemandPJ_historic[Year],CommDemand!G$2,_xlfn.XLOOKUP(CommDemand!$D7,DemandPJ_historic[#Headers],DemandPJ_historic[])), SUMIF(DemandPJ_projection[Year],CommDemand!G$2,_xlfn.XLOOKUP(CommDemand!$D7,DemandPJ_projection[#Headers],DemandPJ_projection[])))/5 -> 0.82556489 | H7: =IF(H$2<YEAR(TODAY()),SUMIF(DemandPJ_historic[Year],CommDemand!H$2,_xlfn.XLOOKUP(CommDemand!$D7,DemandPJ_historic[#Headers],DemandPJ_historic[])), SUMIF(DemandPJ_projection[Year],CommDemand!H$2,_xlfn.XLOOKUP(CommDemand!$D7,DemandPJ_projection[#Headers],DemandPJ_projection[])))/5 -> 0.83968448 | I7: =IF(I$2<YEAR(TODAY()),SUMIF(DemandPJ_historic[Year],CommDemand!I$2,_xlfn.XLOOKUP(CommDemand!$D7,DemandPJ_historic[#Headers],DemandPJ_historic[])), SUMIF(DemandPJ_projection[Year],CommDemand!I$2,_xlfn.XLOOKUP(CommDemand!$D7,DemandPJ_projection[#Headers],DemandPJ_projection[])))/5 -> 0.6845701 | J7: =IF(J$2<YEAR(TODAY()),SUMIF(DemandPJ_historic[Year],CommDemand!J$2,_xlfn.XLOOKUP(CommDemand!$D7,DemandPJ_historic[#Headers],DemandPJ_historic[])), SUMIF(DemandPJ_projection[Year],CommDemand!J$2,_xlfn.XLOOKUP(CommDemand!$D7,DemandPJ_projection[#Headers],DemandPJ_projection[])))/5 -> 0.74225732 | K7: =IF(K$2<YEAR(TODAY()),SUMIF(DemandPJ_historic[Year],CommDemand!K$2,_xlfn.XLOOKUP(CommDemand!$D7,DemandPJ_historic[#Headers],DemandPJ_historic[])), SUMIF(DemandPJ_projection[Year],CommDemand!K$2,_xlfn.XLOOKUP(CommDemand!$D7,DemandPJ_projection[#Headers],DemandPJ_projection[])))/5 -> 0.72605622 | L7: =IF(L$2<YEAR(TODAY()),SUMIF(DemandPJ_historic[Year],CommDemand!L$2,_xlfn.XLOOKUP(CommDemand!$D7,DemandPJ_historic[#Headers],DemandPJ_historic[])), SUMIF(DemandPJ_projection[Year],CommDemand!L$2,_xlfn.XLOOKUP(CommDemand!$D7,DemandPJ_projection[#Headers],DemandPJ_projection[])))/5 -> 0.73787665 | M7: =IF(M$2<YEAR(TODAY()),SUMIF(DemandPJ_historic[Year],CommDemand!M$2,_xlfn.XLOOKUP(CommDemand!$D7,DemandPJ_historic[#Headers],DemandPJ_historic[])), SUMIF(DemandPJ_projection[Year],CommDemand!M$2,_xlfn.XLOOKUP(CommDemand!$D7,DemandPJ_projection[#Headers],DemandPJ_projection[])))/5 -> 0.75251792 | N7: =IF(N$2<YEAR(TODAY()),SUMIF(DemandPJ_historic[Year],CommDemand!N$2,_xlfn.XLOOKUP(CommDemand!$D7,DemandPJ_historic[#Headers],DemandPJ_historic[])), SUMIF(DemandPJ_projection[Year],CommDemand!N$2,_xlfn.XLOOKUP(CommDemand!$D7,DemandPJ_projection[#Headers],DemandPJ_projection[])))/5 -> 0.77250658 | ... Q7: =IF(Q$2<YEAR(TODAY()),SUMIF(DemandPJ_historic[Year],CommDemand!Q$2,_xlfn.XLOOKUP(CommDemand!$D7,DemandPJ_historic[#Headers],DemandPJ_historic[])), SUMIF(DemandPJ_projection[Year],CommDemand!Q$2,_xlfn.XLOOKUP(CommDemand!$D7,DemandPJ_projection[#Headers],DemandPJ_projection[])))/5 -> 0.73787665 | R7: COMSCN01 | S7: 0.023994 | T7: 0.051143 | U7: 0.024568 | V7: 0.001637 | W7: 0.253683 | X7: 0.430038 | Y7: 0.187488 | Z7: 0.017988 | AA7: 0.001904 | AB7: 0.005149 | AC7: 0.002233 | AD7: 0.000175
B8: R2,R3,R4,R5,R6 | C8: IWH | D8: DHW | E8: Industrial Water Heating | F8: PJ | G8: =IF(G$2<YEAR(TODAY()),SUMIF(DemandPJ_historic[Year],CommDemand!G$2,_xlfn.XLOOKUP(CommDemand!$D8,DemandPJ_historic[#Headers],DemandPJ_historic[])), SUMIF(DemandPJ_projection[Year],CommDemand!G$2,_xlfn.XLOOKUP(CommDemand!$D8,DemandPJ_projection[#Headers],DemandPJ_projection[])))/5 -> 0.56345289 | H8: =IF(H$2<YEAR(TODAY()),SUMIF(DemandPJ_historic[Year],CommDemand!H$2,_xlfn.XLOOKUP(CommDemand!$D8,DemandPJ_historic[#Headers],DemandPJ_historic[])), SUMIF(DemandPJ_projection[Year],CommDemand!H$2,_xlfn.XLOOKUP(CommDemand!$D8,DemandPJ_projection[#Headers],DemandPJ_projection[])))/5 -> 0.5676364 | I8: =IF(I$2<YEAR(TODAY()),SUMIF(DemandPJ_historic[Year],CommDemand!I$2,_xlfn.XLOOKUP(CommDemand!$D8,DemandPJ_historic[#Headers],DemandPJ_historic[])), SUMIF(DemandPJ_projection[Year],CommDemand!I$2,_xlfn.XLOOKUP(CommDemand!$D8,DemandPJ_projection[#Headers],DemandPJ_projection[])))/5 -> 0.46820617 | J8: =IF(J$2<YEAR(TODAY()),SUMIF(DemandPJ_historic[Year],CommDemand!J$2,_xlfn.XLOOKUP(CommDemand!$D8,DemandPJ_historic[#Headers],DemandPJ_historic[])), SUMIF(DemandPJ_projection[Year],CommDemand!J$2,_xlfn.XLOOKUP(CommDemand!$D8,DemandPJ_projection[#Headers],DemandPJ_projection[])))/5 -> 0.38960223 | K8: =IF(K$2<YEAR(TODAY()),SUMIF(DemandPJ_historic[Year],CommDemand!K$2,_xlfn.XLOOKUP(CommDemand!$D8,DemandPJ_historic[#Headers],DemandPJ_historic[])), SUMIF(DemandPJ_projection[Year],CommDemand!K$2,_xlfn.XLOOKUP(CommDemand!$D8,DemandPJ_projection[#Headers],DemandPJ_projection[])))/5 -> 0.36767921 | L8: =IF(L$2<YEAR(TODAY()),SUMIF(DemandPJ_historic[Year],CommDemand!L$2,_xlfn.XLOOKUP(CommDemand!$D8,DemandPJ_historic[#Headers],DemandPJ_historic[])), SUMIF(DemandPJ_projection[Year],CommDemand!L$2,_xlfn.XLOOKUP(CommDemand!$D8,DemandPJ_projection[#Headers],DemandPJ_projection[])))/5 -> 0.35032438 | M8: =IF(M$2<YEAR(TODAY()),SUMIF(DemandPJ_historic[Year],CommDemand!M$2,_xlfn.XLOOKUP(CommDemand!$D8,DemandPJ_historic[#Headers],DemandPJ_historic[])), SUMIF(DemandPJ_projection[Year],CommDemand!M$2,_xlfn.XLOOKUP(CommDemand!$D8,DemandPJ_projection[#Headers],DemandPJ_projection[])))/5 -> 0.33639626 | N8: =IF(N$2<YEAR(TODAY()),SUMIF(DemandPJ_historic[Year],CommDemand!N$2,_xlfn.XLOOKUP(CommDemand!$D8,DemandPJ_historic[#Headers],DemandPJ_historic[])), SUMIF(DemandPJ_projection[Year],CommDemand!N$2,_xlfn.XLOOKUP(CommDemand!$D8,DemandPJ_projection[#Headers],DemandPJ_projection[])))/5 -> 0.32582419 | ... Q8: =IF(Q$2<YEAR(TODAY()),SUMIF(DemandPJ_historic[Year],CommDemand!Q$2,_xlfn.XLOOKUP(CommDemand!$D8,DemandPJ_historic[#Headers],DemandPJ_historic[])), SUMIF(DemandPJ_projection[Year],CommDemand!Q$2,_xlfn.XLOOKUP(CommDemand!$D8,DemandPJ_projection[#Headers],DemandPJ_projection[])))/5 -> 0.35032438 | R8: COMWHXXX | S8: 0.084433 | T8: 0.186457 | U8: 0.071359 | V8: 0.004134 | W8: 0.069288 | X8: 0.146371 | Y8: 0.042195 | Z8: 0.004794 | AA8: 0.096436 | AB8: 0.227751 | AC8: 0.062395 | AD8: 0.004387
B9: R2,R3,R4,R5,R6 | C9: ILT | D9: Lighting | E9: Industrial Lighting | F9: PJ | G9: =IF(G$2<YEAR(TODAY()),SUMIF(DemandPJ_historic[Year],CommDemand!G$2,_xlfn.XLOOKUP(CommDemand!$D9,DemandPJ_historic[#Headers],DemandPJ_historic[])), SUMIF(DemandPJ_projection[Year],CommDemand!G$2,_xlfn.XLOOKUP(CommDemand!$D9,DemandPJ_projection[#Headers],DemandPJ_projection[])))/5 -> 2.5771532 | H9: =IF(H$2<YEAR(TODAY()),SUMIF(DemandPJ_historic[Year],CommDemand!H$2,_xlfn.XLOOKUP(CommDemand!$D9,DemandPJ_historic[#Headers],DemandPJ_historic[])), SUMIF(DemandPJ_projection[Year],CommDemand!H$2,_xlfn.XLOOKUP(CommDemand!$D9,DemandPJ_projection[#Headers],DemandPJ_projection[])))/5 -> 2.6212301 | I9: =IF(I$2<YEAR(TODAY()),SUMIF(DemandPJ_historic[Year],CommDemand!I$2,_xlfn.XLOOKUP(CommDemand!$D9,DemandPJ_historic[#Headers],DemandPJ_historic[])), SUMIF(DemandPJ_projection[Year],CommDemand!I$2,_xlfn.XLOOKUP(CommDemand!$D9,DemandPJ_projection[#Headers],DemandPJ_projection[])))/5 -> 2.137012 | J9: =IF(J$2<YEAR(TODAY()),SUMIF(DemandPJ_historic[Year],CommDemand!J$2,_xlfn.XLOOKUP(CommDemand!$D9,DemandPJ_historic[#Headers],DemandPJ_historic[])), SUMIF(DemandPJ_projection[Year],CommDemand!J$2,_xlfn.XLOOKUP(CommDemand!$D9,DemandPJ_projection[#Headers],DemandPJ_projection[])))/5 -> 2.3170933 | K9: =IF(K$2<YEAR(TODAY()),SUMIF(DemandPJ_historic[Year],CommDemand!K$2,_xlfn.XLOOKUP(CommDemand!$D9,DemandPJ_historic[#Headers],DemandPJ_historic[])), SUMIF(DemandPJ_projection[Year],CommDemand!K$2,_xlfn.XLOOKUP(CommDemand!$D9,DemandPJ_projection[#Headers],DemandPJ_projection[])))/5 -> 2.2665186 | L9: =IF(L$2<YEAR(TODAY()),SUMIF(DemandPJ_historic[Year],CommDemand!L$2,_xlfn.XLOOKUP(CommDemand!$D9,DemandPJ_historic[#Headers],DemandPJ_historic[])), SUMIF(DemandPJ_projection[Year],CommDemand!L$2,_xlfn.XLOOKUP(CommDemand!$D9,DemandPJ_projection[#Headers],DemandPJ_projection[])))/5 -> 2.3034182 | M9: =IF(M$2<YEAR(TODAY()),SUMIF(DemandPJ_historic[Year],CommDemand!M$2,_xlfn.XLOOKUP(CommDemand!$D9,DemandPJ_historic[#Headers],DemandPJ_historic[])), SUMIF(DemandPJ_projection[Year],CommDemand!M$2,_xlfn.XLOOKUP(CommDemand!$D9,DemandPJ_projection[#Headers],DemandPJ_projection[])))/5 -> 2.3491236 | N9: =IF(N$2<YEAR(TODAY()),SUMIF(DemandPJ_historic[Year],CommDemand!N$2,_xlfn.XLOOKUP(CommDemand!$D9,DemandPJ_historic[#Headers],DemandPJ_historic[])), SUMIF(DemandPJ_projection[Year],CommDemand!N$2,_xlfn.XLOOKUP(CommDemand!$D9,DemandPJ_projection[#Headers],DemandPJ_projection[])))/5 -> 2.4115219 | ... Q9: =IF(Q$2<YEAR(TODAY()),SUMIF(DemandPJ_historic[Year],CommDemand!Q$2,_xlfn.XLOOKUP(CommDemand!$D9,DemandPJ_historic[#Headers],DemandPJ_historic[])), SUMIF(DemandPJ_projection[Year],CommDemand!Q$2,_xlfn.XLOOKUP(CommDemand!$D9,DemandPJ_projection[#Headers],DemandPJ_projection[])))/5 -> 2.3034182 | R9: COMLTXXX | S9: 0.099018 | T9: 0.144386 | U9: 0.092335 | V9: 0.004213 | W9: 0.099233 | X9: 0.1494 | Y9: 0.071368 | Z9: 0.004574 | AA9: 0.096951 | AB9: 0.156721 | AC9: 0.07783 | AD9: 0.003971
B10: *R2,R3,R4,R5,R6 | C10: IVTE | D10: Ventilation | E10: Industrial Ventilation, E | F10: PJ | G10: =IF(G$2<YEAR(TODAY()),SUMIFS(_xlfn.XLOOKUP(CommDemand!$D10,DemandPJ_historic[#Headers],DemandPJ_historic[]),DemandPJ_historic[Year],CommDemand!G$2,DemandPJ_historic[Fuel],"ELC"), SUMIFS(_xlfn.XLOOKUP(CommDemand!$D10,DemandPJ_projection[#Headers],DemandPJ_projection[]),DemandPJ_projection[Year],CommDemand!G$2,DemandPJ_projection[Fuel],"ELC"))/5 -> 0.54680551 | H10: =IF(H$2<YEAR(TODAY()),SUMIFS(_xlfn.XLOOKUP(CommDemand!$D10,DemandPJ_historic[#Headers],DemandPJ_historic[]),DemandPJ_historic[Year],CommDemand!H$2,DemandPJ_historic[Fuel],"ELC"), SUMIFS(_xlfn.XLOOKUP(CommDemand!$D10,DemandPJ_projection[#Headers],DemandPJ_projection[]),DemandPJ_projection[Year],CommDemand!H$2,DemandPJ_projection[Fuel],"ELC"))/5 -> 0.5561575 | I10: =IF(I$2<YEAR(TODAY()),SUMIFS(_xlfn.XLOOKUP(CommDemand!$D10,DemandPJ_historic[#Headers],DemandPJ_historic[]),DemandPJ_historic[Year],CommDemand!I$2,DemandPJ_historic[Fuel],"ELC"), SUMIFS(_xlfn.XLOOKUP(CommDemand!$D10,DemandPJ_projection[#Headers],DemandPJ_projection[]),DemandPJ_projection[Year],CommDemand!I$2,DemandPJ_projection[Fuel],"ELC"))/5 -> 0.45341888 | J10: =IF(J$2<YEAR(TODAY()),SUMIFS(_xlfn.XLOOKUP(CommDemand!$D10,DemandPJ_historic[#Headers],DemandPJ_historic[]),DemandPJ_historic[Year],CommDemand!J$2,DemandPJ_historic[Fuel],"ELC"), SUMIFS(_xlfn.XLOOKUP(CommDemand!$D10,DemandPJ_projection[#Headers],DemandPJ_projection[]),DemandPJ_projection[Year],CommDemand!J$2,DemandPJ_projection[Fuel],"ELC"))/5 -> 0.49162749 | K10: =IF(K$2<YEAR(TODAY()),SUMIFS(_xlfn.XLOOKUP(CommDemand!$D10,DemandPJ_historic[#Headers],DemandPJ_historic[]),DemandPJ_historic[Year],CommDemand!K$2,DemandPJ_historic[Fuel],"ELC"), SUMIFS(_xlfn.XLOOKUP(CommDemand!$D10,DemandPJ_projection[#Headers],DemandPJ_projection[]),DemandPJ_projection[Year],CommDemand!K$2,DemandPJ_projection[Fuel],"ELC"))/5 -> 0.48089684 | L10: =IF(L$2<YEAR(TODAY()),SUMIFS(_xlfn.XLOOKUP(CommDemand!$D10,DemandPJ_historic[#Headers],DemandPJ_historic[]),DemandPJ_historic[Year],CommDemand!L$2,DemandPJ_historic[Fuel],"ELC"), SUMIFS(_xlfn.XLOOKUP(CommDemand!$D10,DemandPJ_projection[#Headers],DemandPJ_projection[]),DemandPJ_projection[Year],CommDemand!L$2,DemandPJ_projection[Fuel],"ELC"))/5 -> 0.48872599 | M10: =IF(M$2<YEAR(TODAY()),SUMIFS(_xlfn.XLOOKUP(CommDemand!$D10,DemandPJ_historic[#Headers],DemandPJ_historic[]),DemandPJ_historic[Year],CommDemand!M$2,DemandPJ_historic[Fuel],"ELC"), SUMIFS(_xlfn.XLOOKUP(CommDemand!$D10,DemandPJ_projection[#Headers],DemandPJ_projection[]),DemandPJ_projection[Year],CommDemand!M$2,DemandPJ_projection[Fuel],"ELC"))/5 -> 0.49842351 | N10: =IF(N$2<YEAR(TODAY()),SUMIFS(_xlfn.XLOOKUP(CommDemand!$D10,DemandPJ_historic[#Headers],DemandPJ_historic[]),DemandPJ_historic[Year],CommDemand!N$2,DemandPJ_historic[Fuel],"ELC"), SUMIFS(_xlfn.XLOOKUP(CommDemand!$D10,DemandPJ_projection[#Headers],DemandPJ_projection[]),DemandPJ_projection[Year],CommDemand!N$2,DemandPJ_projection[Fuel],"ELC"))/5 -> 0.51166282 | ... Q10: =IF(Q$2<YEAR(TODAY()),SUMIFS(_xlfn.XLOOKUP(CommDemand!$D10,DemandPJ_historic[#Headers],DemandPJ_historic[]),DemandPJ_historic[Year],CommDemand!Q$2,DemandPJ_historic[Fuel],"ELC"), SUMIFS(_xlfn.XLOOKUP(CommDemand!$D10,DemandPJ_projection[#Headers],DemandPJ_projection[]),DemandPJ_projection[Year],CommDemand!Q$2,DemandPJ_projection[Fuel],"ELC"))/5 -> 0.48872599 | R10: COMVTXXX | S10: 0.08349393 | T10: 0.103057 | U10: 0.15240839 | V10: 0.00346679 | W10: 0.10221035 | X10: 0.11540133 | Y10: 0.12991177 | Z10: 0.00289949 | AA10: 0.07424331 | AB10: 0.10591607 | AC10: 0.12385355 | AD10: 0.00313802
B11: *R2,R3,R4,R5,R6 | C11: IVTF | D11: Ventilation | E11: Industrial Ventilation, F | F11: PJ | G11: =(IF(G$2<YEAR(TODAY()),SUMIF(DemandPJ_historic[Year],CommDemand!G$2,_xlfn.XLOOKUP(CommDemand!$D11,DemandPJ_historic[#Headers],DemandPJ_historic[])), SUMIF(DemandPJ_projection[Year],CommDemand!G$2,_xlfn.XLOOKUP(CommDemand!$D11,DemandPJ_projection[#Headers],DemandPJ_projection[])))/5)-G10 -> 0 | H11: =(IF(H$2<YEAR(TODAY()),SUMIF(DemandPJ_historic[Year],CommDemand!H$2,_xlfn.XLOOKUP(CommDemand!$D11,DemandPJ_historic[#Headers],DemandPJ_historic[])), SUMIF(DemandPJ_projection[Year],CommDemand!H$2,_xlfn.XLOOKUP(CommDemand!$D11,DemandPJ_projection[#Headers],DemandPJ_projection[])))/5)-H10 -> 0 | I11: =(IF(I$2<YEAR(TODAY()),SUMIF(DemandPJ_historic[Year],CommDemand!I$2,_xlfn.XLOOKUP(CommDemand!$D11,DemandPJ_historic[#Headers],DemandPJ_historic[])), SUMIF(DemandPJ_projection[Year],CommDemand!I$2,_xlfn.XLOOKUP(CommDemand!$D11,DemandPJ_projection[#Headers],DemandPJ_projection[])))/5)-I10 -> 0 | J11: =(IF(J$2<YEAR(TODAY()),SUMIF(DemandPJ_historic[Year],CommDemand!J$2,_xlfn.XLOOKUP(CommDemand!$D11,DemandPJ_historic[#Headers],DemandPJ_historic[])), SUMIF(DemandPJ_projection[Year],CommDemand!J$2,_xlfn.XLOOKUP(CommDemand!$D11,DemandPJ_projection[#Headers],DemandPJ_projection[])))/5)-J10 -> 0 | K11: =(IF(K$2<YEAR(TODAY()),SUMIF(DemandPJ_historic[Year],CommDemand!K$2,_xlfn.XLOOKUP(CommDemand!$D11,DemandPJ_historic[#Headers],DemandPJ_historic[])), SUMIF(DemandPJ_projection[Year],CommDemand!K$2,_xlfn.XLOOKUP(CommDemand!$D11,DemandPJ_projection[#Headers],DemandPJ_projection[])))/5)-K10 -> 0 | L11: =(IF(L$2<YEAR(TODAY()),SUMIF(DemandPJ_historic[Year],CommDemand!L$2,_xlfn.XLOOKUP(CommDemand!$D11,DemandPJ_historic[#Headers],DemandPJ_historic[])), SUMIF(DemandPJ_projection[Year],CommDemand!L$2,_xlfn.XLOOKUP(CommDemand!$D11,DemandPJ_projection[#Headers],DemandPJ_projection[])))/5)-L10 -> 0 | M11: =(IF(M$2<YEAR(TODAY()),SUMIF(DemandPJ_historic[Year],CommDemand!M$2,_xlfn.XLOOKUP(CommDemand!$D11,DemandPJ_historic[#Headers],DemandPJ_historic[])), SUMIF(DemandPJ_projection[Year],CommDemand!M$2,_xlfn.XLOOKUP(CommDemand!$D11,DemandPJ_projection[#Headers],DemandPJ_projection[])))/5)-M10 -> 0 | N11: =(IF(N$2<YEAR(TODAY()),SUMIF(DemandPJ_historic[Year],CommDemand!N$2,_xlfn.XLOOKUP(CommDemand!$D11,DemandPJ_historic[#Headers],DemandPJ_historic[])), SUMIF(DemandPJ_projection[Year],CommDemand!N$2,_xlfn.XLOOKUP(CommDemand!$D11,DemandPJ_projection[#Headers],DemandPJ_projection[])))/5)-N10 -> 0 | ... Q11: =(IF(Q$2<YEAR(TODAY()),SUMIF(DemandPJ_historic[Year],CommDemand!Q$2,_xlfn.XLOOKUP(CommDemand!$D11,DemandPJ_historic[#Headers],DemandPJ_historic[])), SUMIF(DemandPJ_projection[Year],CommDemand!Q$2,_xlfn.XLOOKUP(CommDemand!$D11,DemandPJ_projection[#Headers],DemandPJ_projection[])))/5)-Q10 -> 0 | R11: COMVTXXX | S11: 0.08349393 | T11: 0.103057 | U11: 0.15240839 | V11: 0.00346679 | W11: 0.10221035 | X11: 0.11540133 | Y11: 0.12991177 | Z11: 0.00289949 | AA11: 0.07424331 | AB11: 0.10591607 | AC11: 0.12385355 | AD11: 0.00313802
B12: *R2,R3,R4,R5,R6 | C12: ICOE | D12: Conveyance | E12: Industrial Conveyance, E | F12: PJ | G12: =IF(G$2<YEAR(TODAY()),SUMIFS(_xlfn.XLOOKUP(CommDemand!$D12,DemandPJ_historic[#Headers],DemandPJ_historic[]),DemandPJ_historic[Year],CommDemand!G$2,DemandPJ_historic[Fuel],"ELC"), SUMIFS(_xlfn.XLOOKUP(CommDemand!$D12,DemandPJ_projection[#Headers],DemandPJ_projection[]),DemandPJ_projection[Year],CommDemand!G$2,DemandPJ_projection[Fuel],"ELC"))/5 -> 0.38878958 | H12: =IF(H$2<YEAR(TODAY()),SUMIFS(_xlfn.XLOOKUP(CommDemand!$D12,DemandPJ_historic[#Headers],DemandPJ_historic[]),DemandPJ_historic[Year],CommDemand!H$2,DemandPJ_historic[Fuel],"ELC"), SUMIFS(_xlfn.XLOOKUP(CommDemand!$D12,DemandPJ_projection[#Headers],DemandPJ_projection[]),DemandPJ_projection[Year],CommDemand!H$2,DemandPJ_projection[Fuel],"ELC"))/5 -> 0.39543903 | I12: =IF(I$2<YEAR(TODAY()),SUMIFS(_xlfn.XLOOKUP(CommDemand!$D12,DemandPJ_historic[#Headers],DemandPJ_historic[]),DemandPJ_historic[Year],CommDemand!I$2,DemandPJ_historic[Fuel],"ELC"), SUMIFS(_xlfn.XLOOKUP(CommDemand!$D12,DemandPJ_projection[#Headers],DemandPJ_projection[]),DemandPJ_projection[Year],CommDemand!I$2,DemandPJ_projection[Fuel],"ELC"))/5 -> 0.32238983 | J12: =IF(J$2<YEAR(TODAY()),SUMIFS(_xlfn.XLOOKUP(CommDemand!$D12,DemandPJ_historic[#Headers],DemandPJ_historic[]),DemandPJ_historic[Year],CommDemand!J$2,DemandPJ_historic[Fuel],"ELC"), SUMIFS(_xlfn.XLOOKUP(CommDemand!$D12,DemandPJ_projection[#Headers],DemandPJ_projection[]),DemandPJ_projection[Year],CommDemand!J$2,DemandPJ_projection[Fuel],"ELC"))/5 -> 0.34955691 | K12: =IF(K$2<YEAR(TODAY()),SUMIFS(_xlfn.XLOOKUP(CommDemand!$D12,DemandPJ_historic[#Headers],DemandPJ_historic[]),DemandPJ_historic[Year],CommDemand!K$2,DemandPJ_historic[Fuel],"ELC"), SUMIFS(_xlfn.XLOOKUP(CommDemand!$D12,DemandPJ_projection[#Headers],DemandPJ_projection[]),DemandPJ_projection[Year],CommDemand!K$2,DemandPJ_projection[Fuel],"ELC"))/5 -> 0.34192721 | L12: =IF(L$2<YEAR(TODAY()),SUMIFS(_xlfn.XLOOKUP(CommDemand!$D12,DemandPJ_historic[#Headers],DemandPJ_historic[]),DemandPJ_historic[Year],CommDemand!L$2,DemandPJ_historic[Fuel],"ELC"), SUMIFS(_xlfn.XLOOKUP(CommDemand!$D12,DemandPJ_projection[#Headers],DemandPJ_projection[]),DemandPJ_projection[Year],CommDemand!L$2,DemandPJ_projection[Fuel],"ELC"))/5 -> 0.34749389 | M12: =IF(M$2<YEAR(TODAY()),SUMIFS(_xlfn.XLOOKUP(CommDemand!$D12,DemandPJ_historic[#Headers],DemandPJ_historic[]),DemandPJ_historic[Year],CommDemand!M$2,DemandPJ_historic[Fuel],"ELC"), SUMIFS(_xlfn.XLOOKUP(CommDemand!$D12,DemandPJ_projection[#Headers],DemandPJ_projection[]),DemandPJ_projection[Year],CommDemand!M$2,DemandPJ_projection[Fuel],"ELC"))/5 -> 0.35438902 | N12: =IF(N$2<YEAR(TODAY()),SUMIFS(_xlfn.XLOOKUP(CommDemand!$D12,DemandPJ_historic[#Headers],DemandPJ_historic[]),DemandPJ_historic[Year],CommDemand!N$2,DemandPJ_historic[Fuel],"ELC"), SUMIFS(_xlfn.XLOOKUP(CommDemand!$D12,DemandPJ_projection[#Headers],DemandPJ_projection[]),DemandPJ_projection[Year],CommDemand!N$2,DemandPJ_projection[Fuel],"ELC"))/5 -> 0.36380243 | ... Q12: =IF(Q$2<YEAR(TODAY()),SUMIFS(_xlfn.XLOOKUP(CommDemand!$D12,DemandPJ_historic[#Headers],DemandPJ_historic[]),DemandPJ_historic[Year],CommDemand!Q$2,DemandPJ_historic[Fuel],"ELC"), SUMIFS(_xlfn.XLOOKUP(CommDemand!$D12,DemandPJ_projection[#Headers],DemandPJ_projection[]),DemandPJ_projection[Year],CommDemand!Q$2,DemandPJ_projection[Fuel],"ELC"))/5 -> 0.34749389 | R12: COMCOXXX | S12: 0.095411 | T12: 0.17413 | U12: 0.067175 | V12: 0.003466 | W12: 0.089708 | X12: 0.185882 | Y12: 0.042992 | Z12: 0.004953 | AA12: 0.093811 | AB12: 0.194873 | AC12: 0.043932 | AD12: 0.003667
C13: ICOE | D13: Conveyance | E13: Industrial Conveyance, F | F13: PJ | G13: =(IF(G$2<YEAR(TODAY()),SUMIF(DemandPJ_historic[Year],CommDemand!G$2,_xlfn.XLOOKUP(CommDemand!$D13,DemandPJ_historic[#Headers],DemandPJ_historic[])), SUMIF(DemandPJ_projection[Year],CommDemand!G$2,_xlfn.XLOOKUP(CommDemand!$D13,DemandPJ_projection[#Headers],DemandPJ_projection[])))/5)-G12 -> 0 | H13: =(IF(H$2<YEAR(TODAY()),SUMIF(DemandPJ_historic[Year],CommDemand!H$2,_xlfn.XLOOKUP(CommDemand!$D13,DemandPJ_historic[#Headers],DemandPJ_historic[])), SUMIF(DemandPJ_projection[Year],CommDemand!H$2,_xlfn.XLOOKUP(CommDemand!$D13,DemandPJ_projection[#Headers],DemandPJ_projection[])))/5)-H12 -> 0 | I13: =(IF(I$2<YEAR(TODAY()),SUMIF(DemandPJ_historic[Year],CommDemand!I$2,_xlfn.XLOOKUP(CommDemand!$D13,DemandPJ_historic[#Headers],DemandPJ_historic[])), SUMIF(DemandPJ_projection[Year],CommDemand!I$2,_xlfn.XLOOKUP(CommDemand!$D13,DemandPJ_projection[#Headers],DemandPJ_projection[])))/5)-I12 -> 0 | J13: =(IF(J$2<YEAR(TODAY()),SUMIF(DemandPJ_historic[Year],CommDemand!J$2,_xlfn.XLOOKUP(CommDemand!$D13,DemandPJ_historic[#Headers],DemandPJ_historic[])), SUMIF(DemandPJ_projection[Year],CommDemand!J$2,_xlfn.XLOOKUP(CommDemand!$D13,DemandPJ_projection[#Headers],DemandPJ_projection[])))/5)-J12 -> 0 | K13: =(IF(K$2<YEAR(TODAY()),SUMIF(DemandPJ_historic[Year],CommDemand!K$2,_xlfn.XLOOKUP(CommDemand!$D13,DemandPJ_historic[#Headers],DemandPJ_historic[])), SUMIF(DemandPJ_projection[Year],CommDemand!K$2,_xlfn.XLOOKUP(CommDemand!$D13,DemandPJ_projection[#Headers],DemandPJ_projection[])))/5)-K12 -> 0 | L13: =(IF(L$2<YEAR(TODAY()),SUMIF(DemandPJ_historic[Year],CommDemand!L$2,_xlfn.XLOOKUP(CommDemand!$D13,DemandPJ_historic[#Headers],DemandPJ_historic[])), SUMIF(DemandPJ_projection[Year],CommDemand!L$2,_xlfn.XLOOKUP(CommDemand!$D13,DemandPJ_projection[#Headers],DemandPJ_projection[])))/5)-L12 -> 0 | M13: =(IF(M$2<YEAR(TODAY()),SUMIF(DemandPJ_historic[Year],CommDemand!M$2,_xlfn.XLOOKUP(CommDemand!$D13,DemandPJ_historic[#Headers],DemandPJ_historic[])), SUMIF(DemandPJ_projection[Year],CommDemand!M$2,_xlfn.XLOOKUP(CommDemand!$D13,DemandPJ_projection[#Headers],DemandPJ_projection[])))/5)-M12 -> 0 | N13: =(IF(N$2<YEAR(TODAY()),SUMIF(DemandPJ_historic[Year],CommDemand!N$2,_xlfn.XLOOKUP(CommDemand!$D13,DemandPJ_historic[#Headers],DemandPJ_historic[])), SUMIF(DemandPJ_projection[Year],CommDemand!N$2,_xlfn.XLOOKUP(CommDemand!$D13,DemandPJ_projection[#Headers],DemandPJ_projection[])))/5)-N12 -> 0 | ... Q13: =(IF(Q$2<YEAR(TODAY()),SUMIF(DemandPJ_historic[Year],CommDemand!Q$2,_xlfn.XLOOKUP(CommDemand!$D13,DemandPJ_historic[#Headers],DemandPJ_historic[])), SUMIF(DemandPJ_projection[Year],CommDemand!Q$2,_xlfn.XLOOKUP(CommDemand!$D13,DemandPJ_projection[#Headers],DemandPJ_projection[])))/5)-Q12 -> 0 | R13: COMCOXXX | S13: 0.095411 | T13: 0.17413 | U13: 0.067175 | V13: 0.003466 | W13: 0.089708 | X13: 0.185882 | Y13: 0.042992 | Z13: 0.004953 | AA13: 0.093811 | AB13: 0.194873 | AC13: 0.043932 | AD13: 0.003667
B14: *R2,R3,R4,R5,R6 | C14: IPLE | D14: Process Loads | E14: Industrial Process Loads, E | F14: PJ | G14: =IF(G$2<YEAR(TODAY()),SUMIFS(_xlfn.XLOOKUP(CommDemand!$D14,DemandPJ_historic[#Headers],DemandPJ_historic[]),DemandPJ_historic[Year],CommDemand!G$2,DemandPJ_historic[Fuel],"ELC"), SUMIFS(_xlfn.XLOOKUP(CommDemand!$D14,DemandPJ_projection[#Headers],DemandPJ_projection[]),DemandPJ_projection[Year],CommDemand!G$2,DemandPJ_projection[Fuel],"ELC"))/5 -> 0.85331797 | H14: =IF(H$2<YEAR(TODAY()),SUMIFS(_xlfn.XLOOKUP(CommDemand!$D14,DemandPJ_historic[#Headers],DemandPJ_historic[]),DemandPJ_historic[Year],CommDemand!H$2,DemandPJ_historic[Fuel],"ELC"), SUMIFS(_xlfn.XLOOKUP(CommDemand!$D14,DemandPJ_projection[#Headers],DemandPJ_projection[]),DemandPJ_projection[Year],CommDemand!H$2,DemandPJ_projection[Fuel],"ELC"))/5 -> 0.86791222 | I14: =IF(I$2<YEAR(TODAY()),SUMIFS(_xlfn.XLOOKUP(CommDemand!$D14,DemandPJ_historic[#Headers],DemandPJ_historic[]),DemandPJ_historic[Year],CommDemand!I$2,DemandPJ_historic[Fuel],"ELC"), SUMIFS(_xlfn.XLOOKUP(CommDemand!$D14,DemandPJ_projection[#Headers],DemandPJ_projection[]),DemandPJ_projection[Year],CommDemand!I$2,DemandPJ_projection[Fuel],"ELC"))/5 -> 0.70758335 | J14: =IF(J$2<YEAR(TODAY()),SUMIFS(_xlfn.XLOOKUP(CommDemand!$D14,DemandPJ_historic[#Headers],DemandPJ_historic[]),DemandPJ_historic[Year],CommDemand!J$2,DemandPJ_historic[Fuel],"ELC"), SUMIFS(_xlfn.XLOOKUP(CommDemand!$D14,DemandPJ_projection[#Headers],DemandPJ_projection[]),DemandPJ_projection[Year],CommDemand!J$2,DemandPJ_projection[Fuel],"ELC"))/5 -> 0.76720984 | K14: =IF(K$2<YEAR(TODAY()),SUMIFS(_xlfn.XLOOKUP(CommDemand!$D14,DemandPJ_historic[#Headers],DemandPJ_historic[]),DemandPJ_historic[Year],CommDemand!K$2,DemandPJ_historic[Fuel],"ELC"), SUMIFS(_xlfn.XLOOKUP(CommDemand!$D14,DemandPJ_projection[#Headers],DemandPJ_projection[]),DemandPJ_projection[Year],CommDemand!K$2,DemandPJ_projection[Fuel],"ELC"))/5 -> 0.75046411 | L14: =IF(L$2<YEAR(TODAY()),SUMIFS(_xlfn.XLOOKUP(CommDemand!$D14,DemandPJ_historic[#Headers],DemandPJ_historic[]),DemandPJ_historic[Year],CommDemand!L$2,DemandPJ_historic[Fuel],"ELC"), SUMIFS(_xlfn.XLOOKUP(CommDemand!$D14,DemandPJ_projection[#Headers],DemandPJ_projection[]),DemandPJ_projection[Year],CommDemand!L$2,DemandPJ_projection[Fuel],"ELC"))/5 -> 0.76268191 | M14: =IF(M$2<YEAR(TODAY()),SUMIFS(_xlfn.XLOOKUP(CommDemand!$D14,DemandPJ_historic[#Headers],DemandPJ_historic[]),DemandPJ_historic[Year],CommDemand!M$2,DemandPJ_historic[Fuel],"ELC"), SUMIFS(_xlfn.XLOOKUP(CommDemand!$D14,DemandPJ_projection[#Headers],DemandPJ_projection[]),DemandPJ_projection[Year],CommDemand!M$2,DemandPJ_projection[Fuel],"ELC"))/5 -> 0.77781538 | N14: =IF(N$2<YEAR(TODAY()),SUMIFS(_xlfn.XLOOKUP(CommDemand!$D14,DemandPJ_historic[#Headers],DemandPJ_historic[]),DemandPJ_historic[Year],CommDemand!N$2,DemandPJ_historic[Fuel],"ELC"), SUMIFS(_xlfn.XLOOKUP(CommDemand!$D14,DemandPJ_projection[#Headers],DemandPJ_projection[]),DemandPJ_projection[Year],CommDemand!N$2,DemandPJ_projection[Fuel],"ELC"))/5 -> 0.798476 | ... Q14: =IF(Q$2<YEAR(TODAY()),SUMIFS(_xlfn.XLOOKUP(CommDemand!$D14,DemandPJ_historic[#Headers],DemandPJ_historic[]),DemandPJ_historic[Year],CommDemand!Q$2,DemandPJ_historic[Fuel],"ELC"), SUMIFS(_xlfn.XLOOKUP(CommDemand!$D14,DemandPJ_projection[#Headers],DemandPJ_projection[]),DemandPJ_projection[Year],CommDemand!Q$2,DemandPJ_projection[Fuel],"ELC"))/5 -> 0.76268191 | R14: INDMSXXX | S14: 0.08840918 | T14: 0.10056911 | U14: 0.14146522 | V14: 0.00389066 | W14: 0.10269188 | X14: 0.11269183 | Y14: 0.11543107 | Z14: 0.00351943 | AA14: 0.08756231 | AB14: 0.11300045 | AC14: 0.12691579 | AD14: 0.00385307
C15: IPLF | D15: Process Loads | E15: Industrial Process Loads, F | F15: PJ | G15: =(IF(G$2<YEAR(TODAY()),SUMIF(DemandPJ_historic[Year],CommDemand!G$2,_xlfn.XLOOKUP(CommDemand!$D15,DemandPJ_historic[#Headers],DemandPJ_historic[])), SUMIF(DemandPJ_projection[Year],CommDemand!G$2,_xlfn.XLOOKUP(CommDemand!$D15,DemandPJ_projection[#Headers],DemandPJ_projection[])))/5)-G14 -> 0.07351398 | H15: =(IF(H$2<YEAR(TODAY()),SUMIF(DemandPJ_historic[Year],CommDemand!H$2,_xlfn.XLOOKUP(CommDemand!$D15,DemandPJ_historic[#Headers],DemandPJ_historic[])), SUMIF(DemandPJ_projection[Year],CommDemand!H$2,_xlfn.XLOOKUP(CommDemand!$D15,DemandPJ_projection[#Headers],DemandPJ_projection[])))/5)-H14 -> 0.084690622 | I15: =(IF(I$2<YEAR(TODAY()),SUMIF(DemandPJ_historic[Year],CommDemand!I$2,_xlfn.XLOOKUP(CommDemand!$D15,DemandPJ_historic[#Headers],DemandPJ_historic[])), SUMIF(DemandPJ_projection[Year],CommDemand!I$2,_xlfn.XLOOKUP(CommDemand!$D15,DemandPJ_projection[#Headers],DemandPJ_projection[])))/5)-I14 -> 0.077758159 | J15: =(IF(J$2<YEAR(TODAY()),SUMIF(DemandPJ_historic[Year],CommDemand!J$2,_xlfn.XLOOKUP(CommDemand!$D15,DemandPJ_historic[#Headers],DemandPJ_historic[])), SUMIF(DemandPJ_projection[Year],CommDemand!J$2,_xlfn.XLOOKUP(CommDemand!$D15,DemandPJ_projection[#Headers],DemandPJ_projection[])))/5)-J14 -> 0.04781816 | K15: =(IF(K$2<YEAR(TODAY()),SUMIF(DemandPJ_historic[Year],CommDemand!K$2,_xlfn.XLOOKUP(CommDemand!$D15,DemandPJ_historic[#Headers],DemandPJ_historic[])), SUMIF(DemandPJ_projection[Year],CommDemand!K$2,_xlfn.XLOOKUP(CommDemand!$D15,DemandPJ_projection[#Headers],DemandPJ_projection[])))/5)-K14 -> 0.046104528 | L15: =(IF(L$2<YEAR(TODAY()),SUMIF(DemandPJ_historic[Year],CommDemand!L$2,_xlfn.XLOOKUP(CommDemand!$D15,DemandPJ_historic[#Headers],DemandPJ_historic[])), SUMIF(DemandPJ_projection[Year],CommDemand!L$2,_xlfn.XLOOKUP(CommDemand!$D15,DemandPJ_projection[#Headers],DemandPJ_projection[])))/5)-L14 -> 0.04453291 | M15: =(IF(M$2<YEAR(TODAY()),SUMIF(DemandPJ_historic[Year],CommDemand!M$2,_xlfn.XLOOKUP(CommDemand!$D15,DemandPJ_historic[#Headers],DemandPJ_historic[])), SUMIF(DemandPJ_projection[Year],CommDemand!M$2,_xlfn.XLOOKUP(CommDemand!$D15,DemandPJ_projection[#Headers],DemandPJ_projection[])))/5)-M14 -> 0.042641031 | N15: =(IF(N$2<YEAR(TODAY()),SUMIF(DemandPJ_historic[Year],CommDemand!N$2,_xlfn.XLOOKUP(CommDemand!$D15,DemandPJ_historic[#Headers],DemandPJ_historic[])), SUMIF(DemandPJ_projection[Year],CommDemand!N$2,_xlfn.XLOOKUP(CommDemand!$D15,DemandPJ_projection[#Headers],DemandPJ_projection[])))/5)-N14 -> 0.042143205 | ... Q15: =(IF(Q$2<YEAR(TODAY()),SUMIF(DemandPJ_historic[Year],CommDemand!Q$2,_xlfn.XLOOKUP(CommDemand!$D15,DemandPJ_historic[#Headers],DemandPJ_historic[])), SUMIF(DemandPJ_projection[Year],CommDemand!Q$2,_xlfn.XLOOKUP(CommDemand!$D15,DemandPJ_projection[#Headers],DemandPJ_projection[])))/5)-Q14 -> 0.04453291 | R15: INDMSXXX | S15: 0.08840918 | T15: 0.10056911 | U15: 0.14146522 | V15: 0.00389066 | W15: 0.10269188 | X15: 0.11269183 | Y15: 0.11543107 | Z15: 0.00351943 | AA15: 0.08756231 | AB15: 0.11300045 | AC15: 0.12691579 | AD15: 0.00385307
B16: *R2,R3,R4,R5,R6 | C16: IPME | D16: Plug Loads/Misc | E16: Industrial Plug Loads / Misc, E | F16: PJ | G16: =IF(G$2<YEAR(TODAY()),SUMIFS(_xlfn.XLOOKUP(CommDemand!$D16,DemandPJ_historic[#Headers],DemandPJ_historic[]),DemandPJ_historic[Year],CommDemand!G$2,DemandPJ_historic[Fuel],"ELC"), SUMIFS(_xlfn.XLOOKUP(CommDemand!$D16,DemandPJ_projection[#Headers],DemandPJ_projection[]),DemandPJ_projection[Year],CommDemand!G$2,DemandPJ_projection[Fuel],"ELC"))/5 -> 0.80485748 | H16: =IF(H$2<YEAR(TODAY()),SUMIFS(_xlfn.XLOOKUP(CommDemand!$D16,DemandPJ_historic[#Headers],DemandPJ_historic[]),DemandPJ_historic[Year],CommDemand!H$2,DemandPJ_historic[Fuel],"ELC"), SUMIFS(_xlfn.XLOOKUP(CommDemand!$D16,DemandPJ_projection[#Headers],DemandPJ_projection[]),DemandPJ_projection[Year],CommDemand!H$2,DemandPJ_projection[Fuel],"ELC"))/5 -> 0.81862291 | I16: =IF(I$2<YEAR(TODAY()),SUMIFS(_xlfn.XLOOKUP(CommDemand!$D16,DemandPJ_historic[#Headers],DemandPJ_historic[]),DemandPJ_historic[Year],CommDemand!I$2,DemandPJ_historic[Fuel],"ELC"), SUMIFS(_xlfn.XLOOKUP(CommDemand!$D16,DemandPJ_projection[#Headers],DemandPJ_projection[]),DemandPJ_projection[Year],CommDemand!I$2,DemandPJ_projection[Fuel],"ELC"))/5 -> 0.66739922 | J16: =IF(J$2<YEAR(TODAY()),SUMIFS(_xlfn.XLOOKUP(CommDemand!$D16,DemandPJ_historic[#Headers],DemandPJ_historic[]),DemandPJ_historic[Year],CommDemand!J$2,DemandPJ_historic[Fuel],"ELC"), SUMIFS(_xlfn.XLOOKUP(CommDemand!$D16,DemandPJ_projection[#Headers],DemandPJ_projection[]),DemandPJ_projection[Year],CommDemand!J$2,DemandPJ_projection[Fuel],"ELC"))/5 -> 0.72363949 | K16: =IF(K$2<YEAR(TODAY()),SUMIFS(_xlfn.XLOOKUP(CommDemand!$D16,DemandPJ_historic[#Headers],DemandPJ_historic[]),DemandPJ_historic[Year],CommDemand!K$2,DemandPJ_historic[Fuel],"ELC"), SUMIFS(_xlfn.XLOOKUP(CommDemand!$D16,DemandPJ_projection[#Headers],DemandPJ_projection[]),DemandPJ_projection[Year],CommDemand!K$2,DemandPJ_projection[Fuel],"ELC"))/5 -> 0.70784476 | L16: =IF(L$2<YEAR(TODAY()),SUMIFS(_xlfn.XLOOKUP(CommDemand!$D16,DemandPJ_historic[#Headers],DemandPJ_historic[]),DemandPJ_historic[Year],CommDemand!L$2,DemandPJ_historic[Fuel],"ELC"), SUMIFS(_xlfn.XLOOKUP(CommDemand!$D16,DemandPJ_projection[#Headers],DemandPJ_projection[]),DemandPJ_projection[Year],CommDemand!L$2,DemandPJ_projection[Fuel],"ELC"))/5 -> 0.71936869 | M16: =IF(M$2<YEAR(TODAY()),SUMIFS(_xlfn.XLOOKUP(CommDemand!$D16,DemandPJ_historic[#Headers],DemandPJ_historic[]),DemandPJ_historic[Year],CommDemand!M$2,DemandPJ_historic[Fuel],"ELC"), SUMIFS(_xlfn.XLOOKUP(CommDemand!$D16,DemandPJ_projection[#Headers],DemandPJ_projection[]),DemandPJ_projection[Year],CommDemand!M$2,DemandPJ_projection[Fuel],"ELC"))/5 -> 0.73364273 | N16: =IF(N$2<YEAR(TODAY()),SUMIFS(_xlfn.XLOOKUP(CommDemand!$D16,DemandPJ_historic[#Headers],DemandPJ_historic[]),DemandPJ_historic[Year],CommDemand!N$2,DemandPJ_historic[Fuel],"ELC"), SUMIFS(_xlfn.XLOOKUP(CommDemand!$D16,DemandPJ_projection[#Headers],DemandPJ_projection[]),DemandPJ_projection[Year],CommDemand!N$2,DemandPJ_projection[Fuel],"ELC"))/5 -> 0.75313002 | ... Q16: =IF(Q$2<YEAR(TODAY()),SUMIFS(_xlfn.XLOOKUP(CommDemand!$D16,DemandPJ_historic[#Headers],DemandPJ_historic[]),DemandPJ_historic[Year],CommDemand!Q$2,DemandPJ_historic[Fuel],"ELC"), SUMIFS(_xlfn.XLOOKUP(CommDemand!$D16,DemandPJ_projection[#Headers],DemandPJ_projection[]),DemandPJ_projection[Year],CommDemand!Q$2,DemandPJ_projection[Fuel],"ELC"))/5 -> 0.71936869 | R16: INDPMXXX | S16: 0.08409339 | T16: 0.09768158 | U16: 0.14881921 | V16: 0.00361859 | W16: 0.09910395 | X16: 0.11041002 | Y16: 0.12152309 | Z16: 0.00317655 | AA16: 0.08339323 | AB16: 0.11061763 | AC16: 0.13394508 | AD16: 0.00361768
C17: IPMF | D17: Plug Loads/Misc | E17: Industrial Plug Loads / Misc, F | F17: PJ | G17: =(IF(G$2<YEAR(TODAY()),SUMIF(DemandPJ_historic[Year],CommDemand!G$2,_xlfn.XLOOKUP(CommDemand!$D17,DemandPJ_historic[#Headers],DemandPJ_historic[])), SUMIF(DemandPJ_projection[Year],CommDemand!G$2,_xlfn.XLOOKUP(CommDemand!$D17,DemandPJ_projection[#Headers],DemandPJ_projection[])))/5)-G16 -> 0.015180916 | H17: =(IF(H$2<YEAR(TODAY()),SUMIF(DemandPJ_historic[Year],CommDemand!H$2,_xlfn.XLOOKUP(CommDemand!$D17,DemandPJ_historic[#Headers],DemandPJ_historic[])), SUMIF(DemandPJ_projection[Year],CommDemand!H$2,_xlfn.XLOOKUP(CommDemand!$D17,DemandPJ_projection[#Headers],DemandPJ_projection[])))/5)-H16 -> 0.017937931 | I17: =(IF(I$2<YEAR(TODAY()),SUMIF(DemandPJ_historic[Year],CommDemand!I$2,_xlfn.XLOOKUP(CommDemand!$D17,DemandPJ_historic[#Headers],DemandPJ_historic[])), SUMIF(DemandPJ_projection[Year],CommDemand!I$2,_xlfn.XLOOKUP(CommDemand!$D17,DemandPJ_projection[#Headers],DemandPJ_projection[])))/5)-I16 -> 0.018510636 | J17: =(IF(J$2<YEAR(TODAY()),SUMIF(DemandPJ_historic[Year],CommDemand!J$2,_xlfn.XLOOKUP(CommDemand!$D17,DemandPJ_historic[#Headers],DemandPJ_historic[])), SUMIF(DemandPJ_projection[Year],CommDemand!J$2,_xlfn.XLOOKUP(CommDemand!$D17,DemandPJ_projection[#Headers],DemandPJ_projection[])))/5)-J16 -> 0.01031893 | K17: =(IF(K$2<YEAR(TODAY()),SUMIF(DemandPJ_historic[Year],CommDemand!K$2,_xlfn.XLOOKUP(CommDemand!$D17,DemandPJ_historic[#Headers],DemandPJ_historic[])), SUMIF(DemandPJ_projection[Year],CommDemand!K$2,_xlfn.XLOOKUP(CommDemand!$D17,DemandPJ_projection[#Headers],DemandPJ_projection[])))/5)-K16 -> 0.010041484 | L17: =(IF(L$2<YEAR(TODAY()),SUMIF(DemandPJ_historic[Year],CommDemand!L$2,_xlfn.XLOOKUP(CommDemand!$D17,DemandPJ_historic[#Headers],DemandPJ_historic[])), SUMIF(DemandPJ_projection[Year],CommDemand!L$2,_xlfn.XLOOKUP(CommDemand!$D17,DemandPJ_projection[#Headers],DemandPJ_projection[])))/5)-L16 -> 0.0096410102 | M17: =(IF(M$2<YEAR(TODAY()),SUMIF(DemandPJ_historic[Year],CommDemand!M$2,_xlfn.XLOOKUP(CommDemand!$D17,DemandPJ_historic[#Headers],DemandPJ_historic[])), SUMIF(DemandPJ_projection[Year],CommDemand!M$2,_xlfn.XLOOKUP(CommDemand!$D17,DemandPJ_projection[#Headers],DemandPJ_projection[])))/5)-M16 -> 0.0091535977 | N17: =(IF(N$2<YEAR(TODAY()),SUMIF(DemandPJ_historic[Year],CommDemand!N$2,_xlfn.XLOOKUP(CommDemand!$D17,DemandPJ_historic[#Headers],DemandPJ_historic[])), SUMIF(DemandPJ_projection[Year],CommDemand!N$2,_xlfn.XLOOKUP(CommDemand!$D17,DemandPJ_projection[#Headers],DemandPJ_projection[])))/5)-N16 -> 0.0088838436 | ... Q17: =(IF(Q$2<YEAR(TODAY()),SUMIF(DemandPJ_historic[Year],CommDemand!Q$2,_xlfn.XLOOKUP(CommDemand!$D17,DemandPJ_historic[#Headers],DemandPJ_historic[])), SUMIF(DemandPJ_projection[Year],CommDemand!Q$2,_xlfn.XLOOKUP(CommDemand!$D17,DemandPJ_projection[#Headers],DemandPJ_projection[])))/5)-Q16 -> 0.0096410102 | R17: INDPMXXX | S17: 0.08409339 | T17: 0.09768158 | U17: 0.14881921 | V17: 0.00361859 | W17: 0.09910395 | X17: 0.11041002 | Y17: 0.12152309 | Z17: 0.00317655 | AA17: 0.08339323 | AB17: 0.11061763 | AC17: 0.13394508 | AD17: 0.00361768
B18: R2,R3,R4,R5,R6 | C18: IOTE | D18: Plug Loads/Misc + Other | E18: Industrial Process Loads + Other | F18: PJ | G18: =SUM(G10,G12,G14,G16) -> 2.5937705 | H18: =SUM(H10,H12,H14,H16) -> 2.6381317 | I18: =SUM(I10,I12,I14,I16) -> 2.1507913 | J18: =SUM(J10,J12,J14,J16) -> 2.3320337 | K18: =SUM(K10,K12,K14,K16) -> 2.2811329 | L18: =SUM(L10,L12,L14,L16) -> 2.3182705 | M18: =SUM(M10,M12,M14,M16) -> 2.3642706 | N18: =SUM(N10,N12,N14,N16) -> 2.4270713 | ... Q18: =SUM(Q10,Q12,Q14,Q16) -> 2.3182705 | R18: INDMSXXX | S18: 0.08840918 | T18: 0.10056911 | U18: 0.14146522 | V18: 0.00389066 | W18: 0.10269188 | X18: 0.11269183 | Y18: 0.11543107 | Z18: 0.00351943 | AA18: 0.08756231 | AB18: 0.11300045 | AC18: 0.12691579 | AD18: 0.00385307
B19: R2,R3,R4,R5,R6 | C19: IOTF | D19: Plug Loads/Misc + Other | E19: Industrial Process Loads + Other | F19: PJ | G19: =SUM(G11,G13,G15,G17) -> 0.088694896 | H19: =SUM(H11,H13,H15,H17) -> 0.10262855 | I19: =SUM(I11,I13,I15,I17) -> 0.096268795 | J19: =SUM(J11,J13,J15,J17) -> 0.058137091 | K19: =SUM(K11,K13,K15,K17) -> 0.056146012 | L19: =SUM(L11,L13,L15,L17) -> 0.05417392 | M19: =SUM(M11,M13,M15,M17) -> 0.051794628 | N19: =SUM(N11,N13,N15,N17) -> 0.051027048 | ... Q19: =SUM(Q11,Q13,Q15,Q17) -> 0.05417392 | R19: INDMSXXX | S19: 0.08840918 | T19: 0.10056911 | U19: 0.14146522 | V19: 0.00389066 | W19: 0.10269188 | X19: 0.11269183 | Y19: 0.11543107 | Z19: 0.00351943 | AA19: 0.08756231 | AB19: 0.11300045 | AC19: 0.12691579 | AD19: 0.00385307

Sheet CommData_DMD_dep
B3: Region | C3: CommName | D3: *CommDesc | E3: *Units | F3: COM_PROJ~2010 | G3: COM_PROJ~2015 | H3: COM_PROJ~2020 | I3: COM_PROJ~2025 | J3: COM_PROJ~2030 | K3: COM_PROJ~2035 | L3: COM_PROJ~2040 | M3: COM_PROJ~2045 | N3: COM_PROJ~2050 | O3: COM_PROJ~2055
B4: *Other
B5: R2 | C5: IOT | D5: Other Industry End Demand | E5: PJ | F5: =NYCIND_DMD!D53 -> 8.30918 | G5: =NYCIND_DMD!E53 -> 9.3622424 | H5: =NYCIND_DMD!F53 -> 10.402576 | I5: =NYCIND_DMD!G53 -> 11.132577 | J5: =NYCIND_DMD!H53 -> 12.024885 | K5: =NYCIND_DMD!I53 -> 11.425521 | L5: =NYCIND_DMD!J53 -> 11.314906 | M5: =NYCIND_DMD!K53 -> 12.034575 | ... O5: =NYCIND_DMD!M53 -> 12.379512
B6: R3 | C6: IOT | D6: Other Industry End Demand | E6: PJ | F6: =NYCIND_DMD!D54 -> 23.925625 | G6: =NYCIND_DMD!E54 -> 24.506902 | H6: =NYCIND_DMD!F54 -> 25.069199 | I6: =NYCIND_DMD!G54 -> 25.475584 | J6: =NYCIND_DMD!H54 -> 25.975055 | K6: =NYCIND_DMD!I54 -> 25.651449 | L6: =NYCIND_DMD!J54 -> 25.596716 | M6: =NYCIND_DMD!K54 -> 26.008436 | ... O6: =NYCIND_DMD!M54 -> 26.2175
B7: R4 | C7: IOT | D7: Other Industry End Demand | E7: PJ | F7: =NYCIND_DMD!D55 -> 8.9383948 | G7: =NYCIND_DMD!E55 -> 9.5951843 | H7: =NYCIND_DMD!F55 -> 10.233329 | I7: =NYCIND_DMD!G55 -> 10.670858 | J7: =NYCIND_DMD!H55 -> 11.200623 | K7: =NYCIND_DMD!I55 -> 10.81467 | L7: =NYCIND_DMD!J55 -> 10.728394 | M7: =NYCIND_DMD!K55 -> 11.158541 | ... O7: =NYCIND_DMD!M55 -> 11.336043
B8: R5 | C8: IOT | D8: Other Industry End Demand | E8: PJ | F8: =NYCIND_DMD!D56 -> 20.115576 | G8: =NYCIND_DMD!E56 -> 21.049788 | H8: =NYCIND_DMD!F56 -> 21.957493 | I8: =NYCIND_DMD!G56 -> 22.573867 | J8: =NYCIND_DMD!H56 -> 23.317968 | K8: =NYCIND_DMD!I56 -> 22.781647 | L8: =NYCIND_DMD!J56 -> 22.668541 | M8: =NYCIND_DMD!K56 -> 23.313585 | ... O8: =NYCIND_DMD!M56 -> 23.591192
B9: R6 | C9: IOT | D9: Other Industry End Demand | E9: PJ | F9: =NYCIND_DMD!D57 -> 2.128264 | G9: =NYCIND_DMD!E57 -> 2.3177935 | H9: =NYCIND_DMD!F57 -> 2.5133223 | I9: =NYCIND_DMD!G57 -> 2.6429877 | J9: =NYCIND_DMD!H57 -> 2.7998263 | K9: =NYCIND_DMD!I57 -> 2.6846609 | L9: =NYCIND_DMD!J57 -> 2.6585167 | M9: =NYCIND_DMD!K57 -> 2.8058186 | ... O9: =NYCIND_DMD!M57 -> 2.8712364

Sheet Technologies_dep
B3: *~FI_Process
B4: Region | C4: Sets | D4: TechName | E4: TechDesc | F4: Tact | G4: Tcap | H4: PrimaryCG | I4: Vintage | J4: Tslvl
B5: *Other
B6: =TechData_OTR_dep!B5 -> R2,R3,R4,R5,R6 | C6: PRE | D6: =TechData_OTR_dep!C5 -> INDELC000 | E6: =TechData_OTR_dep!D5 -> Electricity Going to the Industrial Sector | F6: PJ | G6: Pja | J6: DAYNITE
B7: =TechData_OTR_dep!B11 -> * | C7: PRE | D7: =TechData_OTR_dep!C11 -> IOTEMETCOK | E7: =TechData_OTR_dep!D11 -> Other Industry Metallurgical Coal Plant | F7: PJ | G7: Pja
B8: =TechData_OTR_dep!B12 -> * | C8: PRE | D8: =TechData_OTR_dep!C12 -> IOTEFEDRFL | E8: =TechData_OTR_dep!D12 -> Other Industry Residual Oil Feedstock | F8: PJ | G8: Pja
B9: =TechData_OTR_dep!B13 -> * | C9: PRE | D9: =TechData_OTR_dep!C13 -> IOTEFEDDST | E9: =TechData_OTR_dep!D13 -> Other Industry Distillate Oil Feedstock | F9: PJ | G9: Pja
B10: =TechData_OTR_dep!B14 -> * | C10: PRE | D10: =TechData_OTR_dep!C14 -> IOTEFEDNGA | E10: =TechData_OTR_dep!D14 -> Other Industry Natural Gas Feedstock | F10: PJ | G10: Pja
B11: =TechData_OTR_dep!B15 -> * | C11: PRE | D11: =TechData_OTR_dep!C15 -> IOTEFEDLPG | E11: =TechData_OTR_dep!D15 -> Other Industry LPG Feedstock | F11: PJ | G11: Pja
B12: =TechData_OTR_dep!B16 -> * | C12: PRE | D12: =TechData_OTR_dep!C16 -> IOTEFEDCOK | E12: =TechData_OTR_dep!D16 -> Other Industry Coke Feedstock | F12: PJ | G12: Pja
B13: =TechData_OTR_dep!B17 -> * | C13: PRE | D13: =TechData_OTR_dep!C17 -> IOTEFEDBIO | E13: =TechData_OTR_dep!D17 -> Other Industry Renewables Feedstock | F13: PJ | G13: Pja
B14: =TechData_OTR_dep!B18 -> * | C14: PRE | D14: =TechData_OTR_dep!C18 -> IOTEFEDPTC | E14: =TechData_OTR_dep!D18 -> Other Industry Petroleum Coke Feedstock | F14: PJ | G14: Pja
B15: =TechData_OTR_dep!B19 -> * | C15: PRE | D15: =TechData_OTR_dep!C19 -> IOTEFEDOTP | E15: =TechData_OTR_dep!D19 -> Other Industry Other Petroleum Feedstock | F15: PJ | G15: Pja
B16: =TechData_OTR_dep!B20 -> * | C16: PRE | D16: =TechData_OTR_dep!C20 -> IOTEETCELC | E16: =TechData_OTR_dep!D20 -> Other Industry Electrochemical | F16: PJ | G16: Pja
B17: =TechData_OTR_dep!B21 -> * | C17: PRE | D17: =TechData_OTR_dep!C21 -> IOTEPRHELC | E17: =TechData_OTR_dep!D21 -> Other Industry Electricity Process Heat | F17: PJ | G17: Pja
B18: =TechData_OTR_dep!B22 -> * | C18: PRE | D18: =TechData_OTR_dep!C22 -> IOTEPRHRFL | E18: =TechData_OTR_dep!D22 -> Other Industry Residual Oil Process Heat | F18: PJ | G18: Pja
... B42: =TechData_OTR_dep!B46 -> R2,R3,R4,R5,R6 | C42: DMD | D42: =TechData_OTR_dep!C46 -> IOTTECHEXT | E42: =TechData_OTR_dep!D46 -> Existing Other Industry Technologies | F42: PJ | G42: Pja
B43: *Collector
B44: R2,R3,R4,R5,R6 | C44: PRE | D44: IOTELC00 | E44: Other Industry Electricity collector | F44: PJ | G44: Pja | I44: DAYNITE
B45: R2,R3,R4,R5,R6 | C45: PRE | D45: SEINDNGA | E45: Emissions: NGA to IND | F45: PJ | G45: Pja
B46: R2,R3,R4,R5,R6 | C46: PRE | D46: SEINDRFL | E46: Emissions: RFL to IND | F46: PJ | G46: Pja
B47: R2,R3,R4,R5,R6 | C47: PRE | D47: SEINDDSL | E47: Emissions: DSL to IND | F47: PJ | G47: Pja
B48: * | C48: PRE | D48: SEINDDST | E48: Emissions: DST to IND | F48: PJ | G48: Pja
B49: * | C49: PRE | D49: SEINDBIO | E49: Emissions: Biomass combustion | F49: PJ | G49: Pja
B50: * | C50: PRE | D50: SEINDCOA | E50: Emissions: COA to IND | F50: PJ | G50: Pja
B51: * | C51: PRE | D51: SEINDRFL | E51: Emissions: RFL to IND | F51: PJ | G51: Pja
B52: * | C52: PRE | D52: SEINDLPG | E52: Emissions: LPG to IND | F52: PJ | G52: Pja
B53: * | C53: PRE | D53: SEINDMET | E53: Emissions: MET to IND | F53: PJ | G53: Pja

Sheet TechData_OTR_dep
G3: *~FI_T
B4: Region | C4: TechName | D4: *TechDesc | E4: *Units | F4: CommIN | G4: CommOUT | H4: NCAP_START | I4: PRC_CAPACT | J4: NCAP_AF | K4: EFF | N4: Input | O4: Output
B5: R2,R3,R4,R5,R6 | C5: INDELC000 | D5: Electricity Going to the Industrial Sector | E5: PJ, PJ/a | F5: ELC | G5: INDELC | H5: 2010 | I5: 1 | J5: 1 | K5: 1 | N5: 1 | O5: 1
G8: *~FI_T
B9: Region | C9: TechName | D9: *TechDesc | E9: *Units | F9: CommIN | G9: CommOUT | H9: NCAP_START | I9: NCAP_TLIFE | J9: PRC_CAPACT | K9: NCAP_DRATE | L9: NCAP_COST | M9: NCAP_FOM | N9: *NCAP_BND~FX~2010 | O9: *NCAP_BND~FX~2015 | P9: *NCAP_BND~FX~2055 | Q9: PRC_RESID~R2~2010 | R9: PRC_RESID~R3~2010 | S9: PRC_RESID~R4~2010 | T9: PRC_RESID~R5~2010 | U9: PRC_RESID~R6~2010 | V9: PRC_RESID~R2~2015 | W9: PRC_RESID~R3~2015 | X9: PRC_RESID~R4~2015 | Y9: PRC_RESID~R5~2015 | Z9: PRC_RESID~R6~2015 | AA9: PRC_RESID~R2~2055 | AB9: PRC_RESID~R3~2055 | AC9: PRC_RESID~R4~2055 | AD9: PRC_RESID~R5~2055 | AE9: PRC_RESID~R6~2055 | AF9: NCAP_AF | AG9: NCAP_AF | AH9: EFF~2010 | AI9: EFF~2015 | AJ9: EFF~2020 | AK9: EFF~2025 | AL9: EFF~2030 | AM9: EFF~2035 | AN9: EFF~2040 | AO9: EFF~2045 | AP9: EFF~2050 | AQ9: EFF~2055 | AR9: Share~UP~R2~2010 | AS9: Share~UP~R3~2010 | AT9: Share~UP~R4~2010 | AU9: Share~UP~R5~2010 | AV9: Share~UP~R6~2010 | AW9: Share~UP~R2~2015 | AX9: Share~UP~R3~2015 | AY9: Share~UP~R4~2015 | AZ9: Share~UP~R5~2015 | BA9: Share~UP~R6~2015 | BB9: Share~UP~R2~2055 | BC9: Share~UP~R3~2055 | BD9: Share~UP~R4~2055 | BE9: Share~UP~R5~2055 | BF9: Share~UP~R6~2055 | BG9: Peak | BI9: Input~2010 | BJ9: Input~2015 | BK9: Input~2020 | BL9: Input~2025 | BM9: Input~2030 | BN9: Input~2035 | BO9: Input~2040 | BP9: Input~2045 | BQ9: Input~2050 | BR9: Input~2055 | BS9: Output | BT9: Output | BU9: Input | BV9: Output
B10: * Other | BB10: =IF(AW10="","",AW10) | BC10: =IF(AX10="","",AX10) | BD10: =IF(AY10="","",AY10) | BE10: =IF(AZ10="","",AZ10) | BF10: =IF(BA10="","",BA10) | BJ10: =IF(BI10="","",BI10)
B11: * | C11: IOTEMETCOK | D11: Other Industry Metallurgical Coal Plant | E11: PJ, PJ/a | F11: INDMETEA | G11: COKE | H11: 2010 | I11: 30 | J11: 1 | K11: 0.15 | L11: =IFERROR(IF(_xlfn.XLOOKUP(D11,tbl_tech[TECHNOLOGY - Other],tbl_tech[NCAP_COST])=0,"",_xlfn.XLOOKUP(D11,tbl_tech[TECHNOLOGY - Other],tbl_tech[NCAP_COST])),"") -> 19.887216 | M11: =IFERROR(IF(_xlfn.XLOOKUP(D11,tbl_tech[TECHNOLOGY - Other],tbl_tech[NCAP_FOM])=0,"",_xlfn.XLOOKUP(D11,tbl_tech[TECHNOLOGY - Other],tbl_tech[NCAP_FOM])),"") -> 3.173022 | N11: 0 | Q11: 0.37987591 | R11: 0.91455766 | S11: 0.4127475 | T11: 0.37097101 | U11: 0.27476452 | V11: 0 | W11: 0.87277037 | X11: 0.59114812 | Y11: 0.29877444 | Z11: 0.26042544 | AF11: 1 | AH11: =IF(BI11="","",$BS11/BI11) -> 0.76923077 | AI11: =IF(BJ11="","",$BS11/BJ11) -> 0.76923077 | AJ11: =IF(BK11="","",$BS11/BK11) -> 0.76923077 | AK11: =IF(BL11="","",$BS11/BL11) -> 0.76923077 | AL11: =IF(BM11="","",$BS11/BM11) -> 0.76923077 | AM11: =IF(BN11="","",$BS11/BN11) -> 0.76923077 | AN11: =IF(BO11="","",$BS11/BO11) -> 0.76923077 | AO11: =IF(BP11="","",$BS11/BP11) -> 0.76923077 | ... AQ11: =IF(BR11="","",$BS11/BR11) -> 0.76923077 | BB11: =IF(AW11="","",AW11) | BC11: =IF(AX11="","",AX11) | BD11: =IF(AY11="","",AY11) | BE11: =IF(AZ11="","",AZ11) | BF11: =IF(BA11="","",BA11) | BI11: 1.3 | BJ11: =IF(BI11="","",BI11) -> 1.3 | BK11: 1.3 | BL11: 1.3 | BM11: 1.3 | BN11: 1.3 | BO11: 1.3 | BP11: 1.3 | BQ11: 1.3 | BR11: 1.3 | BS11: 1
B12: * | C12: IOTEFEDRFL | D12: Other Industry Residual Oil Feedstock | E12: PJ, PJ/a | F12: INDRFLEA | G12: IOTFEED | H12: 2010 | I12: 30 | J12: 1 | K12: 0.15 | L12: =IFERROR(IF(_xlfn.XLOOKUP(D12,tbl_tech[TECHNOLOGY - Other],tbl_tech[NCAP_COST])=0,"",_xlfn.XLOOKUP(D12,tbl_tech[TECHNOLOGY - Other],tbl_tech[NCAP_COST])),"") | M12: =IFERROR(IF(_xlfn.XLOOKUP(D12,tbl_tech[TECHNOLOGY - Other],tbl_tech[NCAP_FOM])=0,"",_xlfn.XLOOKUP(D12,tbl_tech[TECHNOLOGY - Other],tbl_tech[NCAP_FOM])),"") | N12: 0 | V12: 0 | W12: 0 | X12: 0 | Y12: 0.14511207 | Z12: 0.1264863 | AF12: 1 | AH12: =IF(BI12="","",$BS12/BI12) -> 1 | AI12: =IF(BJ12="","",$BS12/BJ12) -> 1 | AJ12: =IF(BK12="","",$BS12/BK12) -> 1.0050251 | AK12: =IF(BL12="","",$BS12/BL12) -> 1.010101 | AL12: =IF(BM12="","",$BS12/BM12) -> 1.0152284 | AM12: =IF(BN12="","",$BS12/BN12) -> 1.0204082 | AN12: =IF(BO12="","",$BS12/BO12) -> 1.025641 | AO12: =IF(BP12="","",$BS12/BP12) -> 1.0309278 | ... AQ12: =IF(BR12="","",$BS12/BR12) -> 1.0416667 | BB12: =IF(AW12="","",AW12) | BC12: =IF(AX12="","",AX12) | BD12: =IF(AY12="","",AY12) | BE12: =IF(AZ12="","",AZ12) | BF12: =IF(BA12="","",BA12) | BI12: 1 | BJ12: =IF(BI12="","",BI12) -> 1 | BK12: 0.995 | BL12: 0.99 | BM12: 0.985 | BN12: 0.98 | BO12: 0.975 | BP12: 0.97 | BQ12: 0.965 | BR12: 0.96 | BS12: 1
B13: * | C13: IOTEFEDDST | D13: Other Industry Distillate Oil Feedstock | E13: PJ, PJ/a | F13: INDDSTEA | G13: IOTFEED | H13: 2010 | I13: 30 | J13: 1 | K13: 0.15 | L13: =IFERROR(IF(_xlfn.XLOOKUP(D13,tbl_tech[TECHNOLOGY - Other],tbl_tech[NCAP_COST])=0,"",_xlfn.XLOOKUP(D13,tbl_tech[TECHNOLOGY - Other],tbl_tech[NCAP_COST])),"") | M13: =IFERROR(IF(_xlfn.XLOOKUP(D13,tbl_tech[TECHNOLOGY - Other],tbl_tech[NCAP_FOM])=0,"",_xlfn.XLOOKUP(D13,tbl_tech[TECHNOLOGY - Other],tbl_tech[NCAP_FOM])),"") | N13: 0 | Q13: 0 | R13: 1.2765939 | S13: 0.5761375 | T13: 0.61199828 | U13: 0.45328451 | V13: 0.59133783 | W13: 0.48062378 | X13: 0.32553791 | Y13: 0.32906273 | Z13: 0.2868261 | AF13: 1 | AH13: =IF(BI13="","",$BS13/BI13) -> 1 | AI13: =IF(BJ13="","",$BS13/BJ13) -> 1 | AJ13: =IF(BK13="","",$BS13/BK13) -> 1.0050251 | AK13: =IF(BL13="","",$BS13/BL13) -> 1.010101 | AL13: =IF(BM13="","",$BS13/BM13) -> 1.0152284 | AM13: =IF(BN13="","",$BS13/BN13) -> 1.0204082 | AN13: =IF(BO13="","",$BS13/BO13) -> 1.025641 | AO13: =IF(BP13="","",$BS13/BP13) -> 1.0309278 | ... AQ13: =IF(BR13="","",$BS13/BR13) -> 1.0416667 | BB13: =IF(AW13="","",AW13) | BC13: =IF(AX13="","",AX13) | BD13: =IF(AY13="","",AY13) | BE13: =IF(AZ13="","",AZ13) | BF13: =IF(BA13="","",BA13) | BI13: 1 | BJ13: =IF(BI13="","",BI13) -> 1 | BK13: 0.995 | BL13: 0.99 | BM13: 0.985 | BN13: 0.98 | BO13: 0.975 | BP13: 0.97 | BQ13: 0.965 | BR13: 0.96 | BS13: 1
B14: * | C14: IOTEFEDNGA | D14: Other Industry Natural Gas Feedstock | E14: PJ, PJ/a | F14: INDNGAEA | G14: IOTFEED | H14: 2010 | I14: 30 | J14: 1 | K14: 0.15 | L14: =IFERROR(IF(_xlfn.XLOOKUP(D14,tbl_tech[TECHNOLOGY - Other],tbl_tech[NCAP_COST])=0,"",_xlfn.XLOOKUP(D14,tbl_tech[TECHNOLOGY - Other],tbl_tech[NCAP_COST])),"") | M14: =IFERROR(IF(_xlfn.XLOOKUP(D14,tbl_tech[TECHNOLOGY - Other],tbl_tech[NCAP_FOM])=0,"",_xlfn.XLOOKUP(D14,tbl_tech[TECHNOLOGY - Other],tbl_tech[NCAP_FOM])),"") | N14: 0 | Q14: 0 | R14: 0 | S14: 0 | T14: 0.20384895 | U14: 0.15098338 | V14: 0 | W14: 3.1805834 | X14: 2.1542848 | Y14: 0.81660399 | Z14: 0.71178932 | AF14: 1 | AH14: =IF(BI14="","",$BS14/BI14) -> 1 | AI14: =IF(BJ14="","",$BS14/BJ14) -> 1 | AJ14: =IF(BK14="","",$BS14/BK14) -> 1.0050251 | AK14: =IF(BL14="","",$BS14/BL14) -> 1.010101 | AL14: =IF(BM14="","",$BS14/BM14) -> 1.0152284 | AM14: =IF(BN14="","",$BS14/BN14) -> 1.0204082 | AN14: =IF(BO14="","",$BS14/BO14) -> 1.025641 | AO14: =IF(BP14="","",$BS14/BP14) -> 1.0309278 | ... AQ14: =IF(BR14="","",$BS14/BR14) -> 1.0416667 | BB14: =IF(AW14="","",AW14) | BC14: =IF(AX14="","",AX14) | BD14: =IF(AY14="","",AY14) | BE14: =IF(AZ14="","",AZ14) | BF14: =IF(BA14="","",BA14) | BI14: 1 | BJ14: =IF(BI14="","",BI14) -> 1 | BK14: 0.995 | BL14: 0.99 | BM14: 0.985 | BN14: 0.98 | BO14: 0.975 | BP14: 0.97 | BQ14: 0.965 | BR14: 0.96 | BS14: 1
B15: * | C15: IOTEFEDLPG | D15: Other Industry LPG Feedstock | E15: PJ, PJ/a | F15: INDLPGEA | G15: IOTFEED | H15: 2010 | I15: 30 | J15: 1 | K15: 0.15 | L15: =IFERROR(IF(_xlfn.XLOOKUP(D15,tbl_tech[TECHNOLOGY - Other],tbl_tech[NCAP_COST])=0,"",_xlfn.XLOOKUP(D15,tbl_tech[TECHNOLOGY - Other],tbl_tech[NCAP_COST])),"") | M15: =IFERROR(IF(_xlfn.XLOOKUP(D15,tbl_tech[TECHNOLOGY - Other],tbl_tech[NCAP_FOM])=0,"",_xlfn.XLOOKUP(D15,tbl_tech[TECHNOLOGY - Other],tbl_tech[NCAP_FOM])),"") | N15: 0 | Q15: 0 | R15: 0.34311094 | S15: 0.15484883 | T15: 0 | U15: 0 | V15: 0 | W15: 0 | X15: 0 | Y15: 1.0793182 | Z15: 0.94078302 | AF15: 1 | AH15: =IF(BI15="","",$BS15/BI15) -> 1 | AI15: =IF(BJ15="","",$BS15/BJ15) -> 1 | AJ15: =IF(BK15="","",$BS15/BK15) -> 1.0050251 | AK15: =IF(BL15="","",$BS15/BL15) -> 1.010101 | AL15: =IF(BM15="","",$BS15/BM15) -> 1.0152284 | AM15: =IF(BN15="","",$BS15/BN15) -> 1.0204082 | AN15: =IF(BO15="","",$BS15/BO15) -> 1.025641 | AO15: =IF(BP15="","",$BS15/BP15) -> 1.0309278 | ... AQ15: =IF(BR15="","",$BS15/BR15) -> 1.0416667 | BB15: =IF(AW15="","",AW15) | BC15: =IF(AX15="","",AX15) | BD15: =IF(AY15="","",AY15) | BE15: =IF(AZ15="","",AZ15) | BF15: =IF(BA15="","",BA15) | BI15: 1 | BJ15: =IF(BI15="","",BI15) -> 1 | BK15: 0.995 | BL15: 0.99 | BM15: 0.985 | BN15: 0.98 | BO15: 0.975 | BP15: 0.97 | BQ15: 0.965 | BR15: 0.96 | BS15: 1
B16: * | C16: IOTEFEDCOK | D16: Other Industry Coke Feedstock | E16: PJ, PJ/a | F16: INDCOK | G16: IOTFEED | H16: 2010 | I16: 30 | J16: 1 | K16: 0.15 | L16: =IFERROR(IF(_xlfn.XLOOKUP(D16,tbl_tech[TECHNOLOGY - Other],tbl_tech[NCAP_COST])=0,"",_xlfn.XLOOKUP(D16,tbl_tech[TECHNOLOGY - Other],tbl_tech[NCAP_COST])),"") | M16: =IFERROR(IF(_xlfn.XLOOKUP(D16,tbl_tech[TECHNOLOGY - Other],tbl_tech[NCAP_FOM])=0,"",_xlfn.XLOOKUP(D16,tbl_tech[TECHNOLOGY - Other],tbl_tech[NCAP_FOM])),"") | N16: 0 | Q16: 0.37987591 | R16: 0.91455766 | S16: 0.4127475 | T16: 0.37097101 | U16: 0.27476452 | V16: 0 | W16: 0.87277037 | X16: 0.59114812 | Y16: 0.29877444 | Z16: 0.26042544 | AF16: 1 | AH16: =IF(BI16="","",$BS16/BI16) -> 1 | AI16: =IF(BJ16="","",$BS16/BJ16) -> 1 | AJ16: =IF(BK16="","",$BS16/BK16) -> 1.0050251 | AK16: =IF(BL16="","",$BS16/BL16) -> 1.010101 | AL16: =IF(BM16="","",$BS16/BM16) -> 1.0152284 | AM16: =IF(BN16="","",$BS16/BN16) -> 1.0204082 | AN16: =IF(BO16="","",$BS16/BO16) -> 1.025641 | AO16: =IF(BP16="","",$BS16/BP16) -> 1.0309278 | ... AQ16: =IF(BR16="","",$BS16/BR16) -> 1.0416667 | BB16: =IF(AW16="","",AW16) | BC16: =IF(AX16="","",AX16) | BD16: =IF(AY16="","",AY16) | BE16: =IF(AZ16="","",AZ16) | BF16: =IF(BA16="","",BA16) | BI16: 1 | BJ16: =IF(BI16="","",BI16) -> 1 | BK16: 0.995 | BL16: 0.99 | BM16: 0.985 | BN16: 0.98 | BO16: 0.975 | BP16: 0.97 | BQ16: 0.965 | BR16: 0.96 | BS16: 1
B17: * | C17: IOTEFEDBIO | D17: Other Industry Renewables Feedstock | E17: PJ, PJ/a | F17: INDBIOEA | G17: IOTFEED | H17: 2010 | I17: 30 | J17: 1 | K17: 0.15 | L17: =IFERROR(IF(_xlfn.XLOOKUP(D17,tbl_tech[TECHNOLOGY - Other],tbl_tech[NCAP_COST])=0,"",_xlfn.XLOOKUP(D17,tbl_tech[TECHNOLOGY - Other],tbl_tech[NCAP_COST])),"") | M17: =IFERROR(IF(_xlfn.XLOOKUP(D17,tbl_tech[TECHNOLOGY - Other],tbl_tech[NCAP_FOM])=0,"",_xlfn.XLOOKUP(D17,tbl_tech[TECHNOLOGY - Other],tbl_tech[NCAP_FOM])),"") | N17: 0 | Q17: 0 | R17: 0.93917997 | S17: 0.42385976 | T17: 5.0573358 | U17: 3.7457817 | V17: 0.42866648 | W17: 0.1107891 | X17: 0.075040091 | Y17: 1.1053542 | Z17: 0.96347717 | AF17: 1 | AH17: =IF(BI17="","",$BS17/BI17) -> 1 | AI17: =IF(BJ17="","",$BS17/BJ17) -> 1 | AJ17: =IF(BK17="","",$BS17/BK17) -> 1.0050251 | AK17: =IF(BL17="","",$BS17/BL17) -> 1.010101 | AL17: =IF(BM17="","",$BS17/BM17) -> 1.0152284 | AM17: =IF(BN17="","",$BS17/BN17) -> 1.0204082 | AN17: =IF(BO17="","",$BS17/BO17) -> 1.025641 | AO17: =IF(BP17="","",$BS17/BP17) -> 1.0309278 | ... AQ17: =IF(BR17="","",$BS17/BR17) -> 1.0416667 | BB17: =IF(AW17="","",AW17) | BC17: =IF(AX17="","",AX17) | BD17: =IF(AY17="","",AY17) | BE17: =IF(AZ17="","",AZ17) | BF17: =IF(BA17="","",BA17) | BI17: 1 | BJ17: =IF(BI17="","",BI17) -> 1 | BK17: 0.995 | BL17: 0.99 | BM17: 0.985 | BN17: 0.98 | BO17: 0.975 | BP17: 0.97 | BQ17: 0.965 | BR17: 0.96 | BS17: 1
B18: * | C18: IOTEFEDPTC | D18: Other Industry Petroleum Coke Feedstock | E18: PJ, PJ/a | F18: INDPTC | G18: IOTFEED | H18: 2010 | I18: 30 | J18: 1 | K18: 0.15 | L18: =IFERROR(IF(_xlfn.XLOOKUP(D18,tbl_tech[TECHNOLOGY - Other],tbl_tech[NCAP_COST])=0,"",_xlfn.XLOOKUP(D18,tbl_tech[TECHNOLOGY - Other],tbl_tech[NCAP_COST])),"") | M18: =IFERROR(IF(_xlfn.XLOOKUP(D18,tbl_tech[TECHNOLOGY - Other],tbl_tech[NCAP_FOM])=0,"",_xlfn.XLOOKUP(D18,tbl_tech[TECHNOLOGY - Other],tbl_tech[NCAP_FOM])),"") | N18: 0 | Q18: 0 | R18: 1.2782996 | S18: 0.57690727 | T18: 1.0930738 | U18: 0.80959933 | V18: 0.16735231 | W18: 0.092916319 | X18: 0.062934432 | Y18: 0.86116157 | Z18: 0.75062774 | AF18: 1 | AH18: =IF(BI18="","",$BS18/BI18) -> 1 | AI18: =IF(BJ18="","",$BS18/BJ18) -> 1 | AJ18: =IF(BK18="","",$BS18/BK18) -> 1.0050251 | AK18: =IF(BL18="","",$BS18/BL18) -> 1.010101 | AL18: =IF(BM18="","",$BS18/BM18) -> 1.0152284 | AM18: =IF(BN18="","",$BS18/BN18) -> 1.0204082 | AN18: =IF(BO18="","",$BS18/BO18) -> 1.025641 | AO18: =IF(BP18="","",$BS18/BP18) -> 1.0309278 | ... AQ18: =IF(BR18="","",$BS18/BR18) -> 1.0416667 | BB18: =IF(AW18="","",AW18) | BC18: =IF(AX18="","",AX18) | BD18: =IF(AY18="","",AY18) | BE18: =IF(AZ18="","",AZ18) | BF18: =IF(BA18="","",BA18) | BI18: 1 | BJ18: =IF(BI18="","",BI18) -> 1 | BK18: 0.995 | BL18: 0.99 | BM18: 0.985 | BN18: 0.98 | BO18: 0.975 | BP18: 0.97 | BQ18: 0.965 | BR18: 0.96 | BS18: 1
B19: * | C19: IOTEFEDOTP | D19: Other Industry Other Petroleum Feedstock | E19: PJ, PJ/a | F19: INDOTH | G19: IOTFEED | H19: 2010 | I19: 30 | J19: 1 | K19: 0.15 | L19: =IFERROR(IF(_xlfn.XLOOKUP(D19,tbl_tech[TECHNOLOGY - Other],tbl_tech[NCAP_COST])=0,"",_xlfn.XLOOKUP(D19,tbl_tech[TECHNOLOGY - Other],tbl_tech[NCAP_COST])),"") | M19: =IFERROR(IF(_xlfn.XLOOKUP(D19,tbl_tech[TECHNOLOGY - Other],tbl_tech[NCAP_FOM])=0,"",_xlfn.XLOOKUP(D19,tbl_tech[TECHNOLOGY - Other],tbl_tech[NCAP_FOM])),"") | N19: 0 | Q19: 0 | R19: 0.081920908 | S19: 0.03697159 | T19: 0.025984204 | U19: 0.019245539 | V19: 0 | W19: 0.0040194004 | X19: 0.0027224355 | Y19: 0.033022958 | Z19: 0.028784318 | AF19: 1 | AH19: =IF(BI19="","",$BS19/BI19) -> 1 | AI19: =IF(BJ19="","",$BS19/BJ19) -> 1 | AJ19: =IF(BK19="","",$BS19/BK19) -> 1.0050251 | AK19: =IF(BL19="","",$BS19/BL19) -> 1.010101 | AL19: =IF(BM19="","",$BS19/BM19) -> 1.0152284 | AM19: =IF(BN19="","",$BS19/BN19) -> 1.0204082 | AN19: =IF(BO19="","",$BS19/BO19) -> 1.025641 | AO19: =IF(BP19="","",$BS19/BP19) -> 1.0309278 | ... AQ19: =IF(BR19="","",$BS19/BR19) -> 1.0416667 | BB19: =IF(AW19="","",AW19) | BC19: =IF(AX19="","",AX19) | BD19: =IF(AY19="","",AY19) | BE19: =IF(AZ19="","",AZ19) | BF19: =IF(BA19="","",BA19) | BI19: 1 | BJ19: =IF(BI19="","",BI19) -> 1 | BK19: 0.995 | BL19: 0.99 | BM19: 0.985 | BN19: 0.98 | BO19: 0.975 | BP19: 0.97 | BQ19: 0.965 | BR19: 0.96 | BS19: 1
B20: * | C20: IOTEETCELC | D20: Other Industry Electrochemical | E20: PJ, PJ/a | F20: INDELCOT | G20: IOTETC | H20: 2010 | I20: 30 | J20: 1 | K20: 0.15 | L20: =IFERROR(IF(_xlfn.XLOOKUP(D20,tbl_tech[TECHNOLOGY - Other],tbl_tech[NCAP_COST])=0,"",_xlfn.XLOOKUP(D20,tbl_tech[TECHNOLOGY - Other],tbl_tech[NCAP_COST])),"") -> 177.58015 | M20: =IFERROR(IF(_xlfn.XLOOKUP(D20,tbl_tech[TECHNOLOGY - Other],tbl_tech[NCAP_FOM])=0,"",_xlfn.XLOOKUP(D20,tbl_tech[TECHNOLOGY - Other],tbl_tech[NCAP_FOM])),"") -> 21.847032 | N20: 0 | Q20: 0.92696647 | R20: 2.3688162 | S20: 1.0690665 | T20: 0.90255485 | U20: 0.66848902 | V20: 1.4369922 | W20: 3.2678986 | X20: 2.2134254 | Y20: 1.4013987 | Z20: 1.2215231 | AF20: 1 | AH20: =IF(BI20="","",$BS20/BI20) -> 1 | AI20: =IF(BJ20="","",$BS20/BJ20) -> 1 | AJ20: =IF(BK20="","",$BS20/BK20) -> 1.0944772 | AK20: =IF(BL20="","",$BS20/BL20) -> 1.1900789 | AL20: =IF(BM20="","",$BS20/BM20) -> 1.3017774 | AM20: =IF(BN20="","",$BS20/BN20) -> 1.4111348 | AN20: =IF(BO20="","",$BS20/BO20) -> 1.5095043 | AO20: =IF(BP20="","",$BS20/BP20) -> 1.5083436 | ... AQ20: =IF(BR20="","",$BS20/BR20) -> 1.606141 | BB20: =IF(AW20="","",AW20) | BC20: =IF(AX20="","",AX20) | BD20: =IF(AY20="","",AY20) | BE20: =IF(AZ20="","",AZ20) | BF20: =IF(BA20="","",BA20) | BI20: 1 | BJ20: =IF(BI20="","",BI20) -> 1 | BK20: ='Demand (old)'!G$137 -> 0.91367821 | BL20: ='Demand (old)'!H$137 -> 0.84028046 | BM20: ='Demand (old)'!I$137 -> 0.7681805 | BN20: ='Demand (old)'!J$137 -> 0.70864954 | BO20: ='Demand (old)'!K$137 -> 0.66246912 | BP20: ='Demand (old)'!L$137 -> 0.66297892 | BQ20: ='Demand (old)'!M$137 -> 0.64131463 | BR20: ='Demand (old)'!N$137 -> 0.62261036 | BS20: 1
B21: * | C21: IOTEPRHELC | D21: Other Industry Electricity Process Heat | E21: PJ, PJ/a | F21: INDELCOT | G21: IOTPRH | H21: 2010 | I21: 30 | J21: 1 | K21: 0.15 | L21: =IFERROR(IF(_xlfn.XLOOKUP(D21,tbl_tech[TECHNOLOGY - Other],tbl_tech[NCAP_COST])=0,"",_xlfn.XLOOKUP(D21,tbl_tech[TECHNOLOGY - Other],tbl_tech[NCAP_COST])),"") -> 25.663247 | M21: =IFERROR(IF(_xlfn.XLOOKUP(D21,tbl_tech[TECHNOLOGY - Other],tbl_tech[NCAP_FOM])=0,"",_xlfn.XLOOKUP(D21,tbl_tech[TECHNOLOGY - Other],tbl_tech[NCAP_FOM])),"") -> 2.5663247 | N21: 0 | Q21: 18.745322 | R21: 47.902728 | S21: 21.618901 | T21: 18.251665 | U21: 13.518334 | V21: 17.332336 | W21: 39.415884 | X21: 26.697316 | Y21: 16.903025 | Z21: 14.733448 | AF21: 1 | AH21: =IF(BI21="","",$BS21/BI21) -> 1 | AI21: =IF(BJ21="","",$BS21/BJ21) -> 1 | AJ21: =IF(BK21="","",$BS21/BK21) -> 1.0944772 | AK21: =IF(BL21="","",$BS21/BL21) -> 1.1900789 | AL21: =IF(BM21="","",$BS21/BM21) -> 1.3017774 | AM21: =IF(BN21="","",$BS21/BN21) -> 1.4111348 | AN21: =IF(BO21="","",$BS21/BO21) -> 1.5095043 | AO21: =IF(BP21="","",$BS21/BP21) -> 1.5083436 | ... AQ21: =IF(BR21="","",$BS21/BR21) -> 1.606141 | BB21: =IF(AW21="","",AW21) | BC21: =IF(AX21="","",AX21) | BD21: =IF(AY21="","",AY21) | BE21: =IF(AZ21="","",AZ21) | BF21: =IF(BA21="","",BA21) | BI21: 1 | BJ21: =IF(BI21="","",BI21) -> 1 | BK21: ='Demand (old)'!G$137 -> 0.91367821 | BL21: ='Demand (old)'!H$137 -> 0.84028046 | BM21: ='Demand (old)'!I$137 -> 0.7681805 | BN21: ='Demand (old)'!J$137 -> 0.70864954 | BO21: ='Demand (old)'!K$137 -> 0.66246912 | BP21: ='Demand (old)'!L$137 -> 0.66297892 | BQ21: ='Demand (old)'!M$137 -> 0.64131463 | BR21: ='Demand (old)'!N$137 -> 0.62261036 | BS21: 1
B22: * | C22: IOTEPRHRFL | D22: Other Industry Residual Oil Process Heat | E22: PJ, PJ/a | F22: INDRFLEA | G22: IOTPRH | H22: 2010 | I22: 30 | J22: 1 | K22: 0.15 | L22: =IFERROR(IF(_xlfn.XLOOKUP(D22,tbl_tech[TECHNOLOGY - Other],tbl_tech[NCAP_COST])=0,"",_xlfn.XLOOKUP(D22,tbl_tech[TECHNOLOGY - Other],tbl_tech[NCAP_COST])),"") -> 22.077411 | M22: =IFERROR(IF(_xlfn.XLOOKUP(D22,tbl_tech[TECHNOLOGY - Other],tbl_tech[NCAP_FOM])=0,"",_xlfn.XLOOKUP(D22,tbl_tech[TECHNOLOGY - Other],tbl_tech[NCAP_FOM])),"") -> 2.2077411 | N22: 0 | Q22: 0.53533247 | R22: 0.11740429 | S22: 0.052985536 | T22: 0.1829215 | U22: 0.13548319 | V22: 0.46359417 | W22: 0 | X22: 0 | Y22: 0.096741378 | Z22: 0.084324202 | AF22: 1 | AH22: =IF(BI22="","",$BS22/BI22) -> 1 | AI22: =IF(BJ22="","",$BS22/BJ22) -> 1 | AJ22: =IF(BK22="","",$BS22/BK22) -> 1.0944772 | AK22: =IF(BL22="","",$BS22/BL22) -> 1.1900789 | AL22: =IF(BM22="","",$BS22/BM22) -> 1.3017774 | AM22: =IF(BN22="","",$BS22/BN22) -> 1.4111348 | AN22: =IF(BO22="","",$BS22/BO22) -> 1.5095043 | AO22: =IF(BP22="","",$BS22/BP22) -> 1.5083436 | ... AQ22: =IF(BR22="","",$BS22/BR22) -> 1.606141 | BB22: =IF(AW22="","",AW22) | BC22: =IF(AX22="","",AX22) | BD22: =IF(AY22="","",AY22) | BE22: =IF(AZ22="","",AZ22) | BF22: =IF(BA22="","",BA22) | BI22: 1 | BJ22: =IF(BI22="","",BI22) -> 1 | BK22: ='Demand (old)'!G$137 -> 0.91367821 | BL22: ='Demand (old)'!H$137 -> 0.84028046 | BM22: ='Demand (old)'!I$137 -> 0.7681805 | BN22: ='Demand (old)'!J$137 -> 0.70864954 | BO22: ='Demand (old)'!K$137 -> 0.66246912 | BP22: ='Demand (old)'!L$137 -> 0.66297892 | BQ22: ='Demand (old)'!M$137 -> 0.64131463 | BR22: ='Demand (old)'!N$137 -> 0.62261036 | BS22: 1
B23: * | C23: IOTEPRHDST | D23: Other Industry Distillate Oil Process Heat | E23: PJ, PJ/a | F23: INDDSTEA | G23: IOTPRH | H23: 2010 | I23: 30 | J23: 1 | K23: 0.15 | L23: =IFERROR(IF(_xlfn.XLOOKUP(D23,tbl_tech[TECHNOLOGY - Other],tbl_tech[NCAP_COST])=0,"",_xlfn.XLOOKUP(D23,tbl_tech[TECHNOLOGY - Other],tbl_tech[NCAP_COST])),"") -> 21.147836 | M23: =IFERROR(IF(_xlfn.XLOOKUP(D23,tbl_tech[TECHNOLOGY - Other],tbl_tech[NCAP_FOM])=0,"",_xlfn.XLOOKUP(D23,tbl_tech[TECHNOLOGY - Other],tbl_tech[NCAP_FOM])),"") -> 2.1147836 | N23: 0 | Q23: 0.23471493 | R23: 0.65888719 | S23: 0.29736129 | T23: 0.25170897 | U23: 0.18643153 | V23: 0.80190647 | W23: 0.55865864 | X23: 0.37839278 | Y23: 0.31874158 | Z23: 0.27782971 | AF23: 1 | AH23: =IF(BI23="","",$BS23/BI23) -> 1 | AI23: =IF(BJ23="","",$BS23/BJ23) -> 1 | AJ23: =IF(BK23="","",$BS23/BK23) -> 1.0944772 | AK23: =IF(BL23="","",$BS23/BL23) -> 1.1900789 | AL23: =IF(BM23="","",$BS23/BM23) -> 1.3017774 | AM23: =IF(BN23="","",$BS23/BN23) -> 1.4111348 | AN23: =IF(BO23="","",$BS23/BO23) -> 1.5095043 | AO23: =IF(BP23="","",$BS23/BP23) -> 1.5083436 | ... AQ23: =IF(BR23="","",$BS23/BR23) -> 1.606141 | BB23: =IF(AW23="","",AW23) | BC23: =IF(AX23="","",AX23) | BD23: =IF(AY23="","",AY23) | BE23: =IF(AZ23="","",AZ23) | BF23: =IF(BA23="","",BA23) | BI23: 1 | BJ23: =IF(BI23="","",BI23) -> 1 | BK23: ='Demand (old)'!G$137 -> 0.91367821 | BL23: ='Demand (old)'!H$137 -> 0.84028046 | BM23: ='Demand (old)'!I$137 -> 0.7681805 | BN23: ='Demand (old)'!J$137 -> 0.70864954 | BO23: ='Demand (old)'!K$137 -> 0.66246912 | BP23: ='Demand (old)'!L$137 -> 0.66297892 | BQ23: ='Demand (old)'!M$137 -> 0.64131463 | BR23: ='Demand (old)'!N$137 -> 0.62261036 | BS23: 1
B24: * | C24: IOTEPRHNGA | D24: Other Industry Natural Gas Process Heat | E24: PJ, PJ/a | F24: INDNGAEA | G24: IOTPRH | H24: 2010 | I24: 30 | J24: 1 | K24: 0.15 | L24: =IFERROR(IF(_xlfn.XLOOKUP(D24,tbl_tech[TECHNOLOGY - Other],tbl_tech[NCAP_COST])=0,"",_xlfn.XLOOKUP(D24,tbl_tech[TECHNOLOGY - Other],tbl_tech[NCAP_COST])),"") -> 18.591504 | M24: =IFERROR(IF(_xlfn.XLOOKUP(D24,tbl_tech[TECHNOLOGY - Other],tbl_tech[NCAP_FOM])=0,"",_xlfn.XLOOKUP(D24,tbl_tech[TECHNOLOGY - Other],tbl_tech[NCAP_FOM])),"") -> 1.8591504 | N24: 0 | Q24: 41.577326 | R24: 121.57819 | S24: 54.869252 | T24: 37.33851 | U24: 27.655254 | V24: 39.845322 | W24: 96.154072 | X24: 65.12744 | Y24: 28.687478 | Z24: 25.005315 | AF24: 1 | AH24: =IF(BI24="","",$BS24/BI24) -> 1 | AI24: =IF(BJ24="","",$BS24/BJ24) -> 1 | AJ24: =IF(BK24="","",$BS24/BK24) -> 1.0944772 | AK24: =IF(BL24="","",$BS24/BL24) -> 1.1900789 | AL24: =IF(BM24="","",$BS24/BM24) -> 1.3017774 | AM24: =IF(BN24="","",$BS24/BN24) -> 1.4111348 | AN24: =IF(BO24="","",$BS24/BO24) -> 1.5095043 | AO24: =IF(BP24="","",$BS24/BP24) -> 1.5083436 | ... AQ24: =IF(BR24="","",$BS24/BR24) -> 1.606141 | BB24: =IF(AW24="","",AW24) | BC24: =IF(AX24="","",AX24) | BD24: =IF(AY24="","",AY24) | BE24: =IF(AZ24="","",AZ24) | BF24: =IF(BA24="","",BA24) | BI24: 1 | BJ24: =IF(BI24="","",BI24) -> 1 | BK24: ='Demand (old)'!G$137 -> 0.91367821 | BL24: ='Demand (old)'!H$137 -> 0.84028046 | BM24: ='Demand (old)'!I$137 -> 0.7681805 | BN24: ='Demand (old)'!J$137 -> 0.70864954 | BO24: ='Demand (old)'!K$137 -> 0.66246912 | BP24: ='Demand (old)'!L$137 -> 0.66297892 | BQ24: ='Demand (old)'!M$137 -> 0.64131463 | BR24: ='Demand (old)'!N$137 -> 0.62261036 | BS24: 1
B25: * | C25: IOTEPRHLPG | D25: Other Industry LPG Process Heat | E25: PJ, PJ/a | F25: INDLPGEA | G25: IOTPRH | H25: 2010 | I25: 30 | J25: 1 | K25: 0.15 | L25: =IFERROR(IF(_xlfn.XLOOKUP(D25,tbl_tech[TECHNOLOGY - Other],tbl_tech[NCAP_COST])=0,"",_xlfn.XLOOKUP(D25,tbl_tech[TECHNOLOGY - Other],tbl_tech[NCAP_COST])),"") -> 23.23938 | M25: =IFERROR(IF(_xlfn.XLOOKUP(D25,tbl_tech[TECHNOLOGY - Other],tbl_tech[NCAP_FOM])=0,"",_xlfn.XLOOKUP(D25,tbl_tech[TECHNOLOGY - Other],tbl_tech[NCAP_FOM])),"") -> 2.323938 | N25: 0 | Q25: 0.2649548 | R25: 0.54233665 | S25: 0.24476105 | T25: 0.33428035 | U25: 0.2475891 | V25: 0.21550827 | W25: 2.1019133 | X25: 1.4236758 | Y25: 0.65958334 | Z25: 0.57492295 | AF25: 1 | AH25: =IF(BI25="","",$BS25/BI25) -> 1 | AI25: =IF(BJ25="","",$BS25/BJ25) -> 1 | AJ25: =IF(BK25="","",$BS25/BK25) -> 1.0944772 | AK25: =IF(BL25="","",$BS25/BL25) -> 1.1900789 | AL25: =IF(BM25="","",$BS25/BM25) -> 1.3017774 | AM25: =IF(BN25="","",$BS25/BN25) -> 1.4111348 | AN25: =IF(BO25="","",$BS25/BO25) -> 1.5095043 | AO25: =IF(BP25="","",$BS25/BP25) -> 1.5083436 | ... AQ25: =IF(BR25="","",$BS25/BR25) -> 1.606141 | BB25: =IF(AW25="","",AW25) | BC25: =IF(AX25="","",AX25) | BD25: =IF(AY25="","",AY25) | BE25: =IF(AZ25="","",AZ25) | BF25: =IF(BA25="","",BA25) | BI25: 1 | BJ25: =IF(BI25="","",BI25) -> 1 | BK25: ='Demand (old)'!G$137 -> 0.91367821 | BL25: ='Demand (old)'!H$137 -> 0.84028046 | BM25: ='Demand (old)'!I$137 -> 0.7681805 | BN25: ='Demand (old)'!J$137 -> 0.70864954 | BO25: ='Demand (old)'!K$137 -> 0.66246912 | BP25: ='Demand (old)'!L$137 -> 0.66297892 | BQ25: ='Demand (old)'!M$137 -> 0.64131463 | BR25: ='Demand (old)'!N$137 -> 0.62261036 | BS25: 1
B26: * | C26: IOTEPRHCOA | D26: Other Industry Coal Process Heat | E26: PJ, PJ/a | F26: INDCOAEA | G26: IOTPRH | H26: 2010 | I26: 30 | J26: 1 | K26: 0.2 | L26: =IFERROR(IF(_xlfn.XLOOKUP(D26,tbl_tech[TECHNOLOGY - Other],tbl_tech[NCAP_COST])=0,"",_xlfn.XLOOKUP(D26,tbl_tech[TECHNOLOGY - Other],tbl_tech[NCAP_COST])),"") -> 23.23938 | M26: =IFERROR(IF(_xlfn.XLOOKUP(D26,tbl_tech[TECHNOLOGY - Other],tbl_tech[NCAP_FOM])=0,"",_xlfn.XLOOKUP(D26,tbl_tech[TECHNOLOGY - Other],tbl_tech[NCAP_FOM])),"") -> 2.323938 | N26: 0 | Q26: 0.4978033 | R26: 11.354068 | S26: 5.1241857 | T26: 8.4787259 | U26: 6.2798789 | V26: 1.1837529 | W26: 2.6458385 | X26: 1.7920893 | Y26: 1.070428 | Z26: 0.93303389 | AF26: 1 | AH26: =IF(BI26="","",$BS26/BI26) -> 1 | AI26: =IF(BJ26="","",$BS26/BJ26) -> 1 | AJ26: =IF(BK26="","",$BS26/BK26) -> 1.0944772 | AK26: =IF(BL26="","",$BS26/BL26) -> 1.1900789 | AL26: =IF(BM26="","",$BS26/BM26) -> 1.3017774 | AM26: =IF(BN26="","",$BS26/BN26) -> 1.4111348 | AN26: =IF(BO26="","",$BS26/BO26) -> 1.5095043 | AO26: =IF(BP26="","",$BS26/BP26) -> 1.5083436 | ... AQ26: =IF(BR26="","",$BS26/BR26) -> 1.606141 | BB26: =IF(AW26="","",AW26) | BC26: =IF(AX26="","",AX26) | BD26: =IF(AY26="","",AY26) | BE26: =IF(AZ26="","",AZ26) | BF26: =IF(BA26="","",BA26) | BI26: 1 | BJ26: =IF(BI26="","",BI26) -> 1 | BK26: ='Demand (old)'!G$137 -> 0.91367821 | BL26: ='Demand (old)'!H$137 -> 0.84028046 | BM26: ='Demand (old)'!I$137 -> 0.7681805 | BN26: ='Demand (old)'!J$137 -> 0.70864954 | BO26: ='Demand (old)'!K$137 -> 0.66246912 | BP26: ='Demand (old)'!L$137 -> 0.66297892 | BQ26: ='Demand (old)'!M$137 -> 0.64131463 | BR26: ='Demand (old)'!N$137 -> 0.62261036 | BS26: 1
B27: * | C27: IOTEMDRELC | D27: Other Industry Electricity Machine Drive | E27: PJ, PJ/a | F27: INDELCOT | G27: IOTMDR | H27: 2010 | I27: 30 | J27: 1 | K27: 0.15 | L27: =IFERROR(IF(_xlfn.XLOOKUP(D27,tbl_tech[TECHNOLOGY - Other],tbl_tech[NCAP_COST])=0,"",_xlfn.XLOOKUP(D27,tbl_tech[TECHNOLOGY - Other],tbl_tech[NCAP_COST])),"") -> 2.2387116 | M27: =IFERROR(IF(_xlfn.XLOOKUP(D27,tbl_tech[TECHNOLOGY - Other],tbl_tech[NCAP_FOM])=0,"",_xlfn.XLOOKUP(D27,tbl_tech[TECHNOLOGY - Other],tbl_tech[NCAP_FOM])),"") -> 0.22387116 | Q27: 57.986903 | R27: 148.18261 | S27: 66.876051 | T27: 56.45982 | U27: 41.817702 | V27: 44.184193 | W27: 100.48034 | X27: 68.057723 | Y27: 43.089777 | Z27: 37.559017 | AF27: 1 | AH27: =IF(BI27="","",$BS27/BI27) -> 1 | AI27: =IF(BJ27="","",$BS27/BJ27) -> 1 | AJ27: =IF(BK27="","",$BS27/BK27) -> 1.0944772 | AK27: =IF(BL27="","",$BS27/BL27) -> 1.1900789 | AL27: =IF(BM27="","",$BS27/BM27) -> 1.3017774 | AM27: =IF(BN27="","",$BS27/BN27) -> 1.4111348 | AN27: =IF(BO27="","",$BS27/BO27) -> 1.5095043 | AO27: =IF(BP27="","",$BS27/BP27) -> 1.5083436 | ... AQ27: =IF(BR27="","",$BS27/BR27) -> 1.606141 | BB27: =IF(AW27="","",AW27) | BC27: =IF(AX27="","",AX27) | BD27: =IF(AY27="","",AY27) | BE27: =IF(AZ27="","",AZ27) | BF27: =IF(BA27="","",BA27) | BI27: 1 | BJ27: =IF(BI27="","",BI27) -> 1 | BK27: ='Demand (old)'!G$137 -> 0.91367821 | BL27: ='Demand (old)'!H$137 -> 0.84028046 | BM27: ='Demand (old)'!I$137 -> 0.7681805 | BN27: ='Demand (old)'!J$137 -> 0.70864954 | BO27: ='Demand (old)'!K$137 -> 0.66246912 | BP27: ='Demand (old)'!L$137 -> 0.66297892 | BQ27: ='Demand (old)'!M$137 -> 0.64131463 | BR27: ='Demand (old)'!N$137 -> 0.62261036 | BS27: 1
B28: * | C28: IOTEMDRDST | D28: Other Industry Distillate Oil Machine Drive | E28: PJ, PJ/a | F28: INDDSTEA | G28: IOTMDR | H28: 2010 | I28: 30 | J28: 1 | K28: 0.15 | L28: =IFERROR(IF(_xlfn.XLOOKUP(D28,tbl_tech[TECHNOLOGY - Other],tbl_tech[NCAP_COST])=0,"",_xlfn.XLOOKUP(D28,tbl_tech[TECHNOLOGY - Other],tbl_tech[NCAP_COST])),"") -> 31.461021 | M28: =IFERROR(IF(_xlfn.XLOOKUP(D28,tbl_tech[TECHNOLOGY - Other],tbl_tech[NCAP_FOM])=0,"",_xlfn.XLOOKUP(D28,tbl_tech[TECHNOLOGY - Other],tbl_tech[NCAP_FOM])),"") -> 3.1461021 | Q28: 0.15647662 | R28: 0.43925813 | S28: 0.19824086 | T28: 0.16780598 | U28: 0.12428769 | V28: 1.4281572 | W28: 0.99494443 | X28: 0.67389952 | Y28: 0.56766357 | Z28: 0.49480149 | AF28: 1 | AH28: =IF(BI28="","",$BS28/BI28) -> 1 | AI28: =IF(BJ28="","",$BS28/BJ28) -> 1 | AJ28: =IF(BK28="","",$BS28/BK28) -> 1.0944772 | AK28: =IF(BL28="","",$BS28/BL28) -> 1.1900789 | AL28: =IF(BM28="","",$BS28/BM28) -> 1.3017774 | AM28: =IF(BN28="","",$BS28/BN28) -> 1.4111348 | AN28: =IF(BO28="","",$BS28/BO28) -> 1.5095043 | AO28: =IF(BP28="","",$BS28/BP28) -> 1.5083436 | ... AQ28: =IF(BR28="","",$BS28/BR28) -> 1.606141 | BB28: =IF(AW28="","",AW28) | BC28: =IF(AX28="","",AX28) | BD28: =IF(AY28="","",AY28) | BE28: =IF(AZ28="","",AZ28) | BF28: =IF(BA28="","",BA28) | BI28: 1 | BJ28: =IF(BI28="","",BI28) -> 1 | BK28: ='Demand (old)'!G$137 -> 0.91367821 | BL28: ='Demand (old)'!H$137 -> 0.84028046 | BM28: ='Demand (old)'!I$137 -> 0.7681805 | BN28: ='Demand (old)'!J$137 -> 0.70864954 | BO28: ='Demand (old)'!K$137 -> 0.66246912 | BP28: ='Demand (old)'!L$137 -> 0.66297892 | BQ28: ='Demand (old)'!M$137 -> 0.64131463 | BR28: ='Demand (old)'!N$137 -> 0.62261036 | BS28: 1
B29: * | C29: IOTEMDRNGA | D29: Other Industry Natural Gas Machine Drive | E29: PJ, PJ/a | F29: INDNGAEA | G29: IOTMDR | H29: 2010 | I29: 30 | J29: 1 | K29: 0.15 | L29: =IFERROR(IF(_xlfn.XLOOKUP(D29,tbl_tech[TECHNOLOGY - Other],tbl_tech[NCAP_COST])=0,"",_xlfn.XLOOKUP(D29,tbl_tech[TECHNOLOGY - Other],tbl_tech[NCAP_COST])),"") -> 34.95669 | M29: =IFERROR(IF(_xlfn.XLOOKUP(D29,tbl_tech[TECHNOLOGY - Other],tbl_tech[NCAP_FOM])=0,"",_xlfn.XLOOKUP(D29,tbl_tech[TECHNOLOGY - Other],tbl_tech[NCAP_FOM])),"") -> 3.495669 | Q29: 1.4666543 | R29: 4.2887119 | S29: 1.9355315 | T29: 1.3171286 | U29: 0.97554848 | V29: 1.5488136 | W29: 3.7375713 | X29: 2.5315459 | Y29: 1.1151009 | Z29: 0.97197286 | AF29: 1 | AH29: =IF(BI29="","",$BS29/BI29) -> 1 | AI29: =IF(BJ29="","",$BS29/BJ29) -> 1 | AJ29: =IF(BK29="","",$BS29/BK29) -> 1.0944772 | AK29: =IF(BL29="","",$BS29/BL29) -> 1.1900789 | AL29: =IF(BM29="","",$BS29/BM29) -> 1.3017774 | AM29: =IF(BN29="","",$BS29/BN29) -> 1.4111348 | AN29: =IF(BO29="","",$BS29/BO29) -> 1.5095043 | AO29: =IF(BP29="","",$BS29/BP29) -> 1.5083436 | ... AQ29: =IF(BR29="","",$BS29/BR29) -> 1.606141 | BB29: =IF(AW29="","",AW29) | BC29: =IF(AX29="","",AX29) | BD29: =IF(AY29="","",AY29) | BE29: =IF(AZ29="","",AZ29) | BF29: =IF(BA29="","",BA29) | BI29: 1 | BJ29: =IF(BI29="","",BI29) -> 1 | BK29: ='Demand (old)'!G$137 -> 0.91367821 | BL29: ='Demand (old)'!H$137 -> 0.84028046 | BM29: ='Demand (old)'!I$137 -> 0.7681805 | BN29: ='Demand (old)'!J$137 -> 0.70864954 | BO29: ='Demand (old)'!K$137 -> 0.66246912 | BP29: ='Demand (old)'!L$137 -> 0.66297892 | BQ29: ='Demand (old)'!M$137 -> 0.64131463 | BR29: ='Demand (old)'!N$137 -> 0.62261036 | BS29: 1
B30: * | C30: IOTEMDRLPG | D30: Other Industry LPG Machine Drive | E30: PJ, PJ/a | F30: INDLPGEA | G30: IOTMDR | H30: 2010 | I30: 30 | J30: 1 | K30: 0.15 | L30: =IFERROR(IF(_xlfn.XLOOKUP(D30,tbl_tech[TECHNOLOGY - Other],tbl_tech[NCAP_COST])=0,"",_xlfn.XLOOKUP(D30,tbl_tech[TECHNOLOGY - Other],tbl_tech[NCAP_COST])),"") -> 34.95669 | M30: =IFERROR(IF(_xlfn.XLOOKUP(D30,tbl_tech[TECHNOLOGY - Other],tbl_tech[NCAP_FOM])=0,"",_xlfn.XLOOKUP(D30,tbl_tech[TECHNOLOGY - Other],tbl_tech[NCAP_FOM])),"") -> 3.495669 | N30: 0 | Q30: 0.037850686 | R30: 0.077476664 | S30: 0.034965865 | T30: 0.047754336 | U30: 0.035369872 | V30: 0.16163121 | W30: 1.5764349 | X30: 1.0677569 | Y30: 0.4946875 | Z30: 0.43119222 | AF30: 1 | AH30: =IF(BI30="","",$BS30/BI30) -> 1 | AI30: =IF(BJ30="","",$BS30/BJ30) -> 1 | AJ30: =IF(BK30="","",$BS30/BK30) -> 1.0944772 | AK30: =IF(BL30="","",$BS30/BL30) -> 1.1900789 | AL30: =IF(BM30="","",$BS30/BM30) -> 1.3017774 | AM30: =IF(BN30="","",$BS30/BN30) -> 1.4111348 | AN30: =IF(BO30="","",$BS30/BO30) -> 1.5095043 | AO30: =IF(BP30="","",$BS30/BP30) -> 1.5083436 | ... AQ30: =IF(BR30="","",$BS30/BR30) -> 1.606141 | BB30: =IF(AW30="","",AW30) | BC30: =IF(AX30="","",AX30) | BD30: =IF(AY30="","",AY30) | BE30: =IF(AZ30="","",AZ30) | BF30: =IF(BA30="","",BA30) | BI30: 1 | BJ30: =IF(BI30="","",BI30) -> 1 | BK30: ='Demand (old)'!G$137 -> 0.91367821 | BL30: ='Demand (old)'!H$137 -> 0.84028046 | BM30: ='Demand (old)'!I$137 -> 0.7681805 | BN30: ='Demand (old)'!J$137 -> 0.70864954 | BO30: ='Demand (old)'!K$137 -> 0.66246912 | BP30: ='Demand (old)'!L$137 -> 0.66297892 | BQ30: ='Demand (old)'!M$137 -> 0.64131463 | BR30: ='Demand (old)'!N$137 -> 0.62261036 | BS30: 1
B31: * | C31: IOTEMDRCOA | D31: Other Industry Coal Machine Drive | E31: PJ, PJ/a | F31: INDCOAEA | G31: IOTMDR | H31: 2010 | I31: 30 | J31: 1 | K31: 0.2 | L31: =IFERROR(IF(_xlfn.XLOOKUP(D31,tbl_tech[TECHNOLOGY - Other],tbl_tech[NCAP_COST])=0,"",_xlfn.XLOOKUP(D31,tbl_tech[TECHNOLOGY - Other],tbl_tech[NCAP_COST])),"") -> 34.95723 | M31: =IFERROR(IF(_xlfn.XLOOKUP(D31,tbl_tech[TECHNOLOGY - Other],tbl_tech[NCAP_FOM])=0,"",_xlfn.XLOOKUP(D31,tbl_tech[TECHNOLOGY - Other],tbl_tech[NCAP_FOM])),"") -> 3.495723 | N31: 0 | V31: 0.23675057 | W31: 0.5291677 | X31: 0.35841787 | Y31: 0.21408559 | Z31: 0.18660678 | AF31: 1 | AH31: =IF(BI31="","",$BS31/BI31) -> 1 | AI31: =IF(BJ31="","",$BS31/BJ31) -> 1 | AJ31: =IF(BK31="","",$BS31/BK31) -> 1.0944772 | AK31: =IF(BL31="","",$BS31/BL31) -> 1.1900789 | AL31: =IF(BM31="","",$BS31/BM31) -> 1.3017774 | AM31: =IF(BN31="","",$BS31/BN31) -> 1.4111348 | AN31: =IF(BO31="","",$BS31/BO31) -> 1.5095043 | AO31: =IF(BP31="","",$BS31/BP31) -> 1.5083436 | ... AQ31: =IF(BR31="","",$BS31/BR31) -> 1.606141 | BB31: =IF(AW31="","",AW31) | BC31: =IF(AX31="","",AX31) | BD31: =IF(AY31="","",AY31) | BE31: =IF(AZ31="","",AZ31) | BF31: =IF(BA31="","",BA31) | BI31: 1 | BJ31: =IF(BI31="","",BI31) -> 1 | BK31: ='Demand (old)'!G$137 -> 0.91367821 | BL31: ='Demand (old)'!H$137 -> 0.84028046 | BM31: ='Demand (old)'!I$137 -> 0.7681805 | BN31: ='Demand (old)'!J$137 -> 0.70864954 | BO31: ='Demand (old)'!K$137 -> 0.66246912 | BP31: ='Demand (old)'!L$137 -> 0.66297892 | BQ31: ='Demand (old)'!M$137 -> 0.64131463 | BR31: ='Demand (old)'!N$137 -> 0.62261036 | BS31: 1
B32: R2,R3,R4,R5,R6 | C32: IOTEFACELC | D32: Other Industry Electricity Facilities | E32: PJ, PJ/a | F32: INDELCOT | G32: IOTFAC | H32: 2010 | I32: 30 | J32: 1 | K32: 0.15 | L32: =IFERROR(IF(_xlfn.XLOOKUP(D32,tbl_tech[TECHNOLOGY - Other],tbl_tech[NCAP_COST])=0,"",_xlfn.XLOOKUP(D32,tbl_tech[TECHNOLOGY - Other],tbl_tech[NCAP_COST])),"") -> 100 | M32: =IFERROR(IF(_xlfn.XLOOKUP(D32,tbl_tech[TECHNOLOGY - Other],tbl_tech[NCAP_FOM])=0,"",_xlfn.XLOOKUP(D32,tbl_tech[TECHNOLOGY - Other],tbl_tech[NCAP_FOM])),"") -> 1 | Q32: =Q46-Q35-Q33 -> #REF! | R32: =R46-R35-R33 -> #REF! | S32: =S46-S35-S33 -> #REF! | T32: =T46-T35-T33 -> #REF! | U32: =U46-U35-U33 -> #REF! | V32: =V46-TechData_OTR_dep!V33-V35 -> 6.8078359 | W32: =W46-TechData_OTR_dep!W33-W35 -> 17.821875 | X32: =X46-TechData_OTR_dep!X33-X35 -> 6.9765783 | Y32: =Y46-TechData_OTR_dep!Y33-Y35 -> 15.306989 | Z32: =Z46-TechData_OTR_dep!Z33-Z35 -> 1.6851452 | AA32: =AA46-AA35-AA33 -> #REF! | AB32: =AB46-AB35-AB33 -> #REF! | AC32: =AC46-AC35-AC33 -> #REF! | AD32: =AD46-AD35-AD33 -> #REF! | AE32: =AE46-AE35-AE33 -> #REF! | AF32: 1 | AH32: =IF(BI32="","",$BS32/BI32) -> 1 | AI32: =IF(BJ32="","",$BS32/BJ32) -> 1 | AJ32: =IF(BK32="","",$BS32/BK32) -> 1.0944772 | AK32: =IF(BL32="","",$BS32/BL32) -> 1.1900789 | AL32: =IF(BM32="","",$BS32/BM32) -> 1.3017774 | AM32: =IF(BN32="","",$BS32/BN32) -> 1.4111348 | AN32: =IF(BO32="","",$BS32/BO32) -> 1.5095043 | AO32: =IF(BP32="","",$BS32/BP32) -> 1.5083436 | ... AQ32: =IF(BR32="","",$BS32/BR32) -> 1.606141 | BB32: =IF(AW32="","",AW32) | BC32: =IF(AX32="","",AX32) | BD32: =IF(AY32="","",AY32) | BE32: =IF(AZ32="","",AZ32) | BF32: =IF(BA32="","",BA32) | BI32: 1 | BJ32: =IF(BI32="","",BI32) -> 1 | BK32: ='Demand (old)'!G$137 -> 0.91367821 | BL32: ='Demand (old)'!H$137 -> 0.84028046 | BM32: ='Demand (old)'!I$137 -> 0.7681805 | BN32: ='Demand (old)'!J$137 -> 0.70864954 | BO32: ='Demand (old)'!K$137 -> 0.66246912 | BP32: ='Demand (old)'!L$137 -> 0.66297892 | BQ32: ='Demand (old)'!M$137 -> 0.64131463 | BR32: ='Demand (old)'!N$137 -> 0.62261036 | BS32: 1
B33: R2,R3,R4,R5,R6 | C33: IOTEFACRFL | D33: Other Industry Residual Oil Facilities | E33: PJ, PJ/a | F33: INDRFLEA | G33: IOTFAC | H33: 2010 | I33: 30 | J33: 1 | K33: 0.15 | L33: =IFERROR(IF(_xlfn.XLOOKUP(D33,tbl_tech[TECHNOLOGY - Other],tbl_tech[NCAP_COST])=0,"",_xlfn.XLOOKUP(D33,tbl_tech[TECHNOLOGY - Other],tbl_tech[NCAP_COST])),"") -> 100 | M33: =IFERROR(IF(_xlfn.XLOOKUP(D33,tbl_tech[TECHNOLOGY - Other],tbl_tech[NCAP_FOM])=0,"",_xlfn.XLOOKUP(D33,tbl_tech[TECHNOLOGY - Other],tbl_tech[NCAP_FOM])),"") -> 1 | Q33: =Q$46/$AH$46*AR$51*Original!#REF!*1.1 -> #REF! | R33: =R$46/$AH$46*AS$51*Original!#REF!*1.1 -> #REF! | S33: =S$46/$AH$46*AT$51*Original!#REF!*1.1 -> #REF! | T33: =T$46/$AH$46*AU$51*Original!#REF!*1.1 -> #REF! | U33: =U$46/$AH$46*AV$51*Original!#REF!*1.1 -> #REF! | V33: =TechData_OTR_dep!V$46/TechData_OTR_dep!$AH$46*TechData_OTR_dep!AW$51*0.0315701442609241 -> 0.29556734 | W33: =TechData_OTR_dep!W$46/TechData_OTR_dep!$AH$46*TechData_OTR_dep!AX$51*0.0315664085765336 -> 0.77359488 | X33: =TechData_OTR_dep!X$46/TechData_OTR_dep!$AH$46*TechData_OTR_dep!AY$51*0.0318725099601594 -> 0.30582261 | Y33: =TechData_OTR_dep!Y$46/TechData_OTR_dep!$AH$46*TechData_OTR_dep!AZ$51*0.0315575161180862 -> 0.66427903 | Z33: =TechData_OTR_dep!Z$46/TechData_OTR_dep!$AH$46*TechData_OTR_dep!BA$51*0.032258064516129 -> 0.074767533 | AA33: =AA$46/$AH$46*BB$51*Original!#REF!*1.1 -> #REF! | AB33: =AB$46/$AH$46*BC$51*Original!#REF!*1.1 -> #REF! | AC33: =AC$46/$AH$46*BD$51*Original!#REF!*1.1 -> #REF! | AD33: =AD$46/$AH$46*BE$51*Original!#REF!*1.1 -> #REF! | AE33: =AE$46/$AH$46*BF$51*Original!#REF!*1.1 -> #REF! | AF33: 1 | AH33: =IF(BI33="","",$BS33/BI33) -> 1 | AI33: =IF(BJ33="","",$BS33/BJ33) -> 1 | AJ33: =IF(BK33="","",$BS33/BK33) -> 1.0944772 | AK33: =IF(BL33="","",$BS33/BL33) -> 1.1900789 | AL33: =IF(BM33="","",$BS33/BM33) -> 1.3017774 | AM33: =IF(BN33="","",$BS33/BN33) -> 1.4111348 | AN33: =IF(BO33="","",$BS33/BO33) -> 1.5095043 | AO33: =IF(BP33="","",$BS33/BP33) -> 1.5083436 | ... AQ33: =IF(BR33="","",$BS33/BR33) -> 1.606141 | BB33: =IF(AW33="","",AW33) | BC33: =IF(AX33="","",AX33) | BD33: =IF(AY33="","",AY33) | BE33: =IF(AZ33="","",AZ33) | BF33: =IF(BA33="","",BA33) | BI33: 1 | BJ33: =IF(BI33="","",BI33) -> 1 | BK33: ='Demand (old)'!G$137 -> 0.91367821 | BL33: ='Demand (old)'!H$137 -> 0.84028046 | BM33: ='Demand (old)'!I$137 -> 0.7681805 | BN33: ='Demand (old)'!J$137 -> 0.70864954 | BO33: ='Demand (old)'!K$137 -> 0.66246912 | BP33: ='Demand (old)'!L$137 -> 0.66297892 | BQ33: ='Demand (old)'!M$137 -> 0.64131463 | BR33: ='Demand (old)'!N$137 -> 0.62261036 | BS33: 1
B34: * | C34: IOTEFACDST | D34: Other Industry Distillate Oil Facilities | E34: PJ, PJ/a | F34: INDDSTEA | G34: IOTFAC | H34: 2010 | I34: 30 | J34: 1 | K34: 0.15 | L34: =IFERROR(IF(_xlfn.XLOOKUP(D34,tbl_tech[TECHNOLOGY - Other],tbl_tech[NCAP_COST])=0,"",_xlfn.XLOOKUP(D34,tbl_tech[TECHNOLOGY - Other],tbl_tech[NCAP_COST])),"") | M34: =IFERROR(IF(_xlfn.XLOOKUP(D34,tbl_tech[TECHNOLOGY - Other],tbl_tech[NCAP_FOM])=0,"",_xlfn.XLOOKUP(D34,tbl_tech[TECHNOLOGY - Other],tbl_tech[NCAP_FOM])),"") | Q34: 1.5647662 | R34: 4.3925813 | S34: 1.9824086 | T34: 1.6780598 | U34: 1.2428769 | V34: 1.3365108 | W34: 0.93109773 | X34: 0.63065463 | Y34: 0.53123596 | Z34: 0.46304952 | AF34: 1 | AH34: =IF(BI34="","",$BS34/BI34) -> 1 | AI34: =IF(BJ34="","",$BS34/BJ34) -> 1 | AJ34: =IF(BK34="","",$BS34/BK34) -> 1.0944772 | AK34: =IF(BL34="","",$BS34/BL34) -> 1.1900789 | AL34: =IF(BM34="","",$BS34/BM34) -> 1.3017774 | AM34: =IF(BN34="","",$BS34/BN34) -> 1.4111348 | AN34: =IF(BO34="","",$BS34/BO34) -> 1.5095043 | AO34: =IF(BP34="","",$BS34/BP34) -> 1.5083436 | ... AQ34: =IF(BR34="","",$BS34/BR34) -> 1.606141 | BB34: =IF(AW34="","",AW34) | BC34: =IF(AX34="","",AX34) | BD34: =IF(AY34="","",AY34) | BE34: =IF(AZ34="","",AZ34) | BF34: =IF(BA34="","",BA34) | BI34: 1 | BJ34: =IF(BI34="","",BI34) -> 1 | BK34: ='Demand (old)'!G$137 -> 0.91367821 | BL34: ='Demand (old)'!H$137 -> 0.84028046 | BM34: ='Demand (old)'!I$137 -> 0.7681805 | BN34: ='Demand (old)'!J$137 -> 0.70864954 | BO34: ='Demand (old)'!K$137 -> 0.66246912 | BP34: ='Demand (old)'!L$137 -> 0.66297892 | BQ34: ='Demand (old)'!M$137 -> 0.64131463 | BR34: ='Demand (old)'!N$137 -> 0.62261036 | BS34: 1
B35: R2,R3,R4,R5,R6 | C35: IOTEFACNGA | D35: Other Industry Natural Gas Facilities | E35: PJ, PJ/a | F35: INDNGAEA | G35: IOTFAC | H35: 2010 | I35: 30 | J35: 1 | K35: 0.15 | L35: =IFERROR(IF(_xlfn.XLOOKUP(D35,tbl_tech[TECHNOLOGY - Other],tbl_tech[NCAP_COST])=0,"",_xlfn.XLOOKUP(D35,tbl_tech[TECHNOLOGY - Other],tbl_tech[NCAP_COST])),"") -> 100 | M35: =IFERROR(IF(_xlfn.XLOOKUP(D35,tbl_tech[TECHNOLOGY - Other],tbl_tech[NCAP_FOM])=0,"",_xlfn.XLOOKUP(D35,tbl_tech[TECHNOLOGY - Other],tbl_tech[NCAP_FOM])),"") -> 1 | Q35: =Q$46/$AH$46*AR$51*Original!#REF!*1.1 -> #REF! | R35: =R$46/$AH$46*AS$51*Original!#REF!*1.1 -> #REF! | S35: =S$46/$AH$46*AT$51*Original!#REF!*1.1 -> #REF! | T35: =T$46/$AH$46*AU$51*Original!#REF!*1.1 -> #REF! | U35: =U$46/$AH$46*AV$51*Original!#REF!*1.1 -> #REF! | V35: =V$46/$AH$46*AW$51*0.241271168722559 -> 2.2588392 | W35: =W$46/$AH$46*AX$51*0.241215008933889 -> 5.9114326 | X35: =X$46/$AH$46*AY$51*0.241035856573705 -> 2.3127835 | Y35: =Y$46/$AH$46*AZ$51*0.241262300644723 -> 5.0785203 | Z35: =Z$46/$AH$46*BA$51*0.240694789081886 -> 0.55788082 | AA35: =AA$46/$AH$46*BB$51*Original!#REF!*1.1 -> #REF! | AB35: =AB$46/$AH$46*BC$51*Original!#REF!*1.1 -> #REF! | AC35: =AC$46/$AH$46*BD$51*Original!#REF!*1.1 -> #REF! | AD35: =AD$46/$AH$46*BE$51*Original!#REF!*1.1 -> #REF! | AE35: =AE$46/$AH$46*BF$51*Original!#REF!*1.1 -> #REF! | AF35: 1 | AH35: =IF(BI35="","",$BS35/BI35) -> 1 | AI35: =IF(BJ35="","",$BS35/BJ35) -> 1 | AJ35: =IF(BK35="","",$BS35/BK35) -> 1.0944772 | AK35: =IF(BL35="","",$BS35/BL35) -> 1.1900789 | AL35: =IF(BM35="","",$BS35/BM35) -> 1.3017774 | AM35: =IF(BN35="","",$BS35/BN35) -> 1.4111348 | AN35: =IF(BO35="","",$BS35/BO35) -> 1.5095043 | AO35: =IF(BP35="","",$BS35/BP35) -> 1.5083436 | ... AQ35: =IF(BR35="","",$BS35/BR35) -> 1.606141 | BB35: =IF(AW35="","",AW35) | BC35: =IF(AX35="","",AX35) | BD35: =IF(AY35="","",AY35) | BE35: =IF(AZ35="","",AZ35) | BF35: =IF(BA35="","",BA35) | BI35: 1 | BJ35: =IF(BI35="","",BI35) -> 1 | BK35: ='Demand (old)'!G$137 -> 0.91367821 | BL35: ='Demand (old)'!H$137 -> 0.84028046 | BM35: ='Demand (old)'!I$137 -> 0.7681805 | BN35: ='Demand (old)'!J$137 -> 0.70864954 | BO35: ='Demand (old)'!K$137 -> 0.66246912 | BP35: ='Demand (old)'!L$137 -> 0.66297892 | BQ35: ='Demand (old)'!M$137 -> 0.64131463 | BR35: ='Demand (old)'!N$137 -> 0.62261036 | BS35: 1
B36: * | C36: IOTEFACLPG | D36: Other Industry LPG Facilities | E36: PJ, PJ/a | F36: INDLPGEA | G36: IOTFAC | H36: 2010 | I36: 30 | J36: 1 | K36: 0.15 | L36: =IFERROR(IF(_xlfn.XLOOKUP(D36,tbl_tech[TECHNOLOGY - Other],tbl_tech[NCAP_COST])=0,"",_xlfn.XLOOKUP(D36,tbl_tech[TECHNOLOGY - Other],tbl_tech[NCAP_COST])),"") | M36: =IFERROR(IF(_xlfn.XLOOKUP(D36,tbl_tech[TECHNOLOGY - Other],tbl_tech[NCAP_FOM])=0,"",_xlfn.XLOOKUP(D36,tbl_tech[TECHNOLOGY - Other],tbl_tech[NCAP_FOM])),"") | N36: 0 | Q36: 0.68131234 | R36: 1.3945799 | S36: 0.62938557 | T36: 0.85957804 | U36: 0.63665769 | V36: 0.75427896 | W36: 7.3566964 | X36: 4.9828654 | Y36: 2.3085417 | Z36: 2.0122303 | AF36: 1 | AH36: =IF(BI36="","",$BS36/BI36) -> 1 | AI36: =IF(BJ36="","",$BS36/BJ36) -> 1 | AJ36: =IF(BK36="","",$BS36/BK36) -> 1.0944772 | AK36: =IF(BL36="","",$BS36/BL36) -> 1.1900789 | AL36: =IF(BM36="","",$BS36/BM36) -> 1.3017774 | AM36: =IF(BN36="","",$BS36/BN36) -> 1.4111348 | AN36: =IF(BO36="","",$BS36/BO36) -> 1.5095043 | AO36: =IF(BP36="","",$BS36/BP36) -> 1.5083436 | ... AQ36: =IF(BR36="","",$BS36/BR36) -> 1.606141 | BB36: =IF(AW36="","",AW36) | BC36: =IF(AX36="","",AX36) | BD36: =IF(AY36="","",AY36) | BE36: =IF(AZ36="","",AZ36) | BF36: =IF(BA36="","",BA36) | BI36: 1 | BJ36: =IF(BI36="","",BI36) -> 1 | BK36: ='Demand (old)'!G$137 -> 0.91367821 | BL36: ='Demand (old)'!H$137 -> 0.84028046 | BM36: ='Demand (old)'!I$137 -> 0.7681805 | BN36: ='Demand (old)'!J$137 -> 0.70864954 | BO36: ='Demand (old)'!K$137 -> 0.66246912 | BP36: ='Demand (old)'!L$137 -> 0.66297892 | BQ36: ='Demand (old)'!M$137 -> 0.64131463 | BR36: ='Demand (old)'!N$137 -> 0.62261036 | BS36: 1
B37: * | C37: IOTEFACCOA | D37: Other Industry Coal Facilities | E37: PJ, PJ/a | F37: INDCOAEA | G37: IOTFAC | H37: 2010 | I37: 30 | J37: 1 | K37: 0.2 | L37: =IFERROR(IF(_xlfn.XLOOKUP(D37,tbl_tech[TECHNOLOGY - Other],tbl_tech[NCAP_COST])=0,"",_xlfn.XLOOKUP(D37,tbl_tech[TECHNOLOGY - Other],tbl_tech[NCAP_COST])),"") | M37: =IFERROR(IF(_xlfn.XLOOKUP(D37,tbl_tech[TECHNOLOGY - Other],tbl_tech[NCAP_FOM])=0,"",_xlfn.XLOOKUP(D37,tbl_tech[TECHNOLOGY - Other],tbl_tech[NCAP_FOM])),"") | N37: 0 | Q37: 0.011576821 | R37: 0.26404809 | S37: 0.11916711 | T37: 0.19717967 | U37: 0.1460437 | V37: 0.71025172 | W37: 1.5875031 | X37: 1.0752536 | Y37: 0.64225678 | Z37: 0.55982034 | AF37: 1 | AH37: =IF(BI37="","",$BS37/BI37) -> 1 | AI37: =IF(BJ37="","",$BS37/BJ37) -> 1 | AJ37: =IF(BK37="","",$BS37/BK37) -> 1.0944772 | AK37: =IF(BL37="","",$BS37/BL37) -> 1.1900789 | AL37: =IF(BM37="","",$BS37/BM37) -> 1.3017774 | AM37: =IF(BN37="","",$BS37/BN37) -> 1.4111348 | AN37: =IF(BO37="","",$BS37/BO37) -> 1.5095043 | AO37: =IF(BP37="","",$BS37/BP37) -> 1.5083436 | ... AQ37: =IF(BR37="","",$BS37/BR37) -> 1.606141 | BB37: =IF(AW37="","",AW37) | BC37: =IF(AX37="","",AX37) | BD37: =IF(AY37="","",AY37) | BE37: =IF(AZ37="","",AZ37) | BF37: =IF(BA37="","",BA37) | BI37: 1 | BJ37: =IF(BI37="","",BI37) -> 1 | BK37: ='Demand (old)'!G$137 -> 0.91367821 | BL37: ='Demand (old)'!H$137 -> 0.84028046 | BM37: ='Demand (old)'!I$137 -> 0.7681805 | BN37: ='Demand (old)'!J$137 -> 0.70864954 | BO37: ='Demand (old)'!K$137 -> 0.66246912 | BP37: ='Demand (old)'!L$137 -> 0.66297892 | BQ37: ='Demand (old)'!M$137 -> 0.64131463 | BR37: ='Demand (old)'!N$137 -> 0.62261036 | BS37: 1
B38: * | C38: IOTEOHTELC | D38: Other Industry Electricity Other Heat | E38: PJ, PJ/a | F38: INDELCOT | G38: IOTOHT | H38: 2010 | I38: 30 | J38: 1 | K38: 0.15 | L38: =IFERROR(IF(_xlfn.XLOOKUP(D38,tbl_tech[TECHNOLOGY - Other],tbl_tech[NCAP_COST])=0,"",_xlfn.XLOOKUP(D38,tbl_tech[TECHNOLOGY - Other],tbl_tech[NCAP_COST])),"") | M38: =IFERROR(IF(_xlfn.XLOOKUP(D38,tbl_tech[TECHNOLOGY - Other],tbl_tech[NCAP_FOM])=0,"",_xlfn.XLOOKUP(D38,tbl_tech[TECHNOLOGY - Other],tbl_tech[NCAP_FOM])),"") | N38: 0 | Q38: 1.5449441 | R38: 3.948027 | S38: 1.7817775 | T38: 1.5042581 | U38: 1.1141484 | V38: 2.9845222 | W38: 6.7871739 | X38: 4.5971143 | Y38: 2.9105974 | Z38: 2.5370096 | AF38: 1 | AH38: =IF(BI38="","",$BS38/BI38) -> 1 | AI38: =IF(BJ38="","",$BS38/BJ38) -> 1 | AJ38: =IF(BK38="","",$BS38/BK38) -> 1.0944772 | AK38: =IF(BL38="","",$BS38/BL38) -> 1.1900789 | AL38: =IF(BM38="","",$BS38/BM38) -> 1.3017774 | AM38: =IF(BN38="","",$BS38/BN38) -> 1.4111348 | AN38: =IF(BO38="","",$BS38/BO38) -> 1.5095043 | AO38: =IF(BP38="","",$BS38/BP38) -> 1.5083436 | ... AQ38: =IF(BR38="","",$BS38/BR38) -> 1.606141 | BB38: =IF(AW38="","",AW38) | BC38: =IF(AX38="","",AX38) | BD38: =IF(AY38="","",AY38) | BE38: =IF(AZ38="","",AZ38) | BF38: =IF(BA38="","",BA38) | BI38: 1 | BJ38: =IF(BI38="","",BI38) -> 1 | BK38: ='Demand (old)'!G$137 -> 0.91367821 | BL38: ='Demand (old)'!H$137 -> 0.84028046 | BM38: ='Demand (old)'!I$137 -> 0.7681805 | BN38: ='Demand (old)'!J$137 -> 0.70864954 | BO38: ='Demand (old)'!K$137 -> 0.66246912 | BP38: ='Demand (old)'!L$137 -> 0.66297892 | BQ38: ='Demand (old)'!M$137 -> 0.64131463 | BR38: ='Demand (old)'!N$137 -> 0.62261036 | BS38: 1
B39: * | C39: IOTEOHTRFL | D39: Other Industry Residual Oil Other Heat | E39: PJ, PJ/a | F39: INDRFLEA | G39: IOTOHT | H39: 2010 | I39: 30 | J39: 1 | K39: 0.15 | L39: =IFERROR(IF(_xlfn.XLOOKUP(D39,tbl_tech[TECHNOLOGY - Other],tbl_tech[NCAP_COST])=0,"",_xlfn.XLOOKUP(D39,tbl_tech[TECHNOLOGY - Other],tbl_tech[NCAP_COST])),"") | M39: =IFERROR(IF(_xlfn.XLOOKUP(D39,tbl_tech[TECHNOLOGY - Other],tbl_tech[NCAP_FOM])=0,"",_xlfn.XLOOKUP(D39,tbl_tech[TECHNOLOGY - Other],tbl_tech[NCAP_FOM])),"") | N39: 0 | Q39: 5.4871578 | R39: 1.203394 | S39: 0.54310174 | T39: 1.8749454 | U39: 1.3887027 | V39: 0.46359417 | W39: 0 | X39: 0 | Y39: 0.096741378 | Z39: 0.084324202 | AF39: 1 | AH39: =IF(BI39="","",$BS39/BI39) -> 1 | AI39: =IF(BJ39="","",$BS39/BJ39) -> 1 | AJ39: =IF(BK39="","",$BS39/BK39) -> 1.0944772 | AK39: =IF(BL39="","",$BS39/BL39) -> 1.1900789 | AL39: =IF(BM39="","",$BS39/BM39) -> 1.3017774 | AM39: =IF(BN39="","",$BS39/BN39) -> 1.4111348 | AN39: =IF(BO39="","",$BS39/BO39) -> 1.5095043 | AO39: =IF(BP39="","",$BS39/BP39) -> 1.5083436 | ... AQ39: =IF(BR39="","",$BS39/BR39) -> 1.606141 | BB39: =IF(AW39="","",AW39) | BC39: =IF(AX39="","",AX39) | BD39: =IF(AY39="","",AY39) | BE39: =IF(AZ39="","",AZ39) | BF39: =IF(BA39="","",BA39) | BI39: 1 | BJ39: =IF(BI39="","",BI39) -> 1 | BK39: ='Demand (old)'!G$137 -> 0.91367821 | BL39: ='Demand (old)'!H$137 -> 0.84028046 | BM39: ='Demand (old)'!I$137 -> 0.7681805 | BN39: ='Demand (old)'!J$137 -> 0.70864954 | BO39: ='Demand (old)'!K$137 -> 0.66246912 | BP39: ='Demand (old)'!L$137 -> 0.66297892 | BQ39: ='Demand (old)'!M$137 -> 0.64131463 | BR39: ='Demand (old)'!N$137 -> 0.62261036 | BS39: 1
B40: * | C40: IOTEOHTDST | D40: Other Industry Distillate Oil Other Heat | E40: PJ, PJ/a | F40: INDDSTEA | G40: IOTOHT | H40: 2010 | I40: 30 | J40: 1 | K40: 0.15 | L40: =IFERROR(IF(_xlfn.XLOOKUP(D40,tbl_tech[TECHNOLOGY - Other],tbl_tech[NCAP_COST])=0,"",_xlfn.XLOOKUP(D40,tbl_tech[TECHNOLOGY - Other],tbl_tech[NCAP_COST])),"") | M40: =IFERROR(IF(_xlfn.XLOOKUP(D40,tbl_tech[TECHNOLOGY - Other],tbl_tech[NCAP_FOM])=0,"",_xlfn.XLOOKUP(D40,tbl_tech[TECHNOLOGY - Other],tbl_tech[NCAP_FOM])),"") | N40: 0 | V40: 0.19093011 | W40: 0.13301396 | X40: 0.090093519 | Y40: 0.075890851 | Z40: 0.066149931 | AF40: 1 | AH40: =IF(BI40="","",$BS40/BI40) -> 1 | AI40: =IF(BJ40="","",$BS40/BJ40) -> 1 | AJ40: =IF(BK40="","",$BS40/BK40) -> 1.0944772 | AK40: =IF(BL40="","",$BS40/BL40) -> 1.1900789 | AL40: =IF(BM40="","",$BS40/BM40) -> 1.3017774 | AM40: =IF(BN40="","",$BS40/BN40) -> 1.4111348 | AN40: =IF(BO40="","",$BS40/BO40) -> 1.5095043 | AO40: =IF(BP40="","",$BS40/BP40) -> 1.5083436 | ... AQ40: =IF(BR40="","",$BS40/BR40) -> 1.606141 | BB40: =IF(AW40="","",AW40) | BC40: =IF(AX40="","",AX40) | BD40: =IF(AY40="","",AY40) | BE40: =IF(AZ40="","",AZ40) | BF40: =IF(BA40="","",BA40) | BI40: 1 | BJ40: =IF(BI40="","",BI40) -> 1 | BK40: ='Demand (old)'!G$137 -> 0.91367821 | BL40: ='Demand (old)'!H$137 -> 0.84028046 | BM40: ='Demand (old)'!I$137 -> 0.7681805 | BN40: ='Demand (old)'!J$137 -> 0.70864954 | BO40: ='Demand (old)'!K$137 -> 0.66246912 | BP40: ='Demand (old)'!L$137 -> 0.66297892 | BQ40: ='Demand (old)'!M$137 -> 0.64131463 | BR40: ='Demand (old)'!N$137 -> 0.62261036 | BS40: 1
B41: * | C41: IOTEOHTNGA | D41: Other Industry Natural Gas Other Heat | E41: PJ, PJ/a | F41: INDNGAEA | G41: IOTOHT | H41: 2010 | I41: 30 | J41: 1 | K41: 0.15 | L41: =IFERROR(IF(_xlfn.XLOOKUP(D41,tbl_tech[TECHNOLOGY - Other],tbl_tech[NCAP_COST])=0,"",_xlfn.XLOOKUP(D41,tbl_tech[TECHNOLOGY - Other],tbl_tech[NCAP_COST])),"") | M41: =IFERROR(IF(_xlfn.XLOOKUP(D41,tbl_tech[TECHNOLOGY - Other],tbl_tech[NCAP_FOM])=0,"",_xlfn.XLOOKUP(D41,tbl_tech[TECHNOLOGY - Other],tbl_tech[NCAP_FOM])),"") | N41: 0 | Q41: 2.7375334 | R41: 8.0049486 | S41: 3.6127001 | T41: 2.4584414 | U41: 1.8208767 | V41: 3.2702989 | W41: 7.8918313 | X41: 5.345325 | Y41: 2.3545205 | Z41: 2.0523076 | AF41: 1 | AH41: =IF(BI41="","",$BS41/BI41) -> 1 | AI41: =IF(BJ41="","",$BS41/BJ41) -> 1 | AJ41: =IF(BK41="","",$BS41/BK41) -> 1.0944772 | AK41: =IF(BL41="","",$BS41/BL41) -> 1.1900789 | AL41: =IF(BM41="","",$BS41/BM41) -> 1.3017774 | AM41: =IF(BN41="","",$BS41/BN41) -> 1.4111348 | AN41: =IF(BO41="","",$BS41/BO41) -> 1.5095043 | AO41: =IF(BP41="","",$BS41/BP41) -> 1.5083436 | ... AQ41: =IF(BR41="","",$BS41/BR41) -> 1.606141 | BB41: =IF(AW41="","",AW41) | BC41: =IF(AX41="","",AX41) | BD41: =IF(AY41="","",AY41) | BE41: =IF(AZ41="","",AZ41) | BF41: =IF(BA41="","",BA41) | BI41: 1 | BJ41: =IF(BI41="","",BI41) -> 1 | BK41: ='Demand (old)'!G$137 -> 0.91367821 | BL41: ='Demand (old)'!H$137 -> 0.84028046 | BM41: ='Demand (old)'!I$137 -> 0.7681805 | BN41: ='Demand (old)'!J$137 -> 0.70864954 | BO41: ='Demand (old)'!K$137 -> 0.66246912 | BP41: ='Demand (old)'!L$137 -> 0.66297892 | BQ41: ='Demand (old)'!M$137 -> 0.64131463 | BR41: ='Demand (old)'!N$137 -> 0.62261036 | BS41: 1
B42: * | C42: IOTEOHTLPG | D42: Other Industry LPG Other Heat | E42: PJ, PJ/a | F42: INDLPGEA | G42: IOTOHT | H42: 2010 | I42: 30 | J42: 1 | K42: 0.15 | L42: =IFERROR(IF(_xlfn.XLOOKUP(D42,tbl_tech[TECHNOLOGY - Other],tbl_tech[NCAP_COST])=0,"",_xlfn.XLOOKUP(D42,tbl_tech[TECHNOLOGY - Other],tbl_tech[NCAP_COST])),"") | M42: =IFERROR(IF(_xlfn.XLOOKUP(D42,tbl_tech[TECHNOLOGY - Other],tbl_tech[NCAP_FOM])=0,"",_xlfn.XLOOKUP(D42,tbl_tech[TECHNOLOGY - Other],tbl_tech[NCAP_FOM])),"") | N42: 0 | Q42: 0.11355206 | R42: 0.23242999 | S42: 0.10489759 | T42: 0.14326301 | U42: 0.10610961 | V42: 0.10775414 | W42: 1.0509566 | X42: 0.71183791 | Y42: 0.32979167 | Z42: 0.28746148 | AF42: 1 | AH42: =IF(BI42="","",$BS42/BI42) -> 1 | AI42: =IF(BJ42="","",$BS42/BJ42) -> 1 | AJ42: =IF(BK42="","",$BS42/BK42) -> 1.0944772 | AK42: =IF(BL42="","",$BS42/BL42) -> 1.1900789 | AL42: =IF(BM42="","",$BS42/BM42) -> 1.3017774 | AM42: =IF(BN42="","",$BS42/BN42) -> 1.4111348 | AN42: =IF(BO42="","",$BS42/BO42) -> 1.5095043 | AO42: =IF(BP42="","",$BS42/BP42) -> 1.5083436 | ... AQ42: =IF(BR42="","",$BS42/BR42) -> 1.606141 | BB42: =IF(AW42="","",AW42) | BC42: =IF(AX42="","",AX42) | BD42: =IF(AY42="","",AY42) | BE42: =IF(AZ42="","",AZ42) | BF42: =IF(BA42="","",BA42) | BI42: 1 | BJ42: =IF(BI42="","",BI42) -> 1 | BK42: ='Demand (old)'!G$137 -> 0.91367821 | BL42: ='Demand (old)'!H$137 -> 0.84028046 | BM42: ='Demand (old)'!I$137 -> 0.7681805 | BN42: ='Demand (old)'!J$137 -> 0.70864954 | BO42: ='Demand (old)'!K$137 -> 0.66246912 | BP42: ='Demand (old)'!L$137 -> 0.66297892 | BQ42: ='Demand (old)'!M$137 -> 0.64131463 | BR42: ='Demand (old)'!N$137 -> 0.62261036 | BS42: 1
B43: * | C43: IOTEOHTBIO | D43: Other Industry Renewables Other Heat | E43: PJ, PJ/a | F43: INDBIOEA | G43: IOTOHT | H43: 2010 | I43: 30 | J43: 1 | K43: 0.15 | L43: =IFERROR(IF(_xlfn.XLOOKUP(D43,tbl_tech[TECHNOLOGY - Other],tbl_tech[NCAP_COST])=0,"",_xlfn.XLOOKUP(D43,tbl_tech[TECHNOLOGY - Other],tbl_tech[NCAP_COST])),"") | M43: =IFERROR(IF(_xlfn.XLOOKUP(D43,tbl_tech[TECHNOLOGY - Other],tbl_tech[NCAP_FOM])=0,"",_xlfn.XLOOKUP(D43,tbl_tech[TECHNOLOGY - Other],tbl_tech[NCAP_FOM])),"") | N43: 0 | O43: 0 | Q43: 13.989207 | R43: 0 | S43: 8.1429569 | T43: 13.191862 | U43: 0 | V43: 10.807014 | W43: 0.016317649 | X43: 0.011052332 | Y43: 0.069051177 | Z43: 0.060188159 | AF43: 1 | AH43: =IF(BI43="","",$BS43/BI43) -> 1 | AI43: =IF(BJ43="","",$BS43/BJ43) -> 1 | AJ43: =IF(BK43="","",$BS43/BK43) -> 1.0944772 | AK43: =IF(BL43="","",$BS43/BL43) -> 1.1900789 | AL43: =IF(BM43="","",$BS43/BM43) -> 1.3017774 | AM43: =IF(BN43="","",$BS43/BN43) -> 1.4111348 | AN43: =IF(BO43="","",$BS43/BO43) -> 1.5095043 | AO43: =IF(BP43="","",$BS43/BP43) -> 1.5083436 | ... AQ43: =IF(BR43="","",$BS43/BR43) -> 1.606141 | BB43: =IF(AW43="","",AW43) | BC43: =IF(AX43="","",AX43) | BD43: =IF(AY43="","",AY43) | BE43: =IF(AZ43="","",AZ43) | BF43: =IF(BA43="","",BA43) | BI43: 1 | BJ43: =IF(BI43="","",BI43) -> 1 | BK43: ='Demand (old)'!G$137 -> 0.91367821 | BL43: ='Demand (old)'!H$137 -> 0.84028046 | BM43: ='Demand (old)'!I$137 -> 0.7681805 | BN43: ='Demand (old)'!J$137 -> 0.70864954 | BO43: ='Demand (old)'!K$137 -> 0.66246912 | BP43: ='Demand (old)'!L$137 -> 0.66297892 | BQ43: ='Demand (old)'!M$137 -> 0.64131463 | BR43: ='Demand (old)'!N$137 -> 0.62261036 | BS43: 1
B44: * | C44: IOTEOHTPTC | D44: Other Industry Petroleum Coke Other Heat | E44: PJ, PJ/a | F44: INDPTC | G44: IOTOHT | H44: 2010 | I44: 30 | J44: 1 | K44: 0.15 | L44: =IFERROR(IF(_xlfn.XLOOKUP(D44,tbl_tech[TECHNOLOGY - Other],tbl_tech[NCAP_COST])=0,"",_xlfn.XLOOKUP(D44,tbl_tech[TECHNOLOGY - Other],tbl_tech[NCAP_COST])),"") | M44: =IFERROR(IF(_xlfn.XLOOKUP(D44,tbl_tech[TECHNOLOGY - Other],tbl_tech[NCAP_FOM])=0,"",_xlfn.XLOOKUP(D44,tbl_tech[TECHNOLOGY - Other],tbl_tech[NCAP_FOM])),"") | N44: 0 | Q44: 24.817013 | R44: 6.1597185 | S44: 2.7799324 | T44: 0 | U44: 6.1985441 | V44: 0.78727737 | W44: 0.33977161 | X44: 0.23013539 | Y44: 0.40691551 | Z44: 0.35468613 | AF44: 1 | AH44: =IF(BI44="","",$BS44/BI44) -> 1 | AI44: =IF(BJ44="","",$BS44/BJ44) -> 1 | AJ44: =IF(BK44="","",$BS44/BK44) -> 1.0944772 | AK44: =IF(BL44="","",$BS44/BL44) -> 1.1900789 | AL44: =IF(BM44="","",$BS44/BM44) -> 1.3017774 | AM44: =IF(BN44="","",$BS44/BN44) -> 1.4111348 | AN44: =IF(BO44="","",$BS44/BO44) -> 1.5095043 | AO44: =IF(BP44="","",$BS44/BP44) -> 1.5083436 | ... AQ44: =IF(BR44="","",$BS44/BR44) -> 1.606141 | BB44: =IF(AW44="","",AW44) | BC44: =IF(AX44="","",AX44) | BD44: =IF(AY44="","",AY44) | BE44: =IF(AZ44="","",AZ44) | BF44: =IF(BA44="","",BA44) | BI44: 1 | BJ44: =IF(BI44="","",BI44) -> 1 | BK44: ='Demand (old)'!G$137 -> 0.91367821 | BL44: ='Demand (old)'!H$137 -> 0.84028046 | BM44: ='Demand (old)'!I$137 -> 0.7681805 | BN44: ='Demand (old)'!J$137 -> 0.70864954 | BO44: ='Demand (old)'!K$137 -> 0.66246912 | BP44: ='Demand (old)'!L$137 -> 0.66297892 | BQ44: ='Demand (old)'!M$137 -> 0.64131463 | BR44: ='Demand (old)'!N$137 -> 0.62261036 | BS44: 1
B45: * | C45: IOTEOHTOTP | D45: Other Industry Other Petroleum Other Heat | E45: PJ, PJ/a | F45: INDOTH | G45: IOTOHT | H45: 2010 | I45: 30 | J45: 1 | K45: 0.15 | L45: =IFERROR(IF(_xlfn.XLOOKUP(D45,tbl_tech[TECHNOLOGY - Other],tbl_tech[NCAP_COST])=0,"",_xlfn.XLOOKUP(D45,tbl_tech[TECHNOLOGY - Other],tbl_tech[NCAP_COST])),"") | M45: =IFERROR(IF(_xlfn.XLOOKUP(D45,tbl_tech[TECHNOLOGY - Other],tbl_tech[NCAP_FOM])=0,"",_xlfn.XLOOKUP(D45,tbl_tech[TECHNOLOGY - Other],tbl_tech[NCAP_FOM])),"") | N45: 0 | Q45: 0.50842624 | R45: 0 | S45: 0 | T45: 8.4280193 | U45: 0.043778315 | V45: 0 | W45: 0.0040194004 | X45: 0.0027224355 | Y45: 0 | Z45: 0 | AF45: 1 | AH45: =IF(BI45="","",$BS45/BI45) -> 1 | AI45: =IF(BJ45="","",$BS45/BJ45) -> 1 | AJ45: =IF(BK45="","",$BS45/BK45) -> 1.0944772 | AK45: =IF(BL45="","",$BS45/BL45) -> 1.1900789 | AL45: =IF(BM45="","",$BS45/BM45) -> 1.3017774 | AM45: =IF(BN45="","",$BS45/BN45) -> 1.4111348 | AN45: =IF(BO45="","",$BS45/BO45) -> 1.5095043 | AO45: =IF(BP45="","",$BS45/BP45) -> 1.5083436 | ... AQ45: =IF(BR45="","",$BS45/BR45) -> 1.606141 | BB45: =IF(AW45="","",AW45) | BC45: =IF(AX45="","",AX45) | BD45: =IF(AY45="","",AY45) | BE45: =IF(AZ45="","",AZ45) | BF45: =IF(BA45="","",BA45) | BI45: 1 | BJ45: =IF(BI45="","",BI45) -> 1 | BK45: ='Demand (old)'!G$137 -> 0.91367821 | BL45: ='Demand (old)'!H$137 -> 0.84028046 | BM45: ='Demand (old)'!I$137 -> 0.7681805 | BN45: ='Demand (old)'!J$137 -> 0.70864954 | BO45: ='Demand (old)'!K$137 -> 0.66246912 | BP45: ='Demand (old)'!L$137 -> 0.66297892 | BQ45: ='Demand (old)'!M$137 -> 0.64131463 | BR45: ='Demand (old)'!N$137 -> 0.62261036 | BS45: 1
B46: R2,R3,R4,R5,R6 | C46: IOTTECHEXT | D46: Existing Other Industry Technologies | E46: PJ, PJ/a | F46: IOTFEED | H46: 2010 | I46: 50 | J46: 1 | L46: =IFERROR(IF(_xlfn.XLOOKUP(D46,tbl_tech[TECHNOLOGY - Other],tbl_tech[NCAP_COST])=0,"",_xlfn.XLOOKUP(D46,tbl_tech[TECHNOLOGY - Other],tbl_tech[NCAP_COST])),"") -> 100 | M46: =IFERROR(IF(_xlfn.XLOOKUP(D46,tbl_tech[TECHNOLOGY - Other],tbl_tech[NCAP_FOM])=0,"",_xlfn.XLOOKUP(D46,tbl_tech[TECHNOLOGY - Other],tbl_tech[NCAP_FOM])),"") -> 1 | Q46: =CommData_DMD_dep!$F$5/$J$46 -> 8.30918 | R46: =CommData_DMD_dep!$F$6/$J$46 -> 23.925625 | S46: =CommData_DMD_dep!$F$7/$J$46 -> 8.9383948 | T46: =CommData_DMD_dep!$F$8/$J$46 -> 20.115576 | U46: =CommData_DMD_dep!$F$9/$J$46 -> 2.128264 | V46: =CommData_DMD_dep!$G$5/$J$46 -> 9.3622424 | W46: =CommData_DMD_dep!$G$6/$J$46 -> 24.506902 | X46: =CommData_DMD_dep!$G$7/$J$46 -> 9.5951843 | Y46: =CommData_DMD_dep!$G$8/$J$46 -> 21.049788 | Z46: =CommData_DMD_dep!$G$9/$J$46 -> 2.3177935 | AA46: 0 | AB46: 0 | AC46: 0 | AD46: 0 | AE46: 0 | AF46: 1 | AH46: 1 | AQ46: =AH46 -> 1 | AR46: 0 | AS46: 0 | AT46: 0 | AU46: 0 | AV46: 0 | AW46: 0 | AX46: 0 | AY46: 0 | AZ46: 0 | BA46: 0 | BB46: =IF(AW46="","",AW46) -> 0 | BC46: =IF(AX46="","",AX46) -> 0 | BD46: =IF(AY46="","",AY46) -> 0 | BE46: =IF(AZ46="","",AZ46) -> 0 | BF46: =IF(BA46="","",BA46) -> 0 | BJ46: =IF(BI46="","",BI46) | BS46: 1
B47: R2,R3,R4,R5,R6 | F47: IOTSTM | L47: =IFERROR(IF(_xlfn.XLOOKUP(D47,tbl_tech[TECHNOLOGY - Other],tbl_tech[NCAP_COST])=0,"",_xlfn.XLOOKUP(D47,tbl_tech[TECHNOLOGY - Other],tbl_tech[NCAP_COST])),"") | M47: =IFERROR(IF(_xlfn.XLOOKUP(D47,tbl_tech[TECHNOLOGY - Other],tbl_tech[NCAP_FOM])=0,"",_xlfn.XLOOKUP(D47,tbl_tech[TECHNOLOGY - Other],tbl_tech[NCAP_FOM])),"") | AR47: 0 | AS47: 0 | AT47: 0 | AU47: 0 | AV47: 0 | AW47: 0 | AX47: 0 | AY47: 0 | AZ47: 0 | BA47: 0 | BB47: =IF(AW47="","",AW47) -> 0 | BC47: =IF(AX47="","",AX47) -> 0 | BD47: =IF(AY47="","",AY47) -> 0 | BE47: =IF(AZ47="","",AZ47) -> 0 | BF47: =IF(BA47="","",BA47) -> 0 | BJ47: =IF(BI47="","",BI47)
B48: R2,R3,R4,R5,R6 | F48: IOTETC | L48: =IFERROR(IF(_xlfn.XLOOKUP(D48,tbl_tech[TECHNOLOGY - Other],tbl_tech[NCAP_COST])=0,"",_xlfn.XLOOKUP(D48,tbl_tech[TECHNOLOGY - Other],tbl_tech[NCAP_COST])),"") | M48: =IFERROR(IF(_xlfn.XLOOKUP(D48,tbl_tech[TECHNOLOGY - Other],tbl_tech[NCAP_FOM])=0,"",_xlfn.XLOOKUP(D48,tbl_tech[TECHNOLOGY - Other],tbl_tech[NCAP_FOM])),"") | AR48: 0 | AS48: 0 | AT48: 0 | AU48: 0 | AV48: 0 | AW48: 0 | AX48: 0 | AY48: 0 | AZ48: 0 | BA48: 0 | BB48: =IF(AW48="","",AW48) -> 0 | BC48: =IF(AX48="","",AX48) -> 0 | BD48: =IF(AY48="","",AY48) -> 0 | BE48: =IF(AZ48="","",AZ48) -> 0 | BF48: =IF(BA48="","",BA48) -> 0 | BJ48: =IF(BI48="","",BI48)
B49: R2,R3,R4,R5,R6 | F49: IOTPRH | L49: =IFERROR(IF(_xlfn.XLOOKUP(D49,tbl_tech[TECHNOLOGY - Other],tbl_tech[NCAP_COST])=0,"",_xlfn.XLOOKUP(D49,tbl_tech[TECHNOLOGY - Other],tbl_tech[NCAP_COST])),"") | M49: =IFERROR(IF(_xlfn.XLOOKUP(D49,tbl_tech[TECHNOLOGY - Other],tbl_tech[NCAP_FOM])=0,"",_xlfn.XLOOKUP(D49,tbl_tech[TECHNOLOGY - Other],tbl_tech[NCAP_FOM])),"") | AR49: 0 | AS49: 0 | AT49: 0 | AU49: 0 | AV49: 0 | AW49: 0 | AX49: 0 | AY49: 0 | AZ49: 0 | BA49: 0 | BB49: =IF(AW49="","",AW49) -> 0 | BC49: =IF(AX49="","",AX49) -> 0 | BD49: =IF(AY49="","",AY49) -> 0 | BE49: =IF(AZ49="","",AZ49) -> 0 | BF49: =IF(BA49="","",BA49) -> 0 | BJ49: =IF(BI49="","",BI49)
B50: R2,R3,R4,R5,R6 | F50: IOTMDR | L50: =IFERROR(IF(_xlfn.XLOOKUP(D50,tbl_tech[TECHNOLOGY - Other],tbl_tech[NCAP_COST])=0,"",_xlfn.XLOOKUP(D50,tbl_tech[TECHNOLOGY - Other],tbl_tech[NCAP_COST])),"") | M50: =IFERROR(IF(_xlfn.XLOOKUP(D50,tbl_tech[TECHNOLOGY - Other],tbl_tech[NCAP_FOM])=0,"",_xlfn.XLOOKUP(D50,tbl_tech[TECHNOLOGY - Other],tbl_tech[NCAP_FOM])),"") | AR50: 0 | AS50: 0 | AT50: 0 | AU50: 0 | AV50: 0 | AW50: 0 | AX50: 0 | AY50: 0 | AZ50: 0 | BA50: 0 | BB50: =IF(AW50="","",AW50) -> 0 | BC50: =IF(AX50="","",AX50) -> 0 | BD50: =IF(AY50="","",AY50) -> 0 | BE50: =IF(AZ50="","",AZ50) -> 0 | BF50: =IF(BA50="","",BA50) -> 0 | BJ50: =IF(BI50="","",BI50)
B51: R2,R3,R4,R5,R6 | F51: IOTFAC | L51: =IFERROR(IF(_xlfn.XLOOKUP(D51,tbl_tech[TECHNOLOGY - Other],tbl_tech[NCAP_COST])=0,"",_xlfn.XLOOKUP(D51,tbl_tech[TECHNOLOGY - Other],tbl_tech[NCAP_COST])),"") | M51: =IFERROR(IF(_xlfn.XLOOKUP(D51,tbl_tech[TECHNOLOGY - Other],tbl_tech[NCAP_FOM])=0,"",_xlfn.XLOOKUP(D51,tbl_tech[TECHNOLOGY - Other],tbl_tech[NCAP_FOM])),"") | AR51: =1-AR50 -> 1 | AS51: =1-AS50 -> 1 | AT51: =1-AT50 -> 1 | AU51: =1-AU50 -> 1 | AV51: =1-AV50 -> 1 | AW51: =1-AW50 -> 1 | AX51: =1-AX50 -> 1 | AY51: =1-AY50 -> 1 | ... BA51: =1-BA50 -> 1 | BB51: =IF(AW51="","",AW51) -> 1 | BC51: =IF(AX51="","",AX51) -> 1 | BD51: =IF(AY51="","",AY51) -> 1 | BE51: =IF(AZ51="","",AZ51) -> 1 | BF51: =IF(BA51="","",BA51) -> 1 | BJ51: =IF(BI51="","",BI51)
B52: R2,R3,R4,R5,R6 | F52: IOTOHT | L52: =IFERROR(IF(_xlfn.XLOOKUP(D52,tbl_tech[TECHNOLOGY - Other],tbl_tech[NCAP_COST])=0,"",_xlfn.XLOOKUP(D52,tbl_tech[TECHNOLOGY - Other],tbl_tech[NCAP_COST])),"") | M52: =IFERROR(IF(_xlfn.XLOOKUP(D52,tbl_tech[TECHNOLOGY - Other],tbl_tech[NCAP_FOM])=0,"",_xlfn.XLOOKUP(D52,tbl_tech[TECHNOLOGY - Other],tbl_tech[NCAP_FOM])),"") | AR52: 0 | AS52: 0 | AT52: 0 | AU52: 0 | AV52: 0 | AW52: 0 | AX52: 0 | AY52: 0 | AZ52: 0 | BA52: 0 | BB52: =IF(AW52="","",AW52) -> 0 | BC52: =IF(AX52="","",AX52) -> 0 | BD52: =IF(AY52="","",AY52) -> 0 | BE52: =IF(AZ52="","",AZ52) -> 0 | BF52: =IF(BA52="","",BA52) -> 0 | BJ52: =IF(BI52="","",BI52)
B53: R2,R3,R4,R5,R6 | G53: IOT | L53: =IFERROR(IF(_xlfn.XLOOKUP(D53,tbl_tech[TECHNOLOGY - Other],tbl_tech[NCAP_COST])=0,"",_xlfn.XLOOKUP(D53,tbl_tech[TECHNOLOGY - Other],tbl_tech[NCAP_COST])),"") | M53: =IFERROR(IF(_xlfn.XLOOKUP(D53,tbl_tech[TECHNOLOGY - Other],tbl_tech[NCAP_FOM])=0,"",_xlfn.XLOOKUP(D53,tbl_tech[TECHNOLOGY - Other],tbl_tech[NCAP_FOM])),"") | BB53: =IF(AW53="","",AW53) | BC53: =IF(AX53="","",AX53) | BD53: =IF(AY53="","",AY53) | BE53: =IF(AZ53="","",AZ53) | BF53: =IF(BA53="","",BA53) | BJ53: =IF(BI53="","",BI53)

Sheet TechData_X&ZZ_dep
G3: ~FI_T
B4: Region | C4: TechName | D4: *TechDesc | E4: *Units | F4: CommIN | G4: CommOUT | H4: NCAP_START | I4: NCAP_TLIFE | J4: Share~UP | K4: EFF | L4: NCAP_AF | M4: ACT_COST | N4: COST
B5: R2,R3,R4,R5,R6 | C5: IOTELC00 | D5: Other Industry Electricity collector | E5: PJ, PJ/a | F5: INDELC | G5: INDELCOT | H5: 2010 | I5: 50 | K5: 1 | L5: 1
B6: R2,R3,R4,R5,R6 | C6: SEINDNGA | D6: Emissions: NGA to IND | E6: PJ, PJ/a | F6: INDNGA | G6: INDNGAEA | H6: 2010 | I6: 50 | K6: 1
B7: R2,R3,R4,R5,R6 | C7: SEINDRFL | D7: Emissions: RFL to IND | E7: PJ, PJ/a | F7: INDRFL | G7: INDRFLEA | H7: 2010 | I7: 50 | K7: 1
B8: R2,R3,R4,R5,R6 | C8: SEINDDSL | D8: Emissions: DSL to IND | E8: PJ, PJ/a | F8: INDDSL | G8: INDDSLEA | H8: 2010 | I8: 50 | K8: 1
B9: * | C9: SEINDDST | D9: Emissions: DST to IND | E9: PJ, PJ/a | F9: INDDST | G9: INDDSTEA | H9: 2010 | I9: 50 | K9: 1
B10: * | C10: SEINDBIO | D10: Emissions: Biomass combustion | E10: PJ, PJ/a | F10: INDBIO | G10: INDBIOEA | H10: 2010 | I10: 50 | K10: 1
B11: * | C11: SEINDCOA | D11: Emissions: COA to IND | E11: PJ, PJ/a | F11: INDCOA | G11: INDCOAEA | H11: 2010 | I11: 50 | K11: 1
B12: * | C12: SEINDRFL | D12: Emissions: RFL to IND | E12: PJ, PJ/a | F12: INDRFL | G12: INDRFLEA | H12: 2010 | I12: 50 | K12: 1
B13: * | C13: SEINDLPG | D13: Emissions: LPG to IND | E13: PJ, PJ/a | F13: INDLPG | G13: INDLPGEA | H13: 2010 | I13: 50 | K13: 1
B14: * | C14: SEINDMET | D14: Emissions: MET to IND | E14: PJ, PJ/a | F14: METCOA | G14: INDMETEA | H14: 2010 | I14: 50 | K14: 1
B16: R2,R3,R4,R5,R6 | C16: ZZDMYIOTFC | D16: Dummy backstop for Other Industry Facilities | E16: PJ, PJ/a | F16: ZZDMY | G16: IOTFAC | K16: 1 | M16: 9999
B17: R2,R3,R4,R5,R6 | C17: ZZDMYIOT | D17: Dummy backstop for Other Industry DMDand | E17: PJ, PJ/a | F17: ZZDMY | G17: IOT | K17: 1 | M17: 9999
B18: R2,R3,R4,R5,R6 | C18: ZZINDELC | D18: Dummy backstop for INDELC | E18: PJ, PJ/a | G18: INDELC | N18: 9000
B19: R2,R3,R4,R5,R6 | C19: ZZINDNGAEA | D19: Dummy backstop for INDNGAEA | E19: PJ, PJ/a | G19: INDNGAEA | N19: 9000
B20: R2,R3,R4,R5,R6 | C20: ZZINDRFLEA | D20: Dummy backstop for INDRFLEA | E20: PJ, PJ/a | G20: INDRFLEA | N20: 9000

Sheet zzzTechData_Emis_dep
B1: TechData | C1: R2,R3,R4,R5,R6
G3: *~FI_T
B4: Region | C4: TechName | D4: *TechDesc | E4: *Units | F4: *CommIN | G4: *CommOUT | H4: *NCAP_START | I4: *NCAP_TLIFE | J4: ENV_ACT~CO2 | K4: ENV_ACT~CH4 | L4: ENV_ACT~N2O | M4: ENV_ACT~BC | N4: ENV_ACT~OC | O4: ENV_ACT~CO2I | P4: ENV_ACT~NOX~2010 | Q4: ENV_ACT~NOX~2015 | R4: ENV_ACT~NOX~2020 | S4: ENV_ACT~NOX~2055 | T4: ENV_ACT~SO2~2010 | U4: ENV_ACT~SO2~2015 | V4: ENV_ACT~SO2~2020 | W4: ENV_ACT~SO2~2055 | X4: ENV_ACT~PM10~2010 | Y4: ENV_ACT~PM10~2015 | Z4: ENV_ACT~PM10~2020 | AA4: ENV_ACT~PM10~2055 | AB4: ENV_ACT~PM25~2010 | AC4: ENV_ACT~PM25~2015 | AD4: ENV_ACT~PM25~2020 | AE4: ENV_ACT~PM25~2055 | AF4: ENV_ACT~VOC~2010 | AG4: ENV_ACT~VOC~2015 | AH4: ENV_ACT~VOC~2020 | AI4: ENV_ACT~VOC~2055 | AJ4: ENV_ACT~CO~2010 | AK4: ENV_ACT~CO~2015 | AL4: ENV_ACT~CO~2020 | AM4: ENV_ACT~CO~2055 | AN4: ENV_ACT~NOXI~2010 | AO4: ENV_ACT~NOXI~2015 | AP4: ENV_ACT~NOXI~2020 | AQ4: ENV_ACT~NOXI~2055 | AR4: ENV_ACT~SO2I~2010 | AS4: ENV_ACT~SO2I~2015 | AT4: ENV_ACT~SO2I~2020 | AU4: ENV_ACT~SO2I~2055 | AV4: ENV_ACT~PM10I~2010 | AW4: ENV_ACT~PM10I~2015 | AX4: ENV_ACT~PM10I~2020 | AY4: ENV_ACT~PM10I~2055 | AZ4: ENV_ACT~NOXDICB~2010 | BA4: ENV_ACT~NOXDICB~2015 | BB4: ENV_ACT~NOXDICB~2020 | BC4: ENV_ACT~NOXDICB~2055 | BD4: ENV_ACT~NOXDIGB~2010 | BE4: ENV_ACT~NOXDIGB~2015 | BF4: ENV_ACT~NOXDIGB~2020 | BG4: ENV_ACT~NOXDIGB~2055 | BH4: ENV_ACT~NOXDIDB~2010 | BI4: ENV_ACT~NOXDIDB~2015 | BJ4: ENV_ACT~NOXDIDB~2020 | BK4: ENV_ACT~NOXDIDB~2055 | BL4: ENV_ACT~NOXDIRB~2010 | BM4: ENV_ACT~NOXDIRB~2015 | BN4: ENV_ACT~NOXDIRB~2020 | BO4: ENV_ACT~NOXDIRB~2055 | BP4: ENV_ACT~NOXDILB~2010 | BQ4: ENV_ACT~NOXDILB~2015 | BR4: ENV_ACT~NOXDILB~2020 | BS4: ENV_ACT~NOXDILB~2055 | BT4: ENV_ACT~NOXDIOB~2010 | BU4: ENV_ACT~NOXDIOB~2015 | BV4: ENV_ACT~NOXDIOB~2020 | BW4: ENV_ACT~NOXDIOB~2055 | BX4: ENV_ACT~NOXDIGT~2010 | BY4: ENV_ACT~NOXDIGT~2015 | BZ4: ENV_ACT~NOXDIGT~2020 | CA4: ENV_ACT~NOXDIGT~2055 | CB4: ENV_ACT~NOXDIDT~2010 | CC4: ENV_ACT~NOXDIDT~2015 | CD4: ENV_ACT~NOXDIDT~2020 | CE4: ENV_ACT~NOXDIDT~2055 | CF4: ENV_ACT~NOXDIOT~2010 | CG4: ENV_ACT~NOXDIOT~2015 | CH4: ENV_ACT~NOXDIOT~2020 | CI4: ENV_ACT~NOXDIOT~2055 | CJ4: ENV_ACT~NOXDIGE~2010 | CK4: ENV_ACT~NOXDIGE~2015 | CL4: ENV_ACT~NOXDIGE~2020 | CM4: ENV_ACT~NOXDIGE~2055 | CN4: ENV_ACT~NOXDIDE~2010 | CO4: ENV_ACT~NOXDIDE~2015 | CP4: ENV_ACT~NOXDIDE~2020 | CQ4: ENV_ACT~NOXDIDE~2055 | CR4: ENV_ACT~NOXDICE~2010 | CS4: ENV_ACT~NOXDICE~2015 | CT4: ENV_ACT~NOXDICE~2020 | CU4: ENV_ACT~NOXDICE~2055 | CV4: ENV_ACT~NOXDIOE~2010 | CW4: ENV_ACT~NOXDIOE~2015 | CX4: ENV_ACT~NOXDIOE~2020 | CY4: ENV_ACT~NOXDIOE~2055 | CZ4: ENV_ACT~NOXDICPH~2010 | DA4: ENV_ACT~NOXDICPH~2015 | DB4: ENV_ACT~NOXDICPH~2020 | DC4: ENV_ACT~NOXDICPH~2055 | DD4: ENV_ACT~NOXDIGPH~2010 | DE4: ENV_ACT~NOXDIGPH~2015 | DF4: ENV_ACT~NOXDIGPH~2020 | DG4: ENV_ACT~NOXDIGPH~2055 | DH4: ENV_ACT~NOXDIDPH~2010 | DI4: ENV_ACT~NOXDIDPH~2015 | DJ4: ENV_ACT~NOXDIDPH~2020 | DK4: ENV_ACT~NOXDIDPH~2055 | DL4: ENV_ACT~NOXDIRPH~2010 | DM4: ENV_ACT~NOXDIRPH~2015 | DN4: ENV_ACT~NOXDIRPH~2020 | DO4: ENV_ACT~NOXDIRPH~2055 | DP4: ENV_ACT~NOXDIOPH~2010 | DQ4: ENV_ACT~NOXDIOPH~2015 | DR4: ENV_ACT~NOXDIOPH~2020 | DS4: ENV_ACT~NOXDIOPH~2055 | DT4: ENV_ACT~NOXDIFAC~2010 | DU4: ENV_ACT~NOXDIFAC~2015 | DV4: ENV_ACT~NOXDIFAC~2020 | DW4: ENV_ACT~NOXDIFAC~2055 | DX4: ENV_ACT~NOXDIOH~2010 | DY4: ENV_ACT~NOXDIOH~2015 | DZ4: ENV_ACT~NOXDIOH~2020 | EA4: ENV_ACT~NOXDIOH~2055 | EB4: ENV_ACT~NOXDICOK~2010 | EC4: ENV_ACT~NOXDICOK~2015 | ED4: ENV_ACT~NOXDICOK~2020 | EE4: ENV_ACT~NOXDICOK~2055
B5: R2,R3,R4,R5,R6 | C5: IOTEFACRFL | D5: Other Industry Residual Oil Facilities | E5: PJ, PJ/a | F5: INDRFLEA | G5: IOTFAC | J5: 0.0831 | K5: =Emissions!AC$42 -> 0.00284 | L5: =Emissions!AD$42 -> 0.000284 | M5: =Emissions!AE$42 -> 0.025494307 | N5: =Emissions!AF$42 -> 0.006883463 | O5: =J5*1000 -> 83.1 | P5: =Emissions!F$42 -> 0.83858254 | Q5: =Emissions!G$42 -> 0.83858254 | R5: =Emissions!H$42 -> 0.83858254 | S5: =IF(R5="","",R5) -> 0.83858254 | T5: =Emissions!J$42 -> 0.23453782 | U5: =Emissions!K$42 -> 0.23453782 | V5: =Emissions!L$42 -> 0.23453782 | W5: =IF(V5="","",V5) -> 0.23453782 | X5: =Emissions!N$42 -> 0.084981025 | Y5: =Emissions!O$42 -> 0.084981025 | Z5: =Emissions!P$42 -> 0.084981025 | AA5: =IF(Z5="","",Z5) -> 0.084981025 | AB5: =Emissions!R$42 -> 0.076482922 | AC5: =Emissions!S$42 -> 0.076482922 | AD5: =Emissions!T$42 -> 0.076482922 | AE5: =IF(AD5="","",AD5) -> 0.076482922 | AF5: =Emissions!V$42 -> 0.093519924 | AG5: =Emissions!W$42 -> 0.093519924 | AH5: =Emissions!X$42 -> 0.093519924 | AI5: =IF(AH5="","",AH5) -> 0.093519924 | AJ5: =Emissions!Z$42 -> 0.34250095 | AK5: =Emissions!AA$42 -> 0.34250095 | AL5: =Emissions!AB$42 -> 0.34250095 | AM5: =IF(AL5="","",AL5) -> 0.34250095 | AN5: =P5 -> 0.83858254 | AO5: =Q5 -> 0.83858254 | AP5: =R5 -> 0.83858254 | AQ5: =IF(AP5="","",AP5) -> 0.83858254 | AR5: =T5 -> 0.23453782 | AS5: =U5 -> 0.23453782 | AT5: =V5 -> 0.23453782 | AU5: =IF(AT5="","",AT5) -> 0.23453782 | AV5: =X5 -> 0.084981025 | AW5: =Y5 -> 0.084981025 | AX5: =Z5 -> 0.084981025 | AY5: =IF(AX5="","",AX5) -> 0.084981025 | DT5: =P5 -> 0.83858254 | DU5: =Q5 -> 0.83858254 | DV5: =R5 -> 0.83858254 | DW5: =IF(DV5="","",DV5) -> 0.83858254
B6: R2,R3,R4,R5,R6 | C6: IOTEFACNGA | D6: Other Industry Natural Gas Facilities | E6: PJ, PJ/a | F6: INDNGAEA | G6: IOTFAC | J6: 0.056 | K6: =Emissions!AC$39 -> 0.00085303541 | L6: =Emissions!AD$39 -> 0.00085303541 | M6: =Emissions!AE$39 -> 0.0036351067 | N6: =Emissions!AF$39 -> 0.0007633724 | O6: =J6*1000 -> 56 | P6: =Emissions!F$39 -> 0.041627634 | Q6: =Emissions!G$39 -> 0.041627636 | R6: =Emissions!H$39 -> 0.041627637 | S6: =IF(R6="","",R6) -> 0.041627637 | T6: =Emissions!J$39 -> 0.041773357 | U6: =Emissions!K$39 -> 0.041776205 | V6: =Emissions!L$39 -> 0.041779052 | W6: =IF(V6="","",V6) -> 0.041779052 | X6: =Emissions!N$39 -> 0.041759982 | Y6: =Emissions!O$39 -> 0.041758168 | Z6: =Emissions!P$39 -> 0.041756354 | AA6: =IF(Z6="","",Z6) -> 0.041756354 | AB6: =Emissions!R$39 -> 0.041772152 | AC6: =Emissions!S$39 -> 0.041770304 | AD6: =Emissions!T$39 -> 0.041768456 | AE6: =IF(AD6="","",AD6) -> 0.041768456 | AF6: =Emissions!V$39 -> 0.041772719 | AG6: =Emissions!W$39 -> 0.041772804 | AH6: =Emissions!X$39 -> 0.041772888 | AI6: =IF(AH6="","",AH6) -> 0.041772888 | AJ6: =Emissions!Z$39 -> 0.041782823 | AK6: =Emissions!AA$39 -> 0.04178284 | AL6: =Emissions!AB$39 -> 0.041782856 | AM6: =IF(AL6="","",AL6) -> 0.041782856 | AN6: =P6 -> 0.041627634 | AO6: =Q6 -> 0.041627636 | AP6: =R6 -> 0.041627637 | AQ6: =IF(AP6="","",AP6) -> 0.041627637 | AR6: =T6 -> 0.041773357 | AS6: =U6 -> 0.041776205 | AT6: =V6 -> 0.041779052 | AU6: =IF(AT6="","",AT6) -> 0.041779052 | AV6: =X6 -> 0.041759982 | AW6: =Y6 -> 0.041758168 | AX6: =Z6 -> 0.041756354 | AY6: =IF(AX6="","",AX6) -> 0.041756354 | DT6: =P6 -> 0.041627634 | DU6: =Q6 -> 0.041627636 | DV6: =R6 -> 0.041627637 | DW6: =IF(DV6="","",DV6) -> 0.041627637
B7: R2,R3,R4,R5,R6 | C7: SEINDNGA | D7: Emissions: NGA to IND | E7: PJ, PJ/a | F7: INDNGA | G7: INDNGAEA | H7: 2010 | I7: 50 | J7: 0.056 | K7: 0.00085303541 | L7: 0.00085303541 | M7: 0.00018956357 | N7: 0.00031593928 | O7: 56 | P7: 0.058533344 | Q7: 0.058533344 | R7: 0.058533344 | S7: 0.058533344 | T7: 0.00025069701 | U7: 0.00025069701 | V7: 0.00025069701 | W7: 0.00025069701 | X7: 0.0031593928 | Y7: 0.0031593928 | Z7: 0.0031593928 | AA7: 0.0031593928 | AB7: 0.0031593928 | AC7: 0.0031593928 | AD7: 0.0031593928 | AE7: 0.0031593928 | AF7: 0.0022144903 | AG7: 0.0022144903 | AH7: 0.0022144903 | AI7: 0.0022144903 | AJ7: 0.033169829 | AK7: 0.033169829 | AL7: 0.033169829 | AM7: 0.033169829 | AN7: 0.058533344 | AO7: 0.058533344 | AP7: 0.058533344 | AQ7: 0.058533344 | AR7: 0.00025069701 | AS7: 0.00025069701 | AT7: 0.00025069701 | AU7: 0.00025069701 | AV7: 0.0031593928 | AW7: 0.0031593928 | AX7: 0.0031593928 | AY7: 0.0031593928
B8: R2,R3,R4,R5,R6 | C8: SEINDRFL | D8: Emissions: RFL to IND | E8: PJ, PJ/a | F8: INDRFL | G8: INDRFLEA | H8: 2010 | I8: 50 | J8: 0.0831 | K8: 0.00284 | L8: 0.000284 | M8: 0.025494307 | N8: 0.006883463 | O8: 83.1 | P8: 0.83858254 | Q8: 0.83858254 | R8: 0.83858254 | S8: 0.83858254 | T8: 0.23453782 | U8: 0.23453782 | V8: 0.23453782 | W8: 0.23453782 | X8: 0.084981025 | Y8: 0.084981025 | Z8: 0.084981025 | AA8: 0.084981025 | AB8: 0.076482922 | AC8: 0.076482922 | AD8: 0.076482922 | AE8: 0.076482922 | AF8: 0.093519924 | AG8: 0.093519924 | AH8: 0.093519924 | AI8: 0.093519924 | AJ8: 0.34250095 | AK8: 0.34250095 | AL8: 0.34250095 | AM8: 0.34250095 | AN8: 0.83858254 | AO8: 0.83858254 | AP8: 0.83858254 | AQ8: 0.83858254 | AR8: 0.23453782 | AS8: 0.23453782 | AT8: 0.23453782 | AU8: 0.23453782 | AV8: 0.084981025 | AW8: 0.084981025 | AX8: 0.084981025 | AY8: 0.084981025

Sheet Fuel Share_dep
B1: 1 to 4 | C1: Multifamily | D1: Commercial | E1: Institutional | F1: Industrial | G1: TOTAL
A2: Fuel Oil | B2: 8460295.7 | C2: 29186362 | D2: 8003998.3 | E2: 5537647.8 | F2: 2929826.7 | G2: 54118130
A3: Electricity | B3: 19885543 | C3: 31859848 | D3: 63229620 | E3: 18987067 | F3: 30357435 | G3: 1.6431951e+08
A4: Natural gas | B4: 51014236 | C4: 1.2652206e+08 | D4: 72977381 | E4: 34299731 | F4: 25470689 | G4: 3.1028409e+08
A5: STM | B5: 0 | C5: 0 | D5: 5976355.8 | E5: 3532567.3 | F5: 0 | G5: 9508923.1
A7: TOTAL BLDGAREA | B7: BK | C7: BX | D7: MN | E7: QN | F7: SI | G7: NYC | I7: TOTAL BLDGAREA | J7: BK | K7: BX | L7: MN | M7: QN | N7: SI | O7: NYC
A8: 1 to 4 | B8: 451052104 | C8: 141799753 | D8: 30184806 | E8: 2.4081416e+08 | F8: 188837761 | G8: 1052688580 | I8: 1 to 4 | J8: 0.4284763 | K8: 0.13470247 | L8: 0.028674013 | M8: 0.22876106 | N8: 0.17938616 | O8: 1
A9: Multifamily | B9: 488073637 | C9: 365931051 | D9: 743673556 | E9: 235518283 | F9: 20635136 | G9: 1853831663 | I9: Multifamily | J9: 0.26327829 | K9: 0.19739174 | L9: 0.40115485 | M9: 0.12704405 | N9: 0.011131073 | O9: 1
A10: Commercial | B10: 120536929 | C10: 52844931 | D10: 737990936 | E10: 81617104 | F10: 21255942 | G10: 1014245842 | I10: Commercial | J10: 0.1188439 | K10: 0.052102684 | L10: 0.7276253 | M10: 0.080470731 | N10: 0.020957386 | O10: 1
A11: Industrial | B11: 125278970 | C11: 43875351 | D11: 39271823 | E11: 77054457 | F11: 10499730 | G11: 295980331 | I11: Industrial | J11: 0.42326789 | K11: 0.14823739 | L11: 0.13268389 | M11: 0.26033641 | N11: 0.035474418 | O11: 1
A12: Institutional | B12: 154479825 | C12: 92417027 | D12: 163140516 | E12: 48554369 | F12: 25465478 | G12: 484057215 | I12: Institutional | J12: 0.31913547 | K12: 0.1909217 | L12: 0.33702734 | M12: 0.10030709 | N12: 0.052608405 | O12: 1
B14: 275016754 | C14: 145261958 | D14: 901131452 | E14: 130171473 | F14: 46721420 | G14: 1498303057
A15: Commercial | B15: BK | C15: BX | D15: MN | E15: QN | F15: SI
A16: Commercial | B16: 0.4382894 | C16: 0.36379057 | D16: 0.81896036 | E16: 0.62699685 | F16: 0.45495068
A17: Institutional | B17: 0.5617106 | C17: 0.63620943 | D17: 0.18103964 | E17: 0.37300315 | F17: 0.54504932
B18: 0.18355215 | C18: 0.096950986 | D18: 0.6014347 | E18: 0.086879268 | F18: 0.03118289
A22: Fuel consumption | B22: Fuel Shares
B24: 1 to 4 | C24: Multifamily | D24: Commercial | E24: Industrial | F24: Institutional | K24: 2010 Fuel Cons | L24: 1 to 4 | M24: Multifamily | N24: Commercial | O24: Industrial | P24: Institutional | Q24: Control | S24: Commercial | T24: Institutional | U24: Commercial | V24: Industrial | W24: Institutional
A25: ELC | B25: 0.12101754 | C25: 0.19388962 | D25: 0.38479678 | E25: 0.18474638 | F25: 0.11554968 | G25: 1 | I25: ELC | J25: 0.73508036 | K25: 447.63834 | L25: 54.17209 | M25: 86.792427 | N25: 172.24979 | O25: 82.699562 | P25: 51.724465 | Q25: 0 | R25: ELC | S25: -172.24979 | T25: -51.724465
A26: NGA | B26: 0.16441138 | C26: 0.40776198 | D26: 0.23519537 | E26: 0.082088285 | F26: 0.11054299 | G26: 1 | I26: NGA | J26: 0.19845822 | K26: 271.99211 | L26: 44.718599 | M26: 110.90804 | N26: 63.971285 | O26: 22.327366 | P26: 30.066821 | Q26: 0 | R26: NGA | S26: -63.971285 | T26: -30.066821
A27: DSL | B27: 0.15633015 | C27: 0.53930839 | D27: 0.14789865 | E27: 0.054137619 | F27: 0.10232519 | G27: 1 | I27: DSL | J27: 0.066461416 | K27: 138.11436 | L27: 21.591439 | M27: 74.486232 | N27: 20.426927 | O27: 7.4771825 | P27: 14.132578 | Q27: 0 | R27: DSL | S27: -20.426927 | T27: -14.132578
A28: STM | B28: 0 | C28: 0 | D28: 0.62849975 | E28: 0 | F28: 0.37150025 | G28: 1 | I28: STM | K28: 16.342311 | L28: 0 | M28: 0 | N28: 7.5952768 | O28: 4.2575383 | P28: 4.4894963
O29: 112.50411

Sheet TechData_EmisLITE_dep
G3: *~FI_T
B4: Region | C4: TechName | D4: TechDesc | E4: Units | F4: CommIN | G4: CommOUT | H4: NCAP_START | I4: NCAP_TLIFE | J4: EFF | K4: ENV_ACT~CO2 | L4: ENV_ACT~CH4 | M4: ENV_ACT~N2O | N4: ENV_ACT~BC | O4: ENV_ACT~OC | P4: ENV_ACT~CO2I | Q4: ENV_ACT~NOX~2010 | R4: ENV_ACT~NOX~2015 | S4: ENV_ACT~NOX~2020 | T4: ENV_ACT~NOX~2055 | U4: ENV_ACT~SO2~2010 | V4: ENV_ACT~SO2~2015 | W4: ENV_ACT~SO2~2020 | X4: ENV_ACT~SO2~2055 | Y4: ENV_ACT~PM10~2010 | Z4: ENV_ACT~PM10~2015 | AA4: ENV_ACT~PM10~2020 | AB4: ENV_ACT~PM10~2055 | AC4: *ENV_ACT~PM10~2010 | AD4: *ENV_ACT~PM10~2015 | AE4: *ENV_ACT~PM10~2020 | AF4: *ENV_ACT~PM10~2055 | AG4: ENV_ACT~VOC~2010 | AH4: ENV_ACT~VOC~2015 | AI4: ENV_ACT~VOC~2020 | AJ4: ENV_ACT~VOC~2055 | AK4: ENV_ACT~CO~2010 | AL4: ENV_ACT~CO~2015 | AM4: ENV_ACT~CO~2020 | AN4: ENV_ACT~CO~2055 | AO4: ENV_ACT~NOXI~2010 | AP4: ENV_ACT~NOXI~2015 | AQ4: ENV_ACT~NOXI~2020 | AR4: ENV_ACT~NOXI~2055 | AS4: ENV_ACT~SO2I~2010 | AT4: ENV_ACT~SO2I~2015 | AU4: ENV_ACT~SO2I~2020 | AV4: ENV_ACT~SO2I~2055 | AW4: ENV_ACT~PM10I~2010 | AX4: ENV_ACT~PM10I~2015 | AY4: ENV_ACT~PM10I~2020 | AZ4: ENV_ACT~PM10I~2055 | BB4: Input | BC4: Output
B5: *Dummy technologies previously used for emissions (kept to keep RES aligned properly)
B6: *R2,R3,R4,R5,R6 | C6: SEINDBIO | D6: Emissions: Biomass combustion | E6: PJ, PJ/a | F6: INDBIO | G6: INDBIOEA | H6: 2010 | I6: 50 | J6: 1 | BB6: 1 | BC6: 1
B7: *R2,R3,R4,R5,R6 | C7: SEIPBIO | D7: Emissions: IPBIO Combustion | E7: PJ, PJ/a | F7: IPBIO | G7: IPBIOEA | H7: 2010 | I7: 50 | J7: 1 | BB7: 1 | BC7: 1
B8: *R2,R3,R4,R5,R6 | C8: SEINDAGR | D8: Emissions: INDAGR to IND | E8: PJ, PJ/a | F8: INDAGR | G8: INDAGREA | H8: 2010 | I8: 50 | J8: 1 | BB8: 1 | BC8: 1
B9: *R2,R3,R4,R5,R6 | C9: SEINDCOA | D9: Emissions: COA to IND | E9: PJ, PJ/a | F9: INDCOA | G9: INDCOAEA | H9: 2010 | I9: 50 | J9: 1 | BB9: 1 | BC9: 1
B10: R2,R3,R4,R5,R6 | C10: SEINDNGA | D10: Emissions: NGA to IND | E10: PJ, PJ/a | F10: INDNGA | G10: INDNGAEA | H10: 2010 | I10: 50 | J10: 1 | K10: 0.056 | L10: 0.00085303541 | M10: 0.00085303541 | N10: 0.00018956357 | O10: 0.00031593928 | P10: 56 | Q10: 0.058533344 | R10: 0.058533344 | S10: 0.058533344 | T10: 0.058533344 | U10: 0.00025069701 | V10: 0.00025069701 | W10: 0.00025069701 | X10: 0.00025069701 | Y10: 0.0031593928 | Z10: 0.0031593928 | AA10: 0.0031593928 | AB10: 0.0031593928 | AC10: 0.0031593928 | AD10: 0.0031593928 | AE10: 0.0031593928 | AF10: 0.0031593928 | AG10: 0.0022144903 | AH10: 0.0022144903 | AI10: 0.0022144903 | AJ10: 0.0022144903 | AK10: 0.033169829 | AL10: 0.033169829 | AM10: 0.033169829 | AN10: 0.033169829 | AO10: 0.058533344 | AP10: 0.058533344 | AQ10: 0.058533344 | AR10: 0.058533344 | AS10: 0.00025069701 | AT10: 0.00025069701 | AU10: 0.00025069701 | AV10: 0.00025069701 | AW10: 0.0031593928 | AX10: 0.0031593928 | AY10: 0.0031593928 | AZ10: 0.0031593928 | BB10: 1 | BC10: 1
B11: *R2,R3,R4,R5,R6 | C11: SEINDRFH | D11: Emissions: RFH to IND | E11: PJ, PJ/a | F11: INDRFH | G11: INDRFHEA | H11: 2010 | I11: 50 | J11: 1 | BB11: 1 | BC11: 1
B12: R2,R3,R4,R5,R6 | C12: SEINDRFL | D12: Emissions: RFL to IND | E12: PJ, PJ/a | F12: INDRFL | G12: INDRFLEA | H12: 2010 | I12: 50 | J12: 1 | K12: 0.0831 | L12: 0.00284 | M12: 0.000284 | N12: 0.025494307 | O12: 0.006883463 | P12: 83.1 | Q12: 0.83858254 | R12: 0.83858254 | S12: 0.83858254 | T12: 0.83858254 | U12: 0.23453782 | V12: 0.23453782 | W12: 0.23453782 | X12: 0.23453782 | Y12: 0.084981025 | Z12: 0.084981025 | AA12: 0.084981025 | AB12: 0.084981025 | AC12: 0.076482922 | AD12: 0.076482922 | AE12: 0.076482922 | AF12: 0.076482922 | AG12: 0.093519924 | AH12: 0.093519924 | AI12: 0.093519924 | AJ12: 0.093519924 | AK12: 0.34250095 | AL12: 0.34250095 | AM12: 0.34250095 | AN12: 0.34250095 | AO12: 0.83858254 | AP12: 0.83858254 | AQ12: 0.83858254 | AR12: 0.83858254 | AS12: 0.23453782 | AT12: 0.23453782 | AU12: 0.23453782 | AV12: 0.23453782 | AW12: 0.084981025 | AX12: 0.084981025 | AY12: 0.084981025 | AZ12: 0.084981025 | BB12: 1 | BC12: 1
B13: *R2,R3,R4,R5,R6 | C13: SEINDDSL | D13: Emissions: DSL to IND | E13: PJ, PJ/a | F13: INDDSL | G13: INDDSLEA | H13: 2010 | I13: 50 | J13: 1 | K13: 0.0771 | L13: 0.00018956342 | M13: 0.00037912685 | N13: 0.013168406 | O13: 0.0010815939 | P13: 77.1 | Q13: 0.062683779 | R13: 0.062683779 | S13: 0.062683779 | T13: 0.062683779 | U13: 0.0013283188 | V13: 0.0013283188 | W13: 0.0013283188 | X13: 0.0013283188 | Y13: 0.043894687 | Z13: 0.043894687 | AA13: 0.043894687 | AB13: 0.043894687 | AC13: 0.036053131 | AD13: 0.036053131 | AE13: 0.036053131 | AF13: 0.036053131 | AG13: 0.00062 | AH13: 0.00062 | AI13: 0.00062 | AJ13: 0.00062 | AK13: 0.01546 | AL13: 0.01546 | AM13: 0.01546 | AN13: 0.01546 | AO13: 0.062683779 | AP13: 0.062683779 | AQ13: 0.062683779 | AR13: 0.062683779 | AS13: 0.0013283188 | AT13: 0.0013283188 | AU13: 0.0013283188 | AV13: 0.0013283188 | AW13: 0.043894687 | AX13: 0.043894687 | AY13: 0.043894687 | AZ13: 0.043894687 | BB13: 1 | BC13: 1
B14: *R2,R3,R4,R5,R6 | C14: SEINDKER | D14: Emissions: KER to IND | E14: PJ, PJ/a | F14: INDKER | G14: INDKEREA | H14: 2010 | I14: 50 | J14: 1 | BB14: 1 | BC14: 1
B15: *R2,R3,R4,R5,R6 | C15: SEINDLPG | D15: Emissions: LPG to IND | E15: PJ, PJ/a | F15: INDLPG | G15: INDLPGEA | H15: 2010 | I15: 50 | J15: 1 | BB15: 1 | BC15: 1
B16: *R2,R3,R4,R5,R6 | C16: SEINDMET | D16: Emissions: MET to IND | E16: PJ, PJ/a | F16: METCOA | G16: INDMETEA | H16: 2010 | I16: 50 | J16: 1 | BB16: 1 | BC16: 1
B17: *R2,R3,R4,R5,R6 | C17: SEINDPFS | D17: Emissions: PFS to IND | E17: PJ, PJ/a | F17: INDPFS | G17: INDPFSEA | H17: 2010 | I17: 50 | J17: 1 | BB17: 1 | BC17: 1
B18: *R2,R3,R4,R5,R6 | C18: SEINDASP | D18: Emissions: ASP to IND | E18: PJ, PJ/a | F18: INDASP | G18: INDASPEA | H18: 2010 | I18: 50 | J18: 1 | BB18: 1 | BC18: 1

Sheet Tech_Data
B2: These coefficients are chosent o force the COMET output to match the inventory
B3: Derate for Calibration | D3: 0.78 | E3: 0.7
B4: Inflate for Calibration | D4: 0.3 | E4: 0.38
B6: IND_DEM_TECH
G7: ~FI_T
B8: Region | C8: TechName | D8: *TechDesc | E8: *Units | F8: CommIN | G8: CommOUT | H8: NCAP_START | I8: NCAP_TLIFE | J8: NCAP_COST | K8: NCAP_FOM | L8: NCAP_DRATE | M8: EFF | N8: CAP2ACT | O8: *NCAP_AF | P8: ACT_BND~FX~2010 | Q8: ACT_BND~FX~2015 | R8: ACT_BND~FX~2020 | S8: ACT_BND~FX~2023 | T8: *CF | U8: *PRC_RESID~UP~2010 | V8: *PRC_RESID~UP~2015 | W8: *PRC_RESID~UP~2020 | X8: *PRC_RESID~UP~2023 | Y8: *PRC_RESID~UP~2025
B9: *Energy Transfer
B10: R2,R3,R4,R5,R6 | C10: ETINDNGA | D10: Energy Transfer: NGA to INDNGA | E10: PJ | F10: NGA | G10: INDNGA | H10: 2010 | I10: 50 | M10: 1
B11: R2,R3,R4,R5,R6 | C11: ETINDDSL | D11: Energy Transfer: DSL to INDDSL | E11: PJ | F11: DSL | G11: INDDSL | H11: 2010 | I11: 50 | M11: 1
B12: R2,R3,R4,R5,R6 | C12: ETINDELC | D12: Energy Transfer: ELC to INDELC | E12: PJ | F12: ELC | G12: INDELC | H12: 2010 | I12: 50 | M12: 1
B13: *SPACE HEATING
B14: *Commercial Rooftop Air-source Heat Pumps
B15: R2,R3,R4,R5,R6 | C15: ISHAHPST10 | D15: ISH.ELC.AHP.Ver1.10 | E15: PJ, PJ/a | F15: INDELC | G15: ISH | H15: 2010 | I15: 15 | J15: 7.5395365 | K15: 0.13658581 | L15: 0.18 | M15: 3.3 | N15: 31.536 | O15: 0.28 | P15: 0 | Q15: 0 | R15: 0 | S15: 0
B16: *Commercial Ground Source Heat Pumps
B17: R2,R3,R4,R5,R6 | C17: ISHGHPST10 | D17: ISH.ELC.GHP.Ver1.10 | E17: PJ, PJ/a | F17: INDELC | G17: ISH | H17: 2010 | I17: 20 | J17: 13.767849 | K17: 1.6521419 | L17: 0.24 | M17: 3.5 | N17: 31.536 | O17: 0.28 | P17: 0 | Q17: 0 | R17: 0 | S17: 0
B18: * Natural Gas Heat Pump
B19: R2,R3,R4,R5,R6 | C19: ISHNHPST10 | D19: ISH.NG.HEATPUMP.ST.10 | E19: PJ, PJ/a | F19: INDNGAEA | G19: ISH | H19: 2010 | I19: 30 | J19: 30.731806 | K19: 0.45073316 | L19: 0.18 | M19: 1.4 | O19: 0.28 | P19: 0 | Q19: 0 | R19: 0 | S19: 0
B20: * Space Heating Commercial Electric Resistance Unit Heaters
B21: R2,R3,R4,R5,R6 | C21: ISHERUST10 | D21: ISH.ELC.RSU.STANDARD.SMALL.12 | E21: PJ, PJ/a | F21: INDELC | G21: ISH | H21: 2010 | I21: 18 | J21: 3.7717225 | K21: 0.02 | L21: 0.18 | M21: 1 | N21: 31.536 | O21: 0.28 | P21: 0 | Q21: 0 | R21: 0 | S21: 0
B22: R2,R3,R4,R5,R6 | C22: ISHERUSTL10 | D22: ISH.ELC.RSU.STANDARD.LARGE.12 | E22: PJ, PJ/a | F22: INDELC | G22: ISH | H22: 2010 | I22: 18 | J22: 2.2721586 | K22: 0.02 | L22: 0.18 | M22: 1 | N22: 31.536 | O22: 0.28 | P22: =DemandCalc!N6*CommDemand!G6 -> 0.27236468 | Q22: =DemandCalc!N14*CommDemand!H6 -> 0.27702292 | R22: =DemandCalc!N22*CommDemand!I6 -> 0.22584865 | S22: =DemandCalc!N30*CommDemand!J6 -> 0.24488042 | T22: 0.28 | U22: =P22/($T22*$N22*$M22) -> 0.030845098 | V22: =Q22/($T22*$N22*$M22) -> 0.03137264 | W22: =R22/($T22*$N22*$M22) -> 0.025577192 | X22: =S22/($T22*$N22*$M22) -> 0.027732526 | Y22: =T22/($T22*$N22*$M22) -> 0.031709792
B23: *Commercial Gas-Fired Furnaces
B24: R2,R3,R5,R6 | C24: ISHNGFST10 | D24: ISH.NG.FURNACE.Ver1.10 | E24: PJ, PJ/a | F24: INDNGAEA | G24: ISH | H24: 2010 | I24: 17.5 | J24: 0.96724421 | K24: 0.095138775 | L24: 0.18 | M24: 0.77525 | O24: 0.28 | P24: =DemandCalc!N7*0.5*(CommDemand!G6+P36/(2*5))*var_derate -> 1.7805006 | Q24: =DemandCalc!N15*0.5*(CommDemand!H6+Q36/(2*5))*0.85 -> 2.2686914 | R24: =DemandCalc!N23*0.5*(CommDemand!I6+R36/(2*5))*0.85 -> 2.3217333 | S24: =DemandCalc!N31*0.5*(CommDemand!J6+S36/(2*5))*var_derate -> 1.2215305 | T24: 0.28 | U24: =P24/($T24*$M24) -> 8.202426 | V24: =Q24/($T24*$M24) -> 10.451428 | W24: =R24/($T24*$M24) -> 10.695782 | X24: =S24/($T24*$M24) -> 5.6273573 | Y24: =T24/($T24*$M24) -> 1.2899065
B25: R4 | C25: ISHNGFST10 | D25: ISH.NG.FURNACE.Ver1.10 | E25: PJ, PJ/a | F25: INDNGAEA | G25: ISH | H25: 2010 | I25: 17.5 | J25: 0.96724421 | K25: 0.095138775 | L25: 0.18 | M25: 0.77525 | O25: 0.28 | P25: =P24-(P$36/(2*5)) -> 1.4776975 | Q25: =(Q24-(Q$36/(2*5)))*0.58 -> 1.1618488 | R25: =R24-(R$36/(2*5)) -> 2.125222 | S25: =S24-(S$36/(2*5)) -> 0.97872077 | T25: 0.28 | U25: =P25/($T25*$M25) -> 6.8074701 | V25: =Q25/($T25*$M25) -> 5.3524154 | W25: =R25/($T25*$M25) -> 9.7904916 | X25: =S25/($T25*$M25) -> 4.5087795 | Y25: =T25/($T25*$M25) -> 1.2899065
B26: *Commercial Gas-fired Boilers
B27: R2,R3,R5,R6 | C27: ISHNGBST10 | D27: ISH.NG.BOILER | E27: PJ, PJ/a | F27: INDNGAEA | G27: ISH | H27: 2010 | I27: 30 | J27: 1.5900548 | K27: 0.070919543 | L27: 0.18 | M27: 0.78 | O27: 0.28 | P27: =DemandCalc!N7*0.5*(CommDemand!G6+P36/(2*5))*var_derate -> 1.7805006 | Q27: =DemandCalc!N15*0.5*(CommDemand!H6+Q36/(2*5))*0.85 -> 2.2686914 | R27: =DemandCalc!N23*0.5*(CommDemand!I6+R36/(2*5))*0.74 -> 2.0212737 | S27: =DemandCalc!N31*0.5*(CommDemand!J6+S36/(2*5))*var_derate -> 1.2215305 | T27: 0.28 | U27: =P27/($T27*$M27) -> 8.1524753 | V27: =Q27/($T27*$M27) -> 10.387781 | W27: =R27/($T27*$M27) -> 9.2549164 | X27: =S27/($T27*$M27) -> 5.5930882 | Y27: =T27/($T27*$M27) -> 1.2820513
B28: R4 | C28: ISHNGBST10 | D28: ISH.NG.BOILER | E28: PJ, PJ/a | F28: INDNGAEA | G28: ISH | H28: 2010 | I28: 30 | J28: 1.5900548 | K28: 0.070919543 | L28: 0.18 | M28: 0.78 | O28: 0.28 | P28: =P27-(P$36/(2*5)) -> 1.4776975 | Q28: =(Q27-(Q$36/(2*5)))*0.58 -> 1.1618488 | R28: =R27-(R$36/(2*5)) -> 1.8247624 | S28: =S27-(S$36/(2*5)) -> 0.97872077 | T28: 0.28 | U28: =P28/($T28*$M28) -> 6.7660144 | V28: =Q28/($T28*$M28) -> 5.3198206 | W28: =R28/($T28*$M28) -> 8.3551392 | X28: =S28/($T28*$M28) -> 4.4813222 | Y28: =T28/($T28*$M28) -> 1.2820513
B29: *Commercial Oil-fired Furnaces
B30: R2,R3,R4,R5,R6 | C30: ISHDSFST10 | D30: ISH.DSL.FURNACE.ST.10 | E30: PJ, PJ/a | F30: INDDSLEA | G30: ISH | H30: 2010 | I30: 19 | J30: 1.3061742 | K30: 0.092746099 | L30: 0.18 | M30: 0.79525 | O30: 0.28 | P30: =0.5*DemandCalc!N8*CommDemand!G6*0.75 -> 0.23305646 | Q30: =0.5*DemandCalc!N16*CommDemand!H6*0.75 -> 0.25022281 | R30: =0.5*DemandCalc!N24*CommDemand!I6*var_derate -> 0.15277015 | S30: =0.5*DemandCalc!N32*CommDemand!J6*var_derate -> 0.13890457 | T30: 0.28 | U30: =P30/($T30*$M30) -> 1.0466451 | V30: =Q30/($T30*$M30) -> 1.1237383 | W30: =R30/($T30*$M30) -> 0.68608324 | X30: =S30/($T30*$M30) -> 0.62381356 | Y30: =T30/($T30*$M30) -> 1.2574662
B31: *R4 | C31: ISHDSFST10 | D31: ISH.DSL.FURNACE.ST.10 | E31: PJ, PJ/a | F31: INDDSLEA | G31: ISH | H31: 2010 | I31: 19 | J31: 1.3061742 | K31: 0.092746099 | L31: 0.18 | M31: 0.79525 | O31: 0.28 | T31: 0.28 | U31: =P31/($T31*$M31) -> 0 | V31: =Q31/($T31*$M31) -> 0 | W31: =R31/($T31*$M31) -> 0 | X31: =S31/($T31*$M31) -> 0 | Y31: =T31/($T31*$M31) -> 1.2574662
B32: *Commercial Oil-fired Boilers
B33: R2,R3,R4,R5,R6 | C33: ISHDSBST10 | D33: ISH.DSL.BOILER.BS.10 | E33: PJ, PJ/a | F33: INDDSLEA | G33: ISH | H33: 2010 | I33: 25 | J33: 1.79 | K33: 0.02 | L33: 0.18 | M33: 0.77 | O33: 0.28 | P33: =0.5*DemandCalc!N8*CommDemand!G6*0.75 -> 0.23305646 | Q33: =0.5*DemandCalc!N16*CommDemand!H6*0.75 -> 0.25022281 | R33: =0.5*DemandCalc!N24*CommDemand!I6*var_derate -> 0.15277015 | S33: =0.5*DemandCalc!N32*CommDemand!J6*var_derate -> 0.13890457 | T33: 0.28 | U33: =P33/($T33*$M33) -> 1.0809669 | V33: =Q33/($T33*$M33) -> 1.1605882 | W33: =R33/($T33*$M33) -> 0.70858142 | X33: =S33/($T33*$M33) -> 0.64426978 | Y33: =T33/($T33*$M33) -> 1.2987013
B34: *R4 | C34: ISHDSBST10 | D34: ISH.DSL.BOILER.BS.10 | E34: PJ, PJ/a | F34: INDDSLEA | G34: ISH | H34: 2010 | I34: 25 | J34: 1.79 | K34: 0.02 | L34: 0.18 | M34: 0.77 | O34: 0.28 | T34: 0.28 | U34: =P34/($T34*$M34) -> 0 | V34: =Q34/($T34*$M34) -> 0 | W34: =R34/($T34*$M34) -> 0 | X34: =S34/($T34*$M34) -> 0 | Y34: =T34/($T34*$M34) -> 1.2987013
B35: *UTILITY SCALE CHP - SH
B36: R4 | C36: ISHNUTIBOI10 | D36: ISH.NG.UTILITY.BOILER | E36: PJ, PJ/a | F36: INDSTNB | G36: ISH | H36: 2010 | I36: 30 | J36: 2.5215838 | K36: 0.070919543 | L36: 0.18 | M36: 0.78 | O36: 0.28 | P36: =DemandCalc!N9*CommDemand!G6*5*var_derate -> 3.0280307 | Q36: =DemandCalc!N17*CommDemand!H6*5*var_derate -> 2.6550379 | R36: =DemandCalc!N25*CommDemand!I6*5*var_derate -> 1.9651133 | S36: =DemandCalc!N33*CommDemand!J6*5 -> 2.4280968 | T36: 0.28 | U36: =P36/($T36*$M36) -> 13.86461 | V36: =Q36/($T36*$M36) -> 12.156767 | W36: =R36/($T36*$M36) -> 8.9977715 | X36: =S36/($T36*$M36) -> 11.117659 | Y36: =T36/($T36*$M36) -> 1.2820513
B37: R4 | C37: ISHNUTICHP10 | D37: ISH.NG.UTILITY.CHP | E37: PJ, PJ/a | F37: INDSTNUC | G37: ISH | H37: 2010 | I37: 30 | J37: 2.5215838 | K37: 0.070919543 | L37: 0.18 | M37: 0.78 | O37: 0.28 | P37: 0 | Q37: 0 | R37: 0 | S37: 0
B38: R4 | C38: ISHBUTICHP10 | D38: ISH.DSL.UTILITY.CHP | E38: PJ, PJ/a | F38: INDSTBUC | G38: ISH | H38: 2010 | I38: 30 | J38: 2.5215838 | K38: 0.070919543 | L38: 0.18 | M38: 0.78 | O38: 0.28 | P38: 0 | Q38: 0 | R38: 0 | S38: 0
B39: * SPACE COOLING
B40: *Electric techs
B41: R2,R3,R4,R5,R6 | C41: ISCAHPST10 | D41: ISC.ELC.AHP.ST.10 | E41: PJ, PJ/a | F41: INDELC | G41: ISC | H41: 2010 | I41: 15 | J41: 7.5395365 | K41: 0.13658581 | L41: 0.18 | M41: 3.2239156 | N41: 31.536 | O41: 0.17 | P41: 0 | Q41: 0 | R41: 0 | S41: 0
B42: R2,R3,R4,R5,R6 | C42: ISCGHPST10 | D42: ISC.ELC.GHP.ST.10 | E42: PJ, PJ/a | F42: INDELC | G42: ISC | H42: 2010 | I42: 20 | J42: 13.767849 | K42: 1.6521419 | L42: 0.24 | M42: 4.1031653 | N42: 31.536 | O42: 0.17 | P42: 0 | Q42: 0 | R42: 0 | S42: 0
B43: R2,R3,R4,R5,R6 | C43: ISCCRCST10 | D43: ISC.ELC.CRC.ST.10 | E43: PJ, PJ/a | F43: INDELC | G43: ISC | H43: 2010 | I43: 20 | J43: 4.8146497 | K43: 0.26634232 | L43: 0.18 | M43: 3.9077765 | N43: 31.536 | O43: 0.17 | P43: =0.5*CommDemand!G7/var_inflate -> 1.3759415 | Q43: =0.5*CommDemand!H7/var_inflate -> 1.3994741 | R43: =0.5*CommDemand!I7/var_inflate -> 1.1409502 | S43: =0.5*CommDemand!J7/var_inflate -> 1.2370955 | T43: 0.17 | U43: =P43/($T43*$N43*$M43) -> 0.065677214 | V43: =Q43/($T43*$N43*$M43) -> 0.066800488 | W43: =R43/($T43*$N43*$M43) -> 0.054460476 | X43: =S43/($T43*$N43*$M43) -> 0.059049741 | Y43: =T43/($T43*$N43*$M43) -> 0.0081145358
B44: R2,R3,R4,R5,R6 | C44: ISCCCCST10 | D44: ISC.ELC.CCC.ST.10 | E44: PJ, PJ/a | F44: INDELC | G44: ISC | H44: 2010 | I44: 25 | J44: 2.91 | K44: 0.18439084 | L44: 0.18 | M44: 6.6787452 | N44: 31.536 | O44: 0.17 | P44: 0 | Q44: 0 | R44: 0 | S44: 0
B45: R2,R3,R4,R5,R6 | C45: ISCRACST10 | D45: ISC.ELC.RAC.ST.10 | E45: PJ, PJ/a | F45: INDELC | G45: ISC | H45: 2010 | I45: 15 | J45: 9.0692975 | K45: 0.24585445 | L45: 0.18 | M45: 3.3294256 | N45: 31.536 | O45: 0.17 | P45: 0 | Q45: 0 | R45: 0 | S45: 0
B46: R2,R3,R4,R5,R6 | C46: ISCWACST10 | D46: ISC.ELC.WAC.ST.10 | E46: PJ, PJ/a | F46: INDELC | G46: ISC | H46: 2010 | I46: 11 | J46: 2.5194228 | K46: 0.093658839 | L46: 0.18 | M46: 2.9308324 | N46: 31.536 | O46: 0.17 | P46: =0.5*CommDemand!G7/var_inflate -> 1.3759415 | Q46: =0.5*CommDemand!H7/var_inflate -> 1.3994741 | R46: =0.5*CommDemand!I7/var_inflate -> 1.1409502 | S46: =0.5*CommDemand!J7/var_inflate -> 1.2370955 | T46: 0.17 | U46: =P46/($T46*$N46*$M46) -> 0.087569618 | V46: =Q46/($T46*$N46*$M46) -> 0.089067317 | W46: =R46/($T46*$N46*$M46) -> 0.072613968 | X46: =S46/($T46*$N46*$M46) -> 0.078732988 | Y46: =T46/($T46*$N46*$M46) -> 0.010819381
B47: R2,R3,R4,R5,R6 | C47: ISCCACST10 | D47: ISC.ELC.CAC.ST.10 | E47: PJ, PJ/a | F47: INDELC | G47: ISC | H47: 2010 | I47: 16.5 | J47: 9.7886494 | K47: 0.19122013 | L47: 0.18 | M47: 4.0250098 | N47: 31.536 | O47: 0.17 | P47: 0 | Q47: 0 | R47: 0 | S47: 0
B48: *NG techs
B49: *R2,R3,R4,R5,R6 | C49: ISCNHPST10 | D49: ISC.NG.HEATPUMP.ST.10 | E49: PJ, PJ/a | F49: INDNGAEA | G49: ISC | H49: 2010 | I49: 30 | J49: 30.731806 | K49: 0.45073316 | L49: 0.18 | M49: 1.1 | O49: 0.17 | P49: 0 | Q49: 0 | R49: 0 | S49: 0
B50: *R2,R3,R4,R5,R6 | C50: ISCCHAST10 | D50: ISC.NG.CHA.ST.10 | E50: PJ, PJ/a | F50: INDNGAEA | G50: ISC | H50: 2010 | I50: 23 | J50: 6.7609974 | K50: 0.18439084 | L50: 0.18 | M50: 1.1 | O50: 0.17 | P50: 0 | Q50: 0 | R50: 0 | S50: 0
B51: * WATER HEATING
B52: *heatpump
B53: R2,R3,R4,R5,R6 | C53: IWHEHPST10 | D53: IWH.ELC.HEATPUMP.ST.10 | E53: PJ, PJ/a | F53: INDELC | G53: IWH | H53: 2010 | I53: 13 | J53: 25.990328 | K53: 0.21073239 | L53: 0.24 | M53: 2 | N53: 31.536 | O53: 0.44 | P53: 0 | Q53: 0 | R53: 0 | S53: 0
B54: *ewh
B55: R2,R3,R4,R5,R6 | C55: IWHEWHBS10 | D55: IWH.ELC.EWH.BS.10 | E55: PJ, PJ/a | F55: INDELC | G55: IWH | H55: 2010 | I55: 13 | J55: 3.3015266 | K55: 0.033015266 | L55: 0.18 | M55: 0.97 | N55: 31.536 | O55: 0.44 | P55: =DemandCalc!O6*CommDemand!G8 -> 0.11984021 | Q55: =DemandCalc!O14*CommDemand!H8 -> 0.12188983 | R55: =DemandCalc!O22*CommDemand!I8 -> 0.099373196 | S55: =DemandCalc!O30*CommDemand!J8 -> 0.10774716 | T55: 0.44 | U55: =P55*$M55/($T55*$N55) -> 0.0083775108 | V55: =Q55*$M55/($T55*$N55) -> 0.008520791 | W55: =R55*$M55/($T55*$N55) -> 0.0069467506 | X55: =S55*$M55/($T55*$N55) -> 0.007532138 | Y55: =X55 -> 0.007532138
B56: *R4 | C56: IWHEWHBS10 | D56: IWH.ELC.EWH.BS.10 | E56: PJ, PJ/a | F56: INDELC | G56: IWH | H56: 2010 | I56: 13 | J56: 3.3015266 | K56: 0.033015266 | L56: 0.18 | M56: 0.97 | N56: 31.536 | O56: 0.44 | T56: 0.44 | U56: =P56*$M56/($T56*$N56) -> 0 | V56: =Q56*$M56/($T56*$N56) -> 0 | W56: =R56*$M56/($T56*$N56) -> 0 | X56: =S56*$M56/($T56*$N56) -> 0 | Y56: =X56 -> 0
B57: *nwh
B58: R2,R3,R5,R6 | C58: IWHNGIBS10 | D58: IWH.NG.INSTANT.BS.10 | E58: PJ, PJ/a | F58: INDNGAEA | G58: IWH | H58: 2010 | I58: 13 | J58: 2.5215841 | K58: 0.063039603 | L58: 0.18 | M58: 0.78 | O58: 0.44 | P58: =DemandCalc!O7*(CommDemand!G8+(P$68/5)) -> 0.19070166 | Q58: =DemandCalc!O15*(CommDemand!H8+(Q68/5)) -> 0.21819845 | R58: =DemandCalc!O23*(CommDemand!I8+(R66/5)) -> 0.17562092 | S58: =DemandCalc!O31*(CommDemand!J8+(S66/5)) -> 0.097890966 | T58: 0.44 | U58: =P58/($T58*$M58) -> 0.55565752 | V58: =Q58/($T58*$M58) -> 0.63577635 | W58: =R58/($T58*$M58) -> 0.51171598 | X58: =S58/($T58*$M58) -> 0.28523009 | Y58: =T58/($T58*$M58) -> 1.2820513
B59: R4 | C59: IWHNGIBS10 | D59: IWH.NG.INSTANT.BS.10 | E59: PJ, PJ/a | F59: INDNGAEA | G59: IWH | H59: 2010 | I59: 13 | J59: 2.5215841 | K59: 0.063039603 | L59: 0.18 | M59: 0.78 | O59: 0.44 | P59: =P58-(P68/5) -> 0.0080222231 | Q59: =Q58-(Q68/5) -> 0.058021458 | R59: =R58-(R68/5) -> 0.057066712 | S59: =MAX(0,S58-(S68/5)) -> 0 | T59: 0.44 | U59: =P59/($T59*$M59) -> 0.023374776 | V59: =Q59/($T59*$M59) -> 0.16906019 | W59: =R59/($T59*$M59) -> 0.1662783 | X59: =S59/($T59*$M59) -> 0 | Y59: =T59/($T59*$M59) -> 1.2820513
B60: *dwh
B61: R2,R3,R4,R5,R6 | C61: IWHDWHBS10 | D61: IWH.DSL.DWH.BS.10 | E61: PJ, PJ/a | F61: INDDSLEA | G61: IWH | H61: 2010 | I61: 13 | J61: 1.9940477 | K61: 0.062724405 | L61: 1.75 | M61: 0.784 | O61: 0.44 | P61: =DemandCalc!O8*(CommDemand!G8+P68/2)*var_derate -> 0.092354928 | Q61: =DemandCalc!O16*(CommDemand!H8+Q68/2)*0.46 -> 0.055083625 | R61: =DemandCalc!O24*(CommDemand!I8+R66/2)*0.8 -> 0.03297558 | S61: =DemandCalc!O32*(CommDemand!J8+S66/2) -> 0.03747835 | T61: 0.44 | U61: =P61/($T61*$M61) -> 0.26772649 | V61: =Q61/($T61*$M61) -> 0.1596812 | W61: =R61/($T61*$M61) -> 0.095592475 | X61: =S61/($T61*$M61) -> 0.10864549 | Y61: =T61/($T61*$M61) -> 1.2755102
B62: R4* | C62: IWHDWHBS10 | D62: IWH.DSL.DWH.BS.10 | E62: PJ, PJ/a | F62: INDDSLEA | G62: IWH | H62: 2010 | I62: 13 | J62: 1.9940477 | K62: 0.062724405 | L62: 1.75 | M62: 0.784 | O62: 0.44 | T62: 0.44 | U62: =P62/($T62*$M62) -> 0 | V62: =Q62/($T62*$M62) -> 0 | W62: =R62/($T62*$M62) -> 0 | X62: =S62/($T62*$M62) -> 0 | Y62: =T62/($T62*$M62) -> 1.2755102
B63: *chp-wh
B64: *R2,R3,R4,R5,R6 | C64: IWHNOTRCHP | D64: IWH.NG.OTHERCHP | E64: PJ, PJ/a | F64: INDSTNOC | G64: IWH | H64: 2010 | M64: 1 | O64: 0.44 | P64: 0 | Q64: 0 | R64: 0 | S64: 0
B65: *UTILITY SCALE CHP - WH
B66: R4 | C66: IWHNUTIBOI10 | D66: IWH.NG.UTILITY.BOILER | E66: PJ, PJ/a | F66: INDSTB | G66: IWH | H66: 2010 | I66: 30 | J66: 2.5215838 | K66: 0.070919543 | L66: 0.18 | M66: 0.78 | O66: 0.44 | P66: 0 | Q66: 0 | R66: 0 | S66: 0 | T66: 0.44 | U66: =P66*$M66/$T66 -> 0 | V66: =Q66*$M66/$T66 -> 0 | W66: =R66*$M66/$T66 -> 0 | X66: =S66*$M66/$T66 -> 0 | Y66: =X66 -> 0
B67: R4 | C67: IWHNUTICHP10 | D67: IWH.NG.UTILITY.CHP | E67: PJ, PJ/a | F67: INDSTBUC | G67: IWH | H67: 2010 | I67: 30 | J67: 2.5215838 | K67: 0.070919543 | L67: 0.18 | M67: 0.78 | O67: 0.44 | P67: 0 | Q67: 0 | R67: 0 | S67: 0
B68: R4 | C68: IWHBUTICHP10 | D68: IWH.DSL.UTILITY.CHP | E68: PJ, PJ/a | F68: INDSTBUC | G68: IWH | H68: 2010 | I68: 30 | J68: 2.5215838 | K68: 0.070919543 | L68: 0.18 | M68: 0.78 | O68: 0.44 | P68: =DemandCalc!O9*CommDemand!G8*5*var_derate -> 0.91339719 | Q68: =DemandCalc!O17*CommDemand!H8*5*var_derate -> 0.80088493 | R68: =DemandCalc!O25*CommDemand!I8*5*var_derate -> 0.59277105 | S68: =DemandCalc!O33*CommDemand!J8*5 -> 0.73242877 | T68: 0.44 | U68: =P68/($T68*$M68) -> 2.6614137 | V68: =Q68/($T68*$M68) -> 2.3335808 | W68: =R68/($T68*$M68) -> 1.7271884 | X68: =S68/($T68*$M68) -> 2.1341165 | Y68: =T68/($T68*$M68) -> 1.2820513
B69: * LIGHTING
B70: R2,R3,R4,R5,R6 | C70: ILTINCBS | D70: ILT_INC_100W_BS | E70: PJ, PJ/a | F70: INDELC | G70: ILT | H70: 2010 | I70: 15 | J70: 97.010484 | K70: 4.9917018 | L70: 0.18 | M70: 0.31711108 | N70: 31.536 | O70: 0.42 | P70: 0 | Q70: 0 | R70: 0 | S70: 0
B71: R2,R3,R4,R5,R6 | C71: ILTCFLBS | D71: ILT_CFL_26W_BS | E71: PJ, PJ/a | F71: INDELC | G71: ILT | H71: 2010 | I71: 15 | J71: 97.421988 | K71: 1.9665276 | L71: 0.18 | M71: 1.2811288 | N71: 31.536 | O71: 0.42 | P71: 0 | Q71: 0 | R71: 0 | S71: 0
B72: R2,R3,R4,R5,R6 | C72: ILTHAL9010 | D72: ILT_HAL_90W_10 | E72: PJ, PJ/a | F72: INDELC | G72: ILT | H72: 2010 | I72: 15 | J72: 63.095466 | K72: 6.0333852 | L72: 0.18 | M72: 0.6151955 | N72: 31.536 | O72: 0.42 | P72: 0 | Q72: 0 | R72: 0 | S72: 0
B73: R2,R3,R4,R5,R6 | C73: ILTT8MAGBS | D73: ILT_LFL_T8_F32_MAG_BS | E73: PJ, PJ/a | F73: INDELC | G73: ILT | H73: 2010 | I73: 15 | J73: 31.728417 | K73: 0.85953857 | L73: 0.18 | M73: 1.8709902 | N73: 31.536 | O73: 0.42 | P73: 0 | Q73: 0 | R73: 0 | S73: 0
B74: R2,R3,R4,R5,R6 | C74: ILTT810 | D74: ILT_LFL_T8_F32_10 | E74: PJ, PJ/a | F74: INDELC | G74: ILT | H74: 2010 | I74: 15 | J74: 24.294842 | K74: 1.0664664 | L74: 0.18 | M74: 1.5892498 | N74: 31.536 | O74: 0.42 | P74: 0 | Q74: 0 | R74: 0 | S74: 0
B75: R2,R3,R4,R5,R6 | C75: ILTT8HE10 | D75: ILT_LFL_T8_F32_HE_10 | E75: PJ, PJ/a | F75: INDELC | G75: ILT | H75: 2010 | I75: 15 | J75: 25.359062 | K75: 1.2194117 | L75: 0.24 | M75: 2.5556855 | N75: 31.536 | O75: 0.42 | P75: 0 | Q75: 0 | R75: 0 | S75: 0
B76: R2,R3,R4,R5,R6 | C76: ILTT8LBS | D76: ILT_LFL_T8_F96_BS | E76: PJ, PJ/a | F76: INDELC | G76: ILT | H76: 2010 | I76: 15 | J76: 13.677167 | K76: 0.76656389 | L76: 0.18 | M76: 2.3307665 | N76: 31.536 | O76: 0.42 | P76: 0 | Q76: 0 | R76: 0 | S76: 0
B77: R2,R3,R4,R5,R6 | C77: ILTT8LHEBS | D77: ILT_LFL_T8_F96_HE_BS | E77: PJ, PJ/a | F77: INDELC | G77: ILT | H77: 2010 | I77: 15 | J77: 14.486886 | K77: 0.80138805 | L77: 0.24 | M77: 2.6351931 | N77: 31.536 | O77: 0.42 | P77: =CommDemand!G9/var_inflate2 -> 6.7819822 | Q77: =CommDemand!H9/0.38 -> 6.8979741 | R77: =CommDemand!I9/var_inflate2 -> 5.6237157 | S77: =CommDemand!J9/var_inflate2 -> 6.0976138 | T77: 0.42 | U77: =P77/($T77*$N77*$M77) -> 0.19430694 | V77: =Q77/($T77*$N77*$M77) -> 0.19763016 | W77: =R77/($T77*$N77*$M77) -> 0.16112206 | X77: =S77/($T77*$N77*$M77) -> 0.17469947 | Y77: =T77/($T77*$N77*$M77) -> 0.012033195
B78: R2,R3,R4,R5,R6 | C78: ILTT5BS | D78: ILT_LFL_T5_BS | E78: PJ, PJ/a | F78: INDELC | G78: ILT | H78: 2010 | I78: 15 | J78: 37.831863 | K78: 0.92700422 | L78: 0.18 | M78: 2.2578309 | N78: 31.536 | O78: 0.42 | P78: 0 | Q78: 0 | R78: 0 | S78: 0
B79: R2,R3,R4,R5,R6 | C79: ILTHIDLBBS | D79: ILT_HID_LB_BS | E79: PJ, PJ/a | F79: INDELC | G79: ILT | H79: 2010 | I79: 15 | J79: 67.16413 | K79: 1.5221882 | L79: 0.18 | M79: 1.0686643 | N79: 31.536 | O79: 0.42 | P79: 0 | Q79: 0 | R79: 0 | S79: 0
B80: R2,R3,R4,R5,R6 | C80: ILTHIDHBBS | D80: ILT_HID_HB_BS | E80: PJ, PJ/a | F80: INDELC | G80: ILT | H80: 2010 | I80: 15 | J80: 35.710601 | K80: 0.74297117 | L80: 0.18 | M80: 1.6043076 | N80: 31.536 | O80: 0.42 | P80: 0 | Q80: 0 | R80: 0 | S80: 0
B81: * OTHER
B82: R2,R3,R4,R5,R6 | C82: IOTELC10 | D82: Miscellaneous.ELC.BS.00 | E82: PJ, PJ/a | F82: INDELC | G82: IOTE | H82: 2010 | I82: 50 | J82: 0 | K82: 0 | L82: 0.15 | M82: 1 | N82: 31.536 | O82: 1 | P82: =DemandCalc!R6*CommDemand!G18 -> 2.5080083 | Q82: =DemandCalc!R14*CommDemand!H18 -> 2.0702543 | R82: =DemandCalc!R22*CommDemand!I18 -> 2.0586468 | S82: =DemandCalc!R30*CommDemand!J18 -> 2.2753107 | T82: =AVERAGE(T77,T56,T43,T22) -> 0.3275 | U82: =P82/($T82*$N82*$M82) -> 0.24283488 | V82: =Q82/($T82*$N82*$M82) -> 0.20044987 | W82: =R82/($T82*$N82*$M82) -> 0.19932599 | X82: =S82/($T82*$N82*$M82) -> 0.22030421 | Y82: =T82/($T82*$N82*$M82) -> 0.031709792
B83: R2,R3,R4,R5,R6 | C83: IOTELC110 | D83: Miscellaneous.ELC.BS1.00 | E83: PJ, PJ/a | F83: INDELC | G83: IOTF | H83: 2010 | I83: 50 | J83: 0 | K83: 0 | L83: 0.15 | M83: 1 | N83: 31.536 | O83: 1 | P83: 0 | Q83: 0 | R83: 0 | S83: 0 | T83: 0 | U83: 0 | V83: 0 | W83: 0 | X83: 0 | Y83: 0
B84: R2,R3,R4,R5,R6 | C84: IOTNGA10 | D84: Miscellaneous.NG.BS.00 | E84: PJ, PJ/a | F84: INDNGAEA | G84: IOTF | H84: 2010 | I84: 50 | J84: 0 | K84: 0 | L84: 0.15 | M84: 1 | O84: 1 | P84: =DemandCalc!R7*CommDemand!G18 -> 0.066242554 | Q84: =DemandCalc!R15*CommDemand!H18 -> 0.080416487 | R84: =DemandCalc!R23*CommDemand!I18 -> 0.079965611 | S84: =DemandCalc!R31*CommDemand!J18 -> 0.045435145 | T84: =AVERAGE(T58,T28) -> 0.36 | U84: =P84/($T84*$M84) -> 0.18400709 | V84: =Q84/($T84*$M84) -> 0.22337913 | W84: =R84/($T84*$M84) -> 0.2221267 | X84: =S84/($T84*$M84) -> 0.12620874 | Y84: =T84/($T84*$M84) -> 1
B85: R2,R3,R4,R5,R6 | C85: IOTDSL10 | D85: Miscellaneous.DSL.BS.00 | E85: PJ, PJ/a | F85: INDDSLEA | G85: IOTF | H85: 2010 | I85: 50 | J85: 0 | K85: 0 | L85: 0.15 | M85: 1 | O85: 1 | P85: =DemandCalc!R8*CommDemand!G18 -> 0.019515579 | Q85: =DemandCalc!R15*CommDemand!H18 -> 0.080416487 | R85: =DemandCalc!R24*CommDemand!I18 -> 0.012176197 | S85: =DemandCalc!R32*CommDemand!J18 -> 0.01128527 | T85: =AVERAGE(T62,T31) -> 0.36 | U85: =P85/($T85*$M85) -> 0.054209943 | V85: =Q85/($T85*$M85) -> 0.22337913 | W85: =R85/($T85*$M85) -> 0.033822769 | X85: =S85/($T85*$M85) -> 0.031347973 | Y85: =T85/($T85*$M85) -> 1

Sheet TechData
G3: *~FI_T
B4: Region | C4: TechName | D4: *TechDesc | E4: *Units | F4: CommIN | G4: CommOUT | H4: NCAP_START | I4: PRC_CAPACT | J4: NCAP_AF | K4: EFF
B5: =Technologies!#REF! -> #REF! | C5: =Technologies!#REF! -> #REF! | D5: =Technologies!#REF! -> #REF! | E5: PJ, PJ/a | F5: ELC | G5: INDELC | H5: 2010 | I5: 1 | J5: 1 | K5: 1
B6: *IND_DEM_FI_T_01
B7: *Source: ?
G9: *~FI_T
B10: Region | C10: TechName | D10: *TechDesc | E10: *Units | F10: CommIN | G10: CommOUT | H10: NCAP_START | I10: NCAP_TLIFE | J10: PRC_CAPACT | K10: NCAP_DRATE | L10: NCAP_COST | M10: NCAP_FOM | N10: PRC_RESID~R2~2010 | O10: PRC_RESID~R3~2010 | P10: PRC_RESID~R4~2010 | Q10: PRC_RESID~R5~2010 | R10: PRC_RESID~R6~2010 | S10: PRC_RESID~R2~2015 | T10: PRC_RESID~R3~2015 | U10: PRC_RESID~R4~2015 | V10: PRC_RESID~R5~2015 | W10: PRC_RESID~R6~2015 | X10: PRC_RESID~R2~2055 | Y10: PRC_RESID~R3~2055 | Z10: PRC_RESID~R4~2055 | AA10: PRC_RESID~R5~2055 | AB10: PRC_RESID~R6~2055 | AC10: NCAP_AF | AD10: NCAP_AF | AE10: EFF~2010 | AF10: EFF~2015 | AG10: EFF~2020 | AH10: EFF~2025 | AI10: EFF~2030 | AJ10: EFF~2035 | AK10: EFF~2040 | AL10: EFF~2045 | AM10: EFF~2050 | AN10: EFF~2055 | AO10: Share~UP~R2~2010 | AP10: Share~UP~R3~2010 | AQ10: Share~UP~R4~2010 | AR10: Share~UP~R5~2010 | AS10: Share~UP~R6~2010 | AT10: Share~UP~R2~2015 | AU10: Share~UP~R3~2015 | AV10: Share~UP~R4~2015 | AW10: Share~UP~R5~2015 | AX10: Share~UP~R6~2015 | AY10: Share~UP~R2~2055 | AZ10: Share~UP~R3~2055 | BA10: Share~UP~R4~2055 | BB10: Share~UP~R5~2055 | BC10: Share~UP~R6~2055 | BD10: Peak | BF10: Input~2010 | BG10: Input~2015 | BH10: Input~2020 | BI10: Input~2025 | BJ10: Input~2030 | BK10: Input~2035 | BL10: Input~2040 | BM10: Input~2045 | BN10: Input~2050 | BO10: Input~2055 | BP10: Output | BQ10: Output | BR10: Input | BS10: Output
B11: * Other | AY11: =IF(AT11="","",AT11) | AZ11: =IF(AU11="","",AU11) | BA11: =IF(AV11="","",AV11) | BB11: =IF(AW11="","",AW11) | BC11: =IF(AX11="","",AX11) | BG11: =IF(BF11="","",BF11)
B12: =Technologies!#REF! -> #REF! | C12: =Technologies!#REF! -> #REF! | D12: =Technologies!#REF! -> #REF! | E12: PJ, PJ/a | F12: INDELCOT | G12: IOTFAC | H12: 2010 | I12: 30 | J12: 1 | K12: 0.15 | L12: =IFERROR(IF(_xlfn.XLOOKUP(D12,tbl_tech[TECHNOLOGY - Other],tbl_tech[NCAP_COST])=0,"",_xlfn.XLOOKUP(D12,tbl_tech[TECHNOLOGY - Other],tbl_tech[NCAP_COST])),"") | M12: =IFERROR(IF(_xlfn.XLOOKUP(D12,tbl_tech[TECHNOLOGY - Other],tbl_tech[NCAP_FOM])=0,"",_xlfn.XLOOKUP(D12,tbl_tech[TECHNOLOGY - Other],tbl_tech[NCAP_FOM])),"") | N12: =N15-N14-N13 -> 4.5254731 | O12: =O15-O14-O13 -> 13.030741 | P12: =P15-P14-P13 -> 4.8681657 | Q12: =Q15-Q14-Q13 -> 10.955653 | R12: =R15-R14-R13 -> 1.1591278 | S12: =S15-S13-S14 -> 6.8078359 | T12: =T15-T13-T14 -> 17.821875 | U12: =U15-U13-U14 -> 6.9765783 | V12: =V15-V13-V14 -> 15.306989 | W12: =W15-W13-W14 -> 1.6851452 | X12: =X15-X14-X13 -> 0 | Y12: =Y15-Y14-Y13 -> 0 | Z12: =Z15-Z14-Z13 -> 0 | AA12: =AA15-AA14-AA13 -> 0 | AB12: =AB15-AB14-AB13 -> 0 | AC12: 1 | AE12: =IF(BF12="","",$BP12/BF12) -> 1 | AF12: =IF(BG12="","",$BP12/BG12) -> 1 | AG12: =IF(BH12="","",$BP12/BH12) -> 1.0944772 | AH12: =IF(BI12="","",$BP12/BI12) -> 1.1900789 | AI12: =IF(BJ12="","",$BP12/BJ12) -> 1.3017774 | AJ12: =IF(BK12="","",$BP12/BK12) -> 1.4111348 | AK12: =IF(BL12="","",$BP12/BL12) -> 1.5095043 | AL12: =IF(BM12="","",$BP12/BM12) -> 1.5083436 | ... AN12: =IF(BO12="","",$BP12/BO12) -> 1.606141 | AY12: =IF(AT12="","",AT12) | AZ12: =IF(AU12="","",AU12) | BA12: =IF(AV12="","",AV12) | BB12: =IF(AW12="","",AW12) | BC12: =IF(AX12="","",AX12) | BF12: 1 | BG12: =IF(BF12="","",BF12) -> 1 | BH12: ='Demand (old)'!G$137 -> 0.91367821 | BI12: ='Demand (old)'!H$137 -> 0.84028046 | BJ12: ='Demand (old)'!I$137 -> 0.7681805 | BK12: ='Demand (old)'!J$137 -> 0.70864954 | BL12: ='Demand (old)'!K$137 -> 0.66246912 | BM12: ='Demand (old)'!L$137 -> 0.66297892 | BN12: ='Demand (old)'!M$137 -> 0.64131463 | BO12: ='Demand (old)'!N$137 -> 0.62261036 | BP12: 1
B13: =Technologies!#REF! -> #REF! | C13: =Technologies!#REF! -> #REF! | D13: =Technologies!#REF! -> #REF! | E13: PJ, PJ/a | F13: INDRFLEA | G13: IOTFAC | H13: 2010 | I13: 30 | J13: 1 | K13: 0.15 | L13: =IFERROR(IF(_xlfn.XLOOKUP(D13,tbl_tech[TECHNOLOGY - Other],tbl_tech[NCAP_COST])=0,"",_xlfn.XLOOKUP(D13,tbl_tech[TECHNOLOGY - Other],tbl_tech[NCAP_COST])),"") | M13: =IFERROR(IF(_xlfn.XLOOKUP(D13,tbl_tech[TECHNOLOGY - Other],tbl_tech[NCAP_FOM])=0,"",_xlfn.XLOOKUP(D13,tbl_tech[TECHNOLOGY - Other],tbl_tech[NCAP_FOM])),"") | N13: =N$15/$AE$15*AO$20*'NYC 2010'!$CS$16*1.1 -> 0.6082229 | O13: =O$15/$AE$15*AP$20*'NYC 2010'!$CS$16*1.1 -> 1.7513296 | P13: =P$15/$AE$15*AQ$20*'NYC 2010'!$CS$16*1.1 -> 0.65428074 | Q13: =Q$15/$AE$15*AR$20*'NYC 2010'!$CS$16*1.1 -> 1.4724382 | R13: =R$15/$AE$15*AS$20*'NYC 2010'!$CS$16*1.1 -> 0.1557866 | S13: =S$15/$AE$15*AT$20*0.0315701442609241 -> 0.29556734 | T13: =T$15/$AE$15*AU$20*0.0315664085765336 -> 0.77359488 | U13: =U$15/$AE$15*AV$20*0.0318725099601594 -> 0.30582261 | V13: =V$15/$AE$15*AW$20*0.0315575161180862 -> 0.66427903 | W13: =W$15/$AE$15*AX$20*0.032258064516129 -> 0.074767533 | X13: =X$15/$AE$15*AY$20*'NYC 2010'!$CS$16*1.1 -> 0 | Y13: =Y$15/$AE$15*AZ$20*'NYC 2010'!$CS$16*1.1 -> 0 | Z13: =Z$15/$AE$15*BA$20*'NYC 2010'!$CS$16*1.1 -> 0 | AA13: =AA$15/$AE$15*BB$20*'NYC 2010'!$CS$16*1.1 -> 0 | AB13: =AB$15/$AE$15*BC$20*'NYC 2010'!$CS$16*1.1 -> 0 | AC13: 1 | AE13: =IF(BF13="","",$BP13/BF13) -> 1 | AF13: =IF(BG13="","",$BP13/BG13) -> 1 | AG13: =IF(BH13="","",$BP13/BH13) -> 1.0944772 | AH13: =IF(BI13="","",$BP13/BI13) -> 1.1900789 | AI13: =IF(BJ13="","",$BP13/BJ13) -> 1.3017774 | AJ13: =IF(BK13="","",$BP13/BK13) -> 1.4111348 | AK13: =IF(BL13="","",$BP13/BL13) -> 1.5095043 | AL13: =IF(BM13="","",$BP13/BM13) -> 1.5083436 | ... AN13: =IF(BO13="","",$BP13/BO13) -> 1.606141 | AY13: =IF(AT13="","",AT13) | AZ13: =IF(AU13="","",AU13) | BA13: =IF(AV13="","",AV13) | BB13: =IF(AW13="","",AW13) | BC13: =IF(AX13="","",AX13) | BF13: 1 | BG13: =IF(BF13="","",BF13) -> 1 | BH13: ='Demand (old)'!G$137 -> 0.91367821 | BI13: ='Demand (old)'!H$137 -> 0.84028046 | BJ13: ='Demand (old)'!I$137 -> 0.7681805 | BK13: ='Demand (old)'!J$137 -> 0.70864954 | BL13: ='Demand (old)'!K$137 -> 0.66246912 | BM13: ='Demand (old)'!L$137 -> 0.66297892 | BN13: ='Demand (old)'!M$137 -> 0.64131463 | BO13: ='Demand (old)'!N$137 -> 0.62261036 | BP13: 1
B14: =Technologies!#REF! -> #REF! | C14: =Technologies!#REF! -> #REF! | D14: =Technologies!#REF! -> #REF! | E14: PJ, PJ/a | F14: INDNGAEA | G14: IOTFAC | H14: 2010 | I14: 30 | J14: 1 | K14: 0.15 | L14: =IFERROR(IF(_xlfn.XLOOKUP(D14,tbl_tech[TECHNOLOGY - Other],tbl_tech[NCAP_COST])=0,"",_xlfn.XLOOKUP(D14,tbl_tech[TECHNOLOGY - Other],tbl_tech[NCAP_COST])),"") | M14: =IFERROR(IF(_xlfn.XLOOKUP(D14,tbl_tech[TECHNOLOGY - Other],tbl_tech[NCAP_FOM])=0,"",_xlfn.XLOOKUP(D14,tbl_tech[TECHNOLOGY - Other],tbl_tech[NCAP_FOM])),"") | N14: =N$15/$AE$15*AO$20*'NYC 2010'!$CS$18*1.1 -> 3.1754841 | O14: =O$15/$AE$15*AP$20*'NYC 2010'!$CS$18*1.1 -> 9.1435545 | P14: =P$15/$AE$15*AQ$20*'NYC 2010'!$CS$18*1.1 -> 3.4159484 | Q14: =Q$15/$AE$15*AR$20*'NYC 2010'!$CS$18*1.1 -> 7.6874841 | R14: =R$15/$AE$15*AS$20*'NYC 2010'!$CS$18*1.1 -> 0.81334961 | S14: =S$15/$AE$15*AT$20*0.241271168722559 -> 2.2588392 | T14: =T$15/$AE$15*AU$20*0.241215008933889 -> 5.9114326 | U14: =U$15/$AE$15*AV$20*0.241035856573705 -> 2.3127835 | V14: =V$15/$AE$15*AW$20*0.241262300644723 -> 5.0785203 | W14: =W$15/$AE$15*AX$20*0.240694789081886 -> 0.55788082 | X14: =X$15/$AE$15*AY$20*'NYC 2010'!$CS$18*1.1 -> 0 | Y14: =Y$15/$AE$15*AZ$20*'NYC 2010'!$CS$18*1.1 -> 0 | Z14: =Z$15/$AE$15*BA$20*'NYC 2010'!$CS$18*1.1 -> 0 | AA14: =AA$15/$AE$15*BB$20*'NYC 2010'!$CS$18*1.1 -> 0 | AB14: =AB$15/$AE$15*BC$20*'NYC 2010'!$CS$18*1.1 -> 0 | AC14: 1 | AE14: =IF(BF14="","",$BP14/BF14) -> 1 | AF14: =IF(BG14="","",$BP14/BG14) -> 1 | AG14: =IF(BH14="","",$BP14/BH14) -> 1.0944772 | AH14: =IF(BI14="","",$BP14/BI14) -> 1.1900789 | AI14: =IF(BJ14="","",$BP14/BJ14) -> 1.3017774 | AJ14: =IF(BK14="","",$BP14/BK14) -> 1.4111348 | AK14: =IF(BL14="","",$BP14/BL14) -> 1.5095043 | AL14: =IF(BM14="","",$BP14/BM14) -> 1.5083436 | ... AN14: =IF(BO14="","",$BP14/BO14) -> 1.606141 | AY14: =IF(AT14="","",AT14) | AZ14: =IF(AU14="","",AU14) | BA14: =IF(AV14="","",AV14) | BB14: =IF(AW14="","",AW14) | BC14: =IF(AX14="","",AX14) | BF14: 1 | BG14: =IF(BF14="","",BF14) -> 1 | BH14: ='Demand (old)'!G$137 -> 0.91367821 | BI14: ='Demand (old)'!H$137 -> 0.84028046 | BJ14: ='Demand (old)'!I$137 -> 0.7681805 | BK14: ='Demand (old)'!J$137 -> 0.70864954 | BL14: ='Demand (old)'!K$137 -> 0.66246912 | BM14: ='Demand (old)'!L$137 -> 0.66297892 | BN14: ='Demand (old)'!M$137 -> 0.64131463 | BO14: ='Demand (old)'!N$137 -> 0.62261036 | BP14: 1
B15: =Technologies!#REF! -> #REF! | C15: =Technologies!#REF! -> #REF! | D15: =Technologies!#REF! -> #REF! | E15: PJ, PJ/a | F15: IOTFEED | H15: 2010 | I15: 50 | J15: 1 | L15: =IFERROR(IF(_xlfn.XLOOKUP(D15,tbl_tech[TECHNOLOGY - Other],tbl_tech[NCAP_COST])=0,"",_xlfn.XLOOKUP(D15,tbl_tech[TECHNOLOGY - Other],tbl_tech[NCAP_COST])),"") | M15: =IFERROR(IF(_xlfn.XLOOKUP(D15,tbl_tech[TECHNOLOGY - Other],tbl_tech[NCAP_FOM])=0,"",_xlfn.XLOOKUP(D15,tbl_tech[TECHNOLOGY - Other],tbl_tech[NCAP_FOM])),"") | N15: =NYCIND_DMD!D53/$J$15 -> 8.30918 | O15: =NYCIND_DMD!D54/$J$15 -> 23.925625 | P15: =NYCIND_DMD!D55/$J$15 -> 8.9383948 | Q15: =NYCIND_DMD!D56/$J$15 -> 20.115576 | R15: =NYCIND_DMD!D57/$J$15 -> 2.128264 | S15: =NYCIND_DMD!E53/$J$15 -> 9.3622424 | T15: =NYCIND_DMD!E54/$J$15 -> 24.506902 | U15: =NYCIND_DMD!E55/$J$15 -> 9.5951843 | V15: =NYCIND_DMD!E56/$J$15 -> 21.049788 | W15: =NYCIND_DMD!E57/$J$15 -> 2.3177935 | X15: 0 | Y15: 0 | Z15: 0 | AA15: 0 | AB15: 0 | AC15: 1 | AE15: 1 | AN15: =AE15 -> 1 | AO15: 0 | AP15: 0 | AQ15: 0 | AR15: 0 | AS15: 0 | AT15: 0 | AU15: 0 | AV15: 0 | AW15: 0 | AX15: 0 | AY15: =IF(AT15="","",AT15) -> 0 | AZ15: =IF(AU15="","",AU15) -> 0 | BA15: =IF(AV15="","",AV15) -> 0 | BB15: =IF(AW15="","",AW15) -> 0 | BC15: =IF(AX15="","",AX15) -> 0 | BG15: =IF(BF15="","",BF15) | BP15: 1
B16: R2,R3,R4,R5,R6 | F16: IOTSTM | L16: =IFERROR(IF(_xlfn.XLOOKUP(D16,tbl_tech[TECHNOLOGY - Other],tbl_tech[NCAP_COST])=0,"",_xlfn.XLOOKUP(D16,tbl_tech[TECHNOLOGY - Other],tbl_tech[NCAP_COST])),"") | M16: =IFERROR(IF(_xlfn.XLOOKUP(D16,tbl_tech[TECHNOLOGY - Other],tbl_tech[NCAP_FOM])=0,"",_xlfn.XLOOKUP(D16,tbl_tech[TECHNOLOGY - Other],tbl_tech[NCAP_FOM])),"") | AO16: 0 | AP16: 0 | AQ16: 0 | AR16: 0 | AS16: 0 | AT16: 0 | AU16: 0 | AV16: 0 | AW16: 0 | AX16: 0 | AY16: =IF(AT16="","",AT16) -> 0 | AZ16: =IF(AU16="","",AU16) -> 0 | BA16: =IF(AV16="","",AV16) -> 0 | BB16: =IF(AW16="","",AW16) -> 0 | BC16: =IF(AX16="","",AX16) -> 0 | BG16: =IF(BF16="","",BF16)
B17: R2,R3,R4,R5,R6 | F17: IOTETC | L17: =IFERROR(IF(_xlfn.XLOOKUP(D17,tbl_tech[TECHNOLOGY - Other],tbl_tech[NCAP_COST])=0,"",_xlfn.XLOOKUP(D17,tbl_tech[TECHNOLOGY - Other],tbl_tech[NCAP_COST])),"") | M17: =IFERROR(IF(_xlfn.XLOOKUP(D17,tbl_tech[TECHNOLOGY - Other],tbl_tech[NCAP_FOM])=0,"",_xlfn.XLOOKUP(D17,tbl_tech[TECHNOLOGY - Other],tbl_tech[NCAP_FOM])),"") | AO17: 0 | AP17: 0 | AQ17: 0 | AR17: 0 | AS17: 0 | AT17: 0 | AU17: 0 | AV17: 0 | AW17: 0 | AX17: 0 | AY17: =IF(AT17="","",AT17) -> 0 | AZ17: =IF(AU17="","",AU17) -> 0 | BA17: =IF(AV17="","",AV17) -> 0 | BB17: =IF(AW17="","",AW17) -> 0 | BC17: =IF(AX17="","",AX17) -> 0 | BG17: =IF(BF17="","",BF17)
B18: R2,R3,R4,R5,R6 | F18: IOTPRH | L18: =IFERROR(IF(_xlfn.XLOOKUP(D18,tbl_tech[TECHNOLOGY - Other],tbl_tech[NCAP_COST])=0,"",_xlfn.XLOOKUP(D18,tbl_tech[TECHNOLOGY - Other],tbl_tech[NCAP_COST])),"") | M18: =IFERROR(IF(_xlfn.XLOOKUP(D18,tbl_tech[TECHNOLOGY - Other],tbl_tech[NCAP_FOM])=0,"",_xlfn.XLOOKUP(D18,tbl_tech[TECHNOLOGY - Other],tbl_tech[NCAP_FOM])),"") | AO18: 0 | AP18: 0 | AQ18: 0 | AR18: 0 | AS18: 0 | AT18: 0 | AU18: 0 | AV18: 0 | AW18: 0 | AX18: 0 | AY18: =IF(AT18="","",AT18) -> 0 | AZ18: =IF(AU18="","",AU18) -> 0 | BA18: =IF(AV18="","",AV18) -> 0 | BB18: =IF(AW18="","",AW18) -> 0 | BC18: =IF(AX18="","",AX18) -> 0 | BG18: =IF(BF18="","",BF18)
B19: R2,R3,R4,R5,R6 | F19: IOTMDR | L19: =IFERROR(IF(_xlfn.XLOOKUP(D19,tbl_tech[TECHNOLOGY - Other],tbl_tech[NCAP_COST])=0,"",_xlfn.XLOOKUP(D19,tbl_tech[TECHNOLOGY - Other],tbl_tech[NCAP_COST])),"") | M19: =IFERROR(IF(_xlfn.XLOOKUP(D19,tbl_tech[TECHNOLOGY - Other],tbl_tech[NCAP_FOM])=0,"",_xlfn.XLOOKUP(D19,tbl_tech[TECHNOLOGY - Other],tbl_tech[NCAP_FOM])),"") | AO19: 0 | AP19: 0 | AQ19: 0 | AR19: 0 | AS19: 0 | AT19: 0 | AU19: 0 | AV19: 0 | AW19: 0 | AX19: 0 | AY19: =IF(AT19="","",AT19) -> 0 | AZ19: =IF(AU19="","",AU19) -> 0 | BA19: =IF(AV19="","",AV19) -> 0 | BB19: =IF(AW19="","",AW19) -> 0 | BC19: =IF(AX19="","",AX19) -> 0 | BG19: =IF(BF19="","",BF19)
B20: R2,R3,R4,R5,R6 | F20: IOTFAC | L20: =IFERROR(IF(_xlfn.XLOOKUP(D20,tbl_tech[TECHNOLOGY - Other],tbl_tech[NCAP_COST])=0,"",_xlfn.XLOOKUP(D20,tbl_tech[TECHNOLOGY - Other],tbl_tech[NCAP_COST])),"") | M20: =IFERROR(IF(_xlfn.XLOOKUP(D20,tbl_tech[TECHNOLOGY - Other],tbl_tech[NCAP_FOM])=0,"",_xlfn.XLOOKUP(D20,tbl_tech[TECHNOLOGY - Other],tbl_tech[NCAP_FOM])),"") | AO20: =1-AO19 -> 1 | AP20: =1-AP19 -> 1 | AQ20: =1-AQ19 -> 1 | AR20: =1-AR19 -> 1 | AS20: =1-AS19 -> 1 | AT20: =1-AT19 -> 1 | AU20: =1-AU19 -> 1 | AV20: =1-AV19 -> 1 | ... AX20: =1-AX19 -> 1 | AY20: =IF(AT20="","",AT20) -> 1 | AZ20: =IF(AU20="","",AU20) -> 1 | BA20: =IF(AV20="","",AV20) -> 1 | BB20: =IF(AW20="","",AW20) -> 1 | BC20: =IF(AX20="","",AX20) -> 1 | BG20: =IF(BF20="","",BF20)
B21: R2,R3,R4,R5,R6 | F21: IOTOHT | L21: =IFERROR(IF(_xlfn.XLOOKUP(D21,tbl_tech[TECHNOLOGY - Other],tbl_tech[NCAP_COST])=0,"",_xlfn.XLOOKUP(D21,tbl_tech[TECHNOLOGY - Other],tbl_tech[NCAP_COST])),"") | M21: =IFERROR(IF(_xlfn.XLOOKUP(D21,tbl_tech[TECHNOLOGY - Other],tbl_tech[NCAP_FOM])=0,"",_xlfn.XLOOKUP(D21,tbl_tech[TECHNOLOGY - Other],tbl_tech[NCAP_FOM])),"") | AO21: 0 | AP21: 0 | AQ21: 0 | AR21: 0 | AS21: 0 | AT21: 0 | AU21: 0 | AV21: 0 | AW21: 0 | AX21: 0 | AY21: =IF(AT21="","",AT21) -> 0 | AZ21: =IF(AU21="","",AU21) -> 0 | BA21: =IF(AV21="","",AV21) -> 0 | BB21: =IF(AW21="","",AW21) -> 0 | BC21: =IF(AX21="","",AX21) -> 0 | BG21: =IF(BF21="","",BF21)
B22: R2,R3,R4,R5,R6 | G22: IOT | L22: =IFERROR(IF(_xlfn.XLOOKUP(D22,tbl_tech[TECHNOLOGY - Other],tbl_tech[NCAP_COST])=0,"",_xlfn.XLOOKUP(D22,tbl_tech[TECHNOLOGY - Other],tbl_tech[NCAP_COST])),"") | M22: =IFERROR(IF(_xlfn.XLOOKUP(D22,tbl_tech[TECHNOLOGY - Other],tbl_tech[NCAP_FOM])=0,"",_xlfn.XLOOKUP(D22,tbl_tech[TECHNOLOGY - Other],tbl_tech[NCAP_FOM])),"") | AY22: =IF(AT22="","",AT22) | AZ22: =IF(AU22="","",AU22) | BA22: =IF(AV22="","",AV22) | BB22: =IF(AW22="","",AW22) | BC22: =IF(AX22="","",AX22) | BG22: =IF(BF22="","",BF22)
B23: *IND_DEM_FI_T_02
B24: *Source: ? | C24: IND_COST
G26: *~FI_T
B27: Region | C27: TechName | D27: *TechDesc | E27: *Units | F27: CommIN | G27: CommOUT | H27: NCAP_START | I27: NCAP_TLIFE | J27: Share~UP | K27: EFF | L27: NCAP_AF | M27: ACT_COST | N27: COST
B28: =Technologies!#REF! -> #REF! | C28: =Technologies!#REF! -> #REF! | D28: =Technologies!#REF! -> #REF! | E28: PJ, PJ/a | F28: INDELC | G28: INDELCOT | H28: 2010 | I28: 50 | K28: 1 | L28: 1
B29: =Technologies!B6 -> R2,R3,R4,R5,R6 | C29: =Technologies!D6 -> SEINDNGA | D29: =Technologies!E6 -> Emissions: NGA to IND | E29: PJ, PJ/a | F29: INDNGA | G29: INDNGAEA | H29: 2010 | I29: 50 | K29: 1
B30: =Technologies!#REF! -> #REF! | C30: =Technologies!#REF! -> #REF! | D30: =Technologies!#REF! -> #REF! | E30: PJ, PJ/a | F30: INDRFL | G30: INDRFLEA | H30: 2010 | I30: 50 | K30: 1
B31: =Technologies!B7 -> R2,R3,R4,R5,R6 | C31: =Technologies!D7 -> SEINDDSL | D31: =Technologies!E7 -> Emissions: DSL to IND | E31: PJ, PJ/a | F31: INDDSL | G31: INDDSLEA | H31: 2010 | I31: 50 | K31: 1
B32: R2,R3,R4,R5,R6 | C32: ZZDMYIOTFC | D32: Dummy backstop for Other Industry Facilities | E32: PJ, PJ/a | F32: ZZDMY | G32: IOTFAC | K32: 1 | M32: 9999
B33: R2,R3,R4,R5,R6 | C33: ZZDMYIOT | D33: Dummy backstop for Other Industry DMDand | E33: PJ, PJ/a | F33: ZZDMY | G33: IOT | K33: 1 | M33: 9999
B34: R2,R3,R4,R5,R6 | C34: ZZINDELC | D34: Dummy backstop for INDELC | E34: PJ, PJ/a | G34: INDELC | N34: 9000
B35: R2,R3,R4,R5,R6 | C35: ZZINDNGAEA | D35: Dummy backstop for INDNGAEA | E35: PJ, PJ/a | G35: INDNGAEA | N35: 9000
B36: R2,R3,R4,R5,R6 | C36: ZZINDRFLEA | D36: Dummy backstop for INDRFLEA | E36: PJ, PJ/a | G36: INDRFLEA | N36: 9000
B37: *IND_DEM_FI_T_03
B38: *Source: ? | AZ38: -->
AZ39: not read into veda
G40: *~FI_T
B41: Region | C41: TechName | D41: *TechDesc | E41: *Units | F41: *CommIN | G41: *CommOUT | H41: *NCAP_START | I41: *NCAP_TLIFE | J41: ENV_ACT~CO2 | K41: ENV_ACT~CH4 | L41: ENV_ACT~N2O | M41: ENV_ACT~BC | N41: ENV_ACT~OC | O41: ENV_ACT~CO2I | P41: ENV_ACT~NOX~2010 | Q41: ENV_ACT~NOX~2015 | R41: ENV_ACT~NOX~2020 | S41: ENV_ACT~NOX~2055 | T41: ENV_ACT~SO2~2010 | U41: ENV_ACT~SO2~2015 | V41: ENV_ACT~SO2~2020 | W41: ENV_ACT~SO2~2055 | X41: ENV_ACT~PM10~2010 | Y41: ENV_ACT~PM10~2015 | Z41: ENV_ACT~PM10~2020 | AA41: ENV_ACT~PM10~2055 | AB41: ENV_ACT~PM25~2010 | AC41: ENV_ACT~PM25~2015 | AD41: ENV_ACT~PM25~2020 | AE41: ENV_ACT~PM25~2055 | AF41: ENV_ACT~VOC~2010 | AG41: ENV_ACT~VOC~2015 | AH41: ENV_ACT~VOC~2020 | AI41: ENV_ACT~VOC~2055 | AJ41: ENV_ACT~CO~2010 | AK41: ENV_ACT~CO~2015 | AL41: ENV_ACT~CO~2020 | AM41: ENV_ACT~CO~2055 | AN41: ENV_ACT~NOXI~2010 | AO41: ENV_ACT~NOXI~2015 | AP41: ENV_ACT~NOXI~2020 | AQ41: ENV_ACT~NOXI~2055 | AR41: ENV_ACT~SO2I~2010 | AS41: ENV_ACT~SO2I~2015 | AT41: ENV_ACT~SO2I~2020 | AU41: ENV_ACT~SO2I~2055 | AV41: ENV_ACT~PM10I~2010 | AW41: ENV_ACT~PM10I~2015 | AX41: ENV_ACT~PM10I~2020 | AY41: ENV_ACT~PM10I~2055 | AZ41: ENV_ACT~NOXDICB~2010 | BA41: ENV_ACT~NOXDICB~2015 | BB41: ENV_ACT~NOXDICB~2020 | BC41: ENV_ACT~NOXDICB~2055 | BD41: ENV_ACT~NOXDIGB~2010 | BE41: ENV_ACT~NOXDIGB~2015 | BF41: ENV_ACT~NOXDIGB~2020 | BG41: ENV_ACT~NOXDIGB~2055 | BH41: ENV_ACT~NOXDIDB~2010 | BI41: ENV_ACT~NOXDIDB~2015 | BJ41: ENV_ACT~NOXDIDB~2020 | BK41: ENV_ACT~NOXDIDB~2055 | BL41: ENV_ACT~NOXDIRB~2010 | BM41: ENV_ACT~NOXDIRB~2015 | BN41: ENV_ACT~NOXDIRB~2020 | BO41: ENV_ACT~NOXDIRB~2055 | BP41: ENV_ACT~NOXDILB~2010 | BQ41: ENV_ACT~NOXDILB~2015 | BR41: ENV_ACT~NOXDILB~2020 | BS41: ENV_ACT~NOXDILB~2055 | BT41: ENV_ACT~NOXDIOB~2010 | BU41: ENV_ACT~NOXDIOB~2015 | BV41: ENV_ACT~NOXDIOB~2020 | BW41: ENV_ACT~NOXDIOB~2055 | BX41: ENV_ACT~NOXDIGT~2010 | BY41: ENV_ACT~NOXDIGT~2015 | BZ41: ENV_ACT~NOXDIGT~2020 | CA41: ENV_ACT~NOXDIGT~2055 | CB41: ENV_ACT~NOXDIDT~2010 | CC41: ENV_ACT~NOXDIDT~2015 | CD41: ENV_ACT~NOXDIDT~2020 | CE41: ENV_ACT~NOXDIDT~2055 | CF41: ENV_ACT~NOXDIOT~2010 | CG41: ENV_ACT~NOXDIOT~2015 | CH41: ENV_ACT~NOXDIOT~2020 | CI41: ENV_ACT~NOXDIOT~2055 | CJ41: ENV_ACT~NOXDIGE~2010 | CK41: ENV_ACT~NOXDIGE~2015 | CL41: ENV_ACT~NOXDIGE~2020 | CM41: ENV_ACT~NOXDIGE~2055 | CN41: ENV_ACT~NOXDIDE~2010 | CO41: ENV_ACT~NOXDIDE~2015 | CP41: ENV_ACT~NOXDIDE~2020 | CQ41: ENV_ACT~NOXDIDE~2055 | CR41: ENV_ACT~NOXDICE~2010 | CS41: ENV_ACT~NOXDICE~2015 | CT41: ENV_ACT~NOXDICE~2020 | CU41: ENV_ACT~NOXDICE~2055 | CV41: ENV_ACT~NOXDIOE~2010 | CW41: ENV_ACT~NOXDIOE~2015 | CX41: ENV_ACT~NOXDIOE~2020 | CY41: ENV_ACT~NOXDIOE~2055 | CZ41: ENV_ACT~NOXDICPH~2010 | DA41: ENV_ACT~NOXDICPH~2015 | DB41: ENV_ACT~NOXDICPH~2020 | DC41: ENV_ACT~NOXDICPH~2055 | DD41: ENV_ACT~NOXDIGPH~2010 | DE41: ENV_ACT~NOXDIGPH~2015 | DF41: ENV_ACT~NOXDIGPH~2020 | DG41: ENV_ACT~NOXDIGPH~2055 | DH41: ENV_ACT~NOXDIDPH~2010 | DI41: ENV_ACT~NOXDIDPH~2015 | DJ41: ENV_ACT~NOXDIDPH~2020 | DK41: ENV_ACT~NOXDIDPH~2055 | DL41: ENV_ACT~NOXDIRPH~2010 | DM41: ENV_ACT~NOXDIRPH~2015 | DN41: ENV_ACT~NOXDIRPH~2020 | DO41: ENV_ACT~NOXDIRPH~2055 | DP41: ENV_ACT~NOXDIOPH~2010 | DQ41: ENV_ACT~NOXDIOPH~2015 | DR41: ENV_ACT~NOXDIOPH~2020 | DS41: ENV_ACT~NOXDIOPH~2055 | DT41: ENV_ACT~NOXDIFAC~2010 | DU41: ENV_ACT~NOXDIFAC~2015 | DV41: ENV_ACT~NOXDIFAC~2020 | DW41: ENV_ACT~NOXDIFAC~2055 | DX41: ENV_ACT~NOXDIOH~2010 | DY41: ENV_ACT~NOXDIOH~2015 | DZ41: ENV_ACT~NOXDIOH~2020 | EA41: ENV_ACT~NOXDIOH~2055 | EB41: ENV_ACT~NOXDICOK~2010 | EC41: ENV_ACT~NOXDICOK~2015 | ED41: ENV_ACT~NOXDICOK~2020 | EE41: ENV_ACT~NOXDICOK~2055
B42: R2,R3,R4,R5,R6 | C42: IOTEFACRFL | D42: Other Industry Residual Oil Facilities | E42: PJ, PJ/a | F42: INDRFLEA | G42: IOTFAC | J42: 0.0831 | K42: =Emissions!AC$42 -> 0.00284 | L42: =Emissions!AD$42 -> 0.000284 | M42: =Emissions!AE$42 -> 0.025494307 | N42: =Emissions!AF$42 -> 0.006883463 | O42: =J42*1000 -> 83.1 | P42: =Emissions!F$42 -> 0.83858254 | Q42: =Emissions!G$42 -> 0.83858254 | R42: =Emissions!H$42 -> 0.83858254 | S42: =IF(R42="","",R42) -> 0.83858254 | T42: =Emissions!J$42 -> 0.23453782 | U42: =Emissions!K$42 -> 0.23453782 | V42: =Emissions!L$42 -> 0.23453782 | W42: =IF(V42="","",V42) -> 0.23453782 | X42: =Emissions!N$42 -> 0.084981025 | Y42: =Emissions!O$42 -> 0.084981025 | Z42: =Emissions!P$42 -> 0.084981025 | AA42: =IF(Z42="","",Z42) -> 0.084981025 | AB42: =Emissions!R$42 -> 0.076482922 | AC42: =Emissions!S$42 -> 0.076482922 | AD42: =Emissions!T$42 -> 0.076482922 | AE42: =IF(AD42="","",AD42) -> 0.076482922 | AF42: =Emissions!V$42 -> 0.093519924 | AG42: =Emissions!W$42 -> 0.093519924 | AH42: =Emissions!X$42 -> 0.093519924 | AI42: =IF(AH42="","",AH42) -> 0.093519924 | AJ42: =Emissions!Z$42 -> 0.34250095 | AK42: =Emissions!AA$42 -> 0.34250095 | AL42: =Emissions!AB$42 -> 0.34250095 | AM42: =IF(AL42="","",AL42) -> 0.34250095 | AN42: =P42 -> 0.83858254 | AO42: =Q42 -> 0.83858254 | AP42: =R42 -> 0.83858254 | AQ42: =IF(AP42="","",AP42) -> 0.83858254 | AR42: =T42 -> 0.23453782 | AS42: =U42 -> 0.23453782 | AT42: =V42 -> 0.23453782 | AU42: =IF(AT42="","",AT42) -> 0.23453782 | AV42: =X42 -> 0.084981025 | AW42: =Y42 -> 0.084981025 | AX42: =Z42 -> 0.084981025 | AY42: =IF(AX42="","",AX42) -> 0.084981025 | DT42: =P42 -> 0.83858254 | DU42: =Q42 -> 0.83858254 | DV42: =R42 -> 0.83858254 | DW42: =IF(DV42="","",DV42) -> 0.83858254
B43: R2,R3,R4,R5,R6 | C43: IOTEFACNGA | D43: Other Industry Natural Gas Facilities | E43: PJ, PJ/a | F43: INDNGAEA | G43: IOTFAC | J43: 0.056 | K43: =Emissions!AC$39 -> 0.00085303541 | L43: =Emissions!AD$39 -> 0.00085303541 | M43: =Emissions!AE$39 -> 0.0036351067 | N43: =Emissions!AF$39 -> 0.0007633724 | O43: =J43*1000 -> 56 | P43: =Emissions!F$39 -> 0.041627634 | Q43: =Emissions!G$39 -> 0.041627636 | R43: =Emissions!H$39 -> 0.041627637 | S43: =IF(R43="","",R43) -> 0.041627637 | T43: =Emissions!J$39 -> 0.041773357 | U43: =Emissions!K$39 -> 0.041776205 | V43: =Emissions!L$39 -> 0.041779052 | W43: =IF(V43="","",V43) -> 0.041779052 | X43: =Emissions!N$39 -> 0.041759982 | Y43: =Emissions!O$39 -> 0.041758168 | Z43: =Emissions!P$39 -> 0.041756354 | AA43: =IF(Z43="","",Z43) -> 0.041756354 | AB43: =Emissions!R$39 -> 0.041772152 | AC43: =Emissions!S$39 -> 0.041770304 | AD43: =Emissions!T$39 -> 0.041768456 | AE43: =IF(AD43="","",AD43) -> 0.041768456 | AF43: =Emissions!V$39 -> 0.041772719 | AG43: =Emissions!W$39 -> 0.041772804 | AH43: =Emissions!X$39 -> 0.041772888 | AI43: =IF(AH43="","",AH43) -> 0.041772888 | AJ43: =Emissions!Z$39 -> 0.041782823 | AK43: =Emissions!AA$39 -> 0.04178284 | AL43: =Emissions!AB$39 -> 0.041782856 | AM43: =IF(AL43="","",AL43) -> 0.041782856 | AN43: =P43 -> 0.041627634 | AO43: =Q43 -> 0.041627636 | AP43: =R43 -> 0.041627637 | AQ43: =IF(AP43="","",AP43) -> 0.041627637 | AR43: =T43 -> 0.041773357 | AS43: =U43 -> 0.041776205 | AT43: =V43 -> 0.041779052 | AU43: =IF(AT43="","",AT43) -> 0.041779052 | AV43: =X43 -> 0.041759982 | AW43: =Y43 -> 0.041758168 | AX43: =Z43 -> 0.041756354 | AY43: =IF(AX43="","",AX43) -> 0.041756354 | DT43: =P43 -> 0.041627634 | DU43: =Q43 -> 0.041627636 | DV43: =R43 -> 0.041627637 | DW43: =IF(DV43="","",DV43) -> 0.041627637
B44: =Technologies!B6 -> R2,R3,R4,R5,R6 | C44: =Technologies!D6 -> SEINDNGA | D44: =Technologies!E6 -> Emissions: NGA to IND | E44: PJ, PJ/a | F44: INDNGA | G44: INDNGAEA | H44: 2010 | I44: 50 | J44: 0.056 | K44: 0.00085303541 | L44: 0.00085303541 | M44: 0.00018956357 | N44: 0.00031593928 | O44: 56 | P44: 0.058533344 | Q44: 0.058533344 | R44: 0.058533344 | S44: 0.058533344 | T44: 0.00025069701 | U44: 0.00025069701 | V44: 0.00025069701 | W44: 0.00025069701 | X44: 0.0031593928 | Y44: 0.0031593928 | Z44: 0.0031593928 | AA44: 0.0031593928 | AB44: 0.0031593928 | AC44: 0.0031593928 | AD44: 0.0031593928 | AE44: 0.0031593928 | AF44: 0.0022144903 | AG44: 0.0022144903 | AH44: 0.0022144903 | AI44: 0.0022144903 | AJ44: 0.033169829 | AK44: 0.033169829 | AL44: 0.033169829 | AM44: 0.033169829 | AN44: 0.058533344 | AO44: 0.058533344 | AP44: 0.058533344 | AQ44: 0.058533344 | AR44: 0.00025069701 | AS44: 0.00025069701 | AT44: 0.00025069701 | AU44: 0.00025069701 | AV44: 0.0031593928 | AW44: 0.0031593928 | AX44: 0.0031593928 | AY44: 0.0031593928
B45: =Technologies!#REF! -> #REF! | C45: =Technologies!#REF! -> #REF! | D45: =Technologies!#REF! -> #REF! | E45: PJ, PJ/a | F45: INDRFL | G45: INDRFLEA | H45: 2010 | I45: 50 | J45: 0.0831 | K45: 0.00284 | L45: 0.000284 | M45: 0.025494307 | N45: 0.006883463 | O45: 83.1 | P45: 0.83858254 | Q45: 0.83858254 | R45: 0.83858254 | S45: 0.83858254 | T45: 0.23453782 | U45: 0.23453782 | V45: 0.23453782 | W45: 0.23453782 | X45: 0.084981025 | Y45: 0.084981025 | Z45: 0.084981025 | AA45: 0.084981025 | AB45: 0.076482922 | AC45: 0.076482922 | AD45: 0.076482922 | AE45: 0.076482922 | AF45: 0.093519924 | AG45: 0.093519924 | AH45: 0.093519924 | AI45: 0.093519924 | AJ45: 0.34250095 | AK45: 0.34250095 | AL45: 0.34250095 | AM45: 0.34250095 | AN45: 0.83858254 | AO45: 0.83858254 | AP45: 0.83858254 | AQ45: 0.83858254 | AR45: 0.23453782 | AS45: 0.23453782 | AT45: 0.23453782 | AU45: 0.23453782 | AV45: 0.084981025 | AW45: 0.084981025 | AX45: 0.084981025 | AY45: 0.084981025
B46: *IND_DEM_FI_T_04
B47: *Source: ? | C47: EmissionsSummary

Sheet DemandCalc
B3: DemandPJ_historic | M3: FuelDist_2010
B4: Source: Original, GHG_Inv | M4: Source: DemandPJ_historic
B5: Fuel | C5: Year | D5: Space Heating | E5: DHW | F5: Space Cooling | G5: Ventilation | H5: Lighting | I5: Conveyance | J5: Process Loads | K5: Plug Loads/Misc | M5: Fuel | N5: ISH | O5: IWH | P5: ISC | Q5: ILT | R5: IOT
B6: ELC | C6: 2010 | D6: {=_xlfn.XLOOKUP(DemandPJ_historic[[#This Row],[Fuel]],FUEL_PCT_DETAIL[Fuel],_xlfn.XLOOKUP(DemandPJ_historic[[#Headers],[Space Heating]],FUEL_PCT_DETAIL[#Headers],FUEL_PCT_DETAIL[])) * SUMIFS(FuelBySector[Ind_Consumed (PJ)],FuelBySector[Fuel Match],DemandPJ_historic[[#This Row],[Fuel]],FuelBySector[Year Match],DemandPJ_historic[[#This Row],[Year]])} -> 1.3618234 | E6: {=_xlfn.XLOOKUP(DemandPJ_historic[[#This Row],[Fuel]],FUEL_PCT_DETAIL[Fuel],_xlfn.XLOOKUP(DemandPJ_historic[[#Headers],[DHW]],FUEL_PCT_DETAIL[#Headers],FUEL_PCT_DETAIL[])) * SUMIFS(FuelBySector[Ind_Consumed (PJ)],FuelBySector[Fuel Match],DemandPJ_historic[[#This Row],[Fuel]],FuelBySector[Year Match],DemandPJ_historic[[#This Row],[Year]])} -> 0.59920103 | F6: {=_xlfn.XLOOKUP(DemandPJ_historic[[#This Row],[Fuel]],FUEL_PCT_DETAIL[Fuel],_xlfn.XLOOKUP(DemandPJ_historic[[#Headers],[Space Cooling]],FUEL_PCT_DETAIL[#Headers],FUEL_PCT_DETAIL[])) * SUMIFS(FuelBySector[Ind_Consumed (PJ)],FuelBySector[Fuel Match],DemandPJ_historic[[#This Row],[Fuel]],FuelBySector[Year Match],DemandPJ_historic[[#This Row],[Year]])} -> 4.1278244 | G6: {=_xlfn.XLOOKUP(DemandPJ_historic[[#This Row],[Fuel]],FUEL_PCT_DETAIL[Fuel],_xlfn.XLOOKUP(DemandPJ_historic[[#Headers],[Ventilation]],FUEL_PCT_DETAIL[#Headers],FUEL_PCT_DETAIL[])) * SUMIFS(FuelBySector[Ind_Consumed (PJ)],FuelBySector[Fuel Match],DemandPJ_historic[[#This Row],[Fuel]],FuelBySector[Year Match],DemandPJ_historic[[#This Row],[Year]])} -> 2.7340276 | H6: {=_xlfn.XLOOKUP(DemandPJ_historic[[#This Row],[Fuel]],FUEL_PCT_DETAIL[Fuel],_xlfn.XLOOKUP(DemandPJ_historic[[#Headers],[Lighting]],FUEL_PCT_DETAIL[#Headers],FUEL_PCT_DETAIL[])) * SUMIFS(FuelBySector[Ind_Consumed (PJ)],FuelBySector[Fuel Match],DemandPJ_historic[[#This Row],[Fuel]],FuelBySector[Year Match],DemandPJ_historic[[#This Row],[Year]])} -> 12.885766 | I6: {=_xlfn.XLOOKUP(DemandPJ_historic[[#This Row],[Fuel]],FUEL_PCT_DETAIL[Fuel],_xlfn.XLOOKUP(DemandPJ_historic[[#Headers],[Conveyance]],FUEL_PCT_DETAIL[#Headers],FUEL_PCT_DETAIL[])) * SUMIFS(FuelBySector[Ind_Consumed (PJ)],FuelBySector[Fuel Match],DemandPJ_historic[[#This Row],[Fuel]],FuelBySector[Year Match],DemandPJ_historic[[#This Row],[Year]])} -> 1.9439479 | J6: {=_xlfn.XLOOKUP(DemandPJ_historic[[#This Row],[Fuel]],FUEL_PCT_DETAIL[Fuel],_xlfn.XLOOKUP(DemandPJ_historic[[#Headers],[Process Loads]],FUEL_PCT_DETAIL[#Headers],FUEL_PCT_DETAIL[])) * SUMIFS(FuelBySector[Ind_Consumed (PJ)],FuelBySector[Fuel Match],DemandPJ_historic[[#This Row],[Fuel]],FuelBySector[Year Match],DemandPJ_historic[[#This Row],[Year]])} -> 4.2665899 | K6: {=_xlfn.XLOOKUP(DemandPJ_historic[[#This Row],[Fuel]],FUEL_PCT_DETAIL[Fuel],_xlfn.XLOOKUP(DemandPJ_historic[[#Headers],[Plug Loads/Misc]],FUEL_PCT_DETAIL[#Headers],FUEL_PCT_DETAIL[])) * SUMIFS(FuelBySector[Ind_Consumed (PJ)],FuelBySector[Fuel Match],DemandPJ_historic[[#This Row],[Fuel]],FuelBySector[Year Match],DemandPJ_historic[[#This Row],[Year]])} -> 4.0242874 | M6: ELC | N6: =DemandPJ_historic[[#This Row],[Space Heating]]/SUM(D$6:D$9) -> 0.045266563 | O6: =DemandPJ_historic[[#This Row],[DHW]]/SUM(E$6:E$9) -> 0.21268895 | P6: =DemandPJ_historic[[#This Row],[Space Cooling]]/SUM(F$6:F$9) -> 1 | Q6: =DemandPJ_historic[[#This Row],[Lighting]]/SUM(H$6:H$9) -> 1 | R6: =SUM(G6,I6,J6,K6)/SUM(G$6:G$9,I$6:I$9,J$6:J$9,K$6:K$9) -> 0.96693531
B7: NGA | C7: 2010 | D7: {=_xlfn.XLOOKUP(DemandPJ_historic[[#This Row],[Fuel]],FUEL_PCT_DETAIL[Fuel],_xlfn.XLOOKUP(DemandPJ_historic[[#Headers],[Space Heating]],FUEL_PCT_DETAIL[#Headers],FUEL_PCT_DETAIL[])) * SUMIFS(FuelBySector[Ind_Consumed (PJ)],FuelBySector[Fuel Match],DemandPJ_historic[[#This Row],[Fuel]],FuelBySector[Year Match],DemandPJ_historic[[#This Row],[Year]])} -> 21.7332 | E7: {=_xlfn.XLOOKUP(DemandPJ_historic[[#This Row],[Fuel]],FUEL_PCT_DETAIL[Fuel],_xlfn.XLOOKUP(DemandPJ_historic[[#Headers],[DHW]],FUEL_PCT_DETAIL[#Headers],FUEL_PCT_DETAIL[])) * SUMIFS(FuelBySector[Ind_Consumed (PJ)],FuelBySector[Fuel Match],DemandPJ_historic[[#This Row],[Fuel]],FuelBySector[Year Match],DemandPJ_historic[[#This Row],[Year]])} -> 0.72005593 | F7: {=_xlfn.XLOOKUP(DemandPJ_historic[[#This Row],[Fuel]],FUEL_PCT_DETAIL[Fuel],_xlfn.XLOOKUP(DemandPJ_historic[[#Headers],[Space Cooling]],FUEL_PCT_DETAIL[#Headers],FUEL_PCT_DETAIL[])) * SUMIFS(FuelBySector[Ind_Consumed (PJ)],FuelBySector[Fuel Match],DemandPJ_historic[[#This Row],[Fuel]],FuelBySector[Year Match],DemandPJ_historic[[#This Row],[Year]])} -> 0 | G7: {=_xlfn.XLOOKUP(DemandPJ_historic[[#This Row],[Fuel]],FUEL_PCT_DETAIL[Fuel],_xlfn.XLOOKUP(DemandPJ_historic[[#Headers],[Ventilation]],FUEL_PCT_DETAIL[#Headers],FUEL_PCT_DETAIL[])) * SUMIFS(FuelBySector[Ind_Consumed (PJ)],FuelBySector[Fuel Match],DemandPJ_historic[[#This Row],[Fuel]],FuelBySector[Year Match],DemandPJ_historic[[#This Row],[Year]])} -> 0 | H7: {=_xlfn.XLOOKUP(DemandPJ_historic[[#This Row],[Fuel]],FUEL_PCT_DETAIL[Fuel],_xlfn.XLOOKUP(DemandPJ_historic[[#Headers],[Lighting]],FUEL_PCT_DETAIL[#Headers],FUEL_PCT_DETAIL[])) * SUMIFS(FuelBySector[Ind_Consumed (PJ)],FuelBySector[Fuel Match],DemandPJ_historic[[#This Row],[Fuel]],FuelBySector[Year Match],DemandPJ_historic[[#This Row],[Year]])} -> 0 | I7: {=_xlfn.XLOOKUP(DemandPJ_historic[[#This Row],[Fuel]],FUEL_PCT_DETAIL[Fuel],_xlfn.XLOOKUP(DemandPJ_historic[[#Headers],[Conveyance]],FUEL_PCT_DETAIL[#Headers],FUEL_PCT_DETAIL[])) * SUMIFS(FuelBySector[Ind_Consumed (PJ)],FuelBySector[Fuel Match],DemandPJ_historic[[#This Row],[Fuel]],FuelBySector[Year Match],DemandPJ_historic[[#This Row],[Year]])} -> 0 | J7: {=_xlfn.XLOOKUP(DemandPJ_historic[[#This Row],[Fuel]],FUEL_PCT_DETAIL[Fuel],_xlfn.XLOOKUP(DemandPJ_historic[[#Headers],[Process Loads]],FUEL_PCT_DETAIL[#Headers],FUEL_PCT_DETAIL[])) * SUMIFS(FuelBySector[Ind_Consumed (PJ)],FuelBySector[Fuel Match],DemandPJ_historic[[#This Row],[Fuel]],FuelBySector[Year Match],DemandPJ_historic[[#This Row],[Year]])} -> 0.26665529 | K7: {=_xlfn.XLOOKUP(DemandPJ_historic[[#This Row],[Fuel]],FUEL_PCT_DETAIL[Fuel],_xlfn.XLOOKUP(DemandPJ_historic[[#Headers],[Plug Loads/Misc]],FUEL_PCT_DETAIL[#Headers],FUEL_PCT_DETAIL[])) * SUMIFS(FuelBySector[Ind_Consumed (PJ)],FuelBySector[Fuel Match],DemandPJ_historic[[#This Row],[Fuel]],FuelBySector[Year Match],DemandPJ_historic[[#This Row],[Year]])} -> 0.075883414 | M7: NGA | N7: =DemandPJ_historic[[#This Row],[Space Heating]]/SUM(D$6:D$9) -> 0.72240442 | O7: =DemandPJ_historic[[#This Row],[DHW]]/SUM(E$6:E$9) -> 0.25558692 | P7: =DemandPJ_historic[[#This Row],[Space Cooling]]/SUM(F$6:F$9) -> 0 | Q7: =DemandPJ_historic[[#This Row],[Lighting]]/SUM(H$6:H$9) -> 0 | R7: =SUM(G7,I7,J7,K7)/SUM(G$6:G$9,I$6:I$9,J$6:J$9,K$6:K$9) -> 0.025539096
B8: DSL | C8: 2010 | D8: {=_xlfn.XLOOKUP(DemandPJ_historic[[#This Row],[Fuel]],FUEL_PCT_DETAIL[Fuel],_xlfn.XLOOKUP(DemandPJ_historic[[#Headers],[Space Heating]],FUEL_PCT_DETAIL[#Headers],FUEL_PCT_DETAIL[])) * SUMIFS(FuelBySector[Ind_Consumed (PJ)],FuelBySector[Fuel Match],DemandPJ_historic[[#This Row],[Fuel]],FuelBySector[Year Match],DemandPJ_historic[[#This Row],[Year]])} -> 3.1074194 | E8: {=_xlfn.XLOOKUP(DemandPJ_historic[[#This Row],[Fuel]],FUEL_PCT_DETAIL[Fuel],_xlfn.XLOOKUP(DemandPJ_historic[[#Headers],[DHW]],FUEL_PCT_DETAIL[#Headers],FUEL_PCT_DETAIL[])) * SUMIFS(FuelBySector[Ind_Consumed (PJ)],FuelBySector[Fuel Match],DemandPJ_historic[[#This Row],[Fuel]],FuelBySector[Year Match],DemandPJ_historic[[#This Row],[Year]])} -> 0.32698545 | F8: {=_xlfn.XLOOKUP(DemandPJ_historic[[#This Row],[Fuel]],FUEL_PCT_DETAIL[Fuel],_xlfn.XLOOKUP(DemandPJ_historic[[#Headers],[Space Cooling]],FUEL_PCT_DETAIL[#Headers],FUEL_PCT_DETAIL[])) * SUMIFS(FuelBySector[Ind_Consumed (PJ)],FuelBySector[Fuel Match],DemandPJ_historic[[#This Row],[Fuel]],FuelBySector[Year Match],DemandPJ_historic[[#This Row],[Year]])} -> 0 | G8: {=_xlfn.XLOOKUP(DemandPJ_historic[[#This Row],[Fuel]],FUEL_PCT_DETAIL[Fuel],_xlfn.XLOOKUP(DemandPJ_historic[[#Headers],[Ventilation]],FUEL_PCT_DETAIL[#Headers],FUEL_PCT_DETAIL[])) * SUMIFS(FuelBySector[Ind_Consumed (PJ)],FuelBySector[Fuel Match],DemandPJ_historic[[#This Row],[Fuel]],FuelBySector[Year Match],DemandPJ_historic[[#This Row],[Year]])} -> 0 | H8: {=_xlfn.XLOOKUP(DemandPJ_historic[[#This Row],[Fuel]],FUEL_PCT_DETAIL[Fuel],_xlfn.XLOOKUP(DemandPJ_historic[[#Headers],[Lighting]],FUEL_PCT_DETAIL[#Headers],FUEL_PCT_DETAIL[])) * SUMIFS(FuelBySector[Ind_Consumed (PJ)],FuelBySector[Fuel Match],DemandPJ_historic[[#This Row],[Fuel]],FuelBySector[Year Match],DemandPJ_historic[[#This Row],[Year]])} -> 0 | I8: {=_xlfn.XLOOKUP(DemandPJ_historic[[#This Row],[Fuel]],FUEL_PCT_DETAIL[Fuel],_xlfn.XLOOKUP(DemandPJ_historic[[#Headers],[Conveyance]],FUEL_PCT_DETAIL[#Headers],FUEL_PCT_DETAIL[])) * SUMIFS(FuelBySector[Ind_Consumed (PJ)],FuelBySector[Fuel Match],DemandPJ_historic[[#This Row],[Fuel]],FuelBySector[Year Match],DemandPJ_historic[[#This Row],[Year]])} -> 0 | J8: {=_xlfn.XLOOKUP(DemandPJ_historic[[#This Row],[Fuel]],FUEL_PCT_DETAIL[Fuel],_xlfn.XLOOKUP(DemandPJ_historic[[#Headers],[Process Loads]],FUEL_PCT_DETAIL[#Headers],FUEL_PCT_DETAIL[])) * SUMIFS(FuelBySector[Ind_Consumed (PJ)],FuelBySector[Fuel Match],DemandPJ_historic[[#This Row],[Fuel]],FuelBySector[Year Match],DemandPJ_historic[[#This Row],[Year]])} -> 0.10091461 | K8: {=_xlfn.XLOOKUP(DemandPJ_historic[[#This Row],[Fuel]],FUEL_PCT_DETAIL[Fuel],_xlfn.XLOOKUP(DemandPJ_historic[[#Headers],[Plug Loads/Misc]],FUEL_PCT_DETAIL[#Headers],FUEL_PCT_DETAIL[])) * SUMIFS(FuelBySector[Ind_Consumed (PJ)],FuelBySector[Fuel Match],DemandPJ_historic[[#This Row],[Fuel]],FuelBySector[Year Match],DemandPJ_historic[[#This Row],[Year]])} -> 0 | M8: DSL | N8: =DemandPJ_historic[[#This Row],[Space Heating]]/SUM(D$6:D$9) -> 0.1032896 | O8: =DemandPJ_historic[[#This Row],[DHW]]/SUM(E$6:E$9) -> 0.11606487 | P8: =DemandPJ_historic[[#This Row],[Space Cooling]]/SUM(F$6:F$9) -> 0 | Q8: =DemandPJ_historic[[#This Row],[Lighting]]/SUM(H$6:H$9) -> 0 | R8: =SUM(G8,I8,J8,K8)/SUM(G$6:G$9,I$6:I$9,J$6:J$9,K$6:K$9) -> 0.0075240192
