Workbook
Name AnswerData: #REF!
Name bprint: #REF!
Name cprint: #REF!
Name exch_rate: #REF!
Name fitfile: [1]MODEL!$D$38
Name INF: [1]MODEL!$H$14
Name PPP: [1]MODEL!$D$12
Name PPPEX: [1]MODEL!$D$13
Name rail_coal: #REF!

Sheet Commodities
B1: Commodities | C1: R0,R1,R2,R3,R4,R5,R6
B6: ~FI_Comm
B7: Region | C7: CommName | D7: CommDesc | E7: Unit | F7: Csets | G7: LimType | H7: CTSLvl | I7: PeakTS | J7: Ctype | O7: Comment
B8: *R1,R2,R3,R4,R5,R6 | C8: LPG | D8: LPG | E8: PJ | F8: NRG
B9: *R1,R2,R3,R4,R5,R6 | C9: JTF | D9: Jet Fuel | E9: PJ
B10: *R1,R2,R3,R4,R5,R6 | C10: RFH | D10: High Sulfur Residual Fuel Oil | E10: PJ
B11: *R1,R2,R3,R4,R5,R6 | C11: KER | D11: Kerosene and Other Refined Products | E11: PJ
B12: *R1,R2,R3,R4,R5,R6 | C12: PFS | D12: Petrochemical Feedstocks | E12: PJ
B13: *R1,R2,R3,R4,R5,R6 | C13: ASP | D13: Asphalt | E13: PJ
B14: *R1,R2,R3,R4,R5,R6 | C14: PTC | D14: Petroleum Coke | E14: PJ
B15: *R1,R2,R3,R4,R5,R6 | C15: DLG | D15: Dummy Liquid Fuel | E15: PJ
B16: * Refined Products in each Region | E16: PJ
B17: R1 | C17: DummyREF | D17: Refinery dummy commodities | E17: PJ
B18: *R1,R2,R3,R4,R5,R6 | C18: LPG_E | D18: LPG | E18: PJ
B19: R1 | C19: GSC_E | D19: Conventional Gasoline | E19: PJ
B20: R1 | C20: GSR_E | D20: Reformulated Gasoline | E20: PJ
B21: *R1,R2,R3,R4,R5,R6 | C21: JTF_E | D21: Jet Fuel | E21: PJ
B22: R1 | C22: DSH_E | D22: Distillate-Heating Oil No. 2 | E22: PJ
B23: R1 | C23: RFL_E | D23: Low Sulfur Residual Fuel Oil | E23: PJ
B24: *R1,R2,R3,R4,R5,R6 | C24: RFH_E | D24: High Sulfur Residual Fuel Oil | E24: PJ
B25: *R1,R2,R3,R4,R5,R6 | C25: KER_E | D25: Kerosene and Other Refined Products | E25: PJ
B26: *R1,R2,R3,R4,R5,R6 | C26: PFS_E | D26: Petrochemical Feedstocks | E26: PJ
B27: *R1,R2,R3,R4,R5,R6 | C27: ASP_E | D27: Asphalt | E27: PJ
B28: R1 | C28: DSL_E | D28: Distillate-Low Sulfur Highway Diesel (500 ppm) | E28: PJ
... B61: *R1,R2,R3,R4,R5,R6 | C61: ETH_L | D61: Ethanol | E61: PJ
B62: R1,R2,R3,R4,R5,R6 | C62: CO2I | D62: Industrial CO2 emissions | E62: kt | F62: ENV
B63: R1,R2,R3,R4,R5,R6 | C63: NOXI | D63: Industrial NOx emissions | E63: kt | F63: ENV
B64: R1,R2,R3,R4,R5,R6 | C64: SO2I | D64: Industrial SO2 emissions | E64: kt | F64: ENV
B65: R1,R2,R3,R4,R5,R6 | C65: PM10I | D65: Industrial PM emissions | E65: kt | F65: ENV
B66: R1,R2,R3,R4,R5,R6 | C66: NOXDIREF | D66: NOx from refineries | E66: kt | F66: ENV
B73: R1,R2,R3,R4,R5,R6 | C73: ELC | D73: Electricity to Industrial Sector | E73: PJ | F73: NRG
B74: R1 | C74: OIL | D74: Crude Oil-All Sources | E74: PJ | F74: ENT,ENC,EFS,LIQ
B75: R1,R2,R3,R4,R5,R6 | C75: NGA | D75: Natural Gas to Industrial Sector | E75: PJ | F75: ENT,ENC,EFS,GAZ
B76: R1 | C76: GSC | D76: Conventional Gasoline | E76: PJ | F76: ENT,ENC,EFS,LIQ
B77: R1 | C77: GSR | D77: Reformulated Gasoline | E77: PJ | F77: ENT,ENC,EFS,LIQ
B78: R1 | C78: DSH | D78: Distillate-Heating Oil No. 2 | E78: PJ | F78: ENT,ENC,EFS,LIQ
B79: R1 | C79: RFL | D79: Low Sulfur Residual Fuel Oil | E79: PJ | F79: ENT,ENC,EFS,LIQ
... B93: R1,R2,R3,R4,R5,R6 | C93: SO2 | D93: Sulfur dioxide emissions | E93: kt | F93: ENV
B94: =IF(LEFT(B8,1)="*","*R1","R1") -> *R1 | C94: =CONCATENATE(C8,B94) -> LPG*R1 | D94: =CONCATENATE(C8," Refined in ",B94) -> LPG Refined in *R1 | E94: PJ
B95: =IF(LEFT(B76,1)="*","*R1","R1") -> R1 | C95: =CONCATENATE(C76,B95) -> GSCR1 | D95: =CONCATENATE(C76," Refined in ",B95) -> GSC Refined in R1 | E95: PJ
B96: =IF(LEFT(B77,1)="*","*R1","R1") -> R1 | C96: =CONCATENATE(C77,B96) -> GSRR1 | D96: =CONCATENATE(C77," Refined in ",B96) -> GSR Refined in R1 | E96: PJ
B97: =IF(LEFT(B9,1)="*","*R1","R1") -> *R1 | C97: =CONCATENATE(C9,B97) -> JTF*R1 | D97: =CONCATENATE(C9," Refined in ",B97) -> JTF Refined in *R1 | E97: PJ
B98: =IF(LEFT(B78,1)="*","*R1","R1") -> R1 | C98: =CONCATENATE(C78,B98) -> DSHR1 | D98: =CONCATENATE(C78," Refined in ",B98) -> DSH Refined in R1 | E98: PJ
B99: =IF(LEFT(B79,1)="*","*R1","R1") -> R1 | C99: =CONCATENATE(C79,B99) -> RFLR1 | D99: =CONCATENATE(C79," Refined in ",B99) -> RFL Refined in R1 | E99: PJ
B100: =IF(LEFT(B10,1)="*","*R1","R1") -> *R1 | C100: =CONCATENATE(C10,B100) -> RFH*R1 | D100: =CONCATENATE(C10," Refined in ",B100) -> RFH Refined in *R1 | E100: PJ
B101: =IF(LEFT(B11,1)="*","*R1","R1") -> *R1 | C101: =CONCATENATE(C11,B101) -> KER*R1 | D101: =CONCATENATE(C11," Refined in ",B101) -> KER Refined in *R1 | E101: PJ
B102: =IF(LEFT(B12,1)="*","*R1","R1") -> *R1 | C102: =CONCATENATE(C12,B102) -> PFS*R1 | D102: =CONCATENATE(C12," Refined in ",B102) -> PFS Refined in *R1 | E102: PJ
B103: =IF(LEFT(B13,1)="*","*R1","R1") -> *R1 | C103: =CONCATENATE(C13,B103) -> ASP*R1 | D103: =CONCATENATE(C13," Refined in ",B103) -> ASP Refined in *R1 | E103: PJ
B104: =IF(LEFT(B80,1)="*","*R1","R1") -> R1 | C104: =CONCATENATE(C80,B104) -> DSLR1 | D104: =CONCATENATE(C80," Refined in ",B104) -> DSL Refined in R1 | E104: PJ
B105: =IF(LEFT(B81,1)="*","*R1","R1") -> R1 | C105: =CONCATENATE(C81,B105) -> DSUR1 | D105: =CONCATENATE(C81," Refined in ",B105) -> DSU Refined in R1 | E105: PJ
B106: =IF(LEFT(B14,1)="*","*R1","R1") -> *R1 | C106: =CONCATENATE(C14,B106) -> PTC*R1 | D106: =CONCATENATE(C14," Refined in ",B106) -> PTC Refined in *R1 | E106: PJ
B107: =IF(LEFT(B15,1)="*","*R1","R1") -> *R1 | C107: =CONCATENATE(C15,B107) -> DLG*R1 | D107: =CONCATENATE(C15," Refined in ",B107) -> DLG Refined in *R1 | E107: PJ
B108: * | C108: =CONCATENATE(C82,B108) -> NGL* | D108: =CONCATENATE(C82," Refined in ",B108) -> NGL Refined in * | E108: PJ

Sheet Technologies
B1: Technologies | C1: R0,R1,R2,R3,R4,R5,R6
B6: ~FI_Process
B7: Region | C7: TechName | D7: TechDesc | E7: Tact | F7: Tcap | G7: Sets | H7: PrimaryCG | I7: Vintage | O7: Comment
B8: R1 | C8: PREFE | D8: Refinery-existing conversion | E8: PJ | F8: PJ/a | G8: PRE
B9: *R1,R2,R3,R4,R5,R6 | C9: MINNGL | D9: Mined Natural Gas Liquids | E9: PJ | F9: PJ/a | G9: MIN
B10: *R1 | C10: SCLPG_E | D10: Collector: LPG from REF_E | E10: PJ | F10: PJ/a | G10: PRE
B11: R1 | C11: SCGSC_E | D11: Collector: GSC from REF_E | E11: PJ | F11: PJ/a
B12: R1 | C12: SCGSR_E | D12: Collector: GSR from REF_E | E12: PJ | F12: PJ/a
B13: *R1 | C13: SCJTF_E | D13: Collector: JTF from REF_E | E13: PJ | F13: PJ/a
B14: R1 | C14: SCDSH_E | D14: Collector: DSH from REF_E | E14: PJ | F14: PJ/a
B15: R1 | C15: SCRFL_E | D15: Collector: RFL from REF_E | E15: PJ | F15: PJ/a
B16: *R1 | C16: SCRFH_E | D16: Collector: RFH from REF_E | E16: PJ | F16: PJ/a
B17: *R1 | C17: SCKER_E | D17: Collector: KER from REF_E | E17: PJ | F17: PJ/a
B18: *R1 | C18: SCPFS_E | D18: Collector: PFS from REF_E | E18: PJ | F18: PJ/a
B19: *R1 | C19: SCASP_E | D19: Collector: ASP from REF_E | E19: PJ | F19: PJ/a
B20: R1 | C20: SCDSL_E | D20: Collector: DSL from REF_E | E20: PJ | F20: PJ/a
B21: R1 | C21: SCDSU_E | D21: Collector: DSU from REF_E | E21: PJ | F21: PJ/a
B22: *R1 | C22: SCPTC_E | D22: Collector: PTC from REF_E | E22: PJ | F22: PJ/a
... B57: R1 | C57: PREFL | D57: Refinery-new limit | E57: PJ | F57: PJ/a

Sheet TechData_REFNYC
A1: TechData | B1: R0,R1,R2,R3,R4,R5,R6 | Z1: *
E4: ~FI_T
A5: Region | B5: TechName | C5: *TechDesc | D5: CommIN | E5: CommOUT | F5: EFF | G5: NCAP_COST | H5: NCAP_FOM~2010 | I5: NCAP_FOM~2015 | J5: NCAP_FOM~2020 | K5: NCAP_FOM~2025 | L5: NCAP_FOM~2030 | M5: NCAP_FOM~2055 | N5: PRC_RESID~2010 | O5: PRC_RESID~2055 | P5: ACT_BND~LO
A6: * Collectors
A7: =Technologies!B10 -> *R1 | B7: =Technologies!C10 -> SCLPG_E | C7: =Technologies!D10 -> Collector: LPG from REF_E | D7: LPG_E | E7: =Commodities!C8 -> LPG | F7: 1 | H7: 0.001 | I7: 0.001 | J7: 0.001 | K7: 0.001 | L7: 0.001 | M7: =L7 -> 0.001
A8: =Technologies!B11 -> R1 | B8: =Technologies!C11 -> SCGSC_E | C8: =Technologies!D11 -> Collector: GSC from REF_E | D8: GSC_E | E8: =Commodities!C76 -> GSC | F8: 1 | H8: 0.001 | I8: 0.001 | J8: 0.001 | K8: 0.001 | L8: 0.001 | M8: =L8 -> 0.001
A9: =Technologies!B12 -> R1 | B9: =Technologies!C12 -> SCGSR_E | C9: =Technologies!D12 -> Collector: GSR from REF_E | D9: GSR_E | E9: =Commodities!C77 -> GSR | F9: 1 | H9: 0.001 | I9: 0.001 | J9: 0.001 | K9: 0.001 | L9: 0.001 | M9: =L9 -> 0.001
A10: =Technologies!B13 -> *R1 | B10: =Technologies!C13 -> SCJTF_E | C10: =Technologies!D13 -> Collector: JTF from REF_E | D10: JTF_E | E10: =Commodities!C9 -> JTF | F10: 1 | H10: 0.001 | I10: 0.001 | J10: 0.001 | K10: 0.001 | L10: 0.001 | M10: =L10 -> 0.001
A11: =Technologies!B14 -> R1 | B11: =Technologies!C14 -> SCDSH_E | C11: =Technologies!D14 -> Collector: DSH from REF_E | D11: DSH_E | E11: =Commodities!C78 -> DSH | F11: 1 | H11: 0.001 | I11: 0.001 | J11: 0.001 | K11: 0.001 | L11: 0.001 | M11: =L11 -> 0.001
A12: =Technologies!B15 -> R1 | B12: =Technologies!C15 -> SCRFL_E | C12: =Technologies!D15 -> Collector: RFL from REF_E | D12: RFL_E | E12: =Commodities!C79 -> RFL | F12: 1 | H12: 0.001 | I12: 0.001 | J12: 0.001 | K12: 0.001 | L12: 0.001 | M12: =L12 -> 0.001
A13: =Technologies!B16 -> *R1 | B13: =Technologies!C16 -> SCRFH_E | C13: =Technologies!D16 -> Collector: RFH from REF_E | D13: RFH_E | E13: =Commodities!C10 -> RFH | F13: 1 | H13: 0.001 | I13: 0.001 | J13: 0.001 | K13: 0.001 | L13: 0.001 | M13: =L13 -> 0.001
A14: =Technologies!B17 -> *R1 | B14: =Technologies!C17 -> SCKER_E | C14: =Technologies!D17 -> Collector: KER from REF_E | D14: KER_E | E14: =Commodities!C11 -> KER | F14: 1 | H14: 0.001 | I14: 0.001 | J14: 0.001 | K14: 0.001 | L14: 0.001 | M14: =L14 -> 0.001
A15: =Technologies!B18 -> *R1 | B15: =Technologies!C18 -> SCPFS_E | C15: =Technologies!D18 -> Collector: PFS from REF_E | D15: PFS_E | E15: =Commodities!C12 -> PFS | F15: 1 | H15: 0.001 | I15: 0.001 | J15: 0.001 | K15: 0.001 | L15: 0.001 | M15: =L15 -> 0.001
A16: =Technologies!B19 -> *R1 | B16: =Technologies!C19 -> SCASP_E | C16: =Technologies!D19 -> Collector: ASP from REF_E | D16: ASP_E | E16: =Commodities!C13 -> ASP | F16: 1 | H16: 0.001 | I16: 0.001 | J16: 0.001 | K16: 0.001 | L16: 0.001 | M16: =L16 -> 0.001
A17: =Technologies!B20 -> R1 | B17: =Technologies!C20 -> SCDSL_E | C17: =Technologies!D20 -> Collector: DSL from REF_E | D17: DSL_E | E17: =Commodities!C80 -> DSL | F17: 1 | H17: 0.001 | I17: 0.001 | J17: 0.001 | K17: 0.001 | L17: 0.001 | M17: =L17 -> 0.001
A18: =Technologies!B21 -> R1 | B18: =Technologies!C21 -> SCDSU_E | C18: =Technologies!D21 -> Collector: DSU from REF_E | D18: DSU_E | E18: =Commodities!C81 -> DSU | F18: 1 | H18: 0.001 | I18: 0.001 | J18: 0.001 | K18: 0.001 | L18: 0.001 | M18: =L18 -> 0.001
A19: =Technologies!B22 -> *R1 | B19: =Technologies!C22 -> SCPTC_E | C19: =Technologies!D22 -> Collector: PTC from REF_E | D19: PTC_E | E19: =Commodities!C14 -> PTC | F19: 1 | H19: 0.001 | I19: 0.001 | J19: 0.001 | K19: 0.001 | L19: 0.001 | M19: =L19 -> 0.001
A20: =Technologies!B23 -> *R1 | B20: =Technologies!C23 -> SCDLG_E | C20: =Technologies!D23 -> Collector: DLG from REF_E | D20: DLG_E | E20: =Commodities!C15 -> DLG | F20: 1 | H20: 0.001 | I20: 0.001 | J20: 0.001 | K20: 0.001 | L20: 0.001 | M20: =L20 -> 0.001
A21: =Technologies!B24 -> *R1 | B21: =Technologies!C24 -> SCLPG_N | C21: =Technologies!D24 -> Collector: LPG from REF_N | D21: LPG_N | E21: =E7 -> LPG | F21: 1 | H21: 0.001 | I21: 0.001 | J21: 0.001 | K21: 0.001 | L21: 0.001 | M21: =L21 -> 0.001
A22: =Technologies!B25 -> R1 | B22: =Technologies!C25 -> SCGSC_N | C22: =Technologies!D25 -> Collector: GSC from REF_N | D22: GSC_N | E22: =E8 -> GSC | F22: 1 | H22: 0.001 | I22: 0.001 | J22: 0.001 | K22: 0.001 | L22: 0.001 | M22: =L22 -> 0.001
A23: =Technologies!B26 -> R1 | B23: =Technologies!C26 -> SCGSR_N | C23: =Technologies!D26 -> Collector: GSR from REF_N | D23: GSR_N | E23: =E9 -> GSR | F23: 1 | H23: 0.001 | I23: 0.001 | J23: 0.001 | K23: 0.001 | L23: 0.001 | M23: =L23 -> 0.001
A24: =Technologies!B27 -> *R1 | B24: =Technologies!C27 -> SCJTF_N | C24: =Technologies!D27 -> Collector: JTF from REF_N | D24: JTF_N | E24: =E10 -> JTF | F24: 1 | H24: 0.001 | I24: 0.001 | J24: 0.001 | K24: 0.001 | L24: 0.001 | M24: =L24 -> 0.001
A25: =Technologies!B28 -> R1 | B25: =Technologies!C28 -> SCDSH_N | C25: =Technologies!D28 -> Collector: DSH from REF_N | D25: DSH_N | E25: =E11 -> DSH | F25: 1 | H25: 0.001 | I25: 0.001 | J25: 0.001 | K25: 0.001 | L25: 0.001 | M25: =L25 -> 0.001
A26: =Technologies!B29 -> R1 | B26: =Technologies!C29 -> SCRFL_N | C26: =Technologies!D29 -> Collector: RFL from REF_N | D26: RFL_N | E26: =E12 -> RFL | F26: 1 | H26: 0.001 | I26: 0.001 | J26: 0.001 | K26: 0.001 | L26: 0.001 | M26: =L26 -> 0.001
A27: =Technologies!B30 -> *R1 | B27: =Technologies!C30 -> SCRFH_N | C27: =Technologies!D30 -> Collector: RFH from REF_N | D27: RFH_N | E27: =E13 -> RFH | F27: 1 | H27: 0.001 | I27: 0.001 | J27: 0.001 | K27: 0.001 | L27: 0.001 | M27: =L27 -> 0.001
A28: =Technologies!B31 -> *R1 | B28: =Technologies!C31 -> SCKER_N | C28: =Technologies!D31 -> Collector: KER from REF_N | D28: KER_N | E28: =E14 -> KER | F28: 1 | H28: 0.001 | I28: 0.001 | J28: 0.001 | K28: 0.001 | L28: 0.001 | M28: =L28 -> 0.001
A29: =Technologies!B32 -> *R1 | B29: =Technologies!C32 -> SCPFS_N | C29: =Technologies!D32 -> Collector: PFS from REF_N | D29: PFS_N | E29: =E15 -> PFS | F29: 1 | H29: 0.001 | I29: 0.001 | J29: 0.001 | K29: 0.001 | L29: 0.001 | M29: =L29 -> 0.001
A30: =Technologies!B33 -> *R1 | B30: =Technologies!C33 -> SCASP_N | C30: =Technologies!D33 -> Collector: ASP from REF_N | D30: ASP_N | E30: =E16 -> ASP | F30: 1 | H30: 0.001 | I30: 0.001 | J30: 0.001 | K30: 0.001 | L30: 0.001 | M30: =L30 -> 0.001
A31: =Technologies!B34 -> R1 | B31: =Technologies!C34 -> SCDSL_N | C31: =Technologies!D34 -> Collector: DSL from REF_N | D31: DSL_N | E31: =E17 -> DSL | F31: 1 | H31: 0.001 | I31: 0.001 | J31: 0.001 | K31: 0.001 | L31: 0.001 | M31: =L31 -> 0.001
A32: =Technologies!B35 -> R1 | B32: =Technologies!C35 -> SCDSU_N | C32: =Technologies!D35 -> Collector: DSU from REF_N | D32: DSU_N | E32: =E18 -> DSU | F32: 1 | H32: 0.001 | I32: 0.001 | J32: 0.001 | K32: 0.001 | L32: 0.001 | M32: =L32 -> 0.001
... A47: =Technologies!B50 -> *R1 | B47: =Technologies!C50 -> SCPTC_L | C47: =Technologies!D50 -> Collector: PTC from REF_L | D47: PTC_L | E47: =E33 -> PTC | F47: 1 | H47: 0.001 | I47: 0.001 | J47: 0.001 | K47: 0.001 | L47: 0.001 | M47: =L47 -> 0.001
E52: ~FI_T
A53: Region | B53: TechName | C53: *TechDesc | D53: CommIN | E53: CommOUT | F53: EFF | G53: Share~UP~2010 | H53: Share~UP~2055 | I53: Share~UP~2010 | J53: Share~UP~2055 | K53: *NCAP_START | L53: NCAP_TLIFE | M53: PRC_CAPACT | N53: NCAP_AFA | O53: NCAP_COST | P53: NCAP_FOM~2010 | Q53: NCAP_FOM~2015 | R53: NCAP_FOM~2020 | S53: NCAP_FOM~2025 | T53: NCAP_FOM~2030 | U53: NCAP_FOM~2055 | V53: PRC_RESID~2010 | W53: PRC_RESID~2055 | X53: ACT_BND~LO~2010 | Y53: ACT_BND~LO~2050 | AA53: Input | AB53: Output | AD53: IBOND(UP)
A54: R1 | B54: =Technologies!C8 -> PREFE | C54: =Technologies!D8 -> Refinery-existing conversion | D54: =Commodities!C74 -> OIL | F54: =SUM(AB58:AB64)/SUM(AA54:AA57) -> 0.92083406 | G54: =AA54/SUM(AA$54:AA$57) -> 0.95569214 | H54: =G54 -> 0.95569214 | K54: 2010 | L54: 40 | M54: 1 | N54: 1 | P54: 0.12898736 | Q54: 0.14403589 | R54: 0.1470456 | S54: 0.14833547 | T54: 0.14145614 | U54: =T54 -> 0.14145614 | V54: =RESID!K21 -> 2074.6655 | W54: =V54 -> 2074.6655 | X54: =0.1*V54 -> 207.46655 | Y54: =X54 -> 207.46655 | AA54: =EPAUS9RTechData!G50 -> 1.0378549 | AD54: 0
A55: =A54 -> R1 | D55: =Commodities!C75 -> NGA | G55: =AA55/SUM(AA$54:AA$57) -> 0.039891908 | H55: =G55 -> 0.039891908 | AA55: =EPAUS9RTechData!G51 -> 0.043321495
A56: =A55 -> R1 | D56: =Commodities!C73 -> ELC | G56: =AA56/SUM(AA$54:AA$57) -> 0.0044159568 | H56: =G56 -> 0.0044159568 | AA56: =EPAUS9RTechData!G52 -> 0.0047956054
A57: =A56 -> R1 | D57: =Commodities!$C$82 -> NGL | G57: =AA57/SUM(AA$54:AA$57) -> 0 | H57: =G57 -> 0 | AA57: =EPAUS9RTechData!G53 -> 0
A58: =A57 -> R1 | E58: DSH_E | I58: =AB58/SUM(AB$58:AB$64) -> 0.11618676 | J58: =I58*0.2 -> 0.023237353 | AB58: ='PADD Products'!I10/100 -> 0.11618676
A59: =A58 -> R1 | E59: RFL_E | I59: =AB59/SUM(AB$58:AB$64) -> 0.064152 | J59: =I59*0.8 -> 0.0513216 | AB59: ='PADD Products'!I11/100 -> 0.064152
A60: =A59 -> R1 | E60: =Commodities!$C$19 -> GSC_E | I60: =AB60/SUM(AB$58:AB$64) -> 0 | J60: =I60 -> 0 | AB60: =EPAUS9RTechData!H52 -> 0
A61: =A60 -> R1 | E61: =Commodities!$C$20 -> GSR_E | I61: =AB61/SUM(AB$58:AB$64) -> 0.544452 | J61: =I61 -> 0.544452 | AB61: =EPAUS9RTechData!H51 -> 0.544452
A62: =A61 -> R1 | E62: =Commodities!$C$28 -> DSL_E | I62: =AB62/SUM(AB$58:AB$64) -> 0 | J62: =I62 -> 0 | AB62: =EPAUS9RTechData!H56 -> 0
A63: =A62 -> R1 | E63: =Commodities!$C$29 -> DSU_E | I63: =AB63/SUM(AB$58:AB$64) -> 0.21783261 | J63: =1-SUM(J58:J62,J64) -> 0.32361242 | AB63: =EPAUS9RTechData!H55 -> 0.21783261
A64: =A63 -> R1 | E64: DummyREF | I64: =AB64/SUM(AB$58:AB$64) -> 0.057376624 | J64: =I64 -> 0.057376624 | AB64: =1-SUM(AB58:AB63) -> 0.057376624
A69: Region | B69: TechName | C69: *TechDesc | D69: CommIN | E69: CommOUT | F69: Input | G69: Output | H69: NCAP_START | I69: NCAP_TLIFE | J69: PRC_CAPACT | K69: NCAP_AFA | L69: NCAP_COST | M69: NCAP_FOM~2010 | N69: NCAP_FOM~2015 | O69: NCAP_FOM~2020 | P69: NCAP_FOM~2025 | Q69: NCAP_FOM~2030 | R69: NCAP_FOM~2055 | S69: PRC_RESID~2010 | T69: PRC_RESID~2055 | U69: ACT_BND~LO | Y69: IBOND(UP)
A70: R1 | B70: =Technologies!C56 -> PREFN | C70: =Technologies!D56 -> Refinery-new conversion | D70: =Commodities!C74 -> OIL | F70: =EPAUS9RTechData!G64 -> 1.0378549 | H70: 2010 | I70: 40 | J70: 1 | K70: 1 | L70: ='RTI Costs'!F7*Conv!J32 -> 8.8465028 | M70: 0.12898736 | N70: 0.14403589 | O70: 0.1470456 | P70: 0.14833547 | Q70: 0.14145614 | R70: =Q70 -> 0.14145614
D71: =Commodities!C75 -> NGA | F71: =EPAUS9RTechData!G65 -> 0.043321495
D72: =Commodities!C73 -> ELC | F72: =EPAUS9RTechData!G66 -> 0.0047956054
D73: =Commodities!$C$82 -> NGL | F73: =EPAUS9RTechData!G67 -> 0
E74: DSH_N | G74: =AB58 -> 0.11618676
E75: RFL_N | G75: =AB59 -> 0.064152
E76: =Commodities!$C$34 -> GSC_N | G76: =EPAUS9RTechData!H66 -> 0
E77: =Commodities!$C$35 -> GSR_N | G77: =EPAUS9RTechData!H65 -> 0.544452
E78: =Commodities!$C$43 -> DSL_N | G78: =EPAUS9RTechData!H70 -> 0
E79: =Commodities!$C$44 -> DSU_N | G79: =EPAUS9RTechData!H71 -> 0.11618676
A80: *R1 | B80: PREFL | C80: Refinery-new limit | D80: DLG | E80: DSH_L | F80: 1 | G80: =AB58*1.25 -> 0.14523345 | H80: 2010 | I80: 40 | J80: 1 | K80: 1 | L80: =4.4 -> 4.4
A81: =IF(LEFT(A80,1)="*","*","") -> * | E81: RFL_L | G81: =AB59*1.25 -> 0.08019
A82: =IF(LEFT(A81,1)="*","*","") -> * | E82: =Commodities!C49 -> GSC_L | G82: =EPAUS9RTechData!H80 -> 0
A83: =IF(LEFT(A82,1)="*","*","") -> * | E83: =Commodities!C50 -> GSR_L | G83: =EPAUS9RTechData!H79 -> 0.7622328
A84: =IF(LEFT(A83,1)="*","*","") -> * | E84: =Commodities!C58 -> DSL_L | G84: =EPAUS9RTechData!H84 -> 0
A85: =IF(LEFT(A84,1)="*","*","") -> * | E85: =Commodities!C59 -> DSU_L | G85: =EPAUS9RTechData!H83 -> 0.30496566

Sheet RESID
A1: Table 1. Number and Capacity of Operable Petroleum Refineries by PAD District and State as of January 1, 2006
A2: From EIA Refinery Capacity Report
A3: http://www.eia.gov/pub/oil_gas/petroleum/data_publications/refinery_capacity_data/historical/2006/table1.pdf
A5: NYC
A7: PAD District | D7: NEMS Growth Rates
A8: and | D8: Start yr | E8: %/yr | G8: PJ/period
A9: State | B9: Barrels per Calender Day | C9: Region | I9: Region | J9: Capacity | K9: RESID (PJ/a)
A10: PAD District I................... 16 13 3 1,697,900 1,549,900 148,000 1,789,300 1,630,300 159,000 | B10: 1713100 | I10: R1
A11: Delaware ...................... 1 1 0 162,000 162,000 0 167,000 167,000 0 | B11: 181500 | C11: 5 | I11: R2 | J11: =SUM(B13,B14) -> 1425000 | K11: =J11*365*Conv!$C$47*10^-9*Conv!$I$6 -> 3248.4927 | L11: *In R2-R5, an IBOND is imposed corresponding to the fraction of the RESID retiring in each period. EIA projects no increase in capacity in these regions owing to siting difficulties.
A12: Georgia ........................ 2 1 1 33,400 5,400 28,000 40,000 8,000 32,000 | B12: 28000 | C12: 5 | I12: R3 | J12: =IF(A5="EPAUS9R",SUM(B18,B19,B22,B25,B28),0) -> 0 | K12: =J12*365*Conv!$C$47*10^-9*Conv!$I$6 -> 0
A13: New Jersey................... 6 4 2 667,000 547,000 120,000 696,000 569,000 127,000 | B13: 655000 | C13: 2 | I13: R4 | J13: =IF(A5="EPAUS9R",SUM(B23,B24,B20),0) -> 0 | K13: =J13*365*Conv!$C$47*10^-9*Conv!$I$6 -> 0
A14: Pennsylvania ................ 5 5 0 760,000 760,000 0 807,500 807,500 0 | B14: 770000 | C14: 2 | I14: R5 | J14: =IF(A5="EPAUS9R",SUM(B12,B15,B16,B11),0) -> 0 | K14: =J14*365*Conv!$C$47*10^-9*Conv!$I$6 -> 0
A15: Virginia ......................... 1 1 0 59,700 59,700 0 61,800 61,800 0 | B15: 58600 | C15: 5 | I15: R6 | J15: =IF(A5="EPAUS9R",SUM(B21,B27,B33,B30),0) -> 0 | K15: =J15*365*Conv!$C$47*10^-9*Conv!$I$6 -> 0
A16: West Virginia ................ 1 1 0 15,800 15,800 0 17,000 17,000 0 | B16: 20000 | C16: 5 | I16: R7 | J16: =IF(A5="EPAUS9R",SUM(B26,B31,B32,B35),0) -> 0 | K16: =J16*365*Conv!$C$47*10^-9*Conv!$I$6 -> 0
A17: PAD District II.................. 28 28 0 3,637,380 3,637,380 0 3,827,049 3,827,049 0 | B17: 3582640 | D17: 2025 | E17: =Capacity!E23/Capacity!E22 -> 0.027027027 | F17: =B17*E17 -> 96828.108 | G17: =F17*5*Conv!$C$47*10^-9*Conv!$I$6 -> 3.0237482 | I17: R8 | J17: =IF(A5="EPAUS9R",SUM(B37:B40,B45,B34),0) -> 0 | K17: =J17*365*Conv!$C$47*10^-9*Conv!$I$6 -> 0
A18: Illinois ........................... 6 6 0 1,017,885 1,017,885 0 1,069,000 1,069,000 0 | B18: 903500 | C18: 3 | I18: R9 | J18: =IF(A5="EPAUS9R",SUM(B42:B44,B47),0) -> 0 | K18: =J18*365*Conv!$C$47*10^-9*Conv!$I$6 -> 0
A19: Indiana ......................... 2 2 0 433,000 433,000 0 456,000 456,000 0 | B19: 433000 | C19: 3 | F19: R3 | G19: =G17*J24 -> 0 | I19: Total | J19: =SUM(J10:J18) -> 1425000 | K19: =SUM(K11:K18) -> 3248.4927 | M19: padd 1 | N19: padd 2 | O19: padd 3 | P19: R8 | Q19: R9
A20: Kansas ......................... 3 3 0 294,400 294,400 0 307,000 307,000 0 | B20: 299200 | C20: 4 | F20: R4 | G20: =G17*J25 -> 0 | M20: padd 1 | N20: padd 2 | O20: padd 3 | P20: padd 4 | Q20: padd 5
A21: Kentucky....................... 2 2 0 227,500 227,500 0 241,300 241,300 0 | B21: 227500 | C21: 6 | I21: R2 | J21: =J11/(J11+SUM(B12,B15,B16,B11)) -> 0.83182535 | K21: =J21*M21 -> 2074.6655 | M21: =Capacity!F3 -> 2494.1119 | N21: =Capacity!F4 -> 6901.1864 | O21: =Capacity!F5 -> 14663.505 | P21: =Capacity!F6 -> 1086.857 | Q21: =Capacity!F7 -> 4892.5752
A22: Michigan....................... 1 1 0 74,000 74,000 0 75,000 75,000 0 | B22: 100000 | C22: 3 | I22: R5 | J22: =J14/(J11+J14) -> 0 | K22: =J22*M21 -> 0
A23: Minnesota..................... 2 2 0 335,000 335,000 0 366,000 366,000 0 | B23: 349300 | C23: 4
A24: North Dakota ................ 1 1 0 58,000 58,000 0 60,000 60,000 0 | B24: 58000 | C24: 4 | I24: R3 | J24: =IF(A5="EPAUS9R",J12/(J12+J13),0) -> 0 | K24: =J24*N21 -> 0
A25: Ohio.............................. 4 4 0 525,500 525,500 0 539,000 539,000 0 | B25: 510900 | C25: 3 | I25: R4 | J25: =IF(A5="EPAUS9R",J13/(J12+J13),0) -> 0 | K25: =J25*N21 -> 0
A26: Oklahoma..................... 5 5 0 469,095 469,095 0 500,749 500,749 0 | B26: 486940 | C26: 7
A27: Tennessee.................... 1 1 0 170,000 170,000 0 175,000 175,000 0 | B27: 180000 | C27: 6 | I27: R6 | J27: =IF(A5="EPAUS9R",J15/(J15+J16),0) -> 0 | K27: =J27*O21 -> 0
A28: Wisconsin..................... 1 1 0 33,000 33,000 0 38,000 38,000 0 | B28: 34300 | C28: 3 | I28: R7 | J28: =IF(A5="EPAUS9R",J16/(J15+J16),0) -> 0 | K28: =J28*O21 -> 0
A29: PAD District III................. 56 55 1 7,586,485 7,559,485 27,000 8,036,012 8,007,012 29,000 | B29: 8274086 | D29: 2010 | E29: =Capacity!E29/Capacity!E28 -> 0.034883721 | F29: =B29*E29 -> 288630.91 | G29: =F29*5*Conv!$C$47*10^-9*Conv!$I$6 -> 9.013366 | I29: R8 | J29: =IF(A7="EPAUS9R",J17/(J17+J18),0) -> 0 | K29: =J29*O23 -> 0
A30: Alabama ....................... 3 3 0 130,000 130,000 0 138,000 138,000 0 | B30: 135300 | C30: 6 | I30: R9 | J30: =IF(A8="EPAUS9R",J18/(J18+J19),0) -> 0 | K30: =J30*O24 -> 0
A31: Arkansas ...................... 2 2 0 61,455 61,455 0 73,250 73,250 0 | B31: 77200 | C31: 7 | F31: R6 | G31: =G29*J27 -> 0
A32: Louisiana...................... 17 17 0 2,672,200 2,672,200 0 2,796,855 2,796,855 0 | B32: 2900883 | C32: 7 | F32: R7 | G32: =G29*J28 -> 0
A33: Mississippi .................... 4 4 0 334,800 334,800 0 393,300 393,300 0 | B33: 369800 | C33: 6
A34: New Mexico.................. 3 3 0 95,600 95,600 0 101,107 101,107 0 | B34: 112600 | C34: 8
A35: Texas ............................ 27 26 1 4,292,430 4,265,430 27,000 4,533,500 4,504,500 29,000 | B35: 4678303 | C35: 7
A36: PAD District IV ................ 16 15 1 554,476 543,476 11,000 585,600 573,100 12,500 | B36: 595550 | D36: 2010 | E36: 0 | F36: =B36*E36 -> 0 | G36: =F36*5*Conv!$C$47*10^-9*Conv!$I$6 -> 0
A37: Colorado....................... 2 2 0 84,500 84,500 0 92,000 92,000 0 | B37: 94000 | C37: 8
A38: Montana ....................... 4 4 0 166,590 166,590 0 174,800 174,800 0 | B38: 181200 | C38: 8
A39: Utah.............................. 5 4 1 163,000 152,000 11,000 172,500 160,000 12,500 | B39: 167350 | C39: 8
A40: Wyoming ...................... 5 5 0 140,386 140,386 0 146,300 146,300 0 | B40: 153000 | C40: 8
A41: PAD District V.................. 39 39 0 3,119,130 3,029,930 89,200 3,273,300 3,176,300 97,000 | B41: 3173438 | D41: 2020 | E41: 0 | F41: =B41*E41 -> 0 | G41: =F41*5*Conv!$C$47*10^-9*Conv!$I$6 -> 0
A42: Alaska........................... 6 6 0 358,400 358,400 0 390,200 390,200 0 | B42: 373500 | C42: 9
A43: California ...................... 23 23 0 1,999,150 1,919,150 80,000 2,092,100 2,005,100 87,000 | B43: 2026588 | C43: 9
A44: Hawaii........................... 2 2 0 147,500 147,500 0 152,000 152,000 0 | B44: 147500 | C44: 9
A45: Nevada ......................... 2 2 0 5,000 5,000 0 5,000 5,000 0 | B45: 2000 | C45: 8
A46: Oregon ......................... 1 1 0 0 0 0 0 0 0 | B46: 0 | C46: 9
A47: Washington .................. 5 5 0 609,080 599,880 9,200 634,000 624,000 10,000 | B47: 623850 | C47: 9
A48: U.S. Total.......................... 155 150 5 16,595,371 16,320,171 275,200 17,511,261 17,213,761 297,500 | B48: =B10+B17+B29+B36+B41 -> 17338814
A49: Puerto Rico .................. 3 0 3 87,000 0 87,000 94,000 0 94,000 | B49: 77900
A50: Virgin Islands................ 1 1 0 495,000 470,000 25,000 525,000 495,000 30,000 | B50: 495000
A52: Refineries (2005) | B52: 149

Sheet Capacity
A1: Residual Capacity
A2: (use year 2012) | B2: Capacity | C2: Capacity Used | D2: Process Loss | E2: Products not used in MARKAL | F2: RESIDS | H2: Barrels of Oil | I2: % of Capacity that is Crude Oil (98.7)
A3: PADD 1 | B3: =E19*Conv!$C$47*Conv!$I$6*365/1000 -> 3647.4304 | C3: =B3*Utilization!G4/100 -> 2622.6202 | D3: =C3*(1+(Yields!S31)/100) -> 2494.1119 | E3: =C3*(Yields!T31)/100 -> 0 | F3: =D3-E3 -> 2494.1119 | H3: =C3/F3 -> 1.0515247 | I3: =H3*0.987 -> 1.0378549
A4: PADD 2 | B4: =E25*Conv!$C$47*Conv!$I$6*365/1000 -> 8434.6828 | C4: =B4*Utilization!G7/100 -> 7712.9772 | D4: =C4*(1+(Yields!S48)/100) -> 7267.5528 | E4: =C4*(Yields!T48)/100 -> 366.36642 | F4: =D4-E4 -> 6901.1864 | H4: =C4/F4 -> 1.1176306 | I4: =H4*0.987 -> 1.1031014
A5: PADD 3 | B5: =E31*Conv!$C$47*Conv!$I$6*365/1000 -> 19604.938 | C5: =B5*Utilization!G10/100 -> 17225.85 | D5: =C5*(1+(Yields!S65)/100) -> 15938.218 | E5: =C5*(Yields!T65)/100 -> 1274.7129 | F5: =D5-E5 -> 14663.505 | H5: =C5/F5 -> 1.174743 | I5: =H5*0.987 -> 1.1594714
A6: PADD 4 | B6: =E37*Conv!$C$47*Conv!$I$6*365/1000 -> 1367.7864 | C6: =B6*Utilization!G13/100 -> 1199.9525 | D6: =C6*(1+(Yields!S82)/100) -> 1150.1545 | E6: =C6*(Yields!T82)/100 -> 63.297493 | F6: =D6-E6 -> 1086.857 | H6: =C6/F6 -> 1.1040574 | I6: =H6*0.987 -> 1.0897047
A7: PADD 5 | B7: =E43*Conv!$C$47*Conv!$I$6*365/1000 -> 7066.8964 | C7: =B7*Utilization!G16/100 -> 5672.5509 | D7: =C7*(1+(Yields!S99)/100) -> 5262.7091 | E7: =C7*(Yields!T99)/100 -> 370.13395 | F7: =D7-E7 -> 4892.5752 | H7: =C7/F7 -> 1.1594203 | I7: =H7*0.987 -> 1.1443478
A10: AEO 2012 Reference Case
A11: Domestic Refinery Distillation Base Capacity, Expansion, and Utilization, Reference case
A12: (million barrels per day)
A14: Region | B14: 2009 | C14: 2010 | D14: 2011 | E14: 2012 | F14: 2013 | G14: 2014 | H14: 2015 | I14: 2016 | J14: 2017 | K14: 2018 | L14: 2019 | M14: 2020 | N14: 2021 | O14: 2022 | P14: 2023 | Q14: 2024 | R14: 2025 | S14: 2026 | T14: 2027 | U14: 2028 | V14: 2029 | W14: 2030 | X14: 2031 | Y14: 2032 | Z14: 2033 | AA14: 2034 | AB14: 2035 | AC14: Growth Rate (2010-2035)
A15: PAD District I
A16: Base Capacity | B16: 1.7 | C16: 1.4 | D16: 1.6 | E16: 1.6 | F16: 1.6 | G16: 1.6 | H16: 1.6 | I16: 1.6 | J16: 1.6 | K16: 1.6 | L16: 1.6 | M16: 1.6 | N16: 1.6 | O16: 1.6 | P16: 1.6 | Q16: 1.6 | R16: 1.6 | S16: 1.6 | T16: 1.6 | U16: 1.6 | V16: 1.6 | W16: 1.6 | X16: 1.6 | Y16: 1.6 | Z16: 1.6 | AA16: 1.6 | AB16: 1.6 | AC16: 0.004
A17: Capacity Additions | B17: 0 | C17: 0 | D17: 0 | E17: 0 | F17: 0 | G17: 0 | H17: 0 | I17: 0 | J17: 0 | K17: 0 | L17: 0 | M17: 0 | N17: 0 | O17: 0 | P17: 0 | Q17: 0 | R17: 0 | S17: 0 | T17: 0 | U17: 0 | V17: 0 | W17: 0 | X17: 0 | Y17: 0 | Z17: 0 | AA17: 0 | AB17: 0 | AC17: - -
A18: Idled Capacity | B18: 0 | C18: 0 | D18: 0 | E18: 0.1 | F18: 0.1 | G18: 0.1 | H18: 0.1 | I18: 0.1 | J18: 0.3 | K18: 0.4 | L18: 0.5 | M18: 0.5 | N18: 0.5 | O18: 0.6 | P18: 0.6 | Q18: 0.6 | R18: 0.6 | S18: 0.6 | T18: 0.6 | U18: 0.6 | V18: 0.6 | W18: 0.6 | X18: 0.6 | Y18: 0.6 | Z18: 0.6 | AA18: 0.6 | AB18: 0.7 | AC18: - -
A19: Total Capacity | B19: 1.7 | C19: 1.4 | D19: 1.6 | E19: 1.6 | F19: 1.5 | G19: 1.5 | H19: 1.5 | I19: 1.5 | J19: 1.3 | K19: 1.2 | L19: 1.1 | M19: 1.1 | N19: 1 | O19: 1 | P19: 1 | Q19: 1 | R19: 1 | S19: 1 | T19: 1 | U19: 1 | V19: 1 | W19: 1 | X19: 1 | Y19: 1 | Z19: 1 | AA19: 1 | AB19: 0.9 | AC19: -0.018
A21: PAD District II
A22: Base Capacity | B22: 3.7 | C22: 3.7 | D22: 3.7 | E22: 3.7 | F22: 3.7 | G22: 3.7 | H22: 3.7 | I22: 3.7 | J22: 3.7 | K22: 3.7 | L22: 3.7 | M22: 3.7 | N22: 3.7 | O22: 3.7 | P22: 3.7 | Q22: 3.7 | R22: 3.7 | S22: 3.7 | T22: 3.7 | U22: 3.7 | V22: 3.7 | W22: 3.7 | X22: 3.7 | Y22: 3.7 | Z22: 3.7 | AA22: 3.7 | AB22: 3.7 | AC22: 0
A23: Capacity Additions | B23: 0 | C23: 0 | D23: 0 | E23: 0.1 | F23: 0.1 | G23: 0.1 | H23: 0.1 | I23: 0.1 | J23: 0.1 | K23: 0.1 | L23: 0.1 | M23: 0.1 | N23: 0.1 | O23: 0.1 | P23: 0.1 | Q23: 0.1 | R23: 0.1 | S23: 0.1 | T23: 0.1 | U23: 0.1 | V23: 0.1 | W23: 0.1 | X23: 0.1 | Y23: 0.1 | Z23: 0.1 | AA23: 0.1 | AB23: 0.1 | AC23: - -
A24: Idled Capacity | B24: 0 | C24: 0 | D24: 0.1 | E24: 0.1 | F24: 0.2 | G24: 0.2 | H24: 0.2 | I24: 0.3 | J24: 0.4 | K24: 0.5 | L24: 0.6 | M24: 0.8 | N24: 0.8 | O24: 0.8 | P24: 0.9 | Q24: 0.9 | R24: 0.9 | S24: 0.9 | T24: 0.9 | U24: 0.9 | V24: 0.9 | W24: 0.9 | X24: 0.9 | Y24: 0.9 | Z24: 0.9 | AA24: 0.9 | AB24: 0.9 | AC24: - -
A25: Total Capacity | B25: 3.7 | C25: 3.7 | D25: 3.7 | E25: 3.7 | F25: 3.7 | G25: 3.6 | H25: 3.6 | I25: 3.5 | J25: 3.4 | K25: 3.3 | L25: 3.2 | M25: 3 | N25: 3 | O25: 3 | P25: 3 | Q25: 2.9 | R25: 2.9 | S25: 2.9 | T25: 2.9 | U25: 2.9 | V25: 2.9 | W25: 2.9 | X25: 2.9 | Y25: 2.9 | Z25: 2.9 | AA25: 2.9 | AB25: 2.9 | AC25: -0.01
A27: PAD District III
A28: Base Capacity | B28: 8.4 | C28: 8.6 | D28: 8.6 | E28: 8.6 | F28: 8.6 | G28: 8.6 | H28: 8.6 | I28: 8.6 | J28: 8.6 | K28: 8.6 | L28: 8.6 | M28: 8.6 | N28: 8.6 | O28: 8.6 | P28: 8.6 | Q28: 8.6 | R28: 8.6 | S28: 8.6 | T28: 8.6 | U28: 8.6 | V28: 8.6 | W28: 8.6 | X28: 8.6 | Y28: 8.6 | Z28: 8.6 | AA28: 8.6 | AB28: 8.6 | AC28: 0
A29: Capacity Additions | B29: 0 | C29: 0 | D29: 0 | E29: 0.3 | F29: 0.3 | G29: 0.3 | H29: 0.3 | I29: 0.3 | J29: 0.3 | K29: 0.3 | L29: 0.3 | M29: 0.3 | N29: 0.3 | O29: 0.3 | P29: 0.3 | Q29: 0.3 | R29: 0.3 | S29: 0.3 | T29: 0.3 | U29: 0.3 | V29: 0.3 | W29: 0.3 | X29: 0.3 | Y29: 0.3 | Z29: 0.3 | AA29: 0.3 | AB29: 0.3 | AC29: - -
A30: Idled Capacity | B30: 0 | C30: 0 | D30: 0.1 | E30: 0.1 | F30: 0.2 | G30: 0.2 | H30: 0.2 | I30: 0.3 | J30: 0.4 | K30: 0.5 | L30: 0.5 | M30: 0.9 | N30: 0.9 | O30: 0.9 | P30: 0.9 | Q30: 0.9 | R30: 0.9 | S30: 0.9 | T30: 0.9 | U30: 1 | V30: 1 | W30: 1.1 | X30: 1.2 | Y30: 1.3 | Z30: 1.3 | AA30: 1.3 | AB30: 1.3 | AC30: - -
A31: Total Capacity | B31: 8.4 | C31: 8.6 | D31: 8.6 | E31: 8.6 | F31: 8.8 | G31: 8.8 | H31: 8.7 | I31: 8.7 | J31: 8.5 | K31: 8.4 | L31: 8.4 | M31: 8.1 | N31: 8.1 | O31: 8.1 | P31: 8.1 | Q31: 8.1 | R31: 8 | S31: 8 | T31: 8 | U31: 8 | V31: 7.9 | W31: 7.8 | X31: 7.8 | Y31: 7.7 | Z31: 7.7 | AA31: 7.7 | AB31: 7.7 | AC31: -0.005
A33: PAD District IV
A34: Base Capacity | B34: 0.6 | C34: 0.6 | D34: 0.6 | E34: 0.6 | F34: 0.6 | G34: 0.6 | H34: 0.6 | I34: 0.6 | J34: 0.6 | K34: 0.6 | L34: 0.6 | M34: 0.6 | N34: 0.6 | O34: 0.6 | P34: 0.6 | Q34: 0.6 | R34: 0.6 | S34: 0.6 | T34: 0.6 | U34: 0.6 | V34: 0.6 | W34: 0.6 | X34: 0.6 | Y34: 0.6 | Z34: 0.6 | AA34: 0.6 | AB34: 0.6 | AC34: 0
A35: Capacity Additions | B35: 0 | C35: 0 | D35: 0 | E35: 0 | F35: 0 | G35: 0 | H35: 0 | I35: 0 | J35: 0 | K35: 0 | L35: 0 | M35: 0 | N35: 0 | O35: 0 | P35: 0 | Q35: 0 | R35: 0 | S35: 0 | T35: 0 | U35: 0 | V35: 0 | W35: 0 | X35: 0 | Y35: 0 | Z35: 0 | AA35: 0 | AB35: 0 | AC35: - -
A36: Idled Capacity | B36: 0 | C36: 0 | D36: 0 | E36: 0 | F36: 0 | G36: 0 | H36: 0 | I36: 0 | J36: 0.1 | K36: 0.1 | L36: 0.1 | M36: 0.1 | N36: 0.1 | O36: 0.1 | P36: 0.1 | Q36: 0.1 | R36: 0.1 | S36: 0.1 | T36: 0.1 | U36: 0.1 | V36: 0.1 | W36: 0.1 | X36: 0.1 | Y36: 0.1 | Z36: 0.1 | AA36: 0.1 | AB36: 0.1 | AC36: - -
A37: Total Capacity | B37: 0.6 | C37: 0.6 | D37: 0.6 | E37: 0.6 | F37: 0.6 | G37: 0.6 | H37: 0.6 | I37: 0.6 | J37: 0.5 | K37: 0.5 | L37: 0.5 | M37: 0.5 | N37: 0.5 | O37: 0.5 | P37: 0.5 | Q37: 0.5 | R37: 0.5 | S37: 0.5 | T37: 0.5 | U37: 0.5 | V37: 0.5 | W37: 0.5 | X37: 0.5 | Y37: 0.5 | Z37: 0.5 | AA37: 0.5 | AB37: 0.5 | AC37: -0.01
A39: PAD District V
A40: Base Capacity | B40: 3.2 | C40: 3.2 | D40: 3.1 | E40: 3.1 | F40: 3.1 | G40: 3.1 | H40: 3.1 | I40: 3.1 | J40: 3.1 | K40: 3.1 | L40: 3.1 | M40: 3.1 | N40: 3.1 | O40: 3.1 | P40: 3.1 | Q40: 3.1 | R40: 3.1 | S40: 3.1 | T40: 3.1 | U40: 3.1 | V40: 3.1 | W40: 3.1 | X40: 3.1 | Y40: 3.1 | Z40: 3.1 | AA40: 3.1 | AB40: 3.1 | AC40: -0.001
A41: Capacity Additions | B41: 0 | C41: 0 | D41: 0 | E41: 0 | F41: 0 | G41: 0 | H41: 0 | I41: 0 | J41: 0 | K41: 0 | L41: 0 | M41: 0 | N41: 0 | O41: 0 | P41: 0 | Q41: 0 | R41: 0 | S41: 0 | T41: 0 | U41: 0 | V41: 0 | W41: 0.1 | X41: 0.1 | Y41: 0.1 | Z41: 0.1 | AA41: 0.1 | AB41: 0.2 | AC41: - -
A42: Idled Capacity | B42: 0 | C42: 0 | D42: 0 | E42: 0 | F42: 0 | G42: 0 | H42: 0 | I42: 0 | J42: 0 | K42: 0 | L42: 0 | M42: 0 | N42: 0 | O42: 0 | P42: 0 | Q42: 0 | R42: 0 | S42: 0 | T42: 0 | U42: 0 | V42: 0 | W42: 0 | X42: 0 | Y42: 0 | Z42: 0 | AA42: 0 | AB42: 0 | AC42: - -
A43: Total Capacity | B43: 3.2 | C43: 3.2 | D43: 3.1 | E43: 3.1 | F43: 3.1 | G43: 3.1 | H43: 3.1 | I43: 3.1 | J43: 3.1 | K43: 3.1 | L43: 3.1 | M43: 3.1 | N43: 3.1 | O43: 3.1 | P43: 3.1 | Q43: 3.1 | R43: 3.1 | S43: 3.1 | T43: 3.1 | U43: 3.1 | V43: 3.1 | W43: 3.2 | X43: 3.2 | Y43: 3.2 | Z43: 3.2 | AA43: 3.2 | AB43: 3.2 | AC43: 0
A45: United States
A46: Base Capacity | B46: 17.7 | C46: 17.6 | D46: 17.7 | E46: 17.7 | F46: 17.7 | G46: 17.7 | H46: 17.7 | I46: 17.7 | J46: 17.7 | K46: 17.7 | L46: 17.7 | M46: 17.7 | N46: 17.7 | O46: 17.7 | P46: 17.7 | Q46: 17.7 | R46: 17.7 | S46: 17.7 | T46: 17.7 | U46: 17.7 | V46: 17.7 | W46: 17.7 | X46: 17.7 | Y46: 17.7 | Z46: 17.7 | AA46: 17.7 | AB46: 17.7 | AC46: 0
A47: Capacity Additions | B47: 0 | C47: 0 | D47: 0 | E47: 0.4 | F47: 0.4 | G47: 0.4 | H47: 0.4 | I47: 0.4 | J47: 0.4 | K47: 0.4 | L47: 0.4 | M47: 0.4 | N47: 0.4 | O47: 0.4 | P47: 0.4 | Q47: 0.4 | R47: 0.4 | S47: 0.4 | T47: 0.4 | U47: 0.4 | V47: 0.5 | W47: 0.6 | X47: 0.6 | Y47: 0.6 | Z47: 0.5 | AA47: 0.6 | AB47: 0.6 | AC47: - -
A48: Idled Capacity | B48: 0 | C48: 0 | D48: 0.3 | E48: 0.4 | F48: 0.4 | G48: 0.5 | H48: 0.6 | I48: 0.8 | J48: 1.3 | K48: 1.6 | L48: 1.8 | M48: 2.3 | N48: 2.4 | O48: 2.4 | P48: 2.5 | Q48: 2.5 | R48: 2.6 | S48: 2.6 | T48: 2.6 | U48: 2.7 | V48: 2.7 | W48: 2.8 | X48: 2.9 | Y48: 2.9 | Z48: 2.9 | AA48: 2.9 | AB48: 3 | AC48: - -
A49: Total Capacity | B49: 17.7 | C49: 17.6 | D49: 17.7 | E49: 17.7 | F49: 17.6 | G49: 17.6 | H49: 17.5 | I49: 17.3 | J49: 16.8 | K49: 16.5 | L49: 16.3 | M49: 15.8 | N49: 15.7 | O49: 15.7 | P49: 15.6 | Q49: 15.6 | R49: 15.5 | S49: 15.5 | T49: 15.5 | U49: 15.4 | V49: 15.4 | W49: 15.4 | X49: 15.4 | Y49: 15.3 | Z49: 15.3 | AA49: 15.3 | AB49: 15.2 | AC49: -0.006
A51: PAD = Petroleum Administration for Defense.
A52: - - = Not applicable.
A53: Note: Base capacity is operable capacity for the beginning of the year. Capacity additions are cumulative
A54: additions after December 31, 2010.
A55: Source: 2010: U.S. Energy Information Administration (EIA), Petroleum Supply Annual
A56: 2010, DOE/EIA-0340(2010)/1 (Washington, DC, July 2011). 2009: EIA, Petroleum Supply Annual
A57: 2009, DOE/EIA-0340(2009)/1 (Washington, DC, July 2010). Projections: EIA,
A58: AEO2012 National Energy Modeling System.

Sheet PADD Products
B1: 1 | C1: 2 | D1: 3 | E1: 4 | F1: 5 | I1: 1 | J1: 2 | K1: 3 | L1: 4 | M1: 5
B2: PADD1 | C2: PADD2 | D2: PADD3 | E2: PADD4 | F2: PADD5 | I2: PADD1 | J2: PADD2 | K2: PADD3 | L2: PADD4 | M2: PADD5
A3: LPG_E | B3: {=SUM(IF(Yields!$A$4:$A$99=1,Yields!$C$4:$C$99,0))} -> 3.46 | C3: {=SUM(IF(Yields!$A$4:$A$99=2,Yields!$C$4:$C$99,0))} -> 3.375 | D3: {=SUM(IF(Yields!$A$4:$A$99=3,Yields!$C$4:$C$99,0))} -> 5.225 | E3: {=SUM(IF(Yields!$A$4:$A$99=4,Yields!$C$4:$C$99,0))} -> 1.75 | F3: {=SUM(IF(Yields!$A$4:$A$99=5,Yields!$C$4:$C$99,0))} -> 2.675 | H3: LPG_E | I3: =B3*1.08 -> 3.7368 | J3: =C3*1.08 -> 3.645 | K3: =D3*1.08 -> 5.643 | L3: =E3*1.08 -> 1.89 | M3: =F3*1.08 -> 2.889
A4: GSR_E | B4: {=SUM(IF(Yields!$A$4:$A$99=1,Yields!$D$4:$D$99,0))} -> 46.14 | C4: {=SUM(IF(Yields!$A$4:$A$99=2,Yields!$D$4:$D$99,0))} -> 50.325 | D4: {=SUM(IF(Yields!$A$4:$A$99=3,Yields!$D$4:$D$99,0))} -> 42.15 | E4: {=SUM(IF(Yields!$A$4:$A$99=4,Yields!$D$4:$D$99,0))} -> 47.825 | F4: {=SUM(IF(Yields!$A$4:$A$99=5,Yields!$D$4:$D$99,0))} -> 47.2 | H4: GSR_E | I4: =B4*1.18 -> 54.4452 | J4: =C4*1.18 -> 59.3835 | K4: =D4*1.18 -> 49.737 | L4: =E4*1.18 -> 56.4335 | M4: =F4*1.18 -> 55.696
A5: GSC_E | H5: GSC_E | I5: =B5*1.08 -> 0 | J5: =C5*1.08 -> 0 | K5: =D5*1.08 -> 0 | L5: =E5*1.08 -> 0 | M5: =F5*1.08 -> 0
A6: JTF_E | B6: {=SUM(IF(Yields!$A$4:$A$99=1,Yields!$F$4:$F$99,0))} -> 5.66 | C6: {=SUM(IF(Yields!$A$4:$A$99=2,Yields!$F$4:$F$99,0))} -> 6.55 | D6: {=SUM(IF(Yields!$A$4:$A$99=3,Yields!$F$4:$F$99,0))} -> 9.275 | E6: {=SUM(IF(Yields!$A$4:$A$99=4,Yields!$F$4:$F$99,0))} -> 4.925 | F6: {=SUM(IF(Yields!$A$4:$A$99=5,Yields!$F$4:$F$99,0))} -> 16.8 | H6: JTF_E | I6: =B6*1.08 -> 6.1128 | J6: =C6*1.08 -> 7.074 | K6: =D6*1.08 -> 10.017 | L6: =E6*1.08 -> 5.319 | M6: =F6*1.08 -> 18.144
A7: KER_E | B7: {=SUM(IF(Yields!$A$4:$A$99=1,Yields!$G$4:$G$99,0))} -> 0.38 | C7: {=SUM(IF(Yields!$A$4:$A$99=2,Yields!$G$4:$G$99,0))} -> 0.025 | D7: {=SUM(IF(Yields!$A$4:$A$99=3,Yields!$G$4:$G$99,0))} -> 0.075 | E7: {=SUM(IF(Yields!$A$4:$A$99=4,Yields!$G$4:$G$99,0))} -> 0.25 | F7: {=SUM(IF(Yields!$A$4:$A$99=5,Yields!$G$4:$G$99,0))} -> 0.025 | H7: KER_E | I7: =B7*1.08 -> 0.4104 | J7: =C7*1.08 -> 0.027 | K7: =D7*1.08 -> 0.081 | L7: =E7*1.08 -> 0.27 | M7: =F7*1.08 -> 0.027
A8: DSU_E | B8: {=SUM(IF(Yields!$A$4:$A$99=1,Yields!$H$4:$H$99,0))*(1-'DSH percent'!Q2)} -> 18.941966 | C8: {=SUM(IF(Yields!$A$4:$A$99=2,Yields!$H$4:$H$99,0))*(1-'DSH percent'!Q3)} -> 28.805417 | D8: {=SUM(IF(Yields!$A$4:$A$99=3,Yields!$H$4:$H$99,0))*(1-'DSH percent'!Q4)} -> 26.332062 | E8: {=SUM(IF(Yields!$A$4:$A$99=4,Yields!$H$4:$H$99,0))} -> 32.025 | F8: {=SUM(IF(Yields!$A$4:$A$99=5,Yields!$H$4:$H$99,0))*(1-'DSH percent'!Q6)} -> 19.606299 | H8: DSU_E | I8: =B8*1.15 -> 21.783261 | J8: =C8*1.15 -> 33.126229 | K8: =D8*1.15 -> 30.281872 | L8: =E8*1.15 -> 36.82875 | M8: =F8*1.15 -> 22.547244
A9: DSL_E | H9: DSL_E | I9: =B9*1.08 -> 0 | J9: =C9*1.08 -> 0 | K9: =D9*1.08 -> 0 | L9: =E9*1.08 -> 0 | M9: =F9*1.08 -> 0
A10: DSH_E | B10: {=SUM(IF(Yields!$A$4:$A$99=1,Yields!$H$4:$H$99,0))*'DSH percent'!Q2} -> 10.758034 | C10: {=SUM(IF(Yields!$A$4:$A$99=2,Yields!$H$4:$H$99,0))*'DSH percent'!Q3} -> 0.19458322 | D10: {=SUM(IF(Yields!$A$4:$A$99=3,Yields!$H$4:$H$99,0))*'DSH percent'!Q4} -> 2.4679377 | E10: 0 | F10: {=SUM(IF(Yields!$A$4:$A$99=5,Yields!$H$4:$H$99,0))*'DSH percent'!Q6} -> 1.6187012 | H10: DSH_E | I10: =B10*1.08 -> 11.618676 | J10: =C10*1.08 -> 0.21014988 | K10: =D10*1.08 -> 2.6653728 | L10: =E10*1.08 -> 0 | M10: =F10*1.08 -> 1.7481973
A11: RFL_E | B11: {=SUM(IF(Yields!$A$4:$A$99=1,Yields!$I$4:$I$99,0))} -> 5.94 | C11: {=SUM(IF(Yields!$A$4:$A$99=2,Yields!$I$4:$I$99,0))} -> 1.45 | D11: {=SUM(IF(Yields!$A$4:$A$99=3,Yields!$I$4:$I$99,0))} -> 4 | E11: {=SUM(IF(Yields!$A$4:$A$99=4,Yields!$I$4:$I$99,0))} -> 1.8 | F11: {=SUM(IF(Yields!$A$4:$A$99=5,Yields!$I$4:$I$99,0))} -> 5.325 | H11: RFL_E | I11: =B11*1.08 -> 6.4152 | J11: =C11*1.08 -> 1.566 | K11: =D11*1.08 -> 4.32 | L11: =E11*1.08 -> 1.944 | M11: =F11*1.08 -> 5.751
A12: RFH_E | H12: RFH_E | I12: =I11 -> 6.4152 | J12: =J11 -> 1.566 | K12: =K11 -> 4.32 | L12: =L11 -> 1.944 | M12: =M11 -> 5.751
A13: PFS_E | B13: {=SUM(IF(Yields!$A$4:$A$99=1,Yields!$J$4:$J$99,0))+SUM(IF(Yields!$A$4:$A$99=1,Yields!$K$4:$K$99,0))} -> 0.76 | C13: {=SUM(IF(Yields!$A$4:$A$99=2,Yields!$J$4:$J$99,0))+SUM(IF(Yields!$A$4:$A$99=2,Yields!$K$4:$K$99,0))} -> 1.025 | D13: {=SUM(IF(Yields!$A$4:$A$99=3,Yields!$J$4:$J$99,0))+SUM(IF(Yields!$A$4:$A$99=3,Yields!$K$4:$K$99,0))} -> 3.6 | E13: {=SUM(IF(Yields!$A$4:$A$99=4,Yields!$J$4:$J$99,0))+SUM(IF(Yields!$A$4:$A$99=4,Yields!$K$4:$K$99,0))} -> 0.15 | F13: {=SUM(IF(Yields!$A$4:$A$99=5,Yields!$J$4:$J$99,0))+SUM(IF(Yields!$A$4:$A$99=5,Yields!$K$4:$K$99,0))} -> 0.066666667 | H13: PFS_E | I13: =B13*1.08 -> 0.8208 | J13: =C13*1.08 -> 1.107 | K13: =D13*1.08 -> 3.888 | L13: =E13*1.08 -> 0.162 | M13: =F13*1.08 -> 0.072
A14: PTC_E | B14: {=SUM(IF(Yields!$A$4:$A$99=1,Yields!$O$4:$O$99,0))} -> 3.1 | C14: {=SUM(IF(Yields!$A$4:$A$99=2,Yields!$O$4:$O$99,0))} -> 4.35 | D14: {=SUM(IF(Yields!$A$4:$A$99=3,Yields!$O$4:$O$99,0))} -> 6 | E14: {=SUM(IF(Yields!$A$4:$A$99=4,Yields!$O$4:$O$99,0))} -> 4.375 | F14: {=SUM(IF(Yields!$A$4:$A$99=5,Yields!$O$4:$O$99,0))} -> 6.15 | H14: PTC_E | I14: =B14*1.08 -> 3.348 | J14: =C14*1.08 -> 4.698 | K14: =D14*1.08 -> 6.48 | L14: =E14*1.08 -> 4.725 | M14: =F14*1.08 -> 6.642
A15: ASP_E | B15: {=SUM(IF(Yields!$A$4:$A$99=1,Yields!$P$4:$P$99,0))} -> 4.98 | C15: {=SUM(IF(Yields!$A$4:$A$99=2,Yields!$P$4:$P$99,0))} -> 4.95 | D15: {=SUM(IF(Yields!$A$4:$A$99=3,Yields!$P$4:$P$99,0))} -> 1.125 | E15: {=SUM(IF(Yields!$A$4:$A$99=4,Yields!$P$4:$P$99,0))} -> 5.875 | F15: {=SUM(IF(Yields!$A$4:$A$99=5,Yields!$P$4:$P$99,0))} -> 1.275 | H15: ASP_E | I15: =B15*1.08 -> 5.3784 | J15: =C15*1.08 -> 5.346 | K15: =D15*1.08 -> 1.215 | L15: =E15*1.08 -> 6.345 | M15: =F15*1.08 -> 1.377
B16: =SUM(B3:B15) -> 100.12 | C16: =SUM(C3:C15) -> 101.05 | D16: =SUM(D3:D15) -> 100.25 | E16: =SUM(E3:E15) -> 98.975 | F16: =SUM(F3:F15) -> 100.74167 | I16: =SUM(I3:I15) -> 120.48474 | J16: =SUM(J3:J15) -> 117.74888 | K16: =SUM(K3:K15) -> 118.64824 | L16: =SUM(L3:L15) -> 115.86125 | M16: =SUM(M3:M15) -> 120.64444

Sheet Yields
B1: Back to Contents | C1: Data 1: PADD 1 Refinery Yield
B2: Sourcekey | C2: MLRRYP13 | D2: MGFRYP13 | E2: MGARYP13 | F2: MKJRYP13 | G2: MKERYP13 | H2: MDIRYP13 | I2: MRERYP13 | J2: MNFRYP13 | K2: MOTRYP13 | L2: MNSRYP13 | M2: MLURYP13 | N2: MWXRYP13 | O2: MCKRYP13 | P2: MAPRYP13 | Q2: MSGRYP13 | R2: MMSRYP13 | S2: MPGRYP13
A3: PADD | B3: Date | C3: East Coast (PADD 1) Refinery Yield of Liquified Petroleum Gases (Percent) | D3: East Coast (PADD 1) Refinery Yield of Finished Motor Gasoline (Percent) | E3: East Coast (PADD 1) Refinery Yield of Aviation Gasoline (Percent) | F3: East Coast (PADD 1) Refinery Yield of Kerosene-Type Jet Fuel (Percent) | G3: East Coast (PADD 1) Refinery Yield of Kerosene (Percent) | H3: East Coast (PADD 1) Refinery Yield of Distillate Fuel Oil (Percent) | I3: East Coast (PADD 1) Refinery Yield of Residual Fuel Oil (Percent) | J3: East Coast (PADD 1) Refinery Yield of Naphtha for Petrochemical Feedstock Use (Percent) | K3: East Coast (PADD 1) Refinery Yield of Other Oils for Petrochemical Feedstock Use (Percent) | L3: East Coast (PADD 1) Refinery Yield of Special Naphthas (Percent) | M3: East Coast (PADD 1) Refinery Yield of Lubricants (Percent) | N3: East Coast (PADD 1) Refinery Yield of Waxes (Percent) | O3: East Coast (PADD 1) Refinery Yield of Petroleum Coke (Percent) | P3: East Coast (PADD 1) Refinery Yield of Asphalt and Road Oil (Percent) | Q3: East Coast (PADD 1) Refinery Yield of Still Gas (Percent) | R3: East Coast (PADD 1) Refinery Yield of Miscellaneous Petroleum Products (Percent) | S3: East Coast (PADD 1) Refinery Processing Gain (Percent)
C4: LPG | D4: GSL | F4: JTF | G4: KER | H4: DSL | I4: RFL | J4: PFS | K4: PFS | O4: PTC | P4: ASP
B5: 37802 | C5: 3 | D5: 46.4 | E5: 0.2 | F5: 5.2 | G5: 0.8 | H5: 27.2 | I5: 7.8 | J5: 0.8 | L5: 0.1 | M5: 1 | N5: 0 | O5: 2.9 | P5: 5.7 | Q5: 3.8 | R5: 0.1 | S5: -5 | T5: =SUM(C5:R5) -> 105
B6: 38168 | C6: 2.6 | D6: 46.5 | E6: 0.4 | F6: 6.1 | G6: 0.7 | H6: 26.6 | I6: 6.9 | J6: 0.8 | L6: 0.1 | M6: 1.1 | N6: 0 | O6: 3.1 | P6: 6.2 | Q6: 3.9 | R6: 0.1 | S6: -5.3 | T6: =SUM(C6:R6) -> 105.1
B7: 38533 | C7: 2.4 | D7: 46.6 | E7: 0.3 | F7: 5.7 | G7: 0.7 | H7: 28.8 | I7: 6.2 | J7: 0.8 | L7: 0.1 | M7: 1 | N7: 0 | O7: 2.9 | P7: 5.7 | Q7: 3.8 | R7: 0.1 | S7: -5.1 | T7: =SUM(C7:R7) -> 105.1
B8: 38898 | C8: 2.6 | D8: 45.8 | F8: 5.1 | G8: 0.4 | H8: 29.2 | I8: 7.1 | J8: 1.1 | L8: 0.1 | M8: 1.1 | N8: 0 | O8: 3 | P8: 5.6 | Q8: 3.6 | R8: 0.2 | S8: -4.9 | T8: =SUM(C8:R8) -> 104.9
B9: 39263 | C9: 3.2 | D9: 45.5 | E9: 0.1 | F9: 5 | G9: 0.5 | H9: 29.4 | I9: 7.2 | J9: 1.1 | L9: 0 | M9: 1 | N9: 0 | O9: 3.2 | P9: 5 | Q9: 3.9 | R9: 0.2 | S9: -5.1 | T9: =SUM(C9:R9) -> 105.3
B10: 39629 | C10: 3.3 | D10: 44.6 | E10: 0.1 | F10: 5.7 | G10: 0.6 | H10: 29.6 | I10: 7.1 | J10: 1.1 | L10: 0 | M10: 1.1 | N10: 0.1 | O10: 3.3 | P10: 5.1 | Q10: 3.8 | R10: 0.2 | S10: -5.4 | T10: =SUM(C10:R10) -> 105.7
B11: 39994 | C11: 3.4 | D11: 47 | E11: 0.1 | F11: 5.3 | G11: 0.6 | H11: 27.7 | I11: 7.4 | J11: 0.9 | K11: 0 | L11: 0.1 | M11: 1 | N11: 0.1 | O11: 2.9 | P11: 4.8 | Q11: 3.2 | R11: 0.1 | S11: -4.3 | T11: =SUM(C11:R11) -> 104.6
B12: 40359 | C12: 3.3 | D12: 46.7 | E12: 0.1 | F12: 5.7 | G12: 0.4 | H12: 29.9 | I12: 5.4 | J12: 0.8 | K12: 0 | L12: 0.1 | M12: 1.1 | N12: 0 | O12: 2.8 | P12: 5.1 | Q12: 3.2 | R12: 0.1 | S12: -4.7 | T12: =SUM(C12:R12) -> 104.7
B13: 40724 | C13: 3.7 | D13: 46.2 | E13: 0.1 | F13: 6.8 | G13: 0.2 | H13: 30 | I13: 4.9 | J13: 0.6 | K13: 0 | L13: 0.1 | M13: 1.2 | N13: 0 | O13: 3.1 | P13: 4.8 | Q13: 3.3 | R13: 0.2 | S13: -5 | T13: =SUM(C13:R13) -> 105.2
B14: 41090 | C14: 3.6 | D14: 46.2 | E14: 0.1 | F14: 4.8 | G14: 0.1 | H14: 31.3 | I14: 4.9 | J14: 0.4 | K14: 0 | L14: 0.1 | M14: 1.3 | N14: 0 | O14: 3.4 | P14: 5.1 | Q14: 3.6 | R14: 0.3 | S14: -5.1
B15: 41455 | C15: 3.3 | D15: 45 | E15: 0.1 | F15: 6.4 | G15: 0.2 | H15: 31.3 | I15: 5.8 | J15: 0.3 | K15: 0 | L15: 0.1 | M15: 1.3 | N15: 0 | O15: 2.8 | P15: 4.5 | Q15: 3.4 | R15: 0.2 | S15: -4.5
B16: 41820 | C16: 3.5 | D16: 46.3 | E16: 0.1 | F16: 8 | G16: 0.5 | H16: 28.9 | I16: 4.8 | J16: 0.3 | K16: 0 | L16: 0.1 | M16: 1.1 | N16: 0 | O16: 2.8 | P16: 4.4 | Q16: 3.5 | R16: 0.3 | S16: -4.5
B17: 42185 | C17: 3.3 | D17: 46.7 | E17: 0.1 | F17: 8.1 | G17: 0.3 | H17: 28.8 | I17: 4.1 | J17: 0.4 | K17: 0 | L17: 0.1 | M17: 1 | N17: 0 | O17: 3 | P17: 4.7 | Q17: 3.6 | R17: 0.2 | S17: -4.3
B18: 42551 | C18: 2.6 | D18: 47.5 | E18: 0.1 | F18: 7.6 | G18: 0.2 | H18: 29 | I18: 4.1 | J18: 0.4 | K18: 0 | L18: 0.1 | M18: 1.1 | N18: 0 | O18: 3.1 | P18: 4.5 | Q18: 3.6 | R18: 0.2 | S18: -4
B19: 42916 | C19: 2.8 | D19: 48.6 | E19: 0.1 | F19: 8.1 | G19: 0.3 | H19: 28.7 | I19: 3.9 | J19: 0.3 | K19: 0 | L19: 0.1 | M19: 1.1 | N19: 0 | O19: 3.1 | P19: 3.4 | Q19: 3.7 | R19: 0.3 | S19: -4.3
B20: 43281 | C20: 3.3 | D20: 46.6 | E20: 0.1 | F20: 8.2 | G20: 0.4 | H20: 29.5 | I20: 4.4 | J20: 0.3 | K20: 0 | L20: 0.1 | M20: 1.2 | N20: 0.1 | O20: 3.1 | P20: 3.1 | Q20: 4 | R20: 0.3 | S20: -4.4
B21: 43646 | C21: 3.3 | D21: 47.2 | E21: 0.1 | F21: 10.3 | G21: 0.3 | H21: 27.7 | I21: 3.6 | J21: 0.1 | K21: 0 | L21: 0.1 | M21: 1.3 | N21: 0 | O21: 2.8 | P21: 3.7 | Q21: 4.1 | R21: 0.3 | S21: -4.8
B22: 44012 | C22: 2.8 | D22: 50.7 | E22: 0.1 | F22: 4.7 | G22: 0.4 | H22: 27.7 | I22: 4.6 | J22: 0 | K22: 0 | L22: 0.1 | M22: 1.6 | N22: -0.1 | O22: 3.2 | P22: 4.9 | Q22: 4.2 | R22: 0.4 | S22: -5.2
B23: 44377 | C23: 2.9 | D23: 51.2 | E23: 0.1 | F23: 7.8 | G23: 0.2 | H23: 24.9 | I23: 5.6 | J23: 0 | K23: 0 | L23: 0.1 | M23: 1.6 | N23: -0.1 | O23: 3 | P23: 4.3 | Q23: 3.9 | R23: 0.4 | S23: -5.8
B24: 44742 | C24: 2.7 | D24: 46.1 | E24: 0.1 | F24: 11.4 | G24: 0.3 | H24: 26.2 | I24: 5.4 | J24: 0 | K24: 0 | L24: 0 | M24: 1.6 | N24: 0 | O24: 2.9 | P24: 4.1 | Q24: 3.5 | R24: 0.4 | S24: -4.6
B30: 2005 | C30: =AVERAGE(C5:C9) -> 2.76 | D30: =AVERAGE(D5:D9) -> 46.16 | E30: =AVERAGE(E5:E9) -> 0.25 | F30: =AVERAGE(F5:F9) -> 5.42 | G30: =AVERAGE(G5:G9) -> 0.62 | H30: =AVERAGE(H5:H9) -> 28.24 | I30: =AVERAGE(I5:I9) -> 7.04 | J30: =AVERAGE(J5:J9) -> 0.92 | L30: =AVERAGE(L5:L9) -> 0.08 | M30: =AVERAGE(M5:M9) -> 1.04 | N30: =AVERAGE(N5:N9) -> 0 | O30: =AVERAGE(O5:O9) -> 3.02 | P30: =AVERAGE(P5:P9) -> 5.64 | Q30: =AVERAGE(Q5:Q9) -> 3.8 | R30: =AVERAGE(R5:R9) -> 0.14 | S30: =AVERAGE(S5:S9) -> -5.08 | T30: =E30+L30+M30+N30+Q30+R30 -> 5.31
A31: 1 | B31: 2010 | C31: =AVERAGE(C10:C14) -> 3.46 | D31: =AVERAGE(D10:D14) -> 46.14 | E31: =AVERAGE(E10:E14) -> 0.1 | F31: =AVERAGE(F10:F14) -> 5.66 | G31: =AVERAGE(G10:G14) -> 0.38 | H31: =AVERAGE(H10:H14) -> 29.7 | I31: =AVERAGE(I10:I14) -> 5.94 | J31: =AVERAGE(J10:J14) -> 0.76 | ... S31: =AVERAGE(S10:S14) -> -4.9
B32: 2015 | C32: =AVERAGE(C15:C19) -> 3.1 | D32: =AVERAGE(D15:D19) -> 46.82 | E32: =AVERAGE(E15:E19) -> 0.1 | F32: =AVERAGE(F15:F19) -> 7.64 | G32: =AVERAGE(G15:G19) -> 0.3 | H32: =AVERAGE(H15:H19) -> 29.34 | I32: =AVERAGE(I15:I19) -> 4.54 | J32: =AVERAGE(J15:J19) -> 0.34 | ... S32: =AVERAGE(S15:S19) -> -4.32
B33: 2020 | C33: =AVERAGE(C20:C24) -> 3 | D33: =AVERAGE(D20:D24) -> 48.36 | E33: =AVERAGE(E20:E24) -> 0.1 | F33: =AVERAGE(F20:F24) -> 8.48 | G33: =AVERAGE(G20:G24) -> 0.32 | H33: =AVERAGE(H20:H24) -> 27.2 | I33: =AVERAGE(I20:I24) -> 4.72 | J33: =AVERAGE(J20:J24) -> 0.08 | ... S33: =AVERAGE(S20:S24) -> -4.96
B34: Back to Contents | C34: Data 1: PADD 2 Refinery Yield
B35: Sourcekey | C35: MLRRYP23 | D35: MGFRYP23 | E35: MGARYP23 | F35: MKJRYP23 | G35: MKERYP23 | H35: MDIRYP23 | I35: MRERYP23 | J35: MNFRYP23 | K35: MOTRYP23 | L35: MNSRYP23 | M35: MLURYP23 | N35: MWXRYP23 | O35: MCKRYP23 | P35: MAPRYP23 | Q35: MSGRYP23 | R35: MMSRYP23 | S35: MPGRYP23
B36: 37437 | C36: 3.5 | D36: 52 | E36: 0.1 | F36: 6.7 | G36: 0.3 | H36: 25.4 | I36: 1.8 | J36: 0.6 | K36: 0 | L36: 0.5 | M36: 0.5 | N36: 0.1 | O36: 4.1 | P36: 5.3 | Q36: 4 | R36: 0.4 | S36: -5.2
B37: 37802 | C37: 3.3 | D37: 51.5 | E37: 0.1 | F37: 6.2 | G37: 0.3 | H37: 26 | I37: 1.7 | J37: 0.5 | K37: 0 | L37: 0.6 | M37: 0.5 | N37: 0.1 | O37: 4.2 | P37: 5.6 | Q37: 4.1 | R37: 0.4 | S37: -5.1
B38: 38168 | C38: 3.3 | D38: 51.6 | E38: 0.1 | F38: 6.4 | G38: 0.3 | H38: 25.7 | I38: 1.8 | J38: 0.8 | K38: 0.3 | L38: 0.1 | M38: 0.4 | N38: 0.1 | O38: 4.3 | P38: 5.7 | Q38: 4.1 | R38: 0.4 | S38: -5.4
B39: 38533 | C39: 3.1 | D39: 50.4 | E39: 0.1 | F39: 6.5 | G39: 0.3 | H39: 27.1 | I39: 1.6 | J39: 0.8 | K39: 0.3 | L39: 0.2 | M39: 0.4 | N39: 0.1 | O39: 4.5 | P39: 5.7 | Q39: 4.1 | R39: 0.5 | S39: -5.8
B40: 38898 | C40: 4 | D40: 49.4 | E40: 0.1 | F40: 6.2 | G40: 0.3 | H40: 27.3 | I40: 1.7 | J40: 0.9 | K40: 0.2 | L40: 0.2 | M40: 0.5 | N40: 0.1 | O40: 4.4 | P40: 6.1 | Q40: 4.1 | R40: 0.5 | S40: -5.9
B41: 39263 | C41: 3.9 | D41: 49.8 | E41: 0.1 | F41: 6.1 | G41: 0.1 | H41: 28.2 | I41: 1.7 | J41: 0.9 | K41: 0.2 | L41: 0.1 | M41: 0.4 | N41: 0.1 | O41: 4.3 | P41: 5.3 | Q41: 4.2 | R41: 0.4 | S41: -5.8
B42: 39629 | C42: 3.5 | D42: 48.5 | E42: 0.1 | F42: 6.3 | G42: 0 | H42: 30 | I42: 1.6 | J42: 0.8 | K42: 0.2 | L42: 0.1 | M42: 0.4 | N42: 0.1 | O42: 4.3 | P42: 5.3 | Q42: 4 | R42: 0.4 | S42: -5.6
B43: 39994 | C43: 3.3 | D43: 51.6 | E43: 0.1 | F43: 6.5 | G43: 0 | H43: 28.1 | I43: 1.5 | J43: 0.7 | K43: 0.2 | L43: 0 | M43: 0.2 | N43: 0 | O43: 4.4 | P43: 4.6 | Q43: 4.1 | R43: 0.4 | S43: -5.7
B44: 40359 | C44: 3.4 | D44: 50.6 | E44: 0.1 | F44: 6.6 | G44: 0 | H44: 28.9 | I44: 1.3 | J44: 0.8 | K44: 0.3 | L44: 0 | M44: 0.2 | N44: 0.1 | O44: 4.3 | P44: 5 | Q44: 3.8 | R44: 0.4 | S44: -5.9
B45: 40724 | C45: 3.3 | D45: 50.6 | E45: 0.1 | F45: 6.8 | G45: 0.1 | H45: 29 | I45: 1.4 | J45: 0.8 | K45: 0.3 | L45: 0 | M45: 0.2 | N45: 0 | O45: 4.4 | P45: 4.9 | Q45: 3.8 | R45: 0.4 | S45: -5.9
B47: 2005 | C47: =AVERAGE(C37:C41) -> 3.52 | D47: =AVERAGE(D37:D41) -> 50.54 | E47: =AVERAGE(E37:E41) -> 0.1 | F47: =AVERAGE(F37:F41) -> 6.28 | G47: =AVERAGE(G37:G41) -> 0.26 | H47: =AVERAGE(H37:H41) -> 26.86 | I47: =AVERAGE(I37:I41) -> 1.7 | J47: =AVERAGE(J37:J41) -> 0.78 | ... S47: =AVERAGE(S37:S41) -> -5.6 | T47: =E47+L47+M47+N47+Q47+R47 -> 5.44
A48: 2 | B48: 2010 | C48: =AVERAGE(C42:C45) -> 3.375 | D48: =AVERAGE(D42:D45) -> 50.325 | E48: =AVERAGE(E42:E45) -> 0.1 | F48: =AVERAGE(F42:F45) -> 6.55 | G48: =AVERAGE(G42:G45) -> 0.025 | H48: =AVERAGE(H42:H45) -> 29 | I48: =AVERAGE(I42:I45) -> 1.45 | J48: =AVERAGE(J42:J45) -> 0.775 | ... S48: =AVERAGE(S42:S45) -> -5.775 | T48: =E48+L48+M48+N48+Q48+R48 -> 4.75
B51: Back to Contents | C51: Data 1: PADD 3 Refinery Yield
B52: Sourcekey | C52: MLRRYP33 | D52: MGFRYP33 | E52: MGARYP33 | F52: MKJRYP33 | G52: MKERYP33 | H52: MDIRYP33 | I52: MRERYP33 | J52: MNFRYP33 | K52: MOTRYP33 | L52: MNSRYP33 | M52: MLURYP33 | N52: MWXRYP33 | O52: MCKRYP33 | P52: MAPRYP33 | Q52: MSGRYP33 | R52: MMSRYP33 | S52: MPGRYP33
B53: 37437 | C53: 5.8 | D53: 45.4 | E53: 0.1 | F53: 10.3 | G53: 0.4 | H53: 22.3 | I53: 3.7 | J53: 2.7 | K53: 1.9 | L53: 0.4 | M53: 1.6 | N53: 0.1 | O53: 5.7 | P53: 1.6 | Q53: 4.2 | R53: 0.5 | S53: -6.9
B54: 37802 | C54: 5.5 | D54: 44.8 | E54: 0.1 | F54: 9.9 | G54: 0.4 | H54: 23 | I54: 4.1 | J54: 2.6 | K54: 2.3 | L54: 0.4 | M54: 1.5 | N54: 0.1 | O54: 5.7 | P54: 1.6 | Q54: 4.4 | R54: 0.5 | S54: -6.9
B55: 38168 | C55: 5.3 | D55: 44.6 | E55: 0.1 | F55: 10 | G55: 0.5 | H55: 23.5 | I55: 3.9 | J55: 2.8 | K55: 2.4 | L55: 0.5 | M55: 1.6 | N55: 0.1 | O55: 5.9 | P55: 1.5 | Q55: 4.3 | R55: 0.4 | S55: -7.6
B56: 38533 | C56: 4.7 | D56: 43.8 | E56: 0.1 | F56: 10.2 | G56: 0.6 | H56: 24.5 | I56: 3.9 | J56: 2.3 | K56: 2.1 | L56: 0.4 | M56: 1.6 | N56: 0.1 | O56: 6 | P56: 1.6 | Q56: 4.3 | R56: 0.4 | S56: -6.8
B57: 38898 | C57: 4.8 | D57: 43.5 | E57: 0.2 | F57: 9.7 | G57: 0.4 | H57: 25.2 | I57: 3.8 | J57: 1.9 | K57: 2.4 | L57: 0.4 | M57: 1.7 | N57: 0.1 | O57: 6.2 | P57: 1.5 | Q57: 4.6 | R57: 0.5 | S57: -6.8
B58: 39263 | C58: 5 | D58: 43.2 | E58: 0.1 | F58: 9.4 | G58: 0.3 | H58: 26 | I58: 4.1 | J58: 1.9 | K58: 2.4 | L58: 0.5 | M58: 1.7 | N58: 0.1 | O58: 6 | P58: 1.3 | Q58: 4.3 | R58: 0.5 | S58: -6.9
B59: 39629 | C59: 5.1 | D59: 41.6 | E59: 0.1 | F59: 9.6 | G59: 0 | H59: 28.4 | I59: 4 | J59: 1.5 | K59: 2.3 | L59: 0.5 | M59: 1.7 | N59: 0.1 | O59: 6 | P59: 1.1 | Q59: 4.4 | R59: 0.6 | S59: -7
B60: 39994 | C60: 5.2 | D60: 42.9 | E60: 0.1 | F60: 9.3 | G60: 0.1 | H60: 28 | I60: 4.1 | J60: 2.2 | K60: 1.4 | L60: 0.4 | M60: 1.5 | N60: 0.1 | O60: 5.9 | P60: 1.1 | Q60: 4.6 | R60: 0.6 | S60: -7.3
B61: 40359 | C61: 5.5 | D61: 42.5 | E61: 0.1 | F61: 9.2 | G61: 0.1 | H61: 28.3 | I61: 4.3 | J61: 2.2 | K61: 1.4 | L61: 0.5 | M61: 1.6 | N61: 0.1 | O61: 6 | P61: 1.2 | Q61: 4.5 | R61: 0.6 | S61: -7.8
B62: 40724 | C62: 5.1 | D62: 41.6 | E62: 0.1 | F62: 9 | G62: 0.1 | H62: 30.5 | I62: 3.6 | J62: 2.2 | K62: 1.2 | L62: 0.5 | M62: 1.6 | N62: 0.1 | O62: 6.1 | P62: 1.1 | Q62: 4.6 | R62: 0.6 | S62: -7.8
B64: 2005 | C64: =AVERAGE(C54:C58) -> 5.06 | D64: =AVERAGE(D54:D58) -> 43.98 | E64: =AVERAGE(E54:E58) -> 0.12 | F64: =AVERAGE(F54:F58) -> 9.84 | G64: =AVERAGE(G54:G58) -> 0.44 | H64: =AVERAGE(H54:H58) -> 24.44 | I64: =AVERAGE(I54:I58) -> 3.96 | J64: =AVERAGE(J54:J58) -> 2.3 | ... S64: =AVERAGE(S54:S58) -> -7 | T64: =E64+L64+M64+N64+Q64+R64 -> 7.12
A65: 3 | B65: 2010 | C65: =AVERAGE(C59:C62) -> 5.225 | D65: =AVERAGE(D59:D62) -> 42.15 | E65: =AVERAGE(E59:E62) -> 0.1 | F65: =AVERAGE(F59:F62) -> 9.275 | G65: =AVERAGE(G59:G62) -> 0.075 | H65: =AVERAGE(H59:H62) -> 28.8 | I65: =AVERAGE(I59:I62) -> 4 | J65: =AVERAGE(J59:J62) -> 2.025 | ... S65: =AVERAGE(S59:S62) -> -7.475 | T65: =E65+L65+M65+N65+Q65+R65 -> 7.4
B68: Back to Contents | C68: Data 1: PADD 4 Refinery Yield
B69: Sourcekey | C69: MLRRYP43 | D69: MGFRYP43 | E69: MGARYP43 | F69: MKJRYP43 | G69: MKERYP43 | H69: MDIRYP43 | I69: MRERYP43 | J69: MNFRYP43 | K69: MOTRYP43 | L69: MNSRYP43 | M69: MLURY_R40_0 | N69: MWXRYP43 | O69: MCKRYP43 | P69: MAPRYP43 | Q69: MSGRYP43 | R69: MMSRYP43 | S69: MPGRYP43
B70: 37437 | C70: 1.1 | D70: 48 | E70: 0.1 | F70: 4.8 | G70: 0.4 | H70: 29.9 | I70: 2.1 | K70: 0.1 | N70: 0.5 | O70: 3.2 | P70: 9.2 | Q70: 3.8 | R70: 0.4 | S70: -3.6
B71: 37802 | C71: 0.8 | D71: 47.9 | E71: 0.1 | F71: 4.9 | G71: 0.4 | H71: 29.5 | I71: 2.4 | K71: 0.1 | N71: 0.4 | O71: 3.2 | P71: 9.1 | Q71: 4.5 | R71: 0.4 | S71: -3.7
B72: 38168 | C72: 0.8 | D72: 47.5 | E72: 0.1 | F72: 4.9 | G72: 0.3 | H72: 30.4 | I72: 2.5 | K72: 0.1 | N72: 0.4 | O72: 3.2 | P72: 9.3 | Q72: 4.2 | R72: 0.4 | S72: -4.2
B73: 38533 | C73: 0.7 | D73: 46 | E73: 0.1 | F73: 5.4 | G73: 0.3 | H73: 30.6 | I73: 2.7 | K73: 0.1 | L73: 0 | N73: 0.4 | O73: 3.3 | P73: 9.5 | Q73: 4.1 | R73: 0.4 | S73: -3.7
B74: 38898 | C74: 1.3 | D74: 46.4 | E74: 0.1 | F74: 5.3 | G74: 0.4 | H74: 30.6 | I74: 2.8 | K74: 0.1 | L74: 0 | N74: 0.3 | O74: 3.3 | P74: 8.5 | Q74: 4.2 | R74: 0.4 | S74: -3.6
B75: 39263 | C75: 1.5 | D75: 46.3 | E75: 0.1 | F75: 5.4 | G75: 0.3 | H75: 29.8 | I75: 2.6 | K75: 0.1 | L75: 0 | N75: 0 | O75: 3.4 | P75: 8.9 | Q75: 4.2 | R75: 0.3 | S75: -3
B76: 39629 | C76: 1.6 | D76: 47.4 | E76: 0.1 | F76: 4.8 | G76: 0.2 | H76: 31.6 | I76: 2.2 | L76: 0 | N76: 0 | O76: 4.6 | P76: 6.1 | Q76: 4.6 | R76: 0.5 | S76: -3.8
B77: 39994 | C77: 1.9 | D77: 48.1 | E77: 0.1 | F77: 4.9 | G77: 0.3 | H77: 31.4 | I77: 1.6 | K77: 0.3 | O77: 4.3 | P77: 6 | Q77: 4.9 | R77: 0.5 | S77: -4.1
B78: 40359 | C78: 2 | D78: 48.2 | E78: 0.1 | F78: 5.2 | G78: 0.3 | H78: 31.9 | I78: 1.5 | K78: 0 | M78: 0 | O78: 4 | P78: 6 | Q78: 4.3 | R78: 0.7 | S78: -4.2
B79: 40724 | C79: 1.5 | D79: 47.6 | E79: 0.1 | F79: 4.8 | G79: 0.2 | H79: 33.2 | I79: 1.9 | J79: 0 | O79: 4.6 | P79: 5.4 | Q79: 4.4 | R79: 0.8 | S79: -4.5
B81: 2005 | C81: =AVERAGE(C71:C75) -> 1.02 | D81: =AVERAGE(D71:D75) -> 46.82 | E81: =AVERAGE(E71:E75) -> 0.1 | F81: =AVERAGE(F71:F75) -> 5.18 | G81: =AVERAGE(G71:G75) -> 0.34 | H81: =AVERAGE(H71:H75) -> 30.18 | I81: =AVERAGE(I71:I75) -> 2.6 | J81: =AVERAGE(J71:J75) -> #DIV/0! | ... L81: =AVERAGE(L71:L75) -> 0 | N81: =AVERAGE(N71:N75) -> 0.3 | O81: =AVERAGE(O71:O75) -> 3.28 | P81: =AVERAGE(P71:P75) -> 9.06 | Q81: =AVERAGE(Q71:Q75) -> 4.24 | R81: =AVERAGE(R71:R75) -> 0.38 | S81: =AVERAGE(S71:S75) -> -3.64 | T81: =E81+L81+M81+N81+Q81+R81 -> 5.02
A82: 4 | B82: 2010 | C82: =AVERAGE(C76:C79) -> 1.75 | D82: =AVERAGE(D76:D79) -> 47.825 | E82: =AVERAGE(E76:E79) -> 0.1 | F82: =AVERAGE(F76:F79) -> 4.925 | G82: =AVERAGE(G76:G79) -> 0.25 | H82: =AVERAGE(H76:H79) -> 32.025 | I82: =AVERAGE(I76:I79) -> 1.8 | J82: =AVERAGE(J76:J79) -> 0 | ... S82: =AVERAGE(S76:S79) -> -4.15 | T82: =E82+L82+M82+N82+Q82+R82 -> 5.275
B85: Back to Contents | C85: Data 1: PADD 5 Refinery Yield
B86: Sourcekey | C86: MLRRYP53 | D86: MGFRYP53 | E86: MGARYP53 | F86: MKJRYP53 | G86: MKERYP53 | H86: MDIRYP53 | I86: MRERYP53 | J86: MNFRYP53 | K86: MOTRYP53 | L86: MNSRYP53 | M86: MLURYP53 | N86: MWXRYP53 | O86: MCKRYP53 | P86: MAPRYP53 | Q86: MSGRYP53 | R86: MMSRYP53 | S86: MPGRYP53
B87: 37437 | C87: 2.7 | D87: 47.3 | E87: 0.1 | F87: 16 | G87: 0.1 | H87: 19 | I87: 6.2 | J87: 0.1 | K87: 0.3 | L87: 0.1 | M87: 0.8 | N87: 0 | O87: 6 | P87: 2.1 | Q87: 5.5 | R87: 0.3 | S87: -6.7
B88: 37802 | C88: 2.9 | D88: 47.2 | E88: 0.1 | F88: 16 | G88: 0 | H88: 19.5 | I88: 5.8 | J88: 0.1 | K88: 0.3 | L88: 0.1 | M88: 0.8 | O88: 6.2 | P88: 1.9 | Q88: 5.6 | R88: 0.3 | S88: -6.8
B89: 38168 | C89: 2.6 | D89: 47.3 | E89: 0.1 | F89: 16.2 | G89: 0 | H89: 19.5 | I89: 6.1 | J89: 0 | K89: 0.3 | L89: 0 | M89: 0.7 | O89: 6.1 | P89: 1.9 | Q89: 5.4 | R89: 0.3 | S89: -6.4
B90: 38533 | C90: 2.5 | D90: 47.3 | E90: 0.1 | F90: 16.2 | G90: 0 | H90: 20.4 | I90: 5.8 | J90: 0 | K90: 0.4 | L90: 0 | M90: 0.7 | O90: 6.2 | P90: 1.7 | Q90: 5.1 | R90: 0.3 | S90: -6.7
B91: 38898 | C91: 2.8 | D91: 47.7 | E91: 0.1 | F91: 15.3 | G91: 0 | H91: 20.3 | I91: 5.8 | J91: 0 | K91: 0.4 | L91: 0.1 | M91: 0.7 | O91: 6 | P91: 1.8 | Q91: 5.2 | R91: 0.4 | S91: -6.6
B92: 39263 | C92: 2.8 | D92: 46.6 | E92: 0.1 | F92: 15.6 | G92: 0 | H92: 20.8 | I92: 6.3 | J92: 0 | K92: 0.3 | L92: 0 | M92: 0.6 | O92: 5.8 | P92: 1.8 | Q92: 5.4 | R92: 0.4 | S92: -6.4
B93: 39629 | C93: 2.8 | D93: 45.6 | E93: 0.1 | F93: 17.5 | G93: 0 | H93: 21.6 | I93: 5.5 | J93: 0 | K93: 0.1 | L93: 0 | M93: 0.8 | O93: 6.1 | P93: 1.4 | Q93: 5.1 | R93: 0.5 | S93: -7.1
B94: 39994 | C94: 2.8 | D94: 48 | E94: 0.1 | F94: 16.4 | G94: 0 | H94: 20.3 | I94: 5.4 | J94: 0 | K94: 0.1 | L94: 0 | M94: 0.8 | O94: 6.2 | P94: 1.3 | Q94: 4.9 | R94: 0.4 | S94: -6.8
B95: 40359 | C95: 2.8 | D95: 48.1 | E95: 0.1 | F95: 16.4 | G95: 0.1 | H95: 20.9 | I95: 5.1 | J95: 0 | K95: 0 | L95: 0 | M95: 0.8 | O95: 6.1 | P95: 1.2 | Q95: 5.5 | R95: 0.5 | S95: -7.5
B96: 40724 | C96: 2.3 | D96: 47.1 | E96: 0.1 | F96: 16.9 | G96: 0 | H96: 22.1 | I96: 5.3 | J96: 0 | L96: 0.1 | M96: 0.7 | O96: 6.2 | P96: 1.2 | Q96: 5.1 | R96: 0.5 | S96: -7.5
B98: 2005 | C98: =AVERAGE(C88:C92) -> 2.72 | D98: =AVERAGE(D88:D92) -> 47.22 | E98: =AVERAGE(E88:E92) -> 0.1 | F98: =AVERAGE(F88:F92) -> 15.86 | G98: =AVERAGE(G88:G92) -> 0 | H98: =AVERAGE(H88:H92) -> 20.1 | I98: =AVERAGE(I88:I92) -> 5.96 | J98: =AVERAGE(J88:J92) -> 0.02 | ... M98: =AVERAGE(M88:M92) -> 0.7 | O98: =AVERAGE(O88:O92) -> 6.06 | P98: =AVERAGE(P88:P92) -> 1.82 | Q98: =AVERAGE(Q88:Q92) -> 5.34 | R98: =AVERAGE(R88:R92) -> 0.34 | S98: =AVERAGE(S88:S92) -> -6.58 | T98: =E98+L98+M98+N98+Q98+R98 -> 6.52
A99: 5 | B99: 2010 | C99: =AVERAGE(C93:C96) -> 2.675 | D99: =AVERAGE(D93:D96) -> 47.2 | E99: =AVERAGE(E93:E96) -> 0.1 | F99: =AVERAGE(F93:F96) -> 16.8 | G99: =AVERAGE(G93:G96) -> 0.025 | H99: =AVERAGE(H93:H96) -> 21.225 | I99: =AVERAGE(I93:I96) -> 5.325 | J99: =AVERAGE(J93:J96) -> 0 | ... M99: =AVERAGE(M93:M96) -> 0.775 | O99: =AVERAGE(O93:O96) -> 6.15 | P99: =AVERAGE(P93:P96) -> 1.275 | Q99: =AVERAGE(Q93:Q96) -> 5.15 | R99: =AVERAGE(R93:R96) -> 0.475 | S99: =AVERAGE(S93:S96) -> -7.225 | T99: =E99+L99+M99+N99+Q99+R99 -> 6.525

Sheet Utilization
A1: Utilization
F2: Average | J2: Crude Oil Input
A3: PADD 1 | B3: 2010-2011 | C3: =AVERAGE(B22:B73) -> 1045.1923 | D3: =AVERAGE(E22:E73) -> 73.042308
B4: 2011-2012 | C4: =AVERAGE(C74:C126) -> 1061.8868 | D4: =AVERAGE(E74:E126) -> 70.764151 | F4: =AVERAGE(C3:C4) -> 1053.5396 | G4: =AVERAGE(D3:D4) -> 71.903229 | J4: =F4*365*Conv!$C$47*Conv!$I$6*10^-6 -> 2401.6951
A6: PADD 2 | B6: 2010-2011 | C6: =AVERAGE(B139:B190) -> 3299.6346 | D6: =AVERAGE(E139:E190) -> 89.621154
B7: 2011-2012 | C7: =AVERAGE(B191:B243) -> 3440.4151 | D7: =AVERAGE(E191:E243) -> 93.266038 | F7: =AVERAGE(C6:C7) -> 3370.0249 | G7: =AVERAGE(D6:D7) -> 91.443596 | J7: =F7*365*Conv!$C$47*Conv!$I$6*10^-6 -> 7682.4569
A9: PADD 3 | B9: 2010-2011 | C9: =AVERAGE(B255:B306) -> 7342.8846 | D9: =AVERAGE(E255:E306) -> 87.751923
B10: 2011-2012 | C10: =AVERAGE(B307:B360) -> 7487 | D10: =AVERAGE(E307:E360) -> 87.977778 | F10: =AVERAGE(C9:C10) -> 7414.9423 | G10: =AVERAGE(D9:D10) -> 87.86485 | J10: =F10*365*Conv!$C$47*Conv!$I$6*10^-6 -> 16903.429
A12: PADD 4 | B12: 2010-2011 | C12: =AVERAGE(B372:B423) -> 536.84615 | D12: =AVERAGE(E372:E423) -> 86.544231
B13: 2011-2012 | C13: =AVERAGE(B424:B477) -> 551.07407 | D13: =AVERAGE(E424:E477) -> 88.914815 | F13: =AVERAGE(C12:C13) -> 543.96011 | G13: =AVERAGE(D12:D13) -> 87.729523 | J13: =F13*365*Conv!$C$47*Conv!$I$6*10^-6 -> 1240.0354
A15: PADD 5 | B15: 2010-2011 | C15: =AVERAGE(B488:B539) -> 2342.3269 | D15: =AVERAGE(E488:E539) -> 79.594231
B16: 2011-2012 | C16: =AVERAGE(B540:B593) -> 2376.3704 | D16: =AVERAGE(E540:E593) -> 80.944444 | F16: =AVERAGE(C15:C16) -> 2359.3486 | G16: =AVERAGE(D15:D16) -> 80.269338 | J16: =F16*365*Conv!$C$47*Conv!$I$6*10^-6 -> 5378.475
J18: =SUM(J4:J17) -> 33606.091
A19: Back to Contents | B19: Data 1: Refiner Inputs and Utilization
A20: Sourcekey | B20: WCRRIP12 | C20: WGIRIP12 | D20: W_NA_YRL_R10_MBBLD | E20: W_NA_YUP_R10_PER
A21: Date | B21: 4-Week Avg East Coast (PADD 1) Refiner Net Input of Crude Oil (Thousand Barrels per Day) | C21: 4-Week Avg East Coast (PADD 1) Gross Inputs into Refineries (Thousand Barrels per Day) | D21: 4-Week Avg East Coast (PADD 1) Operable Crude Oil Distillation Capacity (Thousand Barrels per Calendar Day) | E21: 4-Week Avg East Coast (PADD 1) Percent Utilization of Refinery Operable Capacity (Percent)
A22: 40354 | B22: 1207 | C22: 1212 | D22: 1397 | E22: 86.8
A23: 40361 | B23: 1211 | C23: 1219 | D23: 1397 | E23: 87.3
A24: 40368 | B24: 1224 | C24: 1234 | D24: 1397 | E24: 88.3
A25: 40375 | B25: 1243 | C25: 1255 | D25: 1397 | E25: 89.8
A26: 40382 | B26: 1256 | C26: 1273 | D26: 1397 | E26: 91.1
A27: 40389 | B27: 1258 | C27: 1273 | D27: 1397 | E27: 91.1
A28: 40396 | B28: 1230 | C28: 1247 | D28: 1397 | E28: 89.3
A29: 40403 | B29: 1213 | C29: 1229 | D29: 1397 | E29: 88
A30: 40410 | B30: 1199 | C30: 1213 | D30: 1397 | E30: 86.8
A31: 40417 | B31: 1175 | C31: 1190 | D31: 1397 | E31: 85.2
A32: 40424 | B32: 1189 | C32: 1200 | D32: 1397 | E32: 85.9
A33: 40431 | B33: 1164 | C33: 1168 | D33: 1397 | E33: 83.6
... A132: 41124 | B132: 994 | C132: 1002 | D132: 1188 | E132: 84.3
A136: Back to Contents | B136: Data 1: Refiner Inputs and Utilization
A137: Sourcekey | B137: WCRRIP22 | C137: WGIRIP22 | D137: W_NA_YRL_R20_MBBLD | E137: W_NA_YUP_R20_PER
A138: Date | B138: 4-Week Avg Midwest (PADD 2) Refiner Net Input of Crude Oil (Thousand Barrels per Day) | C138: 4-Week Avg Midwest (PADD 2) Gross Inputs into Refineries (Thousand Barrels per Day) | D138: 4-Week Avg Midwest (PADD 2) Operable Crude Oil Distillation Capacity (Thousand Barrels per Calendar Day) | E138: 4-Week Avg Midwest (PADD 2) Percent Utilization of Refinery Operable Capacity (Percent)
A139: 40354 | B139: 3403 | C139: 3434 | D139: 3723 | E139: 92.3
A140: 40361 | B140: 3411 | C140: 3447 | D140: 3723 | E140: 92.6
A141: 40368 | B141: 3444 | C141: 3487 | D141: 3723 | E141: 93.7
A142: 40375 | B142: 3440 | C142: 3485 | D142: 3723 | E142: 93.6
A143: 40382 | B143: 3442 | C143: 3485 | D143: 3723 | E143: 93.6
A144: 40389 | B144: 3451 | C144: 3489 | D144: 3723 | E144: 93.7
A145: 40396 | B145: 3431 | C145: 3472 | D145: 3723 | E145: 93.3
A146: 40403 | B146: 3449 | C146: 3492 | D146: 3723 | E146: 93.8
A147: 40410 | B147: 3466 | C147: 3511 | D147: 3723 | E147: 94.3
A148: 40417 | B148: 3450 | C148: 3496 | D148: 3723 | E148: 93.9
A149: 40424 | B149: 3415 | C149: 3461 | D149: 3723 | E149: 93
A150: 40431 | B150: 3367 | C150: 3415 | D150: 3723 | E150: 91.7
... A249: 41124 | B249: 3517 | C249: 3511 | D249: 3665 | E249: 95.8
A252: Back to Contents | B252: Data 1: Refiner Inputs and Utilization
A253: Sourcekey | B253: WCRRIP32 | C253: WGIRIP32 | D253: W_NA_YRL_R30_MBBLD | E253: W_NA_YUP_R30_PER
A254: Date | B254: 4-Week Avg Gulf Coast (PADD 3) Refiner Net Input of Crude Oil (Thousand Barrels per Day) | C254: 4-Week Avg Gulf Coast (PADD 3) Gross Inputs into Refineries (Thousand Barrels per Day) | D254: 4-Week Avg Gulf Coast (PADD 3) Operable Crude Oil Distillation Capacity (Thousand Barrels per Calendar Day) | E254: 4-Week Avg Gulf Coast (PADD 3) Percent Utilization of Refinery Operable Capacity (Percent)
A255: 40354 | B255: 7569 | C255: 7820 | D255: 8621 | E255: 90.7
A256: 40361 | B256: 7517 | C256: 7757 | D256: 8622 | E256: 90
A257: 40368 | B257: 7524 | C257: 7762 | D257: 8623 | E257: 90
A258: 40375 | B258: 7583 | C258: 7808 | D258: 8624 | E258: 90.5
A259: 40382 | B259: 7669 | C259: 7887 | D259: 8625 | E259: 91.5
A260: 40389 | B260: 7778 | C260: 7992 | D260: 8625 | E260: 92.7
A261: 40396 | B261: 7772 | C261: 7988 | D261: 8626 | E261: 92.6
A262: 40403 | B262: 7775 | C262: 7986 | D262: 8626 | E262: 92.6
A263: 40410 | B263: 7656 | C263: 7886 | D263: 8626 | E263: 91.4
A264: 40417 | B264: 7507 | C264: 7738 | D264: 8626 | E264: 89.7
A265: 40424 | B265: 7485 | C265: 7751 | D265: 8626 | E265: 89.9
A266: 40431 | B266: 7439 | C266: 7690 | D266: 8626 | E266: 89.1
... A365: 41124 | B365: 7930 | C365: 8091 | D365: 8725 | E365: 92.7
A369: Back to Contents | B369: Data 1: Refiner Inputs and Utilization
A370: Sourcekey | B370: WCRRIP42 | C370: WGIRIP42 | D370: W_NA_YRL_R40_MBBLD | E370: W_NA_YUP_R40_PER
A371: Date | B371: 4-Week Avg Rocky Mountain (PADD 4) Refiner Net Input of Crude Oil (Thousand Barrels per Day) | C371: 4-Week Avg Rocky Mountain (PADD 4) Gross Inputs into Refineries (Thousand Barrels per Day) | D371: 4-Week Avg Rocky Mountains (PADD 4) Operable Crude Oil Distillation Capacity (Thousand Barrels per Calendar Day) | E371: 4-Week Avg Rocky Mountains (PADD 4) Percent Utilization of Refinery Operable Capacity (Percent)
A372: 40354 | B372: 560 | C372: 564 | D372: 623 | E372: 90.6
A373: 40361 | B373: 564 | C373: 570 | D373: 623 | E373: 91.4
A374: 40368 | B374: 573 | C374: 579 | D374: 623 | E374: 92.9
A375: 40375 | B375: 575 | C375: 580 | D375: 623 | E375: 93.2
A376: 40382 | B376: 575 | C376: 577 | D376: 623 | E376: 92.6
A377: 40389 | B377: 570 | C377: 568 | D377: 623 | E377: 91.2
A378: 40396 | B378: 555 | C378: 551 | D378: 623 | E378: 88.5
A379: 40403 | B379: 551 | C379: 546 | D379: 623 | E379: 87.6
A380: 40410 | B380: 542 | C380: 540 | D380: 623 | E380: 86.7
A381: 40417 | B381: 540 | C381: 540 | D381: 623 | E381: 86.7
A382: 40424 | B382: 543 | C382: 548 | D382: 623 | E382: 87.9
A383: 40431 | B383: 547 | C383: 554 | D383: 623 | E383: 88.9
... A482: 41124 | B482: 605 | C482: 608 | D482: 624 | E482: 97.4
A485: Back to Contents | B485: Data 1: Refiner Inputs and Utilization
A486: Sourcekey | B486: WCRRIP52 | C486: WGIRIP52 | D486: W_NA_YRL_R50_MBBLD | E486: W_NA_YUP_R50_PER
A487: Date | B487: 4-Week Avg West Coast (PADD 5) Refiner Net Input of Crude Oil (Thousand Barrels per Day) | C487: 4-Week Avg West Coast (PADD 5) Gross Inputs into Refineries (Thousand Barrels per Day) | D487: 4-Week Avg West Coast (PADD 5) Operable Crude Oil Distillation Capacity (Thousand Barrels per Calendar Day) | E487: 4-Week Avg West Coast (PADD 5) Percent Utilization of Refinery Operable Capacity (Percent)
A488: 40354 | B488: 2407 | C488: 2561 | D488: 3219 | E488: 79.6
A489: 40361 | B489: 2453 | C489: 2633 | D489: 3219 | E489: 81.8
A490: 40368 | B490: 2480 | C490: 2680 | D490: 3219 | E490: 83.3
A491: 40375 | B491: 2487 | C491: 2707 | D491: 3219 | E491: 84.1
A492: 40382 | B492: 2477 | C492: 2712 | D492: 3219 | E492: 84.2
A493: 40389 | B493: 2449 | C493: 2670 | D493: 3219 | E493: 83
A494: 40396 | B494: 2416 | C494: 2628 | D494: 3219 | E494: 81.6
A495: 40403 | B495: 2348 | C495: 2568 | D495: 3219 | E495: 79.8
A496: 40410 | B496: 2330 | C496: 2544 | D496: 3219 | E496: 79
A497: 40417 | B497: 2332 | C497: 2548 | D497: 3219 | E497: 79.2
A498: 40424 | B498: 2334 | C498: 2560 | D498: 3219 | E498: 79.5
A499: 40431 | B499: 2390 | C499: 2589 | D499: 3219 | E499: 80.4
... A598: 41124 | B598: 2581 | C598: 2712 | D598: 3028 | E598: 89.6

Sheet DSH percent
A1: DSH Percent of DSL Total
A2: Back to Contents | B2: Data 1: East Coast (PADD 1) Weekly Refiner & Blender Net Production | P2: PADD 1 | Q2: =SUM(Q11:Q122)/SUM(N11:N122) -> 0.36222335
P3: PADD 2 | Q3: =SUM(Q129:Q240)/SUM(N129:N240) -> 0.0067097663
P4: PADD 3 | Q4: =SUM(Q246:Q357)/SUM(N246:N357) -> 0.085692282
P5: PADD 4 | Q5: =SUM(Q363:Q474)/SUM(N364:N474) -> -0.0021292399
P6: PADD 5 | Q6: =SUM(Q480:Q591)/SUM(N480:N591) -> 0.076263895
N8: Total | Q8: DSH
A9: Sourcekey | B9: WGFRPP12 | C9: WGRRPP12 | D9: WG1TP_R10_2 | E9: W_EPM0RO_YPT_R10_MBBLD | F9: WG4TP_R10_2 | G9: WG5TP_R10_2 | H9: W_EPM0CAL55_YPT_R10_MBBLD | I9: W_EPM0CAG55_YPT_R10_MBBLD | J9: WG6TP_R10_2 | K9: WKJRPP12 | L9: WKCRPP12 | M9: WKMRPP12 | N9: WDIRPP12 | O9: WD0TP_R10_2 | P9: WD1TP_R10_2 | Q9: WDGRPP12 | R9: WRERPP12 | S9: WPRNPP12
A10: Date | B10: Weekly East Coast (PADD 1) Refiner and Blender Net Production of Finished Motor Gasoline (Thousand Barrels per Day) | C10: Weekly East Coast (PADD 1) Refiner and Blender Net Production of Reformulated Motor Gasoline (Thousand Barrels per Day) | D10: Weekly East Coast (PADD 1) Refiner and Blender Net Production of Finished Reformulated Motor Gasoline with Ethanol (Thousand Barrels per Day) | E10: Weekly East Coast (PADD 1) Refiner and Blender Net Production of Other Finished Reformulated Motor Gasoline (Thousand Barrels per Day) | F10: Weekly East Coast (PADD 1) Refiner and Blender Net Production of Conventional Motor Gasoline (Thousand Barrels per Day) | G10: Weekly East Coast (PADD 1) Refiner and Blender Net Production of Finished Conventional Motor Gasoline with Ethanol (Thousand Barrels per Day) | H10: Weekly East Coast (PADD 1) Refiner and Blender Net Production of Finished Conventional Motor Gasoline, Ed 55 and Lower (Thousand Barrels per Day) | I10: Weekly East Coast (PADD 1) Refiner and Blender Net Production of Finished Conventional Motor Gasoline, Greater than Ed 55 (Thousand Barrels per Day) | J10: Weekly East Coast (PADD 1) Refiner and Blender Net Production of Other Finished Conventional Motor Gasoline (Thousand Barrels per Day) | K10: Weekly East Coast (PADD 1) Refiner and Blender Net Production of Kerosene-Type Jet Fuel (Thousand Barrels per Day) | L10: Weekly East Coast (PADD 1) Refiner and Blender Net Production of Commercial Kerosene-Type Jet Fuel (Thousand Barrels per Day) | M10: Weekly East Coast (PADD 1) Refiner and Blender Net Production of Military Kerosene-Type Jet Fuel (Thousand Barrels per Day) | N10: Weekly East Coast (PADD 1) Refiner and Blender Net Production of Distillate Fuel Oil (Thousand Barrels per Day) | O10: Weekly East Coast (PADD 1) Refiner and Blender Net Production of Distillate Fuel Oil, 0 to 15 ppm Sulfur (Thousand Barrels per Day) | P10: Weekly East Coast (PADD 1) Refiner and Blender Net Production of Distillate Fuel Oil, Greater than 15 to 500 ppm Sulfur (Thousand Barrels per Day) | Q10: Weekly East Coast (PADD 1) Refiner and Blender Net Production of Distillate Fuel Oil Greater than 500 ppm Sulfur (Thousand Barrels per Day) | R10: Weekly East Coast (PADD 1) Refiner and Blender Net Production of Residual Fuel Oil (Thousand Barrels per Day) | S10: Weekly East Coast (PADD 1) Refiner, Blender, and Gas Plant Net Production of Propane and Propylene (Thousand Barrels per Day)
A11: 40354 | B11: 2838 | C11: 1276 | D11: 1276 | E11: 0 | F11: 1562 | G11: 1811 | H11: 1811 | I11: 0 | J11: -249 | K11: 80 | L11: 80 | M11: 0 | N11: 375 | O11: 276 | P11: 4 | Q11: 95 | R11: 67 | S11: 45
A12: 40361 | B12: 2923 | C12: 1317 | D12: 1317 | E12: 0 | F12: 1606 | G12: 1913 | H12: 1913 | I12: 0 | J12: -307 | K12: 83 | L12: 83 | M12: 0 | N12: 353 | O12: 275 | P12: -13 | Q12: 91 | R12: 81 | S12: 44
A13: 40368 | B13: 2881 | C13: 1237 | D13: 1237 | E13: 0 | F13: 1643 | G13: 1824 | H13: 1824 | I13: 0 | J13: -181 | K13: 61 | L13: 61 | M13: 0 | N13: 398 | O13: 261 | P13: -19 | Q13: 156 | R13: 67 | S13: 41
A14: 40375 | B14: 2792 | C14: 1251 | D14: 1251 | E14: 0 | F14: 1541 | G14: 1821 | H14: 1821 | I14: 0 | J14: -280 | K14: 86 | L14: 86 | M14: 0 | N14: 384 | O14: 274 | P14: -24 | Q14: 134 | R14: 65 | S14: 42
A15: 40382 | B15: 2897 | C15: 1290 | D15: 1290 | E15: 0 | F15: 1608 | G15: 1856 | H15: 1856 | I15: 0 | J15: -249 | K15: 70 | L15: 70 | M15: 0 | N15: 388 | O15: 278 | P15: 17 | Q15: 93 | R15: 62 | S15: 45
A16: 40389 | B16: 2849 | C16: 1296 | D16: 1296 | E16: 0 | F16: 1553 | G16: 1824 | H16: 1824 | I16: 0 | J16: -271 | K16: 78 | L16: 78 | M16: 0 | N16: 374 | O16: 274 | P16: -7 | Q16: 107 | R16: 66 | S16: 45
A17: 40396 | B17: 2772 | C17: 1239 | D17: 1239 | E17: 0 | F17: 1533 | G17: 1822 | H17: 1822 | I17: 0 | J17: -289 | K17: 66 | L17: 66 | M17: 0 | N17: 396 | O17: 261 | P17: -2 | Q17: 137 | R17: 53 | S17: 40
A18: 40403 | B18: 2802 | C18: 1252 | D18: 1252 | E18: 0 | F18: 1550 | G18: 1849 | H18: 1849 | I18: 0 | J18: -299 | K18: 81 | L18: 81 | M18: 0 | N18: 398 | O18: 278 | P18: -16 | Q18: 136 | R18: 59 | S18: 45
A19: 40410 | B19: 2844 | C19: 1262 | D19: 1262 | E19: 0 | F19: 1582 | G19: 1885 | H19: 1885 | I19: 0 | J19: -303 | K19: 71 | L19: 71 | M19: 0 | N19: 404 | O19: 291 | P19: 1 | Q19: 112 | R19: 50 | S19: 44
A20: 40417 | B20: 2792 | C20: 1220 | D20: 1220 | E20: 0 | F20: 1573 | G20: 1869 | H20: 1869 | I20: 0 | J20: -297 | K20: 72 | L20: 72 | M20: 0 | N20: 423 | O20: 285 | P20: -34 | Q20: 172 | R20: 64 | S20: 47
A21: 40424 | B21: 2835 | C21: 1279 | D21: 1279 | E21: 0 | F21: 1556 | G21: 1856 | H21: 1856 | I21: 0 | J21: -300 | K21: 83 | L21: 83 | M21: 0 | N21: 403 | O21: 243 | P21: 35 | Q21: 125 | R21: 62 | S21: 49
A22: 40431 | B22: 2727 | C22: 1239 | D22: 1239 | E22: 0 | F22: 1489 | G22: 1793 | H22: 1793 | I22: 0 | J22: -304 | K22: 77 | L22: 77 | M22: 0 | N22: 379 | O22: 232 | P22: -14 | Q22: 162 | R22: 62 | S22: 42
... A122: 41131 | B122: 2975 | C122: 1225 | D122: 1225 | E122: 0 | F122: 1750 | G122: 1938 | H122: 1938 | I122: 0 | J122: -188 | K122: 48 | L122: 48 | M122: 0 | N122: 376 | O122: 241 | P122: 45 | Q122: 90 | R122: 33 | S122: 51
A126: Back to Contents | B126: Data 1: PADD 2 Weekly Refiner & Blender Net Production
A127: Sourcekey | B127: WGFRPP22 | C127: WGRRPP22 | D127: WG1TP_R20_2 | E127: W_EPM0RO_YPT_R20_MBBLD | F127: WG4TP_R20_2 | G127: WG5TP_R20_2 | H127: W_EPM0CAL55_YPT_R20_MBBLD | I127: W_EPM0CAG55_YPT_R20_MBBLD | J127: WG6TP_R20_2 | K127: WKJRPP22 | L127: WKCRPP22 | M127: WKMRPP22 | N127: WDIRPP22 | O127: WD0TP_R20_2 | P127: WD1TP_R20_2 | Q127: WDGRPP22 | R127: WRERPP22 | S127: WPRNPP22
A128: Date | B128: 4-Week Avg Midwest (PADD 2) Refiner and Blender Net Production of Finished Motor Gasoline (Thousand Barrels per Day) | C128: 4-Week Avg Midwest (PADD 2) Refiner and Blender Net Production of Reformulated Motor Gasoline (Thousand Barrels per Day) | D128: 4-Week Avg Midwest (PADD 2) Refiner and Blender Net Production of Finished Reformulated Motor Gasoline with Ethanol (Thousand Barrels per Day) | E128: 4-Week Avg Midwest (PADD 2) Refiner and Blender Net Production of Other Finished Reformulated Motor Gasoline (Thousand Barrels per Day) | F128: 4-Week Avg Midwest (PADD 2) Refiner and Blender Net Production of Conventional Motor Gasoline (Thousand Barrels per Day) | G128: 4-Week Avg Midwest (PADD 2) Refiner and Blender Net Production of Finished Conventional Motor Gasoline with Ethanol (Thousand Barrels per Day) | H128: 4-Week Avg Midwest (PADD 2) Refiner and Blender Net Production of Finished Conventional Motor Gasoline, Ed 55 and Lower (Thousand Barrels per Day) | I128: 4-Week Avg Midwest (PADD 2) Refiner and Blender Net Production of Finished Conventional Motor Gasoline, Greater than Ed 55 (Thousand Barrels per Day) | J128: 4-Week Avg Midwest (PADD 2) Refiner and Blender Net Production of Other Finished Conventional Motor Gasoline (Thousand Barrels per Day) | K128: 4-Week Avg Midwest (PADD 2) Refiner and Blender Net Production of Kerosene-Type Jet Fuel (Thousand Barrels per Day) | L128: 4-Week Avg Midwest (PADD 2) Refiner and Blender Net Production of Commercial Kerosene-Type Jet Fuel (Thousand Barrels per Day) | M128: 4-Week Avg Midwest (PADD 2) Refiner and Blender Net Production of Military Kerosene-Type Jet Fuel (Thousand Barrels per Day) | N128: 4-Week Avg Midwest (PADD 2) Refiner and Blender Net Production of Distillate Fuel Oil (Thousand Barrels per Day) | O128: 4-Week Avg Midwest (PADD 2) Refiner and Blender Net Production of Distillate Fuel Oil, 0 to 15 ppm Sulfur (Thousand Barrels per Day) | P128: 4-Week Avg Midwest (PADD 2)Refiner and Blender Net Production of Distillate Fuel Oil, Greater than 15 to 500 ppm Sulfur (Thousand Barrels per Day) | Q128: 4-Week Avg Midwest (PADD 2) Refiner and Blender Net Production of Distillate Fuel Oil Greater than 500 ppm Sulfur (Thousand Barrels per Day) | R128: 4-Week Avg Midwest (PADD 2) Refiner and Blender Net Production of Residual Fuel Oil (Thousand Barrels per Day) | S128: 4-Week Avg Midwest (PADD 2) Refiner, Blender, and Gas Plant Net Production of Propane and Propylene (Thousand Barrels per Day)
A129: 40354 | B129: 2201 | C129: 356 | D129: 354 | E129: 2 | F129: 1845 | G129: 1812 | H129: 1811 | I129: 1 | J129: 33 | K129: 224 | L129: 211 | M129: 13 | N129: 1007 | O129: 955 | P129: 40 | Q129: 11 | R129: 52 | S129: 262
A130: 40361 | B130: 2227 | C130: 362 | D130: 360 | E130: 2 | F130: 1865 | G130: 1841 | H130: 1840 | I130: 1 | J130: 23 | K130: 231 | L130: 217 | M130: 14 | N130: 998 | O130: 952 | P130: 37 | Q130: 9 | R130: 52 | S130: 264
A131: 40368 | B131: 2252 | C131: 366 | D131: 365 | E131: 1 | F131: 1886 | G131: 1862 | H131: 1861 | I131: 1 | J131: 25 | K131: 241 | L131: 225 | M131: 16 | N131: 993 | O131: 949 | P131: 34 | Q131: 10 | R131: 50 | S131: 263
A132: 40375 | B132: 2262 | C132: 364 | D132: 364 | E132: 0 | F132: 1897 | G132: 1859 | H132: 1858 | I132: 1 | J132: 38 | K132: 248 | L132: 233 | M132: 15 | N132: 1019 | O132: 974 | P132: 32 | Q132: 13 | R132: 48 | S132: 263
A133: 40382 | B133: 2265 | C133: 367 | D133: 367 | E133: 0 | F133: 1899 | G133: 1872 | H133: 1871 | I133: 1 | J133: 27 | K133: 253 | L133: 238 | M133: 15 | N133: 1016 | O133: 965 | P133: 33 | Q133: 17 | R133: 44 | S133: 265
A134: 40389 | B134: 2271 | C134: 365 | D134: 365 | E134: 0 | F134: 1906 | G134: 1868 | H134: 1867 | I134: 1 | J134: 38 | K134: 251 | L134: 233 | M134: 17 | N134: 1023 | O134: 966 | P134: 33 | Q134: 23 | R134: 42 | S134: 262
A135: 40396 | B135: 2262 | C135: 366 | D135: 366 | E135: 0 | F135: 1896 | G135: 1862 | H135: 1861 | I135: 1 | J135: 35 | K135: 247 | L135: 233 | M135: 14 | N135: 1027 | O135: 966 | P135: 37 | Q135: 24 | R135: 47 | S135: 261
A136: 40403 | B136: 2267 | C136: 366 | D136: 366 | E136: 0 | F136: 1901 | G136: 1875 | H136: 1873 | I136: 1 | J136: 26 | K136: 244 | L136: 228 | M136: 16 | N136: 1007 | O136: 943 | P136: 41 | Q136: 24 | R136: 48 | S136: 261
A137: 40410 | B137: 2266 | C137: 369 | D137: 369 | E137: 0 | F137: 1897 | G137: 1886 | H137: 1884 | I137: 1 | J137: 12 | K137: 239 | L137: 223 | M137: 16 | N137: 1014 | O137: 944 | P137: 49 | Q137: 21 | R137: 48 | S137: 260
A138: 40417 | B138: 2262 | C138: 370 | D138: 370 | E138: 0 | F138: 1892 | G138: 1890 | H138: 1888 | I138: 1 | J138: 2 | K138: 240 | L138: 225 | M138: 15 | N138: 1013 | O138: 940 | P138: 54 | Q138: 19 | R138: 51 | S138: 261
A139: 40424 | B139: 2256 | C139: 372 | D139: 372 | E139: 0 | F139: 1884 | G139: 1881 | H139: 1879 | I139: 1 | J139: 4 | K139: 230 | L139: 215 | M139: 15 | N139: 991 | O139: 918 | P139: 52 | Q139: 21 | R139: 51 | S139: 260
A140: 40431 | B140: 2213 | C140: 368 | D140: 368 | E140: 0 | F140: 1845 | G140: 1853 | H140: 1852 | I140: 1 | J140: -8 | K140: 233 | L140: 219 | M140: 15 | N140: 998 | O140: 920 | P140: 59 | Q140: 19 | R140: 47 | S140: 260
... A240: 41131 | B240: 2229 | C240: 364 | D240: 364 | E240: 0 | F240: 1865 | G240: 1958 | H240: 1956 | I240: 1 | J240: -93 | K240: 260 | L240: 244 | M240: 16 | N240: 995 | O240: 976 | P240: 16 | Q240: 2 | R240: 54 | S240: 273
A243: Back to Contents | B243: Data 1: PADD 3 Weekly Refiner & Blender Net Production
A244: Sourcekey | B244: WGFRPP32 | C244: WGRRPP32 | D244: WG1TP_R30_2 | E244: W_EPM0RO_YPT_R30_MBBLD | F244: WG4TP_R30_2 | G244: WG5TP_R30_2 | H244: W_EPM0CAL55_YPT_R30_MBBLD | I244: W_EPM0CAG55_YPT_R30_MBBLD | J244: WG6TP_R30_2 | K244: WKJRPP32 | L244: WKCRPP32 | M244: WKMRPP32 | N244: WDIRPP32 | O244: WD0TP_R30_2 | P244: WD1TP_R30_2 | Q244: WDGRPP32 | R244: WRERPP32 | S244: WPRNPP32
A245: Date | B245: 4-Week Avg Gulf Coast (PADD 3) Refiner and Blender Net Production of Finished Motor Gasoline (Thousand Barrels per Day) | C245: 4-Week Avg Gulf Coast (PADD 3) Refiner and Blender Net Production of Reformulated Motor Gasoline (Thousand Barrels per Day) | D245: 4-Week Avg Gulf Coast (PADD 3) Refiner and Blender Net Production of Finished Reformulated Motor Gasoline with Ethanol (Thousand Barrels per Day) | E245: 4-Week Avg Gulf Coast (PADD 3) Refiner and Blender Net Production of Other Finished Reformulated Motor Gasoline (Thousand Barrels per Day) | F245: 4-Week Avg Gulf Coast (PADD 3) Refiner and Blender Net Production of Conventional Motor Gasoline (Thousand Barrels per Day) | G245: 4-Week Avg Gulf Coast (PADD 3) Refiner and Blender Net Production of Finished Conventional Motor Gasoline with Ethanol (Thousand Barrels per Day) | H245: 4-Week Avg Gulf Coast (PADD 3) Refiner and Blender Net Production of Finished Conventional Motor Gasoline, Ed 55 and Lower (Thousand Barrels per Day) | I245: 4-Week Avg Gulf Coast (PADD 3) Refiner and Blender Net Production of Finished Conventional Motor Gasoline, Greater than Ed 55 (Thousand Barrels per Day) | J245: 4-Week Avg Gulf Coast (PADD 3) Refiner and Blender Net Production of Other Finished Conventional Motor Gasoline (Thousand Barrels per Day) | K245: 4-Week Avg Gulf Coast (PADD 3) Refiner and Blender Net Production of Kerosene-Type Jet Fuel (Thousand Barrels per Day) | L245: 4-Week Avg Gulf Coast (PADD 3) Refiner and Blender Net Production of Commercial Kerosene-Type Jet Fuel (Thousand Barrels per Day) | M245: 4-Week Avg Gulf Coast (PADD 3) Refiner and Blender Net Production of Military Kerosene-Type Jet Fuel (Thousand Barrels per Day) | N245: 4-Week Avg Gulf Coast (PADD 3) Refiner and Blender Net Production of Distillate Fuel Oil (Thousand Barrels per Day) | O245: 4-Week Avg Gulf Coast (PADD 3) Refiner and Blender Net Production of Distillate Fuel Oil, 0 to 15 ppm Sulfur (Thousand Barrels per Day) | P245: 4-Week Avg Gulf Coast (PADD 3) Refiner and Blender Net Production of Distillate Fuel Oil, Greater than 15 to 500 ppm Sulfur (Thousand Barrels per Day) | Q245: 4-Week Avg Gulf Coast (PADD 3) Refiner and Blender Net Production of Distillate Fuel Oil Greater than 500 ppm Sulfur (Thousand Barrels per Day) | R245: 4-Week Avg Gulf Coast (PADD 3) Refiner and Blender Net Production of Residual Fuel Oil (Thousand Barrels per Day) | S245: 4-Week Avg Gulf Coast (PADD 3) Refiner, Blender, and Gas Plant Net Production of Propane and Propylene (Thousand Barrels per Day)
A246: 40354 | B246: 2501 | C246: 396 | D246: 378 | E246: 18 | F246: 2105 | G246: 614 | H246: 614 | I246: 0 | J246: 1491 | K246: 721 | L246: 641 | M246: 80 | N246: 2228 | O246: 1728 | P246: 319 | Q246: 181 | R246: 249 | S246: 709
A247: 40361 | B247: 2505 | C247: 387 | D247: 372 | E247: 15 | F247: 2119 | G247: 632 | H247: 632 | I247: 0 | J247: 1486 | K247: 736 | L247: 661 | M247: 75 | N247: 2253 | O247: 1725 | P247: 322 | Q247: 205 | R247: 249 | S247: 702
A248: 40368 | B248: 2511 | C248: 384 | D248: 368 | E248: 16 | F248: 2127 | G248: 640 | H248: 640 | I248: 0 | J248: 1487 | K248: 738 | L248: 672 | M248: 66 | N248: 2288 | O248: 1731 | P248: 331 | Q248: 226 | R248: 239 | S248: 710
A249: 40375 | B249: 2475 | C249: 378 | D249: 364 | E249: 14 | F249: 2097 | G249: 638 | H249: 638 | I249: 0 | J249: 1459 | K249: 758 | L249: 676 | M249: 82 | N249: 2309 | O249: 1759 | P249: 333 | Q249: 218 | R249: 226 | S249: 711
A250: 40382 | B250: 2463 | C250: 381 | D250: 369 | E250: 13 | F250: 2082 | G250: 637 | H250: 637 | I250: 0 | J250: 1445 | K250: 770 | L250: 688 | M250: 82 | N250: 2303 | O250: 1750 | P250: 364 | Q250: 189 | R250: 205 | S250: 713
A251: 40389 | B251: 2445 | C251: 387 | D251: 376 | E251: 11 | F251: 2058 | G251: 620 | H251: 620 | I251: 0 | J251: 1438 | K251: 770 | L251: 681 | M251: 89 | N251: 2300 | O251: 1762 | P251: 364 | Q251: 174 | R251: 190 | S251: 706
A252: 40396 | B252: 2435 | C252: 391 | D252: 377 | E252: 14 | F252: 2044 | G252: 618 | H252: 618 | I252: 0 | J252: 1426 | K252: 758 | L252: 660 | M252: 98 | N252: 2293 | O252: 1771 | P252: 371 | Q252: 152 | R252: 191 | S252: 705
A253: 40403 | B253: 2406 | C253: 406 | D253: 389 | E253: 17 | F253: 2000 | G253: 621 | H253: 621 | I253: 0 | J253: 1379 | K253: 734 | L253: 657 | M253: 76 | N253: 2269 | O253: 1751 | P253: 365 | Q253: 154 | R253: 188 | S253: 705
A254: 40410 | B254: 2420 | C254: 409 | D254: 393 | E254: 16 | F254: 2011 | G254: 627 | H254: 627 | I254: 0 | J254: 1384 | K254: 719 | L254: 636 | M254: 83 | N254: 2280 | O254: 1765 | P254: 342 | Q254: 173 | R254: 179 | S254: 706
A255: 40417 | B255: 2422 | C255: 416 | D255: 397 | E255: 19 | F255: 2006 | G255: 640 | H255: 640 | I255: 0 | J255: 1365 | K255: 694 | L255: 615 | M255: 80 | N255: 2260 | O255: 1750 | P255: 331 | Q255: 179 | R255: 179 | S255: 706
A256: 40424 | B256: 2401 | C256: 405 | D256: 389 | E256: 16 | F256: 1996 | G256: 654 | H256: 654 | I256: 0 | J256: 1341 | K256: 695 | L256: 615 | M256: 81 | N256: 2258 | O256: 1762 | P256: 310 | Q256: 185 | R256: 213 | S256: 712
A257: 40431 | B257: 2414 | C257: 392 | D257: 377 | E257: 15 | F257: 2022 | G257: 667 | H257: 667 | I257: 0 | J257: 1355 | K257: 697 | L257: 608 | M257: 89 | N257: 2263 | O257: 1796 | P257: 285 | Q257: 182 | R257: 230 | S257: 712
... A357: 41131 | B357: 1889 | C357: 408 | D357: 391 | E357: 17 | F357: 1481 | G357: 881 | H357: 881 | I357: 0 | J357: 600 | K357: 820 | L357: 750 | M357: 70 | N357: 2536 | O357: 2264 | P357: 96 | Q357: 176 | R357: 244 | S357: 809
A360: Back to Contents | B360: Data 1: PADD 4 Weekly Refiner & Blender Net Production
A361: Sourcekey | B361: WGFRPP42 | C361: WGRRPP42 | D361: WG1TP_R40_2 | E361: W_EPM0RO_YPT_R40_MBBLD | F361: WG4TP_R40_2 | G361: WG5TP_R40_2 | H361: W_EPM0CAL55_YPT_R40_MBBLD | I361: W_EPM0CAG55_YPT_R40_MBBLD | J361: WG6TP_R40_2 | K361: WKJRPP42 | L361: WKCRPP42 | M361: WKMRPP42 | N361: WDIRPP42 | O361: WD0TP_R40_2 | P361: WD1TP_R40_2 | Q361: WDGRPP42 | R361: WRERPP42
A362: Date | B362: 4-Week Avg Rocky Mountain (PADD 4) Refiner and Blender Net Production of Finished Motor Gasoline (Thousand Barrels per Day) | C362: 4-Week Avg Rocky Mountain (PADD 4) Refiner and Blender Net Production of Reformulated Motor Gasoline (Thousand Barrels per Day) | D362: 4-Week Avg Rocky Mountain (PADD 4) Refiner and Blender Net Production of Finished Reformulated Motor Gasoline with Ethanol (Thousand Barrels per Day) | E362: 4-Week Avg Rocky Mountain (PADD 4) Refiner and Blender Net Production of Other Finished Reformulated Motor Gasoline (Thousand Barrels per Day) | F362: 4-Week Avg Rocky Mountain (PADD 4) Refiner and Blender Net Production of Conventional Motor Gasoline (Thousand Barrels per Day) | G362: 4-Week Avg Rocky Mountain (PADD 4) Refiner and Blender Net Production of Finished Conventional Motor Gasoline with Ethanol (Thousand Barrels per Day) | H362: 4-Week Avg Rocky Mountain (PADD 4) Refiner and Blender Net Production of Finished Conventional Motor Gasoline, Ed 55 and Lower (Thousand Barrels per Day) | I362: 4-Week Avg Rocky Mountain (PADD 4) Refiner and Blender Net Production of Finished Conventional Motor Gasoline, Greater than Ed 55 (Thousand Barrels per Day) | J362: 4-Week Avg Rocky Mountain (PADD 4) Refiner and Blender Net Production of Other Finished Conventional Motor Gasoline (Thousand Barrels per Day) | K362: 4-Week Avg Rocky Mountain (PADD 4) Refiner and Blender Net Production of Kerosene-Type Jet Fuel (Thousand Barrels per Day) | L362: 4-Week Avg Rocky Mountain (PADD 4) Refiner and Blender Net Production of Commercial Kerosene-Type Jet Fuel (Thousand Barrels per Day) | M362: 4-Week Avg Rocky Mountain (PADD 4) Refiner and Blender Net Production of Military Kerosene-Type Jet Fuel (Thousand Barrels per Day) | N362: 4-Week Avg Rocky Mountain (PADD 4) Refiner and Blender Net Production of Distillate Fuel Oil (Thousand Barrels per Day) | O362: 4-Week Avg Rocky Mountain (PADD 4) Refiner and Blender Net Production of Distillate Fuel Oil, 0 to 15 ppm Sulfur (Thousand Barrels per Day) | P362: 4-Week Avg Rocky Mountain (PADD 4) Refiner and Blender Net Production of Distillate Fuel Oil, Greater than 15 to 500 ppm Sulfur (Thousand Barrels per Day) | Q362: 4-Week Avg Rocky Mountain (PADD 4) Refiner and Blender Net Production of Distillate Fuel Oil Greater than 500 ppm Sulfur (Thousand Barrels per Day) | R362: 4-Week Avg Rocky Mountain (PADD 4) Refiner and Blender Net Production of Residual Fuel Oil (Thousand Barrels per Day)
A363: 40354 | B363: 311 | C363: 0 | D363: 0 | E363: 0 | F363: 311 | G363: 158 | H363: 158 | I363: 0 | J363: 153 | K363: 26 | L363: 20 | M363: 6 | N363: 185 | O363: 169 | P363: 15 | Q363: 1 | R363: 10
A364: 40361 | B364: 314 | C364: 0 | D364: 0 | E364: 0 | F364: 314 | G364: 161 | H364: 161 | I364: 0 | J364: 154 | K364: 25 | L364: 18 | M364: 7 | N364: 192 | O364: 173 | P364: 16 | Q364: 3 | R364: 10
A365: 40368 | B365: 326 | C365: 0 | D365: 0 | E365: 0 | F365: 326 | G365: 161 | H365: 161 | I365: 0 | J365: 165 | K365: 24 | L365: 18 | M365: 6 | N365: 192 | O365: 180 | P365: 11 | Q365: 1 | R365: 10
A366: 40375 | B366: 332 | C366: 0 | D366: 0 | E366: 0 | F366: 332 | G366: 164 | H366: 164 | I366: 0 | J366: 168 | K366: 26 | L366: 20 | M366: 6 | N366: 195 | O366: 184 | P366: 10 | Q366: 1 | R366: 10
A367: 40382 | B367: 337 | C367: 0 | D367: 0 | E367: 0 | F367: 337 | G367: 167 | H367: 166 | I367: 0 | J367: 171 | K367: 27 | L367: 21 | M367: 6 | N367: 194 | O367: 183 | P367: 11 | Q367: 0 | R367: 10
A368: 40389 | B368: 330 | C368: 0 | D368: 0 | E368: 0 | F368: 330 | G368: 168 | H368: 168 | I368: 0 | J368: 162 | K368: 29 | L368: 23 | M368: 6 | N368: 192 | O368: 181 | P368: 12 | Q368: -2 | R368: 10
A369: 40396 | B369: 327 | C369: 0 | D369: 0 | E369: 0 | F369: 327 | G369: 173 | H369: 173 | I369: 0 | J369: 154 | K369: 32 | L369: 26 | M369: 6 | N369: 186 | O369: 174 | P369: 12 | Q369: 0 | R369: 8
A370: 40403 | B370: 315 | C370: 0 | D370: 0 | E370: 0 | F370: 315 | G370: 173 | H370: 173 | I370: 0 | J370: 142 | K370: 32 | L370: 27 | M370: 5 | N370: 179 | O370: 164 | P370: 12 | Q370: 2 | R370: 8
A371: 40410 | B371: 310 | C371: 0 | D371: 0 | E371: 0 | F371: 310 | G371: 173 | H371: 173 | I371: 0 | J371: 137 | K371: 30 | L371: 26 | M371: 4 | N371: 177 | O371: 163 | P371: 12 | Q371: 2 | R371: 8
A372: 40417 | B372: 304 | C372: 0 | D372: 0 | E372: 0 | F372: 304 | G372: 170 | H372: 169 | I372: 0 | J372: 135 | K372: 31 | L372: 26 | M372: 5 | N372: 171 | O372: 158 | P372: 10 | Q372: 3 | R372: 9
A373: 40424 | B373: 302 | C373: 0 | D373: 0 | E373: 0 | F373: 302 | G373: 164 | H373: 163 | I373: 0 | J373: 138 | K373: 28 | L373: 23 | M373: 5 | N373: 176 | O373: 161 | P373: 11 | Q373: 4 | R373: 9
A374: 40431 | B374: 296 | C374: 0 | D374: 0 | E374: 0 | F374: 296 | G374: 158 | H374: 158 | I374: 0 | J374: 138 | K374: 30 | L374: 24 | M374: 6 | N374: 176 | O374: 164 | P374: 11 | Q374: 1 | R374: 10
... A474: 41131 | B474: 291 | C474: 0 | D474: 0 | E474: 0 | F474: 291 | G474: 248 | H474: 248 | I474: 0 | J474: 43 | K474: 26 | L474: 22 | M474: 4 | N474: 202 | O474: 202 | P474: 1 | Q474: -2 | R474: 13
A477: Back to Contents | B477: Data 1: West Coast (PADD 5) Weekly Refiner & Blender Net Production
A478: Sourcekey | B478: WGFRPP52 | C478: WGRRPP52 | D478: WG1TP_R50_2 | E478: W_EPM0RO_YPT_R50_MBBLD | F478: WG4TP_R50_2 | G478: WG5TP_R50_2 | H478: W_EPM0CAL55_YPT_R50_MBBLD | I478: W_EPM0CAG55_YPT_R50_MBBLD | J478: WG6TP_R50_2 | K478: WKJRPP52 | L478: WKCRPP52 | M478: WKMRPP52 | N478: WDIRPP52 | O478: WD0TP_R50_2 | P478: WD1TP_R50_2 | Q478: WDGRPP52 | R478: WRERPP52
A479: Date | B479: 4-Week Avg West Coast (PADD 5) Refiner and Blender Net Production of Finished Motor Gasoline (Thousand Barrels per Day) | C479: 4-Week Avg West Coast (PADD 5) Refiner and Blender Net Production of Reformulated Motor Gasoline (Thousand Barrels per Day) | D479: 4-Week Avg West Coast (PADD 5) Refiner and Blender Net Production of Finished Reformulated Motor Gasoline with Ethanol (Thousand Barrels per Day) | E479: 4-Week Avg West Coast (PADD 5) Refiner and Blender Net Production of Other Finished Reformulated Motor Gasoline (Thousand Barrels per Day) | F479: 4-Week Avg West Coast (PADD 5) Refiner and Blender Net Production of Conventional Motor Gasoline (Thousand Barrels per Day) | G479: 4-Week Avg West Coast (PADD 5) Refiner and Blender Net Production of Finished Conventional Motor Gasoline with Ethanol (Thousand Barrels per Day) | H479: 4-Week Avg West Coast (PADD 5) Refiner and Blender Net Production of Finished Conventional Motor Gasoline, Ed 55 and Lower (Thousand Barrels per Day) | I479: 4-Week Avg West Coast (PADD 5) Refiner and Blender Net Production of Finished Conventional Motor Gasoline, Greater than Ed 55 (Thousand Barrels per Day) | J479: 4-Week Avg West Coast (PADD 5) Refiner and Blender Net Production of Other Finished Conventional Motor Gasoline (Thousand Barrels per Day) | K479: 4-Week Avg West Coast (PADD 5) Refiner and Blender Net Production of Kerosene-Type Jet Fuel (Thousand Barrels per Day) | L479: 4-Week Avg West Coast (PADD 5) Refiner and Blender Net Production of Commercial Kerosene-Type Jet Fuel (Thousand Barrels per Day) | M479: 4-Week Avg West Coast (PADD 5) Refiner and Blender Net Production of Military Kerosene-Type Jet Fuel (Thousand Barrels per Day) | N479: 4-Week Avg West Coast (PADD 5) Refiner and Blender Net Production of Distillate Fuel Oil (Thousand Barrels per Day) | O479: 4-Week Avg West Coast (PADD 5) Refiner and Blender Net Production of Distillate Fuel Oil, 0 to 15 ppm Sulfur (Thousand Barrels per Day) | P479: 4-Week Avg West Coast (PADD 5) Refiner and Blender Net Production of Distillate Fuel Oil, Greater than 15 to 500 ppm Sulfur (Thousand Barrels per Day) | Q479: 4-Week Avg West Coast (PADD 5) Refiner and Blender Net Production of Distillate Fuel Oil Greater than 500 ppm Sulfur (Thousand Barrels per Day) | R479: 4-Week Avg West Coast (PADD 5) Refiner and Blender Net Production of Residual Fuel Oil (Thousand Barrels per Day)
A480: 40354 | B480: 1468 | C480: 980 | D480: 965 | E480: 15 | F480: 488 | G480: 384 | H480: 383 | I480: 1 | J480: 104 | K480: 380 | L480: 337 | M480: 43 | N480: 534 | O480: 485 | P480: 27 | Q480: 22 | R480: 121
A481: 40361 | B481: 1457 | C481: 988 | D481: 978 | E481: 11 | F481: 469 | G481: 377 | H481: 377 | I481: 1 | J481: 91 | K481: 401 | L481: 348 | M481: 54 | N481: 523 | O481: 472 | P481: 29 | Q481: 22 | R481: 111
A482: 40368 | B482: 1447 | C482: 985 | D482: 974 | E482: 11 | F482: 462 | G482: 382 | H482: 382 | I482: 0 | J482: 80 | K482: 414 | L482: 359 | M482: 55 | N482: 531 | O482: 484 | P482: 27 | Q482: 20 | R482: 113
A483: 40375 | B483: 1437 | C483: 976 | D483: 963 | E483: 13 | F483: 461 | G483: 383 | H483: 383 | I483: 0 | J483: 78 | K483: 423 | L483: 375 | M483: 48 | N483: 523 | O483: 476 | P483: 27 | Q483: 20 | R483: 120
A484: 40382 | B484: 1447 | C484: 984 | D484: 968 | E484: 16 | F484: 462 | G484: 388 | H484: 388 | I484: 0 | J484: 74 | K484: 427 | L484: 377 | M484: 50 | N484: 524 | O484: 471 | P484: 26 | Q484: 26 | R484: 123
A485: 40389 | B485: 1481 | C485: 992 | D485: 971 | E485: 21 | F485: 489 | G485: 395 | H485: 394 | I485: 0 | J485: 95 | K485: 412 | L485: 371 | M485: 41 | N485: 516 | O485: 468 | P485: 25 | Q485: 23 | R485: 131
A486: 40396 | B486: 1491 | C486: 999 | D486: 980 | E486: 19 | F486: 492 | G486: 397 | H486: 397 | I486: 0 | J486: 95 | K486: 399 | L486: 363 | M486: 36 | N486: 495 | O486: 444 | P486: 26 | Q486: 26 | R486: 120
A487: 40403 | B487: 1505 | C487: 1004 | D487: 987 | E487: 18 | F487: 501 | G487: 397 | H487: 396 | I487: 0 | J487: 104 | K487: 392 | L487: 352 | M487: 40 | N487: 477 | O487: 423 | P487: 27 | Q487: 27 | R487: 112
A488: 40410 | B488: 1501 | C488: 1004 | D488: 988 | E488: 16 | F488: 498 | G488: 397 | H488: 397 | I488: 0 | J488: 100 | K488: 386 | L488: 350 | M488: 36 | N488: 468 | O488: 408 | P488: 28 | Q488: 33 | R488: 113
A489: 40417 | B489: 1497 | C489: 1009 | D489: 993 | E489: 17 | F489: 488 | G489: 397 | H489: 397 | I489: 0 | J489: 90 | K489: 390 | L489: 349 | M489: 41 | N489: 471 | O489: 404 | P489: 27 | Q489: 41 | R489: 107
A490: 40424 | B490: 1491 | C490: 1008 | D490: 990 | E490: 18 | F490: 484 | G490: 391 | H490: 391 | I490: 0 | J490: 92 | K490: 402 | L490: 356 | M490: 46 | N490: 479 | O490: 404 | P490: 27 | Q490: 48 | R490: 109
A491: 40431 | B491: 1480 | C491: 1004 | D491: 988 | E491: 16 | F491: 476 | G491: 389 | H491: 389 | I491: 0 | J491: 87 | K491: 406 | L491: 355 | M491: 51 | N491: 502 | O491: 431 | P491: 30 | Q491: 41 | R491: 105
... A591: 41131 | B591: 1571 | C591: 1066 | D591: 1066 | E591: 0 | F591: 505 | G591: 403 | H591: 403 | I591: 0 | J591: 102 | K591: 472 | L591: 436 | M591: 36 | N591: 556 | O591: 507 | P591: 8 | Q591: 40 | R591: 130

Sheet Inputs ELC NG
B1: Refining Industry Energy Consumption, Reference case
B3: Shipments and Energy Consumption | C3: 2009 | D3: 2010 | E3: 2015 | F3: 2020 | G3: 2025 | H3: 2030 | I3: 2035
B5: Value of Shipments (billion 2000 dollars) | C5: 424.83 | D5: 437.21 | E5: 439.05 | F5: 436.9 | G5: 437.19 | H5: 438 | I5: 438.9
B6: Inputs to Distillation Units
B7: (million barrels per day) | C7: 15.02 | D7: 15.33 | E7: 15.31 | F7: 14.39 | G7: 14.15 | H7: 14.01 | I7: 14.01
B9: Total Energy Consumption (trillion Btu) 1/
B10: Residual Fuel Oil | C10: 7.9 | D10: 7.9 | E10: 0 | F10: 0 | G10: 0 | H10: 0 | I10: 0
B11: Distillate Fuel Oil | C11: 2 | D11: 2 | E11: 0 | F11: 0 | G11: 0 | H11: 0 | I11: 0
A12: IRF000 | B12: Liquefied Petroleum Gases | C12: 10.3 | D12: 10.3 | E12: 11.5 | F12: 11.5 | G12: 11.5 | H12: 11.5 | I12: 11.5
B13: Petroleum Coke | C13: 518.8 | D13: 518.8 | E13: 531.5 | F13: 491.7 | G13: 493 | H13: 510.7 | I13: 533.6
B14: Still Gas | C14: 1497.7 | D14: 1497.7 | E14: 1547.5 | F14: 1363.4 | G14: 1338.3 | H14: 1385.2 | I14: 1452.8
B15: Other Petroleum 2/ | C15: 16.9 | D15: 16.9 | E15: 23 | F15: 22.2 | G15: 21.8 | H15: 22.3 | I15: 22.8
B16: Petroleum Subtotal | C16: 2053.6 | D16: 2053.6 | E16: 2113.6 | F16: 1888.8 | G16: 1864.6 | H16: 1929.8 | I16: 2020.6
A17: IRF000:ba_ValueofShipme | B17: Natural Gas | C17: 1383.1 | D17: 1441.2 | E17: 1480.1 | F17: 1529.9 | G17: 1545.6 | H17: 1507.9 | I17: 1508
B18: Steam Coal 3/ | C18: 60.3 | D18: 60.3 | E18: 62 | F18: 315.2 | G18: 423.8 | H18: 538.3 | I18: 659.6
A19: IRF000:ba_CrudeOilInput | B19: Renewables | C19: 0 | D19: 0 | E19: 0 | F19: 0 | G19: 0 | H19: 0 | I19: 0
B20: Purchased Electricity | C20: 190.7 | D20: 196.7 | E20: 195.4 | F20: 195.7 | G20: 195 | H20: 203 | I20: 213.3
B21: Total | C21: 3687.6 | D21: 3751.8 | E21: 3851.1 | F21: 3929.6 | G21: 4028.9 | H21: 4179 | I21: 4401.5
A22: IRF000:ca_ResidualOil
A23: IRF000:ca_DistillateOil
A24: IRF000:ca_LiquefiedPetr | B24: Carbon Dioxide Emissions 4/ (million metric tons) | C24: 261.4 | D24: 265.9 | E24: 268 | F24: 278.9 | G24: 288.9 | H24: 303.6 | I24: 322.9
A25: IRF000:ca_PetroleumCoke
A26: IRF000:ca_StillGas | B26: Energy Consumption per Unit of Refinery Input
A27: IRF000:ca_OtherPetroleu | B27: (thousand Btu per barrel)
A28: IRF000:ca_PetroleumSubt | B28: Residual Fuel Oil | C28: 1.4 | D28: 1.4 | E28: 0 | F28: 0 | G28: 0 | H28: 0 | I28: 0
A29: IRF000:ca_NaturalGas | B29: Distillate Fuel Oil | C29: 0.4 | D29: 0.4 | E29: 0 | F29: 0 | G29: 0 | H29: 0 | I29: 0
A30: IRF000:ca_SteamCoal | B30: Liquefied Petroleum Gases | C30: 1.9 | D30: 1.8 | E30: 2.1 | F30: 2.2 | G30: 2.2 | H30: 2.2 | I30: 2.2
A31: IRF000:ca_Renewables | B31: Petroleum Coke | C31: 92.1 | D31: 90.2 | E31: 95.1 | F31: 93.6 | G31: 95.4 | H31: 99.9 | I31: 104.4
A32: IRF000:ca_PurchasedElec | B32: Still Gas | C32: 255 | D32: 249.8 | E32: 254.4 | F32: 236.1 | G32: 235.4 | H32: 247.2 | I32: 260.3
A33: IRF000:ca_Total | B33: Other Petroleum 2/ | C33: 3.1 | D33: 3 | E33: 4.1 | F33: 4.2 | G33: 4.2 | H33: 4.4 | I33: 4.5
B34: Petroleum Subtotal | C34: 353.8 | D34: 346.7 | E34: 355.7 | F34: 336.1 | G34: 337.2 | H34: 353.6 | I34: 371.3
B35: Natural Gas | C35: 134.5 | D35: 131.8 | E35: 139.8 | F35: 149.7 | G35: 150 | H35: 145.4 | I35: 139.8
A36: IRF000:ea_tonscarbon_dd | B36: Steam Coal 3/ | C36: 0 | D36: 0 | E36: 0 | F36: 0 | G36: 0 | H36: 0 | I36: 0
B37: Purchased Electricity | C37: 26.8 | D37: 26.2 | E37: 26 | F37: 26.8 | G37: 26.5 | H37: 28.4 | I37: 29.9
B38: Total | C38: 515.1 | D38: 504.6 | E38: 521.6 | F38: 512.6 | G38: 513.8 | H38: 527.5 | I38: 541
A40: IRF000:db_ResidualOil | B40: Combined Heat and Power
A41: IRF000:db_DistillateOil | B41: Generating Capacity (gigawatts)
A42: IRF000:db_LiquefiedPetr | B42: Petroleum | C42: 0.04 | D42: 0.04 | E42: 0.09 | F42: 0.09 | G42: 0.09 | H42: 0.09 | I42: 0.09
A43: IRF000:db_PetroleumCoke | B43: Natural Gas | C43: 2.9 | D43: 2.9 | E43: 2.63 | F43: 2.63 | G43: 2.63 | H43: 2.63 | I43: 2.63
A44: IRF000:db_StillGas | B44: Coal 3/ | C44: 0.14 | D44: 0.14 | E44: 0.03 | F44: 2.46 | G44: 3.49 | H44: 4.6 | I44: 5.78
A45: IRF000:db_OtherPetroleu | B45: Other 5/ | C45: 0.71 | D45: 0.71 | E45: 1.61 | F45: 1.95 | G45: 2.87 | H45: 5.4 | I45: 7.43
A46: IRF000:db_PetroleumSubt | B46: Total | C46: 3.79 | D46: 3.79 | E46: 4.36 | F46: 7.13 | G46: 9.08 | H46: 12.72 | I46: 15.93
A47: IRF000:db_NaturalGas | B47: Net Generation (billion kilowatthours)
A48: IRF000:db_SteamCoal | B48: Petroleum | C48: 0.42 | D48: 0.42 | E48: 0 | F48: 0 | G48: 0 | H48: 0 | I48: 0
A49: IRF000:db_PurchasedElec | B49: Natural Gas | C49: 16.47 | D49: 16.47 | E49: 16.12 | F49: 15.85 | G49: 15.69 | H49: 15.54 | I49: 15.63
A50: IRF000:db_Total | B50: Coal 3/ | C50: 0.54 | D50: 0.54 | E50: 0.19 | F50: 18.28 | G50: 26.02 | H50: 34.25 | I50: 43.03
B51: Other 5/ | C51: 4.87 | D51: 4.87 | E51: 10.22 | F51: 12.73 | G51: 20.51 | H51: 42.13 | I51: 59.57
B52: Total | C52: 22.31 | D52: 22.31 | E52: 26.53 | F52: 46.86 | G52: 62.22 | H52: 91.92 | I52: 118.23
B53: Disposition
A54: IRF000:ga_Petroleum | B54: Sales to the Grid | C54: 6.9 | D54: 6.9 | E54: 8.56 | F54: 15.98 | G54: 25.67 | H54: 48.33 | I54: 67.1
A55: IRF000:ga_NaturalGas | B55: Generation for Own Use | C55: 15.4 | D55: 15.4 | E55: 17.98 | F55: 30.87 | G55: 36.55 | H55: 43.59 | I55: 51.13
A56: IRF000:ga_Coal
A57: IRF000:ga_Other | B57: Energy Consumed at Ethanol Plants
A58: IRF000:ga_Total | B58: (trillion Btu)
B59: Natural Gas | C59: 422.6 | D59: 480.7 | E59: 477.8 | F59: 526.5 | G59: 555.7 | H59: 551.6 | I59: 578.9
A60: IRF000:ha_Petroleum | B60: Coal | C60: 59.6 | D60: 59.6 | E60: 59.2 | F60: 59.6 | G60: 59.6 | H60: 59.6 | I60: 59.6
A61: IRF000:ha_NaturalGas | B61: Electricity | C61: 43.9 | D61: 49.9 | E61: 49.9 | F61: 54.9 | G61: 58 | H61: 57.5 | I61: 60.5
A62: IRF000:ha_Coal | B62: Total | C62: 526 | D62: 590.2 | E62: 586.9 | F62: 640.9 | G62: 673.2 | H62: 668.7 | I62: 698.9
A63: IRF000:ha_Other
A64: IRF000:ha_Total | B64: 1/ Fuel consumption includes consumption for combined heat and power and consumption at ethanol plants.
B65: 2/ Includes lubricants and miscellaneous petroleum products.
A66: IRF000:ha_SalestotheGri | B66: 3/ Where coal-to-liquids (CTL) technology is adopted in the forecast, the plants are assumed to produce oil products and to
A67: IRF000:ha_Generationfor | B67: generate electricity. A portion of the coal use is attributed to feedstock use to produce the liquids. The feedstock portion
B68: is assumed to be equal to the Btu content of the liquids produced. The rest of the coal used in CTL plants is accounted for in
B69: industrial steam coal consumption, a portion of which is reflected in energy used for end-use sector combined heat and power.
B70: 4/ Includes emissions attributable to the fuels consumed to generate the purchased electricity.
A71: IRF000:ja_NaturalGas | B71: 5/ May include wood and other biomass, waste heat, municipal waste, and renewable sources.
A72: IRF000:ja_Coal | B72: Btu = British thermal unit.
A73: IRF000:ja_Electricity | B73: - - = Not applicable.
A74: IRF000:ja_Total | B74: Note: Totals may not equal sum of components due to independent rounding. Data for 2009 and
B75: 2010 are model results and may differ slightly from official EIA data reports.
B76: Source: 2009 and 2010 combined heat and power capacity and net generation: Energy
B77: Information Administration (EIA), Form EIA-860: "Annual Electric Generator Report," (preliminary). 2009
B78: and 2010 coal and natural gas consumption at ethanol plants: Carbon Dioxide Emissions from the Production and
B79: Combustion of Fuel Ethanol from Corn," Marland, G. and A.F. Turhollow, 1991. 2009 and 2010
B80: electricity consumption at ethanol plants: U.S. Department of Agriculture, 1998 Ethanol Cost-of-Production Survey, Agricultural
B81: Economic Report Number 808. Other 2009 and 2010 data based on: EIA, Manufacturing Energy
B82: Consumption Survey, 2006. Projections: EIA, AEO2012 National Energy Modeling System.

Sheet RTI Costs
A1: From RTI Workbook "Task_5_Refinery_investment_costs", 3/31/2010
A3: Final Costs Data
B4: MARKAL Region | C4: Number of Projects by Region for Data Collected | D4: Expansion / Heavy Crude | E4: Expansion / Sweet Crude | F4: New Refinery / Heavy Crude
D5: Units in 2000$M/PJ/year
B6: R1 | C6: 0 | D6: 0 | E6: 0 | F6: 0
B7: R2 | C7: 0 | D7: 17.48386 | E7: 7.4023218 | F7: 7.8488827
B8: R3 | C8: 4 | D8: 25.079529 | E8: 3.3110095 | F8: 7.8488827
B9: R4 | C9: 8 | D9: 30.78297 | E9: 3.1007907 | F9: 9.5497756
B10: R5 | C10: 0 | D10: 17.48386 | E10: 7.4023218 | F10: 7.8488827
B11: R6 | C11: 2 | D11: 17.48386 | E11: 8.3092468 | F11: 7.8488827
B12: R7 | C12: 9 | D12: 7.8496217 | E12: 3.3801585 | F12: 1.095442
B13: R8 | C13: 3 | D13: 2.9707134 | E13: 3.3785777 | F13: 9.4996447
B14: R9 | C14: 2 | D14: 17.48386 | E14: 41.775402 | F14: 7.8488827
B15: Average values were used in instances where no expansion data was obtained and highlighted in red text. No refineries are located in R1. No refinery expansion data was obtained for refineries in R2 and are therefore represented by average values.
A18: From Costs Summary Sheet:
B19: MARKAL Region | C19: Number of Projects by Region | D19: Expansion / Heavy Crude | E19: Expansion / Sweet Crude | F19: New Refinery / Heavy Crude
D20: Units in 2000$M/PJ/year
B21: R2 | C21: 0 | D21: ND | E21: ND | F21: ND
B22: R3 | C22: 4 | D22: 25.079529 | E22: 3.3110095 | F22: 0
B23: R4 | C23: 8 | D23: 30.78297 | E23: 3.1007907 | F23: 9.5497756
B24: R5 | C24: 0 | D24: ND | E24: ND | F24: ND
B25: R6 | C25: 2 | D25: 0 | E25: 8.3092468 | F25: 0
B26: R7 | C26: 9 | D26: 7.8496217 | E26: 3.3801585 | F26: 1.095442
B27: R8 | C27: 3 | D27: 2.9707134 | E27: 3.3785777 | F27: 9.4996447
B28: R9 | C28: 2 | D28: 0 | E28: 41.775402 | F28: 0
B29: Average for Investment Category | D29: 17.48386 | E29: 7.4023218 | F29: 7.8488827
B30: Note: - means 0 projects in that particular category; ND = no data, no expansion projects at all in that region. No refineries in R1 and no new refineries for processing sweet crude in any region.

Sheet Conv
B1: Conversion Factors
B3: Annual Energy Review 2010
B4: Tablele A1. Approximate Heat Content of Petroleum Products | H4: 1 barrel (bbl) | I4: 42 | J4: U. S. gallons (gal)
B5: http://www.eia.gov/totalenergy/data/annual/pdf/sec12_1.pdf | H5: MMBTU | I5: 1.055056e-06 | J5: PJ
B6: (Million Btu per Barrel) | C6: MMBtu per bbl | D6: MMBtu per gal | H6: Quad= | I6: 1055 | J6: PJ
B7: Asphalt | C7: 6.636 | D7: =C7/$I$4 -> 0.158 | H7: kwh= | I7: 3412 | J7: BTU
B8: Aviation Gasoline | C8: 5.048 | D8: =C8/$I$4 -> 0.12019048
B9: Butane | C9: 4.326 | D9: =C9/$I$4 -> 0.103 | H9: NIPA Table 1.1.9. Implicit Price Deflators for Gross Domestic Product
B10: Butane- Propane Mixture (60 percent-40 percent) | C10: 4.13 | D10: =C10/$I$4 -> 0.098333333 | H10: [Index numbers, 2005=100]
B11: Distillate Fuel Oil | C11: 5.825 | D11: =C11/$I$4 -> 0.13869048 | H11: US Department of Commerce: Bureau of Economic Analysis
B12: Ethane | C12: 3.082 | D12: =C12/$I$4 -> 0.073380952 | H12: http://www.bea.gov/national/nipaweb/SelectTable.asp?Selected=Y
B13: Ethane- Propane Mixture (70 percent-30 percent) | C13: 3.308 | D13: =C13/$I$4 -> 0.078761905 | H13: Downloaded on 4/20/2012 Last Revised March 29,2012
B14: Isobutane | C14: 3.974 | D14: =C14/$I$4 -> 0.094619048 | H14: Year | I14: Deflator | J14: To convert this year to 2005, multiply by
B15: Jet Fuel, Kerosene- Type | C15: 5.67 | D15: =C15/$I$4 -> 0.135 | H15: 1983 | I15: 57.652 | J15: =$I$37/I15 -> 1.7345452
B16: Jet Fuel, Naphtha- Type | C16: 5.355 | D16: =C16/$I$4 -> 0.1275 | H16: 1984 | I16: 59.817 | J16: =$I$37/I16 -> 1.6717656
B17: Kerosene | C17: 5.67 | D17: =C17/$I$4 -> 0.135 | H17: 1985 | I17: 61.628 | J17: =$I$37/I17 -> 1.6226391
B18: Lubricants | C18: 6.065 | D18: =C18/$I$4 -> 0.14440476 | H18: 1986 | I18: 62.991 | J18: =$I$37/I18 -> 1.5875284
B19: Motor Gasoline | H19: 1987 | I19: 64.819 | J19: =$I$37/I19 -> 1.5427575
B20: Conventional | C20: 5.2531 | D20: =C20/$I$4 -> 0.12507381 | H20: 1988 | I20: 67.046 | J20: =$I$37/I20 -> 1.4915133
B21: Oxygenated | C21: 5.1501 | D21: =C21/$I$4 -> 0.12262143 | H21: 1989 | I21: 69.577 | J21: =$I$37/I21 -> 1.4372566
B22: Reformulated | C22: 5.1501 | D22: =C22/$I$4 -> 0.12262143 | H22: 1990 | I22: 72.262 | J22: =$I$37/I22 -> 1.3838532
B23: Fuel Ethanol | C23: 3.539 | D23: =C23/$I$4 -> 0.084261905 | H23: 1991 | I23: 74.824 | J23: =$I$37/I23 -> 1.3364696
B24: Natural Gasoline | C24: 4.62 | D24: =C24/$I$4 -> 0.11 | H24: 1992 | I24: 76.598 | J24: =$I$37/I24 -> 1.3055171
B25: Pentanes Plus | C25: 4.62 | D25: =C25/$I$4 -> 0.11 | H25: 1993 | I25: 78.29 | J25: =$I$37/I25 -> 1.2773023
B26: Petrochemical Feedstocks | C26: =AVERAGE(C27:C29) -> 5.691 | D26: =AVERAGE(D27:D29) -> 0.1355 | H26: 1994 | I26: 79.94 | J26: =$I$37/I26 -> 1.2509382
B27: Naphtha less than 401° F | C27: 5.248 | D27: =C27/$I$4 -> 0.12495238 | H27: 1995 | I27: 81.606 | J27: =$I$37/I27 -> 1.2254001
B28: Other Oils equal to or greater than 401° F | C28: 5.825 | D28: =C28/$I$4 -> 0.13869048 | H28: 1996 | I28: 83.159 | J28: =$I$37/I28 -> 1.2025157
B29: Still Gas | C29: 6 | D29: =C29/$I$4 -> 0.14285714 | H29: 1997 | I29: 84.628 | J29: =$I$37/I29 -> 1.181642
B30: Petroleum Coke | C30: 6.024 | D30: =C30/$I$4 -> 0.14342857 | H30: 1998 | I30: 85.584 | J30: =$I$37/I30 -> 1.1684427
B31: Plant Condensate | C31: 5.418 | D31: =C31/$I$4 -> 0.129 | H31: 1999 | I31: 86.842 | J31: =$I$37/I31 -> 1.1515165
B32: Propane | C32: 3.836 | D32: =C32/$I$4 -> 0.091333333 | H32: 2000 | I32: 88.723 | J32: =$I$37/I32 -> 1.1271035
B33: Residual Fuel Oil | C33: 6.287 | D33: =C33/$I$4 -> 0.14969048 | H33: 2001 | I33: 90.727 | J33: =$I$37/I33 -> 1.1022077
B34: Road Oil | C34: 6.636 | D34: =C34/$I$4 -> 0.158 | H34: 2002 | I34: 92.196 | J34: =$I$37/I34 -> 1.0846458
B35: Special Naphthas | C35: 5.248 | D35: =C35/$I$4 -> 0.12495238 | H35: 2003 | I35: 94.135 | J35: =$I$37/I35 -> 1.0623041
B36: Still Gas | C36: 6 | D36: =C36/$I$4 -> 0.14285714 | H36: 2004 | I36: 96.786 | J36: =$I$37/I36 -> 1.0332073
B37: Unfinished Oils | C37: 5.825 | D37: =C37/$I$4 -> 0.13869048 | H37: 2005 | I37: 100 | J37: =$I$37/I37 -> 1
B38: Unfractionated Stream | C38: 5.418 | D38: =C38/$I$4 -> 0.129 | H38: 2006 | I38: 103.23 | J38: =$I$37/I38 -> 0.96871065
... B40: Miscellaneous | C40: 5.796 | D40: =C40/$I$4 -> 0.138 | H40: 2008 | I40: 108.58 | J40: =$I$37/I40 -> 0.92097992
H41: 2009 | I41: 109.73 | J41: =$I$37/I41 -> 0.9113278
B42: From AEO2012 Appendix | C42: MMBtu per bbl | H42: 2010 | I42: 110.99 | J42: =$I$37/I42 -> 0.90098207
B43: http://www.eia.gov/forecasts/aeo/pdf/0383(2012).pdf
B44: LPG | C44: 3.557 | D44: =C44/$I$4 -> 0.084690476
B45: Crude-domestic | C45: 5.8
B46: Crude-imported | C46: 5.98
B47: Crude-average | C47: =(2*C46+C45)/3 -> 5.92
C49: MMBtu per cf | D49: cf/bblFOE | E49: MMBtu per bblFOE
B50: Natural gas | C50: 0.001024 | D50: 6917 | E50: =C50*D50 -> 7.083008
B51: Natural Gas Plant Liquids (2005) | E51: 3.674
AF57: Btu per cubic foot 1,025
AF58: Btu per cubic foot 1,009

Sheet ANSv6.0-Commodities
A1: ANSWER-Commodities
B7: CommName | C7: CommDesc | D7: CommUnit | E7: Set Memberships | F7: Comment

Sheet ANSv6.1-Commodities
A1: ANSWER-Commodities
B7: CommName | C7: CommDesc | D7: CommUnit | E7: Set Memberships | F7: Comment

Sheet ANSv6.0-Technologies
A1: ANSWER-Technologies
B7: TechName | C7: TechDesc | D7: TACTUnit | E7: TCAPUnit | F7: Set Memberships | G7: Comment

Sheet ANSv6.1-Technologies
A1: ANSWER-Technologies
B7: TechName | C7: TechDesc | D7: TACTUnit | E7: TCAPUnit | F7: Set Memberships | G7: Comment

Sheet ANSv6.0-TechData
A1: ANSWER-TechData
B7: TechName | C7: TechDesc | D7: Units | E7: CommIN | F7: CommOUT

Sheet ANSv6.0-CommData
A1: ANSWER-CommData
B7: CommName | C7: CommDesc | D7: Units

Sheet ANSv6.0-Constraints
A1: ANSWER-Constraints
B7: ConstrName | C7: ConstrDesc | D7: Units | E7: Set Memberships | F7: Comment

Sheet ANSv6.1-Constraints
A1: ANSWER-Constraints
B7: ConstrName | C7: ConstrDesc | D7: Units | E7: Set Memberships | F7: Comment

Sheet ANSv6.1-CommData
A1: ANSWER-CommData
B7: CommName | C7: CommDesc | D7: Units

Sheet ANSv6.1-TechData
A1: ANSWER-TechData
B7: TechName | C7: TechDesc | D7: Units | E7: CommIN | F7: CommOUT

Sheet ANSv6.0-ConstrData
A1: ANSWER-ConstrData
B7: ConstrName | C7: ConstrDesc | D7: Units | E7: TechName

Sheet ANSv6.1-ConstrData
A1: ANSWER-ConstrData
B7: ConstrName | C7: ConstrDesc | D7: Units | E7: TechName

Sheet EPAUS9RTechData
A1: *TechData | B1: R0,R1,R2,R3,R4,R5,R6
G5: INP(ENT)p | H5: OUT(ENC)p | I5: START | J5: LIFE | K5: CAPUNIT | L5: AF | M5: LIMIT | N5: INVCOST | O5: FIXOM | P5: FIXOM | Q5: FIXOM | R5: FIXOM | S5: FIXOM | T5: FIXOM | U5: RESID | V5: IBOND(UP)
B7: TechName | C7: TechDesc | D7: Units | E7: CommIN | F7: CommOUT | H7: 2005-2055 | I7: TID | J7: TID | K7: TID | O7: 2005 | P7: 2010 | Q7: 2015 | R7: 2020 | S7: 2025 | T7: 2030-2055 | U7: 2005-2055
A8: * Collectors
A9: =Commodities!B18 -> *R1,R2,R3,R4,R5,R6 | B9: SCLPG_E | C9: Collector: LPG from REF_E | D9: PJ, PJ/a | E9: LPG_E | F9: LPG | G9: 1 | H9: 1 | O9: 0.001 | P9: 0.001 | Q9: 0.001 | R9: 0.001 | S9: 0.001 | T9: 0.001
A10: =Commodities!B19 -> R1 | B10: SCGSC_E | C10: Collector: GSC from REF_E | E10: GSC_E | F10: GSC | G10: 1 | H10: 1 | O10: 0.001 | P10: 0.001 | Q10: 0.001 | R10: 0.001 | S10: 0.001 | T10: 0.001
A11: =Commodities!B20 -> R1 | B11: SCGSR_E | C11: Collector: GSR from REF_E | E11: GSR_E | F11: GSR | G11: 1 | H11: 1 | O11: 0.001 | P11: 0.001 | Q11: 0.001 | R11: 0.001 | S11: 0.001 | T11: 0.001
A12: =Commodities!B21 -> *R1,R2,R3,R4,R5,R6 | B12: SCJTF_E | C12: Collector: JTF from REF_E | E12: JTF_E | F12: JTF | G12: 1 | H12: 1 | O12: 0.001 | P12: 0.001 | Q12: 0.001 | R12: 0.001 | S12: 0.001 | T12: 0.001
A13: =Commodities!B22 -> R1 | B13: SCDSH_E | C13: Collector: DSH from REF_E | E13: DSH_E | F13: DSH | G13: 1 | H13: 1 | O13: 0.001 | P13: 0.001 | Q13: 0.001 | R13: 0.001 | S13: 0.001 | T13: 0.001
A14: =Commodities!B23 -> R1 | B14: SCRFL_E | C14: Collector: RFL from REF_E | E14: RFL_E | F14: RFL | G14: 1 | H14: 1 | O14: 0.001 | P14: 0.001 | Q14: 0.001 | R14: 0.001 | S14: 0.001 | T14: 0.001
A15: =Commodities!B24 -> *R1,R2,R3,R4,R5,R6 | B15: SCRFH_E | C15: Collector: RFH from REF_E | E15: RFH_E | F15: RFH | G15: 1 | H15: 1 | O15: 0.001 | P15: 0.001 | Q15: 0.001 | R15: 0.001 | S15: 0.001 | T15: 0.001
A16: =Commodities!B25 -> *R1,R2,R3,R4,R5,R6 | B16: SCKER_E | C16: Collector: KER from REF_E | E16: KER_E | F16: KER | G16: 1 | H16: 1 | O16: 0.001 | P16: 0.001 | Q16: 0.001 | R16: 0.001 | S16: 0.001 | T16: 0.001
A17: =Commodities!B26 -> *R1,R2,R3,R4,R5,R6 | B17: SCPFS_E | C17: Collector: PFS from REF_E | E17: PFS_E | F17: PFS | G17: 1 | H17: 1 | O17: 0.001 | P17: 0.001 | Q17: 0.001 | R17: 0.001 | S17: 0.001 | T17: 0.001
A18: =Commodities!B27 -> *R1,R2,R3,R4,R5,R6 | B18: SCASP_E | C18: Collector: ASP from REF_E | E18: ASP_E | F18: ASP | G18: 1 | H18: 1 | O18: 0.001 | P18: 0.001 | Q18: 0.001 | R18: 0.001 | S18: 0.001 | T18: 0.001
A19: =Commodities!B28 -> R1 | B19: SCDSL_E | C19: Collector: DSL from REF_E | E19: DSL_E | F19: DSL | G19: 1 | H19: 1 | O19: 0.001 | P19: 0.001 | Q19: 0.001 | R19: 0.001 | S19: 0.001 | T19: 0.001
A20: =Commodities!B29 -> R1 | B20: SCDSU_E | C20: Collector: DSU from REF_E | E20: DSU_E | F20: DSU | G20: 1 | H20: 1 | O20: 0.001 | P20: 0.001 | Q20: 0.001 | R20: 0.001 | S20: 0.001 | T20: 0.001
A21: =Commodities!B30 -> *R1,R2,R3,R4,R5,R6 | B21: SCPTC_E | C21: Collector: PTC from REF_E | E21: PTC_E | F21: PTC | G21: 1 | H21: 1 | O21: 0.001 | P21: 0.001 | Q21: 0.001 | R21: 0.001 | S21: 0.001 | T21: 0.001
A22: =Commodities!B31 -> *R1,R2,R3,R4,R5,R6 | B22: SCDLG_E | C22: Collector DLG from REF_E | E22: DLG_E | F22: DLG | G22: 1 | H22: 1 | O22: 0.001 | P22: 0.001 | Q22: 0.001 | R22: 0.001 | S22: 0.001 | T22: 0.001
A23: =Commodities!B33 -> *R1,R2,R3,R4,R5,R6 | B23: SCLPG_N | C23: Collector: LPG from REF_N | E23: LPG_N | F23: LPG | G23: 1 | H23: 1 | O23: 0.001 | P23: 0.001 | Q23: 0.001 | R23: 0.001 | S23: 0.001 | T23: 0.001
A24: =Commodities!B34 -> R1 | B24: SCGSC_N | C24: Collector: GSC from REF_N | E24: GSC_N | F24: GSC | G24: 1 | H24: 1 | O24: 0.001 | P24: 0.001 | Q24: 0.001 | R24: 0.001 | S24: 0.001 | T24: 0.001
A25: =Commodities!B35 -> R1 | B25: SCGSR_N | C25: Collector: GSR from REF_N | E25: GSR_N | F25: GSR | G25: 1 | H25: 1 | O25: 0.001 | P25: 0.001 | Q25: 0.001 | R25: 0.001 | S25: 0.001 | T25: 0.001
A26: =Commodities!B36 -> *R1,R2,R3,R4,R5,R6 | B26: SCJTF_N | C26: Collector: JTF from REF_N | E26: JTF_N | F26: JTF | G26: 1 | H26: 1 | O26: 0.001 | P26: 0.001 | Q26: 0.001 | R26: 0.001 | S26: 0.001 | T26: 0.001
A27: =Commodities!B37 -> R1 | B27: SCDSH_N | C27: Collector: DSH from REF_N | E27: DSH_N | F27: DSH | G27: 1 | H27: 1 | O27: 0.001 | P27: 0.001 | Q27: 0.001 | R27: 0.001 | S27: 0.001 | T27: 0.001
A28: =Commodities!B38 -> R1 | B28: SCRFL_N | C28: Collector: RFL from REF_N | E28: RFL_N | F28: RFL | G28: 1 | H28: 1 | O28: 0.001 | P28: 0.001 | Q28: 0.001 | R28: 0.001 | S28: 0.001 | T28: 0.001
A29: =Commodities!B39 -> *R1,R2,R3,R4,R5,R6 | B29: SCRFH_N | C29: Collector: RFH from REF_N | E29: RFH_N | F29: RFH | G29: 1 | H29: 1 | O29: 0.001 | P29: 0.001 | Q29: 0.001 | R29: 0.001 | S29: 0.001 | T29: 0.001
A30: =Commodities!B40 -> *R1,R2,R3,R4,R5,R6 | B30: SCKER_N | C30: Collector: KER from REF_N | E30: KER_N | F30: KER | G30: 1 | H30: 1 | O30: 0.001 | P30: 0.001 | Q30: 0.001 | R30: 0.001 | S30: 0.001 | T30: 0.001
A31: =Commodities!B41 -> *R1,R2,R3,R4,R5,R6 | B31: SCPFS_N | C31: Collector: PFS from REF_N | E31: PFS_N | F31: PFS | G31: 1 | H31: 1 | O31: 0.001 | P31: 0.001 | Q31: 0.001 | R31: 0.001 | S31: 0.001 | T31: 0.001
A32: =Commodities!B42 -> *R1,R2,R3,R4,R5,R6 | B32: SCASP_N | C32: Collector: ASP from REF_N | E32: ASP_N | F32: ASP | G32: 1 | H32: 1 | O32: 0.001 | P32: 0.001 | Q32: 0.001 | R32: 0.001 | S32: 0.001 | T32: 0.001
A33: =Commodities!B43 -> R1 | B33: SCDSL_N | C33: Collector: DSL from REF_N | E33: DSL_N | F33: DSL | G33: 1 | H33: 1 | O33: 0.001 | P33: 0.001 | Q33: 0.001 | R33: 0.001 | S33: 0.001 | T33: 0.001
A34: =Commodities!B44 -> R1 | B34: SCDSU_N | C34: Collector: DSU from REF_N | E34: DSU_N | F34: DSU | G34: 1 | H34: 1 | O34: 0.001 | P34: 0.001 | Q34: 0.001 | R34: 0.001 | S34: 0.001 | T34: 0.001
... A36: =Commodities!B46 -> *R1,R2,R3,R4,R5,R6 | B36: SCDLG_N | C36: Collector DLG from REF_N | E36: DLG_N | F36: DLG | G36: 1 | H36: 1 | O36: 0.001 | P36: 0.001 | Q36: 0.001 | R36: 0.001 | S36: 0.001 | T36: 0.001
A37: =Commodities!B48 -> *R1,R2,R3,R4,R5,R6 | B37: SCLPG_L | C37: Collector: LPG from REF_L | E37: LPG_L | F37: LPG | G37: 1 | H37: 1 | O37: 0.001 | P37: 0.001 | Q37: 0.001 | R37: 0.001 | S37: 0.001 | T37: 0.001
A38: =Commodities!B49 -> R1 | B38: SCGSC_L | C38: Collector: GSC from REF_L | E38: GSC_L | F38: GSC | G38: 1 | H38: 1 | O38: 0.001 | P38: 0.001 | Q38: 0.001 | R38: 0.001 | S38: 0.001 | T38: 0.001
A39: =Commodities!B50 -> R1 | B39: SCGSR_L | C39: Collector: GSR from REF_L | E39: GSR_L | F39: GSR | G39: 1 | H39: 1 | O39: 0.001 | P39: 0.001 | Q39: 0.001 | R39: 0.001 | S39: 0.001 | T39: 0.001
A40: =Commodities!B51 -> *R1,R2,R3,R4,R5,R6 | B40: SCJTF_L | C40: Collector: JTF from REF_L | E40: JTF_L | F40: JTF | G40: 1 | H40: 1 | O40: 0.001 | P40: 0.001 | Q40: 0.001 | R40: 0.001 | S40: 0.001 | T40: 0.001
A41: =Commodities!B52 -> R1 | B41: SCDSH_L | C41: Collector: DSH from REF_L | E41: DSH_L | F41: DSH | G41: 1 | H41: 1 | O41: 0.001 | P41: 0.001 | Q41: 0.001 | R41: 0.001 | S41: 0.001 | T41: 0.001
A42: =Commodities!B53 -> R1 | B42: SCRFL_L | C42: Collector: RFL from REF_L | E42: RFL_L | F42: RFL | G42: 1 | H42: 1 | O42: 0.001 | P42: 0.001 | Q42: 0.001 | R42: 0.001 | S42: 0.001 | T42: 0.001
A43: =Commodities!B54 -> *R1,R2,R3,R4,R5,R6 | B43: SCRFH_L | C43: Collector: RFH from REF_L | E43: RFH_L | F43: RFH | G43: 1 | H43: 1 | O43: 0.001 | P43: 0.001 | Q43: 0.001 | R43: 0.001 | S43: 0.001 | T43: 0.001
A44: =Commodities!B55 -> *R1,R2,R3,R4,R5,R6 | B44: SCKER_L | C44: Collector: KER from REF_L | E44: KER_L | F44: KER | G44: 1 | H44: 1 | O44: 0.001 | P44: 0.001 | Q44: 0.001 | R44: 0.001 | S44: 0.001 | T44: 0.001
A45: =Commodities!B56 -> *R1,R2,R3,R4,R5,R6 | B45: SCPFS_L | C45: Collector: PFS from REF_L | E45: PFS_L | F45: PFS | G45: 1 | H45: 1 | O45: 0.001 | P45: 0.001 | Q45: 0.001 | R45: 0.001 | S45: 0.001 | T45: 0.001
A46: =Commodities!B57 -> *R1,R2,R3,R4,R5,R6 | B46: SCASP_L | C46: Collector: ASP from REF_L | E46: ASP_L | F46: ASP | G46: 1 | H46: 1 | O46: 0.001 | P46: 0.001 | Q46: 0.001 | R46: 0.001 | S46: 0.001 | T46: 0.001
A47: =Commodities!B58 -> R1 | B47: SCDSL_L | C47: Collector: DSL from REF_L | E47: DSL_L | F47: DSL | G47: 1 | H47: 1 | O47: 0.001 | P47: 0.001 | Q47: 0.001 | R47: 0.001 | S47: 0.001 | T47: 0.001
A48: =Commodities!B59 -> R1 | B48: SCDSU_L | C48: Collector: DSU from REF_L | E48: DSU_L | F48: DSU | G48: 1 | H48: 1 | O48: 0.001 | P48: 0.001 | Q48: 0.001 | R48: 0.001 | S48: 0.001 | T48: 0.001
A49: =Commodities!B60 -> *R1,R2,R3,R4,R5,R6 | B49: SCPTC_L | C49: Collector: PTC from REF_L | E49: PTC_L | F49: PTC | G49: 1 | H49: 1 | O49: 0.001 | P49: 0.001 | Q49: 0.001 | R49: 0.001 | S49: 0.001 | T49: 0.001
A50: R1 | B50: PREFE | C50: Refinery-existing conversion | D50: PJ, PJ/a | E50: =Commodities!C74 -> OIL | F50: LPG_E | G50: =Capacity!I3 -> 1.0378549 | H50: 0.06 | I50: 2010 | J50: 40 | K50: 1 | L50: 1 | M50: 1 | O50: 0.11551107 | P50: 0.12898736 | Q50: 0.14403589 | R50: 0.1470456 | S50: 0.14833547 | T50: 0.14145614 | U50: =RESID!K21 -> 2074.6655 | V50: =0 -> 0
E51: =Commodities!C75 -> NGA | F51: GSR_E | G51: ='Inputs ELC NG'!C35/Conv!C45/1000*G50*1.8 -> 0.043321495 | H51: ='PADD Products'!I4/100 -> 0.544452
E52: =Commodities!C73 -> ELC | F52: GSC_E | G52: ='Inputs ELC NG'!C37/Conv!C45/1000*G50 -> 0.0047956054 | H52: ='PADD Products'!I5/100 -> 0
E53: =Commodities!$C$82 -> NGL | F53: JTF_E | G53: 0 | H53: ='PADD Products'!I6/100 -> 0.061128
F54: KER_E | H54: ='PADD Products'!I7/100 -> 0.004104
F55: DSU_E | H55: ='PADD Products'!I8/100 -> 0.21783261
F56: DSL_E | H56: ='PADD Products'!I9/100 -> 0
F57: DSH_E | H57: ='PADD Products'!I10/100 -> 0.11618676
F58: RFL_E | H58: ='PADD Products'!I11/100 -> 0.064152
F59: RFH_E | H59: =H58 -> 0.064152
F60: PFS_E | H60: ='PADD Products'!I13/100 -> 0.008208
F61: PTC_E | H61: ='PADD Products'!I14/100 -> 0.03348
F62: ASP_E | H62: ='PADD Products'!I15/100 -> 0.053784
F63: DLG_E | H63: 0.2
B64: PREFN | C64: Refinery-new conversion | E64: =Commodities!C74 -> OIL | F64: LPG_N | G64: =G50 -> 1.0378549 | H64: =H50 -> 0.06 | I64: 2015 | J64: 40 | K64: 1 | L64: 1 | M64: 1 | N64: ='RTI Costs'!F7*Conv!J32 -> 8.8465028 | O64: 0.11551107 | P64: 0.12898736 | Q64: 0.14403589 | R64: 0.1470456 | S64: 0.14833547 | T64: 0.14145614 | V64: =0 -> 0
E65: =Commodities!C75 -> NGA | F65: GSR_N | G65: =$G$51 -> 0.043321495 | H65: =H51 -> 0.544452
E66: =Commodities!C73 -> ELC | F66: GSC_N | G66: =$G$52 -> 0.0047956054 | H66: =H52 -> 0
E67: =Commodities!$C$82 -> NGL | F67: JTF_N | G67: =$G$53 -> 0 | H67: =H53 -> 0.061128
F68: KER_N | H68: =H54 -> 0.004104
F69: DSU_N | H69: =H55 -> 0.21783261
F70: DSL_N | H70: =H56 -> 0
F71: DSH_N | H71: =H57 -> 0.11618676
F72: RFL_N | H72: =H58 -> 0.064152
F73: RFH_N | H73: =H59 -> 0.064152
F74: PFS_N | H74: =H60 -> 0.008208
F75: PTC_N | H75: =H61 -> 0.03348
F76: ASP_N | H76: =H62 -> 0.053784
F77: DLG_N | H77: 0.2
B78: PREFL | C78: Refinery-new limit | E78: DLG | F78: LPG_L | G78: 1 | H78: =H50*1.25 -> 0.075 | I78: 2010 | J78: 40 | K78: 1 | L78: 1 | M78: 1 | N78: =4.4 -> 4.4
F79: GSR_L | H79: =H51*1.4 -> 0.7622328
F80: GSC_L | H80: =H52*1.4 -> 0
F81: JTF_L | H81: =H53*1.25 -> 0.07641
F82: KER_L | H82: =H54*2 -> 0.008208
F83: DSU_L | H83: =H55*1.4 -> 0.30496566
F84: DSL_L | H84: =H56*1.4 -> 0
F85: DSH_L | H85: =H57*1.25 -> 0.14523345
F86: RFL_L | H86: =H58*1.25 -> 0.08019
F87: RFH_L | H87: =H59*1.25 -> 0.08019
F88: PFS_L | H88: =H60*1.25 -> 0.01026
F89: PTC_L | H89: =H61*1.25 -> 0.04185
F90: ASP_L | H90: =H62*1.25 -> 0.06723
A91: R2 | B91: PREFE | C91: Refinery-existing conversion | E91: =Commodities!$C$74 -> OIL | F91: LPG_E | G91: =Capacity!I4 -> 1.1031014 | H91: 0.06 | I91: 2010 | J91: 40 | K91: 1 | L91: 1 | M91: 1 | O91: 0.10182132 | P91: 0.10733511 | Q91: 0.11314748 | R91: 0.12225353 | S91: 0.11547243 | T91: 0.11977133 | U91: =RESID!K24 -> 0 | V91: =0 -> 0
E92: =Commodities!$C$75 -> NGA | F92: GSR_E | G92: =$G$51 -> 0.043321495 | H92: ='PADD Products'!J4/100 -> 0.593835
E93: =Commodities!$C$73 -> ELC | F93: GSC_E | G93: =$G$52 -> 0.0047956054 | H93: ='PADD Products'!J5/100 -> 0
E94: =Commodities!$C$82 -> NGL | F94: JTF_E | G94: =$G$53 -> 0 | H94: ='PADD Products'!J6/100 -> 0.07074
F95: KER_E | H95: ='PADD Products'!J7/100 -> 0.00027
F96: DSU_E | H96: ='PADD Products'!J8/100 -> 0.33126229
F97: DSL_E | H97: ='PADD Products'!J9/100 -> 0
F98: DSH_E | H98: ='PADD Products'!J10/100 -> 0.0021014988
F99: RFL_E | H99: ='PADD Products'!J11/100 -> 0.01566
F100: RFH_E | H100: =H99 -> 0.01566
F101: PFS_E | H101: ='PADD Products'!J13/100 -> 0.01107
F102: PTC_E | H102: ='PADD Products'!J14/100 -> 0.04698
F103: ASP_E | H103: ='PADD Products'!J15/100 -> 0.05346
F104: DLG_E | H104: 0.2
B105: PREFN | C105: Refinery-new conversion | E105: =Commodities!$C$74 -> OIL | F105: LPG_N | G105: =G91 -> 1.1031014 | H105: =H91 -> 0.06 | I105: 2015 | J105: 40 | K105: 1 | L105: 1 | M105: 1 | N105: ='RTI Costs'!F8*Conv!J32 -> 8.8465028 | O105: 0.10182132 | P105: 0.10733511 | Q105: 0.11314748 | R105: 0.12225353 | S105: 0.11547243 | T105: 0.11977133 | V105: =RESID!G19 -> 0
...
