Workbook
Name __HDV50: #REF!
Name __HDV50: #REF!
Name __HDV50: #REF!
Name __LDV50: #REF!
Name __LDV50: #REF!
Name __LDV50: #REF!
Name _1995_Implicit_GDP_Deflator: #REF!
Name _1995_Implicit_GDP_Deflator: #REF!
Name _1995_Implicit_GDP_Deflator: #REF!
Name _2001_Implicit_GDP_Deflator: #REF!
Name _2001_Implicit_GDP_Deflator: #REF!
Name _2001_Implicit_GDP_Deflator: #REF!
Name Age_of_car: #REF!
Name Age_of_car: #REF!
Name Age_of_car: #REF!
Name avg_water_heater_PJ: '[1]AEO HW'!$B$33
Name btu_per_watthr: #REF!
Name btu_per_watthr: #REF!
Name btu_per_watthr: #REF!
Name conv: #REF!
Name conv: #REF!
Name conv: #REF!
Name days_per_year: #REF!
Name days_per_year: #REF!
Name days_per_year: #REF!
Name Diesel_Car_CO: #REF!
Name Diesel_Car_CO: #REF!
Name Diesel_Car_CO: #REF!
Name Diesel_Car_Nox: #REF!
Name Diesel_Car_Nox: #REF!
Name Diesel_Car_Nox: #REF!
Name Diesel_Car_PM: #REF!
Name Diesel_Car_PM: #REF!
Name Diesel_Car_PM: #REF!
Name Diesel_Car_VOCs: #REF!
Name Diesel_Car_VOCs: #REF!
Name Diesel_Car_VOCs: #REF!
Name Diesel_HDT_CO: #REF!
Name Diesel_HDT_CO: #REF!
Name Diesel_HDT_CO: #REF!
Name Diesel_HDT_NOx: #REF!
Name Diesel_HDT_NOx: #REF!
Name Diesel_HDT_NOx: #REF!
Name Diesel_HDT_PM: #REF!
Name Diesel_HDT_PM: #REF!
Name Diesel_HDT_PM: #REF!
Name Diesel_HDT_SO2: #REF!
Name Diesel_HDT_SO2: #REF!
Name Diesel_HDT_SO2: #REF!
Name Diesel_HDT_VOCs: #REF!
Name Diesel_HDT_VOCs: #REF!
Name Diesel_HDT_VOCs: #REF!
Name Diesel_LDT_CO: #REF!
Name Diesel_LDT_CO: #REF!
Name Diesel_LDT_CO: #REF!
Name Diesel_LDT_Nox: #REF!
Name Diesel_LDT_Nox: #REF!
Name Diesel_LDT_Nox: #REF!
Name Diesel_LDT_PM: #REF!
Name Diesel_LDT_PM: #REF!

Sheet Readme
B1: Readme - 05-12-2022
B3: For questions contact: Ozge Kaplan, kaplan.ozge@epa.gov, 919-541-5069
B4: Contributors:
B5: Mine Isik, Former ORISE
B6: Andrew Zalesak, ORISE
B8: General Notes
B9: Tabs for pages that consist primarily of input data are colored blue
B10: Tabs for pages that consist primarily of calculations are white
B11: Tabs for pages that are read into Answer are colored yellow
B12: The tabs generally should be navigated from right to left, e.g., the
B13: pages with input data tables are the right-most. Calculations
B14: come next (with each subsequent page typically building on the
... B20: Population Data ("Population")
C21: '- U.S. Census Bureau projections
C22: '- U.S. EPA ORD Integrated Land Use Scenarios model projections
C23: - NYC Population Estimates
B24: Vehicle Miles Traveled Breakdown by Region ("Demands")
C25: '- EIA Household Transportation Energy Use Survey, 2001
B27: Price Deflators to Convert Costs to $2000 ("GDPdeflator")
C28: '- Bureau of Economic Analysis NIPA Table 1.1.9
B30: Vehicle Sales Data by Class ("Sales Data")
C31: '- EIA Annual Energy Outlook 2008, Table 51
B33: Technology Cost and Efficiency Estimates ("AEO08 T59","AEO08 T60","OTAQ-Car","OTAQ-Truck","QM2002")
C34: '- EIA Annual Energy Outlook 2008, Tables 59 and 60
C35: '- OTAQ vehicle assumptions for SGM provided by Simon Mui
C36: '- Vehicle maintenance estimates from DOE's Quality Metrics Report 2002
B38: Emissions (ICF WA on County Level MOVES runs)
C39: -county simulated MOVES runs
B41: Existing Fleet Info
C42: '- Transportation Energy Data book, Edition 21
C43: - NYC.GOV
B46: General Flow of Operations for Preparing Data for Input to ANSWER
B47: Demand Calculation:
C48: '- Regional VMT demands are calculated in "VMT by Region"
B50: Vehicle Characterization:
C51: '- Vehicle efficiency and cost calculations for vehicles described in AEO are provided in the "Costs" and "Efficiencies" pages
C52: - Additional vehicle types are characterized in "AdditionalVehs"
C53: '- The AEO and additional vehicle data are consolidated in "ConsolidatedVehData"
B55: Emissions Characterization:
C56: - Emission factors from MOVES are consolidated in "NewEmisData"
C57: '- These factors are linked to vehicle technologies & classes in "Emissions Linkage"
B59: Characterization of Existing Fleet:
C60: '- Carried out in "Existing Fleet"
B62: Formated Input for Loading into Answer
C63: '- Demands: "CommData"
C64: '- Backstop technologies: "TechDataZZ" (not currently used)
C65: '- Emissions: "TechData-Emissions"
C66: '- Characterization of existing vehicles: "TechData_RES" (RES here represents "residual")
C67: '- Characterization of vehicle costs, efficiencies, fuels, lifetimes, etc.: "TechData_All"
C68: '- Market share and fuel share constraints: "ConstrData"
C69: '- Declaration of fuel, technology, and constraint names: "Constraints", "Technologies", "Commodities"
B71: Exogenous Assumptions:
B72: '* Population growth - several projections are available from different sources
B73: * VMT/person by region is calculated from input data.
C74: -inelastic
B76: '* Market share breakdown by class is constrained to follow AEO
C77: projections
B78: '* Vehicle cost and efficiency data is largely from AEO's time
C79: series projections. We do not assume that learning will decrease
C80: costs (although some degree of learning is likely represented in
C81: AEO's projections for technologies that penetrate the market)
B84: Endogenous Calculations:
B85: MARKAL seeks to find the set of technologies in all modeled sectors
B86: that meets energy demands at least cost. Fuel prices are calculated
B87: endogenously as a function of their supply curves. The primary outputs
B88: include technology penetrations, fuel use, and the resulting
B89: emissions. The model may also have to meet other constraints, such
B90: as lower or upper bounds on market share for technologies and/or
B91: fuels.

Sheet ANSv6.0-Commodities
A1: ANSWER-Commodities
B7: CommName | C7: CommDesc | D7: CommUnit | E7: Set Memberships | F7: Comment

Sheet ANSv6.1-Commodities
A1: ANSWER-Commodities
B7: CommName | C7: CommDesc | D7: CommUnit | E7: Set Memberships | F7: Comment

Sheet Commodities
B6: ~FI_Comm
B7: Region | C7: Csets | D7: CommName | E7: CommDesc | F7: Unit | G7: LimType | H7: CTSLvl | I7: PeakTS | J7: Ctype | O7: Comment
B8: *Demands
B9: R2,R3,R4,R5,R6 | C9: DEM | D9: TL | E9: Transportation Light Duty | F9: bn-vmt
B10: *Emissions Commodities
B11: *R2,R3,R4,R5,R6 | C11: ENV | D11: NH3 | E11: Ammonia | F11: kt
B12: *R2,R3,R4,R5,R6 | C12: ENV | D12: CO2T | E12: Transportaiton sector CO2 | F12: kt
B13: *R2,R3,R4,R5,R6 | C13: ENV | D13: NOXT | E13: Transportation sector NOx | F13: kt
B14: *R2,R3,R4,R5,R6 | C14: ENV | D14: SO2T | E14: Transportation sector SO2 | F14: kt
B15: *R2,R3,R4,R5,R6 | C15: ENV | D15: PM10T | E15: Transportation sector PM10 | F15: kt
B16: *R2,R3,R4,R5,R6 | C16: ENV | D16: PM25T | E16: Transportation sector PM25 | F16: kt
B23: *Energy Carriers
B24: R2,R3,R4,R5,R6 | C24: NRG | D24: TRNDSL | E24: DSL to TRN | F24: PJ
B25: R2,R3,R4,R5,R6 | C25: NRG | D25: TLGSL | E25: GSL to TRN | F25: PJ
B26: *R2,R3,R4,R5,R6 | C26: NRG | D26: TLE85X | E26: E85X to TL | F26: PJ
B27: *R2,R3,R4,R5,R6 | C27: NRG | D27: TRNCNG | E27: CNG to TRN | F27: PJ
B28: R2,R3,R4,R5,R6 | C28: NRG | D28: TRNCNGL | E28: CNG to TRN - Light Duty Vehicles | F28: PJ
B29: *R2,R3,R4,R5,R6 | C29: NRG | D29: TRNCNGX | E29: CNGX to TRN | F29: PJ
B30: *R2,R3,R4,R5,R6 | C30: NRG | D30: TRNLPGX | E30: LPGX to TRN | F30: PJ
B31: *R2,R3,R4,R5,R6 | C31: NRG | D31: TRNLPGEA | E31: LPG to TRN after Collection | F31: PJ
B32: R2,R3,R4,R5,R6 | C32: NRG | D32: TRNELC | E32: ELC to TRN | F32: PJ
B33: R2,R3,R4,R5,R6 | C33: NRG | D33: TRNH2 | E33: H2 to TRN | F33: PJ
B44: *Energy Carriers
B45: R2,R3,R4,R5,R6 | C45: NRG | D45: ELC | E45: Electricity | F45: PJ
B46: *R2,R3,R4,R5,R6 | C46: NRG | D46: TRNNGA | E46: Natural Gas to Transportation Sector | F46: PJ
B47: *R2,R3,R4,R5,R6 | C47: NRG | D47: TRNCNGH | E47: CNG to TRN - Heavy Duty Vehicles | F47: PJ
B48: *R2,R3,R4,R5,R6 | C48: NRG | D48: TRNCNGX | E48: CNGX to TRN | F48: PJ
B49: *R2,R3,R4,R5,R6 | C49: NRG | D49: TRDSLL | E49: DSLL to Blend | F49: PJ
B50: *R2,R3,R4,R5,R6 | C50: NRG | D50: TRDSLU | E50: DSLU to Blend | F50: PJ
B51: *R2,R3,R4,R5,R6 | C51: NRG | D51: TRNDSLB | E51: DSL combo of DSLL and DSLU | F51: PJ
B52: *R2,R3,R4,R5,R6 | C52: NRG | D52: TRNE10 | E52: E10 Blend | F52: PJ
B53: *R2,R3,R4,R5,R6 | C53: NRG | D53: TRNE85 | E53: E85 Blend | F53: PJ
B54: *R2,R3,R4,R5,R6 | C54: NRG | D54: TRNETH | E54: Ethanol to Transportation Sector | F54: PJ
B55: *R2,R3,R4,R5,R6 | C55: NRG | D55: TRGSLC1 | E55: CONV GSL to TRN after Collection | F55: PJ
B56: *R2,R3,R4,R5,R6 | C56: NRG | D56: TRGSLR1 | E56: REF GSL to TRN after Collection | F56: PJ
... B71: R2,R3,R4,R5,R6 | C71: NRG | D71: ZZDMY | E71: Dummy commodity | F71: PJ
B72: *Emissions Commodities
B73: *R2,R3,R4,R5,R6 | C73: ENV | D73: CO2 | E73: Carbon dioxide emissions | F73: Mt
B74: R2,R3,R4,R5,R6 | C74: ENV | D74: NOX | E74: NOx emissions | F74: kt
B75: R2,R3,R4,R5,R6 | C75: ENV | D75: SO2 | E75: SO2 emissions | F75: kt
B76: R2,R3,R4,R5,R6 | C76: ENV | D76: PM10 | E76: PM10 emissions | F76: kt
B77: *R2,R3,R4,R5,R6 | C77: ENV | D77: PM25 | E77: PM2.5 emissions | F77: kt
B78: *R2,R3,R4,R5,R6 | C78: ENV | D78: CO | E78: Carbon monoxide | F78: kt
B79: *R2,R3,R4,R5,R6 | C79: ENV | D79: N2O | E79: Nitrous oxide | F79: kt
B80: *R2,R3,R4,R5,R6 | C80: ENV | D80: CH4 | E80: Methane | F80: kt
B81: *R2,R3,R4,R5,R6 | C81: ENV | D81: VOC | E81: VOCs | F81: kt
B82: *R2,R3,R4,R5,R6 | C82: ENV | D82: BC | E82: Black carbon | F82: kt
B83: *R2,R3,R4,R5,R6 | C83: ENV | D83: OC | E83: Organic carbon | F83: kt

Sheet ANSv6.0-Technologies
A1: ANSWER-Technologies
B7: TechName | C7: TechDesc | D7: TACTUnit | E7: TCAPUnit | F7: Set Memberships | G7: Comment

Sheet ANSv6.1-Technologies
A1: ANSWER-Technologies
B7: TechName | C7: TechDesc | D7: TACTUnit | E7: TCAPUnit | F7: Set Memberships | G7: Comment

Sheet Technologies
B6: ~FI_Process
B7: Region | C7: Sets | D7: TechName | E7: TechDesc | F7: Tact | G7: Tcap | H7: PrimaryCG | I7: Vintage
B8: * Light Duty Vehicle Demand Technologies - Existing
B9: =TechData_existing!A7 -> R2,R3,R4,R5,R6 | C9: DMD | D9: =TechData_existing!B7 -> TLEMCGSL | E9: =TechData_existing!C7 -> TL.GSL.MC.Existing fleet | F9: bn-vmt | G9: bn-vmt/a
B10: =TechData_existing!A8 -> R2,R3,R4,R5,R6 | C10: DMD | D10: =TechData_existing!B8 -> TLECGSL | E10: =TechData_existing!C8 -> TL.GSL.C.Existing fleet | F10: bn-vmt | G10: bn-vmt/a
B11: =TechData_existing!A9 -> R2,R3,R4,R5,R6 | C11: DMD | D11: =TechData_existing!B9 -> TLEFDSL | E11: =TechData_existing!C9 -> TL.DSL.F.Existing fleet | F11: bn-vmt | G11: bn-vmt/a
B12: =TechData_existing!A10 -> R2,R3,R4,R5,R6 | C12: DMD | D12: =TechData_existing!B10 -> TLEFGSL | E12: =TechData_existing!C10 -> TL.GSL.F.Existing fleet | F12: bn-vmt | G12: bn-vmt/a
B13: =TechData_existing!A11 -> R2,R3,R4,R5,R6 | C13: DMD | D13: =TechData_existing!B11 -> TLESSGSL | E13: =TechData_existing!C11 -> TL.GSL.SS.Existing fleet | F13: bn-vmt | G13: bn-vmt/a
B14: =TechData_existing!A12 -> R2,R3,R4,R5,R6 | C14: DMD | D14: =TechData_existing!B12 -> TLELSGSL | E14: =TechData_existing!C12 -> TL.GSL.LS.Existing fleet | F14: bn-vmt | G14: bn-vmt/a
B15: =TechData_existing!A13 -> R2,R3,R4,R5,R6 | C15: DMD | D15: =TechData_existing!B13 -> TLEMGSL | E15: =TechData_existing!C13 -> TL.GSL.M.Existing Fleet | F15: bn-vmt | G15: bn-vmt/a
B16: =TechData_existing!A14 -> R2,R3,R4,R5,R6 | C16: DMD | D16: =TechData_existing!B14 -> TLEPGSL | E16: =TechData_existing!C14 -> TL.GSL.P.Existing Fleet | F16: bn-vmt | G16: bn-vmt/a
B17: =TechData_existing!A15 -> R2,R3,R4,R5,R6 | C17: DMD | D17: =TechData_existing!B15 -> TLEPDSL | E17: =TechData_existing!C15 -> TL.DSL.P.Existing fleet | F17: bn-vmt | G17: bn-vmt/a
B18: =TechData_existing!A16 -> * | C18: DMD | D18: =TechData_existing!B16 -> TLEETHX | E18: =TechData_existing!C16 -> TL.E85X.F.Existing fleet | F18: bn-vmt | G18: bn-vmt/a
B19: =TechData_existing!A17 -> * | C19: DMD | D19: =TechData_existing!B17 -> TLECNGX | E19: =TechData_existing!C17 -> TL.CNGX.F.Existing fleet | F19: bn-vmt | G19: bn-vmt/a
B20: =TechData_existing!A18 -> * | C20: DMD | D20: =TechData_existing!B18 -> TLELPGX | E20: =TechData_existing!C18 -> TL.LPGX.F.Existing fleet | F20: bn-vmt | G20: bn-vmt/a
B21: =TechData_existing!A19 -> R2,R3,R4,R5,R6 | C21: DMD | D21: =TechData_existing!B19 -> TLEELC | E21: =TechData_existing!C19 -> TL.ELC.F.Existing fleet | F21: bn-vmt | G21: bn-vmt/a
B29: * Process Technologies
B30: * | C30: PRE | D30: PNGACNG | E30: Conv: NGA to CNG | F30: PJ | G30: PJ/a
B31: * Collectors
B32: *R2,R3,R4,R5,R6 | C32: PRE | D32: SCTRNCNGL | E32: Collector: CNG to TRN LDV | F32: PJ | G32: PJ/a
B33: *R2,R3,R4,R5,R6 | C33: PRE | D33: SCCNGCNGX | E33: Collector: CNG to CNGX | F33: PJ | G33: PJ/a
B34: *R2,R3,R4,R5,R6 | C34: PRE | D34: SCGSLCNGX | E34: Collector: GSL to CNGX | F34: PJ | G34: PJ/a
B35: *R2,R3,R4,R5,R6 | C35: PRE | D35: SCGSLLPGX | E35: Collector: GSL to LPGX | F35: PJ | G35: PJ/a
B36: *R2,R3,R4,R5,R6 | C36: PRE | D36: SCLPGLPGX | E36: Collector: LPG to LPGX | F36: PJ | G36: PJ/a
B37: *R2,R3,R4,R5,R6 | C37: PRE | D37: SCTLGSLE85 | E37: Collector: GSL to E85X | F37: PJ | G37: PJ/a
B38: *R2,R3,R4,R5,R6 | C38: PRE | D38: SCTLE85E85 | E38: Collector: E85 to E85X | F38: PJ | G38: PJ/a
B39: *R2,R3,R4,R5,R6 | C39: PRE | D39: SCTLGSLGSL | E39: Collector: GSLB to TRNGSL | F39: PJ | G39: PJ/a
B40: *R2,R3,R4,R5,R6 | C40: PRE | D40: SCTRGSLRB | E40: Collector: GSLR to TRN for blending | F40: PJ | G40: PJ/a
B41: *R2,R3,R4,R5,R6 | C41: PRE | D41: SCTRGSLCB | E41: Collector: GSLC to TRN for blending | F41: PJ | G41: PJ/a
B42: *R2,R3,R4,R5,R6 | C42: PRE | D42: SCTLE10GSL | E42: Collector: TRNE10 to GSL | F42: PJ | G42: PJ/a
B43: *R2,R3,R4,R5,R6 | C43: PRE | D43: SCDSLLDSL | E43: Collector: DSLL to DSLB | F43: PJ | G43: PJ/a
... B46: *R2,R3,R4,R5,R6 | C46: PRE | D46: SCTRNELC | E46: Collector: ELC to TRN | F46: PJ | G46: PJ/a
B47: *
B48: *
B49: *
B50: *R2,R3,R4,R5,R6 | C50: PRE | D50: SETLGSL | E50: Collector: TRNGSL to TLGSL | F50: PJ | G50: PJ/a
B51: *R2,R3,R4,R5,R6 | C51: PRE | D51: SETLCNG | E51: Collector: TRNCNG to TLCNG | F51: PJ | G51: PJ/a
B52: *R2,R3,R4,R5,R6 | C52: PRE | D52: SCGSL2CNGX | E52: Collector: TRNGSL to TLCNGX | F52: PJ | G52: PJ/a
B53: *R2,R3,R4,R5,R6 | C53: PRE | D53: SCCNG2CNGX | E53: Collector: TRNCNG to TLCNGX | F53: PJ | G53: PJ/a
B54: *R2,R3,R4,R5,R6 | C54: PRE | D54: SETLLPG | E54: Collector: TRNLPG to TLLPG | F54: PJ | G54: PJ/a
B55: *R2,R3,R4,R5,R6 | C55: PRE | D55: SCGSL2LPGX | E55: Collector: TRNGSL to TLLPGX | F55: PJ | G55: PJ/a
B56: *R2,R3,R4,R5,R6 | C56: PRE | D56: SCLPG2LPGX | E56: Collector: TRNLPG to TLLPGX | F56: PJ | G56: PJ/a
B57: *
B58: *
B59: *
B60: *
B61: *
B62: *
B63: * Light Duty Vehicle Demand Technologies
B64: R2,R3,R4,R5,R6 | C64: DMD | D64: =ConsolidatedVehData!A8 -> TLEMCGSL | E64: =ConsolidatedVehData!B8 -> TL.GSL.MC.Existing fleet | F64: bn-vmt | G64: bn-vmt/a
B65: R2,R3,R4,R5,R6 | C65: DMD | D65: =ConsolidatedVehData!A9 -> TLECGSL | E65: =ConsolidatedVehData!B9 -> TL.GSL.C.Existing fleet | F65: bn-vmt | G65: bn-vmt/a
B66: R2,R3,R4,R5,R6 | C66: DMD | D66: =ConsolidatedVehData!A10 -> TLEFDSL | E66: =ConsolidatedVehData!B10 -> TL.DSL.F.Existing fleet | F66: bn-vmt | G66: bn-vmt/a
B67: R2,R3,R4,R5,R6 | C67: DMD | D67: =ConsolidatedVehData!A11 -> TLEFGSL | E67: =ConsolidatedVehData!B11 -> TL.GSL.F.Existing fleet | F67: bn-vmt | G67: bn-vmt/a
B68: R2,R3,R4,R5,R6 | C68: DMD | D68: =ConsolidatedVehData!A12 -> TLESSGSL | E68: =ConsolidatedVehData!B12 -> TL.GSL.SS.Existing fleet | F68: bn-vmt | G68: bn-vmt/a
B69: R2,R3,R4,R5,R6 | C69: DMD | D69: =ConsolidatedVehData!A13 -> TLELSGSL | E69: =ConsolidatedVehData!B13 -> TL.GSL.LS.Existing fleet | F69: bn-vmt | G69: bn-vmt/a
B70: R2,R3,R4,R5,R6 | C70: DMD | D70: =ConsolidatedVehData!A14 -> TLEMGSL | E70: =ConsolidatedVehData!B14 -> TL.GSL.M.Existing Fleet | F70: bn-vmt | G70: bn-vmt/a
B71: R2,R3,R4,R5,R6 | C71: DMD | D71: =ConsolidatedVehData!A15 -> TLEPGSL | E71: =ConsolidatedVehData!B15 -> TL.GSL.P.Existing Fleet | F71: bn-vmt | G71: bn-vmt/a
B72: R2,R3,R4,R5,R6 | C72: DMD | D72: =ConsolidatedVehData!A16 -> TLEPDSL | E72: =ConsolidatedVehData!B16 -> TL.DSL.P.Existing fleet | F72: bn-vmt | G72: bn-vmt/a
B73: *R2,R3,R4,R5,R6 | C73: DMD | D73: =ConsolidatedVehData!A18 -> TLEETHX | E73: =ConsolidatedVehData!B18 -> TL.E85X.F.Existing fleet | F73: bn-vmt | G73: bn-vmt/a
B74: *R2,R3,R4,R5,R6 | C74: DMD | D74: =ConsolidatedVehData!A19 -> TLECNGX | E74: =ConsolidatedVehData!B19 -> TL.CNGX.F.Existing fleet | F74: bn-vmt | G74: bn-vmt/a
B75: *R2,R3,R4,R5,R6 | C75: DMD | D75: =ConsolidatedVehData!A20 -> TLELPGX | E75: =ConsolidatedVehData!B20 -> TL.LPGX.F.Existing fleet | F75: bn-vmt | G75: bn-vmt/a
B76: R2,R3,R4,R5,R6 | C76: DMD | D76: =ConsolidatedVehData!A21 -> TLEELC | E76: =ConsolidatedVehData!B21 -> TL.ELC.F.Existing fleet | F76: bn-vmt | G76: bn-vmt/a
B77: R2,R3,R4,R5,R6 | C77: DMD | D77: TLMCELC | E77: Electric minicar w/100 mi range | F77: bn-vmt | G77: bn-vmt/a
B78: R2,R3,R4,R5,R6 | C78: DMD | D78: TLCELC | E78: Electric compact car w/100 mi range | F78: bn-vmt | G78: bn-vmt/a
B79: R2,R3,R4,R5,R6 | C79: DMD | D79: TLFELC | E79: Electric fullsize car w/100 mi range | F79: bn-vmt | G79: bn-vmt/a
B80: R2,R3,R4,R5,R6 | C80: DMD | D80: TLMELC | E80: Electric minivan w/100 mi range | F80: bn-vmt | G80: bn-vmt/a
B81: R2,R3,R4,R5,R6 | C81: DMD | D81: TLPELC | E81: Electric pickup truck w/100 mi range | F81: bn-vmt | G81: bn-vmt/a
B82: R2,R3,R4,R5,R6 | C82: DMD | D82: TLSSELC | E82: Electric small SUV w/100 mi range | F82: bn-vmt | G82: bn-vmt/a
B83: R2,R3,R4,R5,R6 | C83: DMD | D83: TLLSELC | E83: Electric large SUV w/100 mi range | F83: bn-vmt | G83: bn-vmt/a
B84: R2,R3,R4,R5,R6 | C84: DMD | D84: TLMCELCB | E84: Electric minicar w/200 mi range | F84: bn-vmt | G84: bn-vmt/a
B85: R2,R3,R4,R5,R6 | C85: DMD | D85: TLCELCB | E85: Electric compact car w/200 mi range | F85: bn-vmt | G85: bn-vmt/a
B86: R2,R3,R4,R5,R6 | C86: DMD | D86: TLFELCB | E86: Electric fullsize car w/200 mi range | F86: bn-vmt | G86: bn-vmt/a
B87: R2,R3,R4,R5,R6 | C87: DMD | D87: TLMELCB | E87: Electric minivan w/200 mi range | F87: bn-vmt | G87: bn-vmt/a
B88: R2,R3,R4,R5,R6 | C88: DMD | D88: TLPELCB | E88: Electric pickup truck w/200 mi range | F88: bn-vmt | G88: bn-vmt/a
... B90: R2,R3,R4,R5,R6 | C90: DMD | D90: TLLSELCB | E90: Electric large SUV w/200 mi range | F90: bn-vmt | G90: bn-vmt/a
B91: R2,R3,R4,R5,R6 | C91: DMD | D91: =ConsolidatedVehData!A24 -> TLMCCONV10 | E91: =ConsolidatedVehData!B24 -> TL.GSL.MC.CONV.2010 | F91: bn-vmt | G91: bn-vmt/a
B92: R2,R3,R4,R5,R6 | C92: DMD | D92: =ConsolidatedVehData!A44 -> TLCCONV10 | E92: =ConsolidatedVehData!B44 -> TL.GSL.C.CONV.2010 | F92: bn-vmt | G92: bn-vmt/a
B93: R2,R3,R4,R5,R6 | C93: DMD | D93: =ConsolidatedVehData!A55 -> TLCDSL10 | E93: =ConsolidatedVehData!B55 -> TL.DSL.C.DSL.2010 | F93: bn-vmt | G93: bn-vmt/a
B94: R2,R3,R4,R5,R6 | C94: DMD | D94: =ConsolidatedVehData!A66 -> TLCCNG10 | E94: =ConsolidatedVehData!B66 -> TL.CNG.C.CNG.2010 | F94: bn-vmt | G94: bn-vmt/a
B95: *R2,R3,R4,R5,R6 | C95: DMD | D95: =ConsolidatedVehData!A77 -> TLCCNGX10 | E95: =ConsolidatedVehData!B77 -> TL.CNGX.C.CNGX.2010 | F95: bn-vmt | G95: bn-vmt/a
B96: R2,R3,R4,R5,R6 | C96: DMD | D96: =ConsolidatedVehData!A87 -> TLCDHEV15 | E96: =ConsolidatedVehData!B87 -> TL.DSL.C.DHEV.2015 | F96: bn-vmt | G96: bn-vmt/a
B97: *R2,R3,R4,R5,R6 | C97: DMD | D97: =ConsolidatedVehData!A96 -> TLCETHX10 | E97: =ConsolidatedVehData!B96 -> TL.E85X.C.ETHX.2010 | F97: bn-vmt | G97: bn-vmt/a
B98: R2,R3,R4,R5,R6 | C98: DMD | D98: =ConsolidatedVehData!A106 -> TLCFCH10 | E98: =ConsolidatedVehData!B106 -> TL.H2.C.FCH.2010 | F98: bn-vmt | G98: bn-vmt/a
B99: R2,R3,R4,R5,R6 | C99: DMD | D99: =ConsolidatedVehData!A116 -> TLCHEV10 | E99: =ConsolidatedVehData!B116 -> TL.GSL.C.HEV.2010 | F99: bn-vmt | G99: bn-vmt/a
B100: *R2,R3,R4,R5,R6 | C100: DMD | D100: =ConsolidatedVehData!A127 -> TLCLPGX10 | E100: =ConsolidatedVehData!B127 -> TL.LPGX.C.LPGX.2010 | F100: bn-vmt | G100: bn-vmt/a
B101: R2,R3,R4,R5,R6 | C101: DMD | D101: =ConsolidatedVehData!A136 -> TLCPHVG10 | E101: =ConsolidatedVehData!B136 -> TL.GSL.C.PHVG.2010 | F101: bn-vmt | G101: bn-vmt/a
B102: R2,R3,R4,R5,R6 | C102: DMD | D102: =ConsolidatedVehData!A147 -> TLFCONV10 | E102: =ConsolidatedVehData!B147 -> TL.GSL.F.CONV.2010 | F102: bn-vmt | G102: bn-vmt/a
B103: *R2,R3,R4,R5,R6 | C103: DMD | D103: =ConsolidatedVehData!A158 -> TLFCNG10 | E103: =ConsolidatedVehData!B158 -> TL.CNG.F.CNG.2010 | F103: bn-vmt | G103: bn-vmt/a
B104: *R2,R3,R4,R5,R6 | C104: DMD | D104: =ConsolidatedVehData!A169 -> TLFCNGX10 | E104: =ConsolidatedVehData!B169 -> TL.CNGX.F.CNGX.2010 | F104: bn-vmt | G104: bn-vmt/a
B105: R2,R3,R4,R5,R6 | C105: DMD | D105: =ConsolidatedVehData!A179 -> TLFDHEV20 | E105: =ConsolidatedVehData!B179 -> TL.DSL.F.DHEV.2020 | F105: bn-vmt | G105: bn-vmt/a
B106: R2,R3,R4,R5,R6 | C106: DMD | D106: =ConsolidatedVehData!A188 -> TLFDSL10 | E106: =ConsolidatedVehData!B188 -> TL.DSL.F.DSL.2010 | F106: bn-vmt | G106: bn-vmt/a
B107: *R2,R3,R4,R5,R6 | C107: DMD | D107: =ConsolidatedVehData!A206 -> TLFETHX10 | E107: =ConsolidatedVehData!B206 -> TL.E85X.F.ETHX.2010 | F107: bn-vmt | G107: bn-vmt/a
B108: R2,R3,R4,R5,R6 | C108: DMD | D108: =ConsolidatedVehData!A224 -> TLFFCH15 | E108: =ConsolidatedVehData!B224 -> TL.H2.F.FCH.2015 | F108: bn-vmt | G108: bn-vmt/a
B109: R2,R3,R4,R5,R6 | C109: DMD | D109: =ConsolidatedVehData!A233 -> TLFHEV10 | E109: =ConsolidatedVehData!B233 -> TL.GSL.F.HEV.2010 | F109: bn-vmt | G109: bn-vmt/a
B110: *R2,R3,R4,R5,R6 | C110: DMD | D110: =ConsolidatedVehData!A244 -> TLFLPGX10 | E110: =ConsolidatedVehData!B244 -> TL.LPGX.F.LPGX.2010 | F110: bn-vmt | G110: bn-vmt/a
B111: R2,R3,R4,R5,R6 | C111: DMD | D111: =ConsolidatedVehData!A253 -> TLFPHVG10 | E111: =ConsolidatedVehData!B253 -> TL.GSL.F.PHVG.2010 | F111: bn-vmt | G111: bn-vmt/a
B112: R2,R3,R4,R5,R6 | C112: DMD | D112: =ConsolidatedVehData!A264 -> TLMCONV10 | E112: =ConsolidatedVehData!B264 -> TL.GSL.M.CONV.2010 | F112: bn-vmt | G112: bn-vmt/a
B113: R2,R3,R4,R5,R6 | C113: DMD | D113: =ConsolidatedVehData!A275 -> TLMCNG10 | E113: =ConsolidatedVehData!B275 -> TL.CNG.M.CNG.2010 | F113: bn-vmt | G113: bn-vmt/a
B114: *R2,R3,R4,R5,R6 | C114: DMD | D114: =ConsolidatedVehData!A286 -> TLMCNGX10 | E114: =ConsolidatedVehData!B286 -> TL.CNGX.M.CNGX.2010 | F114: bn-vmt | G114: bn-vmt/a
B115: R2,R3,R4,R5,R6 | C115: DMD | D115: =ConsolidatedVehData!A295 -> TLMDHEV15 | E115: =ConsolidatedVehData!B295 -> TL.DSL.M.DHEV.2015 | F115: bn-vmt | G115: bn-vmt/a
...

Sheet CommData
A1: CommData | B1: R1,R2,R3,R4,R5,R6
E5: ~FI_T
A6: Region | B6: CommName | C6: *CommDesc | D6: *Units | E6: COM_PROJ~2010 | F6: COM_PROJ~2015 | G6: COM_PROJ~2020 | H6: COM_PROJ~2025 | I6: COM_PROJ~2030 | J6: COM_PROJ~2035 | K6: COM_PROJ~2040 | L6: COM_PROJ~2045 | M6: COM_PROJ~2050 | N6: COM_PROJ~2055 | O6: COM_FR~IDAM | P6: COM_FR~IDPM | Q6: COM_FR~IN | R6: COM_FR~IP | S6: COM_FR~SDAM | T6: COM_FR~SDPM | U6: COM_FR~SN | V6: COM_FR~SP | W6: COM_FR~WDAM | X6: COM_FR~WDPM | Y6: COM_FR~WN | Z6: COM_FR~WP
A7: *Energy Demands by End Use
A8: R2 | B8: =Commodities!$D$9 -> TL | C8: =Commodities!$E$9 -> Transportation Light Duty | D8: bn-vmt | E8: ='VMT NYC'!D86 -> 4.3486256 | F8: ='VMT NYC'!E86 -> 4.534572 | G8: ='VMT NYC'!F86 -> 4.7084541 | H8: ='VMT NYC'!G86 -> 7.9819328 | I8: ='VMT NYC'!H86 -> 8.1753543 | J8: ='VMT NYC'!I86 -> 8.3687758 | K8: ='VMT NYC'!J86 -> 8.545568 | L8: ='VMT NYC'!K86 -> 8.7223601 | ... N8: ='VMT NYC'!M86 -> 8.6598825 | O8: 0.0129 | P8: 0.0037 | Q8: 0.3172 | R8: 0.0005 | S8: 0.0501 | T8: 0.0066 | U8: 0.2775 | V8: 0.0001 | W8: 0.0127 | X8: 0.0064 | Y8: 0.3117 | Z8: 0.0006
A9: R3 | B9: =Commodities!$D$9 -> TL | C9: =Commodities!$E$9 -> Transportation Light Duty | D9: bn-vmt | E9: ='VMT NYC'!D90 -> 3.0099004 | F9: ='VMT NYC'!E90 -> 3.0873783 | G9: ='VMT NYC'!F90 -> 3.2294859 | H9: ='VMT NYC'!G90 -> 3.1377448 | I9: ='VMT NYC'!H90 -> 3.2042445 | J9: ='VMT NYC'!I90 -> 3.2707442 | K9: ='VMT NYC'!J90 -> 3.3165636 | L9: ='VMT NYC'!K90 -> 3.3623829 | ... N9: ='VMT NYC'!M90 -> 3.5219104 | O9: 0.0129 | P9: 0.0037 | Q9: 0.3172 | R9: 0.0005 | S9: 0.0501 | T9: 0.0066 | U9: 0.2775 | V9: 0.0001 | W9: 0.0127 | X9: 0.0064 | Y9: 0.3117 | Z9: 0.0006
A10: R4 | B10: =Commodities!$D$9 -> TL | C10: =Commodities!$E$9 -> Transportation Light Duty | D10: bn-vmt | E10: ='VMT NYC'!D94 -> 3.1068522 | F10: ='VMT NYC'!E94 -> 3.0848577 | G10: ='VMT NYC'!F94 -> 3.1426988 | H10: ='VMT NYC'!G94 -> 3.5648024 | I10: ='VMT NYC'!H94 -> 3.630499 | J10: ='VMT NYC'!I94 -> 3.6961955 | K10: ='VMT NYC'!J94 -> 3.7574888 | L10: ='VMT NYC'!K94 -> 3.8187822 | ... N10: ='VMT NYC'!M94 -> 3.9166558 | O10: 0.0129 | P10: 0.0037 | Q10: 0.3172 | R10: 0.0005 | S10: 0.0501 | T10: 0.0066 | U10: 0.2775 | V10: 0.0001 | W10: 0.0127 | X10: 0.0064 | Y10: 0.3117 | Z10: 0.0006
A11: R5 | B11: =Commodities!$D$9 -> TL | C11: =Commodities!$E$9 -> Transportation Light Duty | D11: bn-vmt | E11: ='VMT NYC'!D98 -> 2.0302486 | F11: ='VMT NYC'!E98 -> 2.079645 | G11: ='VMT NYC'!F98 -> 2.1430161 | H11: ='VMT NYC'!G98 -> 2.184425 | I11: ='VMT NYC'!H98 -> 2.2367737 | J11: ='VMT NYC'!I98 -> 2.2891223 | K11: ='VMT NYC'!J98 -> 2.3300414 | L11: ='VMT NYC'!K98 -> 2.3709604 | ... N11: ='VMT NYC'!M98 -> 2.4323318 | O11: 0.0129 | P11: 0.0037 | Q11: 0.3172 | R11: 0.0005 | S11: 0.0501 | T11: 0.0066 | U11: 0.2775 | V11: 0.0001 | W11: 0.0127 | X11: 0.0064 | Y11: 0.3117 | Z11: 0.0006
A12: R6 | B12: =Commodities!$D$9 -> TL | C12: =Commodities!$E$9 -> Transportation Light Duty | D12: bn-vmt | E12: ='VMT NYC'!D102 -> 7.1614064 | F12: ='VMT NYC'!E102 -> 6.8764354 | G12: ='VMT NYC'!F102 -> 6.9182672 | H12: ='VMT NYC'!G102 -> 4.7126752 | I12: ='VMT NYC'!H102 -> 4.8365343 | J12: ='VMT NYC'!I102 -> 4.9603934 | K12: ='VMT NYC'!J102 -> 5.0656795 | L12: ='VMT NYC'!K102 -> 5.1709656 | ... N12: ='VMT NYC'!M102 -> 5.229749 | O12: 0.0129 | P12: 0.0037 | Q12: 0.3172 | R12: 0.0005 | S12: 0.0501 | T12: 0.0066 | U12: 0.2775 | V12: 0.0001 | W12: 0.0127 | X12: 0.0064 | Y12: 0.3117 | Z12: 0.0006
A13: *R7 | B13: =Commodities!$D$9 -> TL | C13: =Commodities!$E$9 -> Transportation Light Duty | D13: bn-vmt | E13: 0 | F13: 0 | G13: 0 | H13: 0 | I13: 0 | J13: 0 | K13: 0 | L13: 0 | M13: 0 | N13: 0
A14: *R8 | B14: =Commodities!$D$9 -> TL | C14: =Commodities!$E$9 -> Transportation Light Duty | D14: bn-vmt | E14: 0 | F14: 0 | G14: 0 | H14: 0 | I14: 0 | J14: 0 | K14: 0 | L14: 0 | M14: 0 | N14: 0
A15: *R9 | B15: =Commodities!$D$9 -> TL | C15: =Commodities!$E$9 -> Transportation Light Duty | D15: bn-vmt | E15: 0 | F15: 0 | G15: 0 | H15: 0 | I15: 0 | J15: 0 | K15: 0 | L15: 0 | M15: 0 | N15: 0
A17: *NYC (R2-R6) | E17: =SUM(E8:E12) -> 19.657033 | F17: =SUM(F8:F12) -> 19.662888 | G17: =SUM(G8:G12) -> 20.141922 | H17: =SUM(H8:H12) -> 21.58158 | I17: =SUM(I8:I12) -> 22.083406 | J17: =SUM(J8:J12) -> 22.585231 | K17: =SUM(K8:K12) -> 23.015341 | L17: =SUM(L8:L12) -> 23.445451 | ... N17: =SUM(N8:N12) -> 23.76053

Sheet TechData_existing
A1: TechData | B1: R1,R2,R3,R4,R5,R6 | L1: R2 | M1: R2 | N1: R2 | O1: R2 | P1: R3 | Q1: R3 | R1: R3 | S1: R3 | T1: R4 | U1: R4 | V1: R4 | W1: R4 | X1: R5 | Y1: R5 | Z1: R5 | AA1: R5 | AB1: R6 | AC1: R6 | AD1: R6 | AE1: R6
F4: ~FI_T
A5: Region | B5: TechName | C5: *TechDesc | D5: *Units | E5: CommIN | F5: CommOUT | G5: NCAP_START | H5: NCAP_LIFE | I5: EFF | J5: NCAP_FOM | K5: NCAP_DRATE | L5: PRC_RESID~R2~2010 | M5: PRC_RESID~R2~2015 | N5: PRC_RESID~R2~2020 | O5: PRC_RESID~R2~2025 | P5: PRC_RESID~R3~2010 | Q5: PRC_RESID~R3~2015 | R5: PRC_RESID~R3~2020 | S5: PRC_RESID~R3~2025 | T5: PRC_RESID~R4~2010 | U5: PRC_RESID~R4~2015 | V5: PRC_RESID~R4~2020 | W5: PRC_RESID~R4~2025 | X5: PRC_RESID~R5~2010 | Y5: PRC_RESID~R5~2015 | Z5: PRC_RESID~R5~2020 | AA5: PRC_RESID~R5~2025 | AB5: PRC_RESID~R6~2010 | AC5: PRC_RESID~R6~2015 | AD5: PRC_RESID~R6~2020 | AE5: PRC_RESID~R6~2025 | AF5: NCAP_AFA | AH5: NCAP_BND~2010 | AI5: NCAP_BND~2015 | AJ5: NCAP_BND~2020 | AK5: NCAP_BND~2025 | AL5: NCAP_BND~2030 | AM5: NCAP_BND~2035 | AN5: NCAP_BND~2040 | AO5: NCAP_BND~2045 | AP5: NCAP_BND~2050 | AQ5: NCAP_BND~2055
A6: * Light Duty Vehicle Demand Technologies - Residuals
A7: =Technologies!B64 -> R2,R3,R4,R5,R6 | B7: =Technologies!D64 -> TLEMCGSL | C7: =Technologies!E64 -> TL.GSL.MC.Existing fleet | D7: bn-vmt, bn-vmt/a | E7: =Commodities!$D$25 -> TLGSL | F7: =Commodities!$D$9 -> TL | G7: 2010 | H7: 15 | I7: =ResidDataAndCalcs!D33 -> 0.085302862 | J7: =ConsolidatedVehData!AB8 -> 38.459799 | K7: 0.18 | L7: =ResidDataAndCalcs!D46 -> 0.13427116 | M7: =ResidDataAndCalcs!E46 -> 0.10070337 | N7: =ResidDataAndCalcs!F46 -> 0.067135579 | O7: =ResidDataAndCalcs!G46 -> 0.033567789 | P7: =ResidDataAndCalcs!I46 -> 0.092935757 | Q7: =ResidDataAndCalcs!J46 -> 0.069701818 | R7: =ResidDataAndCalcs!K46 -> 0.046467878 | S7: =ResidDataAndCalcs!L46 -> 0.023233939 | T7: =ResidDataAndCalcs!N46 -> 0.095929307 | U7: =ResidDataAndCalcs!O46 -> 0.07194698 | V7: =ResidDataAndCalcs!P46 -> 0.047964653 | W7: =ResidDataAndCalcs!Q46 -> 0.023982327 | X7: =ResidDataAndCalcs!S46 -> 0.062687354 | Y7: =ResidDataAndCalcs!T46 -> 0.047015516 | Z7: =ResidDataAndCalcs!U46 -> 0.031343677 | AA7: =ResidDataAndCalcs!V46 -> 0.015671839 | AB7: =ResidDataAndCalcs!X46 -> 0.22112051 | AC7: =ResidDataAndCalcs!Y46 -> 0.16584038 | AD7: =ResidDataAndCalcs!Z46 -> 0.11056026 | AE7: =ResidDataAndCalcs!AA46 -> 0.055280128 | AF7: 1 | AH7: 0 | AI7: 0 | AJ7: 0 | AK7: 0 | AL7: 0 | AM7: 0 | AN7: 0 | AO7: 0 | AP7: 0 | AQ7: 0
A8: =Technologies!B65 -> R2,R3,R4,R5,R6 | B8: =Technologies!D65 -> TLECGSL | C8: =Technologies!E65 -> TL.GSL.C.Existing fleet | D8: bn-vmt, bn-vmt/a | E8: =Commodities!$D$25 -> TLGSL | F8: =Commodities!$D$9 -> TL | G8: 2010 | H8: 15 | I8: =ResidDataAndCalcs!E33 -> 0.10517029 | J8: =ConsolidatedVehData!AB9 -> 38.459799 | K8: 0.18 | L8: =ResidDataAndCalcs!D47 -> 2.7921674 | M8: =ResidDataAndCalcs!E47 -> 2.0941255 | N8: =ResidDataAndCalcs!F47 -> 1.3960837 | O8: =ResidDataAndCalcs!G47 -> 0.69804184 | P8: =ResidDataAndCalcs!I47 -> 1.9325981 | Q8: =ResidDataAndCalcs!J47 -> 1.4494486 | R8: =ResidDataAndCalcs!K47 -> 0.96629906 | S8: =ResidDataAndCalcs!L47 -> 0.48314953 | T8: =ResidDataAndCalcs!N47 -> 1.994849 | U8: =ResidDataAndCalcs!O47 -> 1.4961367 | V8: =ResidDataAndCalcs!P47 -> 0.99742448 | W8: =ResidDataAndCalcs!Q47 -> 0.49871224 | X8: =ResidDataAndCalcs!S47 -> 1.3035829 | Y8: =ResidDataAndCalcs!T47 -> 0.97768717 | Z8: =ResidDataAndCalcs!U47 -> 0.65179145 | AA8: =ResidDataAndCalcs!V47 -> 0.32589572 | AB8: =ResidDataAndCalcs!X47 -> 4.5981988 | AC8: =ResidDataAndCalcs!Y47 -> 3.4486491 | AD8: =ResidDataAndCalcs!Z47 -> 2.2990994 | AE8: =ResidDataAndCalcs!AA47 -> 1.1495497 | AF8: 1 | AH8: 0 | AI8: 0 | AJ8: 0 | AK8: 0 | AL8: 0 | AM8: 0 | AN8: 0 | AO8: 0 | AP8: 0 | AQ8: 0
A9: =Technologies!B66 -> R2,R3,R4,R5,R6 | B9: =Technologies!D66 -> TLEFDSL | C9: =Technologies!E66 -> TL.DSL.F.Existing fleet | D9: bn-vmt, bn-vmt/a | E9: =Commodities!$D$24 -> TRNDSL | F9: =Commodities!$D$9 -> TL | G9: 2010 | H9: 15 | I9: =ResidDataAndCalcs!G33 -> 0.10118525 | J9: =ConsolidatedVehData!AB10 -> 43.267274 | K9: 0.18 | L9: =ResidDataAndCalcs!D48 -> 0.013107509 | M9: =ResidDataAndCalcs!E48 -> 0.0098306321 | N9: =ResidDataAndCalcs!F48 -> 0.0065537547 | O9: =ResidDataAndCalcs!G48 -> 0.0032768774 | P9: =ResidDataAndCalcs!I48 -> 0.0090723602 | Q9: =ResidDataAndCalcs!J48 -> 0.0068042702 | R9: =ResidDataAndCalcs!K48 -> 0.0045361801 | S9: =ResidDataAndCalcs!L48 -> 0.0022680901 | T9: =ResidDataAndCalcs!N48 -> 0.0093645896 | U9: =ResidDataAndCalcs!O48 -> 0.0070234422 | V9: =ResidDataAndCalcs!P48 -> 0.0046822948 | W9: =ResidDataAndCalcs!Q48 -> 0.0023411474 | X9: =ResidDataAndCalcs!S48 -> 0.0061195204 | Y9: =ResidDataAndCalcs!T48 -> 0.0045896403 | Z9: =ResidDataAndCalcs!U48 -> 0.0030597602 | AA9: =ResidDataAndCalcs!V48 -> 0.0015298801 | AB9: =ResidDataAndCalcs!X48 -> 0.021585717 | AC9: =ResidDataAndCalcs!Y48 -> 0.016189288 | AD9: =ResidDataAndCalcs!Z48 -> 0.010792858 | AE9: =ResidDataAndCalcs!AA48 -> 0.0053964292 | AF9: 1 | AH9: 0 | AI9: 0 | AJ9: 0 | AK9: 0 | AL9: 0 | AM9: 0 | AN9: 0 | AO9: 0 | AP9: 0 | AQ9: 0
A10: =Technologies!B67 -> R2,R3,R4,R5,R6 | B10: =Technologies!D67 -> TLEFGSL | C10: =Technologies!E67 -> TL.GSL.F.Existing fleet | D10: bn-vmt, bn-vmt/a | E10: =Commodities!$D$25 -> TLGSL | F10: =Commodities!$D$9 -> TL | G10: 2010 | H10: 15 | I10: =ResidDataAndCalcs!F33 -> 0.091482555 | J10: =ConsolidatedVehData!AB11 -> 43.267274 | K10: 0.18 | L10: =ResidDataAndCalcs!D49 -> 1.0075519 | M10: =ResidDataAndCalcs!E49 -> 0.75566389 | N10: =ResidDataAndCalcs!F49 -> 0.50377593 | O10: =ResidDataAndCalcs!G49 -> 0.25188796 | P10: =ResidDataAndCalcs!I49 -> 0.69737683 | Q10: =ResidDataAndCalcs!J49 -> 0.52303262 | R10: =ResidDataAndCalcs!K49 -> 0.34868842 | S10: =ResidDataAndCalcs!L49 -> 0.17434421 | T10: =ResidDataAndCalcs!N49 -> 0.71984001 | U10: =ResidDataAndCalcs!O49 -> 0.53988001 | V10: =ResidDataAndCalcs!P49 -> 0.35992 | W10: =ResidDataAndCalcs!Q49 -> 0.17996 | X10: =ResidDataAndCalcs!S49 -> 0.47039708 | Y10: =ResidDataAndCalcs!T49 -> 0.35279781 | Z10: =ResidDataAndCalcs!U49 -> 0.23519854 | AA10: =ResidDataAndCalcs!V49 -> 0.11759927 | AB10: =ResidDataAndCalcs!X49 -> 1.6592572 | AC10: =ResidDataAndCalcs!Y49 -> 1.2444429 | AD10: =ResidDataAndCalcs!Z49 -> 0.82962859 | AE10: =ResidDataAndCalcs!AA49 -> 0.4148143 | AF10: 1 | AH10: 0 | AI10: 0 | AJ10: 0 | AK10: 0 | AL10: 0 | AM10: 0 | AN10: 0 | AO10: 0 | AP10: 0 | AQ10: 0
A11: =Technologies!B68 -> R2,R3,R4,R5,R6 | B11: =Technologies!D68 -> TLESSGSL | C11: =Technologies!E68 -> TL.GSL.SS.Existing fleet | D11: bn-vmt, bn-vmt/a | E11: =Commodities!$D$25 -> TLGSL | F11: =Commodities!$D$9 -> TL | G11: 2010 | H11: 15 | I11: =ResidDataAndCalcs!H33 -> 0.083859009 | J11: =ConsolidatedVehData!AB12 -> 43.267274 | K11: 0.18 | L11: =ResidDataAndCalcs!D51 -> 0.090047103 | M11: =ResidDataAndCalcs!E51 -> 0.067535327 | N11: =ResidDataAndCalcs!F51 -> 0.045023552 | O11: =ResidDataAndCalcs!G51 -> 0.022511776 | P11: =ResidDataAndCalcs!I51 -> 0.062326086 | Q11: =ResidDataAndCalcs!J51 -> 0.046744564 | R11: =ResidDataAndCalcs!K51 -> 0.031163043 | S11: =ResidDataAndCalcs!L51 -> 0.015581521 | T11: =ResidDataAndCalcs!N51 -> 0.064333669 | U11: =ResidDataAndCalcs!O51 -> 0.048250252 | V11: =ResidDataAndCalcs!P51 -> 0.032166834 | W11: =ResidDataAndCalcs!Q51 -> 0.016083417 | X11: =ResidDataAndCalcs!S51 -> 0.042040411 | Y11: =ResidDataAndCalcs!T51 -> 0.031530308 | Z11: =ResidDataAndCalcs!U51 -> 0.021020206 | AA11: =ResidDataAndCalcs!V51 -> 0.010510103 | AB11: =ResidDataAndCalcs!X51 -> 0.14829143 | AC11: =ResidDataAndCalcs!Y51 -> 0.11121857 | AD11: =ResidDataAndCalcs!Z51 -> 0.074145714 | AE11: =ResidDataAndCalcs!AA51 -> 0.037072857 | AF11: 1 | AH11: 0 | AI11: 0 | AJ11: 0 | AK11: 0 | AL11: 0 | AM11: 0 | AN11: 0 | AO11: 0 | AP11: 0 | AQ11: 0
A12: =Technologies!B69 -> R2,R3,R4,R5,R6 | B12: =Technologies!D69 -> TLELSGSL | C12: =Technologies!E69 -> TL.GSL.LS.Existing fleet | D12: bn-vmt, bn-vmt/a | E12: =Commodities!$D$25 -> TLGSL | F12: =Commodities!$D$9 -> TL | G12: 2010 | H12: 15 | I12: =ResidDataAndCalcs!I33 -> 0.07005577 | J12: =ConsolidatedVehData!AB13 -> 43.267274 | K12: 0.18 | L12: =ResidDataAndCalcs!D50 -> 0.064089061 | M12: =ResidDataAndCalcs!E50 -> 0.048066795 | N12: =ResidDataAndCalcs!F50 -> 0.03204453 | O12: =ResidDataAndCalcs!G50 -> 0.016022265 | P12: =ResidDataAndCalcs!I50 -> 0.044359231 | Q12: =ResidDataAndCalcs!J50 -> 0.033269424 | R12: =ResidDataAndCalcs!K50 -> 0.022179616 | S12: =ResidDataAndCalcs!L50 -> 0.011089808 | T12: =ResidDataAndCalcs!N50 -> 0.045788085 | U12: =ResidDataAndCalcs!O50 -> 0.034341064 | V12: =ResidDataAndCalcs!P50 -> 0.022894042 | W12: =ResidDataAndCalcs!Q50 -> 0.011447021 | X12: =ResidDataAndCalcs!S50 -> 0.029921345 | Y12: =ResidDataAndCalcs!T50 -> 0.022441009 | Z12: =ResidDataAndCalcs!U50 -> 0.014960673 | AA12: =ResidDataAndCalcs!V50 -> 0.0074803363 | AB12: =ResidDataAndCalcs!X50 -> 0.10554319 | AC12: =ResidDataAndCalcs!Y50 -> 0.07915739 | AD12: =ResidDataAndCalcs!Z50 -> 0.052771594 | AE12: =ResidDataAndCalcs!AA50 -> 0.026385797 | AF12: 1 | AH12: 0 | AI12: 0 | AJ12: 0 | AK12: 0 | AL12: 0 | AM12: 0 | AN12: 0 | AO12: 0 | AP12: 0 | AQ12: 0
A13: =Technologies!B70 -> R2,R3,R4,R5,R6 | B13: =Technologies!D70 -> TLEMGSL | C13: =Technologies!E70 -> TL.GSL.M.Existing Fleet | D13: bn-vmt, bn-vmt/a | E13: =Commodities!$D$25 -> TLGSL | F13: =Commodities!$D$9 -> TL | G13: 2010 | H13: 15 | I13: =ResidDataAndCalcs!J33 -> 0.091020522 | J13: =ConsolidatedVehData!AB14 -> 43.267274 | K13: 0.18 | L13: =ResidDataAndCalcs!D52 -> 0.060335101 | M13: =ResidDataAndCalcs!E52 -> 0.045251326 | N13: =ResidDataAndCalcs!F52 -> 0.030167551 | O13: =ResidDataAndCalcs!G52 -> 0.015083775 | P13: =ResidDataAndCalcs!I52 -> 0.041760929 | Q13: =ResidDataAndCalcs!J52 -> 0.031320697 | R13: =ResidDataAndCalcs!K52 -> 0.020880465 | S13: =ResidDataAndCalcs!L52 -> 0.010440232 | T13: =ResidDataAndCalcs!N52 -> 0.043106089 | U13: =ResidDataAndCalcs!O52 -> 0.032329566 | V13: =ResidDataAndCalcs!P52 -> 0.021553044 | W13: =ResidDataAndCalcs!Q52 -> 0.010776522 | X13: =ResidDataAndCalcs!S52 -> 0.028168729 | Y13: =ResidDataAndCalcs!T52 -> 0.021126547 | Z13: =ResidDataAndCalcs!U52 -> 0.014084365 | AA13: =ResidDataAndCalcs!V52 -> 0.0070421823 | AB13: =ResidDataAndCalcs!X52 -> 0.099361089 | AC13: =ResidDataAndCalcs!Y52 -> 0.074520817 | AD13: =ResidDataAndCalcs!Z52 -> 0.049680545 | AE13: =ResidDataAndCalcs!AA52 -> 0.024840272 | AF13: 1 | AH13: 0 | AI13: 0 | AJ13: 0 | AK13: 0 | AL13: 0 | AM13: 0 | AN13: 0 | AO13: 0 | AP13: 0 | AQ13: 0
A14: =Technologies!B71 -> R2,R3,R4,R5,R6 | B14: =Technologies!D71 -> TLEPGSL | C14: =Technologies!E71 -> TL.GSL.P.Existing Fleet | D14: bn-vmt, bn-vmt/a | E14: =Commodities!$D$25 -> TLGSL | F14: =Commodities!$D$9 -> TL | G14: 2010 | H14: 15 | I14: =ResidDataAndCalcs!K33 -> 0.075138134 | J14: =ConsolidatedVehData!AB15 -> 48.074749 | K14: 0.18 | L14: =ResidDataAndCalcs!D53 -> 0.1575951 | M14: =ResidDataAndCalcs!E53 -> 0.11819632 | N14: =ResidDataAndCalcs!F53 -> 0.078797548 | O14: =ResidDataAndCalcs!G53 -> 0.039398774 | P14: =ResidDataAndCalcs!I53 -> 0.10907942 | Q14: =ResidDataAndCalcs!J53 -> 0.081809563 | R14: =ResidDataAndCalcs!K53 -> 0.054539708 | S14: =ResidDataAndCalcs!L53 -> 0.027269854 | T14: =ResidDataAndCalcs!N53 -> 0.11259297 | U14: =ResidDataAndCalcs!O53 -> 0.084444727 | V14: =ResidDataAndCalcs!P53 -> 0.056296485 | W14: =ResidDataAndCalcs!Q53 -> 0.028148242 | X14: =ResidDataAndCalcs!S53 -> 0.073576633 | Y14: =ResidDataAndCalcs!T53 -> 0.055182475 | Z14: =ResidDataAndCalcs!U53 -> 0.036788316 | AA14: =ResidDataAndCalcs!V53 -> 0.018394158 | AB14: =ResidDataAndCalcs!X53 -> 0.25953086 | AC14: =ResidDataAndCalcs!Y53 -> 0.19464814 | AD14: =ResidDataAndCalcs!Z53 -> 0.12976543 | AE14: =ResidDataAndCalcs!AA53 -> 0.064882714 | AF14: 1 | AH14: 0 | AI14: 0 | AJ14: 0 | AK14: 0 | AL14: 0 | AM14: 0 | AN14: 0 | AO14: 0 | AP14: 0 | AQ14: 0
A15: =Technologies!B72 -> R2,R3,R4,R5,R6 | B15: =Technologies!D72 -> TLEPDSL | C15: =Technologies!E72 -> TL.DSL.P.Existing fleet | D15: bn-vmt, bn-vmt/a | E15: =Commodities!$D$24 -> TRNDSL | F15: =Commodities!$D$9 -> TL | G15: 2010 | H15: 15 | I15: =ResidDataAndCalcs!L33 -> 0.078776644 | J15: =ConsolidatedVehData!AB16 -> 48.074749 | K15: 0.18 | L15: =ResidDataAndCalcs!D54 -> 0.025380885 | M15: =ResidDataAndCalcs!E54 -> 0.019035663 | N15: =ResidDataAndCalcs!F54 -> 0.012690442 | O15: =ResidDataAndCalcs!G54 -> 0.0063452211 | P15: =ResidDataAndCalcs!I54 -> 0.017567375 | Q15: =ResidDataAndCalcs!J54 -> 0.013175531 | R15: =ResidDataAndCalcs!K54 -> 0.0087836873 | S15: =ResidDataAndCalcs!L54 -> 0.0043918436 | T15: =ResidDataAndCalcs!N54 -> 0.018133236 | U15: =ResidDataAndCalcs!O54 -> 0.013599927 | V15: =ResidDataAndCalcs!P54 -> 0.0090666182 | W15: =ResidDataAndCalcs!Q54 -> 0.0045333091 | X15: =ResidDataAndCalcs!S54 -> 0.011849607 | Y15: =ResidDataAndCalcs!T54 -> 0.0088872055 | Z15: =ResidDataAndCalcs!U54 -> 0.0059248037 | AA15: =ResidDataAndCalcs!V54 -> 0.0029624018 | AB15: =ResidDataAndCalcs!X54 -> 0.041797764 | AC15: =ResidDataAndCalcs!Y54 -> 0.031348323 | AD15: =ResidDataAndCalcs!Z54 -> 0.020898882 | AE15: =ResidDataAndCalcs!AA54 -> 0.010449441 | AF15: 1 | AH15: 0 | AI15: 0 | AJ15: 0 | AK15: 0 | AL15: 0 | AM15: 0 | AN15: 0 | AO15: 0 | AP15: 0 | AQ15: 0
A16: * | B16: =Technologies!D73 -> TLEETHX | C16: =Technologies!E73 -> TL.E85X.F.Existing fleet | D16: bn-vmt, bn-vmt/a | E16: =Commodities!$D$26 -> TLE85X | F16: =Commodities!$D$9 -> TL | G16: 2010 | H16: 15 | I16: =ConsolidatedVehData!AF18 -> 0.1596 | J16: =ConsolidatedVehData!AB18 -> 43.267274 | K16: 0.18 | AF16: 1 | AH16: 0 | AI16: 0 | AJ16: 0 | AK16: 0 | AL16: 0 | AM16: 0 | AN16: 0 | AO16: 0 | AP16: 0 | AQ16: 0
A17: * | B17: =Technologies!D74 -> TLECNGX | C17: =Technologies!E74 -> TL.CNGX.F.Existing fleet | D17: bn-vmt, bn-vmt/a | E17: TRNCNG | F17: =Commodities!$D$9 -> TL | G17: 2010 | H17: 15 | I17: =ConsolidatedVehData!AF19 -> 0.1712 | J17: =ConsolidatedVehData!AB19 -> 38.940547 | K17: 0.18 | AF17: 1 | AH17: 0 | AI17: 0 | AJ17: 0 | AK17: 0 | AL17: 0 | AM17: 0 | AN17: 0 | AO17: 0 | AP17: 0 | AQ17: 0
A18: * | B18: =Technologies!D75 -> TLELPGX | C18: =Technologies!E75 -> TL.LPGX.F.Existing fleet | D18: bn-vmt, bn-vmt/a | E18: TRNLPGX | F18: =Commodities!$D$9 -> TL | G18: 2010 | H18: 15 | I18: =ConsolidatedVehData!AF20 -> 0.1703 | J18: =ConsolidatedVehData!AB20 -> 38.940547 | K18: 0.18 | AF18: 1 | AH18: 0 | AI18: 0 | AJ18: 0 | AK18: 0 | AL18: 0 | AM18: 0 | AN18: 0 | AO18: 0 | AP18: 0 | AQ18: 0
A19: =Technologies!B76 -> R2,R3,R4,R5,R6 | B19: =Technologies!D76 -> TLEELC | C19: =Technologies!E76 -> TL.ELC.F.Existing fleet | D19: bn-vmt, bn-vmt/a | E19: =Commodities!$D$32 -> TRNELC | F19: =Commodities!$D$9 -> TL | G19: 2010 | H19: 15 | I19: =ConsolidatedVehData!AF21 -> 0.7225 | J19: =ConsolidatedVehData!AB21 -> 25.960365 | K19: 0.18 | L19: =ResidDataAndCalcs!D55 -> 0.0040804693 | M19: =ResidDataAndCalcs!E55 -> 0.0091717702 | N19: =ResidDataAndCalcs!F55 -> 0.0068788276 | O19: =ResidDataAndCalcs!G55 -> 0.0034394138 | P19: =ResidDataAndCalcs!I55 -> 0.0028242961 | Q19: =ResidDataAndCalcs!J55 -> 0.006348239 | R19: =ResidDataAndCalcs!K55 -> 0.0047611793 | S19: =ResidDataAndCalcs!L55 -> 0.0031741195 | T19: =ResidDataAndCalcs!N55 -> 0.0029152693 | U19: =ResidDataAndCalcs!O55 -> 0.0065527219 | V19: =ResidDataAndCalcs!P55 -> 0.0049145414 | W19: =ResidDataAndCalcs!Q55 -> 0.0032763609 | X19: =ResidDataAndCalcs!S55 -> 0.0019050541 | Y19: =ResidDataAndCalcs!T55 -> 0.0042820366 | Z19: =ResidDataAndCalcs!U55 -> 0.0032115274 | AA19: =ResidDataAndCalcs!V55 -> 0.0021410183 | AB19: =ResidDataAndCalcs!X55 -> 0.006719801 | AC19: =ResidDataAndCalcs!Y55 -> 0.01510426 | AD19: =ResidDataAndCalcs!Z55 -> 0.011328195 | AE19: =ResidDataAndCalcs!AA55 -> 0.0075521302 | AF19: 1 | AH19: 0 | AI19: 0 | AJ19: 0 | AK19: 0 | AL19: 0 | AM19: 0 | AN19: 0 | AO19: 0 | AP19: 0 | AQ19: 0
A21: * | L21: =SUM(L7:L19) -> 4.3486256 | M21: =SUM(M7:M19) -> 3.2675806 | N21: =SUM(N7:N19) -> 2.1791514 | O21: =SUM(O7:O19) -> 1.0895757 | P21: =SUM(P7:P19) -> 3.0099004 | Q21: =SUM(Q7:Q19) -> 2.2616553 | R21: =SUM(R7:R19) -> 1.5082992 | S21: =SUM(S7:S19) -> 0.75494315 | ... AE21: =SUM(AE7:AE19) -> 1.7962238
L23: =SUM(L7:L15,L19)-CommData!$E$8 -> 0 | P23: =SUM(P7:P15,P19)-CommData!$E$9 -> 0 | T23: =SUM(T7:T15,T19)-CommData!$E$10 -> 0 | X23: =SUM(X7:X15,X19)-CommData!$E$11 -> 0 | AB23: =SUM(AB7:AB15,AB19)-CommData!$E$12 -> 0

Sheet VMT NYC
A1: Description: Calculated regional light duty vehicle demand | R1: EMISSIONS INTENSITY FACTORS
R2: Transportation | S2: GJ Consumed | T2: PJ Consumed | U2: GJ/Liter | V2: Liters Consumed | W2: Gal. Consumed | X2: km/liter | Y2: Distance km | Z2: MPGe | AA2: Miles Traveled | AB2: Miles Traveled (B VKM) | AC2: Source | AD2: Average eff | AK2: Eff
A3: Inputs: | R3: Biofuel | S3: 0 | T3: =S3/1000000 -> 0 | V3: =S3*U3 -> 0 | W3: =V3*0.264172 -> 0 | X3: =W3*0.264172 -> 0 | AF3: car | AG3: =ResidDataAndCalcs!N86 -> 0.027631647 | AH3: =AG3/SUM($AG$3:$AG$6) -> 0.031386722 | AI3: =TechData_existing!B7 -> TLEMCGSL | AJ3: =TechData_existing!C7 -> TL.GSL.MC.Existing fleet | AK3: =TechData_existing!I7 -> 0.085302862
A4: Household Vehicles Energy Use, Energy Information Agency, U.S. Department of Energy, http://www.eia.doe.gov/emeu/rtecs/ | R4: CNG-Transit Bus | S4: 1420989 | T4: =S4/1000000 -> 1.420989 | V4: 1420989 | W4: =V4*0.264172 -> 375385.51 | X4: 0.003233282 | Y4: =S4*X4 -> 4594.4582 | Z4: =AA4/W4 -> 0.0076051499 | AA4: =Y4*0.621371 -> 2854.8631 | AC4: NYC GHG Inventory 14 | AF4: car | AG4: =ResidDataAndCalcs!O86 -> 0.46605378 | AH4: =AG4/SUM($AG$3:$AG$6) -> 0.52938939 | AI4: =TechData_existing!B8 -> TLECGSL | AJ4: =TechData_existing!C8 -> TL.GSL.C.Existing fleet | AK4: =TechData_existing!I8 -> 0.10517029
R5: Diesel-Commuter Rail | S5: 195751 | T5: =S5/1000000 -> 0.195751 | V5: 5064028 | W5: =V5*0.264172 -> 1337774.4 | X5: =Y5/V5 -> 17.005703 | Y5: =1.60934*AA5 -> 86117354 | Z5: 40 | AA5: =W5*Z5 -> 53510976 | AC5: Railtec Article | AF5: car | AG5: =ResidDataAndCalcs!P86/2 -> 0.1933378 | AH5: =AG5/SUM($AG$3:$AG$6) -> 0.21961195 | AI5: =TechData_existing!B9 -> TLEFDSL | AJ5: =TechData_existing!C9 -> TL.DSL.F.Existing fleet | AK5: =TechData_existing!I9 -> 0.10118525
R6: Diesel-Heavy Trucks | S6: 12555252 | T6: =S6/1000000 -> 12.555252 | V6: 326200350 | W6: =V6*0.264172 -> 86172999 | X6: 3.65 | Y6: =V6*X6 -> 1.1906313e+09 | Z6: =AA6/W6 -> 8.5853313 | AA6: =Y6*0.621371 -> 7.3982375e+08 | AC6: NYC GHG Inventory 14 | AF6: car | AG6: =AG5 -> 0.1933378 | AH6: =AG6/SUM($AG$3:$AG$6) -> 0.21961195 | AI6: =TechData_existing!B10 -> TLEFGSL | AJ6: =TechData_existing!C10 -> TL.GSL.F.Existing fleet | AK6: =TechData_existing!I10 -> 0.091482555
A7: Note: Calculates VMT/capita per region for 2000, then uses national growth in VMT/capita to project these values. Results used with regional population to derive regional VMT | R7: Diesel-Light Trucks | S7: 1356142 | T7: =S7/1000000 -> 1.356142 | V7: 35234181 | W7: =V7*0.264172 -> 9307884.1 | X7: 4.38 | Y7: =V7*X7 -> 1.5432571e+08 | Z7: =AA7/W7 -> 10.302398 | AA7: =Y7*0.621371 -> 95893522 | AB7: =S7*AD7/1000000 -> 0.10683232 | AC7: NYC GHG Inventory 14 | AD7: =AK11 -> 0.078776644 | AF7: truck | AG7: =ResidDataAndCalcs!Q86 -> 0.018764479 | AH7: =AG7/SUM($AG$7:$AG$11) -> 0.15684252 | AI7: =TechData_existing!B11 -> TLESSGSL | AJ7: =TechData_existing!C11 -> TL.GSL.SS.Existing fleet | AK7: =TechData_existing!I11 -> 0.083859009
R8: Diesel-Non Bus | S8: 290413 | T8: =S8/1000000 -> 0.290413 | V8: 7545275 | W8: =V8*0.264172 -> 1993250.4 | X8: 5.38 | Y8: =V8*X8 -> 40593580 | Z8: =AA8/W8 -> 12.654543 | AA8: =Y8*0.621371 -> 25223673 | AC8: NYC GHG Inventory 14 | AF8: truck | AG8: =ResidDataAndCalcs!R86 -> 0.015986614 | AH8: =AG8/SUM($AG$7:$AG$11) -> 0.13362379 | AI8: =TechData_existing!B12 -> TLELSGSL | AJ8: =TechData_existing!C12 -> TL.GSL.LS.Existing fleet | AK8: =TechData_existing!I12 -> 0.07005577
R9: Diesel-Cars | S9: 545254 | T9: =S9/1000000 -> 0.545254 | V9: 14166357 | W9: =V9*0.264172 -> 3742354.9 | X9: 6.73 | Y9: =V9*X9 -> 95339583 | Z9: =AA9/W9 -> 15.82994 | AA9: =Y9*0.621371 -> 59241252 | AB9: =S9*AD9/1000000 -> 0.055171662 | AC9: NYC GHG Inventory 14 | AD9: =AK5 -> 0.10118525 | AF9: truck | AG9: =ResidDataAndCalcs!S86 -> 0.011583698 | AH9: =AG9/SUM($AG$7:$AG$11) -> 0.096822105 | AI9: =TechData_existing!B13 -> TLEMGSL | AJ9: =TechData_existing!C13 -> TL.GSL.M.Existing Fleet | AK9: =TechData_existing!I13 -> 0.091020522
A10: NYC Light Duty Vehicle Miles Traveled (VMT) Adjusted to Account for Chosen Population Projection | R10: Diesel-Solid Waste | S10: 219257 | T10: =S10/1000000 -> 0.219257 | V10: 5671501 | W10: =V10*0.264172 -> 1498251.8 | X10: 3.65 | Y10: =V10*X10 -> 20700979 | Z10: =AA10/W10 -> 8.5853313 | AA10: =Y10*0.621371 -> 12862988 | AC10: NYC GHG Inventory 14 | AF10: truck | AG10: =ResidDataAndCalcs!T86/2 -> 0.036652094 | AH10: =AG10/SUM($AG$7:$AG$11) -> 0.30635579 | AI10: =TechData_existing!B14 -> TLEPGSL | AJ10: =TechData_existing!C14 -> TL.GSL.P.Existing Fleet | AK10: =TechData_existing!I14 -> 0.075138134
C11: 2005 | D11: 2010 | E11: 2015 | F11: 2020 | G11: 2025 | H11: 2030 | I11: 2035 | J11: 2040 | K11: 2045 | L11: 2050 | M11: 2055 | R11: Diesel-Transit Bus | S11: 7260325 | T11: =S11/1000000 -> 7.260325 | V11: 188631878 | W11: =V11*0.264172 -> 49831260 | X11: 5.38 | Y11: =V11*X11 -> 1.0148395e+09 | Z11: =AA11/W11 -> 12.654543 | AA11: =Y11*0.621371 -> 6.3059184e+08 | AC11: NYC GHG Inventory 14 | AF11: truck | AG11: =AG10 -> 0.036652094 | AH11: =AG11/SUM($AG$7:$AG$11) -> 0.30635579 | AI11: =TechData_existing!B15 -> TLEPDSL | AJ11: =TechData_existing!C15 -> TL.DSL.P.Existing fleet | AK11: =TechData_existing!I15 -> 0.078776644
A12: Scenario Pop from Population Tab (millions) | C12: ='Population NYC'!D15/1000000 -> 8.175133 | D12: ='Population NYC'!E15/1000000 -> 8.175133 | E12: ='Population NYC'!F15/1000000 -> 8.491079 | F12: ='Population NYC'!G15/1000000 -> 8.550971 | G12: ='Population NYC'!H15/1000000 -> 8.685999 | H12: ='Population NYC'!I15/1000000 -> 8.821027 | I12: ='Population NYC'!J15/1000000 -> 8.923086 | J12: ='Population NYC'!K15/1000000 -> 9.025145 | ... M12: ='Population NYC'!N15/1000000 -> 9.485589 | R12: Diesel-Ships & Boats | S12: 0 | T12: =S12/1000000 -> 0 | U12: 0.03866 | V12: =S12*U12 -> 0 | W12: =V12*0.264172 -> 0 | X12: 2 | Y12: =V12*X12 -> 0 | AA12: =Y12*0.621371 -> 0
A13: Scenario LDV vehicle miles traveled (bln-VMT) | C13: =AB19 -> 19.661797 | D13: =C13 -> 19.661797 | E13: =D13*'AEO14 DMD'!E32/'AEO14 DMD'!D32 -> 20.068306 | F13: =E13*'AEO14 DMD'!F32/'AEO14 DMD'!E32 -> 21.057218 | G13: =F13*'AEO14 DMD'!G32/'AEO14 DMD'!F32 -> 21.990086 | H13: =G13*'AEO14 DMD'!H32/'AEO14 DMD'!G32 -> 23.17928 | I13: =H13*'AEO14 DMD'!I32/'AEO14 DMD'!H32 -> 24.394242 | J13: =I13*'AEO14 DMD'!J32/'AEO14 DMD'!I32 -> 24.603292 | K13: =J13*'AEO14 DMD'!K32/'AEO14 DMD'!J32 -> 26.156676 | L13: =K13*'AEO14 DMD'!L32/'AEO14 DMD'!K32 -> 27.037894 | M13: =L13*'AEO14 DMD'!M32/'AEO14 DMD'!L32 -> 27.919111 | R13: Diesel-Other Off-Road Vehicles | S13: 0 | T13: =S13/1000000 -> 0 | X13: 2 | Y13: =V13*X13 -> 0 | AA13: =Y13*0.621371 -> 0
A14: Ratio (bln-VMT/million people) | C14: =C13/C12 -> 2.4050736 | D14: =D13/D12 -> 2.4050736 | E14: =D14*'AEO14 DMD'!E34/'AEO14 DMD'!D34 -> 2.3511439 | F14: =E14*'AEO14 DMD'!F34/'AEO14 DMD'!E34 -> 2.3670522 | G14: =F14*'AEO14 DMD'!G34/'AEO14 DMD'!F34 -> 2.3756671 | H14: =G14*'AEO14 DMD'!H34/'AEO14 DMD'!G34 -> 2.4102902 | I14: =H14*'AEO14 DMD'!I34/'AEO14 DMD'!H34 -> 2.4449944 | J14: =I14*'AEO14 DMD'!J34/'AEO14 DMD'!I34 -> 2.4449944 | K14: =J14*'AEO14 DMD'!K34/'AEO14 DMD'!J34 -> 2.4449944 | L14: =K14*'AEO14 DMD'!L34/'AEO14 DMD'!K34 -> 2.4449944 | M14: =L14*'AEO14 DMD'!M34/'AEO14 DMD'!L34 -> 2.4449944 | R14: Electricity-Subway | S14: 25432916 | T14: =S14/1000000 -> 25.432916 | U14: 1 | X14: =Y14/S14 -> 22.717018 | Y14: =AA14*1.6 -> 577760000 | AA14: 361100000 | AC14: NYC GHG Inventory 14
R15: Ethanol (E100) | S15: 0 | T15: =S15/1000000 -> 0 | U15: 0.02342 | V15: 0 | W15: =V15*0.264172 -> 0 | X15: 6.58 | Y15: =V15*X15 -> 0 | AA15: =Y15*0.621371 -> 0 | AC15: NYC GHG Inventory 14
A16: Assumed LDV VMT (from city data) | R16: Gas-Light Trucks | S16: 14846296 | T16: =S16/1000000 -> 14.846296 | U16: 0.03484 | V16: =S16*U16 -> 517244.95 | W16: =V16*0.264172 -> 136641.63 | X16: 6.21 | Y16: =V16*X16 -> 3212091.2 | Z16: =AA16/W16 -> 14.606824 | AA16: =Y16*0.621371 -> 1995900.3 | AB16: =S16*AD16/1000000 -> 2.4941777 | AC16: NYC GHG Inventory 14 | AD16: 0.168
C17: 2005 | D17: 2010 | E17: 2015 | F17: 2020 | G17: 2025 | H17: 2030 | I17: 2035 | J17: 2040 | K17: 2045 | L17: 2050 | M17: 2055 | R17: Gas-Cars | S17: 122351394 | T17: =S17/1000000 -> 122.35139 | U17: 0.03484 | V17: 3629210490 | W17: =V17*0.264172 -> 9.5873579e+08 | X17: 8.72 | Y17: =V17*X17 -> 3.1646715e+10 | Z17: =AA17/W17 -> 20.510709 | AA17: =Y17*0.621371 -> 1.9664351e+10 | AB17: =S17*AD17/1000000 -> 21.289143 | AC17: NYC GHG Inventory 14 | AD17: 0.174
A18: R1 - Supply Region | AF18: TL-DSL Ratio | AG18: =(T7+T9)/(T7+T9+T16+T17) -> 0.013669364
A19: Brooklyn | C19: =D19 -> 4.3486256e+09 | D19: 4.3486256e+09 | E19: 4.534572e+09 | F19: 4.7084541e+09 | G19: 7981932785 | H19: 8175354315 | I19: 8368775845 | J19: 8545567975 | K19: 8722360105 | L19: 8480175670 | R19: Transportation VMT Estimates | S19: km/year | U19: km/liter | V19: Gallons/year | W19: MPG Rating | X19: Total VMT | Y19: VMT/Person | Z19: References | AB19: =ResidDataAndCalcs!R33+'GHG Reports'!C103 -> 19.661797
A20: Bronx | C20: =D20 -> 3.0099004e+09 | D20: 3.0099004e+09 | E20: 3.0873783e+09 | F20: 3.2294859e+09 | G20: 3137744765 | H20: 3204244480 | I20: 3270744195 | J20: 3.3165636e+09 | K20: 3362382920 | L20: 3445751840 | R20: Biofuel | S20: =Y3 -> 0 | U20: =S20/V3 -> #DIV/0! | V20: =0.264172*S3 -> 0 | W20: =0.264172*S3 -> 0 | X20: =V20*W20 -> 0 | Y20: =X20/9000000 -> 0 | Z20: DOT RITA Bus Fuel Economy
A21: Manhathan | C21: =D21 -> 3.1068522e+09 | D21: 3.1068522e+09 | E21: 3.0848577e+09 | F21: 3.1426988e+09 | G21: 3564802430 | H21: 3.630499e+09 | I21: 3696195495 | J21: 3757488850 | K21: 3818782205 | L21: 3874745100 | R21: CNG-Transit Bus (GJ) | S21: =Y4 -> 4594.4582 | U21: =S21/V4 -> 0.003233282 | V21: =0.264172*S4 -> 375385.51 | W21: 50 | X21: =V21*W21 -> 18769275 | Y21: =X21/9000000 -> 2.085475 | Z21: Assumes 2.78 kBut/PMT
A22: Staten Island | C22: =D22 -> 2.0302486e+09 | D22: 2.0302486e+09 | E22: 2.079645e+09 | F22: 2.1430161e+09 | G22: 2184424990 | H22: 2236773655 | I22: 2289122320 | J22: 2330041375 | K22: 2370960430 | L22: 2405403290 | R22: Diesel-Commuter Rail | S22: =Y5 -> 86117354 | U22: =S22/V5 -> 17.005703 | V22: =0.264172*S5 -> 51711.933 | W22: 0.5 | X22: =V22*W22 -> 25855.967 | Y22: =X22/9000000 -> 0.0028728852 | Z22: 361.1 million miles by NYC subway in 2014
A23: Queens | C23: =D23 -> 7.1614064e+09 | D23: 7.1614064e+09 | E23: 6.8764354e+09 | F23: 6.9182672e+09 | G23: 4712675235 | H23: 4836534335 | I23: 4960393435 | J23: 5065679510 | K23: 5170965585 | L23: 5161858105 | R23: Diesel-Heavy Trucks | S23: =Y6 -> 1.1906313e+09 | U23: =S23/V6 -> 3.65 | V23: =0.264172*S6 -> 3316746 | W23: 5 | X23: =V23*W23 -> 16583730 | Y23: =X23/9000000 -> 1.8426367
R24: Diesel-Light Trucks | S24: =Y7 -> 1.5432571e+08 | U24: =S24/V7 -> 4.38 | V24: =0.264172*S7 -> 358254.74 | W24: 15 | X24: =V24*W24 -> 5373821.2 | Y24: =X24/9000000 -> 0.59709124
R25: Diesel-Non Bus | S25: =Y8 -> 40593580 | U25: =S25/V8 -> 5.38 | V25: =0.264172*S8 -> 76718.983 | W25: 25 | X25: =V25*W25 -> 1917974.6 | Y25: =X25/9000000 -> 0.21310829 | AB25: 30.87
R26: Diesel-Cars | S26: =Y9 -> 95339583 | U26: =S26/V9 -> 6.73 | V26: =0.264172*S9 -> 144040.84 | W26: 25 | X26: =V26*W26 -> 3601021 | Y26: =X26/9000000 -> 0.40011344 | AB26: 17.07
R27: Diesel-Solid Waste | S27: =Y10 -> 20700979 | U27: =S27/V10 -> 3.65 | V27: =0.264172*S10 -> 57921.56 | W27: 5 | X27: =V27*W27 -> 289607.8 | Y27: =X27/9000000 -> 0.032178645 | AB27: 19.54
R28: Diesel-Transit Bus | S28: =Y11 -> 1.0148395e+09 | U28: =S28/V11 -> 5.38 | V28: =0.264172*S11 -> 1917974.6 | W28: 5 | X28: =V28*W28 -> 9589872.9 | Y28: =X28/9000000 -> 1.0655414 | AB28: 5.78
R29: Diesel-Ships & Boats | S29: =Y12 -> 0 | U29: =S29/V12 -> #DIV/0! | V29: =0.264172*S12 -> 0 | W29: 0.1 | X29: =V29*W29 -> 0 | Y29: =X29/9000000 -> 0 | AB29: 27.49
R30: Diesel-Other Off-Road Vehicles | S30: =Y13 -> 0 | U30: =S30/V13 -> #DIV/0! | V30: =0.264172*S13 -> 0 | W30: 0.1 | X30: =V30*W30 -> 0 | Y30: =X30/9000000 -> 0
R31: Electricity-Subway (GJ) | S31: =Y14 -> 577760000 | U31: =S31/V14 -> #DIV/0! | V31: =0.264172*S14 -> 6718664.3 | W31: =X31/V31 -> 53.745802 | X31: 361100000 | Y31: =X31/9000000 -> 40.122222
R32: Ethanol | S32: =Y15 -> 0 | U32: =S32/V15 -> #DIV/0! | V32: =0.264172*S15 -> 0 | X32: =V32*W32 -> 0 | Y32: =X32/9000000 -> 0
R33: Gas-Light Trucks | S33: =Y16 -> 3212091.2 | U33: =S33/V16 -> 6.21 | V33: =0.264172*S16 -> 3921975.7 | W33: 15 | X33: =V33*W33 -> 58829636 | Y33: =X33/9000000 -> 6.5366262
R34: Gas-Cars | S34: =Y17 -> 3.1646715e+10 | U34: =S34/V17 -> 8.72 | V34: =0.264172*S17 -> 32321812 | W34: 25 | X34: =V34*W34 -> 8.0804531e+08 | Y34: =X34/9000000 -> 89.782812
R35: LDV Total | S35: =S24+S26+S33+S34 -> 3.1899593e+10 | V35: =V24+V26+V33+V34 -> 36746084 | X35: =X24+X26+X33+X34 -> 8.7584979e+08 | Y35: =X35/(D12*1000000) -> 107.13585 | Z35: Census Street Blog Post on NYC Car Ownership
R36: LDV Total | S36: =S21+S23+S25+S27+S28 -> 2.2667699e+09 | V36: =V21+V23+V25+V27+V28 -> 5744746.7 | X36: =X21+X23+X25+X27+X28 -> 47150461 | Y36: =X36/(D13*1000000) -> 2.3980749 | Z36: NYC Car Ownership by StatsBee
R37: Subway Ridership | S37: 1751000000 | U37: Subway Miles | V37: 361100000 | W37: Miles/GJ | X37: =V37/S14 -> 14.198136 | Y37: =V37/(D12*1000000) -> 44.170535 | Z37: NYC Estimated VMT/person-day
R39: NYC Car Ownership | S39: 2010 Population | U39: Households | V39: % Car Ownership | W39: Cars/Household | X39: Total Vehicles | Y39: Cars per Capita | Z39: Cars/100 People | AA39: Total Vehicles
R40: Brooklyn | S40: ='Population NYC'!E10 -> 2504700 | U40: =S40/3 -> 834900 | V40: 0.44 | W40: 1.65 | X40: =U40*V40*W40 -> 606137.4 | Y40: =X40/S40 -> 0.242 | Z40: 78 | AA40: =U40/100*Z40 -> 651222
R41: Bronx | S41: ='Population NYC'!E11 -> 1385108 | U41: =S41/3 -> 461702.67 | V41: 0.46 | W41: 1.65 | X41: =U41*V41*W41 -> 350432.32 | Y41: =X41/S41 -> 0.253 | Z41: 78 | AA41: =U41/100*Z41 -> 360128.08
R42: Manhattan | S42: ='Population NYC'!E12 -> 1585873 | U42: =S42/3 -> 528624.33 | V42: 0.24 | W42: 1.65 | X42: =U42*V42*W42 -> 209335.24 | Y42: =X42/S42 -> 0.132 | Z42: 78 | AA42: =U42/100*Z42 -> 412326.98
R43: Staten Island | S43: ='Population NYC'!E13 -> 468730 | U43: =S43/3 -> 156243.33 | V43: 0.84 | W43: 1.65 | X43: =U43*V43*W43 -> 216553.26 | Y43: =X43/S43 -> 0.462 | Z43: 78 | AA43: =U43/100*Z43 -> 121869.8
R44: Queens | S44: ='Population NYC'!E14 -> 2230722 | U44: =S44/3 -> 743574 | V44: 0.64 | W44: 1.65 | X44: =U44*V44*W44 -> 785214.14 | Y44: =X44/S44 -> 0.352 | Z44: 78 | AA44: =U44/100*Z44 -> 579987.72
R45: NYC Total | S45: =SUM(S40:S44) -> 8175133 | U45: =SUM(U40:U44) -> 2725044.3 | V45: =AVERAGE(V40:V44) -> 0.524 | W45: =AVERAGE(W40:W44) -> 1.65 | X45: =SUM(X40:X44) -> 2167672.4 | Y45: =AVERAGE(Y40:Y44) -> 0.2882 | Z45: =AVERAGE(Z40:Z44) -> 78 | AA45: =SUM(AA40:AA44) -> 2125534.6
D48: ='VMT NYC'!T16*ResidDataAndCalcs!C15*'VMT NYC'!AH7/('VMT NYC'!AH7+'VMT NYC'!AH8+'VMT NYC'!AH9+'VMT NYC'!AH10)*8 -> 5.941132
A49: Regional VMT per capita (bln-VMT/million people) Using ICLUS Regional Population and AEO VMT share by region
A50: VMT per capita for all regions is grown using the national VMT/capita growth rate calculated on the AEO10 DMD tab
C51: 2005 | D51: 2010 | E51: 2015 | F51: 2020 | G51: 2025 | H51: 2030 | I51: 2035 | J51: 2040 | K51: 2045 | L51: 2050 | M51: 2055
A52: R1 - Supply Region | B52: NEMA | C52: =C18/(Population!D9/1000000) -> 0 | D52: =D18/(Population!E9/1000000) -> 0 | E52: =E18/(Population!F9/1000000) -> 0 | F52: =F18/(Population!G9/1000000) -> 0 | G52: =G18/(Population!H9/1000000) -> 0 | H52: =H18/(Population!I9/1000000) -> 0 | I52: =I18/(Population!J9/1000000) -> 0 | J52: =J18/(Population!K9/1000000) -> 0 | ... L52: =L18/(Population!M9/1000000) -> 0 | M52: =L52*'AEO14 DMD'!$M$34/'AEO14 DMD'!$L$34 -> 0
A53: R2 - Brooklyn | B53: BK | C53: =(C19*10^-9)/('Population NYC'!D10*10^-6) -> 1.7361862 | D53: =(D19*10^-9)/('Population NYC'!E10*10^-6) -> 1.7361862 | E53: =(E19*10^-9)/('Population NYC'!F10*10^-6) -> 1.729569 | F53: =(F19*10^-9)/('Population NYC'!G10*10^-6) -> 1.7778136 | G53: =(G19*10^-9)/('Population NYC'!H10*10^-6) -> 2.9549247 | H53: =(H19*10^-9)/('Population NYC'!I10*10^-6) -> 2.9685285 | I53: =(I19*10^-9)/('Population NYC'!J10*10^-6) -> 2.9917687 | J53: =(J19*10^-9)/('Population NYC'!K10*10^-6) -> 3.0084467 | ... L53: =(L19*10^-9)/('Population NYC'!M10*10^-6) -> 2.8628061 | M53: =L53*'AEO14 DMD'!$M$34/'AEO14 DMD'!$L$34 -> 2.8628061
A54: R3 - Bronx | B54: BX | C54: =(C20*10^-9)/('Population NYC'!D11*10^-6) -> 2.1730438 | D54: =(D20*10^-9)/('Population NYC'!E11*10^-6) -> 2.1730438 | E54: =(E20*10^-9)/('Population NYC'!F11*10^-6) -> 2.1467573 | F54: =(F20*10^-9)/('Population NYC'!G11*10^-6) -> 2.2321763 | G54: =(G20*10^-9)/('Population NYC'!H11*10^-6) -> 2.1159617 | H54: =(H20*10^-9)/('Population NYC'!I11*10^-6) -> 2.1094461 | I54: =(I20*10^-9)/('Population NYC'!J11*10^-6) -> 2.1113542 | J54: =(J20*10^-9)/('Population NYC'!K11*10^-6) -> 2.1000944 | ... L54: =(L20*10^-9)/('Population NYC'!M11*10^-6) -> 2.0885547 | M54: =L54*'AEO14 DMD'!$M$34/'AEO14 DMD'!$L$34 -> 2.0885547
A55: R4 - Manhattan | B55: MH | C55: =(C21*10^-9)/('Population NYC'!D12*10^-6) -> 1.9590801 | D55: =(D21*10^-9)/('Population NYC'!E12*10^-6) -> 1.9590801 | E55: =(E21*10^-9)/('Population NYC'!F12*10^-6) -> 1.885301 | F55: =(F21*10^-9)/('Population NYC'!G12*10^-6) -> 1.9182905 | G55: =(G21*10^-9)/('Population NYC'!H12*10^-6) -> 2.1507097 | H55: =(H21*10^-9)/('Population NYC'!I12*10^-6) -> 2.1652387 | I55: =(I21*10^-9)/('Population NYC'!J12*10^-6) -> 2.1946708 | J55: =(J21*10^-9)/('Population NYC'!K12*10^-6) -> 2.2212409 | ... L55: =(L21*10^-9)/('Population NYC'!M12*10^-6) -> 2.2417984 | M55: =L55*'AEO14 DMD'!$M$34/'AEO14 DMD'!$L$34 -> 2.2417984
A56: R5 - Staten Island | B56: SI | C56: =(C22*10^-9)/('Population NYC'!D13*10^-6) -> 4.3313819 | D56: =(D22*10^-9)/('Population NYC'!E13*10^-6) -> 4.3313819 | E56: =(E22*10^-9)/('Population NYC'!F13*10^-6) -> 4.3941205 | F56: =(F22*10^-9)/('Population NYC'!G13*10^-6) -> 4.3990437 | G56: =(G22*10^-9)/('Population NYC'!H13*10^-6) -> 4.435813 | H56: =(H22*10^-9)/('Population NYC'!I13*10^-6) -> 4.4937783 | I56: =(I22*10^-9)/('Population NYC'!J13*10^-6) -> 4.583479 | J56: =(J22*10^-9)/('Population NYC'!K13*10^-6) -> 4.6497696 | ... L56: =(L22*10^-9)/('Population NYC'!M13*10^-6) -> 4.6944626 | M56: =L56*'AEO14 DMD'!$M$34/'AEO14 DMD'!$L$34 -> 4.6944626
A57: R6 - Queens | B57: QN | C57: =(C23*10^-9)/('Population NYC'!D14*10^-6) -> 3.2103536 | D57: =(D23*10^-9)/('Population NYC'!E14*10^-6) -> 3.2103536 | E57: =(E23*10^-9)/('Population NYC'!F14*10^-6) -> 2.9619636 | F57: =(F23*10^-9)/('Population NYC'!G14*10^-6) -> 2.9688375 | G57: =(G23*10^-9)/('Population NYC'!H14*10^-6) -> 2.003754 | H57: =(H23*10^-9)/('Population NYC'!I14*10^-6) -> 2.0376787 | I57: =(I23*10^-9)/('Population NYC'!J14*10^-6) -> 2.0727899 | J57: =(J23*10^-9)/('Population NYC'!K14*10^-6) -> 2.0996339 | ... L57: =(L23*10^-9)/('Population NYC'!M14*10^-6) -> 2.0843102 | M57: =L57*'AEO14 DMD'!$M$34/'AEO14 DMD'!$L$34 -> 2.0843102
C61: =SUM(C52:C60) -> 13.410046 | D61: =SUM(D52:D60) -> 13.410046 | E61: =SUM(E52:E60) -> 13.117711 | F61: =SUM(F52:F60) -> 13.296162 | G61: =SUM(G52:G60) -> 13.661163 | H61: =SUM(H52:H60) -> 13.77467 | I61: =SUM(I52:I60) -> 13.954063 | J61: =SUM(J52:J60) -> 14.079185 | ... M61: =SUM(M52:M60) -> 13.971932
D62: =D61/C61 -> 1 | E62: =E61/D61 -> 0.97820036 | F62: =F61/E61 -> 1.0136038 | G62: =G61/F61 -> 1.0274517 | H62: =H61/G61 -> 1.0083087 | I62: =I61/H61 -> 1.0130233 | J62: =J61/I61 -> 1.0089668 | K62: =K61/J61 -> 1.0027458 | ... M62: =M61/L61 -> 1
A63: Calculated Regionalized Light Duty Demand Data
A64: Assumes that the regional VMT/cap is constant over time
B66: Light Duty Vehicles billion vehicle-miles
B67: Region | C67: 2005 | D67: 2010 | E67: 2015 | F67: 2020 | G67: 2025 | H67: 2030 | I67: 2035 | J67: 2040 | K67: 2045 | L67: 2050 | M67: 2055
A68: R1 - Supply Region | B68: NEMA | C68: =C52*(Population!D9/1000000) -> 0 | D68: =D52*(Population!E9/1000000) -> 0 | E68: =E52*(Population!F9/1000000) -> 0 | F68: =F52*(Population!G9/1000000) -> 0 | G68: =G52*(Population!H9/1000000) -> 0 | H68: =H52*(Population!I9/1000000) -> 0 | I68: =I52*(Population!J9/1000000) -> 0 | J68: =J52*(Population!K9/1000000) -> 0 | ... M68: =M52*(Population!N9/1000000) -> 0
A69: R2 - Brooklyn | B69: BK | C69: =C53*('Population NYC'!D10*10^-6) -> 4.3486256 | D69: =D53*('Population NYC'!E10*10^-6) -> 4.3486256 | E69: =E53*('Population NYC'!F10*10^-6) -> 4.534572 | F69: =F53*('Population NYC'!G10*10^-6) -> 4.7084541 | G69: =G53*('Population NYC'!H10*10^-6) -> 7.9819328 | H69: =H53*('Population NYC'!I10*10^-6) -> 8.1753543 | I69: =I53*('Population NYC'!J10*10^-6) -> 8.3687758 | J69: =J53*('Population NYC'!K10*10^-6) -> 8.545568 | ... M69: =M53*('Population NYC'!N10*10^-6) -> 8.6598825
A70: R3 - Bronx | B70: BX | C70: =C54*('Population NYC'!D11*10^-6) -> 3.0099004 | D70: =D54*('Population NYC'!E11*10^-6) -> 3.0099004 | E70: =E54*('Population NYC'!F11*10^-6) -> 3.0873783 | F70: =F54*('Population NYC'!G11*10^-6) -> 3.2294859 | G70: =G54*('Population NYC'!H11*10^-6) -> 3.1377448 | H70: =H54*('Population NYC'!I11*10^-6) -> 3.2042445 | I70: =I54*('Population NYC'!J11*10^-6) -> 3.2707442 | J70: =J54*('Population NYC'!K11*10^-6) -> 3.3165636 | ... M70: =M54*('Population NYC'!N11*10^-6) -> 3.5219104
A71: R4 - Manhattan | B71: MH | C71: =C55*('Population NYC'!D12*10^-6) -> 3.1068522 | D71: =D55*('Population NYC'!E12*10^-6) -> 3.1068522 | E71: =E55*('Population NYC'!F12*10^-6) -> 3.0848577 | F71: =F55*('Population NYC'!G12*10^-6) -> 3.1426988 | G71: =G55*('Population NYC'!H12*10^-6) -> 3.5648024 | H71: =H55*('Population NYC'!I12*10^-6) -> 3.630499 | I71: =I55*('Population NYC'!J12*10^-6) -> 3.6961955 | J71: =J55*('Population NYC'!K12*10^-6) -> 3.7574888 | ... M71: =M55*('Population NYC'!N12*10^-6) -> 3.9166558
A72: R5 - Staten Island | B72: SI | C72: =C56*('Population NYC'!D13*10^-6) -> 2.0302486 | D72: =D56*('Population NYC'!E13*10^-6) -> 2.0302486 | E72: =E56*('Population NYC'!F13*10^-6) -> 2.079645 | F72: =F56*('Population NYC'!G13*10^-6) -> 2.1430161 | G72: =G56*('Population NYC'!H13*10^-6) -> 2.184425 | H72: =H56*('Population NYC'!I13*10^-6) -> 2.2367737 | I72: =I56*('Population NYC'!J13*10^-6) -> 2.2891223 | J72: =J56*('Population NYC'!K13*10^-6) -> 2.3300414 | ... M72: =M56*('Population NYC'!N13*10^-6) -> 2.4323318
A73: R6 - Queens | B73: QN | C73: =C57*('Population NYC'!D14*10^-6) -> 7.1614064 | D73: =D57*('Population NYC'!E14*10^-6) -> 7.1614064 | E73: =E57*('Population NYC'!F14*10^-6) -> 6.8764354 | F73: =F57*('Population NYC'!G14*10^-6) -> 6.9182672 | G73: =G57*('Population NYC'!H14*10^-6) -> 4.7126752 | H73: =H57*('Population NYC'!I14*10^-6) -> 4.8365343 | I73: =I57*('Population NYC'!J14*10^-6) -> 4.9603934 | J73: =J57*('Population NYC'!K14*10^-6) -> 5.0656795 | ... M73: =M57*('Population NYC'!N14*10^-6) -> 5.229749
B77: Total | C77: =SUM(C68:C76) -> 19.657033 | D77: =SUM(D68:D73) -> 19.657033 | E77: =SUM(E68:E73) -> 19.662888 | F77: =SUM(F68:F73) -> 20.141922 | G77: =SUM(G68:G73) -> 21.58158 | H77: =SUM(H68:H73) -> 22.083406 | I77: =SUM(I68:I73) -> 22.585231 | J77: =SUM(J68:J73) -> 23.015341 | K77: =SUM(K68:K73) -> 23.445451 | ... M77: =SUM(M68:M73) -> 23.76053
B78: Ratio | C78: =C77/C12 -> 2.4044909 | D78: =D77/D12 -> 2.4044909 | E78: =E77/E12 -> 2.3157114 | F78: =F77/F12 -> 2.3555129 | G78: =G77/G12 -> 2.48464 | H78: =H77/H12 -> 2.503496 | I78: =I77/I12 -> 2.5311009 | J78: =J77/J12 -> 2.5501353 | ... M78: =M77/M12 -> 2.5049082
A80: R1 - Supply Region
C81: 2005 | D81: 2010 | E81: 2015 | F81: 2020 | G81: 2025 | H81: 2030 | I81: 2035 | J81: 2040 | K81: 2045 | L81: 2050 | M81: 2055
A82: Light Duty Vehicles (passenger) (billion vmt) | B82: TL | C82: =C68 -> 0 | D82: =D68 -> 0 | E82: =E68 -> 0 | F82: =F68 -> 0 | G82: =G68 -> 0 | H82: =H68 -> 0 | I82: =I68 -> 0 | J82: =J68 -> 0 | ... M82: =M68 -> 0
A84: R2 - Brooklyn
C85: 2005 | D85: 2010 | E85: 2015 | F85: 2020 | G85: 2025 | H85: 2030 | I85: 2035 | J85: 2040 | K85: 2045 | L85: 2050 | M85: 2055
A86: Light Duty Vehicles (passenger) (billion vmt) | B86: TL | C86: =C69 -> 4.3486256 | D86: =D69 -> 4.3486256 | E86: =E69 -> 4.534572 | F86: =F69 -> 4.7084541 | G86: =G69 -> 7.9819328 | H86: =H69 -> 8.1753543 | I86: =I69 -> 8.3687758 | J86: =J69 -> 8.545568 | ... M86: =M69 -> 8.6598825
A88: R3 - Bronx
C89: 2005 | D89: 2010 | E89: 2015 | F89: 2020 | G89: 2025 | H89: 2030 | I89: 2035 | J89: 2040 | K89: 2045 | L89: 2050 | M89: 2055
A90: Light Duty Vehicles (passenger) (billion vmt) | B90: TL | C90: =C70 -> 3.0099004 | D90: =D70 -> 3.0099004 | E90: =E70 -> 3.0873783 | F90: =F70 -> 3.2294859 | G90: =G70 -> 3.1377448 | H90: =H70 -> 3.2042445 | I90: =I70 -> 3.2707442 | J90: =J70 -> 3.3165636 | ... M90: =M70 -> 3.5219104
A92: R4 - Manhattan
C93: 2005 | D93: 2010 | E93: 2015 | F93: 2020 | G93: 2025 | H93: 2030 | I93: 2035 | J93: 2040 | K93: 2045 | L93: 2050 | M93: 2055
A94: Light Duty Vehicles (passenger) (billion vmt) | B94: TL | C94: =C71 -> 3.1068522 | D94: =D71 -> 3.1068522 | E94: =E71 -> 3.0848577 | F94: =F71 -> 3.1426988 | G94: =G71 -> 3.5648024 | H94: =H71 -> 3.630499 | I94: =I71 -> 3.6961955 | J94: =J71 -> 3.7574888 | ... M94: =M71 -> 3.9166558
A96: R5 - Staten Island
C97: 2005 | D97: 2010 | E97: 2015 | F97: 2020 | G97: 2025 | H97: 2030 | I97: 2035 | J97: 2040 | K97: 2045 | L97: 2050 | M97: 2055
A98: Light Duty Vehicles (passenger) (billion vmt) | B98: TL | C98: =C72 -> 2.0302486 | D98: =D72 -> 2.0302486 | E98: =E72 -> 2.079645 | F98: =F72 -> 2.1430161 | G98: =G72 -> 2.184425 | H98: =H72 -> 2.2367737 | I98: =I72 -> 2.2891223 | J98: =J72 -> 2.3300414 | ... M98: =M72 -> 2.4323318
A100: R6 - Queens
C101: 2005 | D101: 2010 | E101: 2015 | F101: 2020 | G101: 2025 | H101: 2030 | I101: 2035 | J101: 2040 | K101: 2045 | L101: 2050 | M101: 2055
A102: Light Duty Vehicles (passenger) (billion vmt) | B102: TL | C102: =C73 -> 7.1614064 | D102: =D73 -> 7.1614064 | E102: =E73 -> 6.8764354 | F102: =F73 -> 6.9182672 | G102: =G73 -> 4.7126752 | H102: =H73 -> 4.8365343 | I102: =I73 -> 4.9603934 | J102: =J73 -> 5.0656795 | ... M102: =M73 -> 5.229749
C105: 2005 | D105: 2010 | E105: 2015 | F105: 2020 | G105: 2025 | H105: 2030 | I105: 2035 | J105: 2040 | K105: 2045 | L105: 2050 | M105: 2055
A106: Light Duty Vehicles (passenger) (billion vmt) | B106: TL | C106: =C74 -> 0 | D106: =D74 -> 0 | E106: =E74 -> 0 | F106: =F74 -> 0 | G106: =G74 -> 0 | H106: =H74 -> 0 | I106: =I74 -> 0 | J106: =J74 -> 0 | ... M106: =M74 -> 0
C109: 2005 | D109: 2010 | E109: 2015 | F109: 2020 | G109: 2025 | H109: 2030 | I109: 2035 | J109: 2040 | K109: 2045 | L109: 2050 | M109: 2055
A110: Light Duty Vehicles (passenger) (billion vmt) | B110: TL | C110: =C75 -> 0 | D110: =D75 -> 0 | E110: =E75 -> 0 | F110: =F75 -> 0 | G110: =G75 -> 0 | H110: =H75 -> 0 | I110: =I75 -> 0 | J110: =J75 -> 0 | ... M110: =M75 -> 0
C113: 2005 | D113: 2010 | E113: 2015 | F113: 2020 | G113: 2025 | H113: 2030 | I113: 2035 | J113: 2040 | K113: 2045 | L113: 2050 | M113: 2055
A114: Light Duty Vehicles (passenger) (billion vmt) | B114: TL | C114: =C76 -> 0 | D114: =D76 -> 0 | E114: =E76 -> 0 | F114: =F76 -> 0 | G114: =G76 -> 0 | H114: =H76 -> 0 | I114: =I76 -> 0 | J114: =J76 -> 0 | ... M114: =M76 -> 0
B116: TOTAL
C117: 2005 | D117: 2010 | E117: 2015 | F117: 2020 | G117: 2025 | H117: 2030 | I117: 2035 | J117: 2040 | K117: 2045 | L117: 2050 | M117: 2055
A118: Light Duty Vehicles (passenger) (billion vmt) | B118: TL | C118: =C114+C110+C106+C102+C98+C94+C90+C86+C82 -> 19.657033 | D118: =D114+D110+D106+D102+D98+D94+D90+D86+D82 -> 19.657033 | E118: =E114+E110+E106+E102+E98+E94+E90+E86+E82 -> 19.662888 | F118: =F114+F110+F106+F102+F98+F94+F90+F86+F82 -> 20.141922 | G118: =G114+G110+G106+G102+G98+G94+G90+G86+G82 -> 21.58158 | H118: =H114+H110+H106+H102+H98+H94+H90+H86+H82 -> 22.083406 | I118: =I114+I110+I106+I102+I98+I94+I90+I86+I82 -> 22.585231 | J118: =J114+J110+J106+J102+J98+J94+J90+J86+J82 -> 23.015341 | ... M118: =M114+M110+M106+M102+M98+M94+M90+M86+M82 -> 23.76053

Sheet TechData-Emis
A1: TechData | B1: R1,R2,R3,R4,R5,R6 | G1: * | H1: * | I1: * | J1: * | K1: * | L1: * | M1: * | N1: * | O1: * | P1: * | Q1: * | R1: * | S1: * | T1: * | AY1: * | AZ1: * | BA1: * | BB1: * | BC1: * | BD1: * | BE1: * | BF1: * | BG1: * | BH1: * | BI1: * | BJ1: * | BK1: * | BL1: * | BM1: * | BN1: * | BO1: * | BP1: * | BQ1: * | BR1: * | BS1: * | BT1: * | BU1: * | BV1: * | BW1: * | BX1: * | BY1: * | BZ1: * | CA1: * | CB1: * | CC1: * | CD1: * | CE1: * | CF1: * | CG1: * | CH1: * | CI1: * | CJ1: * | CK1: * | CL1: * | CM1: * | CN1: * | CO1: * | CP1: * | CQ1: * | CR1: * | CS1: * | CT1: * | CU1: * | CV1: * | CW1: * | CX1: * | CY1: * | CZ1: * | DA1: * | DB1: * | DC1: * | DD1: * | DE1: * | DF1: * | DG1: * | DH1: * | DI1: * | DJ1: * | DK1: * | DL1: * | DM1: * | DN1: * | DO1: * | DP1: * | DQ1: * | DR1: * | DS1: * | DT1: * | DU1: * | DV1: * | DW1: * | DX1: * | DY1: * | DZ1: * | EA1: * | EB1: * | EC1: * | ED1: * | EE1: * | EF1: * | EG1: * | EH1: * | EI1: * | EJ1: * | EK1: * | EL1: * | EM1: * | EN1: * | EO1: * | EP1: * | EQ1: * | ER1: * | ES1: * | ET1: * | EU1: * | EV1: * | EW1: * | EX1: * | EY1: * | EZ1: * | FA1: * | FB1: * | FC1: * | FD1: * | FE1: * | FF1: * | FG1: * | FH1: * | FI1: * | FJ1: * | FK1: * | FL1: * | FM1: * | FN1: * | FO1: * | FP1: * | FQ1: * | FR1: * | FS1: * | FT1: * | FU1: * | FV1: * | FW1: * | FX1: *
K2: CO2 | L2: CO2 | M2: CO2 | N2: CO2 | O2: CO2 | P2: CO2 | Q2: CO2 | R2: CO2 | S2: CO2 | T2: CO2 | U2: NOX | V2: NOX | W2: NOX | X2: NOX | Y2: NOX | Z2: NOX | AA2: NOX | AB2: NOX | AC2: NOX | AD2: NOX | AE2: SO2 | AF2: SO2 | AG2: SO2 | AH2: SO2 | AI2: SO2 | AJ2: SO2 | AK2: SO2 | AL2: SO2 | AM2: SO2 | AN2: SO2 | AO2: PM10 | AP2: PM10 | AQ2: PM10 | AR2: PM10 | AS2: PM10 | AT2: PM10 | AU2: PM10 | AV2: PM10 | AW2: PM10 | AX2: PM10 | AY2: PM25 | AZ2: PM25 | BA2: PM25 | BB2: PM25 | BC2: PM25 | BD2: PM25 | BE2: PM25 | BF2: PM25 | BG2: PM25 | BH2: PM25 | BI2: CO | BJ2: CO | BK2: CO | BL2: CO | BM2: CO | BN2: CO | BO2: CO | BP2: CO | BQ2: CO | BR2: CO | BS2: VOC | BT2: VOC | BU2: VOC | BV2: VOC | BW2: VOC | BX2: VOC | BY2: VOC | BZ2: VOC | CA2: VOC | CB2: VOC | CC2: NH3 | CD2: NH3 | CE2: NH3 | CF2: NH3 | CG2: NH3 | CH2: NH3 | CI2: NH3 | CJ2: NH3 | CK2: NH3 | CL2: NH3 | CM2: N2O | CN2: N2O | CO2: N2O | CP2: N2O | CQ2: N2O | CR2: N2O | CS2: N2O | CT2: N2O | CU2: N2O | CV2: N2O | CW2: BC | CX2: BC | CY2: BC | CZ2: BC | DA2: BC | DB2: BC | DC2: BC | DD2: BC | DE2: BC | DF2: BC | DG2: OC | DH2: OC | DI2: OC | DJ2: OC | DK2: OC | DL2: OC | DM2: OC | DN2: OC | DO2: OC | DP2: OC | DQ2: CH4 | DR2: CH4 | DS2: CH4 | DT2: CH4 | DU2: CH4 | DV2: CH4 | DW2: CH4 | DX2: CH4 | DY2: CH4 | DZ2: CH4 | EA2: =CONCATENATE(K2,"T") -> CO2T | EB2: =CONCATENATE(L2,"T") -> CO2T | EC2: =CONCATENATE(M2,"T") -> CO2T | ED2: =CONCATENATE(N2,"T") -> CO2T | EE2: =CONCATENATE(O2,"T") -> CO2T | EF2: =CONCATENATE(P2,"T") -> CO2T | EG2: =CONCATENATE(Q2,"T") -> CO2T | EH2: =CONCATENATE(R2,"T") -> CO2T | ... FX2: =CONCATENATE(BH2,"T") -> PM25T
F7: ~FI_T
A8: Region | B8: TechName | C8: *TechDesc | D8: *Units | E8: *CommIN | F8: *CommOUT | G8: *Type | H8: *Fuel | I8: *Adjustment | J8: *Categories for tracking emissions | K8: *ENV_ACT~CO2~2010 | L8: *ENV_ACT~CO2~2015 | M8: *ENV_ACT~CO2~2020 | N8: *ENV_ACT~CO2~2025 | O8: *ENV_ACT~CO2~2030 | P8: *ENV_ACT~CO2~2035 | Q8: *ENV_ACT~CO2~2040 | R8: *ENV_ACT~CO2~2045 | S8: *ENV_ACT~CO2~2050 | T8: *ENV_ACT~CO2~2055 | U8: ENV_ACT~NOX~2010 | V8: ENV_ACT~NOX~2015 | W8: ENV_ACT~NOX~2020 | X8: ENV_ACT~NOX~2025 | Y8: ENV_ACT~NOX~2030 | Z8: ENV_ACT~NOX~2035 | AA8: ENV_ACT~NOX~2040 | AB8: ENV_ACT~NOX~2045 | AC8: ENV_ACT~NOX~2050 | AD8: ENV_ACT~NOX~2055 | AE8: ENV_ACT~SO2~2010 | AF8: ENV_ACT~SO2~2015 | AG8: ENV_ACT~SO2~2020 | AH8: ENV_ACT~SO2~2025 | AI8: ENV_ACT~SO2~2030 | AJ8: ENV_ACT~SO2~2035 | AK8: ENV_ACT~SO2~2040 | AL8: ENV_ACT~SO2~2045 | AM8: ENV_ACT~SO2~2050 | AN8: ENV_ACT~SO2~2055 | AO8: ENV_ACT~PM10~2010 | AP8: ENV_ACT~PM10~2015 | AQ8: ENV_ACT~PM10~2020 | AR8: ENV_ACT~PM10~2025 | AS8: ENV_ACT~PM10~2030 | AT8: ENV_ACT~PM10~2035 | AU8: ENV_ACT~PM10~2040 | AV8: ENV_ACT~PM10~2045 | AW8: ENV_ACT~PM10~2050 | AX8: ENV_ACT~PM10~2055 | AY8: ENV_ACT~PM25~2010 | AZ8: ENV_ACT~PM25~2015 | BA8: ENV_ACT~PM25~2020 | BB8: ENV_ACT~PM25~2025 | BC8: ENV_ACT~PM25~2030 | BD8: ENV_ACT~PM25~2035 | BE8: ENV_ACT~PM25~2040 | BF8: ENV_ACT~PM25~2045 | BG8: ENV_ACT~PM25~2050 | BH8: ENV_ACT~PM25~2055 | BI8: ENV_ACT~CO~2010 | BJ8: ENV_ACT~CO~2015 | BK8: ENV_ACT~CO~2020 | BL8: ENV_ACT~CO~2025 | BM8: ENV_ACT~CO~2030 | BN8: ENV_ACT~CO~2035 | BO8: ENV_ACT~CO~2040 | BP8: ENV_ACT~CO~2045 | BQ8: ENV_ACT~CO~2050 | BR8: ENV_ACT~CO~2055 | BS8: ENV_ACT~VOC~2010 | BT8: ENV_ACT~VOC~2015 | BU8: ENV_ACT~VOC~2020 | BV8: ENV_ACT~VOC~2025 | BW8: ENV_ACT~VOC~2030 | BX8: ENV_ACT~VOC~2035 | BY8: ENV_ACT~VOC~2040 | BZ8: ENV_ACT~VOC~2045 | CA8: ENV_ACT~VOC~2050 | CB8: ENV_ACT~VOC~2055 | CC8: ENV_ACT~NH3~2010 | CD8: ENV_ACT~NH3~2015 | CE8: ENV_ACT~NH3~2020 | CF8: ENV_ACT~NH3~2025 | CG8: ENV_ACT~NH3~2030 | CH8: ENV_ACT~NH3~2035 | CI8: ENV_ACT~NH3~2040 | CJ8: ENV_ACT~NH3~2045 | CK8: ENV_ACT~NH3~2050 | CL8: ENV_ACT~NH3~2055 | CM8: ENV_ACT~N2O~2010 | CN8: ENV_ACT~N2O~2015 | CO8: ENV_ACT~N2O~2020 | CP8: ENV_ACT~N2O~2025 | CQ8: ENV_ACT~N2O~2030 | CR8: ENV_ACT~N2O~2035 | CS8: ENV_ACT~N2O~2040 | CT8: ENV_ACT~N2O~2045 | CU8: ENV_ACT~N2O~2050 | CV8: ENV_ACT~N2O~2055 | CW8: ENV_ACT~BC~2010 | CX8: ENV_ACT~BC~2015 | CY8: ENV_ACT~BC~2020 | CZ8: ENV_ACT~BC~2025 | DA8: ENV_ACT~BC~2030 | DB8: ENV_ACT~BC~2035 | DC8: ENV_ACT~BC~2040 | DD8: ENV_ACT~BC~2045 | DE8: ENV_ACT~BC~2050 | DF8: ENV_ACT~BC~2055 | DG8: ENV_ACT~OC~2010 | DH8: ENV_ACT~OC~2015 | DI8: ENV_ACT~OC~2020 | DJ8: ENV_ACT~OC~2025 | DK8: ENV_ACT~OC~2030 | DL8: ENV_ACT~OC~2035 | DM8: ENV_ACT~OC~2040 | DN8: ENV_ACT~OC~2045 | DO8: ENV_ACT~OC~2050 | DP8: ENV_ACT~OC~2055 | DQ8: ENV_ACT~CH4~2010 | DR8: ENV_ACT~CH4~2015 | DS8: ENV_ACT~CH4~2020 | DT8: ENV_ACT~CH4~2025 | DU8: ENV_ACT~CH4~2030 | DV8: ENV_ACT~CH4~2035 | DW8: ENV_ACT~CH4~2040 | DX8: ENV_ACT~CH4~2045 | DY8: ENV_ACT~CH4~2050 | DZ8: ENV_ACT~CH4~2055 | EA8: *ENV_ACT~CO2T~2010 | EB8: *ENV_ACT~CO2T~2015 | EC8: *ENV_ACT~CO2T~2020 | ED8: *ENV_ACT~CO2T~2025 | EE8: *ENV_ACT~CO2T~2030 | EF8: *ENV_ACT~CO2T~2035 | EG8: *ENV_ACT~CO2T~2040 | EH8: *ENV_ACT~CO2T~2045 | EI8: *ENV_ACT~CO2T~2050 | EJ8: *ENV_ACT~CO2T~2055 | EK8: *ENV_ACT~NOXT~2010 | EL8: *ENV_ACT~NOXT~2015 | EM8: *ENV_ACT~NOXT~2020 | EN8: *ENV_ACT~NOXT~2025 | EO8: *ENV_ACT~NOXT~2030 | EP8: *ENV_ACT~NOXT~2035 | EQ8: *ENV_ACT~NOXT~2040 | ER8: *ENV_ACT~NOXT~2045 | ES8: *ENV_ACT~NOXT~2050 | ET8: *ENV_ACT~NOXT~2055 | EU8: *ENV_ACT~SO2T~2010 | EV8: *ENV_ACT~SO2T~2015 | EW8: *ENV_ACT~SO2T~2020 | EX8: *ENV_ACT~SO2T~2025 | EY8: *ENV_ACT~SO2T~2030 | EZ8: *ENV_ACT~SO2T~2035 | FA8: *ENV_ACT~SO2T~2040 | FB8: *ENV_ACT~SO2T~2045 | FC8: *ENV_ACT~SO2T~2050 | FD8: *ENV_ACT~SO2T~2055 | FE8: *ENV_ACT~PM10T~2010 | FF8: *ENV_ACT~PM10T~2015 | FG8: *ENV_ACT~PM10T~2020 | FH8: *ENV_ACT~PM10T~2025 | FI8: *ENV_ACT~PM10T~2030 | FJ8: *ENV_ACT~PM10T~2035 | FK8: *ENV_ACT~PM10T~2040 | FL8: *ENV_ACT~PM10T~2045 | FM8: *ENV_ACT~PM10T~2050 | FN8: *ENV_ACT~PM10T~2055 | FO8: *ENV_ACT~PM25T~2010 | FP8: *ENV_ACT~PM25T~2015 | FQ8: *ENV_ACT~PM25T~2020 | FR8: *ENV_ACT~PM25T~2025 | FS8: *ENV_ACT~PM25T~2030 | FT8: *ENV_ACT~PM25T~2035 | FU8: *ENV_ACT~PM25T~2040 | FV8: *ENV_ACT~PM25T~2045 | FW8: *ENV_ACT~PM25T~2050 | FX8: *ENV_ACT~PM25T~2055
A9: * Existing Vehicles
A10: =IF(LEFT(TRIM(Technologies!B64),1)="*", _xlfn.CONCAT("*","R2"), "R2") -> R2 | B10: =TechData_existing!B7 -> TLEMCGSL | C10: =TechData_existing!C7 -> TL.GSL.MC.Existing fleet | D10: =TechData_existing!D7 -> bn-vmt, bn-vmt/a | E10: =TechData_existing!E7 -> TLGSL | F10: =TechData_existing!F7 -> TL | G10: Mini car | H10: GSL | I10: 1 | J10: =CONCATENATE(G10,"-",H10) -> Mini car-GSL | K10: =$I10*IF($G10="Pickup", SUMIFS(NewEmisData!E:E, NewEmisData!$A:$A, "Pickup", NewEmisData!$B:$B, $A10, NewEmisData!$C:$C, $H10, NewEmisData!$D:$D, K$2), SUMIFS(NewEmisData!E:E, NewEmisData!$A:$A, "LDV", NewEmisData!$B:$B, $A10, NewEmisData!$C:$C, $H10, NewEmisData!$D:$D, K$2)) -> 477.08587 | L10: =$I10*IF($G10="Pickup", SUMIFS(NewEmisData!F:F, NewEmisData!$A:$A, "Pickup", NewEmisData!$B:$B, $A10, NewEmisData!$C:$C, $H10, NewEmisData!$D:$D, L$2), SUMIFS(NewEmisData!F:F, NewEmisData!$A:$A, "LDV", NewEmisData!$B:$B, $A10, NewEmisData!$C:$C, $H10, NewEmisData!$D:$D, L$2)) -> 459.34104 | M10: =$I10*IF($G10="Pickup", SUMIFS(NewEmisData!G:G, NewEmisData!$A:$A, "Pickup", NewEmisData!$B:$B, $A10, NewEmisData!$C:$C, $H10, NewEmisData!$D:$D, M$2), SUMIFS(NewEmisData!G:G, NewEmisData!$A:$A, "LDV", NewEmisData!$B:$B, $A10, NewEmisData!$C:$C, $H10, NewEmisData!$D:$D, M$2)) -> 447.45897 | N10: =$I10*IF($G10="Pickup", SUMIFS(NewEmisData!H:H, NewEmisData!$A:$A, "Pickup", NewEmisData!$B:$B, $A10, NewEmisData!$C:$C, $H10, NewEmisData!$D:$D, N$2), SUMIFS(NewEmisData!H:H, NewEmisData!$A:$A, "LDV", NewEmisData!$B:$B, $A10, NewEmisData!$C:$C, $H10, NewEmisData!$D:$D, N$2)) -> 380.72393 | O10: =$I10*IF($G10="Pickup", SUMIFS(NewEmisData!I:I, NewEmisData!$A:$A, "Pickup", NewEmisData!$B:$B, $A10, NewEmisData!$C:$C, $H10, NewEmisData!$D:$D, O$2), SUMIFS(NewEmisData!I:I, NewEmisData!$A:$A, "LDV", NewEmisData!$B:$B, $A10, NewEmisData!$C:$C, $H10, NewEmisData!$D:$D, O$2)) -> 329.54737 | P10: =$I10*IF($G10="Pickup", SUMIFS(NewEmisData!J:J, NewEmisData!$A:$A, "Pickup", NewEmisData!$B:$B, $A10, NewEmisData!$C:$C, $H10, NewEmisData!$D:$D, P$2), SUMIFS(NewEmisData!J:J, NewEmisData!$A:$A, "LDV", NewEmisData!$B:$B, $A10, NewEmisData!$C:$C, $H10, NewEmisData!$D:$D, P$2)) -> 300.6983 | Q10: =$I10*IF($G10="Pickup", SUMIFS(NewEmisData!K:K, NewEmisData!$A:$A, "Pickup", NewEmisData!$B:$B, $A10, NewEmisData!$C:$C, $H10, NewEmisData!$D:$D, Q$2), SUMIFS(NewEmisData!K:K, NewEmisData!$A:$A, "LDV", NewEmisData!$B:$B, $A10, NewEmisData!$C:$C, $H10, NewEmisData!$D:$D, Q$2)) -> 287.838 | R10: =$I10*IF($G10="Pickup", SUMIFS(NewEmisData!L:L, NewEmisData!$A:$A, "Pickup", NewEmisData!$B:$B, $A10, NewEmisData!$C:$C, $H10, NewEmisData!$D:$D, R$2), SUMIFS(NewEmisData!L:L, NewEmisData!$A:$A, "LDV", NewEmisData!$B:$B, $A10, NewEmisData!$C:$C, $H10, NewEmisData!$D:$D, R$2)) -> 283.26611 | S10: =$I10*IF($G10="Pickup", SUMIFS(NewEmisData!M:M, NewEmisData!$A:$A, "Pickup", NewEmisData!$B:$B, $A10, NewEmisData!$C:$C, $H10, NewEmisData!$D:$D, S$2), SUMIFS(NewEmisData!M:M, NewEmisData!$A:$A, "LDV", NewEmisData!$B:$B, $A10, NewEmisData!$C:$C, $H10, NewEmisData!$D:$D, S$2)) -> 281.57834 | T10: =S10 -> 281.57834 | U10: =$I10*IF($G10="Pickup", SUMIFS(NewEmisData!E:E, NewEmisData!$A:$A, "Pickup", NewEmisData!$B:$B, $A10, NewEmisData!$C:$C, $H10, NewEmisData!$D:$D, U$2), SUMIFS(NewEmisData!E:E, NewEmisData!$A:$A, "LDV", NewEmisData!$B:$B, $A10, NewEmisData!$C:$C, $H10, NewEmisData!$D:$D, U$2)) -> 0.82339104 | V10: =$I10*IF($G10="Pickup", SUMIFS(NewEmisData!F:F, NewEmisData!$A:$A, "Pickup", NewEmisData!$B:$B, $A10, NewEmisData!$C:$C, $H10, NewEmisData!$D:$D, V$2), SUMIFS(NewEmisData!F:F, NewEmisData!$A:$A, "LDV", NewEmisData!$B:$B, $A10, NewEmisData!$C:$C, $H10, NewEmisData!$D:$D, V$2)) -> 0.36087273 | W10: =$I10*IF($G10="Pickup", SUMIFS(NewEmisData!G:G, NewEmisData!$A:$A, "Pickup", NewEmisData!$B:$B, $A10, NewEmisData!$C:$C, $H10, NewEmisData!$D:$D, W$2), SUMIFS(NewEmisData!G:G, NewEmisData!$A:$A, "LDV", NewEmisData!$B:$B, $A10, NewEmisData!$C:$C, $H10, NewEmisData!$D:$D, W$2)) -> 0.21658171 | X10: =$I10*IF($G10="Pickup", SUMIFS(NewEmisData!H:H, NewEmisData!$A:$A, "Pickup", NewEmisData!$B:$B, $A10, NewEmisData!$C:$C, $H10, NewEmisData!$D:$D, X$2), SUMIFS(NewEmisData!H:H, NewEmisData!$A:$A, "LDV", NewEmisData!$B:$B, $A10, NewEmisData!$C:$C, $H10, NewEmisData!$D:$D, X$2)) -> 0.14200533 | Y10: =$I10*IF($G10="Pickup", SUMIFS(NewEmisData!I:I, NewEmisData!$A:$A, "Pickup", NewEmisData!$B:$B, $A10, NewEmisData!$C:$C, $H10, NewEmisData!$D:$D, Y$2), SUMIFS(NewEmisData!I:I, NewEmisData!$A:$A, "LDV", NewEmisData!$B:$B, $A10, NewEmisData!$C:$C, $H10, NewEmisData!$D:$D, Y$2)) -> 0.088016805 | Z10: =$I10*IF($G10="Pickup", SUMIFS(NewEmisData!J:J, NewEmisData!$A:$A, "Pickup", NewEmisData!$B:$B, $A10, NewEmisData!$C:$C, $H10, NewEmisData!$D:$D, Z$2), SUMIFS(NewEmisData!J:J, NewEmisData!$A:$A, "LDV", NewEmisData!$B:$B, $A10, NewEmisData!$C:$C, $H10, NewEmisData!$D:$D, Z$2)) -> 0.06573638 | AA10: =$I10*IF($G10="Pickup", SUMIFS(NewEmisData!K:K, NewEmisData!$A:$A, "Pickup", NewEmisData!$B:$B, $A10, NewEmisData!$C:$C, $H10, NewEmisData!$D:$D, AA$2), SUMIFS(NewEmisData!K:K, NewEmisData!$A:$A, "LDV", NewEmisData!$B:$B, $A10, NewEmisData!$C:$C, $H10, NewEmisData!$D:$D, AA$2)) -> 0.056635638 | AB10: =$I10*IF($G10="Pickup", SUMIFS(NewEmisData!L:L, NewEmisData!$A:$A, "Pickup", NewEmisData!$B:$B, $A10, NewEmisData!$C:$C, $H10, NewEmisData!$D:$D, AB$2), SUMIFS(NewEmisData!L:L, NewEmisData!$A:$A, "LDV", NewEmisData!$B:$B, $A10, NewEmisData!$C:$C, $H10, NewEmisData!$D:$D, AB$2)) -> 0.054115247 | AC10: =$I10*IF($G10="Pickup", SUMIFS(NewEmisData!M:M, NewEmisData!$A:$A, "Pickup", NewEmisData!$B:$B, $A10, NewEmisData!$C:$C, $H10, NewEmisData!$D:$D, AC$2), SUMIFS(NewEmisData!M:M, NewEmisData!$A:$A, "LDV", NewEmisData!$B:$B, $A10, NewEmisData!$C:$C, $H10, NewEmisData!$D:$D, AC$2)) -> 0.052826207 | AD10: =AC10 -> 0.052826207 | AE10: =$I10*IF($G10="Pickup", SUMIFS(NewEmisData!E:E, NewEmisData!$A:$A, "Pickup", NewEmisData!$B:$B, $A10, NewEmisData!$C:$C, $H10, NewEmisData!$D:$D, AE$2), SUMIFS(NewEmisData!E:E, NewEmisData!$A:$A, "LDV", NewEmisData!$B:$B, $A10, NewEmisData!$C:$C, $H10, NewEmisData!$D:$D, AE$2)) -> 0.0082552586 | AF10: =$I10*IF($G10="Pickup", SUMIFS(NewEmisData!F:F, NewEmisData!$A:$A, "Pickup", NewEmisData!$B:$B, $A10, NewEmisData!$C:$C, $H10, NewEmisData!$D:$D, AF$2), SUMIFS(NewEmisData!F:F, NewEmisData!$A:$A, "LDV", NewEmisData!$B:$B, $A10, NewEmisData!$C:$C, $H10, NewEmisData!$D:$D, AF$2)) -> 0.0079482132 | AG10: =$I10*IF($G10="Pickup", SUMIFS(NewEmisData!G:G, NewEmisData!$A:$A, "Pickup", NewEmisData!$B:$B, $A10, NewEmisData!$C:$C, $H10, NewEmisData!$D:$D, AG$2), SUMIFS(NewEmisData!G:G, NewEmisData!$A:$A, "LDV", NewEmisData!$B:$B, $A10, NewEmisData!$C:$C, $H10, NewEmisData!$D:$D, AG$2)) -> 0.0064190306 | AH10: =$I10*IF($G10="Pickup", SUMIFS(NewEmisData!H:H, NewEmisData!$A:$A, "Pickup", NewEmisData!$B:$B, $A10, NewEmisData!$C:$C, $H10, NewEmisData!$D:$D, AH$2), SUMIFS(NewEmisData!H:H, NewEmisData!$A:$A, "LDV", NewEmisData!$B:$B, $A10, NewEmisData!$C:$C, $H10, NewEmisData!$D:$D, AH$2)) -> 0.0054616828 | AI10: =$I10*IF($G10="Pickup", SUMIFS(NewEmisData!I:I, NewEmisData!$A:$A, "Pickup", NewEmisData!$B:$B, $A10, NewEmisData!$C:$C, $H10, NewEmisData!$D:$D, AI$2), SUMIFS(NewEmisData!I:I, NewEmisData!$A:$A, "LDV", NewEmisData!$B:$B, $A10, NewEmisData!$C:$C, $H10, NewEmisData!$D:$D, AI$2)) -> 0.0047275286 | AJ10: =$I10*IF($G10="Pickup", SUMIFS(NewEmisData!J:J, NewEmisData!$A:$A, "Pickup", NewEmisData!$B:$B, $A10, NewEmisData!$C:$C, $H10, NewEmisData!$D:$D, AJ$2), SUMIFS(NewEmisData!J:J, NewEmisData!$A:$A, "LDV", NewEmisData!$B:$B, $A10, NewEmisData!$C:$C, $H10, NewEmisData!$D:$D, AJ$2)) -> 0.0043136735 | AK10: =$I10*IF($G10="Pickup", SUMIFS(NewEmisData!K:K, NewEmisData!$A:$A, "Pickup", NewEmisData!$B:$B, $A10, NewEmisData!$C:$C, $H10, NewEmisData!$D:$D, AK$2), SUMIFS(NewEmisData!K:K, NewEmisData!$A:$A, "LDV", NewEmisData!$B:$B, $A10, NewEmisData!$C:$C, $H10, NewEmisData!$D:$D, AK$2)) -> 0.0041291858 | AL10: =$I10*IF($G10="Pickup", SUMIFS(NewEmisData!L:L, NewEmisData!$A:$A, "Pickup", NewEmisData!$B:$B, $A10, NewEmisData!$C:$C, $H10, NewEmisData!$D:$D, AL$2), SUMIFS(NewEmisData!L:L, NewEmisData!$A:$A, "LDV", NewEmisData!$B:$B, $A10, NewEmisData!$C:$C, $H10, NewEmisData!$D:$D, AL$2)) -> 0.0040635984 | AM10: =$I10*IF($G10="Pickup", SUMIFS(NewEmisData!M:M, NewEmisData!$A:$A, "Pickup", NewEmisData!$B:$B, $A10, NewEmisData!$C:$C, $H10, NewEmisData!$D:$D, AM$2), SUMIFS(NewEmisData!M:M, NewEmisData!$A:$A, "LDV", NewEmisData!$B:$B, $A10, NewEmisData!$C:$C, $H10, NewEmisData!$D:$D, AM$2)) -> 0.0040393864 | AN10: =AM10 -> 0.0040393864 | AO10: =$I10*IF($G10="Pickup", SUMIFS(NewEmisData!E:E, NewEmisData!$A:$A, "Pickup", NewEmisData!$B:$B, $A10, NewEmisData!$C:$C, $H10, NewEmisData!$D:$D, AO$2), SUMIFS(NewEmisData!E:E, NewEmisData!$A:$A, "LDV", NewEmisData!$B:$B, $A10, NewEmisData!$C:$C, $H10, NewEmisData!$D:$D, AO$2)) -> 0.081828644 | AP10: =$I10*IF($G10="Pickup", SUMIFS(NewEmisData!F:F, NewEmisData!$A:$A, "Pickup", NewEmisData!$B:$B, $A10, NewEmisData!$C:$C, $H10, NewEmisData!$D:$D, AP$2), SUMIFS(NewEmisData!F:F, NewEmisData!$A:$A, "LDV", NewEmisData!$B:$B, $A10, NewEmisData!$C:$C, $H10, NewEmisData!$D:$D, AP$2)) -> 0.076175839 | AQ10: =$I10*IF($G10="Pickup", SUMIFS(NewEmisData!G:G, NewEmisData!$A:$A, "Pickup", NewEmisData!$B:$B, $A10, NewEmisData!$C:$C, $H10, NewEmisData!$D:$D, AQ$2), SUMIFS(NewEmisData!G:G, NewEmisData!$A:$A, "LDV", NewEmisData!$B:$B, $A10, NewEmisData!$C:$C, $H10, NewEmisData!$D:$D, AQ$2)) -> 0.081302809 | AR10: =$I10*IF($G10="Pickup", SUMIFS(NewEmisData!H:H, NewEmisData!$A:$A, "Pickup", NewEmisData!$B:$B, $A10, NewEmisData!$C:$C, $H10, NewEmisData!$D:$D, AR$2), SUMIFS(NewEmisData!H:H, NewEmisData!$A:$A, "LDV", NewEmisData!$B:$B, $A10, NewEmisData!$C:$C, $H10, NewEmisData!$D:$D, AR$2)) -> 0.079561689 | AS10: =$I10*IF($G10="Pickup", SUMIFS(NewEmisData!I:I, NewEmisData!$A:$A, "Pickup", NewEmisData!$B:$B, $A10, NewEmisData!$C:$C, $H10, NewEmisData!$D:$D, AS$2), SUMIFS(NewEmisData!I:I, NewEmisData!$A:$A, "LDV", NewEmisData!$B:$B, $A10, NewEmisData!$C:$C, $H10, NewEmisData!$D:$D, AS$2)) -> 0.07791053 | AT10: =$I10*IF($G10="Pickup", SUMIFS(NewEmisData!J:J, NewEmisData!$A:$A, "Pickup", NewEmisData!$B:$B, $A10, NewEmisData!$C:$C, $H10, NewEmisData!$D:$D, AT$2), SUMIFS(NewEmisData!J:J, NewEmisData!$A:$A, "LDV", NewEmisData!$B:$B, $A10, NewEmisData!$C:$C, $H10, NewEmisData!$D:$D, AT$2)) -> 0.076590334 | AU10: =$I10*IF($G10="Pickup", SUMIFS(NewEmisData!K:K, NewEmisData!$A:$A, "Pickup", NewEmisData!$B:$B, $A10, NewEmisData!$C:$C, $H10, NewEmisData!$D:$D, AU$2), SUMIFS(NewEmisData!K:K, NewEmisData!$A:$A, "LDV", NewEmisData!$B:$B, $A10, NewEmisData!$C:$C, $H10, NewEmisData!$D:$D, AU$2)) -> 0.075767939 | AV10: =$I10*IF($G10="Pickup", SUMIFS(NewEmisData!L:L, NewEmisData!$A:$A, "Pickup", NewEmisData!$B:$B, $A10, NewEmisData!$C:$C, $H10, NewEmisData!$D:$D, AV$2), SUMIFS(NewEmisData!L:L, NewEmisData!$A:$A, "LDV", NewEmisData!$B:$B, $A10, NewEmisData!$C:$C, $H10, NewEmisData!$D:$D, AV$2)) -> 0.07535371 | AW10: =$I10*IF($G10="Pickup", SUMIFS(NewEmisData!M:M, NewEmisData!$A:$A, "Pickup", NewEmisData!$B:$B, $A10, NewEmisData!$C:$C, $H10, NewEmisData!$D:$D, AW$2), SUMIFS(NewEmisData!M:M, NewEmisData!$A:$A, "LDV", NewEmisData!$B:$B, $A10, NewEmisData!$C:$C, $H10, NewEmisData!$D:$D, AW$2)) -> 0.075117977 | AX10: =AW10 -> 0.075117977 | AY10: =$I10*IF($G10="Pickup", SUMIFS(NewEmisData!E:E, NewEmisData!$A:$A, "Pickup", NewEmisData!$B:$B, $A10, NewEmisData!$C:$C, $H10, NewEmisData!$D:$D, AY$2), SUMIFS(NewEmisData!E:E, NewEmisData!$A:$A, "LDV", NewEmisData!$B:$B, $A10, NewEmisData!$C:$C, $H10, NewEmisData!$D:$D, AY$2)) -> 0.021998194 | AZ10: =$I10*IF($G10="Pickup", SUMIFS(NewEmisData!F:F, NewEmisData!$A:$A, "Pickup", NewEmisData!$B:$B, $A10, NewEmisData!$C:$C, $H10, NewEmisData!$D:$D, AZ$2), SUMIFS(NewEmisData!F:F, NewEmisData!$A:$A, "LDV", NewEmisData!$B:$B, $A10, NewEmisData!$C:$C, $H10, NewEmisData!$D:$D, AZ$2)) -> 0.016997575 | BA10: =$I10*IF($G10="Pickup", SUMIFS(NewEmisData!G:G, NewEmisData!$A:$A, "Pickup", NewEmisData!$B:$B, $A10, NewEmisData!$C:$C, $H10, NewEmisData!$D:$D, BA$2), SUMIFS(NewEmisData!G:G, NewEmisData!$A:$A, "LDV", NewEmisData!$B:$B, $A10, NewEmisData!$C:$C, $H10, NewEmisData!$D:$D, BA$2)) -> 0.016580879 | BB10: =$I10*IF($G10="Pickup", SUMIFS(NewEmisData!H:H, NewEmisData!$A:$A, "Pickup", NewEmisData!$B:$B, $A10, NewEmisData!$C:$C, $H10, NewEmisData!$D:$D, BB$2), SUMIFS(NewEmisData!H:H, NewEmisData!$A:$A, "LDV", NewEmisData!$B:$B, $A10, NewEmisData!$C:$C, $H10, NewEmisData!$D:$D, BB$2)) -> 0.015040645 | BC10: =$I10*IF($G10="Pickup", SUMIFS(NewEmisData!I:I, NewEmisData!$A:$A, "Pickup", NewEmisData!$B:$B, $A10, NewEmisData!$C:$C, $H10, NewEmisData!$D:$D, BC$2), SUMIFS(NewEmisData!I:I, NewEmisData!$A:$A, "LDV", NewEmisData!$B:$B, $A10, NewEmisData!$C:$C, $H10, NewEmisData!$D:$D, BC$2)) -> 0.013579961 | BD10: =$I10*IF($G10="Pickup", SUMIFS(NewEmisData!J:J, NewEmisData!$A:$A, "Pickup", NewEmisData!$B:$B, $A10, NewEmisData!$C:$C, $H10, NewEmisData!$D:$D, BD$2), SUMIFS(NewEmisData!J:J, NewEmisData!$A:$A, "LDV", NewEmisData!$B:$B, $A10, NewEmisData!$C:$C, $H10, NewEmisData!$D:$D, BD$2)) -> 0.012412067 | BE10: =$I10*IF($G10="Pickup", SUMIFS(NewEmisData!K:K, NewEmisData!$A:$A, "Pickup", NewEmisData!$B:$B, $A10, NewEmisData!$C:$C, $H10, NewEmisData!$D:$D, BE$2), SUMIFS(NewEmisData!K:K, NewEmisData!$A:$A, "LDV", NewEmisData!$B:$B, $A10, NewEmisData!$C:$C, $H10, NewEmisData!$D:$D, BE$2)) -> 0.011684507 | BF10: =$I10*IF($G10="Pickup", SUMIFS(NewEmisData!L:L, NewEmisData!$A:$A, "Pickup", NewEmisData!$B:$B, $A10, NewEmisData!$C:$C, $H10, NewEmisData!$D:$D, BF$2), SUMIFS(NewEmisData!L:L, NewEmisData!$A:$A, "LDV", NewEmisData!$B:$B, $A10, NewEmisData!$C:$C, $H10, NewEmisData!$D:$D, BF$2)) -> 0.011318096 | BG10: =$I10*IF($G10="Pickup", SUMIFS(NewEmisData!M:M, NewEmisData!$A:$A, "Pickup", NewEmisData!$B:$B, $A10, NewEmisData!$C:$C, $H10, NewEmisData!$D:$D, BG$2), SUMIFS(NewEmisData!M:M, NewEmisData!$A:$A, "LDV", NewEmisData!$B:$B, $A10, NewEmisData!$C:$C, $H10, NewEmisData!$D:$D, BG$2)) -> 0.011109457 | BH10: =BG10 -> 0.011109457 | BI10: =$I10*IF($G10="Pickup", SUMIFS(NewEmisData!E:E, NewEmisData!$A:$A, "Pickup", NewEmisData!$B:$B, $A10, NewEmisData!$C:$C, $H10, NewEmisData!$D:$D, BI$2), SUMIFS(NewEmisData!E:E, NewEmisData!$A:$A, "LDV", NewEmisData!$B:$B, $A10, NewEmisData!$C:$C, $H10, NewEmisData!$D:$D, BI$2)) -> 6.633983 | BJ10: =$I10*IF($G10="Pickup", SUMIFS(NewEmisData!F:F, NewEmisData!$A:$A, "Pickup", NewEmisData!$B:$B, $A10, NewEmisData!$C:$C, $H10, NewEmisData!$D:$D, BJ$2), SUMIFS(NewEmisData!F:F, NewEmisData!$A:$A, "LDV", NewEmisData!$B:$B, $A10, NewEmisData!$C:$C, $H10, NewEmisData!$D:$D, BJ$2)) -> 3.9206206 | BK10: =$I10*IF($G10="Pickup", SUMIFS(NewEmisData!G:G, NewEmisData!$A:$A, "Pickup", NewEmisData!$B:$B, $A10, NewEmisData!$C:$C, $H10, NewEmisData!$D:$D, BK$2), SUMIFS(NewEmisData!G:G, NewEmisData!$A:$A, "LDV", NewEmisData!$B:$B, $A10, NewEmisData!$C:$C, $H10, NewEmisData!$D:$D, BK$2)) -> 3.0174466 | BL10: =$I10*IF($G10="Pickup", SUMIFS(NewEmisData!H:H, NewEmisData!$A:$A, "Pickup", NewEmisData!$B:$B, $A10, NewEmisData!$C:$C, $H10, NewEmisData!$D:$D, BL$2), SUMIFS(NewEmisData!H:H, NewEmisData!$A:$A, "LDV", NewEmisData!$B:$B, $A10, NewEmisData!$C:$C, $H10, NewEmisData!$D:$D, BL$2)) -> 2.3529222 | BM10: =$I10*IF($G10="Pickup", SUMIFS(NewEmisData!I:I, NewEmisData!$A:$A, "Pickup", NewEmisData!$B:$B, $A10, NewEmisData!$C:$C, $H10, NewEmisData!$D:$D, BM$2), SUMIFS(NewEmisData!I:I, NewEmisData!$A:$A, "LDV", NewEmisData!$B:$B, $A10, NewEmisData!$C:$C, $H10, NewEmisData!$D:$D, BM$2)) -> 1.7038406 | BN10: =$I10*IF($G10="Pickup", SUMIFS(NewEmisData!J:J, NewEmisData!$A:$A, "Pickup", NewEmisData!$B:$B, $A10, NewEmisData!$C:$C, $H10, NewEmisData!$D:$D, BN$2), SUMIFS(NewEmisData!J:J, NewEmisData!$A:$A, "LDV", NewEmisData!$B:$B, $A10, NewEmisData!$C:$C, $H10, NewEmisData!$D:$D, BN$2)) -> 1.3463731 | BO10: =$I10*IF($G10="Pickup", SUMIFS(NewEmisData!K:K, NewEmisData!$A:$A, "Pickup", NewEmisData!$B:$B, $A10, NewEmisData!$C:$C, $H10, NewEmisData!$D:$D, BO$2), SUMIFS(NewEmisData!K:K, NewEmisData!$A:$A, "LDV", NewEmisData!$B:$B, $A10, NewEmisData!$C:$C, $H10, NewEmisData!$D:$D, BO$2)) -> 1.1858347 | BP10: =$I10*IF($G10="Pickup", SUMIFS(NewEmisData!L:L, NewEmisData!$A:$A, "Pickup", NewEmisData!$B:$B, $A10, NewEmisData!$C:$C, $H10, NewEmisData!$D:$D, BP$2), SUMIFS(NewEmisData!L:L, NewEmisData!$A:$A, "LDV", NewEmisData!$B:$B, $A10, NewEmisData!$C:$C, $H10, NewEmisData!$D:$D, BP$2)) -> 1.1335062 | BQ10: =$I10*IF($G10="Pickup", SUMIFS(NewEmisData!M:M, NewEmisData!$A:$A, "Pickup", NewEmisData!$B:$B, $A10, NewEmisData!$C:$C, $H10, NewEmisData!$D:$D, BQ$2), SUMIFS(NewEmisData!M:M, NewEmisData!$A:$A, "LDV", NewEmisData!$B:$B, $A10, NewEmisData!$C:$C, $H10, NewEmisData!$D:$D, BQ$2)) -> 1.1009029 | BR10: =BQ10 -> 1.1009029 | BS10: =$I10*IF($G10="Pickup", SUMIFS(NewEmisData!E:E, NewEmisData!$A:$A, "Pickup", NewEmisData!$B:$B, $A10, NewEmisData!$C:$C, $H10, NewEmisData!$D:$D, BS$2), SUMIFS(NewEmisData!E:E, NewEmisData!$A:$A, "LDV", NewEmisData!$B:$B, $A10, NewEmisData!$C:$C, $H10, NewEmisData!$D:$D, BS$2)) -> 0.77473151 | BT10: =$I10*IF($G10="Pickup", SUMIFS(NewEmisData!F:F, NewEmisData!$A:$A, "Pickup", NewEmisData!$B:$B, $A10, NewEmisData!$C:$C, $H10, NewEmisData!$D:$D, BT$2), SUMIFS(NewEmisData!F:F, NewEmisData!$A:$A, "LDV", NewEmisData!$B:$B, $A10, NewEmisData!$C:$C, $H10, NewEmisData!$D:$D, BT$2)) -> 0.41904908 | BU10: =$I10*IF($G10="Pickup", SUMIFS(NewEmisData!G:G, NewEmisData!$A:$A, "Pickup", NewEmisData!$B:$B, $A10, NewEmisData!$C:$C, $H10, NewEmisData!$D:$D, BU$2), SUMIFS(NewEmisData!G:G, NewEmisData!$A:$A, "LDV", NewEmisData!$B:$B, $A10, NewEmisData!$C:$C, $H10, NewEmisData!$D:$D, BU$2)) -> 0.309829 | BV10: =$I10*IF($G10="Pickup", SUMIFS(NewEmisData!H:H, NewEmisData!$A:$A, "Pickup", NewEmisData!$B:$B, $A10, NewEmisData!$C:$C, $H10, NewEmisData!$D:$D, BV$2), SUMIFS(NewEmisData!H:H, NewEmisData!$A:$A, "LDV", NewEmisData!$B:$B, $A10, NewEmisData!$C:$C, $H10, NewEmisData!$D:$D, BV$2)) -> 0.25046259 | BW10: =$I10*IF($G10="Pickup", SUMIFS(NewEmisData!I:I, NewEmisData!$A:$A, "Pickup", NewEmisData!$B:$B, $A10, NewEmisData!$C:$C, $H10, NewEmisData!$D:$D, BW$2), SUMIFS(NewEmisData!I:I, NewEmisData!$A:$A, "LDV", NewEmisData!$B:$B, $A10, NewEmisData!$C:$C, $H10, NewEmisData!$D:$D, BW$2)) -> 0.18616224 | BX10: =$I10*IF($G10="Pickup", SUMIFS(NewEmisData!J:J, NewEmisData!$A:$A, "Pickup", NewEmisData!$B:$B, $A10, NewEmisData!$C:$C, $H10, NewEmisData!$D:$D, BX$2), SUMIFS(NewEmisData!J:J, NewEmisData!$A:$A, "LDV", NewEmisData!$B:$B, $A10, NewEmisData!$C:$C, $H10, NewEmisData!$D:$D, BX$2)) -> 0.15683047 | BY10: =$I10*IF($G10="Pickup", SUMIFS(NewEmisData!K:K, NewEmisData!$A:$A, "Pickup", NewEmisData!$B:$B, $A10, NewEmisData!$C:$C, $H10, NewEmisData!$D:$D, BY$2), SUMIFS(NewEmisData!K:K, NewEmisData!$A:$A, "LDV", NewEmisData!$B:$B, $A10, NewEmisData!$C:$C, $H10, NewEmisData!$D:$D, BY$2)) -> 0.14094 | BZ10: =$I10*IF($G10="Pickup", SUMIFS(NewEmisData!L:L, NewEmisData!$A:$A, "Pickup", NewEmisData!$B:$B, $A10, NewEmisData!$C:$C, $H10, NewEmisData!$D:$D, BZ$2), SUMIFS(NewEmisData!L:L, NewEmisData!$A:$A, "LDV", NewEmisData!$B:$B, $A10, NewEmisData!$C:$C, $H10, NewEmisData!$D:$D, BZ$2)) -> 0.13477407 | CA10: =$I10*IF($G10="Pickup", SUMIFS(NewEmisData!M:M, NewEmisData!$A:$A, "Pickup", NewEmisData!$B:$B, $A10, NewEmisData!$C:$C, $H10, NewEmisData!$D:$D, CA$2), SUMIFS(NewEmisData!M:M, NewEmisData!$A:$A, "LDV", NewEmisData!$B:$B, $A10, NewEmisData!$C:$C, $H10, NewEmisData!$D:$D, CA$2)) -> 0.12984033 | CB10: =CA10 -> 0.12984033 | CC10: =$I10*IF($G10="Pickup", SUMIFS(NewEmisData!E:E, NewEmisData!$A:$A, "Pickup", NewEmisData!$B:$B, $A10, NewEmisData!$C:$C, $H10, NewEmisData!$D:$D, CC$2), SUMIFS(NewEmisData!E:E, NewEmisData!$A:$A, "LDV", NewEmisData!$B:$B, $A10, NewEmisData!$C:$C, $H10, NewEmisData!$D:$D, CC$2)) -> 0.045278925 | CD10: =$I10*IF($G10="Pickup", SUMIFS(NewEmisData!F:F, NewEmisData!$A:$A, "Pickup", NewEmisData!$B:$B, $A10, NewEmisData!$C:$C, $H10, NewEmisData!$D:$D, CD$2), SUMIFS(NewEmisData!F:F, NewEmisData!$A:$A, "LDV", NewEmisData!$B:$B, $A10, NewEmisData!$C:$C, $H10, NewEmisData!$D:$D, CD$2)) -> 0.030659932 | CE10: =$I10*IF($G10="Pickup", SUMIFS(NewEmisData!G:G, NewEmisData!$A:$A, "Pickup", NewEmisData!$B:$B, $A10, NewEmisData!$C:$C, $H10, NewEmisData!$D:$D, CE$2), SUMIFS(NewEmisData!G:G, NewEmisData!$A:$A, "LDV", NewEmisData!$B:$B, $A10, NewEmisData!$C:$C, $H10, NewEmisData!$D:$D, CE$2)) -> 0.028386595 | CF10: =$I10*IF($G10="Pickup", SUMIFS(NewEmisData!H:H, NewEmisData!$A:$A, "Pickup", NewEmisData!$B:$B, $A10, NewEmisData!$C:$C, $H10, NewEmisData!$D:$D, CF$2), SUMIFS(NewEmisData!H:H, NewEmisData!$A:$A, "LDV", NewEmisData!$B:$B, $A10, NewEmisData!$C:$C, $H10, NewEmisData!$D:$D, CF$2)) -> 0.027093413 | CG10: =$I10*IF($G10="Pickup", SUMIFS(NewEmisData!I:I, NewEmisData!$A:$A, "Pickup", NewEmisData!$B:$B, $A10, NewEmisData!$C:$C, $H10, NewEmisData!$D:$D, CG$2), SUMIFS(NewEmisData!I:I, NewEmisData!$A:$A, "LDV", NewEmisData!$B:$B, $A10, NewEmisData!$C:$C, $H10, NewEmisData!$D:$D, CG$2)) -> 0.026239575 | CH10: =$I10*IF($G10="Pickup", SUMIFS(NewEmisData!J:J, NewEmisData!$A:$A, "Pickup", NewEmisData!$B:$B, $A10, NewEmisData!$C:$C, $H10, NewEmisData!$D:$D, CH$2), SUMIFS(NewEmisData!J:J, NewEmisData!$A:$A, "LDV", NewEmisData!$B:$B, $A10, NewEmisData!$C:$C, $H10, NewEmisData!$D:$D, CH$2)) -> 0.025564245 | CI10: =$I10*IF($G10="Pickup", SUMIFS(NewEmisData!K:K, NewEmisData!$A:$A, "Pickup", NewEmisData!$B:$B, $A10, NewEmisData!$C:$C, $H10, NewEmisData!$D:$D, CI$2), SUMIFS(NewEmisData!K:K, NewEmisData!$A:$A, "LDV", NewEmisData!$B:$B, $A10, NewEmisData!$C:$C, $H10, NewEmisData!$D:$D, CI$2)) -> 0.025562136 | CJ10: =$I10*IF($G10="Pickup", SUMIFS(NewEmisData!L:L, NewEmisData!$A:$A, "Pickup", NewEmisData!$B:$B, $A10, NewEmisData!$C:$C, $H10, NewEmisData!$D:$D, CJ$2), SUMIFS(NewEmisData!L:L, NewEmisData!$A:$A, "LDV", NewEmisData!$B:$B, $A10, NewEmisData!$C:$C, $H10, NewEmisData!$D:$D, CJ$2)) -> 0.02556154 | CK10: =$I10*IF($G10="Pickup", SUMIFS(NewEmisData!M:M, NewEmisData!$A:$A, "Pickup", NewEmisData!$B:$B, $A10, NewEmisData!$C:$C, $H10, NewEmisData!$D:$D, CK$2), SUMIFS(NewEmisData!M:M, NewEmisData!$A:$A, "LDV", NewEmisData!$B:$B, $A10, NewEmisData!$C:$C, $H10, NewEmisData!$D:$D, CK$2)) -> 0.025560994 | CL10: =CK10 -> 0.025560994 | CM10: =$I10*IF($G10="Pickup", SUMIFS(NewEmisData!E:E, NewEmisData!$A:$A, "Pickup", NewEmisData!$B:$B, $A10, NewEmisData!$C:$C, $H10, NewEmisData!$D:$D, CM$2), SUMIFS(NewEmisData!E:E, NewEmisData!$A:$A, "LDV", NewEmisData!$B:$B, $A10, NewEmisData!$C:$C, $H10, NewEmisData!$D:$D, CM$2)) -> 0.022616228 | CN10: =$I10*IF($G10="Pickup", SUMIFS(NewEmisData!F:F, NewEmisData!$A:$A, "Pickup", NewEmisData!$B:$B, $A10, NewEmisData!$C:$C, $H10, NewEmisData!$D:$D, CN$2), SUMIFS(NewEmisData!F:F, NewEmisData!$A:$A, "LDV", NewEmisData!$B:$B, $A10, NewEmisData!$C:$C, $H10, NewEmisData!$D:$D, CN$2)) -> 0.013703994 | CO10: =$I10*IF($G10="Pickup", SUMIFS(NewEmisData!G:G, NewEmisData!$A:$A, "Pickup", NewEmisData!$B:$B, $A10, NewEmisData!$C:$C, $H10, NewEmisData!$D:$D, CO$2), SUMIFS(NewEmisData!G:G, NewEmisData!$A:$A, "LDV", NewEmisData!$B:$B, $A10, NewEmisData!$C:$C, $H10, NewEmisData!$D:$D, CO$2)) -> 0.011127954 | CP10: =$I10*IF($G10="Pickup", SUMIFS(NewEmisData!H:H, NewEmisData!$A:$A, "Pickup", NewEmisData!$B:$B, $A10, NewEmisData!$C:$C, $H10, NewEmisData!$D:$D, CP$2), SUMIFS(NewEmisData!H:H, NewEmisData!$A:$A, "LDV", NewEmisData!$B:$B, $A10, NewEmisData!$C:$C, $H10, NewEmisData!$D:$D, CP$2)) -> 0.0091642249 | CQ10: =$I10*IF($G10="Pickup", SUMIFS(NewEmisData!I:I, NewEmisData!$A:$A, "Pickup", NewEmisData!$B:$B, $A10, NewEmisData!$C:$C, $H10, NewEmisData!$D:$D, CQ$2), SUMIFS(NewEmisData!I:I, NewEmisData!$A:$A, "LDV", NewEmisData!$B:$B, $A10, NewEmisData!$C:$C, $H10, NewEmisData!$D:$D, CQ$2)) -> 0.0082157407 | CR10: =$I10*IF($G10="Pickup", SUMIFS(NewEmisData!J:J, NewEmisData!$A:$A, "Pickup", NewEmisData!$B:$B, $A10, NewEmisData!$C:$C, $H10, NewEmisData!$D:$D, CR$2), SUMIFS(NewEmisData!J:J, NewEmisData!$A:$A, "LDV", NewEmisData!$B:$B, $A10, NewEmisData!$C:$C, $H10, NewEmisData!$D:$D, CR$2)) -> 0.0078051703 | CS10: =$I10*IF($G10="Pickup", SUMIFS(NewEmisData!K:K, NewEmisData!$A:$A, "Pickup", NewEmisData!$B:$B, $A10, NewEmisData!$C:$C, $H10, NewEmisData!$D:$D, CS$2), SUMIFS(NewEmisData!K:K, NewEmisData!$A:$A, "LDV", NewEmisData!$B:$B, $A10, NewEmisData!$C:$C, $H10, NewEmisData!$D:$D, CS$2)) -> 0.0077607553 | CT10: =$I10*IF($G10="Pickup", SUMIFS(NewEmisData!L:L, NewEmisData!$A:$A, "Pickup", NewEmisData!$B:$B, $A10, NewEmisData!$C:$C, $H10, NewEmisData!$D:$D, CT$2), SUMIFS(NewEmisData!L:L, NewEmisData!$A:$A, "LDV", NewEmisData!$B:$B, $A10, NewEmisData!$C:$C, $H10, NewEmisData!$D:$D, CT$2)) -> 0.0076883349 | CU10: =$I10*IF($G10="Pickup", SUMIFS(NewEmisData!M:M, NewEmisData!$A:$A, "Pickup", NewEmisData!$B:$B, $A10, NewEmisData!$C:$C, $H10, NewEmisData!$D:$D, CU$2), SUMIFS(NewEmisData!M:M, NewEmisData!$A:$A, "LDV", NewEmisData!$B:$B, $A10, NewEmisData!$C:$C, $H10, NewEmisData!$D:$D, CU$2)) -> 0.0076878848 | CV10: =CU10 -> 0.0076878848 | CW10: 0.0030448047 | CX10: 0.0018865909 | CY10: 0.0015570268 | CZ10: 0.0012432183 | DA10: 0.00092522519 | DB10: 0.00072309457 | DC10: 0.00068940707 | DD10: 0.00068441484 | DE10: 0.00068634617 | DF10: 0.00068634617 | DG10: =$I10*IF($G10="Pickup", SUMIFS(NewEmisData!E:E, NewEmisData!$A:$A, "Pickup", NewEmisData!$B:$B, $A10, NewEmisData!$C:$C, $H10, NewEmisData!$D:$D, DG$2), SUMIFS(NewEmisData!E:E, NewEmisData!$A:$A, "LDV", NewEmisData!$B:$B, $A10, NewEmisData!$C:$C, $H10, NewEmisData!$D:$D, DG$2)) -> 0 | DH10: =$I10*IF($G10="Pickup", SUMIFS(NewEmisData!F:F, NewEmisData!$A:$A, "Pickup", NewEmisData!$B:$B, $A10, NewEmisData!$C:$C, $H10, NewEmisData!$D:$D, DH$2), SUMIFS(NewEmisData!F:F, NewEmisData!$A:$A, "LDV", NewEmisData!$B:$B, $A10, NewEmisData!$C:$C, $H10, NewEmisData!$D:$D, DH$2)) -> 0 | DI10: =$I10*IF($G10="Pickup", SUMIFS(NewEmisData!G:G, NewEmisData!$A:$A, "Pickup", NewEmisData!$B:$B, $A10, NewEmisData!$C:$C, $H10, NewEmisData!$D:$D, DI$2), SUMIFS(NewEmisData!G:G, NewEmisData!$A:$A, "LDV", NewEmisData!$B:$B, $A10, NewEmisData!$C:$C, $H10, NewEmisData!$D:$D, DI$2)) -> 0 | DJ10: =$I10*IF($G10="Pickup", SUMIFS(NewEmisData!H:H, NewEmisData!$A:$A, "Pickup", NewEmisData!$B:$B, $A10, NewEmisData!$C:$C, $H10, NewEmisData!$D:$D, DJ$2), SUMIFS(NewEmisData!H:H, NewEmisData!$A:$A, "LDV", NewEmisData!$B:$B, $A10, NewEmisData!$C:$C, $H10, NewEmisData!$D:$D, DJ$2)) -> 0 | DK10: =$I10*IF($G10="Pickup", SUMIFS(NewEmisData!I:I, NewEmisData!$A:$A, "Pickup", NewEmisData!$B:$B, $A10, NewEmisData!$C:$C, $H10, NewEmisData!$D:$D, DK$2), SUMIFS(NewEmisData!I:I, NewEmisData!$A:$A, "LDV", NewEmisData!$B:$B, $A10, NewEmisData!$C:$C, $H10, NewEmisData!$D:$D, DK$2)) -> 0 | DL10: =$I10*IF($G10="Pickup", SUMIFS(NewEmisData!J:J, NewEmisData!$A:$A, "Pickup", NewEmisData!$B:$B, $A10, NewEmisData!$C:$C, $H10, NewEmisData!$D:$D, DL$2), SUMIFS(NewEmisData!J:J, NewEmisData!$A:$A, "LDV", NewEmisData!$B:$B, $A10, NewEmisData!$C:$C, $H10, NewEmisData!$D:$D, DL$2)) -> 0 | DM10: =$I10*IF($G10="Pickup", SUMIFS(NewEmisData!K:K, NewEmisData!$A:$A, "Pickup", NewEmisData!$B:$B, $A10, NewEmisData!$C:$C, $H10, NewEmisData!$D:$D, DM$2), SUMIFS(NewEmisData!K:K, NewEmisData!$A:$A, "LDV", NewEmisData!$B:$B, $A10, NewEmisData!$C:$C, $H10, NewEmisData!$D:$D, DM$2)) -> 0 | DN10: =$I10*IF($G10="Pickup", SUMIFS(NewEmisData!L:L, NewEmisData!$A:$A, "Pickup", NewEmisData!$B:$B, $A10, NewEmisData!$C:$C, $H10, NewEmisData!$D:$D, DN$2), SUMIFS(NewEmisData!L:L, NewEmisData!$A:$A, "LDV", NewEmisData!$B:$B, $A10, NewEmisData!$C:$C, $H10, NewEmisData!$D:$D, DN$2)) -> 0 | DO10: =$I10*IF($G10="Pickup", SUMIFS(NewEmisData!M:M, NewEmisData!$A:$A, "Pickup", NewEmisData!$B:$B, $A10, NewEmisData!$C:$C, $H10, NewEmisData!$D:$D, DO$2), SUMIFS(NewEmisData!M:M, NewEmisData!$A:$A, "LDV", NewEmisData!$B:$B, $A10, NewEmisData!$C:$C, $H10, NewEmisData!$D:$D, DO$2)) -> 0 | DP10: =DO10 -> 0 | DQ10: =$I10*IF($G10="Pickup", SUMIFS(NewEmisData!E:E, NewEmisData!$A:$A, "Pickup", NewEmisData!$B:$B, $A10, NewEmisData!$C:$C, $H10, NewEmisData!$D:$D, DQ$2), SUMIFS(NewEmisData!E:E, NewEmisData!$A:$A, "LDV", NewEmisData!$B:$B, $A10, NewEmisData!$C:$C, $H10, NewEmisData!$D:$D, DQ$2)) -> 0.01533373 | DR10: =$I10*IF($G10="Pickup", SUMIFS(NewEmisData!F:F, NewEmisData!$A:$A, "Pickup", NewEmisData!$B:$B, $A10, NewEmisData!$C:$C, $H10, NewEmisData!$D:$D, DR$2), SUMIFS(NewEmisData!F:F, NewEmisData!$A:$A, "LDV", NewEmisData!$B:$B, $A10, NewEmisData!$C:$C, $H10, NewEmisData!$D:$D, DR$2)) -> 0.00857914 | DS10: =$I10*IF($G10="Pickup", SUMIFS(NewEmisData!G:G, NewEmisData!$A:$A, "Pickup", NewEmisData!$B:$B, $A10, NewEmisData!$C:$C, $H10, NewEmisData!$D:$D, DS$2), SUMIFS(NewEmisData!G:G, NewEmisData!$A:$A, "LDV", NewEmisData!$B:$B, $A10, NewEmisData!$C:$C, $H10, NewEmisData!$D:$D, DS$2)) -> 0.0068261405 | DT10: =$I10*IF($G10="Pickup", SUMIFS(NewEmisData!H:H, NewEmisData!$A:$A, "Pickup", NewEmisData!$B:$B, $A10, NewEmisData!$C:$C, $H10, NewEmisData!$D:$D, DT$2), SUMIFS(NewEmisData!H:H, NewEmisData!$A:$A, "LDV", NewEmisData!$B:$B, $A10, NewEmisData!$C:$C, $H10, NewEmisData!$D:$D, DT$2)) -> 0.005230609 | DU10: =$I10*IF($G10="Pickup", SUMIFS(NewEmisData!I:I, NewEmisData!$A:$A, "Pickup", NewEmisData!$B:$B, $A10, NewEmisData!$C:$C, $H10, NewEmisData!$D:$D, DU$2), SUMIFS(NewEmisData!I:I, NewEmisData!$A:$A, "LDV", NewEmisData!$B:$B, $A10, NewEmisData!$C:$C, $H10, NewEmisData!$D:$D, DU$2)) -> 0.0040991034 | DV10: =$I10*IF($G10="Pickup", SUMIFS(NewEmisData!J:J, NewEmisData!$A:$A, "Pickup", NewEmisData!$B:$B, $A10, NewEmisData!$C:$C, $H10, NewEmisData!$D:$D, DV$2), SUMIFS(NewEmisData!J:J, NewEmisData!$A:$A, "LDV", NewEmisData!$B:$B, $A10, NewEmisData!$C:$C, $H10, NewEmisData!$D:$D, DV$2)) -> 0.0035909984 | DW10: =$I10*IF($G10="Pickup", SUMIFS(NewEmisData!K:K, NewEmisData!$A:$A, "Pickup", NewEmisData!$B:$B, $A10, NewEmisData!$C:$C, $H10, NewEmisData!$D:$D, DW$2), SUMIFS(NewEmisData!K:K, NewEmisData!$A:$A, "LDV", NewEmisData!$B:$B, $A10, NewEmisData!$C:$C, $H10, NewEmisData!$D:$D, DW$2)) -> 0.0033016557 | DX10: =$I10*IF($G10="Pickup", SUMIFS(NewEmisData!L:L, NewEmisData!$A:$A, "Pickup", NewEmisData!$B:$B, $A10, NewEmisData!$C:$C, $H10, NewEmisData!$D:$D, DX$2), SUMIFS(NewEmisData!L:L, NewEmisData!$A:$A, "LDV", NewEmisData!$B:$B, $A10, NewEmisData!$C:$C, $H10, NewEmisData!$D:$D, DX$2)) -> 0.0032097041 | DY10: =$I10*IF($G10="Pickup", SUMIFS(NewEmisData!M:M, NewEmisData!$A:$A, "Pickup", NewEmisData!$B:$B, $A10, NewEmisData!$C:$C, $H10, NewEmisData!$D:$D, DY$2), SUMIFS(NewEmisData!M:M, NewEmisData!$A:$A, "LDV", NewEmisData!$B:$B, $A10, NewEmisData!$C:$C, $H10, NewEmisData!$D:$D, DY$2)) -> 0.0031631495 | DZ10: =DY10 -> 0.0031631495 | EA10: =K10 -> 477.08587 | EB10: =L10 -> 459.34104 | EC10: =M10 -> 447.45897 | ED10: =N10 -> 380.72393 | EE10: =O10 -> 329.54737 | EF10: =P10 -> 300.6983 | EG10: =Q10 -> 287.838 | EH10: =R10 -> 283.26611 | ... FX10: =BH10 -> 0.011109457
A11: =_xlfn.CONCAT(IF(LEFT(TRIM(A10),1)="*", "*R", "R"), 1+RIGHT(TRIM(A10),1)) -> R3 | B11: =B10 -> TLEMCGSL | C11: =C10 -> TL.GSL.MC.Existing fleet | D11: =D10 -> bn-vmt, bn-vmt/a | E11: =E10 -> TLGSL | F11: =F10 -> TL | G11: Mini car | H11: GSL | I11: 1 | J11: =CONCATENATE(G11,"-",H11) -> Mini car-GSL | K11: =$I11*IF($G11="Pickup", SUMIFS(NewEmisData!E:E, NewEmisData!$A:$A, "Pickup", NewEmisData!$B:$B, $A11, NewEmisData!$C:$C, $H11, NewEmisData!$D:$D, K$2), SUMIFS(NewEmisData!E:E, NewEmisData!$A:$A, "LDV", NewEmisData!$B:$B, $A11, NewEmisData!$C:$C, $H11, NewEmisData!$D:$D, K$2)) -> 437.85747 | L11: =$I11*IF($G11="Pickup", SUMIFS(NewEmisData!F:F, NewEmisData!$A:$A, "Pickup", NewEmisData!$B:$B, $A11, NewEmisData!$C:$C, $H11, NewEmisData!$D:$D, L$2), SUMIFS(NewEmisData!F:F, NewEmisData!$A:$A, "LDV", NewEmisData!$B:$B, $A11, NewEmisData!$C:$C, $H11, NewEmisData!$D:$D, L$2)) -> 424.60988 | M11: =$I11*IF($G11="Pickup", SUMIFS(NewEmisData!G:G, NewEmisData!$A:$A, "Pickup", NewEmisData!$B:$B, $A11, NewEmisData!$C:$C, $H11, NewEmisData!$D:$D, M$2), SUMIFS(NewEmisData!G:G, NewEmisData!$A:$A, "LDV", NewEmisData!$B:$B, $A11, NewEmisData!$C:$C, $H11, NewEmisData!$D:$D, M$2)) -> 389.26792 | N11: =$I11*IF($G11="Pickup", SUMIFS(NewEmisData!H:H, NewEmisData!$A:$A, "Pickup", NewEmisData!$B:$B, $A11, NewEmisData!$C:$C, $H11, NewEmisData!$D:$D, N$2), SUMIFS(NewEmisData!H:H, NewEmisData!$A:$A, "LDV", NewEmisData!$B:$B, $A11, NewEmisData!$C:$C, $H11, NewEmisData!$D:$D, N$2)) -> 331.09003 | O11: =$I11*IF($G11="Pickup", SUMIFS(NewEmisData!I:I, NewEmisData!$A:$A, "Pickup", NewEmisData!$B:$B, $A11, NewEmisData!$C:$C, $H11, NewEmisData!$D:$D, O$2), SUMIFS(NewEmisData!I:I, NewEmisData!$A:$A, "LDV", NewEmisData!$B:$B, $A11, NewEmisData!$C:$C, $H11, NewEmisData!$D:$D, O$2)) -> 286.4693 | P11: =$I11*IF($G11="Pickup", SUMIFS(NewEmisData!J:J, NewEmisData!$A:$A, "Pickup", NewEmisData!$B:$B, $A11, NewEmisData!$C:$C, $H11, NewEmisData!$D:$D, P$2), SUMIFS(NewEmisData!J:J, NewEmisData!$A:$A, "LDV", NewEmisData!$B:$B, $A11, NewEmisData!$C:$C, $H11, NewEmisData!$D:$D, P$2)) -> 261.3308 | Q11: =$I11*IF($G11="Pickup", SUMIFS(NewEmisData!K:K, NewEmisData!$A:$A, "Pickup", NewEmisData!$B:$B, $A11, NewEmisData!$C:$C, $H11, NewEmisData!$D:$D, Q$2), SUMIFS(NewEmisData!K:K, NewEmisData!$A:$A, "LDV", NewEmisData!$B:$B, $A11, NewEmisData!$C:$C, $H11, NewEmisData!$D:$D, Q$2)) -> 250.12665 | R11: =$I11*IF($G11="Pickup", SUMIFS(NewEmisData!L:L, NewEmisData!$A:$A, "Pickup", NewEmisData!$B:$B, $A11, NewEmisData!$C:$C, $H11, NewEmisData!$D:$D, R$2), SUMIFS(NewEmisData!L:L, NewEmisData!$A:$A, "LDV", NewEmisData!$B:$B, $A11, NewEmisData!$C:$C, $H11, NewEmisData!$D:$D, R$2)) -> 246.14649 | S11: =$I11*IF($G11="Pickup", SUMIFS(NewEmisData!M:M, NewEmisData!$A:$A, "Pickup", NewEmisData!$B:$B, $A11, NewEmisData!$C:$C, $H11, NewEmisData!$D:$D, S$2), SUMIFS(NewEmisData!M:M, NewEmisData!$A:$A, "LDV", NewEmisData!$B:$B, $A11, NewEmisData!$C:$C, $H11, NewEmisData!$D:$D, S$2)) -> 244.67782 | T11: =S11 -> 244.67782 | U11: =$I11*IF($G11="Pickup", SUMIFS(NewEmisData!E:E, NewEmisData!$A:$A, "Pickup", NewEmisData!$B:$B, $A11, NewEmisData!$C:$C, $H11, NewEmisData!$D:$D, U$2), SUMIFS(NewEmisData!E:E, NewEmisData!$A:$A, "LDV", NewEmisData!$B:$B, $A11, NewEmisData!$C:$C, $H11, NewEmisData!$D:$D, U$2)) -> 0.78000131 | V11: =$I11*IF($G11="Pickup", SUMIFS(NewEmisData!F:F, NewEmisData!$A:$A, "Pickup", NewEmisData!$B:$B, $A11, NewEmisData!$C:$C, $H11, NewEmisData!$D:$D, V$2), SUMIFS(NewEmisData!F:F, NewEmisData!$A:$A, "LDV", NewEmisData!$B:$B, $A11, NewEmisData!$C:$C, $H11, NewEmisData!$D:$D, V$2)) -> 0.32360528 | W11: =$I11*IF($G11="Pickup", SUMIFS(NewEmisData!G:G, NewEmisData!$A:$A, "Pickup", NewEmisData!$B:$B, $A11, NewEmisData!$C:$C, $H11, NewEmisData!$D:$D, W$2), SUMIFS(NewEmisData!G:G, NewEmisData!$A:$A, "LDV", NewEmisData!$B:$B, $A11, NewEmisData!$C:$C, $H11, NewEmisData!$D:$D, W$2)) -> 0.19152447 | X11: =$I11*IF($G11="Pickup", SUMIFS(NewEmisData!H:H, NewEmisData!$A:$A, "Pickup", NewEmisData!$B:$B, $A11, NewEmisData!$C:$C, $H11, NewEmisData!$D:$D, X$2), SUMIFS(NewEmisData!H:H, NewEmisData!$A:$A, "LDV", NewEmisData!$B:$B, $A11, NewEmisData!$C:$C, $H11, NewEmisData!$D:$D, X$2)) -> 0.12537128 | Y11: =$I11*IF($G11="Pickup", SUMIFS(NewEmisData!I:I, NewEmisData!$A:$A, "Pickup", NewEmisData!$B:$B, $A11, NewEmisData!$C:$C, $H11, NewEmisData!$D:$D, Y$2), SUMIFS(NewEmisData!I:I, NewEmisData!$A:$A, "LDV", NewEmisData!$B:$B, $A11, NewEmisData!$C:$C, $H11, NewEmisData!$D:$D, Y$2)) -> 0.076671767 | Z11: =$I11*IF($G11="Pickup", SUMIFS(NewEmisData!J:J, NewEmisData!$A:$A, "Pickup", NewEmisData!$B:$B, $A11, NewEmisData!$C:$C, $H11, NewEmisData!$D:$D, Z$2), SUMIFS(NewEmisData!J:J, NewEmisData!$A:$A, "LDV", NewEmisData!$B:$B, $A11, NewEmisData!$C:$C, $H11, NewEmisData!$D:$D, Z$2)) -> 0.057019027 | AA11: =$I11*IF($G11="Pickup", SUMIFS(NewEmisData!K:K, NewEmisData!$A:$A, "Pickup", NewEmisData!$B:$B, $A11, NewEmisData!$C:$C, $H11, NewEmisData!$D:$D, AA$2), SUMIFS(NewEmisData!K:K, NewEmisData!$A:$A, "LDV", NewEmisData!$B:$B, $A11, NewEmisData!$C:$C, $H11, NewEmisData!$D:$D, AA$2)) -> 0.048823282 | AB11: =$I11*IF($G11="Pickup", SUMIFS(NewEmisData!L:L, NewEmisData!$A:$A, "Pickup", NewEmisData!$B:$B, $A11, NewEmisData!$C:$C, $H11, NewEmisData!$D:$D, AB$2), SUMIFS(NewEmisData!L:L, NewEmisData!$A:$A, "LDV", NewEmisData!$B:$B, $A11, NewEmisData!$C:$C, $H11, NewEmisData!$D:$D, AB$2)) -> 0.046542407 | AC11: =$I11*IF($G11="Pickup", SUMIFS(NewEmisData!M:M, NewEmisData!$A:$A, "Pickup", NewEmisData!$B:$B, $A11, NewEmisData!$C:$C, $H11, NewEmisData!$D:$D, AC$2), SUMIFS(NewEmisData!M:M, NewEmisData!$A:$A, "LDV", NewEmisData!$B:$B, $A11, NewEmisData!$C:$C, $H11, NewEmisData!$D:$D, AC$2)) -> 0.045415311 | AD11: =AC11 -> 0.045415311 | AE11: =$I11*IF($G11="Pickup", SUMIFS(NewEmisData!E:E, NewEmisData!$A:$A, "Pickup", NewEmisData!$B:$B, $A11, NewEmisData!$C:$C, $H11, NewEmisData!$D:$D, AE$2), SUMIFS(NewEmisData!E:E, NewEmisData!$A:$A, "LDV", NewEmisData!$B:$B, $A11, NewEmisData!$C:$C, $H11, NewEmisData!$D:$D, AE$2)) -> 0.0075764719 | AF11: =$I11*IF($G11="Pickup", SUMIFS(NewEmisData!F:F, NewEmisData!$A:$A, "Pickup", NewEmisData!$B:$B, $A11, NewEmisData!$C:$C, $H11, NewEmisData!$D:$D, AF$2), SUMIFS(NewEmisData!F:F, NewEmisData!$A:$A, "LDV", NewEmisData!$B:$B, $A11, NewEmisData!$C:$C, $H11, NewEmisData!$D:$D, AF$2)) -> 0.00734724 | AG11: =$I11*IF($G11="Pickup", SUMIFS(NewEmisData!G:G, NewEmisData!$A:$A, "Pickup", NewEmisData!$B:$B, $A11, NewEmisData!$C:$C, $H11, NewEmisData!$D:$D, AG$2), SUMIFS(NewEmisData!G:G, NewEmisData!$A:$A, "LDV", NewEmisData!$B:$B, $A11, NewEmisData!$C:$C, $H11, NewEmisData!$D:$D, AG$2)) -> 0.0055842494 | AH11: =$I11*IF($G11="Pickup", SUMIFS(NewEmisData!H:H, NewEmisData!$A:$A, "Pickup", NewEmisData!$B:$B, $A11, NewEmisData!$C:$C, $H11, NewEmisData!$D:$D, AH$2), SUMIFS(NewEmisData!H:H, NewEmisData!$A:$A, "LDV", NewEmisData!$B:$B, $A11, NewEmisData!$C:$C, $H11, NewEmisData!$D:$D, AH$2)) -> 0.0047496587 | AI11: =$I11*IF($G11="Pickup", SUMIFS(NewEmisData!I:I, NewEmisData!$A:$A, "Pickup", NewEmisData!$B:$B, $A11, NewEmisData!$C:$C, $H11, NewEmisData!$D:$D, AI$2), SUMIFS(NewEmisData!I:I, NewEmisData!$A:$A, "LDV", NewEmisData!$B:$B, $A11, NewEmisData!$C:$C, $H11, NewEmisData!$D:$D, AI$2)) -> 0.0041095519 | AJ11: =$I11*IF($G11="Pickup", SUMIFS(NewEmisData!J:J, NewEmisData!$A:$A, "Pickup", NewEmisData!$B:$B, $A11, NewEmisData!$C:$C, $H11, NewEmisData!$D:$D, AJ$2), SUMIFS(NewEmisData!J:J, NewEmisData!$A:$A, "LDV", NewEmisData!$B:$B, $A11, NewEmisData!$C:$C, $H11, NewEmisData!$D:$D, AJ$2)) -> 0.0037489265 | AK11: =$I11*IF($G11="Pickup", SUMIFS(NewEmisData!K:K, NewEmisData!$A:$A, "Pickup", NewEmisData!$B:$B, $A11, NewEmisData!$C:$C, $H11, NewEmisData!$D:$D, AK$2), SUMIFS(NewEmisData!K:K, NewEmisData!$A:$A, "LDV", NewEmisData!$B:$B, $A11, NewEmisData!$C:$C, $H11, NewEmisData!$D:$D, AK$2)) -> 0.003588196 | AL11: =$I11*IF($G11="Pickup", SUMIFS(NewEmisData!L:L, NewEmisData!$A:$A, "Pickup", NewEmisData!$B:$B, $A11, NewEmisData!$C:$C, $H11, NewEmisData!$D:$D, AL$2), SUMIFS(NewEmisData!L:L, NewEmisData!$A:$A, "LDV", NewEmisData!$B:$B, $A11, NewEmisData!$C:$C, $H11, NewEmisData!$D:$D, AL$2)) -> 0.0035311006 | AM11: =$I11*IF($G11="Pickup", SUMIFS(NewEmisData!M:M, NewEmisData!$A:$A, "Pickup", NewEmisData!$B:$B, $A11, NewEmisData!$C:$C, $H11, NewEmisData!$D:$D, AM$2), SUMIFS(NewEmisData!M:M, NewEmisData!$A:$A, "LDV", NewEmisData!$B:$B, $A11, NewEmisData!$C:$C, $H11, NewEmisData!$D:$D, AM$2)) -> 0.003510031 | AN11: =AM11 -> 0.003510031 | AO11: =$I11*IF($G11="Pickup", SUMIFS(NewEmisData!E:E, NewEmisData!$A:$A, "Pickup", NewEmisData!$B:$B, $A11, NewEmisData!$C:$C, $H11, NewEmisData!$D:$D, AO$2), SUMIFS(NewEmisData!E:E, NewEmisData!$A:$A, "LDV", NewEmisData!$B:$B, $A11, NewEmisData!$C:$C, $H11, NewEmisData!$D:$D, AO$2)) -> 0.067831755 | AP11: =$I11*IF($G11="Pickup", SUMIFS(NewEmisData!F:F, NewEmisData!$A:$A, "Pickup", NewEmisData!$B:$B, $A11, NewEmisData!$C:$C, $H11, NewEmisData!$D:$D, AP$2), SUMIFS(NewEmisData!F:F, NewEmisData!$A:$A, "LDV", NewEmisData!$B:$B, $A11, NewEmisData!$C:$C, $H11, NewEmisData!$D:$D, AP$2)) -> 0.063250667 | AQ11: =$I11*IF($G11="Pickup", SUMIFS(NewEmisData!G:G, NewEmisData!$A:$A, "Pickup", NewEmisData!$B:$B, $A11, NewEmisData!$C:$C, $H11, NewEmisData!$D:$D, AQ$2), SUMIFS(NewEmisData!G:G, NewEmisData!$A:$A, "LDV", NewEmisData!$B:$B, $A11, NewEmisData!$C:$C, $H11, NewEmisData!$D:$D, AQ$2)) -> 0.062628417 | AR11: =$I11*IF($G11="Pickup", SUMIFS(NewEmisData!H:H, NewEmisData!$A:$A, "Pickup", NewEmisData!$B:$B, $A11, NewEmisData!$C:$C, $H11, NewEmisData!$D:$D, AR$2), SUMIFS(NewEmisData!H:H, NewEmisData!$A:$A, "LDV", NewEmisData!$B:$B, $A11, NewEmisData!$C:$C, $H11, NewEmisData!$D:$D, AR$2)) -> 0.061216981 | AS11: =$I11*IF($G11="Pickup", SUMIFS(NewEmisData!I:I, NewEmisData!$A:$A, "Pickup", NewEmisData!$B:$B, $A11, NewEmisData!$C:$C, $H11, NewEmisData!$D:$D, AS$2), SUMIFS(NewEmisData!I:I, NewEmisData!$A:$A, "LDV", NewEmisData!$B:$B, $A11, NewEmisData!$C:$C, $H11, NewEmisData!$D:$D, AS$2)) -> 0.059842025 | AT11: =$I11*IF($G11="Pickup", SUMIFS(NewEmisData!J:J, NewEmisData!$A:$A, "Pickup", NewEmisData!$B:$B, $A11, NewEmisData!$C:$C, $H11, NewEmisData!$D:$D, AT$2), SUMIFS(NewEmisData!J:J, NewEmisData!$A:$A, "LDV", NewEmisData!$B:$B, $A11, NewEmisData!$C:$C, $H11, NewEmisData!$D:$D, AT$2)) -> 0.058761886 | AU11: =$I11*IF($G11="Pickup", SUMIFS(NewEmisData!K:K, NewEmisData!$A:$A, "Pickup", NewEmisData!$B:$B, $A11, NewEmisData!$C:$C, $H11, NewEmisData!$D:$D, AU$2), SUMIFS(NewEmisData!K:K, NewEmisData!$A:$A, "LDV", NewEmisData!$B:$B, $A11, NewEmisData!$C:$C, $H11, NewEmisData!$D:$D, AU$2)) -> 0.058072078 | AV11: =$I11*IF($G11="Pickup", SUMIFS(NewEmisData!L:L, NewEmisData!$A:$A, "Pickup", NewEmisData!$B:$B, $A11, NewEmisData!$C:$C, $H11, NewEmisData!$D:$D, AV$2), SUMIFS(NewEmisData!L:L, NewEmisData!$A:$A, "LDV", NewEmisData!$B:$B, $A11, NewEmisData!$C:$C, $H11, NewEmisData!$D:$D, AV$2)) -> 0.057726484 | AW11: =$I11*IF($G11="Pickup", SUMIFS(NewEmisData!M:M, NewEmisData!$A:$A, "Pickup", NewEmisData!$B:$B, $A11, NewEmisData!$C:$C, $H11, NewEmisData!$D:$D, AW$2), SUMIFS(NewEmisData!M:M, NewEmisData!$A:$A, "LDV", NewEmisData!$B:$B, $A11, NewEmisData!$C:$C, $H11, NewEmisData!$D:$D, AW$2)) -> 0.057530227 | AX11: =AW11 -> 0.057530227 | AY11: =$I11*IF($G11="Pickup", SUMIFS(NewEmisData!E:E, NewEmisData!$A:$A, "Pickup", NewEmisData!$B:$B, $A11, NewEmisData!$C:$C, $H11, NewEmisData!$D:$D, AY$2), SUMIFS(NewEmisData!E:E, NewEmisData!$A:$A, "LDV", NewEmisData!$B:$B, $A11, NewEmisData!$C:$C, $H11, NewEmisData!$D:$D, AY$2)) -> 0.018324823 | AZ11: =$I11*IF($G11="Pickup", SUMIFS(NewEmisData!F:F, NewEmisData!$A:$A, "Pickup", NewEmisData!$B:$B, $A11, NewEmisData!$C:$C, $H11, NewEmisData!$D:$D, AZ$2), SUMIFS(NewEmisData!F:F, NewEmisData!$A:$A, "LDV", NewEmisData!$B:$B, $A11, NewEmisData!$C:$C, $H11, NewEmisData!$D:$D, AZ$2)) -> 0.014272294 | BA11: =$I11*IF($G11="Pickup", SUMIFS(NewEmisData!G:G, NewEmisData!$A:$A, "Pickup", NewEmisData!$B:$B, $A11, NewEmisData!$C:$C, $H11, NewEmisData!$D:$D, BA$2), SUMIFS(NewEmisData!G:G, NewEmisData!$A:$A, "LDV", NewEmisData!$B:$B, $A11, NewEmisData!$C:$C, $H11, NewEmisData!$D:$D, BA$2)) -> 0.013165752 | BB11: =$I11*IF($G11="Pickup", SUMIFS(NewEmisData!H:H, NewEmisData!$A:$A, "Pickup", NewEmisData!$B:$B, $A11, NewEmisData!$C:$C, $H11, NewEmisData!$D:$D, BB$2), SUMIFS(NewEmisData!H:H, NewEmisData!$A:$A, "LDV", NewEmisData!$B:$B, $A11, NewEmisData!$C:$C, $H11, NewEmisData!$D:$D, BB$2)) -> 0.011917195 | BC11: =$I11*IF($G11="Pickup", SUMIFS(NewEmisData!I:I, NewEmisData!$A:$A, "Pickup", NewEmisData!$B:$B, $A11, NewEmisData!$C:$C, $H11, NewEmisData!$D:$D, BC$2), SUMIFS(NewEmisData!I:I, NewEmisData!$A:$A, "LDV", NewEmisData!$B:$B, $A11, NewEmisData!$C:$C, $H11, NewEmisData!$D:$D, BC$2)) -> 0.010700862 | BD11: =$I11*IF($G11="Pickup", SUMIFS(NewEmisData!J:J, NewEmisData!$A:$A, "Pickup", NewEmisData!$B:$B, $A11, NewEmisData!$C:$C, $H11, NewEmisData!$D:$D, BD$2), SUMIFS(NewEmisData!J:J, NewEmisData!$A:$A, "LDV", NewEmisData!$B:$B, $A11, NewEmisData!$C:$C, $H11, NewEmisData!$D:$D, BD$2)) -> 0.0097453522 | BE11: =$I11*IF($G11="Pickup", SUMIFS(NewEmisData!K:K, NewEmisData!$A:$A, "Pickup", NewEmisData!$B:$B, $A11, NewEmisData!$C:$C, $H11, NewEmisData!$D:$D, BE$2), SUMIFS(NewEmisData!K:K, NewEmisData!$A:$A, "LDV", NewEmisData!$B:$B, $A11, NewEmisData!$C:$C, $H11, NewEmisData!$D:$D, BE$2)) -> 0.0091351471 | BF11: =$I11*IF($G11="Pickup", SUMIFS(NewEmisData!L:L, NewEmisData!$A:$A, "Pickup", NewEmisData!$B:$B, $A11, NewEmisData!$C:$C, $H11, NewEmisData!$D:$D, BF$2), SUMIFS(NewEmisData!L:L, NewEmisData!$A:$A, "LDV", NewEmisData!$B:$B, $A11, NewEmisData!$C:$C, $H11, NewEmisData!$D:$D, BF$2)) -> 0.0088293874 | BG11: =$I11*IF($G11="Pickup", SUMIFS(NewEmisData!M:M, NewEmisData!$A:$A, "Pickup", NewEmisData!$B:$B, $A11, NewEmisData!$C:$C, $H11, NewEmisData!$D:$D, BG$2), SUMIFS(NewEmisData!M:M, NewEmisData!$A:$A, "LDV", NewEmisData!$B:$B, $A11, NewEmisData!$C:$C, $H11, NewEmisData!$D:$D, BG$2)) -> 0.0086558174 | BH11: =BG11 -> 0.0086558174 | BI11: =$I11*IF($G11="Pickup", SUMIFS(NewEmisData!E:E, NewEmisData!$A:$A, "Pickup", NewEmisData!$B:$B, $A11, NewEmisData!$C:$C, $H11, NewEmisData!$D:$D, BI$2), SUMIFS(NewEmisData!E:E, NewEmisData!$A:$A, "LDV", NewEmisData!$B:$B, $A11, NewEmisData!$C:$C, $H11, NewEmisData!$D:$D, BI$2)) -> 5.6341972 | BJ11: =$I11*IF($G11="Pickup", SUMIFS(NewEmisData!F:F, NewEmisData!$A:$A, "Pickup", NewEmisData!$B:$B, $A11, NewEmisData!$C:$C, $H11, NewEmisData!$D:$D, BJ$2), SUMIFS(NewEmisData!F:F, NewEmisData!$A:$A, "LDV", NewEmisData!$B:$B, $A11, NewEmisData!$C:$C, $H11, NewEmisData!$D:$D, BJ$2)) -> 3.2912081 | BK11: =$I11*IF($G11="Pickup", SUMIFS(NewEmisData!G:G, NewEmisData!$A:$A, "Pickup", NewEmisData!$B:$B, $A11, NewEmisData!$C:$C, $H11, NewEmisData!$D:$D, BK$2), SUMIFS(NewEmisData!G:G, NewEmisData!$A:$A, "LDV", NewEmisData!$B:$B, $A11, NewEmisData!$C:$C, $H11, NewEmisData!$D:$D, BK$2)) -> 2.5038449 | BL11: =$I11*IF($G11="Pickup", SUMIFS(NewEmisData!H:H, NewEmisData!$A:$A, "Pickup", NewEmisData!$B:$B, $A11, NewEmisData!$C:$C, $H11, NewEmisData!$D:$D, BL$2), SUMIFS(NewEmisData!H:H, NewEmisData!$A:$A, "LDV", NewEmisData!$B:$B, $A11, NewEmisData!$C:$C, $H11, NewEmisData!$D:$D, BL$2)) -> 1.9586302 | BM11: =$I11*IF($G11="Pickup", SUMIFS(NewEmisData!I:I, NewEmisData!$A:$A, "Pickup", NewEmisData!$B:$B, $A11, NewEmisData!$C:$C, $H11, NewEmisData!$D:$D, BM$2), SUMIFS(NewEmisData!I:I, NewEmisData!$A:$A, "LDV", NewEmisData!$B:$B, $A11, NewEmisData!$C:$C, $H11, NewEmisData!$D:$D, BM$2)) -> 1.4188081 | BN11: =$I11*IF($G11="Pickup", SUMIFS(NewEmisData!J:J, NewEmisData!$A:$A, "Pickup", NewEmisData!$B:$B, $A11, NewEmisData!$C:$C, $H11, NewEmisData!$D:$D, BN$2), SUMIFS(NewEmisData!J:J, NewEmisData!$A:$A, "LDV", NewEmisData!$B:$B, $A11, NewEmisData!$C:$C, $H11, NewEmisData!$D:$D, BN$2)) -> 1.1229583 | BO11: =$I11*IF($G11="Pickup", SUMIFS(NewEmisData!K:K, NewEmisData!$A:$A, "Pickup", NewEmisData!$B:$B, $A11, NewEmisData!$C:$C, $H11, NewEmisData!$D:$D, BO$2), SUMIFS(NewEmisData!K:K, NewEmisData!$A:$A, "LDV", NewEmisData!$B:$B, $A11, NewEmisData!$C:$C, $H11, NewEmisData!$D:$D, BO$2)) -> 0.98917471 | BP11: =$I11*IF($G11="Pickup", SUMIFS(NewEmisData!L:L, NewEmisData!$A:$A, "Pickup", NewEmisData!$B:$B, $A11, NewEmisData!$C:$C, $H11, NewEmisData!$D:$D, BP$2), SUMIFS(NewEmisData!L:L, NewEmisData!$A:$A, "LDV", NewEmisData!$B:$B, $A11, NewEmisData!$C:$C, $H11, NewEmisData!$D:$D, BP$2)) -> 0.94587291 | BQ11: =$I11*IF($G11="Pickup", SUMIFS(NewEmisData!M:M, NewEmisData!$A:$A, "Pickup", NewEmisData!$B:$B, $A11, NewEmisData!$C:$C, $H11, NewEmisData!$D:$D, BQ$2), SUMIFS(NewEmisData!M:M, NewEmisData!$A:$A, "LDV", NewEmisData!$B:$B, $A11, NewEmisData!$C:$C, $H11, NewEmisData!$D:$D, BQ$2)) -> 0.91886505 | BR11: =BQ11 -> 0.91886505 | BS11: =$I11*IF($G11="Pickup", SUMIFS(NewEmisData!E:E, NewEmisData!$A:$A, "Pickup", NewEmisData!$B:$B, $A11, NewEmisData!$C:$C, $H11, NewEmisData!$D:$D, BS$2), SUMIFS(NewEmisData!E:E, NewEmisData!$A:$A, "LDV", NewEmisData!$B:$B, $A11, NewEmisData!$C:$C, $H11, NewEmisData!$D:$D, BS$2)) -> 0.64604041 | BT11: =$I11*IF($G11="Pickup", SUMIFS(NewEmisData!F:F, NewEmisData!$A:$A, "Pickup", NewEmisData!$B:$B, $A11, NewEmisData!$C:$C, $H11, NewEmisData!$D:$D, BT$2), SUMIFS(NewEmisData!F:F, NewEmisData!$A:$A, "LDV", NewEmisData!$B:$B, $A11, NewEmisData!$C:$C, $H11, NewEmisData!$D:$D, BT$2)) -> 0.33711602 | BU11: =$I11*IF($G11="Pickup", SUMIFS(NewEmisData!G:G, NewEmisData!$A:$A, "Pickup", NewEmisData!$B:$B, $A11, NewEmisData!$C:$C, $H11, NewEmisData!$D:$D, BU$2), SUMIFS(NewEmisData!G:G, NewEmisData!$A:$A, "LDV", NewEmisData!$B:$B, $A11, NewEmisData!$C:$C, $H11, NewEmisData!$D:$D, BU$2)) -> 0.24835485 | BV11: =$I11*IF($G11="Pickup", SUMIFS(NewEmisData!H:H, NewEmisData!$A:$A, "Pickup", NewEmisData!$B:$B, $A11, NewEmisData!$C:$C, $H11, NewEmisData!$D:$D, BV$2), SUMIFS(NewEmisData!H:H, NewEmisData!$A:$A, "LDV", NewEmisData!$B:$B, $A11, NewEmisData!$C:$C, $H11, NewEmisData!$D:$D, BV$2)) -> 0.20063726 | BW11: =$I11*IF($G11="Pickup", SUMIFS(NewEmisData!I:I, NewEmisData!$A:$A, "Pickup", NewEmisData!$B:$B, $A11, NewEmisData!$C:$C, $H11, NewEmisData!$D:$D, BW$2), SUMIFS(NewEmisData!I:I, NewEmisData!$A:$A, "LDV", NewEmisData!$B:$B, $A11, NewEmisData!$C:$C, $H11, NewEmisData!$D:$D, BW$2)) -> 0.14838807 | BX11: =$I11*IF($G11="Pickup", SUMIFS(NewEmisData!J:J, NewEmisData!$A:$A, "Pickup", NewEmisData!$B:$B, $A11, NewEmisData!$C:$C, $H11, NewEmisData!$D:$D, BX$2), SUMIFS(NewEmisData!J:J, NewEmisData!$A:$A, "LDV", NewEmisData!$B:$B, $A11, NewEmisData!$C:$C, $H11, NewEmisData!$D:$D, BX$2)) -> 0.12460658 | BY11: =$I11*IF($G11="Pickup", SUMIFS(NewEmisData!K:K, NewEmisData!$A:$A, "Pickup", NewEmisData!$B:$B, $A11, NewEmisData!$C:$C, $H11, NewEmisData!$D:$D, BY$2), SUMIFS(NewEmisData!K:K, NewEmisData!$A:$A, "LDV", NewEmisData!$B:$B, $A11, NewEmisData!$C:$C, $H11, NewEmisData!$D:$D, BY$2)) -> 0.1117761 | BZ11: =$I11*IF($G11="Pickup", SUMIFS(NewEmisData!L:L, NewEmisData!$A:$A, "Pickup", NewEmisData!$B:$B, $A11, NewEmisData!$C:$C, $H11, NewEmisData!$D:$D, BZ$2), SUMIFS(NewEmisData!L:L, NewEmisData!$A:$A, "LDV", NewEmisData!$B:$B, $A11, NewEmisData!$C:$C, $H11, NewEmisData!$D:$D, BZ$2)) -> 0.10678198 | CA11: =$I11*IF($G11="Pickup", SUMIFS(NewEmisData!M:M, NewEmisData!$A:$A, "Pickup", NewEmisData!$B:$B, $A11, NewEmisData!$C:$C, $H11, NewEmisData!$D:$D, CA$2), SUMIFS(NewEmisData!M:M, NewEmisData!$A:$A, "LDV", NewEmisData!$B:$B, $A11, NewEmisData!$C:$C, $H11, NewEmisData!$D:$D, CA$2)) -> 0.10278869 | CB11: =CA11 -> 0.10278869 | CC11: =$I11*IF($G11="Pickup", SUMIFS(NewEmisData!E:E, NewEmisData!$A:$A, "Pickup", NewEmisData!$B:$B, $A11, NewEmisData!$C:$C, $H11, NewEmisData!$D:$D, CC$2), SUMIFS(NewEmisData!E:E, NewEmisData!$A:$A, "LDV", NewEmisData!$B:$B, $A11, NewEmisData!$C:$C, $H11, NewEmisData!$D:$D, CC$2)) -> 0.045186599 | CD11: =$I11*IF($G11="Pickup", SUMIFS(NewEmisData!F:F, NewEmisData!$A:$A, "Pickup", NewEmisData!$B:$B, $A11, NewEmisData!$C:$C, $H11, NewEmisData!$D:$D, CD$2), SUMIFS(NewEmisData!F:F, NewEmisData!$A:$A, "LDV", NewEmisData!$B:$B, $A11, NewEmisData!$C:$C, $H11, NewEmisData!$D:$D, CD$2)) -> 0.030321043 | CE11: =$I11*IF($G11="Pickup", SUMIFS(NewEmisData!G:G, NewEmisData!$A:$A, "Pickup", NewEmisData!$B:$B, $A11, NewEmisData!$C:$C, $H11, NewEmisData!$D:$D, CE$2), SUMIFS(NewEmisData!G:G, NewEmisData!$A:$A, "LDV", NewEmisData!$B:$B, $A11, NewEmisData!$C:$C, $H11, NewEmisData!$D:$D, CE$2)) -> 0.025916716 | CF11: =$I11*IF($G11="Pickup", SUMIFS(NewEmisData!H:H, NewEmisData!$A:$A, "Pickup", NewEmisData!$B:$B, $A11, NewEmisData!$C:$C, $H11, NewEmisData!$D:$D, CF$2), SUMIFS(NewEmisData!H:H, NewEmisData!$A:$A, "LDV", NewEmisData!$B:$B, $A11, NewEmisData!$C:$C, $H11, NewEmisData!$D:$D, CF$2)) -> 0.024735956 | CG11: =$I11*IF($G11="Pickup", SUMIFS(NewEmisData!I:I, NewEmisData!$A:$A, "Pickup", NewEmisData!$B:$B, $A11, NewEmisData!$C:$C, $H11, NewEmisData!$D:$D, CG$2), SUMIFS(NewEmisData!I:I, NewEmisData!$A:$A, "LDV", NewEmisData!$B:$B, $A11, NewEmisData!$C:$C, $H11, NewEmisData!$D:$D, CG$2)) -> 0.023950742 | CH11: =$I11*IF($G11="Pickup", SUMIFS(NewEmisData!J:J, NewEmisData!$A:$A, "Pickup", NewEmisData!$B:$B, $A11, NewEmisData!$C:$C, $H11, NewEmisData!$D:$D, CH$2), SUMIFS(NewEmisData!J:J, NewEmisData!$A:$A, "LDV", NewEmisData!$B:$B, $A11, NewEmisData!$C:$C, $H11, NewEmisData!$D:$D, CH$2)) -> 0.02333433 | CI11: =$I11*IF($G11="Pickup", SUMIFS(NewEmisData!K:K, NewEmisData!$A:$A, "Pickup", NewEmisData!$B:$B, $A11, NewEmisData!$C:$C, $H11, NewEmisData!$D:$D, CI$2), SUMIFS(NewEmisData!K:K, NewEmisData!$A:$A, "LDV", NewEmisData!$B:$B, $A11, NewEmisData!$C:$C, $H11, NewEmisData!$D:$D, CI$2)) -> 0.023332378 | CJ11: =$I11*IF($G11="Pickup", SUMIFS(NewEmisData!L:L, NewEmisData!$A:$A, "Pickup", NewEmisData!$B:$B, $A11, NewEmisData!$C:$C, $H11, NewEmisData!$D:$D, CJ$2), SUMIFS(NewEmisData!L:L, NewEmisData!$A:$A, "LDV", NewEmisData!$B:$B, $A11, NewEmisData!$C:$C, $H11, NewEmisData!$D:$D, CJ$2)) -> 0.023331869 | CK11: =$I11*IF($G11="Pickup", SUMIFS(NewEmisData!M:M, NewEmisData!$A:$A, "Pickup", NewEmisData!$B:$B, $A11, NewEmisData!$C:$C, $H11, NewEmisData!$D:$D, CK$2), SUMIFS(NewEmisData!M:M, NewEmisData!$A:$A, "LDV", NewEmisData!$B:$B, $A11, NewEmisData!$C:$C, $H11, NewEmisData!$D:$D, CK$2)) -> 0.023331334 | CL11: =CK11 -> 0.023331334 | CM11: =$I11*IF($G11="Pickup", SUMIFS(NewEmisData!E:E, NewEmisData!$A:$A, "Pickup", NewEmisData!$B:$B, $A11, NewEmisData!$C:$C, $H11, NewEmisData!$D:$D, CM$2), SUMIFS(NewEmisData!E:E, NewEmisData!$A:$A, "LDV", NewEmisData!$B:$B, $A11, NewEmisData!$C:$C, $H11, NewEmisData!$D:$D, CM$2)) -> 0.018999641 | CN11: =$I11*IF($G11="Pickup", SUMIFS(NewEmisData!F:F, NewEmisData!$A:$A, "Pickup", NewEmisData!$B:$B, $A11, NewEmisData!$C:$C, $H11, NewEmisData!$D:$D, CN$2), SUMIFS(NewEmisData!F:F, NewEmisData!$A:$A, "LDV", NewEmisData!$B:$B, $A11, NewEmisData!$C:$C, $H11, NewEmisData!$D:$D, CN$2)) -> 0.011293404 | CO11: =$I11*IF($G11="Pickup", SUMIFS(NewEmisData!G:G, NewEmisData!$A:$A, "Pickup", NewEmisData!$B:$B, $A11, NewEmisData!$C:$C, $H11, NewEmisData!$D:$D, CO$2), SUMIFS(NewEmisData!G:G, NewEmisData!$A:$A, "LDV", NewEmisData!$B:$B, $A11, NewEmisData!$C:$C, $H11, NewEmisData!$D:$D, CO$2)) -> 0.0089155865 | CP11: =$I11*IF($G11="Pickup", SUMIFS(NewEmisData!H:H, NewEmisData!$A:$A, "Pickup", NewEmisData!$B:$B, $A11, NewEmisData!$C:$C, $H11, NewEmisData!$D:$D, CP$2), SUMIFS(NewEmisData!H:H, NewEmisData!$A:$A, "LDV", NewEmisData!$B:$B, $A11, NewEmisData!$C:$C, $H11, NewEmisData!$D:$D, CP$2)) -> 0.0073372922 | CQ11: =$I11*IF($G11="Pickup", SUMIFS(NewEmisData!I:I, NewEmisData!$A:$A, "Pickup", NewEmisData!$B:$B, $A11, NewEmisData!$C:$C, $H11, NewEmisData!$D:$D, CQ$2), SUMIFS(NewEmisData!I:I, NewEmisData!$A:$A, "LDV", NewEmisData!$B:$B, $A11, NewEmisData!$C:$C, $H11, NewEmisData!$D:$D, CQ$2)) -> 0.0065724995 | CR11: =$I11*IF($G11="Pickup", SUMIFS(NewEmisData!J:J, NewEmisData!$A:$A, "Pickup", NewEmisData!$B:$B, $A11, NewEmisData!$C:$C, $H11, NewEmisData!$D:$D, CR$2), SUMIFS(NewEmisData!J:J, NewEmisData!$A:$A, "LDV", NewEmisData!$B:$B, $A11, NewEmisData!$C:$C, $H11, NewEmisData!$D:$D, CR$2)) -> 0.0062407198 | CS11: =$I11*IF($G11="Pickup", SUMIFS(NewEmisData!K:K, NewEmisData!$A:$A, "Pickup", NewEmisData!$B:$B, $A11, NewEmisData!$C:$C, $H11, NewEmisData!$D:$D, CS$2), SUMIFS(NewEmisData!K:K, NewEmisData!$A:$A, "LDV", NewEmisData!$B:$B, $A11, NewEmisData!$C:$C, $H11, NewEmisData!$D:$D, CS$2)) -> 0.0062045762 | CT11: =$I11*IF($G11="Pickup", SUMIFS(NewEmisData!L:L, NewEmisData!$A:$A, "Pickup", NewEmisData!$B:$B, $A11, NewEmisData!$C:$C, $H11, NewEmisData!$D:$D, CT$2), SUMIFS(NewEmisData!L:L, NewEmisData!$A:$A, "LDV", NewEmisData!$B:$B, $A11, NewEmisData!$C:$C, $H11, NewEmisData!$D:$D, CT$2)) -> 0.0061456645 | CU11: =$I11*IF($G11="Pickup", SUMIFS(NewEmisData!M:M, NewEmisData!$A:$A, "Pickup", NewEmisData!$B:$B, $A11, NewEmisData!$C:$C, $H11, NewEmisData!$D:$D, CU$2), SUMIFS(NewEmisData!M:M, NewEmisData!$A:$A, "LDV", NewEmisData!$B:$B, $A11, NewEmisData!$C:$C, $H11, NewEmisData!$D:$D, CU$2)) -> 0.0061452936 | CV11: =CU11 -> 0.0061452936 | CW11: 0.0030448047 | CX11: 0.0018865909 | CY11: 0.0015570268 | CZ11: 0.0012432183 | DA11: 0.00092522519 | DB11: 0.00072309457 | DC11: 0.00068940707 | DD11: 0.00068441484 | DE11: 0.00068634617 | DF11: 0.00068634617 | DG11: =$I11*IF($G11="Pickup", SUMIFS(NewEmisData!E:E, NewEmisData!$A:$A, "Pickup", NewEmisData!$B:$B, $A11, NewEmisData!$C:$C, $H11, NewEmisData!$D:$D, DG$2), SUMIFS(NewEmisData!E:E, NewEmisData!$A:$A, "LDV", NewEmisData!$B:$B, $A11, NewEmisData!$C:$C, $H11, NewEmisData!$D:$D, DG$2)) -> 0 | DH11: =$I11*IF($G11="Pickup", SUMIFS(NewEmisData!F:F, NewEmisData!$A:$A, "Pickup", NewEmisData!$B:$B, $A11, NewEmisData!$C:$C, $H11, NewEmisData!$D:$D, DH$2), SUMIFS(NewEmisData!F:F, NewEmisData!$A:$A, "LDV", NewEmisData!$B:$B, $A11, NewEmisData!$C:$C, $H11, NewEmisData!$D:$D, DH$2)) -> 0 | DI11: =$I11*IF($G11="Pickup", SUMIFS(NewEmisData!G:G, NewEmisData!$A:$A, "Pickup", NewEmisData!$B:$B, $A11, NewEmisData!$C:$C, $H11, NewEmisData!$D:$D, DI$2), SUMIFS(NewEmisData!G:G, NewEmisData!$A:$A, "LDV", NewEmisData!$B:$B, $A11, NewEmisData!$C:$C, $H11, NewEmisData!$D:$D, DI$2)) -> 0 | DJ11: =$I11*IF($G11="Pickup", SUMIFS(NewEmisData!H:H, NewEmisData!$A:$A, "Pickup", NewEmisData!$B:$B, $A11, NewEmisData!$C:$C, $H11, NewEmisData!$D:$D, DJ$2), SUMIFS(NewEmisData!H:H, NewEmisData!$A:$A, "LDV", NewEmisData!$B:$B, $A11, NewEmisData!$C:$C, $H11, NewEmisData!$D:$D, DJ$2)) -> 0 | DK11: =$I11*IF($G11="Pickup", SUMIFS(NewEmisData!I:I, NewEmisData!$A:$A, "Pickup", NewEmisData!$B:$B, $A11, NewEmisData!$C:$C, $H11, NewEmisData!$D:$D, DK$2), SUMIFS(NewEmisData!I:I, NewEmisData!$A:$A, "LDV", NewEmisData!$B:$B, $A11, NewEmisData!$C:$C, $H11, NewEmisData!$D:$D, DK$2)) -> 0 | DL11: =$I11*IF($G11="Pickup", SUMIFS(NewEmisData!J:J, NewEmisData!$A:$A, "Pickup", NewEmisData!$B:$B, $A11, NewEmisData!$C:$C, $H11, NewEmisData!$D:$D, DL$2), SUMIFS(NewEmisData!J:J, NewEmisData!$A:$A, "LDV", NewEmisData!$B:$B, $A11, NewEmisData!$C:$C, $H11, NewEmisData!$D:$D, DL$2)) -> 0 | DM11: =$I11*IF($G11="Pickup", SUMIFS(NewEmisData!K:K, NewEmisData!$A:$A, "Pickup", NewEmisData!$B:$B, $A11, NewEmisData!$C:$C, $H11, NewEmisData!$D:$D, DM$2), SUMIFS(NewEmisData!K:K, NewEmisData!$A:$A, "LDV", NewEmisData!$B:$B, $A11, NewEmisData!$C:$C, $H11, NewEmisData!$D:$D, DM$2)) -> 0 | DN11: =$I11*IF($G11="Pickup", SUMIFS(NewEmisData!L:L, NewEmisData!$A:$A, "Pickup", NewEmisData!$B:$B, $A11, NewEmisData!$C:$C, $H11, NewEmisData!$D:$D, DN$2), SUMIFS(NewEmisData!L:L, NewEmisData!$A:$A, "LDV", NewEmisData!$B:$B, $A11, NewEmisData!$C:$C, $H11, NewEmisData!$D:$D, DN$2)) -> 0 | DO11: =$I11*IF($G11="Pickup", SUMIFS(NewEmisData!M:M, NewEmisData!$A:$A, "Pickup", NewEmisData!$B:$B, $A11, NewEmisData!$C:$C, $H11, NewEmisData!$D:$D, DO$2), SUMIFS(NewEmisData!M:M, NewEmisData!$A:$A, "LDV", NewEmisData!$B:$B, $A11, NewEmisData!$C:$C, $H11, NewEmisData!$D:$D, DO$2)) -> 0 | DP11: =DO11 -> 0 | DQ11: =$I11*IF($G11="Pickup", SUMIFS(NewEmisData!E:E, NewEmisData!$A:$A, "Pickup", NewEmisData!$B:$B, $A11, NewEmisData!$C:$C, $H11, NewEmisData!$D:$D, DQ$2), SUMIFS(NewEmisData!E:E, NewEmisData!$A:$A, "LDV", NewEmisData!$B:$B, $A11, NewEmisData!$C:$C, $H11, NewEmisData!$D:$D, DQ$2)) -> 0.012810027 | DR11: =$I11*IF($G11="Pickup", SUMIFS(NewEmisData!F:F, NewEmisData!$A:$A, "Pickup", NewEmisData!$B:$B, $A11, NewEmisData!$C:$C, $H11, NewEmisData!$D:$D, DR$2), SUMIFS(NewEmisData!F:F, NewEmisData!$A:$A, "LDV", NewEmisData!$B:$B, $A11, NewEmisData!$C:$C, $H11, NewEmisData!$D:$D, DR$2)) -> 0.0069424261 | DS11: =$I11*IF($G11="Pickup", SUMIFS(NewEmisData!G:G, NewEmisData!$A:$A, "Pickup", NewEmisData!$B:$B, $A11, NewEmisData!$C:$C, $H11, NewEmisData!$D:$D, DS$2), SUMIFS(NewEmisData!G:G, NewEmisData!$A:$A, "LDV", NewEmisData!$B:$B, $A11, NewEmisData!$C:$C, $H11, NewEmisData!$D:$D, DS$2)) -> 0.0055718063 | DT11: =$I11*IF($G11="Pickup", SUMIFS(NewEmisData!H:H, NewEmisData!$A:$A, "Pickup", NewEmisData!$B:$B, $A11, NewEmisData!$C:$C, $H11, NewEmisData!$D:$D, DT$2), SUMIFS(NewEmisData!H:H, NewEmisData!$A:$A, "LDV", NewEmisData!$B:$B, $A11, NewEmisData!$C:$C, $H11, NewEmisData!$D:$D, DT$2)) -> 0.0042603418 | DU11: =$I11*IF($G11="Pickup", SUMIFS(NewEmisData!I:I, NewEmisData!$A:$A, "Pickup", NewEmisData!$B:$B, $A11, NewEmisData!$C:$C, $H11, NewEmisData!$D:$D, DU$2), SUMIFS(NewEmisData!I:I, NewEmisData!$A:$A, "LDV", NewEmisData!$B:$B, $A11, NewEmisData!$C:$C, $H11, NewEmisData!$D:$D, DU$2)) -> 0.003319595 | DV11: =$I11*IF($G11="Pickup", SUMIFS(NewEmisData!J:J, NewEmisData!$A:$A, "Pickup", NewEmisData!$B:$B, $A11, NewEmisData!$C:$C, $H11, NewEmisData!$D:$D, DV$2), SUMIFS(NewEmisData!J:J, NewEmisData!$A:$A, "LDV", NewEmisData!$B:$B, $A11, NewEmisData!$C:$C, $H11, NewEmisData!$D:$D, DV$2)) -> 0.0028901417 | DW11: =$I11*IF($G11="Pickup", SUMIFS(NewEmisData!K:K, NewEmisData!$A:$A, "Pickup", NewEmisData!$B:$B, $A11, NewEmisData!$C:$C, $H11, NewEmisData!$D:$D, DW$2), SUMIFS(NewEmisData!K:K, NewEmisData!$A:$A, "LDV", NewEmisData!$B:$B, $A11, NewEmisData!$C:$C, $H11, NewEmisData!$D:$D, DW$2)) -> 0.0026480526 | DX11: =$I11*IF($G11="Pickup", SUMIFS(NewEmisData!L:L, NewEmisData!$A:$A, "Pickup", NewEmisData!$B:$B, $A11, NewEmisData!$C:$C, $H11, NewEmisData!$D:$D, DX$2), SUMIFS(NewEmisData!L:L, NewEmisData!$A:$A, "LDV", NewEmisData!$B:$B, $A11, NewEmisData!$C:$C, $H11, NewEmisData!$D:$D, DX$2)) -> 0.0025707167 | DY11: =$I11*IF($G11="Pickup", SUMIFS(NewEmisData!M:M, NewEmisData!$A:$A, "Pickup", NewEmisData!$B:$B, $A11, NewEmisData!$C:$C, $H11, NewEmisData!$D:$D, DY$2), SUMIFS(NewEmisData!M:M, NewEmisData!$A:$A, "LDV", NewEmisData!$B:$B, $A11, NewEmisData!$C:$C, $H11, NewEmisData!$D:$D, DY$2)) -> 0.0025319063 | DZ11: =DY11 -> 0.0025319063 | EA11: =K11 -> 437.85747 | EB11: =L11 -> 424.60988 | EC11: =M11 -> 389.26792 | ED11: =N11 -> 331.09003 | EE11: =O11 -> 286.4693 | EF11: =P11 -> 261.3308 | EG11: =Q11 -> 250.12665 | EH11: =R11 -> 246.14649 | ... FX11: =BH11 -> 0.0086558174
A12: =_xlfn.CONCAT(IF(LEFT(TRIM(A11),1)="*", "*R", "R"), 1+RIGHT(TRIM(A11),1)) -> R4 | B12: =B11 -> TLEMCGSL | C12: =C11 -> TL.GSL.MC.Existing fleet | D12: =D11 -> bn-vmt, bn-vmt/a | E12: =E11 -> TLGSL | F12: =F11 -> TL | G12: Mini car | H12: GSL | I12: 1 | J12: =CONCATENATE(G12,"-",H12) -> Mini car-GSL | K12: =$I12*IF($G12="Pickup", SUMIFS(NewEmisData!E:E, NewEmisData!$A:$A, "Pickup", NewEmisData!$B:$B, $A12, NewEmisData!$C:$C, $H12, NewEmisData!$D:$D, K$2), SUMIFS(NewEmisData!E:E, NewEmisData!$A:$A, "LDV", NewEmisData!$B:$B, $A12, NewEmisData!$C:$C, $H12, NewEmisData!$D:$D, K$2)) -> 605.35194 | L12: =$I12*IF($G12="Pickup", SUMIFS(NewEmisData!F:F, NewEmisData!$A:$A, "Pickup", NewEmisData!$B:$B, $A12, NewEmisData!$C:$C, $H12, NewEmisData!$D:$D, L$2), SUMIFS(NewEmisData!F:F, NewEmisData!$A:$A, "LDV", NewEmisData!$B:$B, $A12, NewEmisData!$C:$C, $H12, NewEmisData!$D:$D, L$2)) -> 575.43678 | M12: =$I12*IF($G12="Pickup", SUMIFS(NewEmisData!G:G, NewEmisData!$A:$A, "Pickup", NewEmisData!$B:$B, $A12, NewEmisData!$C:$C, $H12, NewEmisData!$D:$D, M$2), SUMIFS(NewEmisData!G:G, NewEmisData!$A:$A, "LDV", NewEmisData!$B:$B, $A12, NewEmisData!$C:$C, $H12, NewEmisData!$D:$D, M$2)) -> 447.50307 | N12: =$I12*IF($G12="Pickup", SUMIFS(NewEmisData!H:H, NewEmisData!$A:$A, "Pickup", NewEmisData!$B:$B, $A12, NewEmisData!$C:$C, $H12, NewEmisData!$D:$D, N$2), SUMIFS(NewEmisData!H:H, NewEmisData!$A:$A, "LDV", NewEmisData!$B:$B, $A12, NewEmisData!$C:$C, $H12, NewEmisData!$D:$D, N$2)) -> 380.32749 | O12: =$I12*IF($G12="Pickup", SUMIFS(NewEmisData!I:I, NewEmisData!$A:$A, "Pickup", NewEmisData!$B:$B, $A12, NewEmisData!$C:$C, $H12, NewEmisData!$D:$D, O$2), SUMIFS(NewEmisData!I:I, NewEmisData!$A:$A, "LDV", NewEmisData!$B:$B, $A12, NewEmisData!$C:$C, $H12, NewEmisData!$D:$D, O$2)) -> 328.85087 | P12: =$I12*IF($G12="Pickup", SUMIFS(NewEmisData!J:J, NewEmisData!$A:$A, "Pickup", NewEmisData!$B:$B, $A12, NewEmisData!$C:$C, $H12, NewEmisData!$D:$D, P$2), SUMIFS(NewEmisData!J:J, NewEmisData!$A:$A, "LDV", NewEmisData!$B:$B, $A12, NewEmisData!$C:$C, $H12, NewEmisData!$D:$D, P$2)) -> 299.87343 | Q12: =$I12*IF($G12="Pickup", SUMIFS(NewEmisData!K:K, NewEmisData!$A:$A, "Pickup", NewEmisData!$B:$B, $A12, NewEmisData!$C:$C, $H12, NewEmisData!$D:$D, Q$2), SUMIFS(NewEmisData!K:K, NewEmisData!$A:$A, "LDV", NewEmisData!$B:$B, $A12, NewEmisData!$C:$C, $H12, NewEmisData!$D:$D, Q$2)) -> 286.96646 | R12: =$I12*IF($G12="Pickup", SUMIFS(NewEmisData!L:L, NewEmisData!$A:$A, "Pickup", NewEmisData!$B:$B, $A12, NewEmisData!$C:$C, $H12, NewEmisData!$D:$D, R$2), SUMIFS(NewEmisData!L:L, NewEmisData!$A:$A, "LDV", NewEmisData!$B:$B, $A12, NewEmisData!$C:$C, $H12, NewEmisData!$D:$D, R$2)) -> 282.38592 | S12: =$I12*IF($G12="Pickup", SUMIFS(NewEmisData!M:M, NewEmisData!$A:$A, "Pickup", NewEmisData!$B:$B, $A12, NewEmisData!$C:$C, $H12, NewEmisData!$D:$D, S$2), SUMIFS(NewEmisData!M:M, NewEmisData!$A:$A, "LDV", NewEmisData!$B:$B, $A12, NewEmisData!$C:$C, $H12, NewEmisData!$D:$D, S$2)) -> 280.69816 | T12: =S12 -> 280.69816 | U12: =$I12*IF($G12="Pickup", SUMIFS(NewEmisData!E:E, NewEmisData!$A:$A, "Pickup", NewEmisData!$B:$B, $A12, NewEmisData!$C:$C, $H12, NewEmisData!$D:$D, U$2), SUMIFS(NewEmisData!E:E, NewEmisData!$A:$A, "LDV", NewEmisData!$B:$B, $A12, NewEmisData!$C:$C, $H12, NewEmisData!$D:$D, U$2)) -> 0.73999494 | V12: =$I12*IF($G12="Pickup", SUMIFS(NewEmisData!F:F, NewEmisData!$A:$A, "Pickup", NewEmisData!$B:$B, $A12, NewEmisData!$C:$C, $H12, NewEmisData!$D:$D, V$2), SUMIFS(NewEmisData!F:F, NewEmisData!$A:$A, "LDV", NewEmisData!$B:$B, $A12, NewEmisData!$C:$C, $H12, NewEmisData!$D:$D, V$2)) -> 0.3533524 | W12: =$I12*IF($G12="Pickup", SUMIFS(NewEmisData!G:G, NewEmisData!$A:$A, "Pickup", NewEmisData!$B:$B, $A12, NewEmisData!$C:$C, $H12, NewEmisData!$D:$D, W$2), SUMIFS(NewEmisData!G:G, NewEmisData!$A:$A, "LDV", NewEmisData!$B:$B, $A12, NewEmisData!$C:$C, $H12, NewEmisData!$D:$D, W$2)) -> 0.18897755 | X12: =$I12*IF($G12="Pickup", SUMIFS(NewEmisData!H:H, NewEmisData!$A:$A, "Pickup", NewEmisData!$B:$B, $A12, NewEmisData!$C:$C, $H12, NewEmisData!$D:$D, X$2), SUMIFS(NewEmisData!H:H, NewEmisData!$A:$A, "LDV", NewEmisData!$B:$B, $A12, NewEmisData!$C:$C, $H12, NewEmisData!$D:$D, X$2)) -> 0.12218818 | Y12: =$I12*IF($G12="Pickup", SUMIFS(NewEmisData!I:I, NewEmisData!$A:$A, "Pickup", NewEmisData!$B:$B, $A12, NewEmisData!$C:$C, $H12, NewEmisData!$D:$D, Y$2), SUMIFS(NewEmisData!I:I, NewEmisData!$A:$A, "LDV", NewEmisData!$B:$B, $A12, NewEmisData!$C:$C, $H12, NewEmisData!$D:$D, Y$2)) -> 0.073060825 | Z12: =$I12*IF($G12="Pickup", SUMIFS(NewEmisData!J:J, NewEmisData!$A:$A, "Pickup", NewEmisData!$B:$B, $A12, NewEmisData!$C:$C, $H12, NewEmisData!$D:$D, Z$2), SUMIFS(NewEmisData!J:J, NewEmisData!$A:$A, "LDV", NewEmisData!$B:$B, $A12, NewEmisData!$C:$C, $H12, NewEmisData!$D:$D, Z$2)) -> 0.053764321 | AA12: =$I12*IF($G12="Pickup", SUMIFS(NewEmisData!K:K, NewEmisData!$A:$A, "Pickup", NewEmisData!$B:$B, $A12, NewEmisData!$C:$C, $H12, NewEmisData!$D:$D, AA$2), SUMIFS(NewEmisData!K:K, NewEmisData!$A:$A, "LDV", NewEmisData!$B:$B, $A12, NewEmisData!$C:$C, $H12, NewEmisData!$D:$D, AA$2)) -> 0.045765874 | AB12: =$I12*IF($G12="Pickup", SUMIFS(NewEmisData!L:L, NewEmisData!$A:$A, "Pickup", NewEmisData!$B:$B, $A12, NewEmisData!$C:$C, $H12, NewEmisData!$D:$D, AB$2), SUMIFS(NewEmisData!L:L, NewEmisData!$A:$A, "LDV", NewEmisData!$B:$B, $A12, NewEmisData!$C:$C, $H12, NewEmisData!$D:$D, AB$2)) -> 0.043548109 | AC12: =$I12*IF($G12="Pickup", SUMIFS(NewEmisData!M:M, NewEmisData!$A:$A, "Pickup", NewEmisData!$B:$B, $A12, NewEmisData!$C:$C, $H12, NewEmisData!$D:$D, AC$2), SUMIFS(NewEmisData!M:M, NewEmisData!$A:$A, "LDV", NewEmisData!$B:$B, $A12, NewEmisData!$C:$C, $H12, NewEmisData!$D:$D, AC$2)) -> 0.042460978 | AD12: =AC12 -> 0.042460978 | AE12: =$I12*IF($G12="Pickup", SUMIFS(NewEmisData!E:E, NewEmisData!$A:$A, "Pickup", NewEmisData!$B:$B, $A12, NewEmisData!$C:$C, $H12, NewEmisData!$D:$D, AE$2), SUMIFS(NewEmisData!E:E, NewEmisData!$A:$A, "LDV", NewEmisData!$B:$B, $A12, NewEmisData!$C:$C, $H12, NewEmisData!$D:$D, AE$2)) -> 0.010474716 | AF12: =$I12*IF($G12="Pickup", SUMIFS(NewEmisData!F:F, NewEmisData!$A:$A, "Pickup", NewEmisData!$B:$B, $A12, NewEmisData!$C:$C, $H12, NewEmisData!$D:$D, AF$2), SUMIFS(NewEmisData!F:F, NewEmisData!$A:$A, "LDV", NewEmisData!$B:$B, $A12, NewEmisData!$C:$C, $H12, NewEmisData!$D:$D, AF$2)) -> 0.0099570765 | AG12: =$I12*IF($G12="Pickup", SUMIFS(NewEmisData!G:G, NewEmisData!$A:$A, "Pickup", NewEmisData!$B:$B, $A12, NewEmisData!$C:$C, $H12, NewEmisData!$D:$D, AG$2), SUMIFS(NewEmisData!G:G, NewEmisData!$A:$A, "LDV", NewEmisData!$B:$B, $A12, NewEmisData!$C:$C, $H12, NewEmisData!$D:$D, AG$2)) -> 0.0064196649 | AH12: =$I12*IF($G12="Pickup", SUMIFS(NewEmisData!H:H, NewEmisData!$A:$A, "Pickup", NewEmisData!$B:$B, $A12, NewEmisData!$C:$C, $H12, NewEmisData!$D:$D, AH$2), SUMIFS(NewEmisData!H:H, NewEmisData!$A:$A, "LDV", NewEmisData!$B:$B, $A12, NewEmisData!$C:$C, $H12, NewEmisData!$D:$D, AH$2)) -> 0.0054559953 | AI12: =$I12*IF($G12="Pickup", SUMIFS(NewEmisData!I:I, NewEmisData!$A:$A, "Pickup", NewEmisData!$B:$B, $A12, NewEmisData!$C:$C, $H12, NewEmisData!$D:$D, AI$2), SUMIFS(NewEmisData!I:I, NewEmisData!$A:$A, "LDV", NewEmisData!$B:$B, $A12, NewEmisData!$C:$C, $H12, NewEmisData!$D:$D, AI$2)) -> 0.0047175365 | AJ12: =$I12*IF($G12="Pickup", SUMIFS(NewEmisData!J:J, NewEmisData!$A:$A, "Pickup", NewEmisData!$B:$B, $A12, NewEmisData!$C:$C, $H12, NewEmisData!$D:$D, AJ$2), SUMIFS(NewEmisData!J:J, NewEmisData!$A:$A, "LDV", NewEmisData!$B:$B, $A12, NewEmisData!$C:$C, $H12, NewEmisData!$D:$D, AJ$2)) -> 0.0043018392 | AK12: =$I12*IF($G12="Pickup", SUMIFS(NewEmisData!K:K, NewEmisData!$A:$A, "Pickup", NewEmisData!$B:$B, $A12, NewEmisData!$C:$C, $H12, NewEmisData!$D:$D, AK$2), SUMIFS(NewEmisData!K:K, NewEmisData!$A:$A, "LDV", NewEmisData!$B:$B, $A12, NewEmisData!$C:$C, $H12, NewEmisData!$D:$D, AK$2)) -> 0.0041166816 | AL12: =$I12*IF($G12="Pickup", SUMIFS(NewEmisData!L:L, NewEmisData!$A:$A, "Pickup", NewEmisData!$B:$B, $A12, NewEmisData!$C:$C, $H12, NewEmisData!$D:$D, AL$2), SUMIFS(NewEmisData!L:L, NewEmisData!$A:$A, "LDV", NewEmisData!$B:$B, $A12, NewEmisData!$C:$C, $H12, NewEmisData!$D:$D, AL$2)) -> 0.0040509726 | AM12: =$I12*IF($G12="Pickup", SUMIFS(NewEmisData!M:M, NewEmisData!$A:$A, "Pickup", NewEmisData!$B:$B, $A12, NewEmisData!$C:$C, $H12, NewEmisData!$D:$D, AM$2), SUMIFS(NewEmisData!M:M, NewEmisData!$A:$A, "LDV", NewEmisData!$B:$B, $A12, NewEmisData!$C:$C, $H12, NewEmisData!$D:$D, AM$2)) -> 0.0040267597 | AN12: =AM12 -> 0.0040267597 | AO12: =$I12*IF($G12="Pickup", SUMIFS(NewEmisData!E:E, NewEmisData!$A:$A, "Pickup", NewEmisData!$B:$B, $A12, NewEmisData!$C:$C, $H12, NewEmisData!$D:$D, AO$2), SUMIFS(NewEmisData!E:E, NewEmisData!$A:$A, "LDV", NewEmisData!$B:$B, $A12, NewEmisData!$C:$C, $H12, NewEmisData!$D:$D, AO$2)) -> 0.11252984 | AP12: =$I12*IF($G12="Pickup", SUMIFS(NewEmisData!F:F, NewEmisData!$A:$A, "Pickup", NewEmisData!$B:$B, $A12, NewEmisData!$C:$C, $H12, NewEmisData!$D:$D, AP$2), SUMIFS(NewEmisData!F:F, NewEmisData!$A:$A, "LDV", NewEmisData!$B:$B, $A12, NewEmisData!$C:$C, $H12, NewEmisData!$D:$D, AP$2)) -> 0.10376481 | AQ12: =$I12*IF($G12="Pickup", SUMIFS(NewEmisData!G:G, NewEmisData!$A:$A, "Pickup", NewEmisData!$B:$B, $A12, NewEmisData!$C:$C, $H12, NewEmisData!$D:$D, AQ$2), SUMIFS(NewEmisData!G:G, NewEmisData!$A:$A, "LDV", NewEmisData!$B:$B, $A12, NewEmisData!$C:$C, $H12, NewEmisData!$D:$D, AQ$2)) -> 0.08190401 | AR12: =$I12*IF($G12="Pickup", SUMIFS(NewEmisData!H:H, NewEmisData!$A:$A, "Pickup", NewEmisData!$B:$B, $A12, NewEmisData!$C:$C, $H12, NewEmisData!$D:$D, AR$2), SUMIFS(NewEmisData!H:H, NewEmisData!$A:$A, "LDV", NewEmisData!$B:$B, $A12, NewEmisData!$C:$C, $H12, NewEmisData!$D:$D, AR$2)) -> 0.080372811 | AS12: =$I12*IF($G12="Pickup", SUMIFS(NewEmisData!I:I, NewEmisData!$A:$A, "Pickup", NewEmisData!$B:$B, $A12, NewEmisData!$C:$C, $H12, NewEmisData!$D:$D, AS$2), SUMIFS(NewEmisData!I:I, NewEmisData!$A:$A, "LDV", NewEmisData!$B:$B, $A12, NewEmisData!$C:$C, $H12, NewEmisData!$D:$D, AS$2)) -> 0.078826851 | AT12: =$I12*IF($G12="Pickup", SUMIFS(NewEmisData!J:J, NewEmisData!$A:$A, "Pickup", NewEmisData!$B:$B, $A12, NewEmisData!$C:$C, $H12, NewEmisData!$D:$D, AT$2), SUMIFS(NewEmisData!J:J, NewEmisData!$A:$A, "LDV", NewEmisData!$B:$B, $A12, NewEmisData!$C:$C, $H12, NewEmisData!$D:$D, AT$2)) -> 0.077629472 | AU12: =$I12*IF($G12="Pickup", SUMIFS(NewEmisData!K:K, NewEmisData!$A:$A, "Pickup", NewEmisData!$B:$B, $A12, NewEmisData!$C:$C, $H12, NewEmisData!$D:$D, AU$2), SUMIFS(NewEmisData!K:K, NewEmisData!$A:$A, "LDV", NewEmisData!$B:$B, $A12, NewEmisData!$C:$C, $H12, NewEmisData!$D:$D, AU$2)) -> 0.076869255 | AV12: =$I12*IF($G12="Pickup", SUMIFS(NewEmisData!L:L, NewEmisData!$A:$A, "Pickup", NewEmisData!$B:$B, $A12, NewEmisData!$C:$C, $H12, NewEmisData!$D:$D, AV$2), SUMIFS(NewEmisData!L:L, NewEmisData!$A:$A, "LDV", NewEmisData!$B:$B, $A12, NewEmisData!$C:$C, $H12, NewEmisData!$D:$D, AV$2)) -> 0.076489801 | AW12: =$I12*IF($G12="Pickup", SUMIFS(NewEmisData!M:M, NewEmisData!$A:$A, "Pickup", NewEmisData!$B:$B, $A12, NewEmisData!$C:$C, $H12, NewEmisData!$D:$D, AW$2), SUMIFS(NewEmisData!M:M, NewEmisData!$A:$A, "LDV", NewEmisData!$B:$B, $A12, NewEmisData!$C:$C, $H12, NewEmisData!$D:$D, AW$2)) -> 0.07627589 | AX12: =AW12 -> 0.07627589 | AY12: =$I12*IF($G12="Pickup", SUMIFS(NewEmisData!E:E, NewEmisData!$A:$A, "Pickup", NewEmisData!$B:$B, $A12, NewEmisData!$C:$C, $H12, NewEmisData!$D:$D, AY$2), SUMIFS(NewEmisData!E:E, NewEmisData!$A:$A, "LDV", NewEmisData!$B:$B, $A12, NewEmisData!$C:$C, $H12, NewEmisData!$D:$D, AY$2)) -> 0.029314011 | AZ12: =$I12*IF($G12="Pickup", SUMIFS(NewEmisData!F:F, NewEmisData!$A:$A, "Pickup", NewEmisData!$B:$B, $A12, NewEmisData!$C:$C, $H12, NewEmisData!$D:$D, AZ$2), SUMIFS(NewEmisData!F:F, NewEmisData!$A:$A, "LDV", NewEmisData!$B:$B, $A12, NewEmisData!$C:$C, $H12, NewEmisData!$D:$D, AZ$2)) -> 0.021560332 | BA12: =$I12*IF($G12="Pickup", SUMIFS(NewEmisData!G:G, NewEmisData!$A:$A, "Pickup", NewEmisData!$B:$B, $A12, NewEmisData!$C:$C, $H12, NewEmisData!$D:$D, BA$2), SUMIFS(NewEmisData!G:G, NewEmisData!$A:$A, "LDV", NewEmisData!$B:$B, $A12, NewEmisData!$C:$C, $H12, NewEmisData!$D:$D, BA$2)) -> 0.016135954 | BB12: =$I12*IF($G12="Pickup", SUMIFS(NewEmisData!H:H, NewEmisData!$A:$A, "Pickup", NewEmisData!$B:$B, $A12, NewEmisData!$C:$C, $H12, NewEmisData!$D:$D, BB$2), SUMIFS(NewEmisData!H:H, NewEmisData!$A:$A, "LDV", NewEmisData!$B:$B, $A12, NewEmisData!$C:$C, $H12, NewEmisData!$D:$D, BB$2)) -> 0.014781439 | BC12: =$I12*IF($G12="Pickup", SUMIFS(NewEmisData!I:I, NewEmisData!$A:$A, "Pickup", NewEmisData!$B:$B, $A12, NewEmisData!$C:$C, $H12, NewEmisData!$D:$D, BC$2), SUMIFS(NewEmisData!I:I, NewEmisData!$A:$A, "LDV", NewEmisData!$B:$B, $A12, NewEmisData!$C:$C, $H12, NewEmisData!$D:$D, BC$2)) -> 0.013413838 | BD12: =$I12*IF($G12="Pickup", SUMIFS(NewEmisData!J:J, NewEmisData!$A:$A, "Pickup", NewEmisData!$B:$B, $A12, NewEmisData!$C:$C, $H12, NewEmisData!$D:$D, BD$2), SUMIFS(NewEmisData!J:J, NewEmisData!$A:$A, "LDV", NewEmisData!$B:$B, $A12, NewEmisData!$C:$C, $H12, NewEmisData!$D:$D, BD$2)) -> 0.012354573 | BE12: =$I12*IF($G12="Pickup", SUMIFS(NewEmisData!K:K, NewEmisData!$A:$A, "Pickup", NewEmisData!$B:$B, $A12, NewEmisData!$C:$C, $H12, NewEmisData!$D:$D, BE$2), SUMIFS(NewEmisData!K:K, NewEmisData!$A:$A, "LDV", NewEmisData!$B:$B, $A12, NewEmisData!$C:$C, $H12, NewEmisData!$D:$D, BE$2)) -> 0.011682065 | BF12: =$I12*IF($G12="Pickup", SUMIFS(NewEmisData!L:L, NewEmisData!$A:$A, "Pickup", NewEmisData!$B:$B, $A12, NewEmisData!$C:$C, $H12, NewEmisData!$D:$D, BF$2), SUMIFS(NewEmisData!L:L, NewEmisData!$A:$A, "LDV", NewEmisData!$B:$B, $A12, NewEmisData!$C:$C, $H12, NewEmisData!$D:$D, BF$2)) -> 0.011346346 | BG12: =$I12*IF($G12="Pickup", SUMIFS(NewEmisData!M:M, NewEmisData!$A:$A, "Pickup", NewEmisData!$B:$B, $A12, NewEmisData!$C:$C, $H12, NewEmisData!$D:$D, BG$2), SUMIFS(NewEmisData!M:M, NewEmisData!$A:$A, "LDV", NewEmisData!$B:$B, $A12, NewEmisData!$C:$C, $H12, NewEmisData!$D:$D, BG$2)) -> 0.011157149 | BH12: =BG12 -> 0.011157149 | BI12: =$I12*IF($G12="Pickup", SUMIFS(NewEmisData!E:E, NewEmisData!$A:$A, "Pickup", NewEmisData!$B:$B, $A12, NewEmisData!$C:$C, $H12, NewEmisData!$D:$D, BI$2), SUMIFS(NewEmisData!E:E, NewEmisData!$A:$A, "LDV", NewEmisData!$B:$B, $A12, NewEmisData!$C:$C, $H12, NewEmisData!$D:$D, BI$2)) -> 7.7707306 | BJ12: =$I12*IF($G12="Pickup", SUMIFS(NewEmisData!F:F, NewEmisData!$A:$A, "Pickup", NewEmisData!$B:$B, $A12, NewEmisData!$C:$C, $H12, NewEmisData!$D:$D, BJ$2), SUMIFS(NewEmisData!F:F, NewEmisData!$A:$A, "LDV", NewEmisData!$B:$B, $A12, NewEmisData!$C:$C, $H12, NewEmisData!$D:$D, BJ$2)) -> 4.4247869 | BK12: =$I12*IF($G12="Pickup", SUMIFS(NewEmisData!G:G, NewEmisData!$A:$A, "Pickup", NewEmisData!$B:$B, $A12, NewEmisData!$C:$C, $H12, NewEmisData!$D:$D, BK$2), SUMIFS(NewEmisData!G:G, NewEmisData!$A:$A, "LDV", NewEmisData!$B:$B, $A12, NewEmisData!$C:$C, $H12, NewEmisData!$D:$D, BK$2)) -> 2.6540718 | BL12: =$I12*IF($G12="Pickup", SUMIFS(NewEmisData!H:H, NewEmisData!$A:$A, "Pickup", NewEmisData!$B:$B, $A12, NewEmisData!$C:$C, $H12, NewEmisData!$D:$D, BL$2), SUMIFS(NewEmisData!H:H, NewEmisData!$A:$A, "LDV", NewEmisData!$B:$B, $A12, NewEmisData!$C:$C, $H12, NewEmisData!$D:$D, BL$2)) -> 2.0604732 | BM12: =$I12*IF($G12="Pickup", SUMIFS(NewEmisData!I:I, NewEmisData!$A:$A, "Pickup", NewEmisData!$B:$B, $A12, NewEmisData!$C:$C, $H12, NewEmisData!$D:$D, BM$2), SUMIFS(NewEmisData!I:I, NewEmisData!$A:$A, "LDV", NewEmisData!$B:$B, $A12, NewEmisData!$C:$C, $H12, NewEmisData!$D:$D, BM$2)) -> 1.4768703 | BN12: =$I12*IF($G12="Pickup", SUMIFS(NewEmisData!J:J, NewEmisData!$A:$A, "Pickup", NewEmisData!$B:$B, $A12, NewEmisData!$C:$C, $H12, NewEmisData!$D:$D, BN$2), SUMIFS(NewEmisData!J:J, NewEmisData!$A:$A, "LDV", NewEmisData!$B:$B, $A12, NewEmisData!$C:$C, $H12, NewEmisData!$D:$D, BN$2)) -> 1.1597746 | BO12: =$I12*IF($G12="Pickup", SUMIFS(NewEmisData!K:K, NewEmisData!$A:$A, "Pickup", NewEmisData!$B:$B, $A12, NewEmisData!$C:$C, $H12, NewEmisData!$D:$D, BO$2), SUMIFS(NewEmisData!K:K, NewEmisData!$A:$A, "LDV", NewEmisData!$B:$B, $A12, NewEmisData!$C:$C, $H12, NewEmisData!$D:$D, BO$2)) -> 1.0179564 | BP12: =$I12*IF($G12="Pickup", SUMIFS(NewEmisData!L:L, NewEmisData!$A:$A, "Pickup", NewEmisData!$B:$B, $A12, NewEmisData!$C:$C, $H12, NewEmisData!$D:$D, BP$2), SUMIFS(NewEmisData!L:L, NewEmisData!$A:$A, "LDV", NewEmisData!$B:$B, $A12, NewEmisData!$C:$C, $H12, NewEmisData!$D:$D, BP$2)) -> 0.97243112 | BQ12: =$I12*IF($G12="Pickup", SUMIFS(NewEmisData!M:M, NewEmisData!$A:$A, "Pickup", NewEmisData!$B:$B, $A12, NewEmisData!$C:$C, $H12, NewEmisData!$D:$D, BQ$2), SUMIFS(NewEmisData!M:M, NewEmisData!$A:$A, "LDV", NewEmisData!$B:$B, $A12, NewEmisData!$C:$C, $H12, NewEmisData!$D:$D, BQ$2)) -> 0.94396289 | BR12: =BQ12 -> 0.94396289 | BS12: =$I12*IF($G12="Pickup", SUMIFS(NewEmisData!E:E, NewEmisData!$A:$A, "Pickup", NewEmisData!$B:$B, $A12, NewEmisData!$C:$C, $H12, NewEmisData!$D:$D, BS$2), SUMIFS(NewEmisData!E:E, NewEmisData!$A:$A, "LDV", NewEmisData!$B:$B, $A12, NewEmisData!$C:$C, $H12, NewEmisData!$D:$D, BS$2)) -> 0.86893952 | BT12: =$I12*IF($G12="Pickup", SUMIFS(NewEmisData!F:F, NewEmisData!$A:$A, "Pickup", NewEmisData!$B:$B, $A12, NewEmisData!$C:$C, $H12, NewEmisData!$D:$D, BT$2), SUMIFS(NewEmisData!F:F, NewEmisData!$A:$A, "LDV", NewEmisData!$B:$B, $A12, NewEmisData!$C:$C, $H12, NewEmisData!$D:$D, BT$2)) -> 0.46984847 | BU12: =$I12*IF($G12="Pickup", SUMIFS(NewEmisData!G:G, NewEmisData!$A:$A, "Pickup", NewEmisData!$B:$B, $A12, NewEmisData!$C:$C, $H12, NewEmisData!$D:$D, BU$2), SUMIFS(NewEmisData!G:G, NewEmisData!$A:$A, "LDV", NewEmisData!$B:$B, $A12, NewEmisData!$C:$C, $H12, NewEmisData!$D:$D, BU$2)) -> 0.25380787 | BV12: =$I12*IF($G12="Pickup", SUMIFS(NewEmisData!H:H, NewEmisData!$A:$A, "Pickup", NewEmisData!$B:$B, $A12, NewEmisData!$C:$C, $H12, NewEmisData!$D:$D, BV$2), SUMIFS(NewEmisData!H:H, NewEmisData!$A:$A, "LDV", NewEmisData!$B:$B, $A12, NewEmisData!$C:$C, $H12, NewEmisData!$D:$D, BV$2)) -> 0.20500079 | BW12: =$I12*IF($G12="Pickup", SUMIFS(NewEmisData!I:I, NewEmisData!$A:$A, "Pickup", NewEmisData!$B:$B, $A12, NewEmisData!$C:$C, $H12, NewEmisData!$D:$D, BW$2), SUMIFS(NewEmisData!I:I, NewEmisData!$A:$A, "LDV", NewEmisData!$B:$B, $A12, NewEmisData!$C:$C, $H12, NewEmisData!$D:$D, BW$2)) -> 0.15182918 | BX12: =$I12*IF($G12="Pickup", SUMIFS(NewEmisData!J:J, NewEmisData!$A:$A, "Pickup", NewEmisData!$B:$B, $A12, NewEmisData!$C:$C, $H12, NewEmisData!$D:$D, BX$2), SUMIFS(NewEmisData!J:J, NewEmisData!$A:$A, "LDV", NewEmisData!$B:$B, $A12, NewEmisData!$C:$C, $H12, NewEmisData!$D:$D, BX$2)) -> 0.12865137 | BY12: =$I12*IF($G12="Pickup", SUMIFS(NewEmisData!K:K, NewEmisData!$A:$A, "Pickup", NewEmisData!$B:$B, $A12, NewEmisData!$C:$C, $H12, NewEmisData!$D:$D, BY$2), SUMIFS(NewEmisData!K:K, NewEmisData!$A:$A, "LDV", NewEmisData!$B:$B, $A12, NewEmisData!$C:$C, $H12, NewEmisData!$D:$D, BY$2)) -> 0.11591502 | BZ12: =$I12*IF($G12="Pickup", SUMIFS(NewEmisData!L:L, NewEmisData!$A:$A, "Pickup", NewEmisData!$B:$B, $A12, NewEmisData!$C:$C, $H12, NewEmisData!$D:$D, BZ$2), SUMIFS(NewEmisData!L:L, NewEmisData!$A:$A, "LDV", NewEmisData!$B:$B, $A12, NewEmisData!$C:$C, $H12, NewEmisData!$D:$D, BZ$2)) -> 0.11095133 | CA12: =$I12*IF($G12="Pickup", SUMIFS(NewEmisData!M:M, NewEmisData!$A:$A, "Pickup", NewEmisData!$B:$B, $A12, NewEmisData!$C:$C, $H12, NewEmisData!$D:$D, CA$2), SUMIFS(NewEmisData!M:M, NewEmisData!$A:$A, "LDV", NewEmisData!$B:$B, $A12, NewEmisData!$C:$C, $H12, NewEmisData!$D:$D, CA$2)) -> 0.10699337 | CB12: =CA12 -> 0.10699337 | CC12: =$I12*IF($G12="Pickup", SUMIFS(NewEmisData!E:E, NewEmisData!$A:$A, "Pickup", NewEmisData!$B:$B, $A12, NewEmisData!$C:$C, $H12, NewEmisData!$D:$D, CC$2), SUMIFS(NewEmisData!E:E, NewEmisData!$A:$A, "LDV", NewEmisData!$B:$B, $A12, NewEmisData!$C:$C, $H12, NewEmisData!$D:$D, CC$2)) -> 0.051125584 | CD12: =$I12*IF($G12="Pickup", SUMIFS(NewEmisData!F:F, NewEmisData!$A:$A, "Pickup", NewEmisData!$B:$B, $A12, NewEmisData!$C:$C, $H12, NewEmisData!$D:$D, CD$2), SUMIFS(NewEmisData!F:F, NewEmisData!$A:$A, "LDV", NewEmisData!$B:$B, $A12, NewEmisData!$C:$C, $H12, NewEmisData!$D:$D, CD$2)) -> 0.037154394 | CE12: =$I12*IF($G12="Pickup", SUMIFS(NewEmisData!G:G, NewEmisData!$A:$A, "Pickup", NewEmisData!$B:$B, $A12, NewEmisData!$C:$C, $H12, NewEmisData!$D:$D, CE$2), SUMIFS(NewEmisData!G:G, NewEmisData!$A:$A, "LDV", NewEmisData!$B:$B, $A12, NewEmisData!$C:$C, $H12, NewEmisData!$D:$D, CE$2)) -> 0.028853651 | CF12: =$I12*IF($G12="Pickup", SUMIFS(NewEmisData!H:H, NewEmisData!$A:$A, "Pickup", NewEmisData!$B:$B, $A12, NewEmisData!$C:$C, $H12, NewEmisData!$D:$D, CF$2), SUMIFS(NewEmisData!H:H, NewEmisData!$A:$A, "LDV", NewEmisData!$B:$B, $A12, NewEmisData!$C:$C, $H12, NewEmisData!$D:$D, CF$2)) -> 0.027537521 | CG12: =$I12*IF($G12="Pickup", SUMIFS(NewEmisData!I:I, NewEmisData!$A:$A, "Pickup", NewEmisData!$B:$B, $A12, NewEmisData!$C:$C, $H12, NewEmisData!$D:$D, CG$2), SUMIFS(NewEmisData!I:I, NewEmisData!$A:$A, "LDV", NewEmisData!$B:$B, $A12, NewEmisData!$C:$C, $H12, NewEmisData!$D:$D, CG$2)) -> 0.026666634 | CH12: =$I12*IF($G12="Pickup", SUMIFS(NewEmisData!J:J, NewEmisData!$A:$A, "Pickup", NewEmisData!$B:$B, $A12, NewEmisData!$C:$C, $H12, NewEmisData!$D:$D, CH$2), SUMIFS(NewEmisData!J:J, NewEmisData!$A:$A, "LDV", NewEmisData!$B:$B, $A12, NewEmisData!$C:$C, $H12, NewEmisData!$D:$D, CH$2)) -> 0.025980349 | CI12: =$I12*IF($G12="Pickup", SUMIFS(NewEmisData!K:K, NewEmisData!$A:$A, "Pickup", NewEmisData!$B:$B, $A12, NewEmisData!$C:$C, $H12, NewEmisData!$D:$D, CI$2), SUMIFS(NewEmisData!K:K, NewEmisData!$A:$A, "LDV", NewEmisData!$B:$B, $A12, NewEmisData!$C:$C, $H12, NewEmisData!$D:$D, CI$2)) -> 0.025978185 | CJ12: =$I12*IF($G12="Pickup", SUMIFS(NewEmisData!L:L, NewEmisData!$A:$A, "Pickup", NewEmisData!$B:$B, $A12, NewEmisData!$C:$C, $H12, NewEmisData!$D:$D, CJ$2), SUMIFS(NewEmisData!L:L, NewEmisData!$A:$A, "LDV", NewEmisData!$B:$B, $A12, NewEmisData!$C:$C, $H12, NewEmisData!$D:$D, CJ$2)) -> 0.025977589 | CK12: =$I12*IF($G12="Pickup", SUMIFS(NewEmisData!M:M, NewEmisData!$A:$A, "Pickup", NewEmisData!$B:$B, $A12, NewEmisData!$C:$C, $H12, NewEmisData!$D:$D, CK$2), SUMIFS(NewEmisData!M:M, NewEmisData!$A:$A, "LDV", NewEmisData!$B:$B, $A12, NewEmisData!$C:$C, $H12, NewEmisData!$D:$D, CK$2)) -> 0.025976994 | CL12: =CK12 -> 0.025976994 | CM12: =$I12*IF($G12="Pickup", SUMIFS(NewEmisData!E:E, NewEmisData!$A:$A, "Pickup", NewEmisData!$B:$B, $A12, NewEmisData!$C:$C, $H12, NewEmisData!$D:$D, CM$2), SUMIFS(NewEmisData!E:E, NewEmisData!$A:$A, "LDV", NewEmisData!$B:$B, $A12, NewEmisData!$C:$C, $H12, NewEmisData!$D:$D, CM$2)) -> 0.022752592 | CN12: =$I12*IF($G12="Pickup", SUMIFS(NewEmisData!F:F, NewEmisData!$A:$A, "Pickup", NewEmisData!$B:$B, $A12, NewEmisData!$C:$C, $H12, NewEmisData!$D:$D, CN$2), SUMIFS(NewEmisData!F:F, NewEmisData!$A:$A, "LDV", NewEmisData!$B:$B, $A12, NewEmisData!$C:$C, $H12, NewEmisData!$D:$D, CN$2)) -> 0.014156662 | CO12: =$I12*IF($G12="Pickup", SUMIFS(NewEmisData!G:G, NewEmisData!$A:$A, "Pickup", NewEmisData!$B:$B, $A12, NewEmisData!$C:$C, $H12, NewEmisData!$D:$D, CO$2), SUMIFS(NewEmisData!G:G, NewEmisData!$A:$A, "LDV", NewEmisData!$B:$B, $A12, NewEmisData!$C:$C, $H12, NewEmisData!$D:$D, CO$2)) -> 0.0092962854 | CP12: =$I12*IF($G12="Pickup", SUMIFS(NewEmisData!H:H, NewEmisData!$A:$A, "Pickup", NewEmisData!$B:$B, $A12, NewEmisData!$C:$C, $H12, NewEmisData!$D:$D, CP$2), SUMIFS(NewEmisData!H:H, NewEmisData!$A:$A, "LDV", NewEmisData!$B:$B, $A12, NewEmisData!$C:$C, $H12, NewEmisData!$D:$D, CP$2)) -> 0.0076962231 | CQ12: =$I12*IF($G12="Pickup", SUMIFS(NewEmisData!I:I, NewEmisData!$A:$A, "Pickup", NewEmisData!$B:$B, $A12, NewEmisData!$C:$C, $H12, NewEmisData!$D:$D, CQ$2), SUMIFS(NewEmisData!I:I, NewEmisData!$A:$A, "LDV", NewEmisData!$B:$B, $A12, NewEmisData!$C:$C, $H12, NewEmisData!$D:$D, CQ$2)) -> 0.0069434858 | CR12: =$I12*IF($G12="Pickup", SUMIFS(NewEmisData!J:J, NewEmisData!$A:$A, "Pickup", NewEmisData!$B:$B, $A12, NewEmisData!$C:$C, $H12, NewEmisData!$D:$D, CR$2), SUMIFS(NewEmisData!J:J, NewEmisData!$A:$A, "LDV", NewEmisData!$B:$B, $A12, NewEmisData!$C:$C, $H12, NewEmisData!$D:$D, CR$2)) -> 0.0066235502 | CS12: =$I12*IF($G12="Pickup", SUMIFS(NewEmisData!K:K, NewEmisData!$A:$A, "Pickup", NewEmisData!$B:$B, $A12, NewEmisData!$C:$C, $H12, NewEmisData!$D:$D, CS$2), SUMIFS(NewEmisData!K:K, NewEmisData!$A:$A, "LDV", NewEmisData!$B:$B, $A12, NewEmisData!$C:$C, $H12, NewEmisData!$D:$D, CS$2)) -> 0.0065909545 | CT12: =$I12*IF($G12="Pickup", SUMIFS(NewEmisData!L:L, NewEmisData!$A:$A, "Pickup", NewEmisData!$B:$B, $A12, NewEmisData!$C:$C, $H12, NewEmisData!$D:$D, CT$2), SUMIFS(NewEmisData!L:L, NewEmisData!$A:$A, "LDV", NewEmisData!$B:$B, $A12, NewEmisData!$C:$C, $H12, NewEmisData!$D:$D, CT$2)) -> 0.0065377802 | CU12: =$I12*IF($G12="Pickup", SUMIFS(NewEmisData!M:M, NewEmisData!$A:$A, "Pickup", NewEmisData!$B:$B, $A12, NewEmisData!$C:$C, $H12, NewEmisData!$D:$D, CU$2), SUMIFS(NewEmisData!M:M, NewEmisData!$A:$A, "LDV", NewEmisData!$B:$B, $A12, NewEmisData!$C:$C, $H12, NewEmisData!$D:$D, CU$2)) -> 0.0065374276 | CV12: =CU12 -> 0.0065374276 | CW12: 0.0030448047 | CX12: 0.0018865909 | CY12: 0.0015570268 | CZ12: 0.0012432183 | DA12: 0.00092522519 | DB12: 0.00072309457 | DC12: 0.00068940707 | DD12: 0.00068441484 | DE12: 0.00068634617 | DF12: 0.00068634617 | DG12: =$I12*IF($G12="Pickup", SUMIFS(NewEmisData!E:E, NewEmisData!$A:$A, "Pickup", NewEmisData!$B:$B, $A12, NewEmisData!$C:$C, $H12, NewEmisData!$D:$D, DG$2), SUMIFS(NewEmisData!E:E, NewEmisData!$A:$A, "LDV", NewEmisData!$B:$B, $A12, NewEmisData!$C:$C, $H12, NewEmisData!$D:$D, DG$2)) -> 0 | DH12: =$I12*IF($G12="Pickup", SUMIFS(NewEmisData!F:F, NewEmisData!$A:$A, "Pickup", NewEmisData!$B:$B, $A12, NewEmisData!$C:$C, $H12, NewEmisData!$D:$D, DH$2), SUMIFS(NewEmisData!F:F, NewEmisData!$A:$A, "LDV", NewEmisData!$B:$B, $A12, NewEmisData!$C:$C, $H12, NewEmisData!$D:$D, DH$2)) -> 0 | DI12: =$I12*IF($G12="Pickup", SUMIFS(NewEmisData!G:G, NewEmisData!$A:$A, "Pickup", NewEmisData!$B:$B, $A12, NewEmisData!$C:$C, $H12, NewEmisData!$D:$D, DI$2), SUMIFS(NewEmisData!G:G, NewEmisData!$A:$A, "LDV", NewEmisData!$B:$B, $A12, NewEmisData!$C:$C, $H12, NewEmisData!$D:$D, DI$2)) -> 0 | DJ12: =$I12*IF($G12="Pickup", SUMIFS(NewEmisData!H:H, NewEmisData!$A:$A, "Pickup", NewEmisData!$B:$B, $A12, NewEmisData!$C:$C, $H12, NewEmisData!$D:$D, DJ$2), SUMIFS(NewEmisData!H:H, NewEmisData!$A:$A, "LDV", NewEmisData!$B:$B, $A12, NewEmisData!$C:$C, $H12, NewEmisData!$D:$D, DJ$2)) -> 0 | DK12: =$I12*IF($G12="Pickup", SUMIFS(NewEmisData!I:I, NewEmisData!$A:$A, "Pickup", NewEmisData!$B:$B, $A12, NewEmisData!$C:$C, $H12, NewEmisData!$D:$D, DK$2), SUMIFS(NewEmisData!I:I, NewEmisData!$A:$A, "LDV", NewEmisData!$B:$B, $A12, NewEmisData!$C:$C, $H12, NewEmisData!$D:$D, DK$2)) -> 0 | DL12: =$I12*IF($G12="Pickup", SUMIFS(NewEmisData!J:J, NewEmisData!$A:$A, "Pickup", NewEmisData!$B:$B, $A12, NewEmisData!$C:$C, $H12, NewEmisData!$D:$D, DL$2), SUMIFS(NewEmisData!J:J, NewEmisData!$A:$A, "LDV", NewEmisData!$B:$B, $A12, NewEmisData!$C:$C, $H12, NewEmisData!$D:$D, DL$2)) -> 0 | DM12: =$I12*IF($G12="Pickup", SUMIFS(NewEmisData!K:K, NewEmisData!$A:$A, "Pickup", NewEmisData!$B:$B, $A12, NewEmisData!$C:$C, $H12, NewEmisData!$D:$D, DM$2), SUMIFS(NewEmisData!K:K, NewEmisData!$A:$A, "LDV", NewEmisData!$B:$B, $A12, NewEmisData!$C:$C, $H12, NewEmisData!$D:$D, DM$2)) -> 0 | DN12: =$I12*IF($G12="Pickup", SUMIFS(NewEmisData!L:L, NewEmisData!$A:$A, "Pickup", NewEmisData!$B:$B, $A12, NewEmisData!$C:$C, $H12, NewEmisData!$D:$D, DN$2), SUMIFS(NewEmisData!L:L, NewEmisData!$A:$A, "LDV", NewEmisData!$B:$B, $A12, NewEmisData!$C:$C, $H12, NewEmisData!$D:$D, DN$2)) -> 0 | DO12: =$I12*IF($G12="Pickup", SUMIFS(NewEmisData!M:M, NewEmisData!$A:$A, "Pickup", NewEmisData!$B:$B, $A12, NewEmisData!$C:$C, $H12, NewEmisData!$D:$D, DO$2), SUMIFS(NewEmisData!M:M, NewEmisData!$A:$A, "LDV", NewEmisData!$B:$B, $A12, NewEmisData!$C:$C, $H12, NewEmisData!$D:$D, DO$2)) -> 0 | DP12: =DO12 -> 0 | DQ12: =$I12*IF($G12="Pickup", SUMIFS(NewEmisData!E:E, NewEmisData!$A:$A, "Pickup", NewEmisData!$B:$B, $A12, NewEmisData!$C:$C, $H12, NewEmisData!$D:$D, DQ$2), SUMIFS(NewEmisData!E:E, NewEmisData!$A:$A, "LDV", NewEmisData!$B:$B, $A12, NewEmisData!$C:$C, $H12, NewEmisData!$D:$D, DQ$2)) -> 0.017231431 | DR12: =$I12*IF($G12="Pickup", SUMIFS(NewEmisData!F:F, NewEmisData!$A:$A, "Pickup", NewEmisData!$B:$B, $A12, NewEmisData!$C:$C, $H12, NewEmisData!$D:$D, DR$2), SUMIFS(NewEmisData!F:F, NewEmisData!$A:$A, "LDV", NewEmisData!$B:$B, $A12, NewEmisData!$C:$C, $H12, NewEmisData!$D:$D, DR$2)) -> 0.0089963646 | DS12: =$I12*IF($G12="Pickup", SUMIFS(NewEmisData!G:G, NewEmisData!$A:$A, "Pickup", NewEmisData!$B:$B, $A12, NewEmisData!$C:$C, $H12, NewEmisData!$D:$D, DS$2), SUMIFS(NewEmisData!G:G, NewEmisData!$A:$A, "LDV", NewEmisData!$B:$B, $A12, NewEmisData!$C:$C, $H12, NewEmisData!$D:$D, DS$2)) -> 0.0056961523 | DT12: =$I12*IF($G12="Pickup", SUMIFS(NewEmisData!H:H, NewEmisData!$A:$A, "Pickup", NewEmisData!$B:$B, $A12, NewEmisData!$C:$C, $H12, NewEmisData!$D:$D, DT$2), SUMIFS(NewEmisData!H:H, NewEmisData!$A:$A, "LDV", NewEmisData!$B:$B, $A12, NewEmisData!$C:$C, $H12, NewEmisData!$D:$D, DT$2)) -> 0.0043151144 | DU12: =$I12*IF($G12="Pickup", SUMIFS(NewEmisData!I:I, NewEmisData!$A:$A, "Pickup", NewEmisData!$B:$B, $A12, NewEmisData!$C:$C, $H12, NewEmisData!$D:$D, DU$2), SUMIFS(NewEmisData!I:I, NewEmisData!$A:$A, "LDV", NewEmisData!$B:$B, $A12, NewEmisData!$C:$C, $H12, NewEmisData!$D:$D, DU$2)) -> 0.0033502898 | DV12: =$I12*IF($G12="Pickup", SUMIFS(NewEmisData!J:J, NewEmisData!$A:$A, "Pickup", NewEmisData!$B:$B, $A12, NewEmisData!$C:$C, $H12, NewEmisData!$D:$D, DV$2), SUMIFS(NewEmisData!J:J, NewEmisData!$A:$A, "LDV", NewEmisData!$B:$B, $A12, NewEmisData!$C:$C, $H12, NewEmisData!$D:$D, DV$2)) -> 0.0029288859 | DW12: =$I12*IF($G12="Pickup", SUMIFS(NewEmisData!K:K, NewEmisData!$A:$A, "Pickup", NewEmisData!$B:$B, $A12, NewEmisData!$C:$C, $H12, NewEmisData!$D:$D, DW$2), SUMIFS(NewEmisData!K:K, NewEmisData!$A:$A, "LDV", NewEmisData!$B:$B, $A12, NewEmisData!$C:$C, $H12, NewEmisData!$D:$D, DW$2)) -> 0.0026889749 | DX12: =$I12*IF($G12="Pickup", SUMIFS(NewEmisData!L:L, NewEmisData!$A:$A, "Pickup", NewEmisData!$B:$B, $A12, NewEmisData!$C:$C, $H12, NewEmisData!$D:$D, DX$2), SUMIFS(NewEmisData!L:L, NewEmisData!$A:$A, "LDV", NewEmisData!$B:$B, $A12, NewEmisData!$C:$C, $H12, NewEmisData!$D:$D, DX$2)) -> 0.0026131015 | DY12: =$I12*IF($G12="Pickup", SUMIFS(NewEmisData!M:M, NewEmisData!$A:$A, "Pickup", NewEmisData!$B:$B, $A12, NewEmisData!$C:$C, $H12, NewEmisData!$D:$D, DY$2), SUMIFS(NewEmisData!M:M, NewEmisData!$A:$A, "LDV", NewEmisData!$B:$B, $A12, NewEmisData!$C:$C, $H12, NewEmisData!$D:$D, DY$2)) -> 0.0025757099 | DZ12: =DY12 -> 0.0025757099 | EA12: =K12 -> 605.35194 | EB12: =L12 -> 575.43678 | EC12: =M12 -> 447.50307 | ED12: =N12 -> 380.32749 | EE12: =O12 -> 328.85087 | EF12: =P12 -> 299.87343 | EG12: =Q12 -> 286.96646 | EH12: =R12 -> 282.38592 | ... FX12: =BH12 -> 0.011157149
