Workbook
Name AnswerData: #REF!
Name AnswerData: #REF!
Name bprint: #REF!
Name btu_per_watthr: '[1]Conversion Factors'!$B$5
Name CMM_SUPPLY_CRV_TABLE: [2]cum2025curves!#REF!
Name cprint: #REF!
Name days_per_year: '[1]Conversion Factors'!$B$3
Name dollar____per__m: '[1]Conversion Factors'!$B$7
Name exch_rate: #REF!
Name exch_rate: #REF!
Name fitfile: [3]MODEL!$D$38
Name hours_per_day: '[1]Conversion Factors'!$B$2
Name INF: [3]MODEL!$H$14
Name j_per_btu: '[1]Conversion Factors'!$B$4
Name j_per_pj: '[1]Conversion Factors'!$B$6
Name lumens_per_billion_lumens: '[1]Conversion Factors'!$B$9
Name MAXREC: #REF!
Name million_short_tons_to_short_ton: [4]Steps!$Y$5
Name MMBTU_to_PJ: [4]Steps!$Y$6
Name PPP: [3]MODEL!$D$12
Name PPPEX: [3]MODEL!$D$13
Name rail_coal: #REF!
Name rail_coal: #REF!
Name region1: [5]Regions!$B$3:$C$61
Name TECHNAME: #REF!
Name TRNDTYPE: #REF!

Sheet ANSv6.1-Commodities
A1: ANSWER-Commodities
B7: CommName | C7: CommDesc | D7: CommUnit | E7: Set Memberships | F7: Comment

Sheet Commodities
B1: Commodities | C1: _GLOBAL,R0,R1,R2,R3,R4,R5,R6
B6: ~FI_Comm
B7: Region | C7: CommName | D7: CommDesc | E7: Unit | F7: Csets | G7: LimType | H7: CTSLvl | I7: PeakTS | J7: Ctype | O7: Comment
B8: * Natural Gas Supply Commodities - Domestic and Imported
B9: R1,R2,R3,R4,R5,R6 | C9: NGA | D9: Natural Gas | E9: PJ | F9: NRG
B10: R1,R2,R3,R4,R5,R6 | C10: NGAD | D10: Domestic Natural Gas | E10: PJ
B11: R1,R2,R3,R4,R5,R6 | C11: NGAD0 | D11: Domestic Natural Gas - D0 | E11: PJ
B12: R1 | C12: NGAD1 | D12: Domestic Natural Gas - R1 | E12: PJ
B13: R2 | C13: NGAD2 | D13: Domestic Natural Gas - R2 | E13: PJ
B14: R3 | C14: NGAD3 | D14: Domestic Natural Gas - R3 | E14: PJ
B15: R4 | C15: NGAD4 | D15: Domestic Natural Gas - R4 | E15: PJ
B16: R5 | C16: NGAD5 | D16: Domestic Natural Gas - R5 | E16: PJ
B17: R6 | C17: NGAD6 | D17: Domestic Natural Gas - R6 | E17: PJ
B18: R1,R2,R3,R4,R5,R6 | C18: NGAR1 | D18: Natural Gas - R1 | E18: PJ
B19: R1,R2,R3,R4,R5,R6 | C19: NGAR2 | D19: Natural Gas - R2 | E19: PJ
B20: R1,R2,R3,R4,R5,R6 | C20: NGAR3 | D20: Natural Gas - R3 | E20: PJ
B21: R1,R2,R3,R4,R5,R6 | C21: NGAR4 | D21: Natural Gas - R4 | E21: PJ
... B43: R1,R2,R3,R4,R5,R6 | C43: NGLR6 | D43: Traded natural gas plant liquids from R6 | E43: PJ
B44: * Natural Gas End-Use Commodities
B45: R1,R2,R3,R4,R5,R6 | C45: RESNGA | D45: Natural gas to Residential sector | E45: PJ | F45: NRG
B46: R1,R2,R3,R4,R5,R6 | C46: COMNGA | D46: Natural gas to Commercial sector | E46: PJ
B47: R1,R2,R3,R4,R5,R6 | C47: INDNGA | D47: Natural gas to Industrial sector | E47: PJ
B48: R1,R2,R3,R4,R5,R6 | C48: ELCNGA | D48: Natural gas to Electricity generation | E48: PJ
B49: R1,R2,R3,R4,R5,R6 | C49: TRNNGA | D49: Natural gas to Transportation sector | E49: PJ
B50: *R1,R2,R3,R4,R5,R6 | C50: LPG | D50: LPG from NGL | E50: PJ
B51: *R1,R2,R3,R4,R5,R7 | C51: PFS | D51: PFS from NGL | E51: PJ
B52: *R1,R2,R3,R4,R5,R8 | C52: PENTS | D52: Pentanes from NGL | E52: PJ
B53: *R1,R2,R3,R4,R5,R9 | C53: GSR | D53: NGL Pentanes to gasoline | E53: PJ
B54: *R1,R2,R3,R4,R5,R10 | C54: DENAT | D54: NGL Pentanes to ethanol denaturant | E54: PJ
B55: *R1,R2,R3,R4,R5,R11 | C55: PFS_NGL | D55: Natural gas liquids to PFS (C2 & C4) | E55: PJ
B56: *R1,R2,R3,R4,R5,R12 | C56: LPG_NGL | D56: Natural gas liquids to LPG (C3) | E56: PJ
B57: *R1,R2,R3,R4,R5,R13 | C57: NGLPENT | D57: Natural gas liquids to pentanes (C5+) | E57: PJ
B74: * Emissions Commodities
B75: R1,R2,R3,R4,R5,R6 | C75: CO2 | D75: Carbon dioxide | E75: Mt | F75: ENV
B76: R1,R2,R3,R4,R5,R6 | C76: NOX | D76: Nitrogen oxide | E76: kt | F76: ENV
B77: R1,R2,R3,R4,R5,R6 | C77: PM10 | D77: Particulate matter | E77: kt | F77: ENV
B78: R1,R2,R3,R4,R5,R6 | C78: PM25 | D78: Fine particulate matter | E78: kt | F78: ENV
B79: R1,R2,R3,R4,R5,R6 | C79: VOC | D79: Volatile organic compounds | E79: kt | F79: ENV
B80: R1,R2,R3,R4,R5,R6 | C80: CO | D80: Carbon monoxide | E80: kt | F80: ENV
B81: R1,R2,R3,R4,R5,R6 | C81: CH4 | D81: Methane | E81: kt | F81: ENV
B82: R1,R2,R3,R4,R5,R6 | C82: N2O | D82: N2O | E82: kt | F82: ENV
B83: R1,R2,R3,R4,R5,R6 | C83: BC | D83: Black carbon | E83: kt | F83: ENV
B84: R1,R2,R3,R4,R5,R6 | C84: OC | D84: Organic carbon | E84: kt | F84: ENV
B85: R1,R2,R3,R4,R5,R6 | C85: SO2 | D85: Sulfur dioxide | E85: kt | F85: ENV

Sheet ANSv6.1-Technologies
A1: ANSWER-Technologies
B7: TechName | C7: TechDesc | D7: TACTUnit | E7: TCAPUnit | F7: Set Memberships | G7: Comment

Sheet Technologies
B1: Technologies | C1: _GLOBAL,R0,R1,R2,R3,R4,R5,R6
B6: ~FI_Process
B7: Region | C7: TechName | D7: TechDesc | E7: Tact | F7: Tcap | G7: Sets | H7: PrimaryCG | I7: Vintage | O7: Comment
B8: R1,R2,R3,R4,R5,R6 | C8: MINNGAD1 | D8: Domestic natural gas - step 1 | E8: PJ | F8: PJ/a | G8: MIN
B9: R1,R2,R3,R4,R5,R6 | C9: MINNGAD2 | D9: Domestic natural gas - step 2 | E9: PJ | F9: PJ/a
B10: R1,R2,R3,R4,R5,R6 | C10: MINNGAD3 | D10: Domestic natural gas - step 3 | E10: PJ | F10: PJ/a
B11: R1,R2,R3,R4,R5,R6 | C11: MINNGAD4 | D11: Domestic natural gas - step 4 | E11: PJ | F11: PJ/a
B12: R1,R2,R3,R4,R5,R6 | C12: MINNGAD5 | D12: Domestic natural gas - step 5 | E12: PJ | F12: PJ/a
B13: R1,R2,R3,R4,R5,R6 | C13: MINNGAD6 | D13: Domestic natural gas - step 6 | E13: PJ | F13: PJ/a
B14: R1,R2,R3,R4,R5,R6 | C14: SCMINNGAD | D14: Collector: MINNGAD | E14: PJ | F14: PJ/a | G14: PRE
B15: R1 | C15: MINNGLDMY | D15: Dummy NGL Resource Supply | E15: PJ | F15: PJ/a | G15: MIN
B16: R1 | C16: SCNGAR1 | D16: Collector: Natural Gas R1 | E16: PJ | F16: PJ/a | G16: PRE
B17: R2 | C17: SCNGAR2 | D17: Collector: Natural Gas R2 | E17: PJ | F17: PJ/a
B18: R3 | C18: SCNGAR3 | D18: Collector: Natural Gas R3 | E18: PJ | F18: PJ/a
B19: R4 | C19: SCNGAR4 | D19: Collector: Natural Gas R4 | E19: PJ | F19: PJ/a
B20: R5 | C20: SCNGAR5 | D20: Collector: Natural Gas R5 | E20: PJ | F20: PJ/a
B21: R6 | C21: SCNGAR6 | D21: Collector: Natural Gas R6 | E21: PJ | F21: PJ/a
B22: *
B23: R1 | C23: SCNGAD1 | D23: Domestic natural gas Existing infrastructure in R1 | E23: PJ | F23: PJ/a
B24: R2 | C24: SCNGAD2 | D24: Domestic natural gas Existing infrastructure in R2 | E24: PJ | F24: PJ/a
B25: R3 | C25: SCNGAD3 | D25: Domestic natural gas Existing infrastructure in R3 | E25: PJ | F25: PJ/a
B26: R4 | C26: SCNGAD4 | D26: Domestic natural gas Existing infrastructure in R4 | E26: PJ | F26: PJ/a
B27: R5 | C27: SCNGAD5 | D27: Domestic natural gas Existing infrastructure in R5 | E27: PJ | F27: PJ/a
B28: R6 | C28: SCNGAD6 | D28: Domestic natural gas Existing infrastructure in R6 | E28: PJ | F28: PJ/a
B29: *Imported natural gas supply and transport
B30: R0 | C30: IMPNGALA | D30: Imported LNG - Step A | E30: PJ | F30: PJ/a | G30: IMP
B31: R0 | C31: IMPNGALB | D31: Imported LNG - Step B | E31: PJ | F31: PJ/a
B32: R0 | C32: IMPNGALC | D32: Imported LNG - Step C | E32: PJ | F32: PJ/a
B33: R0 | C33: SCIMPNGAL | D33: Share of Imported LNG to Existing Terminals | E33: PJ | F33: PJ/a | G33: PRE
B34: R0 | C34: IMPNGAC1 | D34: Imported natural gas from Canada - Step 1 | E34: PJ | F34: PJ/a | G34: IMP
B35: R0 | C35: IMPNGAC2 | D35: Imported natural gas from Canada - Step 2 | E35: PJ | F35: PJ/a
B36: R0 | C36: IMPNGAC3 | D36: Imported natural gas from Canada - Step 3 | E36: PJ | F36: PJ/a
B37: R0 | C37: IMPNGAC4 | D37: Imported natural gas from Canada - Step 4 | E37: PJ | F37: PJ/a
B38: R0 | C38: IMPNGAC5 | D38: Imported natural gas from Canada - Step 5 | E38: PJ | F38: PJ/a
B39: R0 | C39: IMPNGAC6 | D39: Imported natural gas from Canada - Step 6 | E39: PJ | F39: PJ/a
B40: R0 | C40: SCIMPNGAC | D40: Canadian imported natural gas shares | E40: PJ | F40: PJ/a | G40: PRE
B41: R0 | C41: SCNGAC1 | D41: Canadian imported natural gas in R1 | E41: PJ | F41: PJ/a
B42: *R0 | C42: SCNGAC2 | D42: Canadian imported natural gas in R2 | E42: PJ | F42: PJ/a
B43: *R0 | C43: SCNGAC3 | D43: Canadian imported natural gas in R3 | E43: PJ | F43: PJ/a
B44: *R0 | C44: SCNGAC4 | D44: Canadian imported natural gas in R4 | E44: PJ | F44: PJ/a
B45: *R0 | C45: SCNGAC5 | D45: Canadian imported natural gas in R5 | E45: PJ | F45: PJ/a
B46: *R0 | C46: SCNGAC6 | D46: Canadian imported natural gas in R6 | E46: PJ | F46: PJ/a
B47: *Export natural gas supply and transport
B48: *R7,R8,R9 | C48: EXPNGAM | D48: Exported natural gas to Mexico | G48: TCH,SRCENCP,SEP_EXP
B49: R1,R2,R3,R4,R5,R6 | C49: EXPNGAL | D49: Exported natural gas liquids | E49: PJ | F49: PJ/a | G49: EXP
B50: R1 | C50: XNGAC1E | D50: Existing Pipeline for Import Canadian natural gas to R1 | E50: PJ | F50: PJ/a | G50: PRE
B51: *R2 | C51: XNGAC2E | D51: Existing Pipeline for Import Canadian natural gas to R2 | E51: PJ | F51: PJ/a
B52: *R3 | C52: XNGAC3E | D52: Existing Pipeline for Import Canadian natural gas to R3 | E52: PJ | F52: PJ/a
B53: *R4 | C53: XNGAC4E | D53: Existing Pipeline for Import Canadian natural gas to R4 | E53: PJ | F53: PJ/a
B54: *R5 | C54: XNGAC5E | D54: Existing Pipeline for Import Canadian natural gas to R5 | E54: PJ | F54: PJ/a
B55: *R6 | C55: XNGAC6E | D55: Existing Pipeline for Import Canadian natural gas to R6 | E55: PJ | F55: PJ/a
B56: *
B57: R1 | C57: XNGALE1E | D57: Infrastructure for Import LNG to Existing terminal in R1 | E57: PJ | F57: PJ/a
B58: R4 | C58: XNGALE4E | D58: Infrastructure for Import LNG to Existing terminal in R4 - Manhattan | E58: PJ | F58: PJ/a
B59: R5 | C59: XNGALE5E | D59: Infrastructure for Import LNG to Existing terminal in R5 - Staten Island | E59: PJ | F59: PJ/a
B60: * Domestic natural gas delivery costs to end-use demands
B61: R1,R2,R3,R4,R5,R6 | C61: XNGARES | D61: Domestic natural gas to residential end-use | E61: PJ | F61: PJ/a | G61: PRE
B62: R1,R2,R3,R4,R5,R6 | C62: XNGACOM | D62: Domestic natural gas to commercial end-use | E62: PJ | F62: PJ/a
B63: R1,R2,R3,R4,R5,R6 | C63: XNGAIND | D63: Domestic natural gas to industrial end-use | E63: PJ | F63: PJ/a
B64: R1,R2,R3,R4,R5,R6 | C64: XNGAELC | D64: Domestic natural gas to electricity generation | E64: PJ | F64: PJ/a
B65: R1,R2,R3,R4,R5,R6 | C65: XNGATRN | D65: Domestic natural gas to transportation end-use | E65: PJ | F65: PJ/a
B66: * | C66: XNGLFRAC | D66: Domestic natural gas liquids to end-products
B67: * Collectors for NGL products
B68: *R1,R2,R3,R4,R5,R6 | C68: SCGSRPENT | D68: Collector: GSR from NGL Pentanes
B69: *R1,R2,R3,R4,R5,R6 | C69: SCDENPENT | D69: Collector: Ethanol denaturant from NGL Pentanes
B70: *R1,R2,R3,R4,R5,R6 | C70: SCPFSNGL | D70: Collector: PFS from NGL
B71: *R1,R2,R3,R4,R5,R6 | C71: SCLPGNGL | D71: Collector: LPG from NGL
B72: *R1,R2,R3,R4,R5,R6 | C72: SCPENTNGL | D72: Collector: Pentanes from NGL
B73: *
B74: * Imported natural gas Pipeline technologies
B75: R2 | C75: XNGA12E | D75: Existing natural gas pipeline from R1 to R2 | E75: PJ | F75: PJ/a | G75: PRE
B76: R3 | C76: XNGA13E | D76: Existing natural gas pipeline from R1 to R3 | E76: PJ | F76: PJ/a
B77: R4 | C77: XNGA14E | D77: Existing natural gas pipeline from R1 to R4 | E77: PJ | F77: PJ/a
B78: R5 | C78: XNGA15E | D78: Existing natural gas pipeline from R1 to R5 | E78: PJ | F78: PJ/a
B79: R6 | C79: XNGA16E | D79: Existing natural gas pipeline from R1 to R6 | E79: PJ | F79: PJ/a
B80: R3 | C80: XNGA23E | D80: Existing natural gas pipeline from R2 to R3 | E80: PJ | F80: PJ/a
B81: R4 | C81: XNGA24E | D81: Existing natural gas pipeline from R2 to R4 | E81: PJ | F81: PJ/a
B82: R5 | C82: XNGA25E | D82: Existing natural gas pipeline from R2 to R5 | E82: PJ | F82: PJ/a
B83: R2 | C83: XNGA32E | D83: Existing natural gas pipeline from R3 to R2 | E83: PJ | F83: PJ/a
B84: R4 | C84: XNGA34E | D84: Existing natural gas pipeline from R3 to R4 | E84: PJ | F84: PJ/a
B85: R6 | C85: XNGA36E | D85: Existing natural gas pipeline from R3 to R6 | E85: PJ | F85: PJ/a
B86: R2 | C86: XNGA42E | D86: Existing natural gas pipeline from R4 to R2 | E86: PJ | F86: PJ/a
B87: R3 | C87: XNGA43E | D87: Existing natural gas pipeline from R4 to R3 | E87: PJ | F87: PJ/a
... B93: R4 | C93: XNGA64E | D93: Existing natural gas pipeline from R6 to R4 | E93: PJ | F93: PJ/a
B94: *
B103: =B75 -> R2 | C103: XNGA12N | D103: New natural gas pipeline from R1 to R2 | E103: PJ | F103: PJ/a | G103: PRE
B104: =B76 -> R3 | C104: XNGA13N | D104: New natural gas pipeline from R1 to R3 | E104: PJ | F104: PJ/a
B105: =B77 -> R4 | C105: XNGA14N | D105: New natural gas pipeline from R1 to R4 | E105: PJ | F105: PJ/a
B106: =B78 -> R5 | C106: XNGA15N | D106: New natural gas pipeline from R1 to R5 | E106: PJ | F106: PJ/a
B107: =B79 -> R6 | C107: XNGA16N | D107: New natural gas pipeline from R1 to R6 | E107: PJ | F107: PJ/a
B108: =B80 -> R3 | C108: XNGA23N | D108: New natural gas pipeline from R2 to R3 | E108: PJ | F108: PJ/a
B109: =B81 -> R4 | C109: XNGA24N | D109: New natural gas pipeline from R2 to R4 | E109: PJ | F109: PJ/a
B110: =B82 -> R5 | C110: XNGA25N | D110: New natural gas pipeline from R2 to R5 | E110: PJ | F110: PJ/a
B111: =B83 -> R2 | C111: XNGA32N | D111: New natural gas pipeline from R3 to R3 | E111: PJ | F111: PJ/a
B112: =B84 -> R4 | C112: XNGA34N | D112: New natural gas pipeline from R3 to R4 | E112: PJ | F112: PJ/a
B113: =B85 -> R6 | C113: XNGA36N | D113: New natural gas pipeline from R3 to R6 | E113: PJ | F113: PJ/a
B114: =B86 -> R2 | C114: XNGA42N | D114: New natural gas pipeline from R4 to R2 | E114: PJ | F114: PJ/a
B115: =B87 -> R3 | C115: XNGA43N | D115: New natural gas pipeline from R4 to R3 | E115: PJ | F115: PJ/a
... B121: =B93 -> R4 | C121: XNGA64N | D121: New natural gas pipeline from R6 to R4 | E121: PJ | F121: PJ/a
B122: *
...

Sheet ANSv6.1-Constraints
A1: ANSWER-Constraints
B7: ConstrName | C7: ConstrDesc | D7: Units | E7: Set Memberships | F7: Comment

Sheet ANSv6.1-CommData
A1: ANSWER-CommData
B7: CommName | C7: CommDesc | D7: Units

Sheet ANSv6.1-TechData
A1: ANSWER-TechData
B7: TechName | C7: TechDesc | D7: Units | E7: CommIN | F7: CommOUT

Sheet TechData_R0
A1: TechData | B1: _GLOBAL,R0,R1,R2,R3,R4,R5,R6 | BO1: *
D5: ~FI_T
A6: Region | B6: TechName | C6: TechDesc | D6: CommOUT | E6: *NCAP_START | F6: COST~2010 | G6: COST~2015 | H6: COST~2020 | I6: COST~2025 | J6: COST~2030 | K6: COST~2035 | L6: COST~2040 | M6: COST~2045 | N6: COST~2050 | O6: COST~2055 | P6: CUM | Q6: ACT_BND~LO~2010 | R6: ACT_BND~UP~2010 | S6: ACT_BND~UP~2015 | T6: ACT_BND~UP~2020 | U6: ACT_BND~UP~2055 | W6: *GROWTH_TIDr | X6: *GROWTHr~2010 | Y6: *GROWTHr~2015-2020 | Z6: *GROWTHr~2025-2055 | AA6: *DECAYr~2010 | AB6: *DECAYr~2015-2055
A7: *Minning Natural gas
A8: * Price Shocks | G8: 1 | H8: 1 | I8: 1 | J8: 1 | K8: 1 | L8: 1 | M8: 1 | N8: 1 | O8: 1
A9: R1 | B9: MINNGAD1 | C9: Domestic natural gas - step 1 | D9: =Commodities!C$11 -> NGAD0 | E9: 2010 | F9: =F11*'Domestic NG Prices'!$N$19 -> 3.5667714 | G9: =G11*'Domestic NG Prices'!$N$19 -> 2.93191 | H9: =H11*'Domestic NG Prices'!$N$19 -> 3.427406 | I9: =I11*'Domestic NG Prices'!$N$19 -> 4.0985992 | J9: =J11*'Domestic NG Prices'!$N$19 -> 4.7260766 | K9: =K11*'Domestic NG Prices'!$N$19 -> 5.4230838 | L9: =L11*'Domestic NG Prices'!$N$19 -> 5.9926204 | M9: =M11*'Domestic NG Prices'!$N$19 -> 6.6176 | ... O9: =O11*'Domestic NG Prices'!$N$19 -> 8.0872 | P9: =R9/SUM($R$9:$R$14)*'Domestic NG CUM'!$T$6 -> 3637.3548 | Q9: ='Domestic NG Production'!B94 -> 14.464222 | R9: ='Domestic NG Production'!B79 -> 326.2332 | X9: 1.25 | Y9: 1.1 | Z9: 1.1 | AA9: 1.1 | AB9: 1.01
A10: R1 | B10: MINNGAD2 | C10: Domestic natural gas - step 2 | D10: =Commodities!C$11 -> NGAD0 | E10: 2010 | F10: =F11*'Domestic NG Prices'!$N$20 -> 3.8504918 | G10: =G11*'Domestic NG Prices'!$N$20 -> 3.1651301 | H10: =H11*'Domestic NG Prices'!$N$20 -> 3.7000405 | I10: =I11*'Domestic NG Prices'!$N$20 -> 4.4246241 | J10: =J11*'Domestic NG Prices'!$N$20 -> 5.1020145 | K10: =K11*'Domestic NG Prices'!$N$20 -> 5.8544654 | L10: =L11*'Domestic NG Prices'!$N$20 -> 6.4693061 | M10: =M11*'Domestic NG Prices'!$N$20 -> 7.144 | ... O10: =O11*'Domestic NG Prices'!$N$20 -> 8.7305 | P10: =R10/SUM($R$9:$R$14)*'Domestic NG CUM'!$T$6 -> 2728.0161 | Q10: ='Domestic NG Production'!B95 -> 10.848166 | R10: ='Domestic NG Production'!B80 -> 244.6749 | X10: 1.25 | Y10: 1.1 | Z10: 1.1 | AA10: 1.1 | AB10: 1.01
A11: R1 | B11: MINNGAD3 | C11: Domestic natural gas - step 3 | D11: =Commodities!C$11 -> NGAD0 | E11: 2010 | F11: ='Domestic NG Prices'!N42*'Domestic NG Prices'!$P$27*TechData_DelNGA!$I$8 -> 4.0531493 | G11: ='Domestic NG Prices'!O42*'Domestic NG Prices'!$P$27*TechData_DelNGA!$I$8*G8 -> 3.3317159 | H11: ='Domestic NG Prices'!P42*'Domestic NG Prices'!$P$27*TechData_DelNGA!$I$8*H8 -> 3.8947795 | I11: ='Domestic NG Prices'!Q42*'Domestic NG Prices'!$P$27*TechData_DelNGA!$I$8*I8 -> 4.6574991 | J11: ='Domestic NG Prices'!R42*'Domestic NG Prices'!$P$27*TechData_DelNGA!$I$8*J8 -> 5.3705416 | K11: ='Domestic NG Prices'!S42*'Domestic NG Prices'!$P$27*TechData_DelNGA!$I$8*K8 -> 6.1625952 | L11: ='Domestic NG Prices'!T42*'Domestic NG Prices'!$P$27*TechData_DelNGA!$I$8*L8 -> 6.8097959 | M11: =7.52*M8 -> 7.52 | N11: =8.32*N8 -> 8.32 | O11: =9.19*O8 -> 9.19 | P11: =R11/SUM($R$9:$R$14)*'Domestic NG CUM'!$T$6 -> 2728.0161 | Q11: ='Domestic NG Production'!B96 -> 10.848166 | R11: ='Domestic NG Production'!B81 -> 244.6749 | X11: 1.25 | Y11: 1.1 | Z11: 1.1 | AA11: 1.1 | AB11: 1.01
A12: R1 | B12: MINNGAD4 | C12: Domestic natural gas - step 4 | D12: =Commodities!C$11 -> NGAD0 | E12: 2010 | F12: =F11*'Domestic NG Prices'!$N$22 -> 4.3774012 | G12: =G11*'Domestic NG Prices'!$N$22 -> 3.5982532 | H12: =H11*'Domestic NG Prices'!$N$22 -> 4.2063619 | I12: =I11*'Domestic NG Prices'!$N$22 -> 5.030099 | J12: =J11*'Domestic NG Prices'!$N$22 -> 5.8001849 | K12: =K11*'Domestic NG Prices'!$N$22 -> 6.6556028 | L12: =L11*'Domestic NG Prices'!$N$22 -> 7.3545796 | M12: =M11*'Domestic NG Prices'!$N$22 -> 8.1216 | ... O12: =O11*'Domestic NG Prices'!$N$22 -> 9.9252 | P12: =R12/SUM($R$9:$R$14)*'Domestic NG CUM'!$T$6 -> 454.66935 | Q12: ='Domestic NG Production'!B97 -> 1.8080277 | R12: ='Domestic NG Production'!B82 -> 40.77915 | X12: 1.25 | Y12: 1.1 | Z12: 1.1 | AA12: 1.1 | AB12: 1.01
A13: R1 | B13: MINNGAD5 | C13: Domestic natural gas - step 5 | D13: =Commodities!C$11 -> NGAD0 | E13: 2010 | F13: =F11*'Domestic NG Prices'!$N$23 -> 4.5395272 | G13: =G11*'Domestic NG Prices'!$N$23 -> 3.7315218 | H13: =H11*'Domestic NG Prices'!$N$23 -> 4.362153 | I13: =I11*'Domestic NG Prices'!$N$23 -> 5.216399 | J13: =J11*'Domestic NG Prices'!$N$23 -> 6.0150066 | K13: =K11*'Domestic NG Prices'!$N$23 -> 6.9021066 | L13: =L11*'Domestic NG Prices'!$N$23 -> 7.6269714 | M13: =M11*'Domestic NG Prices'!$N$23 -> 8.4224 | ... O13: =O11*'Domestic NG Prices'!$N$23 -> 10.2928 | P13: =R13/SUM($R$9:$R$14)*'Domestic NG CUM'!$T$6 -> 454.66935 | R13: ='Domestic NG Production'!B83 -> 40.77915 | W13: =R13 -> 40.77915 | X13: 1.25 | Y13: 1.1 | Z13: 1.1 | AA13: 1.1 | AB13: 1.01
A14: R1 | B14: MINNGAD6 | C14: Domestic natural gas - step 6 | D14: =Commodities!C$11 -> NGAD0 | E14: 2010 | F14: =F11*'Domestic NG Prices'!$N$24 -> 6.2013184 | G14: =G11*'Domestic NG Prices'!$N$24 -> 5.0975254 | H14: =H11*'Domestic NG Prices'!$N$24 -> 5.9590126 | I14: =I11*'Domestic NG Prices'!$N$24 -> 7.1259736 | J14: =J11*'Domestic NG Prices'!$N$24 -> 8.2169286 | K14: =K11*'Domestic NG Prices'!$N$24 -> 9.4287707 | L14: =L11*'Domestic NG Prices'!$N$24 -> 10.418988 | M14: =M11*'Domestic NG Prices'!$N$24 -> 11.5056 | ... O14: =O11*'Domestic NG Prices'!$N$24 -> 14.0607 | P14: =R14/SUM($R$9:$R$14)*'Domestic NG CUM'!$T$6 -> 909.3387 | R14: ='Domestic NG Production'!B84 -> 81.5583 | W14: =R14 -> 81.5583 | X14: 1.25 | Y14: 1.1 | Z14: 1.1 | AA14: 1.1 | AB14: 1.01
A15: *
A16: R2 | B16: MINNGAD1 | C16: Domestic natural gas - step 1 | D16: =Commodities!C$11 -> NGAD0 | E16: 2010 | F16: =F18*'Domestic NG Prices'!$N$19 -> 3.5667714 | G16: =G18*'Domestic NG Prices'!$N$19 -> 2.93191 | H16: =H18*'Domestic NG Prices'!$N$19 -> 3.427406 | I16: =I18*'Domestic NG Prices'!$N$19 -> 4.0985992 | J16: =J18*'Domestic NG Prices'!$N$19 -> 4.7260766 | K16: =K18*'Domestic NG Prices'!$N$19 -> 5.4230838 | L16: =L18*'Domestic NG Prices'!$N$19 -> 5.9926204 | M16: =M18*'Domestic NG Prices'!$N$19 -> 6.5694775 | ... O16: =O18*'Domestic NG Prices'!$N$19 -> 8.0217982 | P16: 0 | Q16: =R16*0.9 -> 0 | R16: 0 | S16: 0 | T16: 0 | U16: =T16 -> 0 | X16: 1.25 | Y16: 1.1 | Z16: 1.1 | AA16: 1.1 | AB16: 1.01
A17: R2 | B17: MINNGAD2 | C17: Domestic natural gas - step 2 | D17: =Commodities!C$11 -> NGAD0 | E17: 2010 | F17: =F18*'Domestic NG Prices'!$N$20 -> 3.8504918 | G17: =G18*'Domestic NG Prices'!$N$20 -> 3.1651301 | H17: =H18*'Domestic NG Prices'!$N$20 -> 3.7000405 | I17: =I18*'Domestic NG Prices'!$N$20 -> 4.4246241 | J17: =J18*'Domestic NG Prices'!$N$20 -> 5.1020145 | K17: =K18*'Domestic NG Prices'!$N$20 -> 5.8544654 | L17: =L18*'Domestic NG Prices'!$N$20 -> 6.4693061 | M17: =M18*'Domestic NG Prices'!$N$20 -> 7.0920495 | ... O17: =O18*'Domestic NG Prices'!$N$20 -> 8.6598958 | P17: 0 | Q17: =R17*0.9 -> 0 | R17: 0 | S17: 0 | T17: 0 | U17: =T17 -> 0 | X17: 1.25 | Y17: 1.1 | Z17: 1.1 | AA17: 1.1 | AB17: 1.01
A18: R2 | B18: MINNGAD3 | C18: Domestic natural gas - step 3 | D18: =Commodities!C$11 -> NGAD0 | E18: 2010 | F18: ='Domestic NG Prices'!N42*'Domestic NG Prices'!$P$27*TechData_DelNGA!$I$11 -> 4.0531493 | G18: ='Domestic NG Prices'!O42*'Domestic NG Prices'!$P$27*TechData_DelNGA!$I$11*G8 -> 3.3317159 | H18: ='Domestic NG Prices'!P42*'Domestic NG Prices'!$P$27*TechData_DelNGA!$I$11*H8 -> 3.8947795 | I18: ='Domestic NG Prices'!Q42*'Domestic NG Prices'!$P$27*TechData_DelNGA!$I$11*I8 -> 4.6574991 | J18: ='Domestic NG Prices'!R42*'Domestic NG Prices'!$P$27*TechData_DelNGA!$I$11*J8 -> 5.3705416 | K18: ='Domestic NG Prices'!S42*'Domestic NG Prices'!$P$27*TechData_DelNGA!$I$11*K8 -> 6.1625952 | L18: ='Domestic NG Prices'!T42*'Domestic NG Prices'!$P$27*TechData_DelNGA!$I$11*L8 -> 6.8097959 | M18: =7.46531529457816*M8 -> 7.4653153 | N18: =8.2493286895923*N8 -> 8.2493287 | O18: =9.11567979966692*O8 -> 9.1156798 | P18: 0 | Q18: =R18*0.9 -> 0 | R18: 0 | S18: 0 | T18: 0 | U18: =T18 -> 0 | X18: 1.25 | Y18: 1.1 | Z18: 1.1 | AA18: 1.1 | AB18: 1.01
A19: R2 | B19: MINNGAD4 | C19: Domestic natural gas - step 4 | D19: =Commodities!C$11 -> NGAD0 | E19: 2010 | F19: =F18*'Domestic NG Prices'!$N$22 -> 4.3774012 | G19: =G18*'Domestic NG Prices'!$N$22 -> 3.5982532 | H19: =H18*'Domestic NG Prices'!$N$22 -> 4.2063619 | I19: =I18*'Domestic NG Prices'!$N$22 -> 5.030099 | J19: =J18*'Domestic NG Prices'!$N$22 -> 5.8001849 | K19: =K18*'Domestic NG Prices'!$N$22 -> 6.6556028 | L19: =L18*'Domestic NG Prices'!$N$22 -> 7.3545796 | M19: =M18*'Domestic NG Prices'!$N$22 -> 8.0625405 | ... O19: =O18*'Domestic NG Prices'!$N$22 -> 9.8449342 | P19: 0 | Q19: =R19*0.9 -> 0 | R19: 0 | S19: 0 | T19: 0 | U19: =T19 -> 0 | X19: 1.25 | Y19: 1.1 | Z19: 1.1 | AA19: 1.1 | AB19: 1.01
A20: R2 | B20: MINNGAD5 | C20: Domestic natural gas - step 5 | D20: =Commodities!C$11 -> NGAD0 | E20: 2010 | F20: =F18*'Domestic NG Prices'!$N$23 -> 4.5395272 | G20: =G18*'Domestic NG Prices'!$N$23 -> 3.7315218 | H20: =H18*'Domestic NG Prices'!$N$23 -> 4.362153 | I20: =I18*'Domestic NG Prices'!$N$23 -> 5.216399 | J20: =J18*'Domestic NG Prices'!$N$23 -> 6.0150066 | K20: =K18*'Domestic NG Prices'!$N$23 -> 6.9021066 | L20: =L18*'Domestic NG Prices'!$N$23 -> 7.6269714 | M20: =M18*'Domestic NG Prices'!$N$23 -> 8.3611531 | ... O20: =O18*'Domestic NG Prices'!$N$23 -> 10.209561 | P20: 0 | Q20: =R20*0.9 -> 0 | R20: 0 | S20: 0 | T20: 0 | U20: =T20 -> 0 | W20: =R20 -> 0 | X20: 1.25 | Y20: 1.1 | Z20: 1.1 | AA20: 1.1 | AB20: 1.01
A21: R2 | B21: MINNGAD6 | C21: Domestic natural gas - step 6 | D21: =Commodities!C$11 -> NGAD0 | E21: 2010 | F21: =F18*'Domestic NG Prices'!$N$24 -> 6.2013184 | G21: =G18*'Domestic NG Prices'!$N$24 -> 5.0975254 | H21: =H18*'Domestic NG Prices'!$N$24 -> 5.9590126 | I21: =I18*'Domestic NG Prices'!$N$24 -> 7.1259736 | J21: =J18*'Domestic NG Prices'!$N$24 -> 8.2169286 | K21: =K18*'Domestic NG Prices'!$N$24 -> 9.4287707 | L21: =L18*'Domestic NG Prices'!$N$24 -> 10.418988 | M21: =M18*'Domestic NG Prices'!$N$24 -> 11.421932 | ... O21: =O18*'Domestic NG Prices'!$N$24 -> 13.94699 | P21: 0 | Q21: =R21*0.9 -> 0 | R21: 0 | S21: 0 | T21: 0 | U21: =T21 -> 0 | W21: =R21 -> 0 | X21: 1.25 | Y21: 1.1 | Z21: 1.1 | AA21: 1.1 | AB21: 1.01
A22: *
A23: R3 | B23: MINNGAD1 | C23: Domestic natural gas - step 1 | D23: =Commodities!C$11 -> NGAD0 | E23: 2010 | F23: =F25*'Domestic NG Prices'!$N$19 -> 3.5667714 | G23: =G25*'Domestic NG Prices'!$N$19 -> 2.93191 | H23: =H25*'Domestic NG Prices'!$N$19 -> 3.427406 | I23: =I25*'Domestic NG Prices'!$N$19 -> 4.0985992 | J23: =J25*'Domestic NG Prices'!$N$19 -> 4.7260766 | K23: =K25*'Domestic NG Prices'!$N$19 -> 5.4230838 | L23: =L25*'Domestic NG Prices'!$N$19 -> 5.9926204 | M23: =M25*'Domestic NG Prices'!$N$19 -> 6.0617197 | ... O23: =O25*'Domestic NG Prices'!$N$19 -> 7.40179 | P23: 0 | Q23: =R23*0.9 -> 0 | R23: 0 | S23: 0 | T23: 0 | U23: =T23 -> 0 | X23: 1.25 | Y23: 1.1 | Z23: 1.1 | AA23: 1.1 | AB23: 1.01
A24: R3 | B24: MINNGAD2 | C24: Domestic natural gas - step 2 | D24: =Commodities!C$11 -> NGAD0 | E24: 2010 | F24: =F25*'Domestic NG Prices'!$N$20 -> 3.8504918 | G24: =G25*'Domestic NG Prices'!$N$20 -> 3.1651301 | H24: =H25*'Domestic NG Prices'!$N$20 -> 3.7000405 | I24: =I25*'Domestic NG Prices'!$N$20 -> 4.4246241 | J24: =J25*'Domestic NG Prices'!$N$20 -> 5.1020145 | K24: =K25*'Domestic NG Prices'!$N$20 -> 5.8544654 | L24: =L25*'Domestic NG Prices'!$N$20 -> 6.4693061 | M24: =M25*'Domestic NG Prices'!$N$20 -> 6.543902 | ... O24: =O25*'Domestic NG Prices'!$N$20 -> 7.9905688 | P24: 0 | Q24: =R24*0.9 -> 0 | R24: 0 | S24: 0 | T24: 0 | U24: =T24 -> 0 | X24: 1.25 | Y24: 1.1 | Z24: 1.1 | AA24: 1.1 | AB24: 1.01
A25: R3 | B25: MINNGAD3 | C25: Domestic natural gas - step 3 | D25: =Commodities!C$11 -> NGAD0 | E25: 2010 | F25: ='Domestic NG Prices'!N42*'Domestic NG Prices'!$P$27*TechData_DelNGA!$I$14 -> 4.0531493 | G25: ='Domestic NG Prices'!O42*'Domestic NG Prices'!$P$27*TechData_DelNGA!$I$14*G8 -> 3.3317159 | H25: ='Domestic NG Prices'!P42*'Domestic NG Prices'!$P$27*TechData_DelNGA!$I$14*H8 -> 3.8947795 | I25: ='Domestic NG Prices'!Q42*'Domestic NG Prices'!$P$27*TechData_DelNGA!$I$14*I8 -> 4.6574991 | J25: ='Domestic NG Prices'!R42*'Domestic NG Prices'!$P$27*TechData_DelNGA!$I$14*J8 -> 5.3705416 | K25: ='Domestic NG Prices'!S42*'Domestic NG Prices'!$P$27*TechData_DelNGA!$I$14*K8 -> 6.1625952 | L25: ='Domestic NG Prices'!T42*'Domestic NG Prices'!$P$27*TechData_DelNGA!$I$14*L8 -> 6.8097959 | M25: =6.88831787744587*M8 -> 6.8883179 | N25: =7.61173454130134*N8 -> 7.6117345 | O25: =8.41112500294819*O8 -> 8.411125 | P25: 0 | Q25: =R25*0.9 -> 0 | R25: 0 | S25: 0 | T25: 0 | U25: =T25 -> 0 | X25: 1.25 | Y25: 1.1 | Z25: 1.1 | AA25: 1.1 | AB25: 1.01
A26: R3 | B26: MINNGAD4 | C26: Domestic natural gas - step 4 | D26: =Commodities!C$11 -> NGAD0 | E26: 2010 | F26: =F25*'Domestic NG Prices'!$N$22 -> 4.3774012 | G26: =G25*'Domestic NG Prices'!$N$22 -> 3.5982532 | H26: =H25*'Domestic NG Prices'!$N$22 -> 4.2063619 | I26: =I25*'Domestic NG Prices'!$N$22 -> 5.030099 | J26: =J25*'Domestic NG Prices'!$N$22 -> 5.8001849 | K26: =K25*'Domestic NG Prices'!$N$22 -> 6.6556028 | L26: =L25*'Domestic NG Prices'!$N$22 -> 7.3545796 | M26: =M25*'Domestic NG Prices'!$N$22 -> 7.4393833 | ... O26: =O25*'Domestic NG Prices'!$N$22 -> 9.084015 | P26: 0 | Q26: =R26*0.9 -> 0 | R26: 0 | S26: 0 | T26: 0 | U26: =T26 -> 0 | X26: 1.1 | Y26: 1.1 | Z26: 1.1 | AA26: 1.1 | AB26: 1.01
A27: R3 | B27: MINNGAD5 | C27: Domestic natural gas - step 5 | D27: =Commodities!C$11 -> NGAD0 | E27: 2010 | F27: =F25*'Domestic NG Prices'!$N$23 -> 4.5395272 | G27: =G25*'Domestic NG Prices'!$N$23 -> 3.7315218 | H27: =H25*'Domestic NG Prices'!$N$23 -> 4.362153 | I27: =I25*'Domestic NG Prices'!$N$23 -> 5.216399 | J27: =J25*'Domestic NG Prices'!$N$23 -> 6.0150066 | K27: =K25*'Domestic NG Prices'!$N$23 -> 6.9021066 | L27: =L25*'Domestic NG Prices'!$N$23 -> 7.6269714 | M27: =M25*'Domestic NG Prices'!$N$23 -> 7.714916 | ... O27: =O25*'Domestic NG Prices'!$N$23 -> 9.42046 | P27: 0 | Q27: =R27*0.9 -> 0 | R27: 0 | S27: 0 | T27: 0 | U27: =T27 -> 0 | W27: =R27 -> 0 | X27: 1.01 | Y27: 1.01 | Z27: 1.01 | AA27: 1.1 | AB27: 1.01
A28: R3 | B28: MINNGAD6 | C28: Domestic natural gas - step 6 | D28: =Commodities!C$11 -> NGAD0 | E28: 2010 | F28: =F25*'Domestic NG Prices'!$N$24 -> 6.2013184 | G28: =G25*'Domestic NG Prices'!$N$24 -> 5.0975254 | H28: =H25*'Domestic NG Prices'!$N$24 -> 5.9590126 | I28: =I25*'Domestic NG Prices'!$N$24 -> 7.1259736 | J28: =J25*'Domestic NG Prices'!$N$24 -> 8.2169286 | K28: =K25*'Domestic NG Prices'!$N$24 -> 9.4287707 | L28: =L25*'Domestic NG Prices'!$N$24 -> 10.418988 | M28: =M25*'Domestic NG Prices'!$N$24 -> 10.539126 | ... O28: =O25*'Domestic NG Prices'!$N$24 -> 12.869021 | P28: 0 | Q28: =R28*0.9 -> 0 | R28: 0 | S28: 0 | T28: 0 | U28: =T28 -> 0 | W28: =R28 -> 0 | X28: 1.01 | Y28: 1.01 | Z28: 1.01 | AA28: 1.1 | AB28: 1.01
A29: *
A30: R4 | B30: MINNGAD1 | C30: Domestic natural gas - step 1 | D30: =Commodities!C$11 -> NGAD0 | E30: 2010 | F30: =F32*'Domestic NG Prices'!$N$19 -> 3.5667714 | G30: =G32*'Domestic NG Prices'!$N$19 -> 2.93191 | H30: =H32*'Domestic NG Prices'!$N$19 -> 3.427406 | I30: =I32*'Domestic NG Prices'!$N$19 -> 4.0985992 | J30: =J32*'Domestic NG Prices'!$N$19 -> 4.7260766 | K30: =K32*'Domestic NG Prices'!$N$19 -> 5.4230838 | L30: =L32*'Domestic NG Prices'!$N$19 -> 5.9926204 | M30: =M32*'Domestic NG Prices'!$N$19 -> 6.4965138 | ... O30: =O32*'Domestic NG Prices'!$N$19 -> 7.9327045 | P30: 0 | Q30: =R30*0.9 -> 0 | R30: 0 | S30: 0 | T30: 0 | U30: =T30 -> 0 | X30: 1.1 | Y30: 1.05 | Z30: 1.01 | AA30: 1.1 | AB30: 1.01
A31: R4 | B31: MINNGAD2 | C31: Domestic natural gas - step 2 | D31: =Commodities!C$11 -> NGAD0 | E31: 2010 | F31: =F32*'Domestic NG Prices'!$N$20 -> 3.8504918 | G31: =G32*'Domestic NG Prices'!$N$20 -> 3.1651301 | H31: =H32*'Domestic NG Prices'!$N$20 -> 3.7000405 | I31: =I32*'Domestic NG Prices'!$N$20 -> 4.4246241 | J31: =J32*'Domestic NG Prices'!$N$20 -> 5.1020145 | K31: =K32*'Domestic NG Prices'!$N$20 -> 5.8544654 | L31: =L32*'Domestic NG Prices'!$N$20 -> 6.4693061 | M31: =M32*'Domestic NG Prices'!$N$20 -> 7.013282 | ... O31: =O32*'Domestic NG Prices'!$N$20 -> 8.5637151 | P31: 0 | Q31: =R31*0.9 -> 0 | R31: 0 | S31: 0 | T31: 0 | U31: =T31 -> 0 | X31: 1.2 | Y31: 1.1 | Z31: 1.05 | AA31: 1.1 | AB31: 1.01
A32: R4 | B32: MINNGAD3 | C32: Domestic natural gas - step 3 | D32: =Commodities!C$11 -> NGAD0 | E32: 2010 | F32: ='Domestic NG Prices'!N42*'Domestic NG Prices'!$P$27*TechData_DelNGA!$I$17 -> 4.0531493 | G32: ='Domestic NG Prices'!O42*'Domestic NG Prices'!$P$27*TechData_DelNGA!$I$17*G8 -> 3.3317159 | H32: ='Domestic NG Prices'!P42*'Domestic NG Prices'!$P$27*TechData_DelNGA!$I$17*H8 -> 3.8947795 | I32: ='Domestic NG Prices'!Q42*'Domestic NG Prices'!$P$27*TechData_DelNGA!$I$17*I8 -> 4.6574991 | J32: ='Domestic NG Prices'!R42*'Domestic NG Prices'!$P$27*TechData_DelNGA!$I$17*J8 -> 5.3705416 | K32: ='Domestic NG Prices'!S42*'Domestic NG Prices'!$P$27*TechData_DelNGA!$I$17*K8 -> 6.1625952 | L32: ='Domestic NG Prices'!T42*'Domestic NG Prices'!$P$27*TechData_DelNGA!$I$17*L8 -> 6.8097959 | M32: =7.38240209732537*M8 -> 7.3824021 | N32: =8.15770788191657*N8 -> 8.1577079 | O32: =9.01443690134327*O8 -> 9.0144369 | P32: 0 | Q32: =R32*0.9 -> 0 | R32: 0 | S32: 0 | T32: 0 | U32: =T32 -> 0 | X32: 1.1 | Y32: 1.1 | Z32: 1.05 | AA32: 1.1 | AB32: 1.01
A33: R4 | B33: MINNGAD4 | C33: Domestic natural gas - step 4 | D33: =Commodities!C$11 -> NGAD0 | E33: 2010 | F33: =F32*'Domestic NG Prices'!$N$22 -> 4.3774012 | G33: =G32*'Domestic NG Prices'!$N$22 -> 3.5982532 | H33: =H32*'Domestic NG Prices'!$N$22 -> 4.2063619 | I33: =I32*'Domestic NG Prices'!$N$22 -> 5.030099 | J33: =J32*'Domestic NG Prices'!$N$22 -> 5.8001849 | K33: =K32*'Domestic NG Prices'!$N$22 -> 6.6556028 | L33: =L32*'Domestic NG Prices'!$N$22 -> 7.3545796 | M33: =M32*'Domestic NG Prices'!$N$22 -> 7.9729943 | ... O33: =O32*'Domestic NG Prices'!$N$22 -> 9.7355919 | P33: 0 | Q33: =R33*0.9 -> 0 | R33: 0 | S33: 0 | T33: 0 | U33: =T33 -> 0 | X33: 1.1 | Y33: 1.1 | Z33: 1.1 | AA33: 1.1 | AB33: 1.01
A34: R4 | B34: MINNGAD5 | C34: Domestic natural gas - step 5 | D34: =Commodities!C$11 -> NGAD0 | E34: 2010 | F34: =F32*'Domestic NG Prices'!$N$23 -> 4.5395272 | G34: =G32*'Domestic NG Prices'!$N$23 -> 3.7315218 | H34: =H32*'Domestic NG Prices'!$N$23 -> 4.362153 | I34: =I32*'Domestic NG Prices'!$N$23 -> 5.216399 | J34: =J32*'Domestic NG Prices'!$N$23 -> 6.0150066 | K34: =K32*'Domestic NG Prices'!$N$23 -> 6.9021066 | L34: =L32*'Domestic NG Prices'!$N$23 -> 7.6269714 | M34: =M32*'Domestic NG Prices'!$N$23 -> 8.2682903 | ... O34: =O32*'Domestic NG Prices'!$N$23 -> 10.096169 | P34: 0 | Q34: =R34*0.9 -> 0 | R34: 0 | S34: 0 | T34: 0 | U34: =T34 -> 0 | W34: =R34 -> 0 | X34: 1.01 | Y34: 1.01 | Z34: 1.01 | AA34: 1.1 | AB34: 1.01
A35: R4 | B35: MINNGAD6 | C35: Domestic natural gas - step 6 | D35: =Commodities!C$11 -> NGAD0 | E35: 2010 | F35: =F32*'Domestic NG Prices'!$N$24 -> 6.2013184 | G35: =G32*'Domestic NG Prices'!$N$24 -> 5.0975254 | H35: =H32*'Domestic NG Prices'!$N$24 -> 5.9590126 | I35: =I32*'Domestic NG Prices'!$N$24 -> 7.1259736 | J35: =J32*'Domestic NG Prices'!$N$24 -> 8.2169286 | K35: =K32*'Domestic NG Prices'!$N$24 -> 9.4287707 | L35: =L32*'Domestic NG Prices'!$N$24 -> 10.418988 | M35: =M32*'Domestic NG Prices'!$N$24 -> 11.295075 | ... O35: =O32*'Domestic NG Prices'!$N$24 -> 13.792088 | P35: 0 | Q35: =R35*0.9 -> 0 | R35: 0 | S35: 0 | T35: 0 | U35: =T35 -> 0 | W35: =R35 -> 0 | X35: 1.01 | Y35: 1.01 | Z35: 1.01 | AA35: 1.1 | AB35: 1.01
A36: *
A37: R5 | B37: MINNGAD1 | C37: Domestic natural gas - step 1 | D37: =Commodities!C$11 -> NGAD0 | E37: 2010 | F37: =F39*'Domestic NG Prices'!$N$19 -> 3.5667714 | G37: =G39*'Domestic NG Prices'!$N$19 -> 2.93191 | H37: =H39*'Domestic NG Prices'!$N$19 -> 3.427406 | I37: =I39*'Domestic NG Prices'!$N$19 -> 4.0985992 | J37: =J39*'Domestic NG Prices'!$N$19 -> 4.7260766 | K37: =K39*'Domestic NG Prices'!$N$19 -> 5.4230838 | L37: =L39*'Domestic NG Prices'!$N$19 -> 5.9926204 | M37: =M39*'Domestic NG Prices'!$N$19 -> 6.286944 | ... O37: =O39*'Domestic NG Prices'!$N$19 -> 7.6768048 | P37: 0 | Q37: =R37*0.9 -> 0 | R37: 0 | S37: 0 | T37: 0 | U37: =T37 -> 0 | X37: 1.1 | Y37: 1.05 | Z37: 1.01 | AA37: 1.1 | AB37: 1.01
A38: R5 | B38: MINNGAD2 | C38: Domestic natural gas - step 2 | D38: =Commodities!C$11 -> NGAD0 | E38: 2010 | F38: =F39*'Domestic NG Prices'!$N$20 -> 3.8504918 | G38: =G39*'Domestic NG Prices'!$N$20 -> 3.1651301 | H38: =H39*'Domestic NG Prices'!$N$20 -> 3.7000405 | I38: =I39*'Domestic NG Prices'!$N$20 -> 4.4246241 | J38: =J39*'Domestic NG Prices'!$N$20 -> 5.1020145 | K38: =K39*'Domestic NG Prices'!$N$20 -> 5.8544654 | L38: =L39*'Domestic NG Prices'!$N$20 -> 6.4693061 | M38: =M39*'Domestic NG Prices'!$N$20 -> 6.7870418 | ... O38: =O39*'Domestic NG Prices'!$N$20 -> 8.2874597 | P38: 0 | Q38: =R38*0.9 -> 0 | R38: 0 | S38: 0 | T38: 0 | U38: =T38 -> 0 | X38: 1.2 | Y38: 1.1 | Z38: 1.05 | AA38: 1.1 | AB38: 1.01
A39: R5 | B39: MINNGAD3 | C39: Domestic natural gas - step 3 | D39: =Commodities!C$11 -> NGAD0 | E39: 2010 | F39: ='Domestic NG Prices'!N42*'Domestic NG Prices'!$P$27*TechData_DelNGA!$I$20 -> 4.0531493 | G39: ='Domestic NG Prices'!O42*'Domestic NG Prices'!$P$27*TechData_DelNGA!$I$20*G8 -> 3.3317159 | H39: ='Domestic NG Prices'!P42*'Domestic NG Prices'!$P$27*TechData_DelNGA!$I$20*H8 -> 3.8947795 | I39: ='Domestic NG Prices'!Q42*'Domestic NG Prices'!$P$27*TechData_DelNGA!$I$20*I8 -> 4.6574991 | J39: ='Domestic NG Prices'!R42*'Domestic NG Prices'!$P$27*TechData_DelNGA!$I$20*J8 -> 5.3705416 | K39: ='Domestic NG Prices'!S42*'Domestic NG Prices'!$P$27*TechData_DelNGA!$I$20*K8 -> 6.1625952 | L39: ='Domestic NG Prices'!T42*'Domestic NG Prices'!$P$27*TechData_DelNGA!$I$20*L8 -> 6.8097959 | M39: =7.14425453277032*M8 -> 7.1442545 | N39: =7.89454986927814*N8 -> 7.8945499 | O39: =8.72364182332011*O8 -> 8.7236418 | P39: 0 | Q39: =R39*0.9 -> 0 | R39: 0 | S39: 0 | T39: 0 | U39: =T39 -> 0 | X39: 1.1 | Y39: 1.1 | Z39: 1.05 | AA39: 1.1 | AB39: 1.01
A40: R5 | B40: MINNGAD4 | C40: Domestic natural gas - step 4 | D40: =Commodities!C$11 -> NGAD0 | E40: 2010 | F40: =F39*'Domestic NG Prices'!$N$22 -> 4.3774012 | G40: =G39*'Domestic NG Prices'!$N$22 -> 3.5982532 | H40: =H39*'Domestic NG Prices'!$N$22 -> 4.2063619 | I40: =I39*'Domestic NG Prices'!$N$22 -> 5.030099 | J40: =J39*'Domestic NG Prices'!$N$22 -> 5.8001849 | K40: =K39*'Domestic NG Prices'!$N$22 -> 6.6556028 | L40: =L39*'Domestic NG Prices'!$N$22 -> 7.3545796 | M40: =M39*'Domestic NG Prices'!$N$22 -> 7.7157949 | ... O40: =O39*'Domestic NG Prices'!$N$22 -> 9.4215332 | P40: 0 | Q40: =R40*0.9 -> 0 | R40: 0 | S40: 0 | T40: 0 | U40: =T40 -> 0 | X40: 1.1 | Y40: 1.1 | Z40: 1.1 | AA40: 1.1 | AB40: 1.01
A41: R5 | B41: MINNGAD5 | C41: Domestic natural gas - step 5 | D41: =Commodities!C$11 -> NGAD0 | E41: 2010 | F41: =F39*'Domestic NG Prices'!$N$23 -> 4.5395272 | G41: =G39*'Domestic NG Prices'!$N$23 -> 3.7315218 | H41: =H39*'Domestic NG Prices'!$N$23 -> 4.362153 | I41: =I39*'Domestic NG Prices'!$N$23 -> 5.216399 | J41: =J39*'Domestic NG Prices'!$N$23 -> 6.0150066 | K41: =K39*'Domestic NG Prices'!$N$23 -> 6.9021066 | L41: =L39*'Domestic NG Prices'!$N$23 -> 7.6269714 | M41: =M39*'Domestic NG Prices'!$N$23 -> 8.0015651 | ... O41: =O39*'Domestic NG Prices'!$N$23 -> 9.7704788 | P41: 0 | Q41: =R41*0.9 -> 0 | R41: 0 | S41: 0 | T41: 0 | U41: =T41 -> 0 | W41: =R41 -> 0 | X41: 1.01 | Y41: 1.01 | Z41: 1.01 | AA41: 1.1 | AB41: 1.01
A42: R5 | B42: MINNGAD6 | C42: Domestic natural gas - step 6 | D42: =Commodities!C$11 -> NGAD0 | E42: 2010 | F42: =F39*'Domestic NG Prices'!$N$24 -> 6.2013184 | G42: =G39*'Domestic NG Prices'!$N$24 -> 5.0975254 | H42: =H39*'Domestic NG Prices'!$N$24 -> 5.9590126 | I42: =I39*'Domestic NG Prices'!$N$24 -> 7.1259736 | J42: =J39*'Domestic NG Prices'!$N$24 -> 8.2169286 | K42: =K39*'Domestic NG Prices'!$N$24 -> 9.4287707 | L42: =L39*'Domestic NG Prices'!$N$24 -> 10.418988 | M42: =M39*'Domestic NG Prices'!$N$24 -> 10.930709 | ... O42: =O39*'Domestic NG Prices'!$N$24 -> 13.347172 | P42: 0 | Q42: =R42*0.9 -> 0 | R42: 0 | S42: 0 | T42: 0 | U42: =T42 -> 0 | W42: =R42 -> 0 | X42: 1.01 | Y42: 1.01 | Z42: 1.01 | AA42: 1.1 | AB42: 1.01
A43: *
A44: *
E47: ~FI_T
A48: Region | B48: TechName | C48: TechDesc | D48: CommIN | E48: CommOUT | F48: *TID | G48: EFF | H48: NCAP_COST | I48: NCAP_FOM | J48: ACT_COST | K48: AFA | N48: ENV_ACT~CO2~2010 | O48: ENV_ACT~CO2~2015-2055 | P48: ENV_ACT~VOC~2010 | Q48: ENV_ACT~VOC~2015 | R48: ENV_ACT~VOC~2020-2055 | S48: ENV_ACT~CO~2010 | T48: ENV_ACT~CO~2015 | U48: ENV_ACT~CO~2020-2055 | V48: ENV_ACT~NOX~2010 | W48: ENV_ACT~NOX~2015 | X48: ENV_ACT~NOX~2020-2055 | Y48: ENV_ACT~PM10~2010 | Z48: ENV_ACT~PM10~2015 | AA48: ENV_ACT~PM10~2020-2055 | AB48: ENV_ACT~PM25~2010 | AC48: ENV_ACT~PM25~2015 | AD48: ENV_ACT~PM25~2020-2055 | AE48: ENV_ACT~SO2~2010 | AF48: ENV_ACT~SO2~2015 | AG48: ENV_ACT~SO2~2020-2055 | AH48: ENV_ACT~CH4~2010-2015 | AI48: ENV_ACT~CH4~2015 | AJ48: ENV_ACT~CH4~2020-2055 | AK48: ENV_ACT~N2O~2010 | AL48: ENV_ACT~N2O~2015 | AM48: ENV_ACT~N2O~2020-2055 | AN48: ENV_ACT~OC~2010 | AO48: ENV_ACT~OC~2015 | AP48: ENV_ACT~OC~2020-2055 | AQ48: ENV_ACT~BC~2010 | AR48: ENV_ACT~BC~2015 | AS48: ENV_ACT~BC~2020-2055
A49: *Extraction Natural gas
A50: R1 | B50: SCMINNGAD | C50: Collector: MINNGAD | D50: NGAD0 | E50: =Commodities!C12 -> NGAD1 | F50: 2010 | G50: 1 | N50: =N51 -> 0.0056288631 | O50: =O51 -> 0.0056288631 | P50: =P51 -> 0.00073165 | Q50: =Q51 -> 0.00069187 | R50: =R51 -> 0.00066926 | S50: =S51 -> 0.00482293 | T50: =T51 -> 0.00459133 | U50: =U51 -> 0.00442755 | ... AN50: =AN51 -> 1.8008454e-05 | AO50: =AN51 -> 1.8008454e-05 | AP50: =AP51 -> 1.4447292e-05 | AQ50: =AQ51 -> 4.739067e-06 | AR50: =AR51 -> 4.2047746e-06 | AS50: =AS51 -> 3.8019189e-06
A51: R2 | B51: SCMINNGAD | C51: Collector: MINNGAD | D51: NGAD0 | E51: =Commodities!C13 -> NGAD2 | F51: 2010 | G51: 1 | N51: =Emissions!G109/1000 -> 0.0056288631 | O51: =Emissions!H109/1000 -> 0.0056288631 | P51: =Emissions!D71 -> 0.00073165 | Q51: =Emissions!E71 -> 0.00069187 | R51: =Emissions!F71 -> 0.00066926 | S51: =Emissions!D72 -> 0.00482293 | T51: =Emissions!E72 -> 0.00459133 | U51: =Emissions!F72 -> 0.00442755 | V51: =Emissions!D73 -> 0.01509156 | W51: =Emissions!E73 -> 0.01298537 | X51: =Emissions!F73 -> 0.01214993 | Y51: =Emissions!D74 -> 0.00035759 | Z51: =Emissions!E74 -> 0.00032223 | AA51: =Emissions!F74 -> 0.00029514 | AB51: =Emissions!D75 -> 0.00027727 | AC51: =Emissions!E75 -> 0.00024601 | AD51: =Emissions!F75 -> 0.00022244 | AE51: =Emissions!D76 -> 0.00054063 | AF51: =Emissions!E76 -> 0.00048401 | AG51: =Emissions!F76 -> 0.00048117 | AH51: =Emissions!J109 -> 0.28887951 | AI51: =Emissions!K109 -> 0.2251827 | AJ51: =AI51 -> 0.2251827 | AK51: =Emissions!D78 -> 4.3059e-05 | AL51: =Emissions!E78 -> 4.3051e-05 | AM51: =Emissions!F78 -> 4.3033e-05 | AN51: =Emissions!M11 -> 1.8008454e-05 | AO51: =$AN51/$AB51*AC51 -> 1.5978144e-05 | AP51: =$AN51/$AB51*AD51 -> 1.4447292e-05 | AQ51: =Emissions!N11 -> 4.739067e-06 | AR51: =$AQ51/$AB51*AC51 -> 4.2047746e-06 | AS51: =$AQ51/$AB51*AD51 -> 3.8019189e-06
A52: R3 | B52: SCMINNGAD | C52: Collector: MINNGAD | D52: NGAD0 | E52: =Commodities!C14 -> NGAD3 | F52: 2010 | G52: 1 | N52: =Emissions!G110/1000 -> 0.0055391483 | O52: =Emissions!H110/1000 -> 0.0055391483 | P52: =P51 -> 0.00073165 | Q52: =Q51 -> 0.00069187 | R52: =R51 -> 0.00066926 | S52: =S51 -> 0.00482293 | T52: =T51 -> 0.00459133 | U52: =U51 -> 0.00442755 | V52: =V51 -> 0.01509156 | W52: =W51 -> 0.01298537 | ... AG52: =AG51 -> 0.00048117 | AH52: =Emissions!J110 -> 0.30777943 | AI52: =Emissions!K110 -> 0.26800655 | AJ52: =AI52 -> 0.26800655 | AK52: =AK51 -> 4.3059e-05 | AL52: =AL51 -> 4.3051e-05 | AM52: =AM51 -> 4.3033e-05 | AN52: =AN51 -> 1.8008454e-05 | AO52: =AO51 -> 1.5978144e-05 | AP52: =AP51 -> 1.4447292e-05 | AQ52: =AQ51 -> 4.739067e-06 | AR52: =AR51 -> 4.2047746e-06 | AS52: =AS51 -> 3.8019189e-06
A53: R4 | B53: SCMINNGAD | C53: Collector: MINNGAD | D53: NGAD0 | E53: =Commodities!C15 -> NGAD4 | F53: 2010 | G53: 1 | N53: =Emissions!G111/1000 -> 0.0054616638 | O53: =Emissions!H111/1000 -> 0.0054616638 | P53: =P52 -> 0.00073165 | Q53: =Q52 -> 0.00069187 | R53: =R52 -> 0.00066926 | S53: =S52 -> 0.00482293 | T53: =T52 -> 0.00459133 | U53: =U52 -> 0.00442755 | V53: =V52 -> 0.01509156 | W53: =W52 -> 0.01298537 | ... AG53: =AG52 -> 0.00048117 | AH53: =Emissions!J111 -> 0.32410282 | AI53: =Emissions!K111 -> 0.30499246 | AJ53: =AI53 -> 0.30499246 | AK53: =AK52 -> 4.3059e-05 | AL53: =AL52 -> 4.3051e-05 | AM53: =AM52 -> 4.3033e-05 | AN53: =AN52 -> 1.8008454e-05 | AO53: =AO52 -> 1.5978144e-05 | AP53: =AP52 -> 1.4447292e-05 | AQ53: =AQ52 -> 4.739067e-06 | AR53: =AR52 -> 4.2047746e-06 | AS53: =AS52 -> 3.8019189e-06
A54: R5 | B54: SCMINNGAD | C54: Collector: MINNGAD | D54: NGAD0 | E54: =Commodities!C16 -> NGAD5 | F54: 2010 | G54: 1 | N54: =Emissions!G112/1000 -> 0.0055209677 | O54: =Emissions!H112/1000 -> 0.0055209677 | P54: =P53 -> 0.00073165 | Q54: =Q53 -> 0.00069187 | R54: =R53 -> 0.00066926 | S54: =S53 -> 0.00482293 | T54: =T53 -> 0.00459133 | U54: =U53 -> 0.00442755 | V54: =V53 -> 0.01509156 | W54: =W53 -> 0.01298537 | ... AG54: =AG53 -> 0.00048117 | AH54: =Emissions!J112 -> 0.31160946 | AI54: =Emissions!K112 -> 0.27668473 | AJ54: =AI54 -> 0.27668473 | AK54: =AK53 -> 4.3059e-05 | AL54: =AL53 -> 4.3051e-05 | AM54: =AM53 -> 4.3033e-05 | AN54: =AN53 -> 1.8008454e-05 | AO54: =AO53 -> 1.5978144e-05 | AP54: =AP53 -> 1.4447292e-05 | AQ54: =AQ53 -> 4.739067e-06 | AR54: =AR53 -> 4.2047746e-06 | AS54: =AS53 -> 3.8019189e-06
A55: R6 | B55: SCMINNGAD | C55: Collector: MINNGAD | D55: NGAD0 | E55: =Commodities!C17 -> NGAD6 | F55: 2010 | G55: 1 | N55: =Emissions!G113/1000 -> 0.00539 | O55: =Emissions!H113/1000 -> 0.00539 | P55: =P54 -> 0.00073165 | Q55: =Q54 -> 0.00069187 | R55: =R54 -> 0.00066926 | S55: =S54 -> 0.00482293 | T55: =T54 -> 0.00459133 | U55: =U54 -> 0.00442755 | V55: =V54 -> 0.01509156 | W55: =W54 -> 0.01298537 | ... AG55: =AG54 -> 0.00048117 | AH55: =Emissions!J113 -> 0.3392 | AI55: =Emissions!K113 -> 0.3392 | AJ55: =AI55 -> 0.3392 | AK55: =AK54 -> 4.3059e-05 | AL55: =AL54 -> 4.3051e-05 | AM55: =AM54 -> 4.3033e-05 | AN55: =AN54 -> 1.8008454e-05 | AO55: =AO54 -> 1.5978144e-05 | AP55: =AP54 -> 1.4447292e-05 | AQ55: =AQ54 -> 4.739067e-06 | AR55: =AR54 -> 4.2047746e-06 | AS55: =AS54 -> 3.8019189e-06
A56: *
A57: *
D60: ~FI_T
A61: Region | B61: TechName | C61: TechDesc | D61: CommOUT | E61: *TID | F61: COST~2010 | G61: COST~2015 | H61: COST~2020 | I61: COST~2025 | J61: COST~2030 | K61: COST~2035 | L61: COST~2040 | M61: COST~2045 | N61: COST~2050 | O61: COST~2055 | P61: ACT_BND~LO~2010 | Q61: ACT_BND~UP~2010 | R61: ACT_BND~UP~2015 | S61: ACT_BND~UP~2020 | T61: ACT_BND~UP~2055 | V61: *GROWTH_TIDr | W61: *GROWTHr~2010 | X61: *GROWTHr~2015-2020 | Y61: *GROWTHr~2025-2055 | Z61: *DECAYr~2010 | AA61: *DECAYr~2015-2055
A62: *Imported Natural Gas supply
A63: R0 | B63: =Technologies!C30 -> IMPNGALA | C63: =Technologies!D30 -> Imported LNG - Step A | D63: =Commodities!$C$27 -> NGAL | E63: 2010 | F63: =F65*'Domestic NG Prices'!$N$19 -> 4.0308211 | G63: =G65*'Domestic NG Prices'!$N$19 -> 3.8312125 | H63: =H65*'Domestic NG Prices'!$N$19 -> 4.4927205 | I63: =I65*'Domestic NG Prices'!$N$19 -> 4.930375 | J63: =J65*'Domestic NG Prices'!$N$19 -> 5.4268446 | K63: =K65*'Domestic NG Prices'!$N$19 -> 6.1015641 | L63: =L65*'Domestic NG Prices'!$N$19 -> 6.7357129 | M63: =M65*'Domestic NG Prices'!$N$19 -> 7.4743024 | ... O63: =O65*'Domestic NG Prices'!$N$19 -> 9.2033271 | P63: =Q63*0.9 -> 143.6252 | Q63: ='AEO NG Imports'!AB16 -> 159.58355 | R63: ='AEO NG Imports'!AC16 -> 16.799403 | S63: 0 | T63: =S63 -> 0
A64: R0 | B64: =Technologies!C31 -> IMPNGALB | C64: =Technologies!D31 -> Imported LNG - Step B | D64: =Commodities!$C$27 -> NGAL | E64: 2010 | F64: =F65*'Domestic NG Prices'!$N$20 -> 4.3514546 | G64: =G65*'Domestic NG Prices'!$N$20 -> 4.1359681 | H64: =H65*'Domestic NG Prices'!$N$20 -> 4.850096 | I64: =I65*'Domestic NG Prices'!$N$20 -> 5.322564 | J64: =J65*'Domestic NG Prices'!$N$20 -> 5.8585254 | K64: =K65*'Domestic NG Prices'!$N$20 -> 6.5869158 | L64: =L65*'Domestic NG Prices'!$N$20 -> 7.2715083 | M64: =M65*'Domestic NG Prices'!$N$20 -> 8.0688492 | ... O64: =O65*'Domestic NG Prices'!$N$20 -> 9.9354099 | P64: =Q64*0.9 -> 107.7189 | Q64: ='AEO NG Imports'!AB17 -> 119.68766 | R64: ='AEO NG Imports'!AC17 -> 12.599553 | S64: 0 | T64: =S64 -> 0
A65: R0 | B65: =Technologies!C32 -> IMPNGALC | C65: =Technologies!D32 -> Imported LNG - Step C | D65: =Commodities!$C$27 -> NGAL | E65: 2010 | F65: ='AEO NG Imports'!L29*'Domestic NG Prices'!$P$27 -> 4.5804785 | G65: ='AEO NG Imports'!M29*'Domestic NG Prices'!$P$27 -> 4.3536506 | H65: ='AEO NG Imports'!N29*'Domestic NG Prices'!$P$27 -> 5.1053642 | I65: ='AEO NG Imports'!O29*'Domestic NG Prices'!$P$27 -> 5.6026989 | J65: ='AEO NG Imports'!P29*'Domestic NG Prices'!$P$27 -> 6.1668688 | K65: ='AEO NG Imports'!Q29*'Domestic NG Prices'!$P$27 -> 6.9335955 | L65: ='AEO NG Imports'!R29*'Domestic NG Prices'!$P$27 -> 7.6542192 | M65: =L65*'AEO NG Imports'!$S$29 -> 8.4935255 | N65: =M65*'AEO NG Imports'!$S$29 -> 9.424864 | O65: =N65*'AEO NG Imports'!$S$29 -> 10.458326 | P65: =Q65*0.9 -> 107.7189 | Q65: ='AEO NG Imports'!AB18 -> 119.68766 | R65: ='AEO NG Imports'!AC18 -> 12.599553 | S65: 0 | T65: =S65 -> 0
A66: R0 | B66: =Technologies!$C$34 -> IMPNGAC1 | C66: =Technologies!$D$34 -> Imported natural gas from Canada - Step 1 | D66: =Commodities!$C$25 -> NGAC | E66: 2010 | F66: =F68*'Domestic NG Prices'!$N$19 -> 3.6554815 | G66: =G68*'Domestic NG Prices'!$N$19 -> 3.1311435 | H66: =H68*'Domestic NG Prices'!$N$19 -> 4.2346097 | I66: =I68*'Domestic NG Prices'!$N$19 -> 4.6125943 | J66: =J68*'Domestic NG Prices'!$N$19 -> 5.1934754 | K66: =K68*'Domestic NG Prices'!$N$19 -> 5.7363474 | L66: =L68*'Domestic NG Prices'!$N$19 -> 6.2166128 | M66: =M68*'Domestic NG Prices'!$N$19 -> 6.8676714 | ... O66: =O68*'Domestic NG Prices'!$N$19 -> 8.3814834 | P66: =Q66*0.9 -> 974.32227 | Q66: ='AEO NG Imports'!AB9 -> 1082.5803 | W66: 1.005 | X66: 1.005 | Y66: 1.005 | Z66: 1.25 | AA66: 1.25
A67: R0 | B67: =Technologies!$C$35 -> IMPNGAC2 | C67: =Technologies!$D$35 -> Imported natural gas from Canada - Step 2 | D67: =Commodities!$C$25 -> NGAC | E67: 2010 | F67: =F68*'Domestic NG Prices'!$N$20 -> 3.9462584 | G67: =G68*'Domestic NG Prices'!$N$20 -> 3.3802117 | H67: =H68*'Domestic NG Prices'!$N$20 -> 4.5714536 | I67: =I68*'Domestic NG Prices'!$N$20 -> 4.9795052 | J67: =J68*'Domestic NG Prices'!$N$20 -> 5.6065927 | K67: =K68*'Domestic NG Prices'!$N$20 -> 6.1926478 | L67: =L68*'Domestic NG Prices'!$N$20 -> 6.711116 | M67: =M68*'Domestic NG Prices'!$N$20 -> 7.4139634 | ... O67: =O68*'Domestic NG Prices'!$N$20 -> 9.0481923 | P67: =Q67*0.9 -> 730.7417 | Q67: ='AEO NG Imports'!AB10 -> 811.93523 | W67: 1.005 | X67: 1.005 | Y67: 1.005 | Z67: 1.25 | AA67: 1.25
A68: R0 | B68: =Technologies!$C$36 -> IMPNGAC3 | C68: =Technologies!$D$36 -> Imported natural gas from Canada - Step 3 | D68: =Commodities!$C$25 -> NGAC | E68: 2010 | F68: ='AEO NG Imports'!L26*'Domestic NG Prices'!$P$27 -> 4.1539562 | G68: ='AEO NG Imports'!M26*'Domestic NG Prices'!$P$27 -> 3.5581176 | H68: ='AEO NG Imports'!N26*'Domestic NG Prices'!$P$27 -> 4.8120564 | I68: ='AEO NG Imports'!O26*'Domestic NG Prices'!$P$27 -> 5.2415845 | J68: ='AEO NG Imports'!P26*'Domestic NG Prices'!$P$27 -> 5.9016766 | K68: ='AEO NG Imports'!Q26*'Domestic NG Prices'!$P$27 -> 6.5185766 | L68: ='AEO NG Imports'!R26*'Domestic NG Prices'!$P$27 -> 7.0643327 | M68: =L68*'AEO NG Imports'!$S$26 -> 7.804172 | N68: =M68*'AEO NG Imports'!$S$26 -> 8.6214939 | O68: =N68*'AEO NG Imports'!$S$26 -> 9.524413 | P68: =Q68*0.9 -> 730.7417 | Q68: ='AEO NG Imports'!AB11 -> 811.93523 | W68: 1.005 | X68: 1.005 | Y68: 1.005 | Z68: 1.25 | AA68: 1.25
A69: R0 | B69: =Technologies!$C$37 -> IMPNGAC4 | C69: =Technologies!$D$37 -> Imported natural gas from Canada - Step 4 | D69: =Commodities!$C$25 -> NGAC | E69: 2010 | F69: =F68*'Domestic NG Prices'!$N$22 -> 4.4862727 | G69: =G68*'Domestic NG Prices'!$N$22 -> 3.842767 | H69: =H68*'Domestic NG Prices'!$N$22 -> 5.197021 | I69: =I68*'Domestic NG Prices'!$N$22 -> 5.6609112 | J69: =J68*'Domestic NG Prices'!$N$22 -> 6.3738107 | K69: =K68*'Domestic NG Prices'!$N$22 -> 7.0400627 | L69: =L68*'Domestic NG Prices'!$N$22 -> 7.6294793 | M69: =M68*'Domestic NG Prices'!$N$22 -> 8.4285058 | ... O69: =O68*'Domestic NG Prices'!$N$22 -> 10.286366 | Q69: ='AEO NG Imports'!AB12 -> 135.32254 | W69: 1.005 | X69: 1.005 | Y69: 1.005 | Z69: 1.25 | AA69: 1.25
A70: R0 | B70: =Technologies!$C$38 -> IMPNGAC5 | C70: =Technologies!$D$38 -> Imported natural gas from Canada - Step 5 | D70: =Commodities!$C$25 -> NGAC | E70: 2010 | F70: =F68*'Domestic NG Prices'!$N$23 -> 4.652431 | G70: =G68*'Domestic NG Prices'!$N$23 -> 3.9850917 | H70: =H68*'Domestic NG Prices'!$N$23 -> 5.3895032 | I70: =I68*'Domestic NG Prices'!$N$23 -> 5.8705746 | J70: =J68*'Domestic NG Prices'!$N$23 -> 6.6098777 | K70: =K68*'Domestic NG Prices'!$N$23 -> 7.3008058 | L70: =L68*'Domestic NG Prices'!$N$23 -> 7.9120526 | M70: =M68*'Domestic NG Prices'!$N$23 -> 8.7406727 | ... O70: =O68*'Domestic NG Prices'!$N$23 -> 10.667343 | Q70: ='AEO NG Imports'!AB13 -> 135.32254 | W70: 1.005 | X70: 1.005 | Y70: 1.005 | Z70: 1.25 | AA70: 1.25
A71: R0 | B71: =Technologies!$C$39 -> IMPNGAC6 | C71: =Technologies!$D$39 -> Imported natural gas from Canada - Step 6 | D71: =Commodities!$C$25 -> NGAC | E71: 2010 | F71: =F68*'Domestic NG Prices'!$N$24 -> 6.355553 | G71: =G68*'Domestic NG Prices'!$N$24 -> 5.4439199 | H71: =H68*'Domestic NG Prices'!$N$24 -> 7.3624464 | I71: =I68*'Domestic NG Prices'!$N$24 -> 8.0196242 | J71: =J68*'Domestic NG Prices'!$N$24 -> 9.0295651 | K71: =K68*'Domestic NG Prices'!$N$24 -> 9.9734222 | L71: =L68*'Domestic NG Prices'!$N$24 -> 10.808429 | M71: =M68*'Domestic NG Prices'!$N$24 -> 11.940383 | ... O71: =O68*'Domestic NG Prices'!$N$24 -> 14.572352 | Q71: ='AEO NG Imports'!AB14 -> 270.64508 | W71: 1.005 | X71: 1.005 | Y71: 1.005 | Z71: 1.25 | AA71: 1.25
E75: ~FI_T
A76: Region | B76: TechName | C76: TechDesc | D76: CommIN | E76: CommOUT | F76: *TID | G76: EFF | H76: Share~UP
A77: R0 | B77: SCIMPNGAL | C77: Share of Imported LNG to Existing Terminals | D77: NGAL | F77: 2010 | G77: 1
A78: =A77 -> R0 | E78: NGALE1 | H78: 0.266993
A79: =A78 -> R0 | E79: NGALE4 | H79: 0.5604
A80: =A79 -> R0 | E80: NGALE5 | H80: 0.17261824
A81: R0 | B81: SCIMPNGAC | C81: Canadian imported natural gas shares | D81: NGAC | E81: NGACX | F81: 2010 | G81: 1
A82: =Technologies!B41 -> R0 | B82: =Technologies!C41 -> SCNGAC1 | C82: =Technologies!D41 -> Canadian imported natural gas in R1 | D82: NGACX | E82: =Commodities!C29 -> NGAC1 | F82: 2010 | G82: 1
A83: =Technologies!B42 -> *R0 | B83: =Technologies!C42 -> SCNGAC2 | C83: =Technologies!D42 -> Canadian imported natural gas in R2 | D83: NGACX | E83: =Commodities!C30 -> NGAC2 | F83: 2010 | G83: 1
A84: =Technologies!B43 -> *R0 | B84: =Technologies!C43 -> SCNGAC3 | C84: =Technologies!D43 -> Canadian imported natural gas in R3 | D84: NGACX | E84: =Commodities!C31 -> NGAC3 | F84: 2010 | G84: 1
A85: =Technologies!B44 -> *R0 | B85: =Technologies!C44 -> SCNGAC4 | C85: =Technologies!D44 -> Canadian imported natural gas in R4 | D85: NGACX | E85: =Commodities!C32 -> NGAC4 | F85: 2010 | G85: 1
A86: =Technologies!B45 -> *R0 | B86: =Technologies!C45 -> SCNGAC5 | C86: =Technologies!D45 -> Canadian imported natural gas in R5 | D86: NGACX | E86: =Commodities!C33 -> NGAC5 | F86: 2010 | G86: 1
A87: =Technologies!B46 -> *R0 | B87: =Technologies!C46 -> SCNGAC6 | C87: =Technologies!D46 -> Canadian imported natural gas in R6 | D87: NGACX | E87: =Commodities!C34 -> NGAC6 | F87: 2010 | G87: 1
D93: ~FI_T
A94: Region | B94: TechName | C94: TechDesc | D94: CommIN | E94: ACT_BND~FX~2010 | F94: ACT_BND~FX~2015 | G94: ACT_BND~FX~2020 | H94: ACT_BND~FX~2025 | I94: ACT_BND~FX~2030 | J94: ACT_BND~FX~2035 | K94: ACT_BND~FX~2040 | L94: ACT_BND~FX~2045 | M94: ACT_BND~FX~2050 | N94: ACT_BND~FX~2055
A95: * Exports of NG Liguids
A96: R1 | B96: =Technologies!C$49 -> EXPNGAL | C96: =Technologies!D$49 -> Exported natural gas liquids | D96: =Commodities!C18 -> NGAR1 | G96: 0 | H96: =-'AEO NG Imports'!O$20*'LNG Export Regions'!AP17 -> 277.11468 | I96: =-'AEO NG Imports'!P$20*'LNG Export Regions'!AQ17 -> 545.06409 | J96: =-'AEO NG Imports'!Q$20*'LNG Export Regions'!AR17 -> 726.75211 | K96: =-'AEO NG Imports'!R$20*'LNG Export Regions'!AS17 -> 908.44014 | L96: =K96 -> 908.44014 | M96: =L96 -> 908.44014 | N96: =M96 -> 908.44014
A97: R2 | B97: =Technologies!C$49 -> EXPNGAL | C97: =Technologies!D$49 -> Exported natural gas liquids | D97: =Commodities!C19 -> NGAR2 | E97: 0 | F97: 0 | G97: 0 | H97: 0 | I97: 0 | J97: 0 | K97: 0 | L97: 0 | M97: 0 | N97: 0
A98: R3 | B98: =Technologies!C$49 -> EXPNGAL | C98: =Technologies!D$49 -> Exported natural gas liquids | D98: =Commodities!C20 -> NGAR3 | E98: 0 | F98: 0 | G98: 0 | H98: 0 | I98: 0 | J98: 0 | K98: 0 | L98: 0 | M98: 0 | N98: 0
A99: R4 | B99: =Technologies!C$49 -> EXPNGAL | C99: =Technologies!D$49 -> Exported natural gas liquids | D99: =Commodities!C21 -> NGAR4 | E99: 0 | F99: 0 | G99: 0 | H99: 0 | I99: 0 | J99: 0 | K99: 0 | L99: 0 | M99: 0 | N99: 0
A100: R5 | B100: =Technologies!C$49 -> EXPNGAL | C100: =Technologies!D$49 -> Exported natural gas liquids | D100: =Commodities!C22 -> NGAR5 | E100: 0 | F100: 0 | G100: 0 | H100: 0 | I100: 0 | J100: 0 | K100: 0 | L100: 0 | M100: 0 | N100: 0
A101: R6 | B101: =Technologies!C$49 -> EXPNGAL | C101: =Technologies!D$49 -> Exported natural gas liquids | D101: =Commodities!C23 -> NGAR6 | E101: 0 | F101: 0 | G101: 0 | H101: 0 | I101: 0 | J101: 0 | K101: 0 | L101: 0 | M101: 0 | N101: 0
D108: ~FI_T
A109: Region | B109: TechName | C109: TechDesc | D109: CommOUT | E109: *TID | F109: COST~2010 | G109: COST~2015 | H109: COST~2020 | I109: COST~2025 | J109: COST~2030 | K109: COST~2035 | L109: COST~2040 | M109: COST~2045 | N109: COST~2050 | O109: COST~2055
A110: * Dummy NGA Supply Technologies (COST is 1.25 x the highest price step)
A111: =Technologies!B15 -> R1 | B111: =Technologies!C15 -> MINNGLDMY | C111: =Technologies!D15 -> Dummy NGL Resource Supply | D111: =Commodities!C24 -> NGL | E111: 2010 | F111: =F65*1.25 -> 5.7255981 | G111: =G65*1.25 -> 5.4420633 | H111: =H65*1.25 -> 6.3817052 | I111: =I65*1.25 -> 7.0033736 | J111: =J65*1.25 -> 7.708586 | K111: =K65*1.25 -> 8.6669944 | L111: =L65*1.25 -> 9.5677741 | M111: =M65*1.25 -> 10.616907 | ... O111: =O65*1.25 -> 13.072908

Sheet TechData_DelNGA
B1: TechData | C1: _GLOBAL,R0,R1,R2,R3,R4,R5,R6
F4: ~FI_T
B5: Region | C5: TechName | D5: TechDesc | E5: CommIN | F5: CommOUT | G5: NCAP_TLIFE | H5: EFF | I5: Share~UP
B6: *Domestic natural gas infrastructure
B7: R1 | C7: =Technologies!C$23 -> SCNGAD1 | D7: =Technologies!D$23 -> Domestic natural gas Existing infrastructure in R1 | E7: =Commodities!C$12 -> NGAD1 | G7: 55 | H7: 1
B8: =B7 -> R1 | F8: =Commodities!$C$9 -> NGA | I8: ='Domestic NG Production'!M59 -> 0.99573593
B9: =B8 -> R1 | F9: NGL | I9: ='Domestic NG Production'!M60 -> 0.0042640693
B10: R2 | C10: =Technologies!C$24 -> SCNGAD2 | D10: =Technologies!D$24 -> Domestic natural gas Existing infrastructure in R2 | E10: =Commodities!C$13 -> NGAD2 | G10: 55 | H10: 1
B11: =B10 -> R2 | F11: =Commodities!$C$9 -> NGA | I11: =I8 -> 0.99573593
B12: =B11 -> R2 | F12: NGL | I12: =I9 -> 0.0042640693
B13: R3 | C13: =Technologies!C$25 -> SCNGAD3 | D13: =Technologies!D$25 -> Domestic natural gas Existing infrastructure in R3 | E13: =Commodities!C$14 -> NGAD3 | G13: 55 | H13: 1
B14: =B13 -> R3 | F14: =Commodities!$C$9 -> NGA | I14: =I11 -> 0.99573593
B15: =B14 -> R3 | F15: NGL | I15: =I12 -> 0.0042640693
B16: R4 | C16: =Technologies!C$26 -> SCNGAD4 | D16: =Technologies!D$26 -> Domestic natural gas Existing infrastructure in R4 | E16: =Commodities!C$15 -> NGAD4 | G16: 55 | H16: 1
B17: =B16 -> R4 | F17: =Commodities!$C$9 -> NGA | I17: =I14 -> 0.99573593
B18: =B17 -> R4 | F18: NGL | I18: =I15 -> 0.0042640693
B19: R5 | C19: =Technologies!C$27 -> SCNGAD5 | D19: =Technologies!D$27 -> Domestic natural gas Existing infrastructure in R5 | E19: =Commodities!C$16 -> NGAD5 | G19: 55 | H19: 1
B20: =B19 -> R5 | F20: =Commodities!$C$9 -> NGA | I20: =I17 -> 0.99573593
B21: =B20 -> R5 | F21: NGL | I21: =I18 -> 0.0042640693
B22: R6 | C22: =Technologies!C$28 -> SCNGAD6 | D22: =Technologies!D$28 -> Domestic natural gas Existing infrastructure in R6 | E22: =Commodities!C$17 -> NGAD6 | G22: 55 | H22: 1
B23: =B22 -> R6 | F23: =Commodities!$C$9 -> NGA | I23: =I20 -> 0.99573593
B24: =B23 -> R6 | F24: NGL | I24: =I21 -> 0.0042640693
F27: ~FI_T
B28: Region | C28: TechName | D28: TechDesc | E28: CommIN | F28: CommOUT | G28: NCAP_TLIFE | H28: EFF | I28: ACT_BND~UP | J28: NCAP_COST
B29: * Imported natural gas Pipeline technologies
B30: =Technologies!$B$50 -> R1 | C30: =Technologies!$C$50 -> XNGAC1E | D30: =Technologies!$D$50 -> Existing Pipeline for Import Canadian natural gas to R1 | E30: =Commodities!C29 -> NGAC1 | F30: =Commodities!$C$9 -> NGA | G30: 55 | H30: 1 | I30: =NGACap!B17*Conv!$D$6*Conv!$J$5*10^9 -> 1412.2711
B31: =Technologies!$B$51 -> *R2 | C31: =Technologies!$C$51 -> XNGAC2E | D31: =Technologies!$D$51 -> Existing Pipeline for Import Canadian natural gas to R2 | E31: =Commodities!C30 -> NGAC2 | F31: =Commodities!$C$9 -> NGA | G31: 55 | H31: 1 | I31: 9999
B32: =Technologies!$B$52 -> *R3 | C32: =Technologies!$C$52 -> XNGAC3E | D32: =Technologies!$D$52 -> Existing Pipeline for Import Canadian natural gas to R3 | E32: =Commodities!C31 -> NGAC3 | F32: =Commodities!$C$9 -> NGA | G32: 55 | H32: 1 | I32: 9999
B33: =Technologies!$B$53 -> *R4 | C33: =Technologies!$C$53 -> XNGAC4E | D33: =Technologies!$D$53 -> Existing Pipeline for Import Canadian natural gas to R4 | E33: =Commodities!C32 -> NGAC4 | F33: =Commodities!$C$9 -> NGA | G33: 55 | H33: 1 | I33: 9999
B34: =Technologies!$B$54 -> *R5 | C34: =Technologies!$C$54 -> XNGAC5E | D34: =Technologies!$D$54 -> Existing Pipeline for Import Canadian natural gas to R5 | E34: =Commodities!C33 -> NGAC5 | F34: =Commodities!$C$9 -> NGA | G34: 55 | H34: 1 | I34: 9999
B35: =Technologies!$B$55 -> *R6 | C35: =Technologies!$C$55 -> XNGAC6E | D35: =Technologies!$D$55 -> Existing Pipeline for Import Canadian natural gas to R6 | E35: =Commodities!C34 -> NGAC6 | F35: =Commodities!$C$9 -> NGA | G35: 55 | H35: 1 | I35: 9999
B36: *LNG Terminals
B37: =Technologies!$B$57 -> R1 | C37: =Technologies!$C$57 -> XNGALE1E | D37: =Technologies!$D$57 -> Infrastructure for Import LNG to Existing terminal in R1 | E37: =Commodities!C35 -> NGALE1 | F37: =Commodities!$C$9 -> NGA | G37: 55 | H37: 1 | I37: 0
B38: =Technologies!$B$58 -> R4 | C38: =Technologies!$C$58 -> XNGALE4E | D38: =Technologies!$D$58 -> Infrastructure for Import LNG to Existing terminal in R4 - Manhattan | E38: =Commodities!C36 -> NGALE4 | F38: =Commodities!$C$9 -> NGA | G38: 55 | H38: 1 | I38: 0
B39: =Technologies!$B$59 -> R5 | C39: =Technologies!$C$59 -> XNGALE5E | D39: =Technologies!$D$59 -> Infrastructure for Import LNG to Existing terminal in R5 - Staten Island | E39: =Commodities!C37 -> NGALE5 | F39: =Commodities!$C$9 -> NGA | G39: 55 | H39: 1 | I39: 0
B42: Region | C42: TechName | D42: TechDesc | E42: CommIN | F42: CommOUT | G42: NCAP_START | H42: NCAP_TLIFE | I42: EFF | J42: ACT_BND~UP | K42: NCAP_COST
B43: * Imported natural gas Pipeline technologies
B44: =Technologies!$B$123 -> R1 | C44: =Technologies!$C$123 -> XNGAC1N | D44: =Technologies!$D$123 -> New Pipeline for Import Canadian natural gas to R1 | E44: =Commodities!C29 -> NGAC1 | F44: =Commodities!$C$9 -> NGA | G44: 2010 | H44: 55 | I44: 1 | K44: =NGExpansion!M72 -> 4.2380354
B45: =Technologies!$B$124 -> *R2 | C45: =Technologies!$C$124 -> XNGAC2N | D45: =Technologies!$D$124 -> New Pipeline for Import Canadian natural gas to R2 | E45: =Commodities!C30 -> NGAC2 | F45: =Commodities!$C$9 -> NGA | G45: 2010 | H45: 55 | I45: 1 | K45: =NGExpansion!M73 -> 2.62137
B46: =Technologies!$B$125 -> *R3 | C46: =Technologies!$C$125 -> XNGAC3N | D46: =Technologies!$D$125 -> New Pipeline for Import Canadian natural gas to R3 | E46: =Commodities!C31 -> NGAC3 | F46: =Commodities!$C$9 -> NGA | G46: 2010 | H46: 55 | I46: 1 | K46: =(NGExpansion!M75+NGExpansion!M76)/2 -> 8.5091105
B47: =Technologies!$B$126 -> *R4 | C47: =Technologies!$C$126 -> XNGAC4N | D47: =Technologies!$D$126 -> New Pipeline for Import Canadian natural gas to R4 | E47: =Commodities!C32 -> NGAC4 | F47: =Commodities!$C$9 -> NGA | G47: 2010 | H47: 55 | I47: 1 | K47: =NGExpansion!M77 -> 7.9762289
B48: =Technologies!$B$127 -> *R5 | C48: =Technologies!$C$127 -> XNGAC5N | D48: =Technologies!$D$127 -> New Pipeline for Import Canadian natural gas to R5 | E48: =Commodities!C33 -> NGAC5 | F48: =Commodities!$C$9 -> NGA | G48: 2010 | H48: 55 | I48: 1 | K48: =(NGExpansion!M78+NGExpansion!M79)/2 -> 8.512558
B49: =Technologies!$B$128 -> *R6 | C49: =Technologies!$C$128 -> XNGAC6N | D49: =Technologies!$D$128 -> New Pipeline for Import Canadian natural gas to R6 | E49: =Commodities!C34 -> NGAC6 | F49: =Commodities!$C$9 -> NGA | G49: 2010 | H49: 55 | I49: 1
B50: *LNG Terminals
B51: =Technologies!$B$129 -> R1 | C51: =Technologies!$C$129 -> XNGALE1N | D51: =Technologies!$D$129 -> New Infrastructure for Import LNG to Existing terminal in R1 | E51: =Commodities!C35 -> NGALE1 | F51: =Commodities!$C$9 -> NGA | G51: 2010 | H51: 55 | I51: 1 | J51: 0 | K51: =NGExpansion!M41 -> 4.4957141
B52: =Technologies!$B$130 -> R4 | C52: =Technologies!$C$130 -> XNGALE4N | D52: =Technologies!$D$130 -> New Infrastructure for Import LNG to Existing terminal in R4 - Manhattan | E52: =Commodities!C36 -> NGALE4 | F52: =Commodities!$C$9 -> NGA | G52: 2010 | H52: 55 | I52: 1 | J52: 0 | K52: =K51 -> 4.4957141
B53: =Technologies!$B$131 -> R5 | C53: =Technologies!$C$131 -> XNGALE5N | D53: =Technologies!$D$131 -> New Infrastructure for Import LNG to Existing terminal in R5 - Staten Island | E53: =Commodities!C37 -> NGALE5 | F53: =Commodities!$C$9 -> NGA | G53: 2010 | H53: 55 | I53: 1 | J53: 0 | K53: =K51 -> 4.4957141
F57: ~FI_T
B58: Region | C58: TechName | D58: TechDesc | E58: CommIN | F58: CommOUT | G58: EFF | H58: ACT_BND~UP | I58: ACT_COST~2010 | J58: ACT_COST~2015 | K58: ACT_COST~2020 | L58: ACT_COST~2025 | M58: ACT_COST~2030 | N58: ACT_COST~2035 | O58: ACT_COST~2040 | P58: ACT_COST~2045 | Q58: ACT_COST~2050 | R58: ACT_COST~2055 | S58: NCAP_COST | W58: ENV_ACT~VOC | X58: ENV_ACT~CO | Y58: ENV_ACT~NOX | Z58: ENV_ACT~PM10 | AA58: ENV_ACT~PM25 | AB58: ENV_ACT~SO2 | AC58: ENV_ACT~CH4 | AD58: ENV_ACT~N2O | AE58: ENV_ACT~CO2
B59: *Domestic natural gas delivery to end-uses
B60: *R1 | C60: =Technologies!C61 -> XNGARES | D60: =Technologies!D61 -> Domestic natural gas to residential end-use | E60: =Commodities!$C$9 -> NGA | F60: =Commodities!C45 -> RESNGA | G60: 1 | I60: 31.27138 | J60: 27.875356 | K60: 28.662273 | L60: 32.15056 | M60: 36.330812 | N60: 35.987667 | O60: 39.714141 | P60: 39.714141 | Q60: 39.714141 | R60: 39.714141 | W60: =Emissions!A$46 -> 0.0004270238 | X60: =Emissions!B$46 -> 0.00098095011 | Y60: =Emissions!C$46 -> 0.0026126522 | Z60: =Emissions!D$46 -> 0.00013711738 | AA60: =Emissions!E$46 -> 7.538438e-05 | AB60: =Emissions!F$46 -> 0.00019290627 | AC60: =Emissions!G$46 -> 0.0795441 | AD60: =Emissions!H$46 -> 1.0079863e-05 | AE60: =Emissions!I$46/1000 -> 0.00034352762
B61: *R1 | C61: =Technologies!C62 -> XNGACOM | D61: =Technologies!D62 -> Domestic natural gas to commercial end-use | E61: =Commodities!$C$9 -> NGA | F61: =Commodities!C46 -> COMNGA | G61: 1 | I61: 6.9577496 | J61: 5.8354751 | K61: 6.3184519 | L61: 7.3716926 | M61: 8.6721959 | N61: 8.5043044 | O61: 9.5894072 | P61: 9.5894072 | Q61: 9.5894072 | R61: 9.5894072 | W61: =W$60 -> 0.0004270238 | X61: =X$60 -> 0.00098095011 | Y61: =Y$60 -> 0.0026126522 | Z61: =Z$60 -> 0.00013711738 | AA61: =AA$60 -> 7.538438e-05 | AB61: =AB$60 -> 0.00019290627 | AC61: =AC$60 -> 0.0795441 | AD61: =AD$60 -> 1.0079863e-05 | AE61: =AE$60 -> 0.00034352762
B62: *R1 | C62: =Technologies!C63 -> XNGAIND | D62: =Technologies!D63 -> Domestic natural gas to industrial end-use | E62: =Commodities!$C$9 -> NGA | F62: =Commodities!C47 -> INDNGA | G62: 1 | I62: =DelivNGA!$B116*DelivNGA!C126*2 -> 6.3709196 | J62: =DelivNGA!$B116*DelivNGA!D126*2 -> 5.3432999 | K62: =DelivNGA!$B116*DelivNGA!E126*2 -> 5.7855415 | L62: =DelivNGA!$B116*DelivNGA!F126*2 -> 6.7499499 | M62: =DelivNGA!$B116*DelivNGA!G126*2 -> 7.9407663 | N62: =DelivNGA!$B116*DelivNGA!H126*2 -> 7.7870351 | O62: =DelivNGA!$B116*DelivNGA!I126*2 -> 8.7806182 | P62: =DelivNGA!$B116*DelivNGA!J126*2 -> 8.7806182 | ... R62: =DelivNGA!$B116*DelivNGA!L126*2 -> 8.7806182 | W62: =W$60 -> 0.0004270238 | X62: =X$60 -> 0.00098095011 | Y62: =Y$60 -> 0.0026126522 | Z62: =Z$60 -> 0.00013711738 | AA62: =AA$60 -> 7.538438e-05 | AB62: =AB$60 -> 0.00019290627 | AC62: =AC$60 -> 0.0795441 | AD62: =AD$60 -> 1.0079863e-05 | AE62: =AE$60 -> 0.00034352762
B63: R1 | C63: =Technologies!C64 -> XNGAELC | D63: =Technologies!D64 -> Domestic natural gas to electricity generation | E63: =Commodities!$C$9 -> NGA | F63: =Commodities!C48 -> ELCNGA | G63: 1 | I63: =DelivNGA!$B117*DelivNGA!C127*2 -> 1.9501678 | J63: =DelivNGA!$B117*DelivNGA!D127*2 -> 1.5466661 | K63: =DelivNGA!$B117*DelivNGA!E127*2 -> 1.7024673 | L63: =DelivNGA!$B117*DelivNGA!F127*2 -> 2.1424886 | M63: =DelivNGA!$B117*DelivNGA!G127*2 -> 2.6474742 | N63: =DelivNGA!$B117*DelivNGA!H127*2 -> 2.5606575 | O63: =DelivNGA!$B117*DelivNGA!I127*2 -> 2.9437926 | P63: =DelivNGA!$B117*DelivNGA!J127*2 -> 2.9437926 | ... R63: =DelivNGA!$B117*DelivNGA!L127*2 -> 2.9437926 | W63: =W$60 -> 0.0004270238 | X63: =X$60 -> 0.00098095011 | Y63: =Y$60 -> 0.0026126522 | Z63: =Z$60 -> 0.00013711738 | AA63: =AA$60 -> 7.538438e-05 | AB63: =AB$60 -> 0.00019290627 | AC63: =AC$60 -> 0.0795441 | AD63: =AD$60 -> 1.0079863e-05 | AE63: =AE$60 -> 0.00034352762
B64: *R1 | C64: =Technologies!C65 -> XNGATRN | D64: =Technologies!D65 -> Domestic natural gas to transportation end-use | E64: =Commodities!$C$9 -> NGA | F64: =Commodities!C49 -> TRNNGA | G64: 1 | I64: 6.9577496 | J64: 6.215317 | K64: 6.4216899 | L64: 7.1569657 | M64: 8.0581373 | N64: 8.1972515 | O64: 9.043171 | P64: 9.043171 | Q64: 9.043171 | R64: 9.043171 | W64: =W$60 -> 0.0004270238 | X64: =X$60 -> 0.00098095011 | Y64: =Y$60 -> 0.0026126522 | Z64: =Z$60 -> 0.00013711738 | AA64: =AA$60 -> 7.538438e-05 | AB64: =AB$60 -> 0.00019290627 | AC64: =AC$60 -> 0.0795441 | AD64: =AD$60 -> 1.0079863e-05 | AE64: =AE$60 -> 0.00034352762
B65: R2 | C65: =C60 -> XNGARES | D65: =D60 -> Domestic natural gas to residential end-use | E65: =Commodities!$C$9 -> NGA | F65: =Commodities!C45 -> RESNGA | G65: 1 | I65: =I60 -> 31.27138 | J65: =J60 -> 27.875356 | K65: =K60 -> 28.662273 | L65: =L60 -> 32.15056 | M65: =M60 -> 36.330812 | N65: =N60 -> 35.987667 | O65: =O60 -> 39.714141 | P65: =P60 -> 39.714141 | ... R65: =R60 -> 39.714141 | W65: =W$60 -> 0.0004270238 | X65: =X$60 -> 0.00098095011 | Y65: =Y$60 -> 0.0026126522 | Z65: =Z$60 -> 0.00013711738 | AA65: =AA$60 -> 7.538438e-05 | AB65: =AB$60 -> 0.00019290627 | AC65: =AC$60 -> 0.0795441 | AD65: =AD$60 -> 1.0079863e-05 | AE65: =AE$60 -> 0.00034352762
B66: R2 | C66: =C61 -> XNGACOM | D66: =D61 -> Domestic natural gas to commercial end-use | E66: =Commodities!$C$9 -> NGA | F66: =Commodities!C46 -> COMNGA | G66: 1 | I66: =I61 -> 6.9577496 | J66: =J61 -> 5.8354751 | K66: =K61 -> 6.3184519 | L66: =L61 -> 7.3716926 | M66: =M61 -> 8.6721959 | N66: =N61 -> 8.5043044 | O66: =O61 -> 9.5894072 | P66: =P61 -> 9.5894072 | ... R66: =R61 -> 9.5894072 | W66: =W$60 -> 0.0004270238 | X66: =X$60 -> 0.00098095011 | Y66: =Y$60 -> 0.0026126522 | Z66: =Z$60 -> 0.00013711738 | AA66: =AA$60 -> 7.538438e-05 | AB66: =AB$60 -> 0.00019290627 | AC66: =AC$60 -> 0.0795441 | AD66: =AD$60 -> 1.0079863e-05 | AE66: =AE$60 -> 0.00034352762
B67: R2 | C67: =C62 -> XNGAIND | D67: =D62 -> Domestic natural gas to industrial end-use | E67: =Commodities!$C$9 -> NGA | F67: =Commodities!C47 -> INDNGA | G67: 1 | I67: =I62 -> 6.3709196 | J67: =J62 -> 5.3432999 | K67: =K62 -> 5.7855415 | L67: =L62 -> 6.7499499 | M67: =M62 -> 7.9407663 | N67: =N62 -> 7.7870351 | O67: =O62 -> 8.7806182 | P67: =P62 -> 8.7806182 | ... R67: =R62 -> 8.7806182 | W67: =W$60 -> 0.0004270238 | X67: =X$60 -> 0.00098095011 | Y67: =Y$60 -> 0.0026126522 | Z67: =Z$60 -> 0.00013711738 | AA67: =AA$60 -> 7.538438e-05 | AB67: =AB$60 -> 0.00019290627 | AC67: =AC$60 -> 0.0795441 | AD67: =AD$60 -> 1.0079863e-05 | AE67: =AE$60 -> 0.00034352762
B68: R2 | C68: =C63 -> XNGAELC | D68: =D63 -> Domestic natural gas to electricity generation | E68: =Commodities!$C$9 -> NGA | F68: =Commodities!C48 -> ELCNGA | G68: 1 | I68: =I63 -> 1.9501678 | J68: =J63 -> 1.5466661 | K68: =K63 -> 1.7024673 | L68: =L63 -> 2.1424886 | M68: =M63 -> 2.6474742 | N68: =N63 -> 2.5606575 | O68: =O63 -> 2.9437926 | P68: =P63 -> 2.9437926 | ... R68: =R63 -> 2.9437926 | W68: =W$60 -> 0.0004270238 | X68: =X$60 -> 0.00098095011 | Y68: =Y$60 -> 0.0026126522 | Z68: =Z$60 -> 0.00013711738 | AA68: =AA$60 -> 7.538438e-05 | AB68: =AB$60 -> 0.00019290627 | AC68: =AC$60 -> 0.0795441 | AD68: =AD$60 -> 1.0079863e-05 | AE68: =AE$60 -> 0.00034352762
B69: R2 | C69: =C64 -> XNGATRN | D69: =D64 -> Domestic natural gas to transportation end-use | E69: =Commodities!$C$9 -> NGA | F69: =Commodities!C49 -> TRNNGA | G69: 1 | I69: =I64 -> 6.9577496 | J69: =J64 -> 6.215317 | K69: =K64 -> 6.4216899 | L69: =L64 -> 7.1569657 | M69: =M64 -> 8.0581373 | N69: =N64 -> 8.1972515 | O69: =O64 -> 9.043171 | P69: =P64 -> 9.043171 | ... R69: =R64 -> 9.043171 | W69: =W$60 -> 0.0004270238 | X69: =X$60 -> 0.00098095011 | Y69: =Y$60 -> 0.0026126522 | Z69: =Z$60 -> 0.00013711738 | AA69: =AA$60 -> 7.538438e-05 | AB69: =AB$60 -> 0.00019290627 | AC69: =AC$60 -> 0.0795441 | AD69: =AD$60 -> 1.0079863e-05 | AE69: =AE$60 -> 0.00034352762
B70: R3 | C70: =C65 -> XNGARES | D70: =D65 -> Domestic natural gas to residential end-use | E70: =Commodities!$C$9 -> NGA | F70: =Commodities!C45 -> RESNGA | G70: 1 | I70: =I65 -> 31.27138 | J70: =J65 -> 27.875356 | K70: =K65 -> 28.662273 | L70: =L65 -> 32.15056 | M70: =M65 -> 36.330812 | N70: =N65 -> 35.987667 | O70: =O65 -> 39.714141 | P70: =P65 -> 39.714141 | ... R70: =R65 -> 39.714141 | W70: =W$60 -> 0.0004270238 | X70: =X$60 -> 0.00098095011 | Y70: =Y$60 -> 0.0026126522 | Z70: =Z$60 -> 0.00013711738 | AA70: =AA$60 -> 7.538438e-05 | AB70: =AB$60 -> 0.00019290627 | AC70: =AC$60 -> 0.0795441 | AD70: =AD$60 -> 1.0079863e-05 | AE70: =AE$60 -> 0.00034352762
B71: R3 | C71: =C66 -> XNGACOM | D71: =D66 -> Domestic natural gas to commercial end-use | E71: =Commodities!$C$9 -> NGA | F71: =Commodities!C46 -> COMNGA | G71: 1 | I71: =I66 -> 6.9577496 | J71: =J66 -> 5.8354751 | K71: =K66 -> 6.3184519 | L71: =L66 -> 7.3716926 | M71: =M66 -> 8.6721959 | N71: =N66 -> 8.5043044 | O71: =O66 -> 9.5894072 | P71: =P66 -> 9.5894072 | ... R71: =R66 -> 9.5894072 | W71: =W$60 -> 0.0004270238 | X71: =X$60 -> 0.00098095011 | Y71: =Y$60 -> 0.0026126522 | Z71: =Z$60 -> 0.00013711738 | AA71: =AA$60 -> 7.538438e-05 | AB71: =AB$60 -> 0.00019290627 | AC71: =AC$60 -> 0.0795441 | AD71: =AD$60 -> 1.0079863e-05 | AE71: =AE$60 -> 0.00034352762
B72: R3 | C72: =C67 -> XNGAIND | D72: =D67 -> Domestic natural gas to industrial end-use | E72: =Commodities!$C$9 -> NGA | F72: =Commodities!C47 -> INDNGA | G72: 1 | I72: =I67 -> 6.3709196 | J72: =J67 -> 5.3432999 | K72: =K67 -> 5.7855415 | L72: =L67 -> 6.7499499 | M72: =M67 -> 7.9407663 | N72: =N67 -> 7.7870351 | O72: =O67 -> 8.7806182 | P72: =P67 -> 8.7806182 | ... R72: =R67 -> 8.7806182 | W72: =W$60 -> 0.0004270238 | X72: =X$60 -> 0.00098095011 | Y72: =Y$60 -> 0.0026126522 | Z72: =Z$60 -> 0.00013711738 | AA72: =AA$60 -> 7.538438e-05 | AB72: =AB$60 -> 0.00019290627 | AC72: =AC$60 -> 0.0795441 | AD72: =AD$60 -> 1.0079863e-05 | AE72: =AE$60 -> 0.00034352762
B73: R3 | C73: =C68 -> XNGAELC | D73: =D68 -> Domestic natural gas to electricity generation | E73: =Commodities!$C$9 -> NGA | F73: =Commodities!C48 -> ELCNGA | G73: 1 | I73: =I68 -> 1.9501678 | J73: =J68 -> 1.5466661 | K73: =K68 -> 1.7024673 | L73: =L68 -> 2.1424886 | M73: =M68 -> 2.6474742 | N73: =N68 -> 2.5606575 | O73: =O68 -> 2.9437926 | P73: =P68 -> 2.9437926 | ... R73: =R68 -> 2.9437926 | W73: =W$60 -> 0.0004270238 | X73: =X$60 -> 0.00098095011 | Y73: =Y$60 -> 0.0026126522 | Z73: =Z$60 -> 0.00013711738 | AA73: =AA$60 -> 7.538438e-05 | AB73: =AB$60 -> 0.00019290627 | AC73: =AC$60 -> 0.0795441 | AD73: =AD$60 -> 1.0079863e-05 | AE73: =AE$60 -> 0.00034352762
B74: R3 | C74: =C69 -> XNGATRN | D74: =D69 -> Domestic natural gas to transportation end-use | E74: =Commodities!$C$9 -> NGA | F74: =Commodities!C49 -> TRNNGA | G74: 1 | I74: =I69 -> 6.9577496 | J74: =J69 -> 6.215317 | K74: =K69 -> 6.4216899 | L74: =L69 -> 7.1569657 | M74: =M69 -> 8.0581373 | N74: =N69 -> 8.1972515 | O74: =O69 -> 9.043171 | P74: =P69 -> 9.043171 | ... R74: =R69 -> 9.043171 | W74: =W$60 -> 0.0004270238 | X74: =X$60 -> 0.00098095011 | Y74: =Y$60 -> 0.0026126522 | Z74: =Z$60 -> 0.00013711738 | AA74: =AA$60 -> 7.538438e-05 | AB74: =AB$60 -> 0.00019290627 | AC74: =AC$60 -> 0.0795441 | AD74: =AD$60 -> 1.0079863e-05 | AE74: =AE$60 -> 0.00034352762
B75: R4 | C75: =C70 -> XNGARES | D75: =D70 -> Domestic natural gas to residential end-use | E75: =Commodities!$C$9 -> NGA | F75: =Commodities!C45 -> RESNGA | G75: 1 | I75: =I70 -> 31.27138 | J75: =J70 -> 27.875356 | K75: =K70 -> 28.662273 | L75: =L70 -> 32.15056 | M75: =M70 -> 36.330812 | N75: =N70 -> 35.987667 | O75: =O70 -> 39.714141 | P75: =P70 -> 39.714141 | ... R75: =R70 -> 39.714141 | W75: =W$60 -> 0.0004270238 | X75: =X$60 -> 0.00098095011 | Y75: =Y$60 -> 0.0026126522 | Z75: =Z$60 -> 0.00013711738 | AA75: =AA$60 -> 7.538438e-05 | AB75: =AB$60 -> 0.00019290627 | AC75: =AC$60 -> 0.0795441 | AD75: =AD$60 -> 1.0079863e-05 | AE75: =AE$60 -> 0.00034352762
B76: R4 | C76: =C71 -> XNGACOM | D76: =D71 -> Domestic natural gas to commercial end-use | E76: =Commodities!$C$9 -> NGA | F76: =Commodities!C46 -> COMNGA | G76: 1 | I76: =I71 -> 6.9577496 | J76: =J71 -> 5.8354751 | K76: =K71 -> 6.3184519 | L76: =L71 -> 7.3716926 | M76: =M71 -> 8.6721959 | N76: =N71 -> 8.5043044 | O76: =O71 -> 9.5894072 | P76: =P71 -> 9.5894072 | ... R76: =R71 -> 9.5894072 | W76: =W$60 -> 0.0004270238 | X76: =X$60 -> 0.00098095011 | Y76: =Y$60 -> 0.0026126522 | Z76: =Z$60 -> 0.00013711738 | AA76: =AA$60 -> 7.538438e-05 | AB76: =AB$60 -> 0.00019290627 | AC76: =AC$60 -> 0.0795441 | AD76: =AD$60 -> 1.0079863e-05 | AE76: =AE$60 -> 0.00034352762
B77: R4 | C77: =C72 -> XNGAIND | D77: =D72 -> Domestic natural gas to industrial end-use | E77: =Commodities!$C$9 -> NGA | F77: =Commodities!C47 -> INDNGA | G77: 1 | I77: =I72 -> 6.3709196 | J77: =J72 -> 5.3432999 | K77: =K72 -> 5.7855415 | L77: =L72 -> 6.7499499 | M77: =M72 -> 7.9407663 | N77: =N72 -> 7.7870351 | O77: =O72 -> 8.7806182 | P77: =P72 -> 8.7806182 | ... R77: =R72 -> 8.7806182 | W77: =W$60 -> 0.0004270238 | X77: =X$60 -> 0.00098095011 | Y77: =Y$60 -> 0.0026126522 | Z77: =Z$60 -> 0.00013711738 | AA77: =AA$60 -> 7.538438e-05 | AB77: =AB$60 -> 0.00019290627 | AC77: =AC$60 -> 0.0795441 | AD77: =AD$60 -> 1.0079863e-05 | AE77: =AE$60 -> 0.00034352762
B78: R4 | C78: =C73 -> XNGAELC | D78: =D73 -> Domestic natural gas to electricity generation | E78: =Commodities!$C$9 -> NGA | F78: =Commodities!C48 -> ELCNGA | G78: 1 | I78: =I73 -> 1.9501678 | J78: =J73 -> 1.5466661 | K78: =K73 -> 1.7024673 | L78: =L73 -> 2.1424886 | M78: =M73 -> 2.6474742 | N78: =N73 -> 2.5606575 | O78: =O73 -> 2.9437926 | P78: =P73 -> 2.9437926 | ... R78: =R73 -> 2.9437926 | W78: =W$60 -> 0.0004270238 | X78: =X$60 -> 0.00098095011 | Y78: =Y$60 -> 0.0026126522 | Z78: =Z$60 -> 0.00013711738 | AA78: =AA$60 -> 7.538438e-05 | AB78: =AB$60 -> 0.00019290627 | AC78: =AC$60 -> 0.0795441 | AD78: =AD$60 -> 1.0079863e-05 | AE78: =AE$60 -> 0.00034352762
B79: R4 | C79: =C74 -> XNGATRN | D79: =D74 -> Domestic natural gas to transportation end-use | E79: =Commodities!$C$9 -> NGA | F79: =Commodities!C49 -> TRNNGA | G79: 1 | I79: =I74 -> 6.9577496 | J79: =J74 -> 6.215317 | K79: =K74 -> 6.4216899 | L79: =L74 -> 7.1569657 | M79: =M74 -> 8.0581373 | N79: =N74 -> 8.1972515 | O79: =O74 -> 9.043171 | P79: =P74 -> 9.043171 | ... R79: =R74 -> 9.043171 | W79: =W$60 -> 0.0004270238 | X79: =X$60 -> 0.00098095011 | Y79: =Y$60 -> 0.0026126522 | Z79: =Z$60 -> 0.00013711738 | AA79: =AA$60 -> 7.538438e-05 | AB79: =AB$60 -> 0.00019290627 | AC79: =AC$60 -> 0.0795441 | AD79: =AD$60 -> 1.0079863e-05 | AE79: =AE$60 -> 0.00034352762
B80: R5 | C80: =C75 -> XNGARES | D80: =D75 -> Domestic natural gas to residential end-use | E80: =Commodities!$C$9 -> NGA | F80: =Commodities!C45 -> RESNGA | G80: 1 | I80: =I75 -> 31.27138 | J80: =J75 -> 27.875356 | K80: =K75 -> 28.662273 | L80: =L75 -> 32.15056 | M80: =M75 -> 36.330812 | N80: =N75 -> 35.987667 | O80: =O75 -> 39.714141 | P80: =P75 -> 39.714141 | ... R80: =R75 -> 39.714141 | W80: =W$60 -> 0.0004270238 | X80: =X$60 -> 0.00098095011 | Y80: =Y$60 -> 0.0026126522 | Z80: =Z$60 -> 0.00013711738 | AA80: =AA$60 -> 7.538438e-05 | AB80: =AB$60 -> 0.00019290627 | AC80: =AC$60 -> 0.0795441 | AD80: =AD$60 -> 1.0079863e-05 | AE80: =AE$60 -> 0.00034352762
B81: R5 | C81: =C76 -> XNGACOM | D81: =D76 -> Domestic natural gas to commercial end-use | E81: =Commodities!$C$9 -> NGA | F81: =Commodities!C46 -> COMNGA | G81: 1 | I81: =I76 -> 6.9577496 | J81: =J76 -> 5.8354751 | K81: =K76 -> 6.3184519 | L81: =L76 -> 7.3716926 | M81: =M76 -> 8.6721959 | N81: =N76 -> 8.5043044 | O81: =O76 -> 9.5894072 | P81: =P76 -> 9.5894072 | ... R81: =R76 -> 9.5894072 | W81: =W$60 -> 0.0004270238 | X81: =X$60 -> 0.00098095011 | Y81: =Y$60 -> 0.0026126522 | Z81: =Z$60 -> 0.00013711738 | AA81: =AA$60 -> 7.538438e-05 | AB81: =AB$60 -> 0.00019290627 | AC81: =AC$60 -> 0.0795441 | AD81: =AD$60 -> 1.0079863e-05 | AE81: =AE$60 -> 0.00034352762
B82: R5 | C82: =C77 -> XNGAIND | D82: =D77 -> Domestic natural gas to industrial end-use | E82: =Commodities!$C$9 -> NGA | F82: =Commodities!C47 -> INDNGA | G82: 1 | I82: =I77 -> 6.3709196 | J82: =J77 -> 5.3432999 | K82: =K77 -> 5.7855415 | L82: =L77 -> 6.7499499 | M82: =M77 -> 7.9407663 | N82: =N77 -> 7.7870351 | O82: =O77 -> 8.7806182 | P82: =P77 -> 8.7806182 | ... R82: =R77 -> 8.7806182 | W82: =W$60 -> 0.0004270238 | X82: =X$60 -> 0.00098095011 | Y82: =Y$60 -> 0.0026126522 | Z82: =Z$60 -> 0.00013711738 | AA82: =AA$60 -> 7.538438e-05 | AB82: =AB$60 -> 0.00019290627 | AC82: =AC$60 -> 0.0795441 | AD82: =AD$60 -> 1.0079863e-05 | AE82: =AE$60 -> 0.00034352762
B83: R5 | C83: =C78 -> XNGAELC | D83: =D78 -> Domestic natural gas to electricity generation | E83: =Commodities!$C$9 -> NGA | F83: =Commodities!C48 -> ELCNGA | G83: 1 | I83: =I78 -> 1.9501678 | J83: =J78 -> 1.5466661 | K83: =K78 -> 1.7024673 | L83: =L78 -> 2.1424886 | M83: =M78 -> 2.6474742 | N83: =N78 -> 2.5606575 | O83: =O78 -> 2.9437926 | P83: =P78 -> 2.9437926 | ... R83: =R78 -> 2.9437926 | W83: =W$60 -> 0.0004270238 | X83: =X$60 -> 0.00098095011 | Y83: =Y$60 -> 0.0026126522 | Z83: =Z$60 -> 0.00013711738 | AA83: =AA$60 -> 7.538438e-05 | AB83: =AB$60 -> 0.00019290627 | AC83: =AC$60 -> 0.0795441 | AD83: =AD$60 -> 1.0079863e-05 | AE83: =AE$60 -> 0.00034352762
B84: R5 | C84: =C79 -> XNGATRN | D84: =D79 -> Domestic natural gas to transportation end-use | E84: =Commodities!$C$9 -> NGA | F84: =Commodities!C49 -> TRNNGA | G84: 1 | I84: =I79 -> 6.9577496 | J84: =J79 -> 6.215317 | K84: =K79 -> 6.4216899 | L84: =L79 -> 7.1569657 | M84: =M79 -> 8.0581373 | N84: =N79 -> 8.1972515 | O84: =O79 -> 9.043171 | P84: =P79 -> 9.043171 | ... R84: =R79 -> 9.043171 | W84: =W$60 -> 0.0004270238 | X84: =X$60 -> 0.00098095011 | Y84: =Y$60 -> 0.0026126522 | Z84: =Z$60 -> 0.00013711738 | AA84: =AA$60 -> 7.538438e-05 | AB84: =AB$60 -> 0.00019290627 | AC84: =AC$60 -> 0.0795441 | AD84: =AD$60 -> 1.0079863e-05 | AE84: =AE$60 -> 0.00034352762
B85: R6 | C85: =C80 -> XNGARES | D85: =D80 -> Domestic natural gas to residential end-use | E85: =Commodities!$C$9 -> NGA | F85: =Commodities!C45 -> RESNGA | G85: 1 | I85: =I80 -> 31.27138 | J85: =J80 -> 27.875356 | K85: =K80 -> 28.662273 | L85: =L80 -> 32.15056 | M85: =M80 -> 36.330812 | N85: =N80 -> 35.987667 | O85: =O80 -> 39.714141 | P85: =P80 -> 39.714141 | ... R85: =R80 -> 39.714141 | W85: =W$60 -> 0.0004270238 | X85: =X$60 -> 0.00098095011 | Y85: =Y$60 -> 0.0026126522 | Z85: =Z$60 -> 0.00013711738 | AA85: =AA$60 -> 7.538438e-05 | AB85: =AB$60 -> 0.00019290627 | AC85: =AC$60 -> 0.0795441 | AD85: =AD$60 -> 1.0079863e-05 | AE85: =AE$60 -> 0.00034352762
B86: R6 | C86: =C81 -> XNGACOM | D86: =D81 -> Domestic natural gas to commercial end-use | E86: =Commodities!$C$9 -> NGA | F86: =Commodities!C46 -> COMNGA | G86: 1 | I86: =I81 -> 6.9577496 | J86: =J81 -> 5.8354751 | K86: =K81 -> 6.3184519 | L86: =L81 -> 7.3716926 | M86: =M81 -> 8.6721959 | N86: =N81 -> 8.5043044 | O86: =O81 -> 9.5894072 | P86: =P81 -> 9.5894072 | ... R86: =R81 -> 9.5894072 | W86: =W$60 -> 0.0004270238 | X86: =X$60 -> 0.00098095011 | Y86: =Y$60 -> 0.0026126522 | Z86: =Z$60 -> 0.00013711738 | AA86: =AA$60 -> 7.538438e-05 | AB86: =AB$60 -> 0.00019290627 | AC86: =AC$60 -> 0.0795441 | AD86: =AD$60 -> 1.0079863e-05 | AE86: =AE$60 -> 0.00034352762
B87: R6 | C87: =C82 -> XNGAIND | D87: =D82 -> Domestic natural gas to industrial end-use | E87: =Commodities!$C$9 -> NGA | F87: =Commodities!C47 -> INDNGA | G87: 1 | I87: =I82 -> 6.3709196 | J87: =J82 -> 5.3432999 | K87: =K82 -> 5.7855415 | L87: =L82 -> 6.7499499 | M87: =M82 -> 7.9407663 | N87: =N82 -> 7.7870351 | O87: =O82 -> 8.7806182 | P87: =P82 -> 8.7806182 | ... R87: =R82 -> 8.7806182 | W87: =W$60 -> 0.0004270238 | X87: =X$60 -> 0.00098095011 | Y87: =Y$60 -> 0.0026126522 | Z87: =Z$60 -> 0.00013711738 | AA87: =AA$60 -> 7.538438e-05 | AB87: =AB$60 -> 0.00019290627 | AC87: =AC$60 -> 0.0795441 | AD87: =AD$60 -> 1.0079863e-05 | AE87: =AE$60 -> 0.00034352762
B88: R6 | C88: =C83 -> XNGAELC | D88: =D83 -> Domestic natural gas to electricity generation | E88: =Commodities!$C$9 -> NGA | F88: =Commodities!C48 -> ELCNGA | G88: 1 | I88: =I83 -> 1.9501678 | J88: =J83 -> 1.5466661 | K88: =K83 -> 1.7024673 | L88: =L83 -> 2.1424886 | M88: =M83 -> 2.6474742 | N88: =N83 -> 2.5606575 | O88: =O83 -> 2.9437926 | P88: =P83 -> 2.9437926 | ... R88: =R83 -> 2.9437926 | W88: =W$60 -> 0.0004270238 | X88: =X$60 -> 0.00098095011 | Y88: =Y$60 -> 0.0026126522 | Z88: =Z$60 -> 0.00013711738 | AA88: =AA$60 -> 7.538438e-05 | AB88: =AB$60 -> 0.00019290627 | AC88: =AC$60 -> 0.0795441 | AD88: =AD$60 -> 1.0079863e-05 | AE88: =AE$60 -> 0.00034352762
B89: R6 | C89: =C84 -> XNGATRN | D89: =D84 -> Domestic natural gas to transportation end-use | E89: =Commodities!$C$9 -> NGA | F89: =Commodities!C49 -> TRNNGA | G89: 1 | I89: =I84 -> 6.9577496 | J89: =J84 -> 6.215317 | K89: =K84 -> 6.4216899 | L89: =L84 -> 7.1569657 | M89: =M84 -> 8.0581373 | N89: =N84 -> 8.1972515 | O89: =O84 -> 9.043171 | P89: =P84 -> 9.043171 | ... R89: =R84 -> 9.043171 | W89: =W$60 -> 0.0004270238 | X89: =X$60 -> 0.00098095011 | Y89: =Y$60 -> 0.0026126522 | Z89: =Z$60 -> 0.00013711738 | AA89: =AA$60 -> 7.538438e-05 | AB89: =AB$60 -> 0.00019290627 | AC89: =AC$60 -> 0.0795441 | AD89: =AD$60 -> 1.0079863e-05 | AE89: =AE$60 -> 0.00034352762
F94: ~FI_T
B95: Region | C95: TechName | D95: TechDesc | E95: CommIN | F95: CommOUT | G95: NCAP_TLIFE | H95: EFF | I95: Share~UP~2010 | J95: Share~UP~2055 | K95: ACT_BND~UP | L95: ACT_COST~2010 | M95: ACT_COST~2015 | N95: ACT_COST~2020 | O95: ACT_COST~2025 | P95: ACT_COST~2030 | Q95: ACT_COST~2035 | R95: ACT_COST~2040 | S95: ACT_COST~2045 | T95: ACT_COST~2050 | U95: ACT_COST~2055 | V95: NCAP_COST | Z95: ENV_ACT~VOC | AA95: ENV_ACT~CO | AB95: ENV_ACT~NOX | AC95: ENV_ACT~PM10 | AD95: ENV_ACT~PM25 | AE95: ENV_ACT~SO2 | AF95: ENV_ACT~CH4 | AG95: ENV_ACT~N2O | AH95: ENV_ACT~CO2
B96: * Natural Gas Liquids products
B97: * | C97: =Technologies!C$66 -> XNGLFRAC | D97: =Technologies!D$66 -> Domestic natural gas liquids to end-products | E97: NGL | H97: 1 | L97: =AVERAGE(I62,I67,I72,I77,I82,I87) -> 6.3709196 | M97: =AVERAGE(J62,J67,J72,J77,J82,J87) -> 5.3432999 | N97: =AVERAGE(K62,K67,K72,K77,K82,K87) -> 5.7855415 | O97: =AVERAGE(L62,L67,L72,L77,L82,L87) -> 6.7499499 | P97: =AVERAGE(M62,M67,M72,M77,M82,M87) -> 7.9407663 | Q97: =AVERAGE(N62,N67,N72,N77,N82,N87) -> 7.7870351 | R97: =AVERAGE(O62,O67,O72,O77,O82,O87) -> 8.7806182 | S97: =AVERAGE(P62,P67,P72,P77,P82,P87) -> 8.7806182 | ... U97: =AVERAGE(R62,R67,R72,R77,R82,R87) -> 8.7806182 | Z97: =W89 -> 0.0004270238 | AA97: =X89 -> 0.00098095011 | AB97: =Y89 -> 0.0026126522 | AC97: =Z89 -> 0.00013711738 | AD97: =AA89 -> 7.538438e-05 | AE97: =AB89 -> 0.00019290627 | AF97: =AC89 -> 0.0795441 | AG97: =AD89 -> 1.0079863e-05 | AH97: =AE89 -> 0.00034352762
B98: =B97 -> * | F98: =Commodities!C56 -> LPG_NGL | I98: 0.37 | J98: =+I98 -> 0.37
B99: =B98 -> * | F99: =Commodities!C55 -> PFS_NGL | I99: 0.42 | J99: =+I99 -> 0.42
B100: =B99 -> * | F100: =Commodities!C57 -> NGLPENT | I100: 0.21 | J100: =+I100 -> 0.21
B101: * | C101: =Technologies!C$69 -> SCDENPENT | D101: =Technologies!D$69 -> Collector: Ethanol denaturant from NGL Pentanes | E101: =Commodities!C52 -> PENTS | F101: =Commodities!C54 -> DENAT | G101: 55 | H101: 1
B102: * | C102: =Technologies!C$68 -> SCGSRPENT | D102: =Technologies!D$68 -> Collector: GSR from NGL Pentanes | E102: =Commodities!C52 -> PENTS | F102: =Commodities!C53 -> GSR | G102: 55 | H102: 1
B103: * | C103: =Technologies!C70 -> SCPFSNGL | D103: =Technologies!D70 -> Collector: PFS from NGL | E103: =Commodities!C55 -> PFS_NGL | F103: =Commodities!C51 -> PFS | G103: 55 | H103: 1
B104: * | C104: =Technologies!C71 -> SCLPGNGL | D104: =Technologies!D71 -> Collector: LPG from NGL | E104: =Commodities!C56 -> LPG_NGL | F104: =Commodities!C50 -> LPG | G104: 55 | H104: 1
B105: * | C105: =Technologies!C72 -> SCPENTNGL | D105: =Technologies!D72 -> Collector: Pentanes from NGL | E105: =Commodities!C57 -> NGLPENT | F105: =Commodities!C52 -> PENTS | G105: 55 | H105: 1
F109: ~FI_T
B110: Region | C110: TechName | D110: TechDesc | E110: CommIN | F110: CommOUT | G110: NCAP_TLIFE | H110: EFF | I110: CAP_BND~UP | J110: NCAP_COST | K110: NCAP_FOM | L110: ACT_COST | M110: AFA
B111: * Existing NGA Pipelines
B112: =Technologies!B75 -> R2 | C112: =Technologies!C75 -> XNGA12E | D112: =Technologies!D75 -> Existing natural gas pipeline from R1 to R2 | E112: =Commodities!C$18 -> NGAR1 | F112: =Commodities!$C$9 -> NGA | G112: 55 | H112: 1 | I112: 9999
B113: =Technologies!B76 -> R3 | C113: =Technologies!C76 -> XNGA13E | D113: =Technologies!D76 -> Existing natural gas pipeline from R1 to R3 | E113: =Commodities!C$18 -> NGAR1 | F113: =Commodities!$C$9 -> NGA | G113: 55 | H113: 1 | I113: 9999
B114: =Technologies!B77 -> R4 | C114: =Technologies!C77 -> XNGA14E | D114: =Technologies!D77 -> Existing natural gas pipeline from R1 to R4 | E114: =Commodities!C$18 -> NGAR1 | F114: =Commodities!$C$9 -> NGA | G114: 55 | H114: 1 | I114: 9999
B115: =Technologies!B78 -> R5 | C115: =Technologies!C78 -> XNGA15E | D115: =Technologies!D78 -> Existing natural gas pipeline from R1 to R5 | E115: =Commodities!C$18 -> NGAR1 | F115: =Commodities!$C$9 -> NGA | G115: 55 | H115: 1 | I115: 9999
B116: =Technologies!B79 -> R6 | C116: =Technologies!C79 -> XNGA16E | D116: =Technologies!D79 -> Existing natural gas pipeline from R1 to R6 | E116: =Commodities!C$18 -> NGAR1 | F116: =Commodities!$C$9 -> NGA | G116: 55 | H116: 1 | I116: 9999
...

Sheet TechData_ExIm
B1: TechData | C1: _GLOBAL,R0,R1,R2,R3,R4,R5,R6
F5: ~FI_T
B6: Region | C6: TechName | D6: TechDesc | E6: CommIN | F6: CommOUT | G6: *TID | H6: EFF | I6: NCAP_COST | J6: NCAP_FOM | K6: ACT_COST | L6: AFA
B7: *Natural gas change names
B8: =Technologies!B16 -> R1 | C8: =Technologies!C16 -> SCNGAR1 | D8: =Technologies!D16 -> Collector: Natural Gas R1 | E8: =Commodities!C$9 -> NGA | F8: =Commodities!C18 -> NGAR1 | G8: 2010 | H8: 1
B9: =Technologies!B17 -> R2 | C9: =Technologies!C17 -> SCNGAR2 | D9: =Technologies!D17 -> Collector: Natural Gas R2 | E9: =Commodities!C$9 -> NGA | F9: =Commodities!C19 -> NGAR2 | G9: 2010 | H9: 1
B10: R3 | C10: SCNGAR3 | D10: Collector: Natural Gas R3 | E10: =Commodities!C$9 -> NGA | F10: =Commodities!C20 -> NGAR3 | G10: 2010 | H10: 1
B11: R4 | C11: SCNGAR4 | D11: Collector: Natural Gas R4 | E11: =Commodities!C$9 -> NGA | F11: =Commodities!C21 -> NGAR4 | G11: 2010 | H11: 1
B12: R5 | C12: SCNGAR5 | D12: Collector: Natural Gas R5 | E12: =Commodities!C$9 -> NGA | F12: =Commodities!C22 -> NGAR5 | G12: 2010 | H12: 1
B13: R6 | C13: SCNGAR6 | D13: Collector: Natural Gas R6 | E13: =Commodities!C$9 -> NGA | F13: =Commodities!C23 -> NGAR6 | G13: 2010 | H13: 1

Sheet Domestic NG CUM
A1: EIA Report: U.S. Crude Oil, Natural Gas, and Natural Gas Liquids Proved Reserves, 2011
A2: http://www.eia.gov/naturalgas/crudeoilreserves/
A3: Table 10: Total natural gas proved reserves, reserves changes, and production, wet after lease separation, 2011
A4: billion cubic feet
C5: Changes in reserves during 2011 | Q5: Region | R5: Reserves by Region | S5: % Total | T5: Reserves PJ
B6: Published | J6: New Reservoir | Q6: R2 | R6: =L33 -> 253 | S6: =R6/$R$14 -> 0.00072532532 | T6: =R6*1000000000*Conv!$D$6*Conv!$J$5*40 -> 10912.064
B7: Proved | D7: Revision | E7: Revision | I7: New Field | J7: Discoveries | K7: Estimated | L7: Proved | Q7: R3 | R7: =L27+L35 -> 3307 | S7: =R7/$R$14 -> 0.0094808334 | T7: =R7*1000000000*Conv!$D$6*Conv!$J$5*20 -> 71316.595
B8: Reserves | C8: Adjustments | D8: Increases | E8: Decreases | F8: Sales | G8: Acquisitions | H8: Extensions | I8: Discoveries | J8: in Old Fields | K8: Production | L8: Reserves | N8: MARKAL REGION | Q8: R4 | R8: =L21+L34 -> 6399 | S8: =R8/$R$14 -> 0.018345284 | T8: =R8*1000000000*Conv!$D$6*Conv!$J$5*20 -> 137996.64
A9: State and subdivision | B9: 40543 | C9: (+,-) | D9: (+) | E9: (-) | F9: (-) | G9: (+) | H9: (+) | I9: (+) | J9: (+) | K9: (-) | L9: 40908 | Q9: R5 | R9: =L20+L53+L54 -> 13370 | S9: =R9/$R$14 -> 0.038330433 | T9: =R9*1000000000*Conv!$D$6*Conv!$J$5*20 -> 288328.66
A10: Alaska | B10: 8917 | C10: -2 | D10: 938 | E10: 207 | F10: 36 | G10: 222 | H10: 4 | I10: 0 | J10: 3 | K10: 328 | L10: 9511 | N10: 9 | Q10: R6 | R10: =L12+L22+L28 -> 5566 | S10: =R10/$R$14 -> 0.015957157 | T10: =R10*1000000000*Conv!$D$6*Conv!$J$5*20 -> 120032.71
A11: Lower 48 States | B11: 308730 | C11: 2717 | D11: 55077 | E11: 55920 | F11: 44539 | G11: 47651 | H11: 47631 | I11: 987 | J11: 1257 | K11: 24293 | L11: 339298 | Q11: R7 | R11: =L13+L23+L36+L38+L58+L59 -> 191419 | S11: =R11/$R$14 -> 0.54877884 | T11: =R11*1000000000*Conv!$D$6*Conv!$J$5*20 -> 4128016.7
A12: Alabama | B12: 2724 | C12: -45 | D12: 472 | E12: 163 | F12: 595 | G12: 398 | H12: 3 | I12: 2 | J12: 0 | K12: 226 | L12: 2570 | N12: 6 | Q12: R8 | R12: =L19+L29+L30+L52+L55 -> 88119 | S12: =R12/$R$14 -> 0.25262823 | T12: =R12*1000000000*Conv!$D$6*Conv!$J$5*20 -> 1900316.6
A13: Arkansas | B13: 14181 | C13: 729 | D13: 631 | E13: 324 | F13: 6762 | G13: 6882 | H13: 2094 | I13: 0 | J13: 23 | K13: 1080 | L13: 16374 | N13: 7 | Q13: R9 | R13: =L10+L14+L57 -> 13264 | S13: =R13/$R$14 -> 0.038026542 | T13: =R13*1000000000*Conv!$D$6*Conv!$J$5*20 -> 286042.73
A14: California | B14: 2785 | C14: 917 | D14: 1542 | E14: 1959 | F14: 49 | G14: 55 | H14: 75 | I14: 0 | J14: 0 | K14: 324 | L14: 3042 | N14: 9 | Q14: Total | R14: =SUM(R6:R13)+L60+L37 -> 348809 | S14: =SUM(S6:S13) -> 0.92227265 | T14: =SUM(T6:T13) -> 6942962.7
A15: Coastal Region Onshore | B15: 180 | C15: 15 | D15: 21 | E15: 32 | F15: 0 | G15: 0 | H15: 1 | I15: 0 | J15: 0 | K15: 12 | L15: 173
A16: Los Angeles Basin Onshore | B16: 92 | C16: 6 | D16: 12 | E16: 4 | F16: 0 | G16: 3 | H16: 0 | I16: 0 | J16: 0 | K16: 7 | L16: 102
A17: San Joaquin Basin Onshore | B17: 2447 | C17: 895 | D17: 1498 | E17: 1923 | F17: 47 | G17: 44 | H17: 71 | I17: 0 | J17: 0 | K17: 300 | L17: 2685
A18: State Offshore | B18: 66 | C18: 1 | D18: 11 | E18: 0 | F18: 2 | G18: 8 | H18: 3 | I18: 0 | J18: 0 | K18: 5 | L18: 82
A19: Colorado | B19: 25372 | C19: 883 | D19: 2644 | E19: 3077 | F19: 1311 | G19: 1283 | H19: 2123 | I19: 19 | J19: 0 | K19: 1785 | L19: 26151 | N19: 8
A20: Florida | B20: 56 | C20: -54 | D20: 13 | E20: 9 | F20: 0 | G20: 0 | H20: 0 | I20: 0 | J20: 0 | K20: 0 | L20: 6 | N20: 5
A21: Kansas | B21: 3937 | C21: 145 | D21: 164 | E21: 258 | F21: 133 | G21: 131 | H21: 66 | I21: 0 | J21: 1 | K21: 306 | L21: 3747 | N21: 4
A22: Kentucky | B22: 2785 | C22: -48 | D22: 188 | E22: 678 | F22: 106 | G22: 89 | H22: 4 | I22: 2 | J22: 0 | K22: 108 | L22: 2128 | N22: 6
A23: Louisiana | B23: 29517 | C23: 126 | D23: 3789 | E23: 5877 | F23: 5618 | G23: 5585 | H23: 5813 | I23: 49 | J23: 169 | K23: 3008 | L23: 30545 | N23: 7
A24: North | B24: 26136 | C24: 177 | D24: 3105 | E24: 5335 | F24: 4999 | G24: 5060 | H24: 5693 | I24: 0 | J24: 144 | K24: 2570 | L24: 27411
A25: South Onshore | B25: 2995 | C25: -48 | D25: 627 | E25: 523 | F25: 608 | G25: 381 | H25: 104 | I25: 49 | J25: 25 | K25: 387 | L25: 2615
A26: State Offshore | B26: 386 | C26: -3 | D26: 57 | E26: 19 | F26: 11 | G26: 144 | H26: 16 | I26: 0 | J26: 0 | K26: 51 | L26: 519
A27: Michigan | B27: 2975 | C27: 5 | D27: 213 | E27: 272 | F27: 654 | G27: 410 | H27: 0 | I27: 14 | J27: 0 | K27: 142 | L27: 2549 | N27: 3
A28: Mississippi | B28: 858 | C28: 112 | D28: 106 | E28: 157 | F28: 11 | G28: 10 | H28: 24 | I28: 1 | J28: 0 | K28: 75 | L28: 868 | N28: 6
A29: Montana | B29: 959 | C29: -58 | D29: 44 | E29: 99 | F29: 45 | G29: 45 | H29: 14 | I29: 7 | J29: 1 | K29: 76 | L29: 792 | N29: 8
A30: New Mexico | B30: 16529 | C30: 107 | D30: 2267 | E30: 2386 | F30: 1088 | G30: 1155 | H30: 802 | I30: 3 | J30: 9 | K30: 1260 | L30: 16138 | N30: 8
A31: East | B31: 4720 | C31: -143 | D31: 560 | E31: 481 | F31: 222 | G31: 286 | H31: 579 | I31: 3 | J31: 2 | K31: 420 | L31: 4884
A32: West | B32: 11809 | C32: 250 | D32: 1707 | E32: 1905 | F32: 866 | G32: 869 | H32: 223 | I32: 0 | J32: 7 | K32: 840 | L32: 11254
A33: New York | B33: 281 | C33: -22 | D33: 48 | E33: 50 | F33: 0 | G33: 0 | H33: 0 | I33: 0 | J33: 27 | K33: 31 | L33: 253 | N33: 2
A34: North Dakota | B34: 1869 | C34: -15 | D34: 635 | E34: 417 | F34: 126 | G34: 188 | H34: 638 | I34: 11 | J34: 18 | K34: 149 | L34: 2652 | N34: 4
A35: Ohio | B35: 832 | C35: -99 | D35: 17 | E35: 38 | F35: 0 | G35: 4 | H35: 118 | I35: 0 | J35: 0 | K35: 76 | L35: 758 | N35: 3
A36: Oklahoma | B36: 28182 | C36: -238 | D36: 5531 | E36: 7375 | F36: 3222 | G36: 2645 | H36: 6170 | I36: 50 | J36: 19 | K36: 1825 | L36: 29937 | N36: 7
A37: Pennsylvania | B37: 14068 | C37: -231 | D37: 7127 | E37: 4907 | F37: 805 | G37: 1897 | H37: 10337 | I37: 166 | J37: 324 | K37: 1257 | L37: 26719 | N37: 2
A38: Texas | B38: 94287 | C38: 676 | D38: 21098 | E38: 20135 | F38: 21329 | G38: 23629 | H38: 13321 | I38: 72 | J38: 446 | K38: 7611 | L38: 104454 | N38: 7
A39: RRC District 1 | B39: 2599 | C39: -57 | D39: 2303 | E39: 180 | F39: 1237 | G39: 1181 | H39: 1718 | I39: 24 | J39: 2 | K39: 226 | L39: 6127
A40: RRC District 2 Onshore | B40: 2235 | C40: 210 | D40: 458 | E40: 593 | F40: 175 | G40: 684 | H40: 1079 | I40: 0 | J40: 122 | K40: 330 | L40: 3690
A41: RRC District 3 Onshore | B41: 2774 | C41: -28 | D41: 413 | E41: 277 | F41: 302 | G41: 225 | H41: 115 | I41: 17 | J41: 4 | K41: 451 | L41: 2490
A42: RRC District 4 Onshore | B42: 7392 | C42: 445 | D42: 2415 | E42: 1156 | F42: 998 | G42: 1323 | H42: 1543 | I42: 7 | J42: 24 | K42: 941 | L42: 10054
A43: RRC District 5 | B43: 24694 | C43: 653 | D43: 3739 | E43: 2184 | F43: 10687 | G43: 10827 | H43: 3071 | I43: 2 | J43: 0 | K43: 1928 | L43: 28187
A44: RRC District 6 | B44: 15416 | C44: 271 | D44: 5057 | E44: 5646 | F44: 4069 | G44: 4075 | H44: 1726 | I44: 3 | J44: 277 | K44: 1115 | L44: 15995
A45: RRC District 7B | B45: 2625 | C45: -65 | D45: 456 | E45: 405 | F45: 803 | G45: 2182 | H45: 128 | I45: 0 | J45: 0 | K45: 231 | L45: 3887
A46: RRC District 7C | B46: 5432 | C46: -195 | D46: 800 | E46: 828 | F46: 304 | G46: 318 | H46: 357 | I46: 0 | J46: 0 | K46: 344 | L46: 5236
A47: RRC District 8 | B47: 8105 | C47: -631 | D47: 1214 | E47: 1182 | F47: 213 | G47: 554 | H47: 776 | I47: 4 | J47: 1 | K47: 540 | L47: 8088
A48: RRC District 8A | B48: 1228 | C48: -36 | D48: 205 | E48: 38 | F48: 26 | G48: 43 | H48: 11 | I48: 0 | J48: 1 | K48: 99 | L48: 1289
A49: RRC District 9 | B49: 13172 | C49: 163 | D49: 3077 | E49: 6006 | F49: 1299 | G49: 1546 | H49: 917 | I49: 11 | J49: 0 | K49: 661 | L49: 10920
A50: RRC District 10 | B50: 8484 | C50: -29 | D50: 886 | E50: 1574 | F50: 1214 | G50: 645 | H50: 1880 | I50: 4 | J50: 15 | K50: 724 | L50: 8373
A51: State Offshore | B51: 131 | C51: -25 | D51: 75 | E51: 66 | F51: 2 | G51: 26 | H51: 0 | I51: 0 | J51: 0 | K51: 21 | L51: 118
A52: Utah | B52: 7146 | C52: 195 | D52: 839 | E52: 352 | F52: 782 | G52: 860 | H52: 664 | I52: 1 | J52: 0 | K52: 463 | L52: 8108 | N52: 8
A53: Virginia | B53: 3215 | C53: -413 | D53: 378 | E53: 255 | F53: 3 | G53: 3 | H53: 63 | I53: 0 | J53: 0 | K53: 156 | L53: 2832 | N53: 5
A54: West Virginia | B54: 7163 | C54: -37 | D54: 1240 | E54: 773 | F54: 270 | G54: 601 | H54: 2871 | I54: 0 | J54: 139 | K54: 402 | L54: 10532 | N54: 5
A55: Wyoming | B55: 36526 | C55: -42 | D55: 3423 | E55: 3173 | F55: 1198 | G55: 1261 | H55: 2317 | I55: 0 | J55: 1 | K55: 2185 | L55: 36930 | N55: 8
A56: Federal Offshorea | B56: 12120 | C56: 51 | D56: 2567 | E56: 3104 | F56: 332 | G56: 474 | H56: 98 | I56: 590 | J56: 80 | K56: 1724 | L56: 10820
A57: Pacific (California) | B57: 725 | C57: -1 | D57: 39 | E57: 21 | F57: 0 | G57: 0 | H57: 0 | I57: 0 | J57: 0 | K57: 31 | L57: 711 | N57: 9
A58: Gulf of Mexico (Louisiana)a | B58: 9250 | C58: 51 | D58: 2150 | E58: 2371 | F58: 309 | G58: 404 | H58: 85 | I58: 590 | J58: 80 | K58: 1375 | L58: 8555 | N58: 7
A59: Gulf of Mexico (Texas) | B59: 2145 | C59: 1 | D59: 378 | E59: 712 | F59: 23 | G59: 70 | H59: 13 | I59: 0 | J59: 0 | K59: 318 | L59: 1554 | N59: 7
A60: Miscellaneousb | B60: 363 | C60: 73 | D60: 101 | E60: 82 | F60: 100 | G60: 46 | H60: 16 | I60: 0 | J60: 0 | K60: 24 | L60: 393
A61: U.S. Total | B61: 317647 | C61: 2715 | D61: 56015 | E61: 56127 | F61: 44575 | G61: 47873 | H61: 47635 | I61: 987 | J61: 1260 | K61: 24621 | L61: 348809 | M61: =SUM(M10:M60) -> 0
A62: a Includes Federal offshore Alabama.
A63: b Includes Arizona, Illinois, Indiana, Maryland, Missouri, Nebraska, Nevada, Oregon, South Dakota, and Tennessee.
A65: Note: The production estimates in this table are based on data reported on Form EIA-23, "Annual Survey of Domestic Oil and Gas Reserves,"
A66: They may differ from the official Energy Information Administration production data for natural gas for 2011 contained in the Natural Gas Annual 2011, DOE/EIA-0131(11).
A67: EIA Natural Gas Data
A68: http://www.eia.gov/naturalgas/data.cfm
A69: Natural gas is measured at 60 degrees Farenheit and atmospheric pressure base of 14.73 pounds per square inch (psia)
A70: Source: U.S. Energy Information Administration, Form EIA-23, “Annual Survey of Domestic Oil and Gas Reserves.”

Sheet NGACap
A1: Trade Links
B2: 2005 Capacity (billion cubic feet per year) | C2: 2010 | D2: 2015 | E2: 2020 | F2: 2025 | G2: 2030
A3: R2 to R1 | B3: =B29*T29 -> 841.51091 | C3: =C29*U29 -> 931.00691 | D3: =D29*V29 -> 997.0439 | E3: =E29*W29 -> 1089.6932 | F3: =F29*X29 -> 1161.4342 | G3: =G29*Y29 -> 1090.645
A4: R3 to R2 | B4: =B30*N77*T30 -> 711.53892 | C4: =C30*O77*U30 -> 740.76291 | D4: =D30*P77*V30 -> 588.95718 | E4: =E30*Q77*W30 -> 1127.4329 | F4: =F30*R77*X30 -> 1672.5097 | G4: =G30*S77*Y30 -> 1650.0836
A5: R3 to R5 | B5: =B35*N95*T35 -> 738.8962 | C5: =C35*O95*U35 -> 675.84918 | D5: =D35*P95*V35 -> 569.7805 | E5: =E35*Q95*W35 -> 474.1315 | F5: =F35*R95*X35 -> 431.72837 | G5: =G35*S95*Y35 -> 496.12024
A6: R4 to R3 | B6: =B33*N83*T33 -> 3980.2715 | C6: =C33*O83*U33 -> 3879.6746 | D6: =D33*P83*V33 -> 3479.9697 | E6: =E33*Q83*W33 -> 3130.7141 | F6: =F33*R83*X33 -> 2867.0799 | G6: =G33*S83*Y33 -> 2649.7341
A7: R5 to R2 | B7: =B30*N78*T30 -> 2370.5572 | C7: =C30*O78*U30 -> 2382.1156 | D7: =D30*P78*V30 -> 2721.9842 | E7: =E30*Q78*W30 -> 2256.1001 | F7: =F30*R78*X30 -> 1640.5264 | G7: =G30*S78*Y30 -> 1544.3135
A8: R6 to R3 | B8: =B33*N84*T33 -> 1773.1273 | C8: =C33*O84*U33 -> 2289.265 | D8: =D33*P84*V33 -> 2944.4108 | E8: =E33*Q84*W33 -> 3324.3184 | F8: =F33*R84*X33 -> 3587.8594 | G8: =G33*S84*Y33 -> 3665.113
A9: R6 to R5 | B9: =B35*N96*T35 -> 2906.9313 | C9: =C35*O96*U35 -> 2912.2119 | D9: =D35*P96*V35 -> 3495.0084 | E9: =E35*Q96*W35 -> 3360.2108 | F9: =F35*R96*X35 -> 3267.1702 | G9: =G35*S96*Y35 -> 3050.4881
A10: R7 to R4 | B10: =B34*N87*T34 -> 2921.7356 | C10: =C34*O87*U34 -> 2053.023 | D10: =D34*P87*V34 -> 3033.7256 | E10: =E34*Q87*W34 -> 3118.3711 | F10: =F34*R87*X34 -> 3206.3104 | G10: =G34*S87*Y34 -> 2906.3653
A11: R7 to R6 | B11: =B36*T36 -> 5576.4599 | C11: =C36*U36 -> 6099.0257 | D11: =D36*V36 -> 7138.2818 | E11: =E36*W36 -> 7094.0284 | F11: =F36*X36 -> 6684.2628 | G11: =G36*Y36 -> 6576.5555
A12: R8 to R4 | B12: =B34*N88*T34 -> 1950.4105 | C12: =C34*O88*U34 -> 3120.4368 | D12: =D34*P88*V34 -> 2060.4607 | E12: =E34*Q88*W34 -> 2050.3612 | F12: =F34*R88*X34 -> 1955.9731 | G12: =G34*S88*Y34 -> 2161.9355
A13: R8 to R7 | B13: =B37*T37 -> 804.90139 | C13: =C37*U37 -> 745.47851 | D13: =D37*V37 -> 606.87026 | E13: =E37*W37 -> 712.04625 | F13: =F37*X37 -> 721.60296 | G13: =G37*Y37 -> 689.48573 | V13: * Taken from the AEO2007
A14: R8 to R9 | B14: =B39*T39 -> 2785.1306 | C14: =C39*U39 -> 2904.4028 | D14: =D39*V39 -> 3130.4791 | E14: =E39*W39 -> 3104.6554 | F14: =F39*X39 -> 3205.0279 | G14: =G39*Y39 -> 3297.0241
A16: Canada to R1 | B16: =B41*N71 -> 314.14553 | C16: =C41*O71 -> 269.64204 | D16: =D41*P71 -> 337.47455 | E16: =E41*Q71 -> 328.83673 | F16: =F41*R71 -> 222.48607 | G16: =G41*S71 -> 180.89989 | V16: * For more information on capacity use see
A17: Canada to R2 | B17: =B41*N79 -> 1309.7599 | C17: =C41*O79 -> 902.0752 | D17: =D41*P79 -> 751.79975 | E17: =E41*Q79 -> 610.69679 | F17: =F41*R79 -> 374.27563 | G17: =G41*S79 -> 305.65843 | V17: http://www.eia.gov/pub/oil_gas/natural_gas/analysis_publications/ngpipeline/usage.html
A18: Canada to R4 | B18: =B41*N89 -> 3318.1196 | C18: =C41*O89 -> 3422.0027 | D18: =D41*P89 -> 3991.2213 | E18: =E41*Q89 -> 4450.5295 | F18: =F41*R89 -> 3983.9561 | G18: =G41*S89 -> 4038.0182
A19: Canada to R8 | B19: =B41*N106 -> 73.271147 | C19: =C41*O106 -> 23.667128 | D19: =D41*P106 -> 51.364972 | E19: =E41*Q106 -> 69.4675 | F19: =F41*R106 -> 78.2614 | G19: =G41*S106 -> 90.173499
A20: Canada to R9 | B20: =B41*N110 -> 1486.5539 | C20: =C41*O110 -> 1527.9716 | D20: =D41*P110 -> 1506.9408 | E20: =E41*Q110 -> 1958.7232 | F20: =F41*R110 -> 2035.6435 | G20: =G41*S110 -> 2229.0193
A24: Table 109. Natural Gas Pipeline Capacity By Census Division | F24: * Taken from the AEO2007 | M24: Table 110. Natural Gas Pipeline Capacity Utilization 1/ by Census Division
A25: (design capacity in billion cubic feet per year) | M25: (fraction)
T26: Utilization
B27: 2005 | C27: 2010 | D27: 2015 | E27: 2020 | F27: 2025 | G27: 2030 | N27: 2005 | O27: 2010 | P27: 2015 | Q27: 2020 | R27: 2025 | S27: 2030 | T27: 2005 | U27: 2010 | V27: 2015 | W27: 2020 | X27: 2025 | Y27: 2030
A28: Capacity Entering Region 1/ | M28: Utilization Entering Region
A29: New England | B29: 1457.46 | C29: 1807.6101 | D29: 1962.6101 | E29: 1962.6101 | F29: 1962.6101 | G29: 1962.6101 | M29: New England | N29: 0.52738184 | O29: 0.46504852 | P29: 0.45801935 | Q29: 0.50522655 | R29: 0.54178041 | S29: 0.5057115 | T29: =N29+0.05 -> 0.57738184 | U29: =O29+0.05 -> 0.51504852 | V29: =P29+0.05 -> 0.50801935 | W29: =Q29+0.05 -> 0.55522655 | X29: =R29+0.05 -> 0.59178041 | Y29: =S29+0.05 -> 0.5557115
A30: Middle Atlantic | B30: 4835.2114 | C30: 4894.7065 | D30: 4894.7065 | E30: 4894.7065 | F30: 4894.7065 | G30: 4894.7065 | M30: Middle Atlantic | N30: 0.58742738 | O30: 0.58801138 | P30: 0.62643307 | Q30: 0.64126372 | R30: 0.62686104 | S30: 0.60262281 | T30: =N30+0.05 -> 0.63742738 | U30: =O30+0.05 -> 0.63801138 | V30: =P30+0.05 -> 0.67643307 | W30: =Q30+0.05 -> 0.69126372 | X30: =R30+0.05 -> 0.67686104 | Y30: =S30+0.05 -> 0.65262281
A31: NYS | C31: =#REF!+#REF!+#REF!+#REF!+#REF!+#REF!+#REF!+#REF!+#REF!+#REF!+#REF!+#REF!+#REF!+#REF!+#REF!+#REF!+#REF!+#REF!+#REF!+#REF!+#REF!+#REF!+#REF!+#REF! -> #REF! | D31: =SUM(#REF!) -> #REF!
A32: (%) | C32: =C31/C30 -> #REF! | D32: =D31/D30 -> #REF!
A33: East North Central | B33: 9278.541 | C33: 9717.5576 | D33: 10323.524 | E33: 10380.955 | F33: 10426.616 | G33: 10426.616 | M33: East North Central | N33: 0.57007581 | O33: 0.58482409 | P33: 0.57230496 | Q33: 0.57181489 | R33: 0.56908286 | S33: 0.55564684 | T33: =N33+0.05 -> 0.62007581 | U33: =O33+0.05 -> 0.63482409 | V33: =P33+0.05 -> 0.62230496 | W33: =Q33+0.05 -> 0.62181489 | X33: =R33+0.05 -> 0.61908286 | Y33: =S33+0.05 -> 0.60564684
A34: West North Central | B34: 7584.0049 | C34: 8211.8047 | D34: 8441.9521 | E34: 9374.9512 | F34: 9467.4111 | G34: 9467.4111 | M34: West North Central | N34: 0.59242392 | O34: 0.58000278 | P34: 0.55343699 | Q34: 0.50133431 | R34: 0.49526876 | S34: 0.48534179 | T34: =N34+0.05 -> 0.64242392 | U34: =O34+0.05 -> 0.63000278 | V34: =P34+0.05 -> 0.60343699 | W34: =Q34+0.05 -> 0.55133431 | X34: =R34+0.05 -> 0.54526876 | Y34: =S34+0.05 -> 0.53534179
A35: South Atlantic | B35: 7253.3164 | C35: 7594.7383 | D35: 7594.7383 | E35: 7594.7383 | F35: 7594.7383 | G35: 7594.7383 | M35: South Atlantic | N35: 0.45264283 | O35: 0.42244038 | P35: 0.48521119 | Q35: 0.45486826 | R35: 0.43703437 | S35: 0.41698229 | T35: =N35+0.05 -> 0.50264283 | U35: =O35+0.05 -> 0.47244038 | V35: =P35+0.05 -> 0.53521119 | W35: =Q35+0.05 -> 0.50486826 | X35: =R35+0.05 -> 0.48703437 | Y35: =S35+0.05 -> 0.46698229
A36: East South Central | B36: 9910.8145 | C36: 12035.144 | D36: 12035.144 | E36: 12035.144 | F36: 12035.144 | G36: 12035.144 | M36: East South Central | N36: 0.51266414 | O36: 0.45676801 | P36: 0.54311979 | Q36: 0.53944278 | R36: 0.50539535 | S36: 0.49644595 | T36: =N36+0.05 -> 0.56266414 | U36: =O36+0.05 -> 0.50676801 | V36: =P36+0.05 -> 0.59311979 | W36: =Q36+0.05 -> 0.58944278 | X36: =R36+0.05 -> 0.55539535 | Y36: =S36+0.05 -> 0.54644595
A37: West South Central | B37: 2155.0769 | C37: 2180.51 | D37: 2180.51 | E37: 2180.51 | F37: 2180.51 | G37: 2180.51 | M37: West South Central | N37: 0.3234908 | O37: 0.29188263 | P37: 0.22831574 | Q37: 0.27655032 | R37: 0.28093311 | S37: 0.26620388 | T37: =N37+0.05 -> 0.3734908 | U37: =O37+0.05 -> 0.34188263 | V37: =P37+0.05 -> 0.27831574 | W37: =Q37+0.05 -> 0.32655032 | X37: =R37+0.05 -> 0.33093311 | Y37: =S37+0.05 -> 0.31620388
A38: Mountain | B38: 2821.46 | C38: 2821.46 | D38: 2821.46 | E38: 2841.8293 | F38: 2843.8479 | G38: 2843.8479 | M38: Mountain | N38: 0.12451178 | O38: 0.13006356 | P38: 0.13062556 | Q38: 0.12941578 | R38: 0.13097328 | S38: 0.13185398 | T38: =N38+0.05 -> 0.17451178 | U38: =O38+0.05 -> 0.18006356 | V38: =P38+0.05 -> 0.18062556 | W38: =Q38+0.05 -> 0.17941578 | X38: =R38+0.05 -> 0.18097328 | Y38: =S38+0.05 -> 0.18185398
A39: Pacific | B39: 4559.9697 | C39: 4603.77 | D39: 4603.77 | E39: 5232.583 | F39: 5294.6895 | G39: 5294.6895 | M39: Pacific | N39: 0.56077832 | O39: 0.58087486 | P39: 0.62998164 | Q39: 0.54333133 | R39: 0.55532879 | S39: 0.57270396 | T39: =N39+0.05 -> 0.61077832 | U39: =O39+0.05 -> 0.63087486 | V39: =P39+0.05 -> 0.67998164 | W39: =Q39+0.05 -> 0.59333133 | X39: =R39+0.05 -> 0.60532879 | Y39: =S39+0.05 -> 0.62270396
A40: Total | B40: 49855.855 | C40: 53867.301 | D40: 54858.418 | E40: 56498.027 | F40: 56700.277 | G40: 56700.277 | M40: Average 2/ | N40: 0.50868762 | O40: 0.4928394 | P40: 0.52013314 | Q40: 0.5049209 | R40: 0.49525565 | S40: 0.48430136 | T40: =N40+0.05 -> 0.55868762 | U40: =O40+0.05 -> 0.5428394 | V40: =P40+0.05 -> 0.57013314 | W40: =Q40+0.05 -> 0.5549209 | X40: =R40+0.05 -> 0.54525565 | Y40: =S40+0.05 -> 0.53430136
A41: United States (Pipeline Imports) | B41: 6501.8501 | C41: 6945.0752 | D41: 7100.0752 | E41: 8680.1602 | F41: 8836.7451 | G41: 8836.7451 | M41: United States (Pipeline Imports) | N41: 0.64688349 | O41: 0.56445765 | P41: 0.53024685 | Q41: 0.50292164 | R41: 0.47014397 | S41: 0.44361678 | T41: =N41+0.05 -> 0.69688349 | U41: =O41+0.05 -> 0.61445765 | V41: =P41+0.05 -> 0.58024685 | W41: =Q41+0.05 -> 0.55292164 | X41: =R41+0.05 -> 0.52014397 | Y41: =S41+0.05 -> 0.49361678
A43: Capacity Exiting Region 2/ | M43: Utilization Exiting Region
A44: New England | B44: 132.86 | C44: 132.86 | D44: 132.86 | E44: 132.86 | F44: 132.86 | G44: 132.86 | M44: New England | N44: 0.79432482 | O44: 0.79432482 | P44: 0.79432482 | Q44: 0.79432482 | R44: 0.79432482 | S44: 0.79432482
A45: Middle Atlantic | B45: 2280.4526 | C45: 2598.9807 | D45: 2598.9807 | E45: 2598.9807 | F45: 2598.9807 | G45: 2598.9807 | M45: Middle Atlantic | N45: 0.28399223 | O45: 0.26432943 | P45: 0.27671316 | Q45: 0.29788712 | R45: 0.30035669 | S45: 0.27832127
A46: East North Central | B46: 3799.3218 | C46: 3888.7471 | D46: 3888.7471 | E46: 3888.7471 | F46: 3888.7471 | G46: 3888.7471 | M46: East North Central | N46: 0.52424747 | O46: 0.4945516 | P46: 0.49873406 | Q46: 0.47750065 | R46: 0.45452663 | S46: 0.43679568
A47: West North Central | B47: 5642.7764 | C47: 5992.3691 | D47: 6164.8486 | E47: 6164.8486 | F47: 6164.8486 | G47: 6164.8486 | M47: West North Central | N47: 0.63224912 | O47: 0.60877985 | P47: 0.56554663 | Q47: 0.56179559 | R47: 0.55800134 | S47: 0.5389632
A48: South Atlantic | B48: 3494.116 | C48: 3559.48 | D48: 3559.48 | E48: 3559.48 | F48: 3559.48 | G48: 3559.48 | M48: South Atlantic | N48: 0.48443529 | O48: 0.52294922 | P48: 0.5941717 | Q48: 0.62353677 | R48: 0.60782826 | S48: 0.58816266
A49: East South Central | B49: 8769.126 | C49: 8833.001 | D49: 9266.4883 | E49: 9323.9189 | F49: 9369.5791 | G49: 9369.5791 | M49: East South Central | N49: 0.49737817 | O49: 0.53006023 | P49: 0.60210055 | Q49: 0.59064049 | R49: 0.58273405 | S49: 0.56905615
A50: West South Central | B50: 15456.765 | C50: 17605.701 | D50: 17744.674 | E50: 17744.674 | F50: 17744.674 | G50: 17744.674 | M50: West South Central | N50: 0.43317866 | O50: 0.41197136 | P50: 0.47257987 | Q50: 0.4452163 | R50: 0.42324331 | S50: 0.41618446
A51: Mountain | B51: 6007.8623 | C51: 6642.8457 | D51: 6734.0205 | E51: 6736.1162 | F51: 6736.1162 | G51: 6736.1162 | M51: Mountain | N51: 0.53964156 | O51: 0.53460568 | P51: 0.51661497 | Q51: 0.49995324 | R51: 0.56205863 | S51: 0.59217536
A52: Pacific | B52: 519.8241 | C52: 519.8241 | D52: 519.8241 | E52: 519.8241 | F52: 519.8241 | G52: 519.8241 | M52: Pacific | N52: 0.13755994 | O52: 0.19193733 | P52: 0.17656533 | Q52: 0.19075 | R52: 0.25690559 | S52: 0.29660183
A53: Total | B53: 46103.098 | C53: 49773.812 | D53: 50609.922 | E53: 50669.445 | F53: 50715.109 | G53: 50715.109 | M53: Average 2/ | N53: 0.48534653 | O53: 0.47839037 | P53: 0.51178545 | Q53: 0.49918982 | R53: 0.49585152 | S53: 0.48907855
A54: United States (Pipeline Exports) | B54: 2749.0952 | C54: 2851.5796 | D54: 2851.5796 | E54: 2851.5796 | F54: 2851.5796 | G54: 2851.5796 | M54: United States (Pipeline Exports) | N54: 0.44409409 | O54: 0.41506237 | P54: 0.39716062 | Q54: 0.39700007 | R54: 0.42803466 | S54: 0.44318721
A56: 1/ Includes only the sum of capacity levels for the States bounding the respective regions including pipeline import capacity. | M56: 1/ Capacity utilization is defined as the annual throughput volume divided by the design capacity (Table 87).
A57: 2/ Includes only the sum of capacity levels for the States bounding the respective regions including pipeline export capacity. | M57: 2/ Weighted average utilization. Weights used are the regional pipeline capacity levels provided in Table 87.
A58: N/A = Not applicable. | M58: N/A = Not applicable.
A59: Note: Totals may not equal sum of components due to independent rounding. | M59: Note: Totals may not equal sum of components due to independent rounding.
A60: Source: Energy Information Administration, AEO2007 National Energy Modeling System run aeo2007.d112106a. | M60: Source: Energy Information Administration, AEO2007 National Energy Modeling System run aeo2007.d112106a.
A61: Updated by AEO 2011 data
A64: Primary Natural Gas Flows Entering NGTDM Region from Neighboring Regions, Reference case
A65: (billion cubic feet per year)
N66: % of total
B67: 2005 | C67: 2010 | D67: 2015 | E67: 2020 | F67: 2025 | G67: 2030 | H67: 2035 | I67: 2040 | J67: 2045 | K67: 2050 | L67: 2055 | Q67: sum from Canada = | S67: =B71+B79+B89+B90+B106+B110+B111 -> 4249.8469
A69: Into New England From: | N69: 2005 | O69: 2010 | P69: 2015 | Q69: 2020 | R69: 2025 | S69: 2030 | T69: 2035 | U69: 2040
A70: Middle Atlantic | B70: 603.4314 | C70: 728 | D70: 816 | E70: 876 | F70: 963 | G70: 1058 | H70: 1122 | I70: =H70*(AVERAGE((H70/G70),(G70/F70))) -> 1211.2784 | J70: =I70*(AVERAGE((I70/H70),(H70/G70))) -> 1296.1056 | K70: =J70*(AVERAGE((J70/I70),(I70/H70))) -> 1393.0555 | L70: =K70*(AVERAGE((K70/J70),(J70/I70))) -> 1493.9351 | N70: 1 | O70: 1 | P70: 1 | Q70: 1 | R70: 1 | S70: 1 | T70: 1 | U70: 1
A71: Canada | B71: 205.33701 | C71: 165 | D71: 202 | E71: 161 | F71: 107 | G71: 87 | H71: 75 | I71: =H71*(AVERAGE((H71/G71),(G71/F71))) -> 62.81824 | J71: =I71*(AVERAGE((I71/H71),(H71/G71))) -> 53.38437 | K71: =J71*(AVERAGE((J71/I71),(I71/H71))) -> 45.040374 | L71: =K71*(AVERAGE((K71/J71),(J71/I71))) -> 38.138441 | N71: =B71/$S$67 -> 0.04831633 | O71: =C71/$S$67 -> 0.038824928 | P71: =D71/$S$67 -> 0.047531124 | Q71: =E71/$S$67 -> 0.037883717 | R71: =F71/$S$67 -> 0.025177377 | S71: =G71/$S$67 -> 0.020471326 | T71: =H71/$S$67 -> 0.017647694 | U71: =I71/$S$67 -> 0.014781295
A72: Middle Atlantic-old | B72: 603.4314 | C72: 742.58484 | D72: 928.89551 | E72: 958.91858 | F72: 944.94678 | G72: 854.2796 | H72: 848.02502 | I72: 770.8158 | J72: =I72*(AVERAGE((I72/H72),(H72/G72))) -> 732.90422 | K72: =J72*(AVERAGE((J72/I72),(I72/H72))) -> 681.51678 | L72: =K72*(AVERAGE((K72/J72),(J72/I72))) -> 640.86481
A73: Canada-old | B73: 205.33701 | C73: 192.60811 | D73: 204.1795 | E73: 200.80328 | F73: 194.46762 | G73: 255.27982 | H73: 322.76916 | I73: 396.94946 | J73: =I73*(AVERAGE((I73/H73),(H73/G73))) -> 495.0354 | K73: =J73*(AVERAGE((J73/I73),(I73/H73))) -> 613.08252 | L73: =K73*(AVERAGE((K73/J73),(J73/I73))) -> 761.92708
A76: Into Middle Atlantic From:
A77: East North Central | B77: 456.14691 | C77: 553.8335 | D77: 67.532448 | E77: 36.491119 | F77: 47.457565 | G77: 56.288845 | H77: 47.872124 | I77: 49.562599 | J77: =I77*(AVERAGE((I77/H77),(H77/G77))) -> 46.732202 | K77: =J77*(AVERAGE((J77/I77),(I77/H77))) -> 46.222933 | L77: =K77*(AVERAGE((K77/J77),(J77/I77))) -> 44.651235 | N77: =B77/SUM(B77:B78) -> 0.23086201 | O77: =C77/SUM(C77:C78) -> 0.23720517 | P77: =D77/SUM(D77:D78) -> 0.17788209 | Q77: =E77/SUM(E77:E78) -> 0.33321174 | R77: =F77/SUM(F77:F78) -> 0.50482689 | S77: =G77/SUM(G77:G78) -> 0.51655557 | T77: =H77/SUM(H77:H78) -> 0.51753148 | U77: =I77/SUM(I77:I78) -> 0.49999911
A78: South Atlantic | B78: 1519.6953 | C78: 1780.9955 | D78: 312.11481 | E78: 73.022186 | F78: 46.550037 | G78: 52.680737 | H78: 44.628769 | I78: 49.562775 | J78: =I78*(AVERAGE((I78/H78),(H78/G78))) -> 48.514819 | K78: =J78*(AVERAGE((J78/I78),(I78/H78))) -> 50.683738 | L78: =K78*(AVERAGE((K78/J78),(J78/I78))) -> 51.280851 | N78: =B78/SUM(B77:B78) -> 0.76913799 | O78: =C78/SUM(C77:C78) -> 0.76279483 | P78: =D78/SUM(D77:D78) -> 0.82211791 | Q78: =E78/SUM(E77:E78) -> 0.66678826 | R78: =F78/SUM(F77:F78) -> 0.49517311 | S78: =G78/SUM(G77:G78) -> 0.48344443 | T78: =H78/SUM(H77:H78) -> 0.48246852 | U78: =I78/SUM(I77:I78) -> 0.50000089
A79: Canada | B79: 856.10693 | C79: 552 | D79: 450 | E79: 299 | F79: 180 | G79: 147 | H79: 112 | I79: =H79*(AVERAGE((H79/G79),(G79/F79))) -> 88.4 | J79: =I79*(AVERAGE((I79/H79),(H79/G79))) -> 68.562619 | K79: =J79*(AVERAGE((J79/I79),(I79/H79))) -> 53.646168 | L79: =K79*(AVERAGE((K79/J79),(J79/I79))) -> 41.791323 | N79: =B79/$S$67 -> 0.20144418 | O79: =C79/$S$67 -> 0.12988703 | P79: =D79/$S$67 -> 0.10588617 | Q79: =E79/$S$67 -> 0.070355475 | R79: =F79/$S$67 -> 0.042354467 | S79: =G79/$S$67 -> 0.034589481 | T79: =H79/$S$67 -> 0.02635389 | U79: =I79/$S$67 -> 0.020800749
A80: Old data | B80: 856.10693 | C80: 432 | D80: 190.44019 | E80: 116.30151 | F80: 166.00392 | G80: 401.69434 | H80: 479.26025 | I80: 504.1785 | J80: 565.96305 | K80: 615.35412 | L80: 679.9091
A81: Canada to NYS
A82: Into East North Central From:
A83: West North Central | B83: 3643.9419 | C83: 3471.0222 | D83: 2676.9531 | E83: 2471.8652 | F83: 2118.4583 | G83: 2019.9231 | H83: 1777.0553 | I83: 1603.3761 | J83: =I83*(AVERAGE((I83/H83),(H83/G83))) -> 1428.6318 | K83: =J83*(AVERAGE((J83/I83),(I83/H83))) -> 1280.9688 | L83: =K83*(AVERAGE((K83/J83),(J83/I83))) -> 1144.9652 | N83: =B83/SUM(B83:B84) -> 0.6918122 | O83: =C83/SUM(C83:C84) -> 0.62890461 | P83: =D83/SUM(D83:D84) -> 0.54168175 | Q83: =E83/SUM(E83:E84) -> 0.48500362 | R83: =F83/SUM(F83:F84) -> 0.44416838 | S83: =G83/SUM(G83:G84) -> 0.41960384 | T83: =H83/SUM(H83:H84) -> 0.39605568 | U83: =I83/SUM(I83:I84) -> 0.36683771
A84: East South Central | B84: 1623.2996 | C84: 2048.1331 | D84: 2264.9766 | E84: 2624.7261 | F84: 2651.0354 | G84: 2793.9583 | H84: 2709.8271 | I84: 2767.429 | J84: =I84*(AVERAGE((I84/H84),(H84/G84))) -> 2755.1759 | K84: =J84*(AVERAGE((J84/I84),(I84/H84))) -> 2778.3594 | L84: =K84*(AVERAGE((K84/J84),(J84/I84))) -> 2783.898 | N84: =B84/SUM(B83:B84) -> 0.3081878 | O84: =C84/SUM(C83:C84) -> 0.37109539 | P84: =D84/SUM(D83:D84) -> 0.45831825 | Q84: =E84/SUM(E83:E84) -> 0.51499638 | R84: =F84/SUM(F83:F84) -> 0.55583162 | S84: =G84/SUM(G83:G84) -> 0.58039616 | T84: =H84/SUM(H83:H84) -> 0.60394432 | U84: =I84/SUM(I83:I84) -> 0.63316229
A86: Into West North Central from:
A87: West South Central | B87: 1614.968 | C87: 1456.217 | D87: 1822.1931 | E87: 2064.4092 | F87: 2180.3018 | G87: 2110.3286 | H87: 1957.3739 | I87: 2040.6125 | J87: =I87*(AVERAGE((I87/H87),(H87/G87))) -> 2010.0509 | K87: =J87*(AVERAGE((J87/I87),(I87/H87))) -> 2037.7383 | L87: =K87*(AVERAGE((K87/J87),(J87/I87))) -> 2036.5134 | N87: =B87/SUM(B87:B88) -> 0.59968143 | O87: =C87/SUM(C87:C88) -> 0.39683754 | P87: =D87/SUM(D87:D88) -> 0.59552703 | Q87: =E87/SUM(E87:E88) -> 0.60331449 | R87: =F87/SUM(F87:F88) -> 0.62110312 | S87: =G87/SUM(G87:G88) -> 0.57343978 | T87: =H87/SUM(H87:H88) -> 0.54749313 | U87: =I87/SUM(I87:I88) -> 0.58806993
A88: Mountain | B88: 1078.0752 | C88: 2213.3376 | D88: 1237.6061 | E88: 1357.3704 | F88: 1330.0682 | G88: 1569.7938 | H88: 1617.7831 | I88: 1429.4043 | J88: =I88*(AVERAGE((I88/H88),(H88/G88))) -> 1368.0313 | K88: =J88*(AVERAGE((J88/I88),(I88/H88))) -> 1259.0138 | L88: =K88*(AVERAGE((K88/J88),(J88/I88))) -> 1181.8203 | N88: =B88/SUM(B87:B88) -> 0.40031857 | O88: =C88/SUM(C87:C88) -> 0.60316246 | P88: =D88/SUM(D87:D88) -> 0.40447297 | Q88: =E88/SUM(E87:E88) -> 0.39668551 | R88: =F88/SUM(F87:F88) -> 0.37889688 | S88: =G88/SUM(G87:G88) -> 0.42656022 | T88: =H88/SUM(H87:H88) -> 0.45250687 | U88: =I88/SUM(I87:I88) -> 0.41193007
A89: Canada (direct) | B89: 1487.886 | C89: 1592 | D89: 1718 | E89: 1535 | F89: 1363 | G89: 1383 | H89: 1263 | I89: =H89*(AVERAGE((H89/G89),(G89/F89))) -> 1217.4724 | J89: =I89*(AVERAGE((I89/H89),(H89/G89))) -> 1142.7104 | K89: =J89*(AVERAGE((J89/I89),(I89/H89))) -> 1087.0291 | L89: =K89*(AVERAGE((K89/J89),(J89/I89))) -> 1027.1692 | N89: =(B89+B90)/$S$67 -> 0.51033469 | O89: =(C89+C90)/$S$67 -> 0.49272363 | P89: =(D89+D90)/$S$67 -> 0.56213789 | Q89: =(E89+E90)/$S$67 -> 0.51272435 | R89: =(F89+F90)/$S$67 -> 0.45083977 | S89: =(G89+G90)/$S$67 -> 0.45695764 | T89: =(H89+H90)/$S$67 -> 0.42048573 | U89: =(I89+I90)/$S$67 -> 0.40658189
A90: Canada (through Mountain) | B90: 680.95831 | C90: 502 | D90: 671 | E90: 644 | F90: 553 | G90: 559 | H90: 524 | I90: =H90*(AVERAGE((H90/G90),(G90/F90))) -> 510.43838 | J90: =I90*(AVERAGE((I90/H90),(H90/G90))) -> 487.85333 | K90: =J90*(AVERAGE((J90/I90),(I90/H90))) -> 470.74741 | L90: =K90*(AVERAGE((K90/J90),(J90/I90))) -> 452.07991
A91: Canada (direct)-old | B91: 1487.886 | C91: 1240.9238 | D91: 876.57953 | E91: 603.97534 | F91: 398.79279 | G91: 286.32898 | H91: 231.58028 | I91: 237.29285 | J91: =I91*(AVERAGE((I91/H91),(H91/G91))) -> 217.53332 | K91: =J91*(AVERAGE((J91/I91),(I91/H91))) -> 211.15928 | L91: =K91*(AVERAGE((K91/J91),(J91/I91))) -> 199.27396
A92: Canada (through Mountain)-old | B92: 680.95831 | C92: 674.48236 | D92: 726.41919 | E92: 539.48852 | F92: 381.06958 | G92: 299.14533 | H92: 260.53186 | I92: 286.10449 | J92: =I92*(AVERAGE((I92/H92),(H92/G92))) -> 281.68077 | K92: =J92*(AVERAGE((J92/I92),(I92/H92))) -> 293.32737 | L92: =K92*(AVERAGE((K92/J92),(J92/I92))) -> 297.12374
A94: Into South Atlantic from:
A95: East North Central | B95: 654.68939 | C95: 795.69128 | D95: 443.19666 | E95: 348.81775 | F95: 317.90311 | G95: 447.00928 | H95: 504.61957 | I95: 465.30542 | J95: =I95*(AVERAGE((I95/H95),(H95/G95))) -> 477.16394 | K95: =J95*(AVERAGE((J95/I95),(I95/H95))) -> 464.65675 | L95: =K95*(AVERAGE((K95/J95),(J95/I95))) -> 464.48807 | N95: =B95/SUM(B95:B96,B116) -> 0.202669 | O95: =C95/SUM(C95:C96,C116) -> 0.18836056 | P95: =D95/SUM(D95:D96,D116) -> 0.14017468 | Q95: =E95/SUM(E95:E96,E116) -> 0.12365393 | R95: =F95/SUM(F95:F96,F116) -> 0.11671809 | S95: =G95/SUM(G95:G96,G116) -> 0.13988583 | T95: =H95/SUM(H95:H96,H116) -> 0.15397445 | U95: =I95/SUM(I95:I96,I116) -> 0.15488811
A96: East South Central | B96: 1821.7283 | C96: 2345.3206 | D96: 1691.6453 | E96: 1327.3754 | F96: 1142.0986 | G96: 1422.7681 | H96: 1406.5107 | I96: 1226.7992 | J96: =I96*(AVERAGE((I96/H96),(H96/G96))) -> 1141.4154 | K96: =J96*(AVERAGE((J96/I96),(I96/H96))) -> 1028.7748 | L96: =K96*(AVERAGE((K96/J96),(J96/I96))) -> 942.21164 | N96: =(B96+B116)/SUM(B95:B96,B116) -> 0.797331 | O96: =(C96+C116)/SUM(C95:C96,C116) -> 0.81163944 | P96: =(D96+D116)/SUM(D95:D96,D116) -> 0.85982532 | Q96: =(E96+E116)/SUM(E95:E96,E116) -> 0.87634607 | R96: =(F96+F116)/SUM(F95:F96,F116) -> 0.88328191 | S96: =(G96+G116)/SUM(G95:G96,G116) -> 0.86011417 | T96: =(H96+H116)/SUM(H95:H96,H116) -> 0.84602555 | U96: =(I96+I116)/SUM(I95:I96,I116) -> 0.84511189
A98: Into East South Central from:
A99: West South Central | B99: 4816.3198 | C99: 6716.5371 | D99: 6148.6123 | E99: 6331.9453 | F99: 5846.9043 | G99: 6044.5571 | H99: 5670.9854 | I99: 5484.8203 | J99: =I99*(AVERAGE((I99/H99),(H99/G99))) -> 5225.3043 | K99: =J99*(AVERAGE((J99/I99),(I99/H99))) -> 5015.9186 | L99: =K99*(AVERAGE((K99/J99),(J99/I99))) -> 4796.7561
A101: Into West South Central from:
A102: Mountain | B102: 147.86678 | C102: 225.48239 | D102: 180.50403 | E102: 222.27867 | F102: 244.57231 | G102: 319.49866 | H102: 364.74658 | I102: 351.19083 | J102: =I102*(AVERAGE((I102/H102),(H102/G102))) -> 369.53296 | K102: =J102*(AVERAGE((J102/I102),(I102/H102))) -> 372.31619 | L102: =K102*(AVERAGE((K102/J102),(J102/I102))) -> 383.44103
A103: Arizona/New Mexico | B103: 534.75806 | C103: 219.11456 | D103: 494.13861 | E103: 641.58954 | F103: 526.7984 | G103: 622.3277 | H103: 642.21045 | I103: 639.66748 | J103: =I103*(AVERAGE((I103/H103),(H103/G103))) -> 648.6194 | K103: =J103*(AVERAGE((J103/I103),(I103/H103))) -> 651.87383 | L103: =K103*(AVERAGE((K103/J103),(J103/I103))) -> 658.07058
A105: Into Mountain from:
A106: Canada | B106: 47.8927 | C106: 14.482445 | D106: 30.745205 | E106: 34.011612 | F106: 37.638176 | G106: 43.36705 | H106: 43.928177 | I106: 43.966381 | J106: =I106*(AVERAGE((I106/H106),(H106/G106))) -> 44.26994 | K106: =J106*(AVERAGE((J106/I106),(I106/H106))) -> 44.442019 | L106: =K106*(AVERAGE((K106/J106),(J106/I106))) -> 44.681814 | N106: =B106/$S$67 -> 0.011269277 | O106: =C106/$S$67 -> 0.0034077569 | P106: =D106/$S$67 -> 0.0072344265 | Q106: =E106/$S$67 -> 0.0080030205 | R106: =F106/$S$67 -> 0.0088563604 | S106: =G106/$S$67 -> 0.010204379 | T106: =H106/$S$67 -> 0.010336414 | U106: =I106/$S$67 -> 0.010345403
A107: Canada-old | B107: 47.8927 | C107: 14.482445 | D107: 30.745205 | E107: 34.011612 | F107: 37.638176 | G107: 43.36705 | H107: 43.928177 | I107: 43.966381 | J107: 44.26994 | K107: 44.442019 | L107: 44.681814
A108: Into Pacific from:
A109: Mountain | B109: 85.877914 | C109: 80.160347 | D109: 492.87271 | E109: 548.34509 | F109: 723.30017 | G109: 874.02026 | H109: 973.00995 | I109: 927.0705 | J109: =I109*(AVERAGE((I109/H109),(H109/G109))) -> 957.68428 | K109: =J109*(AVERAGE((J109/I109),(I109/H109))) -> 950.8887 | L109: =K109*(AVERAGE((K109/J109),(J109/I109))) -> 963.21517 | N109: 1 | O109: 2 | P109: 3 | Q109: 4 | R109: 5 | S109: 6 | T109: 7 | U109: 8
A110: Canada (into Washington) | B110: 336.68399 | C110: 276 | D110: 220 | E110: 250 | F110: 244 | G110: 326 | H110: 332 | I110: =H110*(AVERAGE((H110/G110),(G110/F110))) -> 390.8421 | J110: =I110*(AVERAGE((I110/H110),(H110/G110))) -> 429.0743 | K110: =J110*(AVERAGE((J110/I110),(I110/H110))) -> 488.08389 | L110: =K110*(AVERAGE((K110/J110),(J110/I110))) -> 545.51861 | N110: =(B110+B111)/$S$67 -> 0.22863553 | O110: =(C110+C111)/$S$67 -> 0.22000792 | P110: =(D110+D111)/$S$67 -> 0.21224294 | Q110: =(E110+E111)/$S$67 -> 0.22565519 | R110: =(F110+F111)/$S$67 -> 0.23036124 | S110: =(G110+G111)/$S$67 -> 0.25224438 | T110: =(H110+H111)/$S$67 -> 0.2541268 | U110: =(I110+I111)/$S$67 -> 0.26952549
A111: Canada (through Idaho) | B111: 634.98199 | C111: 659 | D111: 682 | E111: 709 | F111: 735 | G111: 746 | H111: 748 | I111: =H111*(AVERAGE((H111/G111),(G111/F111))) -> 754.59996 | J111: =I111*(AVERAGE((I111/H111),(H111/G111))) -> 758.94059 | K111: =J111*(AVERAGE((J111/I111),(I111/H111))) -> 764.47163 | L111: =K111*(AVERAGE((K111/J111),(J111/I111))) -> 769.45601
A112: Canada (into Washington)-old | B112: 336.68399 | C112: 324.207 | D112: 339.39191 | E112: 251.44253 | F112: 237.14684 | G112: 188.74973 | H112: 175.38406 | I112: 204.00885 | J112: =I112*(AVERAGE((I112/H112),(H112/G112))) -> 213.43411 | K112: =J112*(AVERAGE((J112/I112),(I112/H112))) -> 235.78196 | L112: =K112*(AVERAGE((K112/J112),(J112/I112))) -> 253.57246
A113: Canada (through Idaho)-old | B113: 634.98199 | C113: 691.46179 | D113: 628.49548 | E113: 479.11804 | F113: 463.16022 | G113: 379.19092 | H113: 359.58289 | I113: 425.40424 | J113: =I113*(AVERAGE((I113/H113),(H113/G113))) -> 453.34032 | K113: =J113*(AVERAGE((J113/I113),(I113/H113))) -> 509.71742 | L113: =K113*(AVERAGE((K113/J113),(J113/I113))) -> 558.14792
A115: Into Florida from:
A116: East South Central | B116: 753.92047 | C116: 1083.287 | D116: 1026.9034 | E116: 1144.7261 | F116: 1263.6815 | G116: 1325.7521 | H116: 1366.1639 | I116: 1312.0344 | J116: =I116*(AVERAGE((I116/H116),(H116/G116))) -> 1306.0389 | K116: =J116*(AVERAGE((J116/I116),(I116/H116))) -> 1277.1812 | L116: =K116*(AVERAGE((K116/J116),(J116/I116))) -> 1260.153
A118: Into Arizona/New Mexico from:
...

Sheet Domestic NG Production
A1: Workbook Source (EIA)
A2: Natural Gas Gross Withdrawals and Production | F2: * Volume in million cubic feet
A4: Click worksheet name or tab at bottom for data
A5: Worksheet Name | B5: Description | C5: # Of Series | D5: Frequency | E5: Latest Data for
A6: Data 1 | C6: 10 | D6: Annual | E6: 2011 | F6: 6/30/1967
A8: Release Date: | B8: 8/31/2012
A9: Next Release Date: | B9: 9/28/2012
A11: Excel File Name: | B11: ng_prod_sum_dcu_nus_a.xls
A12: Available from Web Page: | B12: http://www.eia.gov/dnav/ng/ng_prod_sum_dcu_nus_a.htm
A13: Source: | B13: Energy Information Administration
A14: For Help, Contact: | B14: infoctr@eia.gov
B15: (202) 586-8800 | E15: 8/30/2012 2:29:48 PM
F17: *6.1% to R6 based on Reserves
B18: 9 | F18: 7,6 | J18: 7 | N18: 8 | R18: 7 | V18: 7 | Z18: 8 | AD18: 6 | AH18: 8 | AL18: 7 | AP18: 9 | AT18: 8 | AX18: 5 | BB18: 3 | BF18: 3 | BJ18: 4 | BN18: 6 | BR18: 5 | BV18: 3 | BZ18: 6 | CD18: 8 | CH18: 4 | CL18: 8 | CP18: 2 | CT18: 4 | CX18: 3 | DB18: 9 | DF18: 2 | DJ18: 4 | DN18: 6 | DR18: 8 | DV18: 5 | DZ18: 5
A19: Date | B19: Alaska Natural Gas Marketed Production (MMcf) | C19: Alaska Natural Gas Plant Liquids Production, Gaseous Equivalent (MMcf) | D19: Alaska Dry Natural Gas Production (Million Cubic Feet) | E19: %NGL | F19: Federal Offshore--Gulf of Mexico Natural Gas Marketed Production (MMcf) | G19: Federal Offshore--Gulf of Mexico Natural Gas Plant Liquids Production, Gaseous Equivalent (Million Cubic Feet) | H19: Federal Offshore--Gulf of Mexico Dry Natural Gas Production (Million Cubic Feet) | I19: %NGL | J19: Louisiana Natural Gas Marketed Production (MMcf) | K19: Louisiana Natural Gas Plant Liquids Production, Gaseous Equivalent (MMcf) | L19: Louisiana Dry Natural Gas Production (Million Cubic Feet) | M19: %NGL | N19: New Mexico Natural Gas Marketed Production (MMcf) | O19: New Mexico Natural Gas Plant Liquids Production, Gaseous Equivalent (MMcf) | P19: New Mexico Dry Natural Gas Production (Million Cubic Feet) | Q19: %NGL | R19: Oklahoma Natural Gas Marketed Production (MMcf) | S19: Oklahoma Natural Gas Plant Liquids Production, Gaseous Equivalent (MMcf) | T19: Oklahoma Dry Natural Gas Production (Million Cubic Feet) | U19: %NGL | V19: Texas Natural Gas Marketed Production (MMcf) | W19: Texas Natural Gas Plant Liquids Production, Gaseous Equivalent (MMcf) | X19: Texas Dry Natural Gas Production (Million Cubic Feet) | Y19: %NGL | Z19: Wyoming Natural Gas Marketed Production (MMcf) | AA19: Wyoming Natural Gas Plant Liquids Production, Gaseous Equivalent (MMcf) | AB19: Wyoming Dry Natural Gas Production (Million Cubic Feet) | AC19: %NGL | AD19: Alabama Natural Gas Marketed Production (MMcf) | AE19: Alabama Natural Gas Plant Liquids Production, Gaseous Equivalent (MMcf) | AF19: Alabama Dry Natural Gas Production (Million Cubic Feet) | AG19: %NGL | AH19: Arizona Natural Gas Marketed Production (MMcf) | AI19: Arizona Natural Gas Plant Liquids Production, Gaseous Equivalent (MMcf) | AJ19: Arizona Dry Natural Gas Production (Million Cubic Feet) | AK19: %NGL | AL19: Arkansas Natural Gas Marketed Production (MMcf) | AM19: Arkansas Natural Gas Plant Liquids Production, Gaseous Equivalent (MMcf) | AN19: Arkansas Dry Natural Gas Production (Million Cubic Feet) | AO19: %NGL | AP19: California Natural Gas Marketed Production (MMcf) | AQ19: California Natural Gas Plant Liquids Production, Gaseous Equivalent (MMcf) | AR19: California Dry Natural Gas Production (Million Cubic Feet) | AS19: %NGL | AT19: Colorado Natural Gas Marketed Production (MMcf) | AU19: Colorado Natural Gas Plant Liquids Production, Gaseous Equivalent (MMcf) | AV19: Colorado Dry Natural Gas Production (Million Cubic Feet) | AW19: %NGL | AX19: Florida Natural Gas Marketed Production (MMcf) | AY19: Florida Natural Gas Plant Liquids Production, Gaseous Equivalent (MMcf) | AZ19: Florida Dry Natural Gas Production (Million Cubic Feet) | BA19: %NGL | BB19: Illinois Natural Gas Marketed Production (MMcf) | BC19: Illinois Natural Gas Plant Liquids Production, Gaseous Equivalent (MMcf) | BD19: Illinois Dry Natural Gas Production (Million Cubic Feet) | BE19: %NGL | BF19: Indiana Natural Gas Marketed Production (MMcf) | BG19: Indiana Natural Gas Plant Liquids Production, Gaseous Equivalent (MMcf) | BH19: Indiana Dry Natural Gas Production (Million Cubic Feet) | BI19: %NGL | BJ19: Kansas Natural Gas Marketed Production (MMcf) | BK19: Kansas Natural Gas Plant Liquids Production, Gaseous Equivalent (MMcf) | BL19: Kansas Dry Natural Gas Production (Million Cubic Feet) | BM19: %NGL | BN19: Kentucky Natural Gas Marketed Production (MMcf) | BO19: Kentucky Natural Gas Plant Liquids Production, Gaseous Equivalent (MMcf) | BP19: Kentucky Dry Natural Gas Production (Million Cubic Feet) | BQ19: %NGL | BR19: Maryland Natural Gas Marketed Production (MMcf) | BS19: Maryland Natural Gas Plant Liquids Production, Gaseous Equivalent (MMcf) | BT19: Maryland Dry Natural Gas Production (Million Cubic Feet) | BU19: %NGL | BV19: Michigan Natural Gas Marketed Production (MMcf) | BW19: Michigan Natural Gas Plant Liquids Production, Gaseous Equivalent (MMcf) | BX19: Michigan Dry Natural Gas Production (Million Cubic Feet) | BY19: %NGL | BZ19: Mississippi Natural Gas Marketed Production (MMcf) | CA19: Mississippi Natural Gas Plant Liquids Production, Gaseous Equivalent (MMcf) | CB19: Mississippi Dry Natural Gas Production (Million Cubic Feet) | CC19: %NGL | CD19: Montana Natural Gas Marketed Production (MMcf) | CE19: Montana Natural Gas Plant Liquids Production, Gaseous Equivalent (MMcf) | CF19: Montana Dry Natural Gas Production (Million Cubic Feet) | CG19: %NGL | CH19: Nebraska Natural Gas Marketed Production (MMcf) | CI19: Nebraska Natural Gas Plant Liquids Production, Gaseous Equivalent (MMcf) | CJ19: Nebraska Dry Natural Gas Production (Million Cubic Feet) | CK19: %NGL | CL19: Nevada Natural Gas Marketed Production (MMcf) | CM19: Nevada Natural Gas Plant Liquids Production, Gaseous Equivalent (MMcf) | CN19: Nevada Dry Natural Gas Production (Million Cubic Feet) | CO19: %NGL | CP19: New York Natural Gas Marketed Production (MMcf) | CQ19: New York Natural Gas Plant Liquids Production, Gaseous Equivalent (MMcf) | CR19: New York Dry Natural Gas Production (Million Cubic Feet) | CS19: %NGL | CT19: North Dakota Natural Gas Marketed Production (MMcf) | CU19: North Dakota Natural Gas Plant Liquids Production, Gaseous Equivalent (MMcf) | CV19: North Dakota Dry Natural Gas Production (Million Cubic Feet) | CW19: %NGL | CX19: Ohio Natural Gas Marketed Production (MMcf) | CY19: Ohio Natural Gas Plant Liquids Production, Gaseous Equivalent (MMcf) | CZ19: Ohio Dry Natural Gas Production (Million Cubic Feet) | DA19: %NGL | DB19: Oregon Natural Gas Marketed Production (MMcf) | DC19: Oregon Natural Gas Plant Liquids Production, Gaseous Equivalent (MMcf) | DD19: Oregon Dry Natural Gas Production (Million Cubic Feet) | DE19: %NGL | DF19: Pennsylvania Natural Gas Marketed Production (MMcf) | DG19: Pennsylvania Natural Gas Plant Liquids Production, Gaseous Equivalent (MMcf) | DH19: Pennsylvania Dry Natural Gas Production (Million Cubic Feet) | DI19: %NGL | DJ19: South Dakota Natural Gas Marketed Production (MMcf) | DK19: South Dakota Natural Gas Plant Liquids Production, Gaseous Equivalent (MMcf) | DL19: South Dakota Dry Natural Gas Production (Million Cubic Feet) | DM19: %NGL | DN19: Tennessee Natural Gas Marketed Production (MMcf) | DO19: Tennessee Natural Gas Plant Liquids Production, Gaseous Equivalent (Million Cubic Feet) | DP19: Tennessee Dry Natural Gas Production (Million Cubic Feet) | DQ19: %NGL | DR19: Utah Natural Gas Marketed Production (MMcf) | DS19: Utah Natural Gas Plant Liquids Production, Gaseous Equivalent (MMcf) | DT19: Utah Dry Natural Gas Production (Million Cubic Feet) | DU19: %NGL | DV19: Virginia Natural Gas Marketed Production (MMcf) | DW19: Virginia Natural Gas Plant Liquids Production, Gaseous Equivalent (MMcf) | DX19: Virginia Dry Natural Gas Production (Million Cubic Feet) | DY19: %NGL | DZ19: West Virginia Natural Gas Marketed Production (MMcf) | EA19: West Virginia Natural Gas Plant Liquids Production, Gaseous Equivalent (MMcf) | EB19: West Virginia Dry Natural Gas Production (Million Cubic Feet) | EC19: %NGL | EF19: U.S. Natural Gas Marketed Production (MMcf) | EG19: U.S. Natural Gas Plant Liquids Production, Gaseous Equivalent (MMcf) | EH19: U.S. Dry Natural Gas Production (MMcf) | EI19: %NGL
A20: 37802 | B20: 489757 | C20: 33316 | D20: 456441 | E20: =C20/B20 -> 0.068025572 | F20: 4406450 | H20: 4406450 | I20: =G20/F20 -> 0 | J20: 1350399 | K20: 124955 | L20: 1225444 | M20: =K20/J20 -> 0.092531911 | N20: 1604015 | O20: 111292 | P20: 1492723 | Q20: =O20/N20 -> 0.069383391 | R20: 1558155 | S20: 74745 | T20: 1483410 | U20: =S20/R20 -> 0.047970196 | V20: 5243567 | W20: 332405 | X20: 4911162 | Y20: =W20/V20 -> 0.063392916 | Z20: 1539318 | AA20: 69817 | AB20: 1469501 | AC20: =AA20/Z20 -> 0.0453558 | AD20: 346145 | AE20: 11293 | AF20: 334852 | AG20: =AE20/AD20 -> 0.032625056 | AH20: 443 | AI20: 0 | AJ20: 443 | AK20: =AI20/AH20 -> 0 | AL20: 169599 | AM20: 320 | AN20: 169279 | AO20: =AM20/AL20 -> 0.0018868036 | AP20: 337216 | AQ20: 13971 | AR20: 323245 | AS20: =AQ20/AP20 -> 0.041430418 | AT20: 1011285 | AU20: 33650 | AV20: 977635 | AW20: =AU20/AT20 -> 0.033274497 | AX20: 3087 | AY20: 771 | AZ20: 2316 | BA20: =AY20/AX20 -> 0.24975705 | BB20: 174 | BC20: 48 | BD20: 126 | BE20: =BC20/BB20 -> 0.27586207 | BF20: 1464 | BG20: 0 | BH20: 1464 | BI20: =BG20/BF20 -> 0 | BJ20: 418893 | BK20: 34724 | BL20: 384169 | BM20: =BK20/BJ20 -> 0.082894677 | BN20: 87608 | BO20: 1463 | BP20: 86145 | BQ20: =BO20/BN20 -> 0.016699388 | BR20: 48 | BT20: 48 | BU20: =BS20/BR20 -> 0 | BV20: 236987 | BW20: 3838 | BX20: 233149 | BY20: =BW20/BV20 -> 0.016194981 | BZ20: 133901 | CA20: 11430 | CB20: 122471 | CC20: =CA20/BZ20 -> 0.085361573 | CD20: 86027 | CE20: 615 | CF20: 85412 | CG20: =CE20/CD20 -> 0.0071489184 | CH20: 1454 | CI20: 0 | CJ20: 1454 | CK20: =CI20/CH20 -> 0 | CL20: 6 | CN20: 6 | CO20: =CM20/CL20 -> 0 | CP20: 36137 | CR20: 36137 | CS20: =CQ20/CP20 -> 0 | CT20: 55693 | CU20: 5818 | CV20: 49875 | CW20: =CU20/CT20 -> 0.10446555 | CX20: 93641 | CY20: 68 | CZ20: 93573 | DA20: =CY20/CX20 -> 0.00072617764 | DB20: 731 | DD20: 731 | DE20: =DC20/DB20 -> 0 | DF20: 159827 | DG20: 647 | DH20: 159180 | DI20: =DG20/DF20 -> 0.004048127 | DJ20: 1103 | DK20: 0 | DL20: 1103 | DM20: =DK20/DJ20 -> 0 | DN20: 1803 | DP20: 1803 | DQ20: =DO20/DN20 -> 0 | DR20: 268058 | DS20: 3404 | DT20: 264654 | DU20: =DS20/DR20 -> 0.012698744 | DV20: 143644 | DX20: 143644 | DY20: =DW20/DV20 -> 0 | DZ20: 187723 | EA20: 7226 | EB20: 180497 | EC20: =EA20/DZ20 -> 0.038492886 | ED20: =B20+F20+J20+N20+R20+V20+Z20+AD20+AH20+AL20+AP20+AT20+AX20+BB20+BF20+BJ20+BN20+BR20+BV20+BZ20+CD20+CH20+CL20+CP20+CT20+CX20+DB20+DF20+DJ20+DN20+DR20+DV20+DZ20 -> 19974358 | EE20: =ED20-EF20 -> -2 | EF20: 19974360 | EG20: 875816 | EH20: 19098544 | EI20: =EG20/EF20 -> 0.043847012
A21: 38168 | B21: 471899 | C21: 33044 | D21: 438855 | E21: =C21/B21 -> 0.070023458 | F21: 3969450 | H21: 3969450 | I21: =G21/F21 -> 0 | J21: 1353249 | K21: 133434 | L21: 1219815 | M21: =K21/J21 -> 0.098602696 | N21: 1632539 | O21: 105412 | P21: 1527127 | Q21: =O21/N21 -> 0.064569361 | R21: 1655769 | S21: 84355 | T21: 1571414 | U21: =S21/R21 -> 0.050946116 | V21: 5067315 | W21: 360110 | X21: 4707205 | Y21: =W21/V21 -> 0.071065249 | Z21: 1592203 | AA21: 70831 | AB21: 1521372 | AC21: =AA21/Z21 -> 0.044486162 | AD21: 316021 | AE21: 15133 | AF21: 300888 | AG21: =AE21/AD21 -> 0.047886058 | AH21: 331 | AI21: 0 | AJ21: 331 | AK21: =AI21/AH21 -> 0 | AL21: 187069 | AM21: 254 | AN21: 186815 | AO21: =AM21/AL21 -> 0.0013577878 | AP21: 319919 | AQ21: 14061 | AR21: 305858 | AS21: =AQ21/AP21 -> 0.04395175 | AT21: 1079235 | AU21: 35821 | AV21: 1043414 | AW21: =AU21/AT21 -> 0.033191103 | AX21: 3123 | AY21: 618 | AZ21: 2505 | BA21: =AY21/AX21 -> 0.19788665 | BB21: 170 | BC21: 49 | BD21: 121 | BE21: =BC21/BB21 -> 0.28823529 | BF21: 3401 | BG21: 0 | BH21: 3401 | BI21: =BG21/BF21 -> 0 | BJ21: 397121 | BK21: 34573 | BL21: 362548 | BM21: =BK21/BJ21 -> 0.087059108 | BN21: 94259 | BO21: 2413 | BP21: 91846 | BQ21: =BO21/BN21 -> 0.025599677 | BR21: 34 | BT21: 34 | BU21: =BS21/BR21 -> 0 | BV21: 259681 | BW21: 4199 | BX21: 255482 | BY21: =BW21/BV21 -> 0.016169839 | BZ21: 63353 | CA21: 13697 | CB21: 49656 | CC21: =CA21/BZ21 -> 0.21620128 | CD21: 96762 | CE21: 634 | CF21: 96128 | CG21: =CE21/CD21 -> 0.0065521589 | CH21: 1476 | CI21: 0 | CJ21: 1476 | CK21: =CI21/CH21 -> 0 | CL21: 5 | CN21: 5 | CO21: =CM21/CL21 -> 0 | CP21: 46050 | CR21: 46050 | CS21: =CQ21/CP21 -> 0 | CT21: 55009 | CU21: 6233 | CV21: 48776 | CW21: =CU21/CT21 -> 0.11330873 | CX21: 90476 | CY21: 58 | CZ21: 90418 | DA21: =CY21/CX21 -> 0.00064105398 | DB21: 467 | DD21: 467 | DE21: =DC21/DB21 -> 0 | DF21: 197217 | DG21: 634 | DH21: 196583 | DI21: =DG21/DF21 -> 0.003214733 | DJ21: 1093 | DK21: 0 | DL21: 1093 | DM21: =DK21/DJ21 -> 0 | DN21: 2100 | DP21: 2100 | DQ21: =DO21/DN21 -> 0 | DR21: 277969 | DS21: 3381 | DT21: 274588 | DU21: =DS21/DR21 -> 0.012163227 | DV21: 85508 | DX21: 85508 | DY21: =DW21/DV21 -> 0 | DZ21: 197217 | EA21: 7656 | EB21: 189561 | EC21: =EA21/DZ21 -> 0.038820183 | ED21: =B21+F21+J21+N21+R21+V21+Z21+AD21+AH21+AL21+AP21+AT21+AX21+BB21+BF21+BJ21+BN21+BR21+BV21+BZ21+CD21+CH21+CL21+CP21+CT21+CX21+DB21+DF21+DJ21+DN21+DR21+DV21+DZ21 -> 19517490 | EE21: =ED21-EF21 -> -1 | EF21: 19517491 | EG21: 926600 | EH21: 18590891 | EI21: =EG21/EF21 -> 0.047475365
A22: 38533 | B22: 487282 | C22: 27956 | D22: 459326 | E22: =C22/B22 -> 0.057371296 | F22: 3132089 | H22: 3132089 | I22: =G22/F22 -> 0 | J22: 1296048 | K22: 103381 | L22: 1192667 | M22: =K22/J22 -> 0.079766336 | N22: 1645166 | O22: 101064 | P22: 1544102 | Q22: =O22/N22 -> 0.061430883 | R22: 1639310 | S22: 87404 | T22: 1551906 | U22: =S22/R22 -> 0.053317554 | V22: 5276401 | W22: 355589 | X22: 4920812 | Y22: =W22/V22 -> 0.067392338 | Z22: 1639317 | AA22: 67563 | AB22: 1571754 | AC22: =AA22/Z22 -> 0.041214115 | AD22: 296528 | AE22: 13759 | AF22: 282769 | AG22: =AE22/AD22 -> 0.04640034 | AH22: 233 | AI22: 0 | AJ22: 233 | AK22: =AI22/AH22 -> 0 | AL22: 190533 | AM22: 231 | AN22: 190302 | AO22: =AM22/AL22 -> 0.0012123884 | AP22: 317637 | AQ22: 13748 | AR22: 303889 | AS22: =AQ22/AP22 -> 0.043282111 | AT22: 1133086 | AU22: 34782 | AV22: 1098304 | AW22: =AU22/AT22 -> 0.030696699 | AX22: 2616 | AY22: 495 | AZ22: 2121 | BA22: =AY22/AX22 -> 0.18922018 | BB22: 166 | BC22: 46 | BD22: 120 | BE22: =BC22/BB22 -> 0.27710843 | BF22: 3135 | BG22: 0 | BH22: 3135 | BI22: =BG22/BF22 -> 0 | BJ22: 377229 | BK22: 31521 | BL22: 345708 | BM22: =BK22/BJ22 -> 0.083559323 | BN22: 92795 | BO22: 1716 | BP22: 91079 | BQ22: =BO22/BN22 -> 0.018492376 | BR22: 46 | BT22: 46 | BU22: =BS22/BR22 -> 0 | BV22: 261112 | BW22: 3708 | BX22: 257404 | BY22: =BW22/BV22 -> 0.014200803 | BZ22: 52923 | CA22: 14308 | CB22: 38615 | CC22: =CA22/BZ22 -> 0.27035504 | CD22: 107918 | CE22: 1149 | CF22: 106769 | CG22: =CE22/CD22 -> 0.010646973 | CH22: 1172 | CI22: 0 | CJ22: 1172 | CK22: =CI22/CH22 -> 0 | CL22: 5 | CN22: 5 | CO22: =CM22/CL22 -> 0 | CP22: 55180 | CR22: 55180 | CS22: =CQ22/CP22 -> 0 | CT22: 52557 | CU22: 6858 | CV22: 45699 | CW22: =CU22/CT22 -> 0.1304869 | CX22: 83523 | CY22: 29 | CZ22: 83494 | DA22: =CY22/CX22 -> 0.00034720975 | DB22: 454 | DD22: 454 | DE22: =DC22/DB22 -> 0 | DF22: 168501 | DG22: 700 | DH22: 167801 | DI22: =DG22/DF22 -> 0.004154278 | DJ22: 992 | DK22: 0 | DL22: 992 | DM22: =DK22/DJ22 -> 0 | DN22: 2200 | DP22: 2200 | DQ22: =DO22/DN22 -> 0 | DR22: 301223 | DS22: 2815 | DT22: 298408 | DU22: =DS22/DR22 -> 0.0093452359 | DV22: 88610 | DX22: 88610 | DY22: =DW22/DV22 -> 0 | DZ22: 221108 | EA22: 7675 | EB22: 213433 | EC22: =EA22/DZ22 -> 0.034711544 | ED22: =B22+F22+J22+N22+R22+V22+Z22+AD22+AH22+AL22+AP22+AT22+AX22+BB22+BF22+BJ22+BN22+BR22+BV22+BZ22+CD22+CH22+CL22+CP22+CT22+CX22+DB22+DF22+DJ22+DN22+DR22+DV22+DZ22 -> 18927095 | EE22: =ED22-EF22 -> 0 | EF22: 18927095 | EG22: 876497 | EH22: 18050598 | EI22: =EG22/EF22 -> 0.046309114
A23: 38898 | B23: 444724 | C23: 24638 | D23: 420086 | E23: =C23/B23 -> 0.055400653 | F23: 2901969 | H23: 2901969 | I23: =G23/F23 -> 0 | J23: 1361119 | K23: 105236 | L23: 1255883 | M23: =K23/J23 -> 0.077315797 | N23: 1609223 | O23: 99971 | P23: 1509252 | Q23: =O23/N23 -> 0.06212377 | R23: 1688985 | S23: 91937 | T23: 1597048 | U23: =S23/R23 -> 0.054433284 | V23: 5548022 | W23: 373350 | X23: 5174672 | Y23: =W23/V23 -> 0.067294254 | Z23: 1816201 | AA23: 67435 | AB23: 1748766 | AC23: =AA23/Z23 -> 0.037129701 | AD23: 286220 | AE23: 21065 | AF23: 265155 | AG23: =AE23/AD23 -> 0.073597233 | AH23: 611 | AI23: 0 | AJ23: 611 | AK23: =AI23/AH23 -> 0 | AL23: 270293 | AM23: 212 | AN23: 270081 | AO23: =AM23/AL23 -> 0.00078433404 | AP23: 315209 | AQ23: 14056 | AR23: 301153 | AS23: =AQ23/AP23 -> 0.044592635 | AT23: 1202821 | AU23: 36317 | AV23: 1166504 | AW23: =AU23/AT23 -> 0.030193188 | AX23: 2540 | AY23: 485 | AZ23: 2055 | BA23: =AY23/AX23 -> 0.19094488 | BB23: 170 | BC23: 47 | BD23: 123 | BE23: =BC23/BB23 -> 0.27647059 | BF23: 2921 | BG23: 0 | BH23: 2921 | BI23: =BG23/BF23 -> 0 | BJ23: 371044 | BK23: 30726 | BL23: 340318 | BM23: =BK23/BJ23 -> 0.082809586 | BN23: 95320 | BO23: 2252 | BP23: 93068 | BQ23: =BO23/BN23 -> 0.023625682 | BR23: 48 | BT23: 48 | BU23: =BS23/BR23 -> 0 | BV23: 263009 | BW23: 3277 | BX23: 259732 | BY23: =BW23/BV23 -> 0.01245965 | BZ23: 60531 | CA23: 14662 | CB23: 45869 | CC23: =CA23/BZ23 -> 0.24222299 | CD23: 112845 | CE23: 1422 | CF23: 111423 | CG23: =CE23/CD23 -> 0.012601356 | CH23: 1200 | CI23: 0 | CJ23: 1200 | CK23: =CI23/CH23 -> 0 | CL23: 5 | CN23: 5 | CO23: =CM23/CL23 -> 0 | CP23: 55980 | CR23: 55980 | CS23: =CQ23/CP23 -> 0 | CT23: 55273 | CU23: 7254 | CV23: 48019 | CW23: =CU23/CT23 -> 0.13123948 | CX23: 86315 | CY23: 5 | CZ23: 86310 | DA23: =CY23/CX23 -> 5.7927359e-05 | DB23: 621 | DD23: 621 | DE23: =DC23/DB23 -> 0 | DF23: 175950 | DG23: 794 | DH23: 175156 | DI23: =DG23/DF23 -> 0.0045126456 | DJ23: 963 | DK23: 0 | DL23: 963 | DM23: =DK23/DJ23 -> 0 | DN23: 2663 | DP23: 2663 | DQ23: =DO23/DN23 -> 0 | DR23: 348320 | DS23: 2911 | DT23: 345409 | DU23: =DS23/DR23 -> 0.0083572577 | DV23: 103027 | DX23: 103027 | DY23: =DW23/DV23 -> 0 | DZ23: 225530 | EA23: 8017 | EB23: 217513 | EC23: =EA23/DZ23 -> 0.035547377 | ED23: =B23+F23+J23+N23+R23+V23+Z23+AD23+AH23+AL23+AP23+AT23+AX23+BB23+BF23+BJ23+BN23+BR23+BV23+BZ23+CD23+CH23+CL23+CP23+CT23+CX23+DB23+DF23+DJ23+DN23+DR23+DV23+DZ23 -> 19409672 | EE23: =ED23-EF23 -> -2 | EF23: 19409674 | EG23: 906069 | EH23: 18503605 | EI23: =EG23/EF23 -> 0.04668131
A24: 39263 | B24: 433485 | C24: 26332 | D24: 407153 | E24: =C24/B24 -> 0.060744893 | F24: 2798718 | G24: 0 | H24: 2798718 | I24: =G24/F24 -> 0 | J24: 1365333 | K24: 110745 | L24: 1254588 | M24: =K24/J24 -> 0.08111208 | N24: 1517922 | O24: 96250 | P24: 1421672 | Q24: =O24/N24 -> 0.063409055 | R24: 1783682 | S24: 96643 | T24: 1687039 | U24: =S24/R24 -> 0.054181743 | V24: 6123180 | W24: 387349 | X24: 5735831 | Y24: =W24/V24 -> 0.06325945 | Z24: 2047882 | AA24: 74234 | AB24: 1973648 | AC24: =AA24/Z24 -> 0.036249159 | AD24: 270407 | AE24: 19831 | AF24: 250576 | AG24: =AE24/AD24 -> 0.073337599 | AH24: 655 | AI24: 0 | AJ24: 655 | AK24: =AI24/AH24 -> 0 | AL24: 269886 | AM24: 162 | AN24: 269724 | AO24: =AM24/AL24 -> 0.00060025344 | AP24: 307160 | AQ24: 13521 | AR24: 293639 | AS24: =AQ24/AP24 -> 0.044019404 | AT24: 1242571 | AU24: 38180 | AV24: 1204391 | AW24: =AU24/AT24 -> 0.030726614 | AX24: 1778 | AY24: 132 | AZ24: 1646 | BA24: =AY24/AX24 -> 0.07424072 | BB24: 1394 | BC24: 48 | BD24: 1346 | BE24: =BC24/BB24 -> 0.034433286 | BF24: 3606 | BG24: 0 | BH24: 3606 | BI24: =BG24/BF24 -> 0 | BJ24: 365877 | BK24: 28063 | BL24: 337814 | BM24: =BK24/BJ24 -> 0.07670064 | BN24: 95437 | BO24: 1957 | BP24: 93480 | BQ24: =BO24/BN24 -> 0.020505674 | BR24: 35 | BT24: 35 | BU24: =BS24/BR24 -> 0 | BV24: 264907 | BW24: 3094 | BX24: 261813 | BY24: =BW24/BV24 -> 0.011679571 | BZ24: 73460 | CA24: 13097 | CB24: 60363 | CC24: =CA24/BZ24 -> 0.1782875 | CD24: 116848 | CE24: 1576 | CF24: 115272 | CG24: =CE24/CD24 -> 0.013487608 | CH24: 1555 | CI24: 0 | CJ24: 1555 | CK24: =CI24/CH24 -> 0 | CL24: 5 | CN24: 5 | CO24: =CM24/CL24 -> 0 | CP24: 54942 | CR24: 54942 | CS24: =CQ24/CP24 -> 0 | CT24: 60255 | CU24: 7438 | CV24: 52817 | CW24: =CU24/CT24 -> 0.12344204 | CX24: 88095 | CY24: 9 | CZ24: 88086 | DA24: =CY24/CX24 -> 0.00010216244 | DB24: 409 | DD24: 409 | DE24: =DC24/DB24 -> 0 | DF24: 182277 | DG24: 859 | DH24: 181418 | DI24: =DG24/DF24 -> 0.0047126077 | DJ24: 995 | DK24: 0 | DL24: 995 | DM24: =DK24/DJ24 -> 0 | DN24: 3942 | DO24: 0 | DP24: 3942 | DQ24: =DO24/DN24 -> 0 | DR24: 376409 | DS24: 2729 | DT24: 373680 | DU24: =DS24/DR24 -> 0.0072500923 | DV24: 112057 | DX24: 112057 | DY24: =DW24/DV24 -> 0 | DZ24: 231184 | EA24: 8071 | EB24: 223113 | EC24: =EA24/DZ24 -> 0.034911586 | ED24: =B24+F24+J24+N24+R24+V24+Z24+AD24+AH24+AL24+AP24+AT24+AX24+BB24+BF24+BJ24+BN24+BR24+BV24+BZ24+CD24+CH24+CL24+CP24+CT24+CX24+DB24+DF24+DJ24+DN24+DR24+DV24+DZ24 -> 20196348 | EE24: =ED24-EF24 -> 2 | EF24: 20196346 | EG24: 930320 | EH24: 19266026 | EI24: =EG24/EF24 -> 0.046063778
A25: 39629 | B25: 398442 | C25: 24337 | D25: 374105 | E25: =C25/B25 -> 0.061080408 | F25: 2314342 | G25: 0 | H25: 2314342 | I25: =G25/F25 -> 0 | J25: 1377969 | K25: 94785 | L25: 1283184 | M25: =K25/J25 -> 0.068786018 | N25: 1446204 | O25: 92579 | P25: 1353625 | Q25: =O25/N25 -> 0.064015174 | R25: 1886710 | S25: 104689 | T25: 1782021 | U25: =S25/R25 -> 0.055487595 | V25: 6960693 | W25: 401503 | X25: 6559190 | Y25: =W25/V25 -> 0.057681469 | Z25: 2274850 | AA25: 82922 | AB25: 2191928 | AC25: =AA25/Z25 -> 0.036451634 | AD25: 257884 | AE25: 17222 | AF25: 240662 | AG25: =AE25/AD25 -> 0.066781964 | AH25: 523 | AI25: 0 | AJ25: 523 | AK25: =AI25/AH25 -> 0 | AL25: 446457 | AM25: 139 | AN25: 446318 | AO25: =AM25/AL25 -> 0.00031134017 | AP25: 296469 | AQ25: 13972 | AR25: 282497 | AS25: =AQ25/AP25 -> 0.04712803 | AT25: 1389399 | AU25: 53590 | AV25: 1335809 | AW25: =AU25/AT25 -> 0.038570634 | AX25: 2436 | AY25: 22 | AZ25: 2414 | BA25: =AY25/AX25 -> 0.0090311987 | BB25: 1193 | BC25: 42 | BD25: 1151 | BE25: =BC25/BB25 -> 0.035205365 | BF25: 4701 | BG25: 0 | BH25: 4701 | BI25: =BG25/BF25 -> 0 | BJ25: 374310 | BK25: 28302 | BL25: 346008 | BM25: =BK25/BJ25 -> 0.075611124 | BN25: 114116 | BO25: 2401 | BP25: 111715 | BQ25: =BO25/BN25 -> 0.021039994 | BR25: 28 | BT25: 28 | BU25: =BS25/BR25 -> 0 | BV25: 153130 | BW25: 3921 | BX25: 149209 | BY25: =BW25/BV25 -> 0.025605695 | BZ25: 96641 | CA25: 10846 | CB25: 85795 | CC25: =CA25/BZ25 -> 0.1122298 | CD25: 112529 | CE25: 1622 | CF25: 110907 | CG25: =CE25/CD25 -> 0.014414062 | CH25: 3082 | CI25: 0 | CJ25: 3082 | CK25: =CI25/CH25 -> 0 | CL25: 4 | CN25: 4 | CO25: =CM25/CL25 -> 0 | CP25: 50320 | CR25: 50320 | CS25: =CQ25/CP25 -> 0 | CT25: 52444 | CU25: 7878 | CV25: 44566 | CW25: =CU25/CT25 -> 0.15021737 | CX25: 84858 | CY25: 0 | CZ25: 84858 | DA25: =CY25/CX25 -> 0 | DB25: 778 | DD25: 778 | DE25: =DC25/DB25 -> 0 | DF25: 198295 | DG25: 1008 | DH25: 197287 | DI25: =DG25/DF25 -> 0.0050833354 | DJ25: 1644 | DK25: 0 | DL25: 1644 | DM25: =DK25/DJ25 -> 0 | DN25: 4700 | DO25: 0 | DP25: 4700 | DQ25: =DO25/DN25 -> 0 | DR25: 433566 | DS25: 3280 | DT25: 430286 | DU25: =DS25/DR25 -> 0.0075651689 | DV25: 128454 | DX25: 128454 | DY25: =DW25/DV25 -> 0 | DZ25: 244880 | EA25: 8391 | EB25: 236489 | EC25: =EA25/DZ25 -> 0.034265763 | ED25: =B25+F25+J25+N25+R25+V25+Z25+AD25+AH25+AL25+AP25+AT25+AX25+BB25+BF25+BJ25+BN25+BR25+BV25+BZ25+CD25+CH25+CL25+CP25+CT25+CX25+DB25+DF25+DJ25+DN25+DR25+DV25+DZ25 -> 21112051 | EE25: =ED25-EF25 -> -2 | EF25: 21112053 | EG25: 953451 | EH25: 20158602 | EI25: =EG25/EF25 -> 0.045161454
A26: 39994 | B26: 397077 | C26: 22925 | D26: 374152 | E26: =C26/B26 -> 0.057734394 | F26: 2428916 | G26: 0 | H26: 2428916 | I26: =G26/F26 -> 0 | J26: 1548607 | K26: 95359 | L26: 1453248 | M26: =K26/J26 -> 0.061577276 | N26: 1383004 | O26: 94840 | P26: 1288164 | Q26: =O26/N26 -> 0.068575362 | R26: 1901556 | S26: 112891 | T26: 1788665 | U26: =S26/R26 -> 0.059367697 | V26: 6818973 | W26: 424042 | X26: 6394931 | Y26: =W26/V26 -> 0.062185611 | Z26: 2335328 | AA26: 93796 | AB26: 2241532 | AC26: =AA26/Z26 -> 0.040163951 | AD26: 236029 | AE26: 17232 | AF26: 218797 | AG26: =AE26/AD26 -> 0.073007978 | AH26: 712 | AI26: 0 | AJ26: 712 | AK26: =AI26/AH26 -> 0 | AL26: 679952 | AM26: 168 | AN26: 679784 | AO26: =AM26/AL26 -> 0.00024707626 | AP26: 276575 | AQ26: 13722 | AR26: 262853 | AS26: =AQ26/AP26 -> 0.049614029 | AT26: 1499070 | AU26: 67607 | AV26: 1431463 | AW26: =AU26/AT26 -> 0.045099295 | AX26: 257 | AY26: 0 | AZ26: 257 | BA26: =AY26/AX26 -> 0 | BB26: 1443 | BC26: 31 | BD26: 1412 | BE26: =BC26/BB26 -> 0.021483021 | BF26: 4927 | BG26: 0 | BH26: 4927 | BI26: =BG26/BF26 -> 0 | BJ26: 354440 | BK26: 26948 | BL26: 327492 | BM26: =BK26/BJ26 -> 0.076029793 | BN26: 113300 | BO26: 3270 | BP26: 110030 | BQ26: =BO26/BN26 -> 0.02886143 | BR26: 43 | BT26: 43 | BU26: =BS26/BR26 -> 0 | BV26: 153736 | BW26: 2334 | BX26: 151402 | BY26: =BW26/BV26 -> 0.01518187 | BZ26: 88157 | CA26: 18354 | CB26: 69803 | CC26: =CA26/BZ26 -> 0.20819674 | CD26: 98245 | CE26: 1853 | CF26: 96392 | CG26: =CE26/CD26 -> 0.018861011 | CH26: 2908 | CI26: 0 | CJ26: 2908 | CK26: =CI26/CH26 -> 0 | CL26: 4 | CN26: 4 | CO26: =CM26/CL26 -> 0 | CP26: 44849 | CR26: 44849 | CS26: =CQ26/CP26 -> 0 | CT26: 59369 | CU26: 10140 | CV26: 49229 | CW26: =CU26/CT26 -> 0.17079621 | CX26: 88824 | CY26: 0 | CZ26: 88824 | DA26: =CY26/CX26 -> 0 | DB26: 821 | DD26: 821 | DE26: =DC26/DB26 -> 0 | DF26: 273869 | DG26: 1295 | DH26: 272574 | DI26: =DG26/DF26 -> 0.0047285381 | DJ26: 2129 | DK26: 0 | DL26: 2129 | DM26: =DK26/DJ26 -> 0 | DN26: 5478 | DO26: 0 | DP26: 5478 | DQ26: =DO26/DN26 -> 0 | DR26: 444162 | DS26: 8489 | DT26: 435673 | DU26: =DS26/DR26 -> 0.019112396 | DV26: 140738 | DX26: 140738 | DY26: =DW26/DV26 -> 0 | DZ26: 264436 | EA26: 8786 | EB26: 255650 | EC26: =EA26/DZ26 -> 0.033225431 | ED26: =B26+F26+J26+N26+R26+V26+Z26+AD26+AH26+AL26+AP26+AT26+AX26+BB26+BF26+BJ26+BN26+BR26+BV26+BZ26+CD26+CH26+CL26+CP26+CT26+CX26+DB26+DF26+DJ26+DN26+DR26+DV26+DZ26 -> 21647934 | EE26: =ED26-EF26 -> -2 | EF26: 21647936 | EG26: 1024082 | EH26: 20623854 | EI26: =EG26/EF26 -> 0.047306219
A27: 40359 | B27: 374226 | C27: 20835 | D27: 353391 | E27: =C27/B27 -> 0.055674913 | F27: 2245062 | G27: 0 | H27: 2245062 | I27: =G27/F27 -> 0 | J27: 2210099 | K27: 102448 | L27: 2107651 | M27: =K27/J27 -> 0.046354485 | N27: 1292185 | O27: 91963 | P27: 1200222 | Q27: =O27/N27 -> 0.071168602 | R27: 1827328 | S27: 120631 | T27: 1706697 | U27: =S27/R27 -> 0.066014968 | V27: 6715294 | W27: 433622 | X27: 6281672 | Y27: =W27/V27 -> 0.064572303 | Z27: 2305525 | AA27: 92777 | AB27: 2212748 | AC27: =AA27/Z27 -> 0.04024116 | AD27: 222932 | AE27: 19059 | AF27: 203873 | AG27: =AE27/AD27 -> 0.085492437 | AH27: 183 | AI27: 0 | AJ27: 183 | AK27: =AI27/AH27 -> 0 | AL27: 926639 | AM27: 213 | AN27: 926426 | AO27: =AM27/AL27 -> 0.00022986298 | AP27: 286841 | AQ27: 13244 | AR27: 273597 | AS27: =AQ27/AP27 -> 0.046171921 | AT27: 1578379 | AU27: 82637 | AV27: 1495742 | AW27: =AU27/AT27 -> 0.052355613 | AX27: 12409 | AY27: 0 | AZ27: 12409 | BA27: =AY27/AX27 -> 0 | BB27: 1702 | BC27: 345 | BD27: 1357 | BE27: =BC27/BB27 -> 0.2027027 | BF27: 6802 | BG27: 0 | BH27: 6802 | BI27: =BG27/BF27 -> 0 | BJ27: 324720 | BK27: 26251 | BL27: 298469 | BM27: =BK27/BJ27 -> 0.080841956 | BN27: 135330 | BO27: 4576 | BP27: 130754 | BQ27: =BO27/BN27 -> 0.033813641 | BR27: 43 | BT27: 43 | BU27: =BS27/BR27 -> 0 | BV27: 131118 | BW27: 2943 | BX27: 128175 | BY27: =BW27/BV27 -> 0.022445431 | BZ27: 73721 | CA27: 18405 | CB27: 55316 | CC27: =CA27/BZ27 -> 0.24965749 | CD27: 87539 | CE27: 1367 | CF27: 86172 | CG27: =CE27/CD27 -> 0.015615897 | CH27: 2231 | CI27: 0 | CJ27: 2231 | CK27: =CI27/CH27 -> 0 | CL27: 4 | CN27: 4 | CO27: =CM27/CL27 -> 0 | CP27: 35813 | CR27: 35813 | CS27: =CQ27/CP27 -> 0 | CT27: 81837 | CU27: 11381 | CV27: 70456 | CW27: =CU27/CT27 -> 0.13906913 | CX27: 78122 | CY27: 0 | CZ27: 78122 | DA27: =CY27/CX27 -> 0 | DB27: 1407 | DD27: 1407 | DE27: =DC27/DB27 -> 0 | DF27: 572902 | DG27: 4578 | DH27: 568324 | DI27: =DG27/DF27 -> 0.0079908955 | DJ27: 1862 | DK27: 0 | DL27: 1862 | DM27: =DK27/DJ27 -> 0 | DN27: 5144 | DO27: 506 | DP27: 4638 | DQ27: =DO27/DN27 -> 0.09836703 | DR27: 432045 | DS27: 9978 | DT27: 422067 | DU27: =DS27/DR27 -> 0.023094817 | DV27: 147255 | DX27: 147255 | DY27: =DW27/DV27 -> 0 | DZ27: 265174 | EA27: 8607 | EB27: 256567 | EC27: =EA27/DZ27 -> 0.032457933 | ED27: =B27+F27+J27+N27+R27+V27+Z27+AD27+AH27+AL27+AP27+AT27+AX27+BB27+BF27+BJ27+BN27+BR27+BV27+BZ27+CD27+CH27+CL27+CP27+CT27+CX27+DB27+DF27+DJ27+DN27+DR27+DV27+DZ27 -> 22381873 | EE27: =ED27-EF27 -> 0 | EF27: 22381873 | EG27: 1066366 | EH27: 21315507 | EI27: =EG27/EF27 -> 0.047644181
A28: 40724 | B28: 356225 | C28: 21554 | D28: 334671 | E28: =C28/B28 -> 0.060506702 | F28: 1812328 | G28: 0 | H28: 1812328 | I28: =G28/F28 -> 0 | J28: 3029206 | K28: 95630 | L28: 2933576 | M28: =K28/J28 -> 0.031569329 | N28: 1237303 | O28: 90291 | P28: 1147012 | Q28: =O28/N28 -> 0.072974041 | R28: 1888870 | S28: 134032 | T28: 1754838 | U28: =S28/R28 -> 0.070958827 | V28: 7112863 | W28: 481308 | X28: 6631555 | Y28: =W28/V28 -> 0.067667267 | Z28: 2159422 | AA28: 97588 | AB28: 2061834 | AC28: =AA28/Z28 -> 0.045191723 | AD28: 195581 | AE28: 17271 | AF28: 178310 | AG28: =AE28/AD28 -> 0.088306124 | AH28: 168 | AI28: 0 | AJ28: 168 | AK28: =AI28/AH28 -> 0 | AL28: 1072212 | AM28: 268 | AN28: 1071944 | AO28: =AM28/AL28 -> 0.00024995057 | AP28: 250177 | AQ28: 12095 | AR28: 238082 | AS28: =AQ28/AP28 -> 0.048345771 | AT28: 1637576 | AU28: 90801 | AV28: 1546775 | AW28: =AU28/AT28 -> 0.055448419 | AX28: 15125 | AY28: 0 | AZ28: 15125 | BA28: =AY28/AX28 -> 0 | BB28: 2121 | BC28: 1043 | BD28: 1078 | BE28: =BC28/BB28 -> 0.49174917 | BF28: 9075 | BG28: 0 | BH28: 9075 | BI28: =BG28/BF28 -> 0 | BJ28: 309124 | BK28: 25804 | BL28: 283320 | BM28: =BK28/BJ28 -> 0.083474593 | BN28: 124243 | BO28: 4684 | BP28: 119559 | BQ28: =BO28/BN28 -> 0.037700313 | BR28: 34 | BT28: 34 | BU28: =BS28/BR28 -> 0 | BV28: 138162 | BW28: 2465 | BX28: 135697 | BY28: =BW28/BV28 -> 0.017841375 | BZ28: 81487 | CA28: 11221 | CB28: 70266 | CC28: =CA28/BZ28 -> 0.13770295 | CD28: 74624 | CE28: 1252 | CF28: 73372 | CG28: =CE28/CD28 -> 0.016777444 | CH28: 1959 | CI28: 0 | CJ28: 1959 | CK28: =CI28/CH28 -> 0 | CL28: 3 | CN28: 3 | CO28: =CM28/CL28 -> 0 | CP28: 31124 | CR28: 31124 | CS28: =CQ28/CP28 -> 0 | CT28: 97102 | CU28: 14182 | CV28: 82920 | CW28: =CU28/CT28 -> 0.1460526 | CX28: 78858 | CY28: 0 | CZ28: 78858 | DA28: =CY28/CX28 -> 0 | DB28: 1344 | DD28: 1344 | DE28: =DC28/DB28 -> 0 | DF28: 1310592 | DG28: 8931 | DH28: 1301661 | DI28: =DG28/DF28 -> 0.0068144777 | DJ28: 1848 | DK28: 0 | DL28: 1848 | DM28: =DK28/DJ28 -> 0 | DN28: 4851 | DO28: 516 | DP28: 4335 | DQ28: =DO28/DN28 -> 0.10636982 | DR28: 457525 | DS28: 14910 | DT28: 442615 | DU28: =DS28/DR28 -> 0.032588383 | DV28: 151094 | DX28: 151094 | DY28: =DW28/DV28 -> 0 | DZ28: 394125 | EA28: 8627 | EB28: 385498 | EC28: =EA28/DZ28 -> 0.021888995 | ED28: =B28+F28+J28+N28+R28+V28+Z28+AD28+AH28+AL28+AP28+AT28+AX28+BB28+BF28+BJ28+BN28+BR28+BV28+BZ28+CD28+CH28+CL28+CP28+CT28+CX28+DB28+DF28+DJ28+DN28+DR28+DV28+DZ28 -> 24036351 | EE28: =ED28-EF28 -> -1 | EF28: 24036352 | EG28: 1134473 | EH28: 22901879 | EI28: =EG28/EF28 -> 0.047198219
A29: 41090 | B29: 351259 | C29: 21470 | D29: 329789 | E29: =C29/B29 -> 0.061122989 | F29: 1507564 | H29: 1423239 | I29: =G29/F29 -> 0 | J29: 2955437 | K29: =J29-L29 -> 37312 | L29: 2918125 | M29: =K29/J29 -> 0.012624867 | N29: 1215773 | O29: =N29-P29 -> 84562 | P29: 1131211 | Q29: =O29/N29 -> 0.069554103 | R29: 2023461 | S29: =R29-T29 -> 140257 | T29: 1883204 | U29: =S29/R29 -> 0.069315396 | V29: 7475495 | W29: =V29-X29 -> 580033 | X29: 6895462 | Y29: =W29/V29 -> 0.07759125 | Z29: 2022275 | AA29: =Z29-AB29 -> 102563 | AB29: 1919712 | AC29: =AA29/Z29 -> 0.050716643 | AD29: 215710 | AE29: =AD29-AF29 -> 7110 | AF29: 208600 | AG29: =AE29/AD29 -> 0.03296092 | AH29: 117 | AI29: 0 | AJ29: 117 | AK29: =AI29/AH29 -> 0 | AL29: 1146168 | AM29: 424 | AN29: 1145744 | AO29: =AM29/AL29 -> 0.00036992832 | AP29: 246822 | AQ29: 12755 | AR29: 234067 | AS29: =AQ29/AP29 -> 0.051676917 | AT29: 1709376 | AU29: =AT29-AV29 -> 81943 | AV29: 1627433 | AW29: =AU29/AT29 -> 0.047937376 | AX29: 18681 | AY29: 0 | AZ29: 18681 | BA29: =AY29/AX29 -> 0 | BB29: 2125 | BC29: 0 | BD29: 2125 | BE29: =BC29/BB29 -> 0 | BF29: 8814 | BG29: 0 | BH29: 8814 | BI29: =BG29/BF29 -> 0 | BJ29: 296299 | BK29: =BJ29-BL29 -> 21220 | BL29: 275079 | BM29: =BK29/BJ29 -> 0.071616846 | BN29: 106122 | BO29: =BN29-BP29 -> 6571 | BP29: 99551 | BQ29: =BO29/BN29 -> 0.0619193 | BR29: 44 | BT29: 44 | BU29: =BS29/BR29 -> 0 | BV29: 129333 | BW29: 2480 | BX29: 126853 | BY29: =BW29/BV29 -> 0.019175307 | BZ29: 63843 | CA29: =BZ29-CB29 -> 509 | CB29: 63334 | CC29: =CA29/BZ29 -> 0.007972683 | CD29: 66954 | CE29: =CD29-CF29 -> 1474 | CF29: 65480 | CG29: =CE29/CD29 -> 0.022015115 | CH29: 1328 | CI29: 0 | CJ29: 1328 | CK29: =CI29/CH29 -> 0 | CL29: 4 | CN29: 4 | CO29: =CM29/CL29 -> 0 | CP29: 26424 | CR29: 26424 | CS29: =CQ29/CP29 -> 0 | CT29: 179004 | CU29: =CT29-CV29 -> 26156 | CV29: 152848 | CW29: =CU29/CT29 -> 0.14611964 | CX29: 84482 | CY29: 155 | CZ29: 84327 | DA29: =CY29/CX29 -> 0.0018347104 | DB29: 770 | DD29: 770 | DE29: =DC29/DB29 -> 0 | DF29: 2256696 | DG29: =DF29-DH29 -> 12003 | DH29: 2244693 | DI29: =DG29/DF29 -> 0.0053188378 | DJ29: 15085 | DK29: 6 | DL29: 15079 | DM29: =DK29/DJ29 -> 0.00039774611 | DN29: 5825 | DO29: 501 | DP29: 5324 | DQ29: =DO29/DN29 -> 0.086008584 | DR29: 490393 | DS29: =DR29-DT29 -> 15622 | DT29: 474771 | DU29: =DS29/DR29 -> 0.031856083 | DV29: 146405 | DX29: 146405 | DY29: =DW29/DV29 -> 0 | DZ29: 539860 | EA29: 10887 | EB29: 528973 | EC29: =EA29/DZ29 -> 0.020166339 | ED29: =B29+F29+J29+N29+R29+V29+Z29+AD29+AH29+AL29+AP29+AT29+AX29+BB29+BF29+BJ29+BN29+BR29+BV29+BZ29+CD29+CH29+CL29+CP29+CT29+CX29+DB29+DF29+DJ29+DN29+DR29+DV29+DZ29 -> 25307948 | EE29: =ED29-EF29 -> -1 | EF29: 25307949 | EG29: 1250340 | EH29: 24057609 | EI29: =EG29/EF29 -> 0.049405031
L32: Total NGL
B33: R2 | C33: R3 | D33: R4 | E33: R5 | F33: R6 | G33: R7 | H33: R8 | I33: R9 | J33: Total | M33: R2 | N33: R3 | O33: R4 | P33: R5 | Q33: R6 | R33: R7 | S33: R8 | T33: R9
A34: 37802 | B34: =CP20+DF20 -> 195964 | C34: =BB20+BF20+BV20+CX20 -> 332266 | D34: =BJ20+CH20+CT20+DJ20 -> 477143 | E34: =AX20+BR20+DV20+DZ20 -> 334502 | F34: =AD20+BN20+BZ20+DN20+F20*0.061 -> 838250.45 | G34: =J20+R20+V20+AL20+F20*0.939 -> 12459377 | H34: =N20+Z20+AH20+AT20+CD20+CL20+DR20 -> 4509152 | I34: =B20+AP20+DB20 -> 827704 | J34: =SUM(B34:I34) -> 19974358 | L34: 37802 | M34: =CQ20+DG20 -> 647 | N34: =BC20+BG20+BW20+CY20 -> 3954 | O34: =BK20+CI20+CU20+DK20 -> 40542 | P34: =AY20+BS20+DW20+EA20 -> 7997 | Q34: =AE20+BO20+CA20+DO20 -> 24186 | R34: =K20+S20+W20+AM20 -> 532425 | S34: =O20+AA20+AI20+AU20+CE20+CM20+DS20 -> 218778 | T34: =C20+AQ20+DC20 -> 47287 | U34: =SUM(M34:T34) -> 875816 | V34: =U34-EG20 -> 0
A35: 38168 | B35: =CP21+DF21 -> 243267 | C35: =BB21+BF21+BV21+CX21 -> 353728 | D35: =BJ21+CH21+CT21+DJ21 -> 454699 | E35: =AX21+BR21+DV21+DZ21 -> 285882 | F35: =AD21+BN21+BZ21+DN21+F21*0.061 -> 717869.45 | G35: =J21+R21+V21+AL21+F21*0.939 -> 11990716 | H35: =N21+Z21+AH21+AT21+CD21+CL21+DR21 -> 4679044 | I35: =B21+AP21+DB21 -> 792285 | J35: =SUM(B35:I35) -> 19517490 | L35: 38168 | M35: =CQ21+DG21 -> 634 | N35: =BC21+BG21+BW21+CY21 -> 4306 | O35: =BK21+CI21+CU21+DK21 -> 40806 | P35: =AY21+BS21+DW21+EA21 -> 8274 | Q35: =AE21+BO21+CA21+DO21 -> 31243 | R35: =K21+S21+W21+AM21 -> 578153 | S35: =O21+AA21+AI21+AU21+CE21+CM21+DS21 -> 216079 | T35: =C21+AQ21+DC21 -> 47105 | U35: =SUM(M35:T35) -> 926600 | V35: =U35-EG21 -> 0
A36: 38533 | B36: =CP22+DF22 -> 223681 | C36: =BB22+BF22+BV22+CX22 -> 347936 | D36: =BJ22+CH22+CT22+DJ22 -> 431950 | E36: =AX22+BR22+DV22+DZ22 -> 312380 | F36: =AD22+BN22+BZ22+DN22+F22*0.061 -> 635503.43 | G36: =J22+R22+V22+AL22+F22*0.939 -> 11343324 | H36: =N22+Z22+AH22+AT22+CD22+CL22+DR22 -> 4826948 | I36: =B22+AP22+DB22 -> 805373 | J36: =SUM(B36:I36) -> 18927095 | L36: 38533 | M36: =CQ22+DG22 -> 700 | N36: =BC22+BG22+BW22+CY22 -> 3783 | O36: =BK22+CI22+CU22+DK22 -> 38379 | P36: =AY22+BS22+DW22+EA22 -> 8170 | Q36: =AE22+BO22+CA22+DO22 -> 29783 | R36: =K22+S22+W22+AM22 -> 546605 | S36: =O22+AA22+AI22+AU22+CE22+CM22+DS22 -> 207373 | T36: =C22+AQ22+DC22 -> 41704 | U36: =SUM(M36:T36) -> 876497 | V36: =U36-EG22 -> 0
A37: 38898 | B37: =CP23+DF23 -> 231930 | C37: =BB23+BF23+BV23+CX23 -> 352415 | D37: =BJ23+CH23+CT23+DJ23 -> 428480 | E37: =AX23+BR23+DV23+DZ23 -> 331145 | F37: =AD23+BN23+BZ23+DN23+F23*0.061 -> 621754.11 | G37: =J23+R23+V23+AL23+F23*0.939 -> 11593368 | H37: =N23+Z23+AH23+AT23+CD23+CL23+DR23 -> 5090026 | I37: =B23+AP23+DB23 -> 760554 | J37: =SUM(B37:I37) -> 19409672 | L37: 38898 | M37: =CQ23+DG23 -> 794 | N37: =BC23+BG23+BW23+CY23 -> 3329 | O37: =BK23+CI23+CU23+DK23 -> 37980 | P37: =AY23+BS23+DW23+EA23 -> 8502 | Q37: =AE23+BO23+CA23+DO23 -> 37979 | R37: =K23+S23+W23+AM23 -> 570735 | S37: =O23+AA23+AI23+AU23+CE23+CM23+DS23 -> 208056 | T37: =C23+AQ23+DC23 -> 38694 | U37: =SUM(M37:T37) -> 906069 | V37: =U37-EG23 -> 0
A38: 39263 | B38: =CP24+DF24 -> 237219 | C38: =BB24+BF24+BV24+CX24 -> 358002 | D38: =BJ24+CH24+CT24+DJ24 -> 428682 | E38: =AX24+BR24+DV24+DZ24 -> 345054 | F38: =AD24+BN24+BZ24+DN24+F24*0.061 -> 613967.8 | G38: =J24+R24+V24+AL24+F24*0.939 -> 12170077 | H38: =N24+Z24+AH24+AT24+CD24+CL24+DR24 -> 5302292 | I38: =B24+AP24+DB24 -> 741054 | J38: =SUM(B38:I38) -> 20196348 | L38: 39263 | M38: =CQ24+DG24 -> 859 | N38: =BC24+BG24+BW24+CY24 -> 3151 | O38: =BK24+CI24+CU24+DK24 -> 35501 | P38: =AY24+BS24+DW24+EA24 -> 8203 | Q38: =AE24+BO24+CA24+DO24 -> 34885 | R38: =K24+S24+W24+AM24 -> 594899 | S38: =O24+AA24+AI24+AU24+CE24+CM24+DS24 -> 212969 | T38: =C24+AQ24+DC24 -> 39853 | U38: =SUM(M38:T38) -> 930320 | V38: =U38-EG24 -> 0
A39: 39629 | B39: =CP25+DF25 -> 248615 | C39: =BB25+BF25+BV25+CX25 -> 243882 | D39: =BJ25+CH25+CT25+DJ25 -> 431480 | E39: =AX25+BR25+DV25+DZ25 -> 375798 | F39: =AD25+BN25+BZ25+DN25+F25*0.061 -> 614515.86 | G39: =J25+R25+V25+AL25+F25*0.939 -> 12844996 | H39: =N25+Z25+AH25+AT25+CD25+CL25+DR25 -> 5657075 | I39: =B25+AP25+DB25 -> 695689 | J39: =SUM(B39:I39) -> 21112051 | L39: 39629 | M39: =CQ25+DG25 -> 1008 | N39: =BC25+BG25+BW25+CY25 -> 3963 | O39: =BK25+CI25+CU25+DK25 -> 36180 | P39: =AY25+BS25+DW25+EA25 -> 8413 | Q39: =AE25+BO25+CA25+DO25 -> 30469 | R39: =K25+S25+W25+AM25 -> 601116 | S39: =O25+AA25+AI25+AU25+CE25+CM25+DS25 -> 233993 | T39: =C25+AQ25+DC25 -> 38309 | U39: =SUM(M39:T39) -> 953451 | V39: =U39-EG25 -> 0
A40: 39994 | B40: =CP26+DF26 -> 318718 | C40: =BB26+BF26+BV26+CX26 -> 248930 | D40: =BJ26+CH26+CT26+DJ26 -> 418846 | E40: =AX26+BR26+DV26+DZ26 -> 405474 | F40: =AD26+BN26+BZ26+DN26+F26*0.061 -> 591127.88 | G40: =J26+R26+V26+AL26+F26*0.939 -> 13229840 | H40: =N26+Z26+AH26+AT26+CD26+CL26+DR26 -> 5760525 | I40: =B26+AP26+DB26 -> 674473 | J40: =SUM(B40:I40) -> 21647934 | L40: 39994 | M40: =CQ26+DG26 -> 1295 | N40: =BC26+BG26+BW26+CY26 -> 2365 | O40: =BK26+CI26+CU26+DK26 -> 37088 | P40: =AY26+BS26+DW26+EA26 -> 8786 | Q40: =AE26+BO26+CA26+DO26 -> 38856 | R40: =K26+S26+W26+AM26 -> 632460 | S40: =O26+AA26+AI26+AU26+CE26+CM26+DS26 -> 266585 | T40: =C26+AQ26+DC26 -> 36647 | U40: =SUM(M40:T40) -> 1024082 | V40: =U40-EG26 -> 0
A41: 40359 | B41: =CP27+DF27 -> 608715 | C41: =BB27+BF27+BV27+CX27 -> 217744 | D41: =BJ27+CH27+CT27+DJ27 -> 410650 | E41: =AX27+BR27+DV27+DZ27 -> 424881 | F41: =AD27+BN27+BZ27+DN27+F27*0.061 -> 574075.78 | G41: =J27+R27+V27+AL27+F27*0.939 -> 13787473 | H41: =N27+Z27+AH27+AT27+CD27+CL27+DR27 -> 5695860 | I41: =B27+AP27+DB27 -> 662474 | J41: =SUM(B41:I41) -> 22381873 | L41: 40359 | M41: =CQ27+DG27 -> 4578 | N41: =BC27+BG27+BW27+CY27 -> 3288 | O41: =BK27+CI27+CU27+DK27 -> 37632 | P41: =AY27+BS27+DW27+EA27 -> 8607 | Q41: =AE27+BO27+CA27+DO27 -> 42546 | R41: =K27+S27+W27+AM27 -> 656914 | S41: =O27+AA27+AI27+AU27+CE27+CM27+DS27 -> 278722 | T41: =C27+AQ27+DC27 -> 34079 | U41: =SUM(M41:T41) -> 1066366 | V41: =U41-EG27 -> 0
A42: 40724 | B42: =CP28+DF28 -> 1341716 | C42: =BB28+BF28+BV28+CX28 -> 228216 | D42: =BJ28+CH28+CT28+DJ28 -> 410033 | E42: =AX28+BR28+DV28+DZ28 -> 560378 | F42: =AD28+BN28+BZ28+DN28+F28*0.061 -> 516714.01 | G42: =J28+R28+V28+AL28+F28*0.939 -> 14804927 | H42: =N28+Z28+AH28+AT28+CD28+CL28+DR28 -> 5566621 | I42: =B28+AP28+DB28 -> 607746 | J42: =SUM(B42:I42) -> 24036351 | L42: 40724 | M42: =CQ28+DG28 -> 8931 | N42: =BC28+BG28+BW28+CY28 -> 3508 | O42: =BK28+CI28+CU28+DK28 -> 39986 | P42: =AY28+BS28+DW28+EA28 -> 8627 | Q42: =AE28+BO28+CA28+DO28 -> 33692 | R42: =K28+S28+W28+AM28 -> 711238 | S42: =O28+AA28+AI28+AU28+CE28+CM28+DS28 -> 294842 | T42: =C28+AQ28+DC28 -> 33649 | U42: =SUM(M42:T42) -> 1134473 | V42: =U42-EG28 -> 0
L44: % NGL
A45: 38533 | B45: =AVERAGE(B34:B38) -> 226412.2 | C45: =AVERAGE(C34:C38) -> 348869.4 | D45: =AVERAGE(D34:D38) -> 444190.8 | E45: =AVERAGE(E34:E38) -> 321792.6 | F45: =AVERAGE(F34:F38) -> 685469.05 | G45: =AVERAGE(G34:G38) -> 11911372 | H45: =AVERAGE(H34:H38) -> 4881492.4 | I45: =AVERAGE(I34:I38) -> 785394 | J45: =SUM(B45:I45) -> 19604993 | M45: R2 | N45: R3 | O45: R4 | P45: R5 | Q45: R6 | R45: R7 | S45: R8 | T45: R9
A46: 40359 | B46: =AVERAGE(B40:B42) -> 756383 | C46: =AVERAGE(C40:C42) -> 231630 | D46: =AVERAGE(D40:D42) -> 413176.33 | E46: =AVERAGE(E40:E42) -> 463577.67 | F46: =AVERAGE(F40:F42) -> 560639.22 | G46: =AVERAGE(G40:G42) -> 13940747 | H46: =AVERAGE(H40:H42) -> 5674335.3 | I46: =AVERAGE(I40:I42) -> 648231 | J46: =SUM(B46:I46) -> 22688719 | L46: 37802 | M46: =M34/B34 -> 0.0033016268 | N46: =N34/C34 -> 0.011900104 | O46: =O34/D34 -> 0.084968238 | P46: =P34/E34 -> 0.023907181 | Q46: =Q34/F34 -> 0.028852952 | R46: =R34/G34 -> 0.042732877 | S46: =S34/H34 -> 0.048518657 | T46: =T34/I34 -> 0.057130327 | U46: =U34/J34 -> 0.043847016
A47: 2010 NYS LB | B47: =AVERAGE(CP26:CP28) -> 37262 | L47: 38168 | M47: =M35/B35 -> 0.0026061899 | N47: =N35/C35 -> 0.012173195 | O47: =O35/D35 -> 0.089742885 | P47: =P35/E35 -> 0.028942011 | Q47: =Q35/F35 -> 0.043521841 | R47: =R35/G35 -> 0.048216722 | S47: =S35/H35 -> 0.04618016 | T47: =T35/I35 -> 0.059454615 | U47: =U35/J35 -> 0.047475367
B48: =B45/$J$45 -> 0.011548701 | C48: =C45/$J$45 -> 0.017794926 | D48: =D45/$J$45 -> 0.022657025 | E48: =E45/$J$45 -> 0.016413809 | F48: =F45/$J$45 -> 0.034964004 | G48: =G45/$J$45 -> 0.60756831 | H48: =H45/$J$45 -> 0.24899231 | I48: =I45/$J$45 -> 0.040060918 | L48: 38533 | M48: =M36/B36 -> 0.0031294567 | N48: =N36/C36 -> 0.010872689 | O48: =O36/D36 -> 0.088850561 | P48: =P36/E36 -> 0.026154043 | Q48: =Q36/F36 -> 0.046865207 | R48: =R36/G36 -> 0.048187376 | S48: =S36/H36 -> 0.042961515 | T48: =T36/I36 -> 0.051782218 | U48: =U36/J36 -> 0.046309114
B49: =B46/$J$46 -> 0.033337404 | C49: =C46/$J$46 -> 0.010209038 | D49: =D46/$J$46 -> 0.01821065 | E49: =E46/$J$46 -> 0.020432077 | F49: =F46/$J$46 -> 0.024710043 | G49: =G46/$J$46 -> 0.61443515 | H49: =H46/$J$46 -> 0.250095 | I49: =I46/$J$46 -> 0.02857063 | L49: 38898 | M49: =M37/B37 -> 0.0034234467 | N49: =N37/C37 -> 0.0094462495 | O49: =O37/D37 -> 0.08863891 | P49: =P37/E37 -> 0.025674553 | Q49: =Q37/F37 -> 0.061083633 | R49: =R37/G37 -> 0.049229439 | S49: =S37/H37 -> 0.040875233 | T49: =T37/I37 -> 0.050876072 | U49: =U37/J37 -> 0.046681314
L50: 39263 | M50: =M38/B38 -> 0.0036211265 | N50: =N38/C38 -> 0.0088016268 | O50: =O38/D38 -> 0.082814301 | P50: =P38/E38 -> 0.023773091 | Q50: =Q38/F38 -> 0.056818941 | R50: =R38/G38 -> 0.048882106 | S50: =S38/H38 -> 0.040165461 | T50: =T38/I38 -> 0.053778807 | U50: =U38/J38 -> 0.046063774
L51: 39629 | M51: =M39/B39 -> 0.0040544617 | N51: =N39/C39 -> 0.016249662 | O51: =O39/D39 -> 0.083850932 | P51: =P39/E39 -> 0.022387027 | Q51: =Q39/F39 -> 0.049582121 | R51: =R39/G39 -> 0.046797679 | S51: =S39/H39 -> 0.041362895 | T51: =T39/I39 -> 0.055066272 | U51: =U39/J39 -> 0.045161458
B52: R2 | C52: R3 | D52: R4 | E52: R5 | F52: R6 | G52: R7 | H52: R8 | I52: R9 | L52: 39994 | M52: =M40/B40 -> 0.004063153 | N52: =N40/C40 -> 0.0095006628 | O52: =O40/D40 -> 0.088548058 | P52: =P40/E40 -> 0.021668467 | Q52: =Q40/F40 -> 0.06573197 | R52: =R40/G40 -> 0.047805566 | S52: =S40/H40 -> 0.0462779 | T52: =T40/I40 -> 0.054334273 | U52: =U40/J40 -> 0.047306223
A53: 2005 | L53: 40359 | M53: =M41/B41 -> 0.0075207609 | N53: =N41/C41 -> 0.015100301 | O53: =O41/D41 -> 0.091640083 | P53: =P41/E41 -> 0.020257437 | Q53: =Q41/F41 -> 0.074112167 | R53: =R41/G41 -> 0.047645714 | S53: =S41/H41 -> 0.048934138 | T53: =T41/I41 -> 0.051442019 | U53: =U41/J41 -> 0.047644181
A54: Domestic natural gas - step 1 | B54: =B56*'Domestic NG Prices'!$O$19 -> 97.653142 | C54: =C56*'Domestic NG Prices'!$O$19 -> 150.46978 | D54: =D56*'Domestic NG Prices'!$O$19 -> 191.58255 | E54: =E56*'Domestic NG Prices'!$O$19 -> 138.79137 | F54: =F56*'Domestic NG Prices'!$O$19 -> 295.64752 | G54: =G56*'Domestic NG Prices'!$O$19 -> 5137.4569 | H54: =H56*'Domestic NG Prices'!$O$19 -> 2105.4213 | I54: =I56*'Domestic NG Prices'!$O$19 -> 338.74585 | L54: 40724 | M54: =M42/B42 -> 0.0066564012 | N54: =N42/C42 -> 0.015371403 | O54: =O42/D42 -> 0.09751898 | P54: =P42/E42 -> 0.015394966 | Q54: =Q42/F42 -> 0.065204348 | R54: =R42/G42 -> 0.048040629 | S54: =S42/H42 -> 0.052966063 | T54: =T42/I42 -> 0.05536688 | U54: =U42/J42 -> 0.047198221
A55: Domestic natural gas - step 2 | B55: =B56*'Domestic NG Prices'!$O$20 -> 170.893 | C55: =C56*'Domestic NG Prices'!$O$20 -> 263.32211 | D55: =D56*'Domestic NG Prices'!$O$20 -> 335.26947 | E55: =E56*'Domestic NG Prices'!$O$20 -> 242.88489 | F55: =F56*'Domestic NG Prices'!$O$20 -> 517.38317 | G55: =G56*'Domestic NG Prices'!$O$20 -> 8990.5496 | H55: =H56*'Domestic NG Prices'!$O$20 -> 3684.4873 | I55: =I56*'Domestic NG Prices'!$O$20 -> 592.80523
A56: Domestic natural gas - step 3 | B56: =B45*1000000*Conv!$D$6*Conv!$J$5 -> 244.13286 | C56: =C45*1000000*Conv!$D$6*Conv!$J$5 -> 376.17444 | D56: =D45*1000000*Conv!$D$6*Conv!$J$5 -> 478.95638 | E56: =E45*1000000*Conv!$D$6*Conv!$J$5 -> 346.97842 | F56: =F45*1000000*Conv!$D$6*Conv!$J$5 -> 739.11881 | G56: =G45*1000000*Conv!$D$6*Conv!$J$5 -> 12843.642 | H56: =H45*1000000*Conv!$D$6*Conv!$J$5 -> 5263.5533 | I56: =I45*1000000*Conv!$D$6*Conv!$J$5 -> 846.86461 | J56: =SUM(B56:I56) -> 21139.421 | L56: 2005 | M56: =AVERAGE(M46:M50) -> 0.0032163693 | N56: =AVERAGE(N46:N50) -> 0.010638773 | O56: =AVERAGE(O46:O50) -> 0.087002979 | P56: =AVERAGE(P46:P50) -> 0.025690176 | Q56: =AVERAGE(Q46:Q50) -> 0.047428515 | R56: =AVERAGE(R46:R50) -> 0.047449704 | S56: =AVERAGE(S46:S50) -> 0.043740205 | T56: =AVERAGE(T46:T50) -> 0.054604408
A57: Domestic natural gas - step 4 | B57: =B56*'Domestic NG Prices'!$O$22 -> 256.3395 | C57: =C56*'Domestic NG Prices'!$O$22 -> 394.98316 | D57: =D56*'Domestic NG Prices'!$O$22 -> 502.9042 | E57: =E56*'Domestic NG Prices'!$O$22 -> 364.32734 | F57: =F56*'Domestic NG Prices'!$O$22 -> 776.07475 | G57: =G56*'Domestic NG Prices'!$O$22 -> 13485.824 | H57: =H56*'Domestic NG Prices'!$O$22 -> 5526.731 | I57: =I56*'Domestic NG Prices'!$O$22 -> 889.20785 | L57: 2010 | M57: =AVERAGE(M52:M54) -> 0.0060801051 | N57: =AVERAGE(N52:N54) -> 0.013324122 | O57: =AVERAGE(O52:O54) -> 0.09256904 | P57: =AVERAGE(P52:P54) -> 0.019106956 | Q57: =AVERAGE(Q52:Q54) -> 0.068349495 | R57: =AVERAGE(R52:R54) -> 0.047830636 | S57: =AVERAGE(S52:S54) -> 0.0493927 | T57: =AVERAGE(T52:T54) -> 0.053714391
A58: Domestic natural gas - step 5 | B58: =B56*'Domestic NG Prices'!$O$23 -> 268.54614 | C58: =C56*'Domestic NG Prices'!$O$23 -> 413.79189 | D58: =D56*'Domestic NG Prices'!$O$23 -> 526.85202 | E58: =E56*'Domestic NG Prices'!$O$23 -> 381.67626 | F58: =F56*'Domestic NG Prices'!$O$23 -> 813.03069 | G58: =G56*'Domestic NG Prices'!$O$23 -> 14128.007 | H58: =H56*'Domestic NG Prices'!$O$23 -> 5789.9086 | I58: =I56*'Domestic NG Prices'!$O$23 -> 931.55108 | M58: =AVERAGE(M46:M54) -> 0.0042640693 | N58: =AVERAGE(N46:N54) -> 0.012157321 | O58: =AVERAGE(O46:O54) -> 0.088508105 | P58: =AVERAGE(P46:P54) -> 0.023128753 | Q58: =AVERAGE(Q46:Q54) -> 0.054641465 | R58: =AVERAGE(R46:R54) -> 0.047504234 | S58: =AVERAGE(S46:S54) -> 0.045360225 | T58: =AVERAGE(T46:T54) -> 0.054359054
A59: Domestic natural gas - step 6 | B59: =B56*'Domestic NG Prices'!$O$24 -> 292.95943 | C59: =C56*'Domestic NG Prices'!$O$24 -> 451.40933 | D59: =D56*'Domestic NG Prices'!$O$24 -> 574.74766 | E59: =E56*'Domestic NG Prices'!$O$24 -> 416.3741 | F59: =F56*'Domestic NG Prices'!$O$24 -> 886.94257 | G59: =G56*'Domestic NG Prices'!$O$24 -> 15412.371 | H59: =H56*'Domestic NG Prices'!$O$24 -> 6316.264 | I59: =I56*'Domestic NG Prices'!$O$24 -> 1016.2375 | L59: NGA | M59: =1-M58 -> 0.99573593 | N59: =1-N58 -> 0.98784268 | O59: =1-O58 -> 0.91149189 | P59: =1-P58 -> 0.97687125 | Q59: =1-Q58 -> 0.94535854 | R59: =1-R58 -> 0.95249577 | S59: =1-S58 -> 0.95463978 | T59: =1-T58 -> 0.94564095
L60: NGL | M60: =1-M59 -> 0.0042640693 | N60: =1-N59 -> 0.012157321 | O60: =1-O59 -> 0.088508105 | P60: =1-P59 -> 0.023128753 | Q60: =1-Q59 -> 0.054641465 | R60: =1-R59 -> 0.047504234 | S60: =1-S59 -> 0.045360225 | T60: =1-T59 -> 0.054359054
A61: Steps
A62: Domestic natural gas - step 1 | B62: =B54 -> 97.653142 | C62: =C54 -> 150.46978 | D62: =D54 -> 191.58255 | E62: =E54 -> 138.79137 | F62: =F54 -> 295.64752 | G62: =G54 -> 5137.4569 | H62: =H54 -> 2105.4213 | I62: =I54 -> 338.74585
A63: Domestic natural gas - step 2 | B63: =B55-B54 -> 73.239857 | C63: =C55-C54 -> 112.85233 | D63: =D55-D54 -> 143.68692 | E63: =E55-E54 -> 104.09352 | F63: =F55-F54 -> 221.73564 | G63: =G55-G54 -> 3853.0927 | H63: =H55-H54 -> 1579.066 | I63: =I55-I54 -> 254.05938
A64: Domestic natural gas - step 3 | B64: =B56-B55 -> 73.239857 | C64: =C56-C55 -> 112.85233 | D64: =D56-D55 -> 143.68692 | E64: =E56-E55 -> 104.09352 | F64: =F56-F55 -> 221.73564 | G64: =G56-G55 -> 3853.0927 | H64: =H56-H55 -> 1579.066 | I64: =I56-I55 -> 254.05938
A65: Domestic natural gas - step 4 | B65: =B57-B56 -> 12.206643 | C65: =C57-C56 -> 18.808722 | D65: =D57-D56 -> 23.947819 | E65: =E57-E56 -> 17.348921 | F65: =F57-F56 -> 36.955941 | G65: =G57-G56 -> 642.18211 | H65: =H57-H56 -> 263.17766 | I65: =I57-I56 -> 42.343231
A66: Domestic natural gas - step 5 | B66: =B58-B57 -> 12.206643 | C66: =C58-C57 -> 18.808722 | D66: =D58-D57 -> 23.947819 | E66: =E58-E57 -> 17.348921 | F66: =F58-F57 -> 36.955941 | G66: =G58-G57 -> 642.18211 | H66: =H58-H57 -> 263.17766 | I66: =I58-I57 -> 42.343231
A67: Domestic natural gas - step 6 | B67: =B59-B58 -> 24.413286 | C67: =C59-C58 -> 37.617444 | D67: =D59-D58 -> 47.895638 | E67: =E59-E58 -> 34.697842 | F67: =F59-F58 -> 73.911881 | G67: =G59-G58 -> 1284.3642 | H67: =H59-H58 -> 526.35533 | I67: =I59-I58 -> 84.686461
A70: 2010
A71: Domestic natural gas - step 1 | B71: =B73*'Domestic NG Prices'!$O$19 -> 326.2332 | C71: =C73*'Domestic NG Prices'!$O$19 -> 99.903616 | D71: =D73*'Domestic NG Prices'!$O$19 -> 178.2058 | E71: =E73*'Domestic NG Prices'!$O$19 -> 199.94424 | F71: =F73*'Domestic NG Prices'!$O$19 -> 241.80756 | G71: =G73*'Domestic NG Prices'!$O$19 -> 6012.7402 | H71: =H73*'Domestic NG Prices'!$O$19 -> 2447.3799 | I71: =I73*'Domestic NG Prices'!$O$19 -> 279.5865
A72: Domestic natural gas - step 2 | B72: =B73*'Domestic NG Prices'!$O$20 -> 570.9081 | C72: =C73*'Domestic NG Prices'!$O$20 -> 174.83133 | D72: =D73*'Domestic NG Prices'!$O$20 -> 311.86015 | E72: =E73*'Domestic NG Prices'!$O$20 -> 349.90243 | F72: =F73*'Domestic NG Prices'!$O$20 -> 423.16323 | G72: =G73*'Domestic NG Prices'!$O$20 -> 10522.295 | H72: =H73*'Domestic NG Prices'!$O$20 -> 4282.9149 | I72: =I73*'Domestic NG Prices'!$O$20 -> 489.27637
A73: Domestic natural gas - step 3 | B73: =B46*1000000*Conv!$D$6*Conv!$J$5 -> 815.583 | C73: =C46*1000000*Conv!$D$6*Conv!$J$5 -> 249.75904 | D73: =D46*1000000*Conv!$D$6*Conv!$J$5 -> 445.5145 | E73: =E46*1000000*Conv!$D$6*Conv!$J$5 -> 499.86061 | F73: =F46*1000000*Conv!$D$6*Conv!$J$5 -> 604.5189 | G73: =G46*1000000*Conv!$D$6*Conv!$J$5 -> 15031.85 | H73: =H46*1000000*Conv!$D$6*Conv!$J$5 -> 6118.4499 | I73: =I46*1000000*Conv!$D$6*Conv!$J$5 -> 698.96625 | J73: =SUM(B73:I73) -> 24464.503
A74: Domestic natural gas - step 4 | B74: =B73*'Domestic NG Prices'!$O$22 -> 856.36215 | C74: =C73*'Domestic NG Prices'!$O$22 -> 262.24699 | D74: =D73*'Domestic NG Prices'!$O$22 -> 467.79023 | E74: =E73*'Domestic NG Prices'!$O$22 -> 524.85364 | F74: =F73*'Domestic NG Prices'!$O$22 -> 634.74485 | G74: =G73*'Domestic NG Prices'!$O$22 -> 15783.443 | H74: =H73*'Domestic NG Prices'!$O$22 -> 6424.3723 | I74: =I73*'Domestic NG Prices'!$O$22 -> 733.91456
A75: Domestic natural gas - step 5 | B75: =B73*'Domestic NG Prices'!$O$23 -> 897.1413 | C75: =C73*'Domestic NG Prices'!$O$23 -> 274.73494 | D75: =D73*'Domestic NG Prices'!$O$23 -> 490.06595 | E75: =E73*'Domestic NG Prices'!$O$23 -> 549.84667 | F75: =F73*'Domestic NG Prices'!$O$23 -> 664.97079 | G75: =G73*'Domestic NG Prices'!$O$23 -> 16535.035 | H75: =H73*'Domestic NG Prices'!$O$23 -> 6730.2948 | I75: =I73*'Domestic NG Prices'!$O$23 -> 768.86287
A76: Domestic natural gas - step 6 | B76: =B73*'Domestic NG Prices'!$O$24 -> 978.6996 | C76: =C73*'Domestic NG Prices'!$O$24 -> 299.71085 | D76: =D73*'Domestic NG Prices'!$O$24 -> 534.6174 | E76: =E73*'Domestic NG Prices'!$O$24 -> 599.83273 | F76: =F73*'Domestic NG Prices'!$O$24 -> 725.42268 | G76: =G73*'Domestic NG Prices'!$O$24 -> 18038.221 | H76: =H73*'Domestic NG Prices'!$O$24 -> 7342.1398 | I76: =I73*'Domestic NG Prices'!$O$24 -> 838.7595
A78: Steps
A79: Domestic natural gas - step 1 | B79: =B71 -> 326.2332 | C79: =C71 -> 99.903616 | D79: =D71 -> 178.2058 | E79: =E71 -> 199.94424 | F79: =F71 -> 241.80756 | G79: =G71 -> 6012.7402 | H79: =H71 -> 2447.3799 | I79: =I71 -> 279.5865
A80: Domestic natural gas - step 2 | B80: =B72-B71 -> 244.6749 | C80: =C72-C71 -> 74.927712 | D80: =D72-D71 -> 133.65435 | E80: =E72-E71 -> 149.95818 | F80: =F72-F71 -> 181.35567 | G80: =G72-G71 -> 4509.5551 | H80: =H72-H71 -> 1835.535 | I80: =I72-I71 -> 209.68987
A81: Domestic natural gas - step 3 | B81: =B73-B72 -> 244.6749 | C81: =C73-C72 -> 74.927712 | D81: =D73-D72 -> 133.65435 | E81: =E73-E72 -> 149.95818 | F81: =F73-F72 -> 181.35567 | G81: =G73-G72 -> 4509.5551 | H81: =H73-H72 -> 1835.535 | I81: =I73-I72 -> 209.68987
A82: Domestic natural gas - step 4 | B82: =B74-B73 -> 40.77915 | C82: =C74-C73 -> 12.487952 | D82: =D74-D73 -> 22.275725 | E82: =E74-E73 -> 24.99303 | F82: =F74-F73 -> 30.225945 | G82: =G74-G73 -> 751.59252 | H82: =H74-H73 -> 305.92249 | I82: =I74-I73 -> 34.948312
A83: Domestic natural gas - step 5 | B83: =B75-B74 -> 40.77915 | C83: =C75-C74 -> 12.487952 | D83: =D75-D74 -> 22.275725 | E83: =E75-E74 -> 24.99303 | F83: =F75-F74 -> 30.225945 | G83: =G75-G74 -> 751.59252 | H83: =H75-H74 -> 305.92249 | I83: =I75-I74 -> 34.948312
A84: Domestic natural gas - step 6 | B84: =B76-B75 -> 81.5583 | C84: =C76-C75 -> 24.975904 | D84: =D76-D75 -> 44.55145 | E84: =E76-E75 -> 49.986061 | F84: =F76-F75 -> 60.45189 | G84: =G76-G75 -> 1503.185 | H84: =H76-H75 -> 611.84499 | I84: =I76-I75 -> 69.896625
A85: NYS LB
A86: Domestic natural gas - step 1 | B86: =B88*'Domestic NG Prices'!$O$19*0.9 -> 14.464222
A87: Domestic natural gas - step 2 | B87: =B88*'Domestic NG Prices'!$O$20*0.9 -> 25.312388
A88: Domestic natural gas - step 3 | B88: =B47*1000000*Conv!$D$6*Conv!$J$5 -> 40.178394
A89: Domestic natural gas - step 4 | B89: =B88*'Domestic NG Prices'!$O$22 -> 42.187313
A90: Domestic natural gas - step 5 | B90: =B88*'Domestic NG Prices'!$O$23 -> 44.196233
A91: Domestic natural gas - step 6 | B91: =B88*'Domestic NG Prices'!$O$24 -> 48.214072
A93: Steps
A94: Domestic natural gas - step 1 | B94: =B86 -> 14.464222
A95: Domestic natural gas - step 2 | B95: =B87-B86 -> 10.848166
A96: Domestic natural gas - step 3 | B96: =B87-B86 -> 10.848166
A97: Domestic natural gas - step 4 | B97: =(B89-B88)*0.9 -> 1.8080277
A98: Domestic natural gas - step 5 | B98: =B90-B89 -> 2.0089197
A99: Domestic natural gas - step 6 | B99: =B91-B90 -> 4.0178394

Sheet ANSv6.1-ConstrData
A1: ANSWER-ConstrData
B7: ConstrName | C7: ConstrDesc | D7: Units | E7: TechName

Sheet Domestic NG Prices
A1: Lower 48 Natural Gas Production and Wellhead Prices by Supply Region, Reference case
A3: Region | B3: 2005 in 2005$ | C3: 2010 in 2010$ | D3: 2015 | E3: 2020 | F3: 2025 | G3: 2030 | H3: 2035 | I3: 2040
A5: Dry Production (trillion cubic feet) 1/
A6: Lower 48 Total | B6: 17.772602 | C6: 21.22 | D6: 24.329756 | E6: 28.812149 | F6: 31.609116 | G6: 33.242813 | H6: 34.918686 | I6: 36.377583
A8: Lower 48 Onshore | C8: 18.66 | D8: 22.213337 | E8: 26.654739 | F8: 29.519766 | G8: 30.82295 | H8: 32.458858 | I8: 33.428997
A9: Northeast | B9: 1.0956695 | C9: 1.52 | D9: 4.255119 | E9: 5.287964 | F9: 6.526698 | G9: 6.571349 | H9: 7.722331 | I9: 8.083803
A10: Gulf Coast | B10: 4.651669 | C10: 4.85 | D10: 6.021707 | E10: 8.327435 | F10: 9.761693 | G10: 10.173032 | H10: 10.303289 | I10: 10.544703
A11: Midcontinent | B11: 2.4793184 | C11: 3.43 | D11: 3.387572 | E11: 3.736248 | F11: 3.707607 | G11: 3.486203 | H11: 3.278044 | I11: 2.976638
A12: Southwest | B12: 1.8143151 | C12: 3.59 | D12: 3.454635 | E12: 3.461408 | F12: 3.271382 | G12: 3.288815 | H12: 3.325309 | I12: 4.202095
A13: Rocky Mountain | B13: 4.0738535 | C13: 5.06 | D13: 4.943402 | E13: 5.698319 | F13: 6.122963 | G13: 7.191331 | H13: 7.722852 | I13: 7.498688
A14: West Coast | B14: 0.25004801 | C14: 0.21 | D14: 0.150902 | E14: 0.143363 | F14: 0.129423 | G14: 0.112223 | H14: 0.107034 | I14: 0.123074
A16: Lower 48 Offshore | C16: 2.56 | D16: 2.11642 | E16: 2.157413 | F16: 2.089348 | G16: 2.419865 | H16: 2.459829 | I16: 2.948587
A17: Gulf | B17: 3.3515694 | C17: 2.52 | D17: 2.08797 | E17: 2.136284 | F17: 2.072056 | G17: 2.313114 | H17: 2.297252 | I17: 2.485032 | N17: Supply Curve Steps
A18: Shallow | B18: 1.9836395 | C18: 0.94 | D18: 0.609703 | E18: 0.420437 | F18: 0.490367 | G18: 0.567648 | H18: 0.577533 | I18: 0.526555 | N18: Prices | O18: Quantity
A19: Deep | B19: 1.3679301 | C19: 1.58 | D19: 1.478266 | E19: 1.715847 | F19: 1.581689 | G19: 1.745466 | H19: 1.719719 | I19: 1.958477 | M19: 1 | N19: 0.88 | O19: 0.4
A20: Pacific | B20: 0.056159936 | C20: 0.04 | D20: 0.02845 | E20: 0.02113 | F20: 0.017292 | G20: 0.044993 | H20: 0.119662 | I20: 0.154505 | M20: 2 | N20: 0.95 | O20: 0.7
A21: Atlantic | B21: 0 | C21: 0 | D21: 0 | E21: 0 | F21: 0 | G21: 0.061758 | H21: 0.042915 | I21: 0.30905 | M21: 3 | N21: 1 | O21: 1
M22: 4 | N22: 1.08 | O22: 1.05
A23: Supply Prices | M23: 5 | N23: 1.12 | O23: 1.1 | R23: * Based on estimated state production in the U.S. Crude Oil, NG, and NGL Reserves report found on
A24: (2012 dollars per million Btu) | M24: 6 | N24: 1.53 | O24: 1.2 | R24: Domestic NG CUM worksheet, the following assumptions were made:
A25: Henry Hub Spot Price | B25: 8.6000004 | C25: 4.39 | D25: 3.743775 | E25: 4.376477 | F25: 5.233528 | G25: 6.034758 | H25: 6.924771 | I25: 7.652016 | S25: R4 prices allotted as 33% of Rocky Mountain and 67% of Midcontinent
A26: Lower 48 Average Price | B26: 7.2912626 | C26: 4.06 | D26: 3.451457 | E26: 4.244283 | F26: 4.905202 | G26: 5.631371 | H26: 6.350606 | I26: 7.263971 | J26: =1+(I26-H26)/H26 -> 1.1438233 | S26: R6 prices allotted as 26% of Northeast and 74% of Gulf Coast
B27: =B26/Conv!$J$5/1000000*Conv!$D$38 -> 6.9107826 | C27: =C26/Conv!$J$5/1000000*Conv!$D$43 -> 3.4975839 | D27: =D26/Conv!$J$5/1000000*Conv!$D$45 -> 2.8659904 | E27: =E26/Conv!$J$5/1000000*Conv!$D$45 -> 3.5243302 | F27: =F26/Conv!$J$5/1000000*Conv!$D$45 -> 4.0731383 | G27: =G26/Conv!$J$5/1000000*Conv!$D$45 -> 4.6761281 | H27: =H26/Conv!$J$5/1000000*Conv!$D$45 -> 5.2733601 | I27: =I26/Conv!$J$5/1000000*Conv!$D$45 -> 6.031792 | M27: Step 3 Price Starting Point: | P27: 1.1 | S27: R7 prices allotted as 25% of Southwest, 40% of Gulf Coast, 24% of Midcontinent, and 11% offshore
A28: (2012 dollars per thousand cubic feet) | P28: *10% above average price
A29: Lower 48 Average Price | B29: 7.5100002 | C29: 4.16 | D29: 3.527389 | E29: 4.337657 | F29: 5.013116 | G29: 5.755261 | H29: 6.490319 | I29: 7.423778
B30: =B29/Conv!$D$6/1000/Conv!$J$5/1000000*Conv!$D$38 -> 6.9648785 | C30: =C29/Conv!$D$6/1000/Conv!$J$5/1000000*Conv!$D$43 -> 3.5065864 | D30: =D29/Conv!$D$6/1000/Conv!$J$5/1000000*Conv!$D$45 -> 2.8659903 | E30: =E29/Conv!$D$6/1000/Conv!$J$5/1000000*Conv!$D$45 -> 3.52433 | F30: =F29/Conv!$D$6/1000/Conv!$J$5/1000000*Conv!$D$45 -> 4.0731379 | G30: =G29/Conv!$D$6/1000/Conv!$J$5/1000000*Conv!$D$45 -> 4.6761279 | H30: =H29/Conv!$D$6/1000/Conv!$J$5/1000000*Conv!$D$45 -> 5.2733598 | I30: =I29/Conv!$D$6/1000/Conv!$J$5/1000000*Conv!$D$45 -> 6.0317917
A31: Lower 48 Onshore Price | J31: Growth Rate: 2012-2040 | M31: 2005 | N31: 2010 | O31: 2015 | P31: 2020 | Q31: 2025 | R31: 2030 | S31: 2035 | T31: 2040 | U31: Growth 2040+
A32: Northeast | B32: 7.6983781 | C32: 4.59 | D32: 3.462149 | E32: 4.10648 | F32: 5.444122 | G32: 6.612253 | H32: 6.571887 | I32: 8.110544 | J32: 1.4 | L32: R1 | M32: =B32/Conv!$D$6/1000/Conv!$J$5/1000000*Conv!$D$38 -> 7.1395827 | N32: =C32/Conv!$D$6/1000/Conv!$J$5/1000000*Conv!$D$43 -> 3.8690461 | O32: =D32/Conv!$D$6/1000/Conv!$J$5/1000000*Conv!$D$45 -> 2.8129831 | P32: =E32/Conv!$D$6/1000/Conv!$J$5/1000000*Conv!$D$45 -> 3.3364996 | Q32: =F32/Conv!$D$6/1000/Conv!$J$5/1000000*Conv!$D$45 -> 4.4233287 | R32: =G32/Conv!$D$6/1000/Conv!$J$5/1000000*Conv!$D$45 -> 5.3724307 | S32: =H32/Conv!$D$6/1000/Conv!$J$5/1000000*Conv!$D$45 -> 5.3396335 | T32: =I32/Conv!$D$6/1000/Conv!$J$5/1000000*Conv!$D$45 -> 6.5897865 | U32: =1+(T32-S32)/S32 -> 1.2341271
A33: Gulf Coast | B33: 7.881938 | C33: 4.18 | D33: 3.516361 | E33: 4.144482 | F33: 4.981838 | G33: 5.780926 | H33: 6.654837 | I33: 7.406928 | J33: 1.4 | L33: R2 | M33: =B32/Conv!$D$6/1000/Conv!$J$5/1000000*Conv!$D$38 -> 7.1395827 | N33: =C32/Conv!$D$6/1000/Conv!$J$5/1000000*Conv!$D$43 -> 3.8690461 | O33: =D32/Conv!$D$6/1000/Conv!$J$5/1000000*Conv!$D$45 -> 2.8129831 | P33: =E32/Conv!$D$6/1000/Conv!$J$5/1000000*Conv!$D$45 -> 3.3364996 | Q33: =F32/Conv!$D$6/1000/Conv!$J$5/1000000*Conv!$D$45 -> 4.4233287 | R33: =G32/Conv!$D$6/1000/Conv!$J$5/1000000*Conv!$D$45 -> 5.3724307 | S33: =H32/Conv!$D$6/1000/Conv!$J$5/1000000*Conv!$D$45 -> 5.3396335 | T33: =I32/Conv!$D$6/1000/Conv!$J$5/1000000*Conv!$D$45 -> 6.5897865 | U33: =1+(T33-S33)/S33 -> 1.2341271
A34: Midcontinent | B34: 7.3497467 | C34: 3.85 | D34: 3.693374 | E34: 4.74555 | F34: 5.072756 | G34: 5.835664 | H34: 6.776257 | I34: 7.591363 | J34: 1.5 | L34: R3 | M34: =B32/Conv!$D$6/1000/Conv!$J$5/1000000*Conv!$D$38 -> 7.1395827 | N34: =C32/Conv!$D$6/1000/Conv!$J$5/1000000*Conv!$D$43 -> 3.8690461 | O34: =D32/Conv!$D$6/1000/Conv!$J$5/1000000*Conv!$D$45 -> 2.8129831 | P34: =E32/Conv!$D$6/1000/Conv!$J$5/1000000*Conv!$D$45 -> 3.3364996 | Q34: =F32/Conv!$D$6/1000/Conv!$J$5/1000000*Conv!$D$45 -> 4.4233287 | R34: =G32/Conv!$D$6/1000/Conv!$J$5/1000000*Conv!$D$45 -> 5.3724307 | S34: =H32/Conv!$D$6/1000/Conv!$J$5/1000000*Conv!$D$45 -> 5.3396335 | T34: =I32/Conv!$D$6/1000/Conv!$J$5/1000000*Conv!$D$45 -> 6.5897865 | U34: =1+(T34-S34)/S34 -> 1.2341271
A35: Southwest | B35: 7.4758234 | C35: 4.21 | D35: 3.797485 | E35: 4.900776 | F35: 5.25594 | G35: 5.816219 | H35: 6.761253 | I35: 7.014832 | J35: 1.5 | L35: R4 | M35: =(B34*0.67+B36*0.33)/Conv!$D$6/1000/Conv!$J$5/1000000*Conv!$D$38 -> 6.6324621 | N35: =(C34*0.67+C36*0.33)/Conv!$D$6/1000/Conv!$J$5/1000000*Conv!$D$43 -> 3.2285883 | O35: =(D34*0.67+D36*0.33)/Conv!$D$6/1000/Conv!$J$5/1000000*Conv!$D$45 -> 2.8317147 | P35: =(E34*0.67+E36*0.33)/Conv!$D$6/1000/Conv!$J$5/1000000*Conv!$D$45 -> 3.6307605 | Q35: =(F34*0.67+F36*0.33)/Conv!$D$6/1000/Conv!$J$5/1000000*Conv!$D$45 -> 3.9224538 | R35: =(G34*0.67+G36*0.33)/Conv!$D$6/1000/Conv!$J$5/1000000*Conv!$D$45 -> 4.4561491 | S35: =(H34*0.67+H36*0.33)/Conv!$D$6/1000/Conv!$J$5/1000000*Conv!$D$45 -> 5.2438224 | T35: =(I34*0.67+I36*0.33)/Conv!$D$6/1000/Conv!$J$5/1000000*Conv!$D$45 -> 5.9401603 | U35: =1+(T35-S35)/S35 -> 1.132792
A36: Rocky Mountain | B36: 6.7492008 | C36: 3.79 | D36: 3.062554 | E36: 3.906456 | F36: 4.330034 | G36: 4.771581 | H36: 5.799615 | I36: 6.741779 | J36: 1.6 | L36: R5 | M36: =B32/Conv!$D$6/1000/Conv!$J$5/1000000*Conv!$D$38 -> 7.1395827 | N36: =C32/Conv!$D$6/1000/Conv!$J$5/1000000*Conv!$D$43 -> 3.8690461 | O36: =D32/Conv!$D$6/1000/Conv!$J$5/1000000*Conv!$D$45 -> 2.8129831 | P36: =E32/Conv!$D$6/1000/Conv!$J$5/1000000*Conv!$D$45 -> 3.3364996 | Q36: =F32/Conv!$D$6/1000/Conv!$J$5/1000000*Conv!$D$45 -> 4.4233287 | R36: =G32/Conv!$D$6/1000/Conv!$J$5/1000000*Conv!$D$45 -> 5.3724307 | S36: =H32/Conv!$D$6/1000/Conv!$J$5/1000000*Conv!$D$45 -> 5.3396335 | T36: =I32/Conv!$D$6/1000/Conv!$J$5/1000000*Conv!$D$45 -> 6.5897865 | U36: =1+(T36-S36)/S36 -> 1.2341271
A37: West Coast | B37: 7.5527425 | C37: 4.33 | D37: 4.386786 | E37: 4.760738 | F37: 5.281815 | G37: 5.659292 | H37: 6.794529 | I37: 7.623652 | J37: 1 | L37: R6 | M37: =(B32*0.26+B33*0.74)/Conv!$D$6/1000/Conv!$J$5/1000000*Conv!$D$38 -> 7.2655573 | N37: =(C32*0.26+C33*0.74)/Conv!$D$6/1000/Conv!$J$5/1000000*Conv!$D$43 -> 3.6133013 | O37: =(D32*0.26+D33*0.74)/Conv!$D$6/1000/Conv!$J$5/1000000*Conv!$D$45 -> 2.8455779 | P37: =(E32*0.26+E33*0.74)/Conv!$D$6/1000/Conv!$J$5/1000000*Conv!$D$45 -> 3.3593482 | Q37: =(F32*0.26+F33*0.74)/Conv!$D$6/1000/Conv!$J$5/1000000*Conv!$D$45 -> 4.1453817 | R37: =(G32*0.26+G33*0.74)/Conv!$D$6/1000/Conv!$J$5/1000000*Conv!$D$45 -> 4.8725977 | S37: =(H32*0.26+H33*0.74)/Conv!$D$6/1000/Conv!$J$5/1000000*Conv!$D$45 -> 5.389507 | T37: =(I32*0.26+I33*0.74)/Conv!$D$6/1000/Conv!$J$5/1000000*Conv!$D$45 -> 6.1667394 | U37: =1+(T37-S37)/S37 -> 1.1442122
L38: R7 | M38: =(B33*0.4+B34*0.24+B35*0.25+B40*0.11)/Conv!$D$6/1000/Conv!$J$5/1000000*Conv!$D$38 -> 7.1082317 | N38: =(C33*0.4+C34*0.24+C35*0.25+C40*0.11)/Conv!$D$6/1000/Conv!$J$5/1000000*Conv!$D$43 -> 3.5325487 | O38: =(D33*0.4+D34*0.24+D35*0.25+D40*0.11)/Conv!$D$6/1000/Conv!$J$5/1000000*Conv!$D$45 -> 2.9916272 | P38: =(E33*0.4+E34*0.24+E35*0.25+E40*0.11)/Conv!$D$6/1000/Conv!$J$5/1000000*Conv!$D$45 -> 3.7279214 | Q38: =(F33*0.4+F34*0.24+F35*0.25+F40*0.11)/Conv!$D$6/1000/Conv!$J$5/1000000*Conv!$D$45 -> 4.1502662 | R38: =(G33*0.4+G34*0.24+G35*0.25+G40*0.11)/Conv!$D$6/1000/Conv!$J$5/1000000*Conv!$D$45 -> 4.733051 | S38: =(H33*0.4+H34*0.24+H35*0.25+H40*0.11)/Conv!$D$6/1000/Conv!$J$5/1000000*Conv!$D$45 -> 5.4771501 | T38: =(I33*0.4+I34*0.24+I35*0.25+I40*0.11)/Conv!$D$6/1000/Conv!$J$5/1000000*Conv!$D$45 -> 5.9943983 | U38: =1+(T38-S38)/S38 -> 1.0944375
A39: Lower 48 Offshore Price | L39: R8 | M39: =B36/Conv!$D$6/1000/Conv!$J$5/1000000*Conv!$D$38 -> 6.2593025 | N39: =C36/Conv!$D$6/1000/Conv!$J$5/1000000*Conv!$D$43 -> 3.1947025 | O39: =D36/Conv!$D$6/1000/Conv!$J$5/1000000*Conv!$D$45 -> 2.4883136 | P39: =E36/Conv!$D$6/1000/Conv!$J$5/1000000*Conv!$D$45 -> 3.1739808 | Q39: =F36/Conv!$D$6/1000/Conv!$J$5/1000000*Conv!$D$45 -> 3.5181364 | R39: =G36/Conv!$D$6/1000/Conv!$J$5/1000000*Conv!$D$45 -> 3.8768916 | S39: =H36/Conv!$D$6/1000/Conv!$J$5/1000000*Conv!$D$45 -> 4.7121654 | T39: =I36/Conv!$D$6/1000/Conv!$J$5/1000000*Conv!$D$45 -> 5.4776701 | U39: =1+(T39-S39)/S39 -> 1.1624529
A40: Gulf | B40: 7.9900274 | C40: 4.93 | D40: 3.997221 | E40: 5.148303 | F40: 5.307836 | G40: 5.984872 | H40: 6.93263 | I40: 7.630444 | L40: R9 | M40: =B37/Conv!$D$6/1000/Conv!$J$5/1000000*Conv!$D$38 -> 7.0045182 | N40: =C37/Conv!$D$6/1000/Conv!$J$5/1000000*Conv!$D$43 -> 3.6498844 | O40: =D37/Conv!$D$6/1000/Conv!$J$5/1000000*Conv!$D$45 -> 3.5642471 | P40: =E37/Conv!$D$6/1000/Conv!$J$5/1000000*Conv!$D$45 -> 3.8680817 | Q40: =F37/Conv!$D$6/1000/Conv!$J$5/1000000*Conv!$D$45 -> 4.2914548 | R40: =G37/Conv!$D$6/1000/Conv!$J$5/1000000*Conv!$D$45 -> 4.5981535 | S40: =H37/Conv!$D$6/1000/Conv!$J$5/1000000*Conv!$D$45 -> 5.5205293 | T40: =I37/Conv!$D$6/1000/Conv!$J$5/1000000*Conv!$D$45 -> 6.1941886 | U40: =1+(T40-S40)/S40 -> 1.122028
A41: Pacific | B41: 7.5570188 | C41: 4.52 | D41: 4.76031 | E41: 5.304164 | F41: 5.757464 | G41: 7.071461 | H41: 6.676446 | I41: 7.566227
A42: Atlantic | B42: 0 | C42: 4.25 | D42: 4.103883 | E42: 5.020764 | F42: 5.201926 | G42: 7.711931 | H42: 8.816 | I42: 8.718942 | L42: Henry Hub | M42: =B25/Conv!$D$6/1000/Conv!$J$5/1000000*Conv!$D$38 -> 7.9757597 | N42: =C25/Conv!$D$6/1000/Conv!$J$5/1000000*Conv!$D$43 -> 3.7004602 | O42: =D25/Conv!$D$6/1000/Conv!$J$5/1000000*Conv!$D$45 -> 3.0418031 | P42: =E25/Conv!$D$6/1000/Conv!$J$5/1000000*Conv!$D$45 -> 3.5558711 | Q42: =F25/Conv!$D$6/1000/Conv!$J$5/1000000*Conv!$D$45 -> 4.2522218 | R42: =G25/Conv!$D$6/1000/Conv!$J$5/1000000*Conv!$D$45 -> 4.9032182 | S42: =H25/Conv!$D$6/1000/Conv!$J$5/1000000*Conv!$D$45 -> 5.6263504 | T42: =I25/Conv!$D$6/1000/Conv!$J$5/1000000*Conv!$D$45 -> 6.2172342 | U42: =1+(T42-S42)/S42 -> 1.1050208
A44: 1/ Marketed production (wet) minus extraction losses.
A45: - - = Not applicable.
A46: Note: Oil and Gas Supply Model regions are defined in Appendix F of the Annual Energy Outlook. Totals may not equal sum of
A47: components due to independent rounding.
A48: Sources: 2011 production: U.S. Department of the Interior, Office of Natural Resources Revenue; U.S. Energy
A49: Information Administration (EIA), Natural Gas Annual 2011, DOE/EIA-0131(2011) (Washington, DC, January 2013); EIA, U.S. Crude Oil,
A50: Natural Gas, and Natural Gas Liquids Reserves, DOE/EIA-0216(2011) (Washington, DC, August 2013); and EIA, Office of Energy Analysis
A51: (OEA). 2012 production: EIA, Natural Gas Monthly, DOE/EIA-0130(2013/06) (Washington, DC, June 2013)
A52: and EIA, Office of Energy Analysis. 2011 and 2012 natural gas spot prices at Henry Hub: Thomson Reuters.
A53: 2011 and 2012 offshore prices based on revenue data from the U.S. Department of the
A54: Interior, Office of Natural Resources Revenue; and EIA, OEA. 2011 and 2012 onshore prices based on
A55: daily data from Natural Gas Intelligence and assumed gathering charges. Projections: EIA, AEO2014 National Energy Modeling System.
A59: Oil and Gas Supply, Reference case
A61: Production and Supply | B61: 2005 in 2005$ | C61: 2010 in 2010$ | D61: 2015 | E61: 2020 | F61: 2025 | G61: 2030 | H61: 2035 | I61: 2040
A63: Dry Production (trillion cubic feet) 4/
A64: Alaska | B64: 0.45 | C64: 0.36 | D64: 0.299816 | E64: 0.277361 | F64: 0.255625 | G64: 1.1858 | H64: 1.174398 | I64: 1.167153

Sheet AEO NG Imports
A1: Natural Gas Imports and Exports, Reference case
A3: Volumes and Prices | B3: 2005 | C3: 2010 | D3: 2015 | E3: 2020 | F3: 2025 | G3: 2030 | H3: 2035 | I3: 2040
A5: Volumes (trillion cubic feet)
A6: Net Imports | B6: 3.5729237 | C6: 2.58 | D6: 1.084329 | E6: -1.926104 | F6: -3.410152 | G6: -4.937026 | H6: -5.531103 | I6: -5.798003
A7: Imports | B7: 4.3210435 | C7: 3.71 | D7: 3.108017 | E7: 2.335441 | F7: 1.988579 | G7: 1.964056 | H7: 2.004963 | I7: 2.22168
A8: Pipeline Imports from Canada | B8: 3.6804636 | C8: 3.25 | D8: 2.958251 | E8: 2.187141 | F8: 1.840279 | G8: 1.815756 | H8: 1.856663 | I8: 2.07338 | W8: 2005 | X8: 2010 | Y8: 2015 | AA8: 2005 | AB8: 2010 | AC8: 2015
A9: Pipeline Imports from Mexico | B9: 0.0093200002 | C9: 0.03 | D9: 0.002816 | E9: 0.0003 | F9: 0.0003 | G9: 0.0003 | H9: 0.0003 | I9: 0.0003 | U9: Canada | V9: Step 1 | W9: =W11*'Domestic NG Prices'!$O$19 -> 1424.2786 | X9: =X11*'Domestic NG Prices'!$O$19 -> 1082.5803 | AA9: =W9 -> 1424.2786 | AB9: =X9 -> 1082.5803
A10: Pipeline Imports from Bahamas | B10: 0 | C10: 0 | D10: 0 | E10: 0 | F10: 0 | G10: 0 | H10: 0 | I10: 0 | V10: Step 2 | W10: =W11*'Domestic NG Prices'!$O$20 -> 2492.4876 | X10: =X11*'Domestic NG Prices'!$O$20 -> 1894.5155 | AA10: =W10-W9 -> 1068.209 | AB10: =X10-X9 -> 811.93523
A11: Liquefied Natural Gas Imports 1/ | B11: 0.63126004 | C11: 0.43 | D11: 0.14695 | E11: 0.148 | F11: 0.148 | G11: 0.148 | H11: 0.148 | I11: 0.148 | V11: Step 3 | W11: =K17 -> 3560.6966 | X11: =L17 -> 2706.4508 | AA11: =W11-W10 -> 1068.209 | AB11: =X11-X10 -> 811.93523
