Workbook
Name __HDV50: #REF!
Name __LDV50: #REF!
Name _1995_Implicit_GDP_Deflator: #REF!
Name _1995_Implicit_GDP_Deflator: #REF!
Name _1995_Implicit_GDP_Deflator: #REF!
Name _1995_Implicit_GDP_Deflator: #REF!
Name _2001_Implicit_GDP_Deflator: #REF!
Name _2001_Implicit_GDP_Deflator: #REF!
Name _2001_Implicit_GDP_Deflator: #REF!
Name _2001_Implicit_GDP_Deflator: #REF!
Name _HDV50: #REF!
Name _HDV50: #REF!
Name _HDV50: #REF!
Name _HDV50: #REF!
Name _LDV50: #REF!
Name _LDV50: #REF!
Name _LDV50: #REF!
Name _LDV50: #REF!
Name Age_of_car: #REF!
Name Age_of_car: #REF!
Name Age_of_car: #REF!
Name Age_of_car: #REF!
Name avg_water_heater_PJ: '[1]AEO HW'!$B$33
Name avg_water_heater_PJ: '[2]AEO HW'!$B$33
Name btu_per_watthr: #REF!
Name btu_per_watthr: #REF!
Name btu_per_watthr: #REF!
Name btu_per_watthr: #REF!
Name conv: #REF!
Name conv: #REF!
Name conv: #REF!
Name conv: #REF!
Name days_per_year: #REF!
Name days_per_year: #REF!
Name days_per_year: #REF!
Name days_per_year: #REF!
Name Diesel_Car_CO: #REF!
Name Diesel_Car_CO: #REF!
Name Diesel_Car_CO: #REF!
Name Diesel_Car_CO: #REF!
Name Diesel_Car_Nox: #REF!
Name Diesel_Car_Nox: #REF!
Name Diesel_Car_Nox: #REF!
Name Diesel_Car_Nox: #REF!
Name Diesel_Car_PM: #REF!
Name Diesel_Car_PM: #REF!
Name Diesel_Car_PM: #REF!
Name Diesel_Car_PM: #REF!
Name Diesel_Car_VOCs: #REF!
Name Diesel_Car_VOCs: #REF!
Name Diesel_Car_VOCs: #REF!
Name Diesel_Car_VOCs: #REF!
Name Diesel_HDT_CO: #REF!
Name Diesel_HDT_CO: #REF!
Name Diesel_HDT_CO: #REF!
Name Diesel_HDT_CO: #REF!
Name Diesel_HDT_NOx: #REF!
Name Diesel_HDT_NOx: #REF!
Name Diesel_HDT_NOx: #REF!
Name Diesel_HDT_NOx: #REF!

Sheet ANSv6.0-Commodities
A1: ANSWER-Commodities
B7: CommName | C7: CommDesc | D7: CommUnit | E7: Set Memberships | F7: Comment

Sheet Readme
B1: Readme - 05-12-2022
B3: For questions contact: Ozge Kaplan, kaplan.ozge@epa.gov, 919-541-5069
B4: Contributors:
B5: Mine Isik, Former ORISE
B6: Andrew Zalesak, ORISE
B8: General Notes
B9: Tabs for pages that consist primarily of input data are colored blue
B10: Tabs for pages that consist primarily of calculations are white
B11: Tabs for pages that are read into Answer are colored yellow
B12: The tabs generally should be navigated from right to left, e.g., the
B13: pages with input data tables are the right-most. Calculations
B14: come next (with each subsequent page typically building on the
... B20: Population Data ("Population")
C21: '- U.S. Census Bureau projections
C22: '- U.S. EPA ORD Integrated Land Use Scenarios model projections
C23: - NYC Population Estimates
B24: Vehicle Miles Traveled Breakdown by Region ("Demands")
C25: '- EIA Household Transportation Energy Use Survey, 2001
B27: Price Deflators to Convert Costs to $2000 ("GDPdeflator")
C28: '- Bureau of Economic Analysis NIPA Table 1.1.9
B30: Vehicle Sales Data by Class ("Sales Data")
C31: '- EIA Annual Energy Outlook 2008, Table 51
B33: Technology Cost and Efficiency Estimates ("AEO08 T59","AEO08 T60","OTAQ-Car","OTAQ-Truck","QM2002")
C34: '- EIA Annual Energy Outlook 2008, Tables 59 and 60
C35: '- OTAQ vehicle assumptions for SGM provided by Simon Mui
C36: '- Vehicle maintenance estimates from DOE's Quality Metrics Report 2002
B38: Emissions (ICF WA on County Level MOVES runs)
C39: -county simulated MOVES runs
B41: Existing Fleet Info
C42: '- Transportation Energy Data book, Edition 21
C43: - NYC.GOV
B46: General Flow of Operations for Preparing Data for Input to ANSWER
B47: Demand Calculation:
C48: '- Regional VMT demands are calculated in "VMT by Region"
B50: Vehicle Characterization:
C51: '- Vehicle efficiency and cost calculations for vehicles described in AEO are provided in the "Costs" and "Efficiencies" pages
C52: - Additional vehicle types are characterized in "AdditionalVehs"
C53: '- The AEO and additional vehicle data are consolidated in "ConsolidatedVehData"
B55: Emissions Characterization:
C56: - Emission factors from MOVES are consolidated in "NewEmisData"
C57: '- These factors are linked to vehicle technologies & classes in "Emissions Linkage"
B59: Characterization of Existing Fleet:
C60: '- Carried out in "Existing Fleet"
B62: Formated Input for Loading into Answer
C63: '- Demands: "CommData"
C64: '- Backstop technologies: "TechDataZZ" (not currently used)
C65: '- Emissions: "TechData-Emissions"
C66: '- Characterization of existing vehicles: "TechData_RES" (RES here represents "residual")
C67: '- Characterization of vehicle costs, efficiencies, fuels, lifetimes, etc.: "TechData_All"
C68: '- Market share and fuel share constraints: "ConstrData"
C69: '- Declaration of fuel, technology, and constraint names: "Constraints", "Technologies", "Commodities"
B71: Exogenous Assumptions:
B72: '* Population growth - several projections are available from different sources
B73: * VMT/person by region is calculated from input data.
C74: -inelastic
B76: '* Market share breakdown by class is constrained to follow AEO
C77: projections
B78: '* Vehicle cost and efficiency data is largely from AEO's time
C79: series projections. We do not assume that learning will decrease
C80: costs (although some degree of learning is likely represented in
C81: AEO's projections for technologies that penetrate the market)
B84: Endogenous Calculations:
B85: MARKAL seeks to find the set of technologies in all modeled sectors
B86: that meets energy demands at least cost. Fuel prices are calculated
B87: endogenously as a function of their supply curves. The primary outputs
B88: include technology penetrations, fuel use, and the resulting
B89: emissions. The model may also have to meet other constraints, such
B90: as lower or upper bounds on market share for technologies and/or
B91: fuels.

Sheet Commodities
B1: Commodities | C1: R1,R2,R3,R4,R5,R6
B6: ~FI_Comm
B7: Region | C7: CommName | D7: CommDesc | E7: Unit | F7: Csets | G7: LimType | H7: CTSLvl | I7: PeakTS | J7: Ctype | O7: Comment
B8: *Demands
B9: R1,R2,R3,R4,R5,R6 | C9: TA | D9: TRN.AIR | E9: bn-pass-miles | F9: DEM
B10: R2,R3,R4,R5,R6 | C10: TB | D10: TRN.BUS | E10: bn-vmt | F10: DEM
B11: R2,R3,R4,R5,R6 | C11: TM | D11: TRN.Medium Duty Trucks | E11: bn-vmt | F11: DEM
B12: R2,R3,R4,R5,R6 | C12: THS | D12: TRN.HDV Short Haul | E12: bn-vmt | F12: DEM
B13: *R1,R2,R3,R4,R5,R6 | C13: THL | D13: TRN.HDV Long Haul | E13: bn-vmt | F13: DEM
B14: R1,R2,R3,R4,R5,R6 | C14: TS | D14: TRN.SHIP | E14: bn-t-m | F14: DEM
B15: *R2,R3,R4,R5,R6 | C15: TRF | D15: TRN.RAIL.FREIGHT | E15: bn-t-m | F15: DEM
B16: *R2,R3,R4,R5,R6 | C16: TSW | D16: TRN.MSW | E16: bn-vmt | F16: DEM
B17: R2,R3,R4,R5,R6 | C17: TRP | D17: TRN.RAIL.PASS | E17: bn-pass-miles | F17: DEM
B18: *R2,R3,R4,R5,R6 | C18: TC | D18: TRN.TRUCK.COMMERCIAL | E18: bn-vmt | F18: DEM
B26: *Energy Carriers
B27: R1,R2,R3,R4,R5,R6 | C27: TRNELC | D27: ELC to TRN | E27: PJ | F27: NRG
B28: *R1,R2,R3,R4,R5,R6 | C28: TRNDSL | D28: DSL to rail emissions collector | E28: PJ | F28: NRG
B29: *R1,R2,R3,R4,R5,R6 | C29: TRNLPG1 | D29: LPG to TRN after Collection | E29: PJ | F29: NRG
B30: *R1,R2,R3,R4,R5,R6 | C30: TRNLPG | D30: LPG after collection | E30: PJ | F30: NRG
B31: R1,R2,R3,R4,R5,R6 | C31: TRNJTF1 | D31: JTF to TRN after Collection | E31: PJ | F31: NRG
B32: R1,R2,R3,R4,R5,R6 | C32: TRNJTF | D32: JTF after collection | E32: PJ | F32: NRG
B33: *R1,R2,R3,R4,R5,R6 | C33: TRNRFH | D33: High Sulfur Residual Fuel Oil to Transportation Sector | E33: PJ | F33: NRG
B34: R1,R2,R3,R4,R5,R6 | C34: TRNRFH1 | D34: RFH to TRN after collector | E34: PJ | F34: NRG
B35: R1,R2,R3,R4,R5,R6 | C35: TRNGSL | D35: GSL to TRN | E35: PJ | F35: NRG
B36: R1,R2,R3,R4,R5,R6 | C36: TRNGSLB | D36: GSLB to TRN | E36: PJ | F36: NRG
B37: R1,R2,R3,R4,R5,R6 | C37: TBGSL | D37: GSL to TB | E37: PJ | F37: NRG
B38: R1,R2,R3,R4,R5,R6 | C38: TCGSL | D38: GSL to TC | E38: PJ | F38: NRG
... B65: *R1,R2,R3,R4,R5,R6 | C65: TSB20X | D65: B20X to TS | E65: PJ | F65: NRG
B66: *Emissions Commodities
B67: * | C67: CARBON | D67: Carbon Emissions | E67: Mt | F67: ENV
B68: R2,R3,R4,R5,R6 | C68: SULFUR | D68: Sulfur Emissions | E68: kt | F68: ENV
B69: R2,R3,R4,R5,R6 | C69: SO2T | D69: Sulfur Emissions -Transportation | E69: kt | F69: ENV
B70: R2,R3,R4,R5,R6 | C70: NOXT | D70: NOX Emissions -Transportation | E70: kt | F70: ENV
B71: R2,R3,R4,R5,R6 | C71: PM10T | D71: PM10 Emissions -Transportation | E71: kt | F71: ENV
B72: R2,R3,R4,R5,R6 | C72: VOCT | D72: VOC Emissions - Transportation | E72: kt | F72: ENV
B73: R2,R3,R4,R5,R6 | C73: PM25T | D73: PM25 Emissions - Trasportation | E73: kt | F73: ENV
B74: R2,R3,R4,R5,R6 | C74: CO2 | D74: Carbon dioxide emissions | E74: Mt | F74: ENV
B75: R2,R3,R4,R5,R6 | C75: SO2 | D75: Sulfur emissions | E75: kt | F75: ENV
B76: R2,R3,R4,R5,R6 | C76: NOX | D76: NOX Emissions | E76: kt | F76: ENV
B77: R2,R3,R4,R5,R6 | C77: PM10 | D77: PM10 Emissions | E77: kt | F77: ENV
B78: R2,R3,R4,R5,R6 | C78: VOC | D78: VOC Emissions | E78: kt | F78: ENV
... B85: R2,R3,R4,R5,R6 | C85: NH3 | D85: Ammonia | E85: kt | F85: ENV

Sheet ANSv6.0-Technologies
A1: ANSWER-Technologies
B7: TechName | C7: TechDesc | D7: TACTUnit | E7: TCAPUnit | F7: Set Memberships | G7: Comment

Sheet ANSv6.0-Constraints
A1: ANSWER-Constraints
B7: ConstrName | C7: ConstrDesc | D7: Units | E7: Set Memberships | F7: Comment

Sheet ANSv6.0-CommData
A1: ANSWER-CommData
B7: CommName | C7: CommDesc | D7: Units

Sheet ANSv6.0-TechData
A1: ANSWER-TechData
B7: TechName | C7: TechDesc | D7: Units | E7: CommIN | F7: CommOUT

Sheet ANSv6.0-ConstrData
A1: ANSWER-ConstrData
B7: ConstrName | C7: ConstrDesc | D7: Units | E7: TechName

Sheet Technologies
B1: Technologies | C1: R1,R2,R3,R4,R5,R6
B6: ~FI_Process
B7: Region | C7: TechName | D7: TechDesc | E7: Tact | F7: Tcap | G7: Sets | H7: PrimaryCG | I7: Vintage
B8: * Existing Technologies
B9: =TechData!A8 -> R2,R3,R4,R5,R6 | C9: =TechData!B8 -> TAJE | D9: =TechData!C8 -> Air Jet, Passenger Existing | E9: bn-pass-miles | F9: bn-pmt/a | G9: DMD
B10: =TechData!A9 -> * | C10: =TechData!B9 -> TAPE | D10: =TechData!C9 -> Airplane, General Aviation, exisiting | E10: bn-pass-miles | F10: bn-pmt/a | G10: DMD
B11: =TechData!A11 -> R2,R3,R4,R5,R6 | C11: =TechData!B11 -> TBDSLE | D11: =TechData!C11 -> Bus, Exisiting Diesel | E11: bn-vmt | F11: bn-vmt/a | G11: DMD
B12: =TechData!A12 -> * | C12: =TechData!B12 -> TBGSLE | D12: =TechData!C12 -> Bus, Exisiting Gasoline | E12: bn-vmt | F12: bn-vmt/a | G12: DMD
B13: =TechData!A13 -> R2,R3,R4,R5,R6 | C13: =TechData!B13 -> TBCNGE | D13: =TechData!C13 -> Bus, Exisiting CNG | E13: bn-vmt | F13: bn-vmt/a | G13: DMD
B14: =TechData!A15 -> * | C14: =TechData!B15 -> TCGSLE | D14: =TechData!C15 -> Truck, Commerical, Exisiting Gasoline | E14: bn-vmt | F14: bn-vmt/a | G14: DMD
B15: =TechData!A16 -> * | C15: =TechData!B16 -> TCDSLE | D15: =TechData!C16 -> Truck, Commerical, Existing Diesel | E15: bn-vmt | F15: bn-vmt/a | G15: DMD
B16: =TechData!A18 -> R2,R3,R4,R5,R6 | C16: =TechData!B18 -> TMGSLE | D16: =TechData!C18 -> Medium Duty Truck, Existing Gasoline | E16: bn-vmt | F16: bn-vmt/a | G16: DMD
B17: =TechData!A19 -> R2,R3,R4,R5,R6 | C17: =TechData!B19 -> TMDSLE | D17: =TechData!C19 -> Medium Duty Truck, Existing Diesel | E17: bn-vmt | F17: bn-vmt/a | G17: DMD
B18: =TechData!A20 -> R2,R3,R4,R5,R6 | C18: =TechData!B20 -> TMCNGE | D18: =TechData!C20 -> Medium Duty Truck, Existing CNG | E18: bn-vmt | F18: bn-vmt/a | G18: DMD
B19: =TechData!A21 -> * | C19: =TechData!B21 -> TMLPGE | D19: =TechData!C21 -> Medium Duty Truck, Existing LPG | E19: bn-vmt | F19: bn-vmt/a | G19: DMD
B20: =TechData!A23 -> R2,R3,R4,R5,R6 | C20: =TechData!B23 -> THSGSLE | D20: =TechData!C23 -> Heavy Truck, Short Haul, Gasoline exisiting | E20: bn-vmt | F20: bn-vmt/a | G20: DMD
B21: =TechData!A24 -> R2,R3,R4,R5,R6 | C21: =TechData!B24 -> THSDSLE | D21: =TechData!C24 -> Heavy Truck, Short Haul, Diesel exisiting | E21: bn-vmt | F21: bn-vmt/a | G21: DMD
B22: =TechData!A25 -> * | C22: =TechData!B25 -> THSDSLE2 | D22: =TechData!C25 -> Heavy Truck, Short Haul, Diesel exisiting MSW | E22: bn-vmt | F22: bn-vmt/a | G22: DMD
B23: =TechData!A26 -> * | C23: =TechData!B26 -> THSCNGE2 | D23: =TechData!C26 -> Heavy Truck, Short Haul, CNG exisiting MSW | E23: bn-vmt | F23: bn-vmt/a | G23: DMD
B24: =TechData!A28 -> R2,R3,R4,R5,R6 | C24: =TechData!B28 -> TPDSLCR | D24: =TechData!C28 -> Commuter Rail, Diesel | E24: bn-pass-miles | F24: bn-pmt/a | G24: DMD
B25: =TechData!A29 -> R2,R3,R4,R5,R6 | C25: =TechData!B29 -> TPELCSUB | D25: =TechData!C29 -> Subways and Streetcars, Electricity | E25: bn-pass-miles | F25: bn-pmt/a | G25: DMD
B26: =TechData!A31 -> * | C26: =TechData!B31 -> TRFDSLE | D26: =TechData!C31 -> Rail Freight, Diesel Existing | E26: bn-t-m | F26: bn-ton-m/a | G26: DMD
B27: =TechData!A32 -> * | C27: =TechData!B32 -> TRFDSLE2 | D27: =TechData!C32 -> Rail Freight, Diesel Existing-MSW | E27: bn-vmt | F27: bn-vmt/a | G27: DMD
B28: =TechData!A33 -> R2,R3,R4,R5,R6 | C28: =TechData!B33 -> TSDSLE | D28: =TechData!C33 -> Water Shipping, Diesel exisiting | E28: bn-t-m | F28: bn-ton-m/a | G28: DMD
B33: =#REF! -> #REF! | C33: =#REF! -> #REF! | E33: PJ | F33: Pja | G33: PRE
B34: =#REF! -> #REF! | C34: =#REF! -> #REF! | E34: PJ | F34: Pja | G34: PRE
B35: =#REF! -> #REF! | C35: =#REF! -> #REF! | E35: PJ | F35: Pja | G35: PRE
B36: =#REF! -> #REF! | C36: =#REF! -> #REF! | E36: PJ | F36: Pja | G36: PRE
B37: =#REF! -> #REF! | C37: =#REF! -> #REF! | E37: PJ | F37: Pja | G37: PRE
B38: =#REF! -> #REF! | C38: =#REF! -> #REF! | E38: PJ | F38: Pja | G38: PRE
B39: =#REF! -> #REF! | C39: =#REF! -> #REF! | E39: PJ | F39: Pja | G39: PRE
B40: =#REF! -> #REF! | C40: =#REF! -> #REF! | E40: PJ | F40: Pja | G40: PRE
B41: =#REF! -> #REF! | C41: =#REF! -> #REF! | E41: PJ | F41: Pja | G41: PRE
B42: =#REF! -> #REF! | C42: =#REF! -> #REF! | E42: PJ | F42: Pja | G42: PRE
B47: R2,R3,R4,R5,R6 | C47: TAJE | D47: ='Air&Marine'!B6 -> Air Jet, Passenger Existing | E47: bn-pass-miles | F47: bn-pmt/a | G47: DMD
B48: *R2,R3,R4,R5,R6 | C48: TAPE | D48: Airplane, General Aviation, exisiting | E48: bn-pass-miles | F48: bn-pmt/a | G48: DMD
B49: R2,R3,R4,R5,R6 | C49: TAJ10 | D49: ='Air&Marine'!B7 -> Air Jet, Passenger 2010 | E49: bn-pass-miles | F49: bn-pmt/a | G49: DMD
B50: R2,R3,R4,R5,R6 | C50: TAJSYN10 | D50: ='Air&Marine'!B8 -> Air Jet, Passenger, Syn fuel, 2010 | E50: bn-pass-miles | F50: bn-pmt/a | G50: DMD
B51: R2,R3,R4,R5,R6 | C51: TAJWT10 | D51: ='Air&Marine'!B9 -> Air Jet, Passenger (Wing tips),2010 | E51: bn-pass-miles | F51: bn-pmt/a | G51: DMD
B52: R2,R3,R4,R5,R6 | C52: TAJAPU15 | D52: ='Air&Marine'!B11 -> Air Jet Passeneger (APU) 2015 | E52: bn-pass-miles | F52: bn-pmt/a | G52: DMD
B53: R2,R3,R4,R5,R6 | C53: TAJBW30 | D53: ='Air&Marine'!B12 -> Air Jet, Passenger(blended wing), 2030 | E53: bn-pass-miles | F53: bn-pmt/a | G53: DMD
B54: R2,R3,R4,R5,R6 | C54: TAJAE30 | D54: ='Air&Marine'!B13 -> Air Jet, Passenger (improved aero), 2030 | E54: bn-pass-miles | F54: bn-pmt/a | G54: DMD
B55: R2,R3,R4,R5,R6 | C55: TAJGE15 | D55: ='Air&Marine'!B15 -> Air Jet Passenger, (geared engine), 2015 | E55: bn-pass-miles | F55: bn-pmt/a | G55: DMD
B56: *R2,R3,R4,R5,R6 | C56: TAP10 | D56: Airplane, General Aviation - 2010 | E56: bn-pass-miles | F56: bn-pmt/a | G56: DMD
B57: R2,R3,R4,R5,R6 | C57: TBDSLE | D57: =TechData!C11 -> Bus, Exisiting Diesel | E57: bn-vmt | F57: bn-vmt/a | G57: DMD
B58: *R2,R3,R4,R5,R6 | C58: TBGSLE | D58: =TechData!C12 -> Bus, Exisiting Gasoline | E58: bn-vmt | F58: bn-vmt/a | G58: DMD
B59: R2,R3,R4,R5,R6 | C59: TBCNGE | D59: =TechData!C13 -> Bus, Exisiting CNG | E59: bn-vmt | F59: bn-vmt/a | G59: DMD
B60: R2,R3,R4,R5,R6 | C60: TBDSLC10 | D60: Bus, Conventional Diesel, 2010 | E60: bn-vmt | F60: bn-vmt/a | G60: DMD
B61: R2,R3,R4,R5,R6 | C61: TBDSLC | D61: =NewTech!C18 -> Bus, Conventional Diesel | E61: bn-vmt | F61: bn-vmt/a | G61: DMD
B62: R2,R3,R4,R5,R6 | C62: TBDSLIM | D62: Bus, Improved Diesel | E62: bn-vmt | F62: bn-vmt/a | G62: DMD
B63: R2,R3,R4,R5,R6 | C63: TBDSLADV | D63: =NewTech!C20 -> Bus, Advanced Tech Diesel | E63: bn-vmt | F63: bn-vmt/a | G63: DMD
B64: R2,R3,R4,R5,R6 | C64: TBDSLAH | D64: =NewTech!C21 -> Bus, Advanced Hybrid Diesel | E64: bn-vmt | F64: bn-vmt/a | G64: DMD
B65: *R2,R3,R4,R5,R6 | C65: TBB20C10 | D65: Bus, Conventional Biodiesel, 2010 | E65: bn-vmt | F65: bn-vmt/a | G65: DMD
B66: *R2,R3,R4,R5,R6 | C66: TBB20C | D66: =NewTech!C23 -> Bus, Conventional B20 | E66: bn-vmt | F66: bn-vmt/a | G66: DMD
B67: *R2,R3,R4,R5,R6 | C67: TBB20IM | D67: Bus, B20, Improved Biodiesel | E67: bn-vmt | F67: bn-vmt/a | G67: DMD
B68: *R2,R3,R4,R5,R6 | C68: TBB20ADV | D68: =NewTech!C25 -> Bus, Advanced Tech B20 | E68: bn-vmt | F68: bn-vmt/a | G68: DMD
B69: *R2,R3,R4,R5,R6 | C69: TBB20AH | D69: =NewTech!C26 -> Bus, Advanced Hybrid B20 | E69: bn-vmt | F69: bn-vmt/a | G69: DMD
B70: R2,R3,R4,R5,R6 | C70: TBCNGC10 | D70: Bus, Conventional CNG, 2010 | E70: bn-vmt | F70: bn-vmt/a | G70: DMD
B71: R2,R3,R4,R5,R6 | C71: TBCNGC | D71: =NewTech!C28 -> Bus, Conventional CNG | E71: bn-vmt | F71: bn-vmt/a | G71: DMD
B72: R2,R3,R4,R5,R6 | C72: TBCNGIM | D72: Bus, Improved CNG | E72: bn-vmt | F72: bn-vmt/a | G72: DMD
B73: R2,R3,R4,R5,R6 | C73: TBCNGADV | D73: =NewTech!C30 -> Bus, Advanced Tech CNG | E73: bn-vmt | F73: bn-vmt/a | G73: DMD
B74: R2,R3,R4,R5,R6 | C74: TBCNGAH | D74: =NewTech!C31 -> Bus, Advanced Hybird CNG | E74: bn-vmt | F74: bn-vmt/a | G74: DMD
B75: R2,R3,R4,R5,R6 | C75: TBH2FC | D75: =NewTech!C32 -> Bus, Hydrogen Fuel Cell | E75: bn-vmt | F75: bn-vmt/a | G75: DMD
B76: R2,R3,R4,R5,R6 | C76: TBH2HYB | D76: =NewTech!C33 -> Bus, Hydrogen Fuel Cell Hybrid | E76: bn-vmt | F76: bn-vmt/a | G76: DMD
B77: R2,R3,R4,R5,R6 | C77: TBELC | D77: Bus, Conventional ELC | E77: bn-vmt | F77: bn-vmt/a | G77: DMD
B78: R2,R3,R4,R5,R6 | C78: TBELCIM | D78: Bus, Improved ELC | E78: bn-vmt | F78: bn-vmt/a | G78: DMD
B79: *R2,R3,R4,R5,R6 | C79: TCGSLE | D79: Truck, Commerical, Exisiting Gasoline | E79: bn-vmt | F79: bn-vmt/a | G79: DMD
B80: *R2,R3,R4,R5,R6 | C80: TCDSLE | D80: Truck, Commerical, Existing Diesel | E80: bn-vmt | F80: bn-vmt/a | G80: DMD
B81: *R2,R3,R4,R5,R6 | C81: TCGSLC10 | D81: =Trucks!A7 -> Commercial Truck, Gasoline 2010 | E81: bn-vmt | F81: bn-vmt/a | G81: DMD
B82: *R2,R3,R4,R5,R6 | C82: TCGSLC | D82: =Trucks!A8 -> Commercial Truck, Conventional Gasoline | E82: bn-vmt | F82: bn-vmt/a | G82: DMD
B83: *R2,R3,R4,R5,R6 | C83: TCGSLIM | D83: =Trucks!A10 -> Commercial Truck, Improved Gasoline | E83: bn-vmt | F83: bn-vmt/a | G83: DMD
B84: *R2,R3,R4,R5,R6 | C84: TCGSLADV | D84: =Trucks!A12 -> Commercial Truck, Advanced Tech Gasoline | E84: bn-vmt | F84: bn-vmt/a | G84: DMD
B85: *R2,R3,R4,R5,R6 | C85: TCGSLAH | D85: =Trucks!A14 -> Commercial Truck, Advanced Hybrid Tech Gasoline | E85: bn-vmt | F85: bn-vmt/a | G85: DMD
B86: *R2,R3,R4,R5,R6 | C86: TCDSLC10 | D86: =Trucks!A17 -> Commercial Truck, Diesel 2010 | E86: bn-vmt | F86: bn-vmt/a | G86: DMD
B87: *R2,R3,R4,R5,R6 | C87: TCDSLC | D87: =Trucks!A18 -> Commercial Truck, Conventional Diesel | E87: bn-vmt | F87: bn-vmt/a | G87: DMD
B88: *R2,R3,R4,R5,R6 | C88: TCDSLIM | D88: =Trucks!A20 -> Commercial Truck, Improved Diesel | E88: bn-vmt | F88: bn-vmt/a | G88: DMD
B89: *R2,R3,R4,R5,R6 | C89: TCDSLAH | D89: =Trucks!A21 -> Commercial Truck, Advanced Hybrid Diesel | E89: bn-vmt | F89: bn-vmt/a | G89: DMD
B90: *R2,R3,R4,R5,R6 | C90: TCB20C10 | D90: =Trucks!A24 -> Commercial Truck, B20 2010 | E90: bn-vmt | F90: bn-vmt/a | G90: DMD
B91: *R2,R3,R4,R5,R6 | C91: TCB20C | D91: =Trucks!A25 -> Commercial Truck, Conventional B20 | E91: bn-vmt | F91: bn-vmt/a | G91: DMD
B92: *R2,R3,R4,R5,R6 | C92: TCB20IM | D92: =Trucks!A27 -> Commercial Truck, Improved B20 | E92: bn-vmt | F92: bn-vmt/a | G92: DMD
B93: *R2,R3,R4,R5,R6 | C93: TCB20AH | D93: =Trucks!A28 -> Commerical Truck, Advanced Hybrid B20 | E93: bn-vmt | F93: bn-vmt/a | G93: DMD
B94: *R2,R3,R4,R5,R6 | C94: TCCNGC10 | D94: =Trucks!A31 -> Commercial Truck, CNG 2010 | E94: bn-vmt | F94: bn-vmt/a | G94: DMD
B95: *R2,R3,R4,R5,R6 | C95: TCCNGC | D95: =Trucks!A32 -> Commercial Truck, Conventional CNG | E95: bn-vmt | F95: bn-vmt/a | G95: DMD
B96: *R2,R3,R4,R5,R6 | C96: TCCNGIM | D96: =Trucks!A34 -> Commercial Truck, Improved CNG | E96: bn-vmt | F96: bn-vmt/a | G96: DMD
B97: *R2,R3,R4,R5,R6 | C97: TCCNGADV | D97: =Trucks!A36 -> Commerical Truck, Advanced CNG | E97: bn-vmt | F97: bn-vmt/a | G97: DMD
B98: *R2,R3,R4,R5,R6 | C98: TCCNGAH | D98: =Trucks!A39 -> Commerical Truck, Advanced Hybrid CNG | E98: bn-vmt | F98: bn-vmt/a | G98: DMD
B99: *R2,R3,R4,R5,R6 | C99: TCE85C10 | D99: =Trucks!A42 -> Commercial Truck, E85 2010 | E99: bn-vmt | F99: bn-vmt/a | G99: DMD
B100: *R2,R3,R4,R5,R6 | C100: TCE85C | D100: =Trucks!A43 -> Commercial Truck, Conventional E85 | E100: bn-vmt | F100: bn-vmt/a | G100: DMD
B101: *R2,R3,R4,R5,R6 | C101: TCE85IM | D101: =Trucks!A45 -> Commercial Truck, Improved E85 | E101: bn-vmt | F101: bn-vmt/a | G101: DMD
B102: *R2,R3,R4,R5,R6 | C102: TCE85ADV | D102: =Trucks!A47 -> Commercial Truck, Advanced E85 | E102: bn-vmt | F102: bn-vmt/a | G102: DMD
B103: *R2,R3,R4,R5,R6 | C103: TCE85AH | D103: =Trucks!A50 -> Commerical Truck, Hybrid E85 | E103: bn-vmt | F103: bn-vmt/a | G103: DMD
B104: *R2,R3,R4,R5,R6 | C104: TCLPGC10 | D104: =Trucks!A53 -> Commercial Truck, LPG 2010 | E104: bn-vmt | F104: bn-vmt/a | G104: DMD
B105: *R2,R3,R4,R5,R6 | C105: TCLPGC | D105: =Trucks!A54 -> Commercial Truck, Conventional LPG | E105: bn-vmt | F105: bn-vmt/a | G105: DMD
B106: *R2,R3,R4,R5,R6 | C106: TCLPGIM | D106: =Trucks!A56 -> Commercial Truck, Improved LPG | E106: bn-vmt | F106: bn-vmt/a | G106: DMD
B107: *R2,R3,R4,R5,R6 | C107: TCLPGADV | D107: =Trucks!A58 -> Commercial Truck, Advanced LPG | E107: bn-vmt | F107: bn-vmt/a | G107: DMD
B108: *R2,R3,R4,R5,R6 | C108: TCLPGAH | D108: =Trucks!A61 -> Commercial Truck, Hybrid LPG | E108: bn-vmt | F108: bn-vmt/a | G108: DMD
B109: *R2,R3,R4,R5,R6 | C109: TCH2FC | D109: =Trucks!A64 -> Commercial Truck, Hydrogen Fuel Cell | E109: bn-vmt | F109: bn-vmt/a | G109: DMD
B110: R2,R3,R4,R5,R6 | C110: TMGSLE | D110: =Trucks!A119 -> Medium Duty Truck, Existing Gasoline | E110: bn-vmt | F110: bn-vmt/a | G110: DMD
B111: R2,R3,R4,R5,R6 | C111: TMDSLE | D111: =Trucks!A120 -> Medium Duty Truck, Existing Diesel | E111: bn-vmt | F111: bn-vmt/a | G111: DMD
B112: R2,R3,R4,R5,R6 | C112: TMCNGE | D112: =Trucks!A122 -> Medium Duty Truck, Existing CNG | E112: bn-vmt | F112: bn-vmt/a | G112: DMD
...

Sheet CommData
A1: CommData | B1: R1,R2,R3,R4,R5,R6
E3: ~FI_T
A4: Region | B4: CommName | C4: *CommDesc | D4: *Units | E4: *COM_PROJ~2005 | F4: COM_PROJ~2010 | G4: COM_PROJ~2015 | H4: COM_PROJ~2020 | I4: COM_PROJ~2025 | J4: COM_PROJ~2030 | K4: COM_PROJ~2035 | L4: COM_PROJ~2040 | M4: COM_PROJ~2045 | N4: COM_PROJ~2050 | O4: COM_PROJ~2055
A5: *Energy Demands by End Use
A6: * | B6: =B16 -> TA | C6: =C16 -> TRN.AIR | D6: =D16 -> bn-pass-miles | E6: =E16+E26+E37+E48+E59+E70 -> 0.01747708 | F6: =F16+F26+F37+F48+F59+F70 -> 0.014855518 | G6: =G16+G26+G37+G48+G59+G70 -> 0.019044073 | H6: =H16+H26+H37+H48+H59+H70 -> 0.019869506 | I6: =I16+I26+I37+I48+I59+I70 -> 0.020959275 | J6: =J16+J26+J37+J48+J59+J70 -> 0.021741127 | K6: =K16+K26+K37+K48+K59+K70 -> 0.022804962 | L6: =L16+L26+L37+L48+L59+L70 -> 0.024131694 | ... O6: =O16+O26+O37+O48+O59+O70 -> 0.02860129
A7: * | B7: =B17 -> TB | C7: =C17 -> TRN.BUS | D7: =D17 -> bn-vmt | E7: =E17+E27+E38+E49+E60+E71 -> 0.44094656 | F7: =F17+F27+F38+F49+F60+F71 -> 0.44094656 | G7: =G17+G27+G38+G49+G60+G71 -> 0.42448077 | H7: =H17+H27+H38+H49+H60+H71 -> 0.4420327 | I7: =I17+I27+I38+I49+I60+I71 -> 0.46037993 | J7: =J17+J27+J38+J49+J60+J71 -> 0.47882279 | K7: =K17+K27+K38+K49+K60+K71 -> 0.4968582 | L7: =L17+L27+L38+L49+L60+L71 -> 0.51425279 | ... O7: =O17+O27+O38+O49+O60+O71 -> 0.59327237
A8: * | B8: TM | C8: TRN.MDV | D8: bn-vmt | E8: =E18+E28+E39+E50+E61+E72 -> 0.49815344 | F8: =F18+F28+F39+F50+F61+F72 -> 0.49815344 | G8: =G18+G28+G39+G50+G61+G72 -> 0.50909164 | H8: =H18+H28+H39+H50+H61+H72 -> 0.50912534 | I8: =I18+I28+I39+I50+I61+I72 -> 0.51716492 | J8: =J18+J28+J39+J50+J61+J72 -> 0.52520449 | K8: =K18+K28+K39+K50+K61+K72 -> 0.53128109 | L8: =L18+L28+L39+L50+L61+L72 -> 0.53735769 | ... O8: =O18+O28+O39+O50+O61+O72 -> 0.57156693
A9: * | B9: =B19 -> THS | C9: =C19 -> TRN.HDV Short Haul | D9: =D19 -> bn-vmt | E9: =E19+E29+E40+E51+E62+E73 -> 0.91154638 | F9: =F19+F29+F40+F51+F62+F73 -> 0.91154638 | G9: =G19+G29+G40+G51+G62+G73 -> 0.94339499 | H9: =H19+H29+H40+H51+H62+H73 -> 0.98428483 | I9: =I19+I29+I40+I51+I62+I73 -> 1.0382692 | J9: =J19+J29+J40+J51+J62+J73 -> 1.0770002 | K9: =K19+K29+K40+K51+K62+K73 -> 1.1296999 | L9: =L19+L29+L40+L51+L62+L73 -> 1.1954228 | ... O9: =O19+O29+O40+O51+O62+O73 -> 1.4168352
A10: * | B10: =B20 -> THL | C10: =C20 -> TRN.HDV Long Haul | D10: =D9 -> bn-vmt | E10: =E20+E30+E41+E52+E63+E74 -> 0 | F10: =F20+F30+F41+F52+F63+F74 -> 0 | G10: =G20+G30+G41+G52+G63+G74 -> 0 | H10: =H20+H30+H41+H52+H63+H74 -> 0 | I10: =I20+I30+I41+I52+I63+I74 -> 0 | J10: =J20+J30+J41+J52+J63+J74 -> 0 | K10: =K20+K30+K41+K52+K63+K74 -> 0 | L10: =L20+L30+L41+L52+L63+L74 -> 0 | ... O10: =O20+O30+O41+O52+O63+O74 -> 0
A11: * | B11: =B21 -> TRF | C11: =C21 -> TRN.RAIL.FREIGHT | D11: =D21 -> bn-t-m | E11: =E21+E31+E42+E53+E64+E75 -> 0 | F11: =F21+F31+F42+F53+F64+F75 -> 0 | G11: =G21+G31+G42+G53+G64+G75 -> 0 | H11: =H21+H31+H42+H53+H64+H75 -> 0 | I11: =I21+I31+I42+I53+I64+I75 -> 0 | J11: =J21+J31+J42+J53+J64+J75 -> 0 | K11: =K21+K31+K42+K53+K64+K75 -> 0 | L11: =L21+L31+L42+L53+L64+L75 -> 0 | ... O11: =O21+O31+O42+O53+O64+O75 -> 0
A12: * | B12: =B22 -> TRP | C12: =C22 -> TRN.RAIL.PASS | D12: =D22 -> bn-pass-miles | E12: =E22+E32+E43+E54+E65+E76 -> 28.027525 | F12: =F22+F32+F43+F54+F65+F76 -> 28.027525 | G12: =G22+G32+G43+G54+G65+G76 -> 29.38391 | H12: =H22+H32+H43+H54+H65+H76 -> 30.881758 | I12: =I22+I32+I43+I54+I65+I76 -> 32.723301 | J12: =J22+J32+J43+J54+J65+J76 -> 34.380043 | K12: =K22+K32+K43+K54+K65+K76 -> 35.920869 | L12: =L22+L32+L43+L54+L65+L76 -> 38.097929 | ... O12: =O22+O32+O43+O54+O65+O76 -> 45.084512
A13: * | B13: =B23 -> TS | C13: =C23 -> TRN.SHIP | D13: =D23 -> bn-t-m | E13: =E23+E33+E44+E55+E66+E77 -> 1.6792504 | F13: =F23+F33+F44+F55+F66+F77 -> 1.6792504 | G13: =G23+G33+G44+G55+G66+G77 -> 1.8745064 | H13: =H23+H33+H44+H55+H66+H77 -> 1.7615035 | I13: =I23+I33+I44+I55+I66+I77 -> 1.6458124 | J13: =J23+J33+J44+J55+J66+J77 -> 1.5707945 | K13: =K23+K33+K44+K55+K66+K77 -> 1.5633757 | L13: =L23+L33+L44+L55+L66+L77 -> 1.5833336 | ... O13: =O23+O33+O44+O55+O66+O77 -> 1.5833336
A14: * | B14: =B24 -> TC | C14: =C24 -> TRN.TRUCK.COMMERCIAL | D14: =D24 -> bn-vmt | E14: =E24+E34+E45+E56+E67+E78 -> 0 | F14: =F24+F34+F45+F56+F67+F78 -> 0 | G14: =G24+G34+G45+G56+G67+G78 -> 0 | H14: =H24+H34+H45+H56+H67+H78 -> 0 | I14: =I24+I34+I45+I56+I67+I78 -> 0 | J14: =J24+J34+J45+J56+J67+J78 -> 0 | K14: =K24+K34+K45+K56+K67+K78 -> 0 | L14: =L24+L34+L45+L56+L67+L78 -> 0 | ... O14: =O24+O34+O45+O56+O67+O78 -> 0
A15: *
A16: *R1 | B16: TA | C16: TRN.AIR | D16: bn-pass-miles | E16: =RegionalDMDNYC!C4 -> 0 | F16: =RegionalDMDNYC!D4 -> 0 | G16: =RegionalDMDNYC!E4 -> 0 | H16: =RegionalDMDNYC!F4 -> 0 | I16: =RegionalDMDNYC!G4 -> 0 | J16: =RegionalDMDNYC!H4 -> 0 | K16: =RegionalDMDNYC!I4 -> 0 | L16: =RegionalDMDNYC!J4 -> 0 | ... O16: =RegionalDMDNYC!M4 -> 0
A17: *R1 | B17: TB | C17: TRN.BUS | D17: bn-vmt | E17: =RegionalDMDNYC!C5 -> 0.081762147 | F17: =RegionalDMDNYC!D5 -> 0.081762147 | G17: =RegionalDMDNYC!E5 -> 0.078708991 | H17: =RegionalDMDNYC!F5 -> 0.081963543 | I17: =RegionalDMDNYC!G5 -> 0.085365562 | J17: =RegionalDMDNYC!H5 -> 0.088785316 | K17: =RegionalDMDNYC!I5 -> 0.092129516 | L17: =RegionalDMDNYC!J5 -> 0.095354894 | ... O17: =RegionalDMDNYC!M5 -> 0.11000703
A18: *R1 | B18: TM | C18: TRN.MDV | D18: bn-vmt | E18: =RegionalDMDNYC!C6 -> 0 | F18: =RegionalDMDNYC!D6 -> 0 | G18: =RegionalDMDNYC!E6 -> 0 | H18: =RegionalDMDNYC!F6 -> 0 | I18: =RegionalDMDNYC!G6 -> 0 | J18: =RegionalDMDNYC!H6 -> 0 | K18: =RegionalDMDNYC!I6 -> 0 | L18: =RegionalDMDNYC!J6 -> 0 | ... O18: =RegionalDMDNYC!M6 -> 0
A19: *R1 | B19: =Commodities!$C$12 -> THS | C19: =Commodities!$D$12 -> TRN.HDV Short Haul | D19: bn-vmt | E19: =RegionalDMDNYC!C7 -> 0.26756986 | F19: =RegionalDMDNYC!D7 -> 0.26756986 | G19: =RegionalDMDNYC!E7 -> 0.287736 | H19: =RegionalDMDNYC!F7 -> 0.30020743 | I19: =RegionalDMDNYC!G7 -> 0.31667271 | J19: =RegionalDMDNYC!H7 -> 0.32848566 | K19: =RegionalDMDNYC!I7 -> 0.34455911 | L19: =RegionalDMDNYC!J7 -> 0.36460463 | ... O19: =RegionalDMDNYC!M7 -> 0.43213555
A20: *R1 | B20: =Commodities!$C$13 -> THL | C20: =Commodities!$D$13 -> TRN.HDV Long Haul | D20: bn-vmt | E20: =RegionalDMDNYC!C8 -> 0 | F20: =RegionalDMDNYC!D8 -> 0 | G20: =RegionalDMDNYC!E8 -> 0 | H20: =RegionalDMDNYC!F8 -> 0 | I20: =RegionalDMDNYC!G8 -> 0 | J20: =RegionalDMDNYC!H8 -> 0 | K20: =RegionalDMDNYC!I8 -> 0 | L20: =RegionalDMDNYC!J8 -> 0 | ... O20: =RegionalDMDNYC!M8 -> 0
A21: *R1 | B21: TRF | C21: TRN.RAIL.FREIGHT | D21: bn-t-m | E21: =RegionalDMDNYC!C9 -> 0 | F21: =RegionalDMDNYC!D9 -> 0 | G21: =RegionalDMDNYC!E9 -> 0 | H21: =RegionalDMDNYC!F9 -> 0 | I21: =RegionalDMDNYC!G9 -> 0 | J21: =RegionalDMDNYC!H9 -> 0 | K21: =RegionalDMDNYC!I9 -> 0 | L21: =RegionalDMDNYC!J9 -> 0 | ... O21: =RegionalDMDNYC!M9 -> 0
A22: *R1 | B22: TRP | C22: TRN.RAIL.PASS | D22: bn-pass-miles | E22: =RegionalDMDNYC!C10 -> 18.739064 | F22: =RegionalDMDNYC!D10 -> 18.739064 | G22: =RegionalDMDNYC!E10 -> 19.650375 | H22: =RegionalDMDNYC!F10 -> 20.64739 | I22: =RegionalDMDNYC!G10 -> 21.878636 | J22: =RegionalDMDNYC!H10 -> 22.986326 | K22: =RegionalDMDNYC!I10 -> 24.016515 | L22: =RegionalDMDNYC!J10 -> 25.472087 | ... O22: =RegionalDMDNYC!M10 -> 30.143281
A23: *R1 | B23: TS | C23: TRN.SHIP | D23: bn-t-m | E23: =RegionalDMDNYC!C11 -> 0 | F23: =RegionalDMDNYC!D11 -> 0 | G23: =RegionalDMDNYC!E11 -> 0 | H23: =RegionalDMDNYC!F11 -> 0 | I23: =RegionalDMDNYC!G11 -> 0 | J23: =RegionalDMDNYC!H11 -> 0 | K23: =RegionalDMDNYC!I11 -> 0 | L23: =RegionalDMDNYC!J11 -> 0 | ... O23: =RegionalDMDNYC!M11 -> 0
A24: *R1 | B24: TC | C24: =Commodities!D18 -> TRN.TRUCK.COMMERCIAL | D24: bn-vmt | E24: =RegionalDMDNYC!C12 -> 0 | F24: =RegionalDMDNYC!D12 -> 0 | G24: =RegionalDMDNYC!E12 -> 0 | H24: =RegionalDMDNYC!F12 -> 0 | I24: =RegionalDMDNYC!G12 -> 0 | J24: =RegionalDMDNYC!H12 -> 0 | K24: =RegionalDMDNYC!I12 -> 0 | L24: =RegionalDMDNYC!J12 -> 0 | ... O24: =RegionalDMDNYC!M12 -> 0
A25: *R2
A26: *R2 | B26: =Commodities!C$9 -> TA | C26: =Commodities!D$9 -> TRN.AIR | D26: bn-pass-miles | E26: =RegionalDMDNYC!C16 -> 0 | F26: =RegionalDMDNYC!D16 -> 0 | G26: =RegionalDMDNYC!E16 -> 0 | H26: =RegionalDMDNYC!F16 -> 0 | I26: =RegionalDMDNYC!G16 -> 0 | J26: =RegionalDMDNYC!H16 -> 0 | K26: =RegionalDMDNYC!I16 -> 0 | L26: =RegionalDMDNYC!J16 -> 0 | ... O26: =RegionalDMDNYC!M16 -> 0
A27: =IF(LEFT(Commodities!B$10,1)="*",A$25,RIGHT(A$25,2)) -> R2 | B27: =Commodities!C$10 -> TB | C27: =Commodities!D$10 -> TRN.BUS | D27: bn-vmt | E27: =RegionalDMDNYC!C17 -> 0.11124684 | F27: =RegionalDMDNYC!D17 -> 0.11124684 | G27: =RegionalDMDNYC!E17 -> 0.10662753 | H27: =RegionalDMDNYC!F17 -> 0.11152253 | I27: =RegionalDMDNYC!G17 -> 0.11662449 | J27: =RegionalDMDNYC!H17 -> 0.12177343 | K27: =RegionalDMDNYC!I17 -> 0.12687698 | L27: =RegionalDMDNYC!J17 -> 0.13184164 | ... O27: =RegionalDMDNYC!M17 -> 0.15156288
A28: R2 | B28: =Commodities!C$11 -> TM | C28: =Commodities!D$11 -> TRN.Medium Duty Trucks | D28: bn-vmt | E28: =RegionalDMDNYC!C18 -> 0.15428842 | F28: =RegionalDMDNYC!D18 -> 0.15428842 | G28: =RegionalDMDNYC!E18 -> 0.15699136 | H28: =RegionalDMDNYC!F18 -> 0.157689 | I28: =RegionalDMDNYC!G18 -> 0.16083143 | J28: =RegionalDMDNYC!H18 -> 0.16397387 | K28: =RegionalDMDNYC!I18 -> 0.16654945 | L28: =RegionalDMDNYC!J18 -> 0.16912503 | ... O28: =RegionalDMDNYC!M18 -> 0.17925624
A29: =IF(LEFT(Commodities!B$12,1)="*",A$25,RIGHT(A$25,2)) -> R2 | B29: =Commodities!C$12 -> THS | C29: =Commodities!$D$12 -> TRN.HDV Short Haul | D29: bn-vmt | E29: =RegionalDMDNYC!C19 -> 0.19945284 | F29: =RegionalDMDNYC!D19 -> 0.19945284 | G29: =RegionalDMDNYC!E19 -> 0.20218913 | H29: =RegionalDMDNYC!F19 -> 0.21187607 | I29: =RegionalDMDNYC!G19 -> 0.22440695 | J29: =RegionalDMDNYC!H19 -> 0.23369339 | K29: =RegionalDMDNYC!I19 -> 0.24613104 | L29: =RegionalDMDNYC!J19 -> 0.26148719 | ... O29: =RegionalDMDNYC!M19 -> 0.30882397
A30: =IF(LEFT(Commodities!B$13,1)="*",A$25,RIGHT(A$25,2)) -> *R2 | B30: =Commodities!C$13 -> THL | C30: =Commodities!$D$13 -> TRN.HDV Long Haul | D30: bn-vmt | E30: =RegionalDMDNYC!C20 -> 0 | F30: =RegionalDMDNYC!D20 -> 0 | G30: =RegionalDMDNYC!E20 -> 0 | H30: =RegionalDMDNYC!F20 -> 0 | I30: =RegionalDMDNYC!G20 -> 0 | J30: =RegionalDMDNYC!H20 -> 0 | K30: =RegionalDMDNYC!I20 -> 0 | L30: =RegionalDMDNYC!J20 -> 0 | ... O30: =RegionalDMDNYC!M20 -> 0
A31: =IF(LEFT(Commodities!B$15,1)="*",A$25,RIGHT(A$25,2)) -> *R2 | B31: =Commodities!C$15 -> TRF | C31: =Commodities!D$15 -> TRN.RAIL.FREIGHT | D31: bn-t-m | E31: =RegionalDMDNYC!C21 -> 0 | F31: =RegionalDMDNYC!D21 -> 0 | G31: =RegionalDMDNYC!E21 -> 0 | H31: =RegionalDMDNYC!F21 -> 0 | I31: =RegionalDMDNYC!G21 -> 0 | J31: =RegionalDMDNYC!H21 -> 0 | K31: =RegionalDMDNYC!I21 -> 0 | L31: =RegionalDMDNYC!J21 -> 0 | ... O31: =RegionalDMDNYC!M21 -> 0
A32: =IF(LEFT(Commodities!B$17,1)="*",A$25,RIGHT(A$25,2)) -> R2 | B32: =Commodities!C$17 -> TRP | C32: =Commodities!D$17 -> TRN.RAIL.PASS | D32: bn-pass-miles | E32: =RegionalDMDNYC!C22 -> 2.8768283 | F32: =RegionalDMDNYC!D22 -> 2.8768283 | G32: =RegionalDMDNYC!E22 -> 3.0036305 | H32: =RegionalDMDNYC!F22 -> 3.1698426 | I32: =RegionalDMDNYC!G22 -> 3.3725467 | J32: =RegionalDMDNYC!H22 -> 3.5572274 | K32: =RegionalDMDNYC!I22 -> 3.7318543 | L32: =RegionalDMDNYC!J22 -> 3.973789 | ... O32: =RegionalDMDNYC!M22 -> 4.685906
A33: =IF(LEFT(Commodities!B$14,1)="*",A$25,RIGHT(A$25,2)) -> R2 | B33: =Commodities!C$14 -> TS | C33: =Commodities!D$14 -> TRN.SHIP | D33: bn-t-m | E33: =RegionalDMDNYC!C23 -> 1.6792504 | F33: =RegionalDMDNYC!D23 -> 1.6792504 | G33: =RegionalDMDNYC!E23 -> 1.8745064 | H33: =RegionalDMDNYC!F23 -> 1.7615035 | I33: =RegionalDMDNYC!G23 -> 1.6458124 | J33: =RegionalDMDNYC!H23 -> 1.5707945 | K33: =RegionalDMDNYC!I23 -> 1.5633757 | L33: =RegionalDMDNYC!J23 -> 1.5833336 | ... O33: =RegionalDMDNYC!M23 -> 1.5833336
A34: =IF(LEFT(Commodities!B$18,1)="*",A$25,RIGHT(A$25,2)) -> *R2 | B34: =Commodities!C$18 -> TC | C34: =Commodities!D$18 -> TRN.TRUCK.COMMERCIAL | D34: bn-vmt | E34: =RegionalDMDNYC!C24 -> 0 | F34: =RegionalDMDNYC!D24 -> 0 | G34: =RegionalDMDNYC!E24 -> 0 | H34: =RegionalDMDNYC!F24 -> 0 | I34: =RegionalDMDNYC!G24 -> 0 | J34: =RegionalDMDNYC!H24 -> 0 | K34: =RegionalDMDNYC!I24 -> 0 | L34: =RegionalDMDNYC!J24 -> 0 | ... O34: =RegionalDMDNYC!M24 -> 0
A35: =IF(LEFT(Commodities!B16,1)="*",A$25,RIGHT(A$25,2)) -> *R2 | B35: =Commodities!C16 -> TSW | C35: =Commodities!D16 -> TRN.MSW | D35: =Commodities!E16 -> bn-vmt
A36: *R3
A37: *R3 | B37: =Commodities!C$9 -> TA | C37: =Commodities!D$9 -> TRN.AIR | D37: bn-pass-miles | E37: =RegionalDMDNYC!C28 -> 0 | F37: =RegionalDMDNYC!D28 -> 0 | G37: =RegionalDMDNYC!E28 -> 0 | H37: =RegionalDMDNYC!F28 -> 0 | I37: =RegionalDMDNYC!G28 -> 0 | J37: =RegionalDMDNYC!H28 -> 0 | K37: =RegionalDMDNYC!I28 -> 0 | L37: =RegionalDMDNYC!J28 -> 0 | ... O37: =RegionalDMDNYC!M28 -> 0
A38: =IF(LEFT(Commodities!B$10,1)="*",A$36,RIGHT(A$36,2)) -> R3 | B38: =Commodities!C$10 -> TB | C38: =Commodities!D$10 -> TRN.BUS | D38: bn-vmt | E38: =RegionalDMDNYC!C29 -> 0.06035811 | F38: =RegionalDMDNYC!D29 -> 0.06035811 | G38: =RegionalDMDNYC!E29 -> 0.058857032 | H38: =RegionalDMDNYC!F29 -> 0.060922173 | I38: =RegionalDMDNYC!G29 -> 0.064023283 | J38: =RegionalDMDNYC!H29 -> 0.067165212 | K38: =RegionalDMDNYC!I29 -> 0.070264245 | L38: =RegionalDMDNYC!J29 -> 0.07329992 | ... O38: =RegionalDMDNYC!M29 -> 0.08534026
A39: R3 | B39: =Commodities!C$11 -> TM | C39: =Commodities!D$11 -> TRN.Medium Duty Trucks | D39: bn-vmt | E39: =RegionalDMDNYC!C30 -> 0.083710759 | F39: =RegionalDMDNYC!D30 -> 0.083710759 | G39: =RegionalDMDNYC!E30 -> 0.086657226 | H39: =RegionalDMDNYC!F30 -> 0.086141847 | I39: =RegionalDMDNYC!G30 -> 0.088291541 | J39: =RegionalDMDNYC!H30 -> 0.090441235 | K39: =RegionalDMDNYC!I30 -> 0.09223479 | L39: =RegionalDMDNYC!J30 -> 0.094028345 | ... O39: =RegionalDMDNYC!M30 -> 0.10093352
A40: =IF(LEFT(Commodities!B$12,1)="*",A$36,RIGHT(A$36,2)) -> R3 | B40: =Commodities!C$12 -> THS | C40: =Commodities!$D$12 -> TRN.HDV Short Haul | D40: bn-vmt | E40: =RegionalDMDNYC!C31 -> 0.10821518 | F40: =RegionalDMDNYC!D31 -> 0.10821518 | G40: =RegionalDMDNYC!E31 -> 0.11160582 | H40: =RegionalDMDNYC!F31 -> 0.11574299 | I40: =RegionalDMDNYC!G31 -> 0.12319256 | J40: =RegionalDMDNYC!H31 -> 0.12889566 | K40: =RegionalDMDNYC!I31 -> 0.13630693 | L40: =RegionalDMDNYC!J31 -> 0.14537888 | ... O40: =RegionalDMDNYC!M31 -> 0.173889
A41: =IF(LEFT(Commodities!B$13,1)="*",A$36,RIGHT(A$36,2)) -> *R3 | B41: =Commodities!C$13 -> THL | C41: =Commodities!$D$13 -> TRN.HDV Long Haul | D41: bn-vmt | E41: =RegionalDMDNYC!C32 -> 0 | F41: =RegionalDMDNYC!D32 -> 0 | G41: =RegionalDMDNYC!E32 -> 0 | H41: =RegionalDMDNYC!F32 -> 0 | I41: =RegionalDMDNYC!G32 -> 0 | J41: =RegionalDMDNYC!H32 -> 0 | K41: =RegionalDMDNYC!I32 -> 0 | L41: =RegionalDMDNYC!J32 -> 0 | ... O41: =RegionalDMDNYC!M32 -> 0
A42: =IF(LEFT(Commodities!B$15,1)="*",A$36,RIGHT(A$36,2)) -> *R3 | B42: =Commodities!C$15 -> TRF | C42: =Commodities!D$15 -> TRN.RAIL.FREIGHT | D42: bn-t-m | E42: =RegionalDMDNYC!C33 -> 0 | F42: =RegionalDMDNYC!D33 -> 0 | G42: =RegionalDMDNYC!E33 -> 0 | H42: =RegionalDMDNYC!F33 -> 0 | I42: =RegionalDMDNYC!G33 -> 0 | J42: =RegionalDMDNYC!H33 -> 0 | K42: =RegionalDMDNYC!I33 -> 0 | L42: =RegionalDMDNYC!J33 -> 0 | ... O42: =RegionalDMDNYC!M33 -> 0
A43: =IF(LEFT(Commodities!B$17,1)="*",A$36,RIGHT(A$36,2)) -> R3 | B43: =Commodities!C$17 -> TRP | C43: =Commodities!D$17 -> TRN.RAIL.PASS | D43: bn-pass-miles | E43: =RegionalDMDNYC!C34 -> 1.5608526 | F43: =RegionalDMDNYC!D34 -> 1.5608526 | G43: =RegionalDMDNYC!E34 -> 1.6579656 | H43: =RegionalDMDNYC!F34 -> 1.7316116 | I43: =RegionalDMDNYC!G34 -> 1.8514251 | J43: =RegionalDMDNYC!H34 -> 1.9620202 | K43: =RegionalDMDNYC!I34 -> 2.0666943 | L43: =RegionalDMDNYC!J34 -> 2.2093051 | ... O43: =RegionalDMDNYC!M34 -> 2.6384854
A44: =IF(LEFT(Commodities!B$14,1)="*",A$36,RIGHT(A$36,2)) -> R3 | B44: =Commodities!C$14 -> TS | C44: =Commodities!D$14 -> TRN.SHIP | D44: bn-t-m | E44: =RegionalDMDNYC!C35 -> 0 | F44: =RegionalDMDNYC!D35 -> 0 | G44: =RegionalDMDNYC!E35 -> 0 | H44: =RegionalDMDNYC!F35 -> 0 | I44: =RegionalDMDNYC!G35 -> 0 | J44: =RegionalDMDNYC!H35 -> 0 | K44: =RegionalDMDNYC!I35 -> 0 | L44: =RegionalDMDNYC!J35 -> 0 | ... O44: =RegionalDMDNYC!M35 -> 0
A45: =IF(LEFT(Commodities!B$18,1)="*",A$36,RIGHT(A$36,2)) -> *R3 | B45: =Commodities!C$18 -> TC | C45: =Commodities!D$18 -> TRN.TRUCK.COMMERCIAL | D45: bn-vmt | E45: =RegionalDMDNYC!C36 -> 0 | F45: =RegionalDMDNYC!D36 -> 0 | G45: =RegionalDMDNYC!E36 -> 0 | H45: =RegionalDMDNYC!F36 -> 0 | I45: =RegionalDMDNYC!G36 -> 0 | J45: =RegionalDMDNYC!H36 -> 0 | K45: =RegionalDMDNYC!I36 -> 0 | L45: =RegionalDMDNYC!J36 -> 0 | ... O45: =RegionalDMDNYC!M36 -> 0
A46: =IF(LEFT(Commodities!B$16,1)="*",A$36,RIGHT(A$36,2)) -> *R3 | B46: =Commodities!C16 -> TSW | C46: =Commodities!D16 -> TRN.MSW | D46: =Commodities!E16 -> bn-vmt
A47: *R4
A48: *R4 | B48: =Commodities!C$9 -> TA | C48: =Commodities!D$9 -> TRN.AIR | D48: bn-pass-miles | E48: =RegionalDMDNYC!C40 -> 0 | F48: =RegionalDMDNYC!D40 -> 0 | G48: =RegionalDMDNYC!E40 -> 0 | H48: =RegionalDMDNYC!F40 -> 0 | I48: =RegionalDMDNYC!G40 -> 0 | J48: =RegionalDMDNYC!H40 -> 0 | K48: =RegionalDMDNYC!I40 -> 0 | L48: =RegionalDMDNYC!J40 -> 0 | ... O48: =RegionalDMDNYC!M40 -> 0
A49: =IF(LEFT(Commodities!B$10,1)="*",A$47,RIGHT(A$47,2)) -> R4 | B49: =Commodities!C$10 -> TB | C49: =Commodities!D$10 -> TRN.BUS | D49: bn-vmt | E49: =RegionalDMDNYC!C41 -> 0.069106738 | F49: =RegionalDMDNYC!D41 -> 0.069106738 | G49: =RegionalDMDNYC!E41 -> 0.066503038 | H49: =RegionalDMDNYC!F41 -> 0.068985669 | I49: =RegionalDMDNYC!G41 -> 0.071561889 | J49: =RegionalDMDNYC!H41 -> 0.074139172 | K49: =RegionalDMDNYC!I41 -> 0.076389637 | L49: =RegionalDMDNYC!J41 -> 0.078515614 | ... O49: =RegionalDMDNYC!M41 -> 0.08927883
A50: R4 | B50: =Commodities!C$11 -> TM | C50: =Commodities!D$11 -> TRN.Medium Duty Trucks | D50: bn-vmt | E50: =RegionalDMDNYC!C42 -> 0.095844247 | F50: =RegionalDMDNYC!D42 -> 0.095844247 | G50: =RegionalDMDNYC!E42 -> 0.097914703 | H50: =RegionalDMDNYC!F42 -> 0.097543352 | I50: =RegionalDMDNYC!G42 -> 0.098687682 | J50: =RegionalDMDNYC!H42 -> 0.099832012 | K50: =RegionalDMDNYC!I42 -> 0.1002755 | L50: =RegionalDMDNYC!J42 -> 0.10071898 | ... O50: =RegionalDMDNYC!M42 -> 0.10559174
A51: =IF(LEFT(Commodities!B$12,1)="*",A$47,RIGHT(A$47,2)) -> R4 | B51: =Commodities!C$12 -> THS | C51: =Commodities!$D$12 -> TRN.HDV Short Haul | D51: bn-vmt | E51: =RegionalDMDNYC!C43 -> 0.12390047 | F51: =RegionalDMDNYC!D43 -> 0.12390047 | G51: =RegionalDMDNYC!E43 -> 0.12610432 | H51: =RegionalDMDNYC!F43 -> 0.13106243 | I51: =RegionalDMDNYC!G43 -> 0.13769822 | J51: =RegionalDMDNYC!H43 -> 0.14227927 | K51: =RegionalDMDNYC!I43 -> 0.1481897 | L51: =RegionalDMDNYC!J43 -> 0.15572339 | ... O51: =RegionalDMDNYC!M43 -> 0.18191422
A52: =IF(LEFT(Commodities!B$13,1)="*",A$47,RIGHT(A$47,2)) -> *R4 | B52: =Commodities!C$13 -> THL | C52: =Commodities!$D$13 -> TRN.HDV Long Haul | D52: bn-vmt | E52: =RegionalDMDNYC!C44 -> 0 | F52: =RegionalDMDNYC!D44 -> 0 | G52: =RegionalDMDNYC!E44 -> 0 | H52: =RegionalDMDNYC!F44 -> 0 | I52: =RegionalDMDNYC!G44 -> 0 | J52: =RegionalDMDNYC!H44 -> 0 | K52: =RegionalDMDNYC!I44 -> 0 | L52: =RegionalDMDNYC!J44 -> 0 | ... O52: =RegionalDMDNYC!M44 -> 0
A53: =IF(LEFT(Commodities!B$15,1)="*",A$47,RIGHT(A$47,2)) -> *R4 | B53: =Commodities!C$15 -> TRF | C53: =Commodities!D$15 -> TRN.RAIL.FREIGHT | D53: bn-t-m | E53: =RegionalDMDNYC!C45 -> 0 | F53: =RegionalDMDNYC!D45 -> 0 | G53: =RegionalDMDNYC!E45 -> 0 | H53: =RegionalDMDNYC!F45 -> 0 | I53: =RegionalDMDNYC!G45 -> 0 | J53: =RegionalDMDNYC!H45 -> 0 | K53: =RegionalDMDNYC!I45 -> 0 | L53: =RegionalDMDNYC!J45 -> 0 | ... O53: =RegionalDMDNYC!M45 -> 0
A54: =IF(LEFT(Commodities!B$17,1)="*",A$47,RIGHT(A$47,2)) -> R4 | B54: =Commodities!C$17 -> TRP | C54: =Commodities!D$17 -> TRN.RAIL.PASS | D54: bn-pass-miles | E54: =RegionalDMDNYC!C46 -> 1.787091 | F54: =RegionalDMDNYC!D46 -> 1.787091 | G54: =RegionalDMDNYC!E46 -> 1.8733488 | H54: =RegionalDMDNYC!F46 -> 1.9608031 | I54: =RegionalDMDNYC!G46 -> 2.0694265 | J54: =RegionalDMDNYC!H46 -> 2.1657425 | K54: =RegionalDMDNYC!I46 -> 2.2468615 | L54: =RegionalDMDNYC!J46 -> 2.3665094 | ... O54: =RegionalDMDNYC!M46 -> 2.7602551
A55: =IF(LEFT(Commodities!B$14,1)="*",A$47,RIGHT(A$47,2)) -> R4 | B55: =Commodities!C$14 -> TS | C55: =Commodities!D$14 -> TRN.SHIP | D55: bn-t-m | E55: =RegionalDMDNYC!C47 -> 0 | F55: =RegionalDMDNYC!D47 -> 0 | G55: =RegionalDMDNYC!E47 -> 0 | H55: =RegionalDMDNYC!F47 -> 0 | I55: =RegionalDMDNYC!G47 -> 0 | J55: =RegionalDMDNYC!H47 -> 0 | K55: =RegionalDMDNYC!I47 -> 0 | L55: =RegionalDMDNYC!J47 -> 0 | ... O55: =RegionalDMDNYC!M47 -> 0
A56: =IF(LEFT(Commodities!B$18,1)="*",A$47,RIGHT(A$47,2)) -> *R4 | B56: =Commodities!C$18 -> TC | C56: =Commodities!D$18 -> TRN.TRUCK.COMMERCIAL | D56: bn-vmt | E56: =RegionalDMDNYC!C48 -> 0 | F56: =RegionalDMDNYC!D48 -> 0 | G56: =RegionalDMDNYC!E48 -> 0 | H56: =RegionalDMDNYC!F48 -> 0 | I56: =RegionalDMDNYC!G48 -> 0 | J56: =RegionalDMDNYC!H48 -> 0 | K56: =RegionalDMDNYC!I48 -> 0 | L56: =RegionalDMDNYC!J48 -> 0 | ... O56: =RegionalDMDNYC!M48 -> 0
A57: =IF(LEFT(Commodities!B$16,1)="*",A$47,RIGHT(A$47,2)) -> *R4 | B57: =Commodities!C16 -> TSW | C57: =Commodities!D16 -> TRN.MSW | D57: =Commodities!E16 -> bn-vmt
A58: *R5
A59: *R5 | B59: =Commodities!C$9 -> TA | C59: =Commodities!D$9 -> TRN.AIR | D59: bn-pass-miles | E59: =RegionalDMDNYC!C52 -> 0 | F59: =RegionalDMDNYC!D52 -> 0 | G59: =RegionalDMDNYC!E52 -> 0 | H59: =RegionalDMDNYC!F52 -> 0 | I59: =RegionalDMDNYC!G52 -> 0 | J59: =RegionalDMDNYC!H52 -> 0 | K59: =RegionalDMDNYC!I52 -> 0 | L59: =RegionalDMDNYC!J52 -> 0 | ... O59: =RegionalDMDNYC!M52 -> 0
A60: =IF(LEFT(Commodities!B$10,1)="*",A$58,RIGHT(A$58,2)) -> R5 | B60: =Commodities!C$10 -> TB | C60: =Commodities!D$10 -> TRN.BUS | D60: bn-vmt | E60: =RegionalDMDNYC!C53 -> 0.020425596 | F60: =RegionalDMDNYC!D53 -> 0.020425596 | G60: =RegionalDMDNYC!E53 -> 0.019190759 | H60: =RegionalDMDNYC!F53 -> 0.0205134 | I60: =RegionalDMDNYC!G53 -> 0.021261409 | J60: =RegionalDMDNYC!H53 -> 0.022008862 | K60: =RegionalDMDNYC!I53 -> 0.02265284 | L60: =RegionalDMDNYC!J53 -> 0.023258741 | ... O60: =RegionalDMDNYC!M53 -> 0.027665324
A61: R5 | B61: =Commodities!C$11 -> TM | C61: =Commodities!D$11 -> TRN.Medium Duty Trucks | D61: bn-vmt | E61: =RegionalDMDNYC!C54 -> 0.028328292 | F61: =RegionalDMDNYC!D54 -> 0.028328292 | G61: =RegionalDMDNYC!E54 -> 0.028255213 | H61: =RegionalDMDNYC!F54 -> 0.029005239 | I61: =RegionalDMDNYC!G54 -> 0.029320623 | J61: =RegionalDMDNYC!H54 -> 0.029636006 | K61: =RegionalDMDNYC!I54 -> 0.029736034 | L61: =RegionalDMDNYC!J54 -> 0.029836061 | ... O61: =RegionalDMDNYC!M54 -> 0.032720295
A62: =IF(LEFT(Commodities!B$12,1)="*",A$58,RIGHT(A$58,2)) -> R5 | B62: =Commodities!C$12 -> THS | C62: =Commodities!$D$12 -> TRN.HDV Short Haul | D62: bn-vmt | E62: =RegionalDMDNYC!C55 -> 0.036620755 | F62: =RegionalDMDNYC!D55 -> 0.036620755 | G62: =RegionalDMDNYC!E55 -> 0.03638988 | H62: =RegionalDMDNYC!F55 -> 0.038972384 | I62: =RegionalDMDNYC!G55 -> 0.040910856 | J62: =RegionalDMDNYC!H55 -> 0.042236845 | K62: =RegionalDMDNYC!I55 -> 0.043944671 | L62: =RegionalDMDNYC!J55 -> 0.046130058 | ... O62: =RegionalDMDNYC!M55 -> 0.056370764
A63: =IF(LEFT(Commodities!B$13,1)="*",A$58,RIGHT(A$58,2)) -> *R5 | B63: =Commodities!C$13 -> THL | C63: =Commodities!$D$13 -> TRN.HDV Long Haul | D63: bn-vmt | E63: =RegionalDMDNYC!C56 -> 0 | F63: =RegionalDMDNYC!D56 -> 0 | G63: =RegionalDMDNYC!E56 -> 0 | H63: =RegionalDMDNYC!F56 -> 0 | I63: =RegionalDMDNYC!G56 -> 0 | J63: =RegionalDMDNYC!H56 -> 0 | K63: =RegionalDMDNYC!I56 -> 0 | L63: =RegionalDMDNYC!J56 -> 0 | ... O63: =RegionalDMDNYC!M56 -> 0
A64: =IF(LEFT(Commodities!B$15,1)="*",A$58,RIGHT(A$58,2)) -> *R5 | B64: =Commodities!C$15 -> TRF | C64: =Commodities!D$15 -> TRN.RAIL.FREIGHT | D64: bn-t-m | E64: =RegionalDMDNYC!C57 -> 0 | F64: =RegionalDMDNYC!D57 -> 0 | G64: =RegionalDMDNYC!E57 -> 0 | H64: =RegionalDMDNYC!F57 -> 0 | I64: =RegionalDMDNYC!G57 -> 0 | J64: =RegionalDMDNYC!H57 -> 0 | K64: =RegionalDMDNYC!I57 -> 0 | L64: =RegionalDMDNYC!J57 -> 0 | ... O64: =RegionalDMDNYC!M57 -> 0
A65: =IF(LEFT(Commodities!B$17,1)="*",A$58,RIGHT(A$58,2)) -> R5 | B65: =Commodities!C$17 -> TRP | C65: =Commodities!D$17 -> TRN.RAIL.PASS | D65: bn-pass-miles | E65: =RegionalDMDNYC!C58 -> 0.52820318 | F65: =RegionalDMDNYC!D58 -> 0.52820318 | G65: =RegionalDMDNYC!E58 -> 0.53395268 | H65: =RegionalDMDNYC!F58 -> 0.58305933 | I65: =RegionalDMDNYC!G58 -> 0.61483734 | J65: =RegionalDMDNYC!H58 -> 0.64291961 | K65: =RegionalDMDNYC!I58 -> 0.66629188 | L65: =RegionalDMDNYC!J58 -> 0.70103289 | ... O65: =RegionalDMDNYC!M58 -> 0.85533551
A66: =IF(LEFT(Commodities!B$14,1)="*",A$58,RIGHT(A$58,2)) -> R5 | B66: =Commodities!C$14 -> TS | C66: =Commodities!D$14 -> TRN.SHIP | D66: bn-t-m | E66: =RegionalDMDNYC!C59 -> 0 | F66: =RegionalDMDNYC!D59 -> 0 | G66: =RegionalDMDNYC!E59 -> 0 | H66: =RegionalDMDNYC!F59 -> 0 | I66: =RegionalDMDNYC!G59 -> 0 | J66: =RegionalDMDNYC!H59 -> 0 | K66: =RegionalDMDNYC!I59 -> 0 | L66: =RegionalDMDNYC!J59 -> 0 | ... O66: =RegionalDMDNYC!M59 -> 0
A67: =IF(LEFT(Commodities!B$18,1)="*",A$58,RIGHT(A$58,2)) -> *R5 | B67: =Commodities!C$18 -> TC | C67: =Commodities!D$18 -> TRN.TRUCK.COMMERCIAL | D67: bn-vmt | E67: =RegionalDMDNYC!C60 -> 0 | F67: =RegionalDMDNYC!D60 -> 0 | G67: =RegionalDMDNYC!E60 -> 0 | H67: =RegionalDMDNYC!F60 -> 0 | I67: =RegionalDMDNYC!G60 -> 0 | J67: =RegionalDMDNYC!H60 -> 0 | K67: =RegionalDMDNYC!I60 -> 0 | L67: =RegionalDMDNYC!J60 -> 0 | ... O67: =RegionalDMDNYC!M60 -> 0
A68: =IF(LEFT(Commodities!B$16,1)="*",A$58,RIGHT(A$58,2)) -> *R5 | B68: =Commodities!C16 -> TSW | C68: =Commodities!D16 -> TRN.MSW | D68: =Commodities!E16 -> bn-vmt
A69: *R6
A70: R6 | B70: =Commodities!C$9 -> TA | C70: =Commodities!D$9 -> TRN.AIR | D70: bn-pass-miles | E70: =RegionalDMDNYC!C64 -> 0.01747708 | F70: =RegionalDMDNYC!D64 -> 0.014855518 | G70: =RegionalDMDNYC!E64 -> 0.019044073 | H70: =RegionalDMDNYC!F64 -> 0.019869506 | I70: =RegionalDMDNYC!G64 -> 0.020959275 | J70: =RegionalDMDNYC!H64 -> 0.021741127 | K70: =RegionalDMDNYC!I64 -> 0.022804962 | L70: =RegionalDMDNYC!J64 -> 0.024131694 | ... O70: =RegionalDMDNYC!M64 -> 0.02860129
A71: =IF(LEFT(Commodities!B$10,1)="*",A$69,RIGHT(A$69,2)) -> R6 | B71: =Commodities!C$10 -> TB | C71: =Commodities!D$10 -> TRN.BUS | D71: bn-vmt | E71: =RegionalDMDNYC!C65 -> 0.098047132 | F71: =RegionalDMDNYC!D65 -> 0.098047132 | G71: =RegionalDMDNYC!E65 -> 0.09459342 | H71: =RegionalDMDNYC!F65 -> 0.098125389 | I71: =RegionalDMDNYC!G65 -> 0.10154329 | J71: =RegionalDMDNYC!H65 -> 0.1049508 | K71: =RegionalDMDNYC!I65 -> 0.10854498 | L71: =RegionalDMDNYC!J65 -> 0.11198198 | ... O71: =RegionalDMDNYC!M65 -> 0.12941805
A72: R6 | B72: =Commodities!C$11 -> TM | C72: =Commodities!D$11 -> TRN.Medium Duty Trucks | D72: bn-vmt | E72: =RegionalDMDNYC!C66 -> 0.13598173 | F72: =RegionalDMDNYC!D66 -> 0.13598173 | G72: =RegionalDMDNYC!E66 -> 0.13927314 | H72: =RegionalDMDNYC!F66 -> 0.13874591 | I72: =RegionalDMDNYC!G66 -> 0.14003364 | J72: =RegionalDMDNYC!H66 -> 0.14132137 | K72: =RegionalDMDNYC!I66 -> 0.14248532 | L72: =RegionalDMDNYC!J66 -> 0.14364927 | ... O72: =RegionalDMDNYC!M66 -> 0.15306514
A73: =IF(LEFT(Commodities!B$12,1)="*",A$69,RIGHT(A$69,2)) -> R6 | B73: =Commodities!C$12 -> THS | C73: =Commodities!$D$12 -> TRN.HDV Short Haul | D73: bn-vmt | E73: =RegionalDMDNYC!C67 -> 0.17578728 | F73: =RegionalDMDNYC!D67 -> 0.17578728 | G73: =RegionalDMDNYC!E67 -> 0.17936983 | H73: =RegionalDMDNYC!F67 -> 0.18642352 | I73: =RegionalDMDNYC!G67 -> 0.19538794 | J73: =RegionalDMDNYC!H67 -> 0.20140936 | K73: =RegionalDMDNYC!I67 -> 0.21056846 | L73: =RegionalDMDNYC!J67 -> 0.22209866 | ... O73: =RegionalDMDNYC!M67 -> 0.26370174
A74: =IF(LEFT(Commodities!B$13,1)="*",A$69,RIGHT(A$69,2)) -> *R6 | B74: =Commodities!C$13 -> THL | C74: =Commodities!$D$13 -> TRN.HDV Long Haul | D74: bn-vmt | E74: =RegionalDMDNYC!C68 -> 0 | F74: =RegionalDMDNYC!D68 -> 0 | G74: =RegionalDMDNYC!E68 -> 0 | H74: =RegionalDMDNYC!F68 -> 0 | I74: =RegionalDMDNYC!G68 -> 0 | J74: =RegionalDMDNYC!H68 -> 0 | K74: =RegionalDMDNYC!I68 -> 0 | L74: =RegionalDMDNYC!J68 -> 0 | ... O74: =RegionalDMDNYC!M68 -> 0
A75: =IF(LEFT(Commodities!B$15,1)="*",A$69,RIGHT(A$69,2)) -> *R6 | B75: =Commodities!C$15 -> TRF | C75: =Commodities!D$15 -> TRN.RAIL.FREIGHT | D75: bn-t-m | E75: =RegionalDMDNYC!C69 -> 0 | F75: =RegionalDMDNYC!D69 -> 0 | G75: =RegionalDMDNYC!E69 -> 0 | H75: =RegionalDMDNYC!F69 -> 0 | I75: =RegionalDMDNYC!G69 -> 0 | J75: =RegionalDMDNYC!H69 -> 0 | K75: =RegionalDMDNYC!I69 -> 0 | L75: =RegionalDMDNYC!J69 -> 0 | ... O75: =RegionalDMDNYC!M69 -> 0
A76: =IF(LEFT(Commodities!B$17,1)="*",A$69,RIGHT(A$69,2)) -> R6 | B76: =Commodities!C$17 -> TRP | C76: =Commodities!D$17 -> TRN.RAIL.PASS | D76: bn-pass-miles | E76: =RegionalDMDNYC!C70 -> 2.5354857 | F76: =RegionalDMDNYC!D70 -> 2.5354857 | G76: =RegionalDMDNYC!E70 -> 2.6646372 | H76: =RegionalDMDNYC!F70 -> 2.7890512 | I76: =RegionalDMDNYC!G70 -> 2.9364285 | J76: =RegionalDMDNYC!H70 -> 3.0658072 | K76: =RegionalDMDNYC!I70 -> 3.1926522 | L76: =RegionalDMDNYC!J70 -> 3.3752064 | ... O76: =RegionalDMDNYC!M70 -> 4.0012489
A77: =IF(LEFT(Commodities!B$14,1)="*",A$69,RIGHT(A$69,2)) -> R6 | B77: =Commodities!C$14 -> TS | C77: =Commodities!D$14 -> TRN.SHIP | D77: bn-t-m | E77: =RegionalDMDNYC!C71 -> 0 | F77: =RegionalDMDNYC!D71 -> 0 | G77: =RegionalDMDNYC!E71 -> 0 | H77: =RegionalDMDNYC!F71 -> 0 | I77: =RegionalDMDNYC!G71 -> 0 | J77: =RegionalDMDNYC!H71 -> 0 | K77: =RegionalDMDNYC!I71 -> 0 | L77: =RegionalDMDNYC!J71 -> 0 | ... O77: =RegionalDMDNYC!M71 -> 0
A78: =IF(LEFT(Commodities!B$18,1)="*",A$69,RIGHT(A$69,2)) -> *R6 | B78: =Commodities!C$18 -> TC | C78: =Commodities!D$18 -> TRN.TRUCK.COMMERCIAL | D78: bn-vmt | E78: =RegionalDMDNYC!C72 -> 0 | F78: =RegionalDMDNYC!D72 -> 0 | G78: =RegionalDMDNYC!E72 -> 0 | H78: =RegionalDMDNYC!F72 -> 0 | I78: =RegionalDMDNYC!G72 -> 0 | J78: =RegionalDMDNYC!H72 -> 0 | K78: =RegionalDMDNYC!I72 -> 0 | L78: =RegionalDMDNYC!J72 -> 0 | ... O78: =RegionalDMDNYC!M72 -> 0
A79: =IF(LEFT(Commodities!B$16,1)="*",A$69,RIGHT(A$69,2)) -> *R6 | B79: =Commodities!C16 -> TSW | C79: =Commodities!D16 -> TRN.MSW | D79: =Commodities!E16 -> bn-vmt
A80: * | B80: TA | C80: TRN.AIR | D80: bn-pass-miles
A81: *R7 | B81: TB | C81: TRN.BUS | D81: bn-vmt | E81: 0 | F81: 0 | G81: 0 | H81: 0 | I81: 0 | J81: 0 | K81: 0 | L81: 0 | M81: 0 | N81: 0 | O81: 0
A82: *R7 | B82: TM | C82: TRN.MDV | D82: bn-vmt | E82: 0 | F82: 0 | G82: 0 | H82: 0 | I82: 0 | J82: 0 | K82: 0 | L82: 0 | M82: 0 | N82: 0 | O82: 0
A83: *R7 | B83: THS | C83: TRN.HDV Short Haul | D83: bn-vmt | E83: 0 | F83: 0 | G83: 0 | H83: 0 | I83: 0 | J83: 0 | K83: 0 | L83: 0 | M83: 0 | N83: 0 | O83: 0
A84: *R7 | B84: THL | C84: TRN.HDV Long Haul | D84: bn-vmt | E84: 0 | F84: 0 | G84: 0 | H84: 0 | I84: 0 | J84: 0 | K84: 0 | L84: 0 | M84: 0 | N84: 0 | O84: 0
A85: *R7 | B85: TRF | C85: TRN.RAIL.FREIGHT | D85: bn-t-m | E85: 0 | F85: 0 | G85: 0 | H85: 0 | I85: 0 | J85: 0 | K85: 0 | L85: 0 | M85: 0 | N85: 0 | O85: 0
A86: *R7 | B86: TRP | C86: TRN.RAIL.PASS | D86: bn-pass-miles | E86: 0 | F86: 0 | G86: 0 | H86: 0 | I86: 0 | J86: 0 | K86: 0 | L86: 0 | M86: 0 | N86: 0 | O86: 0
A87: *R7 | B87: TS | C87: TRN.SHIP | D87: bn-t-m | E87: 0 | F87: 0 | G87: 0 | H87: 0 | I87: 0 | J87: 0 | K87: 0 | L87: 0 | M87: 0 | N87: 0 | O87: 0
A88: *R7 | B88: TC | C88: TRN.TRUCK.COMMERCIAL | D88: bn-vmt | E88: 0 | F88: 0 | G88: 0 | H88: 0 | I88: 0 | J88: 0 | K88: 0 | L88: 0 | M88: 0 | N88: 0 | O88: 0
A89: *
A90: *R8 | B90: TA | C90: TRN.AIR | D90: bn-pass-miles | E90: 0 | F90: 0 | G90: 0 | H90: 0 | I90: 0 | J90: 0 | K90: 0 | L90: 0 | M90: 0 | N90: 0 | O90: 0
A91: *R8 | B91: TB | C91: TRN.BUS | D91: bn-vmt | E91: 0 | F91: 0 | G91: 0 | H91: 0 | I91: 0 | J91: 0 | K91: 0 | L91: 0 | M91: 0 | N91: 0 | O91: 0
A92: *R8 | B92: TM | C92: TRN.MDV | D92: bn-vmt | E92: 0 | F92: 0 | G92: 0 | H92: 0 | I92: 0 | J92: 0 | K92: 0 | L92: 0 | M92: 0 | N92: 0 | O92: 0
A93: *R8 | B93: THS | C93: TRN.HDV Short Haul | D93: bn-vmt | E93: 0 | F93: 0 | G93: 0 | H93: 0 | I93: 0 | J93: 0 | K93: 0 | L93: 0 | M93: 0 | N93: 0 | O93: 0
A94: *R8 | B94: THL | C94: TRN.HDV Long Haul | D94: bn-vmt | E94: 0 | F94: 0 | G94: 0 | H94: 0 | I94: 0 | J94: 0 | K94: 0 | L94: 0 | M94: 0 | N94: 0 | O94: 0
A95: *R8 | B95: TRF | C95: TRN.RAIL.FREIGHT | D95: bn-t-m | E95: 0 | F95: 0 | G95: 0 | H95: 0 | I95: 0 | J95: 0 | K95: 0 | L95: 0 | M95: 0 | N95: 0 | O95: 0
A96: *R8 | B96: TRP | C96: TRN.RAIL.PASS | D96: bn-pass-miles | E96: 0 | F96: 0 | G96: 0 | H96: 0 | I96: 0 | J96: 0 | K96: 0 | L96: 0 | M96: 0 | N96: 0 | O96: 0
A97: *R8 | B97: TS | C97: TRN.SHIP | D97: bn-t-m | E97: 0 | F97: 0 | G97: 0 | H97: 0 | I97: 0 | J97: 0 | K97: 0 | L97: 0 | M97: 0 | N97: 0 | O97: 0
A98: *R8 | B98: TC | C98: TRN.TRUCK.COMMERCIAL | D98: bn-vmt | E98: 0 | F98: 0 | G98: 0 | H98: 0 | I98: 0 | J98: 0 | K98: 0 | L98: 0 | M98: 0 | N98: 0 | O98: 0
A99: *
A100: *R9 | B100: TA | C100: TRN.AIR | D100: bn-pass-miles | E100: 0 | F100: 0 | G100: 0 | H100: 0 | I100: 0 | J100: 0 | K100: 0 | L100: 0 | M100: 0 | N100: 0 | O100: 0
A101: *R9 | B101: TB | C101: TRN.BUS | D101: bn-vmt | E101: 0 | F101: 0 | G101: 0 | H101: 0 | I101: 0 | J101: 0 | K101: 0 | L101: 0 | M101: 0 | N101: 0 | O101: 0
...

Sheet TechData
A1: TechData | B1: R1,R2,R3,R4,R5,R6
F5: ~FI_T
A6: Region | B6: TechName | C6: *TechDesc | D6: *Units | E6: CommIN | F6: CommOUT | G6: Share~UP | H6: NCAP_START | I6: NCAP_TLIFE | J6: NCAP_DRATE | K6: EFF | L6: EFF~2010 | M6: EFF~2015 | N6: EFF~2020 | O6: EFF~2025 | P6: EFF~2030 | Q6: EFF~2035 | R6: EFF~2040 | S6: EFF~2045 | T6: EFF~2050 | U6: EFF~2055 | V6: NCAP_COST~2010 | W6: NCAP_COST~2015 | X6: NCAP_COST~2020 | Y6: NCAP_COST~2025 | Z6: NCAP_COST~2030 | AA6: NCAP_COST~2035 | AB6: NCAP_COST~2040 | AC6: NCAP_COST~2045 | AD6: NCAP_COST~2050 | AE6: NCAP_COST~2055 | AF6: NCAP_FOM | AG6: PRC_RESID~R2~2010 | AH6: PRC_RESID~R3~2010 | AI6: PRC_RESID~R4~2010 | AJ6: PRC_RESID~R5~2010 | AK6: PRC_RESID~R6~2010 | AL6: PRC_RESID~R6~2015 | AM6: NCAP_AFA | AO6: NCAP_BND~2010 | AP6: NCAP_BND~2015 | AQ6: NCAP_BND~2020 | AR6: NCAP_BND~2025 | AS6: NCAP_BND~2030 | AT6: NCAP_BND~2035 | AU6: NCAP_BND~2040 | AV6: NCAP_BND~2045 | AW6: NCAP_BND~2050 | AX6: NCAP_BND~2055 | BA6: NCAP_TLIFE
A7: *Aviation
A8: =Technologies!B47 -> R2,R3,R4,R5,R6 | B8: =Technologies!C47 -> TAJE | C8: =Technologies!D47 -> Air Jet, Passenger Existing | D8: bn-pass-miles, bn-pmt/a | E8: =Commodities!$C$31 -> TRNJTF1 | F8: TA | G8: 1 | H8: 2010 | I8: =BA8+5 -> 17.5 | K8: ='Air&Marine'!J6 -> 0.43762303 | AF8: ='Air&Marine'!I6 -> 7.462576 | AK8: =CommData!F70*1.1 -> 0.01634107 | AL8: =AK8 -> 0.01634107 | AM8: 1 | AQ8: 0 | AR8: 0 | AS8: 0 | AT8: 0 | AU8: 0 | AV8: 0 | AW8: 0 | AX8: 0 | BA8: ='Air&Marine'!G6 -> 12.5
A9: * | B9: =Technologies!C48 -> TAPE | C9: =Technologies!D48 -> Airplane, General Aviation, exisiting | D9: bn-pass-miles, bn-pmt/a | E9: TRGSLB | F9: TA | G9: 1 | H9: 2010 | I9: =BA9+5 -> 25 | AF9: ='Air&Marine'!I17 -> 1.7511 | AM9: 1 | AO9: 0 | AP9: 0 | AQ9: 0 | AR9: 0 | AS9: 0 | AT9: 0 | AU9: 0 | AV9: 0 | AW9: 0 | AX9: 0 | BA9: 20
A10: *BUSES
A11: =Technologies!B57 -> R2,R3,R4,R5,R6 | B11: =Technologies!C57 -> TBDSLE | C11: ='Rail&Bus2'!B7 -> Bus, Exisiting Diesel | D11: bn-vmt, bn-vmt/a | E11: TBDSL | F11: TB | G11: 1 | H11: 2010 | I11: =BA11+5 -> 17 | K11: ='Rail&Bus2'!I7 -> 0.034970963 | AF11: ='Rail&Bus2'!H7 -> 555.05381 | AG11: =TB!B32 -> 0.098160718 | AH11: =TB!B31 -> 0.053258103 | AI11: =TB!B33 -> 0.060977618 | AJ11: =TB!B35 -> 0.018022905 | AK11: =TB!B34 -> 0.086513714 | AM11: 1 | AO11: 0 | AP11: 0 | AQ11: 0 | AR11: 0 | AS11: 0 | AT11: 0 | AU11: 0 | AV11: 0 | AW11: 0 | AX11: 0 | BA11: ='Rail&Bus2'!F7 -> 12
A12: * | B12: =Technologies!C58 -> TBGSLE | C12: ='Rail&Bus2'!B8 -> Bus, Exisiting Gasoline | D12: bn-vmt, bn-vmt/a | E12: TBGSL | F12: TB | G12: 1 | H12: 2010 | I12: =BA12+5 -> 17 | J12: 0.18 | K12: ='Rail&Bus2'!I8 -> 0.03776864 | V12: ='Rail&Bus2'!G8 -> 10426.657 | W12: =V12 -> 10426.657 | X12: =W12 -> 10426.657 | Y12: =X12 -> 10426.657 | Z12: =Y12 -> 10426.657 | AA12: =Z12 -> 10426.657 | AB12: =AA12 -> 10426.657 | AC12: =AB12 -> 10426.657 | AD12: =AC12 -> 10426.657 | AE12: =AD12 -> 10426.657 | AF12: ='Rail&Bus2'!H8 -> 555.05381 | AM12: 1 | BA12: ='Rail&Bus2'!F8 -> 12
A13: =Technologies!B59 -> R2,R3,R4,R5,R6 | B13: =Technologies!C59 -> TBCNGE | C13: Bus, Exisiting CNG | D13: bn-vmt, bn-vmt/a | E13: TBCNG | F13: TB | G13: 1 | H13: 2010 | I13: =BA13+5 -> 17 | K13: ='Rail&Bus2'!I9 -> 0.029733766 | AF13: ='Rail&Bus2'!H9 -> 639.72304 | AG13: =TB!D32 -> 0.013086117 | AH13: =TB!D31 -> 0.007100007 | AI13: =TB!D33 -> 0.0081291202 | AJ13: =TB!D35 -> 0.0024026908 | AK13: =TB!D34 -> 0.011533418 | AM13: 1 | AP13: 0 | AQ13: 0 | AR13: 0 | AS13: 0 | AT13: 0 | AU13: 0 | AV13: 0 | AW13: 0 | AX13: 0 | BA13: 12
A14: *Commercial Trucks | AO14: 0
A15: * | B15: =Technologies!C79 -> TCGSLE | C15: =Technologies!D79 -> Truck, Commerical, Exisiting Gasoline | D15: bn-vmt, bn-vmt/a | E15: TCGSL | F15: =Commodities!C$18 -> TC | G15: 1 | H15: 2010 | I15: =BA15+5 -> 20.5 | K15: =Trucks!H66 -> 0.0971537 | AF15: =Trucks!G66 -> 55.312878 | AM15: 1 | AO15: 0 | AP15: 0 | AQ15: 0 | AR15: 0 | AS15: 0 | AT15: 0 | AU15: 0 | AV15: 0 | AW15: 0 | AX15: 0 | BA15: =Trucks!E66 -> 15.5
A16: * | B16: =Technologies!C80 -> TCDSLE | C16: =Technologies!D80 -> Truck, Commerical, Existing Diesel | D16: bn-vmt, bn-vmt/a | E16: TCDSL | F16: =Commodities!C$18 -> TC | G16: 1 | H16: 2010 | I16: =BA16+5 -> 20.5 | K16: =Trucks!H67 -> 0.11740134 | AF16: =Trucks!G67 -> 55.312878 | AM16: 1 | AO16: 0 | AP16: 0 | AQ16: 0 | AR16: 0 | AS16: 0 | AT16: 0 | AU16: 0 | AV16: 0 | AW16: 0 | AX16: 0 | BA16: =Trucks!E67 -> 15.5
A17: *Medium Duty Trucks
A18: =Technologies!B110 -> R2,R3,R4,R5,R6 | B18: =Technologies!C110 -> TMGSLE | C18: =Technologies!D110 -> Medium Duty Truck, Existing Gasoline | D18: bn-vmt, bn-vmt/a | E18: =Commodities!C39 -> TMGSL | F18: =Commodities!C$11 -> TM | G18: 1 | H18: 2010 | I18: =BA18+5 -> 24 | K18: =Trucks!H119*TM!$L$7 -> 0.081247596 | AF18: =Trucks!G119 -> 248.8047 | AG18: =TM!B48 -> 0.11532313 | AH18: =TM!B47 -> 0.062569744 | AI18: =TM!B49 -> 0.071638939 | AJ18: =TM!B51 -> 0.021174028 | AK18: =TM!B50 -> 0.10163976 | AM18: 1 | AO18: 0 | AP18: 0 | AQ18: 0 | AR18: 0 | AS18: 0 | AT18: 0 | AU18: 0 | AV18: 0 | AW18: 0 | AX18: 0 | BA18: =Trucks!E119 -> 19
A19: =Technologies!B111 -> R2,R3,R4,R5,R6 | B19: =Technologies!C111 -> TMDSLE | C19: =Technologies!D111 -> Medium Duty Truck, Existing Diesel | D19: bn-vmt, bn-vmt/a | E19: =Commodities!C42 -> TMDSL | F19: =Commodities!C$11 -> TM | G19: 1 | H19: 2010 | I19: =BA19+5 -> 24 | K19: =Trucks!H120*TM!$L$7 -> 0.083040936 | AF19: =Trucks!G120 -> 136.84259 | AG19: =TM!B41 -> 0.05411575 | AH19: =TM!B40 -> 0.029361054 | AI19: =TM!B42 -> 0.033616803 | AJ19: =TM!B44 -> 0.009935981 | AK19: =TM!B43 -> 0.047694786 | AM19: 1 | AO19: 0 | AP19: 0 | AQ19: 0 | AR19: 0 | AS19: 0 | AT19: 0 | AU19: 0 | AV19: 0 | AW19: 0 | AX19: 0 | BA19: =Trucks!E120 -> 19
A20: =Technologies!B112 -> R2,R3,R4,R5,R6 | B20: =Technologies!C112 -> TMCNGE | C20: =Technologies!D112 -> Medium Duty Truck, Existing CNG | D20: bn-vmt, bn-vmt/a | E20: =Commodities!C57 -> TMCNG | F20: =Commodities!C$11 -> TM | G20: 1 | H20: 2010 | I20: =BA20+5 -> 24 | K20: =Trucks!H122*TM!$L$7 -> 0.066470533 | AF20: =Trucks!G122 -> 248.8047 | AG20: =TM!B34 -> 0.00027837838 | AH20: =TM!B33 -> 0.00015103704 | AI20: =TM!B35 -> 0.00017292916 | AJ20: =TM!B37 -> 5.1111965e-05 | AK20: =TM!B36 -> 0.00024534812 | AM20: 1 | AO20: 0 | AP20: 0 | AQ20: 0 | AR20: 0 | AS20: 0 | AT20: 0 | AU20: 0 | AV20: 0 | AW20: 0 | AX20: 0 | BA20: =Trucks!E122 -> 19
A21: * | B21: =Technologies!C113 -> TMLPGE | C21: =Technologies!D113 -> Medium Duty Truck, Existing LPG | D21: bn-vmt, bn-vmt/a | E21: =Commodities!C29 -> TRNLPG1 | F21: =Commodities!C$11 -> TM | G21: 1 | H21: 2010 | I21: =BA21+5 -> 24 | K21: =Trucks!H121 -> 0.053551661 | AF21: =Trucks!G121 -> 248.8047 | AM21: 1 | AO21: 0 | AP21: 0 | AQ21: 0 | AR21: 0 | AS21: 0 | AT21: 0 | AU21: 0 | AV21: 0 | AW21: 0 | AX21: 0 | BA21: =Trucks!E121 -> 19
A22: *Heavy Duty Trucks
A23: =Technologies!B136 -> R2,R3,R4,R5,R6 | B23: =Technologies!C136 -> THSGSLE | C23: =Technologies!D136 -> Heavy Truck, Short Haul, Gasoline exisiting | D23: bn-vmt, bn-vmt/a | E23: =Commodities!C47 -> THGSL | F23: =Commodities!C$12 -> THS | G23: 1 | H23: 2010 | I23: =BA23+5 -> 24 | K23: =Trucks!H162 -> 0.029418718 | AF23: =Trucks!G162 -> 301.42015 | AG23: 0 | AH23: 0 | AI23: 0 | AJ23: 0 | AK23: 0 | AM23: 1 | AO23: 0 | AP23: 0 | AQ23: 0 | AR23: 0 | AS23: 0 | AT23: 0 | AU23: 0 | AV23: 0 | AW23: 0 | AX23: 0 | BA23: =Trucks!E162 -> 19
A24: =Technologies!B137 -> R2,R3,R4,R5,R6 | B24: =Technologies!C137 -> THSDSLE | C24: =Technologies!D137 -> Heavy Truck, Short Haul, Diesel exisiting | D24: bn-vmt, bn-vmt/a | E24: =Commodities!$C$44 -> THDSL | F24: =Commodities!C$12 -> THS | G24: 1 | H24: 2010 | I24: =BA24+5 -> 24 | K24: =THS!G5 -> 0.030387433 | AF24: =Trucks!G163 -> 165.78108 | AG24: =THS!B23 -> 0.19945284 | AH24: =THS!B22 -> 0.10821518 | AI24: =THS!B24 -> 0.12390047 | AJ24: =THS!B26 -> 0.036620755 | AK24: =THS!B25 -> 0.17578728 | AM24: 1 | AP24: 0 | AQ24: 0 | AR24: 0 | AS24: 0 | AT24: 0 | AU24: 0 | AV24: 0 | AW24: 0 | AX24: 0 | BA24: =Trucks!E163 -> 19
A25: * | B25: =Technologies!C138 -> THSDSLE2 | C25: =Technologies!D138 -> Heavy Truck, Short Haul, Diesel exisiting MSW | D25: bn-vmt, bn-vmt/a | E25: =Commodities!$C$46 -> TWDSL | F25: =Commodities!$C$16 -> TSW | G25: 1 | H25: 2010 | I25: 24 | K25: 0.039439301 | AF25: 165.78108 | AG25: =TSW!C62 -> 0.013386394 | AH25: =TSW!C61 -> 0.0070042362 | AI25: =TSW!C63 -> 0.0086552157 | AJ25: =TSW!C65 -> 0.0022050745 | AK25: =TSW!C64 -> 0.011355357 | AM25: 1 | BA25: 19
A26: * | B26: =Technologies!C140 -> THSCNGE2 | C26: =Technologies!D140 -> Heavy Truck, Short Haul, CNG exisiting MSW | D26: bn-vmt, bn-vmt/a | E26: =Commodities!$C$46 -> TWDSL | F26: =Commodities!$C$16 -> TSW | G26: 1 | H26: 2010 | I26: 24 | K26: 0.039547347 | AF26: 248.8047 | AM26: 1 | AO26: 0 | AP26: 0 | AQ26: 0 | AR26: 0 | AS26: 0 | AT26: 0 | AU26: 0 | AV26: 0 | AW26: 0 | AX26: 0 | BA26: 19
A27: *Passenger Rail
A28: =Technologies!B191 -> R2,R3,R4,R5,R6 | B28: =Technologies!C191 -> TPDSLCR | C28: =Technologies!D191 -> Commuter Rail, Diesel | D28: bn-pass-miles, bn-pmt/a | E28: TRNDSL | F28: TRP | G28: 1 | H28: 2010 | I28: 20 | L28: ='Rail&Bus2'!H61 -> 0.63495882 | M28: =L28 -> 0.63495882 | N28: =L28 -> 0.63495882 | O28: =N28 -> 0.63495882 | P28: =O28 -> 0.63495882 | Q28: =P28 -> 0.63495882 | R28: =Q28 -> 0.63495882 | S28: =R28 -> 0.63495882 | T28: =S28 -> 0.63495882 | U28: =T28 -> 0.63495882 | V28: ='Rail&Bus2'!F61 -> 1284.7941 | W28: =V28 -> 1284.7941 | X28: =W28 -> 1284.7941 | Y28: =X28 -> 1284.7941 | Z28: =Y28 -> 1284.7941 | AA28: =Z28 -> 1284.7941 | AB28: =AA28 -> 1284.7941 | AC28: =AB28 -> 1284.7941 | AD28: =AC28 -> 1284.7941 | AE28: =AD28 -> 1284.7941 | AF28: ='Rail&Bus2'!G61 -> 128.47941 | AG28: =TRP!C31 -> 0.038496366 | AH28: =TRP!C30 -> 0.020886597 | AI28: =TRP!C32 -> 0.023914013 | AJ28: =TRP!C34 -> 0.0070681671 | AK28: =TRP!C33 -> 0.03392868 | AM28: 1 | AO28: 0 | BA28: 20
A29: =Technologies!B193 -> R2,R3,R4,R5,R6 | B29: =Technologies!C193 -> TPELCSUB | C29: =Technologies!D193 -> Subways and Streetcars, Electricity | D29: bn-pass-miles, bn-pmt/a | E29: TRNELC | F29: TRP | G29: 1 | H29: 2010 | I29: 20 | L29: ='Rail&Bus2'!H59 -> 1.1472366 | M29: =L29 -> 1.1472366 | N29: =M29 -> 1.1472366 | O29: =N29 -> 1.1472366 | P29: =O29 -> 1.1472366 | Q29: =P29 -> 1.1472366 | R29: =Q29 -> 1.1472366 | S29: =R29 -> 1.1472366 | T29: =S29 -> 1.1472366 | U29: =T29 -> 1.1472366 | V29: ='Rail&Bus2'!F59 -> 216.106 | W29: =V29 -> 216.106 | X29: =W29 -> 216.106 | Y29: =X29 -> 216.106 | Z29: =Y29 -> 216.106 | AA29: =Z29 -> 216.106 | AB29: =AA29 -> 216.106 | AC29: =AB29 -> 216.106 | AD29: =AC29 -> 216.106 | AE29: =AD29 -> 216.106 | AF29: ='Rail&Bus2'!G59 -> 10.805 | AG29: =TRP!C39 -> 2.8383319 | AH29: =TRP!C38 -> 1.539966 | AI29: =TRP!C40 -> 1.763177 | AJ29: =TRP!C42 -> 0.52113501 | AK29: =TRP!C41 -> 2.501557 | AM29: 1 | AO29: 0 | BA29: 20
A30: *Freight Rail
A31: * | B31: =Technologies!C195 -> TRFDSLE | C31: =Technologies!D195 -> Rail Freight, Diesel Existing | D31: bn-t-m, bn-ton-m/a | E31: TRNDSL | F31: TRF | G31: 1 | H31: 2010 | I31: 30 | K31: =Freight!H5 -> 2.7635669 | AF31: =Freight!G5 -> 1.4305792 | AM31: 1 | BA31: =Freight!E5 -> 30
A32: * | B32: =Technologies!C196 -> TRFDSLE2 | C32: =Technologies!D196 -> Rail Freight, Diesel Existing-MSW | D32: bn-vmt, bn-vmt/a | E32: =Commodities!$C$46 -> TWDSL | F32: =Commodities!$C$16 -> TSW | G32: =G31 -> 1 | H32: =H31 -> 2010 | I32: =I31 -> 30 | K32: =K31 -> 2.7635669 | AF32: =AF31 -> 1.4305792 | AG32: =TSW!C47 -> 0.19037656 | AH32: =TSW!C46 -> 0.099611766 | AI32: =TSW!C48 -> 0.12309141 | AJ32: =TSW!C50 -> 0.031359788 | AK32: =TSW!C49 -> 0.16149186 | AM32: 1 | BA32: =BA31 -> 30
A33: =Technologies!B210 -> R2,R3,R4,R5,R6 | B33: =Technologies!C210 -> TSDSLE | C33: =Technologies!D210 -> Water Shipping, Diesel exisiting | D33: bn-t-m, bn-ton-m/a | E33: =Commodities!C43 -> TSDSL | F33: TS | G33: 1 | H33: 2010 | I33: 30 | J33: 0.18 | K33: ='Air&Marine'!J32 -> 1.9172147 | V33: ='Air&Marine'!H32 -> 20.108903 | W33: =V33 -> 20.108903 | X33: =W33 -> 20.108903 | Y33: =X33 -> 20.108903 | Z33: =Y33 -> 20.108903 | AA33: =Z33 -> 20.108903 | AB33: =AA33 -> 20.108903 | AC33: =AB33 -> 20.108903 | AD33: =AC33 -> 20.108903 | AE33: =AD33 -> 20.108903 | AF33: ='Air&Marine'!I32 -> 1.0054451 | AG33: =CommData!E13 -> 1.6792504 | AM33: 1 | AP33: 0 | AQ33: 0 | AR33: 0 | AS33: 0 | AT33: 0 | AU33: 0 | AV33: 0 | AW33: 0 | AX33: 0 | BA33: ='Air&Marine'!G32 -> 30
F38: ~FI_T
A39: Region | B39: TechName | C39: TechDesc | D39: Units | E39: CommIN | F39: CommOUT | G39: NCAP_START | H39: NCAP_TLIFE | I39: NCAP_DRATE | J39: EFF | N39: NCAP_TLIFE
A40: *Emissions Collectors
A41: * | B41: =Technologies!C216 -> SETRB20 | C41: =Technologies!D216 -> Emissions: B20 Rail fuel to TRB20X | D41: PJ, PJ/a | E41: TRB20 | F41: =Commodities!C$64 -> TRB20X | G41: 2010 | H41: 50 | J41: 1 | N41: 50
A42: =Technologies!B215 -> R2,R3,R4,R5,R6 | B42: =Technologies!C215 -> SETRDSL | C42: =Technologies!D215 -> Emissions: DSL Rail fuel to TRDSL | D42: PJ, PJ/a | E42: TRNDSL | F42: TRDSL | G42: 2010 | H42: 50 | J42: 1 | N42: 50
F45: FI_T
A46: Region | B46: TechName | C46: TechDesc | D46: Units | E46: CommIN | F46: CommOUT | G46: EFF | H46: NCAP_FOM
A47: * ZZ (DMD) Backstop Technologies
A48: =Technologies!B218 -> R2,R3,R4,R5,R6 | B48: =Technologies!C218 -> ZZTB | C48: =Technologies!D218 -> Transportation Buses - ZZINFES backstop | D48: bn-vmt, bn-vmt/a | E48: ZZDMY | F48: TB | G48: 1 | H48: 9999
A49: =Technologies!B219 -> *R2,R3,R4,R5,R6 | B49: =Technologies!C219 -> ZZTC | C49: =Technologies!D219 -> Transportation Commercial Trucks - ZZINFES backstop | D49: bn-vmt, bn-vmt/a | E49: ZZDMY | F49: TC | G49: 1 | H49: 9999
A50: =Technologies!B220 -> R2,R3,R4,R5,R6 | B50: =Technologies!C220 -> ZZTM | C50: =Technologies!D220 -> Transportation Medium Trucks - ZZINFES backstop | D50: bn-vmt, bn-vmt/a | E50: ZZDMY | F50: TM | G50: 1 | H50: 9999
A51: =Technologies!B221 -> R2,R3,R4,R5,R6 | B51: =Technologies!C221 -> ZZTHS | C51: =Technologies!D221 -> Transportation Heavy Short Haul - ZZINFES backstop | D51: bn-vmt, bn-vmt/a | E51: ZZDMY | F51: THS | G51: 1 | H51: 9999
A52: =Technologies!B222 -> R2,R3,R4,R5,R6 | B52: =Technologies!C222 -> ZZTRP | C52: =Technologies!D222 -> Transportation Rail Passenger - ZZINFES backstop | D52: bn-vmt, bn-vmt/a | E52: ZZDMY | F52: TRP | G52: 1 | H52: 9999
A53: =Technologies!B223 -> *R2,R3,R4,R5,R6 | B53: =Technologies!C223 -> ZZTHL | C53: =Technologies!D223 -> Transportation Rail Freight - ZZINFES backstop | D53: bn-vmt, bn-vmt/a | E53: ZZDMY | F53: THL | G53: 1 | H53: 9999
A54: =Technologies!B224 -> R2,R3,R4,R5,R6 | B54: =Technologies!C224 -> ZZTS | C54: =Technologies!D224 -> Transportation Water Shipping - ZZINFES backstop | D54: bn-t-m, bn-ton-m/a | E54: ZZDMY | F54: TS | G54: 1 | H54: 9999
A55: =Technologies!B225 -> *R2,R3,R4,R5,R6 | B55: =Technologies!C225 -> ZZTSW | C55: =Technologies!D225 -> Transportation MSW - ZZINFES backstop | D55: bn-t-m, bn-ton-m/a | E55: ZZDMY | F55: =Commodities!$C$16 -> TSW | G55: 1

Sheet NewTech
A1: TechData | B1: R1,R2,R3,R4,R5,R6
A6: Region | B6: TechName | C6: *TechDesc | D6: *Units | E6: CommIN | F6: CommOUT | G6: Share~UP | H6: NCAP_START | I6: NCAP_TLIFE | J6: NCAP_DRATE | K6: EFF | L6: EFF~2010 | M6: EFF~2015 | N6: EFF~2020 | O6: EFF~2025 | P6: EFF~2030 | Q6: EFF~2035 | R6: EFF~2040 | S6: EFF~2045 | T6: EFF~2050 | U6: EFF~2055 | V6: NCAP_COST~2010 | W6: NCAP_COST~2015 | X6: NCAP_COST~2020 | Y6: NCAP_COST~2025 | Z6: NCAP_COST~2030 | AA6: NCAP_COST~2035 | AB6: NCAP_COST~2040 | AC6: NCAP_COST~2045 | AD6: NCAP_COST~2050 | AE6: NCAP_COST~2055 | AF6: NCAP_FOM | AG6: PRC_RESID~R2~2010 | AH6: PRC_RESID~R3~2010 | AI6: PRC_RESID~R4~2010 | AJ6: PRC_RESID~R5~2010 | AK6: PRC_RESID~R6~2010 | AL6: NACP_AFA | AM6: NCAP_BND~2010 | AN6: NCAP_BND~2015 | AO6: NCAP_BND~2020 | AP6: NCAP_BND~2025 | AQ6: NCAP_BND~2030 | AR6: NCAP_BND~2035 | AS6: NCAP_BND~2040 | AT6: NCAP_BND~2045 | AU6: NCAP_BND~2050 | AV6: NCAP_BND~2055 | AZ6: NCAP_TLIFE
A7: *Aviation
A8: =Technologies!B49 -> R2,R3,R4,R5,R6 | B8: =Technologies!C49 -> TAJ10 | C8: =Technologies!D49 -> Air Jet, Passenger 2010 | D8: bn-pass-miles, bn-pmt/a | E8: =Commodities!C31 -> TRNJTF1 | F8: TA | G8: 1 | H8: ='Air&Marine'!F7 -> 2010 | I8: =AZ8+5 -> 30 | J8: 0.18 | K8: ='Air&Marine'!J7 -> 0.45147637 | V8: ='Air&Marine'!H7 -> 814.53239 | W8: =V8 -> 814.53239 | X8: =W8 -> 814.53239 | Y8: =X8 -> 814.53239 | Z8: =Y8 -> 814.53239 | AA8: =Z8 -> 814.53239 | AB8: =AA8 -> 814.53239 | AC8: =AB8 -> 814.53239 | AD8: =AC8 -> 814.53239 | AE8: =AD8 -> 814.53239 | AF8: ='Air&Marine'!I7 -> 7.462576 | AL8: 1 | AM8: 0 | AN8: 0 | AZ8: ='Air&Marine'!G7 -> 25
A9: =Technologies!B50 -> R2,R3,R4,R5,R6 | B9: =Technologies!C50 -> TAJSYN10 | C9: =Technologies!D50 -> Air Jet, Passenger, Syn fuel, 2010 | D9: bn-pass-miles, bn-pmt/a | E9: =Commodities!C31 -> TRNJTF1 | F9: TA | G9: 1 | H9: ='Air&Marine'!F8 -> 2010 | I9: =AZ9+5 -> 30 | K9: ='Air&Marine'!J8 -> 0.42712996 | V9: ='Air&Marine'!H8 -> 814.53239 | W9: =V9 -> 814.53239 | X9: =W9 -> 814.53239 | Y9: =X9 -> 814.53239 | Z9: =Y9 -> 814.53239 | AA9: =Z9 -> 814.53239 | AB9: =AA9 -> 814.53239 | AC9: =AB9 -> 814.53239 | AD9: =AC9 -> 814.53239 | AE9: =AD9 -> 814.53239 | AF9: ='Air&Marine'!I8 -> 7.462576 | AL9: 1 | AM9: 0 | AN9: 0 | AZ9: ='Air&Marine'!G8 -> 25
A10: =Technologies!B51 -> R2,R3,R4,R5,R6 | B10: =Technologies!C51 -> TAJWT10 | C10: =Technologies!D51 -> Air Jet, Passenger (Wing tips),2010 | D10: bn-pass-miles, bn-pmt/a | E10: =Commodities!C$31 -> TRNJTF1 | F10: TA | G10: 1 | H10: ='Air&Marine'!F9 -> 2010 | I10: =AZ10+5 -> 30 | J10: 0.2 | K10: ='Air&Marine'!J9 -> 0.47275012 | V10: ='Air&Marine'!H9 -> 820.68444 | W10: =V10 -> 820.68444 | X10: =W10 -> 820.68444 | Y10: =X10 -> 820.68444 | Z10: =Y10 -> 820.68444 | AA10: =Z10 -> 820.68444 | AB10: =AA10 -> 820.68444 | AC10: =AB10 -> 820.68444 | AD10: =AC10 -> 820.68444 | AE10: =AD10 -> 820.68444 | AF10: ='Air&Marine'!I9 -> 7.462576 | AL10: 1 | AM10: 0 | AN10: 0 | AZ10: ='Air&Marine'!G9 -> 25
A11: =Technologies!B52 -> R2,R3,R4,R5,R6 | B11: =Technologies!C52 -> TAJAPU15 | C11: =Technologies!D52 -> Air Jet Passeneger (APU) 2015 | D11: bn-pass-miles, bn-pmt/a | E11: =Commodities!C$31 -> TRNJTF1 | F11: TA | G11: 1 | H11: ='Air&Marine'!F11 -> 2015 | I11: =AZ11+5 -> 30 | J11: 0.2 | K11: ='Air&Marine'!J11 -> 0.45358554 | V11: ='Air&Marine'!H11 -> 815.46191 | W11: =V11 -> 815.46191 | X11: =W11 -> 815.46191 | Y11: =X11 -> 815.46191 | Z11: =Y11 -> 815.46191 | AA11: =Z11 -> 815.46191 | AB11: =AA11 -> 815.46191 | AC11: =AB11 -> 815.46191 | AD11: =AC11 -> 815.46191 | AE11: =AD11 -> 815.46191 | AF11: ='Air&Marine'!I11 -> 7.5083155 | AL11: 1 | AM11: 0 | AN11: 0 | AZ11: ='Air&Marine'!G10 -> 25
A12: =Technologies!B53 -> R2,R3,R4,R5,R6 | B12: =Technologies!C53 -> TAJBW30 | C12: =Technologies!D53 -> Air Jet, Passenger(blended wing), 2030 | D12: bn-pass-miles, bn-pmt/a | E12: =Commodities!C$31 -> TRNJTF1 | F12: TA | G12: 1 | H12: ='Air&Marine'!F12 -> 2030 | I12: =AZ12+5 -> 30 | J12: 0.24 | K12: ='Air&Marine'!J12 -> 0.64496624 | V12: ='Air&Marine'!H12 -> 1127.6931 | W12: =V12 -> 1127.6931 | X12: =W12 -> 1127.6931 | Y12: =X12 -> 1127.6931 | Z12: =Y12 -> 1127.6931 | AA12: =Z12 -> 1127.6931 | AB12: =AA12 -> 1127.6931 | AC12: =AB12 -> 1127.6931 | AD12: =AC12 -> 1127.6931 | AE12: =AD12 -> 1127.6931 | AF12: ='Air&Marine'!I12 -> 7.462576 | AL12: 1 | AM12: 0 | AN12: 0 | AZ12: ='Air&Marine'!G12 -> 25
A13: =Technologies!B54 -> R2,R3,R4,R5,R6 | B13: =Technologies!C54 -> TAJAE30 | C13: =Technologies!D54 -> Air Jet, Passenger (improved aero), 2030 | D13: bn-pass-miles, bn-pmt/a | E13: =Commodities!C$31 -> TRNJTF1 | F13: TA | G13: 1 | H13: ='Air&Marine'!F13 -> 2030 | I13: =AZ13+5 -> 30 | J13: 0.24 | K13: ='Air&Marine'!J13 -> 0.50164041 | V13: ='Air&Marine'!H13 -> 895.98562 | W13: =V13 -> 895.98562 | X13: =W13 -> 895.98562 | Y13: =X13 -> 895.98562 | Z13: =Y13 -> 895.98562 | AA13: =Z13 -> 895.98562 | AB13: =AA13 -> 895.98562 | AC13: =AB13 -> 895.98562 | AD13: =AC13 -> 895.98562 | AE13: =AD13 -> 895.98562 | AF13: ='Air&Marine'!I13 -> 7.462576 | AL13: 1 | AM13: 0 | AN13: 0 | AZ13: ='Air&Marine'!G13 -> 25
A14: =Technologies!B55 -> R2,R3,R4,R5,R6 | B14: =Technologies!C55 -> TAJGE15 | C14: =Technologies!D55 -> Air Jet Passenger, (geared engine), 2015 | D14: bn-pass-miles, bn-pmt/a | E14: =Commodities!C$31 -> TRNJTF1 | F14: TA | G14: 1 | H14: ='Air&Marine'!F15 -> 2015 | I14: =AZ14+5 -> 30 | J14: 0.2 | K14: ='Air&Marine'!J15 -> 0.51597299 | V14: ='Air&Marine'!H15 -> 929.6172 | W14: =V14 -> 929.6172 | X14: =W14 -> 929.6172 | Y14: =X14 -> 929.6172 | Z14: =Y14 -> 929.6172 | AA14: =Z14 -> 929.6172 | AB14: =AA14 -> 929.6172 | AC14: =AB14 -> 929.6172 | AD14: =AC14 -> 929.6172 | AE14: =AD14 -> 929.6172 | AF14: ='Air&Marine'!I15 -> 8.5169591 | AL14: 1 | AM14: 0 | AN14: 0 | AZ14: ='Air&Marine'!G15 -> 25
A15: * | B15: =Technologies!C56 -> TAP10 | C15: =Technologies!D56 -> Airplane, General Aviation - 2010 | D15: bn-pass-miles, bn-pmt/a | E15: TRGSLB | F15: TA | G15: 1 | H15: 2010 | I15: =AZ15+5 -> 25 | J15: 0.18 | V15: ='Air&Marine'!H18 -> 17.511 | W15: =V15 -> 17.511 | X15: =W15 -> 17.511 | Y15: =X15 -> 17.511 | Z15: =Y15 -> 17.511 | AA15: =Z15 -> 17.511 | AB15: =AA15 -> 17.511 | AC15: =AB15 -> 17.511 | AD15: =AC15 -> 17.511 | AE15: =AD15 -> 17.511 | AF15: ='Air&Marine'!I18 -> 1.7511 | AL15: 1 | AZ15: 20
A16: *BUSES
A17: =Technologies!B60 -> R2,R3,R4,R5,R6 | B17: =Technologies!C60 -> TBDSLC10 | C17: =Technologies!D60 -> Bus, Conventional Diesel, 2010 | D17: bn-vmt, bn-vmt/a | E17: =Commodities!C$41 -> TBDSL | F17: TB | G17: 1 | H17: 2010 | I17: =AZ17+5 -> 17 | J17: 0.18 | K17: ='Rail&Bus2'!$L7 -> 0.031791784 | V17: ='Rail&Bus2'!T7 -> 10426.657 | AF17: ='Rail&Bus2'!H11 -> 555.05381 | AL17: 1 | AM17: 0 | AN17: 0 | AO17: 0 | AP17: 0 | AQ17: 0 | AR17: 0 | AS17: 0 | AT17: 0 | AU17: 0 | AV17: 0 | AZ17: 12
A18: =Technologies!B61 -> R2,R3,R4,R5,R6 | B18: =Technologies!C61 -> TBDSLC | C18: ='Rail&Bus2'!B11 -> Bus, Conventional Diesel | D18: bn-vmt, bn-vmt/a | E18: =Commodities!C$41 -> TBDSL | F18: TB | G18: 1 | H18: 2015 | I18: =AZ18+5 -> 17 | J18: 0.18 | M18: ='Rail&Bus2'!$I11 -> 0.033488882 | N18: ='Rail&Bus2'!$I12 -> 0.034986321 | O18: =N18 -> 0.034986321 | P18: =O18 -> 0.034986321 | Q18: =P18 -> 0.034986321 | R18: =Q18 -> 0.034986321 | S18: =R18 -> 0.034986321 | T18: =S18 -> 0.034986321 | U18: =T18 -> 0.034986321 | W18: ='Rail&Bus2'!G11 -> 10488.439 | X18: ='Rail&Bus2'!G12 -> 10598.81 | Y18: =X18 -> 10598.81 | Z18: =Y18 -> 10598.81 | AA18: =Z18 -> 10598.81 | AB18: =AA18 -> 10598.81 | AC18: =AB18 -> 10598.81 | AD18: =AC18 -> 10598.81 | AE18: =AD18 -> 10598.81 | AF18: ='Rail&Bus2'!H11 -> 555.05381 | AL18: 1 | AM18: 0 | AZ18: ='Rail&Bus2'!F11 -> 12
A19: =Technologies!B62 -> R2,R3,R4,R5,R6 | B19: =Technologies!C62 -> TBDSLIM | C19: =Technologies!D62 -> Bus, Improved Diesel | D19: bn-vmt, bn-vmt/a | E19: =Commodities!C$41 -> TBDSL | F19: TB | G19: 1 | H19: 2025 | I19: =AZ19+5 -> 17 | J19: 0.24 | K19: ='Rail&Bus2'!I13 -> 0.03909468 | W19: =X19 -> 10598.81 | X19: =Y19 -> 10598.81 | Y19: ='Rail&Bus2'!V7 -> 10598.81 | Z19: =Y19 -> 10598.81 | AA19: =Z19 -> 10598.81 | AB19: =AA19 -> 10598.81 | AC19: =AB19 -> 10598.81 | AD19: =AC19 -> 10598.81 | AE19: =AD19 -> 10598.81 | AF19: ='Rail&Bus2'!H12 -> 555.05381 | AL19: 1 | AM19: 0 | AZ19: 12
A20: =Technologies!B63 -> R2,R3,R4,R5,R6 | B20: =Technologies!C63 -> TBDSLADV | C20: ='Rail&Bus2'!B14 -> Bus, Advanced Tech Diesel | D20: bn-vmt, bn-vmt/a | E20: =Commodities!C$41 -> TBDSL | F20: TB | G20: 1 | H20: ='Rail&Bus2'!E14 -> 2015 | I20: =AZ20+5 -> 17 | J20: 0.28 | M20: ='Rail&Bus2'!I14 -> 0.037727787 | N20: =M20 -> 0.037727787 | O20: ='Rail&Bus2'!$I15 -> 0.03909468 | P20: =O20 -> 0.03909468 | Q20: =P20 -> 0.03909468 | R20: ='Rail&Bus2'!I16 -> 0.039355772 | S20: =R20 -> 0.039355772 | T20: =S20 -> 0.039355772 | U20: =T20 -> 0.039355772 | W20: ='Rail&Bus2'!G14 -> 10807.968 | X20: =W20 -> 10807.968 | Y20: ='Rail&Bus2'!G15 -> 10912.547 | Z20: =Y20 -> 10912.547 | AA20: =Z20 -> 10912.547 | AB20: ='Rail&Bus2'!G16 -> 11236.002 | AC20: =AB20 -> 11236.002 | AD20: =AC20 -> 11236.002 | AE20: =AD20 -> 11236.002 | AF20: ='Rail&Bus2'!H14 -> 555.05381 | AL20: 1 | AM20: 0 | AZ20: ='Rail&Bus2'!F14 -> 12
A21: =Technologies!B64 -> R2,R3,R4,R5,R6 | B21: =Technologies!C64 -> TBDSLAH | C21: ='Rail&Bus2'!B17 -> Bus, Advanced Hybrid Diesel | D21: bn-vmt, bn-vmt/a | E21: =Commodities!C$41 -> TBDSL | F21: TB | G21: 1 | H21: ='Rail&Bus2'!$E$17 -> 2015 | I21: =AZ21+5 -> 17 | J21: 0.28 | M21: ='Rail&Bus2'!I17 -> 0.05389245 | N21: =M21 -> 0.05389245 | O21: ='Rail&Bus2'!$I18 -> 0.05585064 | P21: =O21 -> 0.05585064 | Q21: =P21 -> 0.05585064 | R21: ='Rail&Bus2'!I19 -> 0.056557124 | S21: =R21 -> 0.056557124 | T21: =S21 -> 0.056557124 | U21: =T21 -> 0.056557124 | W21: ='Rail&Bus2'!G17 -> 17887.168 | X21: =W21 -> 17887.168 | Y21: ='Rail&Bus2'!G18 -> 15563.582 | Z21: =Y21 -> 15563.582 | AA21: =Z21 -> 15563.582 | AB21: ='Rail&Bus2'!G19 -> 15887.037 | AC21: =AB21 -> 15887.037 | AD21: =AC21 -> 15887.037 | AE21: =AD21 -> 15887.037 | AF21: ='Rail&Bus2'!H17 -> 564.4615 | AL21: 1 | AM21: 0 | AZ21: ='Rail&Bus2'!F17 -> 12
A22: * | B22: =Technologies!C65 -> TBB20C10 | C22: =Technologies!D65 -> Bus, Conventional Biodiesel, 2010 | D22: bn-vmt, bn-vmt/a | E22: TBB20X | F22: TB | G22: 1 | H22: 2010 | I22: =AZ22+5 -> 17 | J22: 0.18 | K22: ='Rail&Bus2'!$L9 -> 0.031770687 | V22: ='Rail&Bus2'!T9 -> 10426.657 | AF22: ='Rail&Bus2'!H20 -> 524.22213 | AL22: 1 | AN22: 0 | AO22: 0 | AP22: 0 | AQ22: 0 | AR22: 0 | AS22: 0 | AT22: 0 | AU22: 0 | AV22: 0 | AZ22: 12
A23: * | B23: =Technologies!C66 -> TBB20C | C23: ='Rail&Bus2'!B21 -> Bus, Conventional B20 | D23: bn-vmt, bn-vmt/a | E23: TBB20X | F23: TB | G23: 1 | H23: 2015 | I23: =AZ23+5 -> 17 | J23: 0.18 | M23: ='Rail&Bus2'!I11 -> 0.033488882 | N23: ='Rail&Bus2'!$I22 -> 0.034963103 | O23: =N23 -> 0.034963103 | P23: =O23 -> 0.034963103 | Q23: =P23 -> 0.034963103 | R23: =Q23 -> 0.034963103 | S23: =R23 -> 0.034963103 | T23: =S23 -> 0.034963103 | U23: =T23 -> 0.034963103 | W23: ='Rail&Bus2'!G21 -> 10488.439 | X23: ='Rail&Bus2'!G22 -> 10749.404 | Y23: =X23 -> 10749.404 | Z23: =Y23 -> 10749.404 | AA23: =Z23 -> 10749.404 | AB23: =AA23 -> 10749.404 | AC23: =AB23 -> 10749.404 | AD23: =AC23 -> 10749.404 | AE23: =AD23 -> 10749.404 | AF23: ='Rail&Bus2'!H21 -> 524.22213 | AL23: 1 | AZ23: ='Rail&Bus2'!F21 -> 12
A24: * | B24: =Technologies!C67 -> TBB20IM | C24: =Technologies!D67 -> Bus, B20, Improved Biodiesel | D24: bn-vmt, bn-vmt/a | E24: TBB20X | F24: TB | G24: 1 | H24: 2025 | I24: =AZ24+5 -> 17 | J24: 0.24 | K24: ='Rail&Bus2'!I23 -> 0.039068736 | Y24: ='Rail&Bus2'!G23 -> 11404.873 | Z24: =Y24 -> 11404.873 | AA24: =Z24 -> 11404.873 | AB24: =AA24 -> 11404.873 | AC24: =AB24 -> 11404.873 | AD24: =AC24 -> 11404.873 | AE24: =AD24 -> 11404.873 | AF24: ='Rail&Bus2'!H22 -> 524.22213 | AL24: 1 | AZ24: 12
A25: * | B25: =Technologies!C68 -> TBB20ADV | C25: ='Rail&Bus2'!B24 -> Bus, Advanced Tech B20 | D25: bn-vmt, bn-vmt/a | E25: TBB20X | F25: TB | G25: 1 | H25: 2015 | I25: =AZ25+5 -> 17 | J25: 0.28 | M25: ='Rail&Bus2'!I24 -> 0.037700577 | N25: =M25 -> 0.037700577 | O25: ='Rail&Bus2'!I25 -> 0.039067956 | P25: =O25 -> 0.039067956 | Q25: =P25 -> 0.039067956 | R25: ='Rail&Bus2'!I26 -> 0.039562487 | S25: =R25 -> 0.039562487 | T25: =S25 -> 0.039562487 | U25: =T25 -> 0.039562487 | W25: ='Rail&Bus2'!G24 -> 10807.968 | X25: =W25 -> 10807.968 | Y25: ='Rail&Bus2'!G25 -> 10912.547 | Z25: =Y25 -> 10912.547 | AA25: =Z25 -> 10912.547 | AB25: ='Rail&Bus2'!G26 -> 11236.005 | AC25: =AB25 -> 11236.005 | AD25: =AC25 -> 11236.005 | AE25: =AD25 -> 11236.005 | AF25: ='Rail&Bus2'!H23 -> 524.22213 | AL25: 1 | AZ25: 12
A26: * | B26: =Technologies!C69 -> TBB20AH | C26: ='Rail&Bus2'!B27 -> Bus, Advanced Hybrid B20 | D26: bn-vmt, bn-vmt/a | E26: TBB20X | F26: TB | G26: 1 | H26: 2015 | I26: =AZ26+5 -> 17 | J26: 0.28 | M26: ='Rail&Bus2'!I27 -> 0.053857967 | N26: =M26 -> 0.053857967 | O26: ='Rail&Bus2'!I28 -> 0.055811365 | P26: =O26 -> 0.055811365 | Q26: =P26 -> 0.055811365 | R26: ='Rail&Bus2'!I29 -> 0.056517838 | S26: =R26 -> 0.056517838 | T26: =S26 -> 0.056517838 | U26: =T26 -> 0.056517838 | W26: ='Rail&Bus2'!G27 -> 17887.168 | X26: =W26 -> 17887.168 | Y26: ='Rail&Bus2'!G28 -> 15563.582 | Z26: =Y26 -> 15563.582 | AA26: =Z26 -> 15563.582 | AB26: ='Rail&Bus2'!G29 -> 15887.04 | AC26: =AB26 -> 15887.04 | AD26: =AC26 -> 15887.04 | AE26: =AD26 -> 15887.04 | AF26: ='Rail&Bus2'!H27 -> 564.4615 | AL26: 1 | AZ26: 12
A27: =Technologies!B70 -> R2,R3,R4,R5,R6 | B27: =Technologies!C70 -> TBCNGC10 | C27: =Technologies!D70 -> Bus, Conventional CNG, 2010 | D27: bn-vmt, bn-vmt/a | E27: =Commodities!C$55 -> TBCNG | F27: TB | G27: 1 | H27: 2010 | I27: =AZ27+5 -> 17 | J27: 0.18 | K27: ='Rail&Bus2'!$L10 -> 0.027030696 | V27: ='Rail&Bus2'!T10 -> 12020.947 | AF27: ='Rail&Bus2'!H30 -> 639.72304 | AL27: 1 | AM27: 0 | AN27: 0 | AO27: 0 | AP27: 0 | AQ27: 0 | AR27: 0 | AS27: 0 | AT27: 0 | AU27: 0 | AV27: 0 | AZ27: 12
A28: =Technologies!B71 -> R2,R3,R4,R5,R6 | B28: =Technologies!C71 -> TBCNGC | C28: ='Rail&Bus2'!B31 -> Bus, Conventional CNG | D28: bn-vmt, bn-vmt/a | E28: =Commodities!C$55 -> TBCNG | F28: TB | G28: 1 | H28: 2015 | I28: =AZ28+5 -> 17 | J28: 0.18 | M28: ='Rail&Bus2'!$I31 -> 0.028412947 | N28: ='Rail&Bus2'!$I32 -> 0.029718407 | O28: =N28 -> 0.029718407 | P28: =O28 -> 0.029718407 | Q28: =P28 -> 0.029718407 | R28: =Q28 -> 0.029718407 | S28: =R28 -> 0.029718407 | T28: =S28 -> 0.029718407 | U28: =T28 -> 0.029718407 | W28: ='Rail&Bus2'!G31 -> 12033.046 | X28: ='Rail&Bus2'!G32 -> 12046.85 | Y28: =X28 -> 12046.85 | Z28: =Y28 -> 12046.85 | AA28: =Z28 -> 12046.85 | AB28: =AA28 -> 12046.85 | AC28: =AB28 -> 12046.85 | AD28: =AC28 -> 12046.85 | AE28: =AD28 -> 12046.85 | AF28: ='Rail&Bus2'!H31 -> 639.72304 | AL28: 1 | AM28: 0 | AZ28: ='Rail&Bus2'!F31 -> 12
A29: =Technologies!B72 -> R2,R3,R4,R5,R6 | B29: =Technologies!C72 -> TBCNGIM | C29: =Technologies!D72 -> Bus, Improved CNG | D29: bn-vmt, bn-vmt/a | E29: =Commodities!C$55 -> TBCNG | F29: TB | G29: 1 | H29: 2025 | I29: =AZ29+5 -> 17 | J29: 0.24 | K29: ='Rail&Bus2'!I33 -> 0.031231205 | Y29: ='Rail&Bus2'!G33 -> 12573.414 | Z29: =Y29 -> 12573.414 | AA29: =Z29 -> 12573.414 | AB29: =AA29 -> 12573.414 | AC29: =AB29 -> 12573.414 | AD29: =AC29 -> 12573.414 | AE29: =AD29 -> 12573.414 | AF29: ='Rail&Bus2'!H32 -> 639.72304 | AL29: 1 | AM29: 0 | AZ29: 12
A30: =Technologies!B73 -> R2,R3,R4,R5,R6 | B30: =Technologies!C73 -> TBCNGADV | C30: ='Rail&Bus2'!B34 -> Bus, Advanced Tech CNG | D30: bn-vmt, bn-vmt/a | E30: =Commodities!C$55 -> TBCNG | F30: TB | G30: 1 | H30: ='Rail&Bus2'!E34 -> 2015 | I30: =AZ30+5 -> 17 | J30: 0.28 | M30: ='Rail&Bus2'!I34 -> 0.030225233 | N30: =M30 -> 0.030225233 | O30: ='Rail&Bus2'!$I35 -> 0.030839567 | P30: =O30 -> 0.030839567 | Q30: =P30 -> 0.030839567 | R30: ='Rail&Bus2'!$I36 -> 0.031231205 | S30: =R30 -> 0.031231205 | T30: =S30 -> 0.031231205 | U30: =T30 -> 0.031231205 | W30: ='Rail&Bus2'!G34 -> 12097.885 | X30: =W30 -> 12097.885 | Y30: ='Rail&Bus2'!G35 -> 12081.088 | Z30: =Y30 -> 12081.088 | AA30: =Z30 -> 12081.088 | AB30: ='Rail&Bus2'!G36 -> 12404.543 | AC30: =AB30 -> 12404.543 | AD30: =AC30 -> 12404.543 | AE30: =AD30 -> 12404.543 | AF30: ='Rail&Bus2'!H34 -> 639.72304 | AL30: 1 | AM30: 0 | AZ30: ='Rail&Bus2'!F34 -> 12
A31: =Technologies!B74 -> R2,R3,R4,R5,R6 | B31: =Technologies!C74 -> TBCNGAH | C31: ='Rail&Bus2'!B37 -> Bus, Advanced Hybird CNG | D31: bn-vmt, bn-vmt/a | E31: =Commodities!C$55 -> TBCNG | F31: TB | G31: 1 | H31: 2015 | I31: =AZ31+5 -> 17 | J31: 0.28 | M31: ='Rail&Bus2'!I37 -> 0.04030031 | N31: =M31 -> 0.04030031 | O31: ='Rail&Bus2'!$I38 -> 0.041121982 | P31: =O31 -> 0.041121982 | Q31: =P31 -> 0.041121982 | R31: ='Rail&Bus2'!$I39 -> 0.041644166 | S31: =R31 -> 0.041644166 | T31: =S31 -> 0.041644166 | U31: =T31 -> 0.041644166 | W31: ='Rail&Bus2'!G37 -> 18533.521 | X31: =W31 -> 18533.521 | Y31: ='Rail&Bus2'!G38 -> 16309.301 | Z31: =Y31 -> 16309.301 | AA31: =Z31 -> 16309.301 | AB31: ='Rail&Bus2'!G39 -> 16632.756 | AC31: =AB31 -> 16632.756 | AD31: =AC31 -> 16632.756 | AE31: =AD31 -> 16632.756 | AF31: ='Rail&Bus2'!H37 -> 649.13073 | AL31: 1 | AM31: 0 | AZ31: ='Rail&Bus2'!F35 -> 12
A32: =Technologies!B75 -> R2,R3,R4,R5,R6 | B32: =Technologies!C75 -> TBH2FC | C32: ='Rail&Bus2'!B40 -> Bus, Hydrogen Fuel Cell | D32: bn-vmt, bn-vmt/a | E32: =Commodities!C$53 -> TRNH2 | F32: TB | G32: 1 | H32: ='Rail&Bus2'!E40 -> 2010 | I32: =AZ32+5 -> 17 | J32: 0.24 | K32: ='Rail&Bus2'!I40 -> 0.027477594 | V32: ='Rail&Bus2'!T12 -> 63771.6 | W32: ='Rail&Bus2'!U12 -> 51017.28 | X32: =W32 -> 51017.28 | Y32: ='Rail&Bus2'!V12 -> 31885.8 | Z32: =Y32 -> 31885.8 | AA32: =Z32 -> 31885.8 | AB32: ='Rail&Bus2'!W12 -> 19131.48 | AC32: =AB32 -> 19131.48 | AD32: =AC32 -> 19131.48 | AE32: =AD32 -> 19131.48 | AF32: ='Rail&Bus2'!H43 -> 1317.0768 | AL32: 1 | AM32: 0 | AZ32: ='Rail&Bus2'!F40 -> 12
A33: =Technologies!B76 -> R2,R3,R4,R5,R6 | B33: =Technologies!C76 -> TBH2HYB | C33: ='Rail&Bus2'!B44 -> Bus, Hydrogen Fuel Cell Hybrid | D33: bn-vmt, bn-vmt/a | E33: =Commodities!C$53 -> TRNH2 | F33: TB | G33: 1 | H33: ='Rail&Bus2'!E44 -> 2010 | I33: =AZ33+5 -> 17 | J33: 0.24 | K33: ='Rail&Bus2'!I44 -> 0.049930713 | V33: =V32 -> 63771.6 | W33: ='Rail&Bus2'!U13 -> 51017.28 | X33: =W33 -> 51017.28 | Y33: ='Rail&Bus2'!V13 -> 31885.8 | Z33: =Y33 -> 31885.8 | AA33: =Z33 -> 31885.8 | AB33: ='Rail&Bus2'!W13 -> 19131.48 | AC33: =AB33 -> 19131.48 | AD33: =AC33 -> 19131.48 | AE33: =AD33 -> 19131.48 | AF33: ='Rail&Bus2'!H44 -> 1317.0768 | AL33: 1 | AZ33: ='Rail&Bus2'!F44 -> 12
A34: =Technologies!B77 -> R2,R3,R4,R5,R6 | B34: =Technologies!C77 -> TBELC | C34: =Technologies!D77 -> Bus, Conventional ELC | D34: bn-vmt, bn-vmt/a | E34: TRNELC | F34: TB | G34: 1 | H34: 2020 | I34: 17 | J34: 0.28 | K34: 0.0811 | W34: 16379.979 | X34: 16379.979 | Y34: 16379.979 | Z34: 16379.979 | AA34: 16379.979 | AB34: 16379.979 | AC34: 16379.979 | AD34: 16379.979 | AE34: 16379.979 | AF34: 333.0323 | AL34: 1 | AZ34: 12
A35: =Technologies!B78 -> R2,R3,R4,R5,R6 | B35: =Technologies!C78 -> TBELCIM | C35: =Technologies!D78 -> Bus, Improved ELC | D35: bn-vmt, bn-vmt/a | E35: TRNELC | F35: TB | G35: 1 | H35: 2025 | I35: 17 | J35: 0.28 | L35: 0.0892 | M35: 0.0892 | N35: 0.0892 | O35: 0.0892 | P35: 0.0892 | Q35: 0.0892 | R35: 0.0892 | S35: 0.0937 | T35: 0.0937 | U35: 0.0984 | W35: 16379.979 | X35: 16379.979 | Y35: 16379.979 | Z35: 16379.979 | AA35: 16379.979 | AB35: 16379.979 | AC35: 16379.979 | AD35: 16379.979 | AE35: 16379.979 | AF35: 333.0323 | AL35: 1 | AZ35: 12
A36: *Commercial Trucks | AM36: 0
A37: * | B37: =Technologies!C81 -> TCGSLC10 | C37: =Technologies!D81 -> Commercial Truck, Gasoline 2010 | D37: bn-vmt, bn-vmt/a | E37: TCGSL | F37: =Commodities!C$18 -> TC | G37: 1 | H37: 2010 | I37: =AZ37+5 -> 20.5 | J37: 0.18 | K37: =Trucks!H7 -> 0.11893076 | V37: =Trucks!F7 -> 1113.4943 | W37: =V37 -> 1113.4943 | AF37: =Trucks!G8 -> 56.323061 | AL37: 1 | AN37: 0 | AO37: 0 | AP37: 0 | AQ37: 0 | AR37: 0 | AS37: 0 | AT37: 0 | AU37: 0 | AV37: 0 | AZ37: =Trucks!E67 -> 15.5
A38: * | B38: =Technologies!C82 -> TCGSLC | C38: =Technologies!D82 -> Commercial Truck, Conventional Gasoline | D38: bn-vmt, bn-vmt/a | E38: TCGSL | F38: =Commodities!C$18 -> TC | G38: 1 | H38: 2015 | I38: =AZ38+5 -> 20.5 | J38: 0.18 | M38: =Trucks!H8 -> 0.12946583 | N38: =Trucks!H9 -> 0.13360732 | O38: =N38 -> 0.13360732 | P38: =O38 -> 0.13360732 | Q38: =P38 -> 0.13360732 | R38: =Q38 -> 0.13360732 | S38: =R38 -> 0.13360732 | T38: =S38 -> 0.13360732 | U38: =T38 -> 0.13360732 | W38: =Trucks!F8 -> 1122.3649 | X38: =Trucks!F9 -> 1130.932 | Y38: =X38 -> 1130.932 | Z38: =Y38 -> 1130.932 | AA38: =Z38 -> 1130.932 | AB38: =AA38 -> 1130.932 | AC38: =AB38 -> 1130.932 | AD38: =AC38 -> 1130.932 | AE38: =AD38 -> 1130.932 | AF38: =Trucks!G8 -> 56.323061 | AL38: 1 | AZ38: =Trucks!E8 -> 15.5
A39: * | B39: =Technologies!C83 -> TCGSLIM | C39: =Technologies!D83 -> Commercial Truck, Improved Gasoline | D39: bn-vmt, bn-vmt/a | E39: TCGSL | F39: =Commodities!C$18 -> TC | G39: 1 | H39: 2025 | I39: =AZ39+5 -> 20.5 | J39: 0.24 | O39: =Trucks!H10 -> 0.14372909 | P39: =O39 -> 0.14372909 | Q39: =P39 -> 0.14372909 | R39: =Trucks!H11 -> 0.15823696 | S39: =R39 -> 0.15823696 | T39: =S39 -> 0.15823696 | U39: =T39 -> 0.15823696 | Y39: =Trucks!F10 -> 1170.8328 | Z39: =Y39 -> 1170.8328 | AA39: =Z39 -> 1170.8328 | AB39: =Trucks!F11 -> 1207.5097 | AC39: =AB39 -> 1207.5097 | AD39: =AC39 -> 1207.5097 | AE39: =AD39 -> 1207.5097 | AF39: =AF38 -> 56.323061 | AL39: 1 | AZ39: 15.5
A40: * | B40: =Technologies!C84 -> TCGSLADV | C40: =Technologies!D84 -> Commercial Truck, Advanced Tech Gasoline | D40: bn-vmt, bn-vmt/a | E40: TCGSL | F40: =Commodities!C$18 -> TC | G40: 1 | H40: =Trucks!D12 -> 2015 | I40: =AZ40+5 -> 20.5 | J40: 0.28 | M40: =Trucks!H12 -> 0.1888553 | N40: =M40 -> 0.1888553 | O40: =Trucks!H13 -> 0.23592152 | P40: =O40 -> 0.23592152 | Q40: =P40 -> 0.23592152 | R40: =Q40 -> 0.23592152 | S40: =R40 -> 0.23592152 | T40: =S40 -> 0.23592152 | U40: =T40 -> 0.23592152 | W40: =Trucks!F12 -> 1215.2079 | X40: =W40 -> 1215.2079 | Y40: =Trucks!F13 -> 1256.5737 | Z40: =Y40 -> 1256.5737 | AA40: =Z40 -> 1256.5737 | AB40: =AA40 -> 1256.5737 | AC40: =AB40 -> 1256.5737 | AD40: =AC40 -> 1256.5737 | AE40: =AD40 -> 1256.5737 | AF40: =Trucks!G12 -> 56.323061 | AL40: 1 | AZ40: =Trucks!E12 -> 15.5
A41: * | B41: =Technologies!C85 -> TCGSLAH | C41: =Technologies!D85 -> Commercial Truck, Advanced Hybrid Tech Gasoline | D41: bn-vmt, bn-vmt/a | E41: TCGSL | F41: =Commodities!C$18 -> TC | G41: 1 | H41: =Trucks!D14 -> 2015 | I41: =AZ41+5 -> 20.5 | J41: 0.28 | M41: =Trucks!H14 -> 0.23111368 | N41: =M41 -> 0.23111368 | O41: =Trucks!H15 -> 0.2887234 | P41: =O41 -> 0.2887234 | Q41: =P41 -> 0.2887234 | R41: =Trucks!H16 -> 0.29184428 | S41: =R41 -> 0.29184428 | T41: =S41 -> 0.29184428 | U41: =T41 -> 0.29184428 | W41: =Trucks!F14 -> 1476.4571 | X41: =W41 -> 1476.4571 | Y41: =Trucks!F15 -> 1517.8299 | Z41: =Y41 -> 1517.8299 | AA41: =Z41 -> 1517.8299 | AB41: =Trucks!F16 -> 1524.404 | AC41: =AB41 -> 1524.404 | AD41: =AC41 -> 1524.404 | AE41: =AD41 -> 1524.404 | AF41: =Trucks!G14 -> 56.323061 | AL41: 1 | AZ41: =Trucks!E14 -> 15.5
A42: * | B42: =Technologies!C86 -> TCDSLC10 | C42: =Technologies!D86 -> Commercial Truck, Diesel 2010 | D42: bn-vmt, bn-vmt/a | E42: TCDSL | F42: =Commodities!C$18 -> TC | G42: 1 | H42: 2010 | I42: =AZ42+5 -> 20.5 | J42: 0.18 | K42: =Trucks!H17 -> 0.13584461 | V42: =Trucks!F17 -> 1393.1309 | AF42: =Trucks!G17 -> 30.977683 | AL42: 1 | AN42: 0 | AO42: 0 | AP42: 0 | AQ42: 0 | AR42: 0 | AS42: 0 | AT42: 0 | AU42: 0 | AV42: 0 | AZ42: 15.5
A43: * | B43: =Technologies!C87 -> TCDSLC | C43: =Technologies!D87 -> Commercial Truck, Conventional Diesel | D43: bn-vmt, bn-vmt/a | E43: TCDSL | F43: =Commodities!C$18 -> TC | G43: 1 | H43: 2015 | I43: =AZ43+5 -> 20.5 | J43: 0.18 | M43: =Trucks!H18 -> 0.14846917 | N43: =Trucks!H19 -> 0.15596404 | O43: =N43 -> 0.15596404 | P43: =O43 -> 0.15596404 | Q43: =P43 -> 0.15596404 | R43: =Q43 -> 0.15596404 | S43: =R43 -> 0.15596404 | T43: =S43 -> 0.15596404 | U43: =T43 -> 0.15596404 | W43: =Trucks!F18 -> 1403.6763 | X43: =Trucks!F19 -> 1413.3892 | Y43: =X43 -> 1413.3892 | Z43: =Y43 -> 1413.3892 | AA43: =Z43 -> 1413.3892 | AB43: =AA43 -> 1413.3892 | AC43: =AB43 -> 1413.3892 | AD43: =AC43 -> 1413.3892 | AE43: =AD43 -> 1413.3892 | AF43: =Trucks!G18 -> 30.977683 | AL43: 1 | AZ43: =Trucks!E18 -> 15.5
A44: * | B44: =Technologies!C88 -> TCDSLIM | C44: =Technologies!D88 -> Commercial Truck, Improved Diesel | D44: bn-vmt, bn-vmt/a | E44: TCDSL | F44: =Commodities!C$18 -> TC | G44: 1 | H44: 2025 | I44: =AZ44+5 -> 20.5 | J44: 0.24 | K44: =Trucks!H20 -> 0.1774427 | Y44: =Trucks!F20 -> 1460.5131 | Z44: =Y44 -> 1460.5131 | AA44: =Z44 -> 1460.5131 | AB44: =AA44 -> 1460.5131 | AC44: =AB44 -> 1460.5131 | AD44: =AC44 -> 1460.5131 | AE44: =AD44 -> 1460.5131 | AF44: =AF43 -> 30.977683 | AL44: 1 | AZ44: 15.5
A45: * | B45: =Technologies!C89 -> TCDSLAH | C45: =Technologies!D89 -> Commercial Truck, Advanced Hybrid Diesel | D45: bn-vmt, bn-vmt/a | E45: TCDSL | F45: =Commodities!C$18 -> TC | G45: 1 | H45: =Trucks!D21 -> 2015 | I45: =AZ45+5 -> 20.5 | J45: 0.28 | M45: =Trucks!H21 -> 0.21639147 | N45: =M45 -> 0.21639147 | O45: =Trucks!H22 -> 0.25348957 | P45: =O45 -> 0.25348957 | Q45: =P45 -> 0.25348957 | R45: =Trucks!H23 -> 0.25348957 | S45: =R45 -> 0.25348957 | T45: =S45 -> 0.25348957 | U45: =T45 -> 0.25348957 | W45: =Trucks!F21 -> 1905.3811 | X45: =W45 -> 1905.3811 | Y45: =Trucks!F22 -> 1905.3811 | Z45: =Y45 -> 1905.3811 | AA45: =Z45 -> 1905.3811 | AB45: =Trucks!F23 -> 1905.3811 | AC45: =AB45 -> 1905.3811 | AD45: =AC45 -> 1905.3811 | AE45: =AD45 -> 1905.3811 | AF45: =Trucks!G21 -> 30.977683 | AL45: 1 | AZ45: =Trucks!E21 -> 15.5
A46: * | B46: =Technologies!C90 -> TCB20C10 | C46: =Technologies!D90 -> Commercial Truck, B20 2010 | D46: bn-vmt, bn-vmt/a | E46: TCB20X | F46: =Commodities!C$18 -> TC | G46: 1 | H46: 2010 | I46: =AZ46+5 -> 20.5 | J46: 0.18 | K46: =Trucks!H24 -> 0.1357487 | V46: =Trucks!F24 -> 1393.1309 | AF46: =Trucks!G24 -> 30.977683 | AL46: 1 | AN46: 0 | AO46: 0 | AP46: 0 | AQ46: 0 | AR46: 0 | AS46: 0 | AT46: 0 | AU46: 0 | AV46: 0 | AZ46: 15.5
A47: * | B47: =Technologies!C91 -> TCB20C | C47: =Technologies!D91 -> Commercial Truck, Conventional B20 | D47: bn-vmt, bn-vmt/a | E47: TCB20X | F47: =Commodities!C$18 -> TC | G47: 1 | H47: 2015 | I47: =AZ47+5 -> 20.5 | J47: 0.18 | M47: =Trucks!H25 -> 0.14836435 | N47: =Trucks!H26 -> 0.15585394 | O47: =N47 -> 0.15585394 | P47: =O47 -> 0.15585394 | Q47: =P47 -> 0.15585394 | R47: =Q47 -> 0.15585394 | S47: =R47 -> 0.15585394 | T47: =S47 -> 0.15585394 | U47: =T47 -> 0.15585394 | W47: =Trucks!F25 -> 1403.6763 | X47: =Trucks!F26 -> 1413.3892 | Y47: =X47 -> 1413.3892 | Z47: =Y47 -> 1413.3892 | AA47: =Z47 -> 1413.3892 | AB47: =AA47 -> 1413.3892 | AC47: =AB47 -> 1413.3892 | AD47: =AC47 -> 1413.3892 | AE47: =AD47 -> 1413.3892 | AF47: =Trucks!G25 -> 30.977683 | AL47: 1 | AZ47: =Trucks!E25 -> 15.5
A48: * | B48: =Technologies!C92 -> TCB20IM | C48: =Technologies!D92 -> Commercial Truck, Improved B20 | D48: bn-vmt, bn-vmt/a | E48: TCB20X | F48: =Commodities!C$18 -> TC | G48: 1 | H48: 2025 | I48: =AZ48+5 -> 20.5 | J48: 0.24 | K48: =Trucks!H27 -> 0.17744838 | Y48: =Trucks!F27 -> 1460.5131 | Z48: =Y48 -> 1460.5131 | AA48: =Z48 -> 1460.5131 | AB48: =AA48 -> 1460.5131 | AC48: =AB48 -> 1460.5131 | AD48: =AC48 -> 1460.5131 | AE48: =AD48 -> 1460.5131 | AF48: =Trucks!G27 -> 30.977683 | AL48: 1 | AZ48: 15.5
A49: * | B49: =Technologies!C93 -> TCB20AH | C49: =Technologies!D93 -> Commerical Truck, Advanced Hybrid B20 | D49: bn-vmt, bn-vmt/a | E49: TCB20X | F49: =Commodities!C$18 -> TC | G49: 1 | H49: 2015 | I49: =AZ49+5 -> 20.5 | J49: 0.28 | M49: =Trucks!H28 -> 0.21639841 | N49: =M49 -> 0.21639841 | O49: =Trucks!H29 -> 0.25349769 | P49: =O49 -> 0.25349769 | Q49: =P49 -> 0.25349769 | R49: =Trucks!H30 -> 0.25349769 | S49: =R49 -> 0.25349769 | T49: =S49 -> 0.25349769 | U49: =T49 -> 0.25349769 | W49: =Trucks!F28 -> 1905.3811 | X49: =W49 -> 1905.3811 | Y49: =Trucks!F29 -> 1905.3811 | Z49: =Y49 -> 1905.3811 | AA49: =Z49 -> 1905.3811 | AB49: =Trucks!F30 -> 1905.3811 | AC49: =AB49 -> 1905.3811 | AD49: =AC49 -> 1905.3811 | AE49: =AD49 -> 1905.3811 | AF49: =Trucks!G28 -> 30.977683 | AL49: 1 | AZ49: 15.5
A50: * | B50: =Technologies!C94 -> TCCNGC10 | C50: =Technologies!D94 -> Commercial Truck, CNG 2010 | D50: bn-vmt, bn-vmt/a | E50: =Commodities!C$56 -> TCCNG | F50: =Commodities!C$18 -> TC | G50: 1 | H50: 2010 | I50: =AZ50+5 -> 20.5 | J50: 0.18 | K50: =Trucks!H31 -> 0.12808843 | V50: =Trucks!F31 -> 1441.6321 | AF50: =Trucks!G31 -> 56.323061 | AL50: 1 | AN50: 0 | AO50: 0 | AP50: 0 | AQ50: 0 | AR50: 0 | AS50: 0 | AT50: 0 | AU50: 0 | AV50: 0 | AZ50: 15.5
A51: * | B51: =Technologies!C95 -> TCCNGC | C51: =Technologies!D95 -> Commercial Truck, Conventional CNG | D51: bn-vmt, bn-vmt/a | E51: =Commodities!C$56 -> TCCNG | F51: =Commodities!C$18 -> TC | G51: 1 | H51: 2015 | I51: =AZ51+5 -> 20.5 | J51: 0.18 | M51: =Trucks!H32 -> 0.1394347 | N51: =Trucks!H33 -> 0.14271413 | O51: =N51 -> 0.14271413 | P51: =O51 -> 0.14271413 | Q51: =P51 -> 0.14271413 | R51: =Q51 -> 0.14271413 | S51: =R51 -> 0.14271413 | T51: =S51 -> 0.14271413 | U51: =T51 -> 0.14271413 | W51: =Trucks!F32 -> 1453.1169 | X51: =Trucks!F33 -> 1464.2086 | Y51: =X51 -> 1464.2086 | Z51: =Y51 -> 1464.2086 | AA51: =Z51 -> 1464.2086 | AB51: =AA51 -> 1464.2086 | AC51: =AB51 -> 1464.2086 | AD51: =AC51 -> 1464.2086 | AE51: =AD51 -> 1464.2086 | AF51: =Trucks!G32 -> 56.323061 | AL51: 1 | AZ51: =Trucks!E32 -> 15.5
A52: * | B52: =Technologies!C96 -> TCCNGIM | C52: =Technologies!D96 -> Commercial Truck, Improved CNG | D52: bn-vmt, bn-vmt/a | E52: =Commodities!C$56 -> TCCNG | F52: =Commodities!C$18 -> TC | G52: 1 | H52: 2025 | I52: =AZ52+5 -> 20.5 | J52: 0.24 | O52: =Trucks!H34 -> 0.18738156 | P52: =O52 -> 0.18738156 | Q52: =P52 -> 0.18738156 | R52: =Trucks!H35 -> 0.21329903 | S52: =R52 -> 0.21329903 | T52: =S52 -> 0.21329903 | U52: =T52 -> 0.21329903 | Y52: =Trucks!F34 -> 1503.8621 | Z52: =Y52 -> 1503.8621 | AA52: =Z52 -> 1503.8621 | AB52: =Trucks!F35 -> 1581.2056 | AC52: =AB52 -> 1581.2056 | AD52: =AC52 -> 1581.2056 | AE52: =AD52 -> 1581.2056 | AF52: =AF51 -> 56.323061 | AL52: 1 | AZ52: 15.5
A53: * | B53: =Technologies!C97 -> TCCNGADV | C53: =Technologies!D97 -> Commerical Truck, Advanced CNG | D53: bn-vmt, bn-vmt/a | E53: =Commodities!C$56 -> TCCNG | F53: =Commodities!C$18 -> TC | G53: 1 | H53: 2015 | I53: =AZ53+5 -> 20.5 | J53: 0.28 | M53: =Trucks!H36 -> 0.22501753 | N53: =M53 -> 0.22501753 | O53: =Trucks!H37 -> 0.28110087 | P53: =O53 -> 0.28110087 | Q53: =P53 -> 0.28110087 | R53: =Trucks!H38 -> 0.28415431 | S53: =R53 -> 0.28415431 | T53: =S53 -> 0.28415431 | U53: =T53 -> 0.28415431 | W53: =Trucks!F36 -> 1508.0083 | X53: =W53 -> 1508.0083 | Y53: =Trucks!F37 -> 1549.3743 | Z53: =Y53 -> 1549.3743 | AA53: =Z53 -> 1549.3743 | AB53: =Trucks!F38 -> 1555.9665 | AC53: =AB53 -> 1555.9665 | AD53: =AC53 -> 1555.9665 | AE53: =AD53 -> 1555.9665 | AF53: =Trucks!G36 -> 56.323061 | AL53: 1 | AZ53: 15.5
A54: * | B54: =Technologies!C98 -> TCCNGAH | C54: =Technologies!D98 -> Commerical Truck, Advanced Hybrid CNG | D54: bn-vmt, bn-vmt/a | E54: =Commodities!C$56 -> TCCNG | F54: =Commodities!C$18 -> TC | G54: 1 | H54: 2015 | I54: =AZ54+5 -> 20.5 | J54: 0.28 | M54: =Trucks!H39 -> 0.31614963 | N54: =M54 -> 0.31614963 | O54: =Trucks!H40 -> 0.39494672 | P54: =O54 -> 0.39494672 | Q54: =P54 -> 0.39494672 | R54: =Trucks!H41 -> 0.3992368 | S54: =R54 -> 0.3992368 | T54: =S54 -> 0.3992368 | U54: =T54 -> 0.3992368 | W54: =Trucks!F39 -> 1804.5869 | X54: =W54 -> 1804.5869 | Y54: =Trucks!F40 -> 1845.953 | Z54: =Y54 -> 1845.953 | AA54: =Z54 -> 1845.953 | AB54: =Trucks!F41 -> 1852.5452 | AC54: =AB54 -> 1852.5452 | AD54: =AC54 -> 1852.5452 | AE54: =AD54 -> 1852.5452 | AF54: =Trucks!G39 -> 56.323061 | AL54: 1 | AZ54: 15.5
A55: * | B55: =Technologies!C99 -> TCE85C10 | C55: =Technologies!D99 -> Commercial Truck, E85 2010 | D55: bn-vmt, bn-vmt/a | E55: TCE85X | F55: =Commodities!C$18 -> TC | G55: 1 | H55: 2010 | I55: =AZ55+5 -> 20.5 | J55: 0.18 | K55: =Trucks!H42 -> 0.10181148 | V55: =Trucks!F42 -> 1154.5364 | AF55: =Trucks!G42 -> 56.323061 | AL55: 1 | AN55: 0 | AO55: 0 | AP55: 0 | AQ55: 0 | AR55: 0 | AS55: 0 | AT55: 0 | AU55: 0 | AV55: 0 | AZ55: 15.5
A56: * | B56: =Technologies!C100 -> TCE85C | C56: =Technologies!D100 -> Commercial Truck, Conventional E85 | D56: bn-vmt, bn-vmt/a | E56: TCE85X | F56: =Commodities!C$18 -> TC | G56: 1 | H56: 2015 | I56: =AZ56+5 -> 20.5 | J56: 0.18 | M56: =Trucks!H43 -> 0.1108301 | N56: =Trucks!H44 -> 0.11437545 | O56: =N56 -> 0.11437545 | P56: =O56 -> 0.11437545 | Q56: =P56 -> 0.11437545 | R56: =Q56 -> 0.11437545 | S56: =R56 -> 0.11437545 | T56: =S56 -> 0.11437545 | U56: =T56 -> 0.11437545 | W56: =Trucks!F43 -> 1163.4071 | X56: =Trucks!F44 -> 1136.2853 | Y56: =X56 -> 1136.2853 | Z56: =Y56 -> 1136.2853 | AA56: =Z56 -> 1136.2853 | AB56: =AA56 -> 1136.2853 | AC56: =AB56 -> 1136.2853 | AD56: =AC56 -> 1136.2853 | AE56: =AD56 -> 1136.2853 | AF56: =Trucks!G43 -> 56.323061 | AL56: 1 | AZ56: =Trucks!E43 -> 15.5
A57: * | B57: =Technologies!C101 -> TCE85IM | C57: =Technologies!D101 -> Commercial Truck, Improved E85 | D57: bn-vmt, bn-vmt/a | E57: TCE85X | F57: =Commodities!C$18 -> TC | G57: 1 | H57: 2025 | I57: =AZ57+5 -> 20.5 | J57: 0.24 | O57: =Trucks!H45 -> 0.12304026 | P57: =O57 -> 0.12304026 | Q57: =P57 -> 0.12304026 | R57: =Trucks!H46 -> 0.13545981 | S57: =R57 -> 0.13545981 | T57: =S57 -> 0.13545981 | U57: =T57 -> 0.13545981 | Y57: =Trucks!F45 -> 1176.1861 | Z57: =Y57 -> 1176.1861 | AA57: =Z57 -> 1176.1861 | AB57: =Trucks!F46 -> 1212.863 | AC57: =AB57 -> 1212.863 | AD57: =AC57 -> 1212.863 | AE57: =AD57 -> 1212.863 | AF57: =AF56 -> 56.323061 | AL57: 1 | AZ57: 15.5
A58: * | B58: =Technologies!C102 -> TCE85ADV | C58: =Technologies!D102 -> Commercial Truck, Advanced E85 | D58: bn-vmt, bn-vmt/a | E58: TCE85X | F58: =Commodities!C$18 -> TC | G58: 1 | H58: 2015 | I58: =AZ58+5 -> 20.5 | J58: 0.28 | M58: =Trucks!H47 -> 0.17885587 | N58: =M58 -> 0.17885587 | O58: =Trucks!H48 -> 0.22343388 | P58: =O58 -> 0.22343388 | Q58: =P58 -> 0.22343388 | R58: =Trucks!H49 -> 0.22586092 | S58: =R58 -> 0.22586092 | T58: =S58 -> 0.22586092 | U58: =T58 -> 0.22586092 | W58: =Trucks!F47 -> 1184.7542 | X58: =W58 -> 1184.7542 | Y58: =Trucks!F48 -> 1226.1202 | Z58: =Y58 -> 1226.1202 | AA58: =Z58 -> 1226.1202 | AB58: =Trucks!F49 -> 1232.7124 | AC58: =AB58 -> 1232.7124 | AD58: =AC58 -> 1232.7124 | AE58: =AD58 -> 1232.7124 | AF58: =AF57 -> 56.323061 | AL58: 1 | AZ58: 15.5
A59: * | B59: =Technologies!C103 -> TCE85AH | C59: =Technologies!D103 -> Commerical Truck, Hybrid E85 | D59: bn-vmt, bn-vmt/a | E59: TCE85X | F59: =Commodities!C$18 -> TC | G59: 1 | H59: 2015 | I59: =AZ59+5 -> 20.5 | J59: 0.28 | M59: =Trucks!H50 -> 0.2512925 | N59: =M59 -> 0.2512925 | O59: =Trucks!H51 -> 0.3139246 | P59: =O59 -> 0.3139246 | Q59: =P59 -> 0.3139246 | R59: =Trucks!H52 -> 0.31733459 | S59: =R59 -> 0.31733459 | T59: =S59 -> 0.31733459 | U59: =T59 -> 0.31733459 | W59: =Trucks!F50 -> 1481.3328 | X59: =W59 -> 1481.3328 | Y59: =Trucks!F51 -> 1522.6989 | Z59: =Y59 -> 1522.6989 | AA59: =Z59 -> 1522.6989 | AB59: =Trucks!F52 -> 1529.2911 | AC59: =AB59 -> 1529.2911 | AD59: =AC59 -> 1529.2911 | AE59: =AD59 -> 1529.2911 | AF59: =AF58 -> 56.323061 | AL59: 1 | AZ59: 15.5
A60: * | B60: =Technologies!C104 -> TCLPGC10 | C60: =Technologies!D104 -> Commercial Truck, LPG 2010 | D60: bn-vmt, bn-vmt/a | E60: =Commodities!C29 -> TRNLPG1 | F60: =Commodities!C$18 -> TC | G60: 1 | H60: 2010 | I60: =AZ60+5 -> 20.5 | J60: 0.18 | K60: =Trucks!H53 -> 0.11401158 | V60: =Trucks!F53 -> 1397.7833 | AF60: =Trucks!G53 -> 56.323061 | AL60: 1 | AN60: 0 | AO60: 0 | AP60: 0 | AQ60: 0 | AR60: 0 | AS60: 0 | AT60: 0 | AU60: 0 | AV60: 0 | AZ60: 15.5
A61: * | B61: =Technologies!C105 -> TCLPGC | C61: =Technologies!D105 -> Commercial Truck, Conventional LPG | D61: bn-vmt, bn-vmt/a | E61: =Commodities!C29 -> TRNLPG1 | F61: =Commodities!C$18 -> TC | G61: 1 | H61: 2015 | I61: =AZ61+5 -> 20.5 | J61: 0.18 | M61: =Trucks!H54 -> 0.12411091 | N61: =Trucks!H55 -> 0.1280811 | O61: =N61 -> 0.1280811 | P61: =O61 -> 0.1280811 | Q61: =P61 -> 0.1280811 | R61: =Q61 -> 0.1280811 | S61: =R61 -> 0.1280811 | T61: =S61 -> 0.1280811 | U61: =T61 -> 0.1280811 | W61: =Trucks!F54 -> 1408.9187 | X61: =Trucks!F55 -> 1419.673 | Y61: =X61 -> 1419.673 | Z61: =Y61 -> 1419.673 | AA61: =Z61 -> 1419.673 | AB61: =AA61 -> 1419.673 | AC61: =AB61 -> 1419.673 | AD61: =AC61 -> 1419.673 | AE61: =AD61 -> 1419.673 | AF61: =Trucks!G54 -> 56.323061 | AL61: 1 | AZ61: =Trucks!E54 -> 15.5
A62: * | B62: =Technologies!C106 -> TCLPGIM | C62: =Technologies!D106 -> Commercial Truck, Improved LPG | D62: bn-vmt, bn-vmt/a | E62: =Commodities!C29 -> TRNLPG1 | F62: =Commodities!C$18 -> TC | G62: 1 | H62: 2025 | I62: =AZ62+5 -> 20.5 | J62: 0.24 | O62: =Trucks!H56 -> 0.16678843 | P62: =O62 -> 0.16678843 | Q62: =P62 -> 0.16678843 | R62: =Trucks!H57 -> 0.18985759 | S62: =R62 -> 0.18985759 | T62: =S62 -> 0.18985759 | U62: =T62 -> 0.18985759 | Y62: =Trucks!F56 -> 1458.1205 | Z62: =Y62 -> 1458.1205 | AA62: =Z62 -> 1458.1205 | AB62: =Trucks!F57 -> 1533.1114 | AC62: =AB62 -> 1533.1114 | AD62: =AC62 -> 1533.1114 | AE62: =AD62 -> 1533.1114 | AF62: =AF61 -> 56.323061 | AL62: 1 | AZ62: 15.5
A63: * | B63: =Technologies!C107 -> TCLPGADV | C63: =Technologies!D107 -> Commercial Truck, Advanced LPG | D63: bn-vmt, bn-vmt/a | E63: =Commodities!C29 -> TRNLPG1 | F63: =Commodities!C$18 -> TC | G63: 1 | H63: 2015 | I63: =AZ63+5 -> 20.5 | J63: 0.28 | M63: =Trucks!H58 -> 0.20028823 | N63: =M63 -> 0.20028823 | O63: =Trucks!H59 -> 0.25020804 | P63: =O63 -> 0.25020804 | Q63: =P63 -> 0.25020804 | R63: =Trucks!H60 -> 0.25292591 | S63: =R63 -> 0.25292591 | T63: =S63 -> 0.25292591 | U63: =T63 -> 0.25292591 | W63: =Trucks!F58 -> 1464.1594 | X63: =W63 -> 1464.1594 | Y63: =Trucks!F60 -> 1512.1177 | Z63: =Y63 -> 1512.1177 | AA63: =Z63 -> 1512.1177 | AB63: =Trucks!F60 -> 1512.1177 | AC63: =AB63 -> 1512.1177 | AD63: =AC63 -> 1512.1177 | AE63: =AD63 -> 1512.1177 | AF63: =AF62 -> 56.323061 | AL63: 1 | AZ63: 15.5
A64: * | B64: =Technologies!C108 -> TCLPGAH | C64: =Technologies!D108 -> Commercial Truck, Hybrid LPG | D64: bn-vmt, bn-vmt/a | E64: =Commodities!C29 -> TRNLPG1 | F64: =Commodities!C$18 -> TC | G64: 1 | H64: 2015 | I64: =AZ64+5 -> 20.5 | J64: 0.28 | M64: =Trucks!H61 -> 0.28140496 | N64: =M64 -> 0.28140496 | O64: =Trucks!H62 -> 0.35154229 | P64: =O64 -> 0.35154229 | Q64: =P64 -> 0.35154229 | R64: =Trucks!H63 -> 0.3553609 | S64: =R64 -> 0.3553609 | T64: =S64 -> 0.3553609 | U64: =T64 -> 0.3553609 | W64: =Trucks!F61 -> 1760.7381 | X64: =W64 -> 1760.7381 | Y64: =Trucks!F62 -> 1802.1041 | Z64: =Y64 -> 1802.1041 | AA64: =Z64 -> 1802.1041 | AB64: =Trucks!F63 -> 1808.6964 | AC64: =AB64 -> 1808.6964 | AD64: =AC64 -> 1808.6964 | AE64: =AD64 -> 1808.6964 | AF64: =AF63 -> 56.323061 | AL64: 1 | AZ64: 15.5
A65: * | B65: =Technologies!C109 -> TCH2FC | C65: =Technologies!D109 -> Commercial Truck, Hydrogen Fuel Cell | D65: bn-vmt, bn-vmt/a | E65: =Commodities!C53 -> TRNH2 | F65: =Commodities!C$18 -> TC | G65: 1 | H65: =Trucks!D64 -> 2025 | I65: =AZ65+5 -> 20.5 | J65: 0.24 | O65: =Trucks!H64 -> 0.34109858 | P65: =O65 -> 0.34109858 | Q65: =P65 -> 0.34109858 | R65: =Trucks!H65 -> 0.34109858 | S65: =R65 -> 0.34109858 | T65: =S65 -> 0.34109858 | U65: =T65 -> 0.34109858 | Y65: =Trucks!F64 -> 2696.3939 | Z65: =Y65 -> 2696.3939 | AA65: =Z65 -> 2696.3939 | AB65: =Trucks!F65 -> 2696.3939 | AC65: =AB65 -> 2696.3939 | AD65: =AC65 -> 2696.3939 | AE65: =AD65 -> 2696.3939 | AF65: =Trucks!G64 -> 15.488842 | AL65: 1 | AZ65: =Trucks!E64 -> 15.5
A66: *Medium Duty Trucks
A67: =Technologies!B114 -> R2,R3,R4,R5,R6 | B67: =Technologies!C114 -> TMGSLC10 | C67: =Technologies!D114 -> Medium Duty Truck, Gasoline, 2010 | D67: bn-vmt, bn-vmt/a | E67: =Commodities!C$39 -> TMGSL | F67: =Commodities!C$11 -> TM | G67: 1 | H67: 2010 | I67: =AZ67+5 -> 24 | J67: 0.18 | K67: =Trucks!H88 -> 0.062417563 | V67: =Trucks!F88 -> 5812.2034 | AF67: =Trucks!G88 -> 248.8047 | AL67: 1 | AM67: 0 | AN67: 0 | AO67: 0 | AP67: 0 | AQ67: 0 | AR67: 0 | AS67: 0 | AT67: 0 | AU67: 0 | AV67: 0 | AZ67: 19
A68: =Technologies!B115 -> R2,R3,R4,R5,R6 | B68: =Technologies!C115 -> TMGSLC | C68: =Technologies!D115 -> Medium Duty Truck, Conventional Gasoline | D68: bn-vmt, bn-vmt/a | E68: =Commodities!C$39 -> TMGSL | F68: =Commodities!C$11 -> TM | G68: 1 | H68: 2015 | I68: =AZ68+5 -> 24 | J68: 0.18 | M68: =Trucks!H89 -> 0.064948005 | N68: =Trucks!H90 -> 0.06973054 | O68: =N68 -> 0.06973054 | P68: =O68 -> 0.06973054 | Q68: =P68 -> 0.06973054 | R68: =Q68 -> 0.06973054 | S68: =R68 -> 0.06973054 | T68: =S68 -> 0.06973054 | U68: =T68 -> 0.06973054 | W68: =Trucks!F89 -> 5834.9327 | X68: =Trucks!F90 -> 5908.6664 | Y68: =Trucks!F90 -> 5908.6664 | Z68: =Y68 -> 5908.6664 | AA68: =Z68 -> 5908.6664 | AB68: =AA68 -> 5908.6664 | AC68: =AB68 -> 5908.6664 | AD68: =AC68 -> 5908.6664 | AE68: =AD68 -> 5908.6664 | AF68: =Trucks!G88 -> 248.8047 | AG68: 0 | AH68: 0 | AI68: 0 | AJ68: 0 | AK68: 0 | AL68: 1 | AM68: 0 | AO68: 0 | AP68: 0 | AQ68: 0 | AR68: 0 | AS68: 0 | AT68: 0 | AU68: 0 | AV68: 0 | AZ68: 19
A69: =Technologies!B116 -> R2,R3,R4,R5,R6 | B69: =Technologies!C116 -> TMGSLIM | C69: =Technologies!D116 -> Medium Duty Truck, Improved Gasoline | D69: bn-vmt, bn-vmt/a | E69: =Commodities!C$39 -> TMGSL | F69: =Commodities!C$11 -> TM | G69: 1 | H69: 2025 | I69: =AZ69+5 -> 24 | J69: 0.24 | K69: =Trucks!H91 -> 0.075246903 | Y69: =Trucks!F91 -> 6443.5419 | Z69: =Y69 -> 6443.5419 | AA69: =Z69 -> 6443.5419 | AB69: =AA69 -> 6443.5419 | AC69: =AB69 -> 6443.5419 | AD69: =AC69 -> 6443.5419 | AE69: =AD69 -> 6443.5419 | AF69: =Trucks!G89 -> 248.8047 | AG69: 0 | AH69: 0 | AI69: 0 | AJ69: 0 | AK69: 0 | AL69: 1 | AM69: 0 | AN69: 0 | AZ69: 19
A70: =Technologies!B117 -> R2,R3,R4,R5,R6 | B70: =Technologies!C117 -> TMGSLAH | C70: =Technologies!D117 -> Medium Duty Truck, Advanced Hybrid Gasoline | D70: bn-vmt, bn-vmt/a | E70: =Commodities!C$39 -> TMGSL | F70: =Commodities!C$11 -> TM | G70: 1 | H70: =Trucks!D92 -> 2015 | I70: =AZ70+5 -> 24 | J70: 0.28 | M70: =Trucks!H92 -> 0.078865434 | N70: =M70 -> 0.078865434 | O70: =Trucks!H93 -> 0.099615057 | P70: =O70 -> 0.099615057 | Q70: =P70 -> 0.099615057 | R70: =Trucks!H94 -> 0.10749317 | S70: =R70 -> 0.10749317 | T70: =S70 -> 0.10749317 | U70: =T70 -> 0.10749317 | W70: =Trucks!F92 -> 6616.01 | X70: =W70 -> 6616.01 | Y70: =Trucks!F93 -> 6935.0019 | Z70: =Y70 -> 6935.0019 | AA70: =Z70 -> 6935.0019 | AB70: =Trucks!F94 -> 7469.8773 | AC70: =AB70 -> 7469.8773 | AD70: =AC70 -> 7469.8773 | AE70: =AD70 -> 7469.8773 | AF70: =Trucks!G92 -> 237.85729 | AG70: 0 | AH70: 0 | AI70: 0 | AJ70: 0 | AK70: 0 | AL70: 1 | AM70: 0 | AN70: 0 | AZ70: =Trucks!E92 -> 19
A71: =Technologies!B118 -> R2,R3,R4,R5,R6 | B71: =Technologies!C118 -> TMDSLC10 | C71: =Technologies!D118 -> Medium Duty Truck, Diesel, 2010 | D71: bn-vmt, bn-vmt/a | E71: =Commodities!C$42 -> TMDSL | F71: =Commodities!C$11 -> TM | G71: 1 | H71: 2010 | I71: =AZ71+5 -> 24 | J71: 0.18 | K71: =TechData!K19 -> 0.083040936 | V71: =Trucks!F78 -> 6276.5914 | AF71: =Trucks!G78 -> 136.84259 | AG71: 0 | AH71: 0 | AI71: 0 | AJ71: 0 | AK71: 0 | AL71: 1 | AM71: 0 | AN71: 0 | AO71: 0 | AP71: 0 | AQ71: 0 | AR71: 0 | AS71: 0 | AT71: 0 | AU71: 0 | AV71: 0 | AZ71: 19
A72: =Technologies!B119 -> R2,R3,R4,R5,R6 | B72: =Technologies!C119 -> TMDSLC | C72: =Technologies!D119 -> Medium Duty Truck, Conventional Diesel | D72: bn-vmt, bn-vmt/a | E72: =Commodities!C$42 -> TMDSL | F72: =Commodities!C$11 -> TM | G72: 1 | H72: 2015 | I72: =AZ72+5 -> 24 | J72: 0.18 | M72: =Trucks!H79 -> 0.075263594 | N72: =Trucks!H80 -> 0.082850619 | O72: =N72 -> 0.082850619 | P72: =O72 -> 0.082850619 | Q72: =P72 -> 0.082850619 | R72: =Q72 -> 0.082850619 | S72: =R72 -> 0.082850619 | T72: =S72 -> 0.082850619 | U72: =T72 -> 0.082850619 | W72: =Trucks!F79 -> 6295.5716 | X72: =Trucks!F80 -> 6469.2832 | Y72: =X72 -> 6469.2832 | Z72: =Y72 -> 6469.2832 | AA72: =Z72 -> 6469.2832 | AB72: =AA72 -> 6469.2832 | AC72: =AB72 -> 6469.2832 | AD72: =AC72 -> 6469.2832 | AE72: =AD72 -> 6469.2832 | AF72: =Trucks!G78 -> 136.84259 | AG72: 0 | AH72: 0 | AI72: 0 | AJ72: 0 | AK72: 0 | AL72: 1 | AM72: 0 | AZ72: 19
A73: =Technologies!B120 -> R2,R3,R4,R5,R6 | B73: =Technologies!C120 -> TMDSLIM | C73: =Technologies!D120 -> Medium Duty Truck, Improved Diesel | D73: bn-vmt, bn-vmt/a | E73: =Commodities!C$42 -> TMDSL | F73: =Commodities!C$11 -> TM | G73: 1 | H73: 2025 | I73: =AZ73+5 -> 24 | J73: 0.24 | K73: =Trucks!H81 -> 0.084286625 | Y73: =Trucks!F81 -> 6691.9683 | Z73: =Y73 -> 6691.9683 | AA73: =Z73 -> 6691.9683 | AB73: =AA73 -> 6691.9683 | AC73: =AB73 -> 6691.9683 | AD73: =AC73 -> 6691.9683 | AE73: =AD73 -> 6691.9683 | AF73: =AF72 -> 136.84259 | AG73: 0 | AH73: 0 | AI73: 0 | AJ73: 0 | AK73: 0 | AL73: 1 | AM73: 0 | AN73: 0 | AZ73: 19
A74: =Technologies!B121 -> R2,R3,R4,R5,R6 | B74: =Technologies!C121 -> TMDSLADV | C74: =Technologies!D121 -> Medium Duty Truck, Advanced Diesel | D74: bn-vmt, bn-vmt/a | E74: =Commodities!C$42 -> TMDSL | F74: =Commodities!C$11 -> TM | G74: 1 | H74: 2015 | I74: =AZ74+5 -> 24 | J74: 0.28 | M74: =Trucks!H82 -> 0.084286625 | N74: =M74 -> 0.084286625 | O74: =Trucks!H83 -> 0.087074165 | P74: =O74 -> 0.087074165 | Q74: =P74 -> 0.087074165 | R74: =Trucks!H84 -> 0.087074165 | S74: =R74 -> 0.087074165 | T74: =S74 -> 0.087074165 | U74: =T74 -> 0.087074165 | W74: =Trucks!F82 -> 6767.5657 | X74: =W74 -> 6767.5657 | Y74: =Trucks!F83 -> 6936.7579 | Z74: =Y74 -> 6936.7579 | AA74: =Z74 -> 6936.7579 | AB74: =Trucks!F84 -> 6936.7579 | AC74: =AB74 -> 6936.7579 | AD74: =AC74 -> 6936.7579 | AE74: =AD74 -> 6936.7579 | AF74: =AF73 -> 136.84259 | AG74: 0 | AH74: 0 | AI74: 0 | AJ74: 0 | AK74: 0 | AL74: 1 | AM74: 0 | AN74: 0 | AZ74: 19
A75: =Technologies!B122 -> R2,R3,R4,R5,R6 | B75: =Technologies!C122 -> TMDSLAH | C75: =Technologies!D122 -> Medium Duty Truck, Advanced Hybrid Diesel | D75: bn-vmt, bn-vmt/a | E75: =Commodities!C$42 -> TMDSL | F75: =Commodities!C$11 -> TM | G75: 1 | H75: =Trucks!D85 -> 2015 | I75: =AZ75+5 -> 24 | J75: 0.28 | M75: =Trucks!H85 -> 0.12040946 | N75: =M75 -> 0.12040946 | O75: =Trucks!H86 -> 0.12438728 | P75: =O75 -> 0.12438728 | Q75: =P75 -> 0.12438728 | R75: =Trucks!H87 -> 0.12438728 | S75: =R75 -> 0.12438728 | T75: =S75 -> 0.12438728 | U75: =T75 -> 0.12438728 | W75: =Trucks!F85 -> 8334.2222 | X75: =W75 -> 8334.2222 | Y75: =Trucks!F86 -> 7963.0153 | Z75: =Y75 -> 7963.0153 | AA75: =Z75 -> 7963.0153 | AB75: =Trucks!F87 -> 7963.0153 | AC75: =AB75 -> 7963.0153 | AD75: =AC75 -> 7963.0153 | AE75: =AD75 -> 7963.0153 | AF75: =Trucks!G85 -> 125.89518 | AG75: 0 | AH75: 0 | AI75: 0 | AJ75: 0 | AK75: 0 | AL75: 1 | AM75: 0 | AN75: 0 | AZ75: =Trucks!E85 -> 19
A76: * | B76: =Technologies!C123 -> TMB20C10 | C76: =Technologies!D123 -> Medium Duty Truck, B20, 2010 | D76: bn-vmt, bn-vmt/a | E76: =Commodities!C$63 -> TMB20X | F76: =Commodities!C$11 -> TM | G76: 1 | H76: 2010 | I76: =AZ76+5 -> 24 | J76: 0.18 | K76: =Trucks!H95 -> 0.071504036 | V76: =Trucks!F95 -> 6276.5914 | AF76: =Trucks!G95 -> 136.84259 | AL76: 1 | AN76: 0 | AO76: 0 | AP76: 0 | AQ76: 0 | AR76: 0 | AS76: 0 | AT76: 0 | AU76: 0 | AV76: 0 | AZ76: 19
A77: * | B77: =Technologies!C124 -> TMB20C | C77: =Technologies!D124 -> Medium Duty Truck, Conventional B20 | D77: bn-vmt, bn-vmt/a | E77: =Commodities!C$63 -> TMB20X | F77: =Commodities!C$11 -> TM | G77: 1 | H77: 2015 | I77: =AZ77+5 -> 24 | J77: 0.18 | M77: =Trucks!H96 -> 0.075210459 | N77: =Trucks!H97 -> 0.077965337 | O77: =N77 -> 0.077965337 | P77: =O77 -> 0.077965337 | Q77: =P77 -> 0.077965337 | R77: =Q77 -> 0.077965337 | S77: =R77 -> 0.077965337 | T77: =S77 -> 0.077965337 | U77: =T77 -> 0.077965337 | W77: =Trucks!F96 -> 6295.5716 | X77: =Trucks!F97 -> 6347.8257 | Y77: =X77 -> 6347.8257 | Z77: =Y77 -> 6347.8257 | AA77: =Z77 -> 6347.8257 | AB77: =AA77 -> 6347.8257 | AC77: =AB77 -> 6347.8257 | AD77: =AC77 -> 6347.8257 | AE77: =AD77 -> 6347.8257 | AF77: =Trucks!G96 -> 136.84259 | AL77: 1 | AZ77: 19
A78: * | B78: =Technologies!C125 -> TMB20IM | C78: =Technologies!D125 -> Medium Duty Truck, Improved B20 | D78: bn-vmt, bn-vmt/a | E78: =Commodities!C$63 -> TMB20X | F78: =Commodities!C$11 -> TM | G78: 1 | H78: 2025 | I78: =AZ78+5 -> 24 | J78: 0.24 | K78: =Trucks!H98 -> 0.083060709 | Y78: =Trucks!F98 -> 6469.2832 | Z78: =Y78 -> 6469.2832 | AA78: =Z78 -> 6469.2832 | AB78: =AA78 -> 6469.2832 | AC78: =AB78 -> 6469.2832 | AD78: =AC78 -> 6469.2832 | AE78: =AD78 -> 6469.2832 | AF78: =AF77 -> 136.84259 | AL78: 1 | AZ78: 19
A79: * | B79: =Technologies!C126 -> TMB20ADV | C79: =Technologies!D126 -> Medium Duty Truck, Advanced Tech B20 | D79: bn-vmt, bn-vmt/a | E79: =Commodities!C$63 -> TMB20X | F79: =Commodities!C$11 -> TM | G79: 1 | H79: =Trucks!D99 -> 2015 | I79: =AZ79+5 -> 24 | J79: 0.28 | M79: =Trucks!H99 -> 0.084287694 | N79: =M79 -> 0.084287694 | O79: =Trucks!H100 -> 0.087074064 | P79: =O79 -> 0.087074064 | Q79: =P79 -> 0.087074064 | R79: =Trucks!H101 -> 0.087074064 | S79: =R79 -> 0.087074064 | T79: =S79 -> 0.087074064 | U79: =T79 -> 0.087074064 | W79: =Trucks!F99 -> 6772.0678 | X79: =W79 -> 6772.0678 | Y79: =Trucks!F100 -> 6936.7571 | Z79: =Y79 -> 6936.7571 | AA79: =Z79 -> 6936.7571 | AB79: =Trucks!F101 -> 6936.7571 | AC79: =AB79 -> 6936.7571 | AD79: =AC79 -> 6936.7571 | AE79: =AD79 -> 6936.7571 | AF79: =AF78 -> 136.84259 | AL79: 1 | AZ79: 19
A80: * | B80: =Technologies!C127 -> TMB20AH | C80: =Technologies!D127 -> Medium Duty Truck, Advanced Hybrid B20 | D80: bn-vmt, bn-vmt/a | E80: =Commodities!C$63 -> TMB20X | F80: =Commodities!C$11 -> TM | G80: 1 | H80: =Trucks!D102 -> 2015 | I80: =AZ80+5 -> 24 | J80: 0.28 | M80: =Trucks!H102 -> 0.12041099 | N80: =M80 -> 0.12041099 | O80: =Trucks!H103 -> 0.12439152 | P80: =O80 -> 0.12439152 | Q80: =P80 -> 0.12439152 | R80: =Trucks!H104 -> 0.12439152 | S80: =R80 -> 0.12439152 | T80: =S80 -> 0.12439152 | U80: =T80 -> 0.12439152 | W80: =Trucks!F102 -> 8334.2222 | X80: =W80 -> 8334.2222 | Y80: =Trucks!F103 -> 7963.0926 | Z80: =Y80 -> 7963.0926 | AA80: =Z80 -> 7963.0926 | AB80: =Trucks!F104 -> 7963.0926 | AC80: =AB80 -> 7963.0926 | AD80: =AC80 -> 7963.0926 | AE80: =AD80 -> 7963.0926 | AF80: =Trucks!G102 -> 125.89518 | AL80: 1 | AZ80: 19
A81: =Technologies!B128 -> R2,R3,R4,R5,R6 | B81: =Technologies!C128 -> TMCNGC10 | C81: =Technologies!D128 -> Medium Duty Truck, CNG, 2010 | D81: bn-vmt, bn-vmt/a | E81: =Commodities!C$57 -> TMCNG | F81: =Commodities!C$11 -> TM | G81: 1 | H81: 2010 | I81: =AZ81+5 -> 24 | J81: 0.18 | K81: =Trucks!H105 -> 0.052445275 | V81: =Trucks!F105 -> 6575.7618 | AF81: =Trucks!G105 -> 248.8047 | AG81: 0 | AH81: 0 | AI81: 0 | AJ81: 0 | AK81: 0 | AL81: 1 | AM81: 0 | AO81: 0 | AP81: 0 | AQ81: 0 | AR81: 0 | AS81: 0 | AT81: 0 | AU81: 0 | AV81: 0 | AZ81: 19
A82: =Technologies!B129 -> R2,R3,R4,R5,R6 | B82: =Technologies!C129 -> TMCNGC | C82: =Technologies!D129 -> Medium Duty Truck, Conventional CNG | D82: bn-vmt, bn-vmt/a | E82: =Commodities!C$57 -> TMCNG | F82: =Commodities!C$11 -> TM | G82: 1 | H82: 2015 | I82: =AZ82+5 -> 24 | J82: 0.18 | M82: =Trucks!H106 -> 0.055163784 | N82: =Trucks!H107 -> 0.06092162 | O82: =N82 -> 0.06092162 | P82: =O82 -> 0.06092162 | Q82: =P82 -> 0.06092162 | R82: =Q82 -> 0.06092162 | S82: =R82 -> 0.06092162 | T82: =S82 -> 0.06092162 | U82: =T82 -> 0.06092162 | W82: =Trucks!F106 -> 6601.4772 | X82: =Trucks!F107 -> 6684.8974 | Y82: =X82 -> 6684.8974 | Z82: =Y82 -> 6684.8974 | AA82: =Z82 -> 6684.8974 | AB82: =AA82 -> 6684.8974 | AC82: =AB82 -> 6684.8974 | AD82: =AC82 -> 6684.8974 | AE82: =AD82 -> 6684.8974 | AF82: =Trucks!G106 -> 248.8047 | AG82: 0 | AH82: 0 | AI82: 0 | AJ82: 0 | AK82: 0 | AL82: 1 | AM82: 0 | AN82: 0 | AZ82: 19
A83: =Technologies!B130 -> R2,R3,R4,R5,R6 | B83: =Technologies!C130 -> TMCNGIM | C83: =Technologies!D130 -> Medium Duty Truck, Improved CNG | D83: bn-vmt, bn-vmt/a | E83: =Commodities!C$57 -> TMCNG | F83: =Commodities!C$11 -> TM | G83: 1 | H83: 2025 | I83: =AZ83+5 -> 24 | J83: 0.24 | K83: =Trucks!H108 -> 0.063820237 | Y83: =Trucks!F108 -> 7290.0402 | Z83: =Y83 -> 7290.0402 | AA83: =Z83 -> 7290.0402 | AB83: =AA83 -> 7290.0402 | AC83: =AB83 -> 7290.0402 | AD83: =AC83 -> 7290.0402 | AE83: =AD83 -> 7290.0402 | AF83: =AF82 -> 248.8047 | AG83: 0 | AH83: 0 | AI83: 0 | AJ83: 0 | AK83: 0 | AL83: 1 | AM83: 0 | AN83: 0 | AZ83: 19
A84: =Technologies!B131 -> R2,R3,R4,R5,R6 | B84: =Technologies!C131 -> TMCNGAH | C84: =Technologies!D131 -> Medium Duty Truck, Advanced Hybrid CNG | D84: bn-vmt, bn-vmt/a | E84: =Commodities!C$57 -> TMCNG | F84: =Commodities!C$11 -> TM | G84: 1 | H84: =Trucks!D109 -> 2015 | I84: =AZ84+5 -> 24 | J84: 0.28 | M84: =Trucks!H109 -> 0.066447591 | N84: =M84 -> 0.066447591 | O84: =Trucks!H110 -> 0.083923483 | P84: =O84 -> 0.083923483 | Q84: =P84 -> 0.083923483 | R84: =Trucks!H111 -> 0.09056101 | S84: =R84 -> 0.09056101 | T84: =S84 -> 0.09056101 | U84: =T84 -> 0.09056101 | W84: =Trucks!F109 -> 7843.9564 | X84: =W84 -> 7843.9564 | Y84: =Trucks!F110 -> 8162.9154 | Z84: =Y84 -> 8162.9154 | AA84: =Z84 -> 8162.9154 | AB84: =Trucks!F111 -> 8697.8237 | AC84: =AB84 -> 8697.8237 | AD84: =AC84 -> 8697.8237 | AE84: =AD84 -> 8697.8237 | AF84: =Trucks!G109 -> 237.85729 | AG84: 0 | AH84: 0 | AI84: 0 | AJ84: 0 | AK84: 0 | AL84: 1 | AM84: 0 | AN84: 0 | AZ84: 19
A85: * | B85: =Technologies!C132 -> TMLPGC10 | C85: =Technologies!D132 -> Medium Duty Truck, LPG, 2010 | D85: bn-vmt, bn-vmt/a | E85: =Commodities!C29 -> TRNLPG1 | F85: =Commodities!C$11 -> TM | G85: 1 | H85: 2010 | I85: =AZ85+5 -> 24 | J85: 0.18 | K85: =Trucks!H112 -> 0.067978151 | V85: =Trucks!F112 -> 6193.9826 | AF85: =Trucks!G112 -> 248.8047 | AL85: 1 | AN85: 0 | AO85: 0 | AP85: 0 | AQ85: 0 | AR85: 0 | AS85: 0 | AT85: 0 | AU85: 0 | AV85: 0 | AZ85: 19
A86: * | B86: =Technologies!C133 -> TMLPGC | C86: =Technologies!D133 -> Medium Duty Truck, Conventional LPG | D86: bn-vmt, bn-vmt/a | E86: =Commodities!C29 -> TRNLPG1 | F86: =Commodities!C$11 -> TM | G86: 1 | H86: 2015 | I86: =AZ86+5 -> 24 | J86: 0.18 | M86: =Trucks!H113 -> 0.071501809 | N86: =Trucks!H114 -> 0.078964961 | O86: =N86 -> 0.078964961 | P86: =O86 -> 0.078964961 | Q86: =P86 -> 0.078964961 | R86: =Q86 -> 0.078964961 | S86: =R86 -> 0.078964961 | T86: =S86 -> 0.078964961 | U86: =T86 -> 0.078964961 | W86: =Trucks!F113 -> 6218.205 | X86: =Trucks!F114 -> 6296.7819 | Y86: =X86 -> 6296.7819 | Z86: =Y86 -> 6296.7819 | AA86: =Z86 -> 6296.7819 | AB86: =AA86 -> 6296.7819 | AC86: =AB86 -> 6296.7819 | AD86: =AC86 -> 6296.7819 | AE86: =AD86 -> 6296.7819 | AF86: =Trucks!G113 -> 248.8047 | AL86: 1 | AZ86: 19
A87: * | B87: =Technologies!C134 -> TMLPGIM | C87: =Technologies!D134 -> Medium Duty Truck, Improved LPG | D87: bn-vmt, bn-vmt/a | E87: =Commodities!C29 -> TRNLPG1 | F87: =Commodities!C$11 -> TM | G87: 1 | H87: 2025 | I87: =AZ87+5 -> 24 | J87: 0.24 | K87: =Trucks!H115 -> 0.082722071 | Y87: =Trucks!F115 -> 6866.7911 | Z87: =Y87 -> 6866.7911 | AA87: =Z87 -> 6866.7911 | AB87: =AA87 -> 6866.7911 | AC87: =AB87 -> 6866.7911 | AD87: =AC87 -> 6866.7911 | AE87: =AD87 -> 6866.7911 | AF87: =AF86 -> 248.8047 | AL87: 1 | AZ87: 19
A88: * | B88: =Technologies!C135 -> TMLPGAH | C88: =Technologies!D135 -> Medium Duty Truck, Advanced Hybrid LPG | D88: bn-vmt, bn-vmt/a | E88: =Commodities!C29 -> TRNLPG1 | F88: =Commodities!C$11 -> TM | G88: 1 | H88: =Trucks!D116 -> 2015 | I88: =AZ88+5 -> 24 | J88: 0.28 | M88: =Trucks!H116 -> 0.086127577 | N88: =M88 -> 0.086127577 | O88: =Trucks!H117 -> 0.10877936 | P88: =O88 -> 0.10877936 | Q88: =P88 -> 0.10877936 | R88: =Trucks!H118 -> 0.11738274 | S88: =R88 -> 0.11738274 | T88: =S88 -> 0.11738274 | U88: =T88 -> 0.11738274 | W88: =Trucks!F116 -> 6997.7892 | X88: =W88 -> 6997.7892 | Y88: =Trucks!F117 -> 7316.7482 | Z88: =Y88 -> 7316.7482 | AA88: =Z88 -> 7316.7482 | AB88: =Trucks!F118 -> 7851.6564 | AC88: =AB88 -> 7851.6564 | AD88: =AC88 -> 7851.6564 | AE88: =AD88 -> 7851.6564 | AF88: =Trucks!G116 -> 237.85729 | AL88: 1 | AZ88: 19
A89: *Heavy Duty Trucks
A90: * | B90: =Technologies!C150 -> THSGSL102 | C90: =Technologies!D150 -> Heavy Truck, Short Haul, Gasoline, 2010 | D90: bn-vmt, bn-vmt/a | E90: =Commodities!$C$46 -> TWDSL | F90: =Commodities!$C$16 -> TSW | G90: 1 | H90: 2010 | I90: 24 | J90: 0.18 | K90: 0.038084191 | V90: 4265.2943 | W90: 4265.2943 | X90: 4265.2943 | Y90: 4265.2943 | Z90: 4265.2943 | AA90: 4265.2943 | AB90: 4265.2943 | AC90: 4265.2943 | AD90: 4265.2943 | AE90: 4265.2943 | AF90: 301.42015 | AL90: 1 | AM90: 0 | AN90: 0 | AZ90: 19
A91: * | B91: =Technologies!C151 -> THSDSLC102 | C91: =Technologies!D151 -> Heavy Truck, Short Haul, Conventional Diesel 2010 | D91: bn-vmt, bn-vmt/a | E91: =Commodities!$C$46 -> TWDSL | F91: =Commodities!$C$16 -> TSW | G91: 1 | H91: 2010 | I91: 24 | J91: 0.18 | K91: 0.040092266 | V91: 4606.0861 | AF91: 165.78108 | AL91: 1 | AM91: 0 | AN91: 0 | AS91: 0 | AT91: 0 | AU91: 0 | AV91: 0 | AZ91: 19
A92: * | B92: =Technologies!C152 -> THSDSLC2 | C92: =Technologies!D152 -> Heavy Truck, Short Haul, Conv. Diesel | D92: bn-vmt, bn-vmt/a | E92: =Commodities!$C$46 -> TWDSL | F92: =Commodities!$C$16 -> TSW | G92: 1 | H92: 2015 | I92: 24 | J92: 0.18 | M92: 0.043863448 | N92: 0.043863448 | O92: 0.043863448 | P92: 0.043863448 | Q92: 0.043863448 | R92: 0.043863448 | S92: 0.043863448 | T92: 0.043863448 | U92: 0.043863448 | W92: 4701.3381 | X92: 4701.3381 | Y92: 4701.3381 | Z92: 4701.3381 | AA92: 4701.3381 | AB92: 4701.3381 | AC92: 4701.3381 | AD92: 4701.3381 | AE92: 4701.3381 | AF92: 165.78108 | AL92: 1 | AM92: 0 | AN92: 0 | AZ92: 19
A93: * | B93: =Technologies!C153 -> THSDSLIM2 | C93: =Technologies!D153 -> Heavy Truck, Short Haul, Improved Diesel | D93: bn-vmt, bn-vmt/a | E93: =Commodities!$C$46 -> TWDSL | F93: =Commodities!$C$16 -> TSW | G93: 1 | H93: 2025 | I93: 24 | J93: 0.24 | O93: 0.045383924 | P93: 0.045383924 | Q93: 0.045383924 | R93: 0.046305425 | S93: 0.046305425 | T93: 0.046305425 | U93: 0.046305425 | Y93: 4729.3692 | Z93: 4729.3692 | AA93: 4729.3692 | AB93: 4767.6178 | AC93: 4767.6178 | AD93: 4767.6178 | AE93: 4767.6178 | AF93: 166 | AL93: 1 | AM93: 0 | AN93: 0 | AZ93: 19
A94: * | B94: =Technologies!C154 -> THSDSLADV2 | C94: =Technologies!D154 -> Heavy Truck, Short Haul, Advanced Diesel | D94: bn-vmt, bn-vmt/a | E94: =Commodities!$C$46 -> TWDSL | F94: =Commodities!$C$16 -> TSW | G94: 1 | H94: 2015 | I94: 24 | J94: 0.28 | M94: 0.045998258 | N94: 0.045998258 | O94: 0.046689384 | P94: 0.046689384 | Q94: 0.046689384 | R94: 0.046689384 | S94: 0.046689384 | T94: 0.046689384 | U94: 0.046689384 | W94: 4831.9482 | X94: 4831.9482 | Y94: 5078.3127 | Z94: 5078.3127 | AA94: 5078.3127 | AB94: 5078.3127 | AC94: 5078.3127 | AD94: 5078.3127 | AE94: 5078.3127 | AF94: 165.78108 | AL94: 1 | AM94: 0 | AN94: 0 | AZ94: 19
A95: * | B95: =Technologies!C155 -> THSDSLAH2 | C95: =Technologies!D155 -> Heavy Truck, Short Haul, Hybrid Diesel | D95: bn-vmt, bn-vmt/a | E95: =Commodities!$C$46 -> TWDSL | F95: =Commodities!$C$16 -> TSW | G95: 1 | H95: 2025 | I95: 24 | J95: 0.28 | M95: 0.061126233 | N95: 0.061126233 | O95: 0.061126233 | P95: 0.061126233 | Q95: 0.061126233 | R95: 0.062047734 | S95: 0.062047734 | T95: 0.062047734 | U95: 0.062047734 | W95: 5813.3727 | X95: 5813.3727 | Y95: 5399.9645 | Z95: 5399.9645 | AA95: 5399.9645 | AB95: 5723.2632 | AC95: 5723.2632 | AD95: 5723.2632 | AE95: 5723.2632 | AF95: 165.78108 | AL95: 1 | AM95: 0 | AN95: 0 | AZ95: 19
A96: =Technologies!B139 -> R2,R3,R4,R5,R6 | B96: =Technologies!C139 -> THSCNGE | C96: =Technologies!D139 -> Heavy Truck, Short Haul, CNG exisiting | D96: bn-vmt, bn-vmt/a | E96: =Commodities!C58 -> THCNG | F96: =Commodities!C$12 -> THS | G96: 1 | H96: 2010 | I96: =AZ96+5 -> 24 | K96: =Trucks!H164 -> 0.029974418 | AF96: =Trucks!G164 -> 248.8047 | AL96: 1 | AM96: 0 | AN96: 0 | AO96: 0 | AP96: 0 | AQ96: 0 | AR96: 0 | AS96: 0 | AT96: 0 | AU96: 0 | AV96: 0 | AZ96: =Trucks!E164 -> 19
A97: * | B97: =Technologies!C141 -> THSLPGE | C97: =Technologies!D141 -> Heavy Truck, Short Haul, LPG exisiting | D97: bn-vmt, bn-vmt/a | E97: =Commodities!C29 -> TRNLPG1 | F97: =Commodities!C$12 -> THS | G97: 1 | H97: 2010 | I97: =AZ97+5 -> 24 | J97: 0.18 | K97: =Trucks!H165 -> 0.028246818 | AF97: =Trucks!G165 -> 248.8047 | AL97: 1 | AM97: 0 | AN97: 0 | AO97: 0 | AP97: 0 | AQ97: 0 | AR97: 0 | AS97: 0 | AT97: 0 | AU97: 0 | AV97: 0 | AZ97: =Trucks!E165 -> 19
A98: * | B98: =Technologies!C142 -> THSB20E | C98: =Technologies!D142 -> Heavy Truck, Short Haul, B20exisiting | D98: bn-vmt, bn-vmt/a | E98: =Commodities!C62 -> THB20X | F98: =Commodities!C$12 -> THS | G98: 1 | H98: 2010 | I98: =AZ98+5 -> 24 | K98: =TechData!K24 -> 0.030387433 | AF98: =TechData!AF24 -> 165.78108 | AL98: 1 | AM98: 0 | AN98: 0 | AO98: 0 | AP98: 0 | AQ98: 0 | AR98: 0 | AS98: 0 | AT98: 0 | AU98: 0 | AV98: 0 | AZ98: 19
A99: =Technologies!B143 -> R2,R3,R4,R5,R6 | B99: =Technologies!C143 -> THSGSL10 | C99: =Technologies!D143 -> Heavy Truck, Short Haul, Gasoline, 2010 | D99: bn-vmt, bn-vmt/a | E99: =Commodities!C47 -> THGSL | F99: =Commodities!C$12 -> THS | G99: 1 | H99: =Trucks!D166 -> 2010 | I99: =AZ99+5 -> 24 | J99: 0.18 | K99: =Trucks!H166 -> 0.021878198 | V99: =Trucks!F166 -> 4265.2943 | W99: =V99 -> 4265.2943 | X99: =W99 -> 4265.2943 | Y99: =X99 -> 4265.2943 | Z99: =Y99 -> 4265.2943 | AA99: =Z99 -> 4265.2943 | AB99: =AA99 -> 4265.2943 | AC99: =AB99 -> 4265.2943 | AD99: =AC99 -> 4265.2943 | AE99: =AD99 -> 4265.2943 | AF99: =Trucks!G166 -> 301.42015 | AL99: 1 | AM99: 0 | AN99: 0 | AZ99: =Trucks!E166 -> 19
A100: * | B100: =Technologies!C144 -> THSGSL102 | C100: =Technologies!D144 -> Heavy Truck, Short Haul, Gasoline, 2010 | D100: bn-vmt, bn-vmt/a | E100: =Commodities!$C$48 -> TWGSL | F100: =Commodities!$C$16 -> TSW | G100: 1 | H100: =H99 -> 2010 | I100: =AZ100+5 -> 24 | J100: 0.18 | K100: =K99 -> 0.021878198 | V100: =V99 -> 4265.2943 | W100: =W99 -> 4265.2943 | X100: =X99 -> 4265.2943 | Y100: =Y99 -> 4265.2943 | Z100: =Z99 -> 4265.2943 | AA100: =AA99 -> 4265.2943 | AB100: =AB99 -> 4265.2943 | AC100: =AC99 -> 4265.2943 | ... AF100: =AF99 -> 301.42015 | AL100: 1 | AM100: 0 | AZ100: =AZ99 -> 19
A101: =Technologies!B145 -> R2,R3,R4,R5,R6 | B101: =Technologies!C145 -> THSDSLC10 | C101: =Technologies!D145 -> Heavy Truck, Short Haul, Conventional Diesel 2010 | D101: bn-vmt, bn-vmt/a | E101: =Commodities!C44 -> THDSL | F101: =Commodities!C$12 -> THS | G101: 1 | H101: 2010 | I101: =AZ101+5 -> 24 | J101: 0.18 | K101: =Trucks!H131 -> 0.030387433 | V101: =Trucks!F131 -> 4606.0861 | AF101: =Trucks!G131 -> 165.78108 | AL101: 1 | AM101: 0 | AO101: 0 | AP101: 0 | AQ101: 0 | AR101: 0 | AS101: 0 | AT101: 0 | AU101: 0 | AV101: 0 | AZ101: 19
A102: =Technologies!B146 -> R2,R3,R4,R5,R6 | B102: =Technologies!C146 -> THSDSLC | C102: =Technologies!D146 -> Heavy Truck, Short Haul, Conv. Diesel | D102: bn-vmt, bn-vmt/a | E102: =Commodities!C44 -> THDSL | F102: =Commodities!C$12 -> THS | G102: 1 | H102: 2015 | I102: =AZ102+5 -> 24 | J102: 0.18 | M102: =Trucks!H132 -> 0.033245753 | N102: =M102 -> 0.033245753 | O102: =N102 -> 0.033245753 | P102: =O102 -> 0.033245753 | Q102: =P102 -> 0.033245753 | R102: =Q102 -> 0.033245753 | S102: =R102 -> 0.033245753 | T102: =S102 -> 0.033245753 | U102: =T102 -> 0.033245753 | W102: =Trucks!F132 -> 4701.3381 | X102: =W102 -> 4701.3381 | Y102: =X102 -> 4701.3381 | Z102: =Y102 -> 4701.3381 | AA102: =Z102 -> 4701.3381 | AB102: =AA102 -> 4701.3381 | AC102: =AB102 -> 4701.3381 | AD102: =AC102 -> 4701.3381 | AE102: =AD102 -> 4701.3381 | AF102: =Trucks!G132 -> 165.78108 | AL102: 1 | AM102: 0 | AN102: 0 | AZ102: =Trucks!E132 -> 19
A103: =Technologies!B147 -> R2,R3,R4,R5,R6 | B103: =Technologies!C147 -> THSDSLIM | C103: =Technologies!D147 -> Heavy Truck, Short Haul, Improved Diesel | D103: bn-vmt, bn-vmt/a | E103: =Commodities!C44 -> THDSL | F103: =Commodities!C$12 -> THS | G103: 1 | H103: 2025 | I103: =AZ103+5 -> 24 | J103: 0.24 | O103: =Trucks!H134 -> 0.034398179 | P103: =O103 -> 0.034398179 | Q103: =P103 -> 0.034398179 | R103: =Trucks!H135 -> 0.035096619 | S103: =R103 -> 0.035096619 | T103: =S103 -> 0.035096619 | U103: =T103 -> 0.035096619 | Y103: =Trucks!F134 -> 4729.3692 | Z103: =Y103 -> 4729.3692 | AA103: =Z103 -> 4729.3692 | AB103: =Trucks!F135 -> 4767.6178 | AC103: =AB103 -> 4767.6178 | AD103: =AC103 -> 4767.6178 | AE103: =AD103 -> 4767.6178 | AF103: 166 | AL103: 1 | AM103: 0 | AN103: 0 | AZ103: 19
A104: =Technologies!B148 -> R2,R3,R4,R5,R6 | B104: =Technologies!C148 -> THSDSLADV | C104: =Technologies!D148 -> Heavy Truck, Short Haul, Advanced Diesel | D104: bn-vmt, bn-vmt/a | E104: =Commodities!C44 -> THDSL | F104: =Commodities!C$12 -> THS | G104: 1 | H104: =Trucks!D136 -> 2015 | I104: =AZ104+5 -> 24 | J104: 0.28 | M104: =Trucks!H136 -> 0.034863806 | N104: =M104 -> 0.034863806 | O104: =Trucks!H137 -> 0.035387636 | P104: =O104 -> 0.035387636 | Q104: =P104 -> 0.035387636 | R104: =Q104 -> 0.035387636 | S104: =R104 -> 0.035387636 | T104: =S104 -> 0.035387636 | U104: =T104 -> 0.035387636 | W104: =Trucks!F136 -> 4831.9482 | X104: =W104 -> 4831.9482 | Y104: =Trucks!F137 -> 5078.3127 | Z104: =Y104 -> 5078.3127 | AA104: =Z104 -> 5078.3127 | AB104: =AA104 -> 5078.3127 | AC104: =AB104 -> 5078.3127 | AD104: =AC104 -> 5078.3127 | AE104: =AD104 -> 5078.3127 | AF104: =Trucks!G136 -> 165.78108 | AL104: 1 | AM104: 0 | AN104: 0 | AZ104: =Trucks!E136 -> 19
...

Sheet TechData_Resid_EMIS
A1: TechData | B1: R1,R2,R3,R4,R5,R6
G5: ENV_ACT | H5: ENV_ACT | I5: ENV_ACT | J5: ENV_ACT | K5: ENV_ACT | L5: ENV_ACT | M5: ENV_ACT | N5: ENV_ACT | O5: ENV_ACT | P5: ENV_ACT | Q5: ENV_ACT | R5: ENV_ACT | S5: ENV_ACT | T5: ENV_ACT | U5: ENV_ACT | V5: ENV_ACT | W5: ENV_ACT | X5: ENV_ACT | Y5: ENV_ACT | Z5: ENV_ACT | AA5: ENV_ACT | AB5: ENV_ACT | AC5: ENV_ACT | AD5: ENV_ACT | AE5: ENV_ACT | AF5: ENV_ACT | AG5: ENV_ACT | AH5: ENV_ACT | AI5: ENV_ACT | AJ5: ENV_ACT | AK5: ENV_ACT | AL5: ENV_ACT | AM5: ENV_ACT | AN5: ENV_ACT | AO5: ENV_ACT | AP5: ENV_ACT | AQ5: ENV_ACT | AR5: ENV_ACT | AS5: ENV_ACT | AT5: ENV_ACT
G6: NOX | H6: NOX | I6: NOX | J6: NOX | K6: NOX | L6: SO2 | M6: SO2 | N6: SO2 | O6: SO2 | P6: =O6 -> SO2 | Q6: PM10 | R6: =Q6 -> PM10 | S6: PM25 | T6: PM25 | U6: CO | V6: CO | W6: N2O | X6: N2O | Y6: CH4 | Z6: CH4 | AA6: VOC | AB6: VOC | AC6: BC | AD6: BC | AE6: OC | AF6: OC | AG6: NOXT | AH6: NOXT | AI6: NOXT | AJ6: NOXT | AK6: NOXT | AL6: SO2T | AM6: SO2T | AN6: SO2T | AO6: SO2T | AP6: SO2T | AQ6: PM10T | AR6: PM10T | AS6: PM25T | AT6: PM25T
F8: ~FI_T
A9: Region | B9: TechName | C9: *TechDesc | D9: *Units | E9: *CommIN | F9: *CommOUT | G9: ENV_ACT~NOX~2010 | H9: ENV_ACT~NOX~2015 | I9: ENV_ACT~NOX~2020 | J9: ENV_ACT~NOX~2025 | K9: ENV_ACT~NOX~2055 | L9: ENV_ACT~SO2~2010 | M9: ENV_ACT~SO2~2015 | N9: ENV_ACT~SO2~2020 | O9: ENV_ACT~SO2~2025 | P9: ENV_ACT~SO2~2055 | Q9: ENV_ACT~PM10~2010 | R9: ENV_ACT~PM10~2055 | S9: ENV_ACT~PM25~2010 | T9: ENV_ACT~PM25~2055 | U9: ENV_ACT~CO~2010 | V9: ENV_ACT~CO~2055 | W9: ENV_ACT~N2O~2010 | X9: ENV_ACT~N2O~2055 | Y9: ENV_ACT~CH4~2010 | Z9: ENV_ACT~CH4~2055 | AA9: ENV_ACT~VOC~2010 | AB9: ENV_ACT~VOC~2055 | AC9: ENV_ACT~BC~2010 | AD9: ENV_ACT~BC~2055 | AE9: ENV_ACT~OC~2010 | AF9: ENV_ACT~OC~2055 | AG9: ENV_ACT~NOXT~2010 | AH9: ENV_ACT~NOXT~2015 | AI9: ENV_ACT~NOXT~2020 | AJ9: ENV_ACT~NOXT~2025 | AK9: ENV_ACT~NOXT~2055 | AL9: ENV_ACT~SO2T~2010 | AM9: ENV_ACT~SO2T~2015 | AN9: ENV_ACT~SO2T~2020 | AO9: ENV_ACT~SO2T~2025 | AP9: ENV_ACT~SO2T~2055 | AQ9: ENV_ACT~PM10T~2010 | AR9: ENV_ACT~PM10T~2055 | AS9: ENV_ACT~PM25T~2010 | AT9: ENV_ACT~PM25T~2055
A10: =TechData!A8 -> R2,R3,R4,R5,R6 | B10: =TechData!B8 -> TAJE | C10: =TechData!C8 -> Air Jet, Passenger Existing | D10: =TechData!D8 -> bn-pass-miles, bn-pmt/a | E10: =TechData!E8 -> TRNJTF1 | F10: =TechData!F8 -> TA | G10: ='Resid Emissions'!C26 -> 0.065 | K10: =G95 -> 0 | L10: ='Resid Emissions'!F26 -> 0.021508133 | M10: ='Resid Emissions'!G26 -> 0.01593195 | N10: =M10 -> 0.01593195 | O10: =N10 -> 0.01593195 | P10: =O10 -> 0.01593195 | Q10: ='Resid Emissions'!D26 -> 0.0081908343 | R10: =Q10 -> 0.0081908343 | S10: ='Resid Emissions'!I26 -> 0.0081908343 | T10: =S10 -> 0.0081908343 | U10: ='Resid Emissions'!J26 -> 0.1497 | V10: =U10 -> 0.1497 | W10: ='Resid Emissions'!N26 -> 0.0079197147 | X10: =W10 -> 0.0079197147 | Y10: ='Resid Emissions'!M26 -> 0.0068901518 | Z10: =Y10 -> 0.0068901518 | AA10: ='Resid Emissions'!H26 -> 0.0094153068 | AB10: =AA10 -> 0.0094153068 | AC10: ='Resid Emissions'!K26 -> 0.0054059506 | AD10: =AC10 -> 0.0054059506 | AE10: ='Resid Emissions'!L26 -> 0.0016381669 | AF10: =AE10 -> 0.0016381669 | AG10: =G10 -> 0.065 | AK10: =AG10 -> 0.065 | AL10: =L10 -> 0.021508133 | AM10: =M10 -> 0.01593195 | AN10: =N10 -> 0.01593195 | AO10: =O10 -> 0.01593195 | AP10: =AO10 -> 0.01593195 | AQ10: =Q10 -> 0.0081908343 | AR10: =AQ10 -> 0.0081908343 | AS10: =S10 -> 0.0081908343 | AT10: =AS10 -> 0.0081908343
A11: =TechData!A9 -> * | B11: =TechData!B9 -> TAPE | C11: =TechData!C9 -> Airplane, General Aviation, exisiting | D11: =TechData!D9 -> bn-pass-miles, bn-pmt/a | E11: =TechData!E9 -> TRGSLB | F11: =TechData!F9 -> TA | G11: ='Resid Emissions'!C27 -> 0.18 | K11: =G96 -> 0 | L11: ='Resid Emissions'!F27 -> 0.0010849609 | M11: ='Resid Emissions'!G27 -> 0.0010849609 | N11: =M11 -> 0.0010849609 | O11: =N11 -> 0.0010849609 | P11: =O11 -> 0.0010849609 | Q11: ='Resid Emissions'!D27 -> 0.04 | R11: =Q11 -> 0.04 | S11: ='Resid Emissions'!I27 -> 0.03868 | T11: =S11 -> 0.03868 | U11: ='Resid Emissions'!J27 -> 0.1497 | V11: =U11 -> 0.1497 | W11: ='Resid Emissions'!N27 -> 0.0079197147 | X11: =W11 -> 0.0079197147 | Y11: ='Resid Emissions'!M27 -> 0.0068901518 | Z11: =Y11 -> 0.0068901518 | AA11: ='Resid Emissions'!H27 -> 0.0094153068 | AB11: =AA11 -> 0.0094153068 | AC11: ='Resid Emissions'!K27 -> 0.0264 | AD11: =AC11 -> 0.0264 | AE11: ='Resid Emissions'!L27 -> 0.007736 | AF11: =AE11 -> 0.007736 | AG11: =G11 -> 0.18 | AK11: =AG11 -> 0.18 | AL11: =L11 -> 0.0010849609 | AM11: =M11 -> 0.0010849609 | AN11: =N11 -> 0.0010849609 | AO11: =O11 -> 0.0010849609 | AP11: =AO11 -> 0.0010849609 | AQ11: =Q11 -> 0.04 | AR11: =AQ11 -> 0.04 | AS11: =S11 -> 0.03868 | AT11: =AS11 -> 0.03868
A12: =NewTech!A156 -> * | B12: =NewTech!B156 -> TSDSHE | C12: =NewTech!C156 -> Water Shipping, Residual Oil exisiting | D12: =NewTech!D156 -> bn-t-m, bn-ton-m/a | E12: =NewTech!E156 -> TRNRFH1 | F12: =NewTech!F156 -> TS | G12: ='Resid Emissions'!C28 -> 2.3297866 | K12: =G97 -> 0 | L12: ='Resid Emissions'!F28 -> 1.7572334 | M12: ='Resid Emissions'!G28 -> 0.064412243 | N12: =M12 -> 0.064412243 | O12: =N12 -> 0.064412243 | P12: =O12 -> 0.064412243 | Q12: ='Resid Emissions'!D28 -> 0.22733733 | R12: =Q12 -> 0.22733733 | S12: ='Resid Emissions'!I28 -> 0.20915034 | T12: =S12 -> 0.20915034 | U12: ='Resid Emissions'!J28 -> 0.1953417 | V12: =U12 -> 0.1953417 | W12: ='Resid Emissions'!N28 -> 0.00073410763 | X12: =W12 -> 0.00073410763 | Y12: ='Resid Emissions'!M28 -> 0.002111783 | Z12: =Y12 -> 0.002111783 | AA12: ='Resid Emissions'!H28 -> 0.07746309 | AB12: =AA12 -> 0.07746309 | AC12: ='Resid Emissions'!K28 -> 0.10666667 | AD12: =AC12 -> 0.10666667 | AE12: ='Resid Emissions'!L28 -> 0.043921572 | AF12: =AE12 -> 0.043921572 | AG12: =G12 -> 2.3297866 | AK12: =AG12 -> 2.3297866 | AL12: =L12 -> 1.7572334 | AM12: =M12 -> 0.064412243 | AN12: =N12 -> 0.064412243 | AO12: =O12 -> 0.064412243 | AP12: =AO12 -> 0.064412243 | AQ12: =Q12 -> 0.22733733 | AR12: =AQ12 -> 0.22733733 | AS12: =S12 -> 0.20915034 | AT12: =AS12 -> 0.20915034
A13: =TechData!A33 -> R2,R3,R4,R5,R6 | B13: =TechData!B33 -> TSDSLE | C13: =TechData!C33 -> Water Shipping, Diesel exisiting | D13: =TechData!D33 -> bn-t-m, bn-ton-m/a | E13: =TechData!E33 -> TSDSL | F13: =TechData!F33 -> TS | G13: ='Resid Emissions'!C29 -> 2.0867908 | K13: =G98 -> 0 | L13: ='Resid Emissions'!F29 -> 0.16169228 | M13: ='Resid Emissions'!G29 -> 0.07176465 | N13: =M13 -> 0.07176465 | O13: =N13 -> 0.07176465 | P13: =O13 -> 0.07176465 | Q13: ='Resid Emissions'!D29 -> 0.087175451 | R13: =Q13 -> 0.087175451 | S13: ='Resid Emissions'!I29 -> 0.080201415 | T13: =S13 -> 0.080201415 | U13: ='Resid Emissions'!J29 -> 0.36348373 | V13: =U13 -> 0.36348373 | W13: ='Resid Emissions'!N29 -> 0.00086497293 | X13: =W13 -> 0.00086497293 | Y13: ='Resid Emissions'!M29 -> 0.0027030404 | Z13: =Y13 -> 0.0027030404 | AA13: ='Resid Emissions'!H29 -> 0.060909108 | AB13: =AA13 -> 0.060909108 | AC13: ='Resid Emissions'!K29 -> 0.040902722 | AD13: =AC13 -> 0.040902722 | AE13: ='Resid Emissions'!L29 -> 0.016842297 | AF13: =AE13 -> 0.016842297 | AG13: =G13 -> 2.0867908 | AK13: =AG13 -> 2.0867908 | AL13: =L13 -> 0.16169228 | AM13: =M13 -> 0.07176465 | AN13: =N13 -> 0.07176465 | AO13: =O13 -> 0.07176465 | AP13: =AO13 -> 0.07176465 | AQ13: =Q13 -> 0.087175451 | AR13: =AQ13 -> 0.087175451 | AS13: =S13 -> 0.080201415 | AT13: =AS13 -> 0.080201415
A14: =TechData!A32 -> * | B14: =TechData!B32 -> TRFDSLE2 | C14: =TechData!C32 -> Rail Freight, Diesel Existing-MSW | D14: =TechData!D32 -> bn-vmt, bn-vmt/a | E14: =TechData!E32 -> TWDSL | F14: =TechData!F32 -> TSW | G14: ='Resid Emissions'!P30 -> 0.10057184 | H14: ='Resid Emissions'!Q30 -> 0.12659723 | I14: =H14 -> 0.12659723 | J14: =I14 -> 0.12659723 | K14: =J14 -> 0.12659723 | Q14: ='Resid Emissions'!R30 -> 0.0029043819 | R14: =Q14 -> 0.0029043819 | S14: ='Resid Emissions'!U30 -> 0.0028172504 | T14: =S14 -> 0.0028172504 | AA14: ='Resid Emissions'!X30 -> 0.0053235787 | AB14: =AA14 -> 0.0053235787 | AC14: ='Resid Emissions'!AA30 -> 0.0018593853 | AD14: =AC14 -> 0.0018593853 | AE14: ='Resid Emissions'!AD30 -> 0.00059162259 | AF14: =AE14 -> 0.00059162259 | AG14: =G14 -> 0.10057184 | AH14: =H14 -> 0.12659723 | AI14: =I14 -> 0.12659723 | AJ14: =J14 -> 0.12659723 | AK14: =AJ14 -> 0.12659723 | AQ14: =Q14 -> 0.0029043819 | AR14: =AQ14 -> 0.0029043819 | AS14: =S14 -> 0.0028172504 | AT14: =AS14 -> 0.0028172504

Sheet zzTechData_ALM_EMIS
A1: TechData | B1: R1,R2,R3,R4,R5,R6
F4: ~FI_T
A5: Region | B5: TechName | C5: *TechDesc | D5: *Units | E5: *CommIN | F5: *CommOUT | G5: ENV_ACT~NOX | H5: ENV_ACT~NOX~ | I5: ENV_ACT~NOX~ | J5: ENV_ACT~NOX~ | K5: ENV_ACT~NOX~ | L5: ENV_ACT~SO2~ | M5: ENV_ACT~SO2~ | N5: ENV_ACT~SO2~ | O5: ENV_ACT~PM10 | P5: ENV_ACT~PM10~ | Q5: ENV_ACT~PM10~ | R5: ENV_ACT~PM10~ | S5: ENV_ACT~PM10~ | T5: ENV_ACT~PM25 | U5: ENV_ACT~PM25~ | V5: ENV_ACT~PM25~ | W5: ENV_ACT~PM25~ | X5: ENV_ACT~PM25~ | Y5: ENV_ACT~CO | Z5: ENV_ACT~N2O | AA5: ENV_ACT~CH4 | AB5: ENV_ACT~VOC | AC5: ENV_ACT~VOC~ | AD5: ENV_ACT~VOC~ | AE5: ENV_ACT~VOC~ | AF5: ENV_ACT~VOC~ | AG5: ENV_ACT~BC | AH5: ENV_ACT~BC~ | AI5: ENV_ACT~BC~ | AJ5: ENV_ACT~BC~ | AK5: ENV_ACT~BC~ | AL5: ENV_ACT~OC | AM5: ENV_ACT~OC~ | AN5: ENV_ACT~OC~ | AO5: ENV_ACT~OC~ | AP5: ENV_ACT~OC~ | AQ5: ENV_ACT~NOXT | AR5: ENV_ACT~NOXT~ | AS5: ENV_ACT~NOXT~ | AT5: ENV_ACT~NOXT~ | AU5: ENV_ACT~NOXT~ | AV5: ENV_ACT~SO2T~ | AW5: ENV_ACT~SO2T~ | AX5: ENV_ACT~SO2T~ | AY5: ENV_ACT~PM10T | AZ5: ENV_ACT~PM10T~ | BA5: ENV_ACT~PM10T~ | BB5: ENV_ACT~PM10T~ | BC5: ENV_ACT~PM10T~ | BD5: ENV_ACT~PM25T | BE5: ENV_ACT~PM25T~ | BF5: ENV_ACT~PM25T~ | BG5: ENV_ACT~PM25T~ | BH5: ENV_ACT~PM25T~
A6: =TechData!A28 -> R2,R3,R4,R5,R6 | B6: =TechData!B28 -> TPDSLCR | C6: =TechData!C28 -> Commuter Rail, Diesel | D6: =TechData!D28 -> bn-pass-miles, bn-pmt/a | E6: =TechData!E28 -> TRNDSL | F6: =TechData!F28 -> TRP | H6: ='New Emissions'!CB124 -> 0.2211077 | I6: ='New Emissions'!CC124 -> 0.37289027 | J6: =I6 -> 0.37289027 | P6: ='New Emissions'!CD124 -> 0.0020364557 | Q6: ='New Emissions'!CE124 -> 0.0061854963 | R6: =Q6 -> 0.0061854963 | U6: ='New Emissions'!CF124 -> 0.001975362 | V6: ='New Emissions'!CG124 -> 0.0059999314 | W6: =V6 -> 0.0059999314 | AC6: ='New Emissions'!CH124 -> 0.0059020769 | AD6: ='New Emissions'!CI124 -> 0.0096497454 | AE6: =AD6 -> 0.0096497454 | AH6: ='New Emissions'!CJ124 -> 0.0013037389 | AI6: ='New Emissions'!CK124 -> 0.0039599547 | AJ6: =AI6 -> 0.0039599547 | AM6: ='New Emissions'!CL124 -> 0.00041482603 | AN6: ='New Emissions'!CM124 -> 0.0012599856 | AO6: =AN6 -> 0.0012599856 | AR6: =H6 -> 0.2211077 | AS6: =I6 -> 0.37289027 | AT6: =J6 -> 0.37289027 | AZ6: =P6 -> 0.0020364557 | BA6: =Q6 -> 0.0061854963 | BB6: =R6 -> 0.0061854963 | BE6: =U6 -> 0.001975362 | BF6: =V6 -> 0.0059999314 | BG6: =W6 -> 0.0059999314
A7: =TechData!A29 -> R2,R3,R4,R5,R6 | B7: =TechData!B29 -> TPELCSUB | C7: =TechData!C29 -> Subways and Streetcars, Electricity | D7: =TechData!D29 -> bn-pass-miles, bn-pmt/a | E7: =TechData!E29 -> TRNELC | F7: =TechData!F29 -> TRP
A8: =TechData!A33 -> R2,R3,R4,R5,R6 | B8: =TechData!B33 -> TSDSLE | C8: =TechData!C33 -> Water Shipping, Diesel exisiting | D8: =TechData!D33 -> bn-t-m, bn-ton-m/a | E8: =TechData!E33 -> TSDSL | F8: =TechData!F33 -> TS | G8: ='New Emissions'!C115 -> 2.0867908 | L8: ='New Emissions'!AI115 -> 0.0071396694 | M8: ='New Emissions'!AJ115 -> 0.0071396694 | O8: ='New Emissions'!AG115 -> 0.016842297 | T8: ='New Emissions'!AL115 -> 0.0071396694 | Y8: ='New Emissions'!AM115 -> 0.0071396694 | AA8: ='New Emissions'!AP115 -> 0.0071396694 | AB8: ='New Emissions'!AK115 -> 0.0071396694 | AG8: ='New Emissions'!AN115 -> 0.0071396694 | AL8: ='New Emissions'!AO115 -> 0.0071396694 | AQ8: =G8 -> 2.0867908 | AV8: =L8 -> 0.0071396694 | AW8: =M8 -> 0.0071396694 | AY8: =O8 -> 0.016842297 | BD8: =T8 -> 0.0071396694
A9: =Technologies!B215 -> R2,R3,R4,R5,R6 | B9: =Technologies!C215 -> SETRDSL | C9: =Technologies!D215 -> Emissions: DSL Rail fuel to TRDSL | D9: PJ,PJ/a | E9: =TechData!E42 -> TRNDSL | F9: =TechData!F42 -> TRDSL | H9: ='New Emissions'!CB129 -> 0.82878048 | I9: ='New Emissions'!CC129 -> 0.16204526 | J9: =I9 -> 0.16204526 | L9: ='New Emissions'!AI129 -> 0 | M9: ='New Emissions'!AJ129 -> 0 | P9: ='New Emissions'!CD129 -> 0.029281579 | Q9: ='New Emissions'!CE129 -> 0.0024306789 | R9: =Q9 -> 0.0024306789 | U9: ='New Emissions'!CF129 -> 0.028403131 | V9: ='New Emissions'!CG129 -> 0.0023577585 | W9: =V9 -> 0.0023577585 | Y9: ='New Emissions'!AM129 -> 0 | Z9: 0 | AA9: ='New Emissions'!AP129 -> 0 | AC9: ='New Emissions'!CH129 -> 0.044364751 | AD9: ='New Emissions'!CI129 -> 0.0073031206 | AE9: =AD9 -> 0.0073031206 | AH9: ='New Emissions'!CJ129 -> 0.018746067 | AI9: ='New Emissions'!CK129 -> 0.0015561206 | AJ9: =AI9 -> 0.0015561206 | AM9: ='New Emissions'!CL129 -> 0.0059646576 | AN9: ='New Emissions'!CM129 -> 0.00049512929 | AO9: =AN9 -> 0.00049512929 | AR9: =H9 -> 0.82878048 | AS9: =I9 -> 0.16204526 | AT9: =J9 -> 0.16204526 | AV9: =L9 -> 0 | AW9: =M9 -> 0 | AZ9: =P9 -> 0.029281579 | BA9: =Q9 -> 0.0024306789 | BB9: =R9 -> 0.0024306789 | BE9: =U9 -> 0.028403131 | BF9: =V9 -> 0.0023577585 | BG9: =W9 -> 0.0023577585
A10: * | B10: =Technologies!C216 -> SETRB20 | C10: =Technologies!D216 -> Emissions: B20 Rail fuel to TRB20X | D10: PJ,PJ/a | E10: =TechData!E41 -> TRB20 | F10: =TechData!F41 -> TRB20X | H10: ='New Emissions'!CB128 -> 0.80731567 | I10: ='New Emissions'!CC128 -> 0.1578484 | J10: =I10 -> 0.1578484 | L10: ='New Emissions'!AI128 -> 0 | M10: ='New Emissions'!AJ128 -> 0 | P10: ='New Emissions'!CD128 -> 0.028523207 | Q10: ='New Emissions'!CE128 -> 0.0023677261 | R10: =Q10 -> 0.0023677261 | U10: ='New Emissions'!CF128 -> 0.027667511 | V10: ='New Emissions'!CG128 -> 0.0022966943 | W10: =V10 -> 0.0022966943 | Y10: ='New Emissions'!AM128 -> 0 | Z10: ='New Emissions'!CL128 -> 0.0058101772 | AC10: ='New Emissions'!CH128 -> 0.043215736 | AD10: ='New Emissions'!CI128 -> 0.007113975 | AE10: =AD10 -> 0.007113975 | AH10: ='New Emissions'!CJ128 -> 0.018260557 | AI10: ='New Emissions'!CK128 -> 0.0015158182 | AJ10: =AI10 -> 0.0015158182 | AM10: ='New Emissions'!CL128 -> 0.0058101772 | AN10: ='New Emissions'!CM128 -> 0.0004823058 | AO10: =AN10 -> 0.0004823058 | AR10: =H10 -> 0.80731567 | AS10: =I10 -> 0.1578484 | AT10: =J10 -> 0.1578484 | AV10: =L10 -> 0 | AW10: =M10 -> 0 | AZ10: =P10 -> 0.028523207 | BA10: =Q10 -> 0.0023677261 | BB10: =R10 -> 0.0023677261 | BE10: =U10 -> 0.027667511 | BF10: =V10 -> 0.0022966943 | BG10: =W10 -> 0.0022966943
A15: =NewTech!A142 -> R2,R3,R4,R5,R6 | B15: =NewTech!B142 -> TPELCCR | C15: =NewTech!C142 -> Commuter Rail, Electricity | D15: =NewTech!D142 -> bn-pass-miles, bn-pmt/a | E15: =NewTech!E142 -> TRNELC | F15: =NewTech!F142 -> TRP
A16: =NewTech!A143 -> * | B16: =NewTech!B143 -> TPDSLIR | C16: =NewTech!C143 -> Intercity Rail, Diesel | D16: =NewTech!D143 -> bn-pass-miles, bn-pmt/a | E16: =NewTech!E143 -> TRNDSL | F16: =NewTech!F143 -> 0 | H16: ='New Emissions'!CB125 -> 2.2047532 | I16: ='New Emissions'!CC125 -> 3.7182378 | J16: =I16 -> 3.7182378 | P16: ='New Emissions'!CD125 -> 0.020306313 | Q16: ='New Emissions'!CE125 -> 0.061678055 | R16: =Q16 -> 0.061678055 | U16: ='New Emissions'!CF125 -> 0.019697124 | V16: ='New Emissions'!CG125 -> 0.059827713 | W16: =V16 -> 0.059827713 | AC16: ='New Emissions'!CH125 -> 0.058851967 | AD16: ='New Emissions'!CI125 -> 0.096221466 | AE16: =AD16 -> 0.096221466 | AH16: ='New Emissions'!CJ125 -> 0.013000102 | AI16: ='New Emissions'!CK125 -> 0.039486291 | AJ16: =AI16 -> 0.039486291 | AL16: ='New Emissions'!CL119 -> 0.00026036201 | AR16: =H16 -> 2.2047532 | AS16: =I16 -> 3.7182378 | AT16: =J16 -> 3.7182378 | AZ16: =P16 -> 0.020306313 | BA16: =Q16 -> 0.061678055 | BB16: =R16 -> 0.061678055 | BE16: =U16 -> 0.019697124 | BF16: =V16 -> 0.059827713 | BG16: =W16 -> 0.059827713
A17: =NewTech!A147 -> * | B17: =NewTech!B147 -> TRFDSL | C17: =NewTech!C147 -> Rail Freight, Diesel | D17: =NewTech!D147 -> bn-t-m, bn-ton-m/a | E17: =NewTech!E147 -> TRNDSL | F17: =NewTech!F147 -> TRF | H17: ='New Emissions'!CB119 -> 0.077053626 | I17: ='New Emissions'!CC119 -> 0.077053626 | J17: =I17 -> 0.077053626 | P17: ='New Emissions'!CD119 -> 0.001278164 | Q17: ='New Emissions'!CE119 -> 0.001278164 | R17: =Q17 -> 0.001278164 | U17: ='New Emissions'!CF119 -> 0.0012398191 | V17: ='New Emissions'!CG119 -> 0.0012398191 | W17: =V17 -> 0.0012398191 | AC17: ='New Emissions'!CH119 -> 0.0019940125 | AD17: ='New Emissions'!CI119 -> 0.0019940125 | AE17: =AD17 -> 0.0019940125 | AH17: ='New Emissions'!CJ119 -> 0.0008182806 | AI17: ='New Emissions'!CK119 -> 0.0008182806 | AJ17: =AI17 -> 0.0008182806 | AM17: ='New Emissions'!CL119 -> 0.00026036201 | AN17: ='New Emissions'!CM119 -> 0.00026036201 | AO17: =AN17 -> 0.00026036201 | AS17: =I17 -> 0.077053626 | AT17: =J17 -> 0.077053626 | BA17: =Q17 -> 0.001278164 | BB17: =R17 -> 0.001278164 | BF17: =V17 -> 0.0012398191 | BG17: =W17 -> 0.0012398191
A18: =NewTech!A148 -> * | B18: =NewTech!B148 -> TRFDSL2 | C18: =NewTech!C148 -> Rail Freight, Diesel-MSW | D18: =NewTech!D148 -> bn-vmt, bn-vmt/a | E18: =NewTech!E148 -> TWDSL | F18: =NewTech!F148 -> TSW | H18: =H17 -> 0.077053626 | I18: =I17 -> 0.077053626 | J18: =J17 -> 0.077053626 | P18: =P17 -> 0.001278164 | Q18: =Q17 -> 0.001278164 | R18: =R17 -> 0.001278164 | U18: =U17 -> 0.0012398191 | V18: =V17 -> 0.0012398191 | W18: =W17 -> 0.0012398191 | AC18: =AC17 -> 0.0019940125 | AD18: =AD17 -> 0.0019940125 | AE18: =AE17 -> 0.0019940125 | AH18: =AH17 -> 0.0008182806 | AI18: =AI17 -> 0.0008182806 | AJ18: =AJ17 -> 0.0008182806 | AM18: =AM17 -> 0.00026036201 | AN18: =AN17 -> 0.00026036201 | AO18: =AO17 -> 0.00026036201 | AS18: =AS17 -> 0.077053626 | AT18: =AT17 -> 0.077053626 | BA18: =BA17 -> 0.001278164 | BB18: =BB17 -> 0.001278164 | BF18: =BF17 -> 0.0012398191 | BG18: =BG17 -> 0.0012398191
A19: =NewTech!A149 -> * | B19: =NewTech!B149 -> TRF10DSL | C19: =NewTech!C149 -> Rail Freight Diesel, 10% improvement | D19: =NewTech!D149 -> bn-t-m, bn-ton-m/a | E19: =NewTech!E149 -> TRNDSL | F19: =NewTech!F149 -> TRF | H19: ='New Emissions'!CB120 -> 0.069278404 | I19: ='New Emissions'!CC120 -> 0.069278404 | J19: =I19 -> 0.069278404 | P19: ='New Emissions'!CD120 -> 0.0011491888 | Q19: ='New Emissions'!CE120 -> 0.0011491888 | R19: =Q19 -> 0.0011491888 | U19: ='New Emissions'!CF120 -> 0.0011147131 | V19: ='New Emissions'!CG120 -> 0.0011147131 | W19: =V19 -> 0.0011147131 | AC19: ='New Emissions'!CH120 -> 0.0017928035 | AD19: ='New Emissions'!CI120 -> 0.0017928035 | AE19: =AD19 -> 0.0017928035 | AH19: ='New Emissions'!CJ120 -> 0.00073571066 | AI19: ='New Emissions'!CK120 -> 0.00073571066 | AJ19: =AI19 -> 0.00073571066 | AM19: ='New Emissions'!CL120 -> 0.00023408976 | AN19: ='New Emissions'!CM120 -> 0.00023408976 | AO19: =AN19 -> 0.00023408976 | AS19: =I19 -> 0.069278404 | AT19: =J19 -> 0.069278404 | BA19: =Q19 -> 0.0011491888 | BB19: =R19 -> 0.0011491888 | BF19: =V19 -> 0.0011147131 | BG19: =W19 -> 0.0011147131
A20: =NewTech!A150 -> * | B20: =NewTech!B150 -> TRF10DSL2 | C20: =NewTech!C150 -> Rail Freight Diesel, 10% improvement-MSW | D20: =NewTech!D150 -> bn-vmt, bn-vmt/a | E20: =NewTech!E150 -> TWDSL | F20: =NewTech!F150 -> TSW | H20: =H19 -> 0.069278404 | I20: =I19 -> 0.069278404 | J20: =J19 -> 0.069278404 | P20: =P19 -> 0.0011491888 | Q20: =Q19 -> 0.0011491888 | R20: =R19 -> 0.0011491888 | U20: =U19 -> 0.0011147131 | V20: =V19 -> 0.0011147131 | W20: =W19 -> 0.0011147131 | AC20: =AC19 -> 0.0017928035 | AD20: =AD19 -> 0.0017928035 | AE20: =AE19 -> 0.0017928035 | AM20: =AM19 -> 0.00023408976 | AN20: =AN19 -> 0.00023408976 | AO20: =AO19 -> 0.00023408976 | AS20: =AS19 -> 0.069278404 | AT20: =AT19 -> 0.069278404 | BA20: =BA19 -> 0.0011491888 | BB20: =BB19 -> 0.0011491888 | BF20: =BF19 -> 0.0011147131 | BG20: =BG19 -> 0.0011147131
A21: =NewTech!A151 -> * | B21: =NewTech!B151 -> TRF25DSL | C21: =NewTech!C151 -> Rail Freight Dieseil, 25% improvement | D21: =NewTech!D151 -> bn-t-m, bn-ton-m/a | E21: =NewTech!E151 -> TRNDSL | F21: =NewTech!F151 -> TRF | H21: ='New Emissions'!CB121 -> 0.057732003 | I21: ='New Emissions'!CC121 -> 0.057732003 | J21: =I21 -> 0.057732003 | P21: ='New Emissions'!CD121 -> 0.00095765732 | Q21: ='New Emissions'!CE121 -> 0.00095765732 | R21: =Q21 -> 0.00095765732 | U21: ='New Emissions'!CF121 -> 0.0009289276 | V21: ='New Emissions'!CG121 -> 0.0009289276 | W21: =V21 -> 0.0009289276 | AC21: ='New Emissions'!CH121 -> 0.0014940029 | AD21: ='New Emissions'!CI121 -> 0.0014940029 | AE21: =AD21 -> 0.0014940029 | AH21: ='New Emissions'!CJ121 -> 0.00061309222 | AI21: ='New Emissions'!CK121 -> 0.00061309222 | AJ21: =AI21 -> 0.00061309222 | AM21: ='New Emissions'!CL121 -> 0.0001950748 | AN21: ='New Emissions'!CM121 -> 0.0001950748 | AO21: =AN21 -> 0.0001950748 | AS21: =I21 -> 0.057732003 | AT21: =J21 -> 0.057732003 | BA21: =Q21 -> 0.00095765732 | BB21: =R21 -> 0.00095765732 | BF21: =V21 -> 0.0009289276 | BG21: =W21 -> 0.0009289276
A22: =NewTech!A153 -> * | B22: =NewTech!B153 -> TRFAPU | C22: =NewTech!C153 -> Rail Freight Diesel with APU | D22: =NewTech!D153 -> bn-t-m, bn-ton-m/a | E22: =NewTech!E153 -> TRNDSL | F22: =NewTech!F153 -> TRF | H22: ='New Emissions'!CB122 -> 0.066753591 | I22: ='New Emissions'!CC122 -> 0.066753591 | J22: =I22 -> 0.066753591 | P22: ='New Emissions'!CD122 -> 0.0011073072 | Q22: ='New Emissions'!CE122 -> 0.0011073072 | R22: =Q22 -> 0.0011073072 | U22: ='New Emissions'!CF122 -> 0.001074088 | V22: ='New Emissions'!CG122 -> 0.001074088 | W22: =V22 -> 0.001074088 | AC22: ='New Emissions'!CH122 -> 0.0017274657 | AD22: ='New Emissions'!CI122 -> 0.0017274657 | AE22: =AD22 -> 0.0017274657 | AH22: ='New Emissions'!CJ122 -> 0.00070889809 | AI22: ='New Emissions'!CK122 -> 0.00070889809 | AJ22: =AI22 -> 0.00070889809 | AM22: ='New Emissions'!CL122 -> 0.00022555848 | AN22: ='New Emissions'!CM122 -> 0.00022555848 | AO22: =AN22 -> 0.00022555848 | AS22: =I22 -> 0.066753591 | AT22: =J22 -> 0.066753591 | BA22: =Q22 -> 0.0011073072 | BB22: =R22 -> 0.0011073072 | BF22: =V22 -> 0.001074088 | BG22: =W22 -> 0.001074088
A23: =NewTech!A154 -> * | B23: =NewTech!B154 -> TRFB20 | C23: =NewTech!C154 -> Rail Freight, Biodiesel | D23: =NewTech!D154 -> bn-t-m, bn-ton-m/a | E23: =NewTech!E154 -> TRB20X | F23: =NewTech!F154 -> TRF | H23: ='New Emissions'!CB123 -> 0.089886907 | I23: ='New Emissions'!CC123 -> 0.089886907 | J23: =I23 -> 0.089886907 | P23: ='New Emissions'!CD123 -> 0.0014910422 | Q23: ='New Emissions'!CE123 -> 0.0014910422 | R23: =Q23 -> 0.0014910422 | U23: ='New Emissions'!CF123 -> 0.001446311 | V23: ='New Emissions'!CG123 -> 0.001446311 | W23: =V23 -> 0.001446311 | AC23: ='New Emissions'!CH123 -> 0.0023261153 | AD23: ='New Emissions'!CI123 -> 0.0023261153 | AE23: =AD23 -> 0.0023261153 | AH23: ='New Emissions'!CJ123 -> 0.00095456523 | AI23: ='New Emissions'!CK123 -> 0.00095456523 | AJ23: =AI23 -> 0.00095456523 | AM23: ='New Emissions'!CL123 -> 0.0003037253 | AN23: ='New Emissions'!CM123 -> 0.0003037253 | AO23: =AN23 -> 0.0003037253 | AS23: =I23 -> 0.089886907 | AT23: =J23 -> 0.089886907 | BA23: =Q23 -> 0.0014910422 | BB23: =R23 -> 0.0014910422 | BF23: =V23 -> 0.001446311 | BG23: =W23 -> 0.001446311
A24: =NewTech!A157 -> * | B24: =NewTech!B157 -> TSDSH10 | C24: =NewTech!C157 -> Water Shipping, Residual Oil, 2010 | D24: =NewTech!D157 -> bn-t-m, bn-ton-m/a | E24: =NewTech!E157 -> TRNRFH1 | F24: =NewTech!F157 -> TS | G24: ='New Emissions'!C112 -> 2.0502459 | L24: ='New Emissions'!AI112 -> 0.043921572 | M24: ='New Emissions'!AJ112 -> 0.043921572 | O24: ='New Emissions'!AG112 -> 0.1953417 | T24: ='New Emissions'!AL112 -> 0.043921572 | Y24: ='New Emissions'!AM112 -> 0.043921572 | AA24: ='New Emissions'!AP112 -> 0.043921572 | AB24: ='New Emissions'!AK112 -> 0.043921572 | AG24: ='New Emissions'!AN112 -> 0.043921572 | AL24: ='New Emissions'!AO112 -> 0.043921572 | AQ24: =G24 -> 2.0502459 | AV24: =L24 -> 0.043921572 | AW24: =M24 -> 0.043921572 | AY24: =O24 -> 0.1953417 | BD24: =T24 -> 0.043921572
A25: =NewTech!A158 -> * | B25: =NewTech!B158 -> TSDSHFI15 | C25: =NewTech!C158 -> Water Shipping, Resid Fuel Inject, 2015 | D25: =NewTech!D158 -> bn-t-m, bn-ton-m/a | E25: =NewTech!E158 -> TRNRFH1 | F25: =NewTech!F158 -> TS | G25: ='New Emissions'!C113 -> 0.44204481 | M25: ='New Emissions'!AJ113 -> 0.043921572 | O25: ='New Emissions'!AG113 -> 0.1953417 | T25: ='New Emissions'!AL113 -> 0.043921572 | Y25: ='New Emissions'!AM113 -> 0.043921572 | AA25: ='New Emissions'!AP113 -> 0.043921572 | AB25: ='New Emissions'!AK113 -> 0.043921572 | AG25: ='New Emissions'!AN113 -> 0.043921572 | AL25: ='New Emissions'!AO113 -> 0.043921572 | AQ25: =G25 -> 0.44204481 | AW25: =M25 -> 0.043921572 | AY25: =O25 -> 0.1953417 | BD25: =T25 -> 0.043921572
A26: =NewTech!A159 -> * | B26: =NewTech!B159 -> TSDSHBL15 | C26: =NewTech!C159 -> Water Shipping, Resid Bubble Lub, 2015 | D26: =NewTech!D159 -> bn-t-m, bn-ton-m/a | E26: =NewTech!E159 -> TRNRFH1 | F26: =NewTech!F159 -> TS | G26: ='New Emissions'!C114 -> 0.44204481 | M26: ='New Emissions'!AJ114 -> 0.043921572 | O26: ='New Emissions'!AG114 -> 0.1953417 | T26: ='New Emissions'!AL114 -> 0.043921572 | Y26: ='New Emissions'!AM114 -> 0.043921572 | AA26: ='New Emissions'!AP114 -> 0.043921572 | AB26: ='New Emissions'!AK114 -> 0.043921572 | AG26: ='New Emissions'!AN114 -> 0.043921572 | AL26: ='New Emissions'!AO114 -> 0.043921572 | AQ26: =G26 -> 0.44204481 | AW26: =M26 -> 0.043921572 | AY26: =O26 -> 0.1953417 | BD26: =T26 -> 0.043921572
A27: =NewTech!A160 -> R2,R3,R4,R5,R6 | B27: =NewTech!B160 -> TSDSL10 | C27: =NewTech!C160 -> Water Shipping, Diesel,2010 | D27: =NewTech!D160 -> bn-t-m, bn-ton-m/a | E27: =NewTech!E160 -> TSDSL | F27: =NewTech!F160 -> TS | G27: ='New Emissions'!C116 -> 1.2797735 | L27: ='New Emissions'!AI116 -> 0.0071396694 | M27: ='New Emissions'!AJ116 -> 0.0071396694 | O27: ='New Emissions'!AG116 -> 0.25015564 | T27: ='New Emissions'!AL116 -> 0.0071396694 | Y27: ='New Emissions'!AM116 -> 0.0071396694 | AA27: ='New Emissions'!AP116 -> 0.0071396694 | AB27: ='New Emissions'!AK116 -> 0.0071396694 | AG27: ='New Emissions'!AN116 -> 0.0071396694 | AL27: ='New Emissions'!AO116 -> 0.0071396694 | AQ27: =G27 -> 1.2797735 | AV27: =L27 -> 0.0071396694 | AW27: =M27 -> 0.0071396694 | AY27: =O27 -> 0.25015564 | BD27: =T27 -> 0.0071396694
A28: =NewTech!A161 -> R2,R3,R4,R5,R6 | B28: =NewTech!B161 -> TSDSLFI15 | C28: =NewTech!C161 -> Water Shipping, Diesel Fuel Inj, 2015 | D28: =NewTech!D161 -> bn-t-m, bn-ton-m/a | E28: =NewTech!E161 -> TSDSL | F28: =NewTech!F161 -> TS | G28: ='New Emissions'!C117 -> 0.27100195 | M28: ='New Emissions'!AJ117 -> 0.0071396694 | O28: ='New Emissions'!AG117 -> 0.25015564 | T28: ='New Emissions'!AL117 -> 0.0071396694 | Y28: ='New Emissions'!AM117 -> 0.0071396694 | AA28: ='New Emissions'!AP117 -> 0.0071396694 | AB28: ='New Emissions'!AK117 -> 0.0071396694 | AG28: ='New Emissions'!AN117 -> 0.0071396694 | AL28: ='New Emissions'!AO117 -> 0.0071396694 | AQ28: =G28 -> 0.27100195 | AW28: =M28 -> 0.0071396694 | AY28: =O28 -> 0.25015564 | BD28: =T28 -> 0.0071396694
A29: =NewTech!A162 -> R2,R3,R4,R5,R6 | B29: =NewTech!B162 -> TSDSLHE15 | C29: =NewTech!C162 -> Water Shipping, Diesel, Hybrid Electric, 2015 | D29: =NewTech!D162 -> bn-t-m, bn-ton-m/a | E29: =NewTech!E162 -> TSDSL | F29: =NewTech!F162 -> TS | G29: ='New Emissions'!C118 -> 0.27100195 | M29: ='New Emissions'!AJ118 -> 0.0071396694 | O29: ='New Emissions'!AG118 -> 0.25015564 | T29: ='New Emissions'!AL118 -> 0.0071396694 | Y29: ='New Emissions'!AM118 -> 0.0071396694 | AA29: ='New Emissions'!AP118 -> 0.0071396694 | AB29: ='New Emissions'!AK118 -> 0.0071396694 | AG29: ='New Emissions'!AN118 -> 0.0071396694 | AL29: ='New Emissions'!AO118 -> 0.0071396694 | AQ29: =G29 -> 0.27100195 | AW29: =M29 -> 0.0071396694 | AY29: =O29 -> 0.25015564 | BD29: =T29 -> 0.0071396694
A30: *
A31: =NewTech!A8 -> R2,R3,R4,R5,R6 | B31: =NewTech!B8 -> TAJ10 | C31: =NewTech!C8 -> Air Jet, Passenger 2010 | D31: =NewTech!D8 -> bn-pass-miles, bn-pmt/a | E31: =NewTech!E8 -> TRNJTF1 | F31: =NewTech!F8 -> TA | G31: ='New Emissions'!C104 -> 0.065 | L31: ='New Emissions'!AI104 -> 0.0007966802 | M31: ='New Emissions'!AJ104 -> 0.0007966802 | O31: ='New Emissions'!AG104 -> 0.05763383 | T31: ='New Emissions'!AL104 -> 0.0007966802 | Y31: ='New Emissions'!AM104 -> 0.0007966802 | AA31: ='New Emissions'!AP104 -> 0.0007966802 | AB31: ='New Emissions'!AK104 -> 0.0007966802 | AG31: ='New Emissions'!AN104 -> 0.0007966802 | AL31: ='New Emissions'!AO104 -> 0.0007966802 | AQ31: =G31 -> 0.065 | AV31: =L31 -> 0.0007966802 | AW31: =M31 -> 0.0007966802 | AY31: =O31 -> 0.05763383 | BD31: =T31 -> 0.0007966802
A32: =NewTech!A9 -> R2,R3,R4,R5,R6 | B32: =NewTech!B9 -> TAJSYN10 | C32: =NewTech!C9 -> Air Jet, Passenger, Syn fuel, 2010 | D32: =NewTech!D9 -> bn-pass-miles, bn-pmt/a | E32: =NewTech!E9 -> TRNJTF1 | F32: =NewTech!F9 -> TA | G32: ='New Emissions'!C105 -> 0.065 | L32: ='New Emissions'!AI105 -> 0.0007966802 | M32: ='New Emissions'!AJ105 -> 0.0007966802 | O32: ='New Emissions'!AG105 -> 0.05763383 | T32: ='New Emissions'!AL105 -> 0.0007966802 | Y32: ='New Emissions'!AM105 -> 0.0007966802 | AA32: ='New Emissions'!AP105 -> 0.0007966802 | AB32: ='New Emissions'!AK105 -> 0.0007966802 | AG32: ='New Emissions'!AN105 -> 0.0007966802 | AL32: ='New Emissions'!AO105 -> 0.0007966802 | AQ32: =G32 -> 0.065 | AV32: =L32 -> 0.0007966802 | AW32: =M32 -> 0.0007966802 | AY32: =O32 -> 0.05763383 | BD32: =T32 -> 0.0007966802
A33: =NewTech!A10 -> R2,R3,R4,R5,R6 | B33: =NewTech!B10 -> TAJWT10 | C33: =NewTech!C10 -> Air Jet, Passenger (Wing tips),2010 | D33: =NewTech!D10 -> bn-pass-miles, bn-pmt/a | E33: =NewTech!E10 -> TRNJTF1 | F33: =NewTech!F10 -> TA | G33: ='New Emissions'!C106 -> 0.065 | L33: ='New Emissions'!AI106 -> 0.0007966802 | M33: ='New Emissions'!AJ106 -> 0.0007966802 | O33: ='New Emissions'!AG106 -> 0.05763383 | T33: ='New Emissions'!AL106 -> 0.0007966802 | Y33: ='New Emissions'!AM106 -> 0.0007966802 | AA33: ='New Emissions'!AP106 -> 0.0007966802 | AB33: ='New Emissions'!AK106 -> 0.0007966802 | AG33: ='New Emissions'!AN106 -> 0.0007966802 | AL33: ='New Emissions'!AO106 -> 0.0007966802 | AQ33: =G33 -> 0.065 | AV33: =L33 -> 0.0007966802 | AW33: =M33 -> 0.0007966802 | AY33: =O33 -> 0.05763383 | BD33: =T33 -> 0.0007966802
A34: =NewTech!A11 -> R2,R3,R4,R5,R6 | B34: =NewTech!B11 -> TAJAPU15 | C34: =NewTech!C11 -> Air Jet Passeneger (APU) 2015 | D34: =NewTech!D11 -> bn-pass-miles, bn-pmt/a | E34: =NewTech!E11 -> TRNJTF1 | F34: =NewTech!F11 -> TA | G34: ='New Emissions'!C107 -> 0.065 | M34: ='New Emissions'!AJ107 -> 0.0007966802 | O34: ='New Emissions'!AG107 -> 0.05763383 | T34: ='New Emissions'!AL107 -> 0.0007966802 | Y34: ='New Emissions'!AM107 -> 0.0007966802 | AA34: ='New Emissions'!AP107 -> 0.0007966802 | AB34: ='New Emissions'!AK107 -> 0.0007966802 | AG34: ='New Emissions'!AN107 -> 0.0007966802 | AL34: ='New Emissions'!AO107 -> 0.0007966802 | AQ34: =G34 -> 0.065 | AW34: =M34 -> 0.0007966802 | AY34: =O34 -> 0.05763383 | BD34: =T34 -> 0.0007966802
A35: =NewTech!A12 -> R2,R3,R4,R5,R6 | B35: =NewTech!B12 -> TAJBW30 | C35: =NewTech!C12 -> Air Jet, Passenger(blended wing), 2030 | D35: =NewTech!D12 -> bn-pass-miles, bn-pmt/a | E35: =NewTech!E12 -> TRNJTF1 | F35: =NewTech!F12 -> TA | G35: ='New Emissions'!C108 -> 0.065 | M35: ='New Emissions'!AJ108 -> 0.0007966802 | O35: ='New Emissions'!AG108 -> 0.05763383 | T35: ='New Emissions'!AL108 -> 0.0007966802 | Y35: ='New Emissions'!AM108 -> 0.0007966802 | AA35: ='New Emissions'!AP108 -> 0.0007966802 | AB35: ='New Emissions'!AK108 -> 0.0007966802 | AG35: ='New Emissions'!AN108 -> 0.0007966802 | AL35: ='New Emissions'!AO108 -> 0.0007966802 | AQ35: =G35 -> 0.065 | AW35: =M35 -> 0.0007966802 | AY35: =O35 -> 0.05763383 | BD35: =T35 -> 0.0007966802
A36: =NewTech!A13 -> R2,R3,R4,R5,R6 | B36: =NewTech!B13 -> TAJAE30 | C36: =NewTech!C13 -> Air Jet, Passenger (improved aero), 2030 | D36: =NewTech!D13 -> bn-pass-miles, bn-pmt/a | E36: =NewTech!E13 -> TRNJTF1 | F36: =NewTech!F13 -> TA | G36: ='New Emissions'!C109 -> 0.065 | M36: ='New Emissions'!AJ109 -> 0.0007966802 | O36: ='New Emissions'!AG109 -> 0.05763383 | T36: ='New Emissions'!AL109 -> 0.0007966802 | Y36: ='New Emissions'!AM109 -> 0.0007966802 | AA36: ='New Emissions'!AP109 -> 0.0007966802 | AB36: ='New Emissions'!AK109 -> 0.0007966802 | AG36: ='New Emissions'!AN109 -> 0.0007966802 | AL36: ='New Emissions'!AO109 -> 0.0007966802 | AQ36: =G36 -> 0.065 | AW36: =M36 -> 0.0007966802 | AY36: =O36 -> 0.05763383 | BD36: =T36 -> 0.0007966802
A37: =NewTech!A14 -> R2,R3,R4,R5,R6 | B37: =NewTech!B14 -> TAJGE15 | C37: =NewTech!C14 -> Air Jet Passenger, (geared engine), 2015 | D37: =NewTech!D14 -> bn-pass-miles, bn-pmt/a | E37: =NewTech!E14 -> TRNJTF1 | F37: =NewTech!F14 -> TA | G37: ='New Emissions'!C110 -> 0.065 | M37: ='New Emissions'!AJ110 -> 0.0007966802 | O37: ='New Emissions'!AG110 -> 0.05763383 | T37: ='New Emissions'!AL110 -> 0.0007966802 | Y37: ='New Emissions'!AM110 -> 0.0007966802 | AA37: ='New Emissions'!AP110 -> 0.0007966802 | AB37: ='New Emissions'!AK110 -> 0.0007966802 | AG37: ='New Emissions'!AN110 -> 0.0007966802 | AL37: ='New Emissions'!AO110 -> 0.0007966802 | AQ37: =G37 -> 0.065 | AW37: =M37 -> 0.0007966802 | AY37: =O37 -> 0.05763383 | BD37: =T37 -> 0.0007966802
A38: =NewTech!A15 -> * | B38: =NewTech!B15 -> TAP10 | C38: =NewTech!C15 -> Airplane, General Aviation - 2010 | D38: =NewTech!D15 -> bn-pass-miles, bn-pmt/a | E38: =NewTech!E15 -> TRGSLB | F38: =NewTech!F15 -> TA | G38: ='New Emissions'!C111 -> 0.1636 | L38: ='New Emissions'!AI111 -> 0.00703976 | M38: ='New Emissions'!AJ111 -> 0.00703976 | O38: ='New Emissions'!AG111 -> 0.05763383 | T38: ='New Emissions'!AL111 -> 0.00703976 | Y38: ='New Emissions'!AM111 -> 0.00703976 | AA38: ='New Emissions'!AP111 -> 0.00703976 | AB38: ='New Emissions'!AK111 -> 0.00703976 | AG38: ='New Emissions'!AN111 -> 0.00703976 | AL38: ='New Emissions'!AO111 -> 0.00703976 | AQ38: =G38 -> 0.1636 | AV38: =L38 -> 0.00703976 | AW38: =M38 -> 0.00703976 | AY38: =O38 -> 0.05763383 | BD38: =T38 -> 0.00703976

Sheet TechData_HDV_EMIS
A1: TechData | B1: R1,R2,R3,R4,R5,R6 | G1: * | H1: * | I1: * | J1: * | K1: * | L1: * | M1: * | N1: * | O1: * | P1: * | Q1: * | R1: * | S1: * | T1: * | AE1: * | AP1: * | BA1: * | BL1: * | BW1: * | CH1: * | CS1: * | DD1: * | DO1: * | DZ1: * | EK1: * | EL1: * | EM1: * | EN1: * | EO1: * | EP1: * | EQ1: * | ER1: * | ES1: * | ET1: * | EU1: * | EV1: * | FG1: * | FR1: * | GC1: *
K5: ENV_ACT | L5: ENV_ACT | M5: ENV_ACT | N5: ENV_ACT | O5: ENV_ACT | P5: ENV_ACT | Q5: ENV_ACT | R5: ENV_ACT | S5: ENV_ACT | T5: ENV_ACT | U5: ENV_ACT | V5: ENV_ACT | W5: ENV_ACT | X5: ENV_ACT | Y5: ENV_ACT | Z5: ENV_ACT | AA5: ENV_ACT | AB5: ENV_ACT | AC5: ENV_ACT | AD5: ENV_ACT | AE5: ENV_ACT | AF5: ENV_ACT | AG5: ENV_ACT | AH5: ENV_ACT | AI5: ENV_ACT | AJ5: ENV_ACT | AK5: ENV_ACT | AL5: ENV_ACT | AM5: ENV_ACT | AN5: ENV_ACT | AO5: ENV_ACT | AP5: ENV_ACT | AQ5: ENV_ACT | AR5: ENV_ACT | AS5: ENV_ACT | AT5: ENV_ACT | AU5: ENV_ACT | AV5: ENV_ACT | AW5: ENV_ACT | AX5: ENV_ACT | AY5: ENV_ACT | AZ5: ENV_ACT | BA5: ENV_ACT | BB5: ENV_ACT | BC5: ENV_ACT | BD5: ENV_ACT | BE5: ENV_ACT | BF5: ENV_ACT | BG5: ENV_ACT | BH5: ENV_ACT | BI5: ENV_ACT | BJ5: ENV_ACT | BK5: ENV_ACT | BL5: ENV_ACT | BM5: ENV_ACT | BN5: ENV_ACT | BO5: ENV_ACT | BP5: ENV_ACT | BQ5: ENV_ACT | BR5: ENV_ACT | BS5: ENV_ACT | BT5: ENV_ACT | BU5: ENV_ACT | BV5: ENV_ACT | BW5: ENV_ACT | BX5: ENV_ACT | BY5: ENV_ACT | BZ5: ENV_ACT | CA5: ENV_ACT | CB5: ENV_ACT | CC5: ENV_ACT | CD5: ENV_ACT | CE5: ENV_ACT | CF5: ENV_ACT | CG5: ENV_ACT | CH5: ENV_ACT | CI5: ENV_ACT | CJ5: ENV_ACT | CK5: ENV_ACT | CL5: ENV_ACT | CM5: ENV_ACT | CN5: ENV_ACT | CO5: ENV_ACT | CP5: ENV_ACT | CQ5: ENV_ACT | CR5: ENV_ACT | CS5: ENV_ACT | CT5: ENV_ACT | CU5: ENV_ACT | CV5: ENV_ACT | CW5: ENV_ACT | CX5: ENV_ACT | CY5: ENV_ACT | CZ5: ENV_ACT | DA5: ENV_ACT | DB5: ENV_ACT | DC5: ENV_ACT | DD5: ENV_ACT | DE5: ENV_ACT | DF5: ENV_ACT | DG5: ENV_ACT | DH5: ENV_ACT | DI5: ENV_ACT | DJ5: ENV_ACT | DK5: ENV_ACT | DL5: ENV_ACT | DM5: ENV_ACT | DN5: ENV_ACT | DO5: ENV_ACT | DP5: ENV_ACT | DQ5: ENV_ACT | DR5: ENV_ACT | DS5: ENV_ACT | DT5: ENV_ACT | DU5: ENV_ACT | DV5: ENV_ACT | DW5: ENV_ACT | DX5: ENV_ACT | DY5: ENV_ACT | DZ5: ENV_ACT | EA5: ENV_ACT | EB5: ENV_ACT | EC5: ENV_ACT | ED5: ENV_ACT | EE5: ENV_ACT | EF5: ENV_ACT | EG5: ENV_ACT | EH5: ENV_ACT | EI5: ENV_ACT | EJ5: ENV_ACT | EK5: ENV_ACT | EL5: ENV_ACT | EM5: ENV_ACT | EN5: ENV_ACT | EO5: ENV_ACT | EP5: ENV_ACT | EQ5: ENV_ACT | ER5: ENV_ACT | ES5: ENV_ACT | ET5: ENV_ACT | EU5: ENV_ACT | EV5: ENV_ACT | EW5: ENV_ACT | EX5: ENV_ACT | EY5: ENV_ACT | EZ5: ENV_ACT | FA5: ENV_ACT | FB5: ENV_ACT | FC5: ENV_ACT | FD5: ENV_ACT | FE5: ENV_ACT | FF5: ENV_ACT | FG5: ENV_ACT | FH5: ENV_ACT | FI5: ENV_ACT | FJ5: ENV_ACT | FK5: ENV_ACT | FL5: ENV_ACT | FM5: ENV_ACT | FN5: ENV_ACT | FO5: ENV_ACT | FP5: ENV_ACT | FQ5: ENV_ACT | FR5: ENV_ACT | FS5: ENV_ACT | FT5: ENV_ACT | FU5: ENV_ACT | FV5: ENV_ACT | FW5: ENV_ACT | FX5: ENV_ACT | FY5: ENV_ACT | FZ5: ENV_ACT | GA5: ENV_ACT | GB5: ENV_ACT | GC5: ENV_ACT | GD5: ENV_ACT | GE5: ENV_ACT | GF5: ENV_ACT | GG5: ENV_ACT | GH5: ENV_ACT | GI5: ENV_ACT | GJ5: ENV_ACT | GK5: ENV_ACT | GL5: ENV_ACT | GM5: ENV_ACT
K6: CO2 | L6: CO2 | M6: CO2 | N6: CO2 | O6: CO2 | P6: CO2 | Q6: CO2 | R6: CO2 | S6: CO2 | T6: CO2 | U6: NOX | V6: NOX | W6: NOX | X6: NOX | Y6: NOX | Z6: NOX | AA6: NOX | AB6: NOX | AC6: NOX | AD6: NOX | AE6: SO2 | AF6: SO2 | AG6: SO2 | AH6: SO2 | AI6: SO2 | AJ6: SO2 | AK6: SO2 | AL6: SO2 | AM6: SO2 | AN6: SO2 | AO6: SO2 | AP6: PM10 | AQ6: PM10 | AR6: PM10 | AS6: PM10 | AT6: PM10 | AU6: PM10 | AV6: PM10 | AW6: PM10 | AX6: PM10 | AY6: PM10 | AZ6: PM10 | BA6: PM25 | BB6: PM25 | BC6: PM25 | BD6: PM25 | BE6: PM25 | BF6: PM25 | BG6: PM25 | BH6: PM25 | BI6: PM25 | BJ6: PM25 | BK6: PM25 | BL6: CO | BM6: CO | BN6: CO | BO6: CO | BP6: CO | BQ6: CO | BR6: CO | BS6: CO | BT6: CO | BU6: CO | BV6: CO | BW6: VOC | BX6: VOC | BY6: VOC | BZ6: VOC | CA6: VOC | CB6: VOC | CC6: VOC | CD6: VOC | CE6: VOC | CF6: VOC | CG6: VOC | CH6: NH3 | CI6: NH3 | CJ6: NH3 | CK6: NH3 | CL6: NH3 | CM6: NH3 | CN6: NH3 | CO6: NH3 | CP6: NH3 | CQ6: NH3 | CR6: NH3 | CS6: N2O | CT6: N2O | CU6: N2O | CV6: N2O | CW6: N2O | CX6: N2O | CY6: N2O | CZ6: N2O | DA6: N2O | DB6: N2O | DC6: N2O | DD6: BC | DE6: BC | DF6: BC | DG6: BC | DH6: BC | DI6: BC | DJ6: BC | DK6: BC | DL6: BC | DM6: BC | DN6: BC | DO6: OC | DP6: OC | DQ6: OC | DR6: OC | DS6: OC | DT6: OC | DU6: OC | DV6: OC | DW6: OC | DX6: OC | DY6: OC | DZ6: CH4 | EA6: CH4 | EB6: CH4 | EC6: CH4 | ED6: CH4 | EE6: CH4 | EF6: CH4 | EG6: CH4 | EH6: CH4 | EI6: CH4 | EJ6: CH4 | EK6: CO2T | EL6: =CONCATENATE(K6,"T") -> CO2T | EM6: =CONCATENATE(L6,"T") -> CO2T | EN6: =CONCATENATE(M6,"T") -> CO2T | EO6: =CONCATENATE(N6,"T") -> CO2T | EP6: =CONCATENATE(O6,"T") -> CO2T | EQ6: =CONCATENATE(P6,"T") -> CO2T | ER6: =CONCATENATE(Q6,"T") -> CO2T | ES6: =CONCATENATE(R6,"T") -> CO2T | ... EU6: =CONCATENATE(T6,"T") -> CO2T | EV6: =EX6 -> NOXT | EW6: =CONCATENATE(U6,"T") -> NOXT | EX6: =CONCATENATE(V6,"T") -> NOXT | EY6: =CONCATENATE(W6,"T") -> NOXT | EZ6: =CONCATENATE(X6,"T") -> NOXT | FA6: =CONCATENATE(Y6,"T") -> NOXT | FB6: =CONCATENATE(Z6,"T") -> NOXT | FC6: =CONCATENATE(AA6,"T") -> NOXT | FD6: =CONCATENATE(AB6,"T") -> NOXT | ... GM6: =CONCATENATE(BK6,"T") -> PM25T
F10: ~FI_T
A11: Region | B11: TechName | C11: *TechDesc | D11: *Units | E11: *CommIN | F11: *CommOUT | G11: *Type | H11: *Fuel | I11: *Adjustment | J11: *Categories for tracking emissions | K11: *ENV_ACT~CO2~2010 | L11: *ENV_ACT~CO2~2015 | M11: *ENV_ACT~CO2~2020 | N11: *ENV_ACT~CO2~2025 | O11: *ENV_ACT~CO2~2030 | P11: *ENV_ACT~CO2~2035 | Q11: *ENV_ACT~CO2~2040 | R11: *ENV_ACT~CO2~2045 | S11: *ENV_ACT~CO2~2050 | T11: *ENV_ACT~CO2~2055 | U11: ENV_ACT~NOX~2010 | V11: ENV_ACT~NOX~2015 | W11: ENV_ACT~NOX~2020 | X11: ENV_ACT~NOX~2025 | Y11: ENV_ACT~NOX~2030 | Z11: ENV_ACT~NOX~2035 | AA11: ENV_ACT~NOX~2040 | AB11: ENV_ACT~NOX~2045 | AC11: ENV_ACT~NOX~2050 | AD11: ENV_ACT~NOX~2055 | AE11: *ENV_ACT~SO2~2005 | AF11: ENV_ACT~SO2~2010 | AG11: ENV_ACT~SO2~2015 | AH11: ENV_ACT~SO2~2020 | AI11: ENV_ACT~SO2~2025 | AJ11: ENV_ACT~SO2~2030 | AK11: ENV_ACT~SO2~2035 | AL11: ENV_ACT~SO2~2040 | AM11: ENV_ACT~SO2~2045 | AN11: ENV_ACT~SO2~2050 | AO11: ENV_ACT~SO2~2055 | AP11: *ENV_ACT~PM10~2005 | AQ11: ENV_ACT~PM10~2010 | AR11: ENV_ACT~PM10~2015 | AS11: ENV_ACT~PM10~2020 | AT11: ENV_ACT~PM10~2025 | AU11: ENV_ACT~PM10~2030 | AV11: ENV_ACT~PM10~2035 | AW11: ENV_ACT~PM10~2040 | AX11: ENV_ACT~PM10~2045 | AY11: ENV_ACT~PM10~2050 | AZ11: ENV_ACT~PM10~2055 | BA11: *ENV_ACT~PM25~2005 | BB11: ENV_ACT~PM25~2010 | BC11: ENV_ACT~PM25~2015 | BD11: ENV_ACT~PM25~2020 | BE11: ENV_ACT~PM25~2025 | BF11: ENV_ACT~PM25~2030 | BG11: ENV_ACT~PM25~2035 | BH11: ENV_ACT~PM25~2040 | BI11: ENV_ACT~PM25~2045 | BJ11: ENV_ACT~PM25~2050 | BK11: ENV_ACT~PM25~2055 | BL11: *ENV_ACT~CO~2005 | BM11: ENV_ACT~CO~2010 | BN11: ENV_ACT~CO~2015 | BO11: ENV_ACT~CO~2020 | BP11: ENV_ACT~CO~2025 | BQ11: ENV_ACT~CO~2030 | BR11: ENV_ACT~CO~2035 | BS11: ENV_ACT~CO~2040 | BT11: ENV_ACT~CO~2045 | BU11: ENV_ACT~CO~2050 | BV11: ENV_ACT~CO~2055 | BW11: *ENV_ACT~VOC~2005 | BX11: ENV_ACT~VOC~2010 | BY11: ENV_ACT~VOC~2015 | BZ11: ENV_ACT~VOC~2020 | CA11: ENV_ACT~VOC~2025 | CB11: ENV_ACT~VOC~2030 | CC11: ENV_ACT~VOC~2035 | CD11: ENV_ACT~VOC~2040 | CE11: ENV_ACT~VOC~2045 | CF11: ENV_ACT~VOC~2050 | CG11: ENV_ACT~VOC~2055 | CH11: *ENV_ACT~NH3~2005 | CI11: ENV_ACT~NH3~2010 | CJ11: ENV_ACT~NH3~2015 | CK11: ENV_ACT~NH3~2020 | CL11: ENV_ACT~NH3~2025 | CM11: ENV_ACT~NH3~2030 | CN11: ENV_ACT~NH3~2035 | CO11: ENV_ACT~NH3~2040 | CP11: ENV_ACT~NH3~2045 | CQ11: ENV_ACT~NH3~2050 | CR11: ENV_ACT~NH3~2055 | CS11: *ENV_ACT~N2O~2005 | CT11: ENV_ACT~N2O~2010 | CU11: ENV_ACT~N2O~2015 | CV11: ENV_ACT~N2O~2020 | CW11: ENV_ACT~N2O~2025 | CX11: ENV_ACT~N2O~2030 | CY11: ENV_ACT~N2O~2035 | CZ11: ENV_ACT~N2O~2040 | DA11: ENV_ACT~N2O~2045 | DB11: ENV_ACT~N2O~2050 | DC11: ENV_ACT~N2O~2055 | DD11: *ENV_ACT~BC~2005 | DE11: ENV_ACT~BC~2010 | DF11: ENV_ACT~BC~2015 | DG11: ENV_ACT~BC~2020 | DH11: ENV_ACT~BC~2025 | DI11: ENV_ACT~BC~2030 | DJ11: ENV_ACT~BC~2035 | DK11: ENV_ACT~BC~2040 | DL11: ENV_ACT~BC~2045 | DM11: ENV_ACT~BC~2050 | DN11: ENV_ACT~BC~2055 | DO11: *ENV_ACT~OC~2005 | DP11: ENV_ACT~OC~2010 | DQ11: ENV_ACT~OC~2015 | DR11: ENV_ACT~OC~2020 | DS11: ENV_ACT~OC~2025 | DT11: ENV_ACT~OC~2030 | DU11: ENV_ACT~OC~2035 | DV11: ENV_ACT~OC~2040 | DW11: ENV_ACT~OC~2045 | DX11: ENV_ACT~OC~2050 | DY11: ENV_ACT~OC~2055 | DZ11: *ENV_ACT~CH4~2005 | EA11: ENV_ACT~CH4~2010 | EB11: ENV_ACT~CH4~2015 | EC11: ENV_ACT~CH4~2020 | ED11: ENV_ACT~CH4~2025 | EE11: ENV_ACT~CH4~2030 | EF11: ENV_ACT~CH4~2035 | EG11: ENV_ACT~CH4~2040 | EH11: ENV_ACT~CH4~2045 | EI11: ENV_ACT~CH4~2050 | EJ11: ENV_ACT~CH4~2055 | EK11: *ENV_ACT~CO2T~2005 | EL11: *ENV_ACT~CO2T~2010 | EM11: *ENV_ACT~CO2T~2015 | EN11: *ENV_ACT~CO2T~2020 | EO11: *ENV_ACT~CO2T~2025 | EP11: *ENV_ACT~CO2T~2030 | EQ11: *ENV_ACT~CO2T~2035 | ER11: *ENV_ACT~CO2T~2040 | ES11: *ENV_ACT~CO2T~2045 | ET11: *ENV_ACT~CO2T~2050 | EU11: *ENV_ACT~CO2T~2055 | EV11: *ENV_ACT~NOXT~2005 | EW11: ENV_ACT~NOXT~2010 | EX11: ENV_ACT~NOXT~2015 | EY11: ENV_ACT~NOXT~2020 | EZ11: ENV_ACT~NOXT~2025 | FA11: ENV_ACT~NOXT~2030 | FB11: ENV_ACT~NOXT~2035 | FC11: ENV_ACT~NOXT~2040 | FD11: ENV_ACT~NOXT~2045 | FE11: ENV_ACT~NOXT~2050 | FF11: ENV_ACT~NOXT~2055 | FG11: *ENV_ACT~SO2T~2005 | FH11: ENV_ACT~SO2T~2010 | FI11: ENV_ACT~SO2T~2015 | FJ11: ENV_ACT~SO2T~2020 | FK11: ENV_ACT~SO2T~2025 | FL11: ENV_ACT~SO2T~2030 | FM11: ENV_ACT~SO2T~2035 | FN11: ENV_ACT~SO2T~2040 | FO11: ENV_ACT~SO2T~2045 | FP11: ENV_ACT~SO2T~2050 | FQ11: ENV_ACT~SO2T~2055 | FR11: *ENV_ACT~PM10T~2005 | FS11: ENV_ACT~PM10T~2010 | FT11: ENV_ACT~PM10T~2015 | FU11: ENV_ACT~PM10T~2020 | FV11: ENV_ACT~PM10T~2025 | FW11: ENV_ACT~PM10T~2030 | FX11: ENV_ACT~PM10T~2035 | FY11: ENV_ACT~PM10T~2040 | FZ11: ENV_ACT~PM10T~2045 | GA11: ENV_ACT~PM10T~2050 | GB11: ENV_ACT~PM10T~2055 | GC11: *ENV_ACT~PM25T~2005 | GD11: ENV_ACT~PM25T~2010 | GE11: ENV_ACT~PM25T~2015 | GF11: ENV_ACT~PM25T~2020 | GG11: ENV_ACT~PM25T~2025 | GH11: ENV_ACT~PM25T~2030 | GI11: ENV_ACT~PM25T~2035 | GJ11: ENV_ACT~PM25T~2040 | GK11: ENV_ACT~PM25T~2045 | GL11: ENV_ACT~PM25T~2050 | GM11: ENV_ACT~PM25T~2055
A12: R2 | B12: =TechData!B11 -> TBDSLE | C12: =TechData!C11 -> Bus, Exisiting Diesel | D12: =TechData!D11 -> bn-vmt, bn-vmt/a | E12: =TechData!E11 -> TBDSL | F12: =TechData!F11 -> TB | G12: Bus | H12: DSL | I12: 1 | J12: =CONCATENATE(G12,"-",H12) -> Bus-DSL | K12: =SUMIFS(NewEmisData!E:E, NewEmisData!$A:$A, $G12, NewEmisData!$B:$B, $A12, NewEmisData!$C:$C, $H12, NewEmisData!$D:$D, K$6) -> 1573.0982 | L12: =SUMIFS(NewEmisData!F:F, NewEmisData!$A:$A, $G12, NewEmisData!$B:$B, $A12, NewEmisData!$C:$C, $H12, NewEmisData!$D:$D, L$6) -> 1544.368 | M12: =SUMIFS(NewEmisData!G:G, NewEmisData!$A:$A, $G12, NewEmisData!$B:$B, $A12, NewEmisData!$C:$C, $H12, NewEmisData!$D:$D, M$6) -> 1916.5843 | N12: =SUMIFS(NewEmisData!H:H, NewEmisData!$A:$A, $G12, NewEmisData!$B:$B, $A12, NewEmisData!$C:$C, $H12, NewEmisData!$D:$D, N$6) -> 1868.993 | O12: =SUMIFS(NewEmisData!I:I, NewEmisData!$A:$A, $G12, NewEmisData!$B:$B, $A12, NewEmisData!$C:$C, $H12, NewEmisData!$D:$D, O$6) -> 1812.7967 | P12: =SUMIFS(NewEmisData!J:J, NewEmisData!$A:$A, $G12, NewEmisData!$B:$B, $A12, NewEmisData!$C:$C, $H12, NewEmisData!$D:$D, P$6) -> 1785.4009 | Q12: =SUMIFS(NewEmisData!K:K, NewEmisData!$A:$A, $G12, NewEmisData!$B:$B, $A12, NewEmisData!$C:$C, $H12, NewEmisData!$D:$D, Q$6) -> 1781.167 | R12: =SUMIFS(NewEmisData!L:L, NewEmisData!$A:$A, $G12, NewEmisData!$B:$B, $A12, NewEmisData!$C:$C, $H12, NewEmisData!$D:$D, R$6) -> 1779.8934 | S12: =SUMIFS(NewEmisData!M:M, NewEmisData!$A:$A, $G12, NewEmisData!$B:$B, $A12, NewEmisData!$C:$C, $H12, NewEmisData!$D:$D, S$6) -> 1779.2856 | T12: =S12 -> 1779.2856 | U12: =SUMIFS(NewEmisData!E:E, NewEmisData!$A:$A, $G12, NewEmisData!$B:$B, $A12, NewEmisData!$C:$C, $H12, NewEmisData!$D:$D, U$6) -> 25.485894 | V12: =SUMIFS(NewEmisData!F:F, NewEmisData!$A:$A, $G12, NewEmisData!$B:$B, $A12, NewEmisData!$C:$C, $H12, NewEmisData!$D:$D, V$6) -> 16.635316 | W12: =SUMIFS(NewEmisData!G:G, NewEmisData!$A:$A, $G12, NewEmisData!$B:$B, $A12, NewEmisData!$C:$C, $H12, NewEmisData!$D:$D, W$6) -> 5.6806504 | X12: =SUMIFS(NewEmisData!H:H, NewEmisData!$A:$A, $G12, NewEmisData!$B:$B, $A12, NewEmisData!$C:$C, $H12, NewEmisData!$D:$D, X$6) -> 3.0540393 | Y12: =SUMIFS(NewEmisData!I:I, NewEmisData!$A:$A, $G12, NewEmisData!$B:$B, $A12, NewEmisData!$C:$C, $H12, NewEmisData!$D:$D, Y$6) -> 2.1007258 | Z12: =SUMIFS(NewEmisData!J:J, NewEmisData!$A:$A, $G12, NewEmisData!$B:$B, $A12, NewEmisData!$C:$C, $H12, NewEmisData!$D:$D, Z$6) -> 1.8765899 | AA12: =SUMIFS(NewEmisData!K:K, NewEmisData!$A:$A, $G12, NewEmisData!$B:$B, $A12, NewEmisData!$C:$C, $H12, NewEmisData!$D:$D, AA$6) -> 1.767942 | AB12: =SUMIFS(NewEmisData!L:L, NewEmisData!$A:$A, $G12, NewEmisData!$B:$B, $A12, NewEmisData!$C:$C, $H12, NewEmisData!$D:$D, AB$6) -> 1.7647235 | AC12: =SUMIFS(NewEmisData!M:M, NewEmisData!$A:$A, $G12, NewEmisData!$B:$B, $A12, NewEmisData!$C:$C, $H12, NewEmisData!$D:$D, AC$6) -> 1.7635143 | AD12: =AC12 -> 1.7635143 | AE12: =AF12 -> 0.039377822 | AF12: =SUMIFS(NewEmisData!E:E, NewEmisData!$A:$A, $G12, NewEmisData!$B:$B, $A12, NewEmisData!$C:$C, $H12, NewEmisData!$D:$D, AF$6) -> 0.039377822 | AG12: =SUMIFS(NewEmisData!F:F, NewEmisData!$A:$A, $G12, NewEmisData!$B:$B, $A12, NewEmisData!$C:$C, $H12, NewEmisData!$D:$D, AG$6) -> 0.037984236 | AH12: =SUMIFS(NewEmisData!G:G, NewEmisData!$A:$A, $G12, NewEmisData!$B:$B, $A12, NewEmisData!$C:$C, $H12, NewEmisData!$D:$D, AH$6) -> 0.016214019 | AI12: =SUMIFS(NewEmisData!H:H, NewEmisData!$A:$A, $G12, NewEmisData!$B:$B, $A12, NewEmisData!$C:$C, $H12, NewEmisData!$D:$D, AI$6) -> 0.01564238 | AJ12: =SUMIFS(NewEmisData!I:I, NewEmisData!$A:$A, $G12, NewEmisData!$B:$B, $A12, NewEmisData!$C:$C, $H12, NewEmisData!$D:$D, AJ$6) -> 0.015129566 | AK12: =SUMIFS(NewEmisData!J:J, NewEmisData!$A:$A, $G12, NewEmisData!$B:$B, $A12, NewEmisData!$C:$C, $H12, NewEmisData!$D:$D, AK$6) -> 0.014894054 | AL12: =SUMIFS(NewEmisData!K:K, NewEmisData!$A:$A, $G12, NewEmisData!$B:$B, $A12, NewEmisData!$C:$C, $H12, NewEmisData!$D:$D, AL$6) -> 0.014849806 | AM12: =SUMIFS(NewEmisData!L:L, NewEmisData!$A:$A, $G12, NewEmisData!$B:$B, $A12, NewEmisData!$C:$C, $H12, NewEmisData!$D:$D, AM$6) -> 0.014839187 | AN12: =SUMIFS(NewEmisData!M:M, NewEmisData!$A:$A, $G12, NewEmisData!$B:$B, $A12, NewEmisData!$C:$C, $H12, NewEmisData!$D:$D, AN$6) -> 0.014834122 | AO12: =AN12 -> 0.014834122 | AP12: =AQ12 -> 1.6759761 | AQ12: =SUMIFS(NewEmisData!E:E, NewEmisData!$A:$A, $G12, NewEmisData!$B:$B, $A12, NewEmisData!$C:$C, $H12, NewEmisData!$D:$D, AQ$6) -> 1.6759761 | AR12: =SUMIFS(NewEmisData!F:F, NewEmisData!$A:$A, $G12, NewEmisData!$B:$B, $A12, NewEmisData!$C:$C, $H12, NewEmisData!$D:$D, AR$6) -> 1.2591555 | AS12: =SUMIFS(NewEmisData!G:G, NewEmisData!$A:$A, $G12, NewEmisData!$B:$B, $A12, NewEmisData!$C:$C, $H12, NewEmisData!$D:$D, AS$6) -> 0.67744249 | AT12: =SUMIFS(NewEmisData!H:H, NewEmisData!$A:$A, $G12, NewEmisData!$B:$B, $A12, NewEmisData!$C:$C, $H12, NewEmisData!$D:$D, AT$6) -> 0.52738778 | AU12: =SUMIFS(NewEmisData!I:I, NewEmisData!$A:$A, $G12, NewEmisData!$B:$B, $A12, NewEmisData!$C:$C, $H12, NewEmisData!$D:$D, AU$6) -> 0.48358849 | AV12: =SUMIFS(NewEmisData!J:J, NewEmisData!$A:$A, $G12, NewEmisData!$B:$B, $A12, NewEmisData!$C:$C, $H12, NewEmisData!$D:$D, AV$6) -> 0.47276166 | AW12: =SUMIFS(NewEmisData!K:K, NewEmisData!$A:$A, $G12, NewEmisData!$B:$B, $A12, NewEmisData!$C:$C, $H12, NewEmisData!$D:$D, AW$6) -> 0.46753146 | AX12: =SUMIFS(NewEmisData!L:L, NewEmisData!$A:$A, $G12, NewEmisData!$B:$B, $A12, NewEmisData!$C:$C, $H12, NewEmisData!$D:$D, AX$6) -> 0.46733603 | AY12: =SUMIFS(NewEmisData!M:M, NewEmisData!$A:$A, $G12, NewEmisData!$B:$B, $A12, NewEmisData!$C:$C, $H12, NewEmisData!$D:$D, AY$6) -> 0.46734013 | AZ12: =AY12 -> 0.46734013 | BA12: =BB12 -> 1.317721 | BB12: =SUMIFS(NewEmisData!E:E, NewEmisData!$A:$A, $G12, NewEmisData!$B:$B, $A12, NewEmisData!$C:$C, $H12, NewEmisData!$D:$D, BB$6) -> 1.317721 | BC12: =SUMIFS(NewEmisData!F:F, NewEmisData!$A:$A, $G12, NewEmisData!$B:$B, $A12, NewEmisData!$C:$C, $H12, NewEmisData!$D:$D, BC$6) -> 0.93325433 | BD12: =SUMIFS(NewEmisData!G:G, NewEmisData!$A:$A, $G12, NewEmisData!$B:$B, $A12, NewEmisData!$C:$C, $H12, NewEmisData!$D:$D, BD$6) -> 0.27440126 | BE12: =SUMIFS(NewEmisData!H:H, NewEmisData!$A:$A, $G12, NewEmisData!$B:$B, $A12, NewEmisData!$C:$C, $H12, NewEmisData!$D:$D, BE$6) -> 0.13530769 | BF12: =SUMIFS(NewEmisData!I:I, NewEmisData!$A:$A, $G12, NewEmisData!$B:$B, $A12, NewEmisData!$C:$C, $H12, NewEmisData!$D:$D, BF$6) -> 0.10091566 | BG12: =SUMIFS(NewEmisData!J:J, NewEmisData!$A:$A, $G12, NewEmisData!$B:$B, $A12, NewEmisData!$C:$C, $H12, NewEmisData!$D:$D, BG$6) -> 0.09430718 | BH12: =SUMIFS(NewEmisData!K:K, NewEmisData!$A:$A, $G12, NewEmisData!$B:$B, $A12, NewEmisData!$C:$C, $H12, NewEmisData!$D:$D, BH$6) -> 0.089937296 | BI12: =SUMIFS(NewEmisData!L:L, NewEmisData!$A:$A, $G12, NewEmisData!$B:$B, $A12, NewEmisData!$C:$C, $H12, NewEmisData!$D:$D, BI$6) -> 0.089863312 | BJ12: =SUMIFS(NewEmisData!M:M, NewEmisData!$A:$A, $G12, NewEmisData!$B:$B, $A12, NewEmisData!$C:$C, $H12, NewEmisData!$D:$D, BJ$6) -> 0.089850223 | BK12: =BJ12 -> 0.089850223 | BL12: =BM12 -> 9.424946 | BM12: =SUMIFS(NewEmisData!E:E, NewEmisData!$A:$A, $G12, NewEmisData!$B:$B, $A12, NewEmisData!$C:$C, $H12, NewEmisData!$D:$D, BM$6) -> 9.424946 | BN12: =SUMIFS(NewEmisData!F:F, NewEmisData!$A:$A, $G12, NewEmisData!$B:$B, $A12, NewEmisData!$C:$C, $H12, NewEmisData!$D:$D, BN$6) -> 6.5151522 | BO12: =SUMIFS(NewEmisData!G:G, NewEmisData!$A:$A, $G12, NewEmisData!$B:$B, $A12, NewEmisData!$C:$C, $H12, NewEmisData!$D:$D, BO$6) -> 2.9013963 | BP12: =SUMIFS(NewEmisData!H:H, NewEmisData!$A:$A, $G12, NewEmisData!$B:$B, $A12, NewEmisData!$C:$C, $H12, NewEmisData!$D:$D, BP$6) -> 1.8001555 | BQ12: =SUMIFS(NewEmisData!I:I, NewEmisData!$A:$A, $G12, NewEmisData!$B:$B, $A12, NewEmisData!$C:$C, $H12, NewEmisData!$D:$D, BQ$6) -> 1.6438314 | BR12: =SUMIFS(NewEmisData!J:J, NewEmisData!$A:$A, $G12, NewEmisData!$B:$B, $A12, NewEmisData!$C:$C, $H12, NewEmisData!$D:$D, BR$6) -> 1.5743293 | BS12: =SUMIFS(NewEmisData!K:K, NewEmisData!$A:$A, $G12, NewEmisData!$B:$B, $A12, NewEmisData!$C:$C, $H12, NewEmisData!$D:$D, BS$6) -> 1.5408503 | BT12: =SUMIFS(NewEmisData!L:L, NewEmisData!$A:$A, $G12, NewEmisData!$B:$B, $A12, NewEmisData!$C:$C, $H12, NewEmisData!$D:$D, BT$6) -> 1.5416002 | BU12: =SUMIFS(NewEmisData!M:M, NewEmisData!$A:$A, $G12, NewEmisData!$B:$B, $A12, NewEmisData!$C:$C, $H12, NewEmisData!$D:$D, BU$6) -> 1.541415 | BV12: =BU12 -> 1.541415 | BW12: =BX12 -> 1.8476162 | BX12: =SUMIFS(NewEmisData!E:E, NewEmisData!$A:$A, $G12, NewEmisData!$B:$B, $A12, NewEmisData!$C:$C, $H12, NewEmisData!$D:$D, BX$6) -> 1.8476162 | BY12: =SUMIFS(NewEmisData!F:F, NewEmisData!$A:$A, $G12, NewEmisData!$B:$B, $A12, NewEmisData!$C:$C, $H12, NewEmisData!$D:$D, BY$6) -> 1.4025706 | BZ12: =SUMIFS(NewEmisData!G:G, NewEmisData!$A:$A, $G12, NewEmisData!$B:$B, $A12, NewEmisData!$C:$C, $H12, NewEmisData!$D:$D, BZ$6) -> 0.61956439 | CA12: =SUMIFS(NewEmisData!H:H, NewEmisData!$A:$A, $G12, NewEmisData!$B:$B, $A12, NewEmisData!$C:$C, $H12, NewEmisData!$D:$D, CA$6) -> 0.2692911 | CB12: =SUMIFS(NewEmisData!I:I, NewEmisData!$A:$A, $G12, NewEmisData!$B:$B, $A12, NewEmisData!$C:$C, $H12, NewEmisData!$D:$D, CB$6) -> 0.19094706 | CC12: =SUMIFS(NewEmisData!J:J, NewEmisData!$A:$A, $G12, NewEmisData!$B:$B, $A12, NewEmisData!$C:$C, $H12, NewEmisData!$D:$D, CC$6) -> 0.17228803 | CD12: =SUMIFS(NewEmisData!K:K, NewEmisData!$A:$A, $G12, NewEmisData!$B:$B, $A12, NewEmisData!$C:$C, $H12, NewEmisData!$D:$D, CD$6) -> 0.15756259 | CE12: =SUMIFS(NewEmisData!L:L, NewEmisData!$A:$A, $G12, NewEmisData!$B:$B, $A12, NewEmisData!$C:$C, $H12, NewEmisData!$D:$D, CE$6) -> 0.15751989 | CF12: =SUMIFS(NewEmisData!M:M, NewEmisData!$A:$A, $G12, NewEmisData!$B:$B, $A12, NewEmisData!$C:$C, $H12, NewEmisData!$D:$D, CF$6) -> 0.15750072 | CG12: =CF12 -> 0.15750072 | CH12: =CI12 -> 0.02621203 | CI12: =SUMIFS(NewEmisData!E:E, NewEmisData!$A:$A, $G12, NewEmisData!$B:$B, $A12, NewEmisData!$C:$C, $H12, NewEmisData!$D:$D, CI$6) -> 0.02621203 | CJ12: =SUMIFS(NewEmisData!F:F, NewEmisData!$A:$A, $G12, NewEmisData!$B:$B, $A12, NewEmisData!$C:$C, $H12, NewEmisData!$D:$D, CJ$6) -> 0.026306148 | CK12: =SUMIFS(NewEmisData!G:G, NewEmisData!$A:$A, $G12, NewEmisData!$B:$B, $A12, NewEmisData!$C:$C, $H12, NewEmisData!$D:$D, CK$6) -> 0.036703962 | CL12: =SUMIFS(NewEmisData!H:H, NewEmisData!$A:$A, $G12, NewEmisData!$B:$B, $A12, NewEmisData!$C:$C, $H12, NewEmisData!$D:$D, CL$6) -> 0.036724989 | CM12: =SUMIFS(NewEmisData!I:I, NewEmisData!$A:$A, $G12, NewEmisData!$B:$B, $A12, NewEmisData!$C:$C, $H12, NewEmisData!$D:$D, CM$6) -> 0.036651622 | CN12: =SUMIFS(NewEmisData!J:J, NewEmisData!$A:$A, $G12, NewEmisData!$B:$B, $A12, NewEmisData!$C:$C, $H12, NewEmisData!$D:$D, CN$6) -> 0.036612099 | CO12: =SUMIFS(NewEmisData!K:K, NewEmisData!$A:$A, $G12, NewEmisData!$B:$B, $A12, NewEmisData!$C:$C, $H12, NewEmisData!$D:$D, CO$6) -> 0.036606158 | CP12: =SUMIFS(NewEmisData!L:L, NewEmisData!$A:$A, $G12, NewEmisData!$B:$B, $A12, NewEmisData!$C:$C, $H12, NewEmisData!$D:$D, CP$6) -> 0.036604649 | CQ12: =SUMIFS(NewEmisData!M:M, NewEmisData!$A:$A, $G12, NewEmisData!$B:$B, $A12, NewEmisData!$C:$C, $H12, NewEmisData!$D:$D, CQ$6) -> 0.036605318 | CR12: =CQ12 -> 0.036605318 | CS12: =CT12 -> 0.0049860992 | CT12: =SUMIFS(NewEmisData!E:E, NewEmisData!$A:$A, $G12, NewEmisData!$B:$B, $A12, NewEmisData!$C:$C, $H12, NewEmisData!$D:$D, CT$6) -> 0.0049860992 | CU12: =SUMIFS(NewEmisData!F:F, NewEmisData!$A:$A, $G12, NewEmisData!$B:$B, $A12, NewEmisData!$C:$C, $H12, NewEmisData!$D:$D, CU$6) -> 0.0047742875 | CV12: =SUMIFS(NewEmisData!G:G, NewEmisData!$A:$A, $G12, NewEmisData!$B:$B, $A12, NewEmisData!$C:$C, $H12, NewEmisData!$D:$D, CV$6) -> 0.0072603359 | CW12: =SUMIFS(NewEmisData!H:H, NewEmisData!$A:$A, $G12, NewEmisData!$B:$B, $A12, NewEmisData!$C:$C, $H12, NewEmisData!$D:$D, CW$6) -> 0.0072661934 | CX12: =SUMIFS(NewEmisData!I:I, NewEmisData!$A:$A, $G12, NewEmisData!$B:$B, $A12, NewEmisData!$C:$C, $H12, NewEmisData!$D:$D, CX$6) -> 0.007312389 | CY12: =SUMIFS(NewEmisData!J:J, NewEmisData!$A:$A, $G12, NewEmisData!$B:$B, $A12, NewEmisData!$C:$C, $H12, NewEmisData!$D:$D, CY$6) -> 0.0073404375 | CZ12: =SUMIFS(NewEmisData!K:K, NewEmisData!$A:$A, $G12, NewEmisData!$B:$B, $A12, NewEmisData!$C:$C, $H12, NewEmisData!$D:$D, CZ$6) -> 0.0073437457 | DA12: =SUMIFS(NewEmisData!L:L, NewEmisData!$A:$A, $G12, NewEmisData!$B:$B, $A12, NewEmisData!$C:$C, $H12, NewEmisData!$D:$D, DA$6) -> 0.0073446145 | DB12: =SUMIFS(NewEmisData!M:M, NewEmisData!$A:$A, $G12, NewEmisData!$B:$B, $A12, NewEmisData!$C:$C, $H12, NewEmisData!$D:$D, DB$6) -> 0.0073444995 | DC12: =DB12 -> 0.0073444995 | DD12: 0.39300579 | DE12: 0.25218506 | DF12: 0.090680333 | DG12: 0.015259204 | DH12: 0.0014429846 | DI12: 0.00142163 | DJ12: 0.0014222675 | DK12: 0.0014222969 | DL12: 0.0014226321 | DM12: 0.0014227268 | DN12: 0.0014227268 | DO12: 0.20788279 | DP12: 0.14188647 | DQ12: 0.062736209 | DR12: 0.012554111 | DS12: 0.0025088279 | DT12: 0.0024717001 | DU12: 0.0024728083 | DV12: 0.0024728595 | DW12: 0.0024734423 | DX12: 0.0024736069 | DY12: 0.0024736069 | DZ12: =EA12 -> 0.011359383 | EA12: =SUMIFS(NewEmisData!E:E, NewEmisData!$A:$A, $G12, NewEmisData!$B:$B, $A12, NewEmisData!$C:$C, $H12, NewEmisData!$D:$D, EA$6) -> 0.011359383 | EB12: =SUMIFS(NewEmisData!F:F, NewEmisData!$A:$A, $G12, NewEmisData!$B:$B, $A12, NewEmisData!$C:$C, $H12, NewEmisData!$D:$D, EB$6) -> 0.037803123 | EC12: =SUMIFS(NewEmisData!G:G, NewEmisData!$A:$A, $G12, NewEmisData!$B:$B, $A12, NewEmisData!$C:$C, $H12, NewEmisData!$D:$D, EC$6) -> 0.12443729 | ED12: =SUMIFS(NewEmisData!H:H, NewEmisData!$A:$A, $G12, NewEmisData!$B:$B, $A12, NewEmisData!$C:$C, $H12, NewEmisData!$D:$D, ED$6) -> 0.13690358 | EE12: =SUMIFS(NewEmisData!I:I, NewEmisData!$A:$A, $G12, NewEmisData!$B:$B, $A12, NewEmisData!$C:$C, $H12, NewEmisData!$D:$D, EE$6) -> 0.13674174 | EF12: =SUMIFS(NewEmisData!J:J, NewEmisData!$A:$A, $G12, NewEmisData!$B:$B, $A12, NewEmisData!$C:$C, $H12, NewEmisData!$D:$D, EF$6) -> 0.13774222 | EG12: =SUMIFS(NewEmisData!K:K, NewEmisData!$A:$A, $G12, NewEmisData!$B:$B, $A12, NewEmisData!$C:$C, $H12, NewEmisData!$D:$D, EG$6) -> 0.13873461 | EH12: =SUMIFS(NewEmisData!L:L, NewEmisData!$A:$A, $G12, NewEmisData!$B:$B, $A12, NewEmisData!$C:$C, $H12, NewEmisData!$D:$D, EH$6) -> 0.13871065 | EI12: =SUMIFS(NewEmisData!M:M, NewEmisData!$A:$A, $G12, NewEmisData!$B:$B, $A12, NewEmisData!$C:$C, $H12, NewEmisData!$D:$D, EI$6) -> 0.13870042 | EJ12: =EI12 -> 0.13870042 | EK12: =EL12 -> 1573.0982 | EL12: =K12 -> 1573.0982 | EM12: =L12 -> 1544.368 | EN12: =M12 -> 1916.5843 | EO12: =N12 -> 1868.993 | EP12: =O12 -> 1812.7967 | EQ12: =P12 -> 1785.4009 | ER12: =Q12 -> 1781.167 | ES12: =R12 -> 1779.8934 | ... EU12: =T12 -> 1779.2856 | EV12: =EW12 -> 25.485894 | EW12: =U12 -> 25.485894 | EX12: =V12 -> 16.635316 | EY12: =W12 -> 5.6806504 | EZ12: =X12 -> 3.0540393 | FA12: =Y12 -> 2.1007258 | FB12: =Z12 -> 1.8765899 | FC12: =AA12 -> 1.767942 | FD12: =AB12 -> 1.7647235 | ... GM12: =BK12 -> 0.089850223
